Workbook
Name Collection: #REF!
Name Farmer: #REF!

Sheet Summary
B1: Dues Statement as on Date | G1: Outstanding Aging | AC1: Remark | AD1: (blank)
G2: Sum of Dues | H2: Column Labels | AC2: Delivery Pending against deduction
B3: Godown | C3: Sales Amount | D3: Payment Amt | E3: Sum of Dues | G3: Godown | H3: 0-14 | I3: 15-29 | J3: 30-44 | K3: 45-60 | L3: >60 | M3: Grand Total | Q3: Remarks on Ageing above <30 Days | AC3: Catchment | AD3: Qty | AE3: Value
B4: Bero | C4: 180000 | D4: 177433 | E4: 2567 | G4: Bero | H4: 0 | I4: 2500 | J4: 67 | M4: 2567 | AC4: Pali | AD4: 18 | AE4: 29360
B5: Chanho | C5: 143750 | D5: 124091 | E5: 19659 | G5: Chanho | H5: 9024 | K5: 8091 | L5: 2544 | M5: 19659 | AC5: ITKI | AD5: 80 | AE5: 96000
B6: Chuttu | C6: 50000 | D6: 50000 | E6: 0 | G6: Chuttu | H6: 0 | M6: 0 | AC6: Bero | AD6: 2 | AE6: 835
B7: Dumardagga | C7: 225000 | D7: 200000 | E7: 25000 | G7: Dumardagga | H7: 0 | I7: 12500 | K7: 12500 | M7: 25000 | AC7: Ormanjhi | AD7: 3 | AE7: 3750
B8: Hisri | C8: 13750 | D8: 13750 | E8: 0 | G8: Hisri | H8: 0 | M8: 0 | AC8: Gargaon | AD8: 60 | AE8: 37926
B9: ITKI | C9: 420000 | D9: 420000 | E9: 0 | G9: ITKI | H9: 0 | M9: 0 | AC9: Dumardagga | AD9: 30 | AE9: 37500
B10: Ormanjhi | C10: 63750 | D10: 60455 | E10: 3295 | G10: Ormanjhi | H10: 0 | I10: 3295 | M10: 3295 | AC10: Piragutu | AD10: 15 | AE10: 15994
B11: Pali | C11: 286250 | D11: 231299 | E11: 54951 | G11: Pali | H11: 2039 | I11: 31589 | K11: 12500 | L11: 8823 | M11: 54951 | AC11: Chanho | AD11: 25 | AE11: 15987
B12: Piragutu | C12: 50000 | D12: 50000 | E12: 0 | G12: Piragutu | H12: 0 | M12: 0 | AC12: Chano | AD12: 0 | AE12: 6437
B13: Grand Total | C13: 1432500 | D13: 1327028 | E13: 105472 | G13: Grand Total | H13: 11063 | I13: 49884 | J13: 67 | K13: 33091 | L13: 11367 | M13: 105472 | AC13: Grand Total | AD13: 233 | AE13: 243789
B18: ="Stock as on Date"&" "&TEXT(TODAY(),"dd-mm-yyyy") -> Stock as on Date 19-05-2026
C19: Gomukh Gold 50 Kgs | G19: Buff Spl 50 Kg | K19: Total
B20: Godown | C20: Opening Stock | D20: Purchases | E20: Sales | F20: Closing | G20: Opening Stock | H20: Purchases | I20: Sales | J20: Closing | K20: Opening Stock | L20: Purchases | M20: Sales | N20: Closing
B21: ITKI | C21: 0 | D21: =(SUMIFS(Purchases!M:M,Purchases!K:K,Summary!$B21,Purchases!L:L,Summary!$C$19)) -> 350 | E21: =SUMIFS(Table1[[#All],[Qty Sold]],Table1[[#All],[Godown]],Summary!$B21,Table1[[#All],[Name of Product]],Summary!$C$19) -> 350 | F21: =D21-E21+C21 -> 0 | H21: =(SUMIFS(Purchases!Q:Q,Purchases!O:O,Summary!$B21,Purchases!P:P,Summary!$G$19)) -> 0 | I21: =SUMIFS(Table1[[#All],[Qty Sold]],Table1[[#All],[Godown]],Summary!$B21,Table1[[#All],[Name of Product]],Summary!$G$19) -> 0 | J21: =H21-I21+G21 -> 0 | K21: =+C21+G21 -> 0 | L21: =+D21+H21 -> 350 | M21: =+E21+I21 -> 350 | N21: =+F21+J21 -> 0
B22: Pali | C22: 0 | D22: =(SUMIFS(Purchases!M:M,Purchases!K:K,Summary!$B22,Purchases!L:L,Summary!$C$19)) -> 305 | E22: =SUMIFS(Table1[[#All],[Qty Sold]],Table1[[#All],[Godown]],Summary!$B22,Table1[[#All],[Name of Product]],Summary!$C$19) -> 229 | F22: =D22-E22+C22 -> 76 | H22: =(SUMIFS(Purchases!Q:Q,Purchases!O:O,Summary!$B22,Purchases!P:P,Summary!$G$19)) -> 0 | I22: =SUMIFS(Table1[[#All],[Qty Sold]],Table1[[#All],[Godown]],Summary!$B22,Table1[[#All],[Name of Product]],Summary!$G$19) -> 0 | J22: =H22-I22+G22 -> 0 | K22: =+C22+G22 -> 0 | L22: =+D22+H22 -> 305 | M22: =+E22+I22 -> 229 | N22: =+F22+J22 -> 76
B23: Hisri | C23: 0 | D23: =(SUMIFS(Purchases!M:M,Purchases!K:K,Summary!$B23,Purchases!L:L,Summary!$C$19)) -> 25 | E23: =SUMIFS(Table1[[#All],[Qty Sold]],Table1[[#All],[Godown]],Summary!$B23,Table1[[#All],[Name of Product]],Summary!$C$19) -> 11 | F23: =D23-E23+C23 -> 14 | H23: =(SUMIFS(Purchases!Q:Q,Purchases!O:O,Summary!$B23,Purchases!P:P,Summary!$G$19)) -> 0 | I23: =SUMIFS(Table1[[#All],[Qty Sold]],Table1[[#All],[Godown]],Summary!$B23,Table1[[#All],[Name of Product]],Summary!$G$19) -> 0 | J23: =H23-I23+G23 -> 0 | K23: =+C23+G23 -> 0 | L23: =+D23+H23 -> 25 | M23: =+E23+I23 -> 11 | N23: =+F23+J23 -> 14
B24: Choreya | C24: 0 | D24: =(SUMIFS(Purchases!M:M,Purchases!K:K,Summary!$B24,Purchases!L:L,Summary!$C$19)) -> 0 | E24: =SUMIFS(Table1[[#All],[Qty Sold]],Table1[[#All],[Godown]],Summary!$B24,Table1[[#All],[Name of Product]],Summary!$C$19) -> 0 | F24: =D24-E24+C24 -> 0 | H24: =(SUMIFS(Purchases!Q:Q,Purchases!O:O,Summary!$B24,Purchases!P:P,Summary!$G$19)) -> 0 | I24: =SUMIFS(Table1[[#All],[Qty Sold]],Table1[[#All],[Godown]],Summary!$B24,Table1[[#All],[Name of Product]],Summary!$G$19) -> 0 | J24: =H24-I24+G24 -> 0 | K24: =+C24+G24 -> 0 | L24: =+D24+H24 -> 0 | M24: =+E24+I24 -> 0 | N24: =+F24+J24 -> 0
B25: Ormanjhi | C25: 0 | D25: =(SUMIFS(Purchases!M:M,Purchases!K:K,Summary!$B25,Purchases!L:L,Summary!$C$19)) -> 112 | E25: =SUMIFS(Table1[[#All],[Qty Sold]],Table1[[#All],[Godown]],Summary!$B25,Table1[[#All],[Name of Product]],Summary!$C$19) -> 51 | F25: =D25-E25+C25 -> 61 | H25: =(SUMIFS(Purchases!Q:Q,Purchases!O:O,Summary!$B25,Purchases!P:P,Summary!$G$19)) -> 0 | I25: =SUMIFS(Table1[[#All],[Qty Sold]],Table1[[#All],[Godown]],Summary!$B25,Table1[[#All],[Name of Product]],Summary!$G$19) -> 0 | J25: =H25-I25+G25 -> 0 | K25: =+C25+G25 -> 0 | L25: =+D25+H25 -> 112 | M25: =+E25+I25 -> 51 | N25: =+F25+J25 -> 61
B26: Chuttu | C26: 0 | D26: =(SUMIFS(Purchases!M:M,Purchases!K:K,Summary!$B26,Purchases!L:L,Summary!$C$19)) -> 96 | E26: =SUMIFS(Table1[[#All],[Qty Sold]],Table1[[#All],[Godown]],Summary!$B26,Table1[[#All],[Name of Product]],Summary!$C$19) -> 40 | F26: =D26-E26+C26 -> 56 | H26: =(SUMIFS(Purchases!Q:Q,Purchases!O:O,Summary!$B26,Purchases!P:P,Summary!$G$19)) -> 0 | I26: =SUMIFS(Table1[[#All],[Qty Sold]],Table1[[#All],[Godown]],Summary!$B26,Table1[[#All],[Name of Product]],Summary!$G$19) -> 0 | J26: =H26-I26+G26 -> 0 | K26: =+C26+G26 -> 0 | L26: =+D26+H26 -> 96 | M26: =+E26+I26 -> 40 | N26: =+F26+J26 -> 56
B27: Dumardagga | C27: 0 | D27: =(SUMIFS(Purchases!M:M,Purchases!K:K,Summary!$B27,Purchases!L:L,Summary!$C$19)) -> 250 | E27: =SUMIFS(Table1[[#All],[Qty Sold]],Table1[[#All],[Godown]],Summary!$B27,Table1[[#All],[Name of Product]],Summary!$C$19) -> 180 | F27: =D27-E27+C27 -> 70 | H27: =(SUMIFS(Purchases!Q:Q,Purchases!O:O,Summary!$B27,Purchases!P:P,Summary!$G$19)) -> 0 | I27: =SUMIFS(Table1[[#All],[Qty Sold]],Table1[[#All],[Godown]],Summary!$B27,Table1[[#All],[Name of Product]],Summary!$G$19) -> 0 | J27: =H27-I27+G27 -> 0 | K27: =+C27+G27 -> 0 | L27: =+D27+H27 -> 250 | M27: =+E27+I27 -> 180 | N27: =+F27+J27 -> 70
B28: Gargaon | C28: 0 | D28: =(SUMIFS(Purchases!M:M,Purchases!K:K,Summary!$B28,Purchases!L:L,Summary!$C$19)) -> 0 | E28: =SUMIFS(Table1[[#All],[Qty Sold]],Table1[[#All],[Godown]],Summary!$B28,Table1[[#All],[Name of Product]],Summary!$C$19) -> 0 | F28: =D28-E28+C28 -> 0 | H28: =(SUMIFS(Purchases!Q:Q,Purchases!O:O,Summary!$B28,Purchases!P:P,Summary!$G$19)) -> 0 | I28: =SUMIFS(Table1[[#All],[Qty Sold]],Table1[[#All],[Godown]],Summary!$B28,Table1[[#All],[Name of Product]],Summary!$G$19) -> 0 | J28: =H28-I28+G28 -> 0 | K28: =+C28+G28 -> 0 | L28: =+D28+H28 -> 0 | M28: =+E28+I28 -> 0 | N28: =+F28+J28 -> 0
B29: Bero | C29: 0 | D29: =(SUMIFS(Purchases!M:M,Purchases!K:K,Summary!$B29,Purchases!L:L,Summary!$C$19)) -> 188 | E29: =SUMIFS(Table1[[#All],[Qty Sold]],Table1[[#All],[Godown]],Summary!$B29,Table1[[#All],[Name of Product]],Summary!$C$19) -> 144 | F29: =D29-E29+C29 -> 44 | H29: =(SUMIFS(Purchases!Q:Q,Purchases!O:O,Summary!$B29,Purchases!P:P,Summary!$G$19)) -> 0 | I29: =SUMIFS(Table1[[#All],[Qty Sold]],Table1[[#All],[Godown]],Summary!$B29,Table1[[#All],[Name of Product]],Summary!$G$19) -> 0 | J29: =H29-I29+G29 -> 0 | K29: =+C29+G29 -> 0 | L29: =+D29+H29 -> 188 | M29: =+E29+I29 -> 144 | N29: =+F29+J29 -> 44
B30: Palma | C30: 0 | D30: =(SUMIFS(Purchases!M:M,Purchases!K:K,Summary!$B30,Purchases!L:L,Summary!$C$19)) -> 0 | E30: =SUMIFS(Table1[[#All],[Qty Sold]],Table1[[#All],[Godown]],Summary!$B30,Table1[[#All],[Name of Product]],Summary!$C$19) -> 0 | F30: =D30-E30+C30 -> 0 | H30: =(SUMIFS(Purchases!Q:Q,Purchases!O:O,Summary!$B30,Purchases!P:P,Summary!$G$19)) -> 0 | I30: =SUMIFS(Table1[[#All],[Qty Sold]],Table1[[#All],[Godown]],Summary!$B30,Table1[[#All],[Name of Product]],Summary!$G$19) -> 0 | J30: =H30-I30+G30 -> 0 | K30: =+C30+G30 -> 0 | L30: =+D30+H30 -> 0 | M30: =+E30+I30 -> 0 | N30: =+F30+J30 -> 0
B31: Baski | C31: 0 | D31: =(SUMIFS(Purchases!M:M,Purchases!K:K,Summary!$B31,Purchases!L:L,Summary!$C$19)) -> 0 | E31: =SUMIFS(Table1[[#All],[Qty Sold]],Table1[[#All],[Godown]],Summary!$B31,Table1[[#All],[Name of Product]],Summary!$C$19) -> 0 | F31: =D31-E31+C31 -> 0 | H31: =(SUMIFS(Purchases!Q:Q,Purchases!O:O,Summary!$B31,Purchases!P:P,Summary!$G$19)) -> 0 | I31: =SUMIFS(Table1[[#All],[Qty Sold]],Table1[[#All],[Godown]],Summary!$B31,Table1[[#All],[Name of Product]],Summary!$G$19) -> 0 | J31: =H31-I31+G31 -> 0 | K31: =+C31+G31 -> 0 | L31: =+D31+H31 -> 0 | M31: =+E31+I31 -> 0 | N31: =+F31+J31 -> 0
B32: Piragutu | C32: 0 | D32: =(SUMIFS(Purchases!M:M,Purchases!K:K,Summary!$B32,Purchases!L:L,Summary!$C$19)) -> 50 | E32: =SUMIFS(Table1[[#All],[Qty Sold]],Table1[[#All],[Godown]],Summary!$B32,Table1[[#All],[Name of Product]],Summary!$C$19) -> 40 | F32: =D32-E32+C32 -> 10 | H32: =(SUMIFS(Purchases!Q:Q,Purchases!O:O,Summary!$B32,Purchases!P:P,Summary!$G$19)) -> 0 | I32: =SUMIFS(Table1[[#All],[Qty Sold]],Table1[[#All],[Godown]],Summary!$B32,Table1[[#All],[Name of Product]],Summary!$G$19) -> 0 | J32: =H32-I32+G32 -> 0 | K32: =+C32+G32 -> 0 | L32: =+D32+H32 -> 50 | M32: =+E32+I32 -> 40 | N32: =+F32+J32 -> 10
B33: Chanho | C33: 0 | D33: =(SUMIFS(Purchases!M:M,Purchases!K:K,Summary!$B33,Purchases!L:L,Summary!$C$19)) -> 120 | E33: =SUMIFS(Table1[[#All],[Qty Sold]],Table1[[#All],[Godown]],Summary!$B33,Table1[[#All],[Name of Product]],Summary!$C$19) -> 115 | F33: =D33-E33+C33 -> 5 | H33: =(SUMIFS(Purchases!Q:Q,Purchases!O:O,Summary!$B33,Purchases!P:P,Summary!$G$19)) -> 0 | I33: =SUMIFS(Table1[[#All],[Qty Sold]],Table1[[#All],[Godown]],Summary!$B33,Table1[[#All],[Name of Product]],Summary!$G$19) -> 0 | J33: =H33-I33+G33 -> 0 | K33: =+C33+G33 -> 0 | L33: =+D33+H33 -> 120 | M33: =+E33+I33 -> 115 | N33: =+F33+J33 -> 5
C34: =SUM(C21:C33) -> 0 | D34: =SUM(D21:D33) -> 1496 | E34: =SUM(E21:E33) -> 1160 | F34: =SUM(F21:F33) -> 336 | G34: =SUM(G21:G33) -> 0 | H34: =SUM(H21:H33) -> 0 | I34: =SUM(I21:I33) -> 0 | J34: =SUM(J21:J33) -> 0 | ... N34: =SUM(N21:N33) -> 336

Sheet PnL
A2: Cattle Feed Profit & Loss | B2: Apr'25 | E2: May'25 | H2: Jun'25 | K2: Jul'25 | N2: Aug'25 | Q2: Sep'25 | T2: Oct'25 | W2: Nov'25 | Z2: Dec'25 | AC2: Jan'26 | AF2: Feb'26 | AI2: Mar'26 | AL2: FY 25-26
A3: Particulars | B3: Qty | C3: Rate | D3: Amount | E3: Qty | F3: Rate | G3: Amount | H3: Qty | I3: Rate | J3: Amount | K3: Qty | L3: Rate | M3: Amount | N3: Qty | O3: Rate | P3: Amount | Q3: Qty | R3: Rate | S3: Amount | T3: Qty | U3: Rate | V3: Amount | W3: Qty | X3: Rate | Y3: Amount | Z3: Qty | AA3: Rate | AB3: Amount | AC3: Qty | AD3: Rate | AE3: Amount | AF3: Qty | AG3: Rate | AH3: Amount | AI3: Qty | AJ3: Rate | AK3: Amount | AL3: Qty | AM3: Rate | AN3: Amount
A4: Opening Stock | B4: =+SUM(B5:B8) -> 901 | D4: =+SUM(D5:D8) -> 955060 | E4: =+SUM(E5:E8) -> 424 | G4: =+SUM(G5:G8) -> 449440 | H4: =+SUM(H5:H8) -> 1003 | J4: =+SUM(J5:J8) -> 1063180 | K4: =+SUM(K5:K8) -> 676 | M4: =+SUM(M5:M8) -> 716560 | N4: =+SUM(N5:N8) -> 471 | P4: =+SUM(P5:P8) -> 499260 | Q4: =+SUM(Q5:Q8) -> 711 | S4: =+SUM(S5:S8) -> 739440 | T4: =+SUM(T5:T8) -> 476 | V4: =+SUM(V5:V8) -> 495040 | W4: =+SUM(W5:W8) -> 556 | Y4: =+SUM(Y5:Y8) -> 578240 | Z4: =+SUM(Z5:Z8) -> 885 | AB4: =+SUM(AB5:AB8) -> 920400 | AC4: =+SUM(AC5:AC8) -> 337 | AE4: =+SUM(AE5:AE8) -> 350480 | AF4: =+SUM(AF5:AF8) -> 136 | AH4: =+SUM(AH5:AH8) -> 141440 | AI4: =+SUM(AI5:AI8) -> 871 | AK4: =+SUM(AK5:AK8) -> 923260 | AL4: =+SUM(AL5:AL8) -> 901 | AN4: =+SUM(AN5:AN8) -> 955060
A5: Cattle Feed | B5: 901 | D5: 955060 | E5: =+B20 -> 424 | G5: =+D20 -> 449440 | H5: =+E20 -> 1003 | J5: =+G20 -> 1063180 | K5: =+H20 -> 676 | M5: =+J20 -> 716560 | N5: =+K20 -> 471 | P5: =+M20 -> 499260 | Q5: =+N20 -> 711 | S5: =+P20 -> 739440 | T5: =+Q20 -> 476 | V5: =+S20 -> 495040 | W5: =+T20 -> 556 | Y5: =+V20 -> 578240 | Z5: =+W20 -> 885 | AB5: =+Y20 -> 920400 | AC5: =+Z20 -> 337 | AE5: =+AB20 -> 350480 | AF5: =+AC20 -> 136 | AH5: =+AE20 -> 141440 | AI5: =+AF20 -> 871 | AK5: =+AH20 -> 923260 | AL5: =+B5 -> 901 | AN5: =+D5 -> 955060
G6: =+D21 -> 0 | J6: =+G21 -> 0 | M6: =+J21 -> 0 | P6: =+M21 -> 0 | S6: =+P21 -> 0 | V6: =+S21 -> 0 | Y6: =+V21 -> 0 | AB6: =+Y21 -> 0 | AE6: =+AB21 -> 0 | AH6: =+AE21 -> 0 | AK6: =+AH21 -> 0 | AN6: =+AK21 -> 0
A9: Purchase | B9: =+SUM(B10:B13) -> 0 | C9: =+D9/B9 -> #DIV/0! | D9: =+SUM(D10:D13) -> 0 | E9: =+SUM(E10:E13) -> 1000 | F9: =+G9/E9 -> 1060 | G9: =+SUM(G10:G13) -> 1060000 | H9: =+SUM(H10:H13) -> 0 | I9: =+J9/H9 -> #DIV/0! | J9: =+SUM(J10:J13) -> 0 | K9: =+SUM(K10:K13) -> 0 | L9: =+M9/K9 -> #DIV/0! | M9: =+SUM(M10:M13) -> 0 | N9: =+SUM(N10:N13) -> 500 | O9: =+P9/N9 -> 1040 | P9: =+SUM(P10:P13) -> 520000 | Q9: =+SUM(Q10:Q13) -> 0 | R9: =+S9/Q9 -> #DIV/0! | S9: =+SUM(S10:S13) -> 0 | T9: =+SUM(T10:T13) -> 500 | U9: =+V9/T9 -> 1040 | V9: =+SUM(V10:V13) -> 520000 | W9: =+SUM(W10:W13) -> 500 | X9: =+Y9/W9 -> 1040 | Y9: =+SUM(Y10:Y13) -> 520000 | Z9: =+SUM(Z10:Z13) -> 0 | AA9: =+AB9/Z9 -> #DIV/0! | AB9: =+SUM(AB10:AB13) -> 0 | AC9: =+SUM(AC10:AC13) -> 0 | AD9: =+AE9/AC9 -> #DIV/0! | AE9: =+SUM(AE10:AE13) -> 0 | AF9: =+SUM(AF10:AF13) -> 996 | AG9: =+AH9/AF9 -> 1060 | AH9: =+SUM(AH10:AH13) -> 1055760 | AI9: =+SUM(AI10:AI13) -> 500 | AJ9: =+AK9/AI9 -> 1080 | AK9: =+SUM(AK10:AK13) -> 540000 | AL9: =+SUM(AL10:AL13) -> 3996 | AM9: =+AN9/AL9 -> 1054.995 | AN9: =+SUM(AN10:AN13) -> 4215760
A10: =+A5 -> Cattle Feed | B10: 0 | C10: 1105 | E10: 1000 | G10: 1060000 | K10: 0 | M10: 0 | N10: 500 | P10: 520000 | T10: 500 | V10: 520000 | W10: 500 | Y10: 520000 | AF10: 996 | AH10: 1055760 | AI10: 500 | AK10: 540000 | AL10: =+AI10+AF10+AC10+Z10+W10+T10+Q10+N10+K10+H10+E10+B10 -> 3996 | AN10: =+AK10+AH10+AE10+AB10+Y10+V10+S10+P10+M10+J10+G10+D10 -> 4215760
AN11: =+AK11+AH11+AE11+AB11+Y11+V11+S11+P11+M11+J11+G11+D11 -> 0
A14: Sales | B14: =+SUM(B15:B18) -> 477 | C14: =+D14/B14 -> 1234.2767 | D14: =+SUM(D15:D18) -> 588750 | E14: =+SUM(E15:E18) -> 421 | F14: =+G14/E14 -> 1250 | G14: =+SUM(G15:G18) -> 526250 | H14: =+SUM(H15:H18) -> 327 | I14: =+J14/H14 -> 1250 | J14: =+SUM(J15:J18) -> 408750 | K14: =+SUM(K15:K18) -> 205 | L14: =+M14/K14 -> 1250 | M14: =+SUM(M15:M18) -> 256250 | N14: =+SUM(N15:N18) -> 260 | O14: =+P14/N14 -> 1250 | P14: =+SUM(P15:P18) -> 325000 | Q14: =+SUM(Q15:Q18) -> 235 | R14: =+S14/Q14 -> 1250 | S14: =+SUM(S15:S18) -> 293750 | T14: =+SUM(T15:T18) -> 420 | U14: =+V14/T14 -> 1229 | V14: =+SUM(V15:V18) -> 516180 | W14: =+SUM(W15:W18) -> 171 | X14: =+Y14/W14 -> 1250 | Y14: =+SUM(Y15:Y18) -> 213750 | Z14: =+SUM(Z15:Z18) -> 548 | AA14: =+AB14/Z14 -> 1250 | AB14: =+SUM(AB15:AB18) -> 685000 | AC14: =+SUM(AC15:AC18) -> 201 | AD14: =+AE14/AC14 -> 1250 | AE14: =+SUM(AE15:AE18) -> 251250 | AF14: =+SUM(AF15:AF18) -> 261 | AG14: =+AH14/AF14 -> 1166.3218 | AH14: =+SUM(AH15:AH18) -> 304410 | AI14: =+SUM(AI15:AI18) -> 446 | AJ14: =+AK14/AI14 -> 1233.1839 | AK14: =+SUM(AK15:AK18) -> 550000 | AL14: =+SUM(AL15:AL18) -> 3972 | AM14: =+AN14/AL14 -> 1238.5045 | AN14: =+SUM(AN15:AN18) -> 4919340
A15: =+A10 -> Cattle Feed | B15: 477 | D15: 588750 | E15: 421 | G15: 526250 | H15: 327 | J15: 408750 | K15: 205 | M15: 256250 | N15: 260 | P15: 325000 | Q15: 235 | S15: 293750 | T15: 420 | V15: 516180 | W15: 171 | Y15: 213750 | Z15: 548 | AB15: 685000 | AC15: 201 | AE15: 251250 | AF15: 261 | AH15: =326250-21840 -> 304410 | AI15: 446 | AK15: 550000 | AL15: =+AI15+AF15+AC15+Z15+W15+T15+Q15+N15+K15+H15+E15+B15 -> 3972 | AN15: =+AK15+AH15+AE15+AB15+Y15+V15+S15+P15+M15+J15+G15+D15 -> 4919340
AN16: =+AK16+AH16+AE16+AB16+Y16+V16+S16+P16+M16+J16+G16+D16 -> 0
A19: Closing Stock | B19: =+SUM(B20:B23) -> 424 | C19: =+D19/B19 -> 1060 | D19: =+SUM(D20:D23) -> 449440 | E19: =+SUM(E20:E23) -> 1003 | F19: =+G19/E19 -> 1060 | G19: =+SUM(G20:G23) -> 1063180 | H19: =+SUM(H20:H23) -> 676 | I19: =+J19/H19 -> 1060 | J19: =+SUM(J20:J23) -> 716560 | K19: =+SUM(K20:K23) -> 471 | L19: =+M19/K19 -> 1060 | M19: =+SUM(M20:M23) -> 499260 | N19: =+SUM(N20:N23) -> 711 | O19: =+P19/N19 -> 1040 | P19: =+SUM(P20:P23) -> 739440 | Q19: =+SUM(Q20:Q23) -> 476 | R19: =+S19/Q19 -> 1040 | S19: =+SUM(S20:S23) -> 495040 | T19: =+SUM(T20:T23) -> 556 | U19: =+V19/T19 -> 1040 | V19: =+SUM(V20:V23) -> 578240 | W19: =+SUM(W20:W23) -> 885 | X19: =+Y19/W19 -> 1040 | Y19: =+SUM(Y20:Y23) -> 920400 | Z19: =+SUM(Z20:Z23) -> 337 | AA19: =+AB19/Z19 -> 1040 | AB19: =+SUM(AB20:AB23) -> 350480 | AC19: =+SUM(AC20:AC23) -> 136 | AD19: =+AE19/AC19 -> 1040 | AE19: =+SUM(AE20:AE23) -> 141440 | AF19: =+SUM(AF20:AF23) -> 871 | AG19: =+AH19/AF19 -> 1060 | AH19: =+SUM(AH20:AH23) -> 923260 | AI19: =+SUM(AI20:AI23) -> 925 | AJ19: =+AK19/AI19 -> 1080 | AK19: =+SUM(AK20:AK23) -> 999000 | AL19: =+SUM(AL20:AL23) -> 925 | AM19: =+AN19/AL19 -> 1060 | AN19: =+SUM(AN20:AN23) -> 980500
A20: =+A15 -> Cattle Feed | B20: =+B5+B10-B15 -> 424 | D20: =424*1060 -> 449440 | E20: =+E5+E10-E15 -> 1003 | G20: 1063180 | H20: =+H5+H10-H15 -> 676 | J20: 716560 | K20: =+K5+K10-K15 -> 471 | M20: 499260 | N20: =+N5+N10-N15 -> 711 | P20: 739440 | Q20: =+Q5+Q10-Q15 -> 476 | S20: 495040 | T20: =+T5+T10-T15 -> 556 | V20: 578240 | W20: =+W5+W10-W15 -> 885 | Y20: 920400 | Z20: =+Z5+Z10-Z15 -> 337 | AB20: 350480 | AC20: =+AC5+AC10-AC15 -> 136 | AE20: 141440 | AF20: =+AF5+AF10-AF15 -> 871 | AH20: 923260 | AI20: =+AI5+AI10-AI15 -> 925 | AK20: 999000 | AL20: =+AL5+AL10-AL15 -> 925 | AN20: =+AL20*1060 -> 980500
A21: =+A16 -> 0
A24: Distribution Cost | B24: =+SUM(B25:B28) -> 477 | C24: =+D24/B24 -> 59.926625 | D24: =+SUM(D25:D28) -> 28585 | E24: =+SUM(E25:E28) -> 421 | F24: =+G24/E24 -> 55 | G24: =+SUM(G25:G28) -> 23155 | H24: =+SUM(H25:H28) -> 327 | I24: =+J24/H24 -> 55 | J24: =+SUM(J25:J28) -> 17985 | K24: =+SUM(K25:K28) -> 205 | L24: =+M24/K24 -> 55 | M24: =+SUM(M25:M28) -> 11275 | N24: =+SUM(N25:N28) -> 260 | O24: =+P24/N24 -> 55 | P24: =+SUM(P25:P28) -> 14300 | Q24: =+SUM(Q25:Q28) -> 235 | R24: =+S24/Q24 -> 55 | S24: =+SUM(S25:S28) -> 12925 | T24: =+SUM(T25:T28) -> 420 | U24: =+V24/T24 -> 49.5 | V24: =+SUM(V25:V28) -> 20790 | W24: =+SUM(W25:W28) -> 171 | X24: =+Y24/W24 -> 0 | Y24: =+SUM(Y25:Y28) -> 0 | Z24: =+SUM(Z25:Z28) -> 548 | AA24: =+AB24/Z24 -> 55 | AB24: =+SUM(AB25:AB28) -> 30140 | AC24: =+SUM(AC25:AC28) -> 201 | AD24: =+AE24/AC24 -> 0 | AE24: =+SUM(AE25:AE28) -> 0 | AF24: =+SUM(AF25:AF28) -> 261 | AG24: =+AH24/AF24 -> 0 | AH24: =+SUM(AH25:AH28) -> 0 | AI24: =+SUM(AI25:AI28) -> 446 | AJ24: =+AK24/AI24 -> 0 | AK24: =+SUM(AK25:AK28) -> 0 | AL24: =+SUM(AL25:AL28) -> 3972 | AM24: =+AN24/AL24 -> 40.069235 | AN24: =+SUM(AN25:AN28) -> 159155
A25: =+A15 -> Cattle Feed | B25: =+B15 -> 477 | D25: =+D40 -> 28585 | E25: =+E15 -> 421 | G25: =+G40 -> 23155 | H25: =+H15 -> 327 | J25: =+J40 -> 17985 | K25: =+K15 -> 205 | M25: =+M40 -> 11275 | N25: =+N15 -> 260 | P25: =+P40 -> 14300 | Q25: =+Q15 -> 235 | S25: =+S40 -> 12925 | T25: =+T15 -> 420 | V25: =+V40 -> 20790 | W25: =+W15 -> 171 | Y25: =+Y40 -> 0 | Z25: =+Z15 -> 548 | AB25: =+AB40 -> 30140 | AC25: =+AC15 -> 201 | AE25: =+AE40 -> 0 | AF25: =+AF15 -> 261 | AH25: =+AH40 -> 0 | AI25: =+AI15 -> 446 | AK25: =+AK40 -> 0 | AL25: =+AI25+AF25+AC25+Z25+W25+T25+Q25+N25+K25+H25+E25+B25 -> 3972 | AN25: =+AK25+AH25+AE25+AB25+Y25+V25+S25+P25+M25+J25+G25+D25 -> 159155
A26: =+A16 -> 0 | B26: =+B21 -> 0 | D26: 0 | E26: =+E21 -> 0 | G26: 0 | H26: =+H21 -> 0 | J26: 0 | K26: =+K21 -> 0 | M26: 0 | N26: =+N21 -> 0 | P26: 0 | Q26: =+Q21 -> 0 | S26: 0 | T26: =+T21 -> 0 | V26: 0 | W26: =+W21 -> 0 | Y26: 0 | Z26: =+Z21 -> 0 | AB26: 0 | AC26: =+AC21 -> 0 | AE26: 0 | AF26: =+AF21 -> 0 | AH26: 0 | AI26: =+AI21 -> 0 | AK26: 0 | AN26: =+AK26+AH26+AE26+AB26+Y26+V26+S26+P26+M26+J26+G26+D26 -> 0
A29: Net Profit | B29: =+SUM(B30:B33) -> 477 | C29: =+D29/B29 -> 114.3501 | D29: =+SUM(D30:D33) -> 54545 | E29: =+SUM(E30:E33) -> 421 | F29: =+G29/E29 -> 135 | G29: =+SUM(G30:G33) -> 56835 | H29: =+SUM(H30:H33) -> 327 | I29: =+J29/H29 -> 135 | J29: =+SUM(J30:J33) -> 44145 | K29: =+SUM(K30:K33) -> 205 | L29: =+M29/K29 -> 135 | M29: =+SUM(M30:M33) -> 27675 | N29: =+SUM(N30:N33) -> 260 | O29: =+P29/N29 -> 118.76923 | P29: =+SUM(P30:P33) -> 30880 | Q29: =+SUM(Q30:Q33) -> 235 | R29: =+S29/Q29 -> 155 | S29: =+SUM(S30:S33) -> 36425 | T29: =+SUM(T30:T33) -> 420 | U29: =+V29/T29 -> 139.5 | V29: =+SUM(V30:V33) -> 58590 | W29: =+SUM(W30:W33) -> 171 | X29: =+Y29/W29 -> 210 | Y29: =+SUM(Y30:Y33) -> 35910 | Z29: =+SUM(Z30:Z33) -> 548 | AA29: =+AB29/Z29 -> 155 | AB29: =+SUM(AB30:AB33) -> 84940 | AC29: =+SUM(AC30:AC33) -> 201 | AD29: =+AE29/AC29 -> 210 | AE29: =+SUM(AE30:AE33) -> 42210 | AF29: =+SUM(AF30:AF33) -> 261 | AG29: =+AH29/AF29 -> 116.7433 | AH29: =+SUM(AH30:AH33) -> 30470 | AI29: =+SUM(AI30:AI33) -> 446 | AJ29: =+AK29/AI29 -> 192.24215 | AK29: =+SUM(AK30:AK33) -> 85740 | AL29: =+SUM(AL30:AL33) -> 3972 | AM29: =+AN29/AL29 -> 143.47054 | AN29: =+SUM(AN30:AN33) -> 569865
A30: =+A25 -> Cattle Feed | B30: =+B15 -> 477 | C30: =+D30/B30 -> 114.3501 | D30: =+D15+D20-D5-D10-D25 -> 54545 | E30: =+E15 -> 421 | F30: =+G30/E30 -> 135 | G30: =+G15+G20-G5-G10-G25 -> 56835 | H30: =+H15 -> 327 | I30: =+J30/H30 -> 135 | J30: =+J15+J20-J5-J10-J25 -> 44145 | K30: =+K15 -> 205 | L30: =+M30/K30 -> 135 | M30: =+M15+M20-M5-M10-M25 -> 27675 | N30: =+N15 -> 260 | O30: =+P30/N30 -> 118.76923 | P30: =+P15+P20-P5-P10-P25 -> 30880 | Q30: =+Q15 -> 235 | R30: =+S30/Q30 -> 155 | S30: =+S15+S20-S5-S10-S25 -> 36425 | T30: =+T15 -> 420 | U30: =+V30/T30 -> 139.5 | V30: =+V15+V20-V5-V10-V25 -> 58590 | W30: =+W15 -> 171 | X30: =+Y30/W30 -> 210 | Y30: =+Y15+Y20-Y5-Y10-Y25 -> 35910 | Z30: =+Z15 -> 548 | AA30: =+AB30/Z30 -> 155 | AB30: =+AB15+AB20-AB5-AB10-AB25 -> 84940 | AC30: =+AC15 -> 201 | AD30: =+AE30/AC30 -> 210 | AE30: =+AE15+AE20-AE5-AE10-AE25 -> 42210 | AF30: =+AF15 -> 261 | AG30: =+AH30/AF30 -> 116.7433 | AH30: =+AH15+AH20-AH5-AH10-AH25 -> 30470 | AI30: =+AI15 -> 446 | AJ30: =+AK30/AI30 -> 192.24215 | AK30: =+AK15+AK20-AK5-AK10-AK25 -> 85740 | AL30: =+AL15 -> 3972 | AM30: =+AN30/AL30 -> 143.47054 | AN30: =+AN15+AN20-AN5-AN10-AN25 -> 569865
A31: =+A26 -> 0 | B31: =+B26 -> 0 | C31: =+D31/B31 -> #DIV/0! | D31: =+D16+D21-D6-D11-D26 -> 0 | E31: =+E26 -> 0 | F31: =+G31/E31 -> #DIV/0! | G31: =+G16+G21-G6-G11-G26 -> 0 | H31: =+H26 -> 0 | I31: =+J31/H31 -> #DIV/0! | J31: =+J16+J21-J6-J11-J26 -> 0 | K31: =+K26 -> 0 | L31: =+M31/K31 -> #DIV/0! | M31: =+M16+M21-M6-M11-M26 -> 0 | N31: =+N26 -> 0 | O31: =+P31/N31 -> #DIV/0! | P31: =+P16+P21-P6-P11-P26 -> 0 | Q31: =+Q26 -> 0 | R31: =+S31/Q31 -> #DIV/0! | S31: =+S16+S21-S6-S11-S26 -> 0 | T31: =+T26 -> 0 | U31: =+V31/T31 -> #DIV/0! | V31: =+V16+V21-V6-V11-V26 -> 0 | W31: =+W26 -> 0 | X31: =+Y31/W31 -> #DIV/0! | Y31: =+Y16+Y21-Y6-Y11-Y26 -> 0 | Z31: =+Z26 -> 0 | AA31: =+AB31/Z31 -> #DIV/0! | AB31: =+AB16+AB21-AB6-AB11-AB26 -> 0 | AC31: =+AC26 -> 0 | AD31: =+AE31/AC31 -> #DIV/0! | AE31: =+AE16+AE21-AE6-AE11-AE26 -> 0 | AF31: =+AF26 -> 0 | AG31: =+AH31/AF31 -> #DIV/0! | AH31: =+AH16+AH21-AH6-AH11-AH26 -> 0 | AI31: =+AI26 -> 0 | AJ31: =+AK31/AI31 -> #DIV/0! | AK31: =+AK16+AK21-AK6-AK11-AK26 -> 0 | AL31: =+AL26 -> 0 | AM31: =+AN31/AL31 -> #DIV/0! | AN31: =+AN16+AN21-AN6-AN11-AN26 -> 0
A36: Incentive | D36: =477*25 -> 11925 | G36: 10525 | J36: 8175 | M36: 5125 | P36: 6500 | S36: 5875 | V36: 9450 | AB36: 13700 | AE36: 0 | AH36: 0 | AK36: 0 | AN36: =+AK36+AH36+AE36+AB36+Y36+V36+S36+P36+M36+J36+G36+D36 -> 71275
A37: Sample Test | D37: 0 | G37: 0 | J37: 0 | M37: 0 | P37: 0 | S37: 0 | V37: 0 | AB37: 0 | AE37: 0 | AH37: 0 | AK37: 0 | AN37: =+AK37+AH37+AE37+AB37+Y37+V37+S37+P37+M37+J37+G37+D37 -> 0
A38: Rent | D38: =477*5 -> 2385 | G38: =421*5 -> 2105 | J38: 0 | M38: 0 | P38: 0 | S38: 0 | V38: 0 | AB38: 0 | AE38: 0 | AH38: 0 | AK38: 0 | AN38: =+AK38+AH38+AE38+AB38+Y38+V38+S38+P38+M38+J38+G38+D38 -> 4490
A39: Transportation | D39: =477*25+2350 -> 14275 | G39: =421*25 -> 10525 | J39: 9810 | M39: 6150 | P39: 7800 | S39: 7050 | V39: 11340 | AB39: 16440 | AE39: 0 | AH39: 0 | AK39: 0 | AN39: =+AK39+AH39+AE39+AB39+Y39+V39+S39+P39+M39+J39+G39+D39 -> 83390
D40: =SUM(D36:D39) -> 28585 | G40: =SUM(G36:G39) -> 23155 | J40: =SUM(J36:J39) -> 17985 | M40: =SUM(M36:M39) -> 11275 | P40: =SUM(P36:P39) -> 14300 | S40: =SUM(S36:S39) -> 12925 | V40: =SUM(V36:V39) -> 20790 | Y40: =SUM(Y36:Y39) -> 0 | AB40: =SUM(AB36:AB39) -> 30140 | AE40: =SUM(AE36:AE39) -> 0 | AH40: =SUM(AH36:AH39) -> 0 | AK40: =SUM(AK36:AK39) -> 0 | AN40: =SUM(AN36:AN39) -> 159155

Sheet Sheet3
A1: Month | B1: Feb-26
A3: Sum of Qty Sold
A4: 125

Sheet Purchases
A1: PO NO | B1: PO Date | C1: Purcahse From | D1: Invoice No | E1: Invoice Date | F1: Month | G1: Item | H1: Qty | I1: Rate | J1: AMOUNT | K1: Delivered at | L1: Delivered Item | M1: Delivered Qty | N1: Dilvery Challan Number | O1: GRN document received | P1: Delivered date | Q1: TCS | R1: Payment Amount | S1: Payment Date | T1: Balance
C2: Transfer | E2: 46081 | F2: 46054 | G2: Gomukh Gold 50 Kgs | H2: 50 | I2: 0 | J2: =Table2[[#This Row],[Qty]]*Table2[[#This Row],[Rate]] -> 0 | K2: Piragutu | L2: Gomukh Gold 50 Kgs | M2: 50 | Q2: =ROUND(J2*0.1/100,0) -> 0 | T2: =J2-R2-Q2 -> 0
C3: Transfer | E3: 46081 | F3: 46054 | G3: Gomukh Gold 50 Kgs | H3: -50 | I3: 0 | J3: =Table2[[#This Row],[Qty]]*Table2[[#This Row],[Rate]] -> 0 | K3: Pali | L3: Gomukh Gold 50 Kgs | M3: -50 | Q3: =ROUND(J3*0.1/100,0) -> 0 | T3: =J3-R3-Q3 -> 0
C4: Transfer | E4: 46081 | F4: 46054 | G4: Gomukh Gold 50 Kgs | H4: 25 | I4: 0 | J4: =Table2[[#This Row],[Qty]]*Table2[[#This Row],[Rate]] -> 0 | K4: Hisri | L4: Gomukh Gold 50 Kgs | M4: 25 | Q4: =ROUND(J4*0.1/100,0) -> 0 | T4: =J4-R4-Q4 -> 0
C5: Transfer | E5: 46081 | F5: 46054 | G5: Gomukh Gold 50 Kgs | H5: -25 | I5: 0 | J5: =Table2[[#This Row],[Qty]]*Table2[[#This Row],[Rate]] -> 0 | K5: Pali | L5: Gomukh Gold 50 Kgs | M5: -25 | Q5: =ROUND(J5*0.1/100,0) -> 0 | T5: =J5-R5-Q5 -> 0
C6: Transfer | E6: 46091 | F6: 46082 | G6: Gomukh Gold 50 Kgs | H6: 50 | I6: 0 | J6: =Table2[[#This Row],[Qty]]*Table2[[#This Row],[Rate]] -> 0 | K6: Itki | L6: Gomukh Gold 50 Kgs | M6: 50 | Q6: =ROUND(J6*0.1/100,0) -> 0 | T6: =J6-R6-Q6 -> 0
C7: Transfer | E7: 46091 | F7: 46082 | G7: Gomukh Gold 50 Kgs | H7: -50 | I7: 0 | J7: =Table2[[#This Row],[Qty]]*Table2[[#This Row],[Rate]] -> 0 | K7: Bero | L7: Gomukh Gold 50 Kgs | M7: -50 | Q7: =ROUND(J7*0.1/100,0) -> 0 | T7: =J7-R7-Q7 -> 0
C8: Transfer | E8: 46142 | F8: 46113 | G8: Gomukh Gold 50 Kgs | H8: 38 | I8: 0 | J8: =Table2[[#This Row],[Qty]]*Table2[[#This Row],[Rate]] -> 0 | K8: Bero | L8: Gomukh Gold 50 Kgs | M8: 38 | Q8: =ROUND(J8*0.1/100,0) -> 0 | T8: =J8-R8-Q8 -> 0
C9: Transfer | E9: 46142 | F9: 46113 | G9: Gomukh Gold 50 Kgs | H9: -38 | I9: 0 | J9: =Table2[[#This Row],[Qty]]*Table2[[#This Row],[Rate]] -> 0 | K9: Ormanjhi | L9: Gomukh Gold 50 Kgs | M9: -38 | Q9: =ROUND(J9*0.1/100,0) -> 0 | T9: =J9-R9-Q9 -> 0
C10: Transfer | E10: 46146 | F10: 46113 | G10: Gomukh Gold 50 Kgs | H10: 20 | I10: 0 | J10: =Table2[[#This Row],[Qty]]*Table2[[#This Row],[Rate]] -> 0 | K10: Chanho | L10: Gomukh Gold 50 Kgs | M10: 20 | Q10: =ROUND(J10*0.1/100,0) -> 0 | T10: =J10-R10-Q10 -> 0
C11: Transfer | E11: 46146 | F11: 46113 | G11: Gomukh Gold 50 Kgs | H11: -20 | I11: 0 | J11: =Table2[[#This Row],[Qty]]*Table2[[#This Row],[Rate]] -> 0 | K11: Pali | L11: Gomukh Gold 50 Kgs | M11: -20 | Q11: =ROUND(J11*0.1/100,0) -> 0 | T11: =J11-R11-Q11 -> 0
A12: JH/PO/023/25-26 | B12: 46058 | C12: Godrej | D12: 1282532245 | E12: 46063 | F12: 46054 | G12: Gomukh Gold 50 Kgs | H12: 150 | I12: 1060 | J12: =Table2[[#This Row],[Qty]]*Table2[[#This Row],[Rate]] -> 159000 | K12: Bero | L12: Gomukh Gold 50 Kgs | M12: 200 | N12: 8003564894 | O12: Yes | P12: 46066 | Q12: =ROUND(J12*0.1/100,0) -> 159 | R12: 158841 | S12: 46083 | T12: =J12-R12-Q12 -> 0
A13: JH/PO/023/25-26 | B13: 46058 | C13: Godrej | D13: 1282532246 | E13: 46063 | F13: 46054 | G13: Gomukh Gold 50 Kgs | H13: 200 | I13: 1060 | J13: =Table2[[#This Row],[Qty]]*Table2[[#This Row],[Rate]] -> 212000 | K13: Pali | L13: Gomukh Gold 50 Kgs | M13: 200 | N13: 8003564898 | O13: Yes | P13: 46066 | Q13: =ROUND(J13*0.1/100,0) -> 212 | R13: 211788 | S13: 46083 | T13: =J13-R13-Q13 -> 0
A14: JH/PO/023/25-26 | B14: 46058 | C14: Godrej | D14: 1282532247 | E14: 46063 | F14: 46054 | G14: Gomukh Gold 50 Kgs | H14: 150 | I14: 1060 | J14: =Table2[[#This Row],[Qty]]*Table2[[#This Row],[Rate]] -> 159000 | K14: Chanho | L14: Gomukh Gold 50 Kgs | M14: 100 | N14: 8003564900 | O14: Yes | P14: 46065 | Q14: =ROUND(J14*0.1/100,0) -> 159 | R14: 158841 | S14: 46083 | T14: =J14-R14-Q14 -> 0
A15: JH/PO/025/25-26 | B15: 46070 | C15: Godrej | D15: 1282532303 | E15: 46072 | F15: 46054 | G15: Gomukh Gold 50 Kgs | H15: 196 | I15: 1060 | J15: =Table2[[#This Row],[Qty]]*Table2[[#This Row],[Rate]] -> 207760 | K15: Chuttu | L15: Gomukh Gold 50 Kgs | M15: 96 | N15: 8003571870 | O15: Yes | P15: 46074 | Q15: =ROUND(J15*0.1/100,0) -> 208 | R15: 207552 | S15: 46088 | T15: =J15-R15-Q15 -> 0
A16: JH/PO/025/25-26 | B16: 46070 | C16: Godrej | D16: 1282532304 | E16: 46072 | F16: 46054 | G16: Gomukh Gold 50 Kgs | H16: 200 | I16: 1060 | J16: =Table2[[#This Row],[Qty]]*Table2[[#This Row],[Rate]] -> 212000 | K16: Dumardagga | L16: Gomukh Gold 50 Kgs | M16: 250 | N16: 8003571876 | O16: Yes | P16: 46074 | Q16: =ROUND(J16*0.1/100,0) -> 212 | R16: 211788 | S16: 46088 | T16: =J16-R16-Q16 -> 0
A17: JH/PO/025/25-26 | B17: 46070 | C17: Godrej | D17: 1282532305 | E17: 46072 | F17: 46054 | G17: Gomukh Gold 50 Kgs | H17: 100 | I17: 1060 | J17: =Table2[[#This Row],[Qty]]*Table2[[#This Row],[Rate]] -> 106000 | K17: Ormanjhi | L17: Gomukh Gold 50 Kgs | M17: 150 | N17: 8003571882 | O17: Yes | P17: 46074 | Q17: =ROUND(J17*0.1/100,0) -> 106 | R17: 105894 | S17: 46088 | T17: =J17-R17-Q17 -> 0
A18: JH/PO/026/25-26 | B18: 46083 | C18: Godrej | D18: 1282532428 | E18: 46091 | F18: 46082 | G18: Gomukh Gold 50 Kgs | H18: 300 | I18: 1080 | J18: =Table2[[#This Row],[Qty]]*Table2[[#This Row],[Rate]] -> 324000 | K18: Itki | L18: Gomukh Gold 50 Kgs | M18: 300 | N18: 8003585791 | O18: Yes | P18: 46092 | Q18: =ROUND(J18*0.1/100,0) -> 324 | R18: 323676 | S18: 46104 | T18: =J18-R18-Q18 -> 0
A19: JH/PO/026/25-26 | B19: 46083 | C19: Godrej | D19: 1282532429 | E19: 46091 | F19: 46082 | G19: Gomukh Gold 50 Kgs | H19: 100 | I19: 1080 | J19: =Table2[[#This Row],[Qty]]*Table2[[#This Row],[Rate]] -> 108000 | K19: Pali | L19: Gomukh Gold 50 Kgs | M19: 100 | N19: 8003585799 | O19: Yes | P19: 46093 | Q19: =ROUND(J19*0.1/100,0) -> 108 | R19: 107892 | S19: 46104 | T19: =J19-R19-Q19 -> 0
A20: JH/PO/026/25-26 | B20: 46083 | C20: Godrej | D20: 1282532430 | E20: 46091 | F20: 46082 | G20: Gomukh Gold 50 Kgs | H20: 100 | I20: 1080 | J20: =Table2[[#This Row],[Qty]]*Table2[[#This Row],[Rate]] -> 108000 | K20: Pali | L20: Gomukh Gold 50 Kgs | M20: 100 | N20: 8003585814 | O20: Yes | P20: 46093 | Q20: =ROUND(J20*0.1/100,0) -> 108 | R20: 107892 | S20: 46104 | T20: =J20-R20-Q20 -> 0
H21: =SUBTOTAL(109,Table2[Qty]) -> 1496 | J21: =SUBTOTAL(109,Table2[AMOUNT]) -> 1595760 | T21: =SUBTOTAL(109,Table2[Balance]) -> 0

Sheet Sales
A1: Date | B1: Godown | C1: MPG Name | D1: New Code | E1: Name of Product | F1: Qty Sold | G1: Rate | H1: Sales Amount | I1: Sale Type | J1: Salesman Name | K1: Challan Number | L1: Month | M1: Mode | N1: Cycle | O1: Deduction Date | P1: Payment Amt | Q1: Dues | R1: Remarks | S1: Ageing
A2: 46072 | B2: Pali | C2: Tikotoli | D2: 20020020 | E2: Gomukh Gold 50 Kgs | F2: 5 | G2: 1250 | H2: =Table1[[#This Row],[Qty Sold]]*Table1[[#This Row],[Rate]] -> 6250 | I2: Deduction from Milk Payment | L2: =TEXT(A2,"mmm-yy") -> Feb-26 | M2: Farmer | N2: 13 Feb - 19 Feb & 20-26 Feb | O2: 46072 | P2: =4494+1756 -> 6250 | Q2: =H2-P2 -> 0 | S2: =IF(Q2<=0,0,(TODAY()-A2)) -> 0
A3: 46075 | B3: Chanho | C3: Nawatand | D3: 20090017 | E3: Gomukh Gold 50 Kgs | F3: 2 | G3: 1250 | H3: =Table1[[#This Row],[Qty Sold]]*Table1[[#This Row],[Rate]] -> 2500 | I3: Deduction from Milk Payment | K3: 4844 | L3: =TEXT(A3,"mmm-yy") -> Feb-26 | M3: Farmer | N3: 20 Feb - 26 Feb | O3: 46079 | P3: 2500 | Q3: =H3-P3 -> 0 | S3: =IF(Q3<=0,0,(TODAY()-A3)) -> 0
A4: 46075 | B4: Chanho | C4: Tutlo | D4: 20010053 | E4: Gomukh Gold 50 Kgs | F4: 1 | G4: 1250 | H4: =Table1[[#This Row],[Qty Sold]]*Table1[[#This Row],[Rate]] -> 1250 | I4: Deduction from Milk Payment | K4: 4845 | L4: =TEXT(A4,"mmm-yy") -> Feb-26 | M4: Bank | O4: 46080 | P4: 1250 | Q4: =H4-P4 -> 0 | S4: =IF(Q4<=0,0,(TODAY()-A4)) -> 0
A5: 46075 | B5: Chanho | C5: Tutlo | D5: 20010053 | E5: Gomukh Gold 50 Kgs | F5: 3 | G5: 1250 | H5: =Table1[[#This Row],[Qty Sold]]*Table1[[#This Row],[Rate]] -> 3750 | I5: Deduction from Milk Payment | K5: 4845 | L5: =TEXT(A5,"mmm-yy") -> Feb-26 | M5: Farmer | N5: 20 Feb - 26 Feb | O5: 46079 | P5: 3750 | Q5: =H5-P5 -> 0 | S5: =IF(Q5<=0,0,(TODAY()-A5)) -> 0
A6: 46075 | B6: Chanho | C6: Barhe | D6: 20090011 | E6: Gomukh Gold 50 Kgs | F6: 2 | G6: 1250 | H6: =Table1[[#This Row],[Qty Sold]]*Table1[[#This Row],[Rate]] -> 2500 | I6: Deduction from Milk Payment | K6: 4846 | L6: =TEXT(A6,"mmm-yy") -> Feb-26 | M6: Farmer | N6: 20 Feb - 26 Feb | O6: 46079 | P6: 2500 | Q6: =H6-P6 -> 0 | S6: =IF(Q6<=0,0,(TODAY()-A6)) -> 0
A7: 46075 | B7: Chanho | C7: Tutlo | D7: 20010053 | E7: Gomukh Gold 50 Kgs | F7: 2 | G7: 1250 | H7: =Table1[[#This Row],[Qty Sold]]*Table1[[#This Row],[Rate]] -> 2500 | I7: Deduction from Milk Payment | L7: =TEXT(A7,"mmm-yy") -> Feb-26 | M7: Farmer | N7: 20 Feb - 26 Feb & 27-05 Mar | O7: 46079 | P7: =1591+909 -> 2500 | Q7: =H7-P7 -> 0 | S7: =IF(Q7<=0,0,(TODAY()-A7)) -> 0
A8: 46075 | B8: Chanho | C8: Chanho | D8: 20090001 | E8: Gomukh Gold 50 Kgs | F8: 1 | G8: 1250 | H8: =Table1[[#This Row],[Qty Sold]]*Table1[[#This Row],[Rate]] -> 1250 | I8: Deduction from Milk Payment | K8: 4848 | L8: =TEXT(A8,"mmm-yy") -> Feb-26 | M8: Farmer | N8: 20 Feb - 26 Feb | O8: 46079 | P8: 1250 | Q8: =H8-P8 -> 0 | S8: =IF(Q8<=0,0,(TODAY()-A8)) -> 0
A9: 46079 | B9: Pali | C9: Bijuliya | D9: 20020003 | E9: Gomukh Gold 50 Kgs | F9: 5 | G9: 1250 | H9: =Table1[[#This Row],[Qty Sold]]*Table1[[#This Row],[Rate]] -> 6250 | I9: Deduction from Milk Payment | L9: =TEXT(A9,"mmm-yy") -> Feb-26 | M9: Farmer | N9: 20 Feb - 26 Feb | O9: 46079 | P9: 6250 | Q9: =H9-P9 -> 0 | S9: =IF(Q9<=0,0,(TODAY()-A9)) -> 0
A10: 46079 | B10: Pali | C10: Pali | D10: 20020001 | E10: Gomukh Gold 50 Kgs | F10: 10 | G10: 1250 | H10: =Table1[[#This Row],[Qty Sold]]*Table1[[#This Row],[Rate]] -> 12500 | I10: Deduction from Milk Payment | L10: =TEXT(A10,"mmm-yy") -> Feb-26 | M10: Farmer | N10: 27 Feb - 05 Mar & 06-12 Mar | O10: 46086 | P10: =12468+32 -> 12500 | Q10: =H10-P10 -> 0 | S10: =IF(Q10<=0,0,(TODAY()-A10)) -> 0
A11: 46081 | B11: Dumardagga | C11: Dumardagga | D11: 20060003 | E11: Gomukh Gold 50 Kgs | F11: 20 | G11: 1250 | H11: =Table1[[#This Row],[Qty Sold]]*Table1[[#This Row],[Rate]] -> 25000 | I11: Deduction from Milk Payment | K11: 4736 | L11: =TEXT(A11,"mmm-yy") -> Feb-26 | M11: Farmer | N11: 27 Feb - 05 Mar | O11: 46086 | P11: 25000 | Q11: =H11-P11 -> 0 | S11: =IF(Q11<=0,0,(TODAY()-A11)) -> 0
A12: 46080 | B12: Ormanjhi | C12: Adelhootu | D12: 20060008 | E12: Gomukh Gold 50 Kgs | F12: 20 | G12: 1250 | H12: =Table1[[#This Row],[Qty Sold]]*Table1[[#This Row],[Rate]] -> 25000 | I12: Deduction from Milk Payment | K12: 4730 | L12: =TEXT(A12,"mmm-yy") -> Feb-26 | M12: Farmer | N12: 06 Mar - 12 Mar & 13-19 Mar | O12: 46093 | P12: =12500+12500 -> 25000 | Q12: =H12-P12 -> 0 | S12: =IF(Q12<=0,0,(TODAY()-A12)) -> 0
A13: 46081 | B13: Bero | C13: Boriya | D13: 20010015 | E13: Gomukh Gold 50 Kgs | F13: 0 | G13: 0 | H13: 11000 | I13: Deduction from Milk Payment | L13: =TEXT(A13,"mmm-yy") -> Feb-26 | M13: Bank | O13: 46139 | P13: 11000 | Q13: =H13-P13 -> 0 | S13: =IF(Q13<=0,0,(TODAY()-A13)) -> 0
A14: 46081 | B14: Bero | C14: Boriya | D14: 20010015 | E14: Gomukh Gold 50 Kgs | F14: 22 | G14: 1250 | H14: =Table1[[#This Row],[Qty Sold]]*Table1[[#This Row],[Rate]]-11000 -> 16500 | I14: Deduction from Milk Payment | K14: 4731 | L14: =TEXT(A14,"mmm-yy") -> Feb-26 | M14: Farmer | N14: 20 Mar - 26 Mar & 10-16 Apr 17-23 Apr | O14: 46107 | P14: =12500+2000+2000 -> 16500 | Q14: =H14-P14 -> 0 | S14: =IF(Q14<=0,0,(TODAY()-A14)) -> 0
A15: 46081 | B15: Bero | C15: Erchoro | D15: 20010008 | E15: Gomukh Gold 50 Kgs | F15: 5 | G15: 1250 | H15: =Table1[[#This Row],[Qty Sold]]*Table1[[#This Row],[Rate]] -> 6250 | I15: Deduction from Milk Payment | K15: 4732 | L15: =TEXT(A15,"mmm-yy") -> Feb-26 | M15: Farmer | N15: 27 Feb - 05 Mar | O15: 46086 | P15: 6250 | Q15: =H15-P15 -> 0 | S15: =IF(Q15<=0,0,(TODAY()-A15)) -> 0
A16: 46081 | B16: Bero | C16: Erchoro | D16: 20010008 | E16: Gomukh Gold 50 Kgs | F16: 20 | G16: 1250 | H16: =Table1[[#This Row],[Qty Sold]]*Table1[[#This Row],[Rate]] -> 25000 | I16: Deduction from Milk Payment | K16: 4732 | L16: =TEXT(A16,"mmm-yy") -> Feb-26 | M16: Farmer | N16: 06 Mar - 12 Mar & 13-19 Mar 20-26 Mar/03-09 Apr | O16: 46093 | P16: =6250+6250+6250+6250 -> 25000 | Q16: =H16-P16 -> 0 | S16: =IF(Q16<=0,0,(TODAY()-A16)) -> 0
A17: 46081 | B17: Bero | C17: Etachildri | D17: 20010016 | E17: Gomukh Gold 50 Kgs | F17: 1 | G17: 1250 | H17: =Table1[[#This Row],[Qty Sold]]*Table1[[#This Row],[Rate]] -> 1250 | I17: Deduction from Milk Payment | K17: 4733 | L17: =TEXT(A17,"mmm-yy") -> Feb-26 | M17: Farmer | N17: 28 Nov - 04 Dec | O17: 45995 | P17: 1250 | Q17: =H17-P17 -> 0 | S17: =IF(Q17<=0,0,(TODAY()-A17)) -> 0
A18: 46081 | B18: Bero | C18: Masu | D18: 20010055 | E18: Gomukh Gold 50 Kgs | F18: 1 | G18: 1250 | H18: =Table1[[#This Row],[Qty Sold]]*Table1[[#This Row],[Rate]] -> 1250 | I18: Deduction from Milk Payment | K18: 4734 | L18: =TEXT(A18,"mmm-yy") -> Feb-26 | M18: Bank | O18: 46095 | P18: 1250 | Q18: =H18-P18 -> 0 | S18: =IF(Q18<=0,0,(TODAY()-A18)) -> 0
A19: 46081 | B19: Pali | C19: Tikotoli | D19: 20020020 | E19: Gomukh Gold 50 Kgs | F19: 5 | G19: 1250 | H19: =Table1[[#This Row],[Qty Sold]]*Table1[[#This Row],[Rate]] -> 6250 | I19: Deduction from Milk Payment | L19: =TEXT(A19,"mmm-yy") -> Feb-26 | M19: Farmer | N19: 27 Feb - 05 Mar & 13-19 Mar | O19: 46086 | P19: =4473+1777 -> 6250 | Q19: =H19-P19 -> 0 | S19: =IF(Q19<=0,0,(TODAY()-A19)) -> 0
A20: 46086 | B20: Pali | C20: Bijuliya | D20: 20020003 | E20: Gomukh Gold 50 Kgs | F20: 5 | G20: 1250 | H20: =Table1[[#This Row],[Qty Sold]]*Table1[[#This Row],[Rate]] -> 6250 | I20: Deduction from Milk Payment | L20: =TEXT(A20,"mmm-yy") -> Mar-26 | M20: Farmer | N20: 27 Feb - 05 Mar | O20: 46086 | P20: 6250 | Q20: =H20-P20 -> 0 | S20: =IF(Q20<=0,0,(TODAY()-A20)) -> 0
A21: 46086 | B21: Pali | C21: Dhantatoli | D21: 20020011 | E21: Gomukh Gold 50 Kgs | F21: 3 | G21: 1250 | H21: =Table1[[#This Row],[Qty Sold]]*Table1[[#This Row],[Rate]] -> 3750 | I21: Deduction from Milk Payment | L21: =TEXT(A21,"mmm-yy") -> Mar-26 | M21: Farmer | N21: 27 Feb - 05 Mar & 13-19 Mar | O21: 46086 | P21: =2500+1250 -> 3750 | Q21: =H21-P21 -> 0 | S21: =IF(Q21<=0,0,(TODAY()-A21)) -> 0
A22: 46086 | B22: Piragutu | C22: Saram | D22: 20070002 | E22: Gomukh Gold 50 Kgs | F22: 4 | G22: 1250 | H22: =Table1[[#This Row],[Qty Sold]]*Table1[[#This Row],[Rate]] -> 5000 | I22: Deduction from Milk Payment | L22: =TEXT(A22,"mmm-yy") -> Mar-26 | M22: Farmer | N22: 27 Feb - 05 Mar | O22: 46086 | P22: 5000 | Q22: =H22-P22 -> 0 | S22: =IF(Q22<=0,0,(TODAY()-A22)) -> 0
A23: 46087 | B23: Chanho | C23: Pakariyo2 | D23: 20090020 | E23: Gomukh Gold 50 Kgs | F23: 2 | G23: 1250 | H23: =Table1[[#This Row],[Qty Sold]]*Table1[[#This Row],[Rate]] -> 2500 | I23: Deduction from Milk Payment | L23: =TEXT(A23,"mmm-yy") -> Mar-26 | M23: Farmer | N23: 27 Feb - 05 Mar | O23: 46086 | P23: 2500 | Q23: =H23-P23 -> 0 | S23: =IF(Q23<=0,0,(TODAY()-A23)) -> 0
A24: 46087 | B24: Chanho | C24: Naudi | D24: 20090003 | E24: Gomukh Gold 50 Kgs | F24: 10 | G24: 1250 | H24: =Table1[[#This Row],[Qty Sold]]*Table1[[#This Row],[Rate]] -> 12500 | I24: Deduction from Milk Payment | L24: =TEXT(A24,"mmm-yy") -> Mar-26 | M24: Farmer | N24: 27 Feb - 05 Mar & 06-12 Mar 13-19 Mar 20-26 Mar, 27-31 Mar | O24: 46086 | P24: =4798+2598+1910+391+259 -> 9956 | Q24: =H24-P24 -> 2544 | S24: =IF(Q24<=0,0,(TODAY()-A24)) -> 74
A25: 46087 | B25: Chanho | C25: Narkopi | D25: 20010054 | E25: Gomukh Gold 50 Kgs | F25: 2 | G25: 1250 | H25: =Table1[[#This Row],[Qty Sold]]*Table1[[#This Row],[Rate]] -> 2500 | I25: Deduction from Milk Payment | L25: =TEXT(A25,"mmm-yy") -> Mar-26 | M25: Farmer | N25: 13 Mar - 19 Mar | O25: 46100 | P25: 2500 | Q25: =H25-P25 -> 0 | S25: =IF(Q25<=0,0,(TODAY()-A25)) -> 0
A26: 46087 | B26: Chanho | C26: Pakariyo | D26: 20090015 | E26: Gomukh Gold 50 Kgs | F26: 3 | G26: 1250 | H26: =Table1[[#This Row],[Qty Sold]]*Table1[[#This Row],[Rate]] -> 3750 | I26: Deduction from Milk Payment | L26: =TEXT(A26,"mmm-yy") -> Mar-26 | M26: Farmer | N26: 27 Feb - 05 Mar & 06-12 Mar | O26: 46086 | P26: =2500+1250 -> 3750 | Q26: =H26-P26 -> 0 | S26: =IF(Q26<=0,0,(TODAY()-A26)) -> 0
A27: 46087 | B27: Chanho | C27: Nawatand | D27: 20090017 | E27: Gomukh Gold 50 Kgs | F27: 5 | G27: 1250 | H27: =Table1[[#This Row],[Qty Sold]]*Table1[[#This Row],[Rate]] -> 6250 | I27: Deduction from Milk Payment | L27: =TEXT(A27,"mmm-yy") -> Mar-26 | M27: Farmer | N27: 27 Feb - 05 Mar & 06-12 Mar | O27: 46086 | P27: =3750+2500 -> 6250 | Q27: =H27-P27 -> 0 | S27: =IF(Q27<=0,0,(TODAY()-A27)) -> 0
A28: 46088 | B28: Chuttu | C28: Chuttu | D28: 20060004 | E28: Gomukh Gold 50 Kgs | F28: 10 | G28: 1250 | H28: =Table1[[#This Row],[Qty Sold]]*Table1[[#This Row],[Rate]] -> 12500 | I28: Deduction from Milk Payment | K28: 4738 | L28: =TEXT(A28,"mmm-yy") -> Mar-26 | M28: Farmer | N28: 27 Feb - 05 Mar & 06-12 Mar 13-19 Mar | O28: 46086 | P28: =3750+2500+6250 -> 12500 | Q28: =H28-P28 -> 0 | R28: As per discussed by satendra ji ormanjhi payment 6250 adjust chuttu | S28: =IF(Q28<=0,0,(TODAY()-A28)) -> 0
A29: 46091 | B29: Dumardagga | C29: Dumardagga | D29: 20060003 | E29: Gomukh Gold 50 Kgs | F29: 20 | G29: 1250 | H29: =Table1[[#This Row],[Qty Sold]]*Table1[[#This Row],[Rate]] -> 25000 | I29: Deduction from Milk Payment | K29: 4737 | L29: =TEXT(A29,"mmm-yy") -> Mar-26 | M29: Farmer | N29: 06 Mar - 12 Mar | O29: 46093 | P29: 25000 | Q29: =H29-P29 -> 0 | S29: =IF(Q29<=0,0,(TODAY()-A29)) -> 0
A30: 46088 | B30: Bero | C30: Bero | D30: 20010003 | E30: Gomukh Gold 50 Kgs | F30: 15 | G30: 1250 | H30: =Table1[[#This Row],[Qty Sold]]*Table1[[#This Row],[Rate]] -> 18750 | I30: Deduction from Milk Payment | K30: 4735 | L30: =TEXT(A30,"mmm-yy") -> Mar-26 | M30: Farmer | N30: 20 Feb - 26 Feb & 27-05 Mar 06-12 Mar | O30: 46079 | P30: =4418+7500+6832 -> 18750 | Q30: =H30-P30 -> 0 | S30: =IF(Q30<=0,0,(TODAY()-A30)) -> 0
A31: 46095 | B31: Chanho | C31: Tutlo | D31: 20010053 | E31: Gomukh Gold 50 Kgs | F31: 2 | G31: 1250 | H31: =Table1[[#This Row],[Qty Sold]]*Table1[[#This Row],[Rate]] -> 2500 | I31: Deduction from Milk Payment | L31: =TEXT(A31,"mmm-yy") -> Mar-26 | M31: Farmer | N31: 06 Mar - 12 Mar & 13-19 Mar | O31: 46093 | P31: =2209+291 -> 2500 | Q31: =H31-P31 -> 0 | S31: =IF(Q31<=0,0,(TODAY()-A31)) -> 0
A32: 46099 | B32: Hisri | C32: Hisri | D32: 20030001 | E32: Gomukh Gold 50 Kgs | F32: 5 | G32: 1250 | H32: =Table1[[#This Row],[Qty Sold]]*Table1[[#This Row],[Rate]] -> 6250 | I32: Deduction from Milk Payment | L32: =TEXT(A32,"mmm-yy") -> Mar-26 | M32: Bank | O32: 46099 | P32: 6250 | Q32: =H32-P32 -> 0 | S32: =IF(Q32<=0,0,(TODAY()-A32)) -> 0
A33: 46098 | B33: Dumardagga | C33: Dumardagga | D33: 20060003 | E33: Gomukh Gold 50 Kgs | F33: 20 | G33: 1250 | H33: =Table1[[#This Row],[Qty Sold]]*Table1[[#This Row],[Rate]] -> 25000 | I33: Deduction from Milk Payment | K33: 4740 | L33: =TEXT(A33,"mmm-yy") -> Mar-26 | M33: Farmer | N33: 13 Mar - 19 Mar | O33: 46100 | P33: 25000 | Q33: =H33-P33 -> 0 | S33: =IF(Q33<=0,0,(TODAY()-A33)) -> 0
A34: 46098 | B34: Ormanjhi | C34: Ormanjhi | D34: 20060001 | E34: Gomukh Gold 50 Kgs | F34: 1 | G34: 1250 | H34: =Table1[[#This Row],[Qty Sold]]*Table1[[#This Row],[Rate]] -> 1250 | I34: Deduction from Milk Payment | K34: 4739 | L34: =TEXT(A34,"mmm-yy") -> Mar-26 | M34: Farmer | N34: 06 Feb - 12 Feb | O34: 46065 | P34: 1250 | Q34: =H34-P34 -> 0 | S34: =IF(Q34<=0,0,(TODAY()-A34)) -> 0
A35: 46096 | B35: Pali | C35: Bijuliya | D35: 20020003 | E35: Gomukh Gold 50 Kgs | F35: 15 | G35: 1250 | H35: =Table1[[#This Row],[Qty Sold]]*Table1[[#This Row],[Rate]] -> 18750 | I35: Deduction from Milk Payment | L35: =TEXT(A35,"mmm-yy") -> Mar-26 | M35: Farmer | N35: 13 Mar - 19 Mar & 20-26 Mar | O35: 46100 | P35: =12500+6250 -> 18750 | Q35: =H35-P35 -> 0 | S35: =IF(Q35<=0,0,(TODAY()-A35)) -> 0
A36: 46098 | B36: Pali | C36: Ranikhatanga | D36: 20020006 | E36: Gomukh Gold 50 Kgs | F36: 10 | G36: 1250 | H36: =Table1[[#This Row],[Qty Sold]]*Table1[[#This Row],[Rate]] -> 12500 | I36: Deduction from Milk Payment | L36: =TEXT(A36,"mmm-yy") -> Mar-26 | M36: Farmer | N36: 13 Mar - 19 Mar | O36: 46100 | P36: =3677 -> 3677 | Q36: =H36-P36 -> 8823 | S36: =IF(Q36<=0,0,(TODAY()-A36)) -> 63
A37: 46098 | B37: Pali | C37: Tikotoli | D37: 20020020 | E37: Gomukh Gold 50 Kgs | F37: 5 | G37: 1250 | H37: =Table1[[#This Row],[Qty Sold]]*Table1[[#This Row],[Rate]] -> 6250 | I37: Deduction from Milk Payment | L37: =TEXT(A37,"mmm-yy") -> Mar-26 | M37: Farmer | N37: 13 Mar - 19 Mar & 20-26 Mar/01-07 May | O37: 46100 | P37: =5303+925+22 -> 6250 | Q37: =H37-P37 -> 0 | S37: =IF(Q37<=0,0,(TODAY()-A37)) -> 0
A38: 46098 | B38: Pali | C38: Pali | D38: 20020001 | E38: Gomukh Gold 50 Kgs | F38: 5 | G38: 1250 | H38: =Table1[[#This Row],[Qty Sold]]*Table1[[#This Row],[Rate]] -> 6250 | I38: Deduction from Milk Payment | L38: =TEXT(A38,"mmm-yy") -> Mar-26 | M38: Farmer | N38: 13 Mar - 19 Mar | O38: 46100 | P38: 6250 | Q38: =H38-P38 -> 0 | S38: =IF(Q38<=0,0,(TODAY()-A38)) -> 0
A39: 46098 | B39: Piragutu | C39: Saram | D39: 20070002 | E39: Gomukh Gold 50 Kgs | F39: 2 | G39: 1250 | H39: =Table1[[#This Row],[Qty Sold]]*Table1[[#This Row],[Rate]] -> 2500 | I39: Deduction from Milk Payment | L39: =TEXT(A39,"mmm-yy") -> Mar-26 | M39: Farmer | N39: 13 Mar - 19 Mar | O39: 46100 | P39: 2500 | Q39: =H39-P39 -> 0 | S39: =IF(Q39<=0,0,(TODAY()-A39)) -> 0
A40: 46098 | B40: Piragutu | C40: Piragutu | D40: 20070001 | E40: Gomukh Gold 50 Kgs | F40: 3 | G40: 1250 | H40: =Table1[[#This Row],[Qty Sold]]*Table1[[#This Row],[Rate]] -> 3750 | I40: Deduction from Milk Payment | L40: =TEXT(A40,"mmm-yy") -> Mar-26 | M40: Farmer | N40: 13 Mar - 19 Mar | O40: 46100 | P40: 3750 | Q40: =H40-P40 -> 0 | S40: =IF(Q40<=0,0,(TODAY()-A40)) -> 0
A41: 46098 | B41: Piragutu | C41: Piragutu | D41: 20070001 | E41: Gomukh Gold 50 Kgs | F41: 2 | G41: 1250 | H41: =Table1[[#This Row],[Qty Sold]]*Table1[[#This Row],[Rate]] -> 2500 | I41: Deduction from Milk Payment | L41: =TEXT(A41,"mmm-yy") -> Mar-26 | M41: Farmer | N41: 20 Mar - 26 Mar | O41: 46107 | P41: 2500 | Q41: =H41-P41 -> 0 | S41: =IF(Q41<=0,0,(TODAY()-A41)) -> 0
A42: 46100 | B42: Chanho | C42: Chanho | D42: 20090001 | E42: Gomukh Gold 50 Kgs | F42: 4 | G42: 1250 | H42: =Table1[[#This Row],[Qty Sold]]*Table1[[#This Row],[Rate]] -> 5000 | I42: Deduction from Milk Payment | L42: =TEXT(A42,"mmm-yy") -> Mar-26 | M42: Bank | O42: 46100 | P42: 5000 | Q42: =H42-P42 -> 0 | S42: =IF(Q42<=0,0,(TODAY()-A42)) -> 0
A43: 46100 | B43: Chanho | C43: Pakariyo | D43: 20090015 | E43: Gomukh Gold 50 Kgs | F43: 2 | G43: 1250 | H43: =Table1[[#This Row],[Qty Sold]]*Table1[[#This Row],[Rate]] -> 2500 | I43: Deduction from Milk Payment | L43: =TEXT(A43,"mmm-yy") -> Mar-26 | M43: Farmer | N43: 13 Mar - 19 Mar & 20-26 Mar | O43: 46100 | P43: =1885+615 -> 2500 | Q43: =H43-P43 -> 0 | S43: =IF(Q43<=0,0,(TODAY()-A43)) -> 0
A44: 46100 | B44: Chanho | C44: Barhe | D44: 20090011 | E44: Gomukh Gold 50 Kgs | F44: 3 | G44: 1250 | H44: =Table1[[#This Row],[Qty Sold]]*Table1[[#This Row],[Rate]] -> 3750 | I44: Deduction from Milk Payment | L44: =TEXT(A44,"mmm-yy") -> Mar-26 | M44: Farmer | N44: 13 Mar - 19 Mar | O44: 46100 | P44: 3750 | Q44: =H44-P44 -> 0 | S44: =IF(Q44<=0,0,(TODAY()-A44)) -> 0
A45: 46100 | B45: Chanho | C45: Barhe | D45: 20090011 | E45: Gomukh Gold 50 Kgs | F45: 2 | G45: 1250 | H45: =Table1[[#This Row],[Qty Sold]]*Table1[[#This Row],[Rate]] -> 2500 | I45: Deduction from Milk Payment | L45: =TEXT(A45,"mmm-yy") -> Mar-26 | M45: Farmer | N45: 20 Mar - 26 Mar | O45: 46107 | P45: 2500 | Q45: =H45-P45 -> 0 | S45: =IF(Q45<=0,0,(TODAY()-A45)) -> 0
A46: 46101 | B46: Chanho | C46: Chanho | D46: 20090001 | E46: Gomukh Gold 50 Kgs | F46: 1 | G46: 1250 | H46: =Table1[[#This Row],[Qty Sold]]*Table1[[#This Row],[Rate]] -> 1250 | I46: Deduction from Milk Payment | L46: =TEXT(A46,"mmm-yy") -> Mar-26 | M46: Bank | O46: 46101 | P46: 1250 | Q46: =H46-P46 -> 0 | S46: =IF(Q46<=0,0,(TODAY()-A46)) -> 0
A47: 46101 | B47: Chanho | C47: Chanho | D47: 20090001 | E47: Gomukh Gold 50 Kgs | F47: 1 | G47: 1250 | H47: =Table1[[#This Row],[Qty Sold]]*Table1[[#This Row],[Rate]] -> 1250 | I47: Deduction from Milk Payment | L47: =TEXT(A47,"mmm-yy") -> Mar-26 | M47: Farmer | N47: 13 Mar - 19 Mar & 20-26 Mar | O47: 46100 | P47: =586+664 -> 1250 | Q47: =H47-P47 -> 0 | S47: =IF(Q47<=0,0,(TODAY()-A47)) -> 0
A48: 46101 | B48: Chanho | C48: Tutlo | D48: 20010053 | E48: Gomukh Gold 50 Kgs | F48: 2 | G48: 1250 | H48: =Table1[[#This Row],[Qty Sold]]*Table1[[#This Row],[Rate]] -> 2500 | I48: Deduction from Milk Payment | L48: =TEXT(A48,"mmm-yy") -> Mar-26 | M48: Farmer | N48: 13 Mar - 19 Mar & 20-26 Mar | O48: 46100 | P48: =1994+506 -> 2500 | Q48: =H48-P48 -> 0 | S48: =IF(Q48<=0,0,(TODAY()-A48)) -> 0
A49: 46101 | B49: Chanho | C49: Kullu | D49: 20090025 | E49: Gomukh Gold 50 Kgs | F49: 3 | G49: 1250 | H49: =Table1[[#This Row],[Qty Sold]]*Table1[[#This Row],[Rate]] -> 3750 | I49: Deduction from Milk Payment | L49: =TEXT(A49,"mmm-yy") -> Mar-26 | M49: Farmer | N49: 13 Mar - 19 Mar | O49: 46100 | P49: 3750 | Q49: =H49-P49 -> 0 | S49: =IF(Q49<=0,0,(TODAY()-A49)) -> 0
A50: 46107 | B50: Chuttu | C50: Chuttu | D50: 20060004 | E50: Gomukh Gold 50 Kgs | F50: 2 | G50: 1250 | H50: =Table1[[#This Row],[Qty Sold]]*Table1[[#This Row],[Rate]]-166 -> 2334 | I50: Deduction from Milk Payment | L50: =TEXT(A50,"mmm-yy") -> Mar-26 | M50: Farmer | N50: 20 Mar - 26 Mar | O50: 46107 | P50: 2334 | Q50: =H50-P50 -> 0 | R50: As per discussed by satendra ji ormanjhi payment 2334 adjust chuttu | S50: =IF(Q50<=0,0,(TODAY()-A50)) -> 0
A51: 46101 | B51: Dumardagga | C51: Dumardagga | D51: 20060003 | E51: Gomukh Gold 50 Kgs | F51: 20 | G51: 1250 | H51: =Table1[[#This Row],[Qty Sold]]*Table1[[#This Row],[Rate]] -> 25000 | I51: Deduction from Milk Payment | L51: =TEXT(A51,"mmm-yy") -> Mar-26 | M51: Farmer | N51: 01-07 May | O51: 46149 | P51: 25000 | Q51: =H51-P51 -> 0 | S51: =IF(Q51<=0,0,(TODAY()-A51)) -> 0
A52: 46107 | B52: Dumardagga | C52: Dumardagga | D52: 20060003 | E52: Gomukh Gold 50 Kgs | F52: 20 | G52: 1250 | H52: =Table1[[#This Row],[Qty Sold]]*Table1[[#This Row],[Rate]] -> 25000 | I52: Deduction from Milk Payment | L52: =TEXT(A52,"mmm-yy") -> Mar-26 | M52: Farmer | N52: 03 Apr - 09 Apr | O52: 46121 | P52: =12500 -> 12500 | Q52: =H52-P52 -> 12500 | S52: =IF(Q52<=0,0,(TODAY()-A52)) -> 54
A53: 46101 | B53: Ormanjhi | C53: Ormanjhi | D53: 20060001 | E53: Gomukh Gold 50 Kgs | F53: 5 | G53: 1250 | H53: =Table1[[#This Row],[Qty Sold]]*Table1[[#This Row],[Rate]] -> 6250 | I53: Deduction from Milk Payment | L53: =TEXT(A53,"mmm-yy") -> Mar-26 | M53: Farmer | N53: 13 Mar - 19 Mar | O53: 46100 | P53: 6250 | Q53: =H53-P53 -> 0 | S53: =IF(Q53<=0,0,(TODAY()-A53)) -> 0
A54: 46107 | B54: Ormanjhi | C54: Kukui | D54: 20060017 | E54: Gomukh Gold 50 Kgs | F54: 5 | G54: 1250 | H54: =Table1[[#This Row],[Qty Sold]]*Table1[[#This Row],[Rate]] -> 6250 | I54: Deduction from Milk Payment | L54: =TEXT(A54,"mmm-yy") -> Mar-26 | M54: Farmer | N54: 24 Apr - 30 Apr/ 01-07 May | O54: 46142 | P54: =3173+3077 -> 6250 | Q54: =H54-P54 -> 0 | S54: =IF(Q54<=0,0,(TODAY()-A54)) -> 0
A55: 46107 | B55: Ormanjhi | C55: Kuchu | D55: 20060009 | E55: Gomukh Gold 50 Kgs | F55: 5 | G55: 1250 | H55: =Table1[[#This Row],[Qty Sold]]*Table1[[#This Row],[Rate]] -> 6250 | I55: Deduction from Milk Payment | L55: =TEXT(A55,"mmm-yy") -> Mar-26 | M55: Farmer | N55: 03 Apr - 09 Apr & 17-23 Apr 24-30 Apr | O55: 46121 | P55: =3465+445+2340 -> 6250 | Q55: =H55-P55 -> 0 | S55: =IF(Q55<=0,0,(TODAY()-A55)) -> 0
A56: 46098 | B56: Bero | C56: Bero | D56: 20010003 | E56: Gomukh Gold 50 Kgs | F56: 6 | G56: 1250 | H56: =Table1[[#This Row],[Qty Sold]]*Table1[[#This Row],[Rate]] -> 7500 | I56: Deduction from Milk Payment | L56: =TEXT(A56,"mmm-yy") -> Mar-26 | M56: Farmer | N56: 13 Mar - 19 Mar | O56: 46100 | P56: 7500 | Q56: =H56-P56 -> 0 | S56: =IF(Q56<=0,0,(TODAY()-A56)) -> 0
A57: 46101 | B57: Bero | C57: Bero | D57: 20010003 | E57: Gomukh Gold 50 Kgs | F57: 6 | G57: 1250 | H57: =Table1[[#This Row],[Qty Sold]]*Table1[[#This Row],[Rate]] -> 7500 | I57: Deduction from Milk Payment | L57: =TEXT(A57,"mmm-yy") -> Mar-26 | M57: Farmer | N57: 06 Mar - 12 Mar & 20-26 Mar/03-09 Apr | O57: 46093 | P57: =637+5000+1863 -> 7500 | Q57: =H57-P57 -> 0 | S57: =IF(Q57<=0,0,(TODAY()-A57)) -> 0
A58: 46107 | B58: Bero | C58: Etachildri | D58: 20010016 | E58: Gomukh Gold 50 Kgs | F58: 2 | G58: 1250 | H58: =Table1[[#This Row],[Qty Sold]]*Table1[[#This Row],[Rate]] -> 2500 | I58: Deduction from Milk Payment | L58: =TEXT(A58,"mmm-yy") -> Mar-26 | M58: Farmer | N58: 06 Mar - 12 Mar & 20-26 Mar 10-16 Apr & 01-07 May 2026 | O58: 46093 | P58: =15+665+985+835 -> 2500 | Q58: =H58-P58 -> 0 | S58: =IF(Q58<=0,0,(TODAY()-A58)) -> 0
A59: 46107 | B59: Bero | C59: Bero | D59: 20010003 | E59: Gomukh Gold 50 Kgs | F59: 12 | G59: 1250 | H59: =Table1[[#This Row],[Qty Sold]]*Table1[[#This Row],[Rate]] -> 15000 | I59: Deduction from Milk Payment | L59: =TEXT(A59,"mmm-yy") -> Mar-26 | M59: Farmer | N59: 03 Apr - 09 Apr & 10-16 Apr | O59: 46121 | P59: =8137+6863 -> 15000 | Q59: =H59-P59 -> 0 | S59: =IF(Q59<=0,0,(TODAY()-A59)) -> 0
A60: 46107 | B60: ITKI | C60: Itki | D60: 20010001 | E60: Gomukh Gold 50 Kgs | F60: 150 | G60: 1200 | H60: =Table1[[#This Row],[Qty Sold]]*Table1[[#This Row],[Rate]] -> 180000 | I60: Deduction from Milk Payment | L60: =TEXT(A60,"mmm-yy") -> Mar-26 | M60: Farmer | N60: 20 Mar - 26 Mar/01-07 May | O60: 46107 | P60: =96000+84000 -> 180000 | Q60: =H60-P60 -> 0 | S60: =IF(Q60<=0,0,(TODAY()-A60)) -> 0
A61: 46107 | B61: Chanho | C61: Narkopi | D61: 20010054 | E61: Gomukh Gold 50 Kgs | F61: 3 | G61: 1250 | H61: =Table1[[#This Row],[Qty Sold]]*Table1[[#This Row],[Rate]] -> 3750 | I61: Deduction from Milk Payment | L61: =TEXT(A61,"mmm-yy") -> Mar-26 | M61: Farmer | N61: 20 Mar - 26 Mar | O61: 46107 | P61: 3750 | Q61: =H61-P61 -> 0 | S61: =IF(Q61<=0,0,(TODAY()-A61)) -> 0
A62: 46107 | B62: Chanho | C62: Kullu | D62: 20090025 | E62: Gomukh Gold 50 Kgs | F62: 2 | G62: 1250 | H62: =Table1[[#This Row],[Qty Sold]]*Table1[[#This Row],[Rate]] -> 2500 | I62: Deduction from Milk Payment | L62: =TEXT(A62,"mmm-yy") -> Mar-26 | M62: Farmer | N62: 27-31 Mar | P62: 2500 | Q62: =H62-P62 -> 0 | S62: =IF(Q62<=0,0,(TODAY()-A62)) -> 0
A63: 46107 | B63: Chanho | C63: Tutlo | D63: 20010053 | E63: Gomukh Gold 50 Kgs | F63: 1 | G63: 1250 | H63: =Table1[[#This Row],[Qty Sold]]*Table1[[#This Row],[Rate]] -> 1250 | I63: Deduction from Milk Payment | L63: =TEXT(A63,"mmm-yy") -> Mar-26 | M63: Farmer | N63: 20 Mar - 26 Mar/27-31 Mar | O63: 46107 | P63: =1235+15 -> 1250 | Q63: =H63-P63 -> 0 | S63: =IF(Q63<=0,0,(TODAY()-A63)) -> 0
A64: 46107 | B64: Chanho | C64: Chanho | D64: 20090001 | E64: Gomukh Gold 50 Kgs | F64: 1 | G64: 1250 | H64: =Table1[[#This Row],[Qty Sold]]*Table1[[#This Row],[Rate]] -> 1250 | I64: Deduction from Milk Payment | L64: =TEXT(A64,"mmm-yy") -> Mar-26 | M64: Farmer | N64: 20 Mar - 26 Mar | O64: 46107 | P64: 1250 | Q64: =H64-P64 -> 0 | S64: =IF(Q64<=0,0,(TODAY()-A64)) -> 0
A65: 46107 | B65: Chanho | C65: Pakariyo | D65: 20090015 | E65: Gomukh Gold 50 Kgs | F65: 3 | G65: 1250 | H65: =Table1[[#This Row],[Qty Sold]]*Table1[[#This Row],[Rate]] -> 3750 | I65: Deduction from Milk Payment | L65: =TEXT(A65,"mmm-yy") -> Mar-26 | M65: Farmer | N65: 20 Mar - 26 Mar | O65: 46107 | P65: =3159 -> 3159 | Q65: =H65-P65 -> 591 | S65: =IF(Q65<=0,0,(TODAY()-A65)) -> 54
A66: 46107 | B66: Chanho | C66: Pakariyo2 | D66: 20090020 | E66: Gomukh Gold 50 Kgs | F66: 3 | G66: 1250 | H66: =Table1[[#This Row],[Qty Sold]]*Table1[[#This Row],[Rate]] -> 3750 | I66: Deduction from Milk Payment | L66: =TEXT(A66,"mmm-yy") -> Mar-26 | M66: Farmer | N66: 20 Mar - 26 Mar | O66: 46107 | P66: 3750 | Q66: =H66-P66 -> 0 | S66: =IF(Q66<=0,0,(TODAY()-A66)) -> 0
A67: 46107 | B67: Chanho | C67: Pakariyo2 | D67: 20090020 | E67: Gomukh Gold 50 Kgs | F67: 3 | G67: 1250 | H67: =Table1[[#This Row],[Qty Sold]]*Table1[[#This Row],[Rate]] -> 3750 | I67: Deduction from Milk Payment | L67: =TEXT(A67,"mmm-yy") -> Mar-26 | Q67: =H67-P67 -> 3750 | S67: =IF(Q67<=0,0,(TODAY()-A67)) -> 54
A68: 46107 | B68: Chanho | C68: Pakariyo2 | D68: 20090020 | E68: Gomukh Gold 50 Kgs | F68: 4 | G68: 1250 | H68: =Table1[[#This Row],[Qty Sold]]*Table1[[#This Row],[Rate]] -> 5000 | I68: Deduction from Milk Payment | L68: =TEXT(A68,"mmm-yy") -> Mar-26 | M68: Farmer | N68: 10 Apr - 16 Apr & 17-23 Apr | O68: 46128 | P68: =3750+1250 -> 5000 | Q68: =H68-P68 -> 0 | S68: =IF(Q68<=0,0,(TODAY()-A68)) -> 0
A69: 46107 | B69: Chanho | C69: Barhe | D69: 20090011 | E69: Gomukh Gold 50 Kgs | F69: 3 | G69: 1250 | H69: =Table1[[#This Row],[Qty Sold]]*Table1[[#This Row],[Rate]] -> 3750 | I69: Deduction from Milk Payment | L69: =TEXT(A69,"mmm-yy") -> Mar-26 | Q69: =H69-P69 -> 3750 | S69: =IF(Q69<=0,0,(TODAY()-A69)) -> 54
A70: 46110 | B70: Bero | C70: Bero | D70: 20010003 | E70: Gomukh Gold 50 Kgs | F70: 4 | G70: 1250 | H70: =Table1[[#This Row],[Qty Sold]]*Table1[[#This Row],[Rate]] -> 5000 | I70: Deduction from Milk Payment | L70: =TEXT(A70,"mmm-yy") -> Mar-26 | M70: Farmer | N70: 10 Apr - 16 Apr | O70: 46128 | P70: 5000 | Q70: =H70-P70 -> 0 | S70: =IF(Q70<=0,0,(TODAY()-A70)) -> 0
A71: 46110 | B71: Ormanjhi | C71: Ormanjhi | D71: 20060001 | E71: Gomukh Gold 50 Kgs | F71: 1 | G71: 1250 | H71: =Table1[[#This Row],[Qty Sold]]*Table1[[#This Row],[Rate]] -> 1250 | I71: Deduction from Milk Payment | L71: =TEXT(A71,"mmm-yy") -> Mar-26 | M71: Farmer | N71: 06 Feb - 12 Feb & 20-26 Mar | O71: 46065 | P71: =1172+78 -> 1250 | Q71: =H71-P71 -> 0 | S71: =IF(Q71<=0,0,(TODAY()-A71)) -> 0
A72: 46113 | B72: ITKI | C72: Itki | D72: 20010001 | E72: Gomukh Gold 50 Kgs | F72: 200 | G72: 1200 | H72: =Table1[[#This Row],[Qty Sold]]*Table1[[#This Row],[Rate]] -> 240000 | I72: Deduction from Milk Payment | L72: =TEXT(A72,"mmm-yy") -> Apr-26 | M72: Farmer | N72: 03-09 Apr 17-23 Apr & 01-07 May | O72: 46121 | P72: =102000+126000+12000 -> 240000 | Q72: =H72-P72 -> 0 | S72: =IF(Q72<=0,0,(TODAY()-A72)) -> 0
A73: 46113 | B73: Dumardagga | C73: Dumardagga | D73: 20060003 | E73: Gomukh Gold 50 Kgs | F73: 20 | G73: 1250 | H73: =Table1[[#This Row],[Qty Sold]]*Table1[[#This Row],[Rate]] -> 25000 | I73: Deduction from Milk Payment | L73: =TEXT(A73,"mmm-yy") -> Apr-26 | M73: Farmer | N73: 03 Apr - 09 Apr & 10-16 Apr | O73: 46121 | P73: =12500+12500 -> 25000 | Q73: =H73-P73 -> 0 | S73: =IF(Q73<=0,0,(TODAY()-A73)) -> 0
A74: 46114 | B74: Pali | C74: Tikotoli | D74: 20020020 | E74: Gomukh Gold 50 Kgs | F74: 5 | G74: 1250 | H74: =Table1[[#This Row],[Qty Sold]]*Table1[[#This Row],[Rate]] -> 6250 | I74: Deduction from Milk Payment | L74: =TEXT(A74,"mmm-yy") -> Apr-26 | Q74: =H74-P74 -> 6250 | S74: =IF(Q74<=0,0,(TODAY()-A74)) -> 47
A75: 46114 | B75: Pali | C75: Tikotoli | D75: 20020020 | E75: Gomukh Gold 50 Kgs | F75: 3 | G75: 1250 | H75: =Table1[[#This Row],[Qty Sold]]*Table1[[#This Row],[Rate]] -> 3750 | I75: Deduction from Milk Payment | L75: =TEXT(A75,"mmm-yy") -> Apr-26 | M75: Farmer | N75: 03 Apr - 09 Apr/01-07 May | O75: 46121 | P75: =1985+1765 -> 3750 | Q75: =H75-P75 -> 0 | S75: =IF(Q75<=0,0,(TODAY()-A75)) -> 0
A76: 46114 | B76: Pali | C76: Bijuliya | D76: 20020003 | E76: Gomukh Gold 50 Kgs | F76: 10 | G76: 1250 | H76: =Table1[[#This Row],[Qty Sold]]*Table1[[#This Row],[Rate]] -> 12500 | I76: Deduction from Milk Payment | L76: =TEXT(A76,"mmm-yy") -> Apr-26 | M76: Farmer | N76: 01-07 May | O76: 46149 | P76: 6250 | Q76: =H76-P76 -> 6250 | S76: =IF(Q76<=0,0,(TODAY()-A76)) -> 47
A77: 46114 | B77: Pali | C77: Ranikhatanga | D77: 20020006 | E77: Gomukh Gold 50 Kgs | F77: 5 | G77: 1250 | H77: =Table1[[#This Row],[Qty Sold]]*Table1[[#This Row],[Rate]] -> 6250 | I77: Deduction from Milk Payment | L77: =TEXT(A77,"mmm-yy") -> Apr-26 | M77: Farmer | N77: 03 Apr - 09 Apr | O77: 46121 | P77: 6250 | Q77: =H77-P77 -> 0 | S77: =IF(Q77<=0,0,(TODAY()-A77)) -> 0
A78: 46114 | B78: Piragutu | C78: Murpa | D78: 20070024 | E78: Gomukh Gold 50 Kgs | F78: 10 | G78: 1250 | H78: =Table1[[#This Row],[Qty Sold]]*Table1[[#This Row],[Rate]] -> 12500 | I78: Deduction from Milk Payment | L78: =TEXT(A78,"mmm-yy") -> Apr-26 | M78: Farmer | N78: 10 Apr - 16 Apr/27-31 Mar | O78: 46128 | P78: =8844+3656 -> 12500 | Q78: =H78-P78 -> 0 | S78: =IF(Q78<=0,0,(TODAY()-A78)) -> 0
A79: 46114 | B79: Piragutu | C79: Saram | D79: 20070002 | E79: Gomukh Gold 50 Kgs | F79: 3 | G79: 1250 | H79: =Table1[[#This Row],[Qty Sold]]*Table1[[#This Row],[Rate]] -> 3750 | I79: Deduction from Milk Payment | L79: =TEXT(A79,"mmm-yy") -> Apr-26 | M79: Farmer | N79: 03 Apr - 09 Apr/01-07 May | O79: 46121 | P79: =162+3588 -> 3750 | Q79: =H79-P79 -> 0 | S79: =IF(Q79<=0,0,(TODAY()-A79)) -> 0
A80: 46118 | B80: Chanho | C80: Tutlo | D80: 20010053 | E80: Gomukh Gold 50 Kgs | F80: 1 | G80: 1250 | H80: =Table1[[#This Row],[Qty Sold]]*Table1[[#This Row],[Rate]] -> 1250 | I80: Deduction from Milk Payment | L80: =TEXT(A80,"mmm-yy") -> Apr-26 | M80: Farmer | N80: 10 Apr - 16 Apr | O80: 46128 | P80: 1250 | Q80: =H80-P80 -> 0 | S80: =IF(Q80<=0,0,(TODAY()-A80)) -> 0
A81: 46118 | B81: Chanho | C81: Pakariyo | D81: 20090015 | E81: Gomukh Gold 50 Kgs | F81: 2 | G81: 1250 | H81: =Table1[[#This Row],[Qty Sold]]*Table1[[#This Row],[Rate]] -> 2500 | I81: Deduction from Milk Payment | L81: =TEXT(A81,"mmm-yy") -> Apr-26 | M81: Farmer | N81: 10 Apr - 16 Apr & 17-23 Apr | O81: 46128 | P81: =1737+763 -> 2500 | Q81: =H81-P81 -> 0 | S81: =IF(Q81<=0,0,(TODAY()-A81)) -> 0
A82: 46118 | B82: Chanho | C82: Chanho | D82: 20090001 | E82: Gomukh Gold 50 Kgs | F82: 2 | G82: 1250 | H82: =Table1[[#This Row],[Qty Sold]]*Table1[[#This Row],[Rate]] -> 2500 | I82: Deduction from Milk Payment | L82: =TEXT(A82,"mmm-yy") -> Apr-26 | M82: Bank | O82: 46119 | P82: 2500 | Q82: =H82-P82 -> 0 | S82: =IF(Q82<=0,0,(TODAY()-A82)) -> 0
A83: 46118 | B83: Chanho | C83: Nawatand | D83: 20090017 | E83: Gomukh Gold 50 Kgs | F83: 3 | G83: 1250 | H83: =Table1[[#This Row],[Qty Sold]]*Table1[[#This Row],[Rate]] -> 3750 | I83: Deduction from Milk Payment | L83: =TEXT(A83,"mmm-yy") -> Apr-26 | M83: Farmer | N83: 10 Apr - 16 Apr | O83: 46128 | P83: =2500+1250 -> 3750 | Q83: =H83-P83 -> 0 | S83: =IF(Q83<=0,0,(TODAY()-A83)) -> 0
A84: 46118 | B84: Chanho | C84: Barhe | D84: 20090011 | E84: Gomukh Gold 50 Kgs | F84: 5 | G84: 1250 | H84: =Table1[[#This Row],[Qty Sold]]*Table1[[#This Row],[Rate]] -> 6250 | I84: Deduction from Milk Payment | L84: =TEXT(A84,"mmm-yy") -> Apr-26 | M84: Farmer | N84: 10 Apr - 16 Apr & 17-23 Apr 24-30 Apr | O84: 46128 | P84: =3750+1250+1250 -> 6250 | Q84: =H84-P84 -> 0 | S84: =IF(Q84<=0,0,(TODAY()-A84)) -> 0
A85: 46118 | B85: Chanho | C85: Kokar | D85: 20090023 | E85: Gomukh Gold 50 Kgs | F85: 5 | G85: 1250 | H85: =Table1[[#This Row],[Qty Sold]]*Table1[[#This Row],[Rate]] -> 6250 | I85: Deduction from Milk Payment | L85: =TEXT(A85,"mmm-yy") -> Apr-26 | M85: Farmer | N85: 10 Apr - 16 Apr & 17-23 Apr | O85: 46128 | P85: =35+6215 -> 6250 | Q85: =H85-P85 -> 0 | S85: =IF(Q85<=0,0,(TODAY()-A85)) -> 0
A86: 46121 | B86: Pali | C86: Agru | D86: 20020025 | E86: Gomukh Gold 50 Kgs | F86: 11 | G86: 1250 | H86: =Table1[[#This Row],[Qty Sold]]*Table1[[#This Row],[Rate]] -> 13750 | I86: Deduction from Milk Payment | L86: =TEXT(A86,"mmm-yy") -> Apr-26 | M86: Farmer | N86: 03 Apr - 09 Apr & 10-16 Apr 17-23 Apr | O86: 46121 | P86: =6250+5782+1718 -> 13750 | Q86: =H86-P86 -> 0 | S86: =IF(Q86<=0,0,(TODAY()-A86)) -> 0
A87: 46121 | B87: Pali | C87: Tikotoli | D87: 20020020 | E87: Gomukh Gold 50 Kgs | F87: 5 | G87: 1250 | H87: =Table1[[#This Row],[Qty Sold]]*Table1[[#This Row],[Rate]] -> 6250 | I87: Deduction from Milk Payment | L87: =TEXT(A87,"mmm-yy") -> Apr-26 | M87: Farmer | N87: 03 Apr - 09 Apr & 10-16 Apr | O87: 46121 | P87: =5000+1250 -> 6250 | Q87: =H87-P87 -> 0 | S87: =IF(Q87<=0,0,(TODAY()-A87)) -> 0
A88: 46121 | B88: Pali | C88: Bijuliya | D88: 20020003 | E88: Gomukh Gold 50 Kgs | F88: 10 | G88: 1250 | H88: =Table1[[#This Row],[Qty Sold]]*Table1[[#This Row],[Rate]] -> 12500 | I88: Deduction from Milk Payment | L88: =TEXT(A88,"mmm-yy") -> Apr-26 | M88: Farmer | N88: 03 Apr - 09 Apr | O88: 46121 | P88: 12500 | Q88: =H88-P88 -> 0 | S88: =IF(Q88<=0,0,(TODAY()-A88)) -> 0
A89: 46121 | B89: Pali | C89: Pali | D89: 20020001 | E89: Gomukh Gold 50 Kgs | F89: 8 | G89: 1250 | H89: =Table1[[#This Row],[Qty Sold]]*Table1[[#This Row],[Rate]] -> 10000 | I89: Deduction from Milk Payment | L89: =TEXT(A89,"mmm-yy") -> Apr-26 | M89: Farmer | N89: 03 Apr - 09 Apr & 10-16 Apr | O89: 46121 | P89: =9343+657 -> 10000 | Q89: =H89-P89 -> 0 | S89: =IF(Q89<=0,0,(TODAY()-A89)) -> 0
A90: 46107 | B90: Chuttu | C90: Chuttu | D90: 20060004 | E90: Gomukh Gold 50 Kgs | F90: 18 | G90: 1250 | H90: =Table1[[#This Row],[Qty Sold]]*Table1[[#This Row],[Rate]]+166 -> 22666 | I90: Deduction from Milk Payment | L90: =TEXT(A90,"mmm-yy") -> Mar-26 | M90: Bank | O90: 46122 | P90: 22666 | Q90: =H90-P90 -> 0 | S90: =IF(Q90<=0,0,(TODAY()-A90)) -> 0
A91: 46130 | B91: Chuttu | C91: Chuttu | D91: 20060004 | E91: Gomukh Gold 50 Kgs | F91: 10 | G91: 1250 | H91: =Table1[[#This Row],[Qty Sold]]*Table1[[#This Row],[Rate]] -> 12500 | I91: Deduction from Milk Payment | L91: =TEXT(A91,"mmm-yy") -> Apr-26 | M91: Farmer | N91: 24 Apr - 30 Apr | O91: 46142 | P91: 12500 | Q91: =H91-P91 -> 0 | S91: =IF(Q91<=0,0,(TODAY()-A91)) -> 0
A92: 46123 | B92: Dumardagga | C92: Dumardagga | D92: 20060003 | E92: Gomukh Gold 50 Kgs | F92: 20 | G92: 1250 | H92: =Table1[[#This Row],[Qty Sold]]*Table1[[#This Row],[Rate]] -> 25000 | I92: Deduction from Milk Payment | L92: =TEXT(A92,"mmm-yy") -> Apr-26 | M92: Farmer | N92: 10 Apr - 16 Apr & 17-23 Apr | O92: 46128 | P92: =12500+12500 -> 25000 | Q92: =H92-P92 -> 0 | S92: =IF(Q92<=0,0,(TODAY()-A92)) -> 0
A93: 46130 | B93: Dumardagga | C93: Dumardagga | D93: 20060003 | E93: Gomukh Gold 50 Kgs | F93: 20 | G93: 1250 | H93: =Table1[[#This Row],[Qty Sold]]*Table1[[#This Row],[Rate]] -> 25000 | I93: Deduction from Milk Payment | L93: =TEXT(A93,"mmm-yy") -> Apr-26 | M93: Farmer | N93: 17 Apr - 23 Apr & 24-30 Apr | O93: 46135 | P93: =12500+12500 -> 25000 | Q93: =H93-P93 -> 0 | S93: =IF(Q93<=0,0,(TODAY()-A93)) -> 0
A94: 46130 | B94: Ormanjhi | C94: Jirabar | D94: 20060005 | E94: Gomukh Gold 50 Kgs | F94: 2 | G94: 1250 | H94: =Table1[[#This Row],[Qty Sold]]*Table1[[#This Row],[Rate]] -> 2500 | I94: Deduction from Milk Payment | L94: =TEXT(A94,"mmm-yy") -> Apr-26 | M94: Farmer | N94: 01-07 May | O94: 46149 | P94: 2500 | Q94: =H94-P94 -> 0 | S94: =IF(Q94<=0,0,(TODAY()-A94)) -> 0
A95: 46130 | B95: Ormanjhi | C95: Ormanjhi | D95: 20060001 | E95: Gomukh Gold 50 Kgs | F95: 7 | G95: 1250 | H95: =Table1[[#This Row],[Qty Sold]]*Table1[[#This Row],[Rate]] -> 8750 | I95: Deduction from Milk Payment | L95: =TEXT(A95,"mmm-yy") -> Apr-26 | M95: Farmer | N95: 10 Apr - 16 Apr & 24-30 Apr | O95: 46128 | P95: =7955+795 -> 8750 | Q95: =H95-P95 -> 0 | S95: =IF(Q95<=0,0,(TODAY()-A95)) -> 0
A96: 46115 | B96: Bero | C96: Etachildri | D96: 20010016 | E96: Gomukh Gold 50 Kgs | F96: 2 | G96: 1250 | H96: =Table1[[#This Row],[Qty Sold]]*Table1[[#This Row],[Rate]] -> 2500 | I96: Deduction from Milk Payment | L96: =TEXT(A96,"mmm-yy") -> Apr-26 | M96: Farmer | N96: 10 Apr - 16 Apr/01-07 May/27-31 Mar | O96: 46128 | P96: =490+1108+835 -> 2433 | Q96: =H96-P96 -> 67 | S96: =IF(Q96<=0,0,(TODAY()-A96)) -> 46
A97: 46123 | B97: Bero | C97: Bero | D97: 20010003 | E97: Gomukh Gold 50 Kgs | F97: 8 | G97: 1250 | H97: =Table1[[#This Row],[Qty Sold]]*Table1[[#This Row],[Rate]] -> 10000 | I97: Deduction from Milk Payment | L97: =TEXT(A97,"mmm-yy") -> Apr-26 | M97: Farmer | N97: 17 Apr - 23 Apr | O97: 46135 | P97: 10000 | Q97: =H97-P97 -> 0 | S97: =IF(Q97<=0,0,(TODAY()-A97)) -> 0
A98: 46130 | B98: Bero | C98: Erchoro | D98: 20010008 | E98: Gomukh Gold 50 Kgs | F98: 20 | G98: 1250 | H98: =Table1[[#This Row],[Qty Sold]]*Table1[[#This Row],[Rate]] -> 25000 | I98: Deduction from Milk Payment | L98: =TEXT(A98,"mmm-yy") -> Apr-26 | M98: Farmer | N98: 10 Apr - 16 Apr & 17-23 Apr | O98: 46128 | P98: =12500+12500 -> 25000 | Q98: =H98-P98 -> 0 | S98: =IF(Q98<=0,0,(TODAY()-A98)) -> 0
A99: 46130 | B99: Bero | C99: Bero | D99: 20010003 | E99: Gomukh Gold 50 Kgs | F99: 2 | G99: 1250 | H99: =Table1[[#This Row],[Qty Sold]]*Table1[[#This Row],[Rate]] -> 2500 | I99: Deduction from Milk Payment | L99: =TEXT(A99,"mmm-yy") -> Apr-26 | M99: Farmer | N99: 17 Apr - 23 Apr | O99: 46135 | P99: 2500 | Q99: =H99-P99 -> 0 | S99: =IF(Q99<=0,0,(TODAY()-A99)) -> 0
A100: 46130 | B100: Bero | C100: Bero | D100: 20010003 | E100: Gomukh Gold 50 Kgs | F100: 8 | G100: 1250 | H100: =Table1[[#This Row],[Qty Sold]]*Table1[[#This Row],[Rate]] -> 10000 | I100: Deduction from Milk Payment | L100: =TEXT(A100,"mmm-yy") -> Apr-26 | M100: Farmer | N100: 24 Apr - 30 Apr | O100: 46142 | P100: 10000 | Q100: =H100-P100 -> 0 | S100: =IF(Q100<=0,0,(TODAY()-A100)) -> 0
...

Sheet OS 08-14
A1: Date | B1: Godown | C1: MPG Name | D1: New Code | E1: Name of Product | F1: Qty Sold | G1: Rate | H1: Sales Amount | I1: Dues | J1: Remarks | K1: Ageing
A2: 46087 | B2: Chanho | C2: Naudi | D2: 20090003 | E2: Gomukh Gold 50 Kgs | F2: 10 | G2: 1250 | H2: 12500 | I2: 2544 | K2: 74
A3: 46098 | B3: Pali | C3: Ranikhatanga | D3: 20020006 | E3: Gomukh Gold 50 Kgs | F3: 10 | G3: 1250 | H3: 12500 | I3: 8823 | K3: 63
A4: 46107 | B4: Dumardagga | C4: Dumardagga | D4: 20060003 | E4: Gomukh Gold 50 Kgs | F4: 20 | G4: 1250 | H4: 25000 | I4: 12500 | K4: 54
A5: 46107 | B5: Chanho | C5: Pakariyo | D5: 20090015 | E5: Gomukh Gold 50 Kgs | F5: 3 | G5: 1250 | H5: 3750 | I5: 591 | K5: 54
A6: 46107 | B6: Chanho | C6: Pakariyo2 | D6: 20090020 | E6: Gomukh Gold 50 Kgs | F6: 3 | G6: 1250 | H6: 3750 | I6: 3750 | K6: 54
A7: 46107 | B7: Chanho | C7: Barhe | D7: 20090011 | E7: Gomukh Gold 50 Kgs | F7: 3 | G7: 1250 | H7: 3750 | I7: 3750 | K7: 54
A8: 46114 | B8: Pali | C8: Tikotoli | D8: 20020020 | E8: Gomukh Gold 50 Kgs | F8: 5 | G8: 1250 | H8: 6250 | I8: 6250 | K8: 47
A9: 46114 | B9: Pali | C9: Bijuliya | D9: 20020003 | E9: Gomukh Gold 50 Kgs | F9: 10 | G9: 1250 | H9: 12500 | I9: 6250 | K9: 47
A10: 46115 | B10: Bero | C10: Etachildri | D10: 20010016 | E10: Gomukh Gold 50 Kgs | F10: 2 | G10: 1250 | H10: 2500 | I10: 67 | K10: 46
A11: 46137 | B11: Pali | C11: Bijuliya | D11: 20020003 | E11: Gomukh Gold 50 Kgs | F11: 10 | G11: 1250 | H11: 12500 | I11: 6250 | K11: 24
A12: 46142 | B12: Pali | C12: Bijuliya | D12: 20020003 | E12: Gomukh Gold 50 Kgs | F12: 5 | G12: 1250 | H12: 6250 | I12: 6250 | K12: 19
A13: 46142 | B13: Pali | C13: Agru | D13: 20020025 | E13: Gomukh Gold 50 Kgs | F13: 13 | G13: 1250 | H13: 16250 | I13: 11877 | K13: 19
... A20: 46139 | B20: Bero | C20: Bero | D20: 20010003 | E20: Gomukh Gold 50 Kgs | F20: 10 | G20: 1250 | H20: 12500 | I20: 2500 | K20: 22

Sheet Check
B1: Done
A2: MB | B2: =SUMIF('Farmer Deduction'!O:O,Check!B1,Table3[[#All],[Deliver Value]]) -> 1263362
A3: Farmer | B3: =SUMIF(Table1[[#All],[Mode]],Check!A3,Table1[[#All],[Payment Amt]]) -> 1263362
A4: Old | B4: =SUMIF(Table1[[#All],[Cycle]],Check!A4,Table1[[#All],[Payment Amt]]) -> 0
A5: Net | B5: =+B3-B4 -> 1263362
B6: =+B2-B5 -> 0

Sheet Bank Deposit
A1: Date of Deposit | B1: Deposited Amt | C1: Area | D1: UTR No | E1: MPG Code | F1: Payee Name | G1: Remarks | H1: Sales Mapping | I1: Payment Confirmation | J1: Column1
A2: 46080 | B2: 1250 | C2: Chanho | D2: 605820300186 | E2: 20010053 | F2: Tutlo | H2: Y
A3: 46095 | B3: 1250 | C3: Bero | D3: 793594484107 | E3: 20010055 | F3: Masu | H3: Y
A4: 46099 | B4: 6250 | C4: Hisri | D4: 881916690092 | E4: 20030001 | F4: Hisri | H4: Y
A5: 46100 | B5: 5000 | C5: Chanho | D5: 607823344943 | E5: 20090001 | F5: Chanho | H5: Y
A6: 46101 | B6: 1250 | C6: Chanho | D6: 644582859973 | E6: 20090001 | F6: Chanho | H6: Y
A7: 46119 | B7: 2500 | C7: Chanho | D7: 121244713613 | E7: 20090001 | F7: Chanho | H7: Y
A8: 46122 | B8: 22666 | C8: Chuttu | D8: 332944129905 | E8: 20060004 | F8: Chuttu | H8: Y
A9: 46139 | B9: 11000 | D9: 722267955317 | E9: 20010015 | F9: Boreya | H9: Y
A10: 46134 | B10: 2500 | C10: Hisri | F10: Umedanda | H10: Y
A11: 46146 | B11: 10000 | C11: Pali | D11: 159525964797 | E11: 20020025 | F11: Agru | H11: Y

Sheet Special Rate
A1: BMC Name | B1: MPG Code | C1: MPG Name | D1: Item Name | E1: Rate/Bag
A2: Palma | B2: 20010001 | C2: Itki | D2: Gomukh Gold 50 Kgs | E2: 1200

Sheet Month wise Report
A1: SUM of Delivered Qty | B1: Month | Q1: SUM of Qty Sold | R1: Month
A2: Delivered at | B2: 46054 | C2: 46082 | D2: 46113 | E2: (blank) | F2: Grand Total | Q2: Godown | R2: Apr-26 | S2: Feb-26 | T2: Mar-26 | U2: May-26 | V2: Grand Total
A3: Bero | B3: 200 | C3: -50 | D3: 38 | F3: 188 | Q3: Bero | R3: 50 | S3: 49 | T3: 45 | V3: 144
A4: Chanho | B4: 100 | D4: 20 | F4: 120 | Q4: Chanho | R4: 24 | S4: 11 | T4: 65 | U4: 15 | V4: 115
A5: Chuttu | B5: 96 | F5: 96 | Q5: Chuttu | R5: 10 | T5: 30 | V5: 40
A6: Dumardagga | B6: 250 | F6: 250 | Q6: Dumardagga | R6: 80 | S6: 20 | T6: 80 | V6: 180
A7: Hisri | B7: 25 | F7: 25 | Q7: Hisri | R7: 6 | T7: 5 | V7: 11
A8: Itki | C8: 350 | F8: 350 | Q8: ITKI | R8: 200 | T8: 150 | V8: 350
A9: Ormanjhi | B9: 150 | D9: -38 | F9: 112 | Q9: Ormanjhi | R9: 14 | S9: 20 | T9: 17 | V9: 51
A10: Pali | B10: 125 | C10: 200 | D10: -20 | F10: 305 | Q10: Pali | R10: 143 | S10: 25 | T10: 43 | U10: 18 | V10: 229
A11: Piragutu | B11: 50 | F11: 50 | Q11: Piragutu | R11: 29 | T11: 11 | V11: 40
A12: (blank) | Q12: Grand Total | R12: 556 | S12: 125 | T12: 446 | U12: 33 | V12: 1160
A13: Grand Total | B13: 996 | C13: 500 | D13: 0 | F13: 1496

Sheet Farmer Deduction
A1: Month | B1: Date | C1: Cycle | D1: Product | E1: MPG Code | F1: MPG Name | G1: Farmer code | H1: Farmer Name | I1: BMC Name | J1: CSP | K1: Deliver Qty | L1: Rate | M1: Deliver Value | N1: Challen No | O1: Remark | P1: Column1 | Q1: Column2
A2: Feb | B2: 46072 | C2: 13-02-2026- 19-02-2026 | D2: Gomukh Gold 50KG | E2: 20020020 | F2: Tikotoli | G2: 0030 | I2: Pali | J2: Daya Society | K2: 1 | L2: 1250 | M2: 1194 | O2: Done
A3: Feb | B3: 46072 | C3: 13-02-2026- 19-02-2026 | D3: Gomukh Gold 50KG | E3: 20020020 | F3: Tikotoli | G3: 0033 | I3: Pali | J3: Daya Society | K3: 1 | L3: 1250 | M3: 682 | O3: Done
A4: Feb | B4: 46072 | C4: 13-02-2026- 19-02-2026 | D4: Gomukh Gold 50KG | E4: 20020020 | F4: Tikotoli | G4: 0023 | I4: Pali | J4: Daya Society | K4: 1 | L4: 1250 | M4: 1250 | O4: Done
A5: Feb | B5: 46072 | C5: 13-02-2026- 19-02-2026 | D5: Gomukh Gold 50KG | E5: 20020020 | F5: Tikotoli | G5: 0038 | I5: Pali | J5: Daya Society | K5: 1 | L5: 1250 | M5: 709 | O5: Done
A6: Feb | B6: 46072 | C6: 13-02-2026- 19-02-2026 | D6: Gomukh Gold 50KG | E6: 20020020 | F6: Tikotoli | G6: 0039 | I6: Pali | J6: Daya Society | K6: 1 | L6: 1250 | M6: 659 | O6: Done
A7: Dec | B7: 45995 | C7: 28-11-2025- 04-12-2025 | D7: Gomukh Gold 50KG | E7: 20010016 | F7: Etachildri | G7: 0002 | I7: Bero | J7: Daya Society | K7: 1 | L7: 1250 | M7: 1250 | O7: Done
A8: Feb | B8: 46065 | C8: 06-02-2026- 12-02-2026 | D8: Gomukh Gold 50KG | E8: 20060001 | F8: Ormanjhi | G8: 0024 | I8: Ormanjhi | J8: Daya Society | K8: 1 | L8: 1250 | M8: 1250 | O8: Done
A9: Feb | B9: 46079 | C9: 20-02-2026- 26-02-2026 | D9: Gomukh Gold 50KG | E9: 20090017 | F9: Nawatand | G9: 0003 | I9: Chanho | J9: Daya Society | K9: 2 | L9: 1250 | M9: 2500 | O9: Done
A10: Feb | B10: 46079 | C10: 20-02-2026- 26-02-2026 | D10: Gomukh Gold 50KG | E10: 20090011 | F10: Barhe | G10: 0003 | I10: Chanho | J10: Daya Society | K10: 2 | L10: 1250 | M10: 2500 | O10: Done
A11: Feb | B11: 46079 | C11: 20-02-2026- 26-02-2026 | D11: Gomukh Gold 50KG | E11: 20090001 | F11: Chanho | G11: 0002 | I11: Chanho | J11: Daya Society | K11: 1 | L11: 1250 | M11: 1250 | O11: Done
A12: Feb | B12: 46079 | C12: 20-02-2026- 26-02-2026 | D12: Gomukh Gold 50KG | E12: 20010053 | F12: Tutlo | G12: 0004 | I12: Chanho | J12: Daya Society | K12: 1 | L12: 1250 | M12: 825 | O12: Done
A13: Feb | B13: 46079 | C13: 20-02-2026- 26-02-2026 | D13: Gomukh Gold 50KG | E13: 20010053 | F13: Tutlo | G13: 0058 | I13: Chanho | J13: Daya Society | K13: 1 | L13: 1250 | M13: 766 | O13: Done
... A22: Feb | B22: 46079 | C22: 20-02-2026- 26-02-2026 | D22: Gomukh Gold 50KG | E22: 20010003 | F22: Bero | G22: 0003 | I22: Bero | J22: Daya Society | K22: 4 | L22: 1250 | M22: 4418 | O22: Done
A23: Feb | B23: 46079 | C23: 20-02-2026- 26-02-2026 | D23: Gomukh Gold 50KG | E23: 20010034 | F23: Gargaon | G23: 0002 | I23: Gargaon | J23: Daya Society | K23: 25 | L23: 1250 | M23: 5522 | P23: Shifted from old sheet
A24: Feb | B24: 46079 | C24: 20-02-2026- 26-02-2026 | D24: Gomukh Gold 50KG | E24: 20010034 | F24: Gargaon | G24: 0024 | I24: Gargaon | J24: Daya Society | K24: 10 | L24: 1250 | M24: 877 | P24: Shifted from old sheet
A25: Feb | B25: 46065 | C25: 06-02-2026- 12-02-2026 | D25: Gomukh Gold 50KG | E25: 20060001 | F25: Ormanjhi | G25: 0024 | I25: Ormanjhi | J25: Daya Society | K25: 1 | L25: 1250 | M25: 1172 | O25: Done
A26: Feb | B26: 46079 | C26: 20-02-2026- 26-02-2026 | D26: Gomukh Gold 50KG | E26: 20060001 | F26: Ormanjhi | G26: 0024 | I26: Ormanjhi | J26: Daya Society | K26: 2 | L26: 1250 | M26: 2500 | P26: Shifted from old sheet
A27: Feb | B27: 46079 | C27: 20-02-2026- 26-02-2026 | D27: Gomukh Gold 50KG | E27: 20060001 | F27: Ormanjhi | G27: 0023 | I27: Ormanjhi | J27: Daya Society | K27: 1 | L27: 1250 | M27: 1250 | P27: Shifted from old sheet
A28: Feb | B28: 46079 | C28: 20-02-2026- 26-02-2026 | D28: Gomukh Gold 50KG | E28: 20010008 | F28: Erchoro | G28: 0014 | I28: Gargaon | J28: Daya Society | K28: 1 | L28: 1250 | M28: 1250 | P28: Shifted from old sheet
A29: Feb | B29: 46079 | C29: 20-02-2026- 26-02-2026 | D29: Gomukh Gold 50KG | E29: 20010008 | F29: Erchoro | G29: 0038 | I29: Gargaon | J29: Daya Society | K29: 1 | L29: 1250 | M29: 1250 | P29: Shifted from old sheet
A30: Feb | B30: 46079 | C30: 20-02-2026- 26-02-2026 | D30: Gomukh Gold 50KG | E30: 20010008 | F30: Erchoro | G30: 0035 | I30: Gargaon | J30: Daya Society | K30: 3 | L30: 1250 | M30: 3750 | P30: Shifted from old sheet
A31: Feb | B31: 46079 | C31: 20-02-2026- 26-02-2026 | D31: Gomukh Gold 50KG | E31: 20070009 | F31: Karmba | G31: 0002 | I31: Piragutu | J31: Daya Society | K31: 3 | L31: 1250 | M31: 3750 | P31: Shifted from old sheet
A32: Feb | B32: 46079 | C32: 20-02-2026- 26-02-2026 | D32: Gomukh Gold 50KG | E32: 20070001 | F32: Piragutu | G32: 0020 | I32: Piragutu | J32: Daya Society | K32: 1 | L32: 1250 | M32: 1250 | P32: Shifted from old sheet
A33: Mar | B33: 46086 | C33: 27-02-2026- 05-03-2026 | D33: Gomukh Gold 50KG | E33: 20090015 | F33: Pakariyo | G33: 0031 | I33: Chanho | J33: Daya Society | K33: 1 | L33: 1250 | M33: 300 | O33: Done
A34: Mar | B34: 46086 | C34: 27-02-2026- 05-03-2026 | D34: Gomukh Gold 50KG | E34: 20090020 | F34: Pakariyo2 | G34: 0002 | I34: Chanho | J34: Daya Society | K34: 2 | L34: 1250 | M34: 2500 | O34: Done
A35: Mar | B35: 46086 | C35: 27-02-2026- 05-03-2026 | D35: Gomukh Gold 50KG | E35: 20090003 | F35: Naudi | G35: 0002 | I35: Chanho | J35: Daya Society | K35: 5 | L35: 1250 | M35: 4798 | O35: Done
A36: Mar | B36: 46086 | C36: 27-02-2026- 05-03-2026 | D36: Gomukh Gold 50KG | E36: 20090017 | F36: Nawatand | G36: 0003 | I36: Chanho | J36: Daya Society | K36: 3 | L36: 1250 | M36: 3750 | O36: Done
A37: Mar | B37: 46086 | C37: 27-02-2026- 05-03-2026 | D37: Gomukh Gold 50KG | E37: 20010053 | F37: Tutlo | G37: 0004 | I37: Chanho | J37: Daya Society | K37: 0 | L37: 1250 | M37: 425 | O37: Done
A38: Mar | B38: 46086 | C38: 27-02-2026- 05-03-2026 | D38: Gomukh Gold 50KG | E38: 20010053 | F38: Tutlo | G38: 0058 | I38: Chanho | J38: Daya Society | K38: 0 | L38: 1250 | M38: 484 | O38: Done
A39: Mar | B39: 46086 | C39: 27-02-2026- 05-03-2026 | D39: Gomukh Gold 50KG | E39: 20090015 | F39: Pakariyo | G39: 0014 | I39: Chanho | J39: Daya Society | K39: 0 | L39: 1250 | M39: 204 | O39: Done
A40: Mar | B40: 46086 | C40: 27-02-2026- 05-03-2026 | D40: Gomukh Gold 50KG | E40: 20090015 | F40: Pakariyo | G40: 0022 | I40: Chanho | J40: Daya Society | K40: 0 | L40: 1250 | M40: 1788 | O40: Done
A41: Mar | B41: 46086 | C41: 27-02-2026- 05-03-2026 | D41: Gomukh Gold 50KG | E41: 20090015 | F41: Pakariyo | G41: 0036 | I41: Chanho | J41: Daya Society | K41: 0 | L41: 1250 | M41: 208 | O41: Done
A42: Mar | B42: 46086 | C42: 27-02-2026- 05-03-2026 | D42: Gomukh Gold 50KG | E42: 20070002 | F42: Saram | G42: 0002 | I42: Pali | J42: Daya Society | K42: 4 | L42: 1250 | M42: 5000 | O42: Done
A43: Mar | B43: 46086 | C43: 27-02-2026- 05-03-2026 | D43: Gomukh Gold 50KG | E43: 20020003 | F43: Bijuliya | G43: 0002 | I43: Pali | J43: Daya Society | K43: 5 | L43: 1250 | M43: 6250 | O43: Done
A44: Mar | B44: 46086 | C44: 27-02-2026- 05-03-2026 | D44: Gomukh Gold 50KG | E44: 20020011 | F44: Dhantatoli | G44: 0024 | I44: Pali | J44: Daya Society | K44: 1 | L44: 1250 | M44: 1250 | O44: Done
... A63: Mar | B63: 46086 | C63: 27-02-2026- 05-03-2026 | D63: Gomukh Gold 50KG | E63: 20010008 | F63: Erchoro | G63: 0038 | I63: Gargaon | J63: Daya Society | K63: 1 | L63: 1250 | M63: 1250 | O63: Done
A64: Mar | B64: 46086 | C64: 27-02-2026- 05-03-2026 | D64: Gomukh Gold 50KG | E64: 20010034 | F64: Gargaon | G64: 0002 | I64: Gargaon | J64: Daya Society | K64: 0 | L64: 1250 | M64: 14749 | P64: Shifted from old sheet
A65: Mar | B65: 46086 | C65: 27-02-2026- 05-03-2026 | D65: Gomukh Gold 50KG | E65: 20010034 | F65: Gargaon | G65: 0024 | I65: Gargaon | J65: Daya Society | K65: 10 | L65: 1250 | M65: 936 | P65: Shifted from old sheet
A66: Mar | B66: 46086 | C66: 27-02-2026- 05-03-2026 | D66: Gomukh Gold 50KG | E66: 20090015 | F66: Pakariyo | G66: 0031 | I66: Chanho | J66: Daya Society | K66: 1 | L66: 1250 | M66: 1150 | P66: Shifted from old sheet
A67: Mar | B67: 46093 | C67: 06-03-2026- 12-03-2026 | D67: Gomukh Gold 50KG | E67: 20090003 | F67: Naudi | G67: 0002 | I67: Chanho | J67: Daya Society | K67: 0 | L67: 1250 | M67: 1557 | O67: Done
A68: Mar | B68: 46093 | C68: 06-03-2026- 12-03-2026 | D68: Gomukh Gold 50KG | E68: 20090003 | F68: Naudi | G68: 0005 | I68: Chanho | J68: Daya Society | K68: 0 | L68: 1250 | M68: 1041 | O68: Done
A69: Mar | B69: 46093 | C69: 06-03-2026- 12-03-2026 | D69: Gomukh Gold 50KG | E69: 20090015 | F69: Pakariyo | G69: 0013 | I69: Chanho | J69: Daya Society | K69: 0 | L69: 1250 | M69: 830 | O69: Done
A70: Mar | B70: 46093 | C70: 06-03-2026- 12-03-2026 | D70: Gomukh Gold 50KG | E70: 20090015 | F70: Pakariyo | G70: 0012 | I70: Chanho | J70: Daya Society | K70: 0 | L70: 1250 | M70: 120 | O70: Done
A71: Mar | B71: 46093 | C71: 06-03-2026- 12-03-2026 | D71: Gomukh Gold 50KG | E71: 20090015 | F71: Pakariyo | G71: 0014 | I71: Chanho | J71: Daya Society | K71: 0 | L71: 1250 | M71: 100 | O71: Done
A72: Mar | B72: 46093 | C72: 06-03-2026- 12-03-2026 | D72: Gomukh Gold 50KG | E72: 20090015 | F72: Pakariyo | G72: 0022 | I72: Chanho | J72: Daya Society | K72: 0 | L72: 1250 | M72: 100 | O72: Done
A73: Mar | B73: 46093 | C73: 06-03-2026- 12-03-2026 | D73: Gomukh Gold 50KG | E73: 20090015 | F73: Pakariyo | G73: 0036 | I73: Chanho | J73: Daya Society | K73: 0 | L73: 1250 | M73: 100 | O73: Done
A74: Mar | B74: 46093 | C74: 06-03-2026- 12-03-2026 | D74: Gomukh Gold 50KG | E74: 20090017 | F74: Nawatand | G74: 0003 | I74: Chanho | J74: Daya Society | K74: 2 | L74: 1250 | M74: 2500 | O74: Done
A75: Mar | B75: 46093 | C75: 06-03-2026- 12-03-2026 | D75: Gomukh Gold 50KG | E75: 20010053 | F75: Tutlo | G75: 0020 | I75: Chanho | J75: Daya Society | K75: 1 | L75: 1250 | M75: 1206 | O75: Done
A76: Mar | B76: 46093 | C76: 06-03-2026- 12-03-2026 | D76: Gomukh Gold 50KG | E76: 20010053 | F76: Tutlo | G76: 0004 | I76: Chanho | J76: Daya Society | K76: 1 | L76: 1250 | M76: 1003 | O76: Done
A77: Mar | B77: 46093 | C77: 06-03-2026- 12-03-2026 | D77: Gomukh Gold 50KG | E77: 20060003 | F77: Dumardagga | G77: 0002 | I77: Dumardagga | J77: Daya Society | K77: 20 | L77: 1250 | M77: 25000 | O77: Done
A78: Mar | B78: 46093 | C78: 06-03-2026- 12-03-2026 | D78: Gomukh Gold 50KG | E78: 20010003 | F78: Bero | G78: 0003 | I78: Bero | J78: Daya Society | K78: 0 | M78: 6832 | O78: Done
A79: Mar | B79: 46093 | C79: 06-03-2026- 12-03-2026 | D79: Gomukh Gold 50KG | E79: 20010003 | F79: Bero | G79: 0003 | I79: Bero | J79: Daya Society | K79: 6 | L79: 1250 | M79: 637 | O79: Done
A80: Mar | B80: 46093 | C80: 06-03-2026- 12-03-2026 | D80: Gomukh Gold 50KG | E80: 20010034 | F80: Gargaon | G80: 0002 | I80: Gargaon | J80: Daya Society | K80: 0 | L80: 1250 | M80: 8577 | P80: Shifted from old sheet
A81: Mar | B81: 46093 | C81: 06-03-2026- 12-03-2026 | D81: Gomukh Gold 50KG | E81: 20010034 | F81: Gargaon | G81: 0024 | I81: Gargaon | J81: Daya Society | K81: 10 | L81: 1250 | M81: 1015 | P81: Shifted from old sheet
A82: Mar | B82: 46093 | C82: 06-03-2026- 12-03-2026 | D82: Gomukh Gold 50KG | E82: 20010008 | F82: Erchoro | G82: 0035 | I82: Bero | J82: Daya Society | K82: 4 | L82: 1250 | M82: 5000 | O82: Done
A83: Mar | B83: 46093 | C83: 06-03-2026- 12-03-2026 | D83: Gomukh Gold 50KG | E83: 20010008 | F83: Erchoro | G83: 0037 | I83: Bero | J83: Daya Society | K83: 1 | L83: 1250 | M83: 1250 | O83: Done
A84: Mar | B84: 46093 | C84: 06-03-2026- 12-03-2026 | D84: Gomukh Gold 50KG | E84: 20060001 | F84: Ormanjhi | G84: 0023 | I84: Ormanjhi | J84: Daya Society | K84: 1 | L84: 1250 | M84: 1250 | O84: Done
A85: Mar | B85: 46093 | C85: 06-03-2026- 12-03-2026 | D85: Gomukh Gold 50KG | E85: 20060008 | F85: Adelhootu | G85: 0002 | I85: Ormanjhi | J85: Daya Society | K85: 10 | L85: 1250 | M85: 12500 | O85: Done
A86: Mar | B86: 46093 | C86: 06-03-2026- 12-03-2026 | D86: Gomukh Gold 50KG | E86: 20010016 | F86: Etachildri | G86: 0002 | I86: Bero | J86: Daya Society | K86: 1 | L86: 1250 | M86: 15 | O86: Done
A87: Mar | B87: 46093 | C87: 06-03-2026- 12-03-2026 | D87: Gomukh Gold 50KG | E87: 20060001 | F87: Ormanjhi | G87: 0024 | I87: Ormanjhi | J87: Daya Society | K87: 1 | L87: 1250 | M87: 1250 | O87: Done
A88: Mar | B88: 46093 | C88: 06-03-2026- 12-03-2026 | D88: Gomukh Gold 50KG | E88: 20020001 | F88: Pali | G88: OS | I88: Pali | J88: Daya Society | K88: 0 | L88: 1250 | M88: 32 | O88: Done
A89: Mar | B89: 46093 | C89: 06-03-2026- 12-03-2026 | D89: Gomukh Gold 50KG | E89: 20070009 | F89: Karmba | G89: OS | I89: Piragutu | J89: Daya Society | K89: 3 | L89: 1250 | M89: 3750 | P89: Shifted from old sheet
A90: Mar | B90: 46100 | C90: 13-03-2026- 19-03-2026 | D90: Gomukh Gold 50KG | E90: 20020020 | F90: Tikotoli | G90: 0030 | I90: Pali | J90: Daya Society | K90: 0 | L90: 1250 | M90: 56 | O90: Done
A91: Mar | B91: 46100 | C91: 13-03-2026- 19-03-2026 | D91: Gomukh Gold 50KG | E91: 20020020 | F91: Tikotoli | G91: 0033 | I91: Pali | J91: Daya Society | K91: 0 | L91: 1250 | M91: 568 | O91: Done
A92: Mar | B92: 46100 | C92: 13-03-2026- 19-03-2026 | D92: Gomukh Gold 50KG | E92: 20020020 | F92: Tikotoli | G92: 0038 | I92: Pali | J92: Daya Society | K92: 0 | L92: 1250 | M92: 865 | O92: Done
A93: Mar | B93: 46100 | C93: 13-03-2026- 19-03-2026 | D93: Gomukh Gold 50KG | E93: 20020020 | F93: Tikotoli | G93: 0039 | I93: Pali | J93: Daya Society | K93: 0 | L93: 1250 | M93: 591 | O93: Done
A94: Mar | B94: 46100 | C94: 13-03-2026- 19-03-2026 | D94: Gomukh Gold 50KG | E94: 20020003 | F94: Bijuliya | G94: 0002 | I94: Pali | J94: Daya Society | K94: 10 | L94: 1250 | M94: 12500 | O94: Done
A95: Mar | B95: 46100 | C95: 13-03-2026- 19-03-2026 | D95: Gomukh Gold 50KG | E95: 20020020 | F95: Tikotoli | G95: 0008 | I95: Pali | J95: Daya Society | K95: 1 | L95: 1250 | M95: 1250 | O95: Done
A96: Mar | B96: 46100 | C96: 13-03-2026- 19-03-2026 | D96: Gomukh Gold 50KG | E96: 20020020 | F96: Tikotoli | G96: 0023 | I96: Pali | J96: Daya Society | K96: 2 | L96: 1250 | M96: 2500 | O96: Done
A97: Mar | B97: 46100 | C97: 13-03-2026- 19-03-2026 | D97: Gomukh Gold 50KG | E97: 20020020 | F97: Tikotoli | G97: 0022 | I97: Pali | J97: Daya Society | K97: 1 | L97: 1250 | M97: 1250 | O97: Done
A98: Mar | B98: 46100 | C98: 13-03-2026- 19-03-2026 | D98: Gomukh Gold 50KG | E98: 20020006 | F98: Ranikhatanga | G98: 0002 | I98: Pali | J98: Daya Society | K98: 5 | L98: 1250 | M98: 3677 | O98: Done
A99: Mar | B99: 46100 | C99: 13-03-2026- 19-03-2026 | D99: Gomukh Gold 50KG | E99: 20020011 | F99: Dhantatoli | G99: 0047 | I99: Pali | J99: Daya Society | K99: 1 | L99: 1250 | M99: 1250 | O99: Done
A100: Mar | B100: 46100 | C100: 13-03-2026- 19-03-2026 | D100: Gomukh Gold 50KG | E100: 20070001 | F100: Piragutu | G100: 0002 | I100: Piragutu | J100: Daya Society | K100: 3 | L100: 1250 | M100: 3750 | O100: Done
A101: Mar | B101: 46100 | C101: 13-03-2026- 19-03-2026 | D101: Gomukh Gold 50KG | E101: 20070002 | F101: Saram | G101: 0002 | I101: Piragutu | J101: Daya Society | K101: 2 | L101: 1250 | M101: 2500 | O101: Done
... A169: Mar | B169: 46112 | C169: 27-03-2026- 31-03-2026 | D169: Gomukh Gold 50KG | E169: 20010016 | F169: Etachildri | G169: 0005 | I169: Bero | J169: Daya Society | K169: 1 | L169: 1250 | M169: 445 | O169: Done
A170: Mar | B170: 46112 | C170: 27-03-2026- 31-03-2026 | D170: Gomukh Gold 50KG | E170: 20010001 | F170: ITKI | G170: 0002 | I170: ITKI | J170: Daya Society | K170: 80 | L170: 1250 | M170: 96000 | P170: As per discussed by rahul sir No deduction reason technical error
A171: Mar | B171: 46112 | C171: 27-03-2026- 31-03-2026 | D171: Gomukh Gold 50KG | E171: 20060003 | F171: Dumardagga | G171: 0002 | I171: Dumardagga | J171: Daya Society | K171: 30 | L171: 1250 | M171: 37500 | P171: As per discussed by rahul sir No deduction reason technical error
A172: Mar | B172: 46112 | C172: 27-03-2026- 31-03-2026 | D172: Gomukh Gold 50KG | E172: 20020006 | F172: Ranikhatanga | G172: 0007 | I172: Pali | J172: Daya Society | K172: 0 | L172: 1250 | M172: 8823 | P172: As per discussed by rahul sir No deduction reason technical error
A173: Mar | B173: 46112 | C173: 27-03-2026- 31-03-2026 | D173: Gomukh Gold 50KG | E173: 20020003 | F173: Bijuliya | G173: 0002 | I173: Pali | J173: Daya Society | K173: 10 | L173: 1250 | M173: 12500 | P173: As per discussed by rahul sir No deduction reason technical error
A174: Mar | B174: 46112 | C174: 27-03-2026- 31-03-2026 | D174: Gomukh Gold 50KG | E174: 20020020 | F174: Tikotoli | G174: 0033 | I174: Pali | J174: Daya Society | K174: 1 | L174: 1250 | M174: 562 | O174: Done
A175: Mar | B175: 46112 | C175: 27-03-2026- 31-03-2026 | D175: Gomukh Gold 50KG | E175: 20020020 | F175: Tikotoli | G175: 0042 | I175: Pali | J175: Daya Society | K175: 1 | L175: 1250 | M175: 585 | O175: Done
A176: Mar | B176: 46112 | C176: 27-03-2026- 31-03-2026 | D176: Gomukh Gold 50KG | E176: 20020020 | F176: Tikotoli | G176: 0039 | I176: Pali | J176: Daya Society | K176: 1 | L176: 1250 | M176: 1250 | P176: As per discussed by rahul sir No deduction reason technical error
A177: Mar | B177: 46112 | C177: 27-03-2026- 31-03-2026 | D177: Gomukh Gold 50KG | E177: 20020020 | F177: Tikotoli | G177: 0030 | I177: Pali | J177: Daya Society | K177: 1 | L177: 1250 | M177: 1250 | P177: As per discussed by rahul sir No deduction reason technical error
A178: Mar | B178: 46112 | C178: 27-03-2026- 31-03-2026 | D178: Gomukh Gold 50KG | E178: 20020020 | F178: Tikotoli | G178: 0023 | I178: Pali | J178: Daya Society | K178: 1 | L178: 1250 | M178: 1250 | P178: As per discussed by rahul sir No deduction reason technical error
A179: Mar | B179: 46112 | C179: 27-03-2026- 31-03-2026 | D179: Gomukh Gold 50KG | E179: 20020020 | F179: Tikotoli | G179: 0038 | I179: Pali | J179: Daya Society | K179: 1 | L179: 1250 | M179: 640 | O179: Done
A180: Mar | B180: 46112 | C180: 27-03-2026- 31-03-2026 | D180: Gomukh Gold 50KG | E180: 20020020 | F180: Tikotoli | G180: 0008 | I180: Pali | J180: Daya Society | K180: 1 | L180: 1250 | M180: 1250 | P180: As per discussed by rahul sir No deduction reason technical error
A181: Mar | B181: 46112 | C181: 27-03-2026- 31-03-2026 | D181: Gomukh Gold 50KG | E181: 20020020 | F181: Tikotoli | G181: 0041 | I181: Pali | J181: Daya Society | K181: 1 | L181: 1250 | M181: 1250 | P181: As per discussed by rahul sir No deduction reason technical error
A182: Mar | B182: 46112 | C182: 27-03-2026- 31-03-2026 | D182: Gomukh Gold 50KG | E182: 20070002 | F182: Saram | G182: 0002 | I182: Piragutu | J182: Daya Society | K182: 3 | L182: 1250 | M182: 3588 | O182: Done
A183: Mar | B183: 46112 | C183: 27-03-2026- 31-03-2026 | D183: Gomukh Gold 50KG | E183: 20070024 | F183: Marpa | G183: 0002 | I183: Piragutu | J183: Daya Society | K183: 5 | L183: 1250 | M183: 3656 | O183: Done
A184: Mar | B184: 46112 | C184: 27-03-2026- 31-03-2026 | D184: Gomukh Gold 50KG | E184: 20090003 | F184: Naudi | G184: 0002 | I184: Chanho | J184: Daya Society | K184: 0 | L184: 1250 | M184: 259 | O184: Done
A185: Mar | B185: 46112 | C185: 27-03-2026- 31-03-2026 | D185: Gomukh Gold 50KG | E185: 20090025 | F185: Kullu | G185: 0002 | I185: Chanho | J185: Daya Society | K185: 2 | L185: 1250 | M185: 2500 | O185: Done
A186: Mar | B186: 46112 | C186: 27-03-2026- 31-03-2026 | D186: Gomukh Gold 50KG | E186: 20010053 | F186: Tutlo | G186: 0003 | I186: Chanho | J186: Daya Society | K186: 0 | L186: 1250 | M186: 15 | O186: Done
A187: Mar | B187: 46112 | C187: 27-03-2026- 31-03-2026 | D187: Gomukh Gold 50KG | E187: 20010053 | F187: Tutlo | G187: 0003 | I187: Chanho | J187: Daya Society | K187: 15 | L187: 1250 | M187: 2057 | O187: Done
A188: Mar | B188: 46112 | C188: 27-03-2026- 31-03-2026 | D188: Gomukh Gold 50KG | E188: 20090015 | F188: Pakariyo | G188: 0026 | I188: Chanho | J188: Daya Society | K188: 0 | L188: 1250 | M188: 425 | P188: As per discussed by rahul sir No deduction reason technical error
A189: Mar | B189: 46112 | C189: 27-03-2026- 31-03-2026 | D189: Gomukh Gold 50KG | E189: 20090015 | F189: Pakariyo | G189: 0031 | I189: Chanho | J189: Daya Society | K189: 0 | L189: 1250 | M189: 70 | P189: As per discussed by rahul sir No deduction reason technical error
A190: Mar | B190: 46112 | C190: 27-03-2026- 31-03-2026 | D190: Gomukh Gold 50KG | E190: 20090015 | F190: Pakariyo | G190: 0002 | I190: Chanho | J190: Daya Society | K190: 0 | L190: 1250 | M190: 96 | P190: As per discussed by rahul sir No deduction reason technical error
A191: Mar | B191: 46112 | C191: 27-03-2026- 31-03-2026 | D191: Gomukh Gold 50KG | E191: 20090020 | F191: Pakariyo2 | G191: 0002 | I191: Chanho | J191: Daya Society | K191: 2 | L191: 1250 | M191: 2500 | P191: As per discussed by rahul sir No deduction reason technical error
A192: Mar | B192: 46112 | C192: 27-03-2026- 31-03-2026 | D192: Gomukh Gold 50KG | E192: 20090020 | F192: Pakariyo2 | G192: 0005 | I192: Chanho | J192: Daya Society | K192: 1 | L192: 1250 | M192: 1250 | P192: As per discussed by rahul sir No deduction reason technical error
A193: Mar | B193: 46112 | C193: 27-03-2026- 31-03-2026 | D193: Gomukh Gold 50KG | E193: 20090011 | F193: Barhe | G193: 0003 | I193: Chanho | J193: Daya Society | K193: 3 | L193: 1250 | M193: 3750 | P193: As per discussed by rahul sir No deduction reason technical error
...
