Workbook

Sheet AMCU Details
K1: =SUBTOTAL(9,K3:K1197) -> 31721992 | L1: =SUBTOTAL(9,L3:L1197) -> 9535101.1 | M1: =SUBTOTAL(9,M3:M1197) -> 30000 | P1: =SUBTOTAL(9,P3:P1197) -> 22216891 | Q1: =SUBTOTAL(9,Q3:Q1197) -> 7284344.1 | R1: =SUBTOTAL(9,R3:R1197) -> 1985000 | U1: =SUBTOTAL(9,U3:U1197) -> 190328 | V1: =SUBTOTAL(9,V3:V1197) -> 75429 | W1: =SUBTOTAL(9,W3:W1197) -> 7897.0656 | X1: =SUBTOTAL(9,X3:X1197) -> 11825.474 | Y1: =SUBTOTAL(9,Y3:Y1197) -> 19528.991 | Z1: =SUBTOTAL(9,Z3:Z1197) -> 19478.036 | AA1: =SUBTOTAL(9,AA3:AA1197) -> 26919.933 | AB1: =SUBTOTAL(9,AB3:AB1197) -> 19517.205 | ... DK1: =SUBTOTAL(9,DK3:DK1197) -> 651011.69
A2: Owner | B2: MPG Code | C2: MPG Code New | D2: MPG Name | E2: BMC | F2: Date of Purchase | G2: Issue Date | H2: AMCU No | I2: SD Payment Status | J2: Centre Status | K2: Assets Value | L2: Total Deduction | M2: Amount Returned | N2: Returned Date | O2: Benificery Name | P2: Recoverable Value | Q2: EMI | R2: SD | S2: UTR/UPI | T2: Down Payment Date | U2: Old Deposit | V2: Farmer Payment | W2: Apr-22 | X2: May-22 | Y2: Jun-22 | Z2: Jul-22 | AA2: Aug-22 | AB2: SEp-22 | AC2: Oct-22 | AD2: Nov-22 | AE2: Dec-22 | AF2: Jan-23 | AG2: Feb-23 | AH2: Mar-23 | AI2: FY 22-23 | AJ2: Apr-23 | AK2: May-23 | AL2: Jun-23 | AM2: Jul-23 | AN2: Aug-23 | AO2: SEp-23 | AP2: Oct-23 | AQ2: Nov-23 | AR2: Dec-23 | AS2: Jan-24 | AT2: Feb-24 | AU2: Mar-24 | AV2: FY 23-24 | AW2: Apr-24 | AX2: May-24 | AY2: Jun-24 | AZ2: Jul-24 | BA2: Aug-24 | BB2: 20-26 Sep | BC2: SEp-24 | BD2: 27-03 Oct | BE2: 05-11 Oct | BF2: 11-17 Oct | BG2: 18-24 | BH2: 25-31 | BI2: Oct-24 | BJ2: 01-07 Nov | BK2: 08-14 Nov | BL2: 15-21 Nov | BM2: 22-28 Nov | BN2: Nov-24 | BO2: 29-05 Dec | BP2: 06-12 Dec | BQ2: 13-19 Dec | BR2: 20-26 Dec | BS2: Dec-24 | BT2: 27 Dec -02 Jan | BU2: 03-09 Jan | BV2: 10-16 Jan | BW2: 17-23 Jan | BX2: 24-30 Jan | BY2: Jan-25 | BZ2: 0-06 Feb | CA2: 07-13 Feb | CB2: 14-20 Feb | CC2: 21-27 Feb | CD2: Feb-25 | CE2: 28-06 Mar | CF2: 07-13 Mar | CG2: 14-20 Mar | CH2: 21-27 Mar | CI2: 28-31 Mar | CJ2: Mar-25 | CK2: FY 24-25 | CL2: 01-03 Apr | CM2: 4-10 Apr | CN2: 11-17 Apr | CO2: 18-24 Apr | CP2: Apr-25 | CQ2: 25-01 May | CR2: 02-08 May | CS2: 09-15 May | CT2: 16-22 May | CU2: 23-29 May | CV2: May-25 | CW2: 30-05 Jun | CX2: 06-12 Jun | CY2: 13-18 Jun | CZ2: 19-26 Jun | DA2: Jun-25 | DB2: Jul-25 | DC2: Aug-25 | DD2: Sep-25 | DE2: Oct-25 | DF2: Nov-25 | DG2: Dec-25 | DH2: Jan-26 | DI2: Feb-26 | DJ2: Mar-26 | DK2: FY 25-26
A3: PRAVAH/ITC | B3: 01170 | C3: 00000000 | D3: #N/A | E3: Halsi | G3: 44595 | I3: =IF(Table1[[#This Row],[Centre Status]]="Returned","NA",IF(Table1[[#This Row],[SD]]>19000,"Full Payment",IF(Table1[[#This Row],[SD]]<1,"No Payment","Partial Payment"))) -> No Payment | J3: Active | K3: 64000 | L3: =Q3+R3+U3+Table1[[#This Row],[Farmer Payment]] -> 1567 | P3: =K3-L3+M3 -> 62433 | Q3: =AI3+AV3+CK3+Table1[[#This Row],[FY 25-26]] -> 1567 | W3: 0 | X3: 0 | Y3: 783 | Z3: 784 | AA3: 0 | AB3: 0 | AC3: 0 | AD3: 0 | AE3: 0 | AF3: 0 | AG3: 0 | AH3: 0 | AI3: =SUM(W3:AH3) -> 1567 | AJ3: 0 | AK3: 0 | AL3: 0 | AM3: 0 | AN3: 0 | AO3: 0 | AP3: 0 | AQ3: 0 | AR3: 0 | AS3: 0 | AT3: 0 | AU3: 0 | AV3: =SUM(AJ3:AU3) -> 0 | AW3: 0 | AX3: 0 | AY3: 0 | AZ3: 0 | BA3: 0 | BB3: 0 | BC3: 0 | BD3: 0 | BE3: 0 | BF3: 0 | BG3: 0 | BH3: 0 | BI3: 0 | BJ3: 0 | BK3: 0 | BL3: 0 | BM3: 0 | BN3: 0 | BO3: 0 | BP3: 0 | BQ3: 0 | BR3: 0 | BS3: 0 | BT3: 0 | BU3: 0 | BV3: 0 | BW3: 0 | BX3: 0 | BY3: 0 | BZ3: 0 | CA3: 0 | CB3: 0 | CC3: 0 | CD3: 0 | CE3: 0 | CF3: 0 | CG3: 0 | CH3: 0 | CI3: 0 | CJ3: 0 | CK3: =SUM(AW3:CJ3) -> 0 | CM3: 0 | CN3: 0 | CO3: 0 | CP3: 0 | CQ3: 0 | CR3: 0 | CS3: 0 | CT3: 0 | CU3: 0 | CV3: 0 | CW3: 0 | CX3: 0 | CY3: 0 | CZ3: 0 | DK3: =SUM(Table1[[#This Row],[01-03 Apr]:[Mar-26]]) -> 0
A4: PRAVAH/ITC | B4: 01186 | C4: 00000000 | D4: #N/A | E4: Halsi | G4: 44595 | H4: 277356 | I4: =IF(Table1[[#This Row],[Centre Status]]="Returned","NA",IF(Table1[[#This Row],[SD]]>19000,"Full Payment",IF(Table1[[#This Row],[SD]]<1,"No Payment","Partial Payment"))) -> No Payment | J4: Active | K4: 64000 | L4: =Q4+R4+U4+Table1[[#This Row],[Farmer Payment]] -> 5896.4322 | P4: =K4-L4+M4 -> 58103.568 | Q4: =AI4+AV4+CK4+Table1[[#This Row],[FY 25-26]] -> 5896.4322 | W4: 0 | X4: 0 | Y4: 1861 | Z4: 1861 | AA4: 2174.4322 | AB4: 0 | AC4: 0 | AD4: 0 | AE4: 0 | AF4: 0 | AG4: 0 | AH4: 0 | AI4: =SUM(W4:AH4) -> 5896.4322 | AJ4: 0 | AK4: 0 | AL4: 0 | AM4: 0 | AN4: 0 | AO4: 0 | AP4: 0 | AQ4: 0 | AR4: 0 | AS4: 0 | AT4: 0 | AU4: 0 | AV4: =SUM(AJ4:AU4) -> 0 | AW4: 0 | AX4: 0 | AY4: 0 | AZ4: 0 | BA4: 0 | BB4: 0 | BC4: 0 | BD4: 0 | BE4: 0 | BF4: 0 | BG4: 0 | BH4: 0 | BI4: 0 | BJ4: 0 | BK4: 0 | BL4: 0 | BM4: 0 | BN4: 0 | BO4: 0 | BP4: 0 | BQ4: 0 | BR4: 0 | BS4: 0 | BT4: 0 | BU4: 0 | BV4: 0 | BW4: 0 | BX4: 0 | BY4: 0 | BZ4: 0 | CA4: 0 | CB4: 0 | CC4: 0 | CD4: 0 | CE4: 0 | CF4: 0 | CG4: 0 | CH4: 0 | CI4: 0 | CJ4: 0 | CK4: =SUM(AW4:CJ4) -> 0 | CM4: 0 | CN4: 0 | CO4: 0 | CP4: 0 | CQ4: 0 | CR4: 0 | CS4: 0 | CT4: 0 | CU4: 0 | CV4: 0 | CW4: 0 | CX4: 0 | CY4: 0 | CZ4: 0 | DK4: =SUM(Table1[[#This Row],[01-03 Apr]:[Mar-26]]) -> 0
A5: PRAVAH/ITC | B5: 1187 | C5: 10020017 | D5: Gomukh Ramchanderpur 2 | E5: Laldiyara | G5: 44565 | H5: 274122 | I5: =IF(Table1[[#This Row],[Centre Status]]="Returned","NA",IF(Table1[[#This Row],[SD]]>19000,"Full Payment",IF(Table1[[#This Row],[SD]]<1,"No Payment","Partial Payment"))) -> Full Payment | J5: Active | K5: 64000 | L5: =Q5+R5+U5+Table1[[#This Row],[Farmer Payment]] -> 64000 | P5: =K5-L5+M5 -> 0 | Q5: =AI5+AV5+CK5+Table1[[#This Row],[FY 25-26]] -> 44000 | R5: 20000 | S5: 208683739594 | T5: 44647 | W5: 3603.8126 | X5: 0 | Y5: 13546.712 | Z5: 10993.01 | AA5: 15399.013 | AB5: 457.4528 | AC5: 0 | AD5: 0 | AE5: 0 | AF5: 0 | AG5: 0 | AH5: 0 | AI5: =SUM(W5:AH5) -> 44000 | AJ5: 0 | AK5: 0 | AL5: 0 | AM5: 0 | AN5: 0 | AO5: 0 | AP5: 0 | AQ5: 0 | AR5: 0 | AS5: 0 | AT5: 0 | AU5: 0 | AV5: =SUM(AJ5:AU5) -> 0 | AW5: 0 | AX5: 0 | AY5: 0 | AZ5: 0 | BA5: 0 | BB5: 0 | BC5: 0 | BD5: 0 | BE5: 0 | BF5: 0 | BG5: 0 | BH5: 0 | BI5: 0 | BJ5: 0 | BK5: 0 | BL5: 0 | BM5: 0 | BN5: 0 | BO5: 0 | BP5: 0 | BQ5: 0 | BR5: 0 | BS5: 0 | BT5: 0 | BU5: 0 | BV5: 0 | BW5: 0 | BX5: 0 | BY5: 0 | BZ5: 0 | CA5: 0 | CB5: 0 | CC5: 0 | CD5: 0 | CE5: 0 | CF5: 0 | CG5: 0 | CH5: 0 | CI5: 0 | CJ5: 0 | CK5: =SUM(AW5:CJ5) -> 0 | CM5: 0 | CN5: 0 | CO5: 0 | CP5: 0 | CQ5: 0 | CR5: 0 | CS5: 0 | CT5: 0 | CU5: 0 | CV5: 0 | CW5: 0 | CX5: 0 | CY5: 0 | CZ5: 0 | DK5: =SUM(Table1[[#This Row],[01-03 Apr]:[Mar-26]]) -> 0
C6: 10010082 | D6: Gomukh Sharmatola Sahuri | E6: Manjhaul | G6: 45556 | H6: 381762 | I6: =IF(Table1[[#This Row],[Centre Status]]="Returned","NA",IF(Table1[[#This Row],[SD]]>19000,"Full Payment",IF(Table1[[#This Row],[SD]]<1,"No Payment","Partial Payment"))) -> Full Payment | J6: Active | K6: 110000 | L6: =Q6+R6+U6+Table1[[#This Row],[Farmer Payment]] -> 44235.135 | P6: =K6-L6+M6 -> 65764.865 | Q6: =AI6+AV6+CK6+Table1[[#This Row],[FY 25-26]] -> 24235.135 | R6: 20000 | S6: 426496921266 | T6: 45555 | AI6: =SUM(W6:AH6) -> 0 | AV6: =SUM(AJ6:AU6) -> 0 | BB6: 0 | BC6: 0 | BD6: 0 | BE6: 0 | BF6: 0 | BG6: 0 | BH6: 0 | BI6: 455 | BJ6: 0 | BK6: 0 | BL6: 500 | BM6: 500 | BN6: 861 | BO6: 0 | BP6: 0 | BQ6: 0 | BR6: 0 | BS6: 1733.671 | BT6: 500 | BU6: 500 | BV6: 0 | BW6: 0 | BX6: 0 | BY6: 2757.7018 | BZ6: 0 | CA6: 0 | CB6: 0 | CC6: 0 | CD6: 4465.5445 | CE6: 0 | CF6: 0 | CG6: 0 | CH6: 0 | CI6: 0 | CJ6: 5203.0765 | CK6: =SUM(AW6:CJ6) -> 17475.994 | CM6: 0 | CN6: 0 | CO6: 0 | CP6: 2767.9216 | CQ6: 0 | CR6: 0 | CS6: 0 | CT6: 0 | CU6: 0 | CV6: 3991.2198 | CW6: 0 | CX6: 0 | CY6: 0 | CZ6: 0 | DK6: =SUM(Table1[[#This Row],[01-03 Apr]:[Mar-26]]) -> 6759.1414
C7: 10140125 | D7: Gomukh Dullahpur Niyajipur | E7: Dumraon | G7: 45566 | H7: 399066 | I7: =IF(Table1[[#This Row],[Centre Status]]="Returned","NA",IF(Table1[[#This Row],[SD]]>19000,"Full Payment",IF(Table1[[#This Row],[SD]]<1,"No Payment","Partial Payment"))) -> NA | J7: Returned | K7: 110000 | L7: =Q7+R7+U7+Table1[[#This Row],[Farmer Payment]] -> 20000 | M7: =20000+20000 -> 40000 | N7: 45705 | O7: Rajesh kumar | P7: =K7-L7+M7 -> 130000 | Q7: =AI7+AV7+CK7+Table1[[#This Row],[FY 25-26]] -> 0 | R7: 20000 | S7: 427123622077 | T7: 45562 | AI7: =SUM(W7:AH7) -> 0 | AV7: =SUM(AJ7:AU7) -> 0 | BB7: 0 | BC7: 0 | BD7: 0 | BE7: 0 | BF7: 0 | BG7: 0 | BH7: 0 | BI7: 0 | BJ7: 0 | BK7: 0 | BL7: 0 | BM7: 0 | BN7: 0 | BO7: 0 | BP7: 0 | BQ7: 0 | BR7: 0 | BS7: 0 | BT7: 0 | BU7: 0 | BV7: 0 | BW7: 0 | BX7: 0 | BY7: 0 | BZ7: 0 | CA7: 0 | CB7: 0 | CC7: 0 | CD7: 0 | CE7: 0 | CF7: 0 | CG7: 0 | CH7: 0 | CI7: 0 | CJ7: 0 | CK7: =SUM(AW7:CJ7) -> 0 | CM7: 0 | CN7: 0 | CO7: 0 | CP7: 0 | CQ7: 0 | CR7: 0 | CS7: 0 | CT7: 0 | CU7: 0 | CV7: 0 | CW7: 0 | CX7: 0 | CY7: 0 | CZ7: 0 | DK7: =SUM(Table1[[#This Row],[01-03 Apr]:[Mar-26]]) -> 0
C8: 10530070 | D8: GOMUKH PARAN 2 | E8: Kalyanpur | G8: 45834 | I8: =IF(Table1[[#This Row],[Centre Status]]="Returned","NA",IF(Table1[[#This Row],[SD]]>19000,"Full Payment",IF(Table1[[#This Row],[SD]]<1,"No Payment","Partial Payment"))) -> No Payment | J8: Active | K8: 110000 | L8: =Q8+R8+U8+Table1[[#This Row],[Farmer Payment]] -> 0 | P8: =K8-L8+M8 -> 110000 | Q8: =AI8+AV8+CK8+Table1[[#This Row],[FY 25-26]] -> 0 | AI8: =SUM(W8:AH8) -> 0 | AV8: =SUM(AJ8:AU8) -> 0 | CK8: =SUM(AW8:CJ8) -> 0 | CW8: 0 | CX8: 0 | CY8: 0 | CZ8: 0 | DK8: =SUM(Table1[[#This Row],[01-03 Apr]:[Mar-26]]) -> 0
C9: 10530071 | D9: GOMUKH KHARAGPUR | E9: Kalyanpur | G9: 45834 | I9: =IF(Table1[[#This Row],[Centre Status]]="Returned","NA",IF(Table1[[#This Row],[SD]]>19000,"Full Payment",IF(Table1[[#This Row],[SD]]<1,"No Payment","Partial Payment"))) -> No Payment | J9: Active | K9: 110000 | L9: =Q9+R9+U9+Table1[[#This Row],[Farmer Payment]] -> 0 | P9: =K9-L9+M9 -> 110000 | Q9: =AI9+AV9+CK9+Table1[[#This Row],[FY 25-26]] -> 0 | AI9: =SUM(W9:AH9) -> 0 | AV9: =SUM(AJ9:AU9) -> 0 | CK9: =SUM(AW9:CJ9) -> 0 | CW9: 0 | CX9: 0 | CY9: 0 | CZ9: 0 | DK9: =SUM(Table1[[#This Row],[01-03 Apr]:[Mar-26]]) -> 0
C10: 10110158 | D10: GOMUKH CHOWKI 2 | E10: S kamal | G10: 45842 | I10: =IF(Table1[[#This Row],[Centre Status]]="Returned","NA",IF(Table1[[#This Row],[SD]]>19000,"Full Payment",IF(Table1[[#This Row],[SD]]<1,"No Payment","Partial Payment"))) -> Full Payment | J10: Active | K10: 110000 | L10: =Q10+R10+U10+Table1[[#This Row],[Farmer Payment]] -> 20000 | P10: =K10-L10+M10 -> 90000 | Q10: =AI10+AV10+CK10+Table1[[#This Row],[FY 25-26]] -> 0 | R10: 20000 | S10: 516276355328 | T10: 45819 | AI10: =SUM(W10:AH10) -> 0 | AV10: =SUM(AJ10:AU10) -> 0 | CK10: =SUM(AW10:CJ10) -> 0 | CW10: 0 | CX10: 0 | CY10: 0 | CZ10: 0 | DK10: =SUM(Table1[[#This Row],[01-03 Apr]:[Mar-26]]) -> 0
C11: 10110159 | D11: GOMUKH MOHABA | E11: S kamal | G11: 45842 | I11: =IF(Table1[[#This Row],[Centre Status]]="Returned","NA",IF(Table1[[#This Row],[SD]]>19000,"Full Payment",IF(Table1[[#This Row],[SD]]<1,"No Payment","Partial Payment"))) -> Full Payment | J11: Active | K11: 110000 | L11: =Q11+R11+U11+Table1[[#This Row],[Farmer Payment]] -> 20000 | P11: =K11-L11+M11 -> 90000 | Q11: =AI11+AV11+CK11+Table1[[#This Row],[FY 25-26]] -> 0 | R11: 20000 | S11: 516760882866 | T11: 45824 | AI11: =SUM(W11:AH11) -> 0 | AV11: =SUM(AJ11:AU11) -> 0 | CK11: =SUM(AW11:CJ11) -> 0 | CW11: 0 | CX11: 0 | CY11: 0 | CZ11: 0 | DK11: =SUM(Table1[[#This Row],[01-03 Apr]:[Mar-26]]) -> 0
C12: 10080100 | D12: Sibutol Naya Tola | E12: Teghra | G12: 45842 | H12: 0 | I12: =IF(Table1[[#This Row],[Centre Status]]="Returned","NA",IF(Table1[[#This Row],[SD]]>19000,"Full Payment",IF(Table1[[#This Row],[SD]]<1,"No Payment","Partial Payment"))) -> Full Payment | J12: Active | K12: 110000 | L12: =Q12+R12+U12+Table1[[#This Row],[Farmer Payment]] -> 20000 | P12: =K12-L12+M12 -> 90000 | Q12: =AI12+AV12+CK12+Table1[[#This Row],[FY 25-26]] -> 0 | R12: 20000 | S12: 572989707262 | T12: 45824 | AI12: =SUM(W12:AH12) -> 0 | AV12: =SUM(AJ12:AU12) -> 0 | CK12: =SUM(AW12:CJ12) -> 0 | CW12: 0 | CX12: 0 | CY12: 0 | CZ12: 0 | DK12: =SUM(Table1[[#This Row],[01-03 Apr]:[Mar-26]]) -> 0
C13: 10120108 | D13: GOMUKH MANIKA EAST | E13: dalsingsarai | I13: =IF(Table1[[#This Row],[Centre Status]]="Returned","NA",IF(Table1[[#This Row],[SD]]>19000,"Full Payment",IF(Table1[[#This Row],[SD]]<1,"No Payment","Partial Payment"))) -> No Payment | J13: Active | K13: 110000 | L13: =Q13+R13+U13+Table1[[#This Row],[Farmer Payment]] -> 0 | P13: =K13-L13+M13 -> 110000 | Q13: =AI13+AV13+CK13+Table1[[#This Row],[FY 25-26]] -> 0 | AI13: =SUM(W13:AH13) -> 0 | AV13: =SUM(AJ13:AU13) -> 0 | CK13: =SUM(AW13:CJ13) -> 0 | DK13: =SUM(Table1[[#This Row],[01-03 Apr]:[Mar-26]]) -> 0
C14: 10530067 | D14: GOMUKH BANDRA W-6 | E14: Kalyanpur | I14: =IF(Table1[[#This Row],[Centre Status]]="Returned","NA",IF(Table1[[#This Row],[SD]]>19000,"Full Payment",IF(Table1[[#This Row],[SD]]<1,"No Payment","Partial Payment"))) -> No Payment | J14: Active | K14: 110000 | L14: =Q14+R14+U14+Table1[[#This Row],[Farmer Payment]] -> 0 | P14: =K14-L14+M14 -> 110000 | Q14: =AI14+AV14+CK14+Table1[[#This Row],[FY 25-26]] -> 0 | AI14: =SUM(W14:AH14) -> 0 | AV14: =SUM(AJ14:AU14) -> 0 | CK14: =SUM(AW14:CJ14) -> 0 | DK14: =SUM(Table1[[#This Row],[01-03 Apr]:[Mar-26]]) -> 0
C15: 10530074 | D15: GOMUKH BALAHA W-9 | E15: Kalyanpur | G15: 45834 | I15: =IF(Table1[[#This Row],[Centre Status]]="Returned","NA",IF(Table1[[#This Row],[SD]]>19000,"Full Payment",IF(Table1[[#This Row],[SD]]<1,"No Payment","Partial Payment"))) -> Partial Payment | J15: Active | K15: 110000 | L15: =Q15+R15+U15+Table1[[#This Row],[Farmer Payment]] -> 10000 | P15: =K15-L15+M15 -> 100000 | Q15: =AI15+AV15+CK15+Table1[[#This Row],[FY 25-26]] -> 0 | R15: 10000 | S15: 374860488193 | T15: 45826 | AI15: =SUM(W15:AH15) -> 0 | AV15: =SUM(AJ15:AU15) -> 0 | CK15: =SUM(AW15:CJ15) -> 0 | CW15: 0 | CX15: 0 | CY15: 0 | CZ15: 0 | DK15: =SUM(Table1[[#This Row],[01-03 Apr]:[Mar-26]]) -> 0
C16: 10140183 | D16: Gomukh Uttardahan | E16: Dumraon | I16: =IF(Table1[[#This Row],[Centre Status]]="Returned","NA",IF(Table1[[#This Row],[SD]]>19000,"Full Payment",IF(Table1[[#This Row],[SD]]<1,"No Payment","Partial Payment"))) -> Partial Payment | J16: Active | K16: 110000 | L16: =Q16+R16+U16+Table1[[#This Row],[Farmer Payment]] -> 10000 | P16: =K16-L16+M16 -> 100000 | Q16: =AI16+AV16+CK16+Table1[[#This Row],[FY 25-26]] -> 0 | R16: 10000 | S16: 022405583427 | T16: 45818 | AI16: =SUM(W16:AH16) -> 0 | AV16: =SUM(AJ16:AU16) -> 0 | CK16: =SUM(AW16:CJ16) -> 0 | CW16: 0 | CX16: 0 | CY16: 0 | CZ16: 0 | DK16: =SUM(Table1[[#This Row],[01-03 Apr]:[Mar-26]]) -> 0
C17: 10140182 | D17: Gomukh Pandeypur | E17: Dumraon | I17: =IF(Table1[[#This Row],[Centre Status]]="Returned","NA",IF(Table1[[#This Row],[SD]]>19000,"Full Payment",IF(Table1[[#This Row],[SD]]<1,"No Payment","Partial Payment"))) -> Partial Payment | J17: Active | K17: 110000 | L17: =Q17+R17+U17+Table1[[#This Row],[Farmer Payment]] -> 8000 | P17: =K17-L17+M17 -> 102000 | Q17: =AI17+AV17+CK17+Table1[[#This Row],[FY 25-26]] -> 0 | R17: 8000 | S17: 398060379840 | T17: 45806 | AI17: =SUM(W17:AH17) -> 0 | AV17: =SUM(AJ17:AU17) -> 0 | CK17: =SUM(AW17:CJ17) -> 0 | DK17: =SUM(Table1[[#This Row],[01-03 Apr]:[Mar-26]]) -> 0
C18: 10140178 | D18: Gomukh Tiyar | E18: Dumraon | I18: =IF(Table1[[#This Row],[Centre Status]]="Returned","NA",IF(Table1[[#This Row],[SD]]>19000,"Full Payment",IF(Table1[[#This Row],[SD]]<1,"No Payment","Partial Payment"))) -> Partial Payment | J18: Active | K18: 110000 | L18: =Q18+R18+U18+Table1[[#This Row],[Farmer Payment]] -> 10908 | P18: =K18-L18+M18 -> 99092 | Q18: =AI18+AV18+CK18+Table1[[#This Row],[FY 25-26]] -> 908 | R18: 10000 | S18: 252667001659 | T18: 45784 | AI18: =SUM(W18:AH18) -> 0 | AV18: =SUM(AJ18:AU18) -> 0 | CK18: =SUM(AW18:CJ18) -> 0 | CP18: 0 | CR18: 0 | CS18: 0 | CT18: 0 | CU18: 0 | CV18: 908 | CW18: 0 | CX18: 0 | CY18: 0 | CZ18: 0 | DK18: =SUM(Table1[[#This Row],[01-03 Apr]:[Mar-26]]) -> 908
C19: 10140179 | D19: Gomukh Rajpur | E19: Dumraon | I19: =IF(Table1[[#This Row],[Centre Status]]="Returned","NA",IF(Table1[[#This Row],[SD]]>19000,"Full Payment",IF(Table1[[#This Row],[SD]]<1,"No Payment","Partial Payment"))) -> Partial Payment | J19: Active | K19: 110000 | L19: =Q19+R19+U19+Table1[[#This Row],[Farmer Payment]] -> 10476 | P19: =K19-L19+M19 -> 99524 | Q19: =AI19+AV19+CK19+Table1[[#This Row],[FY 25-26]] -> 476 | R19: 10000 | S19: 550550496098 | T19: 45796 | AI19: =SUM(W19:AH19) -> 0 | AV19: =SUM(AJ19:AU19) -> 0 | CK19: =SUM(AW19:CJ19) -> 0 | CP19: 0 | CR19: 0 | CS19: 0 | CT19: 0 | CU19: 0 | CV19: 476 | CW19: 0 | CX19: 0 | CY19: 0 | CZ19: 0 | DK19: =SUM(Table1[[#This Row],[01-03 Apr]:[Mar-26]]) -> 476
C20: 10140180 | D20: Gomukh Gangauli Dubha | E20: Dumraon | I20: =IF(Table1[[#This Row],[Centre Status]]="Returned","NA",IF(Table1[[#This Row],[SD]]>19000,"Full Payment",IF(Table1[[#This Row],[SD]]<1,"No Payment","Partial Payment"))) -> Partial Payment | J20: Active | K20: 110000 | L20: =Q20+R20+U20+Table1[[#This Row],[Farmer Payment]] -> 10000 | P20: =K20-L20+M20 -> 100000 | Q20: =AI20+AV20+CK20+Table1[[#This Row],[FY 25-26]] -> 0 | R20: 10000 | S20: 846061232899 | T20: 45794 | AI20: =SUM(W20:AH20) -> 0 | AV20: =SUM(AJ20:AU20) -> 0 | CK20: =SUM(AW20:CJ20) -> 0 | CR20: 0 | CT20: 0 | CU20: 0 | CV20: 0 | CW20: 0 | CX20: 0 | CY20: 0 | CZ20: 0 | DK20: =SUM(Table1[[#This Row],[01-03 Apr]:[Mar-26]]) -> 0
C21: 10540008 | D21: GOMUKH PARRI | E21: Alauli | G21: 45832 | I21: =IF(Table1[[#This Row],[Centre Status]]="Returned","NA",IF(Table1[[#This Row],[SD]]>19000,"Full Payment",IF(Table1[[#This Row],[SD]]<1,"No Payment","Partial Payment"))) -> Full Payment | J21: Active | K21: 110000 | L21: =Q21+R21+U21+Table1[[#This Row],[Farmer Payment]] -> 20000 | P21: =K21-L21+M21 -> 90000 | Q21: =AI21+AV21+CK21+Table1[[#This Row],[FY 25-26]] -> 0 | R21: 20000 | T21: 45801 | AI21: =SUM(W21:AH21) -> 0 | AV21: =SUM(AJ21:AU21) -> 0 | CK21: =SUM(AW21:CJ21) -> 0 | CV21: 0 | CW21: 0 | CX21: 0 | CY21: 0 | CZ21: 0 | DK21: =SUM(Table1[[#This Row],[01-03 Apr]:[Mar-26]]) -> 0
C22: 10540009 | D22: GOMUKH BHIKHARI GHAT | E22: Alauli | G22: 45832 | I22: =IF(Table1[[#This Row],[Centre Status]]="Returned","NA",IF(Table1[[#This Row],[SD]]>19000,"Full Payment",IF(Table1[[#This Row],[SD]]<1,"No Payment","Partial Payment"))) -> Full Payment | J22: Active | K22: 110000 | L22: =Q22+R22+U22+Table1[[#This Row],[Farmer Payment]] -> 20000 | P22: =K22-L22+M22 -> 90000 | Q22: =AI22+AV22+CK22+Table1[[#This Row],[FY 25-26]] -> 0 | R22: 20000 | S22: 105321869290 | T22: 45801 | AI22: =SUM(W22:AH22) -> 0 | AV22: =SUM(AJ22:AU22) -> 0 | CK22: =SUM(AW22:CJ22) -> 0 | CV22: 0 | CW22: 0 | CX22: 0 | CY22: 0 | CZ22: 0 | DK22: =SUM(Table1[[#This Row],[01-03 Apr]:[Mar-26]]) -> 0
C23: 10080098 | D23: Rani Panchwati | E23: Majhaul(Gadhpura) | I23: =IF(Table1[[#This Row],[Centre Status]]="Returned","NA",IF(Table1[[#This Row],[SD]]>19000,"Full Payment",IF(Table1[[#This Row],[SD]]<1,"No Payment","Partial Payment"))) -> Partial Payment | J23: Active | K23: 110000 | L23: =Q23+R23+U23+Table1[[#This Row],[Farmer Payment]] -> 10000 | P23: =K23-L23+M23 -> 100000 | Q23: =AI23+AV23+CK23+Table1[[#This Row],[FY 25-26]] -> 0 | R23: 10000 | S23: 284703126001 | T23: 45800 | AI23: =SUM(W23:AH23) -> 0 | AV23: =SUM(AJ23:AU23) -> 0 | CK23: =SUM(AW23:CJ23) -> 0 | CR23: 0 | CT23: 0 | CU23: 0 | CV23: 0 | CW23: 0 | CX23: 0 | CY23: 0 | CZ23: 0 | DK23: =SUM(Table1[[#This Row],[01-03 Apr]:[Mar-26]]) -> 0
C24: 10540005 | D24: GOMUKH GADBANNI | E24: Alauli | I24: =IF(Table1[[#This Row],[Centre Status]]="Returned","NA",IF(Table1[[#This Row],[SD]]>19000,"Full Payment",IF(Table1[[#This Row],[SD]]<1,"No Payment","Partial Payment"))) -> Full Payment | J24: Active | K24: 110000 | L24: =Q24+R24+U24+Table1[[#This Row],[Farmer Payment]] -> 20109 | P24: =K24-L24+M24 -> 89891 | Q24: =AI24+AV24+CK24+Table1[[#This Row],[FY 25-26]] -> 109 | R24: 20000 | S24: 305429278180 | T24: 45794 | AI24: =SUM(W24:AH24) -> 0 | AV24: =SUM(AJ24:AU24) -> 0 | CK24: =SUM(AW24:CJ24) -> 0 | CP24: 0 | CR24: 0 | CS24: 0 | CT24: 0 | CU24: 0 | CV24: 109 | CW24: 0 | CX24: 0 | CY24: 0 | CZ24: 0 | DK24: =SUM(Table1[[#This Row],[01-03 Apr]:[Mar-26]]) -> 109
C25: 10540006 | D25: GOMUKH AMBA | E25: Alauli | I25: =IF(Table1[[#This Row],[Centre Status]]="Returned","NA",IF(Table1[[#This Row],[SD]]>19000,"Full Payment",IF(Table1[[#This Row],[SD]]<1,"No Payment","Partial Payment"))) -> Full Payment | J25: Active | K25: 110000 | L25: =Q25+R25+U25+Table1[[#This Row],[Farmer Payment]] -> 20000 | P25: =K25-L25+M25 -> 90000 | Q25: =AI25+AV25+CK25+Table1[[#This Row],[FY 25-26]] -> 0 | R25: 20000 | S25: 753384965934 | T25: 45794 | AI25: =SUM(W25:AH25) -> 0 | AV25: =SUM(AJ25:AU25) -> 0 | CK25: =SUM(AW25:CJ25) -> 0 | CP25: 0 | CR25: 0 | CS25: 0 | CT25: 0 | CU25: 0 | CV25: 0 | CW25: 0 | CX25: 0 | CY25: 0 | CZ25: 0 | DK25: =SUM(Table1[[#This Row],[01-03 Apr]:[Mar-26]]) -> 0
C26: 10540007 | D26: GOMUKH GORIYAMI | E26: Alauli | I26: =IF(Table1[[#This Row],[Centre Status]]="Returned","NA",IF(Table1[[#This Row],[SD]]>19000,"Full Payment",IF(Table1[[#This Row],[SD]]<1,"No Payment","Partial Payment"))) -> Full Payment | J26: Active | K26: 110000 | L26: =Q26+R26+U26+Table1[[#This Row],[Farmer Payment]] -> 20000 | P26: =K26-L26+M26 -> 90000 | Q26: =AI26+AV26+CK26+Table1[[#This Row],[FY 25-26]] -> 0 | R26: 20000 | S26: 924823190609 | T26: 45797 | AI26: =SUM(W26:AH26) -> 0 | AV26: =SUM(AJ26:AU26) -> 0 | CK26: =SUM(AW26:CJ26) -> 0 | CP26: 0 | CR26: 0 | CS26: 0 | CT26: 0 | CU26: 0 | CV26: 0 | CW26: 0 | CX26: 0 | CY26: 0 | CZ26: 0 | DK26: =SUM(Table1[[#This Row],[01-03 Apr]:[Mar-26]]) -> 0
C27: 10140177 | D27: Gomukh Giridhar Baraw | E27: Dumraon | I27: =IF(Table1[[#This Row],[Centre Status]]="Returned","NA",IF(Table1[[#This Row],[SD]]>19000,"Full Payment",IF(Table1[[#This Row],[SD]]<1,"No Payment","Partial Payment"))) -> Partial Payment | J27: Active | K27: 110000 | L27: =Q27+R27+U27+Table1[[#This Row],[Farmer Payment]] -> 10076 | P27: =K27-L27+M27 -> 99924 | Q27: =AI27+AV27+CK27+Table1[[#This Row],[FY 25-26]] -> 76 | R27: 10000 | S27: 666539780403 | T27: 45791 | AI27: =SUM(W27:AH27) -> 0 | AV27: =SUM(AJ27:AU27) -> 0 | CK27: =SUM(AW27:CJ27) -> 0 | CP27: 0 | CR27: 0 | CS27: 0 | CT27: 0 | CU27: 0 | CV27: 76 | CW27: 0 | CX27: 0 | CY27: 0 | CZ27: 0 | DK27: =SUM(Table1[[#This Row],[01-03 Apr]:[Mar-26]]) -> 76
C28: 10060109 | D28: PACHRUKHI | E28: sonvarsha | I28: =IF(Table1[[#This Row],[Centre Status]]="Returned","NA",IF(Table1[[#This Row],[SD]]>19000,"Full Payment",IF(Table1[[#This Row],[SD]]<1,"No Payment","Partial Payment"))) -> Partial Payment | J28: Active | K28: 110000 | L28: =Q28+R28+U28+Table1[[#This Row],[Farmer Payment]] -> 10000 | P28: =K28-L28+M28 -> 100000 | Q28: =AI28+AV28+CK28+Table1[[#This Row],[FY 25-26]] -> 0 | R28: 10000 | S28: 105668245033 | T28: 45808 | AI28: =SUM(W28:AH28) -> 0 | AV28: =SUM(AJ28:AU28) -> 0 | CK28: =SUM(AW28:CJ28) -> 0 | CV28: 0 | CW28: 0 | CX28: 0 | CY28: 0 | CZ28: 0 | DK28: =SUM(Table1[[#This Row],[01-03 Apr]:[Mar-26]]) -> 0
C29: 10060110 | D29: ORABAGICHA | E29: sonvarsha | I29: =IF(Table1[[#This Row],[Centre Status]]="Returned","NA",IF(Table1[[#This Row],[SD]]>19000,"Full Payment",IF(Table1[[#This Row],[SD]]<1,"No Payment","Partial Payment"))) -> Partial Payment | J29: Active | K29: 110000 | L29: =Q29+R29+U29+Table1[[#This Row],[Farmer Payment]] -> 10000 | P29: =K29-L29+M29 -> 100000 | Q29: =AI29+AV29+CK29+Table1[[#This Row],[FY 25-26]] -> 0 | R29: 10000 | S29: 105604215713 | T29: 45806 | AI29: =SUM(W29:AH29) -> 0 | AV29: =SUM(AJ29:AU29) -> 0 | CK29: =SUM(AW29:CJ29) -> 0 | CV29: 0 | CW29: 0 | CX29: 0 | CY29: 0 | CZ29: 0 | DK29: =SUM(Table1[[#This Row],[01-03 Apr]:[Mar-26]]) -> 0
C30: 10030072 | D30: HARLACHAK | E30: Asarganj | I30: =IF(Table1[[#This Row],[Centre Status]]="Returned","NA",IF(Table1[[#This Row],[SD]]>19000,"Full Payment",IF(Table1[[#This Row],[SD]]<1,"No Payment","Partial Payment"))) -> No Payment | J30: Active | K30: 110000 | L30: =Q30+R30+U30+Table1[[#This Row],[Farmer Payment]] -> 0 | P30: =K30-L30+M30 -> 110000 | Q30: =AI30+AV30+CK30+Table1[[#This Row],[FY 25-26]] -> 0 | AI30: =SUM(W30:AH30) -> 0 | AV30: =SUM(AJ30:AU30) -> 0 | CK30: =SUM(AW30:CJ30) -> 0 | CV30: 0 | CW30: 0 | CX30: 0 | CY30: 0 | CZ30: 0 | DK30: =SUM(Table1[[#This Row],[01-03 Apr]:[Mar-26]]) -> 0
C31: 10030073 | D31: KHIRDIH | E31: Asarganj | I31: =IF(Table1[[#This Row],[Centre Status]]="Returned","NA",IF(Table1[[#This Row],[SD]]>19000,"Full Payment",IF(Table1[[#This Row],[SD]]<1,"No Payment","Partial Payment"))) -> No Payment | J31: Active | K31: 110000 | L31: =Q31+R31+U31+Table1[[#This Row],[Farmer Payment]] -> 0 | P31: =K31-L31+M31 -> 110000 | Q31: =AI31+AV31+CK31+Table1[[#This Row],[FY 25-26]] -> 0 | AI31: =SUM(W31:AH31) -> 0 | AV31: =SUM(AJ31:AU31) -> 0 | CK31: =SUM(AW31:CJ31) -> 0 | CV31: 0 | CW31: 0 | CX31: 0 | CY31: 0 | CZ31: 0 | DK31: =SUM(Table1[[#This Row],[01-03 Apr]:[Mar-26]]) -> 0
C32: 10060111 | D32: KHAJURIYA | E32: sonvarsha | I32: =IF(Table1[[#This Row],[Centre Status]]="Returned","NA",IF(Table1[[#This Row],[SD]]>19000,"Full Payment",IF(Table1[[#This Row],[SD]]<1,"No Payment","Partial Payment"))) -> Partial Payment | J32: Active | K32: 110000 | L32: =Q32+R32+U32+Table1[[#This Row],[Farmer Payment]] -> 15000 | P32: =K32-L32+M32 -> 95000 | Q32: =AI32+AV32+CK32+Table1[[#This Row],[FY 25-26]] -> 0 | R32: 15000 | S32: 624874214920 | T32: 45798 | AI32: =SUM(W32:AH32) -> 0 | AV32: =SUM(AJ32:AU32) -> 0 | CK32: =SUM(AW32:CJ32) -> 0 | CV32: 0 | CW32: 0 | CX32: 0 | CY32: 0 | CZ32: 0 | DK32: =SUM(Table1[[#This Row],[01-03 Apr]:[Mar-26]]) -> 0
C33: 10080099 | D33: Bihat - Chakballi | E33: Manjhaul | I33: =IF(Table1[[#This Row],[Centre Status]]="Returned","NA",IF(Table1[[#This Row],[SD]]>19000,"Full Payment",IF(Table1[[#This Row],[SD]]<1,"No Payment","Partial Payment"))) -> Full Payment | J33: Active | K33: 110000 | L33: =Q33+R33+U33+Table1[[#This Row],[Farmer Payment]] -> 20000 | P33: =K33-L33+M33 -> 90000 | Q33: =AI33+AV33+CK33+Table1[[#This Row],[FY 25-26]] -> 0 | R33: 20000 | S33: 104891278164 | T33: 45794 | AI33: =SUM(W33:AH33) -> 0 | AV33: =SUM(AJ33:AU33) -> 0 | CK33: =SUM(AW33:CJ33) -> 0 | CR33: 0 | CT33: 0 | CU33: 0 | CV33: 0 | CW33: 0 | CX33: 0 | CY33: 0 | CZ33: 0 | DK33: =SUM(Table1[[#This Row],[01-03 Apr]:[Mar-26]]) -> 0
C34: 10110104 | D34: GOMUKH RON | E34: Sahebpur Kamal | H34: 386752 | I34: =IF(Table1[[#This Row],[Centre Status]]="Returned","NA",IF(Table1[[#This Row],[SD]]>19000,"Full Payment",IF(Table1[[#This Row],[SD]]<1,"No Payment","Partial Payment"))) -> Full Payment | J34: Active | K34: 110000 | L34: =Q34+R34+U34+Table1[[#This Row],[Farmer Payment]] -> 29605.071 | P34: =K34-L34+M34 -> 80394.929 | Q34: =AI34+AV34+CK34+Table1[[#This Row],[FY 25-26]] -> 9605.0711 | R34: 20000 | S34: 459299204482 | T34: 46014 | AI34: =SUM(W34:AH34) -> 0 | AV34: =SUM(AJ34:AU34) -> 0 | BP34: 0 | BR34: 0 | BU34: 0 | BV34: 0 | BW34: 0 | BX34: 0 | BY34: 0 | BZ34: 0 | CA34: 0 | CB34: 0 | CC34: 0 | CD34: 0 | CE34: 0 | CF34: 0 | CG34: 0 | CH34: 0 | CI34: 0 | CJ34: 3539.0862 | CK34: =SUM(AW34:CJ34) -> 3539.0862 | CM34: 0 | CN34: 0 | CO34: 0 | CP34: 2911.6575 | CQ34: 0 | CR34: 0 | CS34: 0 | CT34: 0 | CU34: 0 | CV34: 3154.3274 | CW34: 0 | CX34: 0 | CY34: 0 | CZ34: 0 | DK34: =SUM(Table1[[#This Row],[01-03 Apr]:[Mar-26]]) -> 6065.9849
C35: 10110103 | D35: GOMUKH KAMATHAN | E35: Sahebpur Kamal | H35: 387339 | I35: =IF(Table1[[#This Row],[Centre Status]]="Returned","NA",IF(Table1[[#This Row],[SD]]>19000,"Full Payment",IF(Table1[[#This Row],[SD]]<1,"No Payment","Partial Payment"))) -> Partial Payment | J35: Active | K35: 110000 | L35: =Q35+R35+U35+Table1[[#This Row],[Farmer Payment]] -> 5000 | P35: =K35-L35+M35 -> 105000 | Q35: =AI35+AV35+CK35+Table1[[#This Row],[FY 25-26]] -> 0 | R35: 5000 | S35: 435368727369 | T35: 46009 | AI35: =SUM(W35:AH35) -> 0 | AV35: =SUM(AJ35:AU35) -> 0 | BP35: 0 | BR35: 0 | BU35: 0 | BV35: 0 | BW35: 0 | BX35: 0 | BY35: 0 | BZ35: 0 | CA35: 0 | CB35: 0 | CC35: 0 | CD35: 0 | CE35: 0 | CF35: 0 | CG35: 0 | CH35: 0 | CI35: 0 | CJ35: 0 | CK35: =SUM(AW35:CJ35) -> 0 | CM35: 0 | CN35: 0 | CO35: 0 | CP35: 0 | CQ35: 0 | CR35: 0 | CS35: 0 | CT35: 0 | CU35: 0 | CV35: 0 | CW35: 0 | CX35: 0 | CY35: 0 | CZ35: 0 | DK35: =SUM(Table1[[#This Row],[01-03 Apr]:[Mar-26]]) -> 0
C36: 10140153 | D36: Gomukh Bramhpur | E36: Dumraon | H36: 387358 | I36: =IF(Table1[[#This Row],[Centre Status]]="Returned","NA",IF(Table1[[#This Row],[SD]]>19000,"Full Payment",IF(Table1[[#This Row],[SD]]<1,"No Payment","Partial Payment"))) -> Partial Payment | J36: Active | K36: 110000 | L36: =Q36+R36+U36+Table1[[#This Row],[Farmer Payment]] -> 15583 | P36: =K36-L36+M36 -> 94417 | Q36: =AI36+AV36+CK36+Table1[[#This Row],[FY 25-26]] -> 5583 | R36: 10000 | S36: 404083753894 | T36: 45659 | AI36: =SUM(W36:AH36) -> 0 | AV36: =SUM(AJ36:AU36) -> 0 | BP36: 0 | BR36: 0 | BV36: 0 | BW36: 0 | BX36: 0 | BY36: 0 | BZ36: 0 | CA36: 0 | CB36: 0 | CC36: 0 | CD36: 0 | CE36: 0 | CF36: 0 | CG36: 0 | CH36: 0 | CI36: 0 | CJ36: 1861 | CK36: =SUM(AW36:CJ36) -> 1861 | CM36: 0 | CN36: 0 | CO36: 0 | CP36: 1861 | CQ36: 0 | CR36: 0 | CS36: 0 | CT36: 0 | CU36: 0 | CV36: 1861 | CW36: 0 | CX36: 0 | CY36: 0 | CZ36: 0 | DK36: =SUM(Table1[[#This Row],[01-03 Apr]:[Mar-26]]) -> 3722
C37: 10110141 | D37: GHAMARIYA | E37: Sahebpur Kamal | I37: =IF(Table1[[#This Row],[Centre Status]]="Returned","NA",IF(Table1[[#This Row],[SD]]>19000,"Full Payment",IF(Table1[[#This Row],[SD]]<1,"No Payment","Partial Payment"))) -> Full Payment | J37: Active | K37: 110000 | L37: =Q37+R37+U37+Table1[[#This Row],[Farmer Payment]] -> 21861 | P37: =K37-L37+M37 -> 88139 | Q37: =AI37+AV37+CK37+Table1[[#This Row],[FY 25-26]] -> 1861 | R37: 20000 | S37: 342259970412 | T37: 45754 | AI37: =SUM(W37:AH37) -> 0 | AV37: =SUM(AJ37:AU37) -> 0 | CF37: 0 | CG37: 0 | CH37: 0 | CI37: 0 | CJ37: 0 | CK37: =SUM(AW37:CJ37) -> 0 | CM37: 0 | CN37: 0 | CO37: 0 | CP37: 0 | CQ37: 0 | CR37: 0 | CS37: 0 | CT37: 0 | CU37: 0 | CV37: 1861 | CW37: 0 | CX37: 0 | CY37: 0 | CZ37: 0 | DK37: =SUM(Table1[[#This Row],[01-03 Apr]:[Mar-26]]) -> 1861
C38: 10530027 | D38: Kolwara | E38: Kalyanpur | H38: 23120074 | I38: =IF(Table1[[#This Row],[Centre Status]]="Returned","NA",IF(Table1[[#This Row],[SD]]>19000,"Full Payment",IF(Table1[[#This Row],[SD]]<1,"No Payment","Partial Payment"))) -> Full Payment | J38: Active | K38: 110000 | L38: =Q38+R38+U38+Table1[[#This Row],[Farmer Payment]] -> 21861 | P38: =K38-L38+M38 -> 88139 | Q38: =AI38+AV38+CK38+Table1[[#This Row],[FY 25-26]] -> 1861 | R38: 20000 | S38: 282553634463 | T38: 45716 | AI38: =SUM(W38:AH38) -> 0 | AV38: =SUM(AJ38:AU38) -> 0 | CK38: =SUM(AW38:CJ38) -> 0 | CM38: 0 | CP38: 0 | CQ38: 0 | CR38: 0 | CS38: 0 | CT38: 0 | CU38: 0 | CV38: 1861 | CW38: 0 | CX38: 0 | CY38: 0 | CZ38: 0 | DK38: =SUM(Table1[[#This Row],[01-03 Apr]:[Mar-26]]) -> 1861
C39: 10530044 | D39: Gomukh Punas | E39: Kalyanpur | H39: 23120088 | I39: =IF(Table1[[#This Row],[Centre Status]]="Returned","NA",IF(Table1[[#This Row],[SD]]>19000,"Full Payment",IF(Table1[[#This Row],[SD]]<1,"No Payment","Partial Payment"))) -> Full Payment | J39: Active | K39: 110000 | L39: =Q39+R39+U39+Table1[[#This Row],[Farmer Payment]] -> 21861 | P39: =K39-L39+M39 -> 88139 | Q39: =AI39+AV39+CK39+Table1[[#This Row],[FY 25-26]] -> 1861 | R39: 20000 | S39: 953340644063 | T39: 45740 | AI39: =SUM(W39:AH39) -> 0 | AV39: =SUM(AJ39:AU39) -> 0 | CK39: =SUM(AW39:CJ39) -> 0 | CM39: 0 | CP39: 0 | CQ39: 0 | CR39: 0 | CS39: 0 | CT39: 0 | CU39: 0 | CV39: 1861 | CW39: 0 | CX39: 0 | CY39: 0 | CZ39: 0 | DK39: =SUM(Table1[[#This Row],[01-03 Apr]:[Mar-26]]) -> 1861
C40: 10530046 | D40: Loharkha | E40: Kalyanpur | H40: 24010126 | I40: =IF(Table1[[#This Row],[Centre Status]]="Returned","NA",IF(Table1[[#This Row],[SD]]>19000,"Full Payment",IF(Table1[[#This Row],[SD]]<1,"No Payment","Partial Payment"))) -> NA | J40: Returned | K40: 110000 | L40: =Q40+R40+U40+Table1[[#This Row],[Farmer Payment]] -> 0 | M40: 20000 | N40: 45790 | P40: =K40-L40+M40 -> 130000 | Q40: =AI40+AV40+CK40+Table1[[#This Row],[FY 25-26]] -> 0 | AI40: =SUM(W40:AH40) -> 0 | AV40: =SUM(AJ40:AU40) -> 0 | CK40: =SUM(AW40:CJ40) -> 0 | CM40: 0 | CP40: 0 | CQ40: 0 | CR40: 0 | CS40: 0 | CT40: 0 | CU40: 0 | CV40: 0 | CW40: 0 | CX40: 0 | CY40: 0 | CZ40: 0 | DK40: =SUM(Table1[[#This Row],[01-03 Apr]:[Mar-26]]) -> 0
D41: Gomukh Chaksihama | I41: =IF(Table1[[#This Row],[Centre Status]]="Returned","NA",IF(Table1[[#This Row],[SD]]>19000,"Full Payment",IF(Table1[[#This Row],[SD]]<1,"No Payment","Partial Payment"))) -> NA | J41: Returned | K41: 110000 | L41: =Q41+R41+U41+Table1[[#This Row],[Farmer Payment]] -> 0 | M41: 20000 | N41: 45790 | P41: =K41-L41+M41 -> 130000 | Q41: =AI41+AV41+CK41+Table1[[#This Row],[FY 25-26]] -> 0 | AI41: =SUM(W41:AH41) -> 0 | AV41: =SUM(AJ41:AU41) -> 0 | CK41: =SUM(AW41:CJ41) -> 0 | CP41: 0 | CR41: 0 | CS41: 0 | CT41: 0 | CU41: 0 | CV41: 0 | CW41: 0 | CX41: 0 | CY41: 0 | CZ41: 0 | DK41: =SUM(Table1[[#This Row],[01-03 Apr]:[Mar-26]]) -> 0
C42: 10530045 | D42: Bandara | E42: Kalyanpur | H42: 24020152 | I42: =IF(Table1[[#This Row],[Centre Status]]="Returned","NA",IF(Table1[[#This Row],[SD]]>19000,"Full Payment",IF(Table1[[#This Row],[SD]]<1,"No Payment","Partial Payment"))) -> Full Payment | J42: Active | K42: 110000 | L42: =Q42+R42+U42+Table1[[#This Row],[Farmer Payment]] -> 21395 | P42: =K42-L42+M42 -> 88605 | Q42: =AI42+AV42+CK42+Table1[[#This Row],[FY 25-26]] -> 1395 | R42: 20000 | S42: 063554611471 | T42: 45739 | AI42: =SUM(W42:AH42) -> 0 | AV42: =SUM(AJ42:AU42) -> 0 | CK42: =SUM(AW42:CJ42) -> 0 | CM42: 0 | CP42: 0 | CQ42: 0 | CR42: 0 | CS42: 0 | CT42: 0 | CU42: 0 | CV42: 1395 | CW42: 0 | CX42: 0 | CY42: 0 | CZ42: 0 | DK42: =SUM(Table1[[#This Row],[01-03 Apr]:[Mar-26]]) -> 1395
C43: 10530047 | D43: Gomukh Dighra | E43: Kalyanpur | H43: 24020154 | I43: =IF(Table1[[#This Row],[Centre Status]]="Returned","NA",IF(Table1[[#This Row],[SD]]>19000,"Full Payment",IF(Table1[[#This Row],[SD]]<1,"No Payment","Partial Payment"))) -> Full Payment | J43: Active | K43: 110000 | L43: =Q43+R43+U43+Table1[[#This Row],[Farmer Payment]] -> 21861 | P43: =K43-L43+M43 -> 88139 | Q43: =AI43+AV43+CK43+Table1[[#This Row],[FY 25-26]] -> 1861 | R43: 20000 | S43: 102126051799 | T43: 45746 | AI43: =SUM(W43:AH43) -> 0 | AV43: =SUM(AJ43:AU43) -> 0 | CK43: =SUM(AW43:CJ43) -> 0 | CM43: 0 | CP43: 0 | CQ43: 0 | CR43: 0 | CS43: 0 | CT43: 0 | CU43: 0 | CV43: 1861 | CW43: 0 | CX43: 0 | CY43: 0 | CZ43: 0 | DK43: =SUM(Table1[[#This Row],[01-03 Apr]:[Mar-26]]) -> 1861
C44: 10130098 | D44: Gomukh Gaopur Bhagwatpur | E44: Musrigharari | I44: =IF(Table1[[#This Row],[Centre Status]]="Returned","NA",IF(Table1[[#This Row],[SD]]>19000,"Full Payment",IF(Table1[[#This Row],[SD]]<1,"No Payment","Partial Payment"))) -> No Payment | J44: Active | K44: 110000 | L44: =Q44+R44+U44+Table1[[#This Row],[Farmer Payment]] -> 1861 | P44: =K44-L44+M44 -> 108139 | Q44: =AI44+AV44+CK44+Table1[[#This Row],[FY 25-26]] -> 1861 | AI44: =SUM(W44:AH44) -> 0 | AV44: =SUM(AJ44:AU44) -> 0 | CK44: =SUM(AW44:CJ44) -> 0 | CM44: 0 | CP44: 0 | CQ44: 0 | CR44: 0 | CS44: 0 | CT44: 0 | CU44: 0 | CV44: 1861 | CW44: 0 | CX44: 0 | CY44: 0 | CZ44: 0 | DK44: =SUM(Table1[[#This Row],[01-03 Apr]:[Mar-26]]) -> 1861
C45: 10120107 | D45: Gomukh Ramaiya | E45: Dalsingh Sarai | I45: =IF(Table1[[#This Row],[Centre Status]]="Returned","NA",IF(Table1[[#This Row],[SD]]>19000,"Full Payment",IF(Table1[[#This Row],[SD]]<1,"No Payment","Partial Payment"))) -> No Payment | J45: Active | K45: 110000 | L45: =Q45+R45+U45+Table1[[#This Row],[Farmer Payment]] -> 282 | P45: =K45-L45+M45 -> 109718 | Q45: =AI45+AV45+CK45+Table1[[#This Row],[FY 25-26]] -> 282 | AI45: =SUM(W45:AH45) -> 0 | AV45: =SUM(AJ45:AU45) -> 0 | CK45: =SUM(AW45:CJ45) -> 0 | CP45: 0 | CR45: 0 | CS45: 0 | CT45: 0 | CU45: 0 | CV45: 282 | CW45: 0 | CX45: 0 | CY45: 0 | CZ45: 0 | DK45: =SUM(Table1[[#This Row],[01-03 Apr]:[Mar-26]]) -> 282
C46: 10130100 | D46: Gomukh Rajwara | E46: Musrigharari | I46: =IF(Table1[[#This Row],[Centre Status]]="Returned","NA",IF(Table1[[#This Row],[SD]]>19000,"Full Payment",IF(Table1[[#This Row],[SD]]<1,"No Payment","Partial Payment"))) -> No Payment | J46: Active | K46: 110000 | L46: =Q46+R46+U46+Table1[[#This Row],[Farmer Payment]] -> 0 | P46: =K46-L46+M46 -> 110000 | Q46: =AI46+AV46+CK46+Table1[[#This Row],[FY 25-26]] -> 0 | AI46: =SUM(W46:AH46) -> 0 | AV46: =SUM(AJ46:AU46) -> 0 | CK46: =SUM(AW46:CJ46) -> 0 | CP46: 0 | CR46: 0 | CS46: 0 | CT46: 0 | CU46: 0 | CV46: 0 | CW46: 0 | CX46: 0 | CY46: 0 | CZ46: 0 | DK46: =SUM(Table1[[#This Row],[01-03 Apr]:[Mar-26]]) -> 0
C47: 10130102 | D47: GOMUKH NIKASPUR | E47: Musrigharari | I47: =IF(Table1[[#This Row],[Centre Status]]="Returned","NA",IF(Table1[[#This Row],[SD]]>19000,"Full Payment",IF(Table1[[#This Row],[SD]]<1,"No Payment","Partial Payment"))) -> Partial Payment | J47: Active | K47: 110000 | L47: =Q47+R47+U47+Table1[[#This Row],[Farmer Payment]] -> 10000 | P47: =K47-L47+M47 -> 100000 | Q47: =AI47+AV47+CK47+Table1[[#This Row],[FY 25-26]] -> 0 | R47: 10000 | S47: 477588599192 | T47: 45792 | AI47: =SUM(W47:AH47) -> 0 | AV47: =SUM(AJ47:AU47) -> 0 | CK47: =SUM(AW47:CJ47) -> 0 | CR47: 0 | CT47: 0 | CU47: 0 | CV47: 0 | CW47: 0 | CX47: 0 | CY47: 0 | CZ47: 0 | DK47: =SUM(Table1[[#This Row],[01-03 Apr]:[Mar-26]]) -> 0
C48: 10530064 | D48: GOMUKH MANIYARPUR | E48: Kalyanpur | I48: =IF(Table1[[#This Row],[Centre Status]]="Returned","NA",IF(Table1[[#This Row],[SD]]>19000,"Full Payment",IF(Table1[[#This Row],[SD]]<1,"No Payment","Partial Payment"))) -> Full Payment | J48: Active | K48: 110000 | L48: =Q48+R48+U48+Table1[[#This Row],[Farmer Payment]] -> 20000 | P48: =K48-L48+M48 -> 90000 | Q48: =AI48+AV48+CK48+Table1[[#This Row],[FY 25-26]] -> 0 | R48: 20000 | S48: 336404387194 | T48: 45800 | AI48: =SUM(W48:AH48) -> 0 | AV48: =SUM(AJ48:AU48) -> 0 | CK48: =SUM(AW48:CJ48) -> 0 | CR48: 0 | CT48: 0 | CU48: 0 | CV48: 0 | CW48: 0 | CX48: 0 | CY48: 0 | CZ48: 0 | DK48: =SUM(Table1[[#This Row],[01-03 Apr]:[Mar-26]]) -> 0
C49: 10530065 | D49: GOMUKH DIGHRA W-6 | E49: Kalyanpur | I49: =IF(Table1[[#This Row],[Centre Status]]="Returned","NA",IF(Table1[[#This Row],[SD]]>19000,"Full Payment",IF(Table1[[#This Row],[SD]]<1,"No Payment","Partial Payment"))) -> Full Payment | J49: Active | K49: 110000 | L49: =Q49+R49+U49+Table1[[#This Row],[Farmer Payment]] -> 20000 | P49: =K49-L49+M49 -> 90000 | Q49: =AI49+AV49+CK49+Table1[[#This Row],[FY 25-26]] -> 0 | R49: 20000 | S49: PUNBN62025053050061804 | T49: 45807 | AI49: =SUM(W49:AH49) -> 0 | AV49: =SUM(AJ49:AU49) -> 0 | CK49: =SUM(AW49:CJ49) -> 0 | CR49: 0 | CT49: 0 | CU49: 0 | CV49: 0 | CW49: 0 | CX49: 0 | CY49: 0 | CZ49: 0 | DK49: =SUM(Table1[[#This Row],[01-03 Apr]:[Mar-26]]) -> 0
C50: 10530061 | D50: GOMUKH Gopalpur Thahara | E50: Kalyanpur | I50: =IF(Table1[[#This Row],[Centre Status]]="Returned","NA",IF(Table1[[#This Row],[SD]]>19000,"Full Payment",IF(Table1[[#This Row],[SD]]<1,"No Payment","Partial Payment"))) -> Full Payment | J50: Active | K50: 110000 | L50: =Q50+R50+U50+Table1[[#This Row],[Farmer Payment]] -> 20056 | P50: =K50-L50+M50 -> 89944 | Q50: =AI50+AV50+CK50+Table1[[#This Row],[FY 25-26]] -> 56 | R50: 20000 | S50: 928070659100 | T50: 45787 | AI50: =SUM(W50:AH50) -> 0 | AV50: =SUM(AJ50:AU50) -> 0 | CK50: =SUM(AW50:CJ50) -> 0 | CP50: 0 | CR50: 0 | CS50: 0 | CT50: 0 | CU50: 0 | CV50: 56 | CW50: 0 | CX50: 0 | CY50: 0 | CZ50: 0 | DK50: =SUM(Table1[[#This Row],[01-03 Apr]:[Mar-26]]) -> 56
C51: 10530062 | D51: Gomukh Malinagar East | E51: Kalyanpur | I51: =IF(Table1[[#This Row],[Centre Status]]="Returned","NA",IF(Table1[[#This Row],[SD]]>19000,"Full Payment",IF(Table1[[#This Row],[SD]]<1,"No Payment","Partial Payment"))) -> No Payment | J51: Active | K51: 110000 | L51: =Q51+R51+U51+Table1[[#This Row],[Farmer Payment]] -> 195 | P51: =K51-L51+M51 -> 109805 | Q51: =AI51+AV51+CK51+Table1[[#This Row],[FY 25-26]] -> 195 | AI51: =SUM(W51:AH51) -> 0 | AV51: =SUM(AJ51:AU51) -> 0 | CK51: =SUM(AW51:CJ51) -> 0 | CP51: 0 | CR51: 0 | CS51: 0 | CT51: 0 | CU51: 0 | CV51: 195 | CW51: 0 | CX51: 0 | CY51: 0 | CZ51: 0 | DK51: =SUM(Table1[[#This Row],[01-03 Apr]:[Mar-26]]) -> 195
C52: 10530048 | D52: Basuwari | E52: Kalyanpur | H52: 24020159 | I52: =IF(Table1[[#This Row],[Centre Status]]="Returned","NA",IF(Table1[[#This Row],[SD]]>19000,"Full Payment",IF(Table1[[#This Row],[SD]]<1,"No Payment","Partial Payment"))) -> Full Payment | J52: Active | K52: 110000 | L52: =Q52+R52+U52+Table1[[#This Row],[Farmer Payment]] -> 21861 | P52: =K52-L52+M52 -> 88139 | Q52: =AI52+AV52+CK52+Table1[[#This Row],[FY 25-26]] -> 1861 | R52: 20000 | S52: 508775521883 | T52: 45744 | AI52: =SUM(W52:AH52) -> 0 | AV52: =SUM(AJ52:AU52) -> 0 | CK52: =SUM(AW52:CJ52) -> 0 | CM52: 0 | CP52: 0 | CQ52: 0 | CR52: 0 | CS52: 0 | CT52: 0 | CU52: 0 | CV52: 1861 | CW52: 0 | CX52: 0 | CY52: 0 | CZ52: 0 | DK52: =SUM(Table1[[#This Row],[01-03 Apr]:[Mar-26]]) -> 1861
C53: 10120098 | D53: GOMUKH JALALPUR | E53: Dalsinghsarai | H53: 277019 | I53: =IF(Table1[[#This Row],[Centre Status]]="Returned","NA",IF(Table1[[#This Row],[SD]]>19000,"Full Payment",IF(Table1[[#This Row],[SD]]<1,"No Payment","Partial Payment"))) -> Partial Payment | J53: Active | K53: 64000 | L53: =Q53+R53+U53+Table1[[#This Row],[Farmer Payment]] -> 11861 | P53: =K53-L53+M53 -> 52139 | Q53: =AI53+AV53+CK53+Table1[[#This Row],[FY 25-26]] -> 1861 | R53: 10000 | S53: 184904309393 | T53: 45694 | AI53: =SUM(W53:AH53) -> 0 | AV53: =SUM(AJ53:AU53) -> 0 | CK53: =SUM(AW53:CJ53) -> 0 | CM53: 0 | CP53: 0 | CQ53: 0 | CR53: 0 | CS53: 0 | CT53: 0 | CU53: 0 | CV53: 1861 | CW53: 0 | CX53: 0 | CY53: 0 | CZ53: 0 | DK53: =SUM(Table1[[#This Row],[01-03 Apr]:[Mar-26]]) -> 1861
C54: 10130095 | D54: Gomukh Saidpur | E54: Dalsinghsarai | H54: 277509 | I54: =IF(Table1[[#This Row],[Centre Status]]="Returned","NA",IF(Table1[[#This Row],[SD]]>19000,"Full Payment",IF(Table1[[#This Row],[SD]]<1,"No Payment","Partial Payment"))) -> No Payment | J54: Active | K54: 110000 | L54: =Q54+R54+U54+Table1[[#This Row],[Farmer Payment]] -> 1861 | P54: =K54-L54+M54 -> 108139 | Q54: =AI54+AV54+CK54+Table1[[#This Row],[FY 25-26]] -> 1861 | AI54: =SUM(W54:AH54) -> 0 | AV54: =SUM(AJ54:AU54) -> 0 | CK54: =SUM(AW54:CJ54) -> 0 | CM54: 0 | CP54: 0 | CQ54: 0 | CR54: 0 | CS54: 0 | CT54: 0 | CU54: 0 | CV54: 1861 | CW54: 0 | CX54: 0 | CY54: 0 | CZ54: 0 | DK54: =SUM(Table1[[#This Row],[01-03 Apr]:[Mar-26]]) -> 1861
C55: 10540003 | D55: GOMUKH ANANDPUR PARAS 2 | E55: Alauli | I55: =IF(Table1[[#This Row],[Centre Status]]="Returned","NA",IF(Table1[[#This Row],[SD]]>19000,"Full Payment",IF(Table1[[#This Row],[SD]]<1,"No Payment","Partial Payment"))) -> Full Payment | J55: Active | K55: 110000 | L55: =Q55+R55+U55+Table1[[#This Row],[Farmer Payment]] -> 22311.205 | P55: =K55-L55+M55 -> 87688.795 | Q55: =AI55+AV55+CK55+Table1[[#This Row],[FY 25-26]] -> 2311.2055 | R55: 20000 | S55: 530411531031 | T55: 45774 | AI55: =SUM(W55:AH55) -> 0 | AV55: =SUM(AJ55:AU55) -> 0 | CK55: =SUM(AW55:CJ55) -> 0 | CP55: 0 | CR55: 0 | CS55: 0 | CT55: 0 | CU55: 0 | CV55: 2311.2055 | CW55: 0 | CX55: 0 | CY55: 0 | CZ55: 0 | DK55: =SUM(Table1[[#This Row],[01-03 Apr]:[Mar-26]]) -> 2311.2055
C56: 10540004 | D56: GOMUKH SHYAM GHARARI | E56: Alauli | I56: =IF(Table1[[#This Row],[Centre Status]]="Returned","NA",IF(Table1[[#This Row],[SD]]>19000,"Full Payment",IF(Table1[[#This Row],[SD]]<1,"No Payment","Partial Payment"))) -> Full Payment | J56: Active | K56: 110000 | L56: =Q56+R56+U56+Table1[[#This Row],[Farmer Payment]] -> 20000 | P56: =K56-L56+M56 -> 90000 | Q56: =AI56+AV56+CK56+Table1[[#This Row],[FY 25-26]] -> 0 | R56: 20000 | S56: 357173218053 | T56: 45794 | AI56: =SUM(W56:AH56) -> 0 | AV56: =SUM(AJ56:AU56) -> 0 | CK56: =SUM(AW56:CJ56) -> 0 | CP56: 0 | CR56: 0 | CS56: 0 | CT56: 0 | CU56: 0 | CV56: 0 | CW56: 0 | CX56: 0 | CY56: 0 | CZ56: 0 | DK56: =SUM(Table1[[#This Row],[01-03 Apr]:[Mar-26]]) -> 0
C57: 10060106 | D57: PIPARPATI | E57: SONVARSHA | I57: =IF(Table1[[#This Row],[Centre Status]]="Returned","NA",IF(Table1[[#This Row],[SD]]>19000,"Full Payment",IF(Table1[[#This Row],[SD]]<1,"No Payment","Partial Payment"))) -> Partial Payment | J57: Active | K57: 110000 | L57: =Q57+R57+U57+Table1[[#This Row],[Farmer Payment]] -> 10000 | P57: =K57-L57+M57 -> 100000 | Q57: =AI57+AV57+CK57+Table1[[#This Row],[FY 25-26]] -> 0 | R57: 10000 | S57: 511165904815 | T57: 45794 | AI57: =SUM(W57:AH57) -> 0 | AV57: =SUM(AJ57:AU57) -> 0 | CK57: =SUM(AW57:CJ57) -> 0 | CP57: 0 | CR57: 0 | CS57: 0 | CT57: 0 | CU57: 0 | CV57: 0 | CW57: 0 | CX57: 0 | CY57: 0 | CZ57: 0 | DK57: =SUM(Table1[[#This Row],[01-03 Apr]:[Mar-26]]) -> 0
C58: 10090065 | D58: GOWAR NAGAR | E58: Halsi | I58: =IF(Table1[[#This Row],[Centre Status]]="Returned","NA",IF(Table1[[#This Row],[SD]]>19000,"Full Payment",IF(Table1[[#This Row],[SD]]<1,"No Payment","Partial Payment"))) -> Full Payment | J58: Active | K58: 110000 | L58: =Q58+R58+U58+Table1[[#This Row],[Farmer Payment]] -> 20861 | P58: =K58-L58+M58 -> 89139 | Q58: =AI58+AV58+CK58+Table1[[#This Row],[FY 25-26]] -> 861 | R58: 20000 | S58: 880291229135 | T58: 45762 | AI58: =SUM(W58:AH58) -> 0 | AV58: =SUM(AJ58:AU58) -> 0 | CK58: =SUM(AW58:CJ58) -> 0 | CP58: 0 | CR58: 0 | CS58: 0 | CT58: 0 | CU58: 0 | CV58: 861 | CW58: 0 | CX58: 0 | CY58: 0 | CZ58: 0 | DK58: =SUM(Table1[[#This Row],[01-03 Apr]:[Mar-26]]) -> 861
C59: 10130093 | D59: Gomukh Sherpur Narsari East | E59: Dalsinghsarai | I59: =IF(Table1[[#This Row],[Centre Status]]="Returned","NA",IF(Table1[[#This Row],[SD]]>19000,"Full Payment",IF(Table1[[#This Row],[SD]]<1,"No Payment","Partial Payment"))) -> No Payment | J59: Active | K59: 110000 | L59: =Q59+R59+U59+Table1[[#This Row],[Farmer Payment]] -> 1861 | P59: =K59-L59+M59 -> 108139 | Q59: =AI59+AV59+CK59+Table1[[#This Row],[FY 25-26]] -> 1861 | AI59: =SUM(W59:AH59) -> 0 | AV59: =SUM(AJ59:AU59) -> 0 | CK59: =SUM(AW59:CJ59) -> 0 | CM59: 0 | CP59: 0 | CQ59: 0 | CR59: 0 | CS59: 0 | CT59: 0 | CU59: 0 | CV59: 1861 | CW59: 0 | CX59: 0 | CY59: 0 | CZ59: 0 | DK59: =SUM(Table1[[#This Row],[01-03 Apr]:[Mar-26]]) -> 1861
C60: 10110151 | D60: GOMUKH MINAPUR | E60: Sahebpur Kamal | I60: =IF(Table1[[#This Row],[Centre Status]]="Returned","NA",IF(Table1[[#This Row],[SD]]>19000,"Full Payment",IF(Table1[[#This Row],[SD]]<1,"No Payment","Partial Payment"))) -> No Payment | J60: Active | K60: 110000 | L60: =Q60+R60+U60+Table1[[#This Row],[Farmer Payment]] -> 0 | P60: =K60-L60+M60 -> 110000 | Q60: =AI60+AV60+CK60+Table1[[#This Row],[FY 25-26]] -> 0 | AI60: =SUM(W60:AH60) -> 0 | AV60: =SUM(AJ60:AU60) -> 0 | CK60: =SUM(AW60:CJ60) -> 0 | CM60: 0 | CP60: 0 | CQ60: 0 | CR60: 0 | CS60: 0 | CT60: 0 | CU60: 0 | CV60: 0 | CW60: 0 | CX60: 0 | CY60: 0 | CZ60: 0 | DK60: =SUM(Table1[[#This Row],[01-03 Apr]:[Mar-26]]) -> 0
C61: 10140168 | D61: Gomukh Suraundha | E61: buxar | I61: =IF(Table1[[#This Row],[Centre Status]]="Returned","NA",IF(Table1[[#This Row],[SD]]>19000,"Full Payment",IF(Table1[[#This Row],[SD]]<1,"No Payment","Partial Payment"))) -> No Payment | J61: Active | K61: 110000 | L61: =Q61+R61+U61+Table1[[#This Row],[Farmer Payment]] -> 627 | P61: =K61-L61+M61 -> 109373 | Q61: =AI61+AV61+CK61+Table1[[#This Row],[FY 25-26]] -> 627 | AI61: =SUM(W61:AH61) -> 0 | AV61: =SUM(AJ61:AU61) -> 0 | CK61: =SUM(AW61:CJ61) -> 0 | CM61: 0 | CP61: 0 | CQ61: 0 | CR61: 0 | CS61: 0 | CT61: 0 | CU61: 0 | CV61: 627 | CW61: 0 | CX61: 0 | CY61: 0 | CZ61: 0 | DK61: =SUM(Table1[[#This Row],[01-03 Apr]:[Mar-26]]) -> 627
C62: 10140169 | D62: Gomukh Semra Nandpur | E62: Buxar | I62: =IF(Table1[[#This Row],[Centre Status]]="Returned","NA",IF(Table1[[#This Row],[SD]]>19000,"Full Payment",IF(Table1[[#This Row],[SD]]<1,"No Payment","Partial Payment"))) -> No Payment | J62: Active | K62: 110000 | L62: =Q62+R62+U62+Table1[[#This Row],[Farmer Payment]] -> 1040 | P62: =K62-L62+M62 -> 108960 | Q62: =AI62+AV62+CK62+Table1[[#This Row],[FY 25-26]] -> 1040 | AI62: =SUM(W62:AH62) -> 0 | AV62: =SUM(AJ62:AU62) -> 0 | CK62: =SUM(AW62:CJ62) -> 0 | CM62: 0 | CP62: 0 | CQ62: 0 | CR62: 0 | CS62: 0 | CT62: 0 | CU62: 0 | CV62: 1040 | CW62: 0 | CX62: 0 | CY62: 0 | CZ62: 0 | DK62: =SUM(Table1[[#This Row],[01-03 Apr]:[Mar-26]]) -> 1040
C63: 10140156 | D63: Gomukh Mashariya | E63: Buxar | I63: =IF(Table1[[#This Row],[Centre Status]]="Returned","NA",IF(Table1[[#This Row],[SD]]>19000,"Full Payment",IF(Table1[[#This Row],[SD]]<1,"No Payment","Partial Payment"))) -> No Payment | J63: Active | K63: 110000 | L63: =Q63+R63+U63+Table1[[#This Row],[Farmer Payment]] -> 3722 | P63: =K63-L63+M63 -> 106278 | Q63: =AI63+AV63+CK63+Table1[[#This Row],[FY 25-26]] -> 3722 | AI63: =SUM(W63:AH63) -> 0 | AV63: =SUM(AJ63:AU63) -> 0 | CK63: =SUM(AW63:CJ63) -> 0 | CM63: 0 | CP63: 1861 | CQ63: 0 | CR63: 0 | CS63: 0 | CT63: 0 | CU63: 0 | CV63: 1861 | CW63: 0 | CX63: 0 | CY63: 0 | CZ63: 0 | DK63: =SUM(Table1[[#This Row],[01-03 Apr]:[Mar-26]]) -> 3722
C64: 10140120 | D64: Gomukh Sikraul lakh | E64: Buxar | I64: =IF(Table1[[#This Row],[Centre Status]]="Returned","NA",IF(Table1[[#This Row],[SD]]>19000,"Full Payment",IF(Table1[[#This Row],[SD]]<1,"No Payment","Partial Payment"))) -> No Payment | J64: Active | K64: 110000 | L64: =Q64+R64+U64+Table1[[#This Row],[Farmer Payment]] -> 0 | P64: =K64-L64+M64 -> 110000 | Q64: =AI64+AV64+CK64+Table1[[#This Row],[FY 25-26]] -> 0 | AI64: =SUM(W64:AH64) -> 0 | AV64: =SUM(AJ64:AU64) -> 0 | CK64: =SUM(AW64:CJ64) -> 0 | CM64: 0 | CP64: 0 | CQ64: 0 | CR64: 0 | CS64: 0 | CT64: 0 | CU64: 0 | CV64: 0 | CW64: 0 | CX64: 0 | CY64: 0 | CZ64: 0 | DK64: =SUM(Table1[[#This Row],[01-03 Apr]:[Mar-26]]) -> 0
C65: 10140119 | D65: Gomukh Banswar | E65: Buxar | I65: =IF(Table1[[#This Row],[Centre Status]]="Returned","NA",IF(Table1[[#This Row],[SD]]>19000,"Full Payment",IF(Table1[[#This Row],[SD]]<1,"No Payment","Partial Payment"))) -> No Payment | J65: Active | K65: 110000 | L65: =Q65+R65+U65+Table1[[#This Row],[Farmer Payment]] -> 4625.5597 | P65: =K65-L65+M65 -> 105374.44 | Q65: =AI65+AV65+CK65+Table1[[#This Row],[FY 25-26]] -> 4625.5597 | AI65: =SUM(W65:AH65) -> 0 | AV65: =SUM(AJ65:AU65) -> 0 | CK65: =SUM(AW65:CJ65) -> 0 | CM65: 0 | CP65: 2727.4364 | CQ65: 0 | CR65: 0 | CS65: 0 | CT65: 0 | CU65: 0 | CV65: 1898.1232 | CW65: 0 | CX65: 0 | CY65: 0 | CZ65: 0 | DK65: =SUM(Table1[[#This Row],[01-03 Apr]:[Mar-26]]) -> 4625.5597
C66: 10120105 | D66: GOMUKH HANUMAN NAGAR | E66: Dalsingh Sarai | I66: =IF(Table1[[#This Row],[Centre Status]]="Returned","NA",IF(Table1[[#This Row],[SD]]>19000,"Full Payment",IF(Table1[[#This Row],[SD]]<1,"No Payment","Partial Payment"))) -> Partial Payment | J66: Active | K66: 110000 | L66: =Q66+R66+U66+Table1[[#This Row],[Farmer Payment]] -> 10506 | P66: =K66-L66+M66 -> 99494 | Q66: =AI66+AV66+CK66+Table1[[#This Row],[FY 25-26]] -> 506 | R66: 10000 | S66: 170034267096 | T66: 45772 | AI66: =SUM(W66:AH66) -> 0 | AV66: =SUM(AJ66:AU66) -> 0 | CK66: =SUM(AW66:CJ66) -> 0 | CM66: 0 | CP66: 0 | CQ66: 0 | CR66: 0 | CS66: 0 | CT66: 0 | CU66: 0 | CV66: 506 | CW66: 0 | CX66: 0 | CY66: 0 | CZ66: 0 | DK66: =SUM(Table1[[#This Row],[01-03 Apr]:[Mar-26]]) -> 506
C67: 10530055 | D67: GOMUKH HARPUR W-13 | E67: Kalyanpur | I67: =IF(Table1[[#This Row],[Centre Status]]="Returned","NA",IF(Table1[[#This Row],[SD]]>19000,"Full Payment",IF(Table1[[#This Row],[SD]]<1,"No Payment","Partial Payment"))) -> Full Payment | J67: Active | K67: 110000 | L67: =Q67+R67+U67+Table1[[#This Row],[Farmer Payment]] -> 23514.607 | P67: =K67-L67+M67 -> 86485.393 | Q67: =AI67+AV67+CK67+Table1[[#This Row],[FY 25-26]] -> 3514.607 | R67: 20000 | S67: 156766497886 | T67: 45772 | AI67: =SUM(W67:AH67) -> 0 | AV67: =SUM(AJ67:AU67) -> 0 | CK67: =SUM(AW67:CJ67) -> 0 | CM67: 0 | CP67: 0 | CQ67: 0 | CR67: 0 | CS67: 0 | CT67: 0 | CU67: 0 | CV67: 3514.607 | CW67: 0 | CX67: 0 | CY67: 0 | CZ67: 0 | DK67: =SUM(Table1[[#This Row],[01-03 Apr]:[Mar-26]]) -> 3514.607
C68: 10530058 | D68: Gomukh Ratwara | E68: Kalyanpur | I68: =IF(Table1[[#This Row],[Centre Status]]="Returned","NA",IF(Table1[[#This Row],[SD]]>19000,"Full Payment",IF(Table1[[#This Row],[SD]]<1,"No Payment","Partial Payment"))) -> Full Payment | J68: Active | K68: 110000 | L68: =Q68+R68+U68+Table1[[#This Row],[Farmer Payment]] -> 21861 | P68: =K68-L68+M68 -> 88139 | Q68: =AI68+AV68+CK68+Table1[[#This Row],[FY 25-26]] -> 1861 | R68: 20000 | S68: 272612128444 | T68: 45772 | AI68: =SUM(W68:AH68) -> 0 | AV68: =SUM(AJ68:AU68) -> 0 | CK68: =SUM(AW68:CJ68) -> 0 | CM68: 0 | CP68: 0 | CQ68: 0 | CR68: 0 | CS68: 0 | CT68: 0 | CU68: 0 | CV68: 1861 | CW68: 0 | CX68: 0 | CY68: 0 | CZ68: 0 | DK68: =SUM(Table1[[#This Row],[01-03 Apr]:[Mar-26]]) -> 1861
C69: 10080093 | D69: Barauni Bariyarpur | E69: Teghra | I69: =IF(Table1[[#This Row],[Centre Status]]="Returned","NA",IF(Table1[[#This Row],[SD]]>19000,"Full Payment",IF(Table1[[#This Row],[SD]]<1,"No Payment","Partial Payment"))) -> Full Payment | J69: Active | K69: 110000 | L69: =Q69+R69+U69+Table1[[#This Row],[Farmer Payment]] -> 20000 | P69: =K69-L69+M69 -> 90000 | Q69: =AI69+AV69+CK69+Table1[[#This Row],[FY 25-26]] -> 0 | R69: 20000 | T69: 45780 | AI69: =SUM(W69:AH69) -> 0 | AV69: =SUM(AJ69:AU69) -> 0 | CK69: =SUM(AW69:CJ69) -> 0 | CM69: 0 | CP69: 0 | CQ69: 0 | CR69: 0 | CS69: 0 | CT69: 0 | CU69: 0 | CV69: 0 | CW69: 0 | CX69: 0 | CY69: 0 | CZ69: 0 | DK69: =SUM(Table1[[#This Row],[01-03 Apr]:[Mar-26]]) -> 0
C70: 10080094 | D70: Kaji Rasalpur | E70: Teghra | I70: =IF(Table1[[#This Row],[Centre Status]]="Returned","NA",IF(Table1[[#This Row],[SD]]>19000,"Full Payment",IF(Table1[[#This Row],[SD]]<1,"No Payment","Partial Payment"))) -> Full Payment | J70: Active | K70: 110000 | L70: =Q70+R70+U70+Table1[[#This Row],[Farmer Payment]] -> 20000 | P70: =K70-L70+M70 -> 90000 | Q70: =AI70+AV70+CK70+Table1[[#This Row],[FY 25-26]] -> 0 | R70: 20000 | S70: 098883718517 | T70: 45779 | AI70: =SUM(W70:AH70) -> 0 | AV70: =SUM(AJ70:AU70) -> 0 | CK70: =SUM(AW70:CJ70) -> 0 | CM70: 0 | CP70: 0 | CQ70: 0 | CR70: 0 | CS70: 0 | CT70: 0 | CU70: 0 | CV70: 0 | CW70: 0 | CX70: 0 | CY70: 0 | CZ70: 0 | DK70: =SUM(Table1[[#This Row],[01-03 Apr]:[Mar-26]]) -> 0
C71: 10080095 | D71: Jaynagar | E71: Teghra | I71: =IF(Table1[[#This Row],[Centre Status]]="Returned","NA",IF(Table1[[#This Row],[SD]]>19000,"Full Payment",IF(Table1[[#This Row],[SD]]<1,"No Payment","Partial Payment"))) -> Partial Payment | J71: Active | K71: 110000 | L71: =Q71+R71+U71+Table1[[#This Row],[Farmer Payment]] -> 10000 | P71: =K71-L71+M71 -> 100000 | Q71: =AI71+AV71+CK71+Table1[[#This Row],[FY 25-26]] -> 0 | R71: 10000 | T71: 45779 | AI71: =SUM(W71:AH71) -> 0 | AV71: =SUM(AJ71:AU71) -> 0 | CK71: =SUM(AW71:CJ71) -> 0 | CM71: 0 | CP71: 0 | CQ71: 0 | CR71: 0 | CS71: 0 | CT71: 0 | CU71: 0 | CV71: 0 | CW71: 0 | CX71: 0 | CY71: 0 | CZ71: 0 | DK71: =SUM(Table1[[#This Row],[01-03 Apr]:[Mar-26]]) -> 0
C72: 10080096 | D72: Amba-2 | E72: Teghra | I72: =IF(Table1[[#This Row],[Centre Status]]="Returned","NA",IF(Table1[[#This Row],[SD]]>19000,"Full Payment",IF(Table1[[#This Row],[SD]]<1,"No Payment","Partial Payment"))) -> No Payment | J72: Active | K72: 110000 | L72: =Q72+R72+U72+Table1[[#This Row],[Farmer Payment]] -> 0 | P72: =K72-L72+M72 -> 110000 | Q72: =AI72+AV72+CK72+Table1[[#This Row],[FY 25-26]] -> 0 | AI72: =SUM(W72:AH72) -> 0 | AV72: =SUM(AJ72:AU72) -> 0 | CK72: =SUM(AW72:CJ72) -> 0 | CM72: 0 | CP72: 0 | CQ72: 0 | CR72: 0 | CS72: 0 | CT72: 0 | CU72: 0 | CV72: 0 | CW72: 0 | CX72: 0 | CY72: 0 | CZ72: 0 | DK72: =SUM(Table1[[#This Row],[01-03 Apr]:[Mar-26]]) -> 0
C73: 10140171 | D73: Gomukh Mukhiyadera | E73: Dumraon | I73: =IF(Table1[[#This Row],[Centre Status]]="Returned","NA",IF(Table1[[#This Row],[SD]]>19000,"Full Payment",IF(Table1[[#This Row],[SD]]<1,"No Payment","Partial Payment"))) -> Partial Payment | J73: Active | K73: 110000 | L73: =Q73+R73+U73+Table1[[#This Row],[Farmer Payment]] -> 11861 | P73: =K73-L73+M73 -> 98139 | Q73: =AI73+AV73+CK73+Table1[[#This Row],[FY 25-26]] -> 1861 | R73: 10000 | S73: 497838707260 | T73: 45754 | AI73: =SUM(W73:AH73) -> 0 | AV73: =SUM(AJ73:AU73) -> 0 | CF73: 0 | CG73: 0 | CH73: 0 | CI73: 0 | CJ73: 0 | CK73: =SUM(AW73:CJ73) -> 0 | CM73: 0 | CN73: 0 | CO73: 0 | CP73: 0 | CQ73: 0 | CR73: 0 | CS73: 0 | CT73: 0 | CU73: 0 | CV73: 1861 | CW73: 0 | CX73: 0 | CY73: 0 | CZ73: 0 | DK73: =SUM(Table1[[#This Row],[01-03 Apr]:[Mar-26]]) -> 1861
C74: 10140172 | D74: Gomukh Laxman Dera | E74: Dumraon | I74: =IF(Table1[[#This Row],[Centre Status]]="Returned","NA",IF(Table1[[#This Row],[SD]]>19000,"Full Payment",IF(Table1[[#This Row],[SD]]<1,"No Payment","Partial Payment"))) -> Full Payment | J74: Active | K74: 110000 | L74: =Q74+R74+U74+Table1[[#This Row],[Farmer Payment]] -> 21861 | P74: =K74-L74+M74 -> 88139 | Q74: =AI74+AV74+CK74+Table1[[#This Row],[FY 25-26]] -> 1861 | R74: 20000 | S74: 547480793069 | T74: 45765 | AI74: =SUM(W74:AH74) -> 0 | AV74: =SUM(AJ74:AU74) -> 0 | CF74: 0 | CG74: 0 | CH74: 0 | CI74: 0 | CJ74: 0 | CK74: =SUM(AW74:CJ74) -> 0 | CM74: 0 | CN74: 0 | CO74: 0 | CP74: 0 | CQ74: 0 | CR74: 0 | CS74: 0 | CT74: 0 | CU74: 0 | CV74: 1861 | CW74: 0 | CX74: 0 | CY74: 0 | CZ74: 0 | DK74: =SUM(Table1[[#This Row],[01-03 Apr]:[Mar-26]]) -> 1861
C75: 10140173 | D75: Gumukh Gayghat | E75: Dumraon | I75: =IF(Table1[[#This Row],[Centre Status]]="Returned","NA",IF(Table1[[#This Row],[SD]]>19000,"Full Payment",IF(Table1[[#This Row],[SD]]<1,"No Payment","Partial Payment"))) -> Full Payment | J75: Active | K75: 110000 | L75: =Q75+R75+U75+Table1[[#This Row],[Farmer Payment]] -> 21861 | P75: =K75-L75+M75 -> 88139 | Q75: =AI75+AV75+CK75+Table1[[#This Row],[FY 25-26]] -> 1861 | R75: 20000 | S75: 606646595853 | T75: 45765 | AI75: =SUM(W75:AH75) -> 0 | AV75: =SUM(AJ75:AU75) -> 0 | CF75: 0 | CG75: 0 | CH75: 0 | CI75: 0 | CJ75: 0 | CK75: =SUM(AW75:CJ75) -> 0 | CM75: 0 | CN75: 0 | CO75: 0 | CP75: 0 | CQ75: 0 | CR75: 0 | CS75: 0 | CT75: 0 | CU75: 0 | CV75: 1861 | CW75: 0 | CX75: 0 | CY75: 0 | CZ75: 0 | DK75: =SUM(Table1[[#This Row],[01-03 Apr]:[Mar-26]]) -> 1861
C76: 10010108 | D76: Gomukh Pirauna | E76: Majhaul(Gadhpura) | I76: =IF(Table1[[#This Row],[Centre Status]]="Returned","NA",IF(Table1[[#This Row],[SD]]>19000,"Full Payment",IF(Table1[[#This Row],[SD]]<1,"No Payment","Partial Payment"))) -> Partial Payment | J76: Active | K76: 110000 | L76: =Q76+R76+U76+Table1[[#This Row],[Farmer Payment]] -> 10822 | P76: =K76-L76+M76 -> 99178 | Q76: =AI76+AV76+CK76+Table1[[#This Row],[FY 25-26]] -> 822 | R76: 10000 | S76: 510145840868 | T76: 45758 | AI76: =SUM(W76:AH76) -> 0 | AV76: =SUM(AJ76:AU76) -> 0 | CF76: 0 | CG76: 0 | CH76: 0 | CI76: 0 | CK76: =SUM(AW76:CJ76) -> 0 | CM76: 0 | CN76: 0 | CO76: 0 | CP76: 0 | CQ76: 0 | CR76: 0 | CS76: 0 | CT76: 0 | CU76: 0 | CV76: 822 | CW76: 0 | CX76: 0 | CY76: 0 | CZ76: 0 | DK76: =SUM(Table1[[#This Row],[01-03 Apr]:[Mar-26]]) -> 822
C77: 10140174 | D77: Gomukh Shivpur | E77: Dumraon | I77: =IF(Table1[[#This Row],[Centre Status]]="Returned","NA",IF(Table1[[#This Row],[SD]]>19000,"Full Payment",IF(Table1[[#This Row],[SD]]<1,"No Payment","Partial Payment"))) -> Partial Payment | J77: Active | K77: 110000 | L77: =Q77+R77+U77+Table1[[#This Row],[Farmer Payment]] -> 10781 | P77: =K77-L77+M77 -> 99219 | Q77: =AI77+AV77+CK77+Table1[[#This Row],[FY 25-26]] -> 781 | R77: 10000 | S77: 429976796190 | T77: 45754 | AI77: =SUM(W77:AH77) -> 0 | AV77: =SUM(AJ77:AU77) -> 0 | CF77: 0 | CG77: 0 | CH77: 0 | CI77: 0 | CJ77: 0 | CK77: =SUM(AW77:CJ77) -> 0 | CM77: 0 | CN77: 0 | CO77: 0 | CP77: 0 | CQ77: 0 | CR77: 0 | CS77: 0 | CT77: 0 | CU77: 0 | CV77: 781 | CW77: 0 | CX77: 0 | CY77: 0 | CZ77: 0 | DK77: =SUM(Table1[[#This Row],[01-03 Apr]:[Mar-26]]) -> 781
C78: 10120104 | D78: Gomukh Mordiwa East | E78: Dalsingh Sarai | I78: =IF(Table1[[#This Row],[Centre Status]]="Returned","NA",IF(Table1[[#This Row],[SD]]>19000,"Full Payment",IF(Table1[[#This Row],[SD]]<1,"No Payment","Partial Payment"))) -> Partial Payment | J78: Active | K78: 110000 | L78: =Q78+R78+U78+Table1[[#This Row],[Farmer Payment]] -> 11861 | P78: =K78-L78+M78 -> 98139 | Q78: =AI78+AV78+CK78+Table1[[#This Row],[FY 25-26]] -> 1861 | R78: 10000 | S78: 576224653620 | T78: 45749 | AI78: =SUM(W78:AH78) -> 0 | AV78: =SUM(AJ78:AU78) -> 0 | CF78: 0 | CG78: 0 | CH78: 0 | CI78: 0 | CK78: =SUM(AW78:CJ78) -> 0 | CM78: 0 | CN78: 0 | CO78: 0 | CP78: 0 | CQ78: 0 | CR78: 0 | CS78: 0 | CT78: 0 | CU78: 0 | CV78: 1861 | CW78: 0 | CX78: 0 | CY78: 0 | CZ78: 0 | DK78: =SUM(Table1[[#This Row],[01-03 Apr]:[Mar-26]]) -> 1861
C79: 10130099 | D79: GOMUKH TARA | E79: Musrigharari | I79: =IF(Table1[[#This Row],[Centre Status]]="Returned","NA",IF(Table1[[#This Row],[SD]]>19000,"Full Payment",IF(Table1[[#This Row],[SD]]<1,"No Payment","Partial Payment"))) -> Partial Payment | J79: Active | K79: 110000 | L79: =Q79+R79+U79+Table1[[#This Row],[Farmer Payment]] -> 10000 | P79: =K79-L79+M79 -> 100000 | Q79: =AI79+AV79+CK79+Table1[[#This Row],[FY 25-26]] -> 0 | R79: 10000 | T79: 45749 | AI79: =SUM(W79:AH79) -> 0 | AV79: =SUM(AJ79:AU79) -> 0 | CF79: 0 | CG79: 0 | CH79: 0 | CI79: 0 | CK79: =SUM(AW79:CJ79) -> 0 | CM79: 0 | CN79: 0 | CO79: 0 | CP79: 0 | CQ79: 0 | CR79: 0 | CS79: 0 | CT79: 0 | CU79: 0 | CV79: 0 | CW79: 0 | CX79: 0 | CY79: 0 | CZ79: 0 | DK79: =SUM(Table1[[#This Row],[01-03 Apr]:[Mar-26]]) -> 0
C80: 10110140 | D80: MEGHAUNA | E80: Sahebpur Kamal | I80: =IF(Table1[[#This Row],[Centre Status]]="Returned","NA",IF(Table1[[#This Row],[SD]]>19000,"Full Payment",IF(Table1[[#This Row],[SD]]<1,"No Payment","Partial Payment"))) -> Full Payment | J80: Active | K80: 110000 | L80: =Q80+R80+U80+Table1[[#This Row],[Farmer Payment]] -> 21650 | P80: =K80-L80+M80 -> 88350 | Q80: =AI80+AV80+CK80+Table1[[#This Row],[FY 25-26]] -> 1650 | R80: 20000 | S80: 666960447023 | T80: 45754 | AI80: =SUM(W80:AH80) -> 0 | AV80: =SUM(AJ80:AU80) -> 0 | CF80: 0 | CG80: 0 | CH80: 0 | CI80: 0 | CJ80: 0 | CK80: =SUM(AW80:CJ80) -> 0 | CM80: 0 | CN80: 0 | CO80: 0 | CP80: 0 | CQ80: 0 | CR80: 0 | CS80: 0 | CT80: 0 | CU80: 0 | CV80: 1650 | CW80: 0 | CX80: 0 | CY80: 0 | CZ80: 0 | DK80: =SUM(Table1[[#This Row],[01-03 Apr]:[Mar-26]]) -> 1650
C81: 10110142 | D81: SIRSIYA | E81: Sahebpur Kamal | I81: =IF(Table1[[#This Row],[Centre Status]]="Returned","NA",IF(Table1[[#This Row],[SD]]>19000,"Full Payment",IF(Table1[[#This Row],[SD]]<1,"No Payment","Partial Payment"))) -> Full Payment | J81: Active | K81: 110000 | L81: =Q81+R81+U81+Table1[[#This Row],[Farmer Payment]] -> 22081.157 | P81: =K81-L81+M81 -> 87918.843 | Q81: =AI81+AV81+CK81+Table1[[#This Row],[FY 25-26]] -> 2081.1566 | R81: 20000 | S81: 588755727200 | T81: 45754 | AI81: =SUM(W81:AH81) -> 0 | AV81: =SUM(AJ81:AU81) -> 0 | CF81: 0 | CG81: 0 | CH81: 0 | CI81: 0 | CJ81: 0 | CK81: =SUM(AW81:CJ81) -> 0 | CM81: 0 | CN81: 0 | CO81: 0 | CP81: 0 | CQ81: 0 | CR81: 0 | CS81: 0 | CT81: 0 | CU81: 0 | CV81: 2081.1566 | CW81: 0 | CX81: 0 | CY81: 0 | CZ81: 0 | DK81: =SUM(Table1[[#This Row],[01-03 Apr]:[Mar-26]]) -> 2081.1566
C82: 10110143 | D82: AURA | E82: Sahebpur Kamal | I82: =IF(Table1[[#This Row],[Centre Status]]="Returned","NA",IF(Table1[[#This Row],[SD]]>19000,"Full Payment",IF(Table1[[#This Row],[SD]]<1,"No Payment","Partial Payment"))) -> Full Payment | J82: Active | K82: 110000 | L82: =Q82+R82+U82+Table1[[#This Row],[Farmer Payment]] -> 23206.209 | P82: =K82-L82+M82 -> 86793.791 | Q82: =AI82+AV82+CK82+Table1[[#This Row],[FY 25-26]] -> 3206.2088 | R82: 20000 | S82: 546382130281 | T82: 45754 | AI82: =SUM(W82:AH82) -> 0 | AV82: =SUM(AJ82:AU82) -> 0 | CF82: 0 | CG82: 0 | CH82: 0 | CI82: 0 | CJ82: 0 | CK82: =SUM(AW82:CJ82) -> 0 | CM82: 0 | CN82: 0 | CO82: 0 | CP82: 0 | CQ82: 0 | CR82: 0 | CS82: 0 | CT82: 0 | CU82: 0 | CV82: 3206.2088 | CW82: 0 | CX82: 0 | CY82: 0 | CZ82: 0 | DK82: =SUM(Table1[[#This Row],[01-03 Apr]:[Mar-26]]) -> 3206.2088
C83: 10110144 | D83: BEHORBA | E83: Sahebpur Kamal | I83: =IF(Table1[[#This Row],[Centre Status]]="Returned","NA",IF(Table1[[#This Row],[SD]]>19000,"Full Payment",IF(Table1[[#This Row],[SD]]<1,"No Payment","Partial Payment"))) -> Full Payment | J83: Active | K83: 110000 | L83: =Q83+R83+U83+Table1[[#This Row],[Farmer Payment]] -> 20948 | P83: =K83-L83+M83 -> 89052 | Q83: =AI83+AV83+CK83+Table1[[#This Row],[FY 25-26]] -> 948 | R83: 20000 | S83: 324939948431 | T83: 45754 | AI83: =SUM(W83:AH83) -> 0 | AV83: =SUM(AJ83:AU83) -> 0 | CF83: 0 | CG83: 0 | CH83: 0 | CI83: 0 | CJ83: 0 | CK83: =SUM(AW83:CJ83) -> 0 | CM83: 0 | CN83: 0 | CO83: 0 | CP83: 0 | CQ83: 0 | CR83: 0 | CS83: 0 | CT83: 0 | CU83: 0 | CV83: 948 | CW83: 0 | CX83: 0 | CY83: 0 | CZ83: 0 | DK83: =SUM(Table1[[#This Row],[01-03 Apr]:[Mar-26]]) -> 948
C84: 10110145 | D84: GOMUKH SONAPUR BHARAT | E84: Sahebpur Kamal | I84: =IF(Table1[[#This Row],[Centre Status]]="Returned","NA",IF(Table1[[#This Row],[SD]]>19000,"Full Payment",IF(Table1[[#This Row],[SD]]<1,"No Payment","Partial Payment"))) -> Full Payment | J84: Active | K84: 110000 | L84: =Q84+R84+U84+Table1[[#This Row],[Farmer Payment]] -> 22118.88 | P84: =K84-L84+M84 -> 87881.12 | Q84: =AI84+AV84+CK84+Table1[[#This Row],[FY 25-26]] -> 2118.88 | R84: 20000 | S84: 510128545849 | T84: 45754 | AI84: =SUM(W84:AH84) -> 0 | AV84: =SUM(AJ84:AU84) -> 0 | CF84: 0 | CG84: 0 | CH84: 0 | CI84: 0 | CJ84: 0 | CK84: =SUM(AW84:CJ84) -> 0 | CM84: 0 | CN84: 0 | CO84: 0 | CP84: 0 | CQ84: 0 | CR84: 0 | CS84: 0 | CT84: 0 | CU84: 0 | CV84: 2118.88 | CW84: 0 | CX84: 0 | CY84: 0 | CZ84: 0 | DK84: =SUM(Table1[[#This Row],[01-03 Apr]:[Mar-26]]) -> 2118.88
C85: 10110147 | D85: BARIARPUR | E85: Sahebpur Kamal | I85: =IF(Table1[[#This Row],[Centre Status]]="Returned","NA",IF(Table1[[#This Row],[SD]]>19000,"Full Payment",IF(Table1[[#This Row],[SD]]<1,"No Payment","Partial Payment"))) -> Full Payment | J85: Active | K85: 110000 | L85: =Q85+R85+U85+Table1[[#This Row],[Farmer Payment]] -> 20000 | P85: =K85-L85+M85 -> 90000 | Q85: =AI85+AV85+CK85+Table1[[#This Row],[FY 25-26]] -> 0 | R85: 20000 | S85: 510115394258 | T85: 45754 | AI85: =SUM(W85:AH85) -> 0 | AV85: =SUM(AJ85:AU85) -> 0 | CF85: 0 | CG85: 0 | CH85: 0 | CI85: 0 | CJ85: 0 | CK85: =SUM(AW85:CJ85) -> 0 | CM85: 0 | CN85: 0 | CO85: 0 | CP85: 0 | CQ85: 0 | CR85: 0 | CS85: 0 | CT85: 0 | CU85: 0 | CV85: 0 | CW85: 0 | CX85: 0 | CY85: 0 | CZ85: 0 | DK85: =SUM(Table1[[#This Row],[01-03 Apr]:[Mar-26]]) -> 0
C86: 10110146 | D86: SAIDPUR SAMASTIPUR | E86: Sahebpur Kamal | I86: =IF(Table1[[#This Row],[Centre Status]]="Returned","NA",IF(Table1[[#This Row],[SD]]>19000,"Full Payment",IF(Table1[[#This Row],[SD]]<1,"No Payment","Partial Payment"))) -> Full Payment | J86: Active | K86: 110000 | L86: =Q86+R86+U86+Table1[[#This Row],[Farmer Payment]] -> 21861 | P86: =K86-L86+M86 -> 88139 | Q86: =AI86+AV86+CK86+Table1[[#This Row],[FY 25-26]] -> 1861 | R86: 20000 | S86: 993254311858 | T86: 45754 | AI86: =SUM(W86:AH86) -> 0 | AV86: =SUM(AJ86:AU86) -> 0 | CF86: 0 | CG86: 0 | CH86: 0 | CI86: 0 | CJ86: 0 | CK86: =SUM(AW86:CJ86) -> 0 | CM86: 0 | CN86: 0 | CO86: 0 | CP86: 0 | CQ86: 0 | CR86: 0 | CS86: 0 | CT86: 0 | CU86: 0 | CV86: 1861 | CW86: 0 | CX86: 0 | CY86: 0 | CZ86: 0 | DK86: =SUM(Table1[[#This Row],[01-03 Apr]:[Mar-26]]) -> 1861
C87: 10070063 | D87: Gomukh Bandehra Purbi | E87: Parbatta | I87: =IF(Table1[[#This Row],[Centre Status]]="Returned","NA",IF(Table1[[#This Row],[SD]]>19000,"Full Payment",IF(Table1[[#This Row],[SD]]<1,"No Payment","Partial Payment"))) -> Full Payment | J87: Active | K87: 110000 | L87: =Q87+R87+U87+Table1[[#This Row],[Farmer Payment]] -> 21861 | P87: =K87-L87+M87 -> 88139 | Q87: =AI87+AV87+CK87+Table1[[#This Row],[FY 25-26]] -> 1861 | R87: 20000 | T87: 45746 | AI87: =SUM(W87:AH87) -> 0 | AV87: =SUM(AJ87:AU87) -> 0 | CF87: 0 | CG87: 0 | CH87: 0 | CI87: 0 | CJ87: 0 | CK87: =SUM(AW87:CJ87) -> 0 | CM87: 0 | CN87: 0 | CO87: 0 | CP87: 0 | CQ87: 0 | CR87: 0 | CS87: 0 | CT87: 0 | CU87: 0 | CV87: 1861 | CW87: 0 | CX87: 0 | CY87: 0 | CZ87: 0 | DK87: =SUM(Table1[[#This Row],[01-03 Apr]:[Mar-26]]) -> 1861
C88: 10070064 | D88: Gomukh Tila tol | E88: Parbatta | I88: =IF(Table1[[#This Row],[Centre Status]]="Returned","NA",IF(Table1[[#This Row],[SD]]>19000,"Full Payment",IF(Table1[[#This Row],[SD]]<1,"No Payment","Partial Payment"))) -> Full Payment | J88: Active | K88: 110000 | L88: =Q88+R88+U88+Table1[[#This Row],[Farmer Payment]] -> 21861 | P88: =K88-L88+M88 -> 88139 | Q88: =AI88+AV88+CK88+Table1[[#This Row],[FY 25-26]] -> 1861 | R88: 20000 | S88: 724283998452 | T88: 45754 | AI88: =SUM(W88:AH88) -> 0 | AV88: =SUM(AJ88:AU88) -> 0 | CF88: 0 | CG88: 0 | CH88: 0 | CI88: 0 | CJ88: 0 | CK88: =SUM(AW88:CJ88) -> 0 | CM88: 0 | CN88: 0 | CO88: 0 | CP88: 0 | CQ88: 0 | CR88: 0 | CS88: 0 | CT88: 0 | CU88: 0 | CV88: 1861 | CW88: 0 | CX88: 0 | CY88: 0 | CZ88: 0 | DK88: =SUM(Table1[[#This Row],[01-03 Apr]:[Mar-26]]) -> 1861
C89: 10110109 | D89: Morkahi | E89: Sahebpur Kamal | I89: =IF(Table1[[#This Row],[Centre Status]]="Returned","NA",IF(Table1[[#This Row],[SD]]>19000,"Full Payment",IF(Table1[[#This Row],[SD]]<1,"No Payment","Partial Payment"))) -> Partial Payment | J89: Active | K89: 110000 | L89: =Q89+R89+U89+Table1[[#This Row],[Farmer Payment]] -> 13127 | P89: =K89-L89+M89 -> 96873 | Q89: =AI89+AV89+CK89+Table1[[#This Row],[FY 25-26]] -> 3127 | R89: 10000 | S89: 502021351927 | T89: 45677 | AI89: =SUM(W89:AH89) -> 0 | AV89: =SUM(AJ89:AU89) -> 0 | BP89: 0 | BY89: 0 | BZ89: 0 | CA89: 0 | CB89: 0 | CC89: 0 | CD89: 0 | CE89: 0 | CF89: 0 | CG89: 0 | CH89: 0 | CI89: 0 | CJ89: 1861 | CK89: =SUM(AW89:CJ89) -> 1861 | CM89: 0 | CN89: 0 | CO89: 0 | CP89: 0 | CQ89: 0 | CR89: 0 | CS89: 0 | CT89: 0 | CU89: 0 | CV89: 1266 | CW89: 0 | CX89: 0 | CY89: 0 | CZ89: 0 | DK89: =SUM(Table1[[#This Row],[01-03 Apr]:[Mar-26]]) -> 1266
C90: 10110132 | D90: GOMUKH DHUSMURI BISHANPUR | E90: Sahebpur Kamal | I90: =IF(Table1[[#This Row],[Centre Status]]="Returned","NA",IF(Table1[[#This Row],[SD]]>19000,"Full Payment",IF(Table1[[#This Row],[SD]]<1,"No Payment","Partial Payment"))) -> Partial Payment | J90: Active | K90: 110000 | L90: =Q90+R90+U90+Table1[[#This Row],[Farmer Payment]] -> 10736 | P90: =K90-L90+M90 -> 99264 | Q90: =AI90+AV90+CK90+Table1[[#This Row],[FY 25-26]] -> 736 | R90: 10000 | S90: 734077193477 | T90: 45742 | AI90: =SUM(W90:AH90) -> 0 | AV90: =SUM(AJ90:AU90) -> 0 | CF90: 0 | CG90: 0 | CH90: 0 | CI90: 0 | CJ90: 0 | CK90: =SUM(AW90:CJ90) -> 0 | CM90: 0 | CN90: 0 | CO90: 0 | CP90: 0 | CQ90: 0 | CR90: 0 | CS90: 0 | CT90: 0 | CU90: 0 | CV90: 736 | CW90: 0 | CX90: 0 | CY90: 0 | CZ90: 0 | DK90: =SUM(Table1[[#This Row],[01-03 Apr]:[Mar-26]]) -> 736
C91: 10110133 | D91: GOMUKH ANANDPUR PARAS | E91: Sahebpur Kamal | I91: =IF(Table1[[#This Row],[Centre Status]]="Returned","NA",IF(Table1[[#This Row],[SD]]>19000,"Full Payment",IF(Table1[[#This Row],[SD]]<1,"No Payment","Partial Payment"))) -> Full Payment | J91: Active | K91: 110000 | L91: =Q91+R91+U91+Table1[[#This Row],[Farmer Payment]] -> 21861 | P91: =K91-L91+M91 -> 88139 | Q91: =AI91+AV91+CK91+Table1[[#This Row],[FY 25-26]] -> 1861 | R91: 20000 | S91: 435321537741 | T91: 45743 | AI91: =SUM(W91:AH91) -> 0 | AV91: =SUM(AJ91:AU91) -> 0 | CF91: 0 | CG91: 0 | CH91: 0 | CI91: 0 | CJ91: 0 | CK91: =SUM(AW91:CJ91) -> 0 | CM91: 0 | CN91: 0 | CO91: 0 | CP91: 0 | CQ91: 0 | CR91: 0 | CS91: 0 | CT91: 0 | CU91: 0 | CV91: 1861 | CW91: 0 | CX91: 0 | CY91: 0 | CZ91: 0 | DK91: =SUM(Table1[[#This Row],[01-03 Apr]:[Mar-26]]) -> 1861
C92: 10070070 | D92: Gomukh English Lagar | E92: Arariya | I92: =IF(Table1[[#This Row],[Centre Status]]="Returned","NA",IF(Table1[[#This Row],[SD]]>19000,"Full Payment",IF(Table1[[#This Row],[SD]]<1,"No Payment","Partial Payment"))) -> Partial Payment | J92: Active | K92: 110000 | L92: =Q92+R92+U92+Table1[[#This Row],[Farmer Payment]] -> 10000 | P92: =K92-L92+M92 -> 100000 | Q92: =AI92+AV92+CK92+Table1[[#This Row],[FY 25-26]] -> 0 | R92: 10000 | S92: 730267044972 | T92: 45785 | AI92: =SUM(W92:AH92) -> 0 | AV92: =SUM(AJ92:AU92) -> 0 | CK92: =SUM(AW92:CJ92) -> 0 | CR92: 0 | CT92: 0 | CU92: 0 | CV92: 0 | CW92: 0 | CX92: 0 | CY92: 0 | CZ92: 0 | DK92: =SUM(Table1[[#This Row],[01-03 Apr]:[Mar-26]]) -> 0
C93: 10070071 | D93: Gomukh Prem Nagar | E93: Arariya | I93: =IF(Table1[[#This Row],[Centre Status]]="Returned","NA",IF(Table1[[#This Row],[SD]]>19000,"Full Payment",IF(Table1[[#This Row],[SD]]<1,"No Payment","Partial Payment"))) -> Partial Payment | J93: Active | K93: 110000 | L93: =Q93+R93+U93+Table1[[#This Row],[Farmer Payment]] -> 10000 | P93: =K93-L93+M93 -> 100000 | Q93: =AI93+AV93+CK93+Table1[[#This Row],[FY 25-26]] -> 0 | R93: 10000 | S93: 408221501602 | T93: 45799 | AI93: =SUM(W93:AH93) -> 0 | AV93: =SUM(AJ93:AU93) -> 0 | CK93: =SUM(AW93:CJ93) -> 0 | CR93: 0 | CT93: 0 | CU93: 0 | CV93: 0 | CW93: 0 | CX93: 0 | CY93: 0 | CZ93: 0 | DK93: =SUM(Table1[[#This Row],[01-03 Apr]:[Mar-26]]) -> 0
C94: 10070072 | D94: Gomukh purani tola | E94: Arariya | I94: =IF(Table1[[#This Row],[Centre Status]]="Returned","NA",IF(Table1[[#This Row],[SD]]>19000,"Full Payment",IF(Table1[[#This Row],[SD]]<1,"No Payment","Partial Payment"))) -> Partial Payment | J94: Active | K94: 110000 | L94: =Q94+R94+U94+Table1[[#This Row],[Farmer Payment]] -> 10000 | P94: =K94-L94+M94 -> 100000 | Q94: =AI94+AV94+CK94+Table1[[#This Row],[FY 25-26]] -> 0 | R94: 10000 | S94: 644440853982 | T94: 45801 | AI94: =SUM(W94:AH94) -> 0 | AV94: =SUM(AJ94:AU94) -> 0 | CK94: =SUM(AW94:CJ94) -> 0 | CR94: 0 | CT94: 0 | CU94: 0 | CV94: 0 | CW94: 0 | CX94: 0 | CY94: 0 | CZ94: 0 | DK94: =SUM(Table1[[#This Row],[01-03 Apr]:[Mar-26]]) -> 0
C95: 10070073 | D95: Gomukh Bari Malia | E95: Arariya | I95: =IF(Table1[[#This Row],[Centre Status]]="Returned","NA",IF(Table1[[#This Row],[SD]]>19000,"Full Payment",IF(Table1[[#This Row],[SD]]<1,"No Payment","Partial Payment"))) -> Full Payment | J95: Active | K95: 110000 | L95: =Q95+R95+U95+Table1[[#This Row],[Farmer Payment]] -> 20000 | P95: =K95-L95+M95 -> 90000 | Q95: =AI95+AV95+CK95+Table1[[#This Row],[FY 25-26]] -> 0 | R95: 20000 | S95: 924130673113 | T95: 45812 | AI95: =SUM(W95:AH95) -> 0 | AV95: =SUM(AJ95:AU95) -> 0 | CK95: =SUM(AW95:CJ95) -> 0 | CR95: 0 | CT95: 0 | CU95: 0 | CV95: 0 | CW95: 0 | CX95: 0 | CY95: 0 | CZ95: 0 | DK95: =SUM(Table1[[#This Row],[01-03 Apr]:[Mar-26]]) -> 0
C96: 10110134 | D96: GOMUKH BISHANPUR | E96: Sahebpur Kamal | I96: =IF(Table1[[#This Row],[Centre Status]]="Returned","NA",IF(Table1[[#This Row],[SD]]>19000,"Full Payment",IF(Table1[[#This Row],[SD]]<1,"No Payment","Partial Payment"))) -> Full Payment | J96: Active | K96: 110000 | L96: =Q96+R96+U96+Table1[[#This Row],[Farmer Payment]] -> 20275 | P96: =K96-L96+M96 -> 89725 | Q96: =AI96+AV96+CK96+Table1[[#This Row],[FY 25-26]] -> 275 | R96: 20000 | S96: 761516577266 | T96: 45738 | AI96: =SUM(W96:AH96) -> 0 | AV96: =SUM(AJ96:AU96) -> 0 | CF96: 0 | CG96: 0 | CH96: 0 | CI96: 0 | CJ96: 0 | CK96: =SUM(AW96:CJ96) -> 0 | CM96: 0 | CN96: 0 | CO96: 0 | CP96: 0 | CQ96: 0 | CR96: 0 | CS96: 0 | CT96: 0 | CU96: 0 | CV96: 275 | CW96: 0 | CX96: 0 | CY96: 0 | CZ96: 0 | DK96: =SUM(Table1[[#This Row],[01-03 Apr]:[Mar-26]]) -> 275
C97: 10110135 | D97: GOMUKH BISHANPUR 2 | E97: Sahebpur Kamal | I97: =IF(Table1[[#This Row],[Centre Status]]="Returned","NA",IF(Table1[[#This Row],[SD]]>19000,"Full Payment",IF(Table1[[#This Row],[SD]]<1,"No Payment","Partial Payment"))) -> Full Payment | J97: Active | K97: 110000 | L97: =Q97+R97+U97+Table1[[#This Row],[Farmer Payment]] -> 21861 | P97: =K97-L97+M97 -> 88139 | Q97: =AI97+AV97+CK97+Table1[[#This Row],[FY 25-26]] -> 1861 | R97: 20000 | S97: 520575206741 | T97: 45744 | AI97: =SUM(W97:AH97) -> 0 | AV97: =SUM(AJ97:AU97) -> 0 | CF97: 0 | CG97: 0 | CH97: 0 | CI97: 0 | CJ97: 0 | CK97: =SUM(AW97:CJ97) -> 0 | CM97: 0 | CN97: 0 | CO97: 0 | CP97: 0 | CQ97: 0 | CR97: 0 | CS97: 0 | CT97: 0 | CU97: 0 | CV97: 1861 | CW97: 0 | CX97: 0 | CY97: 0 | CZ97: 0 | DK97: =SUM(Table1[[#This Row],[01-03 Apr]:[Mar-26]]) -> 1861
C98: 10140163 | D98: Gomukh Ramgardh Dera | E98: Dumraon | I98: =IF(Table1[[#This Row],[Centre Status]]="Returned","NA",IF(Table1[[#This Row],[SD]]>19000,"Full Payment",IF(Table1[[#This Row],[SD]]<1,"No Payment","Partial Payment"))) -> Partial Payment | J98: Active | K98: 110000 | L98: =Q98+R98+U98+Table1[[#This Row],[Farmer Payment]] -> 10341 | M98: 10000 | N98: 45824 | O98: Dhirendra Kumar Sharma | P98: =K98-L98+M98 -> 109659 | Q98: =AI98+AV98+CK98+Table1[[#This Row],[FY 25-26]] -> 341 | R98: 10000 | S98: 143421012154 | T98: 45735 | AI98: =SUM(W98:AH98) -> 0 | AV98: =SUM(AJ98:AU98) -> 0 | CF98: 0 | CG98: 0 | CH98: 0 | CI98: 0 | CJ98: 341 | CK98: =SUM(AW98:CJ98) -> 341 | CM98: 0 | CN98: 0 | CO98: 0 | CP98: 0 | CQ98: 0 | CR98: 0 | CS98: 0 | CT98: 0 | CU98: 0 | CV98: 0 | CW98: 0 | CX98: 0 | CY98: 0 | CZ98: 0 | DK98: =SUM(Table1[[#This Row],[01-03 Apr]:[Mar-26]]) -> 0
C99: 10140164 | D99: Gomukh Bharkhar | E99: Dumraon | I99: =IF(Table1[[#This Row],[Centre Status]]="Returned","NA",IF(Table1[[#This Row],[SD]]>19000,"Full Payment",IF(Table1[[#This Row],[SD]]<1,"No Payment","Partial Payment"))) -> Partial Payment | J99: Active | K99: 110000 | L99: =Q99+R99+U99+Table1[[#This Row],[Farmer Payment]] -> 12504 | M99: 10000 | N99: 45824 | O99: Dhirendra Kumar Sharma | P99: =K99-L99+M99 -> 107496 | Q99: =AI99+AV99+CK99+Table1[[#This Row],[FY 25-26]] -> 2504 | R99: 10000 | S99: 220138468722 | T99: 45735 | AI99: =SUM(W99:AH99) -> 0 | AV99: =SUM(AJ99:AU99) -> 0 | CF99: 0 | CG99: 0 | CH99: 0 | CI99: 0 | CJ99: 643 | CK99: =SUM(AW99:CJ99) -> 643 | CM99: 0 | CN99: 0 | CO99: 0 | CP99: 0 | CQ99: 0 | CR99: 0 | CS99: 0 | CT99: 0 | CU99: 0 | CV99: 1861 | CW99: 0 | CX99: 0 | CY99: 0 | CZ99: 0 | DK99: =SUM(Table1[[#This Row],[01-03 Apr]:[Mar-26]]) -> 1861
C100: 10070062 | D100: Gomukh Gogri | E100: Arariya | I100: =IF(Table1[[#This Row],[Centre Status]]="Returned","NA",IF(Table1[[#This Row],[SD]]>19000,"Full Payment",IF(Table1[[#This Row],[SD]]<1,"No Payment","Partial Payment"))) -> Partial Payment | J100: Active | K100: 110000 | L100: =Q100+R100+U100+Table1[[#This Row],[Farmer Payment]] -> 11869 | P100: =K100-L100+M100 -> 98131 | Q100: =AI100+AV100+CK100+Table1[[#This Row],[FY 25-26]] -> 1869 | R100: 10000 | S100: 991160574841 | T100: 45695 | AI100: =SUM(W100:AH100) -> 0 | AV100: =SUM(AJ100:AU100) -> 0 | CF100: 0 | CG100: 0 | CH100: 0 | CI100: 0 | CJ100: 8 | CK100: =SUM(AW100:CJ100) -> 8 | CM100: 0 | CN100: 0 | CO100: 0 | CP100: 0 | CQ100: 0 | CR100: 0 | CS100: 0 | CT100: 0 | CU100: 0 | CV100: 1861 | CW100: 0 | CX100: 0 | CY100: 0 | CZ100: 0 | DK100: =SUM(Table1[[#This Row],[01-03 Apr]:[Mar-26]]) -> 1861
...

Sheet Sheet1
N1: Comm Down Paymnet
B2: MPG Code New | C2: MPG Name | D2: BMC | E2: Assets Value | F2: Total Deduction | G2: Amount Returned | H2: Returned Date | I2: Benificery Name | J2: Recoverable Value | K2: EMI | L2: SD | N2: Apr | O2: May | P2: Jun | Q2: Jul | R2: Aug | S2: Sep | T2: Oct | U2: Nov | V2: Dec | W2: Jan | X2: Feb | Y2: Mar | Z2: Apr | AA2: Total Down Payment | AB2: Total Down Payment | AD2: Due | AE2: Pending Payment for Payment
B3: 0 | C3: #N/A | D3: Halsi | E3: 64000 | F3: 1567 | J3: 62433 | K3: 1567 | N3: 0 | O3: 0 | P3: 0 | V3: 0 | W3: 0 | AA3: =SUM(L3:W3) -> 0 | AC3: 20000 | AD3: =AC3-AA3 -> 20000
B4: 0 | C4: #N/A | D4: Halsi | E4: 64000 | F4: 5896.4322 | J4: 58103.568 | K4: 5896.4322 | N4: 0 | O4: 0 | P4: 0 | V4: 0 | W4: 0 | AA4: =SUM(L4:W4) -> 0 | AC4: 20000 | AD4: =AC4-AA4 -> 20000
B5: 10530070 | C5: GOMUKH PARAN 2 | D5: Kalyanpur | E5: 110000 | F5: 0 | J5: 110000 | K5: 0 | L5: 14000 | N5: 0 | O5: 0 | P5: 0 | Q5: 3291 | R5: 2709 | V5: 0 | W5: 0 | AA5: =SUM(L5:W5) -> 20000 | AC5: 20000 | AD5: =AC5-AA5 -> 0
B6: 10530071 | C6: GOMUKH KHARAGPUR | D6: Kalyanpur | E6: 110000 | F6: 0 | J6: 110000 | K6: 0 | N6: 0 | O6: 0 | P6: 0 | V6: 0 | W6: 0 | AA6: =SUM(L6:W6) -> 0 | AC6: 20000 | AD6: =AC6-AA6 -> 20000
B7: 10120108 | C7: GOMUKH MANIKA EAST | D7: dalsingsarai | E7: 110000 | F7: 0 | J7: 110000 | K7: 0 | L7: 10000 | N7: 0 | O7: 0 | P7: 0 | Q7: 67 | R7: 1798 | V7: 0 | W7: 72 | X7: 2377 | AA7: =SUM(L7:X7) -> 14314 | AC7: 20000 | AD7: =AC7-AA7 -> 5686
B8: 10530067 | C8: GOMUKH BANDRA W-6 | D8: Kalyanpur | E8: 110000 | F8: 0 | J8: 110000 | K8: 0 | N8: 0 | O8: 0 | P8: 0 | V8: 0 | W8: 0 | AA8: =SUM(L8:W8) -> 0 | AC8: 20000 | AD8: =AC8-AA8 -> 20000
B9: 10530074 | C9: GOMUKH BALAHA W-9 | D9: Kalyanpur | E9: 110000 | F9: 10000 | J9: 100000 | K9: 0 | L9: 10000 | N9: 0 | O9: 0 | P9: 0 | Q9: 1954 | R9: 2945 | T9: 1685 | V9: 0 | W9: 3416 | AA9: =SUM(L9:W9) -> 20000 | AC9: 20000 | AD9: =AC9-AA9 -> 0
B10: 10140183 | C10: Gomukh Uttardahan | D10: Dumraon | E10: 110000 | F10: 10000 | J10: 100000 | K10: 0 | L10: 10000 | N10: 0 | O10: 0 | P10: 0 | Q10: 4387 | R10: 7445 | V10: 0 | W10: 0 | AA10: =SUM(L10:W10) -> 21832 | AC10: 20000 | AD10: =AC10-AA10 -> -1832
B11: 10140182 | C11: Gomukh Pandeypur | D11: Dumraon | E11: 110000 | F11: 8000 | J11: 102000 | K11: 0 | L11: 8000 | N11: 0 | O11: 0 | P11: 0 | Q11: 2087 | R11: 2161 | V11: 0 | W11: 0 | AA11: =SUM(L11:W11) -> 12248 | AC11: 20000 | AD11: =AC11-AA11 -> 7752
B12: 10140178 | C12: Gomukh Tiyar | D12: Dumraon | E12: 110000 | F12: 10908 | J12: 99092 | K12: 908 | L12: 10000 | N12: 0 | O12: 0 | P12: 0 | Q12: 530 | V12: 0 | W12: 0 | AA12: =SUM(L12:W12) -> 10530 | AC12: 20000 | AD12: =AC12-AA12 -> 9470
B13: 10140179 | C13: Gomukh Rajpur | D13: Dumraon | E13: 110000 | F13: 10476 | J13: 99524 | K13: 476 | L13: 10000 | N13: 0 | O13: 0 | P13: 3407 | Q13: 3357 | R13: 2906 | V13: 0 | W13: 0 | AA13: =SUM(L13:W13) -> 19670 | AC13: 20000 | AD13: =AC13-AA13 -> 330
B14: 10140180 | C14: Gomukh Gangauli Dubha | D14: Dumraon | E14: 110000 | F14: 10000 | J14: 100000 | K14: 0 | L14: 10000 | N14: 0 | O14: 0 | P14: 0 | Q14: 1475 | R14: 2100 | T14: 539 | V14: 1693 | W14: 0 | AA14: =SUM(L14:W14) -> 15807 | AC14: 20000 | AD14: =AC14-AA14 -> 4193
B15: 10080098 | C15: Rani Panchwati | D15: Majhaul(Gadhpura) | E15: 110000 | F15: 10000 | J15: 100000 | K15: 0 | L15: 10000 | N15: 0 | O15: 0 | P15: 1086 | Q15: 4643 | R15: 1868 | V15: 0 | W15: 0 | AA15: =SUM(L15:W15) -> 17597 | AC15: 20000 | AD15: =AC15-AA15 -> 2403
B16: 10140177 | C16: Gomukh Giridhar Baraw | D16: Dumraon | E16: 110000 | F16: 10076 | J16: 99924 | K16: 76 | L16: 10000 | N16: 0 | O16: 0 | P16: 0 | V16: 0 | W16: 0 | AA16: =SUM(L16:W16) -> 10000 | AC16: 20000 | AD16: =AC16-AA16 -> 10000
B17: 10060109 | C17: PACHRUKHI | D17: sonvarsha | E17: 110000 | F17: 10000 | J17: 100000 | K17: 0 | L17: 10000 | N17: 0 | O17: 0 | P17: 0 | Q17: 2161 | R17: 5130 | S17: 0 | T17: 2707 | V17: 0 | W17: 0 | AA17: =SUM(L17:W17) -> 19998 | AC17: 20000 | AD17: =AC17-AA17 -> 2
B18: 10060110 | C18: ORABAGICHA | D18: sonvarsha | E18: 110000 | F18: 10000 | J18: 100000 | K18: 0 | L18: 10000 | N18: 0 | O18: 0 | P18: 0 | Q18: 5736 | R18: 3038 | V18: 0 | W18: 0 | AA18: =SUM(L18:W18) -> 18774 | AC18: 20000 | AD18: =AC18-AA18 -> 1226
B19: 10030072 | C19: HARLACHAK | D19: Asarganj | E19: 110000 | F19: 0 | J19: 110000 | K19: 0 | N19: 0 | O19: 0 | P19: 0 | Q19: 2624 | R19: 2417 | V19: 0 | W19: 0 | AA19: =SUM(L19:W19) -> 5041 | AC19: 20000 | AD19: =AC19-AA19 -> 14959
B20: 10030073 | C20: KHIRDIH | D20: Asarganj | E20: 110000 | F20: 0 | J20: 110000 | K20: 0 | N20: 0 | O20: 0 | P20: 0 | Q20: 599 | R20: 2413 | V20: 0 | W20: 0 | AA20: =SUM(L20:W20) -> 3012 | AC20: 20000 | AD20: =AC20-AA20 -> 16988
B21: 10060111 | C21: KHAJURIYA | D21: sonvarsha | E21: 110000 | F21: 15000 | J21: 95000 | K21: 0 | L21: 15000 | N21: 0 | O21: 0 | P21: 0 | Q21: 5142 | V21: 0 | W21: 0 | AA21: =SUM(L21:W21) -> 20142 | AC21: 20000 | AD21: =AC21-AA21 -> -142 | AE21: 45931
B22: 10110103 | C22: GOMUKH KAMATHAN | D22: Sahebpur Kamal | E22: 110000 | F22: 5000 | J22: 105000 | K22: 0 | L22: 5000 | N22: 0 | O22: 0 | P22: 0 | V22: 0 | W22: 0 | AA22: =SUM(L22:W22) -> 5000 | AC22: 20000 | AD22: =AC22-AA22 -> 15000
B23: 10140153 | C23: Gomukh Bramhpur | D23: Dumraon | E23: 110000 | F23: 15583 | J23: 94417 | K23: 5583 | L23: 10000 | N23: 650 | O23: 0 | P23: 1536 | Q23: 605 | V23: 852 | W23: 1390 | AA23: =SUM(L23:W23) -> 15033 | AC23: 20000 | AD23: =AC23-AA23 -> 4967
B24: 10130098 | C24: Gomukh Gaopur Bhagwatpur | D24: Musrigharari | E24: 110000 | F24: 1861 | J24: 108139 | K24: 1861 | L24: 10000 | N24: 1924 | O24: 1203 | P24: 3519 | Q24: 3304 | R24: 3258 | V24: 0 | W24: 0 | AA24: =SUM(L24:W24) -> 23208 | AC24: 20000 | AD24: =AC24-AA24 -> -3208
B25: 10120107 | C25: Gomukh Ramaiya | D25: Dalsingh Sarai | E25: 110000 | F25: 282 | J25: 109718 | K25: 13052 | L25: 10000 | N25: 0 | O25: 0 | P25: 1685 | Q25: 2146 | R25: 2771 | T25: 2573 | U25: 825 | V25: 0 | W25: 0 | AA25: =SUM(L25:W25) -> 20000 | AC25: 20000 | AD25: =AC25-AA25 -> 0
B26: 10130100 | C26: Gomukh Rajwara | D26: Musrigharari | E26: 110000 | F26: 0 | J26: 110000 | K26: 0 | N26: 0 | O26: 0 | P26: 0 | Q26: 543 | R26: 1390 | V26: 0 | W26: 110 | AA26: =SUM(L26:W26) -> 2043 | AC26: 20000 | AD26: =AC26-AA26 -> 17957
B27: 10130102 | C27: GOMUKH NIKASPUR | D27: Musrigharari | E27: 110000 | F27: 10000 | J27: 100000 | K27: 0 | L27: 10000 | N27: 0 | O27: 0 | P27: 0 | Q27: 1064 | R27: 2903 | V27: 2182 | W27: 3407 | AA27: =SUM(L27:W27) -> 19556 | AC27: 20000 | AD27: =AC27-AA27 -> 444
B28: 10530062 | C28: Gomukh Malinagar East | D28: Kalyanpur | E28: 110000 | F28: 195 | J28: 109805 | K28: 0 | N28: 0 | O28: 0 | P28: 0 | V28: 0 | W28: 0 | AA28: =SUM(L28:W28) -> 0 | AC28: 20000 | AD28: =AC28-AA28 -> 20000
B29: 10120098 | C29: GOMUKH JALALPUR | D29: Dalsinghsarai | E29: 64000 | F29: 11861 | J29: 52139 | K29: 1861 | L29: 10000 | N29: 2639 | O29: 2460 | P29: 0 | Q29: 79 | V29: 0 | W29: 0 | AA29: =SUM(L29:W29) -> 15178 | AC29: 20000 | AD29: =AC29-AA29 -> 4822
B30: 10130095 | C30: Gomukh Saidpur | D30: Dalsinghsarai | E30: 110000 | F30: 1861 | J30: 108139 | K30: 1861 | N30: 2380 | O30: 581 | P30: 0 | V30: 0 | W30: 0 | AA30: =SUM(L30:W30) -> 2961 | AC30: 20000 | AD30: =AC30-AA30 -> 17039
B31: 10060106 | C31: PIPARPATI | D31: SONVARSHA | E31: 110000 | F31: 10000 | J31: 100000 | K31: 0 | L31: 10000 | N31: 0 | O31: 0 | P31: 0 | U31: 355 | V31: 2941 | W31: 929 | AA31: =SUM(L31:W31) -> 14225 | AC31: 20000 | AD31: =AC31-AA31 -> 5775
B32: 10130093 | C32: Gomukh Sherpur Narsari East | D32: Dalsinghsarai | E32: 110000 | F32: 1861 | J32: 108139 | K32: 1861 | N32: 3678 | O32: 805 | P32: 170 | Q32: 1579 | R32: 50 | U32: 322 | V32: 1187 | W32: 854 | AA32: =SUM(L32:W32) -> 8645 | AC32: 20000 | AD32: =AC32-AA32 -> 11355
B33: 10110151 | C33: GOMUKH MINAPUR | D33: Sahebpur Kamal | E33: 110000 | F33: 0 | J33: 110000 | K33: 0 | N33: 0 | O33: 0 | P33: 0 | V33: 0 | W33: 0 | AA33: =SUM(L33:W33) -> 0 | AC33: 20000 | AD33: =AC33-AA33 -> 20000
B34: 10140168 | C34: Gomukh Suraundha | D34: buxar | E34: 110000 | F34: 627 | J34: 109373 | K34: 627 | N34: 625 | O34: 0 | P34: 0 | V34: 0 | W34: 0 | AA34: =SUM(L34:W34) -> 625 | AC34: 20000 | AD34: =AC34-AA34 -> 19375
B35: 10140169 | C35: Gomukh Semra Nandpur | D35: Buxar | E35: 110000 | F35: 1040 | J35: 108960 | K35: 1040 | N35: 4340 | O35: 0 | P35: 0 | R35: 1113 | V35: 0 | W35: 0 | AA35: =SUM(L35:W35) -> 5453 | AC35: 20000 | AD35: =AC35-AA35 -> 14547
B36: 10140156 | C36: Gomukh Mashariya | D36: Buxar | E36: 110000 | F36: 3722 | J36: 106278 | K36: 3722 | N36: 3583 | O36: 3409 | P36: 8105 | Q36: 4903 | R36: 0 | V36: 0 | W36: 0 | AA36: =SUM(L36:W36) -> 20000 | AC36: 20000 | AD36: =AC36-AA36 -> 0
B37: 10140120 | C37: Gomukh Sikraul lakh | D37: Buxar | E37: 110000 | F37: 0 | J37: 110000 | K37: 0 | N37: 0 | O37: 0 | P37: 0 | V37: 0 | W37: 0 | AA37: =SUM(L37:W37) -> 0 | AC37: 20000 | AD37: =AC37-AA37 -> 20000
B38: 10140119 | C38: Gomukh Banswar | D38: Buxar | E38: 110000 | F38: 4625.5597 | J38: 105374.44 | K38: 4625.5597 | N38: 0 | O38: 0 | P38: 0 | V38: 0 | W38: 0 | AA38: =SUM(L38:W38) -> 0 | AC38: 20000 | AD38: =AC38-AA38 -> 20000
B39: 10120105 | C39: GOMUKH HANUMAN NAGAR | D39: Dalsingh Sarai | E39: 110000 | F39: 10506 | J39: 99494 | K39: 506 | L39: 10000 | N39: 0 | O39: 0 | P39: 0 | V39: 0 | W39: 0 | AA39: =SUM(L39:W39) -> 10000 | AC39: 20000 | AD39: =AC39-AA39 -> 10000
B40: 10080095 | C40: Jaynagar | D40: Teghra | E40: 110000 | F40: 10000 | J40: 100000 | K40: 0 | L40: 10000 | N40: 0 | O40: 0 | P40: 0 | Q40: 869 | R40: 1477 | V40: 0 | W40: 0 | AA40: =SUM(L40:W40) -> 12346 | AC40: 20000 | AD40: =AC40-AA40 -> 7654
B41: 10080096 | C41: Amba-2 | D41: Teghra | E41: 110000 | F41: 0 | J41: 110000 | K41: 0 | N41: 0 | O41: 0 | P41: 0 | Q41: 943 | R41: 160 | V41: 0 | W41: 0 | AA41: =SUM(L41:W41) -> 1103 | AC41: 20000 | AD41: =AC41-AA41 -> 18897
B42: 10140171 | C42: Gomukh Mukhiyadera | D42: Dumraon | E42: 110000 | F42: 11861 | J42: 98139 | K42: 1861 | L42: 10000 | N42: 59 | O42: 2191 | P42: 5348 | Q42: 705 | V42: 848 | W42: 849 | AA42: =SUM(L42:W42) -> 20000 | AC42: 20000 | AD42: =AC42-AA42 -> 0 | AF42: =1789-940 -> 849
B43: 10010108 | C43: Gomukh Pirauna | D43: Majhaul(Gadhpura) | E43: 110000 | F43: 10822 | J43: 99178 | K43: 822 | L43: 10000 | N43: 24 | O43: 0 | P43: 173 | V43: 0 | W43: 0 | AA43: =SUM(L43:W43) -> 10197 | AC43: 20000 | AD43: =AC43-AA43 -> 9803
B44: 10140174 | C44: Gomukh Shivpur | D44: Dumraon | E44: 110000 | F44: 10781 | J44: 99219 | K44: 781 | L44: 10000 | N44: 33 | O44: 0 | P44: 1119 | Q44: 2932 | V44: 0 | W44: 0 | AA44: =SUM(L44:W44) -> 14084 | AC44: 20000 | AD44: =AC44-AA44 -> 5916
B45: 10120104 | C45: Gomukh Mordiwa East | D45: Dalsingh Sarai | E45: 110000 | F45: 11861 | J45: 98139 | K45: 1861 | L45: 10000 | N45: 0 | O45: 3780 | P45: 19306 | V45: 0 | W45: 0 | AA45: =SUM(L45:W45) -> 33086 | AC45: 20000 | AD45: =AC45-AA45 -> -13086
B46: 10130099 | C46: GOMUKH TARA | D46: Musrigharari | E46: 110000 | F46: 10000 | J46: 100000 | K46: 0 | L46: 10000 | N46: 0 | O46: 0 | P46: 0 | V46: 0 | W46: 0 | AA46: =SUM(L46:W46) -> 10000 | AC46: 20000 | AD46: =AC46-AA46 -> 10000
B47: 10110109 | C47: Morkahi | D47: Sahebpur Kamal | E47: 110000 | F47: 13127 | J47: 96873 | K47: 3127 | L47: 10000 | N47: 4078 | O47: 0 | P47: 683 | V47: 0 | W47: 0 | AA47: =SUM(L47:W47) -> 14761 | AC47: 20000 | AD47: =AC47-AA47 -> 5239
B48: 10110132 | C48: GOMUKH DHUSMURI BISHANPUR | D48: Sahebpur Kamal | E48: 110000 | F48: 10736 | J48: 99264 | K48: 736 | L48: 10000 | N48: 142 | O48: 0 | P48: 366 | V48: 0 | W48: 0 | AA48: =SUM(L48:W48) -> 10508 | AC48: 20000 | AD48: =AC48-AA48 -> 9492
B49: 10070070 | C49: Gomukh English Lagar | D49: Arariya | E49: 110000 | F49: 10000 | J49: 100000 | K49: 0 | L49: 10000 | N49: 0 | O49: 0 | P49: 0 | V49: 0 | W49: 0 | AA49: =SUM(L49:W49) -> 10000 | AC49: 20000 | AD49: =AC49-AA49 -> 10000
B50: 10070071 | C50: Gomukh Prem Nagar | D50: Arariya | E50: 110000 | F50: 10000 | J50: 100000 | K50: 0 | L50: 10000 | N50: 0 | O50: 0 | P50: 0 | V50: 0 | W50: 0 | AA50: =SUM(L50:W50) -> 10000 | AC50: 20000 | AD50: =AC50-AA50 -> 10000
B51: 10070072 | C51: Gomukh purani tola | D51: Arariya | E51: 110000 | F51: 10000 | J51: 100000 | K51: 0 | L51: 10000 | N51: 0 | O51: 0 | P51: 0 | Q51: 248 | R51: 1106 | V51: 0 | W51: 0 | AA51: =SUM(L51:W51) -> 11354 | AC51: 20000 | AD51: =AC51-AA51 -> 8646
B52: 10140163 | C52: Gomukh Ramgardh Dera | D52: Dumraon | E52: 110000 | F52: 10341 | G52: 10000 | H52: 45824 | I52: Dhirendra Kumar Sharma | J52: 109659 | K52: 341 | L52: 10000 | N52: 892 | O52: 0 | P52: 0 | V52: 0 | W52: 0 | AA52: =SUM(L52:W52) -> 10892 | AC52: 20000 | AD52: =AC52-AA52 -> 9108
B53: 10140164 | C53: Gomukh Bharkhar | D53: Dumraon | E53: 110000 | F53: 12504 | G53: 10000 | H53: 45824 | I53: Dhirendra Kumar Sharma | J53: 107496 | K53: 2504 | L53: 10000 | N53: 7628 | O53: 500 | P53: 0 | V53: 0 | W53: 0 | AA53: =SUM(L53:W53) -> 18128 | AC53: 20000 | AD53: =AC53-AA53 -> 1872
B54: 10070062 | C54: Gomukh Gogri | D54: Arariya | E54: 110000 | F54: 11869 | J54: 98131 | K54: 1869 | L54: 10000 | N54: 2476 | O54: 34 | P54: 782 | V54: 0 | W54: 0 | AA54: =SUM(L54:W54) -> 13292 | AC54: 20000 | AD54: =AC54-AA54 -> 6708
B55: 10110129 | C55: GOMUKH D SANJHAUTI | D55: Sahebpur Kamal | E55: 110000 | F55: 10000 | J55: 100000 | K55: 0 | L55: 10000 | N55: 0 | O55: 0 | P55: 0 | Q55: 5459 | R55: 6730 | T55: 0 | U55: 0 | V55: 0 | W55: 0 | AA55: =SUM(L55:W55) -> 22189 | AC55: 20000 | AD55: =AC55-AA55 -> -2189
B56: 10110130 | C56: GOMUKH KASAHA | D56: Sahebpur Kamal | E56: 110000 | F56: 5000 | J56: 105000 | K56: 0 | L56: 5000 | N56: 0 | O56: 0 | P56: 0 | Q56: 63 | V56: 0 | W56: 0 | AA56: =SUM(L56:W56) -> 5063 | AC56: 20000 | AD56: =AC56-AA56 -> 14937
B57: 10060103 | C57: LADHAUNA | D57: SONVARSHA | E57: 110000 | F57: 11482 | J57: 98518 | K57: 1482 | L57: 10000 | N57: 944 | O57: 0 | P57: 0 | V57: 0 | W57: 0 | AA57: =SUM(L57:W57) -> 10944 | AC57: 20000 | AD57: =AC57-AA57 -> 9056
B58: 10110131 | C58: GOMUKH KAMALPUR | D58: Sahebpur Kamal | E58: 110000 | F58: 11861 | J58: 98139 | K58: 1861 | L58: 10000 | N58: 1219 | O58: 46 | P58: 1297 | V58: 0 | W58: 0 | AA58: =SUM(L58:W58) -> 12562 | AC58: 20000 | AD58: =AC58-AA58 -> 7438
B59: 10140165 | C59: Gomukh Rampur | D59: Dumraon | E59: 110000 | F59: 10061 | G59: 10000 | H59: 45824 | I59: Mina Devi | J59: 109939 | K59: 61 | L59: 10000 | N59: 354 | O59: 0 | P59: 0 | V59: 0 | W59: 0 | AA59: =SUM(L59:W59) -> 10354 | AC59: 20000 | AD59: =AC59-AA59 -> 9646
B60: 10480031 | C60: Gomukh Borba Naya tola | D60: Pakra | E60: 110000 | F60: 5035 | J60: 104965 | K60: 35 | L60: 5000 | N60: 30 | O60: 0 | P60: 0 | V60: 0 | W60: 0 | AA60: =SUM(L60:W60) -> 5030 | AC60: 20000 | AD60: =AC60-AA60 -> 14970
B61: 10140166 | C61: Gomukh KritSagar | E61: 110000 | F61: 12142 | J61: 97858 | K61: 2142 | L61: 10000 | N61: 3059 | O61: 626 | P61: 0 | V61: 0 | W61: 0 | AA61: =SUM(L61:W61) -> 13685 | AC61: 20000 | AD61: =AC61-AA61 -> 6315
B62: 10010105 | C62: Gomukh Kharaiya Sultanpur | E62: 110000 | F62: 10010 | J62: 99990 | K62: 10 | L62: 10000 | N62: 53 | O62: 0 | P62: 0 | V62: 0 | W62: 0 | AA62: =SUM(L62:W62) -> 10053 | AC62: 20000 | AD62: =AC62-AA62 -> 9947
B63: 10010102 | C63: Gomukh Khanjapur Bangali Tola | D63: Manjhaul | E63: 110000 | F63: 11905 | J63: 98095 | K63: 1905 | L63: 10000 | N63: 1398 | O63: 242 | P63: 0 | Q63: 1038 | R63: 1232 | V63: 0 | W63: 0 | AA63: =SUM(L63:W63) -> 13910 | AC63: 20000 | AD63: =AC63-AA63 -> 6090
B64: 10120101 | C64: Gomukh Chhatauna East | D64: Dalsingh Sarai | E64: 110000 | F64: 11925 | J64: 98075 | K64: 1925 | L64: 10000 | N64: 1041 | O64: 0 | P64: 0 | V64: 0 | W64: 0 | AA64: =SUM(L64:W64) -> 11041 | AC64: 20000 | AD64: =AC64-AA64 -> 8959
B65: 10060098 | C65: RAMDEV TOLA | D65: SONVARSHA | E65: 110000 | F65: 11861 | J65: 98139 | K65: 1861 | L65: 10000 | N65: 0 | O65: 94 | P65: 3598 | Q65: 0 | V65: 0 | W65: 0 | AA65: =SUM(L65:W65) -> 13692 | AC65: 20000 | AD65: =AC65-AA65 -> 6308
B66: 10060100 | C66: KHAIRA | D66: SONVARSHA | E66: 110000 | F66: 17020.462 | J66: 92979.538 | K66: 2020.4618 | L66: 15000 | N66: 680 | O66: 4201 | P66: 119 | V66: 0 | W66: 0 | AA66: =SUM(L66:W66) -> 20000 | AC66: 20000 | AD66: =AC66-AA66 -> 0
B67: 10060093 | C67: CHANNAYA | D67: Sonvarsa | E67: 110000 | F67: 11861 | J67: 98139 | K67: 1861 | L67: 10000 | N67: 1228 | O67: 0 | P67: 0 | V67: 0 | W67: 0 | AA67: =SUM(L67:W67) -> 11228 | AC67: 20000 | AD67: =AC67-AA67 -> 8772
B68: 10110128 | C68: GOMUKH MANIAPPA | D68: Sahebpur Kamal | E68: 110000 | F68: 11896 | J68: 98104 | K68: 1896 | L68: 10000 | N68: 1587 | O68: 1023 | P68: 1040 | V68: 540 | W68: 2925 | AA68: =SUM(L68:W68) -> 17115 | AC68: 20000 | AD68: =AC68-AA68 -> 2885
B69: 10110112 | C69: GOMUKH ALOLI | D69: Sahebpur Kamal | E69: 110000 | F69: 10000 | J69: 100000 | K69: 0 | L69: 10000 | N69: 0 | O69: 0 | P69: 0 | Q69: 754 | R69: 1832 | V69: 0 | W69: 0 | AA69: =SUM(L69:W69) -> 12586 | AC69: 20000 | AD69: =AC69-AA69 -> 7414
B70: 10110114 | C70: GOMUKH LABHGAON | D70: Sahebpur Kamal | E70: 110000 | F70: 11882 | J70: 98118 | K70: 1882 | L70: 10000 | N70: 2867 | O70: 1763 | P70: 2178 | V70: 0 | W70: 0 | AA70: =SUM(L70:W70) -> 16808 | AC70: 20000 | AD70: =AC70-AA70 -> 3192
B71: 10110115 | C71: GOMUKH TATRABAD | D71: Sahebpur Kamal | E71: 110000 | F71: 11696 | J71: 98304 | K71: 1696 | L71: 10000 | N71: 1616 | O71: 0 | P71: 0 | V71: 0 | W71: 0 | AA71: =SUM(L71:W71) -> 11616 | AC71: 20000 | AD71: =AC71-AA71 -> 8384
B72: 10110116 | C72: GOMUKH CHANDPURA | D72: Sahebpur Kamal | E72: 110000 | F72: 11924 | J72: 98076 | K72: 1924 | L72: 10000 | N72: 2748 | O72: 357 | P72: 283 | Q72: 471 | R72: 2119 | T72: 875 | U72: 1242 | V72: 160 | W72: 1557 | AA72: =SUM(L72:W72) -> 19812 | AC72: 20000 | AD72: =AC72-AA72 -> 188
B73: 10010095 | C73: Gomukh Goha-02 | D73: Manjhaul | E73: 110000 | F73: 18524 | J73: 91476 | K73: 3524 | L73: 15000 | N73: 3245 | O73: 0 | P73: 0 | V73: 210 | W73: 1545 | AA73: =SUM(L73:W73) -> 20000 | AC73: 20000 | AD73: =AC73-AA73 -> 0 | AF73: =1751-206 -> 1545
B74: 10060074 | C74: BASMATIYA | D74: Sonvarsa | E74: 110000 | F74: 22600.346 | J74: 87399.654 | K74: 7600.3456 | L74: 15000 | N74: 886 | O74: 18 | P74: 0 | V74: 0 | W74: 0 | AA74: =SUM(L74:W74) -> 15904 | AC74: 20000 | AD74: =AC74-AA74 -> 4096
B75: 10120089 | C75: Gomukh Jhaura Tabhka | D75: Simri | E75: 110000 | F75: 18637 | J75: 91363 | K75: 8637 | L75: 10000 | N75: 2323 | O75: 1723 | P75: 1477 | Q75: 0 | R75: 1741 | S75: 1831 | V75: 0 | W75: 0 | AA75: =SUM(L75:W75) -> 19095 | AC75: 20000 | AD75: =AC75-AA75 -> 905
B76: 10060076 | C76: AKHA KURHA | D76: Sonvarsa | E76: 110000 | F76: 23684.609 | J76: 86315.391 | K76: 11684.609 | L76: 12000 | N76: 4532 | O76: 3475 | P76: 6371 | V76: 0 | W76: 0 | AA76: =SUM(L76:W76) -> 26378 | AC76: 20000 | AD76: =AC76-AA76 -> -6378
B77: 10060077 | C77: TILATHI | D77: Sonvarsa | E77: 110000 | F77: 33166.124 | J77: 76833.876 | K77: 18166.124 | L77: 15000 | N77: 0 | O77: 0 | P77: 9433 | V77: 0 | W77: 0 | AA77: =SUM(L77:W77) -> 24433 | AC77: 20000 | AD77: =AC77-AA77 -> -4433
B78: 10120094 | C78: Gomukh Bochaha | D78: Simri | E78: 110000 | F78: 15583 | J78: 94417 | K78: 5583 | L78: 10000 | N78: 2061 | O78: 1826 | P78: 3327 | Q78: 2786 | R78: 0 | S78: 0 | V78: 0 | W78: 0 | AA78: =SUM(L78:W78) -> 20000 | AC78: 20000 | AD78: =AC78-AA78 -> 0 | AE78: 45870
B79: 10130091 | C79: Gomukh Nipur | D79: Musaridharari | E79: 110000 | F79: 13745.009 | J79: 96254.991 | K79: 3745.0087 | L79: 20000 | N79: 0 | O79: 2238 | P79: 3889 | Q79: 2630 | V79: 0 | W79: 0 | AA79: =SUM(L79:W79) -> 28757 | AC79: 20000 | AD79: =AC79-AA79 -> -8757
B80: 10070052 | C80: Gomukh Pachkhutti Jorabarpur | D80: Parbatta | E80: 110000 | F80: 10769 | J80: 99231 | K80: 769 | L80: 10000 | N80: 54 | O80: 0 | P80: 0 | V80: 0 | W80: 0 | AA80: =SUM(L80:W80) -> 10054 | AC80: 20000 | AD80: =AC80-AA80 -> 9946
B81: 10120095 | C81: Gomukh Terganj | D81: Simri | E81: 110000 | F81: 12334 | J81: 97666 | K81: 2334 | L81: 10000 | N81: 2397 | O81: 0 | P81: 0 | R81: 1455 | V81: 0 | W81: 0 | AA81: =SUM(L81:W81) -> 13852 | AC81: 20000 | AD81: =AC81-AA81 -> 6148
B82: 10130084 | C82: Gomukh Gangapur | D82: Musaridharari | E82: 110000 | F82: 13772 | J82: 96228 | K82: 3772 | L82: 10000 | N82: 0 | O82: 0 | P82: 0 | V82: 0 | W82: 0 | AA82: =SUM(L82:W82) -> 10000 | AC82: 20000 | AD82: =AC82-AA82 -> 10000
B83: 10130085 | C83: Gomukh Repura | D83: Musaridharari | E83: 110000 | F83: 21503.799 | J83: 88496.201 | K83: 11503.799 | L83: 10000 | N83: 5456 | O83: 496 | P83: 1280 | Q83: 408 | T83: 0 | U83: 1825 | V83: 535 | W83: 0 | AA83: =SUM(L83:W83) -> 20000 | AC83: 20000 | AD83: =AC83-AA83 -> 0
B84: 10140148 | C84: Gomukh Dalsagar Pachhim | D84: Dumraon | E84: 110000 | F84: 17537 | J84: 92463 | K84: 7537 | L84: 10000 | N84: 1092 | O84: 0 | P84: 0 | V84: 0 | W84: 0 | AA84: =SUM(L84:W84) -> 11092 | AC84: 20000 | AD84: =AC84-AA84 -> 8908
B85: 10120090 | C85: Gomukh Kewasnijamat | D85: Simri | E85: 110000 | F85: 18516 | J85: 91484 | K85: 8516 | L85: 10000 | N85: 191 | O85: 0 | P85: 0 | V85: 0 | W85: 0 | AA85: =SUM(L85:W85) -> 10191 | AC85: 20000 | AD85: =AC85-AA85 -> 9809
B86: 10130077 | C86: Gomukh Akaha | D86: Musaridharari | E86: 110000 | F86: 16032 | J86: 93968 | K86: 6032 | L86: 10000 | N86: 0 | O86: 0 | P86: 0 | T86: 602 | U86: 834 | V86: 1908 | W86: 195 | AA86: =SUM(L86:W86) -> 13539 | AC86: 20000 | AD86: =AC86-AA86 -> 6461
B87: 10130079 | C87: Vishnupur Kowahi | D87: Musaridharari | E87: 110000 | F87: 18484.2 | J87: 91515.8 | K87: 8484.1998 | L87: 10000 | N87: 2529 | O87: 1546 | P87: 0 | V87: 0 | W87: 0 | AA87: =SUM(L87:W87) -> 14075 | AC87: 20000 | AD87: =AC87-AA87 -> 5925
B88: 10080079 | C88: Gomukh Barauni 3 | D88: Teghra | E88: 110000 | F88: 18722 | J88: 91278 | K88: 3722 | L88: 15000 | N88: 0 | O88: 0 | P88: 0 | V88: 0 | W88: 0 | AA88: =SUM(L88:W88) -> 15000 | AC88: 20000 | AD88: =AC88-AA88 -> 5000
B89: 10140146 | C89: Gomukh Koransarai | D89: Dumraon | E89: 110000 | F89: 10864 | J89: 99136 | K89: 864 | L89: 10000 | N89: 0 | O89: 0 | P89: 0 | V89: 0 | W89: 0 | AA89: =SUM(L89:W89) -> 10000 | AC89: 20000 | AD89: =AC89-AA89 -> 10000
B90: 10140152 | C90: Gomukh Badkagaon Yamunatola | D90: Dumraon | E90: 110000 | F90: 17331 | J90: 92669 | K90: 7331 | L90: 10000 | N90: 736 | O90: 558 | P90: 0 | V90: 0 | W90: 769 | AA90: =SUM(L90:W90) -> 12063 | AC90: 20000 | AD90: =AC90-AA90 -> 7937
B91: 10110097 | C91: GOMUKH BACHOTA | D91: Sahebpur Kamal | E91: 110000 | F91: 19417.435 | J91: 90582.565 | K91: 9417.435 | L91: 10000 | N91: 2954 | O91: 2369 | P91: 3668 | Q91: 429 | V91: 0 | W91: 0 | AA91: =SUM(L91:W91) -> 19420 | AC91: 20000 | AD91: =AC91-AA91 -> 580
B92: 10060090 | C92: Sangrampur | D92: Halsi | E92: 110000 | F92: 18861 | J92: 91139 | K92: 1861 | L92: 17000 | N92: 1721 | O92: 0 | P92: 0 | T92: 400 | U92: 370 | V92: 509 | W92: 0 | AA92: =SUM(L92:W92) -> 20000 | AC92: 20000 | AD92: =AC92-AA92 -> 0 | AF92: =591-191 -> 400
B93: 10110101 | C93: GOMUKH TILAK NAGAR | D93: Sahebpur Kamal | E93: 110000 | F93: 15583 | J93: 94417 | K93: 5583 | L93: 10000 | N93: 1763 | O93: 1067 | P93: 2180 | Q93: 2085 | R93: 2495 | T93: 410 | V93: 0 | W93: 0 | AA93: =SUM(L93:W93) -> 20000 | AC93: 20000 | AD93: =AC93-AA93 -> 0
B94: 10080077 | C94: Gomukh Amarpur | D94: Teghra | E94: 110000 | F94: 28023.283 | J94: 81976.717 | K94: 13023.283 | L94: 15000 | N94: 0 | O94: 1075 | P94: 3157 | V94: 0 | W94: 0 | AA94: =SUM(L94:W94) -> 19232 | AC94: 20000 | AD94: =AC94-AA94 -> 768
B95: 10140135 | C95: Gomukh Dhanipur | D95: Dumraon | E95: 110000 | F95: 26050.119 | J95: 83949.881 | K95: 16050.119 | L95: 10000 | N95: 5320 | O95: 3685 | P95: 3032 | V95: 0 | W95: 0 | AA95: =SUM(L95:W95) -> 22037 | AC95: 20000 | AD95: =AC95-AA95 -> -2037
B96: 10140129 | C96: Gomukh Paharpur | D96: Dumraon | E96: 110000 | F96: 28638.46 | J96: 81361.54 | K96: 18638.46 | L96: 10000 | N96: 5600 | O96: 3278 | P96: 0 | Q96: 835 | R96: 177 | T96: 110 | V96: 0 | W96: 0 | AA96: =SUM(L96:W96) -> 20000 | AC96: 20000 | AD96: =AC96-AA96 -> 0
B97: 10110005 | C97: NAYAGAW | D97: Sahebpur Kamal | E97: 110000 | F97: 110000 | J97: 0 | K97: 110000 | L97: 0 | N97: 0 | O97: 0 | P97: 0 | V97: 0 | W97: 0 | AA97: =SUM(L97:W97) -> 0 | AC97: 20000 | AD97: =AC97-AA97 -> 20000
B98: 10110001 | C98: Gomukh Mahendrapur | D98: Sahebpur Kamal | E98: 64000 | F98: 64000 | J98: 0 | K98: 64000 | L98: 0 | N98: 0 | O98: 0 | P98: 0 | V98: 0 | W98: 0 | AA98: =SUM(L98:W98) -> 0 | AC98: 20000 | AD98: =AC98-AA98 -> 20000
B99: 10020069 | C99: CHETAN-TOLA-KHUTHA | D99: Laldiyara | E99: 110000 | F99: 10368.397 | J99: 99631.603 | K99: 10368.397 | N99: 0 | O99: 0 | P99: 0 | V99: 0 | W99: 0 | AA99: =SUM(L99:W99) -> 0 | AC99: 20000 | AD99: =AC99-AA99 -> 20000
B100: 10060068 | C100: BASUHAR | D100: Sonvarsa | E100: 110000 | F100: 29013.288 | J100: 80986.712 | K100: 14013.288 | L100: 15000 | N100: 0 | O100: 0 | P100: 0 | V100: 0 | W100: 0 | AA100: =SUM(L100:W100) -> 15000 | AC100: 20000 | AD100: =AC100-AA100 -> 5000
...

Sheet Sheet2
A1: Date | B1: Particulars | D1: Vch Type | E1: Vch No. | F1: Debit
A2: 13/9/23 | F2: 3718
A3: 28/9/23 | F3: 10000
A4: 20000 | F4: 20000 | G4: Revert
A5: 45412 | B5: Cr | C5: HDFC Bank Ltd. - 50100063899098 | D5: Payment | E5: 84 | F5: 7335
A6: 45426 | B6: Cr | C6: HDFC Bank Ltd. - 50100063899098 | D6: Payment | E6: 124 | F6: 4000
A7: 45429 | B7: Cr | C7: HDFC Bank Ltd. - 50100063899098 | D7: Payment | E7: 145 | F7: 20000
A8: 45450 | B8: Cr | C8: HDFC Bank Ltd. - 50100063899098 | D8: Payment | E8: 212 | F8: 20000
A9: 45461 | B9: Cr | C9: HDFC Bank Ltd. - 50100063899098 | D9: Payment | E9: 248 | F9: 67008 | G9: Check cancilled
A10: 45467 | B10: Cr | C10: HDFC Bank Ltd. - 50100063899098 | D10: Payment | E10: 269 | F10: 13131
A11: 45467 | B11: Cr | C11: HDFC Bank Ltd. - 50100063899098 | D11: Payment | E11: 270 | F11: 15573
L12: 8611 | M12: Amit 2nd lot
A13: 45520 | F13: 5000 | G13: Mahila Re issue Cheque

Sheet PRAVAH
B1: Pravah | E1: Kradex | J1: EIPL
A2: Date | B2: Amount | C2: Purpose | E2: Date | F2: Amount | G2: Purpose | I2: Date | J2: Amount | K2: Purpose
A3: 44676 | B3: 150000 | C3: Battery | E3: 44841 | F3: 150000 | G3: AMCU | I3: 45159 | J3: 700000 | K3: AMCU | L3: ok
A4: 44963 | B4: 204000 | C4: Battery | E4: 44845 | F4: 310000 | G4: AMCU | I4: 45205 | J4: 250000 | K4: AMCU | L4: ok
A5: 44981 | B5: 136000 | C5: Battery | E5: 44855 | F5: 40000 | G5: AMCU | I5: 45238 | J5: 250000 | K5: AMCU | L5: ok
A6: 45031 | B6: 69000 | C6: Battery | E6: 44929 | F6: 250000 | G6: AMCU | I6: 45252 | J6: 250000 | K6: AMCU | L6: ok
A7: 45112 | B7: 109500 | C7: Battery | E7: 45014 | F7: 101967 | G7: AMCU | I7: 45268 | J7: 250000 | K7: AMCU | L7: ok
A8: 45252 | B8: 38075 | C8: Battery | E8: 45090 | F8: 53240 | G8: AMCU | I8: 45299 | J8: 250000 | K8: AMCU | L8: ok | O8: =750000+101967+53240+26620+26620+26620+873835+26620 -> 1885522
A9: 45664 | B9: 72100 | C9: Battery | E9: 45103 | F9: 26620 | G9: AMCU | I9: 45358 | J9: 250000 | K9: AMCU | L9: ok
A10: 45733 | B10: =64396+54250 -> 118646 | C10: Battery | E10: 45134 | F10: 26620 | G10: AMCU | I10: 45426 | J10: 804132 | K10: AMCU
B11: =SUM(B3:B10) -> 897321 | E11: 45175 | F11: 26620 | G11: AMCU | I11: 45448 | J11: 0 | K11: AMCU
E12: 45252 | F12: 873835 | G12: AMCU | J12: =SUM(J3:J11) -> 3004132
F13: =SUM(F3:F12) -> 1858902 | J13: =+J12+F13 -> 4863034
F14: 19715
F15: =+F13+F14 -> 1878617

Sheet Summary
A1: Status as on 28th Feb 25 | E1: Reco | F1: 45846
A2: Security Status of EMI Model (Wef 01/03/2022) | E2: Ledger Name | F2: Amt
A3: Particulars | B3: Amount | E3: AMCU Down Payment | F3: 2355189
A4: Receved as security | B4: =+'AMCU Details'!R1 -> 1985000 | C4: =+B5+B4 -> 3228531.7 | E4: New Assets EMI | F4: 20334481
A5: Unreconciled Security | B5: 1243531.7 | E5: Total | F5: =SUM(F3:F4) -> 22689670
A6: EMI Deduction | B6: =+'AMCU Details'!Q1 -> 7284344.1 | E6: Diff | F6: =+B14-F5 -> -19284454
A7: Total | B7: =+B4+B6+B5 -> 10512876
A8: Retun to MPGs | B8: =+'AMCU Details'!M1 -> 30000
A9: Yet to Map | B9: 0
A10: Fund tr to 51 AMCU purchase | B10: =750000+101967+53240+26620+26620+26620+873835+26620 -> 1885522
B11: =+PRAVAH!J12 -> 3004132
A12: AC - 167600, DPU, 1021611, Coller - 5138, Furnture - 21000, Lab Equipment - 41536, laptop - 33800. | B12: 1290685
A13: Paid to PRAVAH | B13: =+PRAVAH!B11 -> 897321
A14: Net Balance with Daya | B14: =+B7-B8-B10-B13-B11-B9-B12 -> 3405215.8
