Workbook
Name Purchase: Table3[]

Sheet Stock Munger
A1: Item Name | B1: UoM | C1: Opening Stock | D1: Received Stock | E1: Issue Stock | F1: Closing Balance | G1: Reorder Qty | H1: Reorder Level | I1: Open Rate | J1: Stock Value | K1: Stock Staus
A2: 1% Iodine Solution (100ml) | B2: Nos | C2: 15 | D2: 0 | E2: 5 | F2: 10 | G2: 15 | H2: 5 | I2: 90 | J2: 900 | K2: Stock Available
A3: Amber Colour Bottle (250 ML) | B3: Nos | C3: 140 | D3: 0 | E3: 14 | F3: 126 | G3: 50 | H3: 40 | I3: 120 | J3: 15120 | K3: Stock Available
A4: Amyl 500ml | B4: Nos | C4: 50 | D4: 0 | E4: 17 | F4: 33 | G4: 50 | H4: 30 | I4: 366 | J4: 12071 | K4: Stock Available
A5: Analyzer Calibration Cheking Log Book | B5: Nos | C5: 13 | D5: 100 | E5: 0 | F5: 113 | G5: 100 | H5: 20 | I5: 127 | J5: 14401 | K5: Stock Available
A6: Beaker 100 Ml | B6: Nos | C6: 24 | D6: 0 | E6: 6 | F6: 18 | G6: 48 | H6: 10 | I6: 33 | J6: 597 | K6: Stock Available
A7: Beaker 250 ML Borosilicate | B7: Nos | C7: 12 | D7: 0 | E7: 5 | F7: 7 | G7: 48 | H7: 10 | I7: 47 | J7: 330 | K7: PO Required
A8: Beaker 500 Ml | B8: Nos | C8: 49 | D8: 0 | E8: 6 | F8: 43 | G8: 48 | H8: 10 | I8: 64 | J8: 2739 | K8: Stock Available
A9: Beaker 50 ML | B9: Nos | C9: 8 | D9: 0 | E9: 4 | F9: 4 | G9: 48 | H9: 10 | I9: 16 | J9: 64 | K9: PO Required
A10: BMC Cleaning Brush 2" | B10: Nos | C10: 41 | D10: 0 | E10: 4 | F10: 37 | G10: 10 | H10: 10 | I10: 212 | J10: 7859 | K10: Stock Available
A11: BMC Day Book | B11: Nos | C11: 106 | D11: 300 | E11: 98 | F11: 308 | G11: 300 | H11: 60 | I11: 122 | J11: 37434 | K11: Stock Available
A12: Burete Stand | B12: Nos | C12: 16 | D12: 0 | E12: 3 | F12: 13 | G12: 20 | H12: 5 | I12: 258 | J12: 3355 | K12: Stock Available
A13: Burret 50 ML Borosilicate | B13: Nos | C13: 14 | D13: 0 | E13: 6 | F13: 8 | G13: 20 | H13: 5 | I13: 99 | J13: 796 | K13: Stock Available
... A97: Tilt Measure 1 Ml with Bottle | B97: Nos | C97: 256 | D97: 0 | E97: 6 | F97: 250 | G97: 500 | H97: 50 | I97: 32 | J97: 8022 | K97: Stock Available

Sheet Pending Recoveries
A1: Date | B1: (All)
H2: Consumable deduction summary
A3: To BMC/MPG Code | B3: BMC MPG Name | C3: Recovery Done | D3: Sum of Amt | H3: To BMC/MPG Code | I3: BMC MPG Name | J3: Recovery Done | K3: C/F_BAL (FYI-24-25) | L3: C/F_BAL (FYI-25-26) | M3: Purchase Add Amount | N3: Total | O3: Apr | P3: May | Q3: Jun | R3: Jul | S3: Aug | T3: Sep | U3: Oct | V3: Nov | W3: Dec | X3: Jan | Y3: Feb | Z3: Mar | AA3: Balance | AB3: Blank | AC3: Gaurav | AD3: Diff | AE3: Remarks
A4: 2 | B4: Nova Dairy | C4: Pending | D4: 8010.4 | H4: 10520003 | I4: Nova Dairy | J4: Pending | K4: 0 | L4: 9308.4 | M4: 10795.2 | N4: =K4+M4+L4 -> 20103.6 | O4: 0 | P4: 0 | Q4: 0 | R4: 0 | S4: 0 | T4: 0 | U4: 0 | V4: 0 | W4: 0 | Y4: 0 | Z4: 0 | AA4: =N4-SUM(O4:Z4) -> 20103.6 | AC4: =IFERROR(VLOOKUP(H4,'[1]Pending Recoveries'!$A:$D,4,0),0) -> 10795.2 | AD4: =AA4-AC4 -> 9308.4 | AE4: =AC4-M4 -> 0
A5: 1002 | B5: Laldiyara | C5: Pending | D5: 28773.24 | H5: 1002 | I5: Laldiyara | J5: Pending | K5: 0 | L5: 0.19 | M5: 19211.68 | N5: =K5+M5+L5 -> 19211.87 | O5: 0 | P5: 0 | Q5: 0 | R5: 0 | S5: 0 | T5: 0 | U5: 0 | V5: 0 | W5: 0 | Y5: 0 | Z5: 0 | AA5: =N5-SUM(O5:Z5) -> 19211.87 | AC5: =IFERROR(VLOOKUP(H5,'[1]Pending Recoveries'!$A:$D,4,0),0) -> 19211.68 | AD5: =AA5-AC5 -> 0.19 | AE5: =AC5-M5 -> 0
A6: 1003 | B6: Asarganj | C6: Pending | D6: 99.47 | H6: 1003 | I6: Asarganj | J6: Pending | K6: 0 | L6: 0.47 | M6: 0 | N6: =K6+M6+L6 -> 0.47 | O6: 0 | P6: 0 | Q6: 0 | R6: 0 | S6: 0 | T6: 0 | U6: 0 | V6: 0 | W6: 0 | Y6: 0 | Z6: 0 | AA6: =N6-SUM(O6:Z6) -> 0.47 | AC6: =IFERROR(VLOOKUP(H6,'[1]Pending Recoveries'!$A:$D,4,0),0) -> 0 | AD6: =AA6-AC6 -> 0.47 | AE6: =AC6-M6 -> 0
A7: 1004 | B7: Tofir | C7: Pending | D7: 2145.71 | H7: 1004 | I7: Tofir | J7: Pending | K7: 0 | L7: 1707.81 | M7: 0 | N7: =K7+M7+L7 -> 1707.81 | O7: 0 | P7: 0 | Q7: 0 | R7: 0 | S7: 0 | T7: 0 | U7: 0 | V7: 0 | W7: 0 | Y7: 0 | Z7: 0 | AA7: =N7-SUM(O7:Z7) -> 1707.81 | AC7: =IFERROR(VLOOKUP(H7,'[1]Pending Recoveries'!$A:$D,4,0),0) -> 0 | AD7: =AA7-AC7 -> 1707.81 | AE7: =AC7-M7 -> 0
A8: 1006 | B8: Sonvarsha | C8: Pending | D8: 25566.8 | H8: 1006 | I8: Sonvarsha | J8: Pending | K8: 8310 | L8: 0.32 | M8: 0 | N8: =K8+M8+L8 -> 8310.32 | O8: 0 | P8: 0 | Q8: 0 | R8: 0 | S8: 0 | T8: 0 | U8: 0 | V8: 0 | W8: 0 | Y8: 0 | Z8: 0 | AA8: =N8-SUM(O8:Z8) -> 8310.32 | AC8: =IFERROR(VLOOKUP(H8,'[1]Pending Recoveries'!$A:$D,4,0),0) -> 0 | AD8: =AA8-AC8 -> 8310.32 | AE8: =AC8-M8 -> 0
A9: 1007 | B9: Araria | C9: Pending | D9: 31005.2 | H9: 1007 | I9: Araria | J9: Pending | K9: 0 | L9: 0.3 | M9: 19175.416 | N9: =K9+M9+L9 -> 19175.716 | O9: 0 | P9: 0 | Q9: 0 | R9: 0 | S9: 0 | T9: 0 | U9: 0 | V9: 0 | W9: 0 | Y9: 0 | Z9: 0 | AA9: =N9-SUM(O9:Z9) -> 19175.716 | AC9: =IFERROR(VLOOKUP(H9,'[1]Pending Recoveries'!$A:$D,4,0),0) -> 19175.416 | AD9: =AA9-AC9 -> 0.3 | AE9: =AC9-M9 -> 0
A10: 1008 | B10: Teghra | C10: Pending | D10: 11247.46 | H10: 1008 | I10: Teghra | J10: Pending | K10: 0 | L10: -0.14 | M10: 8349.34 | N10: =K10+M10+L10 -> 8349.2 | O10: 0 | P10: 0 | Q10: 0 | R10: 0 | S10: 0 | T10: 0 | U10: 0 | V10: 0 | W10: 0 | Y10: 0 | Z10: 0 | AA10: =N10-SUM(O10:Z10) -> 8349.2 | AC10: =IFERROR(VLOOKUP(H10,'[1]Pending Recoveries'!$A:$D,4,0),0) -> 8349.34 | AD10: =AA10-AC10 -> -0.14 | AE10: =AC10-M10 -> 0
A11: 1009 | B11: Halsi | C11: Pending | D11: 24532.44 | H11: 1009 | I11: Halsi | J11: Pending | K11: 0 | L11: 0.27 | M11: 8712.5 | N11: =K11+M11+L11 -> 8712.77 | O11: 0 | P11: 0 | Q11: 0 | R11: 0 | S11: 0 | T11: 0 | U11: 0 | V11: 0 | W11: 0 | Y11: 0 | Z11: 0 | AA11: =N11-SUM(O11:Z11) -> 8712.77 | AC11: =IFERROR(VLOOKUP(H11,'[1]Pending Recoveries'!$A:$D,4,0),0) -> 8712.5 | AD11: =AA11-AC11 -> 0.27 | AE11: =AC11-M11 -> 0
A12: 10010013 | B12: Gomukh Kumbhi | C12: Pending | D12: 155.09 | H12: 10010013 | I12: Gomukh Kumbhi | J12: Pending | K12: 0 | L12: 0.09 | M12: 0 | N12: =K12+M12+L12 -> 0.09 | O12: 0 | P12: 0 | Q12: 0 | R12: 0 | S12: 0 | T12: 0 | U12: 0 | V12: 0 | W12: 0 | Y12: 0 | Z12: 0 | AA12: =N12-SUM(O12:Z12) -> 0.09 | AC12: =IFERROR(VLOOKUP(H12,'[1]Pending Recoveries'!$A:$D,4,0),0) -> 0 | AD12: =AA12-AC12 -> 0.09 | AE12: =AC12-M12 -> 0
A13: 10010019 | B13: Gomukh Jagdar | C13: Pending | D13: 880.71 | H13: 10010019 | I13: Gomukh Jagdar | J13: Pending | K13: 0 | L13: 0 | M13: 0 | N13: =K13+M13+L13 -> 0 | O13: 0 | P13: 0 | Q13: 0 | R13: 0 | S13: 0 | T13: 0 | U13: 0 | V13: 0 | W13: 0 | Y13: 0 | Z13: 0 | AA13: =N13-SUM(O13:Z13) -> 0 | AC13: =IFERROR(VLOOKUP(H13,'[1]Pending Recoveries'!$A:$D,4,0),0) -> 0 | AD13: =AA13-AC13 -> 0 | AE13: =AC13-M13 -> 0
A14: 10010021 | B14: Gomukh Moradpur | C14: Pending | D14: 52.49 | H14: 10010021 | I14: Gomukh Moradpur | J14: Pending | K14: 469 | L14: 521.49 | M14: 0 | N14: =K14+M14+L14 -> 990.49 | O14: 0 | P14: 0 | Q14: 0 | R14: 0 | S14: 0 | T14: 0 | U14: 0 | V14: 0 | W14: 0 | Y14: 0 | Z14: 0 | AA14: =N14-SUM(O14:Z14) -> 990.49 | AC14: =IFERROR(VLOOKUP(H14,'[1]Pending Recoveries'!$A:$D,4,0),0) -> 0 | AD14: =AA14-AC14 -> 990.49 | AE14: =AC14-M14 -> 0
A15: 10010027 | B15: Gomukh Paroriya | C15: Pending | D15: 52.49 | H15: 10010027 | I15: Gomukh Paroriya | J15: Pending | K15: 0 | L15: 52.49 | M15: 0 | N15: =K15+M15+L15 -> 52.49 | O15: 0 | P15: 0 | Q15: 0 | R15: 0 | S15: 0 | T15: 0 | U15: 0 | V15: 0 | W15: 0 | Y15: 0 | Z15: 0 | AA15: =N15-SUM(O15:Z15) -> 52.49 | AC15: =IFERROR(VLOOKUP(H15,'[1]Pending Recoveries'!$A:$D,4,0),0) -> 0 | AD15: =AA15-AC15 -> 52.49 | AE15: =AC15-M15 -> 0
... A246: 10560001 | B246: Gomukh Chautham(Mithun kumar VLC) | C246: Pending | D246: 1209.52 | H246: 10560001 | I246: Gomukh Chautham(Mithun kumar VLC) | J246: Pending | K246: 0 | L246: 0 | M246: 6745.1455 | N246: =K246+M246+L246 -> 6745.1455 | O246: 3634.92 | P246: 2920.5 | Q246: 0 | R246: 0 | S246: 0 | T246: 0 | U246: 0 | V246: 0 | W246: 0 | Y246: 0 | Z246: 0 | AA246: =N246-SUM(O246:Z246) -> 189.72549 | AC246: =IFERROR(VLOOKUP(H246,'[1]Pending Recoveries'!$A:$D,4,0),0) -> 6745.1455 | AD246: =AA246-AC246 -> -6555.42 | AE246: =AC246-M246 -> 0
A247: Grand Total | D247: 247545.79 | H247: 10110076 | I247: GOMUKH SRINAGAR | J247: Pending | K247: 0 | L247: -257 | M247: 0 | N247: =K247+M247+L247 -> -257 | O247: 0 | P247: 0 | Q247: 0 | R247: 0 | S247: 0 | T247: 0 | U247: 0 | V247: 0 | W247: 0 | Y247: 0 | Z247: 0 | AA247: =N247-SUM(O247:Z247) -> -257 | AC247: =IFERROR(VLOOKUP(H247,'[1]Pending Recoveries'!$A:$D,4,0),0) -> 0 | AD247: =AA247-AC247 -> -257 | AE247: =AC247-M247 -> 0
H248: 10010005 | J248: Pending | K248: 330 | L248: 330 | M248: 0 | N248: =K248+M248+L248 -> 660 | O248: 0 | P248: 0 | Q248: 0 | R248: 0 | S248: 0 | T248: 0 | U248: 0 | V248: 0 | W248: 0 | Y248: 0 | Z248: 0 | AA248: =N248-SUM(O248:Z248) -> 660 | AC248: =IFERROR(VLOOKUP(H248,'[1]Pending Recoveries'!$A:$D,4,0),0) -> 0 | AD248: =AA248-AC248 -> 660 | AE248: =AC248-M248 -> 0
H249: 10010006 | J249: Pending | K249: 0 | L249: 0 | M249: 0 | N249: =K249+M249+L249 -> 0 | O249: 0 | P249: 0 | Q249: 0 | R249: 0 | S249: 0 | T249: 0 | U249: 0 | V249: 0 | W249: 0 | Y249: 0 | Z249: 0 | AA249: =N249-SUM(O249:Z249) -> 0 | AC249: =IFERROR(VLOOKUP(H249,'[1]Pending Recoveries'!$A:$D,4,0),0) -> 0 | AD249: =AA249-AC249 -> 0 | AE249: =AC249-M249 -> 0
H250: 10010007 | J250: Pending | K250: 0 | L250: 0 | M250: 0 | N250: =K250+M250+L250 -> 0 | O250: 0 | P250: 0 | Q250: 0 | R250: 0 | S250: 0 | T250: 0 | U250: 0 | V250: 0 | W250: 0 | Y250: 0 | Z250: 0 | AA250: =N250-SUM(O250:Z250) -> 0 | AC250: =IFERROR(VLOOKUP(H250,'[1]Pending Recoveries'!$A:$D,4,0),0) -> 0 | AD250: =AA250-AC250 -> 0 | AE250: =AC250-M250 -> 0
H251: 10010008 | J251: Pending | K251: 96 | L251: 96 | M251: 0 | N251: =K251+M251+L251 -> 192 | O251: 0 | P251: 0 | Q251: 0 | R251: 0 | S251: 0 | T251: 0 | U251: 0 | V251: 0 | W251: 0 | Y251: 0 | Z251: 0 | AA251: =N251-SUM(O251:Z251) -> 192 | AC251: =IFERROR(VLOOKUP(H251,'[1]Pending Recoveries'!$A:$D,4,0),0) -> 0 | AD251: =AA251-AC251 -> 192 | AE251: =AC251-M251 -> 0
H252: 10010009 | J252: Pending | K252: 204 | L252: 204 | M252: 0 | N252: =K252+M252+L252 -> 408 | O252: 0 | P252: 0 | Q252: 0 | R252: 0 | S252: 0 | T252: 0 | U252: 0 | V252: 0 | W252: 0 | Y252: 0 | Z252: 0 | AA252: =N252-SUM(O252:Z252) -> 408 | AC252: =IFERROR(VLOOKUP(H252,'[1]Pending Recoveries'!$A:$D,4,0),0) -> 0 | AD252: =AA252-AC252 -> 408 | AE252: =AC252-M252 -> 0
H253: 10010012 | J253: Pending | K253: 0 | L253: 0 | M253: 0 | N253: =K253+M253+L253 -> 0 | O253: 0 | P253: 0 | Q253: 0 | R253: 0 | S253: 0 | T253: 0 | U253: 0 | V253: 0 | W253: 0 | Y253: 0 | Z253: 0 | AA253: =N253-SUM(O253:Z253) -> 0 | AC253: =IFERROR(VLOOKUP(H253,'[1]Pending Recoveries'!$A:$D,4,0),0) -> 0 | AD253: =AA253-AC253 -> 0 | AE253: =AC253-M253 -> 0
H254: 10010014 | J254: Pending | K254: 204 | L254: 204 | M254: 0 | N254: =K254+M254+L254 -> 408 | O254: 0 | P254: 0 | Q254: 0 | R254: 0 | S254: 0 | T254: 0 | U254: 0 | V254: 0 | W254: 0 | Y254: 0 | Z254: 0 | AA254: =N254-SUM(O254:Z254) -> 408 | AC254: =IFERROR(VLOOKUP(H254,'[1]Pending Recoveries'!$A:$D,4,0),0) -> 0 | AD254: =AA254-AC254 -> 408 | AE254: =AC254-M254 -> 0
H255: 10010015 | J255: Pending | K255: 204 | L255: 204 | M255: 0 | N255: =K255+M255+L255 -> 408 | O255: 0 | P255: 0 | Q255: 0 | R255: 0 | S255: 0 | T255: 0 | U255: 0 | V255: 0 | W255: 0 | Y255: 0 | Z255: 0 | AA255: =N255-SUM(O255:Z255) -> 408 | AC255: =IFERROR(VLOOKUP(H255,'[1]Pending Recoveries'!$A:$D,4,0),0) -> 0 | AD255: =AA255-AC255 -> 408 | AE255: =AC255-M255 -> 0
H256: 10010016 | J256: Pending | K256: 125 | L256: 125 | M256: 0 | N256: =K256+M256+L256 -> 250 | O256: 0 | P256: 0 | Q256: 0 | R256: 0 | S256: 0 | T256: 0 | U256: 0 | V256: 0 | W256: 0 | Y256: 0 | Z256: 0 | AA256: =N256-SUM(O256:Z256) -> 250 | AC256: =IFERROR(VLOOKUP(H256,'[1]Pending Recoveries'!$A:$D,4,0),0) -> 0 | AD256: =AA256-AC256 -> 250 | AE256: =AC256-M256 -> 0
H257: 10010017 | J257: Pending | K257: 0 | L257: 0 | M257: 0 | N257: =K257+M257+L257 -> 0 | O257: 0 | P257: 0 | Q257: 0 | R257: 0 | S257: 0 | T257: 0 | U257: 0 | V257: 0 | W257: 0 | Y257: 0 | Z257: 0 | AA257: =N257-SUM(O257:Z257) -> 0 | AC257: =IFERROR(VLOOKUP(H257,'[1]Pending Recoveries'!$A:$D,4,0),0) -> 0 | AD257: =AA257-AC257 -> 0 | AE257: =AC257-M257 -> 0
H258: 10010018 | J258: Pending | K258: 204 | L258: 204 | M258: 0 | N258: =K258+M258+L258 -> 408 | O258: 0 | P258: 0 | Q258: 0 | R258: 0 | S258: 0 | T258: 0 | U258: 0 | V258: 0 | W258: 0 | Y258: 0 | Z258: 0 | AA258: =N258-SUM(O258:Z258) -> 408 | AC258: =IFERROR(VLOOKUP(H258,'[1]Pending Recoveries'!$A:$D,4,0),0) -> 0 | AD258: =AA258-AC258 -> 408 | AE258: =AC258-M258 -> 0
H259: 10010024 | J259: Pending | K259: 0 | L259: 0 | M259: 0 | N259: =K259+M259+L259 -> 0 | O259: 0 | P259: 0 | Q259: 0 | R259: 0 | S259: 0 | T259: 0 | U259: 0 | V259: 0 | W259: 0 | Y259: 0 | Z259: 0 | AA259: =N259-SUM(O259:Z259) -> 0 | AC259: =IFERROR(VLOOKUP(H259,'[1]Pending Recoveries'!$A:$D,4,0),0) -> 0 | AD259: =AA259-AC259 -> 0 | AE259: =AC259-M259 -> 0
... H727: 10110134 | J727: Pending | K727: 0 | L727: 209.16 | M727: 1154.54 | N727: =K727+M727+L727 -> 1363.7 | O727: 0 | P727: 0 | Q727: 0 | R727: 0 | S727: 0 | T727: 0 | U727: 0 | V727: 0 | W727: 0 | Y727: 0 | Z727: 0 | AA727: =N727-SUM(O727:Z727) -> 1363.7 | AC727: =IFERROR(VLOOKUP(H727,'[1]Pending Recoveries'!$A:$D,4,0),0) -> 1154.54 | AD727: =AA727-AC727 -> 209.16 | AE727: =AC727-M727 -> 0
H728: 10120091 | I728: GOMUKH MOHANPUR | J728: Pending | K728: 0 | L728: 0 | M728: 0 | N728: =K728+M728+L728 -> 0 | O728: 0 | P728: 0 | Q728: 0 | R728: 0 | S728: 0 | T728: 0 | U728: 0 | V728: 0 | W728: 0 | Y728: 0 | Z728: 0 | AA728: =N728-SUM(O728:Z728) -> 0 | AC728: =IFERROR(VLOOKUP(H728,'[1]Pending Recoveries'!$A:$D,4,0),0) -> 0 | AD728: =AA728-AC728 -> 0 | AE728: =AC728-M728 -> 0
H729: 10120104 | I729: Gomukh Mordiwa East | J729: Pending | K729: 0 | L729: 0 | M729: 0 | N729: =K729+M729+L729 -> 0 | O729: 0 | P729: 0 | Q729: 0 | R729: 0 | S729: 0 | T729: 0 | U729: 0 | V729: 0 | W729: 0 | Y729: 0 | Z729: 0 | AA729: =N729-SUM(O729:Z729) -> 0 | AC729: =IFERROR(VLOOKUP(H729,'[1]Pending Recoveries'!$A:$D,4,0),0) -> 0 | AD729: =AA729-AC729 -> 0 | AE729: =AC729-M729 -> 0
H730: 10120108 | I730: GOMUKH MANIKA EAST | J730: Pending | K730: 0 | L730: 0 | M730: 0 | N730: =K730+M730+L730 -> 0 | O730: 0 | P730: 0 | Q730: 0 | R730: 0 | S730: 0 | T730: 0 | U730: 0 | V730: 0 | W730: 0 | Y730: 0 | Z730: 0 | AA730: =N730-SUM(O730:Z730) -> 0 | AC730: =IFERROR(VLOOKUP(H730,'[1]Pending Recoveries'!$A:$D,4,0),0) -> 0 | AD730: =AA730-AC730 -> 0 | AE730: =AC730-M730 -> 0
H731: 10120111 | I731: GOMUKH Kisanpur Tabhka | J731: Pending | K731: 0 | L731: 0 | M731: 0 | N731: =K731+M731+L731 -> 0 | O731: 0 | P731: 0 | Q731: 0 | R731: 0 | S731: 0 | T731: 0 | U731: 0 | V731: 0 | W731: 0 | Y731: 0 | Z731: 0 | AA731: =N731-SUM(O731:Z731) -> 0 | AC731: =IFERROR(VLOOKUP(H731,'[1]Pending Recoveries'!$A:$D,4,0),0) -> 0 | AD731: =AA731-AC731 -> 0 | AE731: =AC731-M731 -> 0
H732: 10120114 | I732: GOMUKH PATHAKTOL | J732: Pending | K732: 0 | L732: 458.32 | M732: 0 | N732: =K732+M732+L732 -> 458.32 | O732: 0 | P732: 0 | Q732: 0 | R732: 0 | S732: 0 | T732: 0 | U732: 0 | V732: 0 | W732: 0 | Y732: 0 | Z732: 0 | AA732: =N732-SUM(O732:Z732) -> 458.32 | AC732: =IFERROR(VLOOKUP(H732,'[1]Pending Recoveries'!$A:$D,4,0),0) -> 0 | AD732: =AA732-AC732 -> 458.32 | AE732: =AC732-M732 -> 0
H733: 10130044 | I733: Lakshmipur Western Tol - Rajeev | J733: Pending | K733: 0 | L733: 0 | M733: 0 | N733: =K733+M733+L733 -> 0 | O733: 0 | P733: 0 | Q733: 0 | R733: 0 | S733: 0 | T733: 0 | U733: 0 | V733: 0 | W733: 0 | Y733: 0 | Z733: 0 | AA733: =N733-SUM(O733:Z733) -> 0 | AC733: =IFERROR(VLOOKUP(H733,'[1]Pending Recoveries'!$A:$D,4,0),0) -> 0 | AD733: =AA733-AC733 -> 0 | AE733: =AC733-M733 -> 0
H734: 10130073 | I734: Dagarua | J734: Pending | K734: 0 | L734: 109.8 | M734: 0 | N734: =K734+M734+L734 -> 109.8 | O734: 0 | P734: 0 | Q734: 0 | R734: 0 | S734: 0 | T734: 0 | U734: 0 | V734: 0 | W734: 0 | Y734: 0 | Z734: 0 | AA734: =N734-SUM(O734:Z734) -> 109.8 | AC734: =IFERROR(VLOOKUP(H734,'[1]Pending Recoveries'!$A:$D,4,0),0) -> 0 | AD734: =AA734-AC734 -> 109.8 | AE734: =AC734-M734 -> 0
H735: 10130077 | I735: Gomukh Akaha | J735: Pending | K735: 0 | L735: 0 | M735: 0 | N735: =K735+M735+L735 -> 0 | O735: 0 | P735: 0 | Q735: 0 | R735: 0 | S735: 0 | T735: 0 | U735: 0 | V735: 0 | W735: 0 | Y735: 0 | Z735: 0 | AA735: =N735-SUM(O735:Z735) -> 0 | AC735: =IFERROR(VLOOKUP(H735,'[1]Pending Recoveries'!$A:$D,4,0),0) -> 0 | AD735: =AA735-AC735 -> 0 | AE735: =AC735-M735 -> 0
H736: 10130085 | I736: Gomukh Repura | J736: Pending | K736: 0 | L736: 15.52 | M736: 0 | N736: =K736+M736+L736 -> 15.52 | O736: 0 | P736: 0 | Q736: 0 | R736: 0 | S736: 0 | T736: 0 | U736: 0 | V736: 0 | W736: 0 | Y736: 0 | Z736: 0 | AA736: =N736-SUM(O736:Z736) -> 15.52 | AC736: =IFERROR(VLOOKUP(H736,'[1]Pending Recoveries'!$A:$D,4,0),0) -> 0 | AD736: =AA736-AC736 -> 15.52 | AE736: =AC736-M736 -> 0
H737: 10130091 | I737: Gomukh Nipur | J737: Pending | K737: 0 | L737: 0 | M737: 0 | N737: =K737+M737+L737 -> 0 | O737: 0 | P737: 0 | Q737: 0 | R737: 0 | S737: 0 | T737: 0 | U737: 0 | V737: 0 | W737: 0 | Y737: 0 | Z737: 0 | AA737: =N737-SUM(O737:Z737) -> 0 | AC737: =IFERROR(VLOOKUP(H737,'[1]Pending Recoveries'!$A:$D,4,0),0) -> 0 | AD737: =AA737-AC737 -> 0 | AE737: =AC737-M737 -> 0
H738: 10130093 | I738: Gomukh Sherpur Narsari East | J738: Pending | K738: 0 | L738: 45.8 | M738: 0 | N738: =K738+M738+L738 -> 45.8 | O738: 0 | P738: 0 | Q738: 0 | R738: 0 | S738: 0 | T738: 0 | U738: 0 | V738: 0 | W738: 0 | Y738: 0 | Z738: 0 | AA738: =N738-SUM(O738:Z738) -> 45.8 | AC738: =IFERROR(VLOOKUP(H738,'[1]Pending Recoveries'!$A:$D,4,0),0) -> 0 | AD738: =AA738-AC738 -> 45.8 | AE738: =AC738-M738 -> 0
H739: 10130097 | I739: Gomukh Karhatti | J739: Pending | K739: 0 | L739: 348.52 | M739: 0 | N739: =K739+M739+L739 -> 348.52 | O739: 0 | P739: 0 | Q739: 0 | R739: 0 | S739: 0 | T739: 0 | U739: 0 | V739: 0 | W739: 0 | Y739: 0 | Z739: 0 | AA739: =N739-SUM(O739:Z739) -> 348.52 | AC739: =IFERROR(VLOOKUP(H739,'[1]Pending Recoveries'!$A:$D,4,0),0) -> 0 | AD739: =AA739-AC739 -> 348.52 | AE739: =AC739-M739 -> 0
... H759: 10090058 | I759: NAWKADIH | J759: Pending | K759: 0 | L759: 635.04 | M759: 0 | N759: =K759+M759+L759 -> 635.04 | O759: 635.04 | P759: 0 | Q759: 0 | R759: 0 | S759: 0 | T759: 0 | U759: 0 | V759: 0 | W759: 0 | Y759: 0 | Z759: 0 | AA759: =N759-SUM(O759:Z759) -> 0 | AC759: =IFERROR(VLOOKUP(H759,'[1]Pending Recoveries'!$A:$D,4,0),0) -> 0 | AD759: =AA759-AC759 -> 0 | AE759: =AC759-M759 -> 0
H760: 10120116 | J760: Pending | K760: 0 | L760: 0 | M760: 0 | N760: =K760+M760+L760 -> 0 | O760: 0 | P760: 0 | Q760: 0 | R760: 0 | S760: 0 | T760: 0 | U760: 0 | V760: 0 | W760: 0 | Y760: 0 | Z760: 0 | AA760: =N760-SUM(O760:Z760) -> 0 | AC760: =IFERROR(VLOOKUP(H760,'[1]Pending Recoveries'!$A:$D,4,0),0) -> 0 | AD760: =AA760-AC760 -> 0 | AE760: =AC760-M760 -> 0
H761: 10130100 | J761: Pending | K761: 0 | L761: 109.8 | M761: 0 | N761: =K761+M761+L761 -> 109.8 | O761: 0 | P761: 0 | Q761: 0 | R761: 0 | S761: 0 | T761: 0 | U761: 0 | V761: 0 | W761: 0 | Y761: 0 | Z761: 0 | AA761: =N761-SUM(O761:Z761) -> 109.8 | AC761: =IFERROR(VLOOKUP(H761,'[1]Pending Recoveries'!$A:$D,4,0),0) -> 0 | AD761: =AA761-AC761 -> 109.8 | AE761: =AC761-M761 -> 0
H762: 10530084 | J762: Pending | K762: 0 | L762: 0 | M762: 0 | N762: =K762+M762+L762 -> 0 | O762: 0 | P762: 0 | Q762: 0 | R762: 0 | S762: 0 | T762: 0 | U762: 0 | V762: 0 | W762: 0 | Y762: 0 | Z762: 0 | AA762: =N762-SUM(O762:Z762) -> 0 | AC762: =IFERROR(VLOOKUP(H762,'[1]Pending Recoveries'!$A:$D,4,0),0) -> 0 | AD762: =AA762-AC762 -> 0 | AE762: =AC762-M762 -> 0
H763: 10530091 | J763: Pending | K763: 0 | L763: 0 | M763: 0 | N763: =K763+M763+L763 -> 0 | O763: 0 | P763: 0 | Q763: 0 | R763: 0 | S763: 0 | T763: 0 | U763: 0 | V763: 0 | W763: 0 | Y763: 0 | Z763: 0 | AA763: =N763-SUM(O763:Z763) -> 0 | AC763: =IFERROR(VLOOKUP(H763,'[1]Pending Recoveries'!$A:$D,4,0),0) -> 0 | AD763: =AA763-AC763 -> 0 | AE763: =AC763-M763 -> 0
H764: 10530092 | J764: Pending | K764: 0 | L764: 0 | M764: 0 | N764: =K764+M764+L764 -> 0 | O764: 0 | P764: 0 | Q764: 0 | R764: 0 | S764: 0 | T764: 0 | U764: 0 | V764: 0 | W764: 0 | Y764: 0 | Z764: 0 | AA764: =N764-SUM(O764:Z764) -> 0 | AC764: =IFERROR(VLOOKUP(H764,'[1]Pending Recoveries'!$A:$D,4,0),0) -> 0 | AD764: =AA764-AC764 -> 0 | AE764: =AC764-M764 -> 0
H765: 10530097 | J765: Pending | K765: 0 | L765: 0 | M765: 0 | N765: =K765+M765+L765 -> 0 | O765: 0 | P765: 0 | Q765: 0 | R765: 0 | S765: 0 | T765: 0 | U765: 0 | V765: 0 | W765: 0 | Y765: 0 | Z765: 0 | AA765: =N765-SUM(O765:Z765) -> 0 | AC765: =IFERROR(VLOOKUP(H765,'[1]Pending Recoveries'!$A:$D,4,0),0) -> 0 | AD765: =AA765-AC765 -> 0 | AE765: =AC765-M765 -> 0
H766: 10560012 | I766: Gomukh Kharawa | J766: Pending | K766: 0 | L766: 0 | M766: 458.32 | N766: =K766+M766+L766 -> 458.32 | O766: 458.32 | P766: 0 | Q766: 0 | R766: 0 | S766: 0 | T766: 0 | U766: 0 | V766: 0 | W766: 0 | Y766: 0 | Z766: 0 | AA766: =N766-SUM(O766:Z766) -> 0 | AC766: =IFERROR(VLOOKUP(H766,'[1]Pending Recoveries'!$A:$D,4,0),0) -> 458.32 | AD766: =AA766-AC766 -> -458.32 | AE766: =AC766-M766 -> 0
H767: 10560004 | I767: Gomukh Nawada | J767: Pending | K767: 0 | L767: 0 | M767: 697.04 | N767: =K767+M767+L767 -> 697.04 | O767: 697.04 | P767: 0 | Q767: 0 | R767: 0 | S767: 0 | T767: 0 | U767: 0 | V767: 0 | W767: 0 | Y767: 0 | Z767: 0 | AA767: =N767-SUM(O767:Z767) -> 0 | AC767: =IFERROR(VLOOKUP(H767,'[1]Pending Recoveries'!$A:$D,4,0),0) -> 697.04 | AD767: =AA767-AC767 -> -697.04 | AE767: =AC767-M767 -> 0
H768: 10560017 | I768: Gomukh Telihar | J768: Pending | K768: 0 | L768: 0 | M768: 219.6 | N768: =K768+M768+L768 -> 219.6 | O768: 219.6 | P768: 0 | Q768: 0 | R768: 0 | S768: 0 | T768: 0 | U768: 0 | V768: 0 | W768: 0 | Y768: 0 | Z768: 0 | AA768: =N768-SUM(O768:Z768) -> 0 | AC768: =IFERROR(VLOOKUP(H768,'[1]Pending Recoveries'!$A:$D,4,0),0) -> 219.6 | AD768: =AA768-AC768 -> -219.6 | AE768: =AC768-M768 -> 0
H769: 10520005 | I769: Rakesh Dairy | J769: Pending | K769: 0 | L769: 0 | M769: 3486 | N769: =K769+M769+L769 -> 3486 | O769: 0 | P769: 0 | Q769: 0 | R769: 0 | S769: 0 | T769: 0 | U769: 0 | V769: 0 | W769: 0 | Y769: 0 | Z769: 0 | AA769: =N769-SUM(O769:Z769) -> 3486 | AC769: =IFERROR(VLOOKUP(H769,'[1]Pending Recoveries'!$A:$D,4,0),0) -> 3486 | AD769: =AA769-AC769 -> 0 | AE769: =AC769-M769 -> 0
H770: 10570001 | I770: Karian | J770: Pending | K770: 0 | L770: 0 | M770: 159.9 | N770: =K770+M770+L770 -> 159.9 | O770: 0 | P770: 0 | Q770: 0 | R770: 0 | S770: 0 | T770: 0 | U770: 0 | V770: 0 | W770: 0 | Y770: 0 | Z770: 0 | AA770: =N770-SUM(O770:Z770) -> 159.9 | AC770: =IFERROR(VLOOKUP(H770,'[1]Pending Recoveries'!$A:$D,4,0),0) -> 159.9 | AD770: =AA770-AC770 -> 0 | AE770: =AC770-M770 -> 0
H771: 10570003 | I771: Teghara | J771: Pending | K771: 0 | L771: 0 | M771: 178.2 | N771: =K771+M771+L771 -> 178.2 | O771: 0 | P771: 0 | Q771: 0 | R771: 0 | S771: 0 | T771: 0 | U771: 0 | V771: 0 | W771: 0 | Y771: 0 | Z771: 0 | AA771: =N771-SUM(O771:Z771) -> 178.2 | AC771: =IFERROR(VLOOKUP(H771,'[1]Pending Recoveries'!$A:$D,4,0),0) -> 178.2 | AD771: =AA771-AC771 -> 0 | AE771: =AC771-M771 -> 0
H772: 10570007 | I772: Basantpur | J772: Pending | K772: 0 | L772: 0 | M772: 141.6 | N772: =K772+M772+L772 -> 141.6 | O772: 129.8 | P772: 0 | Q772: 0 | R772: 0 | S772: 0 | T772: 0 | U772: 0 | V772: 0 | W772: 0 | Y772: 0 | Z772: 0 | AA772: =N772-SUM(O772:Z772) -> 11.8 | AC772: =IFERROR(VLOOKUP(H772,'[1]Pending Recoveries'!$A:$D,4,0),0) -> 141.6 | AD772: =AA772-AC772 -> -129.8 | AE772: =AC772-M772 -> 0
H773: 10570008 | I773: Chakoti | J773: Pending | K773: 0 | L773: 0 | M773: 187.35 | N773: =K773+M773+L773 -> 187.35 | O773: 129.8 | P773: 0 | Q773: 0 | R773: 0 | S773: 0 | T773: 0 | U773: 0 | V773: 0 | W773: 0 | Y773: 0 | Z773: 0 | AA773: =N773-SUM(O773:Z773) -> 57.55 | AC773: =IFERROR(VLOOKUP(H773,'[1]Pending Recoveries'!$A:$D,4,0),0) -> 187.35 | AD773: =AA773-AC773 -> -129.8 | AE773: =AC773-M773 -> 0
H774: 10570009 | I774: Nathudawar | J774: Pending | K774: 0 | L774: 0 | M774: 233.1 | N774: =K774+M774+L774 -> 233.1 | O774: 129.8 | P774: 0 | Q774: 0 | R774: 0 | S774: 0 | T774: 0 | U774: 0 | V774: 0 | W774: 0 | Y774: 0 | Z774: 0 | AA774: =N774-SUM(O774:Z774) -> 103.3 | AC774: =IFERROR(VLOOKUP(H774,'[1]Pending Recoveries'!$A:$D,4,0),0) -> 233.1 | AD774: =AA774-AC774 -> -129.8 | AE774: =AC774-M774 -> 0
H775: 10570017 | I775: Dewanpur | J775: Pending | K775: 0 | L775: 0 | M775: 187.35 | N775: =K775+M775+L775 -> 187.35 | O775: 0 | P775: 0 | Q775: 0 | R775: 0 | S775: 0 | T775: 0 | U775: 0 | V775: 0 | W775: 0 | Y775: 0 | Z775: 0 | AA775: =N775-SUM(O775:Z775) -> 187.35 | AC775: =IFERROR(VLOOKUP(H775,'[1]Pending Recoveries'!$A:$D,4,0),0) -> 187.35 | AD775: =AA775-AC775 -> 0 | AE775: =AC775-M775 -> 0
H776: 10570018 | I776: Gohi | J776: Pending | K776: 0 | L776: 0 | M776: 169.05 | N776: =K776+M776+L776 -> 169.05 | O776: 129.8 | P776: 0 | Q776: 0 | R776: 0 | S776: 0 | T776: 0 | U776: 0 | V776: 0 | W776: 0 | Y776: 0 | Z776: 0 | AA776: =N776-SUM(O776:Z776) -> 39.25 | AC776: =IFERROR(VLOOKUP(H776,'[1]Pending Recoveries'!$A:$D,4,0),0) -> 169.05 | AD776: =AA776-AC776 -> -129.8 | AE776: =AC776-M776 -> 0
H777: 10570019 | I777: Matua | J777: Pending | K777: 0 | L777: 0 | M777: 187.35 | N777: =K777+M777+L777 -> 187.35 | O777: 129.8 | P777: 0 | Q777: 0 | R777: 0 | S777: 0 | T777: 0 | U777: 0 | V777: 0 | W777: 0 | Y777: 0 | Z777: 0 | AA777: =N777-SUM(O777:Z777) -> 57.55 | AC777: =IFERROR(VLOOKUP(H777,'[1]Pending Recoveries'!$A:$D,4,0),0) -> 187.35 | AD777: =AA777-AC777 -> -129.8 | AE777: =AC777-M777 -> 0
... H787: 10570045 | I787: Buzurgdoar | J787: Pending | K787: 0 | L787: 0 | M787: 233.1 | N787: =K787+M787+L787 -> 233.1 | O787: 129.8 | P787: 0 | Q787: 0 | R787: 0 | S787: 0 | T787: 0 | U787: 0 | V787: 0 | W787: 0 | Y787: 0 | Z787: 0 | AA787: =N787-SUM(O787:Z787) -> 103.3 | AC787: =IFERROR(VLOOKUP(H787,'[1]Pending Recoveries'!$A:$D,4,0),0) -> 233.1 | AD787: =AA787-AC787 -> -129.8 | AE787: =AC787-M787 -> 0
H788: 10530099 | J788: Pending | K788: 0 | L788: 329.4 | M788: 0 | N788: =K788+M788+L788 -> 329.4 | O788: 0 | P788: 0 | Q788: 0 | R788: 0 | S788: 0 | T788: 0 | U788: 0 | V788: 0 | W788: 0 | Y788: 0 | Z788: 0 | AA788: =N788-SUM(O788:Z788) -> 329.4 | AC788: =IFERROR(VLOOKUP(H788,'[1]Pending Recoveries'!$A:$D,4,0),0) -> 0 | AD788: =AA788-AC788 -> 329.4 | AE788: =AC788-M788 -> 0
H789: 10520011 | I789: Nand Kishor Kumar (Maheshkhut) | J789: Pending | K789: 0 | L789: 0 | M789: 2787.56 | N789: =K789+M789+L789 -> 2787.56 | O789: 0 | P789: 2781.9 | Q789: 0 | R789: 0 | S789: 0 | T789: 0 | U789: 0 | V789: 0 | W789: 0 | Y789: 0 | Z789: 0 | AA789: =N789-SUM(O789:Z789) -> 5.66 | AC789: =IFERROR(VLOOKUP(H789,'[1]Pending Recoveries'!$A:$D,4,0),0) -> 2787.56 | AD789: =AA789-AC789 -> -2781.9 | AE789: =AC789-M789 -> 0
H790: 10140201 | I790: Gomukh Lakshman dera Raja | J790: Pending | K790: 0 | L790: 0 | M790: 54.9 | N790: =K790+M790+L790 -> 54.9 | O790: 0 | P790: 54.9 | Q790: 0 | R790: 0 | S790: 0 | T790: 0 | U790: 0 | V790: 0 | W790: 0 | Y790: 0 | Z790: 0 | AA790: =N790-SUM(O790:Z790) -> 0 | AC790: =IFERROR(VLOOKUP(H790,'[1]Pending Recoveries'!$A:$D,4,0),0) -> 54.9 | AD790: =AA790-AC790 -> -54.9 | AE790: =AC790-M790 -> 0
H791: 10140176 | I791: Gomukh Chakki Janardan Yadav | J791: Pending | K791: 0 | L791: 0 | M791: 54.9 | N791: =K791+M791+L791 -> 54.9 | O791: 0 | P791: 0 | Q791: 0 | R791: 0 | S791: 0 | T791: 0 | U791: 0 | V791: 0 | W791: 0 | Y791: 0 | Z791: 0 | AA791: =N791-SUM(O791:Z791) -> 54.9 | AC791: =IFERROR(VLOOKUP(H791,'[1]Pending Recoveries'!$A:$D,4,0),0) -> 54.9 | AD791: =AA791-AC791 -> 0 | AE791: =AC791-M791 -> 0
H792: 10140197 | I792: Gumukh Mathiyapur | J792: Pending | K792: 0 | L792: 0 | M792: 961.12 | N792: =K792+M792+L792 -> 961.12 | O792: 0 | P792: 0 | Q792: 0 | R792: 0 | S792: 0 | T792: 0 | U792: 0 | V792: 0 | W792: 0 | Y792: 0 | Z792: 0 | AA792: =N792-SUM(O792:Z792) -> 961.12 | AC792: =IFERROR(VLOOKUP(H792,'[1]Pending Recoveries'!$A:$D,4,0),0) -> 961.12 | AD792: =AA792-AC792 -> 0 | AE792: =AC792-M792 -> 0
H793: 10140194 | I793: Gumukh Orap Khurd | J793: Pending | K793: 0 | L793: 0 | M793: 567.65086 | N793: =K793+M793+L793 -> 567.65086 | O793: 0 | P793: 459 | Q793: 0 | R793: 0 | S793: 0 | T793: 0 | U793: 0 | V793: 0 | W793: 0 | Y793: 0 | Z793: 0 | AA793: =N793-SUM(O793:Z793) -> 108.65086 | AC793: =IFERROR(VLOOKUP(H793,'[1]Pending Recoveries'!$A:$D,4,0),0) -> 567.65086 | AD793: =AA793-AC793 -> -459 | AE793: =AC793-M793 -> 0
H794: 10140205 | I794: Gumukh Niyajipur Nakchhedi pathak dera | J794: Pending | K794: 0 | L794: 0 | M794: 602.16 | N794: =K794+M794+L794 -> 602.16 | O794: 0 | P794: 590.36 | Q794: 0 | R794: 0 | S794: 0 | T794: 0 | U794: 0 | V794: 0 | W794: 0 | Y794: 0 | Z794: 0 | AA794: =N794-SUM(O794:Z794) -> 11.8 | AC794: =IFERROR(VLOOKUP(H794,'[1]Pending Recoveries'!$A:$D,4,0),0) -> 602.16 | AD794: =AA794-AC794 -> -590.36 | AE794: =AC794-M794 -> 0
H795: 10140181 | I795: Tiyar A2 Milk Producer Company Limited | J795: Pending | K795: 0 | L795: 0 | M795: 838.64 | N795: =K795+M795+L795 -> 838.64 | O795: 0 | P795: 0 | Q795: 0 | R795: 0 | S795: 0 | T795: 0 | U795: 0 | V795: 0 | W795: 0 | Y795: 0 | Z795: 0 | AA795: =N795-SUM(O795:Z795) -> 838.64 | AC795: =IFERROR(VLOOKUP(H795,'[1]Pending Recoveries'!$A:$D,4,0),0) -> 838.64 | AD795: =AA795-AC795 -> 0 | AE795: =AC795-M795 -> 0
H796: 10140141 | I796: Gomukh Bimhnath Girdhar Baraw | J796: Pending | K796: 0 | L796: 0 | M796: 141.6 | N796: =K796+M796+L796 -> 141.6 | O796: 0 | P796: 129.8 | Q796: 0 | R796: 0 | S796: 0 | T796: 0 | U796: 0 | V796: 0 | W796: 0 | Y796: 0 | Z796: 0 | AA796: =N796-SUM(O796:Z796) -> 11.8 | AC796: =IFERROR(VLOOKUP(H796,'[1]Pending Recoveries'!$A:$D,4,0),0) -> 141.6 | AD796: =AA796-AC796 -> -129.8 | AE796: =AC796-M796 -> 0
H797: 10140198 | I797: Gomukh Raghunathpur Dasrath | J797: Pending | K797: 0 | L797: 0 | M797: 102.6 | N797: =K797+M797+L797 -> 102.6 | O797: 0 | P797: 102.6 | Q797: 0 | R797: 0 | S797: 0 | T797: 0 | U797: 0 | V797: 0 | W797: 0 | Y797: 0 | Z797: 0 | AA797: =N797-SUM(O797:Z797) -> 0 | AC797: =IFERROR(VLOOKUP(H797,'[1]Pending Recoveries'!$A:$D,4,0),0) -> 102.6 | AD797: =AA797-AC797 -> -102.6 | AE797: =AC797-M797 -> 0
H798: 10140175 | I798: Gomukh Koilawar Roma Bharti | J798: Pending | K798: 0 | L798: 0 | M798: 513 | N798: =K798+M798+L798 -> 513 | O798: 0 | P798: 0 | Q798: 0 | R798: 0 | S798: 0 | T798: 0 | U798: 0 | V798: 0 | W798: 0 | Y798: 0 | Z798: 0 | AA798: =N798-SUM(O798:Z798) -> 513 | AC798: =IFERROR(VLOOKUP(H798,'[1]Pending Recoveries'!$A:$D,4,0),0) -> 513 | AD798: =AA798-AC798 -> 0 | AE798: =AC798-M798 -> 0
H799: 10140191 | I799: Gumukk JP Dera | J799: Pending | K799: 0 | L799: 0 | M799: 451.12 | N799: =K799+M799+L799 -> 451.12 | O799: 0 | P799: 0 | Q799: 0 | R799: 0 | S799: 0 | T799: 0 | U799: 0 | V799: 0 | W799: 0 | Y799: 0 | Z799: 0 | AA799: =N799-SUM(O799:Z799) -> 451.12 | AC799: =IFERROR(VLOOKUP(H799,'[1]Pending Recoveries'!$A:$D,4,0),0) -> 451.12 | AD799: =AA799-AC799 -> 0 | AE799: =AC799-M799 -> 0
H800: 10140206 | I800: Gumukh Basawkala Dahpura Tola | J800: Pending | K800: 0 | L800: 0 | M800: 206.45086 | N800: =K800+M800+L800 -> 206.45086 | O800: 0 | P800: 115.02 | Q800: 0 | R800: 0 | S800: 0 | T800: 0 | U800: 0 | V800: 0 | W800: 0 | Y800: 0 | Z800: 0 | AA800: =N800-SUM(O800:Z800) -> 91.430862 | AC800: =IFERROR(VLOOKUP(H800,'[1]Pending Recoveries'!$A:$D,4,0),0) -> 206.45086 | AD800: =AA800-AC800 -> -115.02 | AE800: =AC800-M800 -> 0
... H810: 10600013 | I810: Gomukh Chhotaki hardiya | J810: Pending | K810: 0 | L810: 0 | M810: 283.2 | N810: =K810+M810+L810 -> 283.2 | O810: 0 | P810: 259.6 | Q810: 0 | R810: 0 | S810: 0 | T810: 0 | U810: 0 | V810: 0 | W810: 0 | Y810: 0 | Z810: 0 | AA810: =N810-SUM(O810:Z810) -> 23.6 | AC810: =IFERROR(VLOOKUP(H810,'[1]Pending Recoveries'!$A:$D,4,0),0) -> 283.2 | AD810: =AA810-AC810 -> -259.6 | AE810: =AC810-M810 -> 0
H811: 10540042 | I811: Gomukh Balaur | J811: Pending | M811: 531.52 | N811: =K811+M811+L811 -> 531.52 | O811: 0 | P811: 0 | Q811: 0 | R811: 0 | S811: 0 | T811: 0 | U811: 0 | V811: 0 | W811: 0 | Y811: 0 | Z811: 0 | AA811: =N811-SUM(O811:Z811) -> 531.52 | AC811: =IFERROR(VLOOKUP(H811,'[1]Pending Recoveries'!$A:$D,4,0),0) -> 531.52 | AD811: =AA811-AC811 -> 0 | AE811: =AC811-M811 -> 0
H812: 10540046 | I812: Gomukh Hathwan | J812: Pending | M812: 531.52 | N812: =K812+M812+L812 -> 531.52 | O812: 0 | P812: 0 | Q812: 0 | R812: 0 | S812: 0 | T812: 0 | U812: 0 | V812: 0 | W812: 0 | Y812: 0 | Z812: 0 | AA812: =N812-SUM(O812:Z812) -> 531.52 | AC812: =IFERROR(VLOOKUP(H812,'[1]Pending Recoveries'!$A:$D,4,0),0) -> 531.52 | AD812: =AA812-AC812 -> 0 | AE812: =AC812-M812 -> 0
H813: 10070024 | I813: Haripur - Sanjay | J813: Pending | M813: 348.52 | N813: =K813+M813+L813 -> 348.52 | O813: 0 | P813: 0 | Q813: 0 | R813: 0 | S813: 0 | T813: 0 | U813: 0 | V813: 0 | W813: 0 | Y813: 0 | Z813: 0 | AA813: =N813-SUM(O813:Z813) -> 348.52 | AC813: =IFERROR(VLOOKUP(H813,'[1]Pending Recoveries'!$A:$D,4,0),0) -> 348.52 | AD813: =AA813-AC813 -> 0 | AE813: =AC813-M813 -> 0
H814: 10070077 | I814: Gomukh Bari chak Gogri | J814: Pending | M814: 348.52 | N814: =K814+M814+L814 -> 348.52 | O814: 0 | P814: 0 | Q814: 0 | R814: 0 | S814: 0 | T814: 0 | U814: 0 | V814: 0 | W814: 0 | Y814: 0 | Z814: 0 | AA814: =N814-SUM(O814:Z814) -> 348.52 | AC814: =IFERROR(VLOOKUP(H814,'[1]Pending Recoveries'!$A:$D,4,0),0) -> 348.52 | AD814: =AA814-AC814 -> 0 | AE814: =AC814-M814 -> 0
H815: 10070018 | I815: Gomukh Arariya Karjaniya | J815: Pending | M815: 348.52 | N815: =K815+M815+L815 -> 348.52 | O815: 0 | P815: 0 | Q815: 0 | R815: 0 | S815: 0 | T815: 0 | U815: 0 | V815: 0 | W815: 0 | Y815: 0 | Z815: 0 | AA815: =N815-SUM(O815:Z815) -> 348.52 | AC815: =IFERROR(VLOOKUP(H815,'[1]Pending Recoveries'!$A:$D,4,0),0) -> 348.52 | AD815: =AA815-AC815 -> 0 | AE815: =AC815-M815 -> 0
H816: 10070043 | I816: Araria | J816: Pending | M816: 348.52 | N816: =K816+M816+L816 -> 348.52 | O816: 0 | P816: 0 | Q816: 0 | R816: 0 | S816: 0 | T816: 0 | U816: 0 | V816: 0 | W816: 0 | Y816: 0 | Z816: 0 | AA816: =N816-SUM(O816:Z816) -> 348.52 | AC816: =IFERROR(VLOOKUP(H816,'[1]Pending Recoveries'!$A:$D,4,0),0) -> 348.52 | AD816: =AA816-AC816 -> 0 | AE816: =AC816-M816 -> 0
H817: 10070019 | I817: Gomukh Aariya Dummer Kothi | J817: Pending | M817: 348.52 | N817: =K817+M817+L817 -> 348.52 | O817: 0 | P817: 0 | Q817: 0 | R817: 0 | S817: 0 | T817: 0 | U817: 0 | V817: 0 | W817: 0 | Y817: 0 | Z817: 0 | AA817: =N817-SUM(O817:Z817) -> 348.52 | AC817: =IFERROR(VLOOKUP(H817,'[1]Pending Recoveries'!$A:$D,4,0),0) -> 348.52 | AD817: =AA817-AC817 -> 0 | AE817: =AC817-M817 -> 0
H818: 10070020 | I818: Gomukh Balha | J818: Pending | M818: 348.52 | N818: =K818+M818+L818 -> 348.52 | O818: 0 | P818: 0 | Q818: 0 | R818: 0 | S818: 0 | T818: 0 | U818: 0 | V818: 0 | W818: 0 | Y818: 0 | Z818: 0 | AA818: =N818-SUM(O818:Z818) -> 348.52 | AC818: =IFERROR(VLOOKUP(H818,'[1]Pending Recoveries'!$A:$D,4,0),0) -> 348.52 | AD818: =AA818-AC818 -> 0 | AE818: =AC818-M818 -> 0
H819: 10070026 | I819: Araria - Ankesh | J819: Pending | M819: 697.04 | N819: =K819+M819+L819 -> 697.04 | O819: 0 | P819: 0 | Q819: 0 | R819: 0 | S819: 0 | T819: 0 | U819: 0 | V819: 0 | W819: 0 | Y819: 0 | Z819: 0 | AA819: =N819-SUM(O819:Z819) -> 697.04 | AC819: =IFERROR(VLOOKUP(H819,'[1]Pending Recoveries'!$A:$D,4,0),0) -> 697.04 | AD819: =AA819-AC819 -> 0 | AE819: =AC819-M819 -> 0
H820: 10410001 | I820: Bhramarpur | J820: Pending | M820: 697.04 | N820: =K820+M820+L820 -> 697.04 | O820: 0 | P820: 0 | Q820: 0 | R820: 0 | S820: 0 | T820: 0 | U820: 0 | V820: 0 | W820: 0 | Y820: 0 | Z820: 0 | AA820: =N820-SUM(O820:Z820) -> 697.04 | AC820: =IFERROR(VLOOKUP(H820,'[1]Pending Recoveries'!$A:$D,4,0),0) -> 697.04 | AD820: =AA820-AC820 -> 0 | AE820: =AC820-M820 -> 0
H821: 10480003 | I821: Sheela Devi | J821: Pending | M821: 697.04 | N821: =K821+M821+L821 -> 697.04 | O821: 0 | P821: 0 | Q821: 0 | R821: 0 | S821: 0 | T821: 0 | U821: 0 | V821: 0 | W821: 0 | Y821: 0 | Z821: 0 | AA821: =N821-SUM(O821:Z821) -> 697.04 | AC821: =IFERROR(VLOOKUP(H821,'[1]Pending Recoveries'!$A:$D,4,0),0) -> 697.04 | AD821: =AA821-AC821 -> 0 | AE821: =AC821-M821 -> 0
H822: 10380001 | I822: SONBARSHA 1 | J822: Pending | M822: 697.04 | N822: =K822+M822+L822 -> 697.04 | O822: 0 | P822: 0 | Q822: 0 | R822: 0 | S822: 0 | T822: 0 | U822: 0 | V822: 0 | W822: 0 | Y822: 0 | Z822: 0 | AA822: =N822-SUM(O822:Z822) -> 697.04 | AC822: =IFERROR(VLOOKUP(H822,'[1]Pending Recoveries'!$A:$D,4,0),0) -> 697.04 | AD822: =AA822-AC822 -> 0 | AE822: =AC822-M822 -> 0
... H832: 10570051 | I832: Jagdishpur | J832: Pending | M832: 9.15 | N832: =K832+M832+L832 -> 9.15 | O832: 0 | P832: 0 | Q832: 0 | R832: 0 | S832: 0 | T832: 0 | U832: 0 | V832: 0 | W832: 0 | Y832: 0 | Z832: 0 | AA832: =N832-SUM(O832:Z832) -> 9.15 | AC832: =IFERROR(VLOOKUP(H832,'[1]Pending Recoveries'!$A:$D,4,0),0) -> 9.15 | AD832: =AA832-AC832 -> 0 | AE832: =AC832-M832 -> 0
H833: Grand Total | K833: =SUM(K4:K832) -> 68293 | L833: =SUM(L4:L832) -> 143064.82 | M833: =SUM(M4:M832) -> 189878.13 | N833: =SUM(N4:N832) -> 401235.95 | O833: =SUM(O4:O832) -> 14675.06 | P833: =SUM(P4:P832) -> 27705.3 | Q833: =SUM(Q4:Q832) -> 0 | R833: =SUM(R4:R832) -> 0 | ... AE833: =SUM(AE4:AE832) -> 0
L836: Deduction file value
L837: 46113 | M837: 49058
L838: 46143 | M838: =M833-M837 -> 140820.13
L839: 46174 | M839: 63252
L840: 46204
L841: 46235
L842: 46266
L843: 46296
L844: 46327
L845: 46357
...

Sheet Issue
A1: Date | B1: Type | C1: Challan No | D1: From Location Code | E1: Location | F1: Type of Location | G1: To BMC/MPG Code | H1: BMC MPG Name | I1: Type of Location2 | J1: Item Name | K1: UoM | L1: Qty Issued | M1: Rate | N1: Amt | O1: Recoverable | P1: Recovery Done | Q1: Remarks
A2: 45748 | B2: Transfer | C2: 120 | D2: 1 | E2: =IFERROR(VLOOKUP(Table4[[#This Row],[From Location Code]],Table5[#All],3,0),"") -> Munger | F2: =IFERROR(VLOOKUP(Table4[[#This Row],[From Location Code]],Table5[#All],2,0),"") -> Main Godown | G2: 1014 | H2: =IFERROR(VLOOKUP(Table4[[#This Row],[To BMC/MPG Code]],Table5[#All],3,0),"") -> Dumraon | I2: =IFERROR(VLOOKUP(Table4[[#This Row],[To BMC/MPG Code]],Table5[#All],2,0),"") -> BMC | J2: Sample Bottle 100 ML | K2: =IFERROR(VLOOKUP(Table4[[#This Row],[Item Name]],Table2[[Item Name]:[UoM]],2,0),"") -> Nos | L2: 68 | M2: =IFERROR(VLOOKUP(Table4[[#This Row],[Item Name]],Table2[[#All],[Item Name]:[Open Rate]],8,0),"") -> 2.83 | N2: =IFERROR(+Table4[[#This Row],[Qty Issued]]*Table4[[#This Row],[Rate]],"") -> 192.44 | O2: No | P2: NA
A3: 45748 | B3: Transfer | C3: 120 | D3: 1 | E3: =IFERROR(VLOOKUP(Table4[[#This Row],[From Location Code]],Table5[#All],3,0),"") -> Munger | F3: =IFERROR(VLOOKUP(Table4[[#This Row],[From Location Code]],Table5[#All],2,0),"") -> Main Godown | G3: 1014 | H3: =IFERROR(VLOOKUP(Table4[[#This Row],[To BMC/MPG Code]],Table5[#All],3,0),"") -> Dumraon | I3: =IFERROR(VLOOKUP(Table4[[#This Row],[To BMC/MPG Code]],Table5[#All],2,0),"") -> BMC | J3: MPG Register | K3: =IFERROR(VLOOKUP(Table4[[#This Row],[Item Name]],Table2[[Item Name]:[UoM]],2,0),"") -> Nos | L3: 51 | M3: =IFERROR(VLOOKUP(Table4[[#This Row],[Item Name]],Table2[[#All],[Item Name]:[Open Rate]],8,0),"") -> 129.8 | N3: =IFERROR(+Table4[[#This Row],[Qty Issued]]*Table4[[#This Row],[Rate]],"") -> 6619.8 | O3: No | P3: NA
A4: 45748 | B4: Transfer | C4: 120 | D4: 1 | E4: =IFERROR(VLOOKUP(Table4[[#This Row],[From Location Code]],Table5[#All],3,0),"") -> Munger | F4: =IFERROR(VLOOKUP(Table4[[#This Row],[From Location Code]],Table5[#All],2,0),"") -> Main Godown | G4: 1014 | H4: =IFERROR(VLOOKUP(Table4[[#This Row],[To BMC/MPG Code]],Table5[#All],3,0),"") -> Dumraon | I4: =IFERROR(VLOOKUP(Table4[[#This Row],[To BMC/MPG Code]],Table5[#All],2,0),"") -> BMC | J4: Milk Cane Plunger S. S. | K4: =IFERROR(VLOOKUP(Table4[[#This Row],[Item Name]],Table2[[Item Name]:[UoM]],2,0),"") -> Nos | L4: 13 | M4: =IFERROR(VLOOKUP(Table4[[#This Row],[Item Name]],Table2[[#All],[Item Name]:[Open Rate]],8,0),"") -> 112.1 | N4: =IFERROR(+Table4[[#This Row],[Qty Issued]]*Table4[[#This Row],[Rate]],"") -> 1457.3 | O4: No | P4: NA
A5: 45748 | B5: Transfer | C5: 120 | D5: 1 | E5: =IFERROR(VLOOKUP(Table4[[#This Row],[From Location Code]],Table5[#All],3,0),"") -> Munger | F5: =IFERROR(VLOOKUP(Table4[[#This Row],[From Location Code]],Table5[#All],2,0),"") -> Main Godown | G5: 1014 | H5: =IFERROR(VLOOKUP(Table4[[#This Row],[To BMC/MPG Code]],Table5[#All],3,0),"") -> Dumraon | I5: =IFERROR(VLOOKUP(Table4[[#This Row],[To BMC/MPG Code]],Table5[#All],2,0),"") -> BMC | J5: Plastic Strainer | K5: =IFERROR(VLOOKUP(Table4[[#This Row],[Item Name]],Table2[[Item Name]:[UoM]],2,0),"") -> Nos | L5: 14 | M5: =IFERROR(VLOOKUP(Table4[[#This Row],[Item Name]],Table2[[#All],[Item Name]:[Open Rate]],8,0),"") -> 29.5 | N5: =IFERROR(+Table4[[#This Row],[Qty Issued]]*Table4[[#This Row],[Rate]],"") -> 413 | O5: No | P5: NA
A6: 45748 | B6: Transfer | C6: 120 | D6: 1 | E6: =IFERROR(VLOOKUP(Table4[[#This Row],[From Location Code]],Table5[#All],3,0),"") -> Munger | F6: =IFERROR(VLOOKUP(Table4[[#This Row],[From Location Code]],Table5[#All],2,0),"") -> Main Godown | G6: 1014 | H6: =IFERROR(VLOOKUP(Table4[[#This Row],[To BMC/MPG Code]],Table5[#All],3,0),"") -> Dumraon | I6: =IFERROR(VLOOKUP(Table4[[#This Row],[To BMC/MPG Code]],Table5[#All],2,0),"") -> BMC | J6: Eko Day Cleaning Sol | K6: =IFERROR(VLOOKUP(Table4[[#This Row],[Item Name]],Table2[[Item Name]:[UoM]],2,0),"") -> Nos | L6: 61 | M6: =IFERROR(VLOOKUP(Table4[[#This Row],[Item Name]],Table2[[#All],[Item Name]:[Open Rate]],8,0),"") -> 348.52 | N6: =IFERROR(+Table4[[#This Row],[Qty Issued]]*Table4[[#This Row],[Rate]],"") -> 21259.72 | O6: No | P6: NA
A7: 45748 | B7: Transfer | C7: 156 | D7: 1 | E7: =IFERROR(VLOOKUP(Table4[[#This Row],[From Location Code]],Table5[#All],3,0),"") -> Munger | F7: =IFERROR(VLOOKUP(Table4[[#This Row],[From Location Code]],Table5[#All],2,0),"") -> Main Godown | G7: 1014 | H7: =IFERROR(VLOOKUP(Table4[[#This Row],[To BMC/MPG Code]],Table5[#All],3,0),"") -> Dumraon | I7: =IFERROR(VLOOKUP(Table4[[#This Row],[To BMC/MPG Code]],Table5[#All],2,0),"") -> BMC | J7: FAT Scan Weekly | K7: =IFERROR(VLOOKUP(Table4[[#This Row],[Item Name]],Table2[[Item Name]:[UoM]],2,0),"") -> Nos | L7: 39 | M7: =IFERROR(VLOOKUP(Table4[[#This Row],[Item Name]],Table2[[#All],[Item Name]:[Open Rate]],8,0),"") -> 348.52 | N7: =IFERROR(+Table4[[#This Row],[Qty Issued]]*Table4[[#This Row],[Rate]],"") -> 13592.28 | O7: No | P7: NA
A8: 45748 | B8: Transfer | C8: 156 | D8: 1 | E8: =IFERROR(VLOOKUP(Table4[[#This Row],[From Location Code]],Table5[#All],3,0),"") -> Munger | F8: =IFERROR(VLOOKUP(Table4[[#This Row],[From Location Code]],Table5[#All],2,0),"") -> Main Godown | G8: 1014 | H8: =IFERROR(VLOOKUP(Table4[[#This Row],[To BMC/MPG Code]],Table5[#All],3,0),"") -> Dumraon | I8: =IFERROR(VLOOKUP(Table4[[#This Row],[To BMC/MPG Code]],Table5[#All],2,0),"") -> BMC | J8: Eco Power Solution | K8: =IFERROR(VLOOKUP(Table4[[#This Row],[Item Name]],Table2[[Item Name]:[UoM]],2,0),"") -> Nos | L8: 3 | M8: =IFERROR(VLOOKUP(Table4[[#This Row],[Item Name]],Table2[[#All],[Item Name]:[Open Rate]],8,0),"") -> 348.52 | N8: =IFERROR(+Table4[[#This Row],[Qty Issued]]*Table4[[#This Row],[Rate]],"") -> 1045.56 | O8: No | P8: NA
A9: 45748 | B9: Transfer | C9: 156 | D9: 1 | E9: =IFERROR(VLOOKUP(Table4[[#This Row],[From Location Code]],Table5[#All],3,0),"") -> Munger | F9: =IFERROR(VLOOKUP(Table4[[#This Row],[From Location Code]],Table5[#All],2,0),"") -> Main Godown | G9: 1014 | H9: =IFERROR(VLOOKUP(Table4[[#This Row],[To BMC/MPG Code]],Table5[#All],3,0),"") -> Dumraon | I9: =IFERROR(VLOOKUP(Table4[[#This Row],[To BMC/MPG Code]],Table5[#All],2,0),"") -> BMC | J9: EKO Plunger | K9: =IFERROR(VLOOKUP(Table4[[#This Row],[Item Name]],Table2[[Item Name]:[UoM]],2,0),"") -> Nos | L9: 6 | M9: =IFERROR(VLOOKUP(Table4[[#This Row],[Item Name]],Table2[[#All],[Item Name]:[Open Rate]],8,0),"") -> 56.02 | N9: =IFERROR(+Table4[[#This Row],[Qty Issued]]*Table4[[#This Row],[Rate]],"") -> 336.12 | O9: No | P9: NA
A10: 45748 | B10: Consumed | C10: 169 | D10: 1 | E10: =IFERROR(VLOOKUP(Table4[[#This Row],[From Location Code]],Table5[#All],3,0),"") -> Munger | F10: =IFERROR(VLOOKUP(Table4[[#This Row],[From Location Code]],Table5[#All],2,0),"") -> Main Godown | G10: 10090042 | H10: =IFERROR(VLOOKUP(Table4[[#This Row],[To BMC/MPG Code]],Table5[#All],3,0),"") -> REWAI | I10: =IFERROR(VLOOKUP(Table4[[#This Row],[To BMC/MPG Code]],Table5[#All],2,0),"") -> MPG | J10: Eko Day Cleaning Sol | K10: =IFERROR(VLOOKUP(Table4[[#This Row],[Item Name]],Table2[[Item Name]:[UoM]],2,0),"") -> Nos | L10: 2 | M10: =IFERROR(VLOOKUP(Table4[[#This Row],[Item Name]],Table2[[#All],[Item Name]:[Open Rate]],8,0),"") -> 348.52 | N10: =IFERROR(+Table4[[#This Row],[Qty Issued]]*Table4[[#This Row],[Rate]],"") -> 697.04 | O10: Yes | P10: Pending
A11: 45748 | B11: Consumed | C11: 169 | D11: 1 | E11: =IFERROR(VLOOKUP(Table4[[#This Row],[From Location Code]],Table5[#All],3,0),"") -> Munger | F11: =IFERROR(VLOOKUP(Table4[[#This Row],[From Location Code]],Table5[#All],2,0),"") -> Main Godown | G11: 10090056 | H11: =IFERROR(VLOOKUP(Table4[[#This Row],[To BMC/MPG Code]],Table5[#All],3,0),"") -> NARAYANPUR | I11: =IFERROR(VLOOKUP(Table4[[#This Row],[To BMC/MPG Code]],Table5[#All],2,0),"") -> MPG | J11: Eko Day Cleaning Sol | K11: =IFERROR(VLOOKUP(Table4[[#This Row],[Item Name]],Table2[[Item Name]:[UoM]],2,0),"") -> Nos | L11: 1 | M11: =IFERROR(VLOOKUP(Table4[[#This Row],[Item Name]],Table2[[#All],[Item Name]:[Open Rate]],8,0),"") -> 348.52 | N11: =IFERROR(+Table4[[#This Row],[Qty Issued]]*Table4[[#This Row],[Rate]],"") -> 348.52 | O11: Yes | P11: Pending
A12: 45748 | B12: Consumed | C12: 169 | D12: 1 | E12: =IFERROR(VLOOKUP(Table4[[#This Row],[From Location Code]],Table5[#All],3,0),"") -> Munger | F12: =IFERROR(VLOOKUP(Table4[[#This Row],[From Location Code]],Table5[#All],2,0),"") -> Main Godown | G12: 10090029 | H12: =IFERROR(VLOOKUP(Table4[[#This Row],[To BMC/MPG Code]],Table5[#All],3,0),"") -> RAMNAGAR | I12: =IFERROR(VLOOKUP(Table4[[#This Row],[To BMC/MPG Code]],Table5[#All],2,0),"") -> MPG | J12: Eko Day Cleaning Sol | K12: =IFERROR(VLOOKUP(Table4[[#This Row],[Item Name]],Table2[[Item Name]:[UoM]],2,0),"") -> Nos | L12: 1 | M12: =IFERROR(VLOOKUP(Table4[[#This Row],[Item Name]],Table2[[#All],[Item Name]:[Open Rate]],8,0),"") -> 348.52 | N12: =IFERROR(+Table4[[#This Row],[Qty Issued]]*Table4[[#This Row],[Rate]],"") -> 348.52 | O12: Yes | P12: Pending
A13: 45748 | B13: Consumed | C13: 169 | D13: 1 | E13: =IFERROR(VLOOKUP(Table4[[#This Row],[From Location Code]],Table5[#All],3,0),"") -> Munger | F13: =IFERROR(VLOOKUP(Table4[[#This Row],[From Location Code]],Table5[#All],2,0),"") -> Main Godown | G13: 10090009 | H13: =IFERROR(VLOOKUP(Table4[[#This Row],[To BMC/MPG Code]],Table5[#All],3,0),"") -> SONDHI | I13: =IFERROR(VLOOKUP(Table4[[#This Row],[To BMC/MPG Code]],Table5[#All],2,0),"") -> MPG | J13: Eko Day Cleaning Sol | K13: =IFERROR(VLOOKUP(Table4[[#This Row],[Item Name]],Table2[[Item Name]:[UoM]],2,0),"") -> Nos | L13: 1 | M13: =IFERROR(VLOOKUP(Table4[[#This Row],[Item Name]],Table2[[#All],[Item Name]:[Open Rate]],8,0),"") -> 348.52 | N13: =IFERROR(+Table4[[#This Row],[Qty Issued]]*Table4[[#This Row],[Rate]],"") -> 348.52 | O13: Yes | P13: Pending
... A108: 45749 | B108: Transfer | C108: 170 | D108: 1 | E108: =IFERROR(VLOOKUP(Table4[[#This Row],[From Location Code]],Table5[#All],3,0),"") -> Munger | F108: =IFERROR(VLOOKUP(Table4[[#This Row],[From Location Code]],Table5[#All],2,0),"") -> Main Godown | G108: 1014 | H108: =IFERROR(VLOOKUP(Table4[[#This Row],[To BMC/MPG Code]],Table5[#All],3,0),"") -> Dumraon | I108: =IFERROR(VLOOKUP(Table4[[#This Row],[To BMC/MPG Code]],Table5[#All],2,0),"") -> BMC | J108: MPG Register | K108: =IFERROR(VLOOKUP(Table4[[#This Row],[Item Name]],Table2[[Item Name]:[UoM]],2,0),"") -> Nos | L108: 50 | M108: =IFERROR(VLOOKUP(Table4[[#This Row],[Item Name]],Table2[[#All],[Item Name]:[Open Rate]],8,0),"") -> 129.8 | N108: =IFERROR(+Table4[[#This Row],[Qty Issued]]*Table4[[#This Row],[Rate]],"") -> 6490 | O108: No | P108: NA
A109: 45750 | B109: Consumed | C109: 171 | D109: 1 | E109: =IFERROR(VLOOKUP(Table4[[#This Row],[From Location Code]],Table5[#All],3,0),"") -> Munger | F109: =IFERROR(VLOOKUP(Table4[[#This Row],[From Location Code]],Table5[#All],2,0),"") -> Main Godown | G109: Lab | H109: =IFERROR(VLOOKUP(Table4[[#This Row],[To BMC/MPG Code]],Table5[#All],3,0),"") -> Daya_Lab | I109: =IFERROR(VLOOKUP(Table4[[#This Row],[To BMC/MPG Code]],Table5[#All],2,0),"") -> Lab | J109: Milk Despatch Challan | K109: =IFERROR(VLOOKUP(Table4[[#This Row],[Item Name]],Table2[[Item Name]:[UoM]],2,0),"") -> Nos | L109: 1 | M109: =IFERROR(VLOOKUP(Table4[[#This Row],[Item Name]],Table2[[#All],[Item Name]:[Open Rate]],8,0),"") -> 94.4 | N109: =IFERROR(+Table4[[#This Row],[Qty Issued]]*Table4[[#This Row],[Rate]],"") -> 94.4 | O109: No | P109: NA
A110: 45751 | B110: Consumed | C110: 172 | D110: 1 | E110: =IFERROR(VLOOKUP(Table4[[#This Row],[From Location Code]],Table5[#All],3,0),"") -> Munger | F110: =IFERROR(VLOOKUP(Table4[[#This Row],[From Location Code]],Table5[#All],2,0),"") -> Main Godown | G110: 1001 | H110: =IFERROR(VLOOKUP(Table4[[#This Row],[To BMC/MPG Code]],Table5[#All],3,0),"") -> Majhaul | I110: =IFERROR(VLOOKUP(Table4[[#This Row],[To BMC/MPG Code]],Table5[#All],2,0),"") -> BMC | J110: Buterometer | K110: =IFERROR(VLOOKUP(Table4[[#This Row],[Item Name]],Table2[[Item Name]:[UoM]],2,0),"") -> Nos | L110: 2 | M110: =IFERROR(VLOOKUP(Table4[[#This Row],[Item Name]],Table2[[#All],[Item Name]:[Open Rate]],8,0),"") -> 132.7 | N110: =IFERROR(+Table4[[#This Row],[Qty Issued]]*Table4[[#This Row],[Rate]],"") -> 265.4 | O110: No | P110: NA
A111: 45751 | B111: Consumed | C111: 172 | D111: 1 | E111: =IFERROR(VLOOKUP(Table4[[#This Row],[From Location Code]],Table5[#All],3,0),"") -> Munger | F111: =IFERROR(VLOOKUP(Table4[[#This Row],[From Location Code]],Table5[#All],2,0),"") -> Main Godown | G111: 1001 | H111: =IFERROR(VLOOKUP(Table4[[#This Row],[To BMC/MPG Code]],Table5[#All],3,0),"") -> Majhaul | I111: =IFERROR(VLOOKUP(Table4[[#This Row],[To BMC/MPG Code]],Table5[#All],2,0),"") -> BMC | J111: Lactometer 0-40 | K111: =IFERROR(VLOOKUP(Table4[[#This Row],[Item Name]],Table2[[Item Name]:[UoM]],2,0),"") -> Nos | L111: 2 | M111: =IFERROR(VLOOKUP(Table4[[#This Row],[Item Name]],Table2[[#All],[Item Name]:[Open Rate]],8,0),"") -> 132.7 | N111: =IFERROR(+Table4[[#This Row],[Qty Issued]]*Table4[[#This Row],[Rate]],"") -> 265.4 | O111: No | P111: NA
A112: 45751 | B112: Consumed | C112: 172 | D112: 1 | E112: =IFERROR(VLOOKUP(Table4[[#This Row],[From Location Code]],Table5[#All],3,0),"") -> Munger | F112: =IFERROR(VLOOKUP(Table4[[#This Row],[From Location Code]],Table5[#All],2,0),"") -> Main Godown | G112: 1001 | H112: =IFERROR(VLOOKUP(Table4[[#This Row],[To BMC/MPG Code]],Table5[#All],3,0),"") -> Majhaul | I112: =IFERROR(VLOOKUP(Table4[[#This Row],[To BMC/MPG Code]],Table5[#All],2,0),"") -> BMC | J112: Milk Pipete 10.75 ML | K112: =IFERROR(VLOOKUP(Table4[[#This Row],[Item Name]],Table2[[Item Name]:[UoM]],2,0),"") -> Nos | L112: 2 | M112: =IFERROR(VLOOKUP(Table4[[#This Row],[Item Name]],Table2[[#All],[Item Name]:[Open Rate]],8,0),"") -> 132.7 | N112: =IFERROR(+Table4[[#This Row],[Qty Issued]]*Table4[[#This Row],[Rate]],"") -> 265.4 | O112: No | P112: NA
A113: 45751 | B113: Consumed | C113: 172 | D113: 1 | E113: =IFERROR(VLOOKUP(Table4[[#This Row],[From Location Code]],Table5[#All],3,0),"") -> Munger | F113: =IFERROR(VLOOKUP(Table4[[#This Row],[From Location Code]],Table5[#All],2,0),"") -> Main Godown | G113: 1001 | H113: =IFERROR(VLOOKUP(Table4[[#This Row],[To BMC/MPG Code]],Table5[#All],3,0),"") -> Majhaul | I113: =IFERROR(VLOOKUP(Table4[[#This Row],[To BMC/MPG Code]],Table5[#All],2,0),"") -> BMC | J113: Ethyl Alcohol 500 ML Pack | K113: =IFERROR(VLOOKUP(Table4[[#This Row],[Item Name]],Table2[[Item Name]:[UoM]],2,0),"") -> Nos | L113: 5 | M113: =IFERROR(VLOOKUP(Table4[[#This Row],[Item Name]],Table2[[#All],[Item Name]:[Open Rate]],8,0),"") -> 271.4 | N113: =IFERROR(+Table4[[#This Row],[Qty Issued]]*Table4[[#This Row],[Rate]],"") -> 1357 | O113: No | P113: NA
A114: 45751 | B114: Consumed | C114: 172 | D114: 1 | E114: =IFERROR(VLOOKUP(Table4[[#This Row],[From Location Code]],Table5[#All],3,0),"") -> Munger | F114: =IFERROR(VLOOKUP(Table4[[#This Row],[From Location Code]],Table5[#All],2,0),"") -> Main Godown | G114: 1001 | H114: =IFERROR(VLOOKUP(Table4[[#This Row],[To BMC/MPG Code]],Table5[#All],3,0),"") -> Majhaul | I114: =IFERROR(VLOOKUP(Table4[[#This Row],[To BMC/MPG Code]],Table5[#All],2,0),"") -> BMC | J114: Tanker Seal | K114: =IFERROR(VLOOKUP(Table4[[#This Row],[Item Name]],Table2[[Item Name]:[UoM]],2,0),"") -> Nos | L114: 200 | M114: =IFERROR(VLOOKUP(Table4[[#This Row],[Item Name]],Table2[[#All],[Item Name]:[Open Rate]],8,0),"") -> 12.71 | N114: =IFERROR(+Table4[[#This Row],[Qty Issued]]*Table4[[#This Row],[Rate]],"") -> 2542 | O114: No | P114: NA
A115: 45751 | B115: Consumed | C115: 172 | D115: 1 | E115: =IFERROR(VLOOKUP(Table4[[#This Row],[From Location Code]],Table5[#All],3,0),"") -> Munger | F115: =IFERROR(VLOOKUP(Table4[[#This Row],[From Location Code]],Table5[#All],2,0),"") -> Main Godown | G115: 1001 | H115: =IFERROR(VLOOKUP(Table4[[#This Row],[To BMC/MPG Code]],Table5[#All],3,0),"") -> Majhaul | I115: =IFERROR(VLOOKUP(Table4[[#This Row],[To BMC/MPG Code]],Table5[#All],2,0),"") -> BMC | J115: Sodium Hydroxide N/10 Solution | K115: =IFERROR(VLOOKUP(Table4[[#This Row],[Item Name]],Table2[[Item Name]:[UoM]],2,0),"") -> Nos | L115: 1 | M115: =IFERROR(VLOOKUP(Table4[[#This Row],[Item Name]],Table2[[#All],[Item Name]:[Open Rate]],8,0),"") -> 135.7 | N115: =IFERROR(+Table4[[#This Row],[Qty Issued]]*Table4[[#This Row],[Rate]],"") -> 135.7 | O115: No | P115: NA
A116: 45751 | B116: Consumed | C116: 172 | D116: 1 | E116: =IFERROR(VLOOKUP(Table4[[#This Row],[From Location Code]],Table5[#All],3,0),"") -> Munger | F116: =IFERROR(VLOOKUP(Table4[[#This Row],[From Location Code]],Table5[#All],2,0),"") -> Main Godown | G116: 1001 | H116: =IFERROR(VLOOKUP(Table4[[#This Row],[To BMC/MPG Code]],Table5[#All],3,0),"") -> Majhaul | I116: =IFERROR(VLOOKUP(Table4[[#This Row],[To BMC/MPG Code]],Table5[#All],2,0),"") -> BMC | J116: Phenolphthaleing Indicator | K116: =IFERROR(VLOOKUP(Table4[[#This Row],[Item Name]],Table2[[Item Name]:[UoM]],2,0),"") -> Nos | L116: 1 | M116: =IFERROR(VLOOKUP(Table4[[#This Row],[Item Name]],Table2[[#All],[Item Name]:[Open Rate]],8,0),"") -> 106.2 | N116: =IFERROR(+Table4[[#This Row],[Qty Issued]]*Table4[[#This Row],[Rate]],"") -> 106.2 | O116: No | P116: NA
A117: 45751 | B117: Consumed | C117: 172 | D117: 1 | E117: =IFERROR(VLOOKUP(Table4[[#This Row],[From Location Code]],Table5[#All],3,0),"") -> Munger | F117: =IFERROR(VLOOKUP(Table4[[#This Row],[From Location Code]],Table5[#All],2,0),"") -> Main Godown | G117: 1001 | H117: =IFERROR(VLOOKUP(Table4[[#This Row],[To BMC/MPG Code]],Table5[#All],3,0),"") -> Majhaul | I117: =IFERROR(VLOOKUP(Table4[[#This Row],[To BMC/MPG Code]],Table5[#All],2,0),"") -> BMC | J117: Amyl 500ml | K117: =IFERROR(VLOOKUP(Table4[[#This Row],[Item Name]],Table2[[Item Name]:[UoM]],2,0),"") -> Nos | L117: 2 | M117: =IFERROR(VLOOKUP(Table4[[#This Row],[Item Name]],Table2[[#All],[Item Name]:[Open Rate]],8,0),"") -> 365.8 | N117: =IFERROR(+Table4[[#This Row],[Qty Issued]]*Table4[[#This Row],[Rate]],"") -> 731.6 | O117: No | P117: NA
A118: 45751 | B118: Consumed | C118: 172 | D118: 1 | E118: =IFERROR(VLOOKUP(Table4[[#This Row],[From Location Code]],Table5[#All],3,0),"") -> Munger | F118: =IFERROR(VLOOKUP(Table4[[#This Row],[From Location Code]],Table5[#All],2,0),"") -> Main Godown | G118: 1001 | H118: =IFERROR(VLOOKUP(Table4[[#This Row],[To BMC/MPG Code]],Table5[#All],3,0),"") -> Majhaul | I118: =IFERROR(VLOOKUP(Table4[[#This Row],[To BMC/MPG Code]],Table5[#All],2,0),"") -> BMC | J118: Pipette Gradulated 10 ML | K118: =IFERROR(VLOOKUP(Table4[[#This Row],[Item Name]],Table2[[Item Name]:[UoM]],2,0),"") -> Nos | L118: 2 | M118: =IFERROR(VLOOKUP(Table4[[#This Row],[Item Name]],Table2[[#All],[Item Name]:[Open Rate]],8,0),"") -> 23.46 | N118: =IFERROR(+Table4[[#This Row],[Qty Issued]]*Table4[[#This Row],[Rate]],"") -> 46.92 | O118: No | P118: NA
A119: 45754 | B119: Consumed | C119: 174 | D119: 1 | E119: =IFERROR(VLOOKUP(Table4[[#This Row],[From Location Code]],Table5[#All],3,0),"") -> Munger | F119: =IFERROR(VLOOKUP(Table4[[#This Row],[From Location Code]],Table5[#All],2,0),"") -> Main Godown | G119: 1007 | H119: =IFERROR(VLOOKUP(Table4[[#This Row],[To BMC/MPG Code]],Table5[#All],3,0),"") -> Araria | I119: =IFERROR(VLOOKUP(Table4[[#This Row],[To BMC/MPG Code]],Table5[#All],2,0),"") -> BMC | J119: TEEPOL | K119: =IFERROR(VLOOKUP(Table4[[#This Row],[Item Name]],Table2[[Item Name]:[UoM]],2,0),"") -> Nos | L119: 50 | M119: =IFERROR(VLOOKUP(Table4[[#This Row],[Item Name]],Table2[[#All],[Item Name]:[Open Rate]],8,0),"") -> 51.92 | N119: =IFERROR(+Table4[[#This Row],[Qty Issued]]*Table4[[#This Row],[Rate]],"") -> 2596 | O119: Yes | P119: Pending
A120: 45754 | B120: Consumed | C120: 174 | D120: 1 | E120: =IFERROR(VLOOKUP(Table4[[#This Row],[From Location Code]],Table5[#All],3,0),"") -> Munger | F120: =IFERROR(VLOOKUP(Table4[[#This Row],[From Location Code]],Table5[#All],2,0),"") -> Main Godown | G120: 1007 | H120: =IFERROR(VLOOKUP(Table4[[#This Row],[To BMC/MPG Code]],Table5[#All],3,0),"") -> Araria | I120: =IFERROR(VLOOKUP(Table4[[#This Row],[To BMC/MPG Code]],Table5[#All],2,0),"") -> BMC | J120: Satol - 5 KG | K120: =IFERROR(VLOOKUP(Table4[[#This Row],[Item Name]],Table2[[Item Name]:[UoM]],2,0),"") -> Nos | L120: 10 | M120: =IFERROR(VLOOKUP(Table4[[#This Row],[Item Name]],Table2[[#All],[Item Name]:[Open Rate]],8,0),"") -> 135.7 | N120: =IFERROR(+Table4[[#This Row],[Qty Issued]]*Table4[[#This Row],[Rate]],"") -> 1357 | O120: Yes | P120: Pending
A121: 45754 | B121: Consumed | C121: 174 | D121: 1 | E121: =IFERROR(VLOOKUP(Table4[[#This Row],[From Location Code]],Table5[#All],3,0),"") -> Munger | F121: =IFERROR(VLOOKUP(Table4[[#This Row],[From Location Code]],Table5[#All],2,0),"") -> Main Godown | G121: 1007 | H121: =IFERROR(VLOOKUP(Table4[[#This Row],[To BMC/MPG Code]],Table5[#All],3,0),"") -> Araria | I121: =IFERROR(VLOOKUP(Table4[[#This Row],[To BMC/MPG Code]],Table5[#All],2,0),"") -> BMC | J121: Sulphuric Acid SQ 05 Lt | K121: =IFERROR(VLOOKUP(Table4[[#This Row],[Item Name]],Table2[[Item Name]:[UoM]],2,0),"") -> Nos | L121: 1 | M121: =IFERROR(VLOOKUP(Table4[[#This Row],[Item Name]],Table2[[#All],[Item Name]:[Open Rate]],8,0),"") -> 812.2 | N121: =IFERROR(+Table4[[#This Row],[Qty Issued]]*Table4[[#This Row],[Rate]],"") -> 812.2 | O121: Yes | P121: Pending
... A130: 45761 | B130: Consumed | C130: 177 | D130: 1 | E130: =IFERROR(VLOOKUP(Table4[[#This Row],[From Location Code]],Table5[#All],3,0),"") -> Munger | F130: =IFERROR(VLOOKUP(Table4[[#This Row],[From Location Code]],Table5[#All],2,0),"") -> Main Godown | G130: 1002 | H130: =IFERROR(VLOOKUP(Table4[[#This Row],[To BMC/MPG Code]],Table5[#All],3,0),"") -> Laldiyara | I130: =IFERROR(VLOOKUP(Table4[[#This Row],[To BMC/MPG Code]],Table5[#All],2,0),"") -> BMC | J130: Milk Despatch Challan | K130: =IFERROR(VLOOKUP(Table4[[#This Row],[Item Name]],Table2[[Item Name]:[UoM]],2,0),"") -> Nos | L130: 10 | M130: =IFERROR(VLOOKUP(Table4[[#This Row],[Item Name]],Table2[[#All],[Item Name]:[Open Rate]],8,0),"") -> 94.4 | N130: =IFERROR(+Table4[[#This Row],[Qty Issued]]*Table4[[#This Row],[Rate]],"") -> 944 | O130: Yes | P130: Pending
A131: 45761 | B131: Consumed | D131: 1 | E131: =IFERROR(VLOOKUP(Table4[[#This Row],[From Location Code]],Table5[#All],3,0),"") -> Munger | F131: =IFERROR(VLOOKUP(Table4[[#This Row],[From Location Code]],Table5[#All],2,0),"") -> Main Godown | G131: 1054 | H131: =IFERROR(VLOOKUP(Table4[[#This Row],[To BMC/MPG Code]],Table5[#All],3,0),"") -> Alauli | I131: =IFERROR(VLOOKUP(Table4[[#This Row],[To BMC/MPG Code]],Table5[#All],2,0),"") -> BMC | J131: Beaker 100 Ml | K131: =IFERROR(VLOOKUP(Table4[[#This Row],[Item Name]],Table2[[Item Name]:[UoM]],2,0),"") -> Nos | L131: 2 | M131: =IFERROR(VLOOKUP(Table4[[#This Row],[Item Name]],Table2[[#All],[Item Name]:[Open Rate]],8,0),"") -> 33.18 | N131: =IFERROR(+Table4[[#This Row],[Qty Issued]]*Table4[[#This Row],[Rate]],"") -> 66.36 | O131: No | P131: NA
A132: 45761 | B132: Consumed | D132: 1 | E132: =IFERROR(VLOOKUP(Table4[[#This Row],[From Location Code]],Table5[#All],3,0),"") -> Munger | F132: =IFERROR(VLOOKUP(Table4[[#This Row],[From Location Code]],Table5[#All],2,0),"") -> Main Godown | G132: 1054 | H132: =IFERROR(VLOOKUP(Table4[[#This Row],[To BMC/MPG Code]],Table5[#All],3,0),"") -> Alauli | I132: =IFERROR(VLOOKUP(Table4[[#This Row],[To BMC/MPG Code]],Table5[#All],2,0),"") -> BMC | J132: Beaker 500 Ml | K132: =IFERROR(VLOOKUP(Table4[[#This Row],[Item Name]],Table2[[Item Name]:[UoM]],2,0),"") -> Nos | L132: 2 | M132: =IFERROR(VLOOKUP(Table4[[#This Row],[Item Name]],Table2[[#All],[Item Name]:[Open Rate]],8,0),"") -> 63.7 | N132: =IFERROR(+Table4[[#This Row],[Qty Issued]]*Table4[[#This Row],[Rate]],"") -> 127.4 | O132: No | P132: NA
A133: 45761 | B133: Consumed | D133: 1 | E133: =IFERROR(VLOOKUP(Table4[[#This Row],[From Location Code]],Table5[#All],3,0),"") -> Munger | F133: =IFERROR(VLOOKUP(Table4[[#This Row],[From Location Code]],Table5[#All],2,0),"") -> Main Godown | G133: 1054 | H133: =IFERROR(VLOOKUP(Table4[[#This Row],[To BMC/MPG Code]],Table5[#All],3,0),"") -> Alauli | I133: =IFERROR(VLOOKUP(Table4[[#This Row],[To BMC/MPG Code]],Table5[#All],2,0),"") -> BMC | J133: Beaker 50 ML | K133: =IFERROR(VLOOKUP(Table4[[#This Row],[Item Name]],Table2[[Item Name]:[UoM]],2,0),"") -> Nos | L133: 2 | M133: =IFERROR(VLOOKUP(Table4[[#This Row],[Item Name]],Table2[[#All],[Item Name]:[Open Rate]],8,0),"") -> 15.88 | N133: =IFERROR(+Table4[[#This Row],[Qty Issued]]*Table4[[#This Row],[Rate]],"") -> 31.76 | O133: No | P133: NA
A134: 45761 | B134: Consumed | D134: 1 | E134: =IFERROR(VLOOKUP(Table4[[#This Row],[From Location Code]],Table5[#All],3,0),"") -> Munger | F134: =IFERROR(VLOOKUP(Table4[[#This Row],[From Location Code]],Table5[#All],2,0),"") -> Main Godown | G134: 1054 | H134: =IFERROR(VLOOKUP(Table4[[#This Row],[To BMC/MPG Code]],Table5[#All],3,0),"") -> Alauli | I134: =IFERROR(VLOOKUP(Table4[[#This Row],[To BMC/MPG Code]],Table5[#All],2,0),"") -> BMC | J134: Conical Flask 100 ML | K134: =IFERROR(VLOOKUP(Table4[[#This Row],[Item Name]],Table2[[Item Name]:[UoM]],2,0),"") -> Nos | L134: 1 | M134: =IFERROR(VLOOKUP(Table4[[#This Row],[Item Name]],Table2[[#All],[Item Name]:[Open Rate]],8,0),"") -> 29.47 | N134: =IFERROR(+Table4[[#This Row],[Qty Issued]]*Table4[[#This Row],[Rate]],"") -> 29.47 | O134: No | P134: NA
A135: 45761 | B135: Consumed | D135: 1 | E135: =IFERROR(VLOOKUP(Table4[[#This Row],[From Location Code]],Table5[#All],3,0),"") -> Munger | F135: =IFERROR(VLOOKUP(Table4[[#This Row],[From Location Code]],Table5[#All],2,0),"") -> Main Godown | G135: 1054 | H135: =IFERROR(VLOOKUP(Table4[[#This Row],[To BMC/MPG Code]],Table5[#All],3,0),"") -> Alauli | I135: =IFERROR(VLOOKUP(Table4[[#This Row],[To BMC/MPG Code]],Table5[#All],2,0),"") -> BMC | J135: Pipette Gradulated 10 ML | K135: =IFERROR(VLOOKUP(Table4[[#This Row],[Item Name]],Table2[[Item Name]:[UoM]],2,0),"") -> Nos | L135: 2 | M135: =IFERROR(VLOOKUP(Table4[[#This Row],[Item Name]],Table2[[#All],[Item Name]:[Open Rate]],8,0),"") -> 23.46 | N135: =IFERROR(+Table4[[#This Row],[Qty Issued]]*Table4[[#This Row],[Rate]],"") -> 46.92 | O135: No | P135: NA
A136: 45761 | B136: Consumed | D136: 1 | E136: =IFERROR(VLOOKUP(Table4[[#This Row],[From Location Code]],Table5[#All],3,0),"") -> Munger | F136: =IFERROR(VLOOKUP(Table4[[#This Row],[From Location Code]],Table5[#All],2,0),"") -> Main Godown | G136: 1054 | H136: =IFERROR(VLOOKUP(Table4[[#This Row],[To BMC/MPG Code]],Table5[#All],3,0),"") -> Alauli | I136: =IFERROR(VLOOKUP(Table4[[#This Row],[To BMC/MPG Code]],Table5[#All],2,0),"") -> BMC | J136: Pipette Gradulated 1 ML | K136: =IFERROR(VLOOKUP(Table4[[#This Row],[Item Name]],Table2[[Item Name]:[UoM]],2,0),"") -> Nos | L136: 2 | M136: =IFERROR(VLOOKUP(Table4[[#This Row],[Item Name]],Table2[[#All],[Item Name]:[Open Rate]],8,0),"") -> 22.42 | N136: =IFERROR(+Table4[[#This Row],[Qty Issued]]*Table4[[#This Row],[Rate]],"") -> 44.84 | O136: No | P136: NA
A137: 45761 | B137: Consumed | D137: 1 | E137: =IFERROR(VLOOKUP(Table4[[#This Row],[From Location Code]],Table5[#All],3,0),"") -> Munger | F137: =IFERROR(VLOOKUP(Table4[[#This Row],[From Location Code]],Table5[#All],2,0),"") -> Main Godown | G137: 1054 | H137: =IFERROR(VLOOKUP(Table4[[#This Row],[To BMC/MPG Code]],Table5[#All],3,0),"") -> Alauli | I137: =IFERROR(VLOOKUP(Table4[[#This Row],[To BMC/MPG Code]],Table5[#All],2,0),"") -> BMC | J137: Pipette Gradulated 2 ML | K137: =IFERROR(VLOOKUP(Table4[[#This Row],[Item Name]],Table2[[Item Name]:[UoM]],2,0),"") -> Nos | L137: 2 | M137: =IFERROR(VLOOKUP(Table4[[#This Row],[Item Name]],Table2[[#All],[Item Name]:[Open Rate]],8,0),"") -> 28.46 | N137: =IFERROR(+Table4[[#This Row],[Qty Issued]]*Table4[[#This Row],[Rate]],"") -> 56.92 | O137: No | P137: NA
A138: 45761 | B138: Consumed | D138: 1 | E138: =IFERROR(VLOOKUP(Table4[[#This Row],[From Location Code]],Table5[#All],3,0),"") -> Munger | F138: =IFERROR(VLOOKUP(Table4[[#This Row],[From Location Code]],Table5[#All],2,0),"") -> Main Godown | G138: 1054 | H138: =IFERROR(VLOOKUP(Table4[[#This Row],[To BMC/MPG Code]],Table5[#All],3,0),"") -> Alauli | I138: =IFERROR(VLOOKUP(Table4[[#This Row],[To BMC/MPG Code]],Table5[#All],2,0),"") -> BMC | J138: Reagent Bottle 250 ML | K138: =IFERROR(VLOOKUP(Table4[[#This Row],[Item Name]],Table2[[Item Name]:[UoM]],2,0),"") -> Nos | L138: 6 | M138: =IFERROR(VLOOKUP(Table4[[#This Row],[Item Name]],Table2[[#All],[Item Name]:[Open Rate]],8,0),"") -> 88.5 | N138: =IFERROR(+Table4[[#This Row],[Qty Issued]]*Table4[[#This Row],[Rate]],"") -> 531 | O138: No | P138: NA
A139: 45761 | B139: Consumed | D139: 1 | E139: =IFERROR(VLOOKUP(Table4[[#This Row],[From Location Code]],Table5[#All],3,0),"") -> Munger | F139: =IFERROR(VLOOKUP(Table4[[#This Row],[From Location Code]],Table5[#All],2,0),"") -> Main Godown | G139: 1054 | H139: =IFERROR(VLOOKUP(Table4[[#This Row],[To BMC/MPG Code]],Table5[#All],3,0),"") -> Alauli | I139: =IFERROR(VLOOKUP(Table4[[#This Row],[To BMC/MPG Code]],Table5[#All],2,0),"") -> BMC | J139: Lactometer Jar Small | K139: =IFERROR(VLOOKUP(Table4[[#This Row],[Item Name]],Table2[[Item Name]:[UoM]],2,0),"") -> Nos | L139: 2 | M139: =IFERROR(VLOOKUP(Table4[[#This Row],[Item Name]],Table2[[#All],[Item Name]:[Open Rate]],8,0),"") -> 18.95 | N139: =IFERROR(+Table4[[#This Row],[Qty Issued]]*Table4[[#This Row],[Rate]],"") -> 37.9 | O139: No | P139: NA
A140: 45761 | B140: Consumed | D140: 1 | E140: =IFERROR(VLOOKUP(Table4[[#This Row],[From Location Code]],Table5[#All],3,0),"") -> Munger | F140: =IFERROR(VLOOKUP(Table4[[#This Row],[From Location Code]],Table5[#All],2,0),"") -> Main Godown | G140: 1054 | H140: =IFERROR(VLOOKUP(Table4[[#This Row],[To BMC/MPG Code]],Table5[#All],3,0),"") -> Alauli | I140: =IFERROR(VLOOKUP(Table4[[#This Row],[To BMC/MPG Code]],Table5[#All],2,0),"") -> BMC | J140: Tilt Measure 10cc PI Superior | K140: =IFERROR(VLOOKUP(Table4[[#This Row],[Item Name]],Table2[[Item Name]:[UoM]],2,0),"") -> Nos | L140: 2 | M140: =IFERROR(VLOOKUP(Table4[[#This Row],[Item Name]],Table2[[#All],[Item Name]:[Open Rate]],8,0),"") -> 23.71 | N140: =IFERROR(+Table4[[#This Row],[Qty Issued]]*Table4[[#This Row],[Rate]],"") -> 47.42 | O140: No | P140: NA
A141: 45761 | B141: Consumed | D141: 1 | E141: =IFERROR(VLOOKUP(Table4[[#This Row],[From Location Code]],Table5[#All],3,0),"") -> Munger | F141: =IFERROR(VLOOKUP(Table4[[#This Row],[From Location Code]],Table5[#All],2,0),"") -> Main Godown | G141: 1054 | H141: =IFERROR(VLOOKUP(Table4[[#This Row],[To BMC/MPG Code]],Table5[#All],3,0),"") -> Alauli | I141: =IFERROR(VLOOKUP(Table4[[#This Row],[To BMC/MPG Code]],Table5[#All],2,0),"") -> BMC | J141: Tilt Measure 1 Ml with Bottle | K141: =IFERROR(VLOOKUP(Table4[[#This Row],[Item Name]],Table2[[Item Name]:[UoM]],2,0),"") -> Nos | L141: 2 | M141: =IFERROR(VLOOKUP(Table4[[#This Row],[Item Name]],Table2[[#All],[Item Name]:[Open Rate]],8,0),"") -> 32.09 | N141: =IFERROR(+Table4[[#This Row],[Qty Issued]]*Table4[[#This Row],[Rate]],"") -> 64.18 | O141: No | P141: NA
A142: 45761 | B142: Consumed | D142: 1 | E142: =IFERROR(VLOOKUP(Table4[[#This Row],[From Location Code]],Table5[#All],3,0),"") -> Munger | F142: =IFERROR(VLOOKUP(Table4[[#This Row],[From Location Code]],Table5[#All],2,0),"") -> Main Godown | G142: 1054 | H142: =IFERROR(VLOOKUP(Table4[[#This Row],[To BMC/MPG Code]],Table5[#All],3,0),"") -> Alauli | I142: =IFERROR(VLOOKUP(Table4[[#This Row],[To BMC/MPG Code]],Table5[#All],2,0),"") -> BMC | J142: Sample Bottle 100 ML | K142: =IFERROR(VLOOKUP(Table4[[#This Row],[Item Name]],Table2[[Item Name]:[UoM]],2,0),"") -> Nos | L142: 50 | M142: =IFERROR(VLOOKUP(Table4[[#This Row],[Item Name]],Table2[[#All],[Item Name]:[Open Rate]],8,0),"") -> 2.83 | N142: =IFERROR(+Table4[[#This Row],[Qty Issued]]*Table4[[#This Row],[Rate]],"") -> 141.5 | O142: No | P142: NA
... A186: 45761 | B186: Consumed | D186: 1 | E186: =IFERROR(VLOOKUP(Table4[[#This Row],[From Location Code]],Table5[#All],3,0),"") -> Munger | F186: =IFERROR(VLOOKUP(Table4[[#This Row],[From Location Code]],Table5[#All],2,0),"") -> Main Godown | G186: 1055 | H186: =IFERROR(VLOOKUP(Table4[[#This Row],[To BMC/MPG Code]],Table5[#All],3,0),"") -> Matihani | I186: =IFERROR(VLOOKUP(Table4[[#This Row],[To BMC/MPG Code]],Table5[#All],2,0),"") -> BMC | J186: MBRT Test Register | K186: =IFERROR(VLOOKUP(Table4[[#This Row],[Item Name]],Table2[[Item Name]:[UoM]],2,0),"") -> Nos | L186: 3 | M186: =IFERROR(VLOOKUP(Table4[[#This Row],[Item Name]],Table2[[#All],[Item Name]:[Open Rate]],8,0),"") -> 115.36 | N186: =IFERROR(+Table4[[#This Row],[Qty Issued]]*Table4[[#This Row],[Rate]],"") -> 346.08 | O186: No | P186: NA
A187: 45762 | B187: Consumed | C187: 178 | D187: 1 | E187: =IFERROR(VLOOKUP(Table4[[#This Row],[From Location Code]],Table5[#All],3,0),"") -> Munger | F187: =IFERROR(VLOOKUP(Table4[[#This Row],[From Location Code]],Table5[#All],2,0),"") -> Main Godown | G187: 1001 | H187: =IFERROR(VLOOKUP(Table4[[#This Row],[To BMC/MPG Code]],Table5[#All],3,0),"") -> Majhaul | I187: =IFERROR(VLOOKUP(Table4[[#This Row],[To BMC/MPG Code]],Table5[#All],2,0),"") -> BMC | J187: TEEPOL | K187: =IFERROR(VLOOKUP(Table4[[#This Row],[Item Name]],Table2[[Item Name]:[UoM]],2,0),"") -> Nos | L187: 50 | M187: =IFERROR(VLOOKUP(Table4[[#This Row],[Item Name]],Table2[[#All],[Item Name]:[Open Rate]],8,0),"") -> 51.92 | N187: =IFERROR(+Table4[[#This Row],[Qty Issued]]*Table4[[#This Row],[Rate]],"") -> 2596 | O187: No | P187: NA
A188: 45762 | B188: Consumed | C188: 178 | D188: 1 | E188: =IFERROR(VLOOKUP(Table4[[#This Row],[From Location Code]],Table5[#All],3,0),"") -> Munger | F188: =IFERROR(VLOOKUP(Table4[[#This Row],[From Location Code]],Table5[#All],2,0),"") -> Main Godown | G188: 10010071 | H188: =IFERROR(VLOOKUP(Table4[[#This Row],[To BMC/MPG Code]],Table5[#All],3,0),"") -> Gomukh Sherpur | I188: =IFERROR(VLOOKUP(Table4[[#This Row],[To BMC/MPG Code]],Table5[#All],2,0),"") -> MPG | J188: Plastic Strainer | K188: =IFERROR(VLOOKUP(Table4[[#This Row],[Item Name]],Table2[[Item Name]:[UoM]],2,0),"") -> Nos | L188: 1 | M188: =IFERROR(VLOOKUP(Table4[[#This Row],[Item Name]],Table2[[#All],[Item Name]:[Open Rate]],8,0),"") -> 29.5 | N188: =IFERROR(+Table4[[#This Row],[Qty Issued]]*Table4[[#This Row],[Rate]],"") -> 29.5 | O188: Yes | P188: Pending
A189: 45762 | B189: Consumed | C189: 178 | D189: 1 | E189: =IFERROR(VLOOKUP(Table4[[#This Row],[From Location Code]],Table5[#All],3,0),"") -> Munger | F189: =IFERROR(VLOOKUP(Table4[[#This Row],[From Location Code]],Table5[#All],2,0),"") -> Main Godown | G189: 10010082 | H189: =IFERROR(VLOOKUP(Table4[[#This Row],[To BMC/MPG Code]],Table5[#All],3,0),"") -> Gomukh Sharmatola Sahuri | I189: =IFERROR(VLOOKUP(Table4[[#This Row],[To BMC/MPG Code]],Table5[#All],2,0),"") -> MPG | J189: Plastic Strainer | K189: =IFERROR(VLOOKUP(Table4[[#This Row],[Item Name]],Table2[[Item Name]:[UoM]],2,0),"") -> Nos | L189: 1 | M189: =IFERROR(VLOOKUP(Table4[[#This Row],[Item Name]],Table2[[#All],[Item Name]:[Open Rate]],8,0),"") -> 29.5 | N189: =IFERROR(+Table4[[#This Row],[Qty Issued]]*Table4[[#This Row],[Rate]],"") -> 29.5 | O189: Yes | P189: Pending
A190: 45762 | B190: Consumed | C190: 178 | D190: 1 | E190: =IFERROR(VLOOKUP(Table4[[#This Row],[From Location Code]],Table5[#All],3,0),"") -> Munger | F190: =IFERROR(VLOOKUP(Table4[[#This Row],[From Location Code]],Table5[#All],2,0),"") -> Main Godown | G190: 10010055 | H190: =IFERROR(VLOOKUP(Table4[[#This Row],[To BMC/MPG Code]],Table5[#All],3,0),"") -> GOMUKH BIRPUR PASCHIM | I190: =IFERROR(VLOOKUP(Table4[[#This Row],[To BMC/MPG Code]],Table5[#All],2,0),"") -> MPG | J190: Plastic Strainer | K190: =IFERROR(VLOOKUP(Table4[[#This Row],[Item Name]],Table2[[Item Name]:[UoM]],2,0),"") -> Nos | L190: 1 | M190: =IFERROR(VLOOKUP(Table4[[#This Row],[Item Name]],Table2[[#All],[Item Name]:[Open Rate]],8,0),"") -> 29.5 | N190: =IFERROR(+Table4[[#This Row],[Qty Issued]]*Table4[[#This Row],[Rate]],"") -> 29.5 | O190: Yes | P190: Pending
A191: 45762 | B191: Consumed | C191: 178 | D191: 1 | E191: =IFERROR(VLOOKUP(Table4[[#This Row],[From Location Code]],Table5[#All],3,0),"") -> Munger | F191: =IFERROR(VLOOKUP(Table4[[#This Row],[From Location Code]],Table5[#All],2,0),"") -> Main Godown | G191: 10010019 | H191: =IFERROR(VLOOKUP(Table4[[#This Row],[To BMC/MPG Code]],Table5[#All],3,0),"") -> Gomukh Jagdar | I191: =IFERROR(VLOOKUP(Table4[[#This Row],[To BMC/MPG Code]],Table5[#All],2,0),"") -> MPG | J191: Plastic Strainer | K191: =IFERROR(VLOOKUP(Table4[[#This Row],[Item Name]],Table2[[Item Name]:[UoM]],2,0),"") -> Nos | L191: 1 | M191: =IFERROR(VLOOKUP(Table4[[#This Row],[Item Name]],Table2[[#All],[Item Name]:[Open Rate]],8,0),"") -> 29.5 | N191: =IFERROR(+Table4[[#This Row],[Qty Issued]]*Table4[[#This Row],[Rate]],"") -> 29.5 | O191: Yes | P191: Pending
A192: 45762 | B192: Consumed | C192: 178 | D192: 1 | E192: =IFERROR(VLOOKUP(Table4[[#This Row],[From Location Code]],Table5[#All],3,0),"") -> Munger | F192: =IFERROR(VLOOKUP(Table4[[#This Row],[From Location Code]],Table5[#All],2,0),"") -> Main Godown | G192: 10010040 | H192: =IFERROR(VLOOKUP(Table4[[#This Row],[To BMC/MPG Code]],Table5[#All],3,0),"") -> Gomukh Sahuri-2 | I192: =IFERROR(VLOOKUP(Table4[[#This Row],[To BMC/MPG Code]],Table5[#All],2,0),"") -> MPG | J192: Plastic Strainer | K192: =IFERROR(VLOOKUP(Table4[[#This Row],[Item Name]],Table2[[Item Name]:[UoM]],2,0),"") -> Nos | L192: 1 | M192: =IFERROR(VLOOKUP(Table4[[#This Row],[Item Name]],Table2[[#All],[Item Name]:[Open Rate]],8,0),"") -> 29.5 | N192: =IFERROR(+Table4[[#This Row],[Qty Issued]]*Table4[[#This Row],[Rate]],"") -> 29.5 | O192: Yes | P192: Pending
A193: 45762 | B193: Consumed | C193: 178 | D193: 1 | E193: =IFERROR(VLOOKUP(Table4[[#This Row],[From Location Code]],Table5[#All],3,0),"") -> Munger | F193: =IFERROR(VLOOKUP(Table4[[#This Row],[From Location Code]],Table5[#All],2,0),"") -> Main Godown | G193: 10010076 | H193: =IFERROR(VLOOKUP(Table4[[#This Row],[To BMC/MPG Code]],Table5[#All],3,0),"") -> Gomukh Bhith-02 | I193: =IFERROR(VLOOKUP(Table4[[#This Row],[To BMC/MPG Code]],Table5[#All],2,0),"") -> MPG | J193: Plastic Strainer | K193: =IFERROR(VLOOKUP(Table4[[#This Row],[Item Name]],Table2[[Item Name]:[UoM]],2,0),"") -> Nos | L193: 1 | M193: =IFERROR(VLOOKUP(Table4[[#This Row],[Item Name]],Table2[[#All],[Item Name]:[Open Rate]],8,0),"") -> 29.5 | N193: =IFERROR(+Table4[[#This Row],[Qty Issued]]*Table4[[#This Row],[Rate]],"") -> 29.5 | O193: Yes | P193: Pending
A194: 45762 | B194: Consumed | C194: 178 | D194: 1 | E194: =IFERROR(VLOOKUP(Table4[[#This Row],[From Location Code]],Table5[#All],3,0),"") -> Munger | F194: =IFERROR(VLOOKUP(Table4[[#This Row],[From Location Code]],Table5[#All],2,0),"") -> Main Godown | G194: 10010081 | H194: =IFERROR(VLOOKUP(Table4[[#This Row],[To BMC/MPG Code]],Table5[#All],3,0),"") -> Gomukh Dharampur | I194: =IFERROR(VLOOKUP(Table4[[#This Row],[To BMC/MPG Code]],Table5[#All],2,0),"") -> MPG | J194: Plastic Strainer | K194: =IFERROR(VLOOKUP(Table4[[#This Row],[Item Name]],Table2[[Item Name]:[UoM]],2,0),"") -> Nos | L194: 1 | M194: =IFERROR(VLOOKUP(Table4[[#This Row],[Item Name]],Table2[[#All],[Item Name]:[Open Rate]],8,0),"") -> 29.5 | N194: =IFERROR(+Table4[[#This Row],[Qty Issued]]*Table4[[#This Row],[Rate]],"") -> 29.5 | O194: Yes | P194: Pending
A195: 45762 | B195: Consumed | C195: 178 | D195: 1 | E195: =IFERROR(VLOOKUP(Table4[[#This Row],[From Location Code]],Table5[#All],3,0),"") -> Munger | F195: =IFERROR(VLOOKUP(Table4[[#This Row],[From Location Code]],Table5[#All],2,0),"") -> Main Godown | G195: 10010021 | H195: =IFERROR(VLOOKUP(Table4[[#This Row],[To BMC/MPG Code]],Table5[#All],3,0),"") -> Gomukh Moradpur | I195: =IFERROR(VLOOKUP(Table4[[#This Row],[To BMC/MPG Code]],Table5[#All],2,0),"") -> MPG | J195: Plastic Strainer | K195: =IFERROR(VLOOKUP(Table4[[#This Row],[Item Name]],Table2[[Item Name]:[UoM]],2,0),"") -> Nos | L195: 1 | M195: =IFERROR(VLOOKUP(Table4[[#This Row],[Item Name]],Table2[[#All],[Item Name]:[Open Rate]],8,0),"") -> 29.5 | N195: =IFERROR(+Table4[[#This Row],[Qty Issued]]*Table4[[#This Row],[Rate]],"") -> 29.5 | O195: Yes | P195: Pending
A196: 45762 | B196: Consumed | C196: 178 | D196: 1 | E196: =IFERROR(VLOOKUP(Table4[[#This Row],[From Location Code]],Table5[#All],3,0),"") -> Munger | F196: =IFERROR(VLOOKUP(Table4[[#This Row],[From Location Code]],Table5[#All],2,0),"") -> Main Godown | G196: 10010059 | H196: =IFERROR(VLOOKUP(Table4[[#This Row],[To BMC/MPG Code]],Table5[#All],3,0),"") -> Gomukh Menhan | I196: =IFERROR(VLOOKUP(Table4[[#This Row],[To BMC/MPG Code]],Table5[#All],2,0),"") -> MPG | J196: Plastic Strainer | K196: =IFERROR(VLOOKUP(Table4[[#This Row],[Item Name]],Table2[[Item Name]:[UoM]],2,0),"") -> Nos | L196: 1 | M196: =IFERROR(VLOOKUP(Table4[[#This Row],[Item Name]],Table2[[#All],[Item Name]:[Open Rate]],8,0),"") -> 29.5 | N196: =IFERROR(+Table4[[#This Row],[Qty Issued]]*Table4[[#This Row],[Rate]],"") -> 29.5 | O196: Yes | P196: Pending
A197: 45762 | B197: Consumed | C197: 178 | D197: 1 | E197: =IFERROR(VLOOKUP(Table4[[#This Row],[From Location Code]],Table5[#All],3,0),"") -> Munger | F197: =IFERROR(VLOOKUP(Table4[[#This Row],[From Location Code]],Table5[#All],2,0),"") -> Main Godown | G197: 10010027 | H197: =IFERROR(VLOOKUP(Table4[[#This Row],[To BMC/MPG Code]],Table5[#All],3,0),"") -> Gomukh Paroriya | I197: =IFERROR(VLOOKUP(Table4[[#This Row],[To BMC/MPG Code]],Table5[#All],2,0),"") -> MPG | J197: Plastic Strainer | K197: =IFERROR(VLOOKUP(Table4[[#This Row],[Item Name]],Table2[[Item Name]:[UoM]],2,0),"") -> Nos | L197: 1 | M197: =IFERROR(VLOOKUP(Table4[[#This Row],[Item Name]],Table2[[#All],[Item Name]:[Open Rate]],8,0),"") -> 29.5 | N197: =IFERROR(+Table4[[#This Row],[Qty Issued]]*Table4[[#This Row],[Rate]],"") -> 29.5 | O197: Yes | P197: Pending
A198: 45762 | B198: Consumed | C198: 178 | D198: 1 | E198: =IFERROR(VLOOKUP(Table4[[#This Row],[From Location Code]],Table5[#All],3,0),"") -> Munger | F198: =IFERROR(VLOOKUP(Table4[[#This Row],[From Location Code]],Table5[#All],2,0),"") -> Main Godown | G198: 10010030 | H198: =IFERROR(VLOOKUP(Table4[[#This Row],[To BMC/MPG Code]],Table5[#All],3,0),"") -> Gomukh Phulhara | I198: =IFERROR(VLOOKUP(Table4[[#This Row],[To BMC/MPG Code]],Table5[#All],2,0),"") -> MPG | J198: Plastic Strainer | K198: =IFERROR(VLOOKUP(Table4[[#This Row],[Item Name]],Table2[[Item Name]:[UoM]],2,0),"") -> Nos | L198: 1 | M198: =IFERROR(VLOOKUP(Table4[[#This Row],[Item Name]],Table2[[#All],[Item Name]:[Open Rate]],8,0),"") -> 29.5 | N198: =IFERROR(+Table4[[#This Row],[Qty Issued]]*Table4[[#This Row],[Rate]],"") -> 29.5 | O198: Yes | P198: Pending
... A251: 45766 | B251: Consumed | C251: 180 | D251: 1 | E251: =IFERROR(VLOOKUP(Table4[[#This Row],[From Location Code]],Table5[#All],3,0),"") -> Munger | F251: =IFERROR(VLOOKUP(Table4[[#This Row],[From Location Code]],Table5[#All],2,0),"") -> Main Godown | G251: 1011 | H251: =IFERROR(VLOOKUP(Table4[[#This Row],[To BMC/MPG Code]],Table5[#All],3,0),"") -> Sahibpur Kamal | I251: =IFERROR(VLOOKUP(Table4[[#This Row],[To BMC/MPG Code]],Table5[#All],2,0),"") -> BMC | J251: Ethyl Alcohol 500 ML Pack | K251: =IFERROR(VLOOKUP(Table4[[#This Row],[Item Name]],Table2[[Item Name]:[UoM]],2,0),"") -> Nos | L251: 1 | M251: =IFERROR(VLOOKUP(Table4[[#This Row],[Item Name]],Table2[[#All],[Item Name]:[Open Rate]],8,0),"") -> 271.4 | N251: =IFERROR(+Table4[[#This Row],[Qty Issued]]*Table4[[#This Row],[Rate]],"") -> 271.4 | O251: No | P251: NA
A252: 45768 | B252: Consumed | C252: 181 | D252: 1 | E252: =IFERROR(VLOOKUP(Table4[[#This Row],[From Location Code]],Table5[#All],3,0),"") -> Munger | F252: =IFERROR(VLOOKUP(Table4[[#This Row],[From Location Code]],Table5[#All],2,0),"") -> Main Godown | G252: Lab | H252: =IFERROR(VLOOKUP(Table4[[#This Row],[To BMC/MPG Code]],Table5[#All],3,0),"") -> Daya_Lab | I252: =IFERROR(VLOOKUP(Table4[[#This Row],[To BMC/MPG Code]],Table5[#All],2,0),"") -> Lab | J252: Milk Despatch Challan | K252: =IFERROR(VLOOKUP(Table4[[#This Row],[Item Name]],Table2[[Item Name]:[UoM]],2,0),"") -> Nos | L252: 2 | M252: =IFERROR(VLOOKUP(Table4[[#This Row],[Item Name]],Table2[[#All],[Item Name]:[Open Rate]],8,0),"") -> 94.4 | N252: =IFERROR(+Table4[[#This Row],[Qty Issued]]*Table4[[#This Row],[Rate]],"") -> 188.8 | O252: No | P252: NA
A253: 45771 | B253: Consumed | C253: 182 | D253: 1 | E253: =IFERROR(VLOOKUP(Table4[[#This Row],[From Location Code]],Table5[#All],3,0),"") -> Munger | F253: =IFERROR(VLOOKUP(Table4[[#This Row],[From Location Code]],Table5[#All],2,0),"") -> Main Godown | G253: Lab | H253: =IFERROR(VLOOKUP(Table4[[#This Row],[To BMC/MPG Code]],Table5[#All],3,0),"") -> Daya_Lab | I253: =IFERROR(VLOOKUP(Table4[[#This Row],[To BMC/MPG Code]],Table5[#All],2,0),"") -> Lab | J253: Ethyl Alcohol 500 ML Pack | K253: =IFERROR(VLOOKUP(Table4[[#This Row],[Item Name]],Table2[[Item Name]:[UoM]],2,0),"") -> Nos | L253: 1 | M253: =IFERROR(VLOOKUP(Table4[[#This Row],[Item Name]],Table2[[#All],[Item Name]:[Open Rate]],8,0),"") -> 271.4 | N253: =IFERROR(+Table4[[#This Row],[Qty Issued]]*Table4[[#This Row],[Rate]],"") -> 271.4 | O253: No | P253: NA
A254: 45771 | B254: Consumed | C254: 183 | D254: 1 | E254: =IFERROR(VLOOKUP(Table4[[#This Row],[From Location Code]],Table5[#All],3,0),"") -> Munger | F254: =IFERROR(VLOOKUP(Table4[[#This Row],[From Location Code]],Table5[#All],2,0),"") -> Main Godown | G254: 1011 | H254: =IFERROR(VLOOKUP(Table4[[#This Row],[To BMC/MPG Code]],Table5[#All],3,0),"") -> Sahibpur Kamal | I254: =IFERROR(VLOOKUP(Table4[[#This Row],[To BMC/MPG Code]],Table5[#All],2,0),"") -> BMC | J254: Eko Day Cleaning Sol | K254: =IFERROR(VLOOKUP(Table4[[#This Row],[Item Name]],Table2[[Item Name]:[UoM]],2,0),"") -> Nos | L254: 1 | M254: =IFERROR(VLOOKUP(Table4[[#This Row],[Item Name]],Table2[[#All],[Item Name]:[Open Rate]],8,0),"") -> 348.52 | N254: =IFERROR(+Table4[[#This Row],[Qty Issued]]*Table4[[#This Row],[Rate]],"") -> 348.52 | O254: No | P254: NA
A255: 45771 | B255: Consumed | C255: 183 | D255: 1 | E255: =IFERROR(VLOOKUP(Table4[[#This Row],[From Location Code]],Table5[#All],3,0),"") -> Munger | F255: =IFERROR(VLOOKUP(Table4[[#This Row],[From Location Code]],Table5[#All],2,0),"") -> Main Godown | G255: 1011 | H255: =IFERROR(VLOOKUP(Table4[[#This Row],[To BMC/MPG Code]],Table5[#All],3,0),"") -> Sahibpur Kamal | I255: =IFERROR(VLOOKUP(Table4[[#This Row],[To BMC/MPG Code]],Table5[#All],2,0),"") -> BMC | J255: FAT Scan Weekly | K255: =IFERROR(VLOOKUP(Table4[[#This Row],[Item Name]],Table2[[Item Name]:[UoM]],2,0),"") -> Nos | L255: 1 | M255: =IFERROR(VLOOKUP(Table4[[#This Row],[Item Name]],Table2[[#All],[Item Name]:[Open Rate]],8,0),"") -> 348.52 | N255: =IFERROR(+Table4[[#This Row],[Qty Issued]]*Table4[[#This Row],[Rate]],"") -> 348.52 | O255: No | P255: NA
A256: 45771 | B256: Consumed | C256: 183 | D256: 1 | E256: =IFERROR(VLOOKUP(Table4[[#This Row],[From Location Code]],Table5[#All],3,0),"") -> Munger | F256: =IFERROR(VLOOKUP(Table4[[#This Row],[From Location Code]],Table5[#All],2,0),"") -> Main Godown | G256: 1011 | H256: =IFERROR(VLOOKUP(Table4[[#This Row],[To BMC/MPG Code]],Table5[#All],3,0),"") -> Sahibpur Kamal | I256: =IFERROR(VLOOKUP(Table4[[#This Row],[To BMC/MPG Code]],Table5[#All],2,0),"") -> BMC | J256: Eco Power Solution | K256: =IFERROR(VLOOKUP(Table4[[#This Row],[Item Name]],Table2[[Item Name]:[UoM]],2,0),"") -> Nos | L256: 1 | M256: =IFERROR(VLOOKUP(Table4[[#This Row],[Item Name]],Table2[[#All],[Item Name]:[Open Rate]],8,0),"") -> 348.52 | N256: =IFERROR(+Table4[[#This Row],[Qty Issued]]*Table4[[#This Row],[Rate]],"") -> 348.52 | O256: No | P256: NA
A257: 45771 | B257: Consumed | C257: 184 | D257: 1 | E257: =IFERROR(VLOOKUP(Table4[[#This Row],[From Location Code]],Table5[#All],3,0),"") -> Munger | F257: =IFERROR(VLOOKUP(Table4[[#This Row],[From Location Code]],Table5[#All],2,0),"") -> Main Godown | G257: 1007 | H257: =IFERROR(VLOOKUP(Table4[[#This Row],[To BMC/MPG Code]],Table5[#All],3,0),"") -> Araria | I257: =IFERROR(VLOOKUP(Table4[[#This Row],[To BMC/MPG Code]],Table5[#All],2,0),"") -> BMC | J257: Thermal Paper Roll - Small | K257: =IFERROR(VLOOKUP(Table4[[#This Row],[Item Name]],Table2[[Item Name]:[UoM]],2,0),"") -> Nos | L257: 60 | M257: =IFERROR(VLOOKUP(Table4[[#This Row],[Item Name]],Table2[[#All],[Item Name]:[Open Rate]],8,0),"") -> 9.15 | N257: =IFERROR(+Table4[[#This Row],[Qty Issued]]*Table4[[#This Row],[Rate]],"") -> 549 | O257: Yes | P257: Pending
A258: 45771 | B258: Consumed | C258: 184 | D258: 1 | E258: =IFERROR(VLOOKUP(Table4[[#This Row],[From Location Code]],Table5[#All],3,0),"") -> Munger | F258: =IFERROR(VLOOKUP(Table4[[#This Row],[From Location Code]],Table5[#All],2,0),"") -> Main Godown | G258: 1007 | H258: =IFERROR(VLOOKUP(Table4[[#This Row],[To BMC/MPG Code]],Table5[#All],3,0),"") -> Araria | I258: =IFERROR(VLOOKUP(Table4[[#This Row],[To BMC/MPG Code]],Table5[#All],2,0),"") -> BMC | J258: Sodium Hydroxide N/10 Solution | K258: =IFERROR(VLOOKUP(Table4[[#This Row],[Item Name]],Table2[[Item Name]:[UoM]],2,0),"") -> Nos | L258: 1 | M258: =IFERROR(VLOOKUP(Table4[[#This Row],[Item Name]],Table2[[#All],[Item Name]:[Open Rate]],8,0),"") -> 135.7 | N258: =IFERROR(+Table4[[#This Row],[Qty Issued]]*Table4[[#This Row],[Rate]],"") -> 135.7 | O258: Yes | P258: Pending
A259: 45772 | B259: Consumed | C259: 185 | D259: 1 | E259: =IFERROR(VLOOKUP(Table4[[#This Row],[From Location Code]],Table5[#All],3,0),"") -> Munger | F259: =IFERROR(VLOOKUP(Table4[[#This Row],[From Location Code]],Table5[#All],2,0),"") -> Main Godown | G259: 1004 | H259: =IFERROR(VLOOKUP(Table4[[#This Row],[To BMC/MPG Code]],Table5[#All],3,0),"") -> Tofir | I259: =IFERROR(VLOOKUP(Table4[[#This Row],[To BMC/MPG Code]],Table5[#All],2,0),"") -> BMC | J259: Milk Despatch Challan | K259: =IFERROR(VLOOKUP(Table4[[#This Row],[Item Name]],Table2[[Item Name]:[UoM]],2,0),"") -> Nos | L259: 1 | M259: =IFERROR(VLOOKUP(Table4[[#This Row],[Item Name]],Table2[[#All],[Item Name]:[Open Rate]],8,0),"") -> 94.4 | N259: =IFERROR(+Table4[[#This Row],[Qty Issued]]*Table4[[#This Row],[Rate]],"") -> 94.4 | O259: Yes | P259: Pending
A260: 45772 | B260: Consumed | C260: 185 | D260: 1 | E260: =IFERROR(VLOOKUP(Table4[[#This Row],[From Location Code]],Table5[#All],3,0),"") -> Munger | F260: =IFERROR(VLOOKUP(Table4[[#This Row],[From Location Code]],Table5[#All],2,0),"") -> Main Godown | G260: 1004 | H260: =IFERROR(VLOOKUP(Table4[[#This Row],[To BMC/MPG Code]],Table5[#All],3,0),"") -> Tofir | I260: =IFERROR(VLOOKUP(Table4[[#This Row],[To BMC/MPG Code]],Table5[#All],2,0),"") -> BMC | J260: Sample Bottle 100 ML | K260: =IFERROR(VLOOKUP(Table4[[#This Row],[Item Name]],Table2[[Item Name]:[UoM]],2,0),"") -> Nos | L260: 20 | M260: =IFERROR(VLOOKUP(Table4[[#This Row],[Item Name]],Table2[[#All],[Item Name]:[Open Rate]],8,0),"") -> 2.83 | N260: =IFERROR(+Table4[[#This Row],[Qty Issued]]*Table4[[#This Row],[Rate]],"") -> 56.6 | O260: Yes | P260: Pending
A261: 45772 | B261: Consumed | C261: 185 | D261: 1 | E261: =IFERROR(VLOOKUP(Table4[[#This Row],[From Location Code]],Table5[#All],3,0),"") -> Munger | F261: =IFERROR(VLOOKUP(Table4[[#This Row],[From Location Code]],Table5[#All],2,0),"") -> Main Godown | G261: 1004 | H261: =IFERROR(VLOOKUP(Table4[[#This Row],[To BMC/MPG Code]],Table5[#All],3,0),"") -> Tofir | I261: =IFERROR(VLOOKUP(Table4[[#This Row],[To BMC/MPG Code]],Table5[#All],2,0),"") -> BMC | J261: Farmers Passbook | K261: =IFERROR(VLOOKUP(Table4[[#This Row],[Item Name]],Table2[[Item Name]:[UoM]],2,0),"") -> Nos | L261: 20 | M261: =IFERROR(VLOOKUP(Table4[[#This Row],[Item Name]],Table2[[#All],[Item Name]:[Open Rate]],8,0),"") -> 5.13 | N261: =IFERROR(+Table4[[#This Row],[Qty Issued]]*Table4[[#This Row],[Rate]],"") -> 102.6 | O261: Yes | P261: Pending
A262: 45775 | B262: Consumed | C262: 186 | D262: 1 | E262: =IFERROR(VLOOKUP(Table4[[#This Row],[From Location Code]],Table5[#All],3,0),"") -> Munger | F262: =IFERROR(VLOOKUP(Table4[[#This Row],[From Location Code]],Table5[#All],2,0),"") -> Main Godown | G262: 10030002 | H262: =IFERROR(VLOOKUP(Table4[[#This Row],[To BMC/MPG Code]],Table5[#All],3,0),"") -> MOHANPUR | I262: =IFERROR(VLOOKUP(Table4[[#This Row],[To BMC/MPG Code]],Table5[#All],2,0),"") -> MPG | J262: Eko Day Cleaning Sol | K262: =IFERROR(VLOOKUP(Table4[[#This Row],[Item Name]],Table2[[Item Name]:[UoM]],2,0),"") -> Nos | L262: 1 | M262: =IFERROR(VLOOKUP(Table4[[#This Row],[Item Name]],Table2[[#All],[Item Name]:[Open Rate]],8,0),"") -> 348.52 | N262: =IFERROR(+Table4[[#This Row],[Qty Issued]]*Table4[[#This Row],[Rate]],"") -> 348.52 | O262: Yes | P262: Pending
A263: 45775 | B263: Consumed | C263: 186 | D263: 1 | E263: =IFERROR(VLOOKUP(Table4[[#This Row],[From Location Code]],Table5[#All],3,0),"") -> Munger | F263: =IFERROR(VLOOKUP(Table4[[#This Row],[From Location Code]],Table5[#All],2,0),"") -> Main Godown | G263: 10030003 | H263: =IFERROR(VLOOKUP(Table4[[#This Row],[To BMC/MPG Code]],Table5[#All],3,0),"") -> CHATMADIH | I263: =IFERROR(VLOOKUP(Table4[[#This Row],[To BMC/MPG Code]],Table5[#All],2,0),"") -> MPG | J263: Eko Day Cleaning Sol | K263: =IFERROR(VLOOKUP(Table4[[#This Row],[Item Name]],Table2[[Item Name]:[UoM]],2,0),"") -> Nos | L263: 1 | M263: =IFERROR(VLOOKUP(Table4[[#This Row],[Item Name]],Table2[[#All],[Item Name]:[Open Rate]],8,0),"") -> 348.52 | N263: =IFERROR(+Table4[[#This Row],[Qty Issued]]*Table4[[#This Row],[Rate]],"") -> 348.52 | O263: Yes | P263: Pending
A264: 45775 | B264: Consumed | C264: 186 | D264: 1 | E264: =IFERROR(VLOOKUP(Table4[[#This Row],[From Location Code]],Table5[#All],3,0),"") -> Munger | F264: =IFERROR(VLOOKUP(Table4[[#This Row],[From Location Code]],Table5[#All],2,0),"") -> Main Godown | G264: 10030004 | H264: =IFERROR(VLOOKUP(Table4[[#This Row],[To BMC/MPG Code]],Table5[#All],3,0),"") -> KUNNATH | I264: =IFERROR(VLOOKUP(Table4[[#This Row],[To BMC/MPG Code]],Table5[#All],2,0),"") -> MPG | J264: Eko Day Cleaning Sol | K264: =IFERROR(VLOOKUP(Table4[[#This Row],[Item Name]],Table2[[Item Name]:[UoM]],2,0),"") -> Nos | L264: 1 | M264: =IFERROR(VLOOKUP(Table4[[#This Row],[Item Name]],Table2[[#All],[Item Name]:[Open Rate]],8,0),"") -> 348.52 | N264: =IFERROR(+Table4[[#This Row],[Qty Issued]]*Table4[[#This Row],[Rate]],"") -> 348.52 | O264: Yes | P264: Pending
A265: 45775 | B265: Consumed | C265: 186 | D265: 1 | E265: =IFERROR(VLOOKUP(Table4[[#This Row],[From Location Code]],Table5[#All],3,0),"") -> Munger | F265: =IFERROR(VLOOKUP(Table4[[#This Row],[From Location Code]],Table5[#All],2,0),"") -> Main Godown | G265: 10030007 | H265: =IFERROR(VLOOKUP(Table4[[#This Row],[To BMC/MPG Code]],Table5[#All],3,0),"") -> SIYADIH | I265: =IFERROR(VLOOKUP(Table4[[#This Row],[To BMC/MPG Code]],Table5[#All],2,0),"") -> MPG | J265: Eko Day Cleaning Sol | K265: =IFERROR(VLOOKUP(Table4[[#This Row],[Item Name]],Table2[[Item Name]:[UoM]],2,0),"") -> Nos | L265: 1 | M265: =IFERROR(VLOOKUP(Table4[[#This Row],[Item Name]],Table2[[#All],[Item Name]:[Open Rate]],8,0),"") -> 348.52 | N265: =IFERROR(+Table4[[#This Row],[Qty Issued]]*Table4[[#This Row],[Rate]],"") -> 348.52 | O265: Yes | P265: Pending
... A657: 45790 | B657: Consumed | C657: 195 | D657: 1 | E657: =IFERROR(VLOOKUP(Table4[[#This Row],[From Location Code]],Table5[#All],3,0),"") -> Munger | F657: =IFERROR(VLOOKUP(Table4[[#This Row],[From Location Code]],Table5[#All],2,0),"") -> Main Godown | G657: 1054 | H657: =IFERROR(VLOOKUP(Table4[[#This Row],[To BMC/MPG Code]],Table5[#All],3,0),"") -> Alauli | I657: =IFERROR(VLOOKUP(Table4[[#This Row],[To BMC/MPG Code]],Table5[#All],2,0),"") -> BMC | J657: Milk Cane Plunger S. S. | K657: =IFERROR(VLOOKUP(Table4[[#This Row],[Item Name]],Table2[[Item Name]:[UoM]],2,0),"") -> Nos | L657: 1 | M657: =IFERROR(VLOOKUP(Table4[[#This Row],[Item Name]],Table2[[#All],[Item Name]:[Open Rate]],8,0),"") -> 112.1 | N657: =IFERROR(+Table4[[#This Row],[Qty Issued]]*Table4[[#This Row],[Rate]],"") -> 112.1 | O657: No | P657: NA
A658: 45790 | B658: Consumed | C658: 196 | D658: 1 | E658: =IFERROR(VLOOKUP(Table4[[#This Row],[From Location Code]],Table5[#All],3,0),"") -> Munger | F658: =IFERROR(VLOOKUP(Table4[[#This Row],[From Location Code]],Table5[#All],2,0),"") -> Main Godown | G658: Lab | H658: =IFERROR(VLOOKUP(Table4[[#This Row],[To BMC/MPG Code]],Table5[#All],3,0),"") -> Daya_Lab | I658: =IFERROR(VLOOKUP(Table4[[#This Row],[To BMC/MPG Code]],Table5[#All],2,0),"") -> Lab | J658: Milk Despatch Challan | K658: =IFERROR(VLOOKUP(Table4[[#This Row],[Item Name]],Table2[[Item Name]:[UoM]],2,0),"") -> Nos | L658: 3 | M658: =IFERROR(VLOOKUP(Table4[[#This Row],[Item Name]],Table2[[#All],[Item Name]:[Open Rate]],8,0),"") -> 94.4 | N658: =IFERROR(+Table4[[#This Row],[Qty Issued]]*Table4[[#This Row],[Rate]],"") -> 283.2 | O658: No | P658: NA
A659: 45792 | B659: Consumed | C659: 197 | D659: 1 | E659: =IFERROR(VLOOKUP(Table4[[#This Row],[From Location Code]],Table5[#All],3,0),"") -> Munger | F659: =IFERROR(VLOOKUP(Table4[[#This Row],[From Location Code]],Table5[#All],2,0),"") -> Main Godown | G659: 1007 | H659: =IFERROR(VLOOKUP(Table4[[#This Row],[To BMC/MPG Code]],Table5[#All],3,0),"") -> Araria | I659: =IFERROR(VLOOKUP(Table4[[#This Row],[To BMC/MPG Code]],Table5[#All],2,0),"") -> BMC | J659: BMC Day Book | K659: =IFERROR(VLOOKUP(Table4[[#This Row],[Item Name]],Table2[[Item Name]:[UoM]],2,0),"") -> Nos | L659: 20 | M659: =IFERROR(VLOOKUP(Table4[[#This Row],[Item Name]],Table2[[#All],[Item Name]:[Open Rate]],8,0),"") -> 121.54 | N659: =IFERROR(+Table4[[#This Row],[Qty Issued]]*Table4[[#This Row],[Rate]],"") -> 2430.8 | O659: Yes | P659: Pending
A660: 45792 | B660: Consumed | C660: 197 | D660: 1 | E660: =IFERROR(VLOOKUP(Table4[[#This Row],[From Location Code]],Table5[#All],3,0),"") -> Munger | F660: =IFERROR(VLOOKUP(Table4[[#This Row],[From Location Code]],Table5[#All],2,0),"") -> Main Godown | G660: 1007 | H660: =IFERROR(VLOOKUP(Table4[[#This Row],[To BMC/MPG Code]],Table5[#All],3,0),"") -> Araria | I660: =IFERROR(VLOOKUP(Table4[[#This Row],[To BMC/MPG Code]],Table5[#All],2,0),"") -> BMC | J660: Milk Despatch Challan | K660: =IFERROR(VLOOKUP(Table4[[#This Row],[Item Name]],Table2[[Item Name]:[UoM]],2,0),"") -> Nos | L660: 20 | M660: =IFERROR(VLOOKUP(Table4[[#This Row],[Item Name]],Table2[[#All],[Item Name]:[Open Rate]],8,0),"") -> 94.4 | N660: =IFERROR(+Table4[[#This Row],[Qty Issued]]*Table4[[#This Row],[Rate]],"") -> 1888 | O660: Yes | P660: Pending
A661: 45792 | B661: Consumed | C661: 197 | D661: 1 | E661: =IFERROR(VLOOKUP(Table4[[#This Row],[From Location Code]],Table5[#All],3,0),"") -> Munger | F661: =IFERROR(VLOOKUP(Table4[[#This Row],[From Location Code]],Table5[#All],2,0),"") -> Main Godown | G661: 1007 | H661: =IFERROR(VLOOKUP(Table4[[#This Row],[To BMC/MPG Code]],Table5[#All],3,0),"") -> Araria | I661: =IFERROR(VLOOKUP(Table4[[#This Row],[To BMC/MPG Code]],Table5[#All],2,0),"") -> BMC | J661: Sodium Hydroxide N/10 Solution | K661: =IFERROR(VLOOKUP(Table4[[#This Row],[Item Name]],Table2[[Item Name]:[UoM]],2,0),"") -> Nos | L661: 3 | M661: =IFERROR(VLOOKUP(Table4[[#This Row],[Item Name]],Table2[[#All],[Item Name]:[Open Rate]],8,0),"") -> 135.7 | N661: =IFERROR(+Table4[[#This Row],[Qty Issued]]*Table4[[#This Row],[Rate]],"") -> 407.1 | O661: Yes | P661: Pending
A662: 45792 | B662: Consumed | C662: 197 | D662: 1 | E662: =IFERROR(VLOOKUP(Table4[[#This Row],[From Location Code]],Table5[#All],3,0),"") -> Munger | F662: =IFERROR(VLOOKUP(Table4[[#This Row],[From Location Code]],Table5[#All],2,0),"") -> Main Godown | G662: 1007 | H662: =IFERROR(VLOOKUP(Table4[[#This Row],[To BMC/MPG Code]],Table5[#All],3,0),"") -> Araria | I662: =IFERROR(VLOOKUP(Table4[[#This Row],[To BMC/MPG Code]],Table5[#All],2,0),"") -> BMC | J662: Tanker Seal | K662: =IFERROR(VLOOKUP(Table4[[#This Row],[Item Name]],Table2[[Item Name]:[UoM]],2,0),"") -> Nos | L662: 400 | M662: =IFERROR(VLOOKUP(Table4[[#This Row],[Item Name]],Table2[[#All],[Item Name]:[Open Rate]],8,0),"") -> 12.71 | N662: =IFERROR(+Table4[[#This Row],[Qty Issued]]*Table4[[#This Row],[Rate]],"") -> 5084 | O662: Yes | P662: Pending
A663: 45792 | B663: Consumed | C663: 197 | D663: 1 | E663: =IFERROR(VLOOKUP(Table4[[#This Row],[From Location Code]],Table5[#All],3,0),"") -> Munger | F663: =IFERROR(VLOOKUP(Table4[[#This Row],[From Location Code]],Table5[#All],2,0),"") -> Main Godown | G663: 1007 | H663: =IFERROR(VLOOKUP(Table4[[#This Row],[To BMC/MPG Code]],Table5[#All],3,0),"") -> Araria | I663: =IFERROR(VLOOKUP(Table4[[#This Row],[To BMC/MPG Code]],Table5[#All],2,0),"") -> BMC | J663: Sulphuric Acid SQ 05 Lt | K663: =IFERROR(VLOOKUP(Table4[[#This Row],[Item Name]],Table2[[Item Name]:[UoM]],2,0),"") -> Nos | L663: 1 | M663: =IFERROR(VLOOKUP(Table4[[#This Row],[Item Name]],Table2[[#All],[Item Name]:[Open Rate]],8,0),"") -> 812.2 | N663: =IFERROR(+Table4[[#This Row],[Qty Issued]]*Table4[[#This Row],[Rate]],"") -> 812.2 | O663: Yes | P663: Pending
A664: 45792 | B664: Consumed | C664: 197 | D664: 1 | E664: =IFERROR(VLOOKUP(Table4[[#This Row],[From Location Code]],Table5[#All],3,0),"") -> Munger | F664: =IFERROR(VLOOKUP(Table4[[#This Row],[From Location Code]],Table5[#All],2,0),"") -> Main Godown | G664: 1007 | H664: =IFERROR(VLOOKUP(Table4[[#This Row],[To BMC/MPG Code]],Table5[#All],3,0),"") -> Araria | I664: =IFERROR(VLOOKUP(Table4[[#This Row],[To BMC/MPG Code]],Table5[#All],2,0),"") -> BMC | J664: TEEPOL | K664: =IFERROR(VLOOKUP(Table4[[#This Row],[Item Name]],Table2[[Item Name]:[UoM]],2,0),"") -> Nos | L664: 50 | M664: =IFERROR(VLOOKUP(Table4[[#This Row],[Item Name]],Table2[[#All],[Item Name]:[Open Rate]],8,0),"") -> 51.92 | N664: =IFERROR(+Table4[[#This Row],[Qty Issued]]*Table4[[#This Row],[Rate]],"") -> 2596 | O664: Yes | P664: Pending
A665: 45792 | B665: Consumed | C665: 197 | D665: 1 | E665: =IFERROR(VLOOKUP(Table4[[#This Row],[From Location Code]],Table5[#All],3,0),"") -> Munger | F665: =IFERROR(VLOOKUP(Table4[[#This Row],[From Location Code]],Table5[#All],2,0),"") -> Main Godown | G665: 1007 | H665: =IFERROR(VLOOKUP(Table4[[#This Row],[To BMC/MPG Code]],Table5[#All],3,0),"") -> Araria | I665: =IFERROR(VLOOKUP(Table4[[#This Row],[To BMC/MPG Code]],Table5[#All],2,0),"") -> BMC | J665: Satol - 5 KG | K665: =IFERROR(VLOOKUP(Table4[[#This Row],[Item Name]],Table2[[Item Name]:[UoM]],2,0),"") -> Nos | L665: 10 | M665: =IFERROR(VLOOKUP(Table4[[#This Row],[Item Name]],Table2[[#All],[Item Name]:[Open Rate]],8,0),"") -> 135.7 | N665: =IFERROR(+Table4[[#This Row],[Qty Issued]]*Table4[[#This Row],[Rate]],"") -> 1357 | O665: Yes | P665: Pending
A666: 45794 | B666: Consumed | C666: 198 | D666: 1 | E666: =IFERROR(VLOOKUP(Table4[[#This Row],[From Location Code]],Table5[#All],3,0),"") -> Munger | F666: =IFERROR(VLOOKUP(Table4[[#This Row],[From Location Code]],Table5[#All],2,0),"") -> Main Godown | G666: 1011 | H666: =IFERROR(VLOOKUP(Table4[[#This Row],[To BMC/MPG Code]],Table5[#All],3,0),"") -> Sahibpur Kamal | I666: =IFERROR(VLOOKUP(Table4[[#This Row],[To BMC/MPG Code]],Table5[#All],2,0),"") -> BMC | J666: Ethyl Alcohol 500 ML Pack | K666: =IFERROR(VLOOKUP(Table4[[#This Row],[Item Name]],Table2[[Item Name]:[UoM]],2,0),"") -> Nos | L666: 6 | M666: =IFERROR(VLOOKUP(Table4[[#This Row],[Item Name]],Table2[[#All],[Item Name]:[Open Rate]],8,0),"") -> 271.4 | N666: =IFERROR(+Table4[[#This Row],[Qty Issued]]*Table4[[#This Row],[Rate]],"") -> 1628.4 | O666: No | P666: NA
A667: 45794 | B667: Consumed | C667: 198 | D667: 1 | E667: =IFERROR(VLOOKUP(Table4[[#This Row],[From Location Code]],Table5[#All],3,0),"") -> Munger | F667: =IFERROR(VLOOKUP(Table4[[#This Row],[From Location Code]],Table5[#All],2,0),"") -> Main Godown | G667: 1011 | H667: =IFERROR(VLOOKUP(Table4[[#This Row],[To BMC/MPG Code]],Table5[#All],3,0),"") -> Sahibpur Kamal | I667: =IFERROR(VLOOKUP(Table4[[#This Row],[To BMC/MPG Code]],Table5[#All],2,0),"") -> BMC | J667: Silver Nitrate Solution | K667: =IFERROR(VLOOKUP(Table4[[#This Row],[Item Name]],Table2[[Item Name]:[UoM]],2,0),"") -> Nos | L667: 2 | M667: =IFERROR(VLOOKUP(Table4[[#This Row],[Item Name]],Table2[[#All],[Item Name]:[Open Rate]],8,0),"") -> 622.47 | N667: =IFERROR(+Table4[[#This Row],[Qty Issued]]*Table4[[#This Row],[Rate]],"") -> 1244.94 | O667: No | P667: NA
A668: 45794 | B668: Consumed | C668: 198 | D668: 1 | E668: =IFERROR(VLOOKUP(Table4[[#This Row],[From Location Code]],Table5[#All],3,0),"") -> Munger | F668: =IFERROR(VLOOKUP(Table4[[#This Row],[From Location Code]],Table5[#All],2,0),"") -> Main Godown | G668: 1011 | H668: =IFERROR(VLOOKUP(Table4[[#This Row],[To BMC/MPG Code]],Table5[#All],3,0),"") -> Sahibpur Kamal | I668: =IFERROR(VLOOKUP(Table4[[#This Row],[To BMC/MPG Code]],Table5[#All],2,0),"") -> BMC | J668: Amyl 500ml | K668: =IFERROR(VLOOKUP(Table4[[#This Row],[Item Name]],Table2[[Item Name]:[UoM]],2,0),"") -> Nos | L668: 1 | M668: =IFERROR(VLOOKUP(Table4[[#This Row],[Item Name]],Table2[[#All],[Item Name]:[Open Rate]],8,0),"") -> 365.8 | N668: =IFERROR(+Table4[[#This Row],[Qty Issued]]*Table4[[#This Row],[Rate]],"") -> 365.8 | O668: No | P668: NA
A669: 45794 | B669: Consumed | C669: 198 | D669: 1 | E669: =IFERROR(VLOOKUP(Table4[[#This Row],[From Location Code]],Table5[#All],3,0),"") -> Munger | F669: =IFERROR(VLOOKUP(Table4[[#This Row],[From Location Code]],Table5[#All],2,0),"") -> Main Godown | G669: 1011 | H669: =IFERROR(VLOOKUP(Table4[[#This Row],[To BMC/MPG Code]],Table5[#All],3,0),"") -> Sahibpur Kamal | I669: =IFERROR(VLOOKUP(Table4[[#This Row],[To BMC/MPG Code]],Table5[#All],2,0),"") -> BMC | J669: Sulphuric Acid SQ 05 Lt | K669: =IFERROR(VLOOKUP(Table4[[#This Row],[Item Name]],Table2[[Item Name]:[UoM]],2,0),"") -> Nos | L669: 1 | M669: =IFERROR(VLOOKUP(Table4[[#This Row],[Item Name]],Table2[[#All],[Item Name]:[Open Rate]],8,0),"") -> 812.2 | N669: =IFERROR(+Table4[[#This Row],[Qty Issued]]*Table4[[#This Row],[Rate]],"") -> 812.2 | O669: No | P669: NA
A670: 45794 | B670: Consumed | C670: 198 | D670: 1 | E670: =IFERROR(VLOOKUP(Table4[[#This Row],[From Location Code]],Table5[#All],3,0),"") -> Munger | F670: =IFERROR(VLOOKUP(Table4[[#This Row],[From Location Code]],Table5[#All],2,0),"") -> Main Godown | G670: 1011 | H670: =IFERROR(VLOOKUP(Table4[[#This Row],[To BMC/MPG Code]],Table5[#All],3,0),"") -> Sahibpur Kamal | I670: =IFERROR(VLOOKUP(Table4[[#This Row],[To BMC/MPG Code]],Table5[#All],2,0),"") -> BMC | J670: Phenolphthaleing Indicator | K670: =IFERROR(VLOOKUP(Table4[[#This Row],[Item Name]],Table2[[Item Name]:[UoM]],2,0),"") -> Nos | L670: 2 | M670: =IFERROR(VLOOKUP(Table4[[#This Row],[Item Name]],Table2[[#All],[Item Name]:[Open Rate]],8,0),"") -> 106.2 | N670: =IFERROR(+Table4[[#This Row],[Qty Issued]]*Table4[[#This Row],[Rate]],"") -> 212.4 | O670: No | P670: NA
... A763: 45803 | B763: Consumed | C763: 204 | D763: 1 | E763: =IFERROR(VLOOKUP(Table4[[#This Row],[From Location Code]],Table5[#All],3,0),"") -> Munger | F763: =IFERROR(VLOOKUP(Table4[[#This Row],[From Location Code]],Table5[#All],2,0),"") -> Main Godown | G763: 10080099 | H763: =IFERROR(VLOOKUP(Table4[[#This Row],[To BMC/MPG Code]],Table5[#All],3,0),"") -> Bihat - Chakballi | I763: =IFERROR(VLOOKUP(Table4[[#This Row],[To BMC/MPG Code]],Table5[#All],2,0),"") -> MPG | J763: Thermal Paper Roll - Small | K763: =IFERROR(VLOOKUP(Table4[[#This Row],[Item Name]],Table2[[Item Name]:[UoM]],2,0),"") -> Nos | L763: 12 | M763: =IFERROR(VLOOKUP(Table4[[#This Row],[Item Name]],Table2[[#All],[Item Name]:[Open Rate]],8,0),"") -> 9.15 | N763: =IFERROR(+Table4[[#This Row],[Qty Issued]]*Table4[[#This Row],[Rate]],"") -> 109.8 | O763: No | P763: NA
A764: 45804 | B764: Consumed | C764: 206 | D764: 1 | E764: =IFERROR(VLOOKUP(Table4[[#This Row],[From Location Code]],Table5[#All],3,0),"") -> Munger | F764: =IFERROR(VLOOKUP(Table4[[#This Row],[From Location Code]],Table5[#All],2,0),"") -> Main Godown | G764: Lab | H764: =IFERROR(VLOOKUP(Table4[[#This Row],[To BMC/MPG Code]],Table5[#All],3,0),"") -> Daya_Lab | I764: =IFERROR(VLOOKUP(Table4[[#This Row],[To BMC/MPG Code]],Table5[#All],2,0),"") -> Lab | J764: Milk Despatch Challan | K764: =IFERROR(VLOOKUP(Table4[[#This Row],[Item Name]],Table2[[Item Name]:[UoM]],2,0),"") -> Nos | L764: 1 | M764: =IFERROR(VLOOKUP(Table4[[#This Row],[Item Name]],Table2[[#All],[Item Name]:[Open Rate]],8,0),"") -> 94.4 | N764: =IFERROR(+Table4[[#This Row],[Qty Issued]]*Table4[[#This Row],[Rate]],"") -> 94.4 | O764: No | P764: NA
A765: 45811 | B765: Consumed | C765: 207 | D765: 1 | E765: =IFERROR(VLOOKUP(Table4[[#This Row],[From Location Code]],Table5[#All],3,0),"") -> Munger | F765: =IFERROR(VLOOKUP(Table4[[#This Row],[From Location Code]],Table5[#All],2,0),"") -> Main Godown | G765: 1008 | H765: =IFERROR(VLOOKUP(Table4[[#This Row],[To BMC/MPG Code]],Table5[#All],3,0),"") -> Teghra | I765: =IFERROR(VLOOKUP(Table4[[#This Row],[To BMC/MPG Code]],Table5[#All],2,0),"") -> BMC | J765: Tanker Seal | K765: =IFERROR(VLOOKUP(Table4[[#This Row],[Item Name]],Table2[[Item Name]:[UoM]],2,0),"") -> Nos | L765: 400 | M765: =IFERROR(VLOOKUP(Table4[[#This Row],[Item Name]],Table2[[#All],[Item Name]:[Open Rate]],8,0),"") -> 12.71 | N765: =IFERROR(+Table4[[#This Row],[Qty Issued]]*Table4[[#This Row],[Rate]],"") -> 5084 | O765: Yes | P765: Pending
A766: 45811 | B766: Consumed | C766: 207 | D766: 1 | E766: =IFERROR(VLOOKUP(Table4[[#This Row],[From Location Code]],Table5[#All],3,0),"") -> Munger | F766: =IFERROR(VLOOKUP(Table4[[#This Row],[From Location Code]],Table5[#All],2,0),"") -> Main Godown | G766: 1008 | H766: =IFERROR(VLOOKUP(Table4[[#This Row],[To BMC/MPG Code]],Table5[#All],3,0),"") -> Teghra | I766: =IFERROR(VLOOKUP(Table4[[#This Row],[To BMC/MPG Code]],Table5[#All],2,0),"") -> BMC | J766: BMC Day Book | K766: =IFERROR(VLOOKUP(Table4[[#This Row],[Item Name]],Table2[[Item Name]:[UoM]],2,0),"") -> Nos | L766: 10 | M766: =IFERROR(VLOOKUP(Table4[[#This Row],[Item Name]],Table2[[#All],[Item Name]:[Open Rate]],8,0),"") -> 121.54 | N766: =IFERROR(+Table4[[#This Row],[Qty Issued]]*Table4[[#This Row],[Rate]],"") -> 1215.4 | O766: Yes | P766: Pending
A767: 45811 | B767: Consumed | C767: 207 | D767: 1 | E767: =IFERROR(VLOOKUP(Table4[[#This Row],[From Location Code]],Table5[#All],3,0),"") -> Munger | F767: =IFERROR(VLOOKUP(Table4[[#This Row],[From Location Code]],Table5[#All],2,0),"") -> Main Godown | G767: 1008 | H767: =IFERROR(VLOOKUP(Table4[[#This Row],[To BMC/MPG Code]],Table5[#All],3,0),"") -> Teghra | I767: =IFERROR(VLOOKUP(Table4[[#This Row],[To BMC/MPG Code]],Table5[#All],2,0),"") -> BMC | J767: Milk Despatch Challan | K767: =IFERROR(VLOOKUP(Table4[[#This Row],[Item Name]],Table2[[Item Name]:[UoM]],2,0),"") -> Nos | L767: 10 | M767: =IFERROR(VLOOKUP(Table4[[#This Row],[Item Name]],Table2[[#All],[Item Name]:[Open Rate]],8,0),"") -> 94.4 | N767: =IFERROR(+Table4[[#This Row],[Qty Issued]]*Table4[[#This Row],[Rate]],"") -> 944 | O767: Yes | P767: Pending
A768: 45811 | B768: Consumed | C768: 207 | D768: 1 | E768: =IFERROR(VLOOKUP(Table4[[#This Row],[From Location Code]],Table5[#All],3,0),"") -> Munger | F768: =IFERROR(VLOOKUP(Table4[[#This Row],[From Location Code]],Table5[#All],2,0),"") -> Main Godown | G768: 1008 | H768: =IFERROR(VLOOKUP(Table4[[#This Row],[To BMC/MPG Code]],Table5[#All],3,0),"") -> Teghra | I768: =IFERROR(VLOOKUP(Table4[[#This Row],[To BMC/MPG Code]],Table5[#All],2,0),"") -> BMC | J768: Register for Milk Reception Log Book | K768: =IFERROR(VLOOKUP(Table4[[#This Row],[Item Name]],Table2[[Item Name]:[UoM]],2,0),"") -> Nos | L768: 10 | M768: =IFERROR(VLOOKUP(Table4[[#This Row],[Item Name]],Table2[[#All],[Item Name]:[Open Rate]],8,0),"") -> 218.3 | N768: =IFERROR(+Table4[[#This Row],[Qty Issued]]*Table4[[#This Row],[Rate]],"") -> 2183 | O768: Yes | P768: Pending
A769: 45813 | B769: Consumed | C769: 210 | D769: 1 | E769: =IFERROR(VLOOKUP(Table4[[#This Row],[From Location Code]],Table5[#All],3,0),"") -> Munger | F769: =IFERROR(VLOOKUP(Table4[[#This Row],[From Location Code]],Table5[#All],2,0),"") -> Main Godown | G769: 1002 | H769: =IFERROR(VLOOKUP(Table4[[#This Row],[To BMC/MPG Code]],Table5[#All],3,0),"") -> Laldiyara | I769: =IFERROR(VLOOKUP(Table4[[#This Row],[To BMC/MPG Code]],Table5[#All],2,0),"") -> BMC | J769: Tanker Seal | K769: =IFERROR(VLOOKUP(Table4[[#This Row],[Item Name]],Table2[[Item Name]:[UoM]],2,0),"") -> Nos | L769: 400 | M769: =IFERROR(VLOOKUP(Table4[[#This Row],[Item Name]],Table2[[#All],[Item Name]:[Open Rate]],8,0),"") -> 12.71 | N769: =IFERROR(+Table4[[#This Row],[Qty Issued]]*Table4[[#This Row],[Rate]],"") -> 5084 | O769: Yes | P769: Pending
A770: 45813 | B770: Consumed | C770: 210 | D770: 1 | E770: =IFERROR(VLOOKUP(Table4[[#This Row],[From Location Code]],Table5[#All],3,0),"") -> Munger | F770: =IFERROR(VLOOKUP(Table4[[#This Row],[From Location Code]],Table5[#All],2,0),"") -> Main Godown | G770: 1002 | H770: =IFERROR(VLOOKUP(Table4[[#This Row],[To BMC/MPG Code]],Table5[#All],3,0),"") -> Laldiyara | I770: =IFERROR(VLOOKUP(Table4[[#This Row],[To BMC/MPG Code]],Table5[#All],2,0),"") -> BMC | J770: Eko Day Cleaning Sol | K770: =IFERROR(VLOOKUP(Table4[[#This Row],[Item Name]],Table2[[Item Name]:[UoM]],2,0),"") -> Nos | L770: 1 | M770: =IFERROR(VLOOKUP(Table4[[#This Row],[Item Name]],Table2[[#All],[Item Name]:[Open Rate]],8,0),"") -> 348.52 | N770: =IFERROR(+Table4[[#This Row],[Qty Issued]]*Table4[[#This Row],[Rate]],"") -> 348.52 | O770: Yes | P770: Pending
A771: 45813 | B771: Consumed | C771: 210 | D771: 1 | E771: =IFERROR(VLOOKUP(Table4[[#This Row],[From Location Code]],Table5[#All],3,0),"") -> Munger | F771: =IFERROR(VLOOKUP(Table4[[#This Row],[From Location Code]],Table5[#All],2,0),"") -> Main Godown | G771: 1002 | H771: =IFERROR(VLOOKUP(Table4[[#This Row],[To BMC/MPG Code]],Table5[#All],3,0),"") -> Laldiyara | I771: =IFERROR(VLOOKUP(Table4[[#This Row],[To BMC/MPG Code]],Table5[#All],2,0),"") -> BMC | J771: FAT Scan Weekly | K771: =IFERROR(VLOOKUP(Table4[[#This Row],[Item Name]],Table2[[Item Name]:[UoM]],2,0),"") -> Nos | L771: 1 | M771: =IFERROR(VLOOKUP(Table4[[#This Row],[Item Name]],Table2[[#All],[Item Name]:[Open Rate]],8,0),"") -> 348.52 | N771: =IFERROR(+Table4[[#This Row],[Qty Issued]]*Table4[[#This Row],[Rate]],"") -> 348.52 | O771: Yes | P771: Pending
A772: 45813 | B772: Consumed | C772: 210 | D772: 1 | E772: =IFERROR(VLOOKUP(Table4[[#This Row],[From Location Code]],Table5[#All],3,0),"") -> Munger | F772: =IFERROR(VLOOKUP(Table4[[#This Row],[From Location Code]],Table5[#All],2,0),"") -> Main Godown | G772: 1002 | H772: =IFERROR(VLOOKUP(Table4[[#This Row],[To BMC/MPG Code]],Table5[#All],3,0),"") -> Laldiyara | I772: =IFERROR(VLOOKUP(Table4[[#This Row],[To BMC/MPG Code]],Table5[#All],2,0),"") -> BMC | J772: Eco Power Solution | K772: =IFERROR(VLOOKUP(Table4[[#This Row],[Item Name]],Table2[[Item Name]:[UoM]],2,0),"") -> Nos | L772: 1 | M772: =IFERROR(VLOOKUP(Table4[[#This Row],[Item Name]],Table2[[#All],[Item Name]:[Open Rate]],8,0),"") -> 348.52 | N772: =IFERROR(+Table4[[#This Row],[Qty Issued]]*Table4[[#This Row],[Rate]],"") -> 348.52 | O772: Yes | P772: Pending
A773: 45817 | B773: Consumed | C773: 211 | D773: 1 | E773: =IFERROR(VLOOKUP(Table4[[#This Row],[From Location Code]],Table5[#All],3,0),"") -> Munger | F773: =IFERROR(VLOOKUP(Table4[[#This Row],[From Location Code]],Table5[#All],2,0),"") -> Main Godown | G773: 1006 | H773: =IFERROR(VLOOKUP(Table4[[#This Row],[To BMC/MPG Code]],Table5[#All],3,0),"") -> Sonvarsha | I773: =IFERROR(VLOOKUP(Table4[[#This Row],[To BMC/MPG Code]],Table5[#All],2,0),"") -> BMC | J773: Buterometer | K773: =IFERROR(VLOOKUP(Table4[[#This Row],[Item Name]],Table2[[Item Name]:[UoM]],2,0),"") -> Nos | L773: 2 | M773: =IFERROR(VLOOKUP(Table4[[#This Row],[Item Name]],Table2[[#All],[Item Name]:[Open Rate]],8,0),"") -> 132.7 | N773: =IFERROR(+Table4[[#This Row],[Qty Issued]]*Table4[[#This Row],[Rate]],"") -> 265.4 | O773: Yes | P773: Pending
A774: 45817 | B774: Consumed | C774: 211 | D774: 1 | E774: =IFERROR(VLOOKUP(Table4[[#This Row],[From Location Code]],Table5[#All],3,0),"") -> Munger | F774: =IFERROR(VLOOKUP(Table4[[#This Row],[From Location Code]],Table5[#All],2,0),"") -> Main Godown | G774: 1006 | H774: =IFERROR(VLOOKUP(Table4[[#This Row],[To BMC/MPG Code]],Table5[#All],3,0),"") -> Sonvarsha | I774: =IFERROR(VLOOKUP(Table4[[#This Row],[To BMC/MPG Code]],Table5[#All],2,0),"") -> BMC | J774: Milk Pipete 10.75 ML | K774: =IFERROR(VLOOKUP(Table4[[#This Row],[Item Name]],Table2[[Item Name]:[UoM]],2,0),"") -> Nos | L774: 2 | M774: =IFERROR(VLOOKUP(Table4[[#This Row],[Item Name]],Table2[[#All],[Item Name]:[Open Rate]],8,0),"") -> 132.7 | N774: =IFERROR(+Table4[[#This Row],[Qty Issued]]*Table4[[#This Row],[Rate]],"") -> 265.4 | O774: Yes | P774: Pending
A775: 45817 | B775: Consumed | C775: 212 | D775: 1 | E775: =IFERROR(VLOOKUP(Table4[[#This Row],[From Location Code]],Table5[#All],3,0),"") -> Munger | F775: =IFERROR(VLOOKUP(Table4[[#This Row],[From Location Code]],Table5[#All],2,0),"") -> Main Godown | G775: Lab | H775: =IFERROR(VLOOKUP(Table4[[#This Row],[To BMC/MPG Code]],Table5[#All],3,0),"") -> Daya_Lab | I775: =IFERROR(VLOOKUP(Table4[[#This Row],[To BMC/MPG Code]],Table5[#All],2,0),"") -> Lab | J775: Milk Despatch Challan | K775: =IFERROR(VLOOKUP(Table4[[#This Row],[Item Name]],Table2[[Item Name]:[UoM]],2,0),"") -> Nos | L775: 1 | M775: =IFERROR(VLOOKUP(Table4[[#This Row],[Item Name]],Table2[[#All],[Item Name]:[Open Rate]],8,0),"") -> 94.4 | N775: =IFERROR(+Table4[[#This Row],[Qty Issued]]*Table4[[#This Row],[Rate]],"") -> 94.4 | O775: No | P775: NA
A776: 45817 | B776: Consumed | C776: 212 | D776: 1 | E776: =IFERROR(VLOOKUP(Table4[[#This Row],[From Location Code]],Table5[#All],3,0),"") -> Munger | F776: =IFERROR(VLOOKUP(Table4[[#This Row],[From Location Code]],Table5[#All],2,0),"") -> Main Godown | G776: Lab | H776: =IFERROR(VLOOKUP(Table4[[#This Row],[To BMC/MPG Code]],Table5[#All],3,0),"") -> Daya_Lab | I776: =IFERROR(VLOOKUP(Table4[[#This Row],[To BMC/MPG Code]],Table5[#All],2,0),"") -> Lab | J776: Rosalic Acid Powder 25 Gms | K776: =IFERROR(VLOOKUP(Table4[[#This Row],[Item Name]],Table2[[Item Name]:[UoM]],2,0),"") -> Nos | L776: 1 | M776: =IFERROR(VLOOKUP(Table4[[#This Row],[Item Name]],Table2[[#All],[Item Name]:[Open Rate]],8,0),"") -> 732.5 | N776: =IFERROR(+Table4[[#This Row],[Qty Issued]]*Table4[[#This Row],[Rate]],"") -> 732.5 | O776: No | P776: NA
A777: 45817 | B777: Consumed | C777: 213 | D777: 1 | E777: =IFERROR(VLOOKUP(Table4[[#This Row],[From Location Code]],Table5[#All],3,0),"") -> Munger | F777: =IFERROR(VLOOKUP(Table4[[#This Row],[From Location Code]],Table5[#All],2,0),"") -> Main Godown | G777: 1012 | H777: =IFERROR(VLOOKUP(Table4[[#This Row],[To BMC/MPG Code]],Table5[#All],3,0),"") -> DalsinghSarai | I777: =IFERROR(VLOOKUP(Table4[[#This Row],[To BMC/MPG Code]],Table5[#All],2,0),"") -> BMC | J777: MBRT Test Register | K777: =IFERROR(VLOOKUP(Table4[[#This Row],[Item Name]],Table2[[Item Name]:[UoM]],2,0),"") -> Nos | L777: 15 | M777: =IFERROR(VLOOKUP(Table4[[#This Row],[Item Name]],Table2[[#All],[Item Name]:[Open Rate]],8,0),"") -> 115.36 | N777: =IFERROR(+Table4[[#This Row],[Qty Issued]]*Table4[[#This Row],[Rate]],"") -> 1730.4 | O777: No | P777: NA
A778: 45817 | B778: Consumed | C778: 213 | D778: 1 | E778: =IFERROR(VLOOKUP(Table4[[#This Row],[From Location Code]],Table5[#All],3,0),"") -> Munger | F778: =IFERROR(VLOOKUP(Table4[[#This Row],[From Location Code]],Table5[#All],2,0),"") -> Main Godown | G778: 1012 | H778: =IFERROR(VLOOKUP(Table4[[#This Row],[To BMC/MPG Code]],Table5[#All],3,0),"") -> DalsinghSarai | I778: =IFERROR(VLOOKUP(Table4[[#This Row],[To BMC/MPG Code]],Table5[#All],2,0),"") -> BMC | J778: Nylon Filter Cloth - Than | K778: =IFERROR(VLOOKUP(Table4[[#This Row],[Item Name]],Table2[[Item Name]:[UoM]],2,0),"") -> Nos | L778: 2 | M778: =IFERROR(VLOOKUP(Table4[[#This Row],[Item Name]],Table2[[#All],[Item Name]:[Open Rate]],8,0),"") -> 738.09 | N778: =IFERROR(+Table4[[#This Row],[Qty Issued]]*Table4[[#This Row],[Rate]],"") -> 1476.18 | O778: No | P778: NA
A779: 45817 | B779: Consumed | C779: 213 | D779: 1 | E779: =IFERROR(VLOOKUP(Table4[[#This Row],[From Location Code]],Table5[#All],3,0),"") -> Munger | F779: =IFERROR(VLOOKUP(Table4[[#This Row],[From Location Code]],Table5[#All],2,0),"") -> Main Godown | G779: 1012 | H779: =IFERROR(VLOOKUP(Table4[[#This Row],[To BMC/MPG Code]],Table5[#All],3,0),"") -> DalsinghSarai | I779: =IFERROR(VLOOKUP(Table4[[#This Row],[To BMC/MPG Code]],Table5[#All],2,0),"") -> BMC | J779: Amyl 500ml | K779: =IFERROR(VLOOKUP(Table4[[#This Row],[Item Name]],Table2[[Item Name]:[UoM]],2,0),"") -> Nos | L779: 6 | M779: =IFERROR(VLOOKUP(Table4[[#This Row],[Item Name]],Table2[[#All],[Item Name]:[Open Rate]],8,0),"") -> 365.8 | N779: =IFERROR(+Table4[[#This Row],[Qty Issued]]*Table4[[#This Row],[Rate]],"") -> 2194.8 | O779: No | P779: NA
A780: 45817 | B780: Consumed | C780: 213 | D780: 1 | E780: =IFERROR(VLOOKUP(Table4[[#This Row],[From Location Code]],Table5[#All],3,0),"") -> Munger | F780: =IFERROR(VLOOKUP(Table4[[#This Row],[From Location Code]],Table5[#All],2,0),"") -> Main Godown | G780: 1012 | H780: =IFERROR(VLOOKUP(Table4[[#This Row],[To BMC/MPG Code]],Table5[#All],3,0),"") -> DalsinghSarai | I780: =IFERROR(VLOOKUP(Table4[[#This Row],[To BMC/MPG Code]],Table5[#All],2,0),"") -> BMC | J780: Buterometer | K780: =IFERROR(VLOOKUP(Table4[[#This Row],[Item Name]],Table2[[Item Name]:[UoM]],2,0),"") -> Nos | L780: 10 | M780: =IFERROR(VLOOKUP(Table4[[#This Row],[Item Name]],Table2[[#All],[Item Name]:[Open Rate]],8,0),"") -> 132.7 | N780: =IFERROR(+Table4[[#This Row],[Qty Issued]]*Table4[[#This Row],[Rate]],"") -> 1327 | O780: No | P780: NA
...

Sheet Pending Consumption
A1: S No | B1: Name of BMC | C1: Item Name | D1: Issue | E1: Consumed | F1: Balance
A2: 1 | B2: Sahibpur Kamal | C2: 1% Iodine Solution (100ml) | D2: =SUMIFS(Table4[[#All],[Qty Issued]],Table4[[#All],[BMC MPG Name]],'Pending Consumption'!$B2,Table4[[#All],[Item Name]],'Pending Consumption'!$C2,Table4[[#All],[Type]],"Transfer") -> 0 | E2: =SUMIFS(Table4[[#All],[Qty Issued]],Table4[[#All],[Location]],'Pending Consumption'!B2,Table4[[#All],[Item Name]],'Pending Consumption'!$C2,Table4[[#All],[Type]],"Transfer") -> 0 | F2: =+D2-E2 -> 0
A3: 2 | B3: Sahibpur Kamal | C3: Amber Colour Bottle (250 ML) | D3: =SUMIFS(Table4[[#All],[Qty Issued]],Table4[[#All],[BMC MPG Name]],'Pending Consumption'!$B3,Table4[[#All],[Item Name]],'Pending Consumption'!$C3,Table4[[#All],[Type]],"Transfer") -> 0 | E3: =SUMIFS(Table4[[#All],[Qty Issued]],Table4[[#All],[Location]],'Pending Consumption'!B3,Table4[[#All],[Item Name]],'Pending Consumption'!$C3,Table4[[#All],[Type]],"Transfer") -> 0 | F3: =+D3-E3 -> 0
A4: 3 | B4: Sahibpur Kamal | C4: Amyl 500ml | D4: =SUMIFS(Table4[[#All],[Qty Issued]],Table4[[#All],[BMC MPG Name]],'Pending Consumption'!$B4,Table4[[#All],[Item Name]],'Pending Consumption'!$C4,Table4[[#All],[Type]],"Transfer") -> 0 | E4: =SUMIFS(Table4[[#All],[Qty Issued]],Table4[[#All],[Location]],'Pending Consumption'!B4,Table4[[#All],[Item Name]],'Pending Consumption'!$C4,Table4[[#All],[Type]],"Transfer") -> 0 | F4: =+D4-E4 -> 0
A5: 4 | B5: Sahibpur Kamal | C5: Analyzer Calibration Cheking Log Book | D5: =SUMIFS(Table4[[#All],[Qty Issued]],Table4[[#All],[BMC MPG Name]],'Pending Consumption'!$B5,Table4[[#All],[Item Name]],'Pending Consumption'!$C5,Table4[[#All],[Type]],"Transfer") -> 0 | E5: =SUMIFS(Table4[[#All],[Qty Issued]],Table4[[#All],[Location]],'Pending Consumption'!B5,Table4[[#All],[Item Name]],'Pending Consumption'!$C5,Table4[[#All],[Type]],"Transfer") -> 0 | F5: =+D5-E5 -> 0
A6: 5 | B6: Sahibpur Kamal | C6: Beaker 100 Ml | D6: =SUMIFS(Table4[[#All],[Qty Issued]],Table4[[#All],[BMC MPG Name]],'Pending Consumption'!$B6,Table4[[#All],[Item Name]],'Pending Consumption'!$C6,Table4[[#All],[Type]],"Transfer") -> 0 | E6: =SUMIFS(Table4[[#All],[Qty Issued]],Table4[[#All],[Location]],'Pending Consumption'!B6,Table4[[#All],[Item Name]],'Pending Consumption'!$C6,Table4[[#All],[Type]],"Transfer") -> 0 | F6: =+D6-E6 -> 0
A7: 6 | B7: Sahibpur Kamal | C7: Beaker 250 ML Borosilicate | D7: =SUMIFS(Table4[[#All],[Qty Issued]],Table4[[#All],[BMC MPG Name]],'Pending Consumption'!$B7,Table4[[#All],[Item Name]],'Pending Consumption'!$C7,Table4[[#All],[Type]],"Transfer") -> 0 | E7: =SUMIFS(Table4[[#All],[Qty Issued]],Table4[[#All],[Location]],'Pending Consumption'!B7,Table4[[#All],[Item Name]],'Pending Consumption'!$C7,Table4[[#All],[Type]],"Transfer") -> 0 | F7: =+D7-E7 -> 0
A8: 7 | B8: Sahibpur Kamal | C8: Beaker 500 Ml | D8: =SUMIFS(Table4[[#All],[Qty Issued]],Table4[[#All],[BMC MPG Name]],'Pending Consumption'!$B8,Table4[[#All],[Item Name]],'Pending Consumption'!$C8,Table4[[#All],[Type]],"Transfer") -> 0 | E8: =SUMIFS(Table4[[#All],[Qty Issued]],Table4[[#All],[Location]],'Pending Consumption'!B8,Table4[[#All],[Item Name]],'Pending Consumption'!$C8,Table4[[#All],[Type]],"Transfer") -> 0 | F8: =+D8-E8 -> 0
A9: 8 | B9: Sahibpur Kamal | C9: Beaker 50 ML | D9: =SUMIFS(Table4[[#All],[Qty Issued]],Table4[[#All],[BMC MPG Name]],'Pending Consumption'!$B9,Table4[[#All],[Item Name]],'Pending Consumption'!$C9,Table4[[#All],[Type]],"Transfer") -> 0 | E9: =SUMIFS(Table4[[#All],[Qty Issued]],Table4[[#All],[Location]],'Pending Consumption'!B9,Table4[[#All],[Item Name]],'Pending Consumption'!$C9,Table4[[#All],[Type]],"Transfer") -> 0 | F9: =+D9-E9 -> 0
A10: 9 | B10: Sahibpur Kamal | C10: BMC Cleaning Brush 2" | D10: =SUMIFS(Table4[[#All],[Qty Issued]],Table4[[#All],[BMC MPG Name]],'Pending Consumption'!$B10,Table4[[#All],[Item Name]],'Pending Consumption'!$C10,Table4[[#All],[Type]],"Transfer") -> 0 | E10: =SUMIFS(Table4[[#All],[Qty Issued]],Table4[[#All],[Location]],'Pending Consumption'!B10,Table4[[#All],[Item Name]],'Pending Consumption'!$C10,Table4[[#All],[Type]],"Transfer") -> 0 | F10: =+D10-E10 -> 0
A11: 10 | B11: Sahibpur Kamal | C11: BMC Day Book | D11: =SUMIFS(Table4[[#All],[Qty Issued]],Table4[[#All],[BMC MPG Name]],'Pending Consumption'!$B11,Table4[[#All],[Item Name]],'Pending Consumption'!$C11,Table4[[#All],[Type]],"Transfer") -> 0 | E11: =SUMIFS(Table4[[#All],[Qty Issued]],Table4[[#All],[Location]],'Pending Consumption'!B11,Table4[[#All],[Item Name]],'Pending Consumption'!$C11,Table4[[#All],[Type]],"Transfer") -> 0 | F11: =+D11-E11 -> 0
A12: 11 | B12: Sahibpur Kamal | C12: Burete Stand | D12: =SUMIFS(Table4[[#All],[Qty Issued]],Table4[[#All],[BMC MPG Name]],'Pending Consumption'!$B12,Table4[[#All],[Item Name]],'Pending Consumption'!$C12,Table4[[#All],[Type]],"Transfer") -> 0 | E12: =SUMIFS(Table4[[#All],[Qty Issued]],Table4[[#All],[Location]],'Pending Consumption'!B12,Table4[[#All],[Item Name]],'Pending Consumption'!$C12,Table4[[#All],[Type]],"Transfer") -> 0 | F12: =+D12-E12 -> 0
A13: 12 | B13: Sahibpur Kamal | C13: Burret 50 ML Borosilicate | D13: =SUMIFS(Table4[[#All],[Qty Issued]],Table4[[#All],[BMC MPG Name]],'Pending Consumption'!$B13,Table4[[#All],[Item Name]],'Pending Consumption'!$C13,Table4[[#All],[Type]],"Transfer") -> 0 | E13: =SUMIFS(Table4[[#All],[Qty Issued]],Table4[[#All],[Location]],'Pending Consumption'!B13,Table4[[#All],[Item Name]],'Pending Consumption'!$C13,Table4[[#All],[Type]],"Transfer") -> 0 | F13: =+D13-E13 -> 0
... A97: 96 | B97: Sahibpur Kamal | C97: Tilt Measure 1 Ml with Bottle | D97: =SUMIFS(Table4[[#All],[Qty Issued]],Table4[[#All],[BMC MPG Name]],'Pending Consumption'!$B97,Table4[[#All],[Item Name]],'Pending Consumption'!$C97,Table4[[#All],[Type]],"Transfer") -> 0 | E97: =SUMIFS(Table4[[#All],[Qty Issued]],Table4[[#All],[Location]],'Pending Consumption'!B97,Table4[[#All],[Item Name]],'Pending Consumption'!$C97,Table4[[#All],[Type]],"Transfer") -> 0 | F97: =+D97-E97 -> 0
B98: Kalyanpur | C98: 1% Iodine Solution (100ml) | D98: =SUMIFS(Table4[[#All],[Qty Issued]],Table4[[#All],[BMC MPG Name]],'Pending Consumption'!$B98,Table4[[#All],[Item Name]],'Pending Consumption'!$C98,Table4[[#All],[Type]],"Transfer") -> 0 | E98: =SUMIFS(Table4[[#All],[Qty Issued]],Table4[[#All],[Location]],'Pending Consumption'!B98,Table4[[#All],[Item Name]],'Pending Consumption'!$C98,Table4[[#All],[Type]],"Transfer") -> 0 | F98: =+D98-E98 -> 0
B99: Kalyanpur | C99: Amber Colour Bottle (250 ML) | D99: =SUMIFS(Table4[[#All],[Qty Issued]],Table4[[#All],[BMC MPG Name]],'Pending Consumption'!$B99,Table4[[#All],[Item Name]],'Pending Consumption'!$C99,Table4[[#All],[Type]],"Transfer") -> 0 | E99: =SUMIFS(Table4[[#All],[Qty Issued]],Table4[[#All],[Location]],'Pending Consumption'!B99,Table4[[#All],[Item Name]],'Pending Consumption'!$C99,Table4[[#All],[Type]],"Transfer") -> 0 | F99: =+D99-E99 -> 0
B100: Kalyanpur | C100: Amyl 500ml | D100: =SUMIFS(Table4[[#All],[Qty Issued]],Table4[[#All],[BMC MPG Name]],'Pending Consumption'!$B100,Table4[[#All],[Item Name]],'Pending Consumption'!$C100,Table4[[#All],[Type]],"Transfer") -> 0 | E100: =SUMIFS(Table4[[#All],[Qty Issued]],Table4[[#All],[Location]],'Pending Consumption'!B100,Table4[[#All],[Item Name]],'Pending Consumption'!$C100,Table4[[#All],[Type]],"Transfer") -> 0 | F100: =+D100-E100 -> 0
B101: Kalyanpur | C101: Analyzer Calibration Cheking Log Book | D101: =SUMIFS(Table4[[#All],[Qty Issued]],Table4[[#All],[BMC MPG Name]],'Pending Consumption'!$B101,Table4[[#All],[Item Name]],'Pending Consumption'!$C101,Table4[[#All],[Type]],"Transfer") -> 0 | E101: =SUMIFS(Table4[[#All],[Qty Issued]],Table4[[#All],[Location]],'Pending Consumption'!B101,Table4[[#All],[Item Name]],'Pending Consumption'!$C101,Table4[[#All],[Type]],"Transfer") -> 0 | F101: =+D101-E101 -> 0
B102: Kalyanpur | C102: Beaker 100 Ml | D102: =SUMIFS(Table4[[#All],[Qty Issued]],Table4[[#All],[BMC MPG Name]],'Pending Consumption'!$B102,Table4[[#All],[Item Name]],'Pending Consumption'!$C102,Table4[[#All],[Type]],"Transfer") -> 0 | E102: =SUMIFS(Table4[[#All],[Qty Issued]],Table4[[#All],[Location]],'Pending Consumption'!B102,Table4[[#All],[Item Name]],'Pending Consumption'!$C102,Table4[[#All],[Type]],"Transfer") -> 0 | F102: =+D102-E102 -> 0
B103: Kalyanpur | C103: Beaker 250 ML Borosilicate | D103: =SUMIFS(Table4[[#All],[Qty Issued]],Table4[[#All],[BMC MPG Name]],'Pending Consumption'!$B103,Table4[[#All],[Item Name]],'Pending Consumption'!$C103,Table4[[#All],[Type]],"Transfer") -> 0 | E103: =SUMIFS(Table4[[#All],[Qty Issued]],Table4[[#All],[Location]],'Pending Consumption'!B103,Table4[[#All],[Item Name]],'Pending Consumption'!$C103,Table4[[#All],[Type]],"Transfer") -> 0 | F103: =+D103-E103 -> 0
B104: Kalyanpur | C104: Beaker 500 Ml | D104: =SUMIFS(Table4[[#All],[Qty Issued]],Table4[[#All],[BMC MPG Name]],'Pending Consumption'!$B104,Table4[[#All],[Item Name]],'Pending Consumption'!$C104,Table4[[#All],[Type]],"Transfer") -> 0 | E104: =SUMIFS(Table4[[#All],[Qty Issued]],Table4[[#All],[Location]],'Pending Consumption'!B104,Table4[[#All],[Item Name]],'Pending Consumption'!$C104,Table4[[#All],[Type]],"Transfer") -> 0 | F104: =+D104-E104 -> 0
B105: Kalyanpur | C105: Beaker 50 ML | D105: =SUMIFS(Table4[[#All],[Qty Issued]],Table4[[#All],[BMC MPG Name]],'Pending Consumption'!$B105,Table4[[#All],[Item Name]],'Pending Consumption'!$C105,Table4[[#All],[Type]],"Transfer") -> 0 | E105: =SUMIFS(Table4[[#All],[Qty Issued]],Table4[[#All],[Location]],'Pending Consumption'!B105,Table4[[#All],[Item Name]],'Pending Consumption'!$C105,Table4[[#All],[Type]],"Transfer") -> 0 | F105: =+D105-E105 -> 0
B106: Kalyanpur | C106: BMC Cleaning Brush 2" | D106: =SUMIFS(Table4[[#All],[Qty Issued]],Table4[[#All],[BMC MPG Name]],'Pending Consumption'!$B106,Table4[[#All],[Item Name]],'Pending Consumption'!$C106,Table4[[#All],[Type]],"Transfer") -> 0 | E106: =SUMIFS(Table4[[#All],[Qty Issued]],Table4[[#All],[Location]],'Pending Consumption'!B106,Table4[[#All],[Item Name]],'Pending Consumption'!$C106,Table4[[#All],[Type]],"Transfer") -> 0 | F106: =+D106-E106 -> 0
B107: Kalyanpur | C107: BMC Day Book | D107: =SUMIFS(Table4[[#All],[Qty Issued]],Table4[[#All],[BMC MPG Name]],'Pending Consumption'!$B107,Table4[[#All],[Item Name]],'Pending Consumption'!$C107,Table4[[#All],[Type]],"Transfer") -> 0 | E107: =SUMIFS(Table4[[#All],[Qty Issued]],Table4[[#All],[Location]],'Pending Consumption'!B107,Table4[[#All],[Item Name]],'Pending Consumption'!$C107,Table4[[#All],[Type]],"Transfer") -> 0 | F107: =+D107-E107 -> 0
B108: Kalyanpur | C108: Burete Stand | D108: =SUMIFS(Table4[[#All],[Qty Issued]],Table4[[#All],[BMC MPG Name]],'Pending Consumption'!$B108,Table4[[#All],[Item Name]],'Pending Consumption'!$C108,Table4[[#All],[Type]],"Transfer") -> 0 | E108: =SUMIFS(Table4[[#All],[Qty Issued]],Table4[[#All],[Location]],'Pending Consumption'!B108,Table4[[#All],[Item Name]],'Pending Consumption'!$C108,Table4[[#All],[Type]],"Transfer") -> 0 | F108: =+D108-E108 -> 0
B109: Kalyanpur | C109: Burret 50 ML Borosilicate | D109: =SUMIFS(Table4[[#All],[Qty Issued]],Table4[[#All],[BMC MPG Name]],'Pending Consumption'!$B109,Table4[[#All],[Item Name]],'Pending Consumption'!$C109,Table4[[#All],[Type]],"Transfer") -> 0 | E109: =SUMIFS(Table4[[#All],[Qty Issued]],Table4[[#All],[Location]],'Pending Consumption'!B109,Table4[[#All],[Item Name]],'Pending Consumption'!$C109,Table4[[#All],[Type]],"Transfer") -> 0 | F109: =+D109-E109 -> 0
... B385: Dumraon | C385: Tilt Measure 1 Ml with Bottle | D385: =SUMIFS(Table4[[#All],[Qty Issued]],Table4[[#All],[BMC MPG Name]],'Pending Consumption'!$B385,Table4[[#All],[Item Name]],'Pending Consumption'!$C385,Table4[[#All],[Type]],"Transfer") -> 0 | E385: =SUMIFS(Table4[[#All],[Qty Issued]],Table4[[#All],[Location]],'Pending Consumption'!B385,Table4[[#All],[Item Name]],'Pending Consumption'!$C385,Table4[[#All],[Type]],"Transfer") -> 0 | F385: =+D385-E385 -> 0

Sheet Purchase
A1: Vendor ID | B1: Vendor Name | C1: Invoice Date | D1: Invoice No | E1: PO Date | F1: PO No | G1: Date | H1: GRN No | I1: Receipt Location Code | J1: Location | K1: Item Name | L1: UoM | M1: Qty Received | N1: Rate | O1: Amt | P1: GST | Q1: Total Am t | R1: Frieght | S1: Total amt | T1: Cost/Per
A2: 1 | B2: =IFERROR(VLOOKUP(Table3[[#This Row],[Vendor ID]],Table6[#All],2,0),"") -> R R Sales | C2: 45773 | D2: TI/2025-26/65 | G2: 45789 | H2: 4 | I2: 1 | J2: =IFERROR(VLOOKUP(Table3[[#This Row],[Receipt Location Code]],Table5[#All],3,0),"") -> Munger | K2: Tanker Seal | L2: =IFERROR(VLOOKUP(Table3[[#This Row],[Item Name]],Table2[[#All],[Item Name]:[Open Rate]],2,0),"") -> Nos | M2: 10000 | N2: 10 | O2: =+Table3[[#This Row],[Rate]]*Table3[[#This Row],[Qty Received]] -> 100000 | P2: =+Table3[[#This Row],[Amt]]*0.18 -> 18000 | Q2: =+Table3[[#This Row],[Amt]]+Table3[[#This Row],[GST]] -> 118000 | R2: =7700*1.18 -> 9086 | S2: =+Table3[[#This Row],[Total Am t]]+Table3[[#This Row],[Frieght]] -> 127086 | T2: =IFERROR(+Table3[[#This Row],[Total amt]]/Table3[[#This Row],[Qty Received]],0) -> 12.7086
A3: 3 | B3: =IFERROR(VLOOKUP(Table3[[#This Row],[Vendor ID]],Table6[#All],2,0),"") -> Geochem Bio Science | C3: 45829 | D3: INV-2526-90 | G3: 45833 | H3: 6 | I3: 1 | J3: =IFERROR(VLOOKUP(Table3[[#This Row],[Receipt Location Code]],Table5[#All],3,0),"") -> Munger | K3: Ethyl Alcohol 500 ML Pack | L3: =IFERROR(VLOOKUP(Table3[[#This Row],[Item Name]],Table2[[#All],[Item Name]:[Open Rate]],2,0),"") -> Nos | M3: 240 | N3: 230 | O3: =+Table3[[#This Row],[Rate]]*Table3[[#This Row],[Qty Received]] -> 55200 | P3: =+Table3[[#This Row],[Amt]]*0.18 -> 9936 | Q3: =+Table3[[#This Row],[Amt]]+Table3[[#This Row],[GST]] -> 65136 | S3: =+Table3[[#This Row],[Total Am t]]+Table3[[#This Row],[Frieght]] -> 65136 | T3: =IFERROR(+Table3[[#This Row],[Total amt]]/Table3[[#This Row],[Qty Received]],0) -> 271.4
A4: 4 | B4: =IFERROR(VLOOKUP(Table3[[#This Row],[Vendor ID]],Table6[#All],2,0),"") -> Indifoss Analytical Pvt Ltd | C4: 45840 | D4: IF/2526/02957 | E4: 45838 | F4: BR/PO/021/25-26 | G4: 45866 | H4: 12 | I4: 1 | J4: =IFERROR(VLOOKUP(Table3[[#This Row],[Receipt Location Code]],Table5[#All],3,0),"") -> Munger | K4: Clean for Milkoscreen 30ml | L4: =IFERROR(VLOOKUP(Table3[[#This Row],[Item Name]],Table2[[#All],[Item Name]:[Open Rate]],2,0),"") -> Nos | M4: 180 | N4: 171.5 | O4: =+Table3[[#This Row],[Rate]]*Table3[[#This Row],[Qty Received]] -> 30870 | P4: =+Table3[[#This Row],[Amt]]*0.12 -> 3704.4 | Q4: =+Table3[[#This Row],[Amt]]+Table3[[#This Row],[GST]] -> 34574.4 | S4: =+Table3[[#This Row],[Total Am t]]+Table3[[#This Row],[Frieght]] -> 34574.4 | T4: =IFERROR(+Table3[[#This Row],[Total amt]]/Table3[[#This Row],[Qty Received]],0) -> 192.08
A5: 4 | B5: =IFERROR(VLOOKUP(Table3[[#This Row],[Vendor ID]],Table6[#All],2,0),"") -> Indifoss Analytical Pvt Ltd | C5: 45840 | D5: IF/2526/02957 | E5: 45838 | F5: BR/PO/021/25-26 | G5: 45866 | H5: 12 | I5: 1 | J5: =IFERROR(VLOOKUP(Table3[[#This Row],[Receipt Location Code]],Table5[#All],3,0),"") -> Munger | K5: Descaling Solution Milkoscreen 30 Ml | L5: =IFERROR(VLOOKUP(Table3[[#This Row],[Item Name]],Table2[[#All],[Item Name]:[Open Rate]],2,0),"") -> Nos | M5: 120 | N5: 238 | O5: =+Table3[[#This Row],[Rate]]*Table3[[#This Row],[Qty Received]] -> 28560 | P5: =+Table3[[#This Row],[Amt]]*0.12 -> 3427.2 | Q5: =+Table3[[#This Row],[Amt]]+Table3[[#This Row],[GST]] -> 31987.2 | S5: =+Table3[[#This Row],[Total Am t]]+Table3[[#This Row],[Frieght]] -> 31987.2 | T5: =IFERROR(+Table3[[#This Row],[Total amt]]/Table3[[#This Row],[Qty Received]],0) -> 266.56
A6: 5 | B6: =IFERROR(VLOOKUP(Table3[[#This Row],[Vendor ID]],Table6[#All],2,0),"") -> Baranwal Computer | C6: 45897 | D6: 2025-26/65 | E6: 45883 | F6: BR/PO/059/25-26 | G6: 45901 | H6: 17 | I6: 1 | J6: =IFERROR(VLOOKUP(Table3[[#This Row],[Receipt Location Code]],Table5[#All],3,0),"") -> Munger | K6: Analyzer Calibration Cheking Log Book | L6: =IFERROR(VLOOKUP(Table3[[#This Row],[Item Name]],Table2[[#All],[Item Name]:[Open Rate]],2,0),"") -> Nos | M6: 100 | N6: 103 | O6: =+Table3[[#This Row],[Rate]]*Table3[[#This Row],[Qty Received]] -> 10300 | P6: =+Table3[[#This Row],[Amt]]*0.18 -> 1854 | Q6: =+Table3[[#This Row],[Amt]]+Table3[[#This Row],[GST]] -> 12154 | S6: =+Table3[[#This Row],[Total Am t]]+Table3[[#This Row],[Frieght]] -> 12154 | T6: =IFERROR(+Table3[[#This Row],[Total amt]]/Table3[[#This Row],[Qty Received]],0) -> 121.54
A7: 5 | B7: =IFERROR(VLOOKUP(Table3[[#This Row],[Vendor ID]],Table6[#All],2,0),"") -> Baranwal Computer | C7: 45897 | D7: 2025-26/65 | E7: 45883 | F7: BR/PO/059/25-26 | G7: 45901 | H7: 17 | I7: 1 | J7: =IFERROR(VLOOKUP(Table3[[#This Row],[Receipt Location Code]],Table5[#All],3,0),"") -> Munger | K7: BMC Day Book | L7: =IFERROR(VLOOKUP(Table3[[#This Row],[Item Name]],Table2[[#All],[Item Name]:[Open Rate]],2,0),"") -> Nos | M7: 300 | N7: 103 | O7: =+Table3[[#This Row],[Rate]]*Table3[[#This Row],[Qty Received]] -> 30900 | P7: =+Table3[[#This Row],[Amt]]*0.18 -> 5562 | Q7: =+Table3[[#This Row],[Amt]]+Table3[[#This Row],[GST]] -> 36462 | S7: =+Table3[[#This Row],[Total Am t]]+Table3[[#This Row],[Frieght]] -> 36462 | T7: =IFERROR(+Table3[[#This Row],[Total amt]]/Table3[[#This Row],[Qty Received]],0) -> 121.54
A8: 5 | B8: =IFERROR(VLOOKUP(Table3[[#This Row],[Vendor ID]],Table6[#All],2,0),"") -> Baranwal Computer | C8: 45897 | D8: 2025-26/65 | E8: 45883 | F8: BR/PO/059/25-26 | G8: 45901 | H8: 17 | I8: 1 | J8: =IFERROR(VLOOKUP(Table3[[#This Row],[Receipt Location Code]],Table5[#All],3,0),"") -> Munger | K8: Farmers Passbook | L8: =IFERROR(VLOOKUP(Table3[[#This Row],[Item Name]],Table2[[#All],[Item Name]:[Open Rate]],2,0),"") -> Nos | M8: 6000 | N8: 4.35 | O8: =+Table3[[#This Row],[Rate]]*Table3[[#This Row],[Qty Received]] -> 26100 | P8: =+Table3[[#This Row],[Amt]]*0.18 -> 4698 | Q8: =+Table3[[#This Row],[Amt]]+Table3[[#This Row],[GST]] -> 30798 | S8: =+Table3[[#This Row],[Total Am t]]+Table3[[#This Row],[Frieght]] -> 30798 | T8: =IFERROR(+Table3[[#This Row],[Total amt]]/Table3[[#This Row],[Qty Received]],0) -> 5.133
A9: 5 | B9: =IFERROR(VLOOKUP(Table3[[#This Row],[Vendor ID]],Table6[#All],2,0),"") -> Baranwal Computer | C9: 45897 | D9: 2025-26/65 | E9: 45883 | F9: BR/PO/059/25-26 | G9: 45901 | H9: 17 | I9: 1 | J9: =IFERROR(VLOOKUP(Table3[[#This Row],[Receipt Location Code]],Table5[#All],3,0),"") -> Munger | K9: MPG Register | L9: =IFERROR(VLOOKUP(Table3[[#This Row],[Item Name]],Table2[[#All],[Item Name]:[Open Rate]],2,0),"") -> Nos | M9: 200 | N9: 110 | O9: =+Table3[[#This Row],[Rate]]*Table3[[#This Row],[Qty Received]] -> 22000 | P9: =+Table3[[#This Row],[Amt]]*0.18 -> 3960 | Q9: =+Table3[[#This Row],[Amt]]+Table3[[#This Row],[GST]] -> 25960 | S9: =+Table3[[#This Row],[Total Am t]]+Table3[[#This Row],[Frieght]] -> 25960 | T9: =IFERROR(+Table3[[#This Row],[Total amt]]/Table3[[#This Row],[Qty Received]],0) -> 129.8
A10: 5 | B10: =IFERROR(VLOOKUP(Table3[[#This Row],[Vendor ID]],Table6[#All],2,0),"") -> Baranwal Computer | C10: 45897 | D10: 2025-26/65 | E10: 45883 | F10: BR/PO/059/25-26 | G10: 45901 | H10: 17 | I10: 1 | J10: =IFERROR(VLOOKUP(Table3[[#This Row],[Receipt Location Code]],Table5[#All],3,0),"") -> Munger | K10: Milk Despatch Challan | L10: =IFERROR(VLOOKUP(Table3[[#This Row],[Item Name]],Table2[[#All],[Item Name]:[Open Rate]],2,0),"") -> Nos | M10: 200 | N10: 80 | O10: =+Table3[[#This Row],[Rate]]*Table3[[#This Row],[Qty Received]] -> 16000 | P10: =+Table3[[#This Row],[Amt]]*0.18 -> 2880 | Q10: =+Table3[[#This Row],[Amt]]+Table3[[#This Row],[GST]] -> 18880 | S10: =+Table3[[#This Row],[Total Am t]]+Table3[[#This Row],[Frieght]] -> 18880 | T10: =IFERROR(+Table3[[#This Row],[Total amt]]/Table3[[#This Row],[Qty Received]],0) -> 94.4
A11: 5 | B11: =IFERROR(VLOOKUP(Table3[[#This Row],[Vendor ID]],Table6[#All],2,0),"") -> Baranwal Computer | C11: 45897 | D11: 2025-26/65 | E11: 45883 | F11: BR/PO/059/25-26 | G11: 45901 | H11: 17 | I11: 1 | J11: =IFERROR(VLOOKUP(Table3[[#This Row],[Receipt Location Code]],Table5[#All],3,0),"") -> Munger | K11: Register for Milk Reception Log Book | L11: =IFERROR(VLOOKUP(Table3[[#This Row],[Item Name]],Table2[[#All],[Item Name]:[Open Rate]],2,0),"") -> Nos | M11: 300 | N11: 195 | O11: =+Table3[[#This Row],[Rate]]*Table3[[#This Row],[Qty Received]] -> 58500 | P11: =+Table3[[#This Row],[Amt]]*0.18 -> 10530 | Q11: =+Table3[[#This Row],[Amt]]+Table3[[#This Row],[GST]] -> 69030 | S11: =+Table3[[#This Row],[Total Am t]]+Table3[[#This Row],[Frieght]] -> 69030 | T11: =IFERROR(+Table3[[#This Row],[Total amt]]/Table3[[#This Row],[Qty Received]],0) -> 230.1
A12: 6 | B12: =IFERROR(VLOOKUP(Table3[[#This Row],[Vendor ID]],Table6[#All],2,0),"") -> Satol Chemicals LTD | C12: 45891 | D12: SCL/03380/25-26 | E12: 45885 | F12: BR/PO/064/25-26 | G12: 45901 | H12: 18 | I12: 1 | J12: =IFERROR(VLOOKUP(Table3[[#This Row],[Receipt Location Code]],Table5[#All],3,0),"") -> Munger | K12: Satol - 5 KG | L12: =IFERROR(VLOOKUP(Table3[[#This Row],[Item Name]],Table2[[#All],[Item Name]:[Open Rate]],2,0),"") -> Nos | M12: 200 | N12: 90 | O12: =+Table3[[#This Row],[Rate]]*Table3[[#This Row],[Qty Received]] -> 18000 | P12: =+Table3[[#This Row],[Amt]]*0.18 -> 3240 | Q12: =+Table3[[#This Row],[Amt]]+Table3[[#This Row],[GST]] -> 21240 | S12: =+Table3[[#This Row],[Total Am t]]+Table3[[#This Row],[Frieght]] -> 21240 | T12: =IFERROR(+Table3[[#This Row],[Total amt]]/Table3[[#This Row],[Qty Received]],0) -> 106.2
A13: 6 | B13: =IFERROR(VLOOKUP(Table3[[#This Row],[Vendor ID]],Table6[#All],2,0),"") -> Satol Chemicals LTD | C13: 45891 | D13: SCL/03380/25-26 | E13: 45885 | F13: BR/PO/064/25-26 | G13: 45901 | H13: 18 | I13: 1 | J13: =IFERROR(VLOOKUP(Table3[[#This Row],[Receipt Location Code]],Table5[#All],3,0),"") -> Munger | K13: TEEPOL | L13: =IFERROR(VLOOKUP(Table3[[#This Row],[Item Name]],Table2[[#All],[Item Name]:[Open Rate]],2,0),"") -> Nos | M13: 1000 | N13: 44 | O13: =+Table3[[#This Row],[Rate]]*Table3[[#This Row],[Qty Received]] -> 44000 | P13: =+Table3[[#This Row],[Amt]]*0.18 -> 7920 | Q13: =+Table3[[#This Row],[Amt]]+Table3[[#This Row],[GST]] -> 51920 | S13: =+Table3[[#This Row],[Total Am t]]+Table3[[#This Row],[Frieght]] -> 51920 | T13: =IFERROR(+Table3[[#This Row],[Total amt]]/Table3[[#This Row],[Qty Received]],0) -> 51.92
B14: =IFERROR(VLOOKUP(Table3[[#This Row],[Vendor ID]],Table6[#All],2,0),"") | J14: =IFERROR(VLOOKUP(Table3[[#This Row],[Receipt Location Code]],Table5[#All],3,0),"") | L14: =IFERROR(VLOOKUP(Table3[[#This Row],[Item Name]],Table2[[#All],[Item Name]:[Open Rate]],2,0),"") | O14: =+Table3[[#This Row],[Rate]]*Table3[[#This Row],[Qty Received]] -> 0 | P14: =+Table3[[#This Row],[Amt]]*0.18 -> 0 | Q14: =+Table3[[#This Row],[Amt]]+Table3[[#This Row],[GST]] -> 0 | S14: =+Table3[[#This Row],[Total Am t]]+Table3[[#This Row],[Frieght]] -> 0 | T14: =IFERROR(+Table3[[#This Row],[Total amt]]/Table3[[#This Row],[Qty Received]],0) -> 0
B15: =IFERROR(VLOOKUP(Table3[[#This Row],[Vendor ID]],Table6[#All],2,0),"") | J15: =IFERROR(VLOOKUP(Table3[[#This Row],[Receipt Location Code]],Table5[#All],3,0),"") | L15: =IFERROR(VLOOKUP(Table3[[#This Row],[Item Name]],Table2[[#All],[Item Name]:[Open Rate]],2,0),"") | O15: =+Table3[[#This Row],[Rate]]*Table3[[#This Row],[Qty Received]] -> 0 | P15: =+Table3[[#This Row],[Amt]]*0.18 -> 0 | Q15: =+Table3[[#This Row],[Amt]]+Table3[[#This Row],[GST]] -> 0 | S15: =+Table3[[#This Row],[Total Am t]]+Table3[[#This Row],[Frieght]] -> 0 | T15: =IFERROR(+Table3[[#This Row],[Total amt]]/Table3[[#This Row],[Qty Received]],0) -> 0
B16: =IFERROR(VLOOKUP(Table3[[#This Row],[Vendor ID]],Table6[#All],2,0),"") | J16: =IFERROR(VLOOKUP(Table3[[#This Row],[Receipt Location Code]],Table5[#All],3,0),"") | L16: =IFERROR(VLOOKUP(Table3[[#This Row],[Item Name]],Table2[[#All],[Item Name]:[Open Rate]],2,0),"") | O16: =+Table3[[#This Row],[Rate]]*Table3[[#This Row],[Qty Received]] -> 0 | P16: =+Table3[[#This Row],[Amt]]*0.18 -> 0 | Q16: =+Table3[[#This Row],[Amt]]+Table3[[#This Row],[GST]] -> 0 | S16: =+Table3[[#This Row],[Total Am t]]+Table3[[#This Row],[Frieght]] -> 0 | T16: =IFERROR(+Table3[[#This Row],[Total amt]]/Table3[[#This Row],[Qty Received]],0) -> 0
B17: =IFERROR(VLOOKUP(Table3[[#This Row],[Vendor ID]],Table6[#All],2,0),"") | J17: =IFERROR(VLOOKUP(Table3[[#This Row],[Receipt Location Code]],Table5[#All],3,0),"") | L17: =IFERROR(VLOOKUP(Table3[[#This Row],[Item Name]],Table2[[#All],[Item Name]:[Open Rate]],2,0),"") | O17: =+Table3[[#This Row],[Rate]]*Table3[[#This Row],[Qty Received]] -> 0 | P17: =+Table3[[#This Row],[Amt]]*0.18 -> 0 | Q17: =+Table3[[#This Row],[Amt]]+Table3[[#This Row],[GST]] -> 0 | S17: =+Table3[[#This Row],[Total Am t]]+Table3[[#This Row],[Frieght]] -> 0 | T17: =IFERROR(+Table3[[#This Row],[Total amt]]/Table3[[#This Row],[Qty Received]],0) -> 0

Sheet Godown
A1: MPG/BMC Code | B1: Type | C1: Name | D1: BMC Area
A2: 1 | B2: Main Godown | C2: Munger | D2: NA
A3: 10070001 | B3: MPG | C3: MSKMPG LAKXMIPUR | D3: Araria
A4: 10070002 | B4: MPG | C4: Gomukh ID Araria | D4: Araria
A5: 10070003 | B5: MPG | C5: Gomukh ID Chaidha | D5: Araria
A6: 10070004 | B6: MPG | C6: Gomukh ID Pakrail | D6: Araria
A7: 10070008 | B7: MPG | C7: Gomukh ID Pipra | D7: Araria
A8: 10070010 | B8: MPG | C8: Gomukh Araria-1 | D8: Araria
A9: 10070013 | B9: MPG | C9: Gomukh Fatepur | D9: Araria
A10: 10070016 | B10: MPG | C10: Gomukh Gauchhari | D10: Araria
A11: 10070017 | B11: MPG | C11: Gomukh Arariya Uttari | D11: Araria
A12: 10070018 | B12: MPG | C12: Gomukh Arariya Karjaniya | D12: Araria
A13: 10070019 | B13: MPG | C13: Gomukh Aariya Dummer Kothi | D13: Araria
... A874: 1055 | B874: BMC | C874: Matihani | D874: Matihani
A875: Lab | B875: Lab | C875: Daya_Lab | D875: Munger
A876: 10540003 | B876: MPG | C876: GOMUKH ANANDPUR PARAS 2 | D876: Alauli
A877: 10540004 | B877: MPG | C877: GOMUKH SHYAM GHARARI | D877: Alauli
A878: 10540005 | B878: MPG | C878: GOMUKH GADBANNI | D878: Alauli
A879: 10540006 | B879: MPG | C879: GOMUKH AMBA | D879: Alauli
A880: 10540007 | B880: MPG | C880: GOMUKH GORIYAMI | D880: Alauli
A881: 10540003 | B881: MPG | C881: GOMUKH ANANDPUR PARAS 2 | D881: Alauli
A882: 10540004 | B882: MPG | C882: GOMUKH SHYAM GHARARI | D882: Alauli
A883: 10540005 | B883: MPG | C883: GOMUKH GADBANNI | D883: Alauli
A884: 10540006 | B884: MPG | C884: GOMUKH AMBA | D884: Alauli
A885: 10540007 | B885: MPG | C885: GOMUKH GORIYAMI | D885: Alauli
A886: 10540008 | B886: MPG | C886: GOMUKH PARRI | D886: Alauli
A887: 10540009 | B887: MPG | C887: GOMUKH BHIKHARI GHAT | D887: Alauli
... A944: 10010134 | B944: MPG | C944: Gomukh Sakrauli | D944: Manjhaul

Sheet Vendor
A1: Vendor ID | B1: Vendor Name | C1: Address | D1: PAN | E1: GST | F1: Mobile | G1: Email | H1: Supply For
A2: 1 | B2: R R Sales | H2: Tanker Seal
A3: 2 | B3: Minakshi Scientific
A4: 3 | B4: Geochem Bio Science
A5: 4 | B5: Indifoss Analytical Pvt Ltd
A6: 5 | B6: Baranwal Computer
A7: 6 | B7: Satol Chemicals LTD

Sheet Item
A1: S.No | B1: Category | C1: Location | D1: Item Name | E1: UoM | F1: Vendor Name | G1: Stock as on 1st Apr | H1: Reorder Qty | I1: Reorder Level | J1: Avg Consumption of 2 Month | K1: Open Rate | L1: Column1 | M1: diff
A2: 1 | B2: Chemical | C2: Munger | D2: 1% Iodine Solution (100ml) | E2: Nos | F2: Maa enterpires | G2: 15 | H2: 15 | I2: 5 | J2: 1 | K2: 90 | L2: 15 | M2: =Table2[[#This Row],[Stock as on 1st Apr]]-Table2[[#This Row],[Column1]] -> 0
A3: 2 | B3: Glassware | C3: Munger | D3: Amber Colour Bottle (250 ML) | E3: Nos | F3: Maa enterpires | G3: 140 | H3: 50 | I3: 40 | J3: 20 | K3: 120 | L3: 140 | M3: =Table2[[#This Row],[Stock as on 1st Apr]]-Table2[[#This Row],[Column1]] -> 0
A4: 3 | B4: Chemical | C4: Munger | D4: Amyl 500ml | E4: Nos | F4: Maa enterpires | G4: 50 | H4: 50 | I4: 30 | J4: 15 | K4: 365.8 | L4: 50 | M4: =Table2[[#This Row],[Stock as on 1st Apr]]-Table2[[#This Row],[Column1]] -> 0
A5: 4 | B5: Stationery | C5: Munger | D5: Analyzer Calibration Cheking Log Book | E5: Nos | F5: Barnwal Computer | G5: 13 | H5: 100 | I5: 20 | J5: 15 | K5: 127.44 | L5: 13 | M5: =Table2[[#This Row],[Stock as on 1st Apr]]-Table2[[#This Row],[Column1]] -> 0
A6: 5 | B6: Glassware | C6: Munger | D6: Beaker 100 Ml | E6: Nos | F6: Jk India | G6: 24 | H6: 48 | I6: 10 | J6: 10 | K6: 33.18 | L6: 24 | M6: =Table2[[#This Row],[Stock as on 1st Apr]]-Table2[[#This Row],[Column1]] -> 0
A7: 6 | B7: Glassware | C7: Munger | D7: Beaker 250 ML Borosilicate | E7: Nos | F7: Jk India | G7: 12 | H7: 48 | I7: 10 | J7: 10 | K7: 47.2 | L7: 12 | M7: =Table2[[#This Row],[Stock as on 1st Apr]]-Table2[[#This Row],[Column1]] -> 0
A8: 7 | B8: Glassware | C8: Munger | D8: Beaker 500 Ml | E8: Nos | F8: Jk India | G8: 49 | H8: 48 | I8: 10 | J8: 10 | K8: 63.7 | L8: 49 | M8: =Table2[[#This Row],[Stock as on 1st Apr]]-Table2[[#This Row],[Column1]] -> 0
A9: 8 | B9: Glassware | C9: Munger | D9: Beaker 50 ML | E9: Nos | F9: Jk India | G9: 8 | H9: 48 | I9: 10 | J9: 10 | K9: 15.88 | L9: 8 | M9: =Table2[[#This Row],[Stock as on 1st Apr]]-Table2[[#This Row],[Column1]] -> 0
A10: 9 | B10: Consumables | C10: Munger | D10: BMC Cleaning Brush 2" | E10: Nos | F10: Surya Instruments | G10: 41 | H10: 10 | I10: 10 | J10: 10 | K10: 212.4 | L10: 41 | M10: =Table2[[#This Row],[Stock as on 1st Apr]]-Table2[[#This Row],[Column1]] -> 0
A11: 10 | B11: Stationery | C11: Munger | D11: BMC Day Book | E11: Nos | F11: Barnwal Computer | G11: 106 | H11: 300 | I11: 60 | J11: 30 | K11: 121.54 | L11: 106 | M11: =Table2[[#This Row],[Stock as on 1st Apr]]-Table2[[#This Row],[Column1]] -> 0
A12: 11 | B12: Other Items | C12: Munger | D12: Burete Stand | E12: Nos | F12: Maa enterpires | G12: 16 | H12: 20 | I12: 5 | J12: 5 | K12: 258.04 | L12: 16 | M12: =Table2[[#This Row],[Stock as on 1st Apr]]-Table2[[#This Row],[Column1]] -> 0
A13: 12 | B13: Glassware | C13: Munger | D13: Burret 50 ML Borosilicate | E13: Nos | F13: Maa enterpires | G13: 14 | H13: 20 | I13: 5 | J13: 5 | K13: 99.47 | L13: 14 | M13: =Table2[[#This Row],[Stock as on 1st Apr]]-Table2[[#This Row],[Column1]] -> 0
... A32: 31 | B32: Other Items | C32: Munger | D32: Fire Extinguiser, Capacity-6 KG | E32: Nos | F32: Xxtra Care | G32: 11 | H32: 10 | I32: 5 | J32: 5 | K32: 1770 | L32: 0 | M32: =Table2[[#This Row],[Stock as on 1st Apr]]-Table2[[#This Row],[Column1]] -> 11
A33: 32 | B33: Other Items | C33: Munger | D33: FLY KILLER MACHINE 2*18W WH | E33: Nos | G33: 0 | H33: 10 | I33: 5 | J33: 5 | K33: 0 | L33: 0 | M33: =Table2[[#This Row],[Stock as on 1st Apr]]-Table2[[#This Row],[Column1]] -> 0
A34: 33 | B34: Other Items | C34: Munger | D34: Geaser | E34: Nos | G34: 6 | H34: 10 | I34: 5 | J34: 5 | K34: 15000.16 | L34: 0 | M34: =Table2[[#This Row],[Stock as on 1st Apr]]-Table2[[#This Row],[Column1]] -> 6
A35: 34 | B35: Other Items | C35: Munger | D35: Gerber Centrifuse 24 Test Electric | E35: Nos | F35: Maa enterpires | G35: 5 | H35: 5 | I35: 2 | J35: 1 | K35: 3776 | L35: 5 | M35: =Table2[[#This Row],[Stock as on 1st Apr]]-Table2[[#This Row],[Column1]] -> 0
A36: 35 | B36: Consumables | C36: Munger | D36: Gloves | E36: Nos | F36: Maa enterpires | G36: 0 | H36: 10 | I36: 2 | J36: 1 | K36: 289.1 | L36: 0 | M36: =Table2[[#This Row],[Stock as on 1st Apr]]-Table2[[#This Row],[Column1]] -> 0
A37: 36 | B37: Consumables | C37: Munger | D37: Gum Glue Traps | E37: Nos | G37: 200 | H37: 10 | I37: 5 | J37: 5 | K37: 30.68 | L37: 200 | M37: =Table2[[#This Row],[Stock as on 1st Apr]]-Table2[[#This Row],[Column1]] -> 0
A38: 37 | B38: Stationery | C38: Munger | D38: Headload Slip | E38: Nos | F38: Barnwal Computer | G38: 500 | H38: 500 | I38: 5 | J38: 5 | K38: 13.28 | L38: 500 | M38: =Table2[[#This Row],[Stock as on 1st Apr]]-Table2[[#This Row],[Column1]] -> 0
A39: 38 | B39: Chemical | C39: Munger | D39: Hydrolic Acid | E39: Nos | F39: Minakshi Scientific | G39: 10 | H39: 10 | I39: 5 | J39: 5 | K39: 282.8 | L39: 10 | M39: =Table2[[#This Row],[Stock as on 1st Apr]]-Table2[[#This Row],[Column1]] -> 0
A40: 39 | B40: Glassware | C40: Munger | D40: Lactometer 0-40 | E40: Nos | F40: Maa enterpires | G40: 250 | H40: 50 | I40: 5 | J40: 5 | K40: 132.7 | L40: 250 | M40: =Table2[[#This Row],[Stock as on 1st Apr]]-Table2[[#This Row],[Column1]] -> 0
A41: 40 | B41: Consumables | C41: Munger | D41: Lactometer Jar Small | E41: Nos | F41: Maa enterpires | G41: 250 | H41: 500 | I41: 50 | J41: 5 | K41: 18.95 | L41: 250 | M41: =Table2[[#This Row],[Stock as on 1st Apr]]-Table2[[#This Row],[Column1]] -> 0
A42: 41 | B42: Consumables | C42: Munger | D42: Lock Stopper | E42: Nos | F42: Maa enterpires | G42: 786 | H42: 500 | I42: 50 | J42: 5 | K42: 1.99 | L42: 786 | M42: =Table2[[#This Row],[Stock as on 1st Apr]]-Table2[[#This Row],[Column1]] -> 0
A43: 42 | B43: Consumables | C43: Munger | D43: Lock Stopper Key | E43: Nos | F43: Maa enterpires | G43: 150 | H43: 500 | I43: 50 | J43: 5 | K43: 4.32 | L43: 150 | M43: =Table2[[#This Row],[Stock as on 1st Apr]]-Table2[[#This Row],[Column1]] -> 0
A44: 43 | B44: Stationery | C44: Munger | D44: Material Indent Book | E44: Nos | F44: Barnwal Computer | G44: 100 | H44: 100 | I44: 5 | J44: 5 | K44: 26.55 | L44: 100 | M44: =Table2[[#This Row],[Stock as on 1st Apr]]-Table2[[#This Row],[Column1]] -> 0
A45: 44 | B45: Other Items | C45: Munger | D45: MBRT Bath Digital | E45: Nos | F45: Maa enterpires | G45: 0 | H45: 5 | I45: 1 | J45: 1 | K45: 8826.4 | L45: 0 | M45: =Table2[[#This Row],[Stock as on 1st Apr]]-Table2[[#This Row],[Column1]] -> 0
A46: 45 | B46: Other Items | C46: Munger | D46: MBRT Serogical Water Bath | E46: Nos | F46: Narang Scientific | G46: 5 | H46: 10 | I46: 5 | J46: 5 | K46: 9676 | L46: 0 | M46: =Table2[[#This Row],[Stock as on 1st Apr]]-Table2[[#This Row],[Column1]] -> 5
A47: 46 | B47: Stationery | C47: Munger | D47: MBRT Test Register | E47: Nos | F47: Barnwal Computer | G47: 124 | H47: 100 | I47: 5 | J47: 5 | K47: 115.36 | L47: 102 | M47: =Table2[[#This Row],[Stock as on 1st Apr]]-Table2[[#This Row],[Column1]] -> 22
A48: 47 | B48: Glassware | C48: Munger | D48: Measuring Cylinder 1000 ML Plastic | E48: Nos | F48: Maa enterpires | G48: 42 | H48: 20 | I48: 5 | J48: 5 | K48: 258.44 | L48: 42 | M48: =Table2[[#This Row],[Stock as on 1st Apr]]-Table2[[#This Row],[Column1]] -> 0
A49: 48 | B49: Glassware | C49: Munger | D49: Measuring Cylinder 100 ML Plastic | E49: Nos | F49: Maa enterpires | G49: 45 | H49: 20 | I49: 5 | J49: 5 | K49: 47.2 | L49: 45 | M49: =Table2[[#This Row],[Stock as on 1st Apr]]-Table2[[#This Row],[Column1]] -> 0
... A61: 60 | B61: Chemical | C61: Munger | D61: Phenolphthaleing Indicator | E61: Nos | F61: Maa enterpires | G61: 12 | H61: 50 | I61: 15 | J61: 15 | K61: 106.2 | L61: 12 | M61: =Table2[[#This Row],[Stock as on 1st Apr]]-Table2[[#This Row],[Column1]] -> 0
A62: 61 | B62: Consumables | C62: Munger | D62: Pipe Cleaning Brush 5" Long | E62: Nos | G62: 0 | H62: 50 | I62: 5 | J62: 2 | K62: 265.5 | L62: 0 | M62: =Table2[[#This Row],[Stock as on 1st Apr]]-Table2[[#This Row],[Column1]] -> 0
A63: 62 | B63: Consumables | C63: Munger | D63: Pipette Cleaning Brush | E63: Nos | F63: Maa enterpires | G63: 3058 | H63: 5000 | I63: 500 | J63: 100 | K63: 0.9 | L63: 3058 | M63: =Table2[[#This Row],[Stock as on 1st Apr]]-Table2[[#This Row],[Column1]] -> 0
A64: 63 | B64: Glassware | C64: Munger | D64: Pipette Gradulated 10 ML | E64: Nos | F64: Maa enterpires | G64: 118 | H64: 100 | I64: 10 | J64: 15 | K64: 23.46 | L64: 118 | M64: =Table2[[#This Row],[Stock as on 1st Apr]]-Table2[[#This Row],[Column1]] -> 0
A65: 64 | B65: Glassware | C65: Munger | D65: Pipette Gradulated 1 ML | E65: Nos | F65: Maa enterpires | G65: 212 | H65: 100 | I65: 10 | J65: 15 | K65: 22.42 | L65: 212 | M65: =Table2[[#This Row],[Stock as on 1st Apr]]-Table2[[#This Row],[Column1]] -> 0
A66: 65 | B66: Glassware | C66: Munger | D66: Pipette Gradulated 2 ML | E66: Nos | F66: Maa enterpires | G66: 178 | H66: 100 | I66: 10 | J66: 15 | K66: 28.46 | L66: 178 | M66: =Table2[[#This Row],[Stock as on 1st Apr]]-Table2[[#This Row],[Column1]] -> 0
A67: 66 | B67: Glassware | C67: Munger | D67: Pipette NABL Certified | E67: Nos | F67: Jk India | G67: 1 | H67: 10 | I67: 2 | J67: 1 | K67: 4484 | L67: 1 | M67: =Table2[[#This Row],[Stock as on 1st Apr]]-Table2[[#This Row],[Column1]] -> 0
A68: 67 | B68: Consumables | C68: Munger | D68: Plastic Strainer | E68: Nos | F68: Surya Instruments | G68: 118 | H68: 200 | I68: 20 | J68: 20 | K68: 29.5 | L68: 103 | M68: =Table2[[#This Row],[Stock as on 1st Apr]]-Table2[[#This Row],[Column1]] -> 15
A69: 68 | B69: Glassware | C69: Munger | D69: Reagent Botte with Glass Stopper Borosilicate | E69: Nos | F69: Maa enterpires | G69: 0 | H69: 48 | I69: 10 | J69: 10 | K69: 106.2 | L69: 0 | M69: =Table2[[#This Row],[Stock as on 1st Apr]]-Table2[[#This Row],[Column1]] -> 0
A70: 69 | B70: Glassware | C70: Munger | D70: Reagent Bottle 100 ML | E70: Nos | F70: Maa enterpires | G70: 0 | H70: 48 | I70: 10 | J70: 10 | K70: 83.43 | L70: 0 | M70: =Table2[[#This Row],[Stock as on 1st Apr]]-Table2[[#This Row],[Column1]] -> 0
A71: 70 | B71: Glassware | C71: Munger | D71: Reagent Bottle 250 ML | E71: Nos | F71: Maa enterpires | G71: 13 | H71: 48 | I71: 10 | J71: 10 | K71: 88.5 | L71: 1 | M71: =Table2[[#This Row],[Stock as on 1st Apr]]-Table2[[#This Row],[Column1]] -> 12
A72: 71 | B72: Stationery | C72: Munger | D72: Register for Milk Reception Log Book | E72: Nos | F72: Barnwal Computer | G72: 109 | H72: 300 | I72: 50 | J72: 60 | K72: 218.3 | L72: 109 | M72: =Table2[[#This Row],[Stock as on 1st Apr]]-Table2[[#This Row],[Column1]] -> 0
A73: 72 | B73: Chemical | C73: Munger | D73: Resorcinol | E73: Nos | F73: Maa enterpires | G73: 15 | H73: 20 | I73: 5 | J73: 5 | K73: 504.15 | L73: 15 | M73: =Table2[[#This Row],[Stock as on 1st Apr]]-Table2[[#This Row],[Column1]] -> 0
A74: 73 | B74: Other Items | C74: Munger | D74: Rodent Box | E74: Nos | G74: 15 | H74: 20 | I74: 5 | J74: 5 | K74: 359.9 | L74: 15 | M74: =Table2[[#This Row],[Stock as on 1st Apr]]-Table2[[#This Row],[Column1]] -> 0
A75: 74 | B75: Chemical | C75: Munger | D75: Rosalic Acid Powder 25 Gms | E75: Nos | F75: Surya Instruments | G75: 21 | H75: 20 | I75: 5 | J75: 5 | K75: 732.5 | L75: 21 | M75: =Table2[[#This Row],[Stock as on 1st Apr]]-Table2[[#This Row],[Column1]] -> 0
A76: 75 | B76: Consumables | C76: Munger | D76: Sample Bottle 100 ML | E76: Nos | F76: Maa enterpires | G76: 4130 | H76: 5000 | I76: 400 | J76: 300 | K76: 2.83 | L76: 4130 | M76: =Table2[[#This Row],[Stock as on 1st Apr]]-Table2[[#This Row],[Column1]] -> 0
A77: 76 | B77: Consumables | C77: Munger | D77: Sample Bottle Brush Large | E77: Nos | F77: Maa enterpires | G77: 2813 | H77: 2000 | I77: 200 | J77: 100 | K77: 1.68 | L77: 2813 | M77: =Table2[[#This Row],[Stock as on 1st Apr]]-Table2[[#This Row],[Column1]] -> 0
A78: 77 | B78: Consumables | C78: Munger | D78: Sample Bottle Stand PL 25 Test | E78: Nos | F78: Maa enterpires | G78: 42 | H78: 50 | I78: 40 | J78: 10 | K78: 51.74 | L78: 42 | M78: =Table2[[#This Row],[Stock as on 1st Apr]]-Table2[[#This Row],[Column1]] -> 0
A79: 78 | B79: Consumables | C79: Munger | D79: Satol - 5 KG | E79: Nos | F79: Satol pvt | G79: 240 | H79: 250 | I79: 50 | J79: 80 | K79: 135.7 | L79: 240 | M79: =Table2[[#This Row],[Stock as on 1st Apr]]-Table2[[#This Row],[Column1]] -> 0
A80: 79 | B80: Chemical | C80: Munger | D80: Silver Nitrate Solution | E80: Nos | F80: Minakshi Scientific | G80: 22 | H80: 24 | I80: 5 | J80: 10 | K80: 622.47 | L80: 22 | M80: =Table2[[#This Row],[Stock as on 1st Apr]]-Table2[[#This Row],[Column1]] -> 0
A81: 80 | B81: Chemical | C81: Munger | D81: Sodium Hydroxide N/10 Solution | E81: Nos | F81: Maa enterpires | G81: 8 | H81: 100 | I81: 10 | J81: 10 | K81: 135.7 | L81: 8 | M81: =Table2[[#This Row],[Stock as on 1st Apr]]-Table2[[#This Row],[Column1]] -> 0
A82: 81 | B82: Other Items | C82: Munger | D82: Sprit Lamp S. S. | E82: Nos | F82: Maa enterpires | G82: 7 | H82: 24 | I82: 5 | J82: 2 | K82: 37.89 | L82: 7 | M82: =Table2[[#This Row],[Stock as on 1st Apr]]-Table2[[#This Row],[Column1]] -> 0
A83: 82 | B83: Chemical | C83: Munger | D83: Strip for Detection of Glucose in Milk | E83: Nos | F83: Minakshi Scientific | G83: 10 | H83: 25 | I83: 5 | J83: 5 | K83: 839.4 | L83: 10 | M83: =Table2[[#This Row],[Stock as on 1st Apr]]-Table2[[#This Row],[Column1]] -> 0
A84: 83 | B84: Chemical | C84: Munger | D84: Strip for Detection of Maltodextrin in Milk | E84: Nos | F84: Minakshi Scientific | G84: 20 | H84: 25 | I84: 5 | J84: 5 | K84: 1130.7 | L84: 20 | M84: =Table2[[#This Row],[Stock as on 1st Apr]]-Table2[[#This Row],[Column1]] -> 0
A85: 84 | B85: Chemical | C85: Munger | D85: Strip for Detection of Urea in Milk | E85: Nos | F85: Minakshi Scientific | G85: 0 | H85: 25 | I85: 5 | J85: 5 | K85: 840 | L85: 0 | M85: =Table2[[#This Row],[Stock as on 1st Apr]]-Table2[[#This Row],[Column1]] -> 0
A86: 85 | B86: Chemical | C86: Munger | D86: Sulphuric Acid SQ 05 Lt | E86: Nos | F86: Minakshi Scientific | G86: 22 | H86: 50 | I86: 5 | J86: 5 | K86: 812.2 | L86: 22 | M86: =Table2[[#This Row],[Stock as on 1st Apr]]-Table2[[#This Row],[Column1]] -> 0
... A88: 87 | B88: Consumables | C88: Munger | D88: TEEPOL | E88: Nos | F88: Satol pvt | G88: 1000 | H88: 1000 | I88: 200 | J88: 350 | K88: 51.92 | L88: 1000 | M88: =Table2[[#This Row],[Stock as on 1st Apr]]-Table2[[#This Row],[Column1]] -> 0
A89: 88 | B89: Other Items | C89: Munger | D89: Teflon Hammer | E89: Nos | G89: 0 | H89: 10 | I89: 5 | J89: 5 | K89: 365.8 | L89: 0 | M89: =Table2[[#This Row],[Stock as on 1st Apr]]-Table2[[#This Row],[Column1]] -> 0
A90: 89 | B90: Glassware | C90: Munger | D90: Test Tube | E90: Nos | F90: Maa enterpires | G90: 1976 | H90: 2500 | I90: 100 | J90: 50 | K90: 2.96 | L90: 1976 | M90: =Table2[[#This Row],[Stock as on 1st Apr]]-Table2[[#This Row],[Column1]] -> 0
A91: 90 | B91: Consumables | C91: Munger | D91: Test Tube Stand | E91: Nos | F91: Maa enterpires | G91: 38 | H91: 50 | I91: 5 | J91: 5 | K91: 40.62 | L91: 38 | M91: =Table2[[#This Row],[Stock as on 1st Apr]]-Table2[[#This Row],[Column1]] -> 0
A92: 91 | B92: Glassware | C92: Munger | D92: Test Tube with Rubber Cork | E92: Nos | F92: Maa enterpires | G92: 1660 | H92: 2500 | I92: 5 | J92: 5 | K92: 4.93 | L92: 1660 | M92: =Table2[[#This Row],[Stock as on 1st Apr]]-Table2[[#This Row],[Column1]] -> 0
A93: 92 | B93: Stationery | C93: Munger | D93: Thermal Paper Roll - Small | E93: Nos | F93: Pee Jee Transprint | G93: 6837 | H93: 5000 | I93: 1000 | J93: 1500 | K93: 9.15 | L93: 6501 | M93: =Table2[[#This Row],[Stock as on 1st Apr]]-Table2[[#This Row],[Column1]] -> 336
A94: 93 | B94: Glassware | C94: Munger | D94: Thermameter Alcohal NABL Certified | E94: Nos | F94: Jk India | G94: 1 | H94: 10 | I94: 1 | J94: 1 | K94: 4484 | L94: 1 | M94: =Table2[[#This Row],[Stock as on 1st Apr]]-Table2[[#This Row],[Column1]] -> 0
A95: 94 | B95: Other Items | C95: Munger | D95: Thermometer 110 C | E95: Nos | F95: Jk India | G95: 415 | H95: 10 | I95: 24 | J95: 5 | K95: 132.7 | L95: 415 | M95: =Table2[[#This Row],[Stock as on 1st Apr]]-Table2[[#This Row],[Column1]] -> 0
A96: 95 | B96: Consumables | C96: Munger | D96: Tilt Measure 10cc PI Superior | E96: Nos | F96: Maa enterpires | G96: 414 | H96: 500 | I96: 50 | J96: 10 | K96: 23.71 | L96: 414 | M96: =Table2[[#This Row],[Stock as on 1st Apr]]-Table2[[#This Row],[Column1]] -> 0
A97: 96 | B97: Consumables | C97: Munger | D97: Tilt Measure 1 Ml with Bottle | E97: Nos | F97: Maa enterpires | G97: 256 | H97: 500 | I97: 50 | J97: 10 | K97: 32.09 | L97: 256 | M97: =Table2[[#This Row],[Stock as on 1st Apr]]-Table2[[#This Row],[Column1]] -> 0
