Workbook

Sheet PDF
A1: MCC | B1: (All) | C1: Sahayak Comission Month Of Oct'25
C3: Values
A4: Code | B4: MPG NAME | C4: BMC Volume | D4: BMC Amount | E4: Sahayak Comission @ 0.75/- | F4: Std gain @ 0.95/- | G4: Farmer Sample Milk | H4: AMC from MPG @ 0.10/- | I4: Actual Volume Penalty | J4: Net Sahayak Income | K4: New Assets EMI | L4: Can Deduction | M4: PCB Ded | N4: Other | O4: Consumables | P4: Payble to Sahyak | Q4: Hold | R4: Net Payble
A5: 10120099 | B5: GOMUKH Chiranjipur | C5: 11844.5 | D5: 450545.24 | E5: 8883.375 | F5: 11252.275 | G5: 0 | H5: 1184.45 | I5: 0 | J5: 18951 | K5: 0 | L5: 0 | M5: 0 | N5: 0 | O5: 0 | P5: 18951 | Q5: 0 | R5: 18951
A6: 10120099 Total | C6: 11844.5 | D6: 450545.24 | E6: 8883.375 | F6: 11252.275 | G6: 0 | H6: 1184.45 | I6: 0 | J6: 18951 | K6: 0 | L6: 0 | M6: 0 | N6: 0 | O6: 0 | P6: 18951 | Q6: 0 | R6: 18951
A8: Grand Total | C8: 11844.5 | D8: 450545.24 | E8: 8883.375 | F8: 11252.275 | G8: 0 | H8: 1184.45 | I8: 0 | J8: 18951 | K8: 0 | L8: 0 | M8: 0 | N8: 0 | O8: 0 | P8: 18951 | Q8: 0 | R8: 18951

Sheet Shayak Income 
M1: MPG Payment | Q1: MPG Sheet | R1: Internal | T1: MPG Deduction | W1: Other Security Deduction | AG1: -1
A2: Opening Balance ____ | M2: =SUBTOTAL(9,M4:M1057) -> 4064088.6 | N2: =SUBTOTAL(9,N4:N1057) -> 1.6645502e+08 | O2: Income | W2: =SUBTOTAL(9,W4:W1057) -> 828722.81 | X2: =SUBTOTAL(9,X4:X1057) -> 88989.118 | Y2: =SUBTOTAL(9,Y4:Y1057) -> 46315 | Z2: =SUBTOTAL(9,Z4:Z1057) -> 77099.34 | AA2: =SUBTOTAL(9,AA4:AA1057) -> 53086.634 | AB2: =SUBTOTAL(9,AB4:AB1057) -> 5314485 | AC2: =SUBTOTAL(9,AC4:AC1057) -> 254097 | AD2: =SUBTOTAL(9,AD4:AD1057) -> 5060388 | AG2: -1 | AN2: =SUBTOTAL(9,AN4:AN1057) -> 1239371.5 | AO2: =SUBTOTAL(9,AO4:AO1057) -> 130688 | AP2: =SUBTOTAL(9,AP4:AP1057) -> 828722.81 | AQ2: =SUBTOTAL(9,AQ4:AQ1057) -> 959410.81
A3: AMCU | B3: Milk Cans | C3: Assets Value | D3: Code | E3: MPG NAME | F3: Amcu type | G3: VLC Type | H3: Farmer Payment | I3: BMC Code | J3: MCC | K3: status | L3: Start Date | M3: BMC Volume | N3: BMC Amount | O3: Sahayak Comission @ 0.75/- | P3: Std gain @ 0.95/- | Q3: Farmer Sample Milk | R3: Std Gain @ 3% | S3: Reserve from Std Gain | T3: AMC from MPG @ 0.10/- | U3: Actual Volume Penalty | V3: Net Sahayak Income | W3: New Assets EMI | X3: Can Deduction | Y3: PCB Ded | Z3: Other | AA3: Consumables | AB3: Payble to Sahyak | AC3: Hold | AD3: Net Payble | AE3: Payment relase | AG3: Stop Payment | AH3: Remarks | AI3: Pending Down Payment | AJ3: Recommendation | AK3: 31-06 Aug | AL3: Irregular Pourer | AM3: No of pouring shift | AN3: EMI | AO3: Recovery from Milk | AP3: Recovery from Com | AQ3: Net Recovered | AT3: HDFC | AU3: OTHER | AV3: Remarks
A4: =IFERROR(VLOOKUP(D4,'Monthly Deduction'!$I$3:$J$957,2,0),0) -> 19281.576 | B4: =IFERROR(VLOOKUP(D4,'Monthly Deduction'!$E$3:$F$957,2,0),0) -> 16000 | C4: =A4+B4 -> 35281.576 | D4: 10010013 | E4: =VLOOKUP(D4,'MPG Payment '!$E$3:$G$497305,2,0) -> Gomukh Kumbhi | F4: =IFERROR(_xlfn.XLOOKUP(D4,'Monthly Deduction'!$I$3:$I$957,'Monthly Deduction'!$H$3:$H$957),0) -> 0 | G4: =VLOOKUP(D4,'MPG Payment '!$E$3:$G$333666,3,0) -> MPG | H4: =VLOOKUP(D4,'MPG Payment '!$E$3:$H$333666,4,0) -> Direct | I4: =INDEX('MPG Payment '!$C:$C,MATCH('Shayak Income '!D4,'MPG Payment '!E:E,0)) -> 1001 | J4: =INDEX('MPG Payment '!$D:$D,MATCH('Shayak Income '!D4,'MPG Payment '!E:E,0)) -> Majhaul | K4: Old | L4: 45013 | M4: =SUMIF('MPG Payment '!$E$3:$E$344841,'Shayak Income '!D4,'MPG Payment '!$I$3:$I$344841) -> 2231.3 | N4: =SUMIF('MPG Payment '!$E$3:$E$344841,'Shayak Income '!D4,'MPG Payment '!$J$3:$J$344841) -> 84420.7 | O4: =+M4*0.75 -> 1673.475 | P4: =+M4*0.95 -> 2119.735 | Q4: =SUMIF('MPG Payment '!$E$3:$E$344841,'Shayak Income '!D4,'MPG Payment '!$S$3:$S$344841) -> 265.22 | R4: =+N4*3% -> 2532.621 | S4: =R4-P4 -> 412.886 | T4: =M4*0.1 -> 223.13 | U4: =((((((IF(K4="New",0,SUMIF('MPG Payment '!$E$3:$E$344841,'Shayak Income '!D4,'MPG Payment '!$AC$3:$AC$344841))))+0)+0)+0)+0)+0 -> 431.93841 | V4: =ROUND((SUM(O4:Q4)-SUM(T4:U4)),0) -> 3403 | W4: =(((AN4-AO4)))+0 -> 1861 | X4: 0 | Y4: =IFERROR(VLOOKUP(D4,'Monthly Deduction'!$M$2:$N$640,2,0),0) -> 0 | Z4: 0 | AA4: =IFERROR(VLOOKUP(D4,'Monthly Deduction'!A:B,2,0),0) -> 0 | AB4: =ROUND(IFERROR(V4-SUM(W4:AA4),0),0) -> 1542 | AC4: 0 | AD4: =ROUND(AB4-AC4,0) -> 1542 | AE4: =IF(AC4<>0,"Yes","Release") -> Release | AG4: 0 | AI4: 0 | AK4: 372.9 | AL4: =COUNTIF(AK4:AK4,"=NA") -> 0 | AN4: =((MIN(IF(A4>0,MAX(N4*2%,1861),0),A4)))+0 -> 1861 | AO4: =SUMIF('MPG Payment '!E:E,'Shayak Income '!D4,'MPG Payment '!AJ:AJ) -> 0 | AP4: =W4 -> 1861 | AQ4: =AO4+AP4 -> 1861 | AS4: =B4-X4 -> 16000
A5: =IFERROR(VLOOKUP(D5,'Monthly Deduction'!$I$3:$J$957,2,0),0) -> 24418.274 | B5: =IFERROR(VLOOKUP(D5,'Monthly Deduction'!$E$3:$F$957,2,0),0) -> 6400 | C5: =A5+B5 -> 30818.274 | D5: 10010019 | E5: =VLOOKUP(D5,'MPG Payment '!$E$3:$G$497305,2,0) -> Gomukh Jagdar | F5: =IFERROR(_xlfn.XLOOKUP(D5,'Monthly Deduction'!$I$3:$I$957,'Monthly Deduction'!$H$3:$H$957),0) -> 0 | G5: =VLOOKUP(D5,'MPG Payment '!$E$3:$G$333666,3,0) -> MPG | H5: =VLOOKUP(D5,'MPG Payment '!$E$3:$H$333666,4,0) -> Direct | I5: =INDEX('MPG Payment '!$C:$C,MATCH('Shayak Income '!D5,'MPG Payment '!E:E,0)) -> 1001 | J5: =INDEX('MPG Payment '!$D:$D,MATCH('Shayak Income '!D5,'MPG Payment '!E:E,0)) -> Majhaul | K5: Old | L5: 45040 | M5: =SUMIF('MPG Payment '!$E$3:$E$344841,'Shayak Income '!D5,'MPG Payment '!$I$3:$I$344841) -> 3615.7 | N5: =SUMIF('MPG Payment '!$E$3:$E$344841,'Shayak Income '!D5,'MPG Payment '!$J$3:$J$344841) -> 140356.54 | O5: =+M5*0.75 -> 2711.775 | P5: =+M5*0.95 -> 3434.915 | Q5: =SUMIF('MPG Payment '!$E$3:$E$344841,'Shayak Income '!D5,'MPG Payment '!$S$3:$S$344841) -> 1821.46 | R5: =+N5*3% -> 4210.6962 | S5: =R5-P5 -> 775.7812 | T5: =M5*0.1 -> 361.57 | U5: =((((((IF(K5="New",0,SUMIF('MPG Payment '!$E$3:$E$344841,'Shayak Income '!D5,'MPG Payment '!$AC$3:$AC$344841))))+0)+0)+0)+0)+0 -> 0 | V5: =ROUND((SUM(O5:Q5)-SUM(T5:U5)),0) -> 7607 | W5: =(((AN5-AO5)))+0 -> 2807.1308 | X5: 0 | Y5: =IFERROR(VLOOKUP(D5,'Monthly Deduction'!$M$2:$N$640,2,0),0) -> 0 | Z5: 0 | AA5: =IFERROR(VLOOKUP(D5,'Monthly Deduction'!A:B,2,0),0) -> 0 | AB5: =ROUND(IFERROR(V5-SUM(W5:AA5),0),0) -> 4800 | AC5: 0 | AD5: =ROUND(AB5-AC5,0) -> 4800 | AE5: =IF(AC5<>0,"Yes","Release") -> Release | AG5: 0 | AI5: 0 | AK5: 822.2 | AL5: =COUNTIF(AK5:AK5,"=NA") -> 0 | AN5: =((MIN(IF(A5>0,MAX(N5*2%,1861),0),A5)))+0 -> 2807.1308 | AO5: =SUMIF('MPG Payment '!E:E,'Shayak Income '!D5,'MPG Payment '!AJ:AJ) -> 0 | AP5: =W5 -> 2807.1308 | AQ5: =AO5+AP5 -> 2807.1308 | AS5: =B5-X5 -> 6400
A6: =IFERROR(VLOOKUP(D6,'Monthly Deduction'!$I$3:$J$957,2,0),0) -> 29772.487 | B6: =IFERROR(VLOOKUP(D6,'Monthly Deduction'!$E$3:$F$957,2,0),0) -> 5744.916 | C6: =A6+B6 -> 35517.403 | D6: 10010038 | E6: =VLOOKUP(D6,'MPG Payment '!$E$3:$G$497305,2,0) -> Gomukh Goriyari | F6: =IFERROR(_xlfn.XLOOKUP(D6,'Monthly Deduction'!$I$3:$I$957,'Monthly Deduction'!$H$3:$H$957),0) -> 0 | G6: =VLOOKUP(D6,'MPG Payment '!$E$3:$G$333666,3,0) -> MPG | H6: =VLOOKUP(D6,'MPG Payment '!$E$3:$H$333666,4,0) -> Direct | I6: =INDEX('MPG Payment '!$C:$C,MATCH('Shayak Income '!D6,'MPG Payment '!E:E,0)) -> 1058 | J6: =INDEX('MPG Payment '!$D:$D,MATCH('Shayak Income '!D6,'MPG Payment '!E:E,0)) -> Hasanpur | K6: Old | L6: 45128 | M6: =SUMIF('MPG Payment '!$E$3:$E$344841,'Shayak Income '!D6,'MPG Payment '!$I$3:$I$344841) -> 3578.58 | N6: =SUMIF('MPG Payment '!$E$3:$E$344841,'Shayak Income '!D6,'MPG Payment '!$J$3:$J$344841) -> 143943.17 | O6: =+M6*0.75 -> 2683.935 | P6: =+M6*0.95 -> 3399.651 | Q6: =SUMIF('MPG Payment '!$E$3:$E$344841,'Shayak Income '!D6,'MPG Payment '!$S$3:$S$344841) -> 862.01 | R6: =+N6*3% -> 4318.2951 | S6: =R6-P6 -> 918.6441 | T6: =M6*0.1 -> 357.858 | U6: =((((((IF(K6="New",0,SUMIF('MPG Payment '!$E$3:$E$344841,'Shayak Income '!D6,'MPG Payment '!$AC$3:$AC$344841))))+0)+0)+0)+0)+0 -> 0 | V6: =ROUND((SUM(O6:Q6)-SUM(T6:U6)),0) -> 6588 | W6: =(((AN6-AO6)))+0 -> 2878.8634 | X6: 0 | Y6: =IFERROR(VLOOKUP(D6,'Monthly Deduction'!$M$2:$N$640,2,0),0) -> 0 | Z6: 413 | AA6: =IFERROR(VLOOKUP(D6,'Monthly Deduction'!A:B,2,0),0) -> 0 | AB6: =ROUND(IFERROR(V6-SUM(W6:AA6),0),0) -> 3296 | AC6: 0 | AD6: =ROUND(AB6-AC6,0) -> 3296 | AE6: =IF(AC6<>0,"Yes","Release") -> Release | AG6: 0 | AH6: EIPL Deduction | AI6: 0 | AK6: 763.02 | AL6: =COUNTIF(AK6:AK6,"=NA") -> 0 | AN6: =((MIN(IF(A6>0,MAX(N6*2%,1861),0),A6)))+0 -> 2878.8634 | AO6: =SUMIF('MPG Payment '!E:E,'Shayak Income '!D6,'MPG Payment '!AJ:AJ) -> 0 | AP6: =W6 -> 2878.8634 | AQ6: =AO6+AP6 -> 2878.8634 | AS6: =B6-X6 -> 5744.916
A7: =IFERROR(VLOOKUP(D7,'Monthly Deduction'!$I$3:$J$957,2,0),0) -> 0 | B7: =IFERROR(VLOOKUP(D7,'Monthly Deduction'!$E$3:$F$957,2,0),0) -> 0 | C7: =A7+B7 -> 0 | D7: 10010047 | E7: =VLOOKUP(D7,'MPG Payment '!$E$3:$G$497305,2,0) -> Mohanpur - Chandan | F7: =IFERROR(_xlfn.XLOOKUP(D7,'Monthly Deduction'!$I$3:$I$957,'Monthly Deduction'!$H$3:$H$957),0) -> 0 | G7: =VLOOKUP(D7,'MPG Payment '!$E$3:$G$333666,3,0) -> vlc | H7: =VLOOKUP(D7,'MPG Payment '!$E$3:$H$333666,4,0) -> Indirect | I7: =INDEX('MPG Payment '!$C:$C,MATCH('Shayak Income '!D7,'MPG Payment '!E:E,0)) -> 1001 | J7: =INDEX('MPG Payment '!$D:$D,MATCH('Shayak Income '!D7,'MPG Payment '!E:E,0)) -> Majhaul | K7: Old | L7: 45121 | M7: =SUMIF('MPG Payment '!$E$3:$E$344841,'Shayak Income '!D7,'MPG Payment '!$I$3:$I$344841) -> 527.9 | N7: =SUMIF('MPG Payment '!$E$3:$E$344841,'Shayak Income '!D7,'MPG Payment '!$J$3:$J$344841) -> 20684.89 | O7: =+M7*0.75 -> 395.925 | P7: =+M7*0.95 -> 501.505 | Q7: =SUMIF('MPG Payment '!$E$3:$E$344841,'Shayak Income '!D7,'MPG Payment '!$S$3:$S$344841) -> 0 | R7: =+N7*3% -> 620.5467 | S7: =R7-P7 -> 119.0417 | T7: =M7*0.1 -> 52.79 | U7: =((((((IF(K7="New",0,SUMIF('MPG Payment '!$E$3:$E$344841,'Shayak Income '!D7,'MPG Payment '!$AC$3:$AC$344841))))+0)+0)+0)+0)+-952 -> 844.17392 | V7: =ROUND((SUM(O7:Q7)-SUM(T7:U7)),0) -> 0 | W7: 0 | X7: 0 | Y7: 0 | Z7: 0 | AA7: 0 | AB7: =ROUND(IFERROR(V7-SUM(W7:AA7),0),0) -> 0 | AC7: 0 | AD7: =ROUND(AB7-AC7,0) -> 0 | AE7: =IF(AC7<>0,"Yes","Release") -> Release | AG7: 0 | AI7: 0 | AK7: 28.13 | AL7: =COUNTIF(AK7:AK7,"=NA") -> 0 | AN7: =((MIN(IF(A7>0,MAX(N7*2%,1861),0),A7)))+0 -> 0 | AO7: =SUMIF('MPG Payment '!E:E,'Shayak Income '!D7,'MPG Payment '!AJ:AJ) -> 0 | AP7: =W7 -> 0 | AQ7: =AO7+AP7 -> 0 | AS7: =B7-X7 -> 0
A8: =IFERROR(VLOOKUP(D8,'Monthly Deduction'!$I$3:$J$957,2,0),0) -> 30233.6 | B8: =IFERROR(VLOOKUP(D8,'Monthly Deduction'!$E$3:$F$957,2,0),0) -> 0 | C8: =A8+B8 -> 30233.6 | D8: 10010050 | E8: =VLOOKUP(D8,'MPG Payment '!$E$3:$G$497305,2,0) -> Ekamba - Ashutosh | F8: =IFERROR(_xlfn.XLOOKUP(D8,'Monthly Deduction'!$I$3:$I$957,'Monthly Deduction'!$H$3:$H$957),0) -> 0 | G8: =VLOOKUP(D8,'MPG Payment '!$E$3:$G$333666,3,0) -> vlc | H8: =VLOOKUP(D8,'MPG Payment '!$E$3:$H$333666,4,0) -> Indirect | I8: =INDEX('MPG Payment '!$C:$C,MATCH('Shayak Income '!D8,'MPG Payment '!E:E,0)) -> 1058 | J8: =INDEX('MPG Payment '!$D:$D,MATCH('Shayak Income '!D8,'MPG Payment '!E:E,0)) -> Hasanpur | K8: Old | L8: 45098 | M8: =SUMIF('MPG Payment '!$E$3:$E$344841,'Shayak Income '!D8,'MPG Payment '!$I$3:$I$344841) -> 5015.62 | N8: =SUMIF('MPG Payment '!$E$3:$E$344841,'Shayak Income '!D8,'MPG Payment '!$J$3:$J$344841) -> 217108.75 | O8: =+M8*0.75 -> 3761.715 | P8: =+M8*0.95 -> 4764.839 | Q8: =SUMIF('MPG Payment '!$E$3:$E$344841,'Shayak Income '!D8,'MPG Payment '!$S$3:$S$344841) -> 0 | R8: =+N8*3% -> 6513.2625 | S8: =R8-P8 -> 1748.4235 | T8: =M8*0.1 -> 501.562 | U8: =((((((IF(K8="New",0,SUMIF('MPG Payment '!$E$3:$E$344841,'Shayak Income '!D8,'MPG Payment '!$AC$3:$AC$344841))))+0)+0)+0)+0)+0 -> 0 | V8: =ROUND((SUM(O8:Q8)-SUM(T8:U8)),0) -> 8025 | W8: =(((AN8-AO8)))+0 -> 4342.175 | X8: 0 | Y8: =IFERROR(VLOOKUP(D8,'Monthly Deduction'!$M$2:$N$640,2,0),0) -> 0 | Z8: 0 | AA8: =IFERROR(VLOOKUP(D8,'Monthly Deduction'!A:B,2,0),0) -> 0 | AB8: =ROUND(IFERROR(V8-SUM(W8:AA8),0),0) -> 3683 | AC8: 0 | AD8: =ROUND(AB8-AC8,0) -> 3683 | AE8: =IF(AC8<>0,"Yes","Release") -> Release | AG8: 0 | AI8: 0 | AK8: 977.33 | AL8: =COUNTIF(AK8:AK8,"=NA") -> 0 | AN8: =((MIN(IF(A8>0,MAX(N8*2%,1861),0),A8)))+0 -> 4342.175 | AO8: =SUMIF('MPG Payment '!E:E,'Shayak Income '!D8,'MPG Payment '!AJ:AJ) -> 0 | AP8: =W8 -> 4342.175 | AQ8: =AO8+AP8 -> 4342.175 | AS8: =B8-X8 -> 0
A9: =IFERROR(VLOOKUP(D9,'Monthly Deduction'!$I$3:$J$957,2,0),0) -> 22582.277 | B9: =IFERROR(VLOOKUP(D9,'Monthly Deduction'!$E$3:$F$957,2,0),0) -> 6970.1518 | C9: =A9+B9 -> 29552.429 | D9: 10010051 | E9: =VLOOKUP(D9,'MPG Payment '!$E$3:$G$497305,2,0) -> Gomukh Dunahi | F9: =IFERROR(_xlfn.XLOOKUP(D9,'Monthly Deduction'!$I$3:$I$957,'Monthly Deduction'!$H$3:$H$957),0) -> 0 | G9: =VLOOKUP(D9,'MPG Payment '!$E$3:$G$333666,3,0) -> MPG | H9: =VLOOKUP(D9,'MPG Payment '!$E$3:$H$333666,4,0) -> Direct | I9: =INDEX('MPG Payment '!$C:$C,MATCH('Shayak Income '!D9,'MPG Payment '!E:E,0)) -> 1058 | J9: =INDEX('MPG Payment '!$D:$D,MATCH('Shayak Income '!D9,'MPG Payment '!E:E,0)) -> Hasanpur | K9: Old | L9: 45219 | M9: =SUMIF('MPG Payment '!$E$3:$E$344841,'Shayak Income '!D9,'MPG Payment '!$I$3:$I$344841) -> 81.59 | N9: =SUMIF('MPG Payment '!$E$3:$E$344841,'Shayak Income '!D9,'MPG Payment '!$J$3:$J$344841) -> 3336.3 | O9: =+M9*0.75 -> 61.1925 | P9: =+M9*0.95 -> 77.5105 | Q9: =SUMIF('MPG Payment '!$E$3:$E$344841,'Shayak Income '!D9,'MPG Payment '!$S$3:$S$344841) -> 79.17 | R9: =+N9*3% -> 100.089 | S9: =R9-P9 -> 22.5785 | T9: =M9*0.1 -> 8.159 | U9: =((((((IF(K9="New",0,SUMIF('MPG Payment '!$E$3:$E$344841,'Shayak Income '!D9,'MPG Payment '!$AC$3:$AC$344841))))+0)+0)+0)+0)+-296 -> 209.74857 | V9: =ROUND((SUM(O9:Q9)-SUM(T9:U9)),0) -> 0 | W9: 0 | X9: 0 | Y9: 0 | Z9: 0 | AA9: 0 | AB9: =ROUND(IFERROR(V9-SUM(W9:AA9),0),0) -> 0 | AC9: 0 | AD9: =ROUND(AB9-AC9,0) -> 0 | AE9: =IF(AC9<>0,"Yes","Release") -> Release | AG9: 0 | AI9: 0 | AK9: 155.27 | AL9: =COUNTIF(AK9:AK9,"=NA") -> 0 | AN9: =((MIN(IF(A9>0,MAX(N9*2%,1861),0),A9)))+0 -> 1861 | AO9: =SUMIF('MPG Payment '!E:E,'Shayak Income '!D9,'MPG Payment '!AJ:AJ) -> 0 | AP9: =W9 -> 0 | AQ9: =AO9+AP9 -> 0 | AS9: =B9-X9 -> 6970.1518
A10: =IFERROR(VLOOKUP(D10,'Monthly Deduction'!$I$3:$J$957,2,0),0) -> 78375.427 | B10: =IFERROR(VLOOKUP(D10,'Monthly Deduction'!$E$3:$F$957,2,0),0) -> 6400 | C10: =A10+B10 -> 84775.427 | D10: 10010055 | E10: =VLOOKUP(D10,'MPG Payment '!$E$3:$G$497305,2,0) -> GOMUKH BIRPUR PASCHIM | F10: =IFERROR(_xlfn.XLOOKUP(D10,'Monthly Deduction'!$I$3:$I$957,'Monthly Deduction'!$H$3:$H$957),0) -> 0 | G10: =VLOOKUP(D10,'MPG Payment '!$E$3:$G$333666,3,0) -> MPG | H10: =VLOOKUP(D10,'MPG Payment '!$E$3:$H$333666,4,0) -> Direct | I10: =INDEX('MPG Payment '!$C:$C,MATCH('Shayak Income '!D10,'MPG Payment '!E:E,0)) -> 1001 | J10: =INDEX('MPG Payment '!$D:$D,MATCH('Shayak Income '!D10,'MPG Payment '!E:E,0)) -> Majhaul | K10: Old | L10: 45231 | M10: =SUMIF('MPG Payment '!$E$3:$E$344841,'Shayak Income '!D10,'MPG Payment '!$I$3:$I$344841) -> 398.2 | N10: =SUMIF('MPG Payment '!$E$3:$E$344841,'Shayak Income '!D10,'MPG Payment '!$J$3:$J$344841) -> 16578.31 | O10: =+M10*0.75 -> 298.65 | P10: =+M10*0.95 -> 378.29 | Q10: =SUMIF('MPG Payment '!$E$3:$E$344841,'Shayak Income '!D10,'MPG Payment '!$S$3:$S$344841) -> 0 | R10: =+N10*3% -> 497.3493 | S10: =R10-P10 -> 119.0593 | T10: =M10*0.1 -> 39.82 | U10: =((((((IF(K10="New",0,SUMIF('MPG Payment '!$E$3:$E$344841,'Shayak Income '!D10,'MPG Payment '!$AC$3:$AC$344841))))+0)+0)+0)+0)+-1363 -> 637.05971 | V10: =ROUND((SUM(O10:Q10)-SUM(T10:U10)),0) -> 0 | W10: 0 | X10: 0 | Y10: 0 | Z10: 0 | AA10: 0 | AB10: =ROUND(IFERROR(V10-SUM(W10:AA10),0),0) -> 0 | AC10: 0 | AD10: =ROUND(AB10-AC10,0) -> 0 | AE10: =IF(AC10<>0,"Yes","Release") -> Release | AG10: 0 | AI10: 0 | AK10: 93.83 | AL10: =COUNTIF(AK10:AK10,"=NA") -> 0 | AN10: =((MIN(IF(A10>0,MAX(N10*2%,1861),0),A10)))+0 -> 1861 | AO10: =SUMIF('MPG Payment '!E:E,'Shayak Income '!D10,'MPG Payment '!AJ:AJ) -> 2000 | AP10: =W10 -> 0 | AQ10: =AO10+AP10 -> 2000 | AS10: =B10-X10 -> 6400
A11: =IFERROR(VLOOKUP(D11,'Monthly Deduction'!$I$3:$J$957,2,0),0) -> 0 | B11: =IFERROR(VLOOKUP(D11,'Monthly Deduction'!$E$3:$F$957,2,0),0) -> 0 | C11: =A11+B11 -> 0 | D11: 10010057 | E11: =VLOOKUP(D11,'MPG Payment '!$E$3:$G$497305,2,0) -> Manish Dairy | F11: =IFERROR(_xlfn.XLOOKUP(D11,'Monthly Deduction'!$I$3:$I$957,'Monthly Deduction'!$H$3:$H$957),0) -> 0 | G11: =VLOOKUP(D11,'MPG Payment '!$E$3:$G$333666,3,0) -> vlc | H11: =VLOOKUP(D11,'MPG Payment '!$E$3:$H$333666,4,0) -> Indirect | I11: =INDEX('MPG Payment '!$C:$C,MATCH('Shayak Income '!D11,'MPG Payment '!E:E,0)) -> 1001 | J11: =INDEX('MPG Payment '!$D:$D,MATCH('Shayak Income '!D11,'MPG Payment '!E:E,0)) -> Majhaul | K11: Old | L11: 45000 | M11: =SUMIF('MPG Payment '!$E$3:$E$344841,'Shayak Income '!D11,'MPG Payment '!$I$3:$I$344841) -> 36779.8 | N11: =SUMIF('MPG Payment '!$E$3:$E$344841,'Shayak Income '!D11,'MPG Payment '!$J$3:$J$344841) -> 1389812.2 | O11: =+M11*0.75 -> 27584.85 | P11: =+M11*0.95 -> 34940.81 | Q11: =SUMIF('MPG Payment '!$E$3:$E$344841,'Shayak Income '!D11,'MPG Payment '!$S$3:$S$344841) -> 0 | R11: =+N11*3% -> 41694.365 | S11: =R11-P11 -> 6753.5548 | T11: =M11*0.1 -> 3677.98 | U11: =((((((IF(K11="New",0,SUMIF('MPG Payment '!$E$3:$E$344841,'Shayak Income '!D11,'MPG Payment '!$AC$3:$AC$344841))))+0)+0)+0)+0)+0 -> 0 | V11: =ROUND((SUM(O11:Q11)-SUM(T11:U11)),0) -> 58848 | W11: =(((AN11-AO11)))+0 -> 0 | X11: =((MIN(IF(B11>0,MAX(N11*2%),0),B11)))+0 -> 0 | Y11: =IFERROR(VLOOKUP(D11,'Monthly Deduction'!$M$2:$N$640,2,0),0) -> 0 | Z11: 0 | AA11: =IFERROR(VLOOKUP(D11,'Monthly Deduction'!A:B,2,0),0) -> 0 | AB11: =ROUND(IFERROR(V11-SUM(W11:AA11),0),0) -> 58848 | AC11: 0 | AD11: =ROUND(AB11-AC11,0) -> 58848 | AE11: =IF(AC11<>0,"Yes","Release") -> Release | AG11: 0 | AI11: 0 | AK11: 6216 | AL11: =COUNTIF(AK11:AK11,"=NA") -> 0 | AN11: =((MIN(IF(A11>0,MAX(N11*2%,1861),0),A11)))+0 -> 0 | AO11: =SUMIF('MPG Payment '!E:E,'Shayak Income '!D11,'MPG Payment '!AJ:AJ) -> 0 | AP11: =W11 -> 0 | AQ11: =AO11+AP11 -> 0 | AS11: =B11-X11 -> 0
A12: =IFERROR(VLOOKUP(D12,'Monthly Deduction'!$I$3:$J$957,2,0),0) -> 42586.743 | B12: =IFERROR(VLOOKUP(D12,'Monthly Deduction'!$E$3:$F$957,2,0),0) -> 16599 | C12: =A12+B12 -> 59185.743 | D12: 10010076 | E12: =VLOOKUP(D12,'MPG Payment '!$E$3:$G$497305,2,0) -> Gomukh Bhith-02 | F12: =IFERROR(_xlfn.XLOOKUP(D12,'Monthly Deduction'!$I$3:$I$957,'Monthly Deduction'!$H$3:$H$957),0) -> 0 | G12: =VLOOKUP(D12,'MPG Payment '!$E$3:$G$333666,3,0) -> MPG | H12: =VLOOKUP(D12,'MPG Payment '!$E$3:$H$333666,4,0) -> Direct | I12: =INDEX('MPG Payment '!$C:$C,MATCH('Shayak Income '!D12,'MPG Payment '!E:E,0)) -> 1001 | J12: =INDEX('MPG Payment '!$D:$D,MATCH('Shayak Income '!D12,'MPG Payment '!E:E,0)) -> Majhaul | K12: Old | L12: 45471 | M12: =SUMIF('MPG Payment '!$E$3:$E$344841,'Shayak Income '!D12,'MPG Payment '!$I$3:$I$344841) -> 3203.4 | N12: =SUMIF('MPG Payment '!$E$3:$E$344841,'Shayak Income '!D12,'MPG Payment '!$J$3:$J$344841) -> 140070.81 | O12: =+M12*0.75 -> 2402.55 | P12: =+M12*0.95 -> 3043.23 | Q12: =SUMIF('MPG Payment '!$E$3:$E$344841,'Shayak Income '!D12,'MPG Payment '!$S$3:$S$344841) -> 0 | R12: =+N12*3% -> 4202.1243 | S12: =R12-P12 -> 1158.8943 | T12: =M12*0.1 -> 320.34 | U12: =((((((IF(K12="New",0,SUMIF('MPG Payment '!$E$3:$E$344841,'Shayak Income '!D12,'MPG Payment '!$AC$3:$AC$344841))))+0)+0)+0)+0)+0 -> 98.084929 | V12: =ROUND((SUM(O12:Q12)-SUM(T12:U12)),0) -> 5027 | W12: =(((AN12-AO12)))+0 -> 2801.4162 | X12: 0 | Y12: 2226 | Z12: 0 | AA12: =IFERROR(VLOOKUP(D12,'Monthly Deduction'!A:B,2,0),0) -> 0 | AB12: =ROUND(IFERROR(V12-SUM(W12:AA12),0),0) -> 0 | AC12: 0 | AD12: =ROUND(AB12-AC12,0) -> 0 | AE12: =IF(AC12<>0,"Yes","Release") -> Release | AG12: 0 | AI12: 0 | AK12: 722.58 | AL12: =COUNTIF(AK12:AK12,"=NA") -> 0 | AN12: =((MIN(IF(A12>0,MAX(N12*2%,1861),0),A12)))+0 -> 2801.4162 | AO12: =SUMIF('MPG Payment '!E:E,'Shayak Income '!D12,'MPG Payment '!AJ:AJ) -> 0 | AP12: =W12 -> 2801.4162 | AQ12: =AO12+AP12 -> 2801.4162 | AS12: =B12-X12 -> 16599
A13: =IFERROR(VLOOKUP(D13,'Monthly Deduction'!$I$3:$J$957,2,0),0) -> 17208.325 | B13: =IFERROR(VLOOKUP(D13,'Monthly Deduction'!$E$3:$F$957,2,0),0) -> 25600 | C13: =A13+B13 -> 42808.325 | D13: 10010082 | E13: =VLOOKUP(D13,'MPG Payment '!$E$3:$G$497305,2,0) -> Gomukh Sharmatola Sahuri | F13: =IFERROR(_xlfn.XLOOKUP(D13,'Monthly Deduction'!$I$3:$I$957,'Monthly Deduction'!$H$3:$H$957),0) -> 0 | G13: =VLOOKUP(D13,'MPG Payment '!$E$3:$G$333666,3,0) -> MPG | H13: =VLOOKUP(D13,'MPG Payment '!$E$3:$H$333666,4,0) -> Direct | I13: =INDEX('MPG Payment '!$C:$C,MATCH('Shayak Income '!D13,'MPG Payment '!E:E,0)) -> 1001 | J13: =INDEX('MPG Payment '!$D:$D,MATCH('Shayak Income '!D13,'MPG Payment '!E:E,0)) -> Majhaul | K13: Old | L13: 45568 | M13: =SUMIF('MPG Payment '!$E$3:$E$344841,'Shayak Income '!D13,'MPG Payment '!$I$3:$I$344841) -> 4784.1 | N13: =SUMIF('MPG Payment '!$E$3:$E$344841,'Shayak Income '!D13,'MPG Payment '!$J$3:$J$344841) -> 186101.66 | O13: =+M13*0.75 -> 3588.075 | P13: =+M13*0.95 -> 4544.895 | Q13: =SUMIF('MPG Payment '!$E$3:$E$344841,'Shayak Income '!D13,'MPG Payment '!$S$3:$S$344841) -> 0 | R13: =+N13*3% -> 5583.0498 | S13: =R13-P13 -> 1038.1548 | T13: =M13*0.1 -> 478.41 | U13: =((((((IF(K13="New",0,SUMIF('MPG Payment '!$E$3:$E$344841,'Shayak Income '!D13,'MPG Payment '!$AC$3:$AC$344841))))+0)+0)+0)+0)+0 -> 0 | V13: =ROUND((SUM(O13:Q13)-SUM(T13:U13)),0) -> 7655 | W13: =(((AN13-AO13)))+0 -> 3722.0332 | X13: 0 | Y13: =IFERROR(VLOOKUP(D13,'Monthly Deduction'!$M$2:$N$640,2,0),0) -> 0 | Z13: 0 | AA13: =IFERROR(VLOOKUP(D13,'Monthly Deduction'!A:B,2,0),0) -> 0 | AB13: =ROUND(IFERROR(V13-SUM(W13:AA13),0),0) -> 3933 | AC13: 0 | AD13: =ROUND(AB13-AC13,0) -> 3933 | AE13: =IF(AC13<>0,"Yes","Release") -> Release | AG13: 0 | AI13: 0 | AK13: 1160.54 | AL13: =COUNTIF(AK13:AK13,"=NA") -> 0 | AN13: =((MIN(IF(A13>0,MAX(N13*2%,1861),0),A13)))+0 -> 3722.0332 | AO13: =SUMIF('MPG Payment '!E:E,'Shayak Income '!D13,'MPG Payment '!AJ:AJ) -> 0 | AP13: =W13 -> 3722.0332 | AQ13: =AO13+AP13 -> 3722.0332 | AS13: =B13-X13 -> 25600
A14: =IFERROR(VLOOKUP(D14,'Monthly Deduction'!$I$3:$J$957,2,0),0) -> 0 | B14: =IFERROR(VLOOKUP(D14,'Monthly Deduction'!$E$3:$F$957,2,0),0) -> 0 | C14: =A14+B14 -> 0 | D14: 10010084 | E14: =VLOOKUP(D14,'MPG Payment '!$E$3:$G$497305,2,0) -> Sangat- Sanjeev Kumar | F14: =IFERROR(_xlfn.XLOOKUP(D14,'Monthly Deduction'!$I$3:$I$957,'Monthly Deduction'!$H$3:$H$957),0) -> 0 | G14: =VLOOKUP(D14,'MPG Payment '!$E$3:$G$333666,3,0) -> vlc | H14: =VLOOKUP(D14,'MPG Payment '!$E$3:$H$333666,4,0) -> Indirect | I14: =INDEX('MPG Payment '!$C:$C,MATCH('Shayak Income '!D14,'MPG Payment '!E:E,0)) -> 1001 | J14: =INDEX('MPG Payment '!$D:$D,MATCH('Shayak Income '!D14,'MPG Payment '!E:E,0)) -> Majhaul | K14: Old | L14: 45567 | M14: =SUMIF('MPG Payment '!$E$3:$E$344841,'Shayak Income '!D14,'MPG Payment '!$I$3:$I$344841) -> 1017.7 | N14: =SUMIF('MPG Payment '!$E$3:$E$344841,'Shayak Income '!D14,'MPG Payment '!$J$3:$J$344841) -> 34594.48 | O14: =+M14*0.75 -> 763.275 | P14: =+M14*0.95 -> 966.815 | Q14: =SUMIF('MPG Payment '!$E$3:$E$344841,'Shayak Income '!D14,'MPG Payment '!$S$3:$S$344841) -> 0 | R14: =+N14*3% -> 1037.8344 | S14: =R14-P14 -> 71.0194 | T14: =M14*0.1 -> 101.77 | U14: =((((((IF(K14="New",0,SUMIF('MPG Payment '!$E$3:$E$344841,'Shayak Income '!D14,'MPG Payment '!$AC$3:$AC$344841))))+0)+0)+0)+0)+0 -> 1227.1777 | V14: =ROUND((SUM(O14:Q14)-SUM(T14:U14)),0) -> 401 | W14: =(((AN14-AO14)))+0 -> 0 | X14: =((MIN(IF(B14>0,MAX(N14*2%),0),B14)))+0 -> 0 | Y14: =IFERROR(VLOOKUP(D14,'Monthly Deduction'!$M$2:$N$640,2,0),0) -> 0 | Z14: 0 | AA14: =IFERROR(VLOOKUP(D14,'Monthly Deduction'!A:B,2,0),0) -> 0 | AB14: =ROUND(IFERROR(V14-SUM(W14:AA14),0),0) -> 401 | AC14: 0 | AD14: =ROUND(AB14-AC14,0) -> 401 | AE14: =IF(AC14<>0,"Yes","Release") -> Release | AG14: 0 | AI14: 0 | AK14: 156.3 | AL14: =COUNTIF(AK14:AK14,"=NA") -> 0 | AN14: =((MIN(IF(A14>0,MAX(N14*2%,1861),0),A14)))+0 -> 0 | AO14: =SUMIF('MPG Payment '!E:E,'Shayak Income '!D14,'MPG Payment '!AJ:AJ) -> 0 | AP14: =W14 -> 0 | AQ14: =AO14+AP14 -> 0 | AS14: =B14-X14 -> 0
A15: =IFERROR(VLOOKUP(D15,'Monthly Deduction'!$I$3:$J$957,2,0),0) -> 66070 | B15: =IFERROR(VLOOKUP(D15,'Monthly Deduction'!$E$3:$F$957,2,0),0) -> 6400 | C15: =A15+B15 -> 72470 | D15: 10010086 | E15: =VLOOKUP(D15,'MPG Payment '!$E$3:$G$497305,2,0) -> Gomukh Garhi Bisanpur | F15: =IFERROR(_xlfn.XLOOKUP(D15,'Monthly Deduction'!$I$3:$I$957,'Monthly Deduction'!$H$3:$H$957),0) -> 0 | G15: =VLOOKUP(D15,'MPG Payment '!$E$3:$G$333666,3,0) -> MPG | H15: =VLOOKUP(D15,'MPG Payment '!$E$3:$H$333666,4,0) -> Direct | I15: =INDEX('MPG Payment '!$C:$C,MATCH('Shayak Income '!D15,'MPG Payment '!E:E,0)) -> 1058 | J15: =INDEX('MPG Payment '!$D:$D,MATCH('Shayak Income '!D15,'MPG Payment '!E:E,0)) -> Hasanpur | K15: Old | L15: 45631 | M15: =SUMIF('MPG Payment '!$E$3:$E$344841,'Shayak Income '!D15,'MPG Payment '!$I$3:$I$344841) -> 340.43 | N15: =SUMIF('MPG Payment '!$E$3:$E$344841,'Shayak Income '!D15,'MPG Payment '!$J$3:$J$344841) -> 16211.8 | O15: =+M15*0.75 -> 255.3225 | P15: =+M15*0.95 -> 323.4085 | Q15: =SUMIF('MPG Payment '!$E$3:$E$344841,'Shayak Income '!D15,'MPG Payment '!$S$3:$S$344841) -> 360.83 | R15: =+N15*3% -> 486.354 | S15: =R15-P15 -> 162.9455 | T15: =M15*0.1 -> 34.043 | U15: =((((((IF(K15="New",0,SUMIF('MPG Payment '!$E$3:$E$344841,'Shayak Income '!D15,'MPG Payment '!$AC$3:$AC$344841))))+0)+0)+0)+0)+-1441 -> 906.00265 | V15: =ROUND((SUM(O15:Q15)-SUM(T15:U15)),0) -> 0 | W15: 0 | X15: 0 | Y15: 0 | Z15: 0 | AA15: 0 | AB15: =ROUND(IFERROR(V15-SUM(W15:AA15),0),0) -> 0 | AC15: 0 | AD15: =ROUND(AB15-AC15,0) -> 0 | AE15: =IF(AC15<>0,"Yes","Release") -> Release | AG15: 0 | AI15: 0 | AK15: 58.25 | AL15: =COUNTIF(AK15:AK15,"=NA") -> 0 | AN15: =((MIN(IF(A15>0,MAX(N15*2%,1861),0),A15)))+0 -> 1861 | AO15: =SUMIF('MPG Payment '!E:E,'Shayak Income '!D15,'MPG Payment '!AJ:AJ) -> 1500 | AP15: =W15 -> 0 | AQ15: =AO15+AP15 -> 1500 | AS15: =B15-X15 -> 6400
A16: =IFERROR(VLOOKUP(D16,'Monthly Deduction'!$I$3:$J$957,2,0),0) -> 0 | B16: =IFERROR(VLOOKUP(D16,'Monthly Deduction'!$E$3:$F$957,2,0),0) -> 0 | C16: =A16+B16 -> 0 | D16: 10010087 | E16: =VLOOKUP(D16,'MPG Payment '!$E$3:$G$497305,2,0) -> Bagaraha-Gopal Yadav | F16: =IFERROR(_xlfn.XLOOKUP(D16,'Monthly Deduction'!$I$3:$I$957,'Monthly Deduction'!$H$3:$H$957),0) -> 0 | G16: =VLOOKUP(D16,'MPG Payment '!$E$3:$G$333666,3,0) -> vlc | H16: =VLOOKUP(D16,'MPG Payment '!$E$3:$H$333666,4,0) -> Indirect | I16: =INDEX('MPG Payment '!$C:$C,MATCH('Shayak Income '!D16,'MPG Payment '!E:E,0)) -> 1058 | J16: =INDEX('MPG Payment '!$D:$D,MATCH('Shayak Income '!D16,'MPG Payment '!E:E,0)) -> Hasanpur | K16: Old | L16: 45597 | M16: =SUMIF('MPG Payment '!$E$3:$E$344841,'Shayak Income '!D16,'MPG Payment '!$I$3:$I$344841) -> 133.74 | N16: =SUMIF('MPG Payment '!$E$3:$E$344841,'Shayak Income '!D16,'MPG Payment '!$J$3:$J$344841) -> 4762.38 | O16: =+M16*0.75 -> 100.305 | P16: =+M16*0.95 -> 127.053 | Q16: =SUMIF('MPG Payment '!$E$3:$E$344841,'Shayak Income '!D16,'MPG Payment '!$S$3:$S$344841) -> 0 | R16: =+N16*3% -> 142.8714 | S16: =R16-P16 -> 15.8184 | T16: =M16*0.1 -> 13.374 | U16: =((((((IF(K16="New",0,SUMIF('MPG Payment '!$E$3:$E$344841,'Shayak Income '!D16,'MPG Payment '!$AC$3:$AC$344841))))+0)+0)+0)+0)+-189 -> 214.28179 | V16: =ROUND((SUM(O16:Q16)-SUM(T16:U16)),0) -> 0 | W16: 0 | X16: 0 | Y16: 0 | Z16: 0 | AA16: 0 | AB16: =ROUND(IFERROR(V16-SUM(W16:AA16),0),0) -> 0 | AC16: =AB16 -> 0 | AD16: =ROUND(AB16-AC16,0) -> 0 | AE16: =IF(AC16<>0,"Yes","Release") -> Release | AG16: 0 | AH16: Non pouring | AI16: 0 | AK16: 0 | AL16: =COUNTIF(AK16:AK16,"=NA") -> 0 | AN16: =((MIN(IF(A16>0,MAX(N16*2%,1861),0),A16)))+0 -> 0 | AO16: =SUMIF('MPG Payment '!E:E,'Shayak Income '!D16,'MPG Payment '!AJ:AJ) -> 0 | AP16: =W16 -> 0 | AQ16: =AO16+AP16 -> 0 | AS16: =B16-X16 -> 0
A17: =IFERROR(VLOOKUP(D17,'Monthly Deduction'!$I$3:$J$957,2,0),0) -> 72787.047 | B17: =IFERROR(VLOOKUP(D17,'Monthly Deduction'!$E$3:$F$957,2,0),0) -> 5699 | C17: =A17+B17 -> 78486.047 | D17: 10010089 | E17: =VLOOKUP(D17,'MPG Payment '!$E$3:$G$497305,2,0) -> Gomukh Barkurwa | F17: =IFERROR(_xlfn.XLOOKUP(D17,'Monthly Deduction'!$I$3:$I$957,'Monthly Deduction'!$H$3:$H$957),0) -> 0 | G17: =VLOOKUP(D17,'MPG Payment '!$E$3:$G$333666,3,0) -> MPG | H17: =VLOOKUP(D17,'MPG Payment '!$E$3:$H$333666,4,0) -> Direct | I17: =INDEX('MPG Payment '!$C:$C,MATCH('Shayak Income '!D17,'MPG Payment '!E:E,0)) -> 1058 | J17: =INDEX('MPG Payment '!$D:$D,MATCH('Shayak Income '!D17,'MPG Payment '!E:E,0)) -> Hasanpur | K17: Old | L17: 45627 | M17: =SUMIF('MPG Payment '!$E$3:$E$344841,'Shayak Income '!D17,'MPG Payment '!$I$3:$I$344841) -> 1985.29 | N17: =SUMIF('MPG Payment '!$E$3:$E$344841,'Shayak Income '!D17,'MPG Payment '!$J$3:$J$344841) -> 84683.87 | O17: =+M17*0.75 -> 1488.9675 | P17: =+M17*0.95 -> 1886.0255 | Q17: =SUMIF('MPG Payment '!$E$3:$E$344841,'Shayak Income '!D17,'MPG Payment '!$S$3:$S$344841) -> 490.09 | R17: =+N17*3% -> 2540.5161 | S17: =R17-P17 -> 654.4906 | T17: =M17*0.1 -> 198.529 | U17: =((((((IF(K17="New",0,SUMIF('MPG Payment '!$E$3:$E$344841,'Shayak Income '!D17,'MPG Payment '!$AC$3:$AC$344841))))+0)+0)+0)+0)+0 -> 696.14463 | V17: =ROUND((SUM(O17:Q17)-SUM(T17:U17)),0) -> 2970 | W17: =(((AN17-AO17)))+0 -> 1861 | X17: 0 | Y17: =IFERROR(VLOOKUP(D17,'Monthly Deduction'!$M$2:$N$640,2,0),0) -> 0 | Z17: 0 | AA17: =IFERROR(VLOOKUP(D17,'Monthly Deduction'!A:B,2,0),0) -> 0 | AB17: =ROUND(IFERROR(V17-SUM(W17:AA17),0),0) -> 1109 | AC17: 0 | AD17: =ROUND(AB17-AC17,0) -> 1109 | AE17: =IF(AC17<>0,"Yes","Release") -> Release | AG17: 0 | AI17: 0 | AK17: 468.17 | AL17: =COUNTIF(AK17:AK17,"=NA") -> 0 | AN17: =((MIN(IF(A17>0,MAX(N17*2%,1861),0),A17)))+0 -> 1861 | AO17: =SUMIF('MPG Payment '!E:E,'Shayak Income '!D17,'MPG Payment '!AJ:AJ) -> 0 | AP17: =W17 -> 1861 | AQ17: =AO17+AP17 -> 1861 | AS17: =B17-X17 -> 5699
A18: =IFERROR(VLOOKUP(D18,'Monthly Deduction'!$I$3:$J$957,2,0),0) -> 0 | B18: =IFERROR(VLOOKUP(D18,'Monthly Deduction'!$E$3:$F$957,2,0),0) -> 0 | C18: =A18+B18 -> 0 | D18: 10010092 | E18: =VLOOKUP(D18,'MPG Payment '!$E$3:$G$497305,2,0) -> Kamla- Amarjeet | F18: =IFERROR(_xlfn.XLOOKUP(D18,'Monthly Deduction'!$I$3:$I$957,'Monthly Deduction'!$H$3:$H$957),0) -> 0 | G18: =VLOOKUP(D18,'MPG Payment '!$E$3:$G$333666,3,0) -> vlc | H18: =VLOOKUP(D18,'MPG Payment '!$E$3:$H$333666,4,0) -> Indirect | I18: =INDEX('MPG Payment '!$C:$C,MATCH('Shayak Income '!D18,'MPG Payment '!E:E,0)) -> 1001 | J18: =INDEX('MPG Payment '!$D:$D,MATCH('Shayak Income '!D18,'MPG Payment '!E:E,0)) -> Majhaul | K18: Old | L18: 45689 | M18: =SUMIF('MPG Payment '!$E$3:$E$344841,'Shayak Income '!D18,'MPG Payment '!$I$3:$I$344841) -> 2867.6 | N18: =SUMIF('MPG Payment '!$E$3:$E$344841,'Shayak Income '!D18,'MPG Payment '!$J$3:$J$344841) -> 92714.09 | O18: =+M18*0.75 -> 2150.7 | P18: =+M18*0.95 -> 2724.22 | Q18: =SUMIF('MPG Payment '!$E$3:$E$344841,'Shayak Income '!D18,'MPG Payment '!$S$3:$S$344841) -> 0 | R18: =+N18*3% -> 2781.4227 | S18: =R18-P18 -> 57.2027 | T18: =M18*0.1 -> 286.76 | U18: =((((((IF(K18="New",0,SUMIF('MPG Payment '!$E$3:$E$344841,'Shayak Income '!D18,'MPG Payment '!$AC$3:$AC$344841))))+0)+0)+0)+0)+0 -> 92.581663 | V18: =ROUND((SUM(O18:Q18)-SUM(T18:U18)),0) -> 4496 | W18: =(((AN18-AO18)))+0 -> 0 | X18: =((MIN(IF(B18>0,MAX(N18*2%),0),B18)))+0 -> 0 | Y18: =IFERROR(VLOOKUP(D18,'Monthly Deduction'!$M$2:$N$640,2,0),0) -> 0 | Z18: 0 | AA18: =IFERROR(VLOOKUP(D18,'Monthly Deduction'!A:B,2,0),0) -> 0 | AB18: =ROUND(IFERROR(V18-SUM(W18:AA18),0),0) -> 4496 | AC18: 0 | AD18: =ROUND(AB18-AC18,0) -> 4496 | AE18: =IF(AC18<>0,"Yes","Release") -> Release | AG18: 0 | AI18: 0 | AK18: 406.9 | AL18: =COUNTIF(AK18:AK18,"=NA") -> 0 | AN18: =((MIN(IF(A18>0,MAX(N18*2%,1861),0),A18)))+0 -> 0 | AO18: =SUMIF('MPG Payment '!E:E,'Shayak Income '!D18,'MPG Payment '!AJ:AJ) -> 0 | AP18: =W18 -> 0 | AQ18: =AO18+AP18 -> 0 | AS18: =B18-X18 -> 0
A19: =IFERROR(VLOOKUP(D19,'Monthly Deduction'!$I$3:$J$957,2,0),0) -> 71548 | B19: =IFERROR(VLOOKUP(D19,'Monthly Deduction'!$E$3:$F$957,2,0),0) -> 3016.2028 | C19: =A19+B19 -> 74564.203 | D19: 10010095 | E19: =VLOOKUP(D19,'MPG Payment '!$E$3:$G$497305,2,0) -> Gomukh Goha-02 | F19: =IFERROR(_xlfn.XLOOKUP(D19,'Monthly Deduction'!$I$3:$I$957,'Monthly Deduction'!$H$3:$H$957),0) -> 0 | G19: =VLOOKUP(D19,'MPG Payment '!$E$3:$G$333666,3,0) -> MPG | H19: =VLOOKUP(D19,'MPG Payment '!$E$3:$H$333666,4,0) -> Direct | I19: =INDEX('MPG Payment '!$C:$C,MATCH('Shayak Income '!D19,'MPG Payment '!E:E,0)) -> 1058 | J19: =INDEX('MPG Payment '!$D:$D,MATCH('Shayak Income '!D19,'MPG Payment '!E:E,0)) -> Hasanpur | K19: Old | L19: 45700 | M19: =SUMIF('MPG Payment '!$E$3:$E$344841,'Shayak Income '!D19,'MPG Payment '!$I$3:$I$344841) -> 1004.1 | N19: =SUMIF('MPG Payment '!$E$3:$E$344841,'Shayak Income '!D19,'MPG Payment '!$J$3:$J$344841) -> 42066.85 | O19: =+M19*0.75 -> 753.075 | P19: =+M19*0.95 -> 953.895 | Q19: =SUMIF('MPG Payment '!$E$3:$E$344841,'Shayak Income '!D19,'MPG Payment '!$S$3:$S$344841) -> 776.04 | R19: =+N19*3% -> 1262.0055 | S19: =R19-P19 -> 308.1105 | T19: =M19*0.1 -> 100.41 | U19: =((((((IF(K19="New",0,SUMIF('MPG Payment '!$E$3:$E$344841,'Shayak Income '!D19,'MPG Payment '!$AC$3:$AC$344841))))+0)+0)+0)+0)+0 -> 1502.8033 | V19: =ROUND((SUM(O19:Q19)-SUM(T19:U19)),0) -> 880 | W19: 880 | X19: 0 | Y19: =IFERROR(VLOOKUP(D19,'Monthly Deduction'!$M$2:$N$640,2,0),0) -> 0 | Z19: 0 | AA19: =IFERROR(VLOOKUP(D19,'Monthly Deduction'!A:B,2,0),0) -> 0 | AB19: =ROUND(IFERROR(V19-SUM(W19:AA19),0),0) -> 0 | AC19: 0 | AD19: =ROUND(AB19-AC19,0) -> 0 | AE19: =IF(AC19<>0,"Yes","Release") -> Release | AG19: 0 | AI19: 0 | AK19: 201.57 | AL19: =COUNTIF(AK19:AK19,"=NA") -> 0 | AN19: =((MIN(IF(A19>0,MAX(N19*2%,1861),0),A19)))+0 -> 1861 | AO19: =SUMIF('MPG Payment '!E:E,'Shayak Income '!D19,'MPG Payment '!AJ:AJ) -> 0 | AP19: =W19 -> 880 | AQ19: =AO19+AP19 -> 880 | AS19: =B19-X19 -> 3016.2028
A20: =IFERROR(VLOOKUP(D20,'Monthly Deduction'!$I$3:$J$957,2,0),0) -> 44473.397 | B20: =IFERROR(VLOOKUP(D20,'Monthly Deduction'!$E$3:$F$957,2,0),0) -> 17290.967 | C20: =A20+B20 -> 61764.363 | D20: 10010097 | E20: =VLOOKUP(D20,'MPG Payment '!$E$3:$G$497305,2,0) -> Gomukh Cheria Bariarpur | F20: =IFERROR(_xlfn.XLOOKUP(D20,'Monthly Deduction'!$I$3:$I$957,'Monthly Deduction'!$H$3:$H$957),0) -> 0 | G20: =VLOOKUP(D20,'MPG Payment '!$E$3:$G$333666,3,0) -> MPG | H20: =VLOOKUP(D20,'MPG Payment '!$E$3:$H$333666,4,0) -> Direct | I20: =INDEX('MPG Payment '!$C:$C,MATCH('Shayak Income '!D20,'MPG Payment '!E:E,0)) -> 1001 | J20: =INDEX('MPG Payment '!$D:$D,MATCH('Shayak Income '!D20,'MPG Payment '!E:E,0)) -> Majhaul | K20: Old | L20: 45708 | M20: =SUMIF('MPG Payment '!$E$3:$E$344841,'Shayak Income '!D20,'MPG Payment '!$I$3:$I$344841) -> 4607.6 | N20: =SUMIF('MPG Payment '!$E$3:$E$344841,'Shayak Income '!D20,'MPG Payment '!$J$3:$J$344841) -> 178316.71 | O20: =+M20*0.75 -> 3455.7 | P20: =+M20*0.95 -> 4377.22 | Q20: =SUMIF('MPG Payment '!$E$3:$E$344841,'Shayak Income '!D20,'MPG Payment '!$S$3:$S$344841) -> 343.57 | R20: =+N20*3% -> 5349.5013 | S20: =R20-P20 -> 972.2813 | T20: =M20*0.1 -> 460.76 | U20: =((((((IF(K20="New",0,SUMIF('MPG Payment '!$E$3:$E$344841,'Shayak Income '!D20,'MPG Payment '!$AC$3:$AC$344841))))+0)+0)+0)+0)+0 -> 0 | V20: =ROUND((SUM(O20:Q20)-SUM(T20:U20)),0) -> 7716 | W20: =(((AN20-AO20)))+0 -> 3566.3342 | X20: 0 | Y20: =IFERROR(VLOOKUP(D20,'Monthly Deduction'!$M$2:$N$640,2,0),0) -> 0 | Z20: 0 | AA20: =IFERROR(VLOOKUP(D20,'Monthly Deduction'!A:B,2,0),0) -> 0 | AB20: =ROUND(IFERROR(V20-SUM(W20:AA20),0),0) -> 4150 | AC20: 0 | AD20: =ROUND(AB20-AC20,0) -> 4150 | AE20: =IF(AC20<>0,"Yes","Release") -> Release | AG20: 0 | AI20: 0 | AK20: 973.6 | AL20: =COUNTIF(AK20:AK20,"=NA") -> 0 | AN20: =((MIN(IF(A20>0,MAX(N20*2%,1861),0),A20)))+0 -> 3566.3342 | AO20: =SUMIF('MPG Payment '!E:E,'Shayak Income '!D20,'MPG Payment '!AJ:AJ) -> 0 | AP20: =W20 -> 3566.3342 | AQ20: =AO20+AP20 -> 3566.3342 | AS20: =B20-X20 -> 17290.967
A21: =IFERROR(VLOOKUP(D21,'Monthly Deduction'!$I$3:$J$957,2,0),0) -> 68485 | B21: =IFERROR(VLOOKUP(D21,'Monthly Deduction'!$E$3:$F$957,2,0),0) -> 6400 | C21: =A21+B21 -> 74885 | D21: 10010099 | E21: =VLOOKUP(D21,'MPG Payment '!$E$3:$G$497305,2,0) -> Gomukh Bagraha-01 | F21: =IFERROR(_xlfn.XLOOKUP(D21,'Monthly Deduction'!$I$3:$I$957,'Monthly Deduction'!$H$3:$H$957),0) -> 0 | G21: =VLOOKUP(D21,'MPG Payment '!$E$3:$G$333666,3,0) -> MPG | H21: =VLOOKUP(D21,'MPG Payment '!$E$3:$H$333666,4,0) -> Direct | I21: =INDEX('MPG Payment '!$C:$C,MATCH('Shayak Income '!D21,'MPG Payment '!E:E,0)) -> 1058 | J21: =INDEX('MPG Payment '!$D:$D,MATCH('Shayak Income '!D21,'MPG Payment '!E:E,0)) -> Hasanpur | K21: Old | L21: 45736 | M21: =SUMIF('MPG Payment '!$E$3:$E$344841,'Shayak Income '!D21,'MPG Payment '!$I$3:$I$344841) -> 780.52 | N21: =SUMIF('MPG Payment '!$E$3:$E$344841,'Shayak Income '!D21,'MPG Payment '!$J$3:$J$344841) -> 33748.8 | O21: =+M21*0.75 -> 585.39 | P21: =+M21*0.95 -> 741.494 | Q21: =SUMIF('MPG Payment '!$E$3:$E$344841,'Shayak Income '!D21,'MPG Payment '!$S$3:$S$344841) -> 583.79 | R21: =+N21*3% -> 1012.464 | S21: =R21-P21 -> 270.97 | T21: =M21*0.1 -> 78.052 | U21: =((((((IF(K21="New",0,SUMIF('MPG Payment '!$E$3:$E$344841,'Shayak Income '!D21,'MPG Payment '!$AC$3:$AC$344841))))+0)+0)+0)+0)+0 -> 1735.6632 | V21: =ROUND((SUM(O21:Q21)-SUM(T21:U21)),0) -> 97 | W21: 97 | X21: 0 | Y21: =IFERROR(VLOOKUP(D21,'Monthly Deduction'!$M$2:$N$640,2,0),0) -> 0 | Z21: 0 | AA21: =IFERROR(VLOOKUP(D21,'Monthly Deduction'!A:B,2,0),0) -> 0 | AB21: =ROUND(IFERROR(V21-SUM(W21:AA21),0),0) -> 0 | AC21: 0 | AD21: =ROUND(AB21-AC21,0) -> 0 | AE21: =IF(AC21<>0,"Yes","Release") -> Release | AG21: 0 | AI21: 0 | AK21: 125.19 | AL21: =COUNTIF(AK21:AK21,"=NA") -> 0 | AN21: =((MIN(IF(A21>0,MAX(N21*2%,1861),0),A21)))+0 -> 1861 | AO21: =SUMIF('MPG Payment '!E:E,'Shayak Income '!D21,'MPG Payment '!AJ:AJ) -> 1500 | AP21: =W21 -> 97 | AQ21: =AO21+AP21 -> 1597 | AS21: =B21-X21 -> 6400
A22: =IFERROR(VLOOKUP(D22,'Monthly Deduction'!$I$3:$J$957,2,0),0) -> 87749 | B22: =IFERROR(VLOOKUP(D22,'Monthly Deduction'!$E$3:$F$957,2,0),0) -> 6400 | C22: =A22+B22 -> 94149 | D22: 10010108 | E22: =VLOOKUP(D22,'MPG Payment '!$E$3:$G$497305,2,0) -> Gomukh Pirauna | F22: =IFERROR(_xlfn.XLOOKUP(D22,'Monthly Deduction'!$I$3:$I$957,'Monthly Deduction'!$H$3:$H$957),0) -> 0 | G22: =VLOOKUP(D22,'MPG Payment '!$E$3:$G$333666,3,0) -> MPG | H22: =VLOOKUP(D22,'MPG Payment '!$E$3:$H$333666,4,0) -> Direct | I22: =INDEX('MPG Payment '!$C:$C,MATCH('Shayak Income '!D22,'MPG Payment '!E:E,0)) -> 1001 | J22: =INDEX('MPG Payment '!$D:$D,MATCH('Shayak Income '!D22,'MPG Payment '!E:E,0)) -> Majhaul | K22: Old | L22: 45777 | M22: =SUMIF('MPG Payment '!$E$3:$E$344841,'Shayak Income '!D22,'MPG Payment '!$I$3:$I$344841) -> 956.1 | N22: =SUMIF('MPG Payment '!$E$3:$E$344841,'Shayak Income '!D22,'MPG Payment '!$J$3:$J$344841) -> 34333.04 | O22: =+M22*0.75 -> 717.075 | P22: =+M22*0.95 -> 908.295 | Q22: =SUMIF('MPG Payment '!$E$3:$E$344841,'Shayak Income '!D22,'MPG Payment '!$S$3:$S$344841) -> 30.59 | R22: =+N22*3% -> 1029.9912 | S22: =R22-P22 -> 121.6962 | T22: =M22*0.1 -> 95.61 | U22: =((((((IF(K22="New",0,SUMIF('MPG Payment '!$E$3:$E$344841,'Shayak Income '!D22,'MPG Payment '!$AC$3:$AC$344841))))+0)+0)+0)+0)+0 -> 1327.2896 | V22: =ROUND((SUM(O22:Q22)-SUM(T22:U22)),0) -> 233 | W22: 233 | X22: 0 | Y22: =IFERROR(VLOOKUP(D22,'Monthly Deduction'!$M$2:$N$640,2,0),0) -> 0 | Z22: 0 | AA22: =IFERROR(VLOOKUP(D22,'Monthly Deduction'!A:B,2,0),0) -> 0 | AB22: =ROUND(IFERROR(V22-SUM(W22:AA22),0),0) -> 0 | AC22: =AB22 -> 0 | AD22: =ROUND(AB22-AC22,0) -> 0 | AE22: =IF(AC22<>0,"Yes","Release") -> Release | AG22: 0 | AH22: Agreement issue / Down Payment | AI22: 9803 | AK22: 106.57 | AL22: =COUNTIF(AK22:AK22,"=NA") -> 0 | AN22: =((MIN(IF(A22>0,MAX(N22*2%,1861),0),A22)))+0 -> 1861 | AO22: =SUMIF('MPG Payment '!E:E,'Shayak Income '!D22,'MPG Payment '!AJ:AJ) -> 1500 | AP22: =W22 -> 233 | AQ22: =AO22+AP22 -> 1733 | AS22: =B22-X22 -> 6400
A23: =IFERROR(VLOOKUP(D23,'Monthly Deduction'!$I$3:$J$957,2,0),0) -> 0 | B23: =IFERROR(VLOOKUP(D23,'Monthly Deduction'!$E$3:$F$957,2,0),0) -> 0 | C23: =A23+B23 -> 0 | D23: 10010109 | E23: =VLOOKUP(D23,'MPG Payment '!$E$3:$G$497305,2,0) -> Parra- Nagendra Kumar | F23: =IFERROR(_xlfn.XLOOKUP(D23,'Monthly Deduction'!$I$3:$I$957,'Monthly Deduction'!$H$3:$H$957),0) -> 0 | G23: =VLOOKUP(D23,'MPG Payment '!$E$3:$G$333666,3,0) -> vlc | H23: =VLOOKUP(D23,'MPG Payment '!$E$3:$H$333666,4,0) -> Indirect | I23: =INDEX('MPG Payment '!$C:$C,MATCH('Shayak Income '!D23,'MPG Payment '!E:E,0)) -> 1001 | J23: =INDEX('MPG Payment '!$D:$D,MATCH('Shayak Income '!D23,'MPG Payment '!E:E,0)) -> Majhaul | K23: Old | L23: 45777 | M23: =SUMIF('MPG Payment '!$E$3:$E$344841,'Shayak Income '!D23,'MPG Payment '!$I$3:$I$344841) -> 1139.6 | N23: =SUMIF('MPG Payment '!$E$3:$E$344841,'Shayak Income '!D23,'MPG Payment '!$J$3:$J$344841) -> 39508.1 | O23: =+M23*0.75 -> 854.7 | P23: =+M23*0.95 -> 1082.62 | Q23: =SUMIF('MPG Payment '!$E$3:$E$344841,'Shayak Income '!D23,'MPG Payment '!$S$3:$S$344841) -> 0 | R23: =+N23*3% -> 1185.243 | S23: =R23-P23 -> 102.623 | T23: =M23*0.1 -> 113.96 | U23: =((((((IF(K23="New",0,SUMIF('MPG Payment '!$E$3:$E$344841,'Shayak Income '!D23,'MPG Payment '!$AC$3:$AC$344841))))+0)+0)+0)+0)+0 -> 1151.2635 | V23: =ROUND((SUM(O23:Q23)-SUM(T23:U23)),0) -> 672 | W23: =(((AN23-AO23)))+0 -> 0 | X23: =((MIN(IF(B23>0,MAX(N23*2%),0),B23)))+0 -> 0 | Y23: =IFERROR(VLOOKUP(D23,'Monthly Deduction'!$M$2:$N$640,2,0),0) -> 0 | Z23: 0 | AA23: =IFERROR(VLOOKUP(D23,'Monthly Deduction'!A:B,2,0),0) -> 0 | AB23: =ROUND(IFERROR(V23-SUM(W23:AA23),0),0) -> 672 | AC23: 0 | AD23: =ROUND(AB23-AC23,0) -> 672 | AE23: =IF(AC23<>0,"Yes","Release") -> Release | AG23: 0 | AI23: 0 | AK23: 244.63 | AL23: =COUNTIF(AK23:AK23,"=NA") -> 0 | AN23: =((MIN(IF(A23>0,MAX(N23*2%,1861),0),A23)))+0 -> 0 | AO23: =SUMIF('MPG Payment '!E:E,'Shayak Income '!D23,'MPG Payment '!AJ:AJ) -> 0 | AP23: =W23 -> 0 | AQ23: =AO23+AP23 -> 0 | AS23: =B23-X23 -> 0
A24: =IFERROR(VLOOKUP(D24,'Monthly Deduction'!$I$3:$J$957,2,0),0) -> 68205.747 | B24: =IFERROR(VLOOKUP(D24,'Monthly Deduction'!$E$3:$F$957,2,0),0) -> 12800 | C24: =A24+B24 -> 81005.747 | D24: 10010113 | E24: =VLOOKUP(D24,'MPG Payment '!$E$3:$G$497305,2,0) -> Gomukh Basahi | F24: =IFERROR(_xlfn.XLOOKUP(D24,'Monthly Deduction'!$I$3:$I$957,'Monthly Deduction'!$H$3:$H$957),0) -> 0 | G24: =VLOOKUP(D24,'MPG Payment '!$E$3:$G$333666,3,0) -> MPG | H24: =VLOOKUP(D24,'MPG Payment '!$E$3:$H$333666,4,0) -> Direct | I24: =INDEX('MPG Payment '!$C:$C,MATCH('Shayak Income '!D24,'MPG Payment '!E:E,0)) -> 1001 | J24: =INDEX('MPG Payment '!$D:$D,MATCH('Shayak Income '!D24,'MPG Payment '!E:E,0)) -> Majhaul | K24: Old | L24: 45810 | M24: =SUMIF('MPG Payment '!$E$3:$E$344841,'Shayak Income '!D24,'MPG Payment '!$I$3:$I$344841) -> 3405.2 | N24: =SUMIF('MPG Payment '!$E$3:$E$344841,'Shayak Income '!D24,'MPG Payment '!$J$3:$J$344841) -> 137136.07 | O24: =+M24*0.75 -> 2553.9 | P24: =+M24*0.95 -> 3234.94 | Q24: =SUMIF('MPG Payment '!$E$3:$E$344841,'Shayak Income '!D24,'MPG Payment '!$S$3:$S$344841) -> 413.65 | R24: =+N24*3% -> 4114.0821 | S24: =R24-P24 -> 879.1421 | T24: =M24*0.1 -> 340.52 | U24: =((((((IF(K24="New",0,SUMIF('MPG Payment '!$E$3:$E$344841,'Shayak Income '!D24,'MPG Payment '!$AC$3:$AC$344841))))+0)+0)+0)+0)+0 -> 0 | V24: =ROUND((SUM(O24:Q24)-SUM(T24:U24)),0) -> 5862 | W24: =(((AN24-AO24)))+0 -> 2742.7214 | X24: 0 | Y24: =IFERROR(VLOOKUP(D24,'Monthly Deduction'!$M$2:$N$640,2,0),0) -> 0 | Z24: 0 | AA24: =IFERROR(VLOOKUP(D24,'Monthly Deduction'!A:B,2,0),0) -> 0 | AB24: =ROUND(IFERROR(V24-SUM(W24:AA24),0),0) -> 3119 | AC24: 0 | AD24: =ROUND(AB24-AC24,0) -> 3119 | AE24: =IF(AC24<>0,"Yes","Release") -> Release | AG24: 0 | AI24: 0 | AK24: 696.2 | AL24: =COUNTIF(AK24:AK24,"=NA") -> 0 | AN24: =((MIN(IF(A24>0,MAX(N24*2%,1861),0),A24)))+0 -> 2742.7214 | AO24: =SUMIF('MPG Payment '!E:E,'Shayak Income '!D24,'MPG Payment '!AJ:AJ) -> 0 | AP24: =W24 -> 2742.7214 | AQ24: =AO24+AP24 -> 2742.7214 | AS24: =B24-X24 -> 12800
A25: =IFERROR(VLOOKUP(D25,'Monthly Deduction'!$I$3:$J$957,2,0),0) -> 42701.196 | B25: =IFERROR(VLOOKUP(D25,'Monthly Deduction'!$E$3:$F$957,2,0),0) -> 16000 | C25: =A25+B25 -> 58701.196 | D25: 10010121 | E25: =VLOOKUP(D25,'MPG Payment '!$E$3:$G$497305,2,0) -> Gomukh Sawantpur | F25: =IFERROR(_xlfn.XLOOKUP(D25,'Monthly Deduction'!$I$3:$I$957,'Monthly Deduction'!$H$3:$H$957),0) -> 0 | G25: =VLOOKUP(D25,'MPG Payment '!$E$3:$G$333666,3,0) -> MPG | H25: =VLOOKUP(D25,'MPG Payment '!$E$3:$H$333666,4,0) -> Direct | I25: =INDEX('MPG Payment '!$C:$C,MATCH('Shayak Income '!D25,'MPG Payment '!E:E,0)) -> 1001 | J25: =INDEX('MPG Payment '!$D:$D,MATCH('Shayak Income '!D25,'MPG Payment '!E:E,0)) -> Majhaul | K25: Old | L25: 45842 | M25: =SUMIF('MPG Payment '!$E$3:$E$344841,'Shayak Income '!D25,'MPG Payment '!$I$3:$I$344841) -> 5378.7 | N25: =SUMIF('MPG Payment '!$E$3:$E$344841,'Shayak Income '!D25,'MPG Payment '!$J$3:$J$344841) -> 207037.88 | O25: =+M25*0.75 -> 4034.025 | P25: =+M25*0.95 -> 5109.765 | Q25: =SUMIF('MPG Payment '!$E$3:$E$344841,'Shayak Income '!D25,'MPG Payment '!$S$3:$S$344841) -> 208.24 | R25: =+N25*3% -> 6211.1364 | S25: =R25-P25 -> 1101.3714 | T25: =M25*0.1 -> 537.87 | U25: =((((((IF(K25="New",0,SUMIF('MPG Payment '!$E$3:$E$344841,'Shayak Income '!D25,'MPG Payment '!$AC$3:$AC$344841))))+0)+0)+0)+0)+0 -> 0 | V25: =ROUND((SUM(O25:Q25)-SUM(T25:U25)),0) -> 8814 | W25: =(((AN25-AO25)))+0 -> 4140.7576 | X25: 0 | Y25: =IFERROR(VLOOKUP(D25,'Monthly Deduction'!$M$2:$N$640,2,0),0) -> 0 | Z25: 0 | AA25: =IFERROR(VLOOKUP(D25,'Monthly Deduction'!A:B,2,0),0) -> 0 | AB25: =ROUND(IFERROR(V25-SUM(W25:AA25),0),0) -> 4673 | AC25: 0 | AD25: =ROUND(AB25-AC25,0) -> 4673 | AE25: =IF(AC25<>0,"Yes","Release") -> Release | AG25: 0 | AI25: 0 | AK25: 1080.5 | AL25: =COUNTIF(AK25:AK25,"=NA") -> 0 | AN25: =((MIN(IF(A25>0,MAX(N25*2%,1861),0),A25)))+0 -> 4140.7576 | AO25: =SUMIF('MPG Payment '!E:E,'Shayak Income '!D25,'MPG Payment '!AJ:AJ) -> 0 | AP25: =W25 -> 4140.7576 | AQ25: =AO25+AP25 -> 4140.7576 | AS25: =B25-X25 -> 16000
A26: =IFERROR(VLOOKUP(D26,'Monthly Deduction'!$I$3:$J$957,2,0),0) -> 0 | B26: =IFERROR(VLOOKUP(D26,'Monthly Deduction'!$E$3:$F$957,2,0),0) -> 0 | C26: =A26+B26 -> 0 | D26: 10010125 | E26: =VLOOKUP(D26,'MPG Payment '!$E$3:$G$497305,2,0) -> Maida- Ram Kumar | F26: =IFERROR(_xlfn.XLOOKUP(D26,'Monthly Deduction'!$I$3:$I$957,'Monthly Deduction'!$H$3:$H$957),0) -> 0 | G26: =VLOOKUP(D26,'MPG Payment '!$E$3:$G$333666,3,0) -> vlc | H26: =VLOOKUP(D26,'MPG Payment '!$E$3:$H$333666,4,0) -> Indirect | I26: =INDEX('MPG Payment '!$C:$C,MATCH('Shayak Income '!D26,'MPG Payment '!E:E,0)) -> 1001 | J26: =INDEX('MPG Payment '!$D:$D,MATCH('Shayak Income '!D26,'MPG Payment '!E:E,0)) -> Majhaul | K26: Old | L26: 45869 | M26: =SUMIF('MPG Payment '!$E$3:$E$344841,'Shayak Income '!D26,'MPG Payment '!$I$3:$I$344841) -> 1174.6 | N26: =SUMIF('MPG Payment '!$E$3:$E$344841,'Shayak Income '!D26,'MPG Payment '!$J$3:$J$344841) -> 50962.27 | O26: =+M26*0.75 -> 880.95 | P26: =+M26*0.95 -> 1115.87 | Q26: =SUMIF('MPG Payment '!$E$3:$E$344841,'Shayak Income '!D26,'MPG Payment '!$S$3:$S$344841) -> 0 | R26: =+N26*3% -> 1528.8681 | S26: =R26-P26 -> 412.9981 | T26: =M26*0.1 -> 117.46 | U26: =((((((IF(K26="New",0,SUMIF('MPG Payment '!$E$3:$E$344841,'Shayak Income '!D26,'MPG Payment '!$AC$3:$AC$344841))))+0)+0)+0)+0)+0 -> 1330.1852 | V26: =ROUND((SUM(O26:Q26)-SUM(T26:U26)),0) -> 549 | W26: =(((AN26-AO26)))+0 -> 0 | X26: =((MIN(IF(B26>0,MAX(N26*2%),0),B26)))+0 -> 0 | Y26: =IFERROR(VLOOKUP(D26,'Monthly Deduction'!$M$2:$N$640,2,0),0) -> 0 | Z26: 0 | AA26: =IFERROR(VLOOKUP(D26,'Monthly Deduction'!A:B,2,0),0) -> 0 | AB26: =ROUND(IFERROR(V26-SUM(W26:AA26),0),0) -> 549 | AC26: 0 | AD26: =ROUND(AB26-AC26,0) -> 549 | AE26: =IF(AC26<>0,"Yes","Release") -> Release | AG26: 0 | AI26: 0 | AK26: 317.6 | AL26: =COUNTIF(AK26:AK26,"=NA") -> 0 | AN26: =((MIN(IF(A26>0,MAX(N26*2%,1861),0),A26)))+0 -> 0 | AO26: =SUMIF('MPG Payment '!E:E,'Shayak Income '!D26,'MPG Payment '!AJ:AJ) -> 0 | AP26: =W26 -> 0 | AQ26: =AO26+AP26 -> 0 | AS26: =B26-X26 -> 0
A27: =IFERROR(VLOOKUP(D27,'Monthly Deduction'!$I$3:$J$957,2,0),0) -> 41865.425 | B27: =IFERROR(VLOOKUP(D27,'Monthly Deduction'!$E$3:$F$957,2,0),0) -> 16000 | C27: =A27+B27 -> 57865.425 | D27: 10010128 | E27: =VLOOKUP(D27,'MPG Payment '!$E$3:$G$497305,2,0) -> Gomukh Aure Bikrampur | F27: =IFERROR(_xlfn.XLOOKUP(D27,'Monthly Deduction'!$I$3:$I$957,'Monthly Deduction'!$H$3:$H$957),0) -> 0 | G27: =VLOOKUP(D27,'MPG Payment '!$E$3:$G$333666,3,0) -> MPG | H27: =VLOOKUP(D27,'MPG Payment '!$E$3:$H$333666,4,0) -> Direct | I27: =INDEX('MPG Payment '!$C:$C,MATCH('Shayak Income '!D27,'MPG Payment '!E:E,0)) -> 1001 | J27: =INDEX('MPG Payment '!$D:$D,MATCH('Shayak Income '!D27,'MPG Payment '!E:E,0)) -> Majhaul | K27: Old | L27: 45869 | M27: =SUMIF('MPG Payment '!$E$3:$E$344841,'Shayak Income '!D27,'MPG Payment '!$I$3:$I$344841) -> 3903.4 | N27: =SUMIF('MPG Payment '!$E$3:$E$344841,'Shayak Income '!D27,'MPG Payment '!$J$3:$J$344841) -> 167166.49 | O27: =+M27*0.75 -> 2927.55 | P27: =+M27*0.95 -> 3708.23 | Q27: =SUMIF('MPG Payment '!$E$3:$E$344841,'Shayak Income '!D27,'MPG Payment '!$S$3:$S$344841) -> 0 | R27: =+N27*3% -> 5014.9947 | S27: =R27-P27 -> 1306.7647 | T27: =M27*0.1 -> 390.34 | U27: =((((((IF(K27="New",0,SUMIF('MPG Payment '!$E$3:$E$344841,'Shayak Income '!D27,'MPG Payment '!$AC$3:$AC$344841))))+0)+0)+0)+0)+0 -> 0 | V27: =ROUND((SUM(O27:Q27)-SUM(T27:U27)),0) -> 6245 | W27: =(((AN27-AO27)))+0 -> 3343.3298 | X27: 0 | Y27: =IFERROR(VLOOKUP(D27,'Monthly Deduction'!$M$2:$N$640,2,0),0) -> 0 | Z27: 0 | AA27: =IFERROR(VLOOKUP(D27,'Monthly Deduction'!A:B,2,0),0) -> 0 | AB27: =ROUND(IFERROR(V27-SUM(W27:AA27),0),0) -> 2902 | AC27: 0 | AD27: =ROUND(AB27-AC27,0) -> 2902 | AE27: =IF(AC27<>0,"Yes","Release") -> Release | AG27: 0 | AI27: 0 | AK27: 1227.4 | AL27: =COUNTIF(AK27:AK27,"=NA") -> 0 | AN27: =((MIN(IF(A27>0,MAX(N27*2%,1861),0),A27)))+0 -> 3343.3298 | AO27: =SUMIF('MPG Payment '!E:E,'Shayak Income '!D27,'MPG Payment '!AJ:AJ) -> 0 | AP27: =W27 -> 3343.3298 | AQ27: =AO27+AP27 -> 3343.3298 | AS27: =B27-X27 -> 16000
A28: =IFERROR(VLOOKUP(D28,'Monthly Deduction'!$I$3:$J$957,2,0),0) -> 0 | B28: =IFERROR(VLOOKUP(D28,'Monthly Deduction'!$E$3:$F$957,2,0),0) -> 0 | C28: =A28+B28 -> 0 | D28: 10010129 | E28: =VLOOKUP(D28,'MPG Payment '!$E$3:$G$497305,2,0) -> Manjhaul- Gulshan Kumar | F28: =IFERROR(_xlfn.XLOOKUP(D28,'Monthly Deduction'!$I$3:$I$957,'Monthly Deduction'!$H$3:$H$957),0) -> 0 | G28: =VLOOKUP(D28,'MPG Payment '!$E$3:$G$333666,3,0) -> vlc | H28: =VLOOKUP(D28,'MPG Payment '!$E$3:$H$333666,4,0) -> Indirect | I28: =INDEX('MPG Payment '!$C:$C,MATCH('Shayak Income '!D28,'MPG Payment '!E:E,0)) -> 1001 | J28: =INDEX('MPG Payment '!$D:$D,MATCH('Shayak Income '!D28,'MPG Payment '!E:E,0)) -> Majhaul | K28: Old | L28: 45869 | M28: =SUMIF('MPG Payment '!$E$3:$E$344841,'Shayak Income '!D28,'MPG Payment '!$I$3:$I$344841) -> 3307.2 | N28: =SUMIF('MPG Payment '!$E$3:$E$344841,'Shayak Income '!D28,'MPG Payment '!$J$3:$J$344841) -> 139788.44 | O28: =+M28*0.75 -> 2480.4 | P28: =+M28*0.95 -> 3141.84 | Q28: =SUMIF('MPG Payment '!$E$3:$E$344841,'Shayak Income '!D28,'MPG Payment '!$S$3:$S$344841) -> 0 | R28: =+N28*3% -> 4193.6532 | S28: =R28-P28 -> 1051.8132 | T28: =M28*0.1 -> 330.72 | U28: =((((((IF(K28="New",0,SUMIF('MPG Payment '!$E$3:$E$344841,'Shayak Income '!D28,'MPG Payment '!$AC$3:$AC$344841))))+0)+0)+0)+0)+0 -> 249.15465 | V28: =ROUND((SUM(O28:Q28)-SUM(T28:U28)),0) -> 5042 | W28: =(((AN28-AO28)))+0 -> 0 | X28: =((MIN(IF(B28>0,MAX(N28*2%),0),B28)))+0 -> 0 | Y28: =IFERROR(VLOOKUP(D28,'Monthly Deduction'!$M$2:$N$640,2,0),0) -> 0 | Z28: 0 | AA28: =IFERROR(VLOOKUP(D28,'Monthly Deduction'!A:B,2,0),0) -> 0 | AB28: =ROUND(IFERROR(V28-SUM(W28:AA28),0),0) -> 5042 | AC28: 0 | AD28: =ROUND(AB28-AC28,0) -> 5042 | AE28: =IF(AC28<>0,"Yes","Release") -> Release | AG28: 0 | AI28: 0 | AK28: 452.7 | AL28: =COUNTIF(AK28:AK28,"=NA") -> 0 | AN28: =((MIN(IF(A28>0,MAX(N28*2%,1861),0),A28)))+0 -> 0 | AO28: =SUMIF('MPG Payment '!E:E,'Shayak Income '!D28,'MPG Payment '!AJ:AJ) -> 0 | AP28: =W28 -> 0 | AQ28: =AO28+AP28 -> 0 | AS28: =B28-X28 -> 0
A29: =IFERROR(VLOOKUP(D29,'Monthly Deduction'!$I$3:$J$957,2,0),0) -> 0 | B29: =IFERROR(VLOOKUP(D29,'Monthly Deduction'!$E$3:$F$957,2,0),0) -> 0 | C29: =A29+B29 -> 0 | D29: 10010130 | E29: =VLOOKUP(D29,'MPG Payment '!$E$3:$G$497305,2,0) -> Khaira Manjhaul | F29: =IFERROR(_xlfn.XLOOKUP(D29,'Monthly Deduction'!$I$3:$I$957,'Monthly Deduction'!$H$3:$H$957),0) -> 0 | G29: =VLOOKUP(D29,'MPG Payment '!$E$3:$G$333666,3,0) -> vlc | H29: =VLOOKUP(D29,'MPG Payment '!$E$3:$H$333666,4,0) -> Indirect | I29: =INDEX('MPG Payment '!$C:$C,MATCH('Shayak Income '!D29,'MPG Payment '!E:E,0)) -> 1001 | J29: =INDEX('MPG Payment '!$D:$D,MATCH('Shayak Income '!D29,'MPG Payment '!E:E,0)) -> Majhaul | K29: Old | L29: 45870 | M29: =SUMIF('MPG Payment '!$E$3:$E$344841,'Shayak Income '!D29,'MPG Payment '!$I$3:$I$344841) -> 1785 | N29: =SUMIF('MPG Payment '!$E$3:$E$344841,'Shayak Income '!D29,'MPG Payment '!$J$3:$J$344841) -> 65862.27 | O29: =+M29*0.75 -> 1338.75 | P29: =+M29*0.95 -> 1695.75 | Q29: =SUMIF('MPG Payment '!$E$3:$E$344841,'Shayak Income '!D29,'MPG Payment '!$S$3:$S$344841) -> 0 | R29: =+N29*3% -> 1975.8681 | S29: =R29-P29 -> 280.1181 | T29: =M29*0.1 -> 178.5 | U29: =((((((IF(K29="New",0,SUMIF('MPG Payment '!$E$3:$E$344841,'Shayak Income '!D29,'MPG Payment '!$AC$3:$AC$344841))))+0)+0)+0)+0)+0 -> 745.7534 | V29: =ROUND((SUM(O29:Q29)-SUM(T29:U29)),0) -> 2110 | W29: =(((AN29-AO29)))+0 -> 0 | X29: =((MIN(IF(B29>0,MAX(N29*2%),0),B29)))+0 -> 0 | Y29: =IFERROR(VLOOKUP(D29,'Monthly Deduction'!$M$2:$N$640,2,0),0) -> 0 | Z29: 0 | AA29: =IFERROR(VLOOKUP(D29,'Monthly Deduction'!A:B,2,0),0) -> 0 | AB29: =ROUND(IFERROR(V29-SUM(W29:AA29),0),0) -> 2110 | AC29: 0 | AD29: =ROUND(AB29-AC29,0) -> 2110 | AE29: =IF(AC29<>0,"Yes","Release") -> Release | AG29: 0 | AI29: 0 | AK29: 345.1 | AL29: =COUNTIF(AK29:AK29,"=NA") -> 0 | AN29: =((MIN(IF(A29>0,MAX(N29*2%,1861),0),A29)))+0 -> 0 | AO29: =SUMIF('MPG Payment '!E:E,'Shayak Income '!D29,'MPG Payment '!AJ:AJ) -> 0 | AP29: =W29 -> 0 | AQ29: =AO29+AP29 -> 0 | AS29: =B29-X29 -> 0
A30: =IFERROR(VLOOKUP(D30,'Monthly Deduction'!$I$3:$J$957,2,0),0) -> 0 | B30: =IFERROR(VLOOKUP(D30,'Monthly Deduction'!$E$3:$F$957,2,0),0) -> 0 | C30: =A30+B30 -> 0 | D30: 10010131 | E30: =VLOOKUP(D30,'MPG Payment '!$E$3:$G$497305,2,0) -> Mehda Shahpur | F30: =IFERROR(_xlfn.XLOOKUP(D30,'Monthly Deduction'!$I$3:$I$957,'Monthly Deduction'!$H$3:$H$957),0) -> 0 | G30: =VLOOKUP(D30,'MPG Payment '!$E$3:$G$333666,3,0) -> vlc | H30: =VLOOKUP(D30,'MPG Payment '!$E$3:$H$333666,4,0) -> Indirect | I30: =INDEX('MPG Payment '!$C:$C,MATCH('Shayak Income '!D30,'MPG Payment '!E:E,0)) -> 1001 | J30: =INDEX('MPG Payment '!$D:$D,MATCH('Shayak Income '!D30,'MPG Payment '!E:E,0)) -> Majhaul | K30: Old | L30: 45870 | M30: =SUMIF('MPG Payment '!$E$3:$E$344841,'Shayak Income '!D30,'MPG Payment '!$I$3:$I$344841) -> 2838.8 | N30: =SUMIF('MPG Payment '!$E$3:$E$344841,'Shayak Income '!D30,'MPG Payment '!$J$3:$J$344841) -> 107591.78 | O30: =+M30*0.75 -> 2129.1 | P30: =+M30*0.95 -> 2696.86 | Q30: =SUMIF('MPG Payment '!$E$3:$E$344841,'Shayak Income '!D30,'MPG Payment '!$S$3:$S$344841) -> 0 | R30: =+N30*3% -> 3227.7534 | S30: =R30-P30 -> 530.8934 | T30: =M30*0.1 -> 283.88 | U30: =((((((IF(K30="New",0,SUMIF('MPG Payment '!$E$3:$E$344841,'Shayak Income '!D30,'MPG Payment '!$AC$3:$AC$344841))))+0)+0)+0)+0)+0 -> 215.66983 | V30: =ROUND((SUM(O30:Q30)-SUM(T30:U30)),0) -> 4326 | W30: =(((AN30-AO30)))+0 -> 0 | X30: =((MIN(IF(B30>0,MAX(N30*2%),0),B30)))+0 -> 0 | Y30: =IFERROR(VLOOKUP(D30,'Monthly Deduction'!$M$2:$N$640,2,0),0) -> 0 | Z30: 0 | AA30: =IFERROR(VLOOKUP(D30,'Monthly Deduction'!A:B,2,0),0) -> 0 | AB30: =ROUND(IFERROR(V30-SUM(W30:AA30),0),0) -> 4326 | AC30: 0 | AD30: =ROUND(AB30-AC30,0) -> 4326 | AE30: =IF(AC30<>0,"Yes","Release") -> Release | AG30: 0 | AI30: 0 | AK30: 324.6 | AL30: =COUNTIF(AK30:AK30,"=NA") -> 0 | AN30: =((MIN(IF(A30>0,MAX(N30*2%,1861),0),A30)))+0 -> 0 | AO30: =SUMIF('MPG Payment '!E:E,'Shayak Income '!D30,'MPG Payment '!AJ:AJ) -> 0 | AP30: =W30 -> 0 | AQ30: =AO30+AP30 -> 0 | AS30: =B30-X30 -> 0
A31: =IFERROR(VLOOKUP(D31,'Monthly Deduction'!$I$3:$J$957,2,0),0) -> 0 | B31: =IFERROR(VLOOKUP(D31,'Monthly Deduction'!$E$3:$F$957,2,0),0) -> 0 | C31: =A31+B31 -> 0 | D31: 10020002 | E31: =VLOOKUP(D31,'MPG Payment '!$E$3:$G$497305,2,0) -> PIPARIYA DIH -2 | F31: =IFERROR(_xlfn.XLOOKUP(D31,'Monthly Deduction'!$I$3:$I$957,'Monthly Deduction'!$H$3:$H$957),0) -> 0 | G31: =VLOOKUP(D31,'MPG Payment '!$E$3:$G$333666,3,0) -> MPG | H31: =VLOOKUP(D31,'MPG Payment '!$E$3:$H$333666,4,0) -> Direct | I31: =INDEX('MPG Payment '!$C:$C,MATCH('Shayak Income '!D31,'MPG Payment '!E:E,0)) -> 1002 | J31: =INDEX('MPG Payment '!$D:$D,MATCH('Shayak Income '!D31,'MPG Payment '!E:E,0)) -> Laldiyara | K31: Old | L31: 42979 | M31: =SUMIF('MPG Payment '!$E$3:$E$344841,'Shayak Income '!D31,'MPG Payment '!$I$3:$I$344841) -> 9646.5 | N31: =SUMIF('MPG Payment '!$E$3:$E$344841,'Shayak Income '!D31,'MPG Payment '!$J$3:$J$344841) -> 445239.29 | O31: =+M31*0.75 -> 7234.875 | P31: =+M31*0.95 -> 9164.175 | Q31: =SUMIF('MPG Payment '!$E$3:$E$344841,'Shayak Income '!D31,'MPG Payment '!$S$3:$S$344841) -> 4046.71 | R31: =+N31*3% -> 13357.179 | S31: =R31-P31 -> 4193.0037 | T31: =M31*0.1 -> 964.65 | U31: =((((((IF(K31="New",0,SUMIF('MPG Payment '!$E$3:$E$344841,'Shayak Income '!D31,'MPG Payment '!$AC$3:$AC$344841))))+0)+0)+0)+0)+0 -> 0 | V31: =ROUND((SUM(O31:Q31)-SUM(T31:U31)),0) -> 19481 | W31: =(((AN31-AO31)))+0 -> 0 | X31: =((MIN(IF(B31>0,MAX(N31*2%),0),B31)))+0 -> 0 | Y31: =IFERROR(VLOOKUP(D31,'Monthly Deduction'!$M$2:$N$640,2,0),0) -> 0 | Z31: 0 | AA31: =IFERROR(VLOOKUP(D31,'Monthly Deduction'!A:B,2,0),0) -> 0 | AB31: =ROUND(IFERROR(V31-SUM(W31:AA31),0),0) -> 19481 | AC31: 0 | AD31: =ROUND(AB31-AC31,0) -> 19481 | AE31: =IF(AC31<>0,"Yes","Release") -> Release | AG31: 0 | AI31: 0 | AK31: 2652.1 | AL31: =COUNTIF(AK31:AK31,"=NA") -> 0 | AN31: =((MIN(IF(A31>0,MAX(N31*2%,1861),0),A31)))+0 -> 0 | AO31: =SUMIF('MPG Payment '!E:E,'Shayak Income '!D31,'MPG Payment '!AJ:AJ) -> 0 | AP31: =W31 -> 0 | AQ31: =AO31+AP31 -> 0 | AS31: =B31-X31 -> 0
A32: =IFERROR(VLOOKUP(D32,'Monthly Deduction'!$I$3:$J$957,2,0),0) -> 0 | B32: =IFERROR(VLOOKUP(D32,'Monthly Deduction'!$E$3:$F$957,2,0),0) -> 0 | C32: =A32+B32 -> 0 | D32: 10020004 | E32: =VLOOKUP(D32,'MPG Payment '!$E$3:$G$497305,2,0) -> LAL DIYARA -1 | F32: =IFERROR(_xlfn.XLOOKUP(D32,'Monthly Deduction'!$I$3:$I$957,'Monthly Deduction'!$H$3:$H$957),0) -> 0 | G32: =VLOOKUP(D32,'MPG Payment '!$E$3:$G$333666,3,0) -> MPG | H32: =VLOOKUP(D32,'MPG Payment '!$E$3:$H$333666,4,0) -> Direct | I32: =INDEX('MPG Payment '!$C:$C,MATCH('Shayak Income '!D32,'MPG Payment '!E:E,0)) -> 1002 | J32: =INDEX('MPG Payment '!$D:$D,MATCH('Shayak Income '!D32,'MPG Payment '!E:E,0)) -> Laldiyara | K32: Old | L32: 42979 | M32: =SUMIF('MPG Payment '!$E$3:$E$344841,'Shayak Income '!D32,'MPG Payment '!$I$3:$I$344841) -> 2196.6 | N32: =SUMIF('MPG Payment '!$E$3:$E$344841,'Shayak Income '!D32,'MPG Payment '!$J$3:$J$344841) -> 88368.15 | O32: =+M32*0.75 -> 1647.45 | P32: =+M32*0.95 -> 2086.77 | Q32: =SUMIF('MPG Payment '!$E$3:$E$344841,'Shayak Income '!D32,'MPG Payment '!$S$3:$S$344841) -> 0 | R32: =+N32*3% -> 2651.0445 | S32: =R32-P32 -> 564.2745 | T32: =M32*0.1 -> 219.66 | U32: =((((((IF(K32="New",0,SUMIF('MPG Payment '!$E$3:$E$344841,'Shayak Income '!D32,'MPG Payment '!$AC$3:$AC$344841))))+0)+0)+0)+0)+0 -> 485.14124 | V32: =ROUND((SUM(O32:Q32)-SUM(T32:U32)),0) -> 3029 | W32: =(((AN32-AO32)))+0 -> 0 | X32: =((MIN(IF(B32>0,MAX(N32*2%),0),B32)))+0 -> 0 | Y32: =IFERROR(VLOOKUP(D32,'Monthly Deduction'!$M$2:$N$640,2,0),0) -> 0 | Z32: 0 | AA32: =IFERROR(VLOOKUP(D32,'Monthly Deduction'!A:B,2,0),0) -> 0 | AB32: =ROUND(IFERROR(V32-SUM(W32:AA32),0),0) -> 3029 | AC32: 0 | AD32: =ROUND(AB32-AC32,0) -> 3029 | AE32: =IF(AC32<>0,"Yes","Release") -> Release | AG32: 0 | AI32: 0 | AK32: 488.9 | AL32: =COUNTIF(AK32:AK32,"=NA") -> 0 | AN32: =((MIN(IF(A32>0,MAX(N32*2%,1861),0),A32)))+0 -> 0 | AO32: =SUMIF('MPG Payment '!E:E,'Shayak Income '!D32,'MPG Payment '!AJ:AJ) -> 0 | AP32: =W32 -> 0 | AQ32: =AO32+AP32 -> 0 | AS32: =B32-X32 -> 0
A33: =IFERROR(VLOOKUP(D33,'Monthly Deduction'!$I$3:$J$957,2,0),0) -> 0 | B33: =IFERROR(VLOOKUP(D33,'Monthly Deduction'!$E$3:$F$957,2,0),0) -> 0 | C33: =A33+B33 -> 0 | D33: 10020006 | E33: =VLOOKUP(D33,'MPG Payment '!$E$3:$G$497305,2,0) -> GANGA KINARE KHUTHA | F33: =IFERROR(_xlfn.XLOOKUP(D33,'Monthly Deduction'!$I$3:$I$957,'Monthly Deduction'!$H$3:$H$957),0) -> 0 | G33: =VLOOKUP(D33,'MPG Payment '!$E$3:$G$333666,3,0) -> vlc | H33: =VLOOKUP(D33,'MPG Payment '!$E$3:$H$333666,4,0) -> Indirect | I33: =INDEX('MPG Payment '!$C:$C,MATCH('Shayak Income '!D33,'MPG Payment '!E:E,0)) -> 1002 | J33: =INDEX('MPG Payment '!$D:$D,MATCH('Shayak Income '!D33,'MPG Payment '!E:E,0)) -> Laldiyara | K33: Old | L33: 42979 | M33: =SUMIF('MPG Payment '!$E$3:$E$344841,'Shayak Income '!D33,'MPG Payment '!$I$3:$I$344841) -> 684.6 | N33: =SUMIF('MPG Payment '!$E$3:$E$344841,'Shayak Income '!D33,'MPG Payment '!$J$3:$J$344841) -> 26992.8 | O33: =+M33*0.75 -> 513.45 | P33: =+M33*0.95 -> 650.37 | Q33: =SUMIF('MPG Payment '!$E$3:$E$344841,'Shayak Income '!D33,'MPG Payment '!$S$3:$S$344841) -> 0 | R33: =+N33*3% -> 809.784 | S33: =R33-P33 -> 159.414 | T33: =M33*0.1 -> 68.46 | U33: =((((((IF(K33="New",0,SUMIF('MPG Payment '!$E$3:$E$344841,'Shayak Income '!D33,'MPG Payment '!$AC$3:$AC$344841))))+0)+0)+0)+0)+-571 -> 1095.2297 | V33: =ROUND((SUM(O33:Q33)-SUM(T33:U33)),0) -> 0 | W33: 0 | X33: 0 | Y33: 0 | Z33: 0 | AA33: 0 | AB33: =ROUND(IFERROR(V33-SUM(W33:AA33),0),0) -> 0 | AC33: 0 | AD33: =ROUND(AB33-AC33,0) -> 0 | AE33: =IF(AC33<>0,"Yes","Release") -> Release | AG33: 0 | AI33: 0 | AK33: 134.6 | AL33: =COUNTIF(AK33:AK33,"=NA") -> 0 | AN33: =((MIN(IF(A33>0,MAX(N33*2%,1861),0),A33)))+0 -> 0 | AO33: =SUMIF('MPG Payment '!E:E,'Shayak Income '!D33,'MPG Payment '!AJ:AJ) -> 0 | AP33: =W33 -> 0 | AQ33: =AO33+AP33 -> 0 | AS33: =B33-X33 -> 0
A34: =IFERROR(VLOOKUP(D34,'Monthly Deduction'!$I$3:$J$957,2,0),0) -> 0 | B34: =IFERROR(VLOOKUP(D34,'Monthly Deduction'!$E$3:$F$957,2,0),0) -> 0 | C34: =A34+B34 -> 0 | D34: 10020007 | E34: =VLOOKUP(D34,'MPG Payment '!$E$3:$G$497305,2,0) -> Gomukh ID Khutaha Ganga | F34: =IFERROR(_xlfn.XLOOKUP(D34,'Monthly Deduction'!$I$3:$I$957,'Monthly Deduction'!$H$3:$H$957),0) -> 0 | G34: =VLOOKUP(D34,'MPG Payment '!$E$3:$G$333666,3,0) -> vlc | H34: =VLOOKUP(D34,'MPG Payment '!$E$3:$H$333666,4,0) -> Indirect | I34: =INDEX('MPG Payment '!$C:$C,MATCH('Shayak Income '!D34,'MPG Payment '!E:E,0)) -> 1002 | J34: =INDEX('MPG Payment '!$D:$D,MATCH('Shayak Income '!D34,'MPG Payment '!E:E,0)) -> Laldiyara | K34: Old | L34: 42979 | M34: =SUMIF('MPG Payment '!$E$3:$E$344841,'Shayak Income '!D34,'MPG Payment '!$I$3:$I$344841) -> 941.8 | N34: =SUMIF('MPG Payment '!$E$3:$E$344841,'Shayak Income '!D34,'MPG Payment '!$J$3:$J$344841) -> 38313.51 | O34: =+M34*0.75 -> 706.35 | P34: =+M34*0.95 -> 894.71 | Q34: =SUMIF('MPG Payment '!$E$3:$E$344841,'Shayak Income '!D34,'MPG Payment '!$S$3:$S$344841) -> 0 | R34: =+N34*3% -> 1149.4053 | S34: =R34-P34 -> 254.6953 | T34: =M34*0.1 -> 94.18 | U34: =((((((IF(K34="New",0,SUMIF('MPG Payment '!$E$3:$E$344841,'Shayak Income '!D34,'MPG Payment '!$AC$3:$AC$344841))))+0)+0)+0)+0)+0 -> 1437.851 | V34: =ROUND((SUM(O34:Q34)-SUM(T34:U34)),0) -> 69 | W34: =(((AN34-AO34)))+0 -> 0 | X34: =((MIN(IF(B34>0,MAX(N34*2%),0),B34)))+0 -> 0 | Y34: =IFERROR(VLOOKUP(D34,'Monthly Deduction'!$M$2:$N$640,2,0),0) -> 0 | Z34: 0 | AA34: =IFERROR(VLOOKUP(D34,'Monthly Deduction'!A:B,2,0),0) -> 0 | AB34: =ROUND(IFERROR(V34-SUM(W34:AA34),0),0) -> 69 | AC34: 0 | AD34: =ROUND(AB34-AC34,0) -> 69 | AE34: =IF(AC34<>0,"Yes","Release") -> Release | AG34: 0 | AI34: 0 | AK34: 79.7 | AL34: =COUNTIF(AK34:AK34,"=NA") -> 0 | AN34: =((MIN(IF(A34>0,MAX(N34*2%,1861),0),A34)))+0 -> 0 | AO34: =SUMIF('MPG Payment '!E:E,'Shayak Income '!D34,'MPG Payment '!AJ:AJ) -> 0 | AP34: =W34 -> 0 | AQ34: =AO34+AP34 -> 0 | AS34: =B34-X34 -> 0
A35: =IFERROR(VLOOKUP(D35,'Monthly Deduction'!$I$3:$J$957,2,0),0) -> 0 | B35: =IFERROR(VLOOKUP(D35,'Monthly Deduction'!$E$3:$F$957,2,0),0) -> 0 | C35: =A35+B35 -> 0 | D35: 10020008 | E35: =VLOOKUP(D35,'MPG Payment '!$E$3:$G$497305,2,0) -> Gomukh ID Khutaha Dhih | F35: =IFERROR(_xlfn.XLOOKUP(D35,'Monthly Deduction'!$I$3:$I$957,'Monthly Deduction'!$H$3:$H$957),0) -> 0 | G35: =VLOOKUP(D35,'MPG Payment '!$E$3:$G$333666,3,0) -> vlc | H35: =VLOOKUP(D35,'MPG Payment '!$E$3:$H$333666,4,0) -> Indirect | I35: =INDEX('MPG Payment '!$C:$C,MATCH('Shayak Income '!D35,'MPG Payment '!E:E,0)) -> 1002 | J35: =INDEX('MPG Payment '!$D:$D,MATCH('Shayak Income '!D35,'MPG Payment '!E:E,0)) -> Laldiyara | K35: Old | L35: 44161 | M35: =SUMIF('MPG Payment '!$E$3:$E$344841,'Shayak Income '!D35,'MPG Payment '!$I$3:$I$344841) -> 5635.1 | N35: =SUMIF('MPG Payment '!$E$3:$E$344841,'Shayak Income '!D35,'MPG Payment '!$J$3:$J$344841) -> 234286.88 | O35: =+M35*0.75 -> 4226.325 | P35: =+M35*0.95 -> 5353.345 | Q35: =SUMIF('MPG Payment '!$E$3:$E$344841,'Shayak Income '!D35,'MPG Payment '!$S$3:$S$344841) -> 0 | R35: =+N35*3% -> 7028.6064 | S35: =R35-P35 -> 1675.2614 | T35: =M35*0.1 -> 563.51 | U35: =((((((IF(K35="New",0,SUMIF('MPG Payment '!$E$3:$E$344841,'Shayak Income '!D35,'MPG Payment '!$AC$3:$AC$344841))))+0)+0)+0)+0)+0 -> 0 | V35: =ROUND((SUM(O35:Q35)-SUM(T35:U35)),0) -> 9016 | W35: =(((AN35-AO35)))+0 -> 0 | X35: =((MIN(IF(B35>0,MAX(N35*2%),0),B35)))+0 -> 0 | Y35: =IFERROR(VLOOKUP(D35,'Monthly Deduction'!$M$2:$N$640,2,0),0) -> 0 | Z35: 0 | AA35: =IFERROR(VLOOKUP(D35,'Monthly Deduction'!A:B,2,0),0) -> 0 | AB35: =ROUND(IFERROR(V35-SUM(W35:AA35),0),0) -> 9016 | AC35: 0 | AD35: =ROUND(AB35-AC35,0) -> 9016 | AE35: =IF(AC35<>0,"Yes","Release") -> Release | AG35: 0 | AI35: 0 | AK35: 1070.1 | AL35: =COUNTIF(AK35:AK35,"=NA") -> 0 | AN35: =((MIN(IF(A35>0,MAX(N35*2%,1861),0),A35)))+0 -> 0 | AO35: =SUMIF('MPG Payment '!E:E,'Shayak Income '!D35,'MPG Payment '!AJ:AJ) -> 0 | AP35: =W35 -> 0 | AQ35: =AO35+AP35 -> 0 | AS35: =B35-X35 -> 0
A36: =IFERROR(VLOOKUP(D36,'Monthly Deduction'!$I$3:$J$957,2,0),0) -> 0 | B36: =IFERROR(VLOOKUP(D36,'Monthly Deduction'!$E$3:$F$957,2,0),0) -> 0 | C36: =A36+B36 -> 0 | D36: 10020015 | E36: =VLOOKUP(D36,'MPG Payment '!$E$3:$G$497305,2,0) -> GOMUKH LALDIYARA TIRASHI | F36: =IFERROR(_xlfn.XLOOKUP(D36,'Monthly Deduction'!$I$3:$I$957,'Monthly Deduction'!$H$3:$H$957),0) -> 0 | G36: =VLOOKUP(D36,'MPG Payment '!$E$3:$G$333666,3,0) -> vlc | H36: =VLOOKUP(D36,'MPG Payment '!$E$3:$H$333666,4,0) -> Indirect | I36: =INDEX('MPG Payment '!$C:$C,MATCH('Shayak Income '!D36,'MPG Payment '!E:E,0)) -> 1002 | J36: =INDEX('MPG Payment '!$D:$D,MATCH('Shayak Income '!D36,'MPG Payment '!E:E,0)) -> Laldiyara | K36: Old | L36: 44652 | M36: =SUMIF('MPG Payment '!$E$3:$E$344841,'Shayak Income '!D36,'MPG Payment '!$I$3:$I$344841) -> 115041.1 | N36: =SUMIF('MPG Payment '!$E$3:$E$344841,'Shayak Income '!D36,'MPG Payment '!$J$3:$J$344841) -> 4623990.1 | O36: =+M36*0.75 -> 86280.825 | P36: =+M36*0.95 -> 109289.04 | Q36: =SUMIF('MPG Payment '!$E$3:$E$344841,'Shayak Income '!D36,'MPG Payment '!$S$3:$S$344841) -> 0 | R36: =+N36*3% -> 138719.7 | S36: =R36-P36 -> 29430.659 | T36: =M36*0.1 -> 11504.11 | U36: =((((((IF(K36="New",0,SUMIF('MPG Payment '!$E$3:$E$344841,'Shayak Income '!D36,'MPG Payment '!$AC$3:$AC$344841))))+0)+0)+0)+0)+0 -> 0 | V36: =ROUND((SUM(O36:Q36)-SUM(T36:U36)),0) -> 184066 | W36: =(((AN36-AO36)))+0 -> 0 | X36: =((MIN(IF(B36>0,MAX(N36*2%),0),B36)))+0 -> 0 | Y36: =IFERROR(VLOOKUP(D36,'Monthly Deduction'!$M$2:$N$640,2,0),0) -> 0 | Z36: 0 | AA36: =IFERROR(VLOOKUP(D36,'Monthly Deduction'!A:B,2,0),0) -> 0 | AB36: =ROUND(IFERROR(V36-SUM(W36:AA36),0),0) -> 184066 | AC36: 0 | AD36: =ROUND(AB36-AC36,0) -> 184066 | AE36: =IF(AC36<>0,"Yes","Release") -> Release | AG36: 0 | AI36: 0 | AK36: 28315.1 | AL36: =COUNTIF(AK36:AK36,"=NA") -> 0 | AN36: =((MIN(IF(A36>0,MAX(N36*2%,1861),0),A36)))+0 -> 0 | AO36: =SUMIF('MPG Payment '!E:E,'Shayak Income '!D36,'MPG Payment '!AJ:AJ) -> 0 | AP36: =W36 -> 0 | AQ36: =AO36+AP36 -> 0 | AS36: =B36-X36 -> 0
A37: =IFERROR(VLOOKUP(D37,'Monthly Deduction'!$I$3:$J$957,2,0),0) -> 0 | B37: =IFERROR(VLOOKUP(D37,'Monthly Deduction'!$E$3:$F$957,2,0),0) -> 0 | C37: =A37+B37 -> 0 | D37: 10020016 | E37: =VLOOKUP(D37,'MPG Payment '!$E$3:$G$497305,2,0) -> GOMUKH LALDIYARA PURBI | F37: =IFERROR(_xlfn.XLOOKUP(D37,'Monthly Deduction'!$I$3:$I$957,'Monthly Deduction'!$H$3:$H$957),0) -> 0 | G37: =VLOOKUP(D37,'MPG Payment '!$E$3:$G$333666,3,0) -> vlc | H37: =VLOOKUP(D37,'MPG Payment '!$E$3:$H$333666,4,0) -> Indirect | I37: =INDEX('MPG Payment '!$C:$C,MATCH('Shayak Income '!D37,'MPG Payment '!E:E,0)) -> 1002 | J37: =INDEX('MPG Payment '!$D:$D,MATCH('Shayak Income '!D37,'MPG Payment '!E:E,0)) -> Laldiyara | K37: Old | L37: 44652 | M37: =SUMIF('MPG Payment '!$E$3:$E$344841,'Shayak Income '!D37,'MPG Payment '!$I$3:$I$344841) -> 115487.5 | N37: =SUMIF('MPG Payment '!$E$3:$E$344841,'Shayak Income '!D37,'MPG Payment '!$J$3:$J$344841) -> 4641678.7 | O37: =+M37*0.75 -> 86615.625 | P37: =+M37*0.95 -> 109713.13 | Q37: =SUMIF('MPG Payment '!$E$3:$E$344841,'Shayak Income '!D37,'MPG Payment '!$S$3:$S$344841) -> 0 | R37: =+N37*3% -> 139250.36 | S37: =R37-P37 -> 29537.237 | T37: =M37*0.1 -> 11548.75 | U37: =((((((IF(K37="New",0,SUMIF('MPG Payment '!$E$3:$E$344841,'Shayak Income '!D37,'MPG Payment '!$AC$3:$AC$344841))))+0)+0)+0)+0)+0 -> 0 | V37: =ROUND((SUM(O37:Q37)-SUM(T37:U37)),0) -> 184780 | W37: =(((AN37-AO37)))+0 -> 0 | X37: =((MIN(IF(B37>0,MAX(N37*2%),0),B37)))+0 -> 0 | Y37: =IFERROR(VLOOKUP(D37,'Monthly Deduction'!$M$2:$N$640,2,0),0) -> 0 | Z37: 0 | AA37: =IFERROR(VLOOKUP(D37,'Monthly Deduction'!A:B,2,0),0) -> 0 | AB37: =ROUND(IFERROR(V37-SUM(W37:AA37),0),0) -> 184780 | AC37: 0 | AD37: =ROUND(AB37-AC37,0) -> 184780 | AE37: =IF(AC37<>0,"Yes","Release") -> Release | AG37: 0 | AI37: 0 | AK37: 28805.6 | AL37: =COUNTIF(AK37:AK37,"=NA") -> 0 | AN37: =((MIN(IF(A37>0,MAX(N37*2%,1861),0),A37)))+0 -> 0 | AO37: =SUMIF('MPG Payment '!E:E,'Shayak Income '!D37,'MPG Payment '!AJ:AJ) -> 0 | AP37: =W37 -> 0 | AQ37: =AO37+AP37 -> 0 | AS37: =B37-X37 -> 0
A38: =IFERROR(VLOOKUP(D38,'Monthly Deduction'!$I$3:$J$957,2,0),0) -> 0 | B38: =IFERROR(VLOOKUP(D38,'Monthly Deduction'!$E$3:$F$957,2,0),0) -> 0 | C38: =A38+B38 -> 0 | D38: 10020017 | E38: =VLOOKUP(D38,'MPG Payment '!$E$3:$G$497305,2,0) -> GOMUKH RAMCHANDARPUR II | F38: =IFERROR(_xlfn.XLOOKUP(D38,'Monthly Deduction'!$I$3:$I$957,'Monthly Deduction'!$H$3:$H$957),0) -> 0 | G38: =VLOOKUP(D38,'MPG Payment '!$E$3:$G$333666,3,0) -> MPG | H38: =VLOOKUP(D38,'MPG Payment '!$E$3:$H$333666,4,0) -> Direct | I38: =INDEX('MPG Payment '!$C:$C,MATCH('Shayak Income '!D38,'MPG Payment '!E:E,0)) -> 1002 | J38: =INDEX('MPG Payment '!$D:$D,MATCH('Shayak Income '!D38,'MPG Payment '!E:E,0)) -> Laldiyara | K38: Old | L38: 44652 | M38: =SUMIF('MPG Payment '!$E$3:$E$344841,'Shayak Income '!D38,'MPG Payment '!$I$3:$I$344841) -> 14908.4 | N38: =SUMIF('MPG Payment '!$E$3:$E$344841,'Shayak Income '!D38,'MPG Payment '!$J$3:$J$344841) -> 625889.89 | O38: =+M38*0.75 -> 11181.3 | P38: =+M38*0.95 -> 14162.98 | Q38: =SUMIF('MPG Payment '!$E$3:$E$344841,'Shayak Income '!D38,'MPG Payment '!$S$3:$S$344841) -> 5619.79 | R38: =+N38*3% -> 18776.697 | S38: =R38-P38 -> 4613.7167 | T38: =M38*0.1 -> 1490.84 | U38: =((((((IF(K38="New",0,SUMIF('MPG Payment '!$E$3:$E$344841,'Shayak Income '!D38,'MPG Payment '!$AC$3:$AC$344841))))+0)+0)+0)+0)+0 -> 0 | V38: =ROUND((SUM(O38:Q38)-SUM(T38:U38)),0) -> 29473 | W38: =(((AN38-AO38)))+0 -> 0 | X38: =((MIN(IF(B38>0,MAX(N38*2%),0),B38)))+0 -> 0 | Y38: =IFERROR(VLOOKUP(D38,'Monthly Deduction'!$M$2:$N$640,2,0),0) -> 0 | Z38: 0 | AA38: =IFERROR(VLOOKUP(D38,'Monthly Deduction'!A:B,2,0),0) -> 0 | AB38: =ROUND(IFERROR(V38-SUM(W38:AA38),0),0) -> 29473 | AC38: 0 | AD38: =ROUND(AB38-AC38,0) -> 29473 | AE38: =IF(AC38<>0,"Yes","Release") -> Release | AG38: 0 | AI38: 0 | AK38: 3396.4 | AL38: =COUNTIF(AK38:AK38,"=NA") -> 0 | AN38: =((MIN(IF(A38>0,MAX(N38*2%,1861),0),A38)))+0 -> 0 | AO38: =SUMIF('MPG Payment '!E:E,'Shayak Income '!D38,'MPG Payment '!AJ:AJ) -> 0 | AP38: =W38 -> 0 | AQ38: =AO38+AP38 -> 0 | AS38: =B38-X38 -> 0
A39: =IFERROR(VLOOKUP(D39,'Monthly Deduction'!$I$3:$J$957,2,0),0) -> 0 | B39: =IFERROR(VLOOKUP(D39,'Monthly Deduction'!$E$3:$F$957,2,0),0) -> 0 | C39: =A39+B39 -> 0 | D39: 10020021 | E39: =VLOOKUP(D39,'MPG Payment '!$E$3:$G$497305,2,0) -> MOHANPUR | F39: =IFERROR(_xlfn.XLOOKUP(D39,'Monthly Deduction'!$I$3:$I$957,'Monthly Deduction'!$H$3:$H$957),0) -> 0 | G39: =VLOOKUP(D39,'MPG Payment '!$E$3:$G$333666,3,0) -> MPG | H39: =VLOOKUP(D39,'MPG Payment '!$E$3:$H$333666,4,0) -> Direct | I39: =INDEX('MPG Payment '!$C:$C,MATCH('Shayak Income '!D39,'MPG Payment '!E:E,0)) -> 1002 | J39: =INDEX('MPG Payment '!$D:$D,MATCH('Shayak Income '!D39,'MPG Payment '!E:E,0)) -> Laldiyara | K39: Old | L39: 44694 | M39: =SUMIF('MPG Payment '!$E$3:$E$344841,'Shayak Income '!D39,'MPG Payment '!$I$3:$I$344841) -> 15929.8 | N39: =SUMIF('MPG Payment '!$E$3:$E$344841,'Shayak Income '!D39,'MPG Payment '!$J$3:$J$344841) -> 695026.33 | O39: =+M39*0.75 -> 11947.35 | P39: =+M39*0.95 -> 15133.31 | Q39: =SUMIF('MPG Payment '!$E$3:$E$344841,'Shayak Income '!D39,'MPG Payment '!$S$3:$S$344841) -> 6492 | R39: =+N39*3% -> 20850.79 | S39: =R39-P39 -> 5717.4799 | T39: =M39*0.1 -> 1592.98 | U39: =((((((IF(K39="New",0,SUMIF('MPG Payment '!$E$3:$E$344841,'Shayak Income '!D39,'MPG Payment '!$AC$3:$AC$344841))))+0)+0)+0)+0)+0 -> 0 | V39: =ROUND((SUM(O39:Q39)-SUM(T39:U39)),0) -> 31980 | W39: =(((AN39-AO39)))+0 -> 0 | X39: =((MIN(IF(B39>0,MAX(N39*2%),0),B39)))+0 -> 0 | Y39: =IFERROR(VLOOKUP(D39,'Monthly Deduction'!$M$2:$N$640,2,0),0) -> 0 | Z39: 0 | AA39: =IFERROR(VLOOKUP(D39,'Monthly Deduction'!A:B,2,0),0) -> 0 | AB39: =ROUND(IFERROR(V39-SUM(W39:AA39),0),0) -> 31980 | AC39: 0 | AD39: =ROUND(AB39-AC39,0) -> 31980 | AE39: =IF(AC39<>0,"Yes","Release") -> Release | AG39: 0 | AI39: 0 | AK39: 3485.9 | AL39: =COUNTIF(AK39:AK39,"=NA") -> 0 | AN39: =((MIN(IF(A39>0,MAX(N39*2%,1861),0),A39)))+0 -> 0 | AO39: =SUMIF('MPG Payment '!E:E,'Shayak Income '!D39,'MPG Payment '!AJ:AJ) -> 0 | AP39: =W39 -> 0 | AQ39: =AO39+AP39 -> 0 | AS39: =B39-X39 -> 0
A40: =IFERROR(VLOOKUP(D40,'Monthly Deduction'!$I$3:$J$957,2,0),0) -> 0 | B40: =IFERROR(VLOOKUP(D40,'Monthly Deduction'!$E$3:$F$957,2,0),0) -> 0 | C40: =A40+B40 -> 0 | D40: 10020023 | E40: =VLOOKUP(D40,'MPG Payment '!$E$3:$G$497305,2,0) -> Juwas | F40: =IFERROR(_xlfn.XLOOKUP(D40,'Monthly Deduction'!$I$3:$I$957,'Monthly Deduction'!$H$3:$H$957),0) -> 0 | G40: =VLOOKUP(D40,'MPG Payment '!$E$3:$G$333666,3,0) -> MPG | H40: =VLOOKUP(D40,'MPG Payment '!$E$3:$H$333666,4,0) -> Direct | I40: =INDEX('MPG Payment '!$C:$C,MATCH('Shayak Income '!D40,'MPG Payment '!E:E,0)) -> 1002 | J40: =INDEX('MPG Payment '!$D:$D,MATCH('Shayak Income '!D40,'MPG Payment '!E:E,0)) -> Laldiyara | K40: Old | L40: 44779 | M40: =SUMIF('MPG Payment '!$E$3:$E$344841,'Shayak Income '!D40,'MPG Payment '!$I$3:$I$344841) -> 3495.8 | N40: =SUMIF('MPG Payment '!$E$3:$E$344841,'Shayak Income '!D40,'MPG Payment '!$J$3:$J$344841) -> 138826.33 | O40: =+M40*0.75 -> 2621.85 | P40: =+M40*0.95 -> 3321.01 | Q40: =SUMIF('MPG Payment '!$E$3:$E$344841,'Shayak Income '!D40,'MPG Payment '!$S$3:$S$344841) -> 1325.08 | R40: =+N40*3% -> 4164.7899 | S40: =R40-P40 -> 843.7799 | T40: =M40*0.1 -> 349.58 | U40: =((((((IF(K40="New",0,SUMIF('MPG Payment '!$E$3:$E$344841,'Shayak Income '!D40,'MPG Payment '!$AC$3:$AC$344841))))+0)+0)+0)+0)+0 -> 0 | V40: =ROUND((SUM(O40:Q40)-SUM(T40:U40)),0) -> 6918 | W40: =(((AN40-AO40)))+0 -> 0 | X40: =((MIN(IF(B40>0,MAX(N40*2%),0),B40)))+0 -> 0 | Y40: =IFERROR(VLOOKUP(D40,'Monthly Deduction'!$M$2:$N$640,2,0),0) -> 0 | Z40: 413 | AA40: =IFERROR(VLOOKUP(D40,'Monthly Deduction'!A:B,2,0),0) -> 0 | AB40: =ROUND(IFERROR(V40-SUM(W40:AA40),0),0) -> 6505 | AC40: 0 | AD40: =ROUND(AB40-AC40,0) -> 6505 | AE40: =IF(AC40<>0,"Yes","Release") -> Release | AG40: 0 | AH40: EIPL Deduction | AI40: 0 | AK40: 753.3 | AL40: =COUNTIF(AK40:AK40,"=NA") -> 0 | AN40: =((MIN(IF(A40>0,MAX(N40*2%,1861),0),A40)))+0 -> 0 | AO40: =SUMIF('MPG Payment '!E:E,'Shayak Income '!D40,'MPG Payment '!AJ:AJ) -> 0 | AP40: =W40 -> 0 | AQ40: =AO40+AP40 -> 0 | AS40: =B40-X40 -> 0
A41: =IFERROR(VLOOKUP(D41,'Monthly Deduction'!$I$3:$J$957,2,0),0) -> 0 | B41: =IFERROR(VLOOKUP(D41,'Monthly Deduction'!$E$3:$F$957,2,0),0) -> 0 | C41: =A41+B41 -> 0 | D41: 10020024 | E41: =VLOOKUP(D41,'MPG Payment '!$E$3:$G$497305,2,0) -> Morwariya | F41: =IFERROR(_xlfn.XLOOKUP(D41,'Monthly Deduction'!$I$3:$I$957,'Monthly Deduction'!$H$3:$H$957),0) -> 0 | G41: =VLOOKUP(D41,'MPG Payment '!$E$3:$G$333666,3,0) -> MPG | H41: =VLOOKUP(D41,'MPG Payment '!$E$3:$H$333666,4,0) -> Direct | I41: =INDEX('MPG Payment '!$C:$C,MATCH('Shayak Income '!D41,'MPG Payment '!E:E,0)) -> 1002 | J41: =INDEX('MPG Payment '!$D:$D,MATCH('Shayak Income '!D41,'MPG Payment '!E:E,0)) -> Laldiyara | K41: Old | L41: 44801 | M41: =SUMIF('MPG Payment '!$E$3:$E$344841,'Shayak Income '!D41,'MPG Payment '!$I$3:$I$344841) -> 10845.7 | N41: =SUMIF('MPG Payment '!$E$3:$E$344841,'Shayak Income '!D41,'MPG Payment '!$J$3:$J$344841) -> 446700.11 | O41: =+M41*0.75 -> 8134.275 | P41: =+M41*0.95 -> 10303.415 | Q41: =SUMIF('MPG Payment '!$E$3:$E$344841,'Shayak Income '!D41,'MPG Payment '!$S$3:$S$344841) -> 0 | R41: =+N41*3% -> 13401.003 | S41: =R41-P41 -> 3097.5883 | T41: =M41*0.1 -> 1084.57 | U41: =((((((IF(K41="New",0,SUMIF('MPG Payment '!$E$3:$E$344841,'Shayak Income '!D41,'MPG Payment '!$AC$3:$AC$344841))))+0)+0)+0)+0)+0 -> 0 | V41: =ROUND((SUM(O41:Q41)-SUM(T41:U41)),0) -> 17353 | W41: =(((AN41-AO41)))+0 -> 0 | X41: =((MIN(IF(B41>0,MAX(N41*2%),0),B41)))+0 -> 0 | Y41: =IFERROR(VLOOKUP(D41,'Monthly Deduction'!$M$2:$N$640,2,0),0) -> 0 | Z41: 0 | AA41: =IFERROR(VLOOKUP(D41,'Monthly Deduction'!A:B,2,0),0) -> 0 | AB41: =ROUND(IFERROR(V41-SUM(W41:AA41),0),0) -> 17353 | AC41: 0 | AD41: =ROUND(AB41-AC41,0) -> 17353 | AE41: =IF(AC41<>0,"Yes","Release") -> Release | AG41: 0 | AI41: 0 | AK41: 2708.2 | AL41: =COUNTIF(AK41:AK41,"=NA") -> 0 | AN41: =((MIN(IF(A41>0,MAX(N41*2%,1861),0),A41)))+0 -> 0 | AO41: =SUMIF('MPG Payment '!E:E,'Shayak Income '!D41,'MPG Payment '!AJ:AJ) -> 0 | AP41: =W41 -> 0 | AQ41: =AO41+AP41 -> 0 | AS41: =B41-X41 -> 0
A42: =IFERROR(VLOOKUP(D42,'Monthly Deduction'!$I$3:$J$957,2,0),0) -> 0 | B42: =IFERROR(VLOOKUP(D42,'Monthly Deduction'!$E$3:$F$957,2,0),0) -> 0 | C42: =A42+B42 -> 0 | D42: 10020025 | E42: =VLOOKUP(D42,'MPG Payment '!$E$3:$G$497305,2,0) -> Dumri 2 | F42: =IFERROR(_xlfn.XLOOKUP(D42,'Monthly Deduction'!$I$3:$I$957,'Monthly Deduction'!$H$3:$H$957),0) -> 0 | G42: =VLOOKUP(D42,'MPG Payment '!$E$3:$G$333666,3,0) -> MPG | H42: =VLOOKUP(D42,'MPG Payment '!$E$3:$H$333666,4,0) -> Direct | I42: =INDEX('MPG Payment '!$C:$C,MATCH('Shayak Income '!D42,'MPG Payment '!E:E,0)) -> 1002 | J42: =INDEX('MPG Payment '!$D:$D,MATCH('Shayak Income '!D42,'MPG Payment '!E:E,0)) -> Laldiyara | K42: Old | L42: 44866 | M42: =SUMIF('MPG Payment '!$E$3:$E$344841,'Shayak Income '!D42,'MPG Payment '!$I$3:$I$344841) -> 3328.1 | N42: =SUMIF('MPG Payment '!$E$3:$E$344841,'Shayak Income '!D42,'MPG Payment '!$J$3:$J$344841) -> 137251.33 | O42: =+M42*0.75 -> 2496.075 | P42: =+M42*0.95 -> 3161.695 | Q42: =SUMIF('MPG Payment '!$E$3:$E$344841,'Shayak Income '!D42,'MPG Payment '!$S$3:$S$344841) -> 1723.07 | R42: =+N42*3% -> 4117.5399 | S42: =R42-P42 -> 955.8449 | T42: =M42*0.1 -> 332.81 | U42: =((((((IF(K42="New",0,SUMIF('MPG Payment '!$E$3:$E$344841,'Shayak Income '!D42,'MPG Payment '!$AC$3:$AC$344841))))+0)+0)+0)+0)+0 -> 0 | V42: =ROUND((SUM(O42:Q42)-SUM(T42:U42)),0) -> 7048 | W42: =(((AN42-AO42)))+0 -> 0 | X42: =((MIN(IF(B42>0,MAX(N42*2%),0),B42)))+0 -> 0 | Y42: =IFERROR(VLOOKUP(D42,'Monthly Deduction'!$M$2:$N$640,2,0),0) -> 0 | Z42: 165.2 | AA42: =IFERROR(VLOOKUP(D42,'Monthly Deduction'!A:B,2,0),0) -> 348.52 | AB42: =ROUND(IFERROR(V42-SUM(W42:AA42),0),0) -> 6534 | AC42: 0 | AD42: =ROUND(AB42-AC42,0) -> 6534 | AE42: =IF(AC42<>0,"Yes","Release") -> Release | AG42: 0 | AH42: EIPL Deduction | AI42: 0 | AK42: 567.2 | AL42: =COUNTIF(AK42:AK42,"=NA") -> 0 | AN42: =((MIN(IF(A42>0,MAX(N42*2%,1861),0),A42)))+0 -> 0 | AO42: =SUMIF('MPG Payment '!E:E,'Shayak Income '!D42,'MPG Payment '!AJ:AJ) -> 0 | AP42: =W42 -> 0 | AQ42: =AO42+AP42 -> 0 | AS42: =B42-X42 -> 0
A43: =IFERROR(VLOOKUP(D43,'Monthly Deduction'!$I$3:$J$957,2,0),0) -> 0 | B43: =IFERROR(VLOOKUP(D43,'Monthly Deduction'!$E$3:$F$957,2,0),0) -> 0 | C43: =A43+B43 -> 0 | D43: 10020026 | E43: =VLOOKUP(D43,'MPG Payment '!$E$3:$G$497305,2,0) -> Gomukh Jhakhaur | F43: =IFERROR(_xlfn.XLOOKUP(D43,'Monthly Deduction'!$I$3:$I$957,'Monthly Deduction'!$H$3:$H$957),0) -> 0 | G43: =VLOOKUP(D43,'MPG Payment '!$E$3:$G$333666,3,0) -> MPG | H43: =VLOOKUP(D43,'MPG Payment '!$E$3:$H$333666,4,0) -> Direct | I43: =INDEX('MPG Payment '!$C:$C,MATCH('Shayak Income '!D43,'MPG Payment '!E:E,0)) -> 1002 | J43: =INDEX('MPG Payment '!$D:$D,MATCH('Shayak Income '!D43,'MPG Payment '!E:E,0)) -> Laldiyara | K43: Old | L43: 44866 | M43: =SUMIF('MPG Payment '!$E$3:$E$344841,'Shayak Income '!D43,'MPG Payment '!$I$3:$I$344841) -> 1892.3 | N43: =SUMIF('MPG Payment '!$E$3:$E$344841,'Shayak Income '!D43,'MPG Payment '!$J$3:$J$344841) -> 77759.27 | O43: =+M43*0.75 -> 1419.225 | P43: =+M43*0.95 -> 1797.685 | Q43: =SUMIF('MPG Payment '!$E$3:$E$344841,'Shayak Income '!D43,'MPG Payment '!$S$3:$S$344841) -> 165.58 | R43: =+N43*3% -> 2332.7781 | S43: =R43-P43 -> 535.0931 | T43: =M43*0.1 -> 189.23 | U43: =((((((IF(K43="New",0,SUMIF('MPG Payment '!$E$3:$E$344841,'Shayak Income '!D43,'MPG Payment '!$AC$3:$AC$344841))))+0)+0)+0)+0)+0 -> 745.52956 | V43: =ROUND((SUM(O43:Q43)-SUM(T43:U43)),0) -> 2448 | W43: =(((AN43-AO43)))+0 -> 0 | X43: =((MIN(IF(B43>0,MAX(N43*2%),0),B43)))+0 -> 0 | Y43: =IFERROR(VLOOKUP(D43,'Monthly Deduction'!$M$2:$N$640,2,0),0) -> 0 | Z43: 973.5 | AA43: =IFERROR(VLOOKUP(D43,'Monthly Deduction'!A:B,2,0),0) -> 348.52 | AB43: =ROUND(IFERROR(V43-SUM(W43:AA43),0),0) -> 1126 | AC43: 0 | AD43: =ROUND(AB43-AC43,0) -> 1126 | AE43: =IF(AC43<>0,"Yes","Release") -> Release | AG43: 0 | AH43: EIPL Deduction | AI43: 0 | AK43: 375.4 | AL43: =COUNTIF(AK43:AK43,"=NA") -> 0 | AN43: =((MIN(IF(A43>0,MAX(N43*2%,1861),0),A43)))+0 -> 0 | AO43: =SUMIF('MPG Payment '!E:E,'Shayak Income '!D43,'MPG Payment '!AJ:AJ) -> 0 | AP43: =W43 -> 0 | AQ43: =AO43+AP43 -> 0 | AS43: =B43-X43 -> 0
A44: =IFERROR(VLOOKUP(D44,'Monthly Deduction'!$I$3:$J$957,2,0),0) -> 0 | B44: =IFERROR(VLOOKUP(D44,'Monthly Deduction'!$E$3:$F$957,2,0),0) -> 0 | C44: =A44+B44 -> 0 | D44: 10020029 | E44: =VLOOKUP(D44,'MPG Payment '!$E$3:$G$497305,2,0) -> Gomukh Virupur | F44: =IFERROR(_xlfn.XLOOKUP(D44,'Monthly Deduction'!$I$3:$I$957,'Monthly Deduction'!$H$3:$H$957),0) -> 0 | G44: =VLOOKUP(D44,'MPG Payment '!$E$3:$G$333666,3,0) -> MPG | H44: =VLOOKUP(D44,'MPG Payment '!$E$3:$H$333666,4,0) -> Direct | I44: =INDEX('MPG Payment '!$C:$C,MATCH('Shayak Income '!D44,'MPG Payment '!E:E,0)) -> 1002 | J44: =INDEX('MPG Payment '!$D:$D,MATCH('Shayak Income '!D44,'MPG Payment '!E:E,0)) -> Laldiyara | K44: Old | L44: 44899 | M44: =SUMIF('MPG Payment '!$E$3:$E$344841,'Shayak Income '!D44,'MPG Payment '!$I$3:$I$344841) -> 1441.5 | N44: =SUMIF('MPG Payment '!$E$3:$E$344841,'Shayak Income '!D44,'MPG Payment '!$J$3:$J$344841) -> 58828.26 | O44: =+M44*0.75 -> 1081.125 | P44: =+M44*0.95 -> 1369.425 | Q44: =SUMIF('MPG Payment '!$E$3:$E$344841,'Shayak Income '!D44,'MPG Payment '!$S$3:$S$344841) -> 419.97 | R44: =+N44*3% -> 1764.8478 | S44: =R44-P44 -> 395.4228 | T44: =M44*0.1 -> 144.15 | U44: =((((((IF(K44="New",0,SUMIF('MPG Payment '!$E$3:$E$344841,'Shayak Income '!D44,'MPG Payment '!$AC$3:$AC$344841))))+0)+0)+0)+0)+0 -> 1110.9971 | V44: =ROUND((SUM(O44:Q44)-SUM(T44:U44)),0) -> 1615 | W44: =(((AN44-AO44)))+0 -> 0 | X44: =((MIN(IF(B44>0,MAX(N44*2%),0),B44)))+0 -> 0 | Y44: =IFERROR(VLOOKUP(D44,'Monthly Deduction'!$M$2:$N$640,2,0),0) -> 0 | Z44: 165.2 | AA44: =IFERROR(VLOOKUP(D44,'Monthly Deduction'!A:B,2,0),0) -> 0 | AB44: =ROUND(IFERROR(V44-SUM(W44:AA44),0),0) -> 1450 | AC44: 0 | AD44: =ROUND(AB44-AC44,0) -> 1450 | AE44: =IF(AC44<>0,"Yes","Release") -> Release | AG44: 0 | AH44: EIPL Deduction | AI44: 0 | AK44: 300.4 | AL44: =COUNTIF(AK44:AK44,"=NA") -> 0 | AN44: =((MIN(IF(A44>0,MAX(N44*2%,1861),0),A44)))+0 -> 0 | AO44: =SUMIF('MPG Payment '!E:E,'Shayak Income '!D44,'MPG Payment '!AJ:AJ) -> 0 | AP44: =W44 -> 0 | AQ44: =AO44+AP44 -> 0 | AS44: =B44-X44 -> 0
A45: =IFERROR(VLOOKUP(D45,'Monthly Deduction'!$I$3:$J$957,2,0),0) -> 0 | B45: =IFERROR(VLOOKUP(D45,'Monthly Deduction'!$E$3:$F$957,2,0),0) -> 0 | C45: =A45+B45 -> 0 | D45: 10020032 | E45: =VLOOKUP(D45,'MPG Payment '!$E$3:$G$497305,2,0) -> Gomukh Diyarapipariya | F45: =IFERROR(_xlfn.XLOOKUP(D45,'Monthly Deduction'!$I$3:$I$957,'Monthly Deduction'!$H$3:$H$957),0) -> 0 | G45: =VLOOKUP(D45,'MPG Payment '!$E$3:$G$333666,3,0) -> MPG | H45: =VLOOKUP(D45,'MPG Payment '!$E$3:$H$333666,4,0) -> Direct | I45: =INDEX('MPG Payment '!$C:$C,MATCH('Shayak Income '!D45,'MPG Payment '!E:E,0)) -> 1002 | J45: =INDEX('MPG Payment '!$D:$D,MATCH('Shayak Income '!D45,'MPG Payment '!E:E,0)) -> Laldiyara | K45: Old | L45: 44911 | M45: =SUMIF('MPG Payment '!$E$3:$E$344841,'Shayak Income '!D45,'MPG Payment '!$I$3:$I$344841) -> 5207.9 | N45: =SUMIF('MPG Payment '!$E$3:$E$344841,'Shayak Income '!D45,'MPG Payment '!$J$3:$J$344841) -> 233003.65 | O45: =+M45*0.75 -> 3905.925 | P45: =+M45*0.95 -> 4947.505 | Q45: =SUMIF('MPG Payment '!$E$3:$E$344841,'Shayak Income '!D45,'MPG Payment '!$S$3:$S$344841) -> 2631.24 | R45: =+N45*3% -> 6990.1095 | S45: =R45-P45 -> 2042.6045 | T45: =M45*0.1 -> 520.79 | U45: =((((((IF(K45="New",0,SUMIF('MPG Payment '!$E$3:$E$344841,'Shayak Income '!D45,'MPG Payment '!$AC$3:$AC$344841))))+0)+0)+0)+0)+0 -> 0 | V45: =ROUND((SUM(O45:Q45)-SUM(T45:U45)),0) -> 10964 | W45: =(((AN45-AO45)))+0 -> 0 | X45: =((MIN(IF(B45>0,MAX(N45*2%),0),B45)))+0 -> 0 | Y45: =IFERROR(VLOOKUP(D45,'Monthly Deduction'!$M$2:$N$640,2,0),0) -> 0 | Z45: 0 | AA45: =IFERROR(VLOOKUP(D45,'Monthly Deduction'!A:B,2,0),0) -> 0 | AB45: =ROUND(IFERROR(V45-SUM(W45:AA45),0),0) -> 10964 | AC45: 0 | AD45: =ROUND(AB45-AC45,0) -> 10964 | AE45: =IF(AC45<>0,"Yes","Release") -> Release | AG45: 0 | AI45: 0 | AK45: 1183.6 | AL45: =COUNTIF(AK45:AK45,"=NA") -> 0 | AN45: =((MIN(IF(A45>0,MAX(N45*2%,1861),0),A45)))+0 -> 0 | AO45: =SUMIF('MPG Payment '!E:E,'Shayak Income '!D45,'MPG Payment '!AJ:AJ) -> 0 | AP45: =W45 -> 0 | AQ45: =AO45+AP45 -> 0 | AS45: =B45-X45 -> 0
A46: =IFERROR(VLOOKUP(D46,'Monthly Deduction'!$I$3:$J$957,2,0),0) -> 0 | B46: =IFERROR(VLOOKUP(D46,'Monthly Deduction'!$E$3:$F$957,2,0),0) -> 0 | C46: =A46+B46 -> 0 | D46: 10020034 | E46: =VLOOKUP(D46,'MPG Payment '!$E$3:$G$497305,2,0) -> TAJPUR | F46: =IFERROR(_xlfn.XLOOKUP(D46,'Monthly Deduction'!$I$3:$I$957,'Monthly Deduction'!$H$3:$H$957),0) -> 0 | G46: =VLOOKUP(D46,'MPG Payment '!$E$3:$G$333666,3,0) -> MPG | H46: =VLOOKUP(D46,'MPG Payment '!$E$3:$H$333666,4,0) -> Direct | I46: =INDEX('MPG Payment '!$C:$C,MATCH('Shayak Income '!D46,'MPG Payment '!E:E,0)) -> 1002 | J46: =INDEX('MPG Payment '!$D:$D,MATCH('Shayak Income '!D46,'MPG Payment '!E:E,0)) -> Laldiyara | K46: Old | L46: 44944 | M46: =SUMIF('MPG Payment '!$E$3:$E$344841,'Shayak Income '!D46,'MPG Payment '!$I$3:$I$344841) -> 3612.5 | N46: =SUMIF('MPG Payment '!$E$3:$E$344841,'Shayak Income '!D46,'MPG Payment '!$J$3:$J$344841) -> 162884.9 | O46: =+M46*0.75 -> 2709.375 | P46: =+M46*0.95 -> 3431.875 | Q46: =SUMIF('MPG Payment '!$E$3:$E$344841,'Shayak Income '!D46,'MPG Payment '!$S$3:$S$344841) -> 1566.68 | R46: =+N46*3% -> 4886.547 | S46: =R46-P46 -> 1454.672 | T46: =M46*0.1 -> 361.25 | U46: =((((((IF(K46="New",0,SUMIF('MPG Payment '!$E$3:$E$344841,'Shayak Income '!D46,'MPG Payment '!$AC$3:$AC$344841))))+0)+0)+0)+0)+0 -> 0 | V46: =ROUND((SUM(O46:Q46)-SUM(T46:U46)),0) -> 7347 | W46: =(((AN46-AO46)))+0 -> 0 | X46: =((MIN(IF(B46>0,MAX(N46*2%),0),B46)))+0 -> 0 | Y46: =IFERROR(VLOOKUP(D46,'Monthly Deduction'!$M$2:$N$640,2,0),0) -> 3000 | Z46: 0 | AA46: =IFERROR(VLOOKUP(D46,'Monthly Deduction'!A:B,2,0),0) -> 0 | AB46: =ROUND(IFERROR(V46-SUM(W46:AA46),0),0) -> 4347 | AC46: 0 | AD46: =ROUND(AB46-AC46,0) -> 4347 | AE46: =IF(AC46<>0,"Yes","Release") -> Release | AG46: 0 | AI46: 0 | AK46: 713.8 | AL46: =COUNTIF(AK46:AK46,"=NA") -> 0 | AN46: =((MIN(IF(A46>0,MAX(N46*2%,1861),0),A46)))+0 -> 0 | AO46: =SUMIF('MPG Payment '!E:E,'Shayak Income '!D46,'MPG Payment '!AJ:AJ) -> 0 | AP46: =W46 -> 0 | AQ46: =AO46+AP46 -> 0 | AS46: =B46-X46 -> 0
A47: =IFERROR(VLOOKUP(D47,'Monthly Deduction'!$I$3:$J$957,2,0),0) -> 0 | B47: =IFERROR(VLOOKUP(D47,'Monthly Deduction'!$E$3:$F$957,2,0),0) -> 0 | C47: =A47+B47 -> 0 | D47: 10020035 | E47: =VLOOKUP(D47,'MPG Payment '!$E$3:$G$497305,2,0) -> PATHUA | F47: =IFERROR(_xlfn.XLOOKUP(D47,'Monthly Deduction'!$I$3:$I$957,'Monthly Deduction'!$H$3:$H$957),0) -> 0 | G47: =VLOOKUP(D47,'MPG Payment '!$E$3:$G$333666,3,0) -> MPG | H47: =VLOOKUP(D47,'MPG Payment '!$E$3:$H$333666,4,0) -> Direct | I47: =INDEX('MPG Payment '!$C:$C,MATCH('Shayak Income '!D47,'MPG Payment '!E:E,0)) -> 1002 | J47: =INDEX('MPG Payment '!$D:$D,MATCH('Shayak Income '!D47,'MPG Payment '!E:E,0)) -> Laldiyara | K47: Old | L47: 44950 | M47: =SUMIF('MPG Payment '!$E$3:$E$344841,'Shayak Income '!D47,'MPG Payment '!$I$3:$I$344841) -> 6870 | N47: =SUMIF('MPG Payment '!$E$3:$E$344841,'Shayak Income '!D47,'MPG Payment '!$J$3:$J$344841) -> 298991 | O47: =+M47*0.75 -> 5152.5 | P47: =+M47*0.95 -> 6526.5 | Q47: =SUMIF('MPG Payment '!$E$3:$E$344841,'Shayak Income '!D47,'MPG Payment '!$S$3:$S$344841) -> 6338.73 | R47: =+N47*3% -> 8969.73 | S47: =R47-P47 -> 2443.23 | T47: =M47*0.1 -> 687 | U47: =((((((IF(K47="New",0,SUMIF('MPG Payment '!$E$3:$E$344841,'Shayak Income '!D47,'MPG Payment '!$AC$3:$AC$344841))))+0)+0)+0)+0)+0 -> 0 | V47: =ROUND((SUM(O47:Q47)-SUM(T47:U47)),0) -> 17331 | W47: =(((AN47-AO47)))+0 -> 0 | X47: =((MIN(IF(B47>0,MAX(N47*2%),0),B47)))+0 -> 0 | Y47: =IFERROR(VLOOKUP(D47,'Monthly Deduction'!$M$2:$N$640,2,0),0) -> 0 | Z47: 0 | AA47: =IFERROR(VLOOKUP(D47,'Monthly Deduction'!A:B,2,0),0) -> 0 | AB47: =ROUND(IFERROR(V47-SUM(W47:AA47),0),0) -> 17331 | AC47: 0 | AD47: =ROUND(AB47-AC47,0) -> 17331 | AE47: =IF(AC47<>0,"Yes","Release") -> Release | AG47: 0 | AI47: 0 | AK47: 2250.3 | AL47: =COUNTIF(AK47:AK47,"=NA") -> 0 | AN47: =((MIN(IF(A47>0,MAX(N47*2%,1861),0),A47)))+0 -> 0 | AO47: =SUMIF('MPG Payment '!E:E,'Shayak Income '!D47,'MPG Payment '!AJ:AJ) -> 0 | AP47: =W47 -> 0 | AQ47: =AO47+AP47 -> 0 | AS47: =B47-X47 -> 0
A48: =IFERROR(VLOOKUP(D48,'Monthly Deduction'!$I$3:$J$957,2,0),0) -> 5970.9339 | B48: =IFERROR(VLOOKUP(D48,'Monthly Deduction'!$E$3:$F$957,2,0),0) -> 0 | C48: =A48+B48 -> 5970.9339 | D48: 10020038 | E48: =VLOOKUP(D48,'MPG Payment '!$E$3:$G$497305,2,0) -> LODIYA | F48: =IFERROR(_xlfn.XLOOKUP(D48,'Monthly Deduction'!$I$3:$I$957,'Monthly Deduction'!$H$3:$H$957),0) -> 0 | G48: =VLOOKUP(D48,'MPG Payment '!$E$3:$G$333666,3,0) -> MPG | H48: =VLOOKUP(D48,'MPG Payment '!$E$3:$H$333666,4,0) -> Direct | I48: =INDEX('MPG Payment '!$C:$C,MATCH('Shayak Income '!D48,'MPG Payment '!E:E,0)) -> 1002 | J48: =INDEX('MPG Payment '!$D:$D,MATCH('Shayak Income '!D48,'MPG Payment '!E:E,0)) -> Laldiyara | K48: Old | L48: 44967 | M48: =SUMIF('MPG Payment '!$E$3:$E$344841,'Shayak Income '!D48,'MPG Payment '!$I$3:$I$344841) -> 2476.9 | N48: =SUMIF('MPG Payment '!$E$3:$E$344841,'Shayak Income '!D48,'MPG Payment '!$J$3:$J$344841) -> 104139.72 | O48: =+M48*0.75 -> 1857.675 | P48: =+M48*0.95 -> 2353.055 | Q48: =SUMIF('MPG Payment '!$E$3:$E$344841,'Shayak Income '!D48,'MPG Payment '!$S$3:$S$344841) -> 967 | R48: =+N48*3% -> 3124.1916 | S48: =R48-P48 -> 771.1366 | T48: =M48*0.1 -> 247.69 | U48: =((((((IF(K48="New",0,SUMIF('MPG Payment '!$E$3:$E$344841,'Shayak Income '!D48,'MPG Payment '!$AC$3:$AC$344841))))+0)+0)+0)+0)+0 -> 272.8125 | V48: =ROUND((SUM(O48:Q48)-SUM(T48:U48)),0) -> 4657 | W48: =(((AN48-AO48)))+0 -> 2082.7944 | X48: 0 | Y48: =IFERROR(VLOOKUP(D48,'Monthly Deduction'!$M$2:$N$640,2,0),0) -> 0 | Z48: 0 | AA48: =IFERROR(VLOOKUP(D48,'Monthly Deduction'!A:B,2,0),0) -> 0 | AB48: =ROUND(IFERROR(V48-SUM(W48:AA48),0),0) -> 2574 | AC48: 0 | AD48: =ROUND(AB48-AC48,0) -> 2574 | AE48: =IF(AC48<>0,"Yes","Release") -> Release | AG48: 0 | AI48: 0 | AK48: 542.5 | AL48: =COUNTIF(AK48:AK48,"=NA") -> 0 | AN48: =((MIN(IF(A48>0,MAX(N48*2%,1861),0),A48)))+0 -> 2082.7944 | AO48: =SUMIF('MPG Payment '!E:E,'Shayak Income '!D48,'MPG Payment '!AJ:AJ) -> 0 | AP48: =W48 -> 2082.7944 | AQ48: =AO48+AP48 -> 2082.7944 | AS48: =B48-X48 -> 0
A49: =IFERROR(VLOOKUP(D49,'Monthly Deduction'!$I$3:$J$957,2,0),0) -> 0 | B49: =IFERROR(VLOOKUP(D49,'Monthly Deduction'!$E$3:$F$957,2,0),0) -> 3669.6762 | C49: =A49+B49 -> 3669.6762 | D49: 10020041 | E49: =VLOOKUP(D49,'MPG Payment '!$E$3:$G$497305,2,0) -> ADARSH LAXMIPUR-3 | F49: =IFERROR(_xlfn.XLOOKUP(D49,'Monthly Deduction'!$I$3:$I$957,'Monthly Deduction'!$H$3:$H$957),0) -> 0 | G49: =VLOOKUP(D49,'MPG Payment '!$E$3:$G$333666,3,0) -> MPG | H49: =VLOOKUP(D49,'MPG Payment '!$E$3:$H$333666,4,0) -> Direct | I49: =INDEX('MPG Payment '!$C:$C,MATCH('Shayak Income '!D49,'MPG Payment '!E:E,0)) -> 1002 | J49: =INDEX('MPG Payment '!$D:$D,MATCH('Shayak Income '!D49,'MPG Payment '!E:E,0)) -> Laldiyara | K49: Old | L49: 44986 | M49: =SUMIF('MPG Payment '!$E$3:$E$344841,'Shayak Income '!D49,'MPG Payment '!$I$3:$I$344841) -> 832.1 | N49: =SUMIF('MPG Payment '!$E$3:$E$344841,'Shayak Income '!D49,'MPG Payment '!$J$3:$J$344841) -> 41958.95 | O49: =+M49*0.75 -> 624.075 | P49: =+M49*0.95 -> 790.495 | Q49: =SUMIF('MPG Payment '!$E$3:$E$344841,'Shayak Income '!D49,'MPG Payment '!$S$3:$S$344841) -> 106.51 | R49: =+N49*3% -> 1258.7685 | S49: =R49-P49 -> 468.2735 | T49: =M49*0.1 -> 83.21 | U49: =((((((IF(K49="New",0,SUMIF('MPG Payment '!$E$3:$E$344841,'Shayak Income '!D49,'MPG Payment '!$AC$3:$AC$344841))))+0)+0)+0)+0)+-558 -> 1437.5759 | V49: =ROUND((SUM(O49:Q49)-SUM(T49:U49)),0) -> 0 | W49: 0 | X49: 0 | Y49: 0 | Z49: 0 | AA49: 0 | AB49: =ROUND(IFERROR(V49-SUM(W49:AA49),0),0) -> 0 | AC49: 0 | AD49: =ROUND(AB49-AC49,0) -> 0 | AE49: =IF(AC49<>0,"Yes","Release") -> Release | AG49: 0 | AI49: 0 | AK49: 148 | AL49: =COUNTIF(AK49:AK49,"=NA") -> 0 | AN49: =((MIN(IF(A49>0,MAX(N49*2%,1861),0),A49)))+0 -> 0 | AO49: =SUMIF('MPG Payment '!E:E,'Shayak Income '!D49,'MPG Payment '!AJ:AJ) -> 2000 | AP49: =W49 -> 0 | AQ49: =AO49+AP49 -> 2000 | AS49: =B49-X49 -> 3669.6762
A50: =IFERROR(VLOOKUP(D50,'Monthly Deduction'!$I$3:$J$957,2,0),0) -> 3079.9225 | B50: =IFERROR(VLOOKUP(D50,'Monthly Deduction'!$E$3:$F$957,2,0),0) -> 8907 | C50: =A50+B50 -> 11986.923 | D50: 10020042 | E50: =VLOOKUP(D50,'MPG Payment '!$E$3:$G$497305,2,0) -> BHANPUR | F50: =IFERROR(_xlfn.XLOOKUP(D50,'Monthly Deduction'!$I$3:$I$957,'Monthly Deduction'!$H$3:$H$957),0) -> 0 | G50: =VLOOKUP(D50,'MPG Payment '!$E$3:$G$333666,3,0) -> MPG | H50: =VLOOKUP(D50,'MPG Payment '!$E$3:$H$333666,4,0) -> Direct | I50: =INDEX('MPG Payment '!$C:$C,MATCH('Shayak Income '!D50,'MPG Payment '!E:E,0)) -> 1002 | J50: =INDEX('MPG Payment '!$D:$D,MATCH('Shayak Income '!D50,'MPG Payment '!E:E,0)) -> Laldiyara | K50: Old | L50: 45009 | M50: =SUMIF('MPG Payment '!$E$3:$E$344841,'Shayak Income '!D50,'MPG Payment '!$I$3:$I$344841) -> 2991.8 | N50: =SUMIF('MPG Payment '!$E$3:$E$344841,'Shayak Income '!D50,'MPG Payment '!$J$3:$J$344841) -> 114877.9 | O50: =+M50*0.75 -> 2243.85 | P50: =+M50*0.95 -> 2842.21 | Q50: =SUMIF('MPG Payment '!$E$3:$E$344841,'Shayak Income '!D50,'MPG Payment '!$S$3:$S$344841) -> 0 | R50: =+N50*3% -> 3446.337 | S50: =R50-P50 -> 604.127 | T50: =M50*0.1 -> 299.18 | U50: =((((((IF(K50="New",0,SUMIF('MPG Payment '!$E$3:$E$344841,'Shayak Income '!D50,'MPG Payment '!$AC$3:$AC$344841))))+0)+0)+0)+0)+0 -> 10.946867 | V50: =ROUND((SUM(O50:Q50)-SUM(T50:U50)),0) -> 4776 | W50: =(((AN50-AO50)))+0 -> 2297.558 | X50: 0 | Y50: =IFERROR(VLOOKUP(D50,'Monthly Deduction'!$M$2:$N$640,2,0),0) -> 0 | Z50: 2454.4 | AA50: =IFERROR(VLOOKUP(D50,'Monthly Deduction'!A:B,2,0),0) -> 0 | AB50: =ROUND(IFERROR(V50-SUM(W50:AA50),0),0) -> 24 | AC50: 0 | AD50: =ROUND(AB50-AC50,0) -> 24 | AE50: =IF(AC50<>0,"Yes","Release") -> Release | AG50: 0 | AH50: EIPL Deduction | AI50: 0 | AK50: 531.7 | AL50: =COUNTIF(AK50:AK50,"=NA") -> 0 | AN50: =((MIN(IF(A50>0,MAX(N50*2%,1861),0),A50)))+0 -> 2297.558 | AO50: =SUMIF('MPG Payment '!E:E,'Shayak Income '!D50,'MPG Payment '!AJ:AJ) -> 0 | AP50: =W50 -> 2297.558 | AQ50: =AO50+AP50 -> 2297.558 | AS50: =B50-X50 -> 8907
A51: =IFERROR(VLOOKUP(D51,'Monthly Deduction'!$I$3:$J$957,2,0),0) -> 0 | B51: =IFERROR(VLOOKUP(D51,'Monthly Deduction'!$E$3:$F$957,2,0),0) -> 0 | C51: =A51+B51 -> 0 | D51: 10020043 | E51: =VLOOKUP(D51,'MPG Payment '!$E$3:$G$497305,2,0) -> Karari Pipariya 2 | F51: =IFERROR(_xlfn.XLOOKUP(D51,'Monthly Deduction'!$I$3:$I$957,'Monthly Deduction'!$H$3:$H$957),0) -> 0 | G51: =VLOOKUP(D51,'MPG Payment '!$E$3:$G$333666,3,0) -> MPG | H51: =VLOOKUP(D51,'MPG Payment '!$E$3:$H$333666,4,0) -> Direct | I51: =INDEX('MPG Payment '!$C:$C,MATCH('Shayak Income '!D51,'MPG Payment '!E:E,0)) -> 1002 | J51: =INDEX('MPG Payment '!$D:$D,MATCH('Shayak Income '!D51,'MPG Payment '!E:E,0)) -> Laldiyara | K51: Old | L51: 45012 | M51: =SUMIF('MPG Payment '!$E$3:$E$344841,'Shayak Income '!D51,'MPG Payment '!$I$3:$I$344841) -> 3269.5 | N51: =SUMIF('MPG Payment '!$E$3:$E$344841,'Shayak Income '!D51,'MPG Payment '!$J$3:$J$344841) -> 145426.27 | O51: =+M51*0.75 -> 2452.125 | P51: =+M51*0.95 -> 3106.025 | Q51: =SUMIF('MPG Payment '!$E$3:$E$344841,'Shayak Income '!D51,'MPG Payment '!$S$3:$S$344841) -> 1882.48 | R51: =+N51*3% -> 4362.7881 | S51: =R51-P51 -> 1256.7631 | T51: =M51*0.1 -> 326.95 | U51: =((((((IF(K51="New",0,SUMIF('MPG Payment '!$E$3:$E$344841,'Shayak Income '!D51,'MPG Payment '!$AC$3:$AC$344841))))+0)+0)+0)+0)+0 -> 69.23897 | V51: =ROUND((SUM(O51:Q51)-SUM(T51:U51)),0) -> 7044 | W51: =(((AN51-AO51)))+0 -> 0 | X51: =((MIN(IF(B51>0,MAX(N51*2%),0),B51)))+0 -> 0 | Y51: =IFERROR(VLOOKUP(D51,'Monthly Deduction'!$M$2:$N$640,2,0),0) -> 0 | Z51: 0 | AA51: =IFERROR(VLOOKUP(D51,'Monthly Deduction'!A:B,2,0),0) -> 0 | AB51: =ROUND(IFERROR(V51-SUM(W51:AA51),0),0) -> 7044 | AC51: 0 | AD51: =ROUND(AB51-AC51,0) -> 7044 | AE51: =IF(AC51<>0,"Yes","Release") -> Release | AG51: 0 | AI51: 0 | AK51: 909.6 | AL51: =COUNTIF(AK51:AK51,"=NA") -> 0 | AN51: =((MIN(IF(A51>0,MAX(N51*2%,1861),0),A51)))+0 -> 0 | AO51: =SUMIF('MPG Payment '!E:E,'Shayak Income '!D51,'MPG Payment '!AJ:AJ) -> 0 | AP51: =W51 -> 0 | AQ51: =AO51+AP51 -> 0 | AS51: =B51-X51 -> 0
A52: =IFERROR(VLOOKUP(D52,'Monthly Deduction'!$I$3:$J$957,2,0),0) -> 0 | B52: =IFERROR(VLOOKUP(D52,'Monthly Deduction'!$E$3:$F$957,2,0),0) -> 0 | C52: =A52+B52 -> 0 | D52: 10020044 | E52: =VLOOKUP(D52,'MPG Payment '!$E$3:$G$497305,2,0) -> DIYARA PIPARIYA-THANA | F52: =IFERROR(_xlfn.XLOOKUP(D52,'Monthly Deduction'!$I$3:$I$957,'Monthly Deduction'!$H$3:$H$957),0) -> 0 | G52: =VLOOKUP(D52,'MPG Payment '!$E$3:$G$333666,3,0) -> MPG | H52: =VLOOKUP(D52,'MPG Payment '!$E$3:$H$333666,4,0) -> Direct | I52: =INDEX('MPG Payment '!$C:$C,MATCH('Shayak Income '!D52,'MPG Payment '!E:E,0)) -> 1002 | J52: =INDEX('MPG Payment '!$D:$D,MATCH('Shayak Income '!D52,'MPG Payment '!E:E,0)) -> Laldiyara | K52: Old | L52: 45064 | M52: =SUMIF('MPG Payment '!$E$3:$E$344841,'Shayak Income '!D52,'MPG Payment '!$I$3:$I$344841) -> 5171.8 | N52: =SUMIF('MPG Payment '!$E$3:$E$344841,'Shayak Income '!D52,'MPG Payment '!$J$3:$J$344841) -> 232499.73 | O52: =+M52*0.75 -> 3878.85 | P52: =+M52*0.95 -> 4913.21 | Q52: =SUMIF('MPG Payment '!$E$3:$E$344841,'Shayak Income '!D52,'MPG Payment '!$S$3:$S$344841) -> 2243.07 | R52: =+N52*3% -> 6974.9919 | S52: =R52-P52 -> 2061.7819 | T52: =M52*0.1 -> 517.18 | U52: =((((((IF(K52="New",0,SUMIF('MPG Payment '!$E$3:$E$344841,'Shayak Income '!D52,'MPG Payment '!$AC$3:$AC$344841))))+0)+0)+0)+0)+0 -> 0 | V52: =ROUND((SUM(O52:Q52)-SUM(T52:U52)),0) -> 10518 | W52: =(((AN52-AO52)))+0 -> 0 | X52: =((MIN(IF(B52>0,MAX(N52*2%),0),B52)))+0 -> 0 | Y52: =IFERROR(VLOOKUP(D52,'Monthly Deduction'!$M$2:$N$640,2,0),0) -> 0 | Z52: 0 | AA52: =IFERROR(VLOOKUP(D52,'Monthly Deduction'!A:B,2,0),0) -> 0 | AB52: =ROUND(IFERROR(V52-SUM(W52:AA52),0),0) -> 10518 | AC52: 0 | AD52: =ROUND(AB52-AC52,0) -> 10518 | AE52: =IF(AC52<>0,"Yes","Release") -> Release | AG52: 0 | AI52: 0 | AK52: 1241.4 | AL52: =COUNTIF(AK52:AK52,"=NA") -> 0 | AN52: =((MIN(IF(A52>0,MAX(N52*2%,1861),0),A52)))+0 -> 0 | AO52: =SUMIF('MPG Payment '!E:E,'Shayak Income '!D52,'MPG Payment '!AJ:AJ) -> 0 | AP52: =W52 -> 0 | AQ52: =AO52+AP52 -> 0 | AS52: =B52-X52 -> 0
A53: =IFERROR(VLOOKUP(D53,'Monthly Deduction'!$I$3:$J$957,2,0),0) -> 0 | B53: =IFERROR(VLOOKUP(D53,'Monthly Deduction'!$E$3:$F$957,2,0),0) -> 0 | C53: =A53+B53 -> 0 | D53: 10020047 | E53: =VLOOKUP(D53,'MPG Payment '!$E$3:$G$497305,2,0) -> SRI RAM SINGH(VLC) | F53: =IFERROR(_xlfn.XLOOKUP(D53,'Monthly Deduction'!$I$3:$I$957,'Monthly Deduction'!$H$3:$H$957),0) -> 0 | G53: =VLOOKUP(D53,'MPG Payment '!$E$3:$G$333666,3,0) -> vlc | H53: =VLOOKUP(D53,'MPG Payment '!$E$3:$H$333666,4,0) -> Indirect | I53: =INDEX('MPG Payment '!$C:$C,MATCH('Shayak Income '!D53,'MPG Payment '!E:E,0)) -> 1002 | J53: =INDEX('MPG Payment '!$D:$D,MATCH('Shayak Income '!D53,'MPG Payment '!E:E,0)) -> Laldiyara | K53: Old | L53: 45156 | M53: =SUMIF('MPG Payment '!$E$3:$E$344841,'Shayak Income '!D53,'MPG Payment '!$I$3:$I$344841) -> 12531.6 | N53: =SUMIF('MPG Payment '!$E$3:$E$344841,'Shayak Income '!D53,'MPG Payment '!$J$3:$J$344841) -> 537178.78 | O53: =+M53*0.75 -> 9398.7 | P53: =+M53*0.95 -> 11905.02 | Q53: =SUMIF('MPG Payment '!$E$3:$E$344841,'Shayak Income '!D53,'MPG Payment '!$S$3:$S$344841) -> 0 | R53: =+N53*3% -> 16115.363 | S53: =R53-P53 -> 4210.3434 | T53: =M53*0.1 -> 1253.16 | U53: =((((((IF(K53="New",0,SUMIF('MPG Payment '!$E$3:$E$344841,'Shayak Income '!D53,'MPG Payment '!$AC$3:$AC$344841))))+0)+0)+0)+0)+0 -> 0 | V53: =ROUND((SUM(O53:Q53)-SUM(T53:U53)),0) -> 20051 | W53: =(((AN53-AO53)))+0 -> 0 | X53: =((MIN(IF(B53>0,MAX(N53*2%),0),B53)))+0 -> 0 | Y53: =IFERROR(VLOOKUP(D53,'Monthly Deduction'!$M$2:$N$640,2,0),0) -> 0 | Z53: 0 | AA53: =IFERROR(VLOOKUP(D53,'Monthly Deduction'!A:B,2,0),0) -> 0 | AB53: =ROUND(IFERROR(V53-SUM(W53:AA53),0),0) -> 20051 | AC53: 0 | AD53: =ROUND(AB53-AC53,0) -> 20051 | AE53: =IF(AC53<>0,"Yes","Release") -> Release | AG53: 0 | AI53: 0 | AK53: 2826.5 | AL53: =COUNTIF(AK53:AK53,"=NA") -> 0 | AN53: =((MIN(IF(A53>0,MAX(N53*2%,1861),0),A53)))+0 -> 0 | AO53: =SUMIF('MPG Payment '!E:E,'Shayak Income '!D53,'MPG Payment '!AJ:AJ) -> 0 | AP53: =W53 -> 0 | AQ53: =AO53+AP53 -> 0 | AS53: =B53-X53 -> 0
A54: =IFERROR(VLOOKUP(D54,'Monthly Deduction'!$I$3:$J$957,2,0),0) -> 0 | B54: =IFERROR(VLOOKUP(D54,'Monthly Deduction'!$E$3:$F$957,2,0),0) -> 0 | C54: =A54+B54 -> 0 | D54: 10020050 | E54: =VLOOKUP(D54,'MPG Payment '!$E$3:$G$497305,2,0) -> GADHTOLA | F54: =IFERROR(_xlfn.XLOOKUP(D54,'Monthly Deduction'!$I$3:$I$957,'Monthly Deduction'!$H$3:$H$957),0) -> 0 | G54: =VLOOKUP(D54,'MPG Payment '!$E$3:$G$333666,3,0) -> MPG | H54: =VLOOKUP(D54,'MPG Payment '!$E$3:$H$333666,4,0) -> Direct | I54: =INDEX('MPG Payment '!$C:$C,MATCH('Shayak Income '!D54,'MPG Payment '!E:E,0)) -> 1002 | J54: =INDEX('MPG Payment '!$D:$D,MATCH('Shayak Income '!D54,'MPG Payment '!E:E,0)) -> Laldiyara | K54: Old | L54: 45168 | M54: =SUMIF('MPG Payment '!$E$3:$E$344841,'Shayak Income '!D54,'MPG Payment '!$I$3:$I$344841) -> 5121.4 | N54: =SUMIF('MPG Payment '!$E$3:$E$344841,'Shayak Income '!D54,'MPG Payment '!$J$3:$J$344841) -> 240089.98 | O54: =+M54*0.75 -> 3841.05 | P54: =+M54*0.95 -> 4865.33 | Q54: =SUMIF('MPG Payment '!$E$3:$E$344841,'Shayak Income '!D54,'MPG Payment '!$S$3:$S$344841) -> 939.95 | R54: =+N54*3% -> 7202.6994 | S54: =R54-P54 -> 2337.3694 | T54: =M54*0.1 -> 512.14 | U54: =((((((IF(K54="New",0,SUMIF('MPG Payment '!$E$3:$E$344841,'Shayak Income '!D54,'MPG Payment '!$AC$3:$AC$344841))))+0)+0)+0)+0)+0 -> 0 | V54: =ROUND((SUM(O54:Q54)-SUM(T54:U54)),0) -> 9134 | W54: =(((AN54-AO54)))+0 -> 0 | X54: =((MIN(IF(B54>0,MAX(N54*2%),0),B54)))+0 -> 0 | Y54: =IFERROR(VLOOKUP(D54,'Monthly Deduction'!$M$2:$N$640,2,0),0) -> 0 | Z54: 0 | AA54: =IFERROR(VLOOKUP(D54,'Monthly Deduction'!A:B,2,0),0) -> 980.24 | AB54: =ROUND(IFERROR(V54-SUM(W54:AA54),0),0) -> 8154 | AC54: 0 | AD54: =ROUND(AB54-AC54,0) -> 8154 | AE54: =IF(AC54<>0,"Yes","Release") -> Release | AG54: 0 | AI54: 0 | AK54: 1004 | AL54: =COUNTIF(AK54:AK54,"=NA") -> 0 | AN54: =((MIN(IF(A54>0,MAX(N54*2%,1861),0),A54)))+0 -> 0 | AO54: =SUMIF('MPG Payment '!E:E,'Shayak Income '!D54,'MPG Payment '!AJ:AJ) -> 0 | AP54: =W54 -> 0 | AQ54: =AO54+AP54 -> 0 | AS54: =B54-X54 -> 0
A55: =IFERROR(VLOOKUP(D55,'Monthly Deduction'!$I$3:$J$957,2,0),0) -> 0 | B55: =IFERROR(VLOOKUP(D55,'Monthly Deduction'!$E$3:$F$957,2,0),0) -> 0 | C55: =A55+B55 -> 0 | D55: 10020054 | E55: =VLOOKUP(D55,'MPG Payment '!$E$3:$G$497305,2,0) -> Diyara-Pipariya-Utri - Chandan | F55: =IFERROR(_xlfn.XLOOKUP(D55,'Monthly Deduction'!$I$3:$I$957,'Monthly Deduction'!$H$3:$H$957),0) -> 0 | G55: =VLOOKUP(D55,'MPG Payment '!$E$3:$G$333666,3,0) -> vlc | H55: =VLOOKUP(D55,'MPG Payment '!$E$3:$H$333666,4,0) -> Indirect | I55: =INDEX('MPG Payment '!$C:$C,MATCH('Shayak Income '!D55,'MPG Payment '!E:E,0)) -> 1002 | J55: =INDEX('MPG Payment '!$D:$D,MATCH('Shayak Income '!D55,'MPG Payment '!E:E,0)) -> Laldiyara | K55: Old | L55: 44710 | M55: =SUMIF('MPG Payment '!$E$3:$E$344841,'Shayak Income '!D55,'MPG Payment '!$I$3:$I$344841) -> 7298.9 | N55: =SUMIF('MPG Payment '!$E$3:$E$344841,'Shayak Income '!D55,'MPG Payment '!$J$3:$J$344841) -> 315060.4 | O55: =+M55*0.75 -> 5474.175 | P55: =+M55*0.95 -> 6933.955 | Q55: =SUMIF('MPG Payment '!$E$3:$E$344841,'Shayak Income '!D55,'MPG Payment '!$S$3:$S$344841) -> 0 | R55: =+N55*3% -> 9451.812 | S55: =R55-P55 -> 2517.857 | T55: =M55*0.1 -> 729.89 | U55: =((((((IF(K55="New",0,SUMIF('MPG Payment '!$E$3:$E$344841,'Shayak Income '!D55,'MPG Payment '!$AC$3:$AC$344841))))+0)+0)+0)+0)+0 -> 0 | V55: =ROUND((SUM(O55:Q55)-SUM(T55:U55)),0) -> 11678 | W55: =(((AN55-AO55)))+0 -> 0 | X55: =((MIN(IF(B55>0,MAX(N55*2%),0),B55)))+0 -> 0 | Y55: =IFERROR(VLOOKUP(D55,'Monthly Deduction'!$M$2:$N$640,2,0),0) -> 0 | Z55: 0 | AA55: =IFERROR(VLOOKUP(D55,'Monthly Deduction'!A:B,2,0),0) -> 0 | AB55: =ROUND(IFERROR(V55-SUM(W55:AA55),0),0) -> 11678 | AC55: 0 | AD55: =ROUND(AB55-AC55,0) -> 11678 | AE55: =IF(AC55<>0,"Yes","Release") -> Release | AG55: 0 | AI55: 0 | AK55: 1386.9 | AL55: =COUNTIF(AK55:AK55,"=NA") -> 0 | AN55: =((MIN(IF(A55>0,MAX(N55*2%,1861),0),A55)))+0 -> 0 | AO55: =SUMIF('MPG Payment '!E:E,'Shayak Income '!D55,'MPG Payment '!AJ:AJ) -> 0 | AP55: =W55 -> 0 | AQ55: =AO55+AP55 -> 0 | AS55: =B55-X55 -> 0
A56: =IFERROR(VLOOKUP(D56,'Monthly Deduction'!$I$3:$J$957,2,0),0) -> 0 | B56: =IFERROR(VLOOKUP(D56,'Monthly Deduction'!$E$3:$F$957,2,0),0) -> 0 | C56: =A56+B56 -> 0 | D56: 10020057 | E56: =VLOOKUP(D56,'MPG Payment '!$E$3:$G$497305,2,0) -> KANHARPUR-2 | F56: =IFERROR(_xlfn.XLOOKUP(D56,'Monthly Deduction'!$I$3:$I$957,'Monthly Deduction'!$H$3:$H$957),0) -> 0 | G56: =VLOOKUP(D56,'MPG Payment '!$E$3:$G$333666,3,0) -> MPG | H56: =VLOOKUP(D56,'MPG Payment '!$E$3:$H$333666,4,0) -> Direct | I56: =INDEX('MPG Payment '!$C:$C,MATCH('Shayak Income '!D56,'MPG Payment '!E:E,0)) -> 1002 | J56: =INDEX('MPG Payment '!$D:$D,MATCH('Shayak Income '!D56,'MPG Payment '!E:E,0)) -> Laldiyara | K56: Old | L56: 45248 | M56: =SUMIF('MPG Payment '!$E$3:$E$344841,'Shayak Income '!D56,'MPG Payment '!$I$3:$I$344841) -> 10371 | N56: =SUMIF('MPG Payment '!$E$3:$E$344841,'Shayak Income '!D56,'MPG Payment '!$J$3:$J$344841) -> 487216.09 | O56: =+M56*0.75 -> 7778.25 | P56: =+M56*0.95 -> 9852.45 | Q56: =SUMIF('MPG Payment '!$E$3:$E$344841,'Shayak Income '!D56,'MPG Payment '!$S$3:$S$344841) -> 6871.31 | R56: =+N56*3% -> 14616.483 | S56: =R56-P56 -> 4764.0327 | T56: =M56*0.1 -> 1037.1 | U56: =((((((IF(K56="New",0,SUMIF('MPG Payment '!$E$3:$E$344841,'Shayak Income '!D56,'MPG Payment '!$AC$3:$AC$344841))))+0)+0)+0)+0)+0 -> 0 | V56: =ROUND((SUM(O56:Q56)-SUM(T56:U56)),0) -> 23465 | W56: =(((AN56-AO56)))+0 -> 0 | X56: =((MIN(IF(B56>0,MAX(N56*2%),0),B56)))+0 -> 0 | Y56: =IFERROR(VLOOKUP(D56,'Monthly Deduction'!$M$2:$N$640,2,0),0) -> 0 | Z56: 0 | AA56: =IFERROR(VLOOKUP(D56,'Monthly Deduction'!A:B,2,0),0) -> 0 | AB56: =ROUND(IFERROR(V56-SUM(W56:AA56),0),0) -> 23465 | AC56: 0 | AD56: =ROUND(AB56-AC56,0) -> 23465 | AE56: =IF(AC56<>0,"Yes","Release") -> Release | AG56: 0 | AI56: 0 | AK56: 2556.4 | AL56: =COUNTIF(AK56:AK56,"=NA") -> 0 | AN56: =((MIN(IF(A56>0,MAX(N56*2%,1861),0),A56)))+0 -> 0 | AO56: =SUMIF('MPG Payment '!E:E,'Shayak Income '!D56,'MPG Payment '!AJ:AJ) -> 0 | AP56: =W56 -> 0 | AQ56: =AO56+AP56 -> 0 | AS56: =B56-X56 -> 0
A57: =IFERROR(VLOOKUP(D57,'Monthly Deduction'!$I$3:$J$957,2,0),0) -> 0 | B57: =IFERROR(VLOOKUP(D57,'Monthly Deduction'!$E$3:$F$957,2,0),0) -> 0 | C57: =A57+B57 -> 0 | D57: 10020058 | E57: =VLOOKUP(D57,'MPG Payment '!$E$3:$G$497305,2,0) -> BASAUNA | F57: =IFERROR(_xlfn.XLOOKUP(D57,'Monthly Deduction'!$I$3:$I$957,'Monthly Deduction'!$H$3:$H$957),0) -> 0 | G57: =VLOOKUP(D57,'MPG Payment '!$E$3:$G$333666,3,0) -> MPG | H57: =VLOOKUP(D57,'MPG Payment '!$E$3:$H$333666,4,0) -> Direct | I57: =INDEX('MPG Payment '!$C:$C,MATCH('Shayak Income '!D57,'MPG Payment '!E:E,0)) -> 1002 | J57: =INDEX('MPG Payment '!$D:$D,MATCH('Shayak Income '!D57,'MPG Payment '!E:E,0)) -> Laldiyara | K57: Old | L57: 45283 | M57: =SUMIF('MPG Payment '!$E$3:$E$344841,'Shayak Income '!D57,'MPG Payment '!$I$3:$I$344841) -> 2675.6 | N57: =SUMIF('MPG Payment '!$E$3:$E$344841,'Shayak Income '!D57,'MPG Payment '!$J$3:$J$344841) -> 113501.68 | O57: =+M57*0.75 -> 2006.7 | P57: =+M57*0.95 -> 2541.82 | Q57: =SUMIF('MPG Payment '!$E$3:$E$344841,'Shayak Income '!D57,'MPG Payment '!$S$3:$S$344841) -> 1029.61 | R57: =+N57*3% -> 3405.0504 | S57: =R57-P57 -> 863.2304 | T57: =M57*0.1 -> 267.56 | U57: =((((((IF(K57="New",0,SUMIF('MPG Payment '!$E$3:$E$344841,'Shayak Income '!D57,'MPG Payment '!$AC$3:$AC$344841))))+0)+0)+0)+0)+0 -> 116.1352 | V57: =ROUND((SUM(O57:Q57)-SUM(T57:U57)),0) -> 5194 | W57: =(((AN57-AO57)))+0 -> 0 | X57: =((MIN(IF(B57>0,MAX(N57*2%),0),B57)))+0 -> 0 | Y57: =IFERROR(VLOOKUP(D57,'Monthly Deduction'!$M$2:$N$640,2,0),0) -> 0 | Z57: 0 | AA57: =IFERROR(VLOOKUP(D57,'Monthly Deduction'!A:B,2,0),0) -> 0 | AB57: =ROUND(IFERROR(V57-SUM(W57:AA57),0),0) -> 5194 | AC57: 0 | AD57: =ROUND(AB57-AC57,0) -> 5194 | AE57: =IF(AC57<>0,"Yes","Release") -> Release | AG57: 0 | AI57: 0 | AK57: 612.2 | AL57: =COUNTIF(AK57:AK57,"=NA") -> 0 | AN57: =((MIN(IF(A57>0,MAX(N57*2%,1861),0),A57)))+0 -> 0 | AO57: =SUMIF('MPG Payment '!E:E,'Shayak Income '!D57,'MPG Payment '!AJ:AJ) -> 0 | AP57: =W57 -> 0 | AQ57: =AO57+AP57 -> 0 | AS57: =B57-X57 -> 0
A58: =IFERROR(VLOOKUP(D58,'Monthly Deduction'!$I$3:$J$957,2,0),0) -> 0 | B58: =IFERROR(VLOOKUP(D58,'Monthly Deduction'!$E$3:$F$957,2,0),0) -> 12800 | C58: =A58+B58 -> 12800 | D58: 10020059 | E58: =VLOOKUP(D58,'MPG Payment '!$E$3:$G$497305,2,0) -> GANGA-SARAI | F58: =IFERROR(_xlfn.XLOOKUP(D58,'Monthly Deduction'!$I$3:$I$957,'Monthly Deduction'!$H$3:$H$957),0) -> 0 | G58: =VLOOKUP(D58,'MPG Payment '!$E$3:$G$333666,3,0) -> MPG | H58: =VLOOKUP(D58,'MPG Payment '!$E$3:$H$333666,4,0) -> Direct | I58: =INDEX('MPG Payment '!$C:$C,MATCH('Shayak Income '!D58,'MPG Payment '!E:E,0)) -> 1002 | J58: =INDEX('MPG Payment '!$D:$D,MATCH('Shayak Income '!D58,'MPG Payment '!E:E,0)) -> Laldiyara | K58: Old | L58: 45268 | M58: =SUMIF('MPG Payment '!$E$3:$E$344841,'Shayak Income '!D58,'MPG Payment '!$I$3:$I$344841) -> 4603.9 | N58: =SUMIF('MPG Payment '!$E$3:$E$344841,'Shayak Income '!D58,'MPG Payment '!$J$3:$J$344841) -> 199326.13 | O58: =+M58*0.75 -> 3452.925 | P58: =+M58*0.95 -> 4373.705 | Q58: =SUMIF('MPG Payment '!$E$3:$E$344841,'Shayak Income '!D58,'MPG Payment '!$S$3:$S$344841) -> 1771.75 | R58: =+N58*3% -> 5979.7839 | S58: =R58-P58 -> 1606.0789 | T58: =M58*0.1 -> 460.39 | U58: =((((((IF(K58="New",0,SUMIF('MPG Payment '!$E$3:$E$344841,'Shayak Income '!D58,'MPG Payment '!$AC$3:$AC$344841))))+0)+0)+0)+0)+0 -> 0 | V58: =ROUND((SUM(O58:Q58)-SUM(T58:U58)),0) -> 9138 | W58: =(((AN58-AO58)))+0 -> 0 | X58: =((MIN(IF(B58>0,MAX(N58*2%),0),B58)))+0 -> 3986.5226 | Y58: =IFERROR(VLOOKUP(D58,'Monthly Deduction'!$M$2:$N$640,2,0),0) -> 0 | Z58: 2454.4 | AA58: =IFERROR(VLOOKUP(D58,'Monthly Deduction'!A:B,2,0),0) -> 1045.56 | AB58: =ROUND(IFERROR(V58-SUM(W58:AA58),0),0) -> 1652 | AC58: 0 | AD58: =ROUND(AB58-AC58,0) -> 1652 | AE58: =IF(AC58<>0,"Yes","Release") -> Release | AG58: 0 | AH58: EIPL Deduction | AI58: 0 | AK58: 699.1 | AL58: =COUNTIF(AK58:AK58,"=NA") -> 0 | AN58: =((MIN(IF(A58>0,MAX(N58*2%,1861),0),A58)))+0 -> 0 | AO58: =SUMIF('MPG Payment '!E:E,'Shayak Income '!D58,'MPG Payment '!AJ:AJ) -> 0 | AP58: =W58 -> 0 | AQ58: =AO58+AP58 -> 0 | AS58: =B58-X58 -> 8813.4774
A59: =IFERROR(VLOOKUP(D59,'Monthly Deduction'!$I$3:$J$957,2,0),0) -> 23458.522 | B59: =IFERROR(VLOOKUP(D59,'Monthly Deduction'!$E$3:$F$957,2,0),0) -> 11212.327 | C59: =A59+B59 -> 34670.849 | D59: 10020062 | E59: =VLOOKUP(D59,'MPG Payment '!$E$3:$G$497305,2,0) -> GOVIND-BIGHA | F59: =IFERROR(_xlfn.XLOOKUP(D59,'Monthly Deduction'!$I$3:$I$957,'Monthly Deduction'!$H$3:$H$957),0) -> 0 | G59: =VLOOKUP(D59,'MPG Payment '!$E$3:$G$333666,3,0) -> MPG | H59: =VLOOKUP(D59,'MPG Payment '!$E$3:$H$333666,4,0) -> Direct | I59: =INDEX('MPG Payment '!$C:$C,MATCH('Shayak Income '!D59,'MPG Payment '!E:E,0)) -> 1002 | J59: =INDEX('MPG Payment '!$D:$D,MATCH('Shayak Income '!D59,'MPG Payment '!E:E,0)) -> Laldiyara | K59: Old | L59: 45205 | M59: =SUMIF('MPG Payment '!$E$3:$E$344841,'Shayak Income '!D59,'MPG Payment '!$I$3:$I$344841) -> 974.1 | N59: =SUMIF('MPG Payment '!$E$3:$E$344841,'Shayak Income '!D59,'MPG Payment '!$J$3:$J$344841) -> 40954.33 | O59: =+M59*0.75 -> 730.575 | P59: =+M59*0.95 -> 925.395 | Q59: =SUMIF('MPG Payment '!$E$3:$E$344841,'Shayak Income '!D59,'MPG Payment '!$S$3:$S$344841) -> 601.61 | R59: =+N59*3% -> 1228.6299 | S59: =R59-P59 -> 303.2349 | T59: =M59*0.1 -> 97.41 | U59: =((((((IF(K59="New",0,SUMIF('MPG Payment '!$E$3:$E$344841,'Shayak Income '!D59,'MPG Payment '!$AC$3:$AC$344841))))+0)+0)+0)+0)+0 -> 1552.3951 | V59: =ROUND((SUM(O59:Q59)-SUM(T59:U59)),0) -> 608 | W59: 608 | X59: 0 | Y59: =IFERROR(VLOOKUP(D59,'Monthly Deduction'!$M$2:$N$640,2,0),0) -> 0 | Z59: 0 | AA59: =IFERROR(VLOOKUP(D59,'Monthly Deduction'!A:B,2,0),0) -> 0 | AB59: =ROUND(IFERROR(V59-SUM(W59:AA59),0),0) -> 0 | AC59: 0 | AD59: =ROUND(AB59-AC59,0) -> 0 | AE59: =IF(AC59<>0,"Yes","Release") -> Release | AG59: 0 | AI59: 0 | AK59: 246.1 | AL59: =COUNTIF(AK59:AK59,"=NA") -> 0 | AN59: =((MIN(IF(A59>0,MAX(N59*2%,1861),0),A59)))+0 -> 1861 | AO59: =SUMIF('MPG Payment '!E:E,'Shayak Income '!D59,'MPG Payment '!AJ:AJ) -> 0 | AP59: =W59 -> 608 | AQ59: =AO59+AP59 -> 608 | AS59: =B59-X59 -> 11212.327
A60: =IFERROR(VLOOKUP(D60,'Monthly Deduction'!$I$3:$J$957,2,0),0) -> 0 | B60: =IFERROR(VLOOKUP(D60,'Monthly Deduction'!$E$3:$F$957,2,0),0) -> 0 | C60: =A60+B60 -> 0 | D60: 10020063 | E60: =VLOOKUP(D60,'MPG Payment '!$E$3:$G$497305,2,0) -> MALPUR | F60: =IFERROR(_xlfn.XLOOKUP(D60,'Monthly Deduction'!$I$3:$I$957,'Monthly Deduction'!$H$3:$H$957),0) -> 0 | G60: =VLOOKUP(D60,'MPG Payment '!$E$3:$G$333666,3,0) -> MPG | H60: =VLOOKUP(D60,'MPG Payment '!$E$3:$H$333666,4,0) -> Direct | I60: =INDEX('MPG Payment '!$C:$C,MATCH('Shayak Income '!D60,'MPG Payment '!E:E,0)) -> 1002 | J60: =INDEX('MPG Payment '!$D:$D,MATCH('Shayak Income '!D60,'MPG Payment '!E:E,0)) -> Laldiyara | K60: Old | L60: 45198 | M60: =SUMIF('MPG Payment '!$E$3:$E$344841,'Shayak Income '!D60,'MPG Payment '!$I$3:$I$344841) -> 3929.5 | N60: =SUMIF('MPG Payment '!$E$3:$E$344841,'Shayak Income '!D60,'MPG Payment '!$J$3:$J$344841) -> 180757.1 | O60: =+M60*0.75 -> 2947.125 | P60: =+M60*0.95 -> 3733.025 | Q60: =SUMIF('MPG Payment '!$E$3:$E$344841,'Shayak Income '!D60,'MPG Payment '!$S$3:$S$344841) -> 1337.54 | R60: =+N60*3% -> 5422.713 | S60: =R60-P60 -> 1689.688 | T60: =M60*0.1 -> 392.95 | U60: =((((((IF(K60="New",0,SUMIF('MPG Payment '!$E$3:$E$344841,'Shayak Income '!D60,'MPG Payment '!$AC$3:$AC$344841))))+0)+0)+0)+0)+0 -> 0 | V60: =ROUND((SUM(O60:Q60)-SUM(T60:U60)),0) -> 7625 | W60: =(((AN60-AO60)))+0 -> 0 | X60: =((MIN(IF(B60>0,MAX(N60*2%),0),B60)))+0 -> 0 | Y60: =IFERROR(VLOOKUP(D60,'Monthly Deduction'!$M$2:$N$640,2,0),0) -> 0 | Z60: 0 | AA60: =IFERROR(VLOOKUP(D60,'Monthly Deduction'!A:B,2,0),0) -> 0 | AB60: =ROUND(IFERROR(V60-SUM(W60:AA60),0),0) -> 7625 | AC60: 0 | AD60: =ROUND(AB60-AC60,0) -> 7625 | AE60: =IF(AC60<>0,"Yes","Release") -> Release | AG60: 0 | AI60: 0 | AK60: 1022.1 | AL60: =COUNTIF(AK60:AK60,"=NA") -> 0 | AN60: =((MIN(IF(A60>0,MAX(N60*2%,1861),0),A60)))+0 -> 0 | AO60: =SUMIF('MPG Payment '!E:E,'Shayak Income '!D60,'MPG Payment '!AJ:AJ) -> 0 | AP60: =W60 -> 0 | AQ60: =AO60+AP60 -> 0 | AS60: =B60-X60 -> 0
A61: =IFERROR(VLOOKUP(D61,'Monthly Deduction'!$I$3:$J$957,2,0),0) -> 0 | B61: =IFERROR(VLOOKUP(D61,'Monthly Deduction'!$E$3:$F$957,2,0),0) -> 0 | C61: =A61+B61 -> 0 | D61: 10020064 | E61: =VLOOKUP(D61,'MPG Payment '!$E$3:$G$497305,2,0) -> Gomukh Hasanpur | F61: =IFERROR(_xlfn.XLOOKUP(D61,'Monthly Deduction'!$I$3:$I$957,'Monthly Deduction'!$H$3:$H$957),0) -> 0 | G61: =VLOOKUP(D61,'MPG Payment '!$E$3:$G$333666,3,0) -> vlc | H61: =VLOOKUP(D61,'MPG Payment '!$E$3:$H$333666,4,0) -> Indirect | I61: =INDEX('MPG Payment '!$C:$C,MATCH('Shayak Income '!D61,'MPG Payment '!E:E,0)) -> 1002 | J61: =INDEX('MPG Payment '!$D:$D,MATCH('Shayak Income '!D61,'MPG Payment '!E:E,0)) -> Laldiyara | K61: Old | L61: 44958 | M61: =SUMIF('MPG Payment '!$E$3:$E$344841,'Shayak Income '!D61,'MPG Payment '!$I$3:$I$344841) -> 2239.6 | N61: =SUMIF('MPG Payment '!$E$3:$E$344841,'Shayak Income '!D61,'MPG Payment '!$J$3:$J$344841) -> 93575.11 | O61: =+M61*0.75 -> 1679.7 | P61: =+M61*0.95 -> 2127.62 | Q61: =SUMIF('MPG Payment '!$E$3:$E$344841,'Shayak Income '!D61,'MPG Payment '!$S$3:$S$344841) -> 0 | R61: =+N61*3% -> 2807.2533 | S61: =R61-P61 -> 679.6333 | T61: =M61*0.1 -> 223.96 | U61: =((((((IF(K61="New",0,SUMIF('MPG Payment '!$E$3:$E$344841,'Shayak Income '!D61,'MPG Payment '!$AC$3:$AC$344841))))+0)+0)+0)+0)+0 -> 827.03252 | V61: =ROUND((SUM(O61:Q61)-SUM(T61:U61)),0) -> 2756 | W61: =(((AN61-AO61)))+0 -> 0 | X61: =((MIN(IF(B61>0,MAX(N61*2%),0),B61)))+0 -> 0 | Y61: =IFERROR(VLOOKUP(D61,'Monthly Deduction'!$M$2:$N$640,2,0),0) -> 0 | Z61: 0 | AA61: =IFERROR(VLOOKUP(D61,'Monthly Deduction'!A:B,2,0),0) -> 0 | AB61: =ROUND(IFERROR(V61-SUM(W61:AA61),0),0) -> 2756 | AC61: 0 | AD61: =ROUND(AB61-AC61,0) -> 2756 | AE61: =IF(AC61<>0,"Yes","Release") -> Release | AG61: 0 | AI61: 0 | AK61: 94.6 | AL61: =COUNTIF(AK61:AK61,"=NA") -> 0 | AN61: =((MIN(IF(A61>0,MAX(N61*2%,1861),0),A61)))+0 -> 0 | AO61: =SUMIF('MPG Payment '!E:E,'Shayak Income '!D61,'MPG Payment '!AJ:AJ) -> 0 | AP61: =W61 -> 0 | AQ61: =AO61+AP61 -> 0 | AS61: =B61-X61 -> 0
A62: =IFERROR(VLOOKUP(D62,'Monthly Deduction'!$I$3:$J$957,2,0),0) -> 0 | B62: =IFERROR(VLOOKUP(D62,'Monthly Deduction'!$E$3:$F$957,2,0),0) -> 0 | C62: =A62+B62 -> 0 | D62: 10020067 | E62: =VLOOKUP(D62,'MPG Payment '!$E$3:$G$497305,2,0) -> ADARSH LAXMIPUR-2 | F62: =IFERROR(_xlfn.XLOOKUP(D62,'Monthly Deduction'!$I$3:$I$957,'Monthly Deduction'!$H$3:$H$957),0) -> 0 | G62: =VLOOKUP(D62,'MPG Payment '!$E$3:$G$333666,3,0) -> vlc | H62: =VLOOKUP(D62,'MPG Payment '!$E$3:$H$333666,4,0) -> Indirect | I62: =INDEX('MPG Payment '!$C:$C,MATCH('Shayak Income '!D62,'MPG Payment '!E:E,0)) -> 1002 | J62: =INDEX('MPG Payment '!$D:$D,MATCH('Shayak Income '!D62,'MPG Payment '!E:E,0)) -> Laldiyara | K62: Old | L62: 45423 | M62: =SUMIF('MPG Payment '!$E$3:$E$344841,'Shayak Income '!D62,'MPG Payment '!$I$3:$I$344841) -> 2566.8 | N62: =SUMIF('MPG Payment '!$E$3:$E$344841,'Shayak Income '!D62,'MPG Payment '!$J$3:$J$344841) -> 105856.79 | O62: =+M62*0.75 -> 1925.1 | P62: =+M62*0.95 -> 2438.46 | Q62: =SUMIF('MPG Payment '!$E$3:$E$344841,'Shayak Income '!D62,'MPG Payment '!$S$3:$S$344841) -> 0 | R62: =+N62*3% -> 3175.7037 | S62: =R62-P62 -> 737.2437 | T62: =M62*0.1 -> 256.68 | U62: =((((((IF(K62="New",0,SUMIF('MPG Payment '!$E$3:$E$344841,'Shayak Income '!D62,'MPG Payment '!$AC$3:$AC$344841))))+0)+0)+0)+0)+0 -> 0 | V62: =ROUND((SUM(O62:Q62)-SUM(T62:U62)),0) -> 4107 | W62: =(((AN62-AO62)))+0 -> 0 | X62: =((MIN(IF(B62>0,MAX(N62*2%),0),B62)))+0 -> 0 | Y62: =IFERROR(VLOOKUP(D62,'Monthly Deduction'!$M$2:$N$640,2,0),0) -> 0 | Z62: 0 | AA62: =IFERROR(VLOOKUP(D62,'Monthly Deduction'!A:B,2,0),0) -> 0 | AB62: =ROUND(IFERROR(V62-SUM(W62:AA62),0),0) -> 4107 | AC62: =AB62 -> 4107 | AD62: =ROUND(AB62-AC62,0) -> 0 | AE62: =IF(AC62<>0,"Yes","Release") -> Yes | AG62: 0 | AH62: Non pouring | AI62: 0 | AK62: 0 | AL62: =COUNTIF(AK62:AK62,"=NA") -> 0 | AN62: =((MIN(IF(A62>0,MAX(N62*2%,1861),0),A62)))+0 -> 0 | AO62: =SUMIF('MPG Payment '!E:E,'Shayak Income '!D62,'MPG Payment '!AJ:AJ) -> 0 | AP62: =W62 -> 0 | AQ62: =AO62+AP62 -> 0 | AS62: =B62-X62 -> 0
A63: =IFERROR(VLOOKUP(D63,'Monthly Deduction'!$I$3:$J$957,2,0),0) -> 17150.123 | B63: =IFERROR(VLOOKUP(D63,'Monthly Deduction'!$E$3:$F$957,2,0),0) -> 9080.5224 | C63: =A63+B63 -> 26230.645 | D63: 10020068 | E63: =VLOOKUP(D63,'MPG Payment '!$E$3:$G$497305,2,0) -> SABIKPUR | F63: =IFERROR(_xlfn.XLOOKUP(D63,'Monthly Deduction'!$I$3:$I$957,'Monthly Deduction'!$H$3:$H$957),0) -> 0 | G63: =VLOOKUP(D63,'MPG Payment '!$E$3:$G$333666,3,0) -> MPG | H63: =VLOOKUP(D63,'MPG Payment '!$E$3:$H$333666,4,0) -> Direct | I63: =INDEX('MPG Payment '!$C:$C,MATCH('Shayak Income '!D63,'MPG Payment '!E:E,0)) -> 1002 | J63: =INDEX('MPG Payment '!$D:$D,MATCH('Shayak Income '!D63,'MPG Payment '!E:E,0)) -> Laldiyara | K63: Old | L63: 45491 | M63: =SUMIF('MPG Payment '!$E$3:$E$344841,'Shayak Income '!D63,'MPG Payment '!$I$3:$I$344841) -> 5869.7 | N63: =SUMIF('MPG Payment '!$E$3:$E$344841,'Shayak Income '!D63,'MPG Payment '!$J$3:$J$344841) -> 253795.61 | O63: =+M63*0.75 -> 4402.275 | P63: =+M63*0.95 -> 5576.215 | Q63: =SUMIF('MPG Payment '!$E$3:$E$344841,'Shayak Income '!D63,'MPG Payment '!$S$3:$S$344841) -> 0 | R63: =+N63*3% -> 7613.8683 | S63: =R63-P63 -> 2037.6533 | T63: =M63*0.1 -> 586.97 | U63: =((((((IF(K63="New",0,SUMIF('MPG Payment '!$E$3:$E$344841,'Shayak Income '!D63,'MPG Payment '!$AC$3:$AC$344841))))+0)+0)+0)+0)+0 -> 0 | V63: =ROUND((SUM(O63:Q63)-SUM(T63:U63)),0) -> 9392 | W63: =(((AN63-AO63)))+0 -> 5075.9122 | X63: 0 | Y63: =IFERROR(VLOOKUP(D63,'Monthly Deduction'!$M$2:$N$640,2,0),0) -> 0 | Z63: 0 | AA63: =IFERROR(VLOOKUP(D63,'Monthly Deduction'!A:B,2,0),0) -> 0 | AB63: =ROUND(IFERROR(V63-SUM(W63:AA63),0),0) -> 4316 | AC63: =AB63 -> 4316 | AD63: =ROUND(AB63-AC63,0) -> 0 | AE63: =IF(AC63<>0,"Yes","Release") -> Yes | AG63: 0 | AH63: Agreement issue | AI63: 0 | AK63: 1413.1 | AL63: =COUNTIF(AK63:AK63,"=NA") -> 0 | AN63: =((MIN(IF(A63>0,MAX(N63*2%,1861),0),A63)))+0 -> 5075.9122 | AO63: =SUMIF('MPG Payment '!E:E,'Shayak Income '!D63,'MPG Payment '!AJ:AJ) -> 0 | AP63: =W63 -> 5075.9122 | AQ63: =AO63+AP63 -> 5075.9122 | AS63: =B63-X63 -> 9080.5224
A64: =IFERROR(VLOOKUP(D64,'Monthly Deduction'!$I$3:$J$957,2,0),0) -> 89601.603 | B64: =IFERROR(VLOOKUP(D64,'Monthly Deduction'!$E$3:$F$957,2,0),0) -> 9600 | C64: =A64+B64 -> 99201.603 | D64: 10020069 | E64: =VLOOKUP(D64,'MPG Payment '!$E$3:$G$497305,2,0) -> CHETAN-TOLA-KHUTHA | F64: =IFERROR(_xlfn.XLOOKUP(D64,'Monthly Deduction'!$I$3:$I$957,'Monthly Deduction'!$H$3:$H$957),0) -> 0 | G64: =VLOOKUP(D64,'MPG Payment '!$E$3:$G$333666,3,0) -> MPG | H64: =VLOOKUP(D64,'MPG Payment '!$E$3:$H$333666,4,0) -> Direct | I64: =INDEX('MPG Payment '!$C:$C,MATCH('Shayak Income '!D64,'MPG Payment '!E:E,0)) -> 1002 | J64: =INDEX('MPG Payment '!$D:$D,MATCH('Shayak Income '!D64,'MPG Payment '!E:E,0)) -> Laldiyara | K64: Old | L64: 45567 | M64: =SUMIF('MPG Payment '!$E$3:$E$344841,'Shayak Income '!D64,'MPG Payment '!$I$3:$I$344841) -> 728.2 | N64: =SUMIF('MPG Payment '!$E$3:$E$344841,'Shayak Income '!D64,'MPG Payment '!$J$3:$J$344841) -> 31582.78 | O64: =+M64*0.75 -> 546.15 | P64: =+M64*0.95 -> 691.79 | Q64: =SUMIF('MPG Payment '!$E$3:$E$344841,'Shayak Income '!D64,'MPG Payment '!$S$3:$S$344841) -> 47.14 | R64: =+N64*3% -> 947.4834 | S64: =R64-P64 -> 255.6934 | T64: =M64*0.1 -> 72.82 | U64: =((((((IF(K64="New",0,SUMIF('MPG Payment '!$E$3:$E$344841,'Shayak Income '!D64,'MPG Payment '!$AC$3:$AC$344841))))+0)+0)+0)+0)+-588 -> 1212.6101 | V64: =ROUND((SUM(O64:Q64)-SUM(T64:U64)),0) -> 0 | W64: 0 | X64: 0 | Y64: 0 | Z64: 0 | AA64: 0 | AB64: =ROUND(IFERROR(V64-SUM(W64:AA64),0),0) -> 0 | AC64: =AB64 -> 0 | AD64: =ROUND(AB64-AC64,0) -> 0 | AE64: =IF(AC64<>0,"Yes","Release") -> Release | AG64: 0 | AH64: Agreement issue / Down Payment | AI64: 20000 | AK64: 253.1 | AL64: =COUNTIF(AK64:AK64,"=NA") -> 0 | AN64: =((MIN(IF(A64>0,MAX(N64*2%,1861),0),A64)))+0 -> 1861 | AO64: =SUMIF('MPG Payment '!E:E,'Shayak Income '!D64,'MPG Payment '!AJ:AJ) -> 2000 | AP64: =W64 -> 0 | AQ64: =AO64+AP64 -> 2000 | AS64: =B64-X64 -> 9600
A65: =IFERROR(VLOOKUP(D65,'Monthly Deduction'!$I$3:$J$957,2,0),0) -> 31497.079 | B65: =IFERROR(VLOOKUP(D65,'Monthly Deduction'!$E$3:$F$957,2,0),0) -> 6400 | C65: =A65+B65 -> 37897.079 | D65: 10020070 | E65: =VLOOKUP(D65,'MPG Payment '!$E$3:$G$497305,2,0) -> LAXMIPUR | F65: =IFERROR(_xlfn.XLOOKUP(D65,'Monthly Deduction'!$I$3:$I$957,'Monthly Deduction'!$H$3:$H$957),0) -> 0 | G65: =VLOOKUP(D65,'MPG Payment '!$E$3:$G$333666,3,0) -> MPG | H65: =VLOOKUP(D65,'MPG Payment '!$E$3:$H$333666,4,0) -> Direct | I65: =INDEX('MPG Payment '!$C:$C,MATCH('Shayak Income '!D65,'MPG Payment '!E:E,0)) -> 1002 | J65: =INDEX('MPG Payment '!$D:$D,MATCH('Shayak Income '!D65,'MPG Payment '!E:E,0)) -> Laldiyara | K65: Old | L65: 45618 | M65: =SUMIF('MPG Payment '!$E$3:$E$344841,'Shayak Income '!D65,'MPG Payment '!$I$3:$I$344841) -> 3035.2 | N65: =SUMIF('MPG Payment '!$E$3:$E$344841,'Shayak Income '!D65,'MPG Payment '!$J$3:$J$344841) -> 121081.77 | O65: =+M65*0.75 -> 2276.4 | P65: =+M65*0.95 -> 2883.44 | Q65: =SUMIF('MPG Payment '!$E$3:$E$344841,'Shayak Income '!D65,'MPG Payment '!$S$3:$S$344841) -> 0 | R65: =+N65*3% -> 3632.4531 | S65: =R65-P65 -> 749.0131 | T65: =M65*0.1 -> 303.52 | U65: =((((((IF(K65="New",0,SUMIF('MPG Payment '!$E$3:$E$344841,'Shayak Income '!D65,'MPG Payment '!$AC$3:$AC$344841))))+0)+0)+0)+0)+0 -> 1.8499641 | V65: =ROUND((SUM(O65:Q65)-SUM(T65:U65)),0) -> 4854 | W65: =(((AN65-AO65)))+0 -> 2421.6354 | X65: 0 | Y65: =IFERROR(VLOOKUP(D65,'Monthly Deduction'!$M$2:$N$640,2,0),0) -> 465 | Z65: 0 | AA65: =IFERROR(VLOOKUP(D65,'Monthly Deduction'!A:B,2,0),0) -> 0 | AB65: =ROUND(IFERROR(V65-SUM(W65:AA65),0),0) -> 1967 | AC65: 0 | AD65: =ROUND(AB65-AC65,0) -> 1967 | AE65: =IF(AC65<>0,"Yes","Release") -> Release | AG65: 0 | AI65: 0 | AK65: 649 | AL65: =COUNTIF(AK65:AK65,"=NA") -> 0 | AN65: =((MIN(IF(A65>0,MAX(N65*2%,1861),0),A65)))+0 -> 2421.6354 | AO65: =SUMIF('MPG Payment '!E:E,'Shayak Income '!D65,'MPG Payment '!AJ:AJ) -> 0 | AP65: =W65 -> 2421.6354 | AQ65: =AO65+AP65 -> 2421.6354 | AS65: =B65-X65 -> 6400
A66: =IFERROR(VLOOKUP(D66,'Monthly Deduction'!$I$3:$J$957,2,0),0) -> 0 | B66: =IFERROR(VLOOKUP(D66,'Monthly Deduction'!$E$3:$F$957,2,0),0) -> 0 | C66: =A66+B66 -> 0 | D66: 10020073 | E66: =VLOOKUP(D66,'MPG Payment '!$E$3:$G$497305,2,0) -> REHUA RK | F66: =IFERROR(_xlfn.XLOOKUP(D66,'Monthly Deduction'!$I$3:$I$957,'Monthly Deduction'!$H$3:$H$957),0) -> 0 | G66: =VLOOKUP(D66,'MPG Payment '!$E$3:$G$333666,3,0) -> vlc | H66: =VLOOKUP(D66,'MPG Payment '!$E$3:$H$333666,4,0) -> Indirect | I66: =INDEX('MPG Payment '!$C:$C,MATCH('Shayak Income '!D66,'MPG Payment '!E:E,0)) -> 1002 | J66: =INDEX('MPG Payment '!$D:$D,MATCH('Shayak Income '!D66,'MPG Payment '!E:E,0)) -> Laldiyara | K66: Old | L66: 45638 | M66: =SUMIF('MPG Payment '!$E$3:$E$344841,'Shayak Income '!D66,'MPG Payment '!$I$3:$I$344841) -> 4010.4 | N66: =SUMIF('MPG Payment '!$E$3:$E$344841,'Shayak Income '!D66,'MPG Payment '!$J$3:$J$344841) -> 156744.07 | O66: =+M66*0.75 -> 3007.8 | P66: =+M66*0.95 -> 3809.88 | Q66: =SUMIF('MPG Payment '!$E$3:$E$344841,'Shayak Income '!D66,'MPG Payment '!$S$3:$S$344841) -> 0 | R66: =+N66*3% -> 4702.3221 | S66: =R66-P66 -> 892.4421 | T66: =M66*0.1 -> 401.04 | U66: =((((((IF(K66="New",0,SUMIF('MPG Payment '!$E$3:$E$344841,'Shayak Income '!D66,'MPG Payment '!$AC$3:$AC$344841))))+0)+0)+0)+0)+0 -> 0 | V66: =ROUND((SUM(O66:Q66)-SUM(T66:U66)),0) -> 6417 | W66: =(((AN66-AO66)))+0 -> 0 | X66: =((MIN(IF(B66>0,MAX(N66*2%),0),B66)))+0 -> 0 | Y66: =IFERROR(VLOOKUP(D66,'Monthly Deduction'!$M$2:$N$640,2,0),0) -> 0 | Z66: 0 | AA66: =IFERROR(VLOOKUP(D66,'Monthly Deduction'!A:B,2,0),0) -> 0 | AB66: =ROUND(IFERROR(V66-SUM(W66:AA66),0),0) -> 6417 | AC66: 0 | AD66: =ROUND(AB66-AC66,0) -> 6417 | AE66: =IF(AC66<>0,"Yes","Release") -> Release | AG66: 0 | AI66: 0 | AK66: 785 | AL66: =COUNTIF(AK66:AK66,"=NA") -> 0 | AN66: =((MIN(IF(A66>0,MAX(N66*2%,1861),0),A66)))+0 -> 0 | AO66: =SUMIF('MPG Payment '!E:E,'Shayak Income '!D66,'MPG Payment '!AJ:AJ) -> 0 | AP66: =W66 -> 0 | AQ66: =AO66+AP66 -> 0 | AS66: =B66-X66 -> 0
A67: =IFERROR(VLOOKUP(D67,'Monthly Deduction'!$I$3:$J$957,2,0),0) -> 79290.256 | B67: =IFERROR(VLOOKUP(D67,'Monthly Deduction'!$E$3:$F$957,2,0),0) -> 9600 | C67: =A67+B67 -> 88890.256 | D67: 10020075 | E67: =VLOOKUP(D67,'MPG Payment '!$E$3:$G$497305,2,0) -> RAMNAGAR | F67: =IFERROR(_xlfn.XLOOKUP(D67,'Monthly Deduction'!$I$3:$I$957,'Monthly Deduction'!$H$3:$H$957),0) -> 0 | G67: =VLOOKUP(D67,'MPG Payment '!$E$3:$G$333666,3,0) -> MPG | H67: =VLOOKUP(D67,'MPG Payment '!$E$3:$H$333666,4,0) -> Direct | I67: =INDEX('MPG Payment '!$C:$C,MATCH('Shayak Income '!D67,'MPG Payment '!E:E,0)) -> 1002 | J67: =INDEX('MPG Payment '!$D:$D,MATCH('Shayak Income '!D67,'MPG Payment '!E:E,0)) -> Laldiyara | K67: Old | L67: 45869 | M67: =SUMIF('MPG Payment '!$E$3:$E$344841,'Shayak Income '!D67,'MPG Payment '!$I$3:$I$344841) -> 977.7 | N67: =SUMIF('MPG Payment '!$E$3:$E$344841,'Shayak Income '!D67,'MPG Payment '!$J$3:$J$344841) -> 44315.44 | O67: =+M67*0.75 -> 733.275 | P67: =+M67*0.95 -> 928.815 | Q67: =SUMIF('MPG Payment '!$E$3:$E$344841,'Shayak Income '!D67,'MPG Payment '!$S$3:$S$344841) -> 21.52 | R67: =+N67*3% -> 1329.4632 | S67: =R67-P67 -> 400.6482 | T67: =M67*0.1 -> 97.77 | U67: =((((((IF(K67="New",0,SUMIF('MPG Payment '!$E$3:$E$344841,'Shayak Income '!D67,'MPG Payment '!$AC$3:$AC$344841))))+0)+0)+0)+0)+-66 -> 1585.4461 | V67: =ROUND((SUM(O67:Q67)-SUM(T67:U67)),0) -> 0 | W67: 0 | X67: 0 | Y67: 0 | Z67: 0 | AA67: 0 | AB67: =ROUND(IFERROR(V67-SUM(W67:AA67),0),0) -> 0 | AC67: 0 | AD67: =ROUND(AB67-AC67,0) -> 0 | AE67: =IF(AC67<>0,"Yes","Release") -> Release | AG67: 0 | AI67: 0 | AK67: 269.1 | AL67: =COUNTIF(AK67:AK67,"=NA") -> 0 | AN67: =((MIN(IF(A67>0,MAX(N67*2%,1861),0),A67)))+0 -> 1861 | AO67: =SUMIF('MPG Payment '!E:E,'Shayak Income '!D67,'MPG Payment '!AJ:AJ) -> 0 | AP67: =W67 -> 0 | AQ67: =AO67+AP67 -> 0 | AS67: =B67-X67 -> 9600
A68: =IFERROR(VLOOKUP(D68,'Monthly Deduction'!$I$3:$J$957,2,0),0) -> 73879.294 | B68: =IFERROR(VLOOKUP(D68,'Monthly Deduction'!$E$3:$F$957,2,0),0) -> 9600 | C68: =A68+B68 -> 83479.294 | D68: 10020077 | E68: =VLOOKUP(D68,'MPG Payment '!$E$3:$G$497305,2,0) -> BANSIPUR | F68: =IFERROR(_xlfn.XLOOKUP(D68,'Monthly Deduction'!$I$3:$I$957,'Monthly Deduction'!$H$3:$H$957),0) -> 0 | G68: =VLOOKUP(D68,'MPG Payment '!$E$3:$G$333666,3,0) -> MPG | H68: =VLOOKUP(D68,'MPG Payment '!$E$3:$H$333666,4,0) -> Direct | I68: =INDEX('MPG Payment '!$C:$C,MATCH('Shayak Income '!D68,'MPG Payment '!E:E,0)) -> 1002 | J68: =INDEX('MPG Payment '!$D:$D,MATCH('Shayak Income '!D68,'MPG Payment '!E:E,0)) -> Laldiyara | K68: Old | L68: 45869 | M68: =SUMIF('MPG Payment '!$E$3:$E$344841,'Shayak Income '!D68,'MPG Payment '!$I$3:$I$344841) -> 1117.5 | N68: =SUMIF('MPG Payment '!$E$3:$E$344841,'Shayak Income '!D68,'MPG Payment '!$J$3:$J$344841) -> 54943.33 | O68: =+M68*0.75 -> 838.125 | P68: =+M68*0.95 -> 1061.625 | Q68: =SUMIF('MPG Payment '!$E$3:$E$344841,'Shayak Income '!D68,'MPG Payment '!$S$3:$S$344841) -> 0 | R68: =+N68*3% -> 1648.2999 | S68: =R68-P68 -> 586.6749 | T68: =M68*0.1 -> 111.75 | U68: =((((((IF(K68="New",0,SUMIF('MPG Payment '!$E$3:$E$344841,'Shayak Income '!D68,'MPG Payment '!$AC$3:$AC$344841))))+0)+0)+0)+0)+0 -> 1651.1341 | V68: =ROUND((SUM(O68:Q68)-SUM(T68:U68)),0) -> 137 | W68: 0 | X68: 137 | Y68: =IFERROR(VLOOKUP(D68,'Monthly Deduction'!$M$2:$N$640,2,0),0) -> 0 | Z68: 0 | AA68: =IFERROR(VLOOKUP(D68,'Monthly Deduction'!A:B,2,0),0) -> 0 | AB68: =ROUND(IFERROR(V68-SUM(W68:AA68),0),0) -> 0 | AC68: 0 | AD68: =ROUND(AB68-AC68,0) -> 0 | AE68: =IF(AC68<>0,"Yes","Release") -> Release | AG68: 0 | AI68: 0 | AK68: 166.3 | AL68: =COUNTIF(AK68:AK68,"=NA") -> 0 | AN68: =((MIN(IF(A68>0,MAX(N68*2%,1861),0),A68)))+0 -> 1861 | AO68: =SUMIF('MPG Payment '!E:E,'Shayak Income '!D68,'MPG Payment '!AJ:AJ) -> 2000 | AP68: =W68 -> 0 | AQ68: =AO68+AP68 -> 2000 | AS68: =B68-X68 -> 9463
A69: =IFERROR(VLOOKUP(D69,'Monthly Deduction'!$I$3:$J$957,2,0),0) -> 88157 | B69: =IFERROR(VLOOKUP(D69,'Monthly Deduction'!$E$3:$F$957,2,0),0) -> 6400 | C69: =A69+B69 -> 94557 | D69: 10020078 | E69: =VLOOKUP(D69,'MPG Payment '!$E$3:$G$497305,2,0) -> GODIH | F69: =IFERROR(_xlfn.XLOOKUP(D69,'Monthly Deduction'!$I$3:$I$957,'Monthly Deduction'!$H$3:$H$957),0) -> 0 | G69: =VLOOKUP(D69,'MPG Payment '!$E$3:$G$333666,3,0) -> MPG | H69: =VLOOKUP(D69,'MPG Payment '!$E$3:$H$333666,4,0) -> Direct | I69: =INDEX('MPG Payment '!$C:$C,MATCH('Shayak Income '!D69,'MPG Payment '!E:E,0)) -> 1002 | J69: =INDEX('MPG Payment '!$D:$D,MATCH('Shayak Income '!D69,'MPG Payment '!E:E,0)) -> Laldiyara | K69: Old | L69: 45869 | M69: =SUMIF('MPG Payment '!$E$3:$E$344841,'Shayak Income '!D69,'MPG Payment '!$I$3:$I$344841) -> 2125.2 | N69: =SUMIF('MPG Payment '!$E$3:$E$344841,'Shayak Income '!D69,'MPG Payment '!$J$3:$J$344841) -> 91984.34 | O69: =+M69*0.75 -> 1593.9 | P69: =+M69*0.95 -> 2018.94 | Q69: =SUMIF('MPG Payment '!$E$3:$E$344841,'Shayak Income '!D69,'MPG Payment '!$S$3:$S$344841) -> 0 | R69: =+N69*3% -> 2759.5302 | S69: =R69-P69 -> 740.5902 | T69: =M69*0.1 -> 212.52 | U69: =((((((IF(K69="New",0,SUMIF('MPG Payment '!$E$3:$E$344841,'Shayak Income '!D69,'MPG Payment '!$AC$3:$AC$344841))))+0)+0)+0)+0)+0 -> 582.57256 | V69: =ROUND((SUM(O69:Q69)-SUM(T69:U69)),0) -> 2818 | W69: =(((AN69-AO69)))+0 -> 1861 | X69: 0 | Y69: =IFERROR(VLOOKUP(D69,'Monthly Deduction'!$M$2:$N$640,2,0),0) -> 0 | Z69: 0 | AA69: =IFERROR(VLOOKUP(D69,'Monthly Deduction'!A:B,2,0),0) -> 0 | AB69: =ROUND(IFERROR(V69-SUM(W69:AA69),0),0) -> 957 | AC69: =AB69 -> 957 | AD69: =ROUND(AB69-AC69,0) -> 0 | AE69: =IF(AC69<>0,"Yes","Release") -> Yes | AG69: 0 | AH69: Down Payment | AI69: 9637 | AK69: 364.6 | AL69: =COUNTIF(AK69:AK69,"=NA") -> 0 | AN69: =((MIN(IF(A69>0,MAX(N69*2%,1861),0),A69)))+0 -> 1861 | AO69: =SUMIF('MPG Payment '!E:E,'Shayak Income '!D69,'MPG Payment '!AJ:AJ) -> 0 | AP69: =W69 -> 1861 | AQ69: =AO69+AP69 -> 1861 | AS69: =B69-X69 -> 6400
A70: =IFERROR(VLOOKUP(D70,'Monthly Deduction'!$I$3:$J$957,2,0),0) -> 90961 | B70: =IFERROR(VLOOKUP(D70,'Monthly Deduction'!$E$3:$F$957,2,0),0) -> 6400 | C70: =A70+B70 -> 97361 | D70: 10020079 | E70: =VLOOKUP(D70,'MPG Payment '!$E$3:$G$497305,2,0) -> SINGARPUR | F70: =IFERROR(_xlfn.XLOOKUP(D70,'Monthly Deduction'!$I$3:$I$957,'Monthly Deduction'!$H$3:$H$957),0) -> 0 | G70: =VLOOKUP(D70,'MPG Payment '!$E$3:$G$333666,3,0) -> MPG | H70: =VLOOKUP(D70,'MPG Payment '!$E$3:$H$333666,4,0) -> Direct | I70: =INDEX('MPG Payment '!$C:$C,MATCH('Shayak Income '!D70,'MPG Payment '!E:E,0)) -> 1002 | J70: =INDEX('MPG Payment '!$D:$D,MATCH('Shayak Income '!D70,'MPG Payment '!E:E,0)) -> Laldiyara | K70: Old | L70: 45869 | M70: =SUMIF('MPG Payment '!$E$3:$E$344841,'Shayak Income '!D70,'MPG Payment '!$I$3:$I$344841) -> 394.9 | N70: =SUMIF('MPG Payment '!$E$3:$E$344841,'Shayak Income '!D70,'MPG Payment '!$J$3:$J$344841) -> 17651.47 | O70: =+M70*0.75 -> 296.175 | P70: =+M70*0.95 -> 375.155 | Q70: =SUMIF('MPG Payment '!$E$3:$E$344841,'Shayak Income '!D70,'MPG Payment '!$S$3:$S$344841) -> 0 | R70: =+N70*3% -> 529.5441 | S70: =R70-P70 -> 154.3891 | T70: =M70*0.1 -> 39.49 | U70: =((((((IF(K70="New",0,SUMIF('MPG Payment '!$E$3:$E$344841,'Shayak Income '!D70,'MPG Payment '!$AC$3:$AC$344841))))+0)+0)+0)+0)+-1509 -> 632.25489 | V70: =ROUND((SUM(O70:Q70)-SUM(T70:U70)),0) -> 0 | W70: 0 | X70: 0 | Y70: 0 | Z70: 0 | AA70: 0 | AB70: =ROUND(IFERROR(V70-SUM(W70:AA70),0),0) -> 0 | AC70: =AB70 -> 0 | AD70: =ROUND(AB70-AC70,0) -> 0 | AE70: =IF(AC70<>0,"Yes","Release") -> Release | AG70: 0 | AH70: Non pouring / Down Payment | AI70: 9580 | AK70: 0 | AL70: =COUNTIF(AK70:AK70,"=NA") -> 0 | AN70: =((MIN(IF(A70>0,MAX(N70*2%,1861),0),A70)))+0 -> 1861 | AO70: =SUMIF('MPG Payment '!E:E,'Shayak Income '!D70,'MPG Payment '!AJ:AJ) -> 2000 | AP70: =W70 -> 0 | AQ70: =AO70+AP70 -> 2000 | AS70: =B70-X70 -> 6400
A71: =IFERROR(VLOOKUP(D71,'Monthly Deduction'!$I$3:$J$957,2,0),0) -> 0 | B71: =IFERROR(VLOOKUP(D71,'Monthly Deduction'!$E$3:$F$957,2,0),0) -> 0 | C71: =A71+B71 -> 0 | D71: 10030002 | E71: =VLOOKUP(D71,'MPG Payment '!$E$3:$G$497305,2,0) -> MOHANPUR | F71: =IFERROR(_xlfn.XLOOKUP(D71,'Monthly Deduction'!$I$3:$I$957,'Monthly Deduction'!$H$3:$H$957),0) -> 0 | G71: =VLOOKUP(D71,'MPG Payment '!$E$3:$G$333666,3,0) -> vlc | H71: =VLOOKUP(D71,'MPG Payment '!$E$3:$H$333666,4,0) -> Indirect | I71: =INDEX('MPG Payment '!$C:$C,MATCH('Shayak Income '!D71,'MPG Payment '!E:E,0)) -> 1003 | J71: =INDEX('MPG Payment '!$D:$D,MATCH('Shayak Income '!D71,'MPG Payment '!E:E,0)) -> Asarganj | K71: Old | L71: 42979 | M71: =SUMIF('MPG Payment '!$E$3:$E$344841,'Shayak Income '!D71,'MPG Payment '!$I$3:$I$344841) -> 2186.05 | N71: =SUMIF('MPG Payment '!$E$3:$E$344841,'Shayak Income '!D71,'MPG Payment '!$J$3:$J$344841) -> 93216.55 | O71: =+M71*0.75 -> 1639.5375 | P71: =+M71*0.95 -> 2076.7475 | Q71: =SUMIF('MPG Payment '!$E$3:$E$344841,'Shayak Income '!D71,'MPG Payment '!$S$3:$S$344841) -> 0 | R71: =+N71*3% -> 2796.4965 | S71: =R71-P71 -> 719.749 | T71: =M71*0.1 -> 218.605 | U71: =((((((IF(K71="New",0,SUMIF('MPG Payment '!$E$3:$E$344841,'Shayak Income '!D71,'MPG Payment '!$AC$3:$AC$344841))))+0)+0)+0)+0)+0 -> 523.30748 | V71: =ROUND((SUM(O71:Q71)-SUM(T71:U71)),0) -> 2974 | W71: =(((AN71-AO71)))+0 -> 0 | X71: =((MIN(IF(B71>0,MAX(N71*2%),0),B71)))+0 -> 0 | Y71: =IFERROR(VLOOKUP(D71,'Monthly Deduction'!$M$2:$N$640,2,0),0) -> 0 | Z71: 0 | AA71: =IFERROR(VLOOKUP(D71,'Monthly Deduction'!A:B,2,0),0) -> 0 | AB71: =ROUND(IFERROR(V71-SUM(W71:AA71),0),0) -> 2974 | AC71: 0 | AD71: =ROUND(AB71-AC71,0) -> 2974 | AE71: =IF(AC71<>0,"Yes","Release") -> Release | AG71: 0 | AI71: 0 | AK71: 549.1 | AL71: =COUNTIF(AK71:AK71,"=NA") -> 0 | AN71: =((MIN(IF(A71>0,MAX(N71*2%,1861),0),A71)))+0 -> 0 | AO71: =SUMIF('MPG Payment '!E:E,'Shayak Income '!D71,'MPG Payment '!AJ:AJ) -> 0 | AP71: =W71 -> 0 | AQ71: =AO71+AP71 -> 0 | AS71: =B71-X71 -> 0
A72: =IFERROR(VLOOKUP(D72,'Monthly Deduction'!$I$3:$J$957,2,0),0) -> 0 | B72: =IFERROR(VLOOKUP(D72,'Monthly Deduction'!$E$3:$F$957,2,0),0) -> 0 | C72: =A72+B72 -> 0 | D72: 10030003 | E72: =VLOOKUP(D72,'MPG Payment '!$E$3:$G$497305,2,0) -> CHATMADIH | F72: =IFERROR(_xlfn.XLOOKUP(D72,'Monthly Deduction'!$I$3:$I$957,'Monthly Deduction'!$H$3:$H$957),0) -> 0 | G72: =VLOOKUP(D72,'MPG Payment '!$E$3:$G$333666,3,0) -> MPG | H72: =VLOOKUP(D72,'MPG Payment '!$E$3:$H$333666,4,0) -> Direct | I72: =INDEX('MPG Payment '!$C:$C,MATCH('Shayak Income '!D72,'MPG Payment '!E:E,0)) -> 1003 | J72: =INDEX('MPG Payment '!$D:$D,MATCH('Shayak Income '!D72,'MPG Payment '!E:E,0)) -> Asarganj | K72: Old | L72: 42979 | M72: =SUMIF('MPG Payment '!$E$3:$E$344841,'Shayak Income '!D72,'MPG Payment '!$I$3:$I$344841) -> 7341.7 | N72: =SUMIF('MPG Payment '!$E$3:$E$344841,'Shayak Income '!D72,'MPG Payment '!$J$3:$J$344841) -> 355291.88 | O72: =+M72*0.75 -> 5506.275 | P72: =+M72*0.95 -> 6974.615 | Q72: =SUMIF('MPG Payment '!$E$3:$E$344841,'Shayak Income '!D72,'MPG Payment '!$S$3:$S$344841) -> 7610.82 | R72: =+N72*3% -> 10658.756 | S72: =R72-P72 -> 3684.1414 | T72: =M72*0.1 -> 734.17 | U72: =((((((IF(K72="New",0,SUMIF('MPG Payment '!$E$3:$E$344841,'Shayak Income '!D72,'MPG Payment '!$AC$3:$AC$344841))))+0)+0)+0)+0)+0 -> 0 | V72: =ROUND((SUM(O72:Q72)-SUM(T72:U72)),0) -> 19358 | W72: =(((AN72-AO72)))+0 -> 0 | X72: =((MIN(IF(B72>0,MAX(N72*2%),0),B72)))+0 -> 0 | Y72: =IFERROR(VLOOKUP(D72,'Monthly Deduction'!$M$2:$N$640,2,0),0) -> 0 | Z72: 2336.4 | AA72: =IFERROR(VLOOKUP(D72,'Monthly Deduction'!A:B,2,0),0) -> 0 | AB72: =ROUND(IFERROR(V72-SUM(W72:AA72),0),0) -> 17022 | AC72: 0 | AD72: =ROUND(AB72-AC72,0) -> 17022 | AE72: =IF(AC72<>0,"Yes","Release") -> Release | AG72: 0 | AH72: EIPL Deduction | AI72: 0 | AK72: 1671.7 | AL72: =COUNTIF(AK72:AK72,"=NA") -> 0 | AN72: =((MIN(IF(A72>0,MAX(N72*2%,1861),0),A72)))+0 -> 0 | AO72: =SUMIF('MPG Payment '!E:E,'Shayak Income '!D72,'MPG Payment '!AJ:AJ) -> 0 | AP72: =W72 -> 0 | AQ72: =AO72+AP72 -> 0 | AS72: =B72-X72 -> 0
A73: =IFERROR(VLOOKUP(D73,'Monthly Deduction'!$I$3:$J$957,2,0),0) -> 0 | B73: =IFERROR(VLOOKUP(D73,'Monthly Deduction'!$E$3:$F$957,2,0),0) -> 0 | C73: =A73+B73 -> 0 | D73: 10030007 | E73: =VLOOKUP(D73,'MPG Payment '!$E$3:$G$497305,2,0) -> SIYADIH | F73: =IFERROR(_xlfn.XLOOKUP(D73,'Monthly Deduction'!$I$3:$I$957,'Monthly Deduction'!$H$3:$H$957),0) -> 0 | G73: =VLOOKUP(D73,'MPG Payment '!$E$3:$G$333666,3,0) -> vlc | H73: =VLOOKUP(D73,'MPG Payment '!$E$3:$H$333666,4,0) -> Indirect | I73: =INDEX('MPG Payment '!$C:$C,MATCH('Shayak Income '!D73,'MPG Payment '!E:E,0)) -> 1003 | J73: =INDEX('MPG Payment '!$D:$D,MATCH('Shayak Income '!D73,'MPG Payment '!E:E,0)) -> Asarganj | K73: Old | L73: 42979 | M73: =SUMIF('MPG Payment '!$E$3:$E$344841,'Shayak Income '!D73,'MPG Payment '!$I$3:$I$344841) -> 3021.5 | N73: =SUMIF('MPG Payment '!$E$3:$E$344841,'Shayak Income '!D73,'MPG Payment '!$J$3:$J$344841) -> 92549.31 | O73: =+M73*0.75 -> 2266.125 | P73: =+M73*0.95 -> 2870.425 | Q73: =SUMIF('MPG Payment '!$E$3:$E$344841,'Shayak Income '!D73,'MPG Payment '!$S$3:$S$344841) -> 0 | R73: =+N73*3% -> 2776.4793 | S73: =R73-P73 -> -93.9457 | T73: =M73*0.1 -> 302.15 | U73: =((((((IF(K73="New",0,SUMIF('MPG Payment '!$E$3:$E$344841,'Shayak Income '!D73,'MPG Payment '!$AC$3:$AC$344841))))+0)+0)+0)+0)+0 -> 25.466496 | V73: =ROUND((SUM(O73:Q73)-SUM(T73:U73)),0) -> 4809 | W73: =(((AN73-AO73)))+0 -> 0 | X73: =((MIN(IF(B73>0,MAX(N73*2%),0),B73)))+0 -> 0 | Y73: =IFERROR(VLOOKUP(D73,'Monthly Deduction'!$M$2:$N$640,2,0),0) -> 0 | Z73: 0 | AA73: =IFERROR(VLOOKUP(D73,'Monthly Deduction'!A:B,2,0),0) -> 0 | AB73: =ROUND(IFERROR(V73-SUM(W73:AA73),0),0) -> 4809 | AC73: 0 | AD73: =ROUND(AB73-AC73,0) -> 4809 | AE73: =IF(AC73<>0,"Yes","Release") -> Release | AG73: 0 | AI73: 0 | AK73: 740.55 | AL73: =COUNTIF(AK73:AK73,"=NA") -> 0 | AN73: =((MIN(IF(A73>0,MAX(N73*2%,1861),0),A73)))+0 -> 0 | AO73: =SUMIF('MPG Payment '!E:E,'Shayak Income '!D73,'MPG Payment '!AJ:AJ) -> 0 | AP73: =W73 -> 0 | AQ73: =AO73+AP73 -> 0 | AS73: =B73-X73 -> 0
A74: =IFERROR(VLOOKUP(D74,'Monthly Deduction'!$I$3:$J$957,2,0),0) -> 0 | B74: =IFERROR(VLOOKUP(D74,'Monthly Deduction'!$E$3:$F$957,2,0),0) -> 0 | C74: =A74+B74 -> 0 | D74: 10030009 | E74: =VLOOKUP(D74,'MPG Payment '!$E$3:$G$497305,2,0) -> Gomukh ID Laldiyara | F74: =IFERROR(_xlfn.XLOOKUP(D74,'Monthly Deduction'!$I$3:$I$957,'Monthly Deduction'!$H$3:$H$957),0) -> 0 | G74: =VLOOKUP(D74,'MPG Payment '!$E$3:$G$333666,3,0) -> vlc | H74: =VLOOKUP(D74,'MPG Payment '!$E$3:$H$333666,4,0) -> Indirect | I74: =INDEX('MPG Payment '!$C:$C,MATCH('Shayak Income '!D74,'MPG Payment '!E:E,0)) -> 1003 | J74: =INDEX('MPG Payment '!$D:$D,MATCH('Shayak Income '!D74,'MPG Payment '!E:E,0)) -> Asarganj | K74: Old | L74: 43315 | M74: =SUMIF('MPG Payment '!$E$3:$E$344841,'Shayak Income '!D74,'MPG Payment '!$I$3:$I$344841) -> 45084.25 | N74: =SUMIF('MPG Payment '!$E$3:$E$344841,'Shayak Income '!D74,'MPG Payment '!$J$3:$J$344841) -> 1889255 | O74: =+M74*0.75 -> 33813.188 | P74: =+M74*0.95 -> 42830.037 | Q74: =SUMIF('MPG Payment '!$E$3:$E$344841,'Shayak Income '!D74,'MPG Payment '!$S$3:$S$344841) -> 0 | R74: =+N74*3% -> 56677.651 | S74: =R74-P74 -> 13847.613 | T74: =M74*0.1 -> 4508.425 | U74: =((((((IF(K74="New",0,SUMIF('MPG Payment '!$E$3:$E$344841,'Shayak Income '!D74,'MPG Payment '!$AC$3:$AC$344841))))+0)+0)+0)+0)+0 -> 0 | V74: =ROUND((SUM(O74:Q74)-SUM(T74:U74)),0) -> 72135 | W74: =(((AN74-AO74)))+0 -> 0 | X74: =((MIN(IF(B74>0,MAX(N74*2%),0),B74)))+0 -> 0 | Y74: =IFERROR(VLOOKUP(D74,'Monthly Deduction'!$M$2:$N$640,2,0),0) -> 0 | Z74: 0 | AA74: =IFERROR(VLOOKUP(D74,'Monthly Deduction'!A:B,2,0),0) -> 0 | AB74: =ROUND(IFERROR(V74-SUM(W74:AA74),0),0) -> 72135 | AC74: 0 | AD74: =ROUND(AB74-AC74,0) -> 72135 | AE74: =IF(AC74<>0,"Yes","Release") -> Release | AG74: 0 | AI74: 0 | AK74: 9313.7 | AL74: =COUNTIF(AK74:AK74,"=NA") -> 0 | AN74: =((MIN(IF(A74>0,MAX(N74*2%,1861),0),A74)))+0 -> 0 | AO74: =SUMIF('MPG Payment '!E:E,'Shayak Income '!D74,'MPG Payment '!AJ:AJ) -> 0 | AP74: =W74 -> 0 | AQ74: =AO74+AP74 -> 0 | AS74: =B74-X74 -> 0
A75: =IFERROR(VLOOKUP(D75,'Monthly Deduction'!$I$3:$J$957,2,0),0) -> 38142.523 | B75: =IFERROR(VLOOKUP(D75,'Monthly Deduction'!$E$3:$F$957,2,0),0) -> 4335 | C75: =A75+B75 -> 42477.523 | D75: 10030010 | E75: =VLOOKUP(D75,'MPG Payment '!$E$3:$G$497305,2,0) -> KATHNI | F75: =IFERROR(_xlfn.XLOOKUP(D75,'Monthly Deduction'!$I$3:$I$957,'Monthly Deduction'!$H$3:$H$957),0) -> 0 | G75: =VLOOKUP(D75,'MPG Payment '!$E$3:$G$333666,3,0) -> MPG | H75: =VLOOKUP(D75,'MPG Payment '!$E$3:$H$333666,4,0) -> Direct | I75: =INDEX('MPG Payment '!$C:$C,MATCH('Shayak Income '!D75,'MPG Payment '!E:E,0)) -> 1003 | J75: =INDEX('MPG Payment '!$D:$D,MATCH('Shayak Income '!D75,'MPG Payment '!E:E,0)) -> Asarganj | K75: Old | L75: 43315 | M75: =SUMIF('MPG Payment '!$E$3:$E$344841,'Shayak Income '!D75,'MPG Payment '!$I$3:$I$344841) -> 963.9 | N75: =SUMIF('MPG Payment '!$E$3:$E$344841,'Shayak Income '!D75,'MPG Payment '!$J$3:$J$344841) -> 34739.43 | O75: =+M75*0.75 -> 722.925 | P75: =+M75*0.95 -> 915.705 | Q75: =SUMIF('MPG Payment '!$E$3:$E$344841,'Shayak Income '!D75,'MPG Payment '!$S$3:$S$344841) -> 0 | R75: =+N75*3% -> 1042.1829 | S75: =R75-P75 -> 126.4779 | T75: =M75*0.1 -> 96.39 | U75: =((((((IF(K75="New",0,SUMIF('MPG Payment '!$E$3:$E$344841,'Shayak Income '!D75,'MPG Payment '!$AC$3:$AC$344841))))+0)+0)+0)+0)+0 -> 1321.0489 | V75: =ROUND((SUM(O75:Q75)-SUM(T75:U75)),0) -> 221 | W75: 221 | X75: 0 | Y75: =IFERROR(VLOOKUP(D75,'Monthly Deduction'!$M$2:$N$640,2,0),0) -> 0 | Z75: 0 | AA75: =IFERROR(VLOOKUP(D75,'Monthly Deduction'!A:B,2,0),0) -> 0 | AB75: =ROUND(IFERROR(V75-SUM(W75:AA75),0),0) -> 0 | AC75: 0 | AD75: =ROUND(AB75-AC75,0) -> 0 | AE75: =IF(AC75<>0,"Yes","Release") -> Release | AG75: 0 | AI75: 0 | AK75: 146.3 | AL75: =COUNTIF(AK75:AK75,"=NA") -> 0 | AN75: =((MIN(IF(A75>0,MAX(N75*2%,1861),0),A75)))+0 -> 1861 | AO75: =SUMIF('MPG Payment '!E:E,'Shayak Income '!D75,'MPG Payment '!AJ:AJ) -> 0 | AP75: =W75 -> 221 | AQ75: =AO75+AP75 -> 221 | AS75: =B75-X75 -> 4335
A76: =IFERROR(VLOOKUP(D76,'Monthly Deduction'!$I$3:$J$957,2,0),0) -> 0 | B76: =IFERROR(VLOOKUP(D76,'Monthly Deduction'!$E$3:$F$957,2,0),0) -> 0 | C76: =A76+B76 -> 0 | D76: 10030011 | E76: =VLOOKUP(D76,'MPG Payment '!$E$3:$G$497305,2,0) -> DEVDHA GOMUKH MPG | F76: =IFERROR(_xlfn.XLOOKUP(D76,'Monthly Deduction'!$I$3:$I$957,'Monthly Deduction'!$H$3:$H$957),0) -> 0 | G76: =VLOOKUP(D76,'MPG Payment '!$E$3:$G$333666,3,0) -> MPG | H76: =VLOOKUP(D76,'MPG Payment '!$E$3:$H$333666,4,0) -> Direct | I76: =INDEX('MPG Payment '!$C:$C,MATCH('Shayak Income '!D76,'MPG Payment '!E:E,0)) -> 1003 | J76: =INDEX('MPG Payment '!$D:$D,MATCH('Shayak Income '!D76,'MPG Payment '!E:E,0)) -> Asarganj | K76: Old | L76: 43343 | M76: =SUMIF('MPG Payment '!$E$3:$E$344841,'Shayak Income '!D76,'MPG Payment '!$I$3:$I$344841) -> 5989.35 | N76: =SUMIF('MPG Payment '!$E$3:$E$344841,'Shayak Income '!D76,'MPG Payment '!$J$3:$J$344841) -> 256054.57 | O76: =+M76*0.75 -> 4492.0125 | P76: =+M76*0.95 -> 5689.8825 | Q76: =SUMIF('MPG Payment '!$E$3:$E$344841,'Shayak Income '!D76,'MPG Payment '!$S$3:$S$344841) -> 1165.79 | R76: =+N76*3% -> 7681.6371 | S76: =R76-P76 -> 1991.7546 | T76: =M76*0.1 -> 598.935 | U76: =((((((IF(K76="New",0,SUMIF('MPG Payment '!$E$3:$E$344841,'Shayak Income '!D76,'MPG Payment '!$AC$3:$AC$344841))))+0)+0)+0)+0)+0 -> 0 | V76: =ROUND((SUM(O76:Q76)-SUM(T76:U76)),0) -> 10749 | W76: =(((AN76-AO76)))+0 -> 0 | X76: =((MIN(IF(B76>0,MAX(N76*2%),0),B76)))+0 -> 0 | Y76: =IFERROR(VLOOKUP(D76,'Monthly Deduction'!$M$2:$N$640,2,0),0) -> 2700 | Z76: 0 | AA76: =IFERROR(VLOOKUP(D76,'Monthly Deduction'!A:B,2,0),0) -> 0 | AB76: =ROUND(IFERROR(V76-SUM(W76:AA76),0),0) -> 8049 | AC76: 0 | AD76: =ROUND(AB76-AC76,0) -> 8049 | AE76: =IF(AC76<>0,"Yes","Release") -> Release | AG76: 0 | AI76: 0 | AK76: 1359.25 | AL76: =COUNTIF(AK76:AK76,"=NA") -> 0 | AN76: =((MIN(IF(A76>0,MAX(N76*2%,1861),0),A76)))+0 -> 0 | AO76: =SUMIF('MPG Payment '!E:E,'Shayak Income '!D76,'MPG Payment '!AJ:AJ) -> 0 | AP76: =W76 -> 0 | AQ76: =AO76+AP76 -> 0 | AS76: =B76-X76 -> 0
A77: =IFERROR(VLOOKUP(D77,'Monthly Deduction'!$I$3:$J$957,2,0),0) -> 0 | B77: =IFERROR(VLOOKUP(D77,'Monthly Deduction'!$E$3:$F$957,2,0),0) -> 0 | C77: =A77+B77 -> 0 | D77: 10030012 | E77: =VLOOKUP(D77,'MPG Payment '!$E$3:$G$497305,2,0) -> KASBA(MANGOAN) | F77: =IFERROR(_xlfn.XLOOKUP(D77,'Monthly Deduction'!$I$3:$I$957,'Monthly Deduction'!$H$3:$H$957),0) -> 0 | G77: =VLOOKUP(D77,'MPG Payment '!$E$3:$G$333666,3,0) -> vlc | H77: =VLOOKUP(D77,'MPG Payment '!$E$3:$H$333666,4,0) -> Indirect | I77: =INDEX('MPG Payment '!$C:$C,MATCH('Shayak Income '!D77,'MPG Payment '!E:E,0)) -> 1003 | J77: =INDEX('MPG Payment '!$D:$D,MATCH('Shayak Income '!D77,'MPG Payment '!E:E,0)) -> Asarganj | K77: Old | L77: 44652 | M77: =SUMIF('MPG Payment '!$E$3:$E$344841,'Shayak Income '!D77,'MPG Payment '!$I$3:$I$344841) -> 2114 | N77: =SUMIF('MPG Payment '!$E$3:$E$344841,'Shayak Income '!D77,'MPG Payment '!$J$3:$J$344841) -> 75620.4 | O77: =+M77*0.75 -> 1585.5 | P77: =+M77*0.95 -> 2008.3 | Q77: =SUMIF('MPG Payment '!$E$3:$E$344841,'Shayak Income '!D77,'MPG Payment '!$S$3:$S$344841) -> 0 | R77: =+N77*3% -> 2268.612 | S77: =R77-P77 -> 260.312 | T77: =M77*0.1 -> 211.4 | U77: =((((((IF(K77="New",0,SUMIF('MPG Payment '!$E$3:$E$344841,'Shayak Income '!D77,'MPG Payment '!$AC$3:$AC$344841))))+0)+0)+0)+0)+0 -> 830.70472 | V77: =ROUND((SUM(O77:Q77)-SUM(T77:U77)),0) -> 2552 | W77: =(((AN77-AO77)))+0 -> 0 | X77: =((MIN(IF(B77>0,MAX(N77*2%),0),B77)))+0 -> 0 | Y77: =IFERROR(VLOOKUP(D77,'Monthly Deduction'!$M$2:$N$640,2,0),0) -> 0 | Z77: 0 | AA77: =IFERROR(VLOOKUP(D77,'Monthly Deduction'!A:B,2,0),0) -> 0 | AB77: =ROUND(IFERROR(V77-SUM(W77:AA77),0),0) -> 2552 | AC77: 0 | AD77: =ROUND(AB77-AC77,0) -> 2552 | AE77: =IF(AC77<>0,"Yes","Release") -> Release | AG77: 0 | AI77: 0 | AK77: 495 | AL77: =COUNTIF(AK77:AK77,"=NA") -> 0 | AN77: =((MIN(IF(A77>0,MAX(N77*2%,1861),0),A77)))+0 -> 0 | AO77: =SUMIF('MPG Payment '!E:E,'Shayak Income '!D77,'MPG Payment '!AJ:AJ) -> 0 | AP77: =W77 -> 0 | AQ77: =AO77+AP77 -> 0 | AS77: =B77-X77 -> 0
A78: =IFERROR(VLOOKUP(D78,'Monthly Deduction'!$I$3:$J$957,2,0),0) -> 0 | B78: =IFERROR(VLOOKUP(D78,'Monthly Deduction'!$E$3:$F$957,2,0),0) -> 3904.7687 | C78: =A78+B78 -> 3904.7687 | D78: 10030013 | E78: =VLOOKUP(D78,'MPG Payment '!$E$3:$G$497305,2,0) -> LOHRA | F78: =IFERROR(_xlfn.XLOOKUP(D78,'Monthly Deduction'!$I$3:$I$957,'Monthly Deduction'!$H$3:$H$957),0) -> 0 | G78: =VLOOKUP(D78,'MPG Payment '!$E$3:$G$333666,3,0) -> MPG | H78: =VLOOKUP(D78,'MPG Payment '!$E$3:$H$333666,4,0) -> Direct | I78: =INDEX('MPG Payment '!$C:$C,MATCH('Shayak Income '!D78,'MPG Payment '!E:E,0)) -> 1003 | J78: =INDEX('MPG Payment '!$D:$D,MATCH('Shayak Income '!D78,'MPG Payment '!E:E,0)) -> Asarganj | K78: Old | L78: 44927 | M78: =SUMIF('MPG Payment '!$E$3:$E$344841,'Shayak Income '!D78,'MPG Payment '!$I$3:$I$344841) -> 2757.4 | N78: =SUMIF('MPG Payment '!$E$3:$E$344841,'Shayak Income '!D78,'MPG Payment '!$J$3:$J$344841) -> 150208.89 | O78: =+M78*0.75 -> 2068.05 | P78: =+M78*0.95 -> 2619.53 | Q78: =SUMIF('MPG Payment '!$E$3:$E$344841,'Shayak Income '!D78,'MPG Payment '!$S$3:$S$344841) -> 3937.77 | R78: =+N78*3% -> 4506.2667 | S78: =R78-P78 -> 1886.7367 | T78: =M78*0.1 -> 275.74 | U78: =((((((IF(K78="New",0,SUMIF('MPG Payment '!$E$3:$E$344841,'Shayak Income '!D78,'MPG Payment '!$AC$3:$AC$344841))))+0)+0)+0)+0)+0 -> 98.071965 | V78: =ROUND((SUM(O78:Q78)-SUM(T78:U78)),0) -> 8252 | W78: =(((AN78-AO78)))+0 -> 0 | X78: =((MIN(IF(B78>0,MAX(N78*2%),0),B78)))+0 -> 3004.1778 | Y78: =IFERROR(VLOOKUP(D78,'Monthly Deduction'!$M$2:$N$640,2,0),0) -> 0 | Z78: 0 | AA78: =IFERROR(VLOOKUP(D78,'Monthly Deduction'!A:B,2,0),0) -> 0 | AB78: =ROUND(IFERROR(V78-SUM(W78:AA78),0),0) -> 5248 | AC78: 0 | AD78: =ROUND(AB78-AC78,0) -> 5248 | AE78: =IF(AC78<>0,"Yes","Release") -> Release | AG78: 0 | AI78: 0 | AK78: 627.6 | AL78: =COUNTIF(AK78:AK78,"=NA") -> 0 | AN78: =((MIN(IF(A78>0,MAX(N78*2%,1861),0),A78)))+0 -> 0 | AO78: =SUMIF('MPG Payment '!E:E,'Shayak Income '!D78,'MPG Payment '!AJ:AJ) -> 0 | AP78: =W78 -> 0 | AQ78: =AO78+AP78 -> 0 | AS78: =B78-X78 -> 900.59091
A79: =IFERROR(VLOOKUP(D79,'Monthly Deduction'!$I$3:$J$957,2,0),0) -> 40531.951 | B79: =IFERROR(VLOOKUP(D79,'Monthly Deduction'!$E$3:$F$957,2,0),0) -> 6400 | C79: =A79+B79 -> 46931.951 | D79: 10030015 | E79: =VLOOKUP(D79,'MPG Payment '!$E$3:$G$497305,2,0) -> KAMATPUR | F79: =IFERROR(_xlfn.XLOOKUP(D79,'Monthly Deduction'!$I$3:$I$957,'Monthly Deduction'!$H$3:$H$957),0) -> 0 | G79: =VLOOKUP(D79,'MPG Payment '!$E$3:$G$333666,3,0) -> MPG | H79: =VLOOKUP(D79,'MPG Payment '!$E$3:$H$333666,4,0) -> Direct | I79: =INDEX('MPG Payment '!$C:$C,MATCH('Shayak Income '!D79,'MPG Payment '!E:E,0)) -> 1003 | J79: =INDEX('MPG Payment '!$D:$D,MATCH('Shayak Income '!D79,'MPG Payment '!E:E,0)) -> Asarganj | K79: Old | L79: 44981 | M79: =SUMIF('MPG Payment '!$E$3:$E$344841,'Shayak Income '!D79,'MPG Payment '!$I$3:$I$344841) -> 463.6 | N79: =SUMIF('MPG Payment '!$E$3:$E$344841,'Shayak Income '!D79,'MPG Payment '!$J$3:$J$344841) -> 18633.83 | O79: =+M79*0.75 -> 347.7 | P79: =+M79*0.95 -> 440.42 | Q79: =SUMIF('MPG Payment '!$E$3:$E$344841,'Shayak Income '!D79,'MPG Payment '!$S$3:$S$344841) -> 0 | R79: =+N79*3% -> 559.0149 | S79: =R79-P79 -> 118.5949 | T79: =M79*0.1 -> 46.36 | U79: =((((((IF(K79="New",0,SUMIF('MPG Payment '!$E$3:$E$344841,'Shayak Income '!D79,'MPG Payment '!$AC$3:$AC$344841))))+0)+0)+0)+0)+-9 -> 741.26672 | V79: =ROUND((SUM(O79:Q79)-SUM(T79:U79)),0) -> 0 | W79: 0 | X79: 0 | Y79: 0 | Z79: 0 | AA79: 0 | AB79: =ROUND(IFERROR(V79-SUM(W79:AA79),0),0) -> 0 | AC79: =AB79 -> 0 | AD79: =ROUND(AB79-AC79,0) -> 0 | AE79: =IF(AC79<>0,"Yes","Release") -> Release | AG79: 0 | AH79: Non pouring | AI79: 0 | AK79: 0 | AL79: =COUNTIF(AK79:AK79,"=NA") -> 0 | AN79: =((MIN(IF(A79>0,MAX(N79*2%,1861),0),A79)))+0 -> 1861 | AO79: =SUMIF('MPG Payment '!E:E,'Shayak Income '!D79,'MPG Payment '!AJ:AJ) -> 0 | AP79: =W79 -> 0 | AQ79: =AO79+AP79 -> 0 | AS79: =B79-X79 -> 6400
A80: =IFERROR(VLOOKUP(D80,'Monthly Deduction'!$I$3:$J$957,2,0),0) -> 10653.716 | B80: =IFERROR(VLOOKUP(D80,'Monthly Deduction'!$E$3:$F$957,2,0),0) -> 22400 | C80: =A80+B80 -> 33053.716 | D80: 10030016 | E80: =VLOOKUP(D80,'MPG Payment '!$E$3:$G$497305,2,0) -> GIRDHARA | F80: =IFERROR(_xlfn.XLOOKUP(D80,'Monthly Deduction'!$I$3:$I$957,'Monthly Deduction'!$H$3:$H$957),0) -> 0 | G80: =VLOOKUP(D80,'MPG Payment '!$E$3:$G$333666,3,0) -> MPG | H80: =VLOOKUP(D80,'MPG Payment '!$E$3:$H$333666,4,0) -> Direct | I80: =INDEX('MPG Payment '!$C:$C,MATCH('Shayak Income '!D80,'MPG Payment '!E:E,0)) -> 1003 | J80: =INDEX('MPG Payment '!$D:$D,MATCH('Shayak Income '!D80,'MPG Payment '!E:E,0)) -> Asarganj | K80: Old | L80: 44982 | M80: =SUMIF('MPG Payment '!$E$3:$E$344841,'Shayak Income '!D80,'MPG Payment '!$I$3:$I$344841) -> 5074.9 | N80: =SUMIF('MPG Payment '!$E$3:$E$344841,'Shayak Income '!D80,'MPG Payment '!$J$3:$J$344841) -> 222153.32 | O80: =+M80*0.75 -> 3806.175 | P80: =+M80*0.95 -> 4821.155 | Q80: =SUMIF('MPG Payment '!$E$3:$E$344841,'Shayak Income '!D80,'MPG Payment '!$S$3:$S$344841) -> 1453.14 | R80: =+N80*3% -> 6664.5996 | S80: =R80-P80 -> 1843.4446 | T80: =M80*0.1 -> 507.49 | U80: =((((((IF(K80="New",0,SUMIF('MPG Payment '!$E$3:$E$344841,'Shayak Income '!D80,'MPG Payment '!$AC$3:$AC$344841))))+0)+0)+0)+0)+0 -> 0 | V80: =ROUND((SUM(O80:Q80)-SUM(T80:U80)),0) -> 9573 | W80: =(((AN80-AO80)))+0 -> 4443.0664 | X80: 0 | Y80: =IFERROR(VLOOKUP(D80,'Monthly Deduction'!$M$2:$N$640,2,0),0) -> 0 | Z80: 2500 | AA80: =IFERROR(VLOOKUP(D80,'Monthly Deduction'!A:B,2,0),0) -> 0 | AB80: =ROUND(IFERROR(V80-SUM(W80:AA80),0),0) -> 2630 | AC80: 0 | AD80: =ROUND(AB80-AC80,0) -> 2630 | AE80: =IF(AC80<>0,"Yes","Release") -> Release | AG80: 0 | AH80: BIO GAS | AI80: 0 | AK80: 1072.05 | AL80: =COUNTIF(AK80:AK80,"=NA") -> 0 | AN80: =((MIN(IF(A80>0,MAX(N80*2%,1861),0),A80)))+0 -> 4443.0664 | AO80: =SUMIF('MPG Payment '!E:E,'Shayak Income '!D80,'MPG Payment '!AJ:AJ) -> 0 | AP80: =W80 -> 4443.0664 | AQ80: =AO80+AP80 -> 4443.0664 | AS80: =B80-X80 -> 22400
A81: =IFERROR(VLOOKUP(D81,'Monthly Deduction'!$I$3:$J$957,2,0),0) -> 0 | B81: =IFERROR(VLOOKUP(D81,'Monthly Deduction'!$E$3:$F$957,2,0),0) -> 0 | C81: =A81+B81 -> 0 | D81: 10030017 | E81: =VLOOKUP(D81,'MPG Payment '!$E$3:$G$497305,2,0) -> RATNI | F81: =IFERROR(_xlfn.XLOOKUP(D81,'Monthly Deduction'!$I$3:$I$957,'Monthly Deduction'!$H$3:$H$957),0) -> 0 | G81: =VLOOKUP(D81,'MPG Payment '!$E$3:$G$333666,3,0) -> MPG | H81: =VLOOKUP(D81,'MPG Payment '!$E$3:$H$333666,4,0) -> Direct | I81: =INDEX('MPG Payment '!$C:$C,MATCH('Shayak Income '!D81,'MPG Payment '!E:E,0)) -> 1003 | J81: =INDEX('MPG Payment '!$D:$D,MATCH('Shayak Income '!D81,'MPG Payment '!E:E,0)) -> Asarganj | K81: Old | L81: 44995 | M81: =SUMIF('MPG Payment '!$E$3:$E$344841,'Shayak Income '!D81,'MPG Payment '!$I$3:$I$344841) -> 5588.2 | N81: =SUMIF('MPG Payment '!$E$3:$E$344841,'Shayak Income '!D81,'MPG Payment '!$J$3:$J$344841) -> 290877.16 | O81: =+M81*0.75 -> 4191.15 | P81: =+M81*0.95 -> 5308.79 | Q81: =SUMIF('MPG Payment '!$E$3:$E$344841,'Shayak Income '!D81,'MPG Payment '!$S$3:$S$344841) -> 7709.64 | R81: =+N81*3% -> 8726.3148 | S81: =R81-P81 -> 3417.5248 | T81: =M81*0.1 -> 558.82 | U81: =((((((IF(K81="New",0,SUMIF('MPG Payment '!$E$3:$E$344841,'Shayak Income '!D81,'MPG Payment '!$AC$3:$AC$344841))))+0)+0)+0)+0)+0 -> 0 | V81: =ROUND((SUM(O81:Q81)-SUM(T81:U81)),0) -> 16651 | W81: =(((AN81-AO81)))+0 -> 0 | X81: =((MIN(IF(B81>0,MAX(N81*2%),0),B81)))+0 -> 0 | Y81: =IFERROR(VLOOKUP(D81,'Monthly Deduction'!$M$2:$N$640,2,0),0) -> 0 | Z81: 0 | AA81: =IFERROR(VLOOKUP(D81,'Monthly Deduction'!A:B,2,0),0) -> 0 | AB81: =ROUND(IFERROR(V81-SUM(W81:AA81),0),0) -> 16651 | AC81: 0 | AD81: =ROUND(AB81-AC81,0) -> 16651 | AE81: =IF(AC81<>0,"Yes","Release") -> Release | AG81: 0 | AI81: 0 | AK81: 1320.15 | AL81: =COUNTIF(AK81:AK81,"=NA") -> 0 | AN81: =((MIN(IF(A81>0,MAX(N81*2%,1861),0),A81)))+0 -> 0 | AO81: =SUMIF('MPG Payment '!E:E,'Shayak Income '!D81,'MPG Payment '!AJ:AJ) -> 0 | AP81: =W81 -> 0 | AQ81: =AO81+AP81 -> 0 | AS81: =B81-X81 -> 0
A82: =IFERROR(VLOOKUP(D82,'Monthly Deduction'!$I$3:$J$957,2,0),0) -> 0 | B82: =IFERROR(VLOOKUP(D82,'Monthly Deduction'!$E$3:$F$957,2,0),0) -> 0 | C82: =A82+B82 -> 0 | D82: 10030018 | E82: =VLOOKUP(D82,'MPG Payment '!$E$3:$G$497305,2,0) -> DHAPARI | F82: =IFERROR(_xlfn.XLOOKUP(D82,'Monthly Deduction'!$I$3:$I$957,'Monthly Deduction'!$H$3:$H$957),0) -> 0 | G82: =VLOOKUP(D82,'MPG Payment '!$E$3:$G$333666,3,0) -> MPG | H82: =VLOOKUP(D82,'MPG Payment '!$E$3:$H$333666,4,0) -> Direct | I82: =INDEX('MPG Payment '!$C:$C,MATCH('Shayak Income '!D82,'MPG Payment '!E:E,0)) -> 1003 | J82: =INDEX('MPG Payment '!$D:$D,MATCH('Shayak Income '!D82,'MPG Payment '!E:E,0)) -> Asarganj | K82: Old | L82: 44995 | M82: =SUMIF('MPG Payment '!$E$3:$E$344841,'Shayak Income '!D82,'MPG Payment '!$I$3:$I$344841) -> 2936.95 | N82: =SUMIF('MPG Payment '!$E$3:$E$344841,'Shayak Income '!D82,'MPG Payment '!$J$3:$J$344841) -> 124484.47 | O82: =+M82*0.75 -> 2202.7125 | P82: =+M82*0.95 -> 2790.1025 | Q82: =SUMIF('MPG Payment '!$E$3:$E$344841,'Shayak Income '!D82,'MPG Payment '!$S$3:$S$344841) -> 4089.94 | R82: =+N82*3% -> 3734.5341 | S82: =R82-P82 -> 944.4316 | T82: =M82*0.1 -> 293.695 | U82: =((((((IF(K82="New",0,SUMIF('MPG Payment '!$E$3:$E$344841,'Shayak Income '!D82,'MPG Payment '!$AC$3:$AC$344841))))+0)+0)+0)+0)+0 -> 75.902212 | V82: =ROUND((SUM(O82:Q82)-SUM(T82:U82)),0) -> 8713 | W82: =(((AN82-AO82)))+0 -> 0 | X82: =((MIN(IF(B82>0,MAX(N82*2%),0),B82)))+0 -> 0 | Y82: =IFERROR(VLOOKUP(D82,'Monthly Deduction'!$M$2:$N$640,2,0),0) -> 0 | Z82: 0 | AA82: =IFERROR(VLOOKUP(D82,'Monthly Deduction'!A:B,2,0),0) -> 0 | AB82: =ROUND(IFERROR(V82-SUM(W82:AA82),0),0) -> 8713 | AC82: 0 | AD82: =ROUND(AB82-AC82,0) -> 8713 | AE82: =IF(AC82<>0,"Yes","Release") -> Release | AG82: 0 | AI82: 0 | AK82: 648.5 | AL82: =COUNTIF(AK82:AK82,"=NA") -> 0 | AN82: =((MIN(IF(A82>0,MAX(N82*2%,1861),0),A82)))+0 -> 0 | AO82: =SUMIF('MPG Payment '!E:E,'Shayak Income '!D82,'MPG Payment '!AJ:AJ) -> 0 | AP82: =W82 -> 0 | AQ82: =AO82+AP82 -> 0 | AS82: =B82-X82 -> 0
A83: =IFERROR(VLOOKUP(D83,'Monthly Deduction'!$I$3:$J$957,2,0),0) -> 0 | B83: =IFERROR(VLOOKUP(D83,'Monthly Deduction'!$E$3:$F$957,2,0),0) -> 0 | C83: =A83+B83 -> 0 | D83: 10030019 | E83: =VLOOKUP(D83,'MPG Payment '!$E$3:$G$497305,2,0) -> KHARUI | F83: =IFERROR(_xlfn.XLOOKUP(D83,'Monthly Deduction'!$I$3:$I$957,'Monthly Deduction'!$H$3:$H$957),0) -> 0 | G83: =VLOOKUP(D83,'MPG Payment '!$E$3:$G$333666,3,0) -> MPG | H83: =VLOOKUP(D83,'MPG Payment '!$E$3:$H$333666,4,0) -> Direct | I83: =INDEX('MPG Payment '!$C:$C,MATCH('Shayak Income '!D83,'MPG Payment '!E:E,0)) -> 1003 | J83: =INDEX('MPG Payment '!$D:$D,MATCH('Shayak Income '!D83,'MPG Payment '!E:E,0)) -> Asarganj | K83: Old | L83: 44995 | M83: =SUMIF('MPG Payment '!$E$3:$E$344841,'Shayak Income '!D83,'MPG Payment '!$I$3:$I$344841) -> 1511.8 | N83: =SUMIF('MPG Payment '!$E$3:$E$344841,'Shayak Income '!D83,'MPG Payment '!$J$3:$J$344841) -> 66316.12 | O83: =+M83*0.75 -> 1133.85 | P83: =+M83*0.95 -> 1436.21 | Q83: =SUMIF('MPG Payment '!$E$3:$E$344841,'Shayak Income '!D83,'MPG Payment '!$S$3:$S$344841) -> 4387.2 | R83: =+N83*3% -> 1989.4836 | S83: =R83-P83 -> 553.2736 | T83: =M83*0.1 -> 151.18 | U83: =((((((IF(K83="New",0,SUMIF('MPG Payment '!$E$3:$E$344841,'Shayak Income '!D83,'MPG Payment '!$AC$3:$AC$344841))))+0)+0)+0)+0)+0 -> 1129.7614 | V83: =ROUND((SUM(O83:Q83)-SUM(T83:U83)),0) -> 5676 | W83: =(((AN83-AO83)))+0 -> 0 | X83: =((MIN(IF(B83>0,MAX(N83*2%),0),B83)))+0 -> 0 | Y83: =IFERROR(VLOOKUP(D83,'Monthly Deduction'!$M$2:$N$640,2,0),0) -> 0 | Z83: 0 | AA83: =IFERROR(VLOOKUP(D83,'Monthly Deduction'!A:B,2,0),0) -> 0 | AB83: =ROUND(IFERROR(V83-SUM(W83:AA83),0),0) -> 5676 | AC83: 0 | AD83: =ROUND(AB83-AC83,0) -> 5676 | AE83: =IF(AC83<>0,"Yes","Release") -> Release | AG83: 0 | AI83: 0 | AK83: 223.25 | AL83: =COUNTIF(AK83:AK83,"=NA") -> 0 | AN83: =((MIN(IF(A83>0,MAX(N83*2%,1861),0),A83)))+0 -> 0 | AO83: =SUMIF('MPG Payment '!E:E,'Shayak Income '!D83,'MPG Payment '!AJ:AJ) -> 0 | AP83: =W83 -> 0 | AQ83: =AO83+AP83 -> 0 | AS83: =B83-X83 -> 0
A84: =IFERROR(VLOOKUP(D84,'Monthly Deduction'!$I$3:$J$957,2,0),0) -> 0 | B84: =IFERROR(VLOOKUP(D84,'Monthly Deduction'!$E$3:$F$957,2,0),0) -> 3431.314 | C84: =A84+B84 -> 3431.314 | D84: 10030021 | E84: =VLOOKUP(D84,'MPG Payment '!$E$3:$G$497305,2,0) -> KHAIRA | F84: =IFERROR(_xlfn.XLOOKUP(D84,'Monthly Deduction'!$I$3:$I$957,'Monthly Deduction'!$H$3:$H$957),0) -> 0 | G84: =VLOOKUP(D84,'MPG Payment '!$E$3:$G$333666,3,0) -> MPG | H84: =VLOOKUP(D84,'MPG Payment '!$E$3:$H$333666,4,0) -> Direct | I84: =INDEX('MPG Payment '!$C:$C,MATCH('Shayak Income '!D84,'MPG Payment '!E:E,0)) -> 1003 | J84: =INDEX('MPG Payment '!$D:$D,MATCH('Shayak Income '!D84,'MPG Payment '!E:E,0)) -> Asarganj | K84: Old | L84: 44995 | M84: =SUMIF('MPG Payment '!$E$3:$E$344841,'Shayak Income '!D84,'MPG Payment '!$I$3:$I$344841) -> 2126.7 | N84: =SUMIF('MPG Payment '!$E$3:$E$344841,'Shayak Income '!D84,'MPG Payment '!$J$3:$J$344841) -> 88213.54 | O84: =+M84*0.75 -> 1595.025 | P84: =+M84*0.95 -> 2020.365 | Q84: =SUMIF('MPG Payment '!$E$3:$E$344841,'Shayak Income '!D84,'MPG Payment '!$S$3:$S$344841) -> 3995.34 | R84: =+N84*3% -> 2646.4062 | S84: =R84-P84 -> 626.0412 | T84: =M84*0.1 -> 212.67 | U84: =((((((IF(K84="New",0,SUMIF('MPG Payment '!$E$3:$E$344841,'Shayak Income '!D84,'MPG Payment '!$AC$3:$AC$344841))))+0)+0)+0)+0)+0 -> 561.51555 | V84: =ROUND((SUM(O84:Q84)-SUM(T84:U84)),0) -> 6837 | W84: =(((AN84-AO84)))+0 -> 0 | X84: =((MIN(IF(B84>0,MAX(N84*2%),0),B84)))+0 -> 1764.2708 | Y84: =IFERROR(VLOOKUP(D84,'Monthly Deduction'!$M$2:$N$640,2,0),0) -> 0 | Z84: 0 | AA84: =IFERROR(VLOOKUP(D84,'Monthly Deduction'!A:B,2,0),0) -> 0 | AB84: =ROUND(IFERROR(V84-SUM(W84:AA84),0),0) -> 5073 | AC84: 0 | AD84: =ROUND(AB84-AC84,0) -> 5073 | AE84: =IF(AC84<>0,"Yes","Release") -> Release | AG84: 0 | AI84: 0 | AK84: 390.7 | AL84: =COUNTIF(AK84:AK84,"=NA") -> 0 | AN84: =((MIN(IF(A84>0,MAX(N84*2%,1861),0),A84)))+0 -> 0 | AO84: =SUMIF('MPG Payment '!E:E,'Shayak Income '!D84,'MPG Payment '!AJ:AJ) -> 0 | AP84: =W84 -> 0 | AQ84: =AO84+AP84 -> 0 | AS84: =B84-X84 -> 1667.0432
A85: =IFERROR(VLOOKUP(D85,'Monthly Deduction'!$I$3:$J$957,2,0),0) -> 0 | B85: =IFERROR(VLOOKUP(D85,'Monthly Deduction'!$E$3:$F$957,2,0),0) -> 0 | C85: =A85+B85 -> 0 | D85: 10030022 | E85: =VLOOKUP(D85,'MPG Payment '!$E$3:$G$497305,2,0) -> SISUA | F85: =IFERROR(_xlfn.XLOOKUP(D85,'Monthly Deduction'!$I$3:$I$957,'Monthly Deduction'!$H$3:$H$957),0) -> 0 | G85: =VLOOKUP(D85,'MPG Payment '!$E$3:$G$333666,3,0) -> MPG | H85: =VLOOKUP(D85,'MPG Payment '!$E$3:$H$333666,4,0) -> Direct | I85: =INDEX('MPG Payment '!$C:$C,MATCH('Shayak Income '!D85,'MPG Payment '!E:E,0)) -> 1003 | J85: =INDEX('MPG Payment '!$D:$D,MATCH('Shayak Income '!D85,'MPG Payment '!E:E,0)) -> Asarganj | K85: Old | L85: 44995 | M85: =SUMIF('MPG Payment '!$E$3:$E$344841,'Shayak Income '!D85,'MPG Payment '!$I$3:$I$344841) -> 6096.35 | N85: =SUMIF('MPG Payment '!$E$3:$E$344841,'Shayak Income '!D85,'MPG Payment '!$J$3:$J$344841) -> 251349.8 | O85: =+M85*0.75 -> 4572.2625 | P85: =+M85*0.95 -> 5791.5325 | Q85: =SUMIF('MPG Payment '!$E$3:$E$344841,'Shayak Income '!D85,'MPG Payment '!$S$3:$S$344841) -> 2784.52 | R85: =+N85*3% -> 7540.494 | S85: =R85-P85 -> 1748.9615 | T85: =M85*0.1 -> 609.635 | U85: =((((((IF(K85="New",0,SUMIF('MPG Payment '!$E$3:$E$344841,'Shayak Income '!D85,'MPG Payment '!$AC$3:$AC$344841))))+0)+0)+0)+0)+0 -> 0 | V85: =ROUND((SUM(O85:Q85)-SUM(T85:U85)),0) -> 12539 | W85: =(((AN85-AO85)))+0 -> 0 | X85: =((MIN(IF(B85>0,MAX(N85*2%),0),B85)))+0 -> 0 | Y85: =IFERROR(VLOOKUP(D85,'Monthly Deduction'!$M$2:$N$640,2,0),0) -> 0 | Z85: 0 | AA85: =IFERROR(VLOOKUP(D85,'Monthly Deduction'!A:B,2,0),0) -> 0 | AB85: =ROUND(IFERROR(V85-SUM(W85:AA85),0),0) -> 12539 | AC85: 0 | AD85: =ROUND(AB85-AC85,0) -> 12539 | AE85: =IF(AC85<>0,"Yes","Release") -> Release | AG85: 0 | AI85: 0 | AK85: 1376.2 | AL85: =COUNTIF(AK85:AK85,"=NA") -> 0 | AN85: =((MIN(IF(A85>0,MAX(N85*2%,1861),0),A85)))+0 -> 0 | AO85: =SUMIF('MPG Payment '!E:E,'Shayak Income '!D85,'MPG Payment '!AJ:AJ) -> 0 | AP85: =W85 -> 0 | AQ85: =AO85+AP85 -> 0 | AS85: =B85-X85 -> 0
A86: =IFERROR(VLOOKUP(D86,'Monthly Deduction'!$I$3:$J$957,2,0),0) -> 29603.281 | B86: =IFERROR(VLOOKUP(D86,'Monthly Deduction'!$E$3:$F$957,2,0),0) -> 3656.774 | C86: =A86+B86 -> 33260.055 | D86: 10030023 | E86: =VLOOKUP(D86,'MPG Payment '!$E$3:$G$497305,2,0) -> BISAI | F86: =IFERROR(_xlfn.XLOOKUP(D86,'Monthly Deduction'!$I$3:$I$957,'Monthly Deduction'!$H$3:$H$957),0) -> 0 | G86: =VLOOKUP(D86,'MPG Payment '!$E$3:$G$333666,3,0) -> MPG | H86: =VLOOKUP(D86,'MPG Payment '!$E$3:$H$333666,4,0) -> Direct | I86: =INDEX('MPG Payment '!$C:$C,MATCH('Shayak Income '!D86,'MPG Payment '!E:E,0)) -> 1003 | J86: =INDEX('MPG Payment '!$D:$D,MATCH('Shayak Income '!D86,'MPG Payment '!E:E,0)) -> Asarganj | K86: Old | L86: 44995 | M86: =SUMIF('MPG Payment '!$E$3:$E$344841,'Shayak Income '!D86,'MPG Payment '!$I$3:$I$344841) -> 1635.3 | N86: =SUMIF('MPG Payment '!$E$3:$E$344841,'Shayak Income '!D86,'MPG Payment '!$J$3:$J$344841) -> 68177.7 | O86: =+M86*0.75 -> 1226.475 | P86: =+M86*0.95 -> 1553.535 | Q86: =SUMIF('MPG Payment '!$E$3:$E$344841,'Shayak Income '!D86,'MPG Payment '!$S$3:$S$344841) -> 1892.28 | R86: =+N86*3% -> 2045.331 | S86: =R86-P86 -> 491.796 | T86: =M86*0.1 -> 163.53 | U86: =((((((IF(K86="New",0,SUMIF('MPG Payment '!$E$3:$E$344841,'Shayak Income '!D86,'MPG Payment '!$AC$3:$AC$344841))))+0)+0)+0)+0)+0 -> 971.02118 | V86: =ROUND((SUM(O86:Q86)-SUM(T86:U86)),0) -> 3538 | W86: =(((AN86-AO86)))+0 -> 1861 | X86: 0 | Y86: =IFERROR(VLOOKUP(D86,'Monthly Deduction'!$M$2:$N$640,2,0),0) -> 0 | Z86: 0 | AA86: =IFERROR(VLOOKUP(D86,'Monthly Deduction'!A:B,2,0),0) -> 0 | AB86: =ROUND(IFERROR(V86-SUM(W86:AA86),0),0) -> 1677 | AC86: 0 | AD86: =ROUND(AB86-AC86,0) -> 1677 | AE86: =IF(AC86<>0,"Yes","Release") -> Release | AG86: 0 | AI86: 0 | AK86: 409.45 | AL86: =COUNTIF(AK86:AK86,"=NA") -> 0 | AN86: =((MIN(IF(A86>0,MAX(N86*2%,1861),0),A86)))+0 -> 1861 | AO86: =SUMIF('MPG Payment '!E:E,'Shayak Income '!D86,'MPG Payment '!AJ:AJ) -> 0 | AP86: =W86 -> 1861 | AQ86: =AO86+AP86 -> 1861 | AS86: =B86-X86 -> 3656.774
A87: =IFERROR(VLOOKUP(D87,'Monthly Deduction'!$I$3:$J$957,2,0),0) -> 0 | B87: =IFERROR(VLOOKUP(D87,'Monthly Deduction'!$E$3:$F$957,2,0),0) -> 0 | C87: =A87+B87 -> 0 | D87: 10030025 | E87: =VLOOKUP(D87,'MPG Payment '!$E$3:$G$497305,2,0) -> SAJUA-1 | F87: =IFERROR(_xlfn.XLOOKUP(D87,'Monthly Deduction'!$I$3:$I$957,'Monthly Deduction'!$H$3:$H$957),0) -> 0 | G87: =VLOOKUP(D87,'MPG Payment '!$E$3:$G$333666,3,0) -> MPG | H87: =VLOOKUP(D87,'MPG Payment '!$E$3:$H$333666,4,0) -> Direct | I87: =INDEX('MPG Payment '!$C:$C,MATCH('Shayak Income '!D87,'MPG Payment '!E:E,0)) -> 1003 | J87: =INDEX('MPG Payment '!$D:$D,MATCH('Shayak Income '!D87,'MPG Payment '!E:E,0)) -> Asarganj | K87: Old | L87: 45015 | M87: =SUMIF('MPG Payment '!$E$3:$E$344841,'Shayak Income '!D87,'MPG Payment '!$I$3:$I$344841) -> 3126.4 | N87: =SUMIF('MPG Payment '!$E$3:$E$344841,'Shayak Income '!D87,'MPG Payment '!$J$3:$J$344841) -> 125257.3 | O87: =+M87*0.75 -> 2344.8 | P87: =+M87*0.95 -> 2970.08 | Q87: =SUMIF('MPG Payment '!$E$3:$E$344841,'Shayak Income '!D87,'MPG Payment '!$S$3:$S$344841) -> 1457.06 | R87: =+N87*3% -> 3757.719 | S87: =R87-P87 -> 787.639 | T87: =M87*0.1 -> 312.64 | U87: =((((((IF(K87="New",0,SUMIF('MPG Payment '!$E$3:$E$344841,'Shayak Income '!D87,'MPG Payment '!$AC$3:$AC$344841))))+0)+0)+0)+0)+0 -> 7.954861 | V87: =ROUND((SUM(O87:Q87)-SUM(T87:U87)),0) -> 6451 | W87: =(((AN87-AO87)))+0 -> 0 | X87: =((MIN(IF(B87>0,MAX(N87*2%),0),B87)))+0 -> 0 | Y87: =IFERROR(VLOOKUP(D87,'Monthly Deduction'!$M$2:$N$640,2,0),0) -> 0 | Z87: 0 | AA87: =IFERROR(VLOOKUP(D87,'Monthly Deduction'!A:B,2,0),0) -> 0 | AB87: =ROUND(IFERROR(V87-SUM(W87:AA87),0),0) -> 6451 | AC87: 0 | AD87: =ROUND(AB87-AC87,0) -> 6451 | AE87: =IF(AC87<>0,"Yes","Release") -> Release | AG87: 0 | AI87: 0 | AK87: 494.95 | AL87: =COUNTIF(AK87:AK87,"=NA") -> 0 | AN87: =((MIN(IF(A87>0,MAX(N87*2%,1861),0),A87)))+0 -> 0 | AO87: =SUMIF('MPG Payment '!E:E,'Shayak Income '!D87,'MPG Payment '!AJ:AJ) -> 0 | AP87: =W87 -> 0 | AQ87: =AO87+AP87 -> 0 | AS87: =B87-X87 -> 0
A88: =IFERROR(VLOOKUP(D88,'Monthly Deduction'!$I$3:$J$957,2,0),0) -> 0 | B88: =IFERROR(VLOOKUP(D88,'Monthly Deduction'!$E$3:$F$957,2,0),0) -> 0 | C88: =A88+B88 -> 0 | D88: 10030026 | E88: =VLOOKUP(D88,'MPG Payment '!$E$3:$G$497305,2,0) -> SAJUA-2 | F88: =IFERROR(_xlfn.XLOOKUP(D88,'Monthly Deduction'!$I$3:$I$957,'Monthly Deduction'!$H$3:$H$957),0) -> 0 | G88: =VLOOKUP(D88,'MPG Payment '!$E$3:$G$333666,3,0) -> MPG | H88: =VLOOKUP(D88,'MPG Payment '!$E$3:$H$333666,4,0) -> Direct | I88: =INDEX('MPG Payment '!$C:$C,MATCH('Shayak Income '!D88,'MPG Payment '!E:E,0)) -> 1003 | J88: =INDEX('MPG Payment '!$D:$D,MATCH('Shayak Income '!D88,'MPG Payment '!E:E,0)) -> Asarganj | K88: Old | L88: 45015 | M88: =SUMIF('MPG Payment '!$E$3:$E$344841,'Shayak Income '!D88,'MPG Payment '!$I$3:$I$344841) -> 4993.65 | N88: =SUMIF('MPG Payment '!$E$3:$E$344841,'Shayak Income '!D88,'MPG Payment '!$J$3:$J$344841) -> 203974.96 | O88: =+M88*0.75 -> 3745.2375 | P88: =+M88*0.95 -> 4743.9675 | Q88: =SUMIF('MPG Payment '!$E$3:$E$344841,'Shayak Income '!D88,'MPG Payment '!$S$3:$S$344841) -> 2644.91 | R88: =+N88*3% -> 6119.2488 | S88: =R88-P88 -> 1375.2813 | T88: =M88*0.1 -> 499.365 | U88: =((((((IF(K88="New",0,SUMIF('MPG Payment '!$E$3:$E$344841,'Shayak Income '!D88,'MPG Payment '!$AC$3:$AC$344841))))+0)+0)+0)+0)+0 -> 0 | V88: =ROUND((SUM(O88:Q88)-SUM(T88:U88)),0) -> 10635 | W88: =(((AN88-AO88)))+0 -> 0 | X88: =((MIN(IF(B88>0,MAX(N88*2%),0),B88)))+0 -> 0 | Y88: =IFERROR(VLOOKUP(D88,'Monthly Deduction'!$M$2:$N$640,2,0),0) -> 0 | Z88: 0 | AA88: =IFERROR(VLOOKUP(D88,'Monthly Deduction'!A:B,2,0),0) -> 0 | AB88: =ROUND(IFERROR(V88-SUM(W88:AA88),0),0) -> 10635 | AC88: 0 | AD88: =ROUND(AB88-AC88,0) -> 10635 | AE88: =IF(AC88<>0,"Yes","Release") -> Release | AG88: 0 | AI88: 0 | AK88: 400.4 | AL88: =COUNTIF(AK88:AK88,"=NA") -> 0 | AN88: =((MIN(IF(A88>0,MAX(N88*2%,1861),0),A88)))+0 -> 0 | AO88: =SUMIF('MPG Payment '!E:E,'Shayak Income '!D88,'MPG Payment '!AJ:AJ) -> 0 | AP88: =W88 -> 0 | AQ88: =AO88+AP88 -> 0 | AS88: =B88-X88 -> 0
A89: =IFERROR(VLOOKUP(D89,'Monthly Deduction'!$I$3:$J$957,2,0),0) -> 0 | B89: =IFERROR(VLOOKUP(D89,'Monthly Deduction'!$E$3:$F$957,2,0),0) -> 0 | C89: =A89+B89 -> 0 | D89: 10030027 | E89: =VLOOKUP(D89,'MPG Payment '!$E$3:$G$497305,2,0) -> CHORGAUN | F89: =IFERROR(_xlfn.XLOOKUP(D89,'Monthly Deduction'!$I$3:$I$957,'Monthly Deduction'!$H$3:$H$957),0) -> 0 | G89: =VLOOKUP(D89,'MPG Payment '!$E$3:$G$333666,3,0) -> MPG | H89: =VLOOKUP(D89,'MPG Payment '!$E$3:$H$333666,4,0) -> Direct | I89: =INDEX('MPG Payment '!$C:$C,MATCH('Shayak Income '!D89,'MPG Payment '!E:E,0)) -> 1003 | J89: =INDEX('MPG Payment '!$D:$D,MATCH('Shayak Income '!D89,'MPG Payment '!E:E,0)) -> Asarganj | K89: Old | L89: 45015 | M89: =SUMIF('MPG Payment '!$E$3:$E$344841,'Shayak Income '!D89,'MPG Payment '!$I$3:$I$344841) -> 4117.8 | N89: =SUMIF('MPG Payment '!$E$3:$E$344841,'Shayak Income '!D89,'MPG Payment '!$J$3:$J$344841) -> 161212.2 | O89: =+M89*0.75 -> 3088.35 | P89: =+M89*0.95 -> 3911.91 | Q89: =SUMIF('MPG Payment '!$E$3:$E$344841,'Shayak Income '!D89,'MPG Payment '!$S$3:$S$344841) -> 4614.46 | R89: =+N89*3% -> 4836.366 | S89: =R89-P89 -> 924.456 | T89: =M89*0.1 -> 411.78 | U89: =((((((IF(K89="New",0,SUMIF('MPG Payment '!$E$3:$E$344841,'Shayak Income '!D89,'MPG Payment '!$AC$3:$AC$344841))))+0)+0)+0)+0)+0 -> 0 | V89: =ROUND((SUM(O89:Q89)-SUM(T89:U89)),0) -> 11203 | W89: =(((AN89-AO89)))+0 -> 0 | X89: =((MIN(IF(B89>0,MAX(N89*2%),0),B89)))+0 -> 0 | Y89: =IFERROR(VLOOKUP(D89,'Monthly Deduction'!$M$2:$N$640,2,0),0) -> 0 | Z89: 0 | AA89: =IFERROR(VLOOKUP(D89,'Monthly Deduction'!A:B,2,0),0) -> 0 | AB89: =ROUND(IFERROR(V89-SUM(W89:AA89),0),0) -> 11203 | AC89: 0 | AD89: =ROUND(AB89-AC89,0) -> 11203 | AE89: =IF(AC89<>0,"Yes","Release") -> Release | AG89: 0 | AI89: 0 | AK89: 799.25 | AL89: =COUNTIF(AK89:AK89,"=NA") -> 0 | AN89: =((MIN(IF(A89>0,MAX(N89*2%,1861),0),A89)))+0 -> 0 | AO89: =SUMIF('MPG Payment '!E:E,'Shayak Income '!D89,'MPG Payment '!AJ:AJ) -> 0 | AP89: =W89 -> 0 | AQ89: =AO89+AP89 -> 0 | AS89: =B89-X89 -> 0
A90: =IFERROR(VLOOKUP(D90,'Monthly Deduction'!$I$3:$J$957,2,0),0) -> 0 | B90: =IFERROR(VLOOKUP(D90,'Monthly Deduction'!$E$3:$F$957,2,0),0) -> 0 | C90: =A90+B90 -> 0 | D90: 10030028 | E90: =VLOOKUP(D90,'MPG Payment '!$E$3:$G$497305,2,0) -> PADARATHPUR | F90: =IFERROR(_xlfn.XLOOKUP(D90,'Monthly Deduction'!$I$3:$I$957,'Monthly Deduction'!$H$3:$H$957),0) -> 0 | G90: =VLOOKUP(D90,'MPG Payment '!$E$3:$G$333666,3,0) -> MPG | H90: =VLOOKUP(D90,'MPG Payment '!$E$3:$H$333666,4,0) -> Direct | I90: =INDEX('MPG Payment '!$C:$C,MATCH('Shayak Income '!D90,'MPG Payment '!E:E,0)) -> 1003 | J90: =INDEX('MPG Payment '!$D:$D,MATCH('Shayak Income '!D90,'MPG Payment '!E:E,0)) -> Asarganj | K90: Old | L90: 45015 | M90: =SUMIF('MPG Payment '!$E$3:$E$344841,'Shayak Income '!D90,'MPG Payment '!$I$3:$I$344841) -> 4651.3 | N90: =SUMIF('MPG Payment '!$E$3:$E$344841,'Shayak Income '!D90,'MPG Payment '!$J$3:$J$344841) -> 196144.65 | O90: =+M90*0.75 -> 3488.475 | P90: =+M90*0.95 -> 4418.735 | Q90: =SUMIF('MPG Payment '!$E$3:$E$344841,'Shayak Income '!D90,'MPG Payment '!$S$3:$S$344841) -> 3460.68 | R90: =+N90*3% -> 5884.3395 | S90: =R90-P90 -> 1465.6045 | T90: =M90*0.1 -> 465.13 | U90: =((((((IF(K90="New",0,SUMIF('MPG Payment '!$E$3:$E$344841,'Shayak Income '!D90,'MPG Payment '!$AC$3:$AC$344841))))+0)+0)+0)+0)+0 -> 0 | V90: =ROUND((SUM(O90:Q90)-SUM(T90:U90)),0) -> 10903 | W90: =(((AN90-AO90)))+0 -> 0 | X90: =((MIN(IF(B90>0,MAX(N90*2%),0),B90)))+0 -> 0 | Y90: =IFERROR(VLOOKUP(D90,'Monthly Deduction'!$M$2:$N$640,2,0),0) -> 0 | Z90: 0 | AA90: =IFERROR(VLOOKUP(D90,'Monthly Deduction'!A:B,2,0),0) -> 0 | AB90: =ROUND(IFERROR(V90-SUM(W90:AA90),0),0) -> 10903 | AC90: 0 | AD90: =ROUND(AB90-AC90,0) -> 10903 | AE90: =IF(AC90<>0,"Yes","Release") -> Release | AG90: 0 | AI90: 0 | AK90: 999.65 | AL90: =COUNTIF(AK90:AK90,"=NA") -> 0 | AN90: =((MIN(IF(A90>0,MAX(N90*2%,1861),0),A90)))+0 -> 0 | AO90: =SUMIF('MPG Payment '!E:E,'Shayak Income '!D90,'MPG Payment '!AJ:AJ) -> 0 | AP90: =W90 -> 0 | AQ90: =AO90+AP90 -> 0 | AS90: =B90-X90 -> 0
A91: =IFERROR(VLOOKUP(D91,'Monthly Deduction'!$I$3:$J$957,2,0),0) -> 0 | B91: =IFERROR(VLOOKUP(D91,'Monthly Deduction'!$E$3:$F$957,2,0),0) -> 0 | C91: =A91+B91 -> 0 | D91: 10030031 | E91: =VLOOKUP(D91,'MPG Payment '!$E$3:$G$497305,2,0) -> BADARKHA | F91: =IFERROR(_xlfn.XLOOKUP(D91,'Monthly Deduction'!$I$3:$I$957,'Monthly Deduction'!$H$3:$H$957),0) -> 0 | G91: =VLOOKUP(D91,'MPG Payment '!$E$3:$G$333666,3,0) -> MPG | H91: =VLOOKUP(D91,'MPG Payment '!$E$3:$H$333666,4,0) -> Direct | I91: =INDEX('MPG Payment '!$C:$C,MATCH('Shayak Income '!D91,'MPG Payment '!E:E,0)) -> 1003 | J91: =INDEX('MPG Payment '!$D:$D,MATCH('Shayak Income '!D91,'MPG Payment '!E:E,0)) -> Asarganj | K91: Old | L91: 45016 | M91: =SUMIF('MPG Payment '!$E$3:$E$344841,'Shayak Income '!D91,'MPG Payment '!$I$3:$I$344841) -> 3276.55 | N91: =SUMIF('MPG Payment '!$E$3:$E$344841,'Shayak Income '!D91,'MPG Payment '!$J$3:$J$344841) -> 125951.44 | O91: =+M91*0.75 -> 2457.4125 | P91: =+M91*0.95 -> 3112.7225 | Q91: =SUMIF('MPG Payment '!$E$3:$E$344841,'Shayak Income '!D91,'MPG Payment '!$S$3:$S$344841) -> 0 | R91: =+N91*3% -> 3778.5432 | S91: =R91-P91 -> 665.8207 | T91: =M91*0.1 -> 327.655 | U91: =((((((IF(K91="New",0,SUMIF('MPG Payment '!$E$3:$E$344841,'Shayak Income '!D91,'MPG Payment '!$AC$3:$AC$344841))))+0)+0)+0)+0)+0 -> 0 | V91: =ROUND((SUM(O91:Q91)-SUM(T91:U91)),0) -> 5242 | W91: =(((AN91-AO91)))+0 -> 0 | X91: =((MIN(IF(B91>0,MAX(N91*2%),0),B91)))+0 -> 0 | Y91: =IFERROR(VLOOKUP(D91,'Monthly Deduction'!$M$2:$N$640,2,0),0) -> 0 | Z91: 0 | AA91: =IFERROR(VLOOKUP(D91,'Monthly Deduction'!A:B,2,0),0) -> 0 | AB91: =ROUND(IFERROR(V91-SUM(W91:AA91),0),0) -> 5242 | AC91: 0 | AD91: =ROUND(AB91-AC91,0) -> 5242 | AE91: =IF(AC91<>0,"Yes","Release") -> Release | AG91: 0 | AI91: 0 | AK91: 691.05 | AL91: =COUNTIF(AK91:AK91,"=NA") -> 0 | AN91: =((MIN(IF(A91>0,MAX(N91*2%,1861),0),A91)))+0 -> 0 | AO91: =SUMIF('MPG Payment '!E:E,'Shayak Income '!D91,'MPG Payment '!AJ:AJ) -> 0 | AP91: =W91 -> 0 | AQ91: =AO91+AP91 -> 0 | AS91: =B91-X91 -> 0
A92: =IFERROR(VLOOKUP(D92,'Monthly Deduction'!$I$3:$J$957,2,0),0) -> 0 | B92: =IFERROR(VLOOKUP(D92,'Monthly Deduction'!$E$3:$F$957,2,0),0) -> 0 | C92: =A92+B92 -> 0 | D92: 10030032 | E92: =VLOOKUP(D92,'MPG Payment '!$E$3:$G$497305,2,0) -> MAHDMADPUR | F92: =IFERROR(_xlfn.XLOOKUP(D92,'Monthly Deduction'!$I$3:$I$957,'Monthly Deduction'!$H$3:$H$957),0) -> 0 | G92: =VLOOKUP(D92,'MPG Payment '!$E$3:$G$333666,3,0) -> MPG | H92: =VLOOKUP(D92,'MPG Payment '!$E$3:$H$333666,4,0) -> Direct | I92: =INDEX('MPG Payment '!$C:$C,MATCH('Shayak Income '!D92,'MPG Payment '!E:E,0)) -> 1003 | J92: =INDEX('MPG Payment '!$D:$D,MATCH('Shayak Income '!D92,'MPG Payment '!E:E,0)) -> Asarganj | K92: Old | L92: 45017 | M92: =SUMIF('MPG Payment '!$E$3:$E$344841,'Shayak Income '!D92,'MPG Payment '!$I$3:$I$344841) -> 4995.05 | N92: =SUMIF('MPG Payment '!$E$3:$E$344841,'Shayak Income '!D92,'MPG Payment '!$J$3:$J$344841) -> 185601.22 | O92: =+M92*0.75 -> 3746.2875 | P92: =+M92*0.95 -> 4745.2975 | Q92: =SUMIF('MPG Payment '!$E$3:$E$344841,'Shayak Income '!D92,'MPG Payment '!$S$3:$S$344841) -> 1117.13 | R92: =+N92*3% -> 5568.0366 | S92: =R92-P92 -> 822.7391 | T92: =M92*0.1 -> 499.505 | U92: =((((((IF(K92="New",0,SUMIF('MPG Payment '!$E$3:$E$344841,'Shayak Income '!D92,'MPG Payment '!$AC$3:$AC$344841))))+0)+0)+0)+0)+0 -> 0 | V92: =ROUND((SUM(O92:Q92)-SUM(T92:U92)),0) -> 9109 | W92: =(((AN92-AO92)))+0 -> 0 | X92: =((MIN(IF(B92>0,MAX(N92*2%),0),B92)))+0 -> 0 | Y92: =IFERROR(VLOOKUP(D92,'Monthly Deduction'!$M$2:$N$640,2,0),0) -> 0 | Z92: 0 | AA92: =IFERROR(VLOOKUP(D92,'Monthly Deduction'!A:B,2,0),0) -> 0 | AB92: =ROUND(IFERROR(V92-SUM(W92:AA92),0),0) -> 9109 | AC92: 0 | AD92: =ROUND(AB92-AC92,0) -> 9109 | AE92: =IF(AC92<>0,"Yes","Release") -> Release | AG92: 0 | AI92: 0 | AK92: 892.85 | AL92: =COUNTIF(AK92:AK92,"=NA") -> 0 | AN92: =((MIN(IF(A92>0,MAX(N92*2%,1861),0),A92)))+0 -> 0 | AO92: =SUMIF('MPG Payment '!E:E,'Shayak Income '!D92,'MPG Payment '!AJ:AJ) -> 0 | AP92: =W92 -> 0 | AQ92: =AO92+AP92 -> 0 | AS92: =B92-X92 -> 0
A93: =IFERROR(VLOOKUP(D93,'Monthly Deduction'!$I$3:$J$957,2,0),0) -> 0 | B93: =IFERROR(VLOOKUP(D93,'Monthly Deduction'!$E$3:$F$957,2,0),0) -> 0 | C93: =A93+B93 -> 0 | D93: 10030034 | E93: =VLOOKUP(D93,'MPG Payment '!$E$3:$G$497305,2,0) -> MUSKIPUR | F93: =IFERROR(_xlfn.XLOOKUP(D93,'Monthly Deduction'!$I$3:$I$957,'Monthly Deduction'!$H$3:$H$957),0) -> 0 | G93: =VLOOKUP(D93,'MPG Payment '!$E$3:$G$333666,3,0) -> MPG | H93: =VLOOKUP(D93,'MPG Payment '!$E$3:$H$333666,4,0) -> Direct | I93: =INDEX('MPG Payment '!$C:$C,MATCH('Shayak Income '!D93,'MPG Payment '!E:E,0)) -> 1003 | J93: =INDEX('MPG Payment '!$D:$D,MATCH('Shayak Income '!D93,'MPG Payment '!E:E,0)) -> Asarganj | K93: Old | L93: 45082 | M93: =SUMIF('MPG Payment '!$E$3:$E$344841,'Shayak Income '!D93,'MPG Payment '!$I$3:$I$344841) -> 5091.95 | N93: =SUMIF('MPG Payment '!$E$3:$E$344841,'Shayak Income '!D93,'MPG Payment '!$J$3:$J$344841) -> 220432.74 | O93: =+M93*0.75 -> 3818.9625 | P93: =+M93*0.95 -> 4837.3525 | Q93: =SUMIF('MPG Payment '!$E$3:$E$344841,'Shayak Income '!D93,'MPG Payment '!$S$3:$S$344841) -> 0 | R93: =+N93*3% -> 6612.9822 | S93: =R93-P93 -> 1775.6297 | T93: =M93*0.1 -> 509.195 | U93: =((((((IF(K93="New",0,SUMIF('MPG Payment '!$E$3:$E$344841,'Shayak Income '!D93,'MPG Payment '!$AC$3:$AC$344841))))+0)+0)+0)+0)+0 -> 0 | V93: =ROUND((SUM(O93:Q93)-SUM(T93:U93)),0) -> 8147 | W93: =(((AN93-AO93)))+0 -> 0 | X93: =((MIN(IF(B93>0,MAX(N93*2%),0),B93)))+0 -> 0 | Y93: =IFERROR(VLOOKUP(D93,'Monthly Deduction'!$M$2:$N$640,2,0),0) -> 0 | Z93: 165.2 | AA93: =IFERROR(VLOOKUP(D93,'Monthly Deduction'!A:B,2,0),0) -> 0 | AB93: =ROUND(IFERROR(V93-SUM(W93:AA93),0),0) -> 7982 | AC93: 0 | AD93: =ROUND(AB93-AC93,0) -> 7982 | AE93: =IF(AC93<>0,"Yes","Release") -> Release | AG93: 0 | AH93: EIPL Deduction | AI93: 0 | AK93: 1112.8 | AL93: =COUNTIF(AK93:AK93,"=NA") -> 0 | AN93: =((MIN(IF(A93>0,MAX(N93*2%,1861),0),A93)))+0 -> 0 | AO93: =SUMIF('MPG Payment '!E:E,'Shayak Income '!D93,'MPG Payment '!AJ:AJ) -> 0 | AP93: =W93 -> 0 | AQ93: =AO93+AP93 -> 0 | AS93: =B93-X93 -> 0
A94: =IFERROR(VLOOKUP(D94,'Monthly Deduction'!$I$3:$J$957,2,0),0) -> 22290.304 | B94: =IFERROR(VLOOKUP(D94,'Monthly Deduction'!$E$3:$F$957,2,0),0) -> 0 | C94: =A94+B94 -> 22290.304 | D94: 10030035 | E94: =VLOOKUP(D94,'MPG Payment '!$E$3:$G$497305,2,0) -> NAYAGAUN | F94: =IFERROR(_xlfn.XLOOKUP(D94,'Monthly Deduction'!$I$3:$I$957,'Monthly Deduction'!$H$3:$H$957),0) -> 0 | G94: =VLOOKUP(D94,'MPG Payment '!$E$3:$G$333666,3,0) -> MPG | H94: =VLOOKUP(D94,'MPG Payment '!$E$3:$H$333666,4,0) -> Direct | I94: =INDEX('MPG Payment '!$C:$C,MATCH('Shayak Income '!D94,'MPG Payment '!E:E,0)) -> 1003 | J94: =INDEX('MPG Payment '!$D:$D,MATCH('Shayak Income '!D94,'MPG Payment '!E:E,0)) -> Asarganj | K94: Old | L94: 45084 | M94: =SUMIF('MPG Payment '!$E$3:$E$344841,'Shayak Income '!D94,'MPG Payment '!$I$3:$I$344841) -> 2833.6 | N94: =SUMIF('MPG Payment '!$E$3:$E$344841,'Shayak Income '!D94,'MPG Payment '!$J$3:$J$344841) -> 117932.69 | O94: =+M94*0.75 -> 2125.2 | P94: =+M94*0.95 -> 2691.92 | Q94: =SUMIF('MPG Payment '!$E$3:$E$344841,'Shayak Income '!D94,'MPG Payment '!$S$3:$S$344841) -> 567.32 | R94: =+N94*3% -> 3537.9807 | S94: =R94-P94 -> 846.0607 | T94: =M94*0.1 -> 283.36 | U94: =((((((IF(K94="New",0,SUMIF('MPG Payment '!$E$3:$E$344841,'Shayak Income '!D94,'MPG Payment '!$AC$3:$AC$344841))))+0)+0)+0)+0)+0 -> 40.440918 | V94: =ROUND((SUM(O94:Q94)-SUM(T94:U94)),0) -> 5061 | W94: =(((AN94-AO94)))+0 -> 2358.6538 | X94: 0 | Y94: =IFERROR(VLOOKUP(D94,'Monthly Deduction'!$M$2:$N$640,2,0),0) -> 0 | Z94: 0 | AA94: =IFERROR(VLOOKUP(D94,'Monthly Deduction'!A:B,2,0),0) -> 0 | AB94: =ROUND(IFERROR(V94-SUM(W94:AA94),0),0) -> 2702 | AC94: 0 | AD94: =ROUND(AB94-AC94,0) -> 2702 | AE94: =IF(AC94<>0,"Yes","Release") -> Release | AG94: 0 | AI94: 0 | AK94: 483.2 | AL94: =COUNTIF(AK94:AK94,"=NA") -> 0 | AN94: =((MIN(IF(A94>0,MAX(N94*2%,1861),0),A94)))+0 -> 2358.6538 | AO94: =SUMIF('MPG Payment '!E:E,'Shayak Income '!D94,'MPG Payment '!AJ:AJ) -> 0 | AP94: =W94 -> 2358.6538 | AQ94: =AO94+AP94 -> 2358.6538 | AS94: =B94-X94 -> 0
A95: =IFERROR(VLOOKUP(D95,'Monthly Deduction'!$I$3:$J$957,2,0),0) -> 0 | B95: =IFERROR(VLOOKUP(D95,'Monthly Deduction'!$E$3:$F$957,2,0),0) -> 0 | C95: =A95+B95 -> 0 | D95: 10030037 | E95: =VLOOKUP(D95,'MPG Payment '!$E$3:$G$497305,2,0) -> LAUNA | F95: =IFERROR(_xlfn.XLOOKUP(D95,'Monthly Deduction'!$I$3:$I$957,'Monthly Deduction'!$H$3:$H$957),0) -> 0 | G95: =VLOOKUP(D95,'MPG Payment '!$E$3:$G$333666,3,0) -> MPG | H95: =VLOOKUP(D95,'MPG Payment '!$E$3:$H$333666,4,0) -> Direct | I95: =INDEX('MPG Payment '!$C:$C,MATCH('Shayak Income '!D95,'MPG Payment '!E:E,0)) -> 1003 | J95: =INDEX('MPG Payment '!$D:$D,MATCH('Shayak Income '!D95,'MPG Payment '!E:E,0)) -> Asarganj | K95: Old | L95: 45091 | M95: =SUMIF('MPG Payment '!$E$3:$E$344841,'Shayak Income '!D95,'MPG Payment '!$I$3:$I$344841) -> 5988.1 | N95: =SUMIF('MPG Payment '!$E$3:$E$344841,'Shayak Income '!D95,'MPG Payment '!$J$3:$J$344841) -> 228047.94 | O95: =+M95*0.75 -> 4491.075 | P95: =+M95*0.95 -> 5688.695 | Q95: =SUMIF('MPG Payment '!$E$3:$E$344841,'Shayak Income '!D95,'MPG Payment '!$S$3:$S$344841) -> 2651.73 | R95: =+N95*3% -> 6841.4382 | S95: =R95-P95 -> 1152.7432 | T95: =M95*0.1 -> 598.81 | U95: =((((((IF(K95="New",0,SUMIF('MPG Payment '!$E$3:$E$344841,'Shayak Income '!D95,'MPG Payment '!$AC$3:$AC$344841))))+0)+0)+0)+0)+0 -> 0 | V95: =ROUND((SUM(O95:Q95)-SUM(T95:U95)),0) -> 12233 | W95: =(((AN95-AO95)))+0 -> 0 | X95: =((MIN(IF(B95>0,MAX(N95*2%),0),B95)))+0 -> 0 | Y95: =IFERROR(VLOOKUP(D95,'Monthly Deduction'!$M$2:$N$640,2,0),0) -> 0 | Z95: 0 | AA95: =IFERROR(VLOOKUP(D95,'Monthly Deduction'!A:B,2,0),0) -> 0 | AB95: =ROUND(IFERROR(V95-SUM(W95:AA95),0),0) -> 12233 | AC95: 0 | AD95: =ROUND(AB95-AC95,0) -> 12233 | AE95: =IF(AC95<>0,"Yes","Release") -> Release | AG95: 0 | AI95: 0 | AK95: 1362.25 | AL95: =COUNTIF(AK95:AK95,"=NA") -> 0 | AN95: =((MIN(IF(A95>0,MAX(N95*2%,1861),0),A95)))+0 -> 0 | AO95: =SUMIF('MPG Payment '!E:E,'Shayak Income '!D95,'MPG Payment '!AJ:AJ) -> 0 | AP95: =W95 -> 0 | AQ95: =AO95+AP95 -> 0 | AS95: =B95-X95 -> 0
A96: =IFERROR(VLOOKUP(D96,'Monthly Deduction'!$I$3:$J$957,2,0),0) -> 18977.626 | B96: =IFERROR(VLOOKUP(D96,'Monthly Deduction'!$E$3:$F$957,2,0),0) -> 16000 | C96: =A96+B96 -> 34977.626 | D96: 10030038 | E96: =VLOOKUP(D96,'MPG Payment '!$E$3:$G$497305,2,0) -> DULHAR | F96: =IFERROR(_xlfn.XLOOKUP(D96,'Monthly Deduction'!$I$3:$I$957,'Monthly Deduction'!$H$3:$H$957),0) -> 0 | G96: =VLOOKUP(D96,'MPG Payment '!$E$3:$G$333666,3,0) -> MPG | H96: =VLOOKUP(D96,'MPG Payment '!$E$3:$H$333666,4,0) -> Direct | I96: =INDEX('MPG Payment '!$C:$C,MATCH('Shayak Income '!D96,'MPG Payment '!E:E,0)) -> 1003 | J96: =INDEX('MPG Payment '!$D:$D,MATCH('Shayak Income '!D96,'MPG Payment '!E:E,0)) -> Asarganj | K96: Old | L96: 45121 | M96: =SUMIF('MPG Payment '!$E$3:$E$344841,'Shayak Income '!D96,'MPG Payment '!$I$3:$I$344841) -> 2640.4 | N96: =SUMIF('MPG Payment '!$E$3:$E$344841,'Shayak Income '!D96,'MPG Payment '!$J$3:$J$344841) -> 112537.2 | O96: =+M96*0.75 -> 1980.3 | P96: =+M96*0.95 -> 2508.38 | Q96: =SUMIF('MPG Payment '!$E$3:$E$344841,'Shayak Income '!D96,'MPG Payment '!$S$3:$S$344841) -> 0 | R96: =+N96*3% -> 3376.116 | S96: =R96-P96 -> 867.736 | T96: =M96*0.1 -> 264.04 | U96: =((((((IF(K96="New",0,SUMIF('MPG Payment '!$E$3:$E$344841,'Shayak Income '!D96,'MPG Payment '!$AC$3:$AC$344841))))+0)+0)+0)+0)+0 -> 175.78193 | V96: =ROUND((SUM(O96:Q96)-SUM(T96:U96)),0) -> 4049 | W96: =(((AN96-AO96)))+0 -> 2250.744 | X96: 0 | Y96: =IFERROR(VLOOKUP(D96,'Monthly Deduction'!$M$2:$N$640,2,0),0) -> 0 | Z96: 0 | AA96: =IFERROR(VLOOKUP(D96,'Monthly Deduction'!A:B,2,0),0) -> 0 | AB96: =ROUND(IFERROR(V96-SUM(W96:AA96),0),0) -> 1798 | AC96: 0 | AD96: =ROUND(AB96-AC96,0) -> 1798 | AE96: =IF(AC96<>0,"Yes","Release") -> Release | AG96: 0 | AI96: 0 | AK96: 649.35 | AL96: =COUNTIF(AK96:AK96,"=NA") -> 0 | AN96: =((MIN(IF(A96>0,MAX(N96*2%,1861),0),A96)))+0 -> 2250.744 | AO96: =SUMIF('MPG Payment '!E:E,'Shayak Income '!D96,'MPG Payment '!AJ:AJ) -> 0 | AP96: =W96 -> 2250.744 | AQ96: =AO96+AP96 -> 2250.744 | AS96: =B96-X96 -> 16000
A97: =IFERROR(VLOOKUP(D97,'Monthly Deduction'!$I$3:$J$957,2,0),0) -> 0 | B97: =IFERROR(VLOOKUP(D97,'Monthly Deduction'!$E$3:$F$957,2,0),0) -> 0 | C97: =A97+B97 -> 0 | D97: 10030040 | E97: =VLOOKUP(D97,'MPG Payment '!$E$3:$G$497305,2,0) -> Ghorpithiya - Vikas | F97: =IFERROR(_xlfn.XLOOKUP(D97,'Monthly Deduction'!$I$3:$I$957,'Monthly Deduction'!$H$3:$H$957),0) -> 0 | G97: =VLOOKUP(D97,'MPG Payment '!$E$3:$G$333666,3,0) -> vlc | H97: =VLOOKUP(D97,'MPG Payment '!$E$3:$H$333666,4,0) -> Indirect | I97: =INDEX('MPG Payment '!$C:$C,MATCH('Shayak Income '!D97,'MPG Payment '!E:E,0)) -> 1003 | J97: =INDEX('MPG Payment '!$D:$D,MATCH('Shayak Income '!D97,'MPG Payment '!E:E,0)) -> Asarganj | K97: Old | L97: 45212 | M97: =SUMIF('MPG Payment '!$E$3:$E$344841,'Shayak Income '!D97,'MPG Payment '!$I$3:$I$344841) -> 1449 | N97: =SUMIF('MPG Payment '!$E$3:$E$344841,'Shayak Income '!D97,'MPG Payment '!$J$3:$J$344841) -> 65008.73 | O97: =+M97*0.75 -> 1086.75 | P97: =+M97*0.95 -> 1376.55 | Q97: =SUMIF('MPG Payment '!$E$3:$E$344841,'Shayak Income '!D97,'MPG Payment '!$S$3:$S$344841) -> 0 | R97: =+N97*3% -> 1950.2619 | S97: =R97-P97 -> 573.7119 | T97: =M97*0.1 -> 144.9 | U97: =((((((IF(K97="New",0,SUMIF('MPG Payment '!$E$3:$E$344841,'Shayak Income '!D97,'MPG Payment '!$AC$3:$AC$344841))))+0)+0)+0)+0)+0 -> 1212.1954 | V97: =ROUND((SUM(O97:Q97)-SUM(T97:U97)),0) -> 1106 | W97: =(((AN97-AO97)))+0 -> 0 | X97: =((MIN(IF(B97>0,MAX(N97*2%),0),B97)))+0 -> 0 | Y97: =IFERROR(VLOOKUP(D97,'Monthly Deduction'!$M$2:$N$640,2,0),0) -> 0 | Z97: 0 | AA97: =IFERROR(VLOOKUP(D97,'Monthly Deduction'!A:B,2,0),0) -> 0 | AB97: =ROUND(IFERROR(V97-SUM(W97:AA97),0),0) -> 1106 | AC97: 0 | AD97: =ROUND(AB97-AC97,0) -> 1106 | AE97: =IF(AC97<>0,"Yes","Release") -> Release | AG97: 0 | AI97: 0 | AK97: 387.65 | AL97: =COUNTIF(AK97:AK97,"=NA") -> 0 | AN97: =((MIN(IF(A97>0,MAX(N97*2%,1861),0),A97)))+0 -> 0 | AO97: =SUMIF('MPG Payment '!E:E,'Shayak Income '!D97,'MPG Payment '!AJ:AJ) -> 0 | AP97: =W97 -> 0 | AQ97: =AO97+AP97 -> 0 | AS97: =B97-X97 -> 0
A98: =IFERROR(VLOOKUP(D98,'Monthly Deduction'!$I$3:$J$957,2,0),0) -> 0 | B98: =IFERROR(VLOOKUP(D98,'Monthly Deduction'!$E$3:$F$957,2,0),0) -> 0 | C98: =A98+B98 -> 0 | D98: 10030041 | E98: =VLOOKUP(D98,'MPG Payment '!$E$3:$G$497305,2,0) -> Akbarnagar - Rakhi | F98: =IFERROR(_xlfn.XLOOKUP(D98,'Monthly Deduction'!$I$3:$I$957,'Monthly Deduction'!$H$3:$H$957),0) -> 0 | G98: =VLOOKUP(D98,'MPG Payment '!$E$3:$G$333666,3,0) -> vlc | H98: =VLOOKUP(D98,'MPG Payment '!$E$3:$H$333666,4,0) -> Indirect | I98: =INDEX('MPG Payment '!$C:$C,MATCH('Shayak Income '!D98,'MPG Payment '!E:E,0)) -> 1003 | J98: =INDEX('MPG Payment '!$D:$D,MATCH('Shayak Income '!D98,'MPG Payment '!E:E,0)) -> Asarganj | K98: Old | L98: 45212 | M98: =SUMIF('MPG Payment '!$E$3:$E$344841,'Shayak Income '!D98,'MPG Payment '!$I$3:$I$344841) -> 4592.5 | N98: =SUMIF('MPG Payment '!$E$3:$E$344841,'Shayak Income '!D98,'MPG Payment '!$J$3:$J$344841) -> 184859.13 | O98: =+M98*0.75 -> 3444.375 | P98: =+M98*0.95 -> 4362.875 | Q98: =SUMIF('MPG Payment '!$E$3:$E$344841,'Shayak Income '!D98,'MPG Payment '!$S$3:$S$344841) -> 0 | R98: =+N98*3% -> 5545.7739 | S98: =R98-P98 -> 1182.8989 | T98: =M98*0.1 -> 459.25 | U98: =((((((IF(K98="New",0,SUMIF('MPG Payment '!$E$3:$E$344841,'Shayak Income '!D98,'MPG Payment '!$AC$3:$AC$344841))))+0)+0)+0)+0)+0 -> 0 | V98: =ROUND((SUM(O98:Q98)-SUM(T98:U98)),0) -> 7348 | W98: =(((AN98-AO98)))+0 -> 0 | X98: =((MIN(IF(B98>0,MAX(N98*2%),0),B98)))+0 -> 0 | Y98: =IFERROR(VLOOKUP(D98,'Monthly Deduction'!$M$2:$N$640,2,0),0) -> 0 | Z98: 0 | AA98: =IFERROR(VLOOKUP(D98,'Monthly Deduction'!A:B,2,0),0) -> 0 | AB98: =ROUND(IFERROR(V98-SUM(W98:AA98),0),0) -> 7348 | AC98: 0 | AD98: =ROUND(AB98-AC98,0) -> 7348 | AE98: =IF(AC98<>0,"Yes","Release") -> Release | AG98: 0 | AI98: 0 | AK98: 1166.6 | AL98: =COUNTIF(AK98:AK98,"=NA") -> 0 | AN98: =((MIN(IF(A98>0,MAX(N98*2%,1861),0),A98)))+0 -> 0 | AO98: =SUMIF('MPG Payment '!E:E,'Shayak Income '!D98,'MPG Payment '!AJ:AJ) -> 0 | AP98: =W98 -> 0 | AQ98: =AO98+AP98 -> 0 | AS98: =B98-X98 -> 0
A99: =IFERROR(VLOOKUP(D99,'Monthly Deduction'!$I$3:$J$957,2,0),0) -> 0 | B99: =IFERROR(VLOOKUP(D99,'Monthly Deduction'!$E$3:$F$957,2,0),0) -> 0 | C99: =A99+B99 -> 0 | D99: 10030042 | E99: =VLOOKUP(D99,'MPG Payment '!$E$3:$G$497305,2,0) -> Maheshi - Chamcham | F99: =IFERROR(_xlfn.XLOOKUP(D99,'Monthly Deduction'!$I$3:$I$957,'Monthly Deduction'!$H$3:$H$957),0) -> 0 | G99: =VLOOKUP(D99,'MPG Payment '!$E$3:$G$333666,3,0) -> VLC | H99: =VLOOKUP(D99,'MPG Payment '!$E$3:$H$333666,4,0) -> Indirect | I99: =INDEX('MPG Payment '!$C:$C,MATCH('Shayak Income '!D99,'MPG Payment '!E:E,0)) -> 1003 | J99: =INDEX('MPG Payment '!$D:$D,MATCH('Shayak Income '!D99,'MPG Payment '!E:E,0)) -> Asarganj | K99: Old | L99: 45212 | M99: =SUMIF('MPG Payment '!$E$3:$E$344841,'Shayak Income '!D99,'MPG Payment '!$I$3:$I$344841) -> 1957.7 | N99: =SUMIF('MPG Payment '!$E$3:$E$344841,'Shayak Income '!D99,'MPG Payment '!$J$3:$J$344841) -> 81694.19 | O99: =+M99*0.75 -> 1468.275 | P99: =+M99*0.95 -> 1859.815 | Q99: =SUMIF('MPG Payment '!$E$3:$E$344841,'Shayak Income '!D99,'MPG Payment '!$S$3:$S$344841) -> 0 | R99: =+N99*3% -> 2450.8257 | S99: =R99-P99 -> 591.0107 | T99: =M99*0.1 -> 195.77 | U99: =((((((IF(K99="New",0,SUMIF('MPG Payment '!$E$3:$E$344841,'Shayak Income '!D99,'MPG Payment '!$AC$3:$AC$344841))))+0)+0)+0)+0)+0 -> 163.62991 | V99: =ROUND((SUM(O99:Q99)-SUM(T99:U99)),0) -> 2969 | W99: =(((AN99-AO99)))+0 -> 0 | X99: =((MIN(IF(B99>0,MAX(N99*2%),0),B99)))+0 -> 0 | Y99: =IFERROR(VLOOKUP(D99,'Monthly Deduction'!$M$2:$N$640,2,0),0) -> 0 | Z99: 0 | AA99: =IFERROR(VLOOKUP(D99,'Monthly Deduction'!A:B,2,0),0) -> 0 | AB99: =ROUND(IFERROR(V99-SUM(W99:AA99),0),0) -> 2969 | AC99: 0 | AD99: =ROUND(AB99-AC99,0) -> 2969 | AE99: =IF(AC99<>0,"Yes","Release") -> Release | AG99: 0 | AI99: 0 | AK99: 503.6 | AL99: =COUNTIF(AK99:AK99,"=NA") -> 0 | AN99: =((MIN(IF(A99>0,MAX(N99*2%,1861),0),A99)))+0 -> 0 | AO99: =SUMIF('MPG Payment '!E:E,'Shayak Income '!D99,'MPG Payment '!AJ:AJ) -> 0 | AP99: =W99 -> 0 | AQ99: =AO99+AP99 -> 0 | AS99: =B99-X99 -> 0
A100: =IFERROR(VLOOKUP(D100,'Monthly Deduction'!$I$3:$J$957,2,0),0) -> 0 | B100: =IFERROR(VLOOKUP(D100,'Monthly Deduction'!$E$3:$F$957,2,0),0) -> 0 | C100: =A100+B100 -> 0 | D100: 10030043 | E100: =VLOOKUP(D100,'MPG Payment '!$E$3:$G$497305,2,0) -> Ghorpithiya - Dheeraj | F100: =IFERROR(_xlfn.XLOOKUP(D100,'Monthly Deduction'!$I$3:$I$957,'Monthly Deduction'!$H$3:$H$957),0) -> 0 | G100: =VLOOKUP(D100,'MPG Payment '!$E$3:$G$333666,3,0) -> vlc | H100: =VLOOKUP(D100,'MPG Payment '!$E$3:$H$333666,4,0) -> Indirect | I100: =INDEX('MPG Payment '!$C:$C,MATCH('Shayak Income '!D100,'MPG Payment '!E:E,0)) -> 1003 | J100: =INDEX('MPG Payment '!$D:$D,MATCH('Shayak Income '!D100,'MPG Payment '!E:E,0)) -> Asarganj | K100: Old | L100: 45212 | M100: =SUMIF('MPG Payment '!$E$3:$E$344841,'Shayak Income '!D100,'MPG Payment '!$I$3:$I$344841) -> 42075.95 | N100: =SUMIF('MPG Payment '!$E$3:$E$344841,'Shayak Income '!D100,'MPG Payment '!$J$3:$J$344841) -> 1761671.3 | O100: =+M100*0.75 -> 31556.962 | P100: =+M100*0.95 -> 39972.152 | Q100: =SUMIF('MPG Payment '!$E$3:$E$344841,'Shayak Income '!D100,'MPG Payment '!$S$3:$S$344841) -> 0 | R100: =+N100*3% -> 52850.14 | S100: =R100-P100 -> 12877.987 | T100: =M100*0.1 -> 4207.595 | U100: =((((((IF(K100="New",0,SUMIF('MPG Payment '!$E$3:$E$344841,'Shayak Income '!D100,'MPG Payment '!$AC$3:$AC$344841))))+0)+0)+0)+0)+0 -> 0 | V100: =ROUND((SUM(O100:Q100)-SUM(T100:U100)),0) -> 67322 | W100: =(((AN100-AO100)))+0 -> 0 | X100: =((MIN(IF(B100>0,MAX(N100*2%),0),B100)))+0 -> 0 | Y100: =IFERROR(VLOOKUP(D100,'Monthly Deduction'!$M$2:$N$640,2,0),0) -> 0 | Z100: 0 | AA100: =IFERROR(VLOOKUP(D100,'Monthly Deduction'!A:B,2,0),0) -> 0 | AB100: =ROUND(IFERROR(V100-SUM(W100:AA100),0),0) -> 67322 | AC100: 0 | AD100: =ROUND(AB100-AC100,0) -> 67322 | AE100: =IF(AC100<>0,"Yes","Release") -> Release | AG100: 0 | AI100: 0 | AK100: 8342.5 | AL100: =COUNTIF(AK100:AK100,"=NA") -> 0 | AN100: =((MIN(IF(A100>0,MAX(N100*2%,1861),0),A100)))+0 -> 0 | AO100: =SUMIF('MPG Payment '!E:E,'Shayak Income '!D100,'MPG Payment '!AJ:AJ) -> 0 | AP100: =W100 -> 0 | AQ100: =AO100+AP100 -> 0 | AS100: =B100-X100 -> 0
...

Sheet Sheet1
B3: Values
A4: Code | B4: Sum of BMC Volume | C4: Sum of BMC Amount
A5: 10010013 | B5: 2231.3 | C5: 84420.7
A6: 10010019 | B6: 3615.7 | C6: 140356.54
A7: 10010038 | B7: 3578.58 | C7: 143943.17
A8: 10010047 | B8: 527.9 | C8: 20684.89
A9: 10010050 | B9: 5015.62 | C9: 217108.75
A10: 10010051 | B10: 81.59 | C10: 3336.3
A11: 10010055 | B11: 398.2 | C11: 16578.31
A12: 10010057 | B12: 36779.8 | C12: 1389812.2
A13: 10010076 | B13: 3203.4 | C13: 140070.81
A14: 10010082 | B14: 4784.1 | C14: 186101.66
A15: 10010084 | B15: 1017.7 | C15: 34594.48
A16: 10010086 | B16: 340.43 | C16: 16211.8
... A1058: 10660037 | B1058: 22 | C1058: 889.9
A1059: Grand Total | B1059: 4064088.6 | C1059: 1.6645502e+08

Sheet Sheet2
A3: Row Labels | B3: Sum of EMI Recovery | F3: Row Labels | G3: Sum of EMI Recovery
A4: 10010013 | B4: 0 | F4: 10010013 | G4: 0
A5: 10010019 | B5: 0 | F5: 10010017 | G5: 1000
A6: 10010038 | B6: 0 | F6: 10010019 | G6: 0
A7: 10010044 | B7: 0 | F7: 10010038 | G7: 0
A8: 10010047 | B8: 0 | F8: 10010044 | G8: 0
A9: 10010049 | B9: 0 | F9: 10010047 | G9: 0
A10: 10010050 | B10: 0 | F10: 10010049 | G10: 0
A11: 10010051 | B11: 0 | F11: 10010050 | G11: 0
A12: 10010055 | B12: 2000 | F12: 10010051 | G12: 0
A13: 10010057 | B13: 0 | F13: 10010055 | G13: 0
A14: 10010076 | B14: 0 | F14: 10010056 | G14: 0
A15: 10010079 | B15: 0 | F15: 10010057 | G15: 0
... A1057: 10660037 | B1057: 0 | F1057: 10640003 | G1057: 0
A1058: Grand Total | B1058: 130688 | F1058: 10640004 | G1058: 0
F1059: 10640005 | G1059: 0
F1060: 10640006 | G1060: 0
F1061: 10640007 | G1061: 0
F1062: 10640009 | G1062: 0
F1063: 10640010 | G1063: 0
F1064: 10640011 | G1064: 0
F1065: 10650001 | G1065: 0
F1066: 10650003 | G1066: 0
F1067: 10650004 | G1067: 0
F1068: 10650006 | G1068: 0
F1069: 10650007 | G1069: 0
F1070: 10650008 | G1070: 0
... F1073: 10650012 | G1073: 0
F1074: Grand Total | G1074: 74459

Sheet MPG Payment 
I1: New Format | K1: Reg. Farmers | M1: Unreg. Farmers | O1: Total farmer
A2: Area | B2: Period | C2: BMC Code | D2: MCC Name | E2: Code | F2: MPG NAME | G2: Type | H2: Farmer Payment | I2: BMC Volume | J2: BMC Amount | K2: Vol | L2: Amt | M2: Vol | N2: Amt | O2: Vol | P2: Amt | Q2: Payable | R2: Other Ded | S2: Sample Am | T2: Loss Apportion | U2: CF/Vet Ded | V2: Advance | W2: Others | X2: Payment to Farmer A/c | Y2: Unreg. Farmer payment | Z2: Payment to MPGs A/c | AA2: Closing Reserve | AB2: Stop Payment | AC2: Vol Penalty Amount | AD2: Vol | AE2: loss/gain | AF2: Nos.Of farmer | AJ2: EMI Recovery | AK2: Cow Segre % | AL2: Inward Penalty | AM2: Total
A3: Munger | B3: 03-09 Jul | C3: 1001 | D3: Majhaul | E3: 10010013 | F3: Gomukh Kumbhi | G3: MPG | H3: Direct | I3: 612.4 | J3: 22833.28 | K3: 623.03 | L3: 24057.63 | M3: 2.13 | N3: 82.85 | O3: 625.16 | P3: 24140.48 | Q3: 22833.28 | R3: 0 | S3: 82.85 | T3: 1307.2 | U3: 0 | V3: 0 | W3: 0 | X3: 22750 | Y3: 0 | Z3: 0 | AA3: 0 | AB3: Release4 | AC3: =((IF(AD3=0,0,100-AD3))*7*(J3/I3))*2% -> 65.323166 | AD3: =IF((I3/7)>100,0,(I3/7)) -> 87.485714 | AE3: -0.057249769 | AF3: 16 | AH3: =TEXT(D3,"0000") -> Majhaul | AJ3: 0
