Workbook
Name Purchase: Table3[]
Name Table4: 'Stock Munger'!$D$88

Sheet Stock Munger
A1: Item Name | B1: UoM | C1: Opening Stock | D1: Received Stock | E1: Issue Stock | F1: Closing Balance | G1: Reorder Qty | H1: Reorder Level | I1: Open Rate | J1: Stock Value | K1: Stock Staus
A2: 1% Iodine Solution (100ml) | B2: Nos | C2: 13 | D2: 0 | E2: 1 | F2: 12 | G2: 15 | H2: 5 | I2: 90 | J2: 1080 | K2: Stock Available
A3: Amber Colour Bottle (250 ML) | B3: Nos | C3: 120 | D3: 0 | E3: 2 | F3: 118 | G3: 50 | H3: 40 | I3: 120 | J3: 14160 | K3: Stock Available
A4: Amyl 500ml | B4: Nos | C4: 47 | D4: 0 | E4: 24 | F4: 23 | G4: 50 | H4: 30 | I4: 366 | J4: 8413 | K4: PO Required
A5: Analyzer Calibration Cheking Log Book | B5: Nos | C5: 61 | D5: 0 | E5: 27 | F5: 34 | G5: 100 | H5: 20 | I5: 127 | J5: 4333 | K5: Stock Available
A6: Beaker 100 Ml | B6: Nos | C6: 16 | D6: 0 | E6: 3 | F6: 13 | G6: 48 | H6: 10 | I6: 33 | J6: 431 | K6: Stock Available
A7: Beaker 250 ML Borosilicate | B7: Nos | C7: 20 | D7: 0 | E7: 2 | F7: 18 | G7: 48 | H7: 10 | I7: 65 | J7: 1168 | K7: Stock Available
A8: Beaker 500 Ml | B8: Nos | C8: 25 | D8: 0 | E8: 2 | F8: 23 | G8: 48 | H8: 10 | I8: 64 | J8: 1465 | K8: Stock Available
A9: Beaker 50 ML | B9: Nos | C9: 28 | D9: 0 | E9: 3 | F9: 25 | G9: 48 | H9: 10 | I9: 16 | J9: 397 | K9: Stock Available
A10: BMC Cleaning Brush 2" | B10: Nos | C10: 26 | D10: 0 | E10: 3 | F10: 23 | G10: 10 | H10: 10 | I10: 212 | J10: 4885 | K10: Stock Available
A11: BMC Day Book | B11: Nos | C11: 90 | D11: 0 | E11: 86 | F11: 4 | G11: 300 | H11: 60 | I11: 122 | J11: 486 | K11: PO Required
A12: Burete Stand | B12: Nos | C12: 2 | D12: 0 | E12: 1 | F12: 1 | G12: 20 | H12: 5 | I12: 258 | J12: 258 | K12: PO Required
A13: Burret 50 ML Borosilicate | B13: Nos | C13: 8 | D13: 0 | E13: 3 | F13: 5 | G13: 20 | H13: 5 | I13: 99 | J13: 497 | K13: PO Required
... A97: Tilt Measure 1 Ml with Bottle | B97: Nos | C97: 230 | D97: 0 | E97: 8 | F97: 222 | G97: 500 | H97: 50 | I97: 32 | J97: 7124 | K97: Stock Available

Sheet Pending Recoveries
A1: Date | B1: (All)
A3: To BMC/MPG Code | B3: BMC MPG Name | C3: Recovery Done | D3: Sum of Amt
A4: 1002 | B4: Laldiyara | C4: Pending | D4: 19211.68
A5: 1007 | B5: Araria | C5: Pending | D5: 5616.8
A6: 1009 | B6: Halsi | C6: Pending | D6: 8712.5
A7: 1008 | B7: Teghra | C7: Pending | D7: 3204.32
A8: 10140002 | B8: Simri | C8: Pending | D8: 458.32
A9: 10140007 | B9: ENGLISH DUBAULI | C9: Pending | D9: 165.82
A10: 10140055 | B10: PURANA BHOJPUR | C10: Pending | D10: 1711.7
A11: 10140087 | B11: Gomukh Churamanpur | C11: Pending | D11: 1637.68
A12: 10140099 | B12: Gomukh Dhakaich | C12: Pending | D12: 1529
A13: 10510001 | B13: ARAK | C13: Pending | D13: 1208.99
A14: 10140145 | B14: Gomukh Pokhraha | C14: Pending | D14: 129.8
A15: 10140166 | B15: Gomukh KritSagar | C15: Pending | D15: 184.7
... A114: 10600013 | B114: Gomukh Chhotaki hardiya | C114: Pending | D114: 259.6
A115: Grand Total | D115: 126626.26

Sheet Issue
A1: Date | B1: Type | C1: Challan No | D1: From Location Code | E1: Location | F1: Type of Location | G1: To BMC/MPG Code | H1: BMC MPG Name | I1: Type of Location2 | J1: Item Name | K1: UoM | L1: Qty Issued | M1: Rate | N1: Amt | O1: Recoverable | P1: Recovery Done | Q1: Remarks
A2: 46113 | B2: Transfer | D2: 1 | E2: =IFERROR(VLOOKUP(Issue!$D2,Table5[#All],3,0),"") -> Munger | F2: =IFERROR(VLOOKUP(Issue!$D2,Table5[#All],2,0),"") -> Main Godown | G2: 1053 | H2: =IFERROR(VLOOKUP(Issue!$G2,Table5[#All],3,0),"") -> Kalyanpur | I2: =IFERROR(VLOOKUP(Issue!$G2,Table5[#All],2,0),"") -> BMC | J2: Eco Power Solution | K2: =IFERROR(VLOOKUP(Issue!$J2,Table2[[Item Name]:[UoM]],2,0),"") -> Nos | L2: 1 | M2: =IFERROR(VLOOKUP(Issue!$J2,Table2[[#All],[Item Name]:[Open Rate]],8,0),"") -> 348.52 | N2: =IFERROR(+Issue!$L2*Issue!$M2,"") -> 348.52 | O2: No | P2: NA
A3: 46113 | B3: Transfer | D3: 1 | E3: =IFERROR(VLOOKUP(Issue!$D3,Table5[#All],3,0),"") -> Munger | F3: =IFERROR(VLOOKUP(Issue!$D3,Table5[#All],2,0),"") -> Main Godown | G3: 1053 | H3: =IFERROR(VLOOKUP(Issue!$G3,Table5[#All],3,0),"") -> Kalyanpur | I3: =IFERROR(VLOOKUP(Issue!$G3,Table5[#All],2,0),"") -> BMC | J3: Eko Day Cleaning Sol | K3: =IFERROR(VLOOKUP(Issue!$J3,Table2[[Item Name]:[UoM]],2,0),"") -> Nos | L3: 21 | M3: =IFERROR(VLOOKUP(Issue!$J3,Table2[[#All],[Item Name]:[Open Rate]],8,0),"") -> 348.52 | N3: =IFERROR(+Issue!$L3*Issue!$M3,"") -> 7318.92 | O3: No | P3: NA
A4: 46113 | B4: Transfer | D4: 1 | E4: =IFERROR(VLOOKUP(Issue!$D4,Table5[#All],3,0),"") -> Munger | F4: =IFERROR(VLOOKUP(Issue!$D4,Table5[#All],2,0),"") -> Main Godown | G4: 1053 | H4: =IFERROR(VLOOKUP(Issue!$G4,Table5[#All],3,0),"") -> Kalyanpur | I4: =IFERROR(VLOOKUP(Issue!$G4,Table5[#All],2,0),"") -> BMC | J4: FAT Scan Weekly | K4: =IFERROR(VLOOKUP(Issue!$J4,Table2[[Item Name]:[UoM]],2,0),"") -> Nos | L4: 1 | M4: =IFERROR(VLOOKUP(Issue!$J4,Table2[[#All],[Item Name]:[Open Rate]],8,0),"") -> 348.52 | N4: =IFERROR(+Issue!$L4*Issue!$M4,"") -> 348.52 | O4: No | P4: NA
A5: 46113 | B5: Transfer | D5: 1 | E5: =IFERROR(VLOOKUP(Issue!$D5,Table5[#All],3,0),"") -> Munger | F5: =IFERROR(VLOOKUP(Issue!$D5,Table5[#All],2,0),"") -> Main Godown | G5: 1053 | H5: =IFERROR(VLOOKUP(Issue!$G5,Table5[#All],3,0),"") -> Kalyanpur | I5: =IFERROR(VLOOKUP(Issue!$G5,Table5[#All],2,0),"") -> BMC | J5: Milk Sampler Dipper SS Capacity 50ml | K5: =IFERROR(VLOOKUP(Issue!$J5,Table2[[Item Name]:[UoM]],2,0),"") -> Nos | L5: 4 | M5: =IFERROR(VLOOKUP(Issue!$J5,Table2[[#All],[Item Name]:[Open Rate]],8,0),"") -> 22.99 | N5: =IFERROR(+Issue!$L5*Issue!$M5,"") -> 91.96 | O5: No | P5: NA
A6: 46113 | B6: Transfer | D6: 1 | E6: =IFERROR(VLOOKUP(Issue!$D6,Table5[#All],3,0),"") -> Munger | F6: =IFERROR(VLOOKUP(Issue!$D6,Table5[#All],2,0),"") -> Main Godown | G6: 1053 | H6: =IFERROR(VLOOKUP(Issue!$G6,Table5[#All],3,0),"") -> Kalyanpur | I6: =IFERROR(VLOOKUP(Issue!$G6,Table5[#All],2,0),"") -> BMC | J6: MPG Register | K6: =IFERROR(VLOOKUP(Issue!$J6,Table2[[Item Name]:[UoM]],2,0),"") -> Nos | L6: 10 | M6: =IFERROR(VLOOKUP(Issue!$J6,Table2[[#All],[Item Name]:[Open Rate]],8,0),"") -> 129.8 | N6: =IFERROR(+Issue!$L6*Issue!$M6,"") -> 1298 | O6: No | P6: NA
A7: 46113 | B7: Transfer | D7: 1 | E7: =IFERROR(VLOOKUP(Issue!$D7,Table5[#All],3,0),"") -> Munger | F7: =IFERROR(VLOOKUP(Issue!$D7,Table5[#All],2,0),"") -> Main Godown | G7: 1053 | H7: =IFERROR(VLOOKUP(Issue!$G7,Table5[#All],3,0),"") -> Kalyanpur | I7: =IFERROR(VLOOKUP(Issue!$G7,Table5[#All],2,0),"") -> BMC | J7: Plastic Strainer | K7: =IFERROR(VLOOKUP(Issue!$J7,Table2[[Item Name]:[UoM]],2,0),"") -> Nos | L7: 4 | M7: =IFERROR(VLOOKUP(Issue!$J7,Table2[[#All],[Item Name]:[Open Rate]],8,0),"") -> 29.5 | N7: =IFERROR(+Issue!$L7*Issue!$M7,"") -> 118 | O7: No | P7: NA
A8: 46113 | B8: Transfer | D8: 1 | E8: =IFERROR(VLOOKUP(Issue!$D8,Table5[#All],3,0),"") -> Munger | F8: =IFERROR(VLOOKUP(Issue!$D8,Table5[#All],2,0),"") -> Main Godown | G8: 1053 | H8: =IFERROR(VLOOKUP(Issue!$G8,Table5[#All],3,0),"") -> Kalyanpur | I8: =IFERROR(VLOOKUP(Issue!$G8,Table5[#All],2,0),"") -> BMC | J8: Sample Bottle 100 ML | K8: =IFERROR(VLOOKUP(Issue!$J8,Table2[[Item Name]:[UoM]],2,0),"") -> Nos | L8: 4 | M8: =IFERROR(VLOOKUP(Issue!$J8,Table2[[#All],[Item Name]:[Open Rate]],8,0),"") -> 2.83 | N8: =IFERROR(+Issue!$L8*Issue!$M8,"") -> 11.32 | O8: No | P8: NA
A9: 46113 | B9: Transfer | D9: 1 | E9: =IFERROR(VLOOKUP(Issue!$D9,Table5[#All],3,0),"") -> Munger | F9: =IFERROR(VLOOKUP(Issue!$D9,Table5[#All],2,0),"") -> Main Godown | G9: 1053 | H9: =IFERROR(VLOOKUP(Issue!$G9,Table5[#All],3,0),"") -> Kalyanpur | I9: =IFERROR(VLOOKUP(Issue!$G9,Table5[#All],2,0),"") -> BMC | J9: Thermal Paper Roll - Small | K9: =IFERROR(VLOOKUP(Issue!$J9,Table2[[Item Name]:[UoM]],2,0),"") -> Nos | L9: 374 | M9: =IFERROR(VLOOKUP(Issue!$J9,Table2[[#All],[Item Name]:[Open Rate]],8,0),"") -> 9.15 | N9: =IFERROR(+Issue!$L9*Issue!$M9,"") -> 3422.1 | O9: No | P9: NA
A10: 46113 | B10: Transfer | D10: 1 | E10: =IFERROR(VLOOKUP(Issue!$D10,Table5[#All],3,0),"") -> Munger | F10: =IFERROR(VLOOKUP(Issue!$D10,Table5[#All],2,0),"") -> Main Godown | G10: 1014 | H10: =IFERROR(VLOOKUP(Issue!$G10,Table5[#All],3,0),"") -> Dumraon | I10: =IFERROR(VLOOKUP(Issue!$G10,Table5[#All],2,0),"") -> BMC | J10: Eco Power Solution | K10: =IFERROR(VLOOKUP(Issue!$J10,Table2[[Item Name]:[UoM]],2,0),"") -> Nos | L10: 18 | M10: =IFERROR(VLOOKUP(Issue!$J10,Table2[[#All],[Item Name]:[Open Rate]],8,0),"") -> 348.52 | N10: =IFERROR(+Issue!$L10*Issue!$M10,"") -> 6273.36 | O10: No | P10: NA
A11: 46113 | B11: Transfer | D11: 1 | E11: =IFERROR(VLOOKUP(Issue!$D11,Table5[#All],3,0),"") -> Munger | F11: =IFERROR(VLOOKUP(Issue!$D11,Table5[#All],2,0),"") -> Main Godown | G11: 1014 | H11: =IFERROR(VLOOKUP(Issue!$G11,Table5[#All],3,0),"") -> Dumraon | I11: =IFERROR(VLOOKUP(Issue!$G11,Table5[#All],2,0),"") -> BMC | J11: Eko Day Cleaning Sol | K11: =IFERROR(VLOOKUP(Issue!$J11,Table2[[Item Name]:[UoM]],2,0),"") -> Nos | L11: 96 | M11: =IFERROR(VLOOKUP(Issue!$J11,Table2[[#All],[Item Name]:[Open Rate]],8,0),"") -> 348.52 | N11: =IFERROR(+Issue!$L11*Issue!$M11,"") -> 33457.92 | O11: No | P11: NA
A12: 46113 | B12: Transfer | D12: 1 | E12: =IFERROR(VLOOKUP(Issue!$D12,Table5[#All],3,0),"") -> Munger | F12: =IFERROR(VLOOKUP(Issue!$D12,Table5[#All],2,0),"") -> Main Godown | G12: 1014 | H12: =IFERROR(VLOOKUP(Issue!$G12,Table5[#All],3,0),"") -> Dumraon | I12: =IFERROR(VLOOKUP(Issue!$G12,Table5[#All],2,0),"") -> BMC | J12: EKO Plunger | K12: =IFERROR(VLOOKUP(Issue!$J12,Table2[[Item Name]:[UoM]],2,0),"") -> Nos | L12: 81 | M12: =IFERROR(VLOOKUP(Issue!$J12,Table2[[#All],[Item Name]:[Open Rate]],8,0),"") -> 56.02 | N12: =IFERROR(+Issue!$L12*Issue!$M12,"") -> 4537.62 | O12: No | P12: NA
A13: 46113 | B13: Transfer | D13: 1 | E13: =IFERROR(VLOOKUP(Issue!$D13,Table5[#All],3,0),"") -> Munger | F13: =IFERROR(VLOOKUP(Issue!$D13,Table5[#All],2,0),"") -> Main Godown | G13: 1014 | H13: =IFERROR(VLOOKUP(Issue!$G13,Table5[#All],3,0),"") -> Dumraon | I13: =IFERROR(VLOOKUP(Issue!$G13,Table5[#All],2,0),"") -> BMC | J13: Farmers Passbook | K13: =IFERROR(VLOOKUP(Issue!$J13,Table2[[Item Name]:[UoM]],2,0),"") -> Nos | L13: 656 | M13: =IFERROR(VLOOKUP(Issue!$J13,Table2[[#All],[Item Name]:[Open Rate]],8,0),"") -> 5.13 | N13: =IFERROR(+Issue!$L13*Issue!$M13,"") -> 3365.28 | O13: No | P13: NA
... A29: 46113 | B29: Transfer | D29: 1 | E29: =IFERROR(VLOOKUP(Issue!$D29,Table5[#All],3,0),"") -> Munger | F29: =IFERROR(VLOOKUP(Issue!$D29,Table5[#All],2,0),"") -> Main Godown | G29: 1012 | H29: =IFERROR(VLOOKUP(Issue!$G29,Table5[#All],3,0),"") -> DalsinghSarai | I29: =IFERROR(VLOOKUP(Issue!$G29,Table5[#All],2,0),"") -> BMC | J29: MPG Register | K29: =IFERROR(VLOOKUP(Issue!$J29,Table2[[Item Name]:[UoM]],2,0),"") -> Nos | L29: 20 | M29: =IFERROR(VLOOKUP(Issue!$J29,Table2[[#All],[Item Name]:[Open Rate]],8,0),"") -> 129.8 | N29: =IFERROR(+Issue!$L29*Issue!$M29,"") -> 2596 | O29: No | P29: NA
A30: 46114 | B30: Consumed | C30: 623 | D30: 1 | E30: =IFERROR(VLOOKUP(Issue!$D30,Table5[#All],3,0),"") -> Munger | F30: =IFERROR(VLOOKUP(Issue!$D30,Table5[#All],2,0),"") -> Main Godown | G30: 1010 | H30: =IFERROR(VLOOKUP(Issue!$G30,Table5[#All],3,0),"") -> Parbatta | I30: =IFERROR(VLOOKUP(Issue!$G30,Table5[#All],2,0),"") -> BMC | J30: BMC Day Book | K30: =IFERROR(VLOOKUP(Issue!$J30,Table2[[Item Name]:[UoM]],2,0),"") -> Nos | L30: 10 | M30: =IFERROR(VLOOKUP(Issue!$J30,Table2[[#All],[Item Name]:[Open Rate]],8,0),"") -> 121.54 | N30: =IFERROR(+Issue!$L30*Issue!$M30,"") -> 1215.4 | O30: Yes | P30: Pending
A31: 46114 | B31: Consumed | C31: 623 | D31: 1 | E31: =IFERROR(VLOOKUP(Issue!$D31,Table5[#All],3,0),"") -> Munger | F31: =IFERROR(VLOOKUP(Issue!$D31,Table5[#All],2,0),"") -> Main Godown | G31: 1010 | H31: =IFERROR(VLOOKUP(Issue!$G31,Table5[#All],3,0),"") -> Parbatta | I31: =IFERROR(VLOOKUP(Issue!$G31,Table5[#All],2,0),"") -> BMC | J31: Buterometer | K31: =IFERROR(VLOOKUP(Issue!$J31,Table2[[Item Name]:[UoM]],2,0),"") -> Nos | L31: 1 | M31: =IFERROR(VLOOKUP(Issue!$J31,Table2[[#All],[Item Name]:[Open Rate]],8,0),"") -> 132.7 | N31: =IFERROR(+Issue!$L31*Issue!$M31,"") -> 132.7 | O31: Yes | P31: Pending
A32: 46114 | B32: Consumed | C32: 623 | D32: 1 | E32: =IFERROR(VLOOKUP(Issue!$D32,Table5[#All],3,0),"") -> Munger | F32: =IFERROR(VLOOKUP(Issue!$D32,Table5[#All],2,0),"") -> Main Godown | G32: 1010 | H32: =IFERROR(VLOOKUP(Issue!$G32,Table5[#All],3,0),"") -> Parbatta | I32: =IFERROR(VLOOKUP(Issue!$G32,Table5[#All],2,0),"") -> BMC | J32: Lactometer 0-40 | K32: =IFERROR(VLOOKUP(Issue!$J32,Table2[[Item Name]:[UoM]],2,0),"") -> Nos | L32: 1 | M32: =IFERROR(VLOOKUP(Issue!$J32,Table2[[#All],[Item Name]:[Open Rate]],8,0),"") -> 132.7 | N32: =IFERROR(+Issue!$L32*Issue!$M32,"") -> 132.7 | O32: Yes | P32: Pending
A33: 46116 | B33: Consumed | C33: 624 | D33: 1 | E33: =IFERROR(VLOOKUP(Issue!$D33,Table5[#All],3,0),"") -> Munger | F33: =IFERROR(VLOOKUP(Issue!$D33,Table5[#All],2,0),"") -> Main Godown | G33: 1054 | H33: =IFERROR(VLOOKUP(Issue!$G33,Table5[#All],3,0),"") -> Alauli | I33: =IFERROR(VLOOKUP(Issue!$G33,Table5[#All],2,0),"") -> BMC | J33: TEEPOL | K33: =IFERROR(VLOOKUP(Issue!$J33,Table2[[Item Name]:[UoM]],2,0),"") -> Nos | L33: 25 | M33: =IFERROR(VLOOKUP(Issue!$J33,Table2[[#All],[Item Name]:[Open Rate]],8,0),"") -> 51.92 | N33: =IFERROR(+Issue!$L33*Issue!$M33,"") -> 1298 | O33: No | P33: NA
A34: 46116 | B34: Consumed | C34: 624 | D34: 1 | E34: =IFERROR(VLOOKUP(Issue!$D34,Table5[#All],3,0),"") -> Munger | F34: =IFERROR(VLOOKUP(Issue!$D34,Table5[#All],2,0),"") -> Main Godown | G34: 1054 | H34: =IFERROR(VLOOKUP(Issue!$G34,Table5[#All],3,0),"") -> Alauli | I34: =IFERROR(VLOOKUP(Issue!$G34,Table5[#All],2,0),"") -> BMC | J34: Satol - 5 KG | K34: =IFERROR(VLOOKUP(Issue!$J34,Table2[[Item Name]:[UoM]],2,0),"") -> Nos | L34: 5 | M34: =IFERROR(VLOOKUP(Issue!$J34,Table2[[#All],[Item Name]:[Open Rate]],8,0),"") -> 135.7 | N34: =IFERROR(+Issue!$L34*Issue!$M34,"") -> 678.5 | O34: No | P34: NA
A35: 46116 | B35: Consumed | C35: 624 | D35: 1 | E35: =IFERROR(VLOOKUP(Issue!$D35,Table5[#All],3,0),"") -> Munger | F35: =IFERROR(VLOOKUP(Issue!$D35,Table5[#All],2,0),"") -> Main Godown | G35: 1054 | H35: =IFERROR(VLOOKUP(Issue!$G35,Table5[#All],3,0),"") -> Alauli | I35: =IFERROR(VLOOKUP(Issue!$G35,Table5[#All],2,0),"") -> BMC | J35: Sulphuric Acid SQ 05 Lt | K35: =IFERROR(VLOOKUP(Issue!$J35,Table2[[Item Name]:[UoM]],2,0),"") -> Nos | L35: 1 | M35: =IFERROR(VLOOKUP(Issue!$J35,Table2[[#All],[Item Name]:[Open Rate]],8,0),"") -> 812.2 | N35: =IFERROR(+Issue!$L35*Issue!$M35,"") -> 812.2 | O35: No | P35: NA
A36: 46116 | B36: Consumed | C36: 624 | D36: 1 | E36: =IFERROR(VLOOKUP(Issue!$D36,Table5[#All],3,0),"") -> Munger | F36: =IFERROR(VLOOKUP(Issue!$D36,Table5[#All],2,0),"") -> Main Godown | G36: 1054 | H36: =IFERROR(VLOOKUP(Issue!$G36,Table5[#All],3,0),"") -> Alauli | I36: =IFERROR(VLOOKUP(Issue!$G36,Table5[#All],2,0),"") -> BMC | J36: Test Tube with Rubber Cork | K36: =IFERROR(VLOOKUP(Issue!$J36,Table2[[Item Name]:[UoM]],2,0),"") -> Nos | L36: 30 | M36: =IFERROR(VLOOKUP(Issue!$J36,Table2[[#All],[Item Name]:[Open Rate]],8,0),"") -> 4.93 | N36: =IFERROR(+Issue!$L36*Issue!$M36,"") -> 147.9 | O36: No | P36: NA
A37: 46116 | B37: Consumed | C37: 624 | D37: 1 | E37: =IFERROR(VLOOKUP(Issue!$D37,Table5[#All],3,0),"") -> Munger | F37: =IFERROR(VLOOKUP(Issue!$D37,Table5[#All],2,0),"") -> Main Godown | G37: 1054 | H37: =IFERROR(VLOOKUP(Issue!$G37,Table5[#All],3,0),"") -> Alauli | I37: =IFERROR(VLOOKUP(Issue!$G37,Table5[#All],2,0),"") -> BMC | J37: Distil Water 5 Ltr | K37: =IFERROR(VLOOKUP(Issue!$J37,Table2[[Item Name]:[UoM]],2,0),"") -> Nos | L37: 1 | M37: =IFERROR(VLOOKUP(Issue!$J37,Table2[[#All],[Item Name]:[Open Rate]],8,0),"") -> 168 | N37: =IFERROR(+Issue!$L37*Issue!$M37,"") -> 168 | O37: No | P37: NA
A38: 46116 | B38: Consumed | C38: 625 | D38: 1 | E38: =IFERROR(VLOOKUP(Issue!$D38,Table5[#All],3,0),"") -> Munger | F38: =IFERROR(VLOOKUP(Issue!$D38,Table5[#All],2,0),"") -> Main Godown | G38: 1011 | H38: =IFERROR(VLOOKUP(Issue!$G38,Table5[#All],3,0),"") -> Sahibpur Kamal | I38: =IFERROR(VLOOKUP(Issue!$G38,Table5[#All],2,0),"") -> BMC | J38: Tanker Seal | K38: =IFERROR(VLOOKUP(Issue!$J38,Table2[[Item Name]:[UoM]],2,0),"") -> Nos | L38: 200 | M38: =IFERROR(VLOOKUP(Issue!$J38,Table2[[#All],[Item Name]:[Open Rate]],8,0),"") -> 12.71 | N38: =IFERROR(+Issue!$L38*Issue!$M38,"") -> 2542 | O38: No | P38: NA
A39: 46116 | B39: Consumed | C39: 625 | D39: 1 | E39: =IFERROR(VLOOKUP(Issue!$D39,Table5[#All],3,0),"") -> Munger | F39: =IFERROR(VLOOKUP(Issue!$D39,Table5[#All],2,0),"") -> Main Godown | G39: 1055 | H39: =IFERROR(VLOOKUP(Issue!$G39,Table5[#All],3,0),"") -> Matihani | I39: =IFERROR(VLOOKUP(Issue!$G39,Table5[#All],2,0),"") -> BMC | J39: Tanker Seal | K39: =IFERROR(VLOOKUP(Issue!$J39,Table2[[Item Name]:[UoM]],2,0),"") -> Nos | L39: 200 | M39: =IFERROR(VLOOKUP(Issue!$J39,Table2[[#All],[Item Name]:[Open Rate]],8,0),"") -> 12.71 | N39: =IFERROR(+Issue!$L39*Issue!$M39,"") -> 2542 | O39: No | P39: NA
A40: 46116 | B40: Consumed | C40: 625 | D40: 1 | E40: =IFERROR(VLOOKUP(Issue!$D40,Table5[#All],3,0),"") -> Munger | F40: =IFERROR(VLOOKUP(Issue!$D40,Table5[#All],2,0),"") -> Main Godown | G40: 1008 | H40: =IFERROR(VLOOKUP(Issue!$G40,Table5[#All],3,0),"") -> Teghra | I40: =IFERROR(VLOOKUP(Issue!$G40,Table5[#All],2,0),"") -> BMC | J40: Tanker Seal | K40: =IFERROR(VLOOKUP(Issue!$J40,Table2[[Item Name]:[UoM]],2,0),"") -> Nos | L40: 200 | M40: =IFERROR(VLOOKUP(Issue!$J40,Table2[[#All],[Item Name]:[Open Rate]],8,0),"") -> 12.71 | N40: =IFERROR(+Issue!$L40*Issue!$M40,"") -> 2542 | O40: Yes | P40: Pending
A41: 46116 | B41: Consumed | C41: 625 | D41: 1 | E41: =IFERROR(VLOOKUP(Issue!$D41,Table5[#All],3,0),"") -> Munger | F41: =IFERROR(VLOOKUP(Issue!$D41,Table5[#All],2,0),"") -> Main Godown | G41: 1011 | H41: =IFERROR(VLOOKUP(Issue!$G41,Table5[#All],3,0),"") -> Sahibpur Kamal | I41: =IFERROR(VLOOKUP(Issue!$G41,Table5[#All],2,0),"") -> BMC | J41: Milk Despatch Challan | K41: =IFERROR(VLOOKUP(Issue!$J41,Table2[[Item Name]:[UoM]],2,0),"") -> Nos | L41: 2 | M41: =IFERROR(VLOOKUP(Issue!$J41,Table2[[#All],[Item Name]:[Open Rate]],8,0),"") -> 94.4 | N41: =IFERROR(+Issue!$L41*Issue!$M41,"") -> 188.8 | O41: No | P41: NA
... A90: 46121 | B90: Consumed | C90: 631 | D90: 1 | E90: =IFERROR(VLOOKUP(Issue!$D90,Table5[#All],3,0),"") -> Munger | F90: =IFERROR(VLOOKUP(Issue!$D90,Table5[#All],2,0),"") -> Main Godown | G90: 1065 | H90: =IFERROR(VLOOKUP(Issue!$G90,Table5[#All],3,0),"") -> Bachhwara BMC | I90: =IFERROR(VLOOKUP(Issue!$G90,Table5[#All],2,0),"") -> MPG | J90: Sample Bottle Brush Large | K90: =IFERROR(VLOOKUP(Issue!$J90,Table2[[Item Name]:[UoM]],2,0),"") -> Nos | L90: 18 | M90: =IFERROR(VLOOKUP(Issue!$J90,Table2[[#All],[Item Name]:[Open Rate]],8,0),"") -> 1.68 | N90: =IFERROR(+Issue!$L90*Issue!$M90,"") -> 30.24 | O90: No | P90: NA
A91: 46121 | B91: Consumed | C91: 632 | D91: 1 | E91: =IFERROR(VLOOKUP(Issue!$D91,Table5[#All],3,0),"") -> Munger | F91: =IFERROR(VLOOKUP(Issue!$D91,Table5[#All],2,0),"") -> Main Godown | G91: Lab | H91: =IFERROR(VLOOKUP(Issue!$G91,Table5[#All],3,0),"") -> Daya_Lab | I91: =IFERROR(VLOOKUP(Issue!$G91,Table5[#All],2,0),"") -> Lab | J91: Para Dimethyle Amino | K91: =IFERROR(VLOOKUP(Issue!$J91,Table2[[Item Name]:[UoM]],2,0),"") -> Nos | L91: 1 | M91: =IFERROR(VLOOKUP(Issue!$J91,Table2[[#All],[Item Name]:[Open Rate]],8,0),"") -> 689.39 | N91: =IFERROR(+Issue!$L91*Issue!$M91,"") -> 689.39 | O91: No | P91: NA
A92: 46121 | B92: Consumed | C92: 632 | D92: 1 | E92: =IFERROR(VLOOKUP(Issue!$D92,Table5[#All],3,0),"") -> Munger | F92: =IFERROR(VLOOKUP(Issue!$D92,Table5[#All],2,0),"") -> Main Godown | G92: Lab | H92: =IFERROR(VLOOKUP(Issue!$G92,Table5[#All],3,0),"") -> Daya_Lab | I92: =IFERROR(VLOOKUP(Issue!$G92,Table5[#All],2,0),"") -> Lab | J92: Resorcinol | K92: =IFERROR(VLOOKUP(Issue!$J92,Table2[[Item Name]:[UoM]],2,0),"") -> Nos | L92: 1 | M92: =IFERROR(VLOOKUP(Issue!$J92,Table2[[#All],[Item Name]:[Open Rate]],8,0),"") -> 504.15 | N92: =IFERROR(+Issue!$L92*Issue!$M92,"") -> 504.15 | O92: No | P92: NA
A93: 46121 | B93: Consumed | C93: 632 | D93: 1 | E93: =IFERROR(VLOOKUP(Issue!$D93,Table5[#All],3,0),"") -> Munger | F93: =IFERROR(VLOOKUP(Issue!$D93,Table5[#All],2,0),"") -> Main Godown | G93: Lab | H93: =IFERROR(VLOOKUP(Issue!$G93,Table5[#All],3,0),"") -> Daya_Lab | I93: =IFERROR(VLOOKUP(Issue!$G93,Table5[#All],2,0),"") -> Lab | J93: Milk Despatch Challan | K93: =IFERROR(VLOOKUP(Issue!$J93,Table2[[Item Name]:[UoM]],2,0),"") -> Nos | L93: 5 | M93: =IFERROR(VLOOKUP(Issue!$J93,Table2[[#All],[Item Name]:[Open Rate]],8,0),"") -> 94.4 | N93: =IFERROR(+Issue!$L93*Issue!$M93,"") -> 472 | O93: No | P93: NA
A94: 46125 | B94: Consumed | C94: 634 | D94: 1 | E94: =IFERROR(VLOOKUP(Issue!$D94,Table5[#All],3,0),"") -> Munger | F94: =IFERROR(VLOOKUP(Issue!$D94,Table5[#All],2,0),"") -> Main Godown | G94: 1001 | H94: =IFERROR(VLOOKUP(Issue!$G94,Table5[#All],3,0),"") -> Majhaul | I94: =IFERROR(VLOOKUP(Issue!$G94,Table5[#All],2,0),"") -> BMC | J94: Tanker Seal | K94: =IFERROR(VLOOKUP(Issue!$J94,Table2[[Item Name]:[UoM]],2,0),"") -> Nos | L94: 200 | M94: =IFERROR(VLOOKUP(Issue!$J94,Table2[[#All],[Item Name]:[Open Rate]],8,0),"") -> 12.71 | N94: =IFERROR(+Issue!$L94*Issue!$M94,"") -> 2542 | O94: No | P94: NA
A95: 46125 | B95: Consumed | C95: 634 | D95: 1 | E95: =IFERROR(VLOOKUP(Issue!$D95,Table5[#All],3,0),"") -> Munger | F95: =IFERROR(VLOOKUP(Issue!$D95,Table5[#All],2,0),"") -> Main Godown | G95: 1001 | H95: =IFERROR(VLOOKUP(Issue!$G95,Table5[#All],3,0),"") -> Majhaul | I95: =IFERROR(VLOOKUP(Issue!$G95,Table5[#All],2,0),"") -> BMC | J95: Phenolphthaleing Indicator | K95: =IFERROR(VLOOKUP(Issue!$J95,Table2[[Item Name]:[UoM]],2,0),"") -> Nos | L95: 1 | M95: =IFERROR(VLOOKUP(Issue!$J95,Table2[[#All],[Item Name]:[Open Rate]],8,0),"") -> 106.2 | N95: =IFERROR(+Issue!$L95*Issue!$M95,"") -> 106.2 | O95: No | P95: NA
A96: 46125 | B96: Consumed | C96: 634 | D96: 1 | E96: =IFERROR(VLOOKUP(Issue!$D96,Table5[#All],3,0),"") -> Munger | F96: =IFERROR(VLOOKUP(Issue!$D96,Table5[#All],2,0),"") -> Main Godown | G96: 1001 | H96: =IFERROR(VLOOKUP(Issue!$G96,Table5[#All],3,0),"") -> Majhaul | I96: =IFERROR(VLOOKUP(Issue!$G96,Table5[#All],2,0),"") -> BMC | J96: Sodium Hydroxide N/10 Solution | K96: =IFERROR(VLOOKUP(Issue!$J96,Table2[[Item Name]:[UoM]],2,0),"") -> Nos | L96: 1 | M96: =IFERROR(VLOOKUP(Issue!$J96,Table2[[#All],[Item Name]:[Open Rate]],8,0),"") -> 135.7 | N96: =IFERROR(+Issue!$L96*Issue!$M96,"") -> 135.7 | O96: No | P96: NA
A97: 46125 | B97: Consumed | C97: 634 | D97: 1 | E97: =IFERROR(VLOOKUP(Issue!$D97,Table5[#All],3,0),"") -> Munger | F97: =IFERROR(VLOOKUP(Issue!$D97,Table5[#All],2,0),"") -> Main Godown | G97: 1001 | H97: =IFERROR(VLOOKUP(Issue!$G97,Table5[#All],3,0),"") -> Majhaul | I97: =IFERROR(VLOOKUP(Issue!$G97,Table5[#All],2,0),"") -> BMC | J97: Amyl 500ml | K97: =IFERROR(VLOOKUP(Issue!$J97,Table2[[Item Name]:[UoM]],2,0),"") -> Nos | L97: 1 | M97: =IFERROR(VLOOKUP(Issue!$J97,Table2[[#All],[Item Name]:[Open Rate]],8,0),"") -> 365.8 | N97: =IFERROR(+Issue!$L97*Issue!$M97,"") -> 365.8 | O97: No | P97: NA
A98: 46125 | B98: Consumed | C98: 634 | D98: 1 | E98: =IFERROR(VLOOKUP(Issue!$D98,Table5[#All],3,0),"") -> Munger | F98: =IFERROR(VLOOKUP(Issue!$D98,Table5[#All],2,0),"") -> Main Godown | G98: 1001 | H98: =IFERROR(VLOOKUP(Issue!$G98,Table5[#All],3,0),"") -> Majhaul | I98: =IFERROR(VLOOKUP(Issue!$G98,Table5[#All],2,0),"") -> BMC | J98: Hydrolic Acid | K98: =IFERROR(VLOOKUP(Issue!$J98,Table2[[Item Name]:[UoM]],2,0),"") -> Nos | L98: 1 | M98: =IFERROR(VLOOKUP(Issue!$J98,Table2[[#All],[Item Name]:[Open Rate]],8,0),"") -> 282.8 | N98: =IFERROR(+Issue!$L98*Issue!$M98,"") -> 282.8 | O98: No | P98: NA
A99: 46125 | B99: Consumed | C99: 634 | D99: 1 | E99: =IFERROR(VLOOKUP(Issue!$D99,Table5[#All],3,0),"") -> Munger | F99: =IFERROR(VLOOKUP(Issue!$D99,Table5[#All],2,0),"") -> Main Godown | G99: 1001 | H99: =IFERROR(VLOOKUP(Issue!$G99,Table5[#All],3,0),"") -> Majhaul | I99: =IFERROR(VLOOKUP(Issue!$G99,Table5[#All],2,0),"") -> BMC | J99: TEEPOL | K99: =IFERROR(VLOOKUP(Issue!$J99,Table2[[Item Name]:[UoM]],2,0),"") -> Nos | L99: 25 | M99: =IFERROR(VLOOKUP(Issue!$J99,Table2[[#All],[Item Name]:[Open Rate]],8,0),"") -> 51.92 | N99: =IFERROR(+Issue!$L99*Issue!$M99,"") -> 1298 | O99: No | P99: NA
A100: 46125 | B100: Consumed | C100: 634 | D100: 1 | E100: =IFERROR(VLOOKUP(Issue!$D100,Table5[#All],3,0),"") -> Munger | F100: =IFERROR(VLOOKUP(Issue!$D100,Table5[#All],2,0),"") -> Main Godown | G100: 1001 | H100: =IFERROR(VLOOKUP(Issue!$G100,Table5[#All],3,0),"") -> Majhaul | I100: =IFERROR(VLOOKUP(Issue!$G100,Table5[#All],2,0),"") -> BMC | J100: Satol - 5 KG | K100: =IFERROR(VLOOKUP(Issue!$J100,Table2[[Item Name]:[UoM]],2,0),"") -> Nos | L100: 5 | M100: =IFERROR(VLOOKUP(Issue!$J100,Table2[[#All],[Item Name]:[Open Rate]],8,0),"") -> 135.7 | N100: =IFERROR(+Issue!$L100*Issue!$M100,"") -> 678.5 | O100: No | P100: NA
A101: 46125 | B101: Consumed | C101: 634 | D101: 1 | E101: =IFERROR(VLOOKUP(Issue!$D101,Table5[#All],3,0),"") -> Munger | F101: =IFERROR(VLOOKUP(Issue!$D101,Table5[#All],2,0),"") -> Main Godown | G101: 1001 | H101: =IFERROR(VLOOKUP(Issue!$G101,Table5[#All],3,0),"") -> Majhaul | I101: =IFERROR(VLOOKUP(Issue!$G101,Table5[#All],2,0),"") -> BMC | J101: Register for Milk Reception Log Book | K101: =IFERROR(VLOOKUP(Issue!$J101,Table2[[Item Name]:[UoM]],2,0),"") -> Nos | L101: 6 | M101: =IFERROR(VLOOKUP(Issue!$J101,Table2[[#All],[Item Name]:[Open Rate]],8,0),"") -> 218.3 | N101: =IFERROR(+Issue!$L101*Issue!$M101,"") -> 1309.8 | O101: No | P101: NA
A102: 46125 | B102: Consumed | C102: 634 | D102: 1 | E102: =IFERROR(VLOOKUP(Issue!$D102,Table5[#All],3,0),"") -> Munger | F102: =IFERROR(VLOOKUP(Issue!$D102,Table5[#All],2,0),"") -> Main Godown | G102: 1001 | H102: =IFERROR(VLOOKUP(Issue!$G102,Table5[#All],3,0),"") -> Majhaul | I102: =IFERROR(VLOOKUP(Issue!$G102,Table5[#All],2,0),"") -> BMC | J102: BMC Day Book | K102: =IFERROR(VLOOKUP(Issue!$J102,Table2[[Item Name]:[UoM]],2,0),"") -> Nos | L102: 6 | M102: =IFERROR(VLOOKUP(Issue!$J102,Table2[[#All],[Item Name]:[Open Rate]],8,0),"") -> 121.54 | N102: =IFERROR(+Issue!$L102*Issue!$M102,"") -> 729.24 | O102: No | P102: NA
A103: 46125 | B103: Consumed | C103: 634 | D103: 1 | E103: =IFERROR(VLOOKUP(Issue!$D103,Table5[#All],3,0),"") -> Munger | F103: =IFERROR(VLOOKUP(Issue!$D103,Table5[#All],2,0),"") -> Main Godown | G103: 1001 | H103: =IFERROR(VLOOKUP(Issue!$G103,Table5[#All],3,0),"") -> Majhaul | I103: =IFERROR(VLOOKUP(Issue!$G103,Table5[#All],2,0),"") -> BMC | J103: Milk Despatch Challan | K103: =IFERROR(VLOOKUP(Issue!$J103,Table2[[Item Name]:[UoM]],2,0),"") -> Nos | L103: 6 | M103: =IFERROR(VLOOKUP(Issue!$J103,Table2[[#All],[Item Name]:[Open Rate]],8,0),"") -> 94.4 | N103: =IFERROR(+Issue!$L103*Issue!$M103,"") -> 566.4 | O103: No | P103: NA
A104: 46125 | B104: Consumed | C104: 635 | D104: 1 | E104: =IFERROR(VLOOKUP(Issue!$D104,Table5[#All],3,0),"") -> Munger | F104: =IFERROR(VLOOKUP(Issue!$D104,Table5[#All],2,0),"") -> Main Godown | G104: 1058 | H104: =IFERROR(VLOOKUP(Issue!$G104,Table5[#All],3,0),"") -> Hasanpur | I104: =IFERROR(VLOOKUP(Issue!$G104,Table5[#All],2,0),"") -> BMC | J104: Tanker Seal | K104: =IFERROR(VLOOKUP(Issue!$J104,Table2[[Item Name]:[UoM]],2,0),"") -> Nos | L104: 100 | M104: =IFERROR(VLOOKUP(Issue!$J104,Table2[[#All],[Item Name]:[Open Rate]],8,0),"") -> 12.71 | N104: =IFERROR(+Issue!$L104*Issue!$M104,"") -> 1271 | O104: No | P104: NA
A105: 46125 | B105: Consumed | C105: 635 | D105: 1 | E105: =IFERROR(VLOOKUP(Issue!$D105,Table5[#All],3,0),"") -> Munger | F105: =IFERROR(VLOOKUP(Issue!$D105,Table5[#All],2,0),"") -> Main Godown | G105: 1058 | H105: =IFERROR(VLOOKUP(Issue!$G105,Table5[#All],3,0),"") -> Hasanpur | I105: =IFERROR(VLOOKUP(Issue!$G105,Table5[#All],2,0),"") -> BMC | J105: Beaker 100 Ml | K105: =IFERROR(VLOOKUP(Issue!$J105,Table2[[Item Name]:[UoM]],2,0),"") -> Nos | L105: 1 | M105: =IFERROR(VLOOKUP(Issue!$J105,Table2[[#All],[Item Name]:[Open Rate]],8,0),"") -> 33.18 | N105: =IFERROR(+Issue!$L105*Issue!$M105,"") -> 33.18 | O105: No | P105: NA
... A371: 46165 | B371: Consumed | C371: 666 | D371: 1 | E371: =IFERROR(VLOOKUP(Issue!$D371,Table5[#All],3,0),"") -> Munger | F371: =IFERROR(VLOOKUP(Issue!$D371,Table5[#All],2,0),"") -> Main Godown | G371: 1010 | H371: =IFERROR(VLOOKUP(Issue!$G371,Table5[#All],3,0),"") -> Parbatta | I371: =IFERROR(VLOOKUP(Issue!$G371,Table5[#All],2,0),"") -> BMC | J371: Phenolphthaleing Indicator | K371: =IFERROR(VLOOKUP(Issue!$J371,Table2[[Item Name]:[UoM]],2,0),"") -> Nos | L371: 1 | M371: =IFERROR(VLOOKUP(Issue!$J371,Table2[[#All],[Item Name]:[Open Rate]],8,0),"") -> 106.2 | N371: =IFERROR(+Issue!$L371*Issue!$M371,"") -> 106.2 | O371: Yes | P371: Pending
A372: 46167 | B372: Consumed | D372: 1014 | E372: =IFERROR(VLOOKUP(Issue!$D372,Table5[#All],3,0),"") -> Dumraon | F372: =IFERROR(VLOOKUP(Issue!$D372,Table5[#All],2,0),"") -> BMC | G372: 10140001 | H372: =IFERROR(VLOOKUP(Issue!$G372,Table5[#All],3,0),"") -> Dumri Purvi Tola | I372: =IFERROR(VLOOKUP(Issue!$G372,Table5[#All],2,0),"") -> MPG | J372: Thermal Paper Roll - Small | K372: =IFERROR(VLOOKUP(Issue!$J372,Table2[[Item Name]:[UoM]],2,0),"") -> Nos | L372: 24 | M372: =IFERROR(VLOOKUP(Issue!$J372,Table2[[#All],[Item Name]:[Open Rate]],8,0),"") -> 9.15 | N372: =IFERROR(+Issue!$L372*Issue!$M372,"") -> 219.6 | O372: Yes | P372: Pending
A373: 46167 | B373: Consumed | D373: 1014 | E373: =IFERROR(VLOOKUP(Issue!$D373,Table5[#All],3,0),"") -> Dumraon | F373: =IFERROR(VLOOKUP(Issue!$D373,Table5[#All],2,0),"") -> BMC | G373: 10140002 | H373: =IFERROR(VLOOKUP(Issue!$G373,Table5[#All],3,0),"") -> Simri | I373: =IFERROR(VLOOKUP(Issue!$G373,Table5[#All],2,0),"") -> MPG | J373: Thermal Paper Roll - Small | K373: =IFERROR(VLOOKUP(Issue!$J373,Table2[[Item Name]:[UoM]],2,0),"") -> Nos | L373: 12 | M373: =IFERROR(VLOOKUP(Issue!$J373,Table2[[#All],[Item Name]:[Open Rate]],8,0),"") -> 9.15 | N373: =IFERROR(+Issue!$L373*Issue!$M373,"") -> 109.8 | O373: Yes | P373: Pending
A374: 46167 | B374: Consumed | D374: 1014 | E374: =IFERROR(VLOOKUP(Issue!$D374,Table5[#All],3,0),"") -> Dumraon | F374: =IFERROR(VLOOKUP(Issue!$D374,Table5[#All],2,0),"") -> BMC | G374: 10140003 | H374: =IFERROR(VLOOKUP(Issue!$G374,Table5[#All],3,0),"") -> Sahiyar | I374: =IFERROR(VLOOKUP(Issue!$G374,Table5[#All],2,0),"") -> MPG | J374: Thermal Paper Roll - Small | K374: =IFERROR(VLOOKUP(Issue!$J374,Table2[[Item Name]:[UoM]],2,0),"") -> Nos | L374: 12 | M374: =IFERROR(VLOOKUP(Issue!$J374,Table2[[#All],[Item Name]:[Open Rate]],8,0),"") -> 9.15 | N374: =IFERROR(+Issue!$L374*Issue!$M374,"") -> 109.8 | O374: Yes | P374: Pending
A375: 46167 | B375: Consumed | D375: 1014 | E375: =IFERROR(VLOOKUP(Issue!$D375,Table5[#All],3,0),"") -> Dumraon | F375: =IFERROR(VLOOKUP(Issue!$D375,Table5[#All],2,0),"") -> BMC | G375: 10140007 | H375: =IFERROR(VLOOKUP(Issue!$G375,Table5[#All],3,0),"") -> ENGLISH DUBAULI | I375: =IFERROR(VLOOKUP(Issue!$G375,Table5[#All],2,0),"") -> MPG | J375: Thermal Paper Roll - Small | K375: =IFERROR(VLOOKUP(Issue!$J375,Table2[[Item Name]:[UoM]],2,0),"") -> Nos | L375: 12 | M375: =IFERROR(VLOOKUP(Issue!$J375,Table2[[#All],[Item Name]:[Open Rate]],8,0),"") -> 9.15 | N375: =IFERROR(+Issue!$L375*Issue!$M375,"") -> 109.8 | O375: Yes | P375: Pending
A376: 46167 | B376: Consumed | D376: 1014 | E376: =IFERROR(VLOOKUP(Issue!$D376,Table5[#All],3,0),"") -> Dumraon | F376: =IFERROR(VLOOKUP(Issue!$D376,Table5[#All],2,0),"") -> BMC | G376: 10140034 | H376: =IFERROR(VLOOKUP(Issue!$G376,Table5[#All],3,0),"") -> Chhotka Sihanpura | I376: =IFERROR(VLOOKUP(Issue!$G376,Table5[#All],2,0),"") -> MPG | J376: Thermal Paper Roll - Small | K376: =IFERROR(VLOOKUP(Issue!$J376,Table2[[Item Name]:[UoM]],2,0),"") -> Nos | L376: 12 | M376: =IFERROR(VLOOKUP(Issue!$J376,Table2[[#All],[Item Name]:[Open Rate]],8,0),"") -> 9.15 | N376: =IFERROR(+Issue!$L376*Issue!$M376,"") -> 109.8 | O376: Yes | P376: Pending
A377: 46167 | B377: Consumed | D377: 1014 | E377: =IFERROR(VLOOKUP(Issue!$D377,Table5[#All],3,0),"") -> Dumraon | F377: =IFERROR(VLOOKUP(Issue!$D377,Table5[#All],2,0),"") -> BMC | G377: 10140055 | H377: =IFERROR(VLOOKUP(Issue!$G377,Table5[#All],3,0),"") -> PURANA BHOJPUR | I377: =IFERROR(VLOOKUP(Issue!$G377,Table5[#All],2,0),"") -> MPG | J377: Thermal Paper Roll - Small | K377: =IFERROR(VLOOKUP(Issue!$J377,Table2[[Item Name]:[UoM]],2,0),"") -> Nos | L377: 18 | M377: =IFERROR(VLOOKUP(Issue!$J377,Table2[[#All],[Item Name]:[Open Rate]],8,0),"") -> 9.15 | N377: =IFERROR(+Issue!$L377*Issue!$M377,"") -> 164.7 | O377: Yes | P377: Pending
A378: 46167 | B378: Consumed | D378: 1014 | E378: =IFERROR(VLOOKUP(Issue!$D378,Table5[#All],3,0),"") -> Dumraon | F378: =IFERROR(VLOOKUP(Issue!$D378,Table5[#All],2,0),"") -> BMC | G378: 10140009 | H378: =IFERROR(VLOOKUP(Issue!$G378,Table5[#All],3,0),"") -> HITAN PARARI | I378: =IFERROR(VLOOKUP(Issue!$G378,Table5[#All],2,0),"") -> MPG | J378: Thermal Paper Roll - Small | K378: =IFERROR(VLOOKUP(Issue!$J378,Table2[[Item Name]:[UoM]],2,0),"") -> Nos | L378: 30 | M378: =IFERROR(VLOOKUP(Issue!$J378,Table2[[#All],[Item Name]:[Open Rate]],8,0),"") -> 9.15 | N378: =IFERROR(+Issue!$L378*Issue!$M378,"") -> 274.5 | O378: Yes | P378: Pending
A379: 46167 | B379: Consumed | D379: 1014 | E379: =IFERROR(VLOOKUP(Issue!$D379,Table5[#All],3,0),"") -> Dumraon | F379: =IFERROR(VLOOKUP(Issue!$D379,Table5[#All],2,0),"") -> BMC | G379: 10140020 | H379: =IFERROR(VLOOKUP(Issue!$G379,Table5[#All],3,0),"") -> RAJAPUR | I379: =IFERROR(VLOOKUP(Issue!$G379,Table5[#All],2,0),"") -> MPG | J379: Thermal Paper Roll - Small | K379: =IFERROR(VLOOKUP(Issue!$J379,Table2[[Item Name]:[UoM]],2,0),"") -> Nos | L379: 6 | M379: =IFERROR(VLOOKUP(Issue!$J379,Table2[[#All],[Item Name]:[Open Rate]],8,0),"") -> 9.15 | N379: =IFERROR(+Issue!$L379*Issue!$M379,"") -> 54.9 | O379: Yes | P379: Pending
A380: 46167 | B380: Consumed | D380: 1014 | E380: =IFERROR(VLOOKUP(Issue!$D380,Table5[#All],3,0),"") -> Dumraon | F380: =IFERROR(VLOOKUP(Issue!$D380,Table5[#All],2,0),"") -> BMC | G380: 10140041 | H380: =IFERROR(VLOOKUP(Issue!$G380,Table5[#All],3,0),"") -> Ramopatti | I380: =IFERROR(VLOOKUP(Issue!$G380,Table5[#All],2,0),"") -> MPG | J380: Thermal Paper Roll - Small | K380: =IFERROR(VLOOKUP(Issue!$J380,Table2[[Item Name]:[UoM]],2,0),"") -> Nos | L380: 12 | M380: =IFERROR(VLOOKUP(Issue!$J380,Table2[[#All],[Item Name]:[Open Rate]],8,0),"") -> 9.15 | N380: =IFERROR(+Issue!$L380*Issue!$M380,"") -> 109.8 | O380: Yes | P380: Pending
A381: 46167 | B381: Consumed | D381: 1014 | E381: =IFERROR(VLOOKUP(Issue!$D381,Table5[#All],3,0),"") -> Dumraon | F381: =IFERROR(VLOOKUP(Issue!$D381,Table5[#All],2,0),"") -> BMC | G381: 10140048 | H381: =IFERROR(VLOOKUP(Issue!$G381,Table5[#All],3,0),"") -> Sonvarsa | I381: =IFERROR(VLOOKUP(Issue!$G381,Table5[#All],2,0),"") -> MPG | J381: Thermal Paper Roll - Small | K381: =IFERROR(VLOOKUP(Issue!$J381,Table2[[Item Name]:[UoM]],2,0),"") -> Nos | L381: 6 | M381: =IFERROR(VLOOKUP(Issue!$J381,Table2[[#All],[Item Name]:[Open Rate]],8,0),"") -> 9.15 | N381: =IFERROR(+Issue!$L381*Issue!$M381,"") -> 54.9 | O381: Yes | P381: Pending
A382: 46167 | B382: Consumed | D382: 1014 | E382: =IFERROR(VLOOKUP(Issue!$D382,Table5[#All],3,0),"") -> Dumraon | F382: =IFERROR(VLOOKUP(Issue!$D382,Table5[#All],2,0),"") -> BMC | G382: 10140087 | H382: =IFERROR(VLOOKUP(Issue!$G382,Table5[#All],3,0),"") -> Gomukh Churamanpur | I382: =IFERROR(VLOOKUP(Issue!$G382,Table5[#All],2,0),"") -> MPG | J382: Thermal Paper Roll - Small | K382: =IFERROR(VLOOKUP(Issue!$J382,Table2[[Item Name]:[UoM]],2,0),"") -> Nos | L382: 48 | M382: =IFERROR(VLOOKUP(Issue!$J382,Table2[[#All],[Item Name]:[Open Rate]],8,0),"") -> 9.15 | N382: =IFERROR(+Issue!$L382*Issue!$M382,"") -> 439.2 | O382: Yes | P382: Pending
A383: 46167 | B383: Consumed | D383: 1014 | E383: =IFERROR(VLOOKUP(Issue!$D383,Table5[#All],3,0),"") -> Dumraon | F383: =IFERROR(VLOOKUP(Issue!$D383,Table5[#All],2,0),"") -> BMC | G383: 10140109 | H383: =IFERROR(VLOOKUP(Issue!$G383,Table5[#All],3,0),"") -> Gomukh Kajipura Chandan | I383: =IFERROR(VLOOKUP(Issue!$G383,Table5[#All],2,0),"") -> MPG | J383: Thermal Paper Roll - Small | K383: =IFERROR(VLOOKUP(Issue!$J383,Table2[[Item Name]:[UoM]],2,0),"") -> Nos | L383: 12 | M383: =IFERROR(VLOOKUP(Issue!$J383,Table2[[#All],[Item Name]:[Open Rate]],8,0),"") -> 9.15 | N383: =IFERROR(+Issue!$L383*Issue!$M383,"") -> 109.8 | O383: Yes | P383: Pending
... A652: 46171 | B652: Consumed | D652: 1 | E652: =IFERROR(VLOOKUP(Issue!$D652,Table5[#All],3,0),"") -> Munger | F652: =IFERROR(VLOOKUP(Issue!$D652,Table5[#All],2,0),"") -> Main Godown | G652: 1010 | H652: =IFERROR(VLOOKUP(Issue!$G652,Table5[#All],3,0),"") -> Parbatta | I652: =IFERROR(VLOOKUP(Issue!$G652,Table5[#All],2,0),"") -> BMC | J652: Thermometer 110 C | K652: =IFERROR(VLOOKUP(Issue!$J652,Table2[[Item Name]:[UoM]],2,0),"") -> Nos | L652: 2 | M652: =IFERROR(VLOOKUP(Issue!$J652,Table2[[#All],[Item Name]:[Open Rate]],8,0),"") -> 132.7 | N652: =IFERROR(+Issue!$L652*Issue!$M652,"") -> 265.4 | O652: Yes | P652: Pending
E653: =IFERROR(VLOOKUP(Issue!$D653,Table5[#All],3,0),"") | F653: =IFERROR(VLOOKUP(Issue!$D653,Table5[#All],2,0),"") | H653: =IFERROR(VLOOKUP(Issue!$G653,Table5[#All],3,0),"") | I653: =IFERROR(VLOOKUP(Issue!$G653,Table5[#All],2,0),"") | K653: =IFERROR(VLOOKUP(Issue!$J653,Table2[[Item Name]:[UoM]],2,0),"") | M653: =IFERROR(VLOOKUP(Issue!$J653,Table2[[#All],[Item Name]:[Open Rate]],8,0),"") | N653: =IFERROR(+Issue!$L653*Issue!$M653,"")
E654: =IFERROR(VLOOKUP(Issue!$D654,Table5[#All],3,0),"") | F654: =IFERROR(VLOOKUP(Issue!$D654,Table5[#All],2,0),"") | H654: =IFERROR(VLOOKUP(Issue!$G654,Table5[#All],3,0),"") | I654: =IFERROR(VLOOKUP(Issue!$G654,Table5[#All],2,0),"") | K654: =IFERROR(VLOOKUP(Issue!$J654,Table2[[Item Name]:[UoM]],2,0),"") | M654: =IFERROR(VLOOKUP(Issue!$J654,Table2[[#All],[Item Name]:[Open Rate]],8,0),"") | N654: =IFERROR(+Issue!$L654*Issue!$M654,"")
E655: =IFERROR(VLOOKUP(Issue!$D655,Table5[#All],3,0),"") | F655: =IFERROR(VLOOKUP(Issue!$D655,Table5[#All],2,0),"") | H655: =IFERROR(VLOOKUP(Issue!$G655,Table5[#All],3,0),"") | I655: =IFERROR(VLOOKUP(Issue!$G655,Table5[#All],2,0),"") | K655: =IFERROR(VLOOKUP(Issue!$J655,Table2[[Item Name]:[UoM]],2,0),"") | M655: =IFERROR(VLOOKUP(Issue!$J655,Table2[[#All],[Item Name]:[Open Rate]],8,0),"") | N655: =IFERROR(+Issue!$L655*Issue!$M655,"")
E656: =IFERROR(VLOOKUP(Issue!$D656,Table5[#All],3,0),"") | F656: =IFERROR(VLOOKUP(Issue!$D656,Table5[#All],2,0),"") | H656: =IFERROR(VLOOKUP(Issue!$G656,Table5[#All],3,0),"") | I656: =IFERROR(VLOOKUP(Issue!$G656,Table5[#All],2,0),"") | K656: =IFERROR(VLOOKUP(Issue!$J656,Table2[[Item Name]:[UoM]],2,0),"") | M656: =IFERROR(VLOOKUP(Issue!$J656,Table2[[#All],[Item Name]:[Open Rate]],8,0),"") | N656: =IFERROR(+Issue!$L656*Issue!$M656,"")
E657: =IFERROR(VLOOKUP(Issue!$D657,Table5[#All],3,0),"") | F657: =IFERROR(VLOOKUP(Issue!$D657,Table5[#All],2,0),"") | H657: =IFERROR(VLOOKUP(Issue!$G657,Table5[#All],3,0),"") | I657: =IFERROR(VLOOKUP(Issue!$G657,Table5[#All],2,0),"") | K657: =IFERROR(VLOOKUP(Issue!$J657,Table2[[Item Name]:[UoM]],2,0),"") | M657: =IFERROR(VLOOKUP(Issue!$J657,Table2[[#All],[Item Name]:[Open Rate]],8,0),"") | N657: =IFERROR(+Issue!$L657*Issue!$M657,"")
E658: =IFERROR(VLOOKUP(Issue!$D658,Table5[#All],3,0),"") | F658: =IFERROR(VLOOKUP(Issue!$D658,Table5[#All],2,0),"") | H658: =IFERROR(VLOOKUP(Issue!$G658,Table5[#All],3,0),"") | I658: =IFERROR(VLOOKUP(Issue!$G658,Table5[#All],2,0),"") | K658: =IFERROR(VLOOKUP(Issue!$J658,Table2[[Item Name]:[UoM]],2,0),"") | M658: =IFERROR(VLOOKUP(Issue!$J658,Table2[[#All],[Item Name]:[Open Rate]],8,0),"") | N658: =IFERROR(+Issue!$L658*Issue!$M658,"")
E659: =IFERROR(VLOOKUP(Issue!$D659,Table5[#All],3,0),"") | F659: =IFERROR(VLOOKUP(Issue!$D659,Table5[#All],2,0),"") | H659: =IFERROR(VLOOKUP(Issue!$G659,Table5[#All],3,0),"") | I659: =IFERROR(VLOOKUP(Issue!$G659,Table5[#All],2,0),"") | K659: =IFERROR(VLOOKUP(Issue!$J659,Table2[[Item Name]:[UoM]],2,0),"") | M659: =IFERROR(VLOOKUP(Issue!$J659,Table2[[#All],[Item Name]:[Open Rate]],8,0),"") | N659: =IFERROR(+Issue!$L659*Issue!$M659,"")
E660: =IFERROR(VLOOKUP(Issue!$D660,Table5[#All],3,0),"") | F660: =IFERROR(VLOOKUP(Issue!$D660,Table5[#All],2,0),"") | H660: =IFERROR(VLOOKUP(Issue!$G660,Table5[#All],3,0),"") | I660: =IFERROR(VLOOKUP(Issue!$G660,Table5[#All],2,0),"") | K660: =IFERROR(VLOOKUP(Issue!$J660,Table2[[Item Name]:[UoM]],2,0),"") | M660: =IFERROR(VLOOKUP(Issue!$J660,Table2[[#All],[Item Name]:[Open Rate]],8,0),"") | N660: =IFERROR(+Issue!$L660*Issue!$M660,"")
E661: =IFERROR(VLOOKUP(Issue!$D661,Table5[#All],3,0),"") | F661: =IFERROR(VLOOKUP(Issue!$D661,Table5[#All],2,0),"") | H661: =IFERROR(VLOOKUP(Issue!$G661,Table5[#All],3,0),"") | I661: =IFERROR(VLOOKUP(Issue!$G661,Table5[#All],2,0),"") | K661: =IFERROR(VLOOKUP(Issue!$J661,Table2[[Item Name]:[UoM]],2,0),"") | M661: =IFERROR(VLOOKUP(Issue!$J661,Table2[[#All],[Item Name]:[Open Rate]],8,0),"") | N661: =IFERROR(+Issue!$L661*Issue!$M661,"")
E662: =IFERROR(VLOOKUP(Issue!$D662,Table5[#All],3,0),"") | F662: =IFERROR(VLOOKUP(Issue!$D662,Table5[#All],2,0),"") | H662: =IFERROR(VLOOKUP(Issue!$G662,Table5[#All],3,0),"") | I662: =IFERROR(VLOOKUP(Issue!$G662,Table5[#All],2,0),"") | K662: =IFERROR(VLOOKUP(Issue!$J662,Table2[[Item Name]:[UoM]],2,0),"") | M662: =IFERROR(VLOOKUP(Issue!$J662,Table2[[#All],[Item Name]:[Open Rate]],8,0),"") | N662: =IFERROR(+Issue!$L662*Issue!$M662,"")
E663: =IFERROR(VLOOKUP(Issue!$D663,Table5[#All],3,0),"") | F663: =IFERROR(VLOOKUP(Issue!$D663,Table5[#All],2,0),"") | H663: =IFERROR(VLOOKUP(Issue!$G663,Table5[#All],3,0),"") | I663: =IFERROR(VLOOKUP(Issue!$G663,Table5[#All],2,0),"") | K663: =IFERROR(VLOOKUP(Issue!$J663,Table2[[Item Name]:[UoM]],2,0),"") | M663: =IFERROR(VLOOKUP(Issue!$J663,Table2[[#All],[Item Name]:[Open Rate]],8,0),"") | N663: =IFERROR(+Issue!$L663*Issue!$M663,"")
E664: =IFERROR(VLOOKUP(Issue!$D664,Table5[#All],3,0),"") | F664: =IFERROR(VLOOKUP(Issue!$D664,Table5[#All],2,0),"") | H664: =IFERROR(VLOOKUP(Issue!$G664,Table5[#All],3,0),"") | I664: =IFERROR(VLOOKUP(Issue!$G664,Table5[#All],2,0),"") | K664: =IFERROR(VLOOKUP(Issue!$J664,Table2[[Item Name]:[UoM]],2,0),"") | M664: =IFERROR(VLOOKUP(Issue!$J664,Table2[[#All],[Item Name]:[Open Rate]],8,0),"") | N664: =IFERROR(+Issue!$L664*Issue!$M664,"")
... E4036: =IFERROR(VLOOKUP(Issue!$D4036,Table5[#All],3,0),"") | F4036: =IFERROR(VLOOKUP(Issue!$D4036,Table5[#All],2,0),"") | H4036: =IFERROR(VLOOKUP(Issue!$G4036,Table5[#All],3,0),"") | I4036: =IFERROR(VLOOKUP(Issue!$G4036,Table5[#All],2,0),"") | K4036: =IFERROR(VLOOKUP(Issue!$J4036,Table2[[Item Name]:[UoM]],2,0),"") | M4036: =IFERROR(VLOOKUP(Issue!$J4036,Table2[[#All],[Item Name]:[Open Rate]],8,0),"") | N4036: =IFERROR(+Issue!$L4036*Issue!$M4036,"")

Sheet Pending Consumption
A1: S No | B1: Name of BMC | C1: Item Name | D1: Issue | E1: Consumed | F1: Balance
A2: 1 | B2: Sahibpur Kamal | C2: 1% Iodine Solution (100ml) | D2: =SUMIFS(Issue!$L$1:$L$4036,Issue!$H$1:$H$4036,'Pending Consumption'!$B2,Issue!$J$1:$J$4036,'Pending Consumption'!$C2,Issue!$B$1:$B$4036,"Transfer") -> 0 | E2: =SUMIFS(Issue!$L$1:$L$4036,Issue!$E$1:$E$4036,'Pending Consumption'!B2,Issue!$J$1:$J$4036,'Pending Consumption'!$C2,Issue!$B$1:$B$4036,"Consumed") -> 0 | F2: =+D2-E2 -> 0
A3: 2 | B3: Sahibpur Kamal | C3: Amber Colour Bottle (250 ML) | D3: =SUMIFS(Issue!$L$1:$L$4036,Issue!$H$1:$H$4036,'Pending Consumption'!$B3,Issue!$J$1:$J$4036,'Pending Consumption'!$C3,Issue!$B$1:$B$4036,"Transfer") -> 0 | E3: =SUMIFS(Issue!$L$1:$L$4036,Issue!$E$1:$E$4036,'Pending Consumption'!B3,Issue!$J$1:$J$4036,'Pending Consumption'!$C3,Issue!$B$1:$B$4036,"Consumed") -> 0 | F3: =+D3-E3 -> 0
A4: 3 | B4: Sahibpur Kamal | C4: Amyl 500ml | D4: =SUMIFS(Issue!$L$1:$L$4036,Issue!$H$1:$H$4036,'Pending Consumption'!$B4,Issue!$J$1:$J$4036,'Pending Consumption'!$C4,Issue!$B$1:$B$4036,"Transfer") -> 0 | E4: =SUMIFS(Issue!$L$1:$L$4036,Issue!$E$1:$E$4036,'Pending Consumption'!B4,Issue!$J$1:$J$4036,'Pending Consumption'!$C4,Issue!$B$1:$B$4036,"Consumed") -> 0 | F4: =+D4-E4 -> 0
A5: 4 | B5: Sahibpur Kamal | C5: Analyzer Calibration Cheking Log Book | D5: =SUMIFS(Issue!$L$1:$L$4036,Issue!$H$1:$H$4036,'Pending Consumption'!$B5,Issue!$J$1:$J$4036,'Pending Consumption'!$C5,Issue!$B$1:$B$4036,"Transfer") -> 0 | E5: =SUMIFS(Issue!$L$1:$L$4036,Issue!$E$1:$E$4036,'Pending Consumption'!B5,Issue!$J$1:$J$4036,'Pending Consumption'!$C5,Issue!$B$1:$B$4036,"Consumed") -> 0 | F5: =+D5-E5 -> 0
A6: 5 | B6: Sahibpur Kamal | C6: Beaker 100 Ml | D6: =SUMIFS(Issue!$L$1:$L$4036,Issue!$H$1:$H$4036,'Pending Consumption'!$B6,Issue!$J$1:$J$4036,'Pending Consumption'!$C6,Issue!$B$1:$B$4036,"Transfer") -> 0 | E6: =SUMIFS(Issue!$L$1:$L$4036,Issue!$E$1:$E$4036,'Pending Consumption'!B6,Issue!$J$1:$J$4036,'Pending Consumption'!$C6,Issue!$B$1:$B$4036,"Consumed") -> 0 | F6: =+D6-E6 -> 0
A7: 6 | B7: Sahibpur Kamal | C7: Beaker 250 ML Borosilicate | D7: =SUMIFS(Issue!$L$1:$L$4036,Issue!$H$1:$H$4036,'Pending Consumption'!$B7,Issue!$J$1:$J$4036,'Pending Consumption'!$C7,Issue!$B$1:$B$4036,"Transfer") -> 0 | E7: =SUMIFS(Issue!$L$1:$L$4036,Issue!$E$1:$E$4036,'Pending Consumption'!B7,Issue!$J$1:$J$4036,'Pending Consumption'!$C7,Issue!$B$1:$B$4036,"Consumed") -> 0 | F7: =+D7-E7 -> 0
A8: 7 | B8: Sahibpur Kamal | C8: Beaker 500 Ml | D8: =SUMIFS(Issue!$L$1:$L$4036,Issue!$H$1:$H$4036,'Pending Consumption'!$B8,Issue!$J$1:$J$4036,'Pending Consumption'!$C8,Issue!$B$1:$B$4036,"Transfer") -> 0 | E8: =SUMIFS(Issue!$L$1:$L$4036,Issue!$E$1:$E$4036,'Pending Consumption'!B8,Issue!$J$1:$J$4036,'Pending Consumption'!$C8,Issue!$B$1:$B$4036,"Consumed") -> 0 | F8: =+D8-E8 -> 0
A9: 8 | B9: Sahibpur Kamal | C9: Beaker 50 ML | D9: =SUMIFS(Issue!$L$1:$L$4036,Issue!$H$1:$H$4036,'Pending Consumption'!$B9,Issue!$J$1:$J$4036,'Pending Consumption'!$C9,Issue!$B$1:$B$4036,"Transfer") -> 0 | E9: =SUMIFS(Issue!$L$1:$L$4036,Issue!$E$1:$E$4036,'Pending Consumption'!B9,Issue!$J$1:$J$4036,'Pending Consumption'!$C9,Issue!$B$1:$B$4036,"Consumed") -> 0 | F9: =+D9-E9 -> 0
A10: 9 | B10: Sahibpur Kamal | C10: BMC Cleaning Brush 2" | D10: =SUMIFS(Issue!$L$1:$L$4036,Issue!$H$1:$H$4036,'Pending Consumption'!$B10,Issue!$J$1:$J$4036,'Pending Consumption'!$C10,Issue!$B$1:$B$4036,"Transfer") -> 0 | E10: =SUMIFS(Issue!$L$1:$L$4036,Issue!$E$1:$E$4036,'Pending Consumption'!B10,Issue!$J$1:$J$4036,'Pending Consumption'!$C10,Issue!$B$1:$B$4036,"Consumed") -> 0 | F10: =+D10-E10 -> 0
A11: 10 | B11: Sahibpur Kamal | C11: BMC Day Book | D11: =SUMIFS(Issue!$L$1:$L$4036,Issue!$H$1:$H$4036,'Pending Consumption'!$B11,Issue!$J$1:$J$4036,'Pending Consumption'!$C11,Issue!$B$1:$B$4036,"Transfer") -> 0 | E11: =SUMIFS(Issue!$L$1:$L$4036,Issue!$E$1:$E$4036,'Pending Consumption'!B11,Issue!$J$1:$J$4036,'Pending Consumption'!$C11,Issue!$B$1:$B$4036,"Consumed") -> 0 | F11: =+D11-E11 -> 0
A12: 11 | B12: Sahibpur Kamal | C12: Burete Stand | D12: =SUMIFS(Issue!$L$1:$L$4036,Issue!$H$1:$H$4036,'Pending Consumption'!$B12,Issue!$J$1:$J$4036,'Pending Consumption'!$C12,Issue!$B$1:$B$4036,"Transfer") -> 0 | E12: =SUMIFS(Issue!$L$1:$L$4036,Issue!$E$1:$E$4036,'Pending Consumption'!B12,Issue!$J$1:$J$4036,'Pending Consumption'!$C12,Issue!$B$1:$B$4036,"Consumed") -> 0 | F12: =+D12-E12 -> 0
A13: 12 | B13: Sahibpur Kamal | C13: Burret 50 ML Borosilicate | D13: =SUMIFS(Issue!$L$1:$L$4036,Issue!$H$1:$H$4036,'Pending Consumption'!$B13,Issue!$J$1:$J$4036,'Pending Consumption'!$C13,Issue!$B$1:$B$4036,"Transfer") -> 0 | E13: =SUMIFS(Issue!$L$1:$L$4036,Issue!$E$1:$E$4036,'Pending Consumption'!B13,Issue!$J$1:$J$4036,'Pending Consumption'!$C13,Issue!$B$1:$B$4036,"Consumed") -> 0 | F13: =+D13-E13 -> 0
... A97: 96 | B97: Sahibpur Kamal | C97: Tilt Measure 1 Ml with Bottle | D97: =SUMIFS(Issue!$L$1:$L$4036,Issue!$H$1:$H$4036,'Pending Consumption'!$B97,Issue!$J$1:$J$4036,'Pending Consumption'!$C97,Issue!$B$1:$B$4036,"Transfer") -> 0 | E97: =SUMIFS(Issue!$L$1:$L$4036,Issue!$E$1:$E$4036,'Pending Consumption'!B97,Issue!$J$1:$J$4036,'Pending Consumption'!$C97,Issue!$B$1:$B$4036,"Consumed") -> 0 | F97: =+D97-E97 -> 0
B98: Kalyanpur | C98: 1% Iodine Solution (100ml) | D98: =SUMIFS(Issue!$L$1:$L$4036,Issue!$H$1:$H$4036,'Pending Consumption'!$B98,Issue!$J$1:$J$4036,'Pending Consumption'!$C98,Issue!$B$1:$B$4036,"Transfer") -> 0 | E98: =SUMIFS(Issue!$L$1:$L$4036,Issue!$E$1:$E$4036,'Pending Consumption'!B98,Issue!$J$1:$J$4036,'Pending Consumption'!$C98,Issue!$B$1:$B$4036,"Consumed") -> 0 | F98: =+D98-E98 -> 0
B99: Kalyanpur | C99: Amber Colour Bottle (250 ML) | D99: =SUMIFS(Issue!$L$1:$L$4036,Issue!$H$1:$H$4036,'Pending Consumption'!$B99,Issue!$J$1:$J$4036,'Pending Consumption'!$C99,Issue!$B$1:$B$4036,"Transfer") -> 0 | E99: =SUMIFS(Issue!$L$1:$L$4036,Issue!$E$1:$E$4036,'Pending Consumption'!B99,Issue!$J$1:$J$4036,'Pending Consumption'!$C99,Issue!$B$1:$B$4036,"Consumed") -> 0 | F99: =+D99-E99 -> 0
B100: Kalyanpur | C100: Amyl 500ml | D100: =SUMIFS(Issue!$L$1:$L$4036,Issue!$H$1:$H$4036,'Pending Consumption'!$B100,Issue!$J$1:$J$4036,'Pending Consumption'!$C100,Issue!$B$1:$B$4036,"Transfer") -> 0 | E100: =SUMIFS(Issue!$L$1:$L$4036,Issue!$E$1:$E$4036,'Pending Consumption'!B100,Issue!$J$1:$J$4036,'Pending Consumption'!$C100,Issue!$B$1:$B$4036,"Consumed") -> 0 | F100: =+D100-E100 -> 0
B101: Kalyanpur | C101: Analyzer Calibration Cheking Log Book | D101: =SUMIFS(Issue!$L$1:$L$4036,Issue!$H$1:$H$4036,'Pending Consumption'!$B101,Issue!$J$1:$J$4036,'Pending Consumption'!$C101,Issue!$B$1:$B$4036,"Transfer") -> 0 | E101: =SUMIFS(Issue!$L$1:$L$4036,Issue!$E$1:$E$4036,'Pending Consumption'!B101,Issue!$J$1:$J$4036,'Pending Consumption'!$C101,Issue!$B$1:$B$4036,"Consumed") -> 0 | F101: =+D101-E101 -> 0
B102: Kalyanpur | C102: Beaker 100 Ml | D102: =SUMIFS(Issue!$L$1:$L$4036,Issue!$H$1:$H$4036,'Pending Consumption'!$B102,Issue!$J$1:$J$4036,'Pending Consumption'!$C102,Issue!$B$1:$B$4036,"Transfer") -> 0 | E102: =SUMIFS(Issue!$L$1:$L$4036,Issue!$E$1:$E$4036,'Pending Consumption'!B102,Issue!$J$1:$J$4036,'Pending Consumption'!$C102,Issue!$B$1:$B$4036,"Consumed") -> 0 | F102: =+D102-E102 -> 0
B103: Kalyanpur | C103: Beaker 250 ML Borosilicate | D103: =SUMIFS(Issue!$L$1:$L$4036,Issue!$H$1:$H$4036,'Pending Consumption'!$B103,Issue!$J$1:$J$4036,'Pending Consumption'!$C103,Issue!$B$1:$B$4036,"Transfer") -> 0 | E103: =SUMIFS(Issue!$L$1:$L$4036,Issue!$E$1:$E$4036,'Pending Consumption'!B103,Issue!$J$1:$J$4036,'Pending Consumption'!$C103,Issue!$B$1:$B$4036,"Consumed") -> 0 | F103: =+D103-E103 -> 0
B104: Kalyanpur | C104: Beaker 500 Ml | D104: =SUMIFS(Issue!$L$1:$L$4036,Issue!$H$1:$H$4036,'Pending Consumption'!$B104,Issue!$J$1:$J$4036,'Pending Consumption'!$C104,Issue!$B$1:$B$4036,"Transfer") -> 0 | E104: =SUMIFS(Issue!$L$1:$L$4036,Issue!$E$1:$E$4036,'Pending Consumption'!B104,Issue!$J$1:$J$4036,'Pending Consumption'!$C104,Issue!$B$1:$B$4036,"Consumed") -> 0 | F104: =+D104-E104 -> 0
B105: Kalyanpur | C105: Beaker 50 ML | D105: =SUMIFS(Issue!$L$1:$L$4036,Issue!$H$1:$H$4036,'Pending Consumption'!$B105,Issue!$J$1:$J$4036,'Pending Consumption'!$C105,Issue!$B$1:$B$4036,"Transfer") -> 0 | E105: =SUMIFS(Issue!$L$1:$L$4036,Issue!$E$1:$E$4036,'Pending Consumption'!B105,Issue!$J$1:$J$4036,'Pending Consumption'!$C105,Issue!$B$1:$B$4036,"Consumed") -> 0 | F105: =+D105-E105 -> 0
B106: Kalyanpur | C106: BMC Cleaning Brush 2" | D106: =SUMIFS(Issue!$L$1:$L$4036,Issue!$H$1:$H$4036,'Pending Consumption'!$B106,Issue!$J$1:$J$4036,'Pending Consumption'!$C106,Issue!$B$1:$B$4036,"Transfer") -> 0 | E106: =SUMIFS(Issue!$L$1:$L$4036,Issue!$E$1:$E$4036,'Pending Consumption'!B106,Issue!$J$1:$J$4036,'Pending Consumption'!$C106,Issue!$B$1:$B$4036,"Consumed") -> 0 | F106: =+D106-E106 -> 0
B107: Kalyanpur | C107: BMC Day Book | D107: =SUMIFS(Issue!$L$1:$L$4036,Issue!$H$1:$H$4036,'Pending Consumption'!$B107,Issue!$J$1:$J$4036,'Pending Consumption'!$C107,Issue!$B$1:$B$4036,"Transfer") -> 0 | E107: =SUMIFS(Issue!$L$1:$L$4036,Issue!$E$1:$E$4036,'Pending Consumption'!B107,Issue!$J$1:$J$4036,'Pending Consumption'!$C107,Issue!$B$1:$B$4036,"Consumed") -> 0 | F107: =+D107-E107 -> 0
B108: Kalyanpur | C108: Burete Stand | D108: =SUMIFS(Issue!$L$1:$L$4036,Issue!$H$1:$H$4036,'Pending Consumption'!$B108,Issue!$J$1:$J$4036,'Pending Consumption'!$C108,Issue!$B$1:$B$4036,"Transfer") -> 0 | E108: =SUMIFS(Issue!$L$1:$L$4036,Issue!$E$1:$E$4036,'Pending Consumption'!B108,Issue!$J$1:$J$4036,'Pending Consumption'!$C108,Issue!$B$1:$B$4036,"Consumed") -> 0 | F108: =+D108-E108 -> 0
B109: Kalyanpur | C109: Burret 50 ML Borosilicate | D109: =SUMIFS(Issue!$L$1:$L$4036,Issue!$H$1:$H$4036,'Pending Consumption'!$B109,Issue!$J$1:$J$4036,'Pending Consumption'!$C109,Issue!$B$1:$B$4036,"Transfer") -> 0 | E109: =SUMIFS(Issue!$L$1:$L$4036,Issue!$E$1:$E$4036,'Pending Consumption'!B109,Issue!$J$1:$J$4036,'Pending Consumption'!$C109,Issue!$B$1:$B$4036,"Consumed") -> 0 | F109: =+D109-E109 -> 0
... B1249: Araria | C1249: Tilt Measure 1 Ml with Bottle | D1249: =SUMIFS(Issue!$L$1:$L$4036,Issue!$H$1:$H$4036,'Pending Consumption'!$B1249,Issue!$J$1:$J$4036,'Pending Consumption'!$C1249,Issue!$B$1:$B$4036,"Transfer") -> 0 | E1249: =SUMIFS(Issue!$L$1:$L$4036,Issue!$E$1:$E$4036,'Pending Consumption'!B1249,Issue!$J$1:$J$4036,'Pending Consumption'!$C1249,Issue!$B$1:$B$4036,"Consumed") -> 0 | F1249: =+D1249-E1249 -> 0

Sheet Purchase
A1: Vendor ID | B1: Vendor Name | C1: Invoice Date | D1: Invoice No | E1: PO Date | F1: PO No | G1: Date | H1: GRN No | I1: Receipt Location Code | J1: Location | K1: Item Name | L1: UoM | M1: Qty Received | N1: Rate | O1: Amt | P1: GST | Q1: Total Am t | R1: Frieght | S1: Total amt | T1: Cost/Per
A2: 6 | B2: =IFERROR(VLOOKUP(Table3[[#This Row],[Vendor ID]],Table6[[Vendor ID]:[Vendor Name]],2,0),"") -> Satol Chemicals LTD | C2: 46142 | D2: SCL/00635/26-27 | E2: 46139 | F2: BR/PO/15/26-27 | G2: 46156 | H2: 1 | I2: 1 | J2: =IFERROR(VLOOKUP(Table3[[#This Row],[Receipt Location Code]],Table5[#All],3,0),"") -> Munger | K2: TEEPOL | L2: =IFERROR(VLOOKUP(Table3[[#This Row],[Item Name]],Table2[[#All],[Item Name]:[Open Rate]],2,0),"") -> Nos | M2: 1000 | N2: 44 | O2: =+Table3[[#This Row],[Rate]]*Table3[[#This Row],[Qty Received]] -> 44000 | P2: =+Table3[[#This Row],[Amt]]*0.18 -> 7920 | Q2: =+Table3[[#This Row],[Amt]]+Table3[[#This Row],[GST]] -> 51920 | S2: =+Table3[[#This Row],[Total Am t]]+Table3[[#This Row],[Frieght]] -> 51920 | T2: =IFERROR(+Table3[[#This Row],[Total amt]]/Table3[[#This Row],[Qty Received]],0) -> 51.92
B3: =IFERROR(VLOOKUP(Table3[[#This Row],[Vendor ID]],Table6[[Vendor ID]:[Vendor Name]],2,0),"") | J3: =IFERROR(VLOOKUP(Table3[[#This Row],[Receipt Location Code]],Table5[#All],3,0),"") | L3: =IFERROR(VLOOKUP(Table3[[#This Row],[Item Name]],Table2[[#All],[Item Name]:[Open Rate]],2,0),"") | O3: =+Table3[[#This Row],[Rate]]*Table3[[#This Row],[Qty Received]] -> 0 | P3: =+Table3[[#This Row],[Amt]]*0.18 -> 0 | Q3: =+Table3[[#This Row],[Amt]]+Table3[[#This Row],[GST]] -> 0 | S3: =+Table3[[#This Row],[Total Am t]]+Table3[[#This Row],[Frieght]] -> 0 | T3: =IFERROR(+Table3[[#This Row],[Total amt]]/Table3[[#This Row],[Qty Received]],0) -> 0
B4: =IFERROR(VLOOKUP(Table3[[#This Row],[Vendor ID]],Table6[[Vendor ID]:[Vendor Name]],2,0),"") | J4: =IFERROR(VLOOKUP(Table3[[#This Row],[Receipt Location Code]],Table5[#All],3,0),"") | L4: =IFERROR(VLOOKUP(Table3[[#This Row],[Item Name]],Table2[[#All],[Item Name]:[Open Rate]],2,0),"") | O4: =+Table3[[#This Row],[Rate]]*Table3[[#This Row],[Qty Received]] -> 0 | P4: =+Table3[[#This Row],[Amt]]*0.12 -> 0 | Q4: =+Table3[[#This Row],[Amt]]+Table3[[#This Row],[GST]] -> 0 | S4: =+Table3[[#This Row],[Total Am t]]+Table3[[#This Row],[Frieght]] -> 0 | T4: =IFERROR(+Table3[[#This Row],[Total amt]]/Table3[[#This Row],[Qty Received]],0) -> 0
B5: =IFERROR(VLOOKUP(Table3[[#This Row],[Vendor ID]],Table6[[Vendor ID]:[Vendor Name]],2,0),"") | J5: =IFERROR(VLOOKUP(Table3[[#This Row],[Receipt Location Code]],Table5[#All],3,0),"") | L5: =IFERROR(VLOOKUP(Table3[[#This Row],[Item Name]],Table2[[#All],[Item Name]:[Open Rate]],2,0),"") | O5: =+Table3[[#This Row],[Rate]]*Table3[[#This Row],[Qty Received]] -> 0 | P5: =+Table3[[#This Row],[Amt]]*0.12 -> 0 | Q5: =+Table3[[#This Row],[Amt]]+Table3[[#This Row],[GST]] -> 0 | S5: =+Table3[[#This Row],[Total Am t]]+Table3[[#This Row],[Frieght]] -> 0 | T5: =IFERROR(+Table3[[#This Row],[Total amt]]/Table3[[#This Row],[Qty Received]],0) -> 0
B6: =IFERROR(VLOOKUP(Table3[[#This Row],[Vendor ID]],Table6[[Vendor ID]:[Vendor Name]],2,0),"") | J6: =IFERROR(VLOOKUP(Table3[[#This Row],[Receipt Location Code]],Table5[#All],3,0),"") | L6: =IFERROR(VLOOKUP(Table3[[#This Row],[Item Name]],Table2[[#All],[Item Name]:[Open Rate]],2,0),"") | O6: =+Table3[[#This Row],[Rate]]*Table3[[#This Row],[Qty Received]] -> 0 | P6: =+Table3[[#This Row],[Amt]]*0.18 -> 0 | Q6: =+Table3[[#This Row],[Amt]]+Table3[[#This Row],[GST]] -> 0 | S6: =+Table3[[#This Row],[Total Am t]]+Table3[[#This Row],[Frieght]] -> 0 | T6: =IFERROR(+Table3[[#This Row],[Total amt]]/Table3[[#This Row],[Qty Received]],0) -> 0
B7: =IFERROR(VLOOKUP(Table3[[#This Row],[Vendor ID]],Table6[[Vendor ID]:[Vendor Name]],2,0),"") | J7: =IFERROR(VLOOKUP(Table3[[#This Row],[Receipt Location Code]],Table5[#All],3,0),"") | L7: =IFERROR(VLOOKUP(Table3[[#This Row],[Item Name]],Table2[[#All],[Item Name]:[Open Rate]],2,0),"") | O7: =+Table3[[#This Row],[Rate]]*Table3[[#This Row],[Qty Received]] -> 0 | P7: =+Table3[[#This Row],[Amt]]*0.18 -> 0 | Q7: =+Table3[[#This Row],[Amt]]+Table3[[#This Row],[GST]] -> 0 | S7: =+Table3[[#This Row],[Total Am t]]+Table3[[#This Row],[Frieght]] -> 0 | T7: =IFERROR(+Table3[[#This Row],[Total amt]]/Table3[[#This Row],[Qty Received]],0) -> 0
B8: =IFERROR(VLOOKUP(Table3[[#This Row],[Vendor ID]],Table6[[Vendor ID]:[Vendor Name]],2,0),"") | J8: =IFERROR(VLOOKUP(Table3[[#This Row],[Receipt Location Code]],Table5[#All],3,0),"") | L8: =IFERROR(VLOOKUP(Table3[[#This Row],[Item Name]],Table2[[#All],[Item Name]:[Open Rate]],2,0),"") | O8: =+Table3[[#This Row],[Rate]]*Table3[[#This Row],[Qty Received]] -> 0 | P8: =+Table3[[#This Row],[Amt]]*0.18 -> 0 | Q8: =+Table3[[#This Row],[Amt]]+Table3[[#This Row],[GST]] -> 0 | S8: =+Table3[[#This Row],[Total Am t]]+Table3[[#This Row],[Frieght]] -> 0 | T8: =IFERROR(+Table3[[#This Row],[Total amt]]/Table3[[#This Row],[Qty Received]],0) -> 0
B9: =IFERROR(VLOOKUP(Table3[[#This Row],[Vendor ID]],Table6[[Vendor ID]:[Vendor Name]],2,0),"") | J9: =IFERROR(VLOOKUP(Table3[[#This Row],[Receipt Location Code]],Table5[#All],3,0),"") | L9: =IFERROR(VLOOKUP(Table3[[#This Row],[Item Name]],Table2[[#All],[Item Name]:[Open Rate]],2,0),"") | O9: =+Table3[[#This Row],[Rate]]*Table3[[#This Row],[Qty Received]] -> 0 | P9: =+Table3[[#This Row],[Amt]]*0.18 -> 0 | Q9: =+Table3[[#This Row],[Amt]]+Table3[[#This Row],[GST]] -> 0 | S9: =+Table3[[#This Row],[Total Am t]]+Table3[[#This Row],[Frieght]] -> 0 | T9: =IFERROR(+Table3[[#This Row],[Total amt]]/Table3[[#This Row],[Qty Received]],0) -> 0
B10: =IFERROR(VLOOKUP(Table3[[#This Row],[Vendor ID]],Table6[[Vendor ID]:[Vendor Name]],2,0),"") | J10: =IFERROR(VLOOKUP(Table3[[#This Row],[Receipt Location Code]],Table5[#All],3,0),"") | L10: =IFERROR(VLOOKUP(Table3[[#This Row],[Item Name]],Table2[[#All],[Item Name]:[Open Rate]],2,0),"") | O10: =+Table3[[#This Row],[Rate]]*Table3[[#This Row],[Qty Received]] -> 0 | P10: =+Table3[[#This Row],[Amt]]*0.18 -> 0 | Q10: =+Table3[[#This Row],[Amt]]+Table3[[#This Row],[GST]] -> 0 | S10: =+Table3[[#This Row],[Total Am t]]+Table3[[#This Row],[Frieght]] -> 0 | T10: =IFERROR(+Table3[[#This Row],[Total amt]]/Table3[[#This Row],[Qty Received]],0) -> 0
B11: =IFERROR(VLOOKUP(Table3[[#This Row],[Vendor ID]],Table6[[Vendor ID]:[Vendor Name]],2,0),"") | J11: =IFERROR(VLOOKUP(Table3[[#This Row],[Receipt Location Code]],Table5[#All],3,0),"") | L11: =IFERROR(VLOOKUP(Table3[[#This Row],[Item Name]],Table2[[#All],[Item Name]:[Open Rate]],2,0),"") | O11: =+Table3[[#This Row],[Rate]]*Table3[[#This Row],[Qty Received]] -> 0 | P11: =+Table3[[#This Row],[Amt]]*0.18 -> 0 | Q11: =+Table3[[#This Row],[Amt]]+Table3[[#This Row],[GST]] -> 0 | S11: =+Table3[[#This Row],[Total Am t]]+Table3[[#This Row],[Frieght]] -> 0 | T11: =IFERROR(+Table3[[#This Row],[Total amt]]/Table3[[#This Row],[Qty Received]],0) -> 0
B12: =IFERROR(VLOOKUP(Table3[[#This Row],[Vendor ID]],Table6[[Vendor ID]:[Vendor Name]],2,0),"") | J12: =IFERROR(VLOOKUP(Table3[[#This Row],[Receipt Location Code]],Table5[#All],3,0),"") | L12: =IFERROR(VLOOKUP(Table3[[#This Row],[Item Name]],Table2[[#All],[Item Name]:[Open Rate]],2,0),"") | O12: =+Table3[[#This Row],[Rate]]*Table3[[#This Row],[Qty Received]] -> 0 | P12: =+Table3[[#This Row],[Amt]]*0.18 -> 0 | Q12: =+Table3[[#This Row],[Amt]]+Table3[[#This Row],[GST]] -> 0 | S12: =+Table3[[#This Row],[Total Am t]]+Table3[[#This Row],[Frieght]] -> 0 | T12: =IFERROR(+Table3[[#This Row],[Total amt]]/Table3[[#This Row],[Qty Received]],0) -> 0
B13: =IFERROR(VLOOKUP(Table3[[#This Row],[Vendor ID]],Table6[[Vendor ID]:[Vendor Name]],2,0),"") | J13: =IFERROR(VLOOKUP(Table3[[#This Row],[Receipt Location Code]],Table5[#All],3,0),"") | L13: =IFERROR(VLOOKUP(Table3[[#This Row],[Item Name]],Table2[[#All],[Item Name]:[Open Rate]],2,0),"") | O13: =+Table3[[#This Row],[Rate]]*Table3[[#This Row],[Qty Received]] -> 0 | P13: =+Table3[[#This Row],[Amt]]*0.18 -> 0 | Q13: =+Table3[[#This Row],[Amt]]+Table3[[#This Row],[GST]] -> 0 | S13: =+Table3[[#This Row],[Total Am t]]+Table3[[#This Row],[Frieght]] -> 0 | T13: =IFERROR(+Table3[[#This Row],[Total amt]]/Table3[[#This Row],[Qty Received]],0) -> 0
B14: =IFERROR(VLOOKUP(Table3[[#This Row],[Vendor ID]],Table6[[Vendor ID]:[Vendor Name]],2,0),"") | J14: =IFERROR(VLOOKUP(Table3[[#This Row],[Receipt Location Code]],Table5[#All],3,0),"") | L14: =IFERROR(VLOOKUP(Table3[[#This Row],[Item Name]],Table2[[#All],[Item Name]:[Open Rate]],2,0),"") | O14: =+Table3[[#This Row],[Rate]]*Table3[[#This Row],[Qty Received]] -> 0 | P14: =+Table3[[#This Row],[Amt]]*0.18 -> 0 | Q14: =+Table3[[#This Row],[Amt]]+Table3[[#This Row],[GST]] -> 0 | S14: =+Table3[[#This Row],[Total Am t]]+Table3[[#This Row],[Frieght]] -> 0 | T14: =IFERROR(+Table3[[#This Row],[Total amt]]/Table3[[#This Row],[Qty Received]],0) -> 0
B15: =IFERROR(VLOOKUP(Table3[[#This Row],[Vendor ID]],Table6[[Vendor ID]:[Vendor Name]],2,0),"") | J15: =IFERROR(VLOOKUP(Table3[[#This Row],[Receipt Location Code]],Table5[#All],3,0),"") | L15: =IFERROR(VLOOKUP(Table3[[#This Row],[Item Name]],Table2[[#All],[Item Name]:[Open Rate]],2,0),"") | O15: =+Table3[[#This Row],[Rate]]*Table3[[#This Row],[Qty Received]] -> 0 | P15: =+Table3[[#This Row],[Amt]]*0.18 -> 0 | Q15: =+Table3[[#This Row],[Amt]]+Table3[[#This Row],[GST]] -> 0 | S15: =+Table3[[#This Row],[Total Am t]]+Table3[[#This Row],[Frieght]] -> 0 | T15: =IFERROR(+Table3[[#This Row],[Total amt]]/Table3[[#This Row],[Qty Received]],0) -> 0
B16: =IFERROR(VLOOKUP(Table3[[#This Row],[Vendor ID]],Table6[[Vendor ID]:[Vendor Name]],2,0),"") | J16: =IFERROR(VLOOKUP(Table3[[#This Row],[Receipt Location Code]],Table5[#All],3,0),"") | L16: =IFERROR(VLOOKUP(Table3[[#This Row],[Item Name]],Table2[[#All],[Item Name]:[Open Rate]],2,0),"") | O16: =+Table3[[#This Row],[Rate]]*Table3[[#This Row],[Qty Received]] -> 0 | P16: =+Table3[[#This Row],[Amt]]*0.18 -> 0 | Q16: =+Table3[[#This Row],[Amt]]+Table3[[#This Row],[GST]] -> 0 | S16: =+Table3[[#This Row],[Total Am t]]+Table3[[#This Row],[Frieght]] -> 0 | T16: =IFERROR(+Table3[[#This Row],[Total amt]]/Table3[[#This Row],[Qty Received]],0) -> 0
B17: =IFERROR(VLOOKUP(Table3[[#This Row],[Vendor ID]],Table6[[Vendor ID]:[Vendor Name]],2,0),"") | J17: =IFERROR(VLOOKUP(Table3[[#This Row],[Receipt Location Code]],Table5[#All],3,0),"") | L17: =IFERROR(VLOOKUP(Table3[[#This Row],[Item Name]],Table2[[#All],[Item Name]:[Open Rate]],2,0),"") | O17: =+Table3[[#This Row],[Rate]]*Table3[[#This Row],[Qty Received]] -> 0 | P17: =+Table3[[#This Row],[Amt]]*0.18 -> 0 | Q17: =+Table3[[#This Row],[Amt]]+Table3[[#This Row],[GST]] -> 0 | S17: =+Table3[[#This Row],[Total Am t]]+Table3[[#This Row],[Frieght]] -> 0 | T17: =IFERROR(+Table3[[#This Row],[Total amt]]/Table3[[#This Row],[Qty Received]],0) -> 0
... B55: =IFERROR(VLOOKUP(Table3[[#This Row],[Vendor ID]],Table6[[Vendor ID]:[Vendor Name]],2,0),"") | J55: =IFERROR(VLOOKUP(Table3[[#This Row],[Receipt Location Code]],Table5[#All],3,0),"") | L55: =IFERROR(VLOOKUP(Table3[[#This Row],[Item Name]],Table2[[#All],[Item Name]:[Open Rate]],2,0),"") | O55: =+Table3[[#This Row],[Rate]]*Table3[[#This Row],[Qty Received]] -> 0 | P55: =+Table3[[#This Row],[Amt]]*0.18 -> 0 | Q55: =+Table3[[#This Row],[Amt]]+Table3[[#This Row],[GST]] -> 0 | S55: =+Table3[[#This Row],[Total Am t]]+Table3[[#This Row],[Frieght]] -> 0 | T55: =IFERROR(+Table3[[#This Row],[Total amt]]/Table3[[#This Row],[Qty Received]],0) -> 0
B56: =IFERROR(VLOOKUP(Table3[[#This Row],[Vendor ID]],Table6[[Vendor ID]:[Vendor Name]],2,0),"") | J56: =IFERROR(VLOOKUP(Table3[[#This Row],[Receipt Location Code]],Table5[#All],3,0),"") | L56: =IFERROR(VLOOKUP(Table3[[#This Row],[Item Name]],Table2[[#All],[Item Name]:[Open Rate]],2,0),"") | O56: =+Table3[[#This Row],[Rate]]*Table3[[#This Row],[Qty Received]] -> 0 | P56: =+Table3[[#This Row],[Amt]]*0.05 -> 0 | Q56: =+Table3[[#This Row],[Amt]]+Table3[[#This Row],[GST]] -> 0 | S56: =+Table3[[#This Row],[Total Am t]]+Table3[[#This Row],[Frieght]] -> 0 | T56: =IFERROR(+Table3[[#This Row],[Total amt]]/Table3[[#This Row],[Qty Received]],0) -> 0
B57: =IFERROR(VLOOKUP(Table3[[#This Row],[Vendor ID]],Table6[[Vendor ID]:[Vendor Name]],2,0),"") | J57: =IFERROR(VLOOKUP(Table3[[#This Row],[Receipt Location Code]],Table5[#All],3,0),"") | L57: =IFERROR(VLOOKUP(Table3[[#This Row],[Item Name]],Table2[[#All],[Item Name]:[Open Rate]],2,0),"") | O57: =+Table3[[#This Row],[Rate]]*Table3[[#This Row],[Qty Received]] -> 0 | P57: =+Table3[[#This Row],[Amt]]*0.18 -> 0 | Q57: =+Table3[[#This Row],[Amt]]+Table3[[#This Row],[GST]] -> 0 | S57: =+Table3[[#This Row],[Total Am t]]+Table3[[#This Row],[Frieght]] -> 0 | T57: =IFERROR(+Table3[[#This Row],[Total amt]]/Table3[[#This Row],[Qty Received]],0) -> 0
B58: =IFERROR(VLOOKUP(Table3[[#This Row],[Vendor ID]],Table6[[Vendor ID]:[Vendor Name]],2,0),"") | J58: =IFERROR(VLOOKUP(Table3[[#This Row],[Receipt Location Code]],Table5[#All],3,0),"") | L58: =IFERROR(VLOOKUP(Table3[[#This Row],[Item Name]],Table2[[#All],[Item Name]:[Open Rate]],2,0),"") | O58: =+Table3[[#This Row],[Rate]]*Table3[[#This Row],[Qty Received]] -> 0 | P58: =+Table3[[#This Row],[Amt]]*0.18 -> 0 | Q58: =+Table3[[#This Row],[Amt]]+Table3[[#This Row],[GST]] -> 0 | S58: =+Table3[[#This Row],[Total Am t]]+Table3[[#This Row],[Frieght]] -> 0 | T58: =IFERROR(+Table3[[#This Row],[Total amt]]/Table3[[#This Row],[Qty Received]],0) -> 0
B59: =IFERROR(VLOOKUP(Table3[[#This Row],[Vendor ID]],Table6[[Vendor ID]:[Vendor Name]],2,0),"") | J59: =IFERROR(VLOOKUP(Table3[[#This Row],[Receipt Location Code]],Table5[#All],3,0),"") | L59: =IFERROR(VLOOKUP(Table3[[#This Row],[Item Name]],Table2[[#All],[Item Name]:[Open Rate]],2,0),"") | O59: =+Table3[[#This Row],[Rate]]*Table3[[#This Row],[Qty Received]] -> 0 | P59: =+Table3[[#This Row],[Amt]]*0.18 -> 0 | Q59: =+Table3[[#This Row],[Amt]]+Table3[[#This Row],[GST]] -> 0 | S59: =+Table3[[#This Row],[Total Am t]]+Table3[[#This Row],[Frieght]] -> 0 | T59: =IFERROR(+Table3[[#This Row],[Total amt]]/Table3[[#This Row],[Qty Received]],0) -> 0
B60: =IFERROR(VLOOKUP(Table3[[#This Row],[Vendor ID]],Table6[[Vendor ID]:[Vendor Name]],2,0),"") | J60: =IFERROR(VLOOKUP(Table3[[#This Row],[Receipt Location Code]],Table5[#All],3,0),"") | L60: =IFERROR(VLOOKUP(Table3[[#This Row],[Item Name]],Table2[[#All],[Item Name]:[Open Rate]],2,0),"") | O60: =+Table3[[#This Row],[Rate]]*Table3[[#This Row],[Qty Received]] -> 0 | P60: =+Table3[[#This Row],[Amt]]*0.05 -> 0 | Q60: =+Table3[[#This Row],[Amt]]+Table3[[#This Row],[GST]] -> 0 | S60: =+Table3[[#This Row],[Total Am t]]+Table3[[#This Row],[Frieght]] -> 0 | T60: =IFERROR(+Table3[[#This Row],[Total amt]]/Table3[[#This Row],[Qty Received]],0) -> 0
B61: =IFERROR(VLOOKUP(Table3[[#This Row],[Vendor ID]],Table6[[Vendor ID]:[Vendor Name]],2,0),"") | J61: =IFERROR(VLOOKUP(Table3[[#This Row],[Receipt Location Code]],Table5[#All],3,0),"") | L61: =IFERROR(VLOOKUP(Table3[[#This Row],[Item Name]],Table2[[#All],[Item Name]:[Open Rate]],2,0),"") | O61: =+Table3[[#This Row],[Rate]]*Table3[[#This Row],[Qty Received]] -> 0 | P61: =+Table3[[#This Row],[Amt]]*0.18 -> 0 | Q61: =+Table3[[#This Row],[Amt]]+Table3[[#This Row],[GST]] -> 0 | S61: =+Table3[[#This Row],[Total Am t]]+Table3[[#This Row],[Frieght]] -> 0 | T61: =IFERROR(+Table3[[#This Row],[Total amt]]/Table3[[#This Row],[Qty Received]],0) -> 0
B62: =IFERROR(VLOOKUP(Table3[[#This Row],[Vendor ID]],Table6[[Vendor ID]:[Vendor Name]],2,0),"") | J62: =IFERROR(VLOOKUP(Table3[[#This Row],[Receipt Location Code]],Table5[#All],3,0),"") | L62: =IFERROR(VLOOKUP(Table3[[#This Row],[Item Name]],Table2[[#All],[Item Name]:[Open Rate]],2,0),"") | O62: =+Table3[[#This Row],[Rate]]*Table3[[#This Row],[Qty Received]] -> 0 | P62: =+Table3[[#This Row],[Amt]]*0.18 -> 0 | Q62: =+Table3[[#This Row],[Amt]]+Table3[[#This Row],[GST]] -> 0 | S62: =+Table3[[#This Row],[Total Am t]]+Table3[[#This Row],[Frieght]] -> 0 | T62: =IFERROR(+Table3[[#This Row],[Total amt]]/Table3[[#This Row],[Qty Received]],0) -> 0
B63: =IFERROR(VLOOKUP(Table3[[#This Row],[Vendor ID]],Table6[[Vendor ID]:[Vendor Name]],2,0),"") | J63: =IFERROR(VLOOKUP(Table3[[#This Row],[Receipt Location Code]],Table5[#All],3,0),"") | L63: =IFERROR(VLOOKUP(Table3[[#This Row],[Item Name]],Table2[[#All],[Item Name]:[Open Rate]],2,0),"") | O63: =+Table3[[#This Row],[Rate]]*Table3[[#This Row],[Qty Received]] -> 0 | P63: =+Table3[[#This Row],[Amt]]*0.18 -> 0 | Q63: =+Table3[[#This Row],[Amt]]+Table3[[#This Row],[GST]] -> 0 | S63: =+Table3[[#This Row],[Total Am t]]+Table3[[#This Row],[Frieght]] -> 0 | T63: =IFERROR(+Table3[[#This Row],[Total amt]]/Table3[[#This Row],[Qty Received]],0) -> 0
B64: =IFERROR(VLOOKUP(Table3[[#This Row],[Vendor ID]],Table6[#All],2,0),"") | J64: =IFERROR(VLOOKUP(Table3[[#This Row],[Receipt Location Code]],Table5[#All],3,0),"") | L64: =IFERROR(VLOOKUP(Table3[[#This Row],[Item Name]],Table2[[#All],[Item Name]:[UoM]],2,0),"") | O64: =+Table3[[#This Row],[Rate]]*Table3[[#This Row],[Qty Received]] -> 0 | P64: =+Table3[[#This Row],[Amt]]*0.18 -> 0 | Q64: =+Table3[[#This Row],[Amt]]+Table3[[#This Row],[GST]] -> 0 | S64: =+Table3[[#This Row],[Total Am t]]+Table3[[#This Row],[Frieght]] -> 0 | T64: =IFERROR(+Table3[[#This Row],[Total amt]]/Table3[[#This Row],[Qty Received]],0) -> 0
B65: =IFERROR(VLOOKUP(Table3[[#This Row],[Vendor ID]],Table6[#All],2,0),"") | J65: =IFERROR(VLOOKUP(Table3[[#This Row],[Receipt Location Code]],Table5[#All],3,0),"") | L65: =IFERROR(VLOOKUP(Table3[[#This Row],[Item Name]],Table2[[#All],[Item Name]:[UoM]],2,0),"") | O65: =+Table3[[#This Row],[Rate]]*Table3[[#This Row],[Qty Received]] -> 0 | P65: =+Table3[[#This Row],[Amt]]*0.18 -> 0 | Q65: =+Table3[[#This Row],[Amt]]+Table3[[#This Row],[GST]] -> 0 | S65: =+Table3[[#This Row],[Total Am t]]+Table3[[#This Row],[Frieght]] -> 0 | T65: =IFERROR(+Table3[[#This Row],[Total amt]]/Table3[[#This Row],[Qty Received]],0) -> 0

Sheet Godown
A1: MPG/BMC Code | B1: Type | C1: Name | D1: BMC Area
A2: 1 | B2: Main Godown | C2: Munger | D2: NA
A3: 10070001 | B3: MPG | C3: MSKMPG LAKXMIPUR | D3: Araria
A4: 10070002 | B4: MPG | C4: Gomukh ID Araria | D4: Araria
A5: 10070003 | B5: MPG | C5: Gomukh ID Chaidha | D5: Araria
A6: 10070004 | B6: MPG | C6: Gomukh ID Pakrail | D6: Araria
A7: 10070008 | B7: MPG | C7: Gomukh ID Pipra | D7: Araria
A8: 10070010 | B8: MPG | C8: Gomukh Araria-1 | D8: Araria
A9: 10070013 | B9: MPG | C9: Gomukh Fatepur | D9: Araria
A10: 10070016 | B10: MPG | C10: Gomukh Gauchhari | D10: Araria
A11: 10070017 | B11: MPG | C11: Gomukh Arariya Uttari | D11: Araria
A12: 10070018 | B12: MPG | C12: Gomukh Arariya Karjaniya | D12: Araria
A13: 10070019 | B13: MPG | C13: Gomukh Aariya Dummer Kothi | D13: Araria
... A872: 1055 | B872: BMC | C872: Matihani | D872: Matihani
A873: Lab | B873: Lab | C873: Daya_Lab | D873: Munger
A874: 10540003 | B874: MPG | C874: GOMUKH ANANDPUR PARAS 2 | D874: Alauli
A875: 10540004 | B875: MPG | C875: GOMUKH SHYAM GHARARI | D875: Alauli
A876: 10540005 | B876: MPG | C876: GOMUKH GADBANNI | D876: Alauli
A877: 10540006 | B877: MPG | C877: GOMUKH AMBA | D877: Alauli
A878: 10540007 | B878: MPG | C878: GOMUKH GORIYAMI | D878: Alauli
A879: 10540008 | B879: MPG | C879: GOMUKH PARRI | D879: Alauli
A880: 10540009 | B880: MPG | C880: GOMUKH BHIKHARI GHAT | D880: Alauli
A881: 10540010 | B881: MPG | C881: Vikash Kumar | D881: Alauli
A882: 10540011 | B882: MPG | C882: Jayvir Kumar | D882: Alauli
A883: 10540012 | B883: MPG | C883: Rajkishore Yadav | D883: Alauli
A884: 10540013 | B884: MPG | C884: Jalkaura VLC | D884: Alauli
A885: 10540014 | B885: MPG | C885: BHADAS VLC | D885: Alauli
... A1261: 10600014 | B1261: MPG | C1261: Gumukh Dhamar Ajit | D1261: Behiya

Sheet Vendor
A1: Vendor ID | B1: Vendor Name | C1: Address | D1: PAN | E1: GST | F1: Mobile | G1: Email | H1: Supply For
A2: 1 | B2: R R Sales | H2: Tanker Seal
A3: 2 | B3: Minakshi Scientific
A4: 3 | B4: Geochem Bio Science
A5: 4 | B5: Indifoss Analytical Pvt Ltd
A6: 5 | B6: Baranwal Computer
A7: 6 | B7: Satol Chemicals LTD
A8: 7 | B8: Everest Instruments PVT LTD
A9: 8 | B9: JK India Instruments PVT LTD
A10: 9 | B10: Narang scientific Industries
A11: 10 | B11: Peejay Transprint

Sheet Item
A1: S.No | B1: Category | C1: Location | D1: Item Name | E1: UoM | F1: Vendor Name | G1: Stock as on 1st Apr | H1: Reorder Qty | I1: Reorder Level | J1: Avg Consumption of 2 Month | K1: Open Rate | L1: Column1 | M1: diff
A2: 1 | B2: Chemical | C2: Munger | D2: 1% Iodine Solution (100ml) | E2: Nos | F2: Maa enterpires | G2: 13 | H2: 15 | I2: 5 | J2: 1 | K2: 90 | L2: 15 | M2: =Table2[[#This Row],[Stock as on 1st Apr]]-Table2[[#This Row],[Column1]] -> -2
A3: 2 | B3: Glassware | C3: Munger | D3: Amber Colour Bottle (250 ML) | E3: Nos | F3: Maa enterpires | G3: 120 | H3: 50 | I3: 40 | J3: 20 | K3: 120 | L3: 140 | M3: =Table2[[#This Row],[Stock as on 1st Apr]]-Table2[[#This Row],[Column1]] -> -20
A4: 3 | B4: Chemical | C4: Munger | D4: Amyl 500ml | E4: Nos | F4: Maa enterpires | G4: 47 | H4: 50 | I4: 30 | J4: 15 | K4: 365.8 | L4: 50 | M4: =Table2[[#This Row],[Stock as on 1st Apr]]-Table2[[#This Row],[Column1]] -> -3
A5: 4 | B5: Stationery | C5: Munger | D5: Analyzer Calibration Cheking Log Book | E5: Nos | F5: Barnwal Computer | G5: 61 | H5: 100 | I5: 20 | J5: 15 | K5: 127.44 | L5: 13 | M5: =Table2[[#This Row],[Stock as on 1st Apr]]-Table2[[#This Row],[Column1]] -> 48
A6: 5 | B6: Glassware | C6: Munger | D6: Beaker 100 Ml | E6: Nos | F6: Jk India | G6: 16 | H6: 48 | I6: 10 | J6: 10 | K6: 33.18 | L6: 24 | M6: =Table2[[#This Row],[Stock as on 1st Apr]]-Table2[[#This Row],[Column1]] -> -8
A7: 6 | B7: Glassware | C7: Munger | D7: Beaker 250 ML Borosilicate | E7: Nos | F7: Jk India | G7: 20 | H7: 48 | I7: 10 | J7: 10 | K7: 64.9 | L7: 12 | M7: =Table2[[#This Row],[Stock as on 1st Apr]]-Table2[[#This Row],[Column1]] -> 8
A8: 7 | B8: Glassware | C8: Munger | D8: Beaker 500 Ml | E8: Nos | F8: Jk India | G8: 25 | H8: 48 | I8: 10 | J8: 10 | K8: 63.7 | L8: 49 | M8: =Table2[[#This Row],[Stock as on 1st Apr]]-Table2[[#This Row],[Column1]] -> -24
A9: 8 | B9: Glassware | C9: Munger | D9: Beaker 50 ML | E9: Nos | F9: Jk India | G9: 28 | H9: 48 | I9: 10 | J9: 10 | K9: 15.88 | L9: 8 | M9: =Table2[[#This Row],[Stock as on 1st Apr]]-Table2[[#This Row],[Column1]] -> 20
A10: 9 | B10: Consumables | C10: Munger | D10: BMC Cleaning Brush 2" | E10: Nos | F10: Surya Instruments | G10: 26 | H10: 10 | I10: 10 | J10: 10 | K10: 212.4 | L10: 41 | M10: =Table2[[#This Row],[Stock as on 1st Apr]]-Table2[[#This Row],[Column1]] -> -15
A11: 10 | B11: Stationery | C11: Munger | D11: BMC Day Book | E11: Nos | F11: Barnwal Computer | G11: 90 | H11: 300 | I11: 60 | J11: 30 | K11: 121.54 | L11: 106 | M11: =Table2[[#This Row],[Stock as on 1st Apr]]-Table2[[#This Row],[Column1]] -> -16
A12: 11 | B12: Other Items | C12: Munger | D12: Burete Stand | E12: Nos | F12: Maa enterpires | G12: 2 | H12: 20 | I12: 5 | J12: 5 | K12: 258.04 | L12: 16 | M12: =Table2[[#This Row],[Stock as on 1st Apr]]-Table2[[#This Row],[Column1]] -> -14
A13: 12 | B13: Glassware | C13: Munger | D13: Burret 50 ML Borosilicate | E13: Nos | F13: Maa enterpires | G13: 8 | H13: 20 | I13: 5 | J13: 5 | K13: 99.47 | L13: 14 | M13: =Table2[[#This Row],[Stock as on 1st Apr]]-Table2[[#This Row],[Column1]] -> -6
... A21: 20 | B21: Chemical | C21: Munger | D21: Distil Water 5 Ltr | E21: Nos | F21: Narang Scientific | G21: 40 | H21: 10 | I21: 5 | J21: 5 | K21: 168 | L21: 100 | M21: =Table2[[#This Row],[Stock as on 1st Apr]]-Table2[[#This Row],[Column1]] -> -60
A22: 21 | B22: Consumables | C22: Munger | D22: Eco Power Solution | E22: Nos | F22: STIPL | G22: =148+19 -> 167 | H22: 200 | I22: 20 | J22: 20 | K22: 348.52 | L22: 177 | M22: =Table2[[#This Row],[Stock as on 1st Apr]]-Table2[[#This Row],[Column1]] -> -10
A23: 22 | B23: Consumables | C23: Munger | D23: EKO Clean 25 Kg | E23: Nos | F23: Satol pvt | G23: 0 | H23: 10 | I23: 5 | J23: 5 | K23: 53.1 | L23: 0 | M23: =Table2[[#This Row],[Stock as on 1st Apr]]-Table2[[#This Row],[Column1]] -> 0
A24: 23 | B24: Consumables | C24: Munger | D24: Eko Day Cleaning Sol | E24: Nos | F24: STIPL | G24: =93+117 -> 210 | H24: 500 | I24: 50 | J24: 150 | K24: 348.52 | L24: 199 | M24: =Table2[[#This Row],[Stock as on 1st Apr]]-Table2[[#This Row],[Column1]] -> 11
A25: 24 | B25: Consumables | C25: Munger | D25: Eko Measuring Plastic Mug | E25: Nos | F25: Everest | G25: 34 | H25: 100 | I25: 5 | J25: 10 | K25: 36.88 | L25: 50 | M25: =Table2[[#This Row],[Stock as on 1st Apr]]-Table2[[#This Row],[Column1]] -> -16
A26: 25 | B26: Consumables | C26: Munger | D26: EKO Plunger | E26: Nos | F26: STIPL | G26: =110+81 -> 191 | H26: 200 | I26: 20 | J26: 100 | K26: 56.02 | L26: 134 | M26: =Table2[[#This Row],[Stock as on 1st Apr]]-Table2[[#This Row],[Column1]] -> 57
A27: 26 | B27: Chemical | C27: Munger | D27: Ethyl Alcohol 500 ML Pack | E27: Nos | F27: Surya Instruments | G27: 97 | H27: 250 | I27: 25 | J27: 100 | K27: 271.4 | L27: 208 | M27: =Table2[[#This Row],[Stock as on 1st Apr]]-Table2[[#This Row],[Column1]] -> -111
A28: 27 | B28: Stationery | C28: Munger | D28: Farmers Passbook | E28: Nos | F28: Barnwal Computer | G28: =936+19 -> 955 | H28: 6000 | I28: 1000 | J28: 1000 | K28: 5.13 | L28: 4394 | M28: =Table2[[#This Row],[Stock as on 1st Apr]]-Table2[[#This Row],[Column1]] -> -3439
A29: 28 | B29: Consumables | C29: Munger | D29: Fat Sacn Jet | E29: Nos | F29: Everest | G29: 0 | H29: 200 | I29: 20 | J29: 20 | K29: 337.4 | L29: 0 | M29: =Table2[[#This Row],[Stock as on 1st Apr]]-Table2[[#This Row],[Column1]] -> 0
A30: 29 | B30: Consumables | C30: Munger | D30: FAT Scan Weekly | E30: Nos | F30: STIPL | G30: =5+27 -> 32 | H30: 300 | I30: 30 | J30: 100 | K30: 348.52 | L30: 163 | M30: =Table2[[#This Row],[Stock as on 1st Apr]]-Table2[[#This Row],[Column1]] -> -131
A31: 30 | B31: Chemical | C31: Munger | D31: Ferric Chloride 500 Gms | E31: Nos | F31: Maa enterpires | G31: 6 | H31: 10 | I31: 5 | J31: 2 | K31: 132.62 | L31: 6 | M31: =Table2[[#This Row],[Stock as on 1st Apr]]-Table2[[#This Row],[Column1]] -> 0
A32: 31 | B32: Other Items | C32: Munger | D32: Fire Extinguiser, Capacity-6 KG | E32: Nos | F32: Xxtra Care | G32: 11 | H32: 10 | I32: 5 | J32: 5 | K32: 1770 | L32: 0 | M32: =Table2[[#This Row],[Stock as on 1st Apr]]-Table2[[#This Row],[Column1]] -> 11
A33: 32 | B33: Other Items | C33: Munger | D33: FLY KILLER MACHINE 2*18W WH | E33: Nos | G33: 4 | H33: 10 | I33: 5 | J33: 5 | K33: 0 | L33: 0 | M33: =Table2[[#This Row],[Stock as on 1st Apr]]-Table2[[#This Row],[Column1]] -> 4
A34: 33 | B34: Other Items | C34: Munger | D34: Geaser | E34: Nos | G34: 6 | H34: 10 | I34: 5 | J34: 5 | K34: 15000.16 | L34: 0 | M34: =Table2[[#This Row],[Stock as on 1st Apr]]-Table2[[#This Row],[Column1]] -> 6
A35: 34 | B35: Other Items | C35: Munger | D35: Gerber Centrifuse 24 Test Electric | E35: Nos | F35: Jk India | G35: 1 | H35: 5 | I35: 2 | J35: 1 | K35: 4720 | L35: 5 | M35: =Table2[[#This Row],[Stock as on 1st Apr]]-Table2[[#This Row],[Column1]] -> -4
A36: 35 | B36: Consumables | C36: Munger | D36: Gloves | E36: Nos | F36: Maa enterpires | G36: 0 | H36: 10 | I36: 2 | J36: 1 | K36: 289.1 | L36: 0 | M36: =Table2[[#This Row],[Stock as on 1st Apr]]-Table2[[#This Row],[Column1]] -> 0
A37: 36 | B37: Consumables | C37: Munger | D37: Gum Glue Traps | E37: Nos | G37: 180 | H37: 10 | I37: 5 | J37: 5 | K37: 30.68 | L37: 200 | M37: =Table2[[#This Row],[Stock as on 1st Apr]]-Table2[[#This Row],[Column1]] -> -20
A38: 37 | B38: Stationery | C38: Munger | D38: Headload Slip | E38: Nos | F38: Barnwal Computer | G38: 500 | H38: 500 | I38: 5 | J38: 5 | K38: 13.28 | L38: 500 | M38: =Table2[[#This Row],[Stock as on 1st Apr]]-Table2[[#This Row],[Column1]] -> 0
A39: 38 | B39: Chemical | C39: Munger | D39: Hydrolic Acid | E39: Nos | F39: Minakshi Scientific | G39: 7 | H39: 10 | I39: 5 | J39: 5 | K39: 282.8 | L39: 10 | M39: =Table2[[#This Row],[Stock as on 1st Apr]]-Table2[[#This Row],[Column1]] -> -3
A40: 39 | B40: Glassware | C40: Munger | D40: Lactometer 0-40 | E40: Nos | F40: Jk India | G40: 240 | H40: 50 | I40: 5 | J40: 5 | K40: 132.7 | L40: 250 | M40: =Table2[[#This Row],[Stock as on 1st Apr]]-Table2[[#This Row],[Column1]] -> -10
A41: 40 | B41: Consumables | C41: Munger | D41: Lactometer Jar Small | E41: Nos | F41: Maa enterpires | G41: 230 | H41: 500 | I41: 50 | J41: 5 | K41: 18.95 | L41: 250 | M41: =Table2[[#This Row],[Stock as on 1st Apr]]-Table2[[#This Row],[Column1]] -> -20
A42: 41 | B42: Consumables | C42: Munger | D42: Lock Stopper | E42: Nos | F42: Maa enterpires | G42: 282 | H42: 500 | I42: 50 | J42: 5 | K42: 1.99 | L42: 786 | M42: =Table2[[#This Row],[Stock as on 1st Apr]]-Table2[[#This Row],[Column1]] -> -504
A43: 42 | B43: Consumables | C43: Munger | D43: Lock Stopper Key | E43: Nos | F43: Maa enterpires | G43: 135 | H43: 500 | I43: 50 | J43: 5 | K43: 4.32 | L43: 150 | M43: =Table2[[#This Row],[Stock as on 1st Apr]]-Table2[[#This Row],[Column1]] -> -15
A44: 43 | B44: Stationery | C44: Munger | D44: Material Indent Book | E44: Nos | F44: Barnwal Computer | G44: 100 | H44: 100 | I44: 5 | J44: 5 | K44: 26.55 | L44: 100 | M44: =Table2[[#This Row],[Stock as on 1st Apr]]-Table2[[#This Row],[Column1]] -> 0
A45: 44 | B45: Other Items | C45: Munger | D45: MBRT Bath Digital | E45: Nos | F45: Maa enterpires | G45: 0 | H45: 5 | I45: 1 | J45: 1 | K45: 8826.4 | L45: 0 | M45: =Table2[[#This Row],[Stock as on 1st Apr]]-Table2[[#This Row],[Column1]] -> 0
A46: 45 | B46: Other Items | C46: Munger | D46: MBRT Serogical Water Bath | E46: Nos | F46: Narang Scientific | G46: 2 | H46: 10 | I46: 2 | J46: 1 | K46: 9676 | L46: 0 | M46: =Table2[[#This Row],[Stock as on 1st Apr]]-Table2[[#This Row],[Column1]] -> 2
A47: 46 | B47: Stationery | C47: Munger | D47: MBRT Test Register | E47: Nos | F47: Barnwal Computer | G47: 51 | H47: 100 | I47: 5 | J47: 5 | K47: 115.36 | L47: 102 | M47: =Table2[[#This Row],[Stock as on 1st Apr]]-Table2[[#This Row],[Column1]] -> -51
A48: 47 | B48: Glassware | C48: Munger | D48: Measuring Cylinder 1000 ML Plastic | E48: Nos | F48: Maa enterpires | G48: 31 | H48: 20 | I48: 5 | J48: 5 | K48: 258.44 | L48: 42 | M48: =Table2[[#This Row],[Stock as on 1st Apr]]-Table2[[#This Row],[Column1]] -> -11
A49: 48 | B49: Glassware | C49: Munger | D49: Measuring Cylinder 100 ML Plastic | E49: Nos | F49: Maa enterpires | G49: 35 | H49: 20 | I49: 5 | J49: 5 | K49: 47.2 | L49: 45 | M49: =Table2[[#This Row],[Stock as on 1st Apr]]-Table2[[#This Row],[Column1]] -> -10
A50: 49 | B50: Glassware | C50: Munger | D50: Measuring Cylinder 250 ML | E50: Nos | F50: Maa enterpires | G50: 18 | H50: 20 | I50: 5 | J50: 5 | K50: 106.2 | L50: 15 | M50: =Table2[[#This Row],[Stock as on 1st Apr]]-Table2[[#This Row],[Column1]] -> 3
A51: 50 | B51: Other Items | C51: Munger | D51: Milk Cane Plunger S. S. | E51: Nos | F51: Narang Scientific | G51: =78+52 -> 130 | H51: 200 | I51: 10 | J51: 50 | K51: 188.8 | L51: 2 | M51: =Table2[[#This Row],[Stock as on 1st Apr]]-Table2[[#This Row],[Column1]] -> 128
A52: 51 | B52: Stationery | C52: Munger | D52: Milk Despatch Challan | E52: Nos | F52: Barnwal Computer | G52: 184 | H52: 400 | I52: 10 | J52: 150 | K52: 94.4 | L52: 182 | M52: =Table2[[#This Row],[Stock as on 1st Apr]]-Table2[[#This Row],[Column1]] -> 2
A53: 52 | B53: Glassware | C53: Munger | D53: Milk Pipete 10.75 ML | E53: Nos | F53: Jk India | G53: 623 | H53: 50 | I53: 5 | J53: 5 | K53: 132.7 | L53: 619 | M53: =Table2[[#This Row],[Stock as on 1st Apr]]-Table2[[#This Row],[Column1]] -> 4
A54: 53 | B54: Other Items | C54: Munger | D54: Milk Sampler Dipper SS Capacity 50ml | E54: Nos | F54: Maa enterpires | G54: =185+59 -> 244 | H54: 500 | I54: 5 | J54: 5 | K54: 22.99 | L54: 150 | M54: =Table2[[#This Row],[Stock as on 1st Apr]]-Table2[[#This Row],[Column1]] -> 94
A55: 54 | B55: Stationery | C55: Munger | D55: MPG Register | E55: Nos | F55: Barnwal Computer | G55: =57+173 -> 230 | H55: 200 | I55: 20 | J55: 50 | K55: 129.8 | L55: 108 | M55: =Table2[[#This Row],[Stock as on 1st Apr]]-Table2[[#This Row],[Column1]] -> 122
A56: 55 | B56: Glassware | C56: Munger | D56: NABL Buyterometer | E56: Nos | F56: Jk India | G56: 1 | H56: 5 | I56: 1 | J56: 1 | K56: 4484 | L56: 1 | M56: =Table2[[#This Row],[Stock as on 1st Apr]]-Table2[[#This Row],[Column1]] -> 0
A57: 56 | B57: Glassware | C57: Munger | D57: NABL Certified Lactometer | E57: Nos | F57: Jk India | G57: 2 | H57: 5 | I57: 1 | J57: 1 | K57: 4484 | L57: 1 | M57: =Table2[[#This Row],[Stock as on 1st Apr]]-Table2[[#This Row],[Column1]] -> 1
A58: 57 | B58: Other Items | C58: Munger | D58: Nylon Filter Cloth - Than | E58: Nos | F58: Maa enterpires | G58: 38 | H58: 100 | I58: 5 | J58: 5 | K58: 738.09 | L58: 4 | M58: =Table2[[#This Row],[Stock as on 1st Apr]]-Table2[[#This Row],[Column1]] -> 34
A59: 58 | B59: Chemical | C59: Munger | D59: Para Dimethyle Amino | E59: Nos | F59: Maa enterpires | G59: 33 | H59: 10 | I59: 2 | J59: 1 | K59: 689.39 | L59: 36 | M59: =Table2[[#This Row],[Stock as on 1st Apr]]-Table2[[#This Row],[Column1]] -> -3
A60: 59 | B60: Glassware | C60: Munger | D60: Petri Dish Borosilicate | E60: Nos | F60: Jk India | G60: 7 | H60: 24 | I60: 5 | J60: 5 | K60: 79.62 | L60: 24 | M60: =Table2[[#This Row],[Stock as on 1st Apr]]-Table2[[#This Row],[Column1]] -> -17
A61: 60 | B61: Chemical | C61: Munger | D61: Phenolphthaleing Indicator | E61: Nos | F61: Minakshi Scientific | G61: 47 | H61: 50 | I61: 15 | J61: 15 | K61: 106.2 | L61: 12 | M61: =Table2[[#This Row],[Stock as on 1st Apr]]-Table2[[#This Row],[Column1]] -> 35
A62: 61 | B62: Consumables | C62: Munger | D62: Pipe Cleaning Brush 5" Long | E62: Nos | G62: 0 | H62: 50 | I62: 5 | J62: 2 | K62: 265.5 | L62: 0 | M62: =Table2[[#This Row],[Stock as on 1st Apr]]-Table2[[#This Row],[Column1]] -> 0
A63: 62 | B63: Consumables | C63: Munger | D63: Pipette Cleaning Brush | E63: Nos | F63: Maa enterpires | G63: 2606 | H63: 5000 | I63: 500 | J63: 100 | K63: 0.9 | L63: 3058 | M63: =Table2[[#This Row],[Stock as on 1st Apr]]-Table2[[#This Row],[Column1]] -> -452
A64: 63 | B64: Glassware | C64: Munger | D64: Pipette Gradulated 10 ML | E64: Nos | F64: Maa enterpires | G64: 70 | H64: 100 | I64: 10 | J64: 15 | K64: 23.46 | L64: 118 | M64: =Table2[[#This Row],[Stock as on 1st Apr]]-Table2[[#This Row],[Column1]] -> -48
A65: 64 | B65: Glassware | C65: Munger | D65: Pipette Gradulated 1 ML | E65: Nos | F65: Maa enterpires | G65: 154 | H65: 100 | I65: 10 | J65: 15 | K65: 22.42 | L65: 212 | M65: =Table2[[#This Row],[Stock as on 1st Apr]]-Table2[[#This Row],[Column1]] -> -58
A66: 65 | B66: Glassware | C66: Munger | D66: Pipette Gradulated 2 ML | E66: Nos | F66: Maa enterpires | G66: 135 | H66: 100 | I66: 10 | J66: 15 | K66: 28.46 | L66: 178 | M66: =Table2[[#This Row],[Stock as on 1st Apr]]-Table2[[#This Row],[Column1]] -> -43
A67: 66 | B67: Glassware | C67: Munger | D67: Pipette NABL Certified | E67: Nos | F67: Jk India | G67: 1 | H67: 10 | I67: 2 | J67: 1 | K67: 4484 | L67: 1 | M67: =Table2[[#This Row],[Stock as on 1st Apr]]-Table2[[#This Row],[Column1]] -> 0
A68: 67 | B68: Consumables | C68: Munger | D68: Plastic Strainer | E68: Nos | F68: Surya Instruments | G68: =3+60 -> 63 | H68: 200 | I68: 20 | J68: 20 | K68: 29.5 | L68: 103 | M68: =Table2[[#This Row],[Stock as on 1st Apr]]-Table2[[#This Row],[Column1]] -> -40
A69: 68 | B69: Glassware | C69: Munger | D69: Reagent Botte with Glass Stopper Borosilicate | E69: Nos | F69: Maa enterpires | G69: 0 | H69: 48 | I69: 10 | J69: 10 | K69: 106.2 | L69: 0 | M69: =Table2[[#This Row],[Stock as on 1st Apr]]-Table2[[#This Row],[Column1]] -> 0
A70: 69 | B70: Glassware | C70: Munger | D70: Reagent Bottle 100 ML | E70: Nos | F70: Minakshi Scientific | G70: 22 | H70: 48 | I70: 10 | J70: 10 | K70: 106.2 | L70: 0 | M70: =Table2[[#This Row],[Stock as on 1st Apr]]-Table2[[#This Row],[Column1]] -> 22
A71: 70 | B71: Glassware | C71: Munger | D71: Reagent Bottle 250 ML | E71: Nos | F71: Minakshi Scientific | G71: 8 | H71: 48 | I71: 10 | J71: 10 | K71: 159.3 | L71: 1 | M71: =Table2[[#This Row],[Stock as on 1st Apr]]-Table2[[#This Row],[Column1]] -> 7
A72: 71 | B72: Stationery | C72: Munger | D72: Register for Milk Reception Log Book | E72: Nos | F72: Barnwal Computer | G72: 47 | H72: 300 | I72: 50 | J72: 60 | K72: 218.3 | L72: 109 | M72: =Table2[[#This Row],[Stock as on 1st Apr]]-Table2[[#This Row],[Column1]] -> -62
A73: 72 | B73: Chemical | C73: Munger | D73: Resorcinol | E73: Nos | F73: Maa enterpires | G73: 4 | H73: 20 | I73: 5 | J73: 5 | K73: 504.15 | L73: 15 | M73: =Table2[[#This Row],[Stock as on 1st Apr]]-Table2[[#This Row],[Column1]] -> -11
A74: 73 | B74: Other Items | C74: Munger | D74: Rodent Box | E74: Nos | G74: 0 | H74: 20 | I74: 5 | J74: 5 | K74: 359.9 | L74: 15 | M74: =Table2[[#This Row],[Stock as on 1st Apr]]-Table2[[#This Row],[Column1]] -> -15
A75: 74 | B75: Chemical | C75: Munger | D75: Rosalic Acid Powder 25 Gms | E75: Nos | F75: Surya Instruments | G75: 2 | H75: 20 | I75: 5 | J75: 5 | K75: 732.5 | L75: 21 | M75: =Table2[[#This Row],[Stock as on 1st Apr]]-Table2[[#This Row],[Column1]] -> -19
A76: 75 | B76: Consumables | C76: Munger | D76: Sample Bottle 100 ML | E76: Nos | F76: Maa enterpires | G76: =3169+204 -> 3373 | H76: 5000 | I76: 400 | J76: 300 | K76: 2.83 | L76: 4130 | M76: =Table2[[#This Row],[Stock as on 1st Apr]]-Table2[[#This Row],[Column1]] -> -757
A77: 76 | B77: Consumables | C77: Munger | D77: Sample Bottle Brush Large | E77: Nos | F77: Maa enterpires | G77: 2508 | H77: 2000 | I77: 200 | J77: 100 | K77: 1.68 | L77: 2813 | M77: =Table2[[#This Row],[Stock as on 1st Apr]]-Table2[[#This Row],[Column1]] -> -305
A78: 77 | B78: Consumables | C78: Munger | D78: Sample Bottle Stand PL 25 Test | E78: Nos | F78: Maa enterpires | G78: 65 | H78: 50 | I78: 40 | J78: 10 | K78: 51.74 | L78: 42 | M78: =Table2[[#This Row],[Stock as on 1st Apr]]-Table2[[#This Row],[Column1]] -> 23
A79: 78 | B79: Consumables | C79: Munger | D79: Satol - 5 KG | E79: Nos | F79: Satol pvt | G79: 245 | H79: 250 | I79: 50 | J79: 80 | K79: 135.7 | L79: 240 | M79: =Table2[[#This Row],[Stock as on 1st Apr]]-Table2[[#This Row],[Column1]] -> 5
A80: 79 | B80: Chemical | C80: Munger | D80: Silver Nitrate Solution | E80: Nos | F80: Minakshi Scientific | G80: 44 | H80: 24 | I80: 5 | J80: 10 | K80: 622.47 | L80: 22 | M80: =Table2[[#This Row],[Stock as on 1st Apr]]-Table2[[#This Row],[Column1]] -> 22
A81: 80 | B81: Chemical | C81: Munger | D81: Sodium Hydroxide N/10 Solution | E81: Nos | F81: Narang Scientific | G81: 40 | H81: 100 | I81: 10 | J81: 10 | K81: 135.7 | L81: 8 | M81: =Table2[[#This Row],[Stock as on 1st Apr]]-Table2[[#This Row],[Column1]] -> 32
A82: 81 | B82: Other Items | C82: Munger | D82: Sprit Lamp S. S. | E82: Nos | F82: Maa enterpires | G82: 2 | H82: 24 | I82: 5 | J82: 2 | K82: 37.89 | L82: 7 | M82: =Table2[[#This Row],[Stock as on 1st Apr]]-Table2[[#This Row],[Column1]] -> -5
A83: 82 | B83: Chemical | C83: Munger | D83: Strip for Detection of Glucose in Milk | E83: Nos | F83: Minakshi Scientific | G83: 7 | H83: 25 | I83: 5 | J83: 5 | K83: 867.3 | L83: 10 | M83: =Table2[[#This Row],[Stock as on 1st Apr]]-Table2[[#This Row],[Column1]] -> -3
A84: 83 | B84: Chemical | C84: Munger | D84: Strip for Detection of Maltodextrin in Milk | E84: Nos | F84: Minakshi Scientific | G84: 18 | H84: 25 | I84: 5 | J84: 5 | K84: 1168.2 | L84: 20 | M84: =Table2[[#This Row],[Stock as on 1st Apr]]-Table2[[#This Row],[Column1]] -> -2
A85: 84 | B85: Chemical | C85: Munger | D85: Strip for Detection of Urea in Milk | E85: Nos | F85: Minakshi Scientific | G85: 2 | H85: 25 | I85: 5 | J85: 5 | K85: 840 | L85: 0 | M85: =Table2[[#This Row],[Stock as on 1st Apr]]-Table2[[#This Row],[Column1]] -> 2
A86: 85 | B86: Chemical | C86: Munger | D86: Sulphuric Acid SQ 05 Lt | E86: Nos | F86: Minakshi Scientific | G86: 16 | H86: 50 | I86: 5 | J86: 5 | K86: 812.2 | L86: 22 | M86: =Table2[[#This Row],[Stock as on 1st Apr]]-Table2[[#This Row],[Column1]] -> -6
A87: 86 | B87: Consumables | C87: Munger | D87: Tanker Seal | E87: Nos | F87: RR Sales | G87: 10300 | H87: 15000 | I87: 5000 | J87: 1250 | K87: 12.71 | L87: 5460 | M87: =Table2[[#This Row],[Stock as on 1st Apr]]-Table2[[#This Row],[Column1]] -> 4840
A88: 87 | B88: Consumables | C88: Munger | D88: TEEPOL | E88: Nos | F88: Satol pvt | G88: 375 | H88: 1000 | I88: 200 | J88: 350 | K88: 51.92 | L88: 1000 | M88: =Table2[[#This Row],[Stock as on 1st Apr]]-Table2[[#This Row],[Column1]] -> -625
A89: 88 | B89: Other Items | C89: Munger | D89: Teflon Hammer | E89: Nos | G89: 0 | H89: 10 | I89: 5 | J89: 5 | K89: 365.8 | L89: 0 | M89: =Table2[[#This Row],[Stock as on 1st Apr]]-Table2[[#This Row],[Column1]] -> 0
A90: 89 | B90: Glassware | C90: Munger | D90: Test Tube | E90: Nos | F90: Maa enterpires | G90: 1689 | H90: 2500 | I90: 100 | J90: 50 | K90: 2.96 | L90: 1976 | M90: =Table2[[#This Row],[Stock as on 1st Apr]]-Table2[[#This Row],[Column1]] -> -287
A91: 90 | B91: Consumables | C91: Munger | D91: Test Tube Stand | E91: Nos | F91: Maa enterpires | G91: 3 | H91: 50 | I91: 5 | J91: 5 | K91: 40.62 | L91: 38 | M91: =Table2[[#This Row],[Stock as on 1st Apr]]-Table2[[#This Row],[Column1]] -> -35
A92: 91 | B92: Glassware | C92: Munger | D92: Test Tube with Rubber Cork | E92: Nos | F92: Maa enterpires | G92: 1294 | H92: 2500 | I92: 5 | J92: 5 | K92: 4.93 | L92: 1660 | M92: =Table2[[#This Row],[Stock as on 1st Apr]]-Table2[[#This Row],[Column1]] -> -366
A93: 92 | B93: Stationery | C93: Munger | D93: Thermal Paper Roll - Small | E93: Nos | F93: Pee Jee Transprint | G93: =7395+2070 -> 9465 | H93: 5000 | I93: 1000 | J93: 1500 | K93: 9.15 | L93: 6501 | M93: =Table2[[#This Row],[Stock as on 1st Apr]]-Table2[[#This Row],[Column1]] -> 2964
A94: 93 | B94: Glassware | C94: Munger | D94: Thermameter Alcohal NABL Certified | E94: Nos | F94: Jk India | G94: 1 | H94: 10 | I94: 1 | J94: 1 | K94: 4484 | L94: 1 | M94: =Table2[[#This Row],[Stock as on 1st Apr]]-Table2[[#This Row],[Column1]] -> 0
A95: 94 | B95: Other Items | C95: Munger | D95: Thermometer 110 C | E95: Nos | F95: Jk India | G95: 415 | H95: 10 | I95: 24 | J95: 5 | K95: 132.7 | L95: 415 | M95: =Table2[[#This Row],[Stock as on 1st Apr]]-Table2[[#This Row],[Column1]] -> 0
A96: 95 | B96: Consumables | C96: Munger | D96: Tilt Measure 10cc PI Superior | E96: Nos | F96: Maa enterpires | G96: 388 | H96: 500 | I96: 50 | J96: 10 | K96: 23.71 | L96: 414 | M96: =Table2[[#This Row],[Stock as on 1st Apr]]-Table2[[#This Row],[Column1]] -> -26
A97: 96 | B97: Consumables | C97: Munger | D97: Tilt Measure 1 Ml with Bottle | E97: Nos | F97: Maa enterpires | G97: 230 | H97: 500 | I97: 50 | J97: 10 | K97: 32.09 | L97: 256 | M97: =Table2[[#This Row],[Stock as on 1st Apr]]-Table2[[#This Row],[Column1]] -> -26
