Workbook
Name Code: #REF!

Sheet MPG PIVOT
A1: BMC Code | B1: (All)
A2: For the period of 08-14 Nov'24
E3: Values
A4: Code | B4: MPG NAME | C4: Type | D4: Farmer Payment | E4: BMC Volume | F4: BMC Amount | G4: Reg Vol | H4: reg Amt | I4: Unreg Vol | J4: Unreg Amt | K4: Total Vol | L4: Total Amt | M4: Payable | N4: Loss Apportion | O4: Advance | P4: Others | Q4: Payment to Farmer A/c | R4: Unreg. Farmer payment | S4: Payment to MPGs A/c
A5: (blank) | B5: Total: | C5: (blank) | D5: 117 | E5: 0 | F5: 0 | G5: 0 | H5: 0 | I5: 0 | J5: 0 | K5: 0 | L5: 0 | M5: 0 | N5: 0 | O5: 0 | P5: 0 | Q5: 0 | R5: 0 | S5: 0
B6: (blank) | C6: MPG | D6: Indirect | G6: 0 | H6: 0 | I6: 0 | J6: 0 | K6: 0 | L6: 0 | M6: 0 | N6: 0 | O6: 0 | P6: 0 | Q6: 0 | R6: 0 | S6: 0
C7: RMC | D7: Indirect | G7: 0 | H7: 0 | I7: 0 | J7: 0 | K7: 0 | L7: 0 | M7: 0 | N7: 0 | O7: 0 | P7: 0 | Q7: 0 | R7: 0 | S7: 0
C8: VLC | D8: Indirect | G8: 0 | H8: 0 | I8: 0 | J8: 0 | K8: 0 | L8: 0 | M8: 0 | N8: 0 | O8: 0 | P8: 0 | Q8: 0 | R8: 0 | S8: 0
A9: (blank) Total | E9: 0 | F9: 0 | G9: 0 | H9: 0 | I9: 0 | J9: 0 | K9: 0 | L9: 0 | M9: 0 | N9: 0 | O9: 0 | P9: 0 | Q9: 0 | R9: 0 | S9: 0
A10: Grand Total | E10: 0 | F10: 0 | G10: 0 | H10: 0 | I10: 0 | J10: 0 | K10: 0 | L10: 0 | M10: 0 | N10: 0 | O10: 0 | P10: 0 | Q10: 0 | R10: 0 | S10: 0

Sheet MGP PDF
A1: BMC Code | B1: BMC Code :2008
D2: Payment cycle-08th to 14th May'26
E3: Values
A4: Code | B4: MPG NAME | C4: Type | D4: Farmer Payment | E4: BMC Volume | F4: BMC Amount | G4: Reg Vol | H4: reg Amt | I4: Unreg Vol | J4: Unreg Amt | K4: Total Vol | L4: Total Amt | M4: Payable | N4: TS Loss | O4: Loss Apportion | P4: CF Deduction | Q4: Deduction for excess payment | R4: Vet Deduction | S4: Advance | T4: Others | U4: Payment to Farmer A/c | V4: Unreg. Farmer payment | W4: Payment to MPGs A/c
A5: 20080001 | B5: CHATTI BHANDRA | C5: RMC | D5: Direct | E5: 2319.32 | F5: 90847.83 | G5: 2321.28 | H5: 90924.52 | I5: 0 | J5: 0 | K5: 2321.28 | L5: 90924.52 | M5: 90847.83 | N5: 0 | O5: 76.69 | P5: 0 | Q5: 0 | R5: 0 | S5: 0 | T5: 0 | U5: 90848 | V5: 0 | W5: 0
A6: 20080002 | B6: BHITTA | C6: MPG | D6: Direct | E6: 716.42 | F6: 26490 | G6: 667.83 | H6: 26368.88 | I6: 0 | J6: 0 | K6: 667.83 | L6: 26368.88 | M6: 26368.88 | N6: 0 | O6: 0 | P6: 0 | Q6: 0 | R6: 0 | S6: 0 | T6: 0 | U6: 26368 | V6: 0 | W6: 0
A7: 20080004 | B7: Guri | C7: MPG | D7: Direct | E7: 1078.76 | F7: 41168.59 | G7: 1070.32 | H7: 41879.62 | I7: 0 | J7: 0 | K7: 1070.32 | L7: 41879.62 | M7: 41168.59 | N7: 0 | O7: 711.03 | P7: 0 | Q7: 0 | R7: 0 | S7: 0 | T7: 0 | U7: 41169 | V7: 0 | W7: 0
A8: 20080006 | B8: Chitri Ambatoli | C8: MPG | D8: Direct | E8: 1319 | F8: 50885.38 | G8: 1315.65 | H8: 50184.82 | I8: 0 | J8: 0 | K8: 1315.65 | L8: 50184.82 | M8: 50184.82 | N8: 0 | O8: 0 | P8: 0 | Q8: 0 | R8: 0 | S8: 0 | T8: 0 | U8: 50185 | V8: 0 | W8: 0
A9: 20080007 | B9: Rampur | C9: MPG | D9: Direct | E9: 3167.38 | F9: 117245.44 | G9: 3074.06 | H9: 119687.25 | I9: 0 | J9: 0 | K9: 3074.06 | L9: 119687.25 | M9: 117245.44 | N9: 0 | O9: 2441.81 | P9: 0 | Q9: 0 | R9: 0 | S9: 0 | T9: 0 | U9: 117245 | V9: 0 | W9: 0
A10: 20080009 | B10: MASHMANO | C10: MPG | D10: Direct | E10: 572.62 | F10: 21331.24 | G10: 555.01 | H10: 21280.09 | I10: 0 | J10: 0 | K10: 555.01 | L10: 21280.09 | M10: 21280.09 | N10: 0 | O10: 0 | P10: 0 | Q10: 0 | R10: 0 | S10: 0 | T10: 0 | U10: 21280 | V10: 0 | W10: 0
A11: 20080010 | B11: PAHARKESA | C11: MPG | D11: Direct | E11: 527.34 | F11: 22181.72 | G11: 527.59 | H11: 22590.77 | I11: 0 | J11: 0 | K11: 527.59 | L11: 22590.77 | M11: 22181.72 | N11: 0 | O11: 409.05 | P11: 0 | Q11: 0 | R11: 0 | S11: 0 | T11: 0 | U11: 22182 | V11: 0 | W11: 0
A12: 20080014 | B12: BHUJANIYA | C12: MPG | D12: Indirect | E12: 440.56 | F12: 15917.16 | G12: 0 | H12: 0 | I12: 0 | J12: 0 | K12: 0 | L12: 0 | M12: 15917.16 | N12: 0 | O12: 0 | P12: 0 | Q12: 0 | R12: 0 | S12: 0 | T12: 0 | U12: 0 | V12: 0 | W12: 15917.16
A13: 20080025 | B13: DAARU | C13: MPG | D13: Indirect | E13: 480.88 | F13: 16849.43 | G13: 0 | H13: 0 | I13: 0 | J13: 0 | K13: 0 | L13: 0 | M13: 16849.43 | N13: 0 | O13: 0 | P13: 0 | Q13: 0 | R13: 0 | S13: 0 | T13: 0 | U13: 0 | V13: 0 | W13: 16849.43
A14: 20080026 | B14: CHHARDA | C14: MPG | D14: Direct | E14: 259.18 | F14: 9779.77 | G14: 266.52 | H14: 10129.94 | I14: 0 | J14: 0 | K14: 266.52 | L14: 10129.94 | M14: 9779.77 | N14: 0 | O14: 350.17 | P14: 0 | Q14: 0 | R14: 0 | S14: 0 | T14: 0 | U14: 9780 | V14: 0 | W14: 0
A15: 20080008 | B15: Ningni | C15: MPG | D15: Direct | E15: 863.96 | F15: 32771.31 | G15: 868.77 | H15: 32717.48 | I15: 0 | J15: 0 | K15: 868.77 | L15: 32717.48 | M15: 32717.48 | N15: 0 | O15: 0 | P15: 0 | Q15: 0 | R15: 0 | S15: 0 | T15: 0 | U15: 32717 | V15: 0 | W15: 0
A16: 20080028 | B16: BASRI NAGRA | C16: MPG | D16: Direct | E16: 211.42 | F16: 8947.19 | G16: 211.99 | H16: 8854.91 | I16: 0 | J16: 0 | K16: 211.99 | L16: 8854.91 | M16: 8854.91 | N16: 0 | O16: 0 | P16: 0 | Q16: 0 | R16: 0 | S16: 0 | T16: 0 | U16: 8855 | V16: 0 | W16: 0
... A27: 20080050 | B27: KACHMACHI 2 | C27: MPG | D27: Direct | E27: 225.04 | F27: 8504 | G27: 225.09 | H27: 8457.55 | I27: 0 | J27: 0 | K27: 225.09 | L27: 8457.55 | M27: 8457.55 | N27: 0 | O27: 0 | P27: 0 | Q27: 0 | R27: 0 | S27: 0 | T27: 0 | U27: 8457 | V27: 0 | W27: 0
A28: Grand Total | E28: 16523.04 | F28: 634420.81 | G28: 14367.58 | H28: 566072.16 | I28: 0 | J28: 0 | K28: 14367.58 | L28: 566072.16 | M28: 633161.89 | N28: 0 | O28: 16977.26 | P28: 0 | Q28: 0 | R28: 0 | S28: 0 | T28: 0 | U28: 549094 | V28: 0 | W28: 84066.99

Sheet Farmer PDF
A1: BMC Area | B1: (All)
A2: Category | B2: Direct | C2: Payment cycle-08th to 14th May'26
F4: Values
A5: Code | B5: Farmers Code | C5: Farmers Account Name | D5: Accont no | E5: IFSC code | F5: Vol_L | G5: Amount | H5: TS Loss | I5: CF Deduction | J5: Vet Deduction | K5: Deduction for excess Payment | L5: Milk Short | M5: Net Amount
A6: 20010001 | B6: 0002 | C6: AMIT KUMAR TIWARI | D6: 7125658980 | E6: IDIB000I021 | F6: 9769 | G6: 417636.15 | H6: 14964 | I6: 0 | J6: 0 | K6: 0 | L6: 0 | M6: 402672
A7: 20010001 | B7: 0004 | C7: BIRSA ORAON | D7: 358702010006943 | E7: UBIN0535877 | F7: 21.58 | G7: 1026.4586 | H7: 0 | I7: 0 | J7: 0 | K7: 0 | L7: 0 | M7: 1026
A8: 20010001 | B8: 0010 | C8: SHANTI DEVI | D8: 6496430309 | E8: IDIB000I021 | F8: 58.76 | G8: 2666.0376 | H8: 0 | I8: 0 | J8: 0 | K8: 0 | L8: 0 | M8: 2666
A9: 20010001 | B9: 0016 | C9: Suko Tirki | D9: 7100914953 | E9: IDIB000I021 | F9: 27.04 | G9: 1148.0662 | H9: 0 | I9: 0 | J9: 0 | K9: 0 | L9: 0 | M9: 1148
A10: 20010001 | B10: 0017 | C10: Bikram Gope | D10: 358702010006937 | E10: UBIN0535877 | F10: 17.98 | G10: 769.6052 | H10: 0 | I10: 0 | J10: 0 | K10: 0 | L10: 0 | M10: 770
A11: 20010001 | B11: 0019 | C11: Hiramani Kachhap | D11: 494310110016645 | E11: BKID0004943 | F11: 37.3 | G11: 1471.0452 | H11: 0 | I11: 0 | J11: 0 | K11: 0 | L11: 0 | M11: 1471
A12: 20010001 | B12: 0046 | C12: DHANI MAHALI | D12: 358702010628606 | E12: UBIN0535877 | F12: 53.26 | G12: 2076.4026 | H12: 0 | I12: 0 | J12: 0 | K12: 0 | L12: 0 | M12: 2076
A13: 20010001 | B13: 0047 | C13: Kusum Tirki | D13: 6511075905 | E13: IDIB000I021 | F13: 27.6 | G13: 1065.9122 | H13: 0 | I13: 0 | J13: 0 | K13: 0 | L13: 0 | M13: 1066
A14: 20010001 | B14: 0048 | C14: Anil Tirki | D14: 358702010004453 | E14: UBIN0535877 | F14: 37.54 | G14: 1563.155 | H14: 0 | I14: 0 | J14: 0 | K14: 0 | L14: 0 | M14: 1563
A15: 20010001 | B15: 0050 | C15: SABITA TIWARI | D15: 762901500038 | E15: ICIC0007629 | F15: 140 | G15: 5681.6 | H15: 0 | I15: 0 | J15: 0 | K15: 0 | L15: 0 | M15: 5682
A16: 20010001 | B16: 0051 | C16: SAHIL RAJ | D16: 40723769931 | E16: SBIN0000081 | F16: 72 | G16: 2923.55 | H16: 0 | I16: 0 | J16: 0 | K16: 0 | L16: 0 | M16: 2924
A17: 20010001 | B17: 0064 | C17: SOHEL ANSARI | D17: 358702120002626 | E17: UBIN0535877 | F17: 54.8 | G17: 2449.294 | H17: 0 | I17: 0 | J17: 0 | K17: 0 | L17: 0 | M17: 2449
... A26: 20010001 | B26: 0082 | C26: CHANDRA CHUDAMANI PATHAK | D26: 59103904965996 | E26: HDFC0008691 | F26: 804.94 | G26: 32214.236 | H26: 0 | I26: 0 | J26: 0 | K26: 0 | L26: 0 | M26: 32214
A27: 20010001 Total | F27: 11528.02 | G27: 489944.47 | H27: 14964 | I27: 0 | J27: 0 | K27: 0 | L27: 0 | M27: 474980
A28: 20010003 | B28: 0003 | C28: PINKI DEVI | D28: 4895101003786 | E28: CNRB0004895 | F28: 1183.71 | G28: 47883.822 | H28: 0 | I28: 7620 | J28: 0 | K28: 0 | L28: 20 | M28: 40244
A29: 20010003 | B29: 0013 | C29: JOSEF LAKRA | D29: 495910510003202 | E29: BKID0004959 | F29: 38.9 | G29: 1877.992 | H29: 0 | I29: 0 | J29: 0 | K29: 0 | L29: 500 | M29: 1378
A30: 20010003 | B30: 0026 | C30: Pankaj Tigga | D30: 41383270689 | E30: SBIN0012618 | F30: 31.96 | G30: 1303.1576 | H30: 0 | I30: 1270 | J30: 0 | K30: 0 | L30: 33 | M30: 0
A31: 20010003 | B31: 0044 | C31: Manju Devi | D31: 08030100922544 | E31: UCBA0000803 | F31: 23.45 | G31: 1011.0627 | H31: 0 | I31: 0 | J31: 0 | K31: 0 | L31: 200 | M31: 811
A32: 20010003 | B32: 0077 | C32: PUNAM SINHA | D32: 495910100000166 | E32: BKID0004959 | F32: 5.35 | G32: 242.203 | H32: 0 | I32: 0 | J32: 0 | K32: 0 | L32: 0 | M32: 242
A33: 20010003 | B33: 0080 | C33: GEETA TANA BHAGTAIN | D33: 08033211029311 | E33: UCBA0000803 | F33: 8.22 | G33: 447.5265 | H33: 0 | I33: 0 | J33: 0 | K33: 0 | L33: 0 | M33: 448
A34: 20010003 | B34: 0105 | C34: SUKA TANA BHAGAT | D34: 08030100921195 | E34: UCBA0000803 | F34: 11.73 | G34: 569.2787 | H34: 0 | I34: 0 | J34: 0 | K34: 0 | L34: 426 | M34: 143
A35: 20010003 | B35: 0112 | C35: BANDE ORAON | D35: 495910510003218 | E35: BKID0004959 | F35: 40.63 | G35: 2002.2369 | H35: 0 | I35: 0 | J35: 0 | K35: 0 | L35: 300 | M35: 1702
A36: 20010003 | B36: 0116 | C36: ANITA DEVI | D36: 495918210005225 | E36: BKID0004959 | F36: 37.32 | G36: 1602.0912 | H36: 0 | I36: 1270 | J36: 0 | K36: 0 | L36: 0 | M36: 332
A37: 20010003 | B37: 0115 | C37: SUNITA KUMARI | D37: 110048432290 | E37: CNRB0004895 | F37: 15.77 | G37: 717.9342 | H37: 0 | I37: 0 | J37: 0 | K37: 0 | L37: 0 | M37: 718
A38: 20010003 Total | F38: 1397.04 | G38: 57657.305 | H38: 0 | I38: 10160 | J38: 0 | K38: 0 | L38: 1479 | M38: 46018
A39: 20010005 | B39: 0002 | C39: SAJJAD ANSARI | D39: 20421406720 | E39: SBIN0014340 | F39: 89.5 | G39: 3691.875 | H39: 0 | I39: 0 | J39: 0 | K39: 0 | L39: 0 | M39: 3692
A40: 20010005 | B40: 0005 | C40: MUNEJA KHATUN | D40: 494318210006630 | E40: BKID0004943 | F40: 47.37 | G40: 1864.3849 | H40: 0 | I40: 0 | J40: 0 | K40: 0 | L40: 0 | M40: 1864
A41: 20010005 | B41: 0008 | C41: ANISA KHATUN | D41: 50370873265 | E41: IDIB000N518 | F41: 35.21 | G41: 1504.7457 | H41: 0 | I41: 0 | J41: 0 | K41: 0 | L41: 0 | M41: 1505
A42: 20010005 | B42: 0009 | C42: RABUL ANSARI | D42: 494318210000448 | E42: BKID0004943 | F42: 51.19 | G42: 2129.8845 | H42: 0 | I42: 0 | J42: 0 | K42: 0 | L42: 0 | M42: 2130
A43: 20010005 | B43: 0011 | C43: EYASIN ANSARI | D43: 50363172838 | E43: IDIB000N518 | F43: 42.23 | G43: 2046.4712 | H43: 0 | I43: 0 | J43: 0 | K43: 0 | L43: 0 | M43: 2046
A44: 20010005 | B44: 0012 | C44: TAIRUN NISHA | D44: 371101000005005 | E44: IOBA0003711 | F44: 10.77 | G44: 513.242 | H44: 0 | I44: 0 | J44: 0 | K44: 0 | L44: 0 | M44: 513
A45: 20010005 | B45: 0014 | C45: SALIM ANSARI | D45: 494310110018804 | E45: BKID0004943 | F45: 52.81 | G45: 2472.5713 | H45: 0 | I45: 0 | J45: 0 | K45: 0 | L45: 0 | M45: 2473
A46: 20010005 | B46: 0016 | C46: ASIYA KHATOON | D46: 494318210006966 | E46: BKID0004943 | F46: 1.63 | G46: 64.5397 | H46: 0 | I46: 0 | J46: 0 | K46: 0 | L46: 0 | M46: 65
A47: 20010005 | B47: 0022 | C47: SHEIKH SAFIQUE | D47: 494310100000875 | E47: BKID0004943 | F47: 7.64 | G47: 278.2609 | H47: 0 | I47: 0 | J47: 0 | K47: 0 | L47: 0 | M47: 278
A48: 20010005 | B48: 0023 | C48: JOHRA KHATOON | D48: 50369500332 | E48: IDIB000N518 | F48: 24.88 | G48: 1007.5236 | H48: 0 | I48: 0 | J48: 0 | K48: 0 | L48: 0 | M48: 1008
A49: 20010005 | B49: 0029 | C49: IMAM ANSARI | D49: 494318210005769 | E49: BKID0004943 | F49: 19.35 | G49: 795.6549 | H49: 0 | I49: 0 | J49: 0 | K49: 0 | L49: 0 | M49: 796
A50: 20010005 | B50: 0033 | C50: Hamida Khatoon | D50: 39470934026 | E50: SBIN0014340 | F50: 22.14 | G50: 820.1015 | H50: 0 | I50: 0 | J50: 0 | K50: 0 | L50: 0 | M50: 820
... A61: 20010005 | B61: 0056 | C61: AFROJ ANSARI | D61: 490710110013111 | E61: BKID0004907 | F61: 71.97 | G61: 2735.4468 | H61: 0 | I61: 0 | J61: 0 | K61: 0 | L61: 0 | M61: 2735
A62: 20010005 Total | F62: 1352.05 | G62: 54956.825 | H62: 0 | I62: 0 | J62: 0 | K62: 0 | L62: 0 | M62: 54958
A63: 20010008 | B63: 0005 | C63: SANJAY SAHU | D63: 494310100013455 | E63: BKID0004943 | F63: 29.63 | G63: 1247.2893 | H63: 0 | I63: 0 | J63: 0 | K63: 0 | L63: 0 | M63: 1247
A64: 20010008 | B64: 0010 | C64: MAMITA KUMARI | D64: 371101000006331 | E64: IOBA0003711 | F64: 12.84 | G64: 445.0187 | H64: 0 | I64: 0 | J64: 0 | K64: 0 | L64: 0 | M64: 445
A65: 20010008 | B65: 0017 | C65: RAM JI SAHU | D65: 22016771417 | E65: SBIN0RRVCGB | F65: 74.11 | G65: 2762.9766 | H65: 0 | I65: 0 | J65: 0 | K65: 0 | L65: 0 | M65: 2763
A66: 20010008 | B66: 0024 | C66: Mila Devi | D66: 494318210000940 | E66: BKID0004943 | F66: 44.14 | G66: 2007.8533 | H66: 0 | I66: 0 | J66: 0 | K66: 0 | L66: 0 | M66: 2008
A67: 20010008 | B67: 0035 | C67: LALITA DEVI | D67: 22016772818 | E67: SBIN0RRVCGB | F67: 472.35 | G67: 19721.392 | H67: 0 | I67: 0 | J67: 0 | K67: 0 | L67: 0 | M67: 19721
A68: 20010008 | B68: 0040 | C68: Rekha Kumari | D68: 371101000006095 | E68: IOBA0003711 | F68: 9.31 | G68: 474.606 | H68: 0 | I68: 0 | J68: 0 | K68: 0 | L68: 0 | M68: 475
A69: 20010008 | B69: 0041 | C69: Giridhari Sahu | D69: 31955655087 | E69: SBIN0014340 | F69: 31.3 | G69: 1369.0595 | H69: 0 | I69: 0 | J69: 0 | K69: 0 | L69: 0 | M69: 1369
A70: 20010008 | B70: 0045 | C70: BASANT SAW | D70: 43418630101 | E70: SBIN0014340 | F70: 9.04 | G70: 380.4024 | H70: 0 | I70: 0 | J70: 0 | K70: 0 | L70: 0 | M70: 380
A71: 20010008 | B71: 0050 | C71: SURAJMANI TOPPO | D71: 494310110002155 | E71: BKID0004943 | F71: 26.51 | G71: 1230.6473 | H71: 0 | I71: 0 | J71: 0 | K71: 0 | L71: 0 | M71: 1231
A72: 20010008 | B72: 0053 | C72: RAMA TOPPO | D72: 494310100006318 | E72: BKID0004943 | F72: 13.3 | G72: 696.5886 | H72: 0 | I72: 0 | J72: 0 | K72: 0 | L72: 0 | M72: 697
A73: 20010008 | B73: 0055 | C73: NITU LAKRA | D73: 000110144776 | E73: IPOS0000001 | F73: 43.22 | G73: 1650.6031 | H73: 0 | I73: 0 | J73: 0 | K73: 0 | L73: 0 | M73: 1651
A74: 20010008 | B74: 0059 | C74: REKHA DEVI | D74: 84065679489 | E74: SBIN0RRVCGB | F74: 230.6 | G74: 9022.2713 | H74: 0 | I74: 0 | J74: 0 | K74: 0 | L74: 0 | M74: 9022
... A76: 20010008 | B76: 0061 | C76: SHANTI DEVI | D76: 33055486434 | E76: SBIN0014340 | F76: 95.35 | G76: 3574.2593 | H76: 0 | I76: 0 | J76: 0 | K76: 0 | L76: 0 | M76: 3574
A77: 20010008 Total | F77: 1185.43 | G77: 48571.347 | H77: 0 | I77: 0 | J77: 0 | K77: 0 | L77: 0 | M77: 48571
A78: 20010009 | B78: 0002 | C78: BAL KISHORE TIWARI | D78: 358702010009142 | E78: UBIN0535877 | F78: 56.88 | G78: 2277.0154 | H78: 0 | I78: 0 | J78: 0 | K78: 0 | L78: 0 | M78: 2277
A79: 20010009 | B79: 0016 | C79: BIRENDAR KUMAR GOPE | D79: 358702010626226 | E79: UBIN0535877 | F79: 182.28 | G79: 7741.1212 | H79: 0 | I79: 0 | J79: 0 | K79: 0 | L79: 0 | M79: 7741
A80: 20010009 | B80: 0017 | C80: PUSPA DEVI | D80: 50100184717426 | E80: HDFC0001470 | F80: 96.04 | G80: 3950.1017 | H80: 0 | I80: 0 | J80: 0 | K80: 0 | L80: 0 | M80: 3950
A81: 20010009 | B81: 0030 | C81: SUBHASH GOPE | D81: 7768139451 | E81: IDIB000I021 | F81: 188.99 | G81: 7923.5784 | H81: 0 | I81: 0 | J81: 0 | K81: 0 | L81: 0 | M81: 7924
A82: 20010009 | B82: 0031 | C82: MAMTA DEVI | D82: 589510110004327 | E82: BKID0005895 | F82: 56.54 | G82: 2361.2821 | H82: 0 | I82: 0 | J82: 0 | K82: 0 | L82: 0 | M82: 2361
A83: 20010009 | B83: 0032 | C83: REENA KUMARI | D83: 490218210000253 | E83: BKID0004902 | F83: 45.63 | G83: 1905.6502 | H83: 0 | I83: 0 | J83: 0 | K83: 0 | L83: 0 | M83: 1906
A84: 20010009 | B84: 0034 | C84: SOMESH GOPE | D84: 358702010629551 | E84: UBIN0535877 | F84: 25.12 | G84: 1019.5985 | H84: 0 | I84: 0 | J84: 0 | K84: 0 | L84: 0 | M84: 1020
A85: 20010009 Total | F85: 651.48 | G85: 27178.347 | H85: 0 | I85: 0 | J85: 0 | K85: 0 | L85: 0 | M85: 27179
A86: 20010015 | B86: 0003 | C86: Manga Bhagat | D86: 358702010612721 | E86: UBIN0535877 | F86: 4 | G86: 165.56 | H86: 0 | I86: 0 | J86: 0 | K86: 0 | L86: 0 | M86: 166
A87: 20010015 | B87: 0006 | C87: Shkila Khatoon | D87: 358702010614868 | E87: UBIN0535877 | F87: 20.48 | G87: 825.4914 | H87: 0 | I87: 0 | J87: 0 | K87: 0 | L87: 0 | M87: 825
A88: 20010015 | B88: 0013 | C88: Shashi Kala Urain | D88: 6443192285 | E88: IDIB000I021 | F88: 64.81 | G88: 2723.6595 | H88: 0 | I88: 0 | J88: 0 | K88: 0 | L88: 0 | M88: 2724
A89: 20010015 | B89: 0014 | C89: Putun Devi | D89: 358702120002678 | E89: UBIN0535877 | F89: 70.14 | G89: 3043.5703 | H89: 0 | I89: 0 | J89: 0 | K89: 0 | L89: 0 | M89: 3044
A90: 20010015 | B90: 0016 | C90: Evaren Khes | D90: 358702010605620 | E90: UBIN0535877 | F90: 42.68 | G90: 1927.1325 | H90: 0 | I90: 0 | J90: 0 | K90: 0 | L90: 0 | M90: 1927
A91: 20010015 | B91: 0017 | C91: Halima Khatoon | D91: 35769326327 | E91: SBIN0015346 | F91: 53.02 | G91: 2175.221 | H91: 0 | I91: 0 | J91: 0 | K91: 0 | L91: 0 | M91: 2175
A92: 20010015 | B92: 0021 | C92: Etwari Urain | D92: 6940856322 | E92: IDIB000I021 | F92: 50.38 | G92: 2046.3229 | H92: 0 | I92: 0 | J92: 0 | K92: 0 | L92: 0 | M92: 2046
A93: 20010015 | B93: 0022 | C93: Nejam Ansari | D93: 358702010612736 | E93: UBIN0535877 | F93: 13.89 | G93: 562.9346 | H93: 0 | I93: 0 | J93: 0 | K93: 0 | L93: 0 | M93: 563
A94: 20010015 | B94: 0024 | C94: Haidar Ansari | D94: 358702010603995 | E94: UBIN0535877 | F94: 5.76 | G94: 234.129 | H94: 0 | I94: 0 | J94: 0 | K94: 0 | L94: 0 | M94: 234
A95: 20010015 | B95: 0026 | C95: Jamahir Ansari | D95: 32449556244 | E95: SBIN0015346 | F95: 36.15 | G95: 1509.5489 | H95: 0 | I95: 0 | J95: 0 | K95: 0 | L95: 0 | M95: 1510
A96: 20010015 | B96: 0027 | C96: Shahid Ansari | D96: 7202563588 | E96: IDIB000I021 | F96: 73.3 | G96: 3022.2857 | H96: 0 | I96: 0 | J96: 0 | K96: 0 | L96: 0 | M96: 3022
A97: 20010015 | B97: 0028 | C97: Manita Khes | D97: 358702010005279 | E97: UBIN0535877 | F97: 46.62 | G97: 1898.4255 | H97: 0 | I97: 0 | J97: 0 | K97: 0 | L97: 0 | M97: 1898
... A138: 20010015 | B138: 0120 | C138: DULARI TOPPO | D138: 7416578560 | E138: IDIB000I021 | F138: 6.1 | G138: 251.783 | H138: 0 | I138: 0 | J138: 0 | K138: 0 | L138: 0 | M138: 252
A139: 20010015 Total | F139: 2579.38 | G139: 107851.96 | H139: 0 | I139: 0 | J139: 0 | K139: 0 | L139: 0 | M139: 107853
A140: 20010017 | B140: 0002 | C140: Suhail Hussain | D140: 9760000100022416 | E140: PUNB0976000 | F140: 169.04 | G140: 7490.8292 | H140: 0 | I140: 0 | J140: 0 | K140: 0 | L140: 395.28 | M140: 7096
A141: 20010017 | B141: 0010 | C141: Mahadev Minj | D141: 9760001700014250 | E141: PUNB0976000 | F141: 16.33 | G141: 841.5242 | H141: 0 | I141: 0 | J141: 0 | K141: 0 | L141: 0 | M141: 842
A142: 20010017 | B142: 0018 | C142: ANITA DEVI | D142: 495910510007136 | E142: BKID0004959 | F142: 18.81 | G142: 857.6571 | H142: 0 | I142: 0 | J142: 0 | K142: 0 | L142: 0 | M142: 858
A143: 20010017 | B143: 0020 | C143: Pyari Devi | D143: 495918210006595 | E143: BKID0004959 | F143: 6.82 | G143: 310.8392 | H143: 0 | I143: 0 | J143: 0 | K143: 0 | L143: 0 | M143: 311
A144: 20010017 | B144: 0025 | C144: ANITA DEVI | D144: 495910110006141 | E144: BKID0004959 | F144: 37.54 | G144: 1403.0564 | H144: 0 | I144: 0 | J144: 0 | K144: 0 | L144: 0 | M144: 1403
A145: 20010017 | B145: 0026 | C145: JAGAT PAL SAHU | D145: 08030100009205 | E145: UCBA0000803 | F145: 26.27 | G145: 1308.8734 | H145: 0 | I145: 0 | J145: 0 | K145: 0 | L145: 0 | M145: 1309
A146: 20010017 | B146: 0027 | C146: PANKAJ KHESS | D146: 495910510005882 | E146: BKID0004959 | F146: 10.77 | G146: 662.238 | H146: 0 | I146: 0 | J146: 0 | K146: 0 | L146: 0 | M146: 662
A147: 20010017 | B147: 0029 | C147: ISRAT PRAWEEN | D147: 9760001700028475 | E147: PUNB0976000 | F147: 11.6 | G147: 565.2456 | H147: 0 | I147: 0 | J147: 0 | K147: 0 | L147: 0 | M147: 565
A148: 20010017 | B148: 0030 | C148: AFJAL HUSSAIN | D148: 495918210007034 | E148: BKID0004959 | F148: 17.36 | G148: 675.0978 | H148: 0 | I148: 0 | J148: 0 | K148: 0 | L148: 0 | M148: 675
A149: 20010017 Total | F149: 314.54 | G149: 14115.361 | H149: 0 | I149: 0 | J149: 0 | K149: 0 | L149: 395.28 | M149: 13721
A150: 20010023 | B150: 0004 | C150: Somra Munda | D150: 371101000004289 | E150: IOBA0003711 | F150: 54.2 | G150: 2706.3362 | H150: 0 | I150: 0 | J150: 0 | K150: 0 | L150: 0 | M150: 2706
A151: 20010023 | B151: 0008 | C151: Lalo Munda | D151: 84032231436 | E151: SBIN0RRVCGB | F151: 31.82 | G151: 1667.718 | H151: 0 | I151: 0 | J151: 0 | K151: 0 | L151: 0 | M151: 1668
A152: 20010023 | B152: 0010 | C152: Sudama Gope | D152: 371101000002155 | E152: IOBA0003711 | F152: 8.22 | G152: 329.4634 | H152: 0 | I152: 0 | J152: 0 | K152: 0 | L152: 0 | M152: 329
A153: 20010023 | B153: 0011 | C153: Geeta Devi | D153: 22016749426 | E153: SBIN0RRVCGB | F153: 47.6 | G153: 1959.6806 | H153: 0 | I153: 0 | J153: 0 | K153: 0 | L153: 0 | M153: 1960
A154: 20010023 | B154: 0015 | C154: Charo Munda | D154: 494310100006547 | E154: BKID0004943 | F154: 39.07 | G154: 1781.7679 | H154: 0 | I154: 0 | J154: 0 | K154: 0 | L154: 0 | M154: 1782
A155: 20010023 | B155: 0016 | C155: Rani Devi | D155: 494310110014797 | E155: BKID0004943 | F155: 54.51 | G155: 2282.3886 | H155: 0 | I155: 0 | J155: 0 | K155: 0 | L155: 0 | M155: 2282
A156: 20010023 | B156: 0021 | C156: Dhaneshwar Gop | D156: 494310110002166 | E156: BKID0004943 | F156: 75.65 | G156: 3098.7116 | H156: 0 | I156: 0 | J156: 0 | K156: 0 | L156: 0 | M156: 3099
A157: 20010023 | B157: 0023 | C157: Shani Munda | D157: 7203940137 | E157: IDIB000N518 | F157: 61.76 | G157: 2653.8508 | H157: 0 | I157: 0 | J157: 0 | K157: 0 | L157: 0 | M157: 2654
A158: 20010023 | B158: 0024 | C158: Rupan Devi | D158: 494310110016123 | E158: BKID0004943 | F158: 33.93 | G158: 1371.7776 | H158: 0 | I158: 0 | J158: 0 | K158: 0 | L158: 0 | M158: 1372
A159: 20010023 | B159: 0026 | C159: Rajesh Gop | D159: 494318210002779 | E159: BKID0004943 | F159: 68.47 | G159: 3983.4398 | H159: 0 | I159: 0 | J159: 0 | K159: 0 | L159: 0 | M159: 3983
A160: 20010023 | B160: 0027 | C160: Chhoti Devi | D160: 371101000005125 | E160: IOBA0003711 | F160: 14.7 | G160: 604.2096 | H160: 0 | I160: 0 | J160: 0 | K160: 0 | L160: 0 | M160: 604
...

Sheet MPG Performance
I1: 8 | O1: -0.1 | P1: -0.03 | S1: 201
A2: BMC Code | B2: MPG Code | C2: MPG NAME | D2: Type | E2: Farmer Payment | F2: MPG Start Date | G2: Vol Ltr/Day | H2: Nos Of Farmer | I2: Avg pouring/farmer | J2: Total MPG Pouring Shift | K2: Manual Shift | L2: Assets Value | M2: Ideal Sample | N2: Actual Sample | O2: Sample Diff % | P2: MPG Loss/Gain% | Q2: CF Sales | R2: MPG Cow% | S2: BMC Cow% | T2: Diff
A3: ='MPG Payment'!A4 -> BMC Code :2001 | B3: ='MPG Payment'!B4 -> 20010001 | C3: ='MPG Payment'!C4 -> Itki | D3: ='MPG Payment'!D4 -> RMC | E3: ='MPG Payment'!E4 -> Direct | G3: ='MPG Payment'!F4/3 -> 3842.6533 | H3: =COUNTIF('Farmer Payment Calc'!D:D,'MPG Performance'!B3) -> 21 | I3: =IFERROR(G3/J3/H3*2,0) -> 26.140499 | J3: 14 | K3: 0 | L3: ='MPG Payment'!#REF! -> #REF! | M3: =SUMIF('Farmer Payment Calc'!D:D,'MPG Performance'!B3,'Farmer Payment Calc'!Y:Y) -> 414.68119 | N3: ='MPG Payment'!P4 -> 0 | O3: =IFERROR(N3-M3/M3,0) -> -1 | P3: ='MPG Payment'!AB4 -> -5.6474231e-05 | Q3: ='MPG Payment'!R4 -> 0 | R3: 0.6416872 | S3: 0.63564064 | T3: =R3-S3 -> 0.0060465611
A4: ='MPG Payment'!A5 -> BMC Code :2001 | B4: ='MPG Payment'!B5 -> 20010002 | C4: ='MPG Payment'!C5 -> Jamtoli | D4: ='MPG Payment'!D5 -> MPG | E4: ='MPG Payment'!E5 -> Direct | G4: ='MPG Payment'!F5/3 -> 4.3933333 | H4: =COUNTIF('Farmer Payment Calc'!D:D,'MPG Performance'!B4) -> 1 | I4: =IFERROR(G4/J4/H4*2,0) -> 0.9762963 | J4: 9 | K4: 0 | L4: ='MPG Payment'!#REF! -> #REF! | M4: =SUMIF('Farmer Payment Calc'!D:D,'MPG Performance'!B4,'Farmer Payment Calc'!Y:Y) -> 2.0625 | N4: ='MPG Payment'!P5 -> 0 | O4: =IFERROR(N4-M4/M4,0) -> -1 | P4: ='MPG Payment'!AB5 -> -0.0067421141 | Q4: ='MPG Payment'!R5 -> 0 | R4: 0.74174054 | S4: 1 | T4: =R4-S4 -> -0.25825946
A5: ='MPG Payment'!A6 -> BMC Code :2001 | B5: ='MPG Payment'!B6 -> 20010003 | C5: ='MPG Payment'!C6 -> Bero | D5: ='MPG Payment'!D6 -> MPG | E5: ='MPG Payment'!E6 -> Direct | G5: ='MPG Payment'!F6/3 -> 462.39 | H5: =COUNTIF('Farmer Payment Calc'!D:D,'MPG Performance'!B5) -> 10 | I5: =IFERROR(G5/J5/H5*2,0) -> 6.6055714 | J5: 14 | K5: 0 | L5: ='MPG Payment'!#REF! -> #REF! | M5: =SUMIF('Farmer Payment Calc'!D:D,'MPG Performance'!B5,'Farmer Payment Calc'!Y:Y) -> 135.28572 | N5: ='MPG Payment'!P6 -> 0 | O5: =IFERROR(N5-M5/M5,0) -> -1 | P5: ='MPG Payment'!AB6 -> 0.026332821 | Q5: ='MPG Payment'!R6 -> 10160 | R5: 0.6664974 | S5: 0.79953999 | T5: =R5-S5 -> -0.13304259
A6: ='MPG Payment'!A7 -> BMC Code :2001 | B6: ='MPG Payment'!B7 -> 20010005 | C6: ='MPG Payment'!C7 -> Basila | D6: ='MPG Payment'!D7 -> MPG | E6: ='MPG Payment'!E7 -> Direct | G6: ='MPG Payment'!F7/3 -> 458.14 | H6: =COUNTIF('Farmer Payment Calc'!D:D,'MPG Performance'!B6) -> 23 | I6: =IFERROR(G6/J6/H6*2,0) -> 2.8455901 | J6: 14 | K6: 0 | L6: ='MPG Payment'!#REF! -> #REF! | M6: =SUMIF('Farmer Payment Calc'!D:D,'MPG Performance'!B6,'Farmer Payment Calc'!Y:Y) -> 458.55773 | N6: ='MPG Payment'!P7 -> 0 | O6: =IFERROR(N6-M6/M6,0) -> -1 | P6: ='MPG Payment'!AB7 -> -0.00029442448 | Q6: ='MPG Payment'!R7 -> 0 | R6: 0.89433589 | S6: 1 | T6: =R6-S6 -> -0.10566411
A7: ='MPG Payment'!A8 -> BMC Code :2001 | B7: ='MPG Payment'!B8 -> 20010008 | C7: ='MPG Payment'!C8 -> Erchoro | D7: ='MPG Payment'!D8 -> MPG | E7: ='MPG Payment'!E8 -> Direct | G7: ='MPG Payment'!F8/3 -> 405.30667 | H7: =COUNTIF('Farmer Payment Calc'!D:D,'MPG Performance'!B7) -> 14 | I7: =IFERROR(G7/J7/H7*2,0) -> 4.8250794 | J7: 12 | K7: 0 | L7: ='MPG Payment'!#REF! -> #REF! | M7: =SUMIF('Farmer Payment Calc'!D:D,'MPG Performance'!B7,'Farmer Payment Calc'!Y:Y) -> 270.92325 | N7: ='MPG Payment'!P8 -> 0 | O7: =IFERROR(N7-M7/M7,0) -> -1 | P7: ='MPG Payment'!AB8 -> -0.0010467041 | Q7: ='MPG Payment'!R8 -> 0 | R7: 0.5160694 | S7: 0.61848838 | T7: =R7-S7 -> -0.10241898
A8: ='MPG Payment'!A9 -> BMC Code :2001 | B8: ='MPG Payment'!B9 -> 20010009 | C8: ='MPG Payment'!C9 -> Makunda | D8: ='MPG Payment'!D9 -> MPG | E8: ='MPG Payment'!E9 -> Direct | G8: ='MPG Payment'!F9/3 -> 214.81333 | H8: =COUNTIF('Farmer Payment Calc'!D:D,'MPG Performance'!B8) -> 7 | I8: =IFERROR(G8/J8/H8*2,0) -> 4.7211722 | J8: 13 | K8: 0 | L8: ='MPG Payment'!#REF! -> #REF! | M8: =SUMIF('Farmer Payment Calc'!D:D,'MPG Performance'!B8,'Farmer Payment Calc'!Y:Y) -> 147.59644 | N8: ='MPG Payment'!P9 -> 0 | O8: =IFERROR(N8-M8/M8,0) -> -1 | P8: ='MPG Payment'!AB9 -> -0.0016325476 | Q8: ='MPG Payment'!R9 -> 0 | R8: 0 | S8: 0.88561644 | T8: =R8-S8 -> -0.88561644
A9: ='MPG Payment'!A10 -> BMC Code :2001 | B9: ='MPG Payment'!B10 -> 20010012 | C9: ='MPG Payment'!C10 -> NAGRI | D9: ='MPG Payment'!D10 -> VLC | E9: ='MPG Payment'!E10 -> Indirect | G9: ='MPG Payment'!F10/3 -> 92.166667 | H9: =COUNTIF('Farmer Payment Calc'!D:D,'MPG Performance'!B9) -> 0 | I9: =IFERROR(G9/J9/H9*2,0) -> 0 | J9: 14 | K9: 0 | L9: ='MPG Payment'!#REF! -> #REF! | M9: =SUMIF('Farmer Payment Calc'!D:D,'MPG Performance'!B9,'Farmer Payment Calc'!Y:Y) -> 0 | N9: ='MPG Payment'!P10 -> 0 | O9: =IFERROR(N9-M9/M9,0) -> 0 | P9: ='MPG Payment'!AB10 -> -1 | Q9: ='MPG Payment'!R10 -> 0 | R9: 0.82014661 | S9: 0.957239 | T9: =R9-S9 -> -0.13709239
A10: ='MPG Payment'!A11 -> BMC Code :2001 | B10: ='MPG Payment'!B11 -> 20010015 | C10: ='MPG Payment'!C11 -> BOREYA | D10: ='MPG Payment'!D11 -> MPG | E10: ='MPG Payment'!E11 -> Direct | G10: ='MPG Payment'!F11/3 -> 887.1 | H10: =COUNTIF('Farmer Payment Calc'!D:D,'MPG Performance'!B10) -> 53 | I10: =IFERROR(G10/J10/H10*2,0) -> 4.7822102 | J10: 7 | K10: 0 | L10: ='MPG Payment'!#REF! -> #REF! | M10: =SUMIF('Farmer Payment Calc'!D:D,'MPG Performance'!B10,'Farmer Payment Calc'!Y:Y) -> 1123.5397 | N10: ='MPG Payment'!P11 -> 0 | O10: =IFERROR(N10-M10/M10,0) -> -1 | P10: ='MPG Payment'!AB11 -> -0.0029764747 | Q10: ='MPG Payment'!R11 -> 0 | R10: 0.6066686 | S10: 0.86905567 | T10: =R10-S10 -> -0.26238707
A11: ='MPG Payment'!A12 -> BMC Code :2001 | B11: ='MPG Payment'!B12 -> 20010017 | C11: ='MPG Payment'!C12 -> DIGHIYA | D11: ='MPG Payment'!D12 -> MPG | E11: ='MPG Payment'!E12 -> Direct | G11: ='MPG Payment'!F12/3 -> 107.75333 | H11: =COUNTIF('Farmer Payment Calc'!D:D,'MPG Performance'!B11) -> 9 | I11: =IFERROR(G11/J11/H11*2,0) -> 1.7103704 | J11: 14 | K11: 0 | L11: ='MPG Payment'!#REF! -> #REF! | M11: =SUMIF('Farmer Payment Calc'!D:D,'MPG Performance'!B11,'Farmer Payment Calc'!Y:Y) -> 137.90864 | N11: ='MPG Payment'!P12 -> 0 | O11: =IFERROR(N11-M11/M11,0) -> -1 | P11: ='MPG Payment'!AB12 -> 0.028762405 | Q11: ='MPG Payment'!R12 -> 0 | R11: 0.80666745 | S11: 1 | T11: =R11-S11 -> -0.19333255
A12: ='MPG Payment'!A13 -> BMC Code :2001 | B12: ='MPG Payment'!B13 -> 20010023 | C12: ='MPG Payment'!C13 -> KATARPA | D12: ='MPG Payment'!D13 -> MPG | E12: ='MPG Payment'!E13 -> Direct | G12: ='MPG Payment'!F13/3 -> 272.72667 | H12: =COUNTIF('Farmer Payment Calc'!D:D,'MPG Performance'!B12) -> 22 | I12: =IFERROR(G12/J12/H12*2,0) -> 1.7709524 | J12: 14 | K12: 0 | L12: ='MPG Payment'!#REF! -> #REF! | M12: =SUMIF('Farmer Payment Calc'!D:D,'MPG Performance'!B12,'Farmer Payment Calc'!Y:Y) -> 488.37975 | N12: ='MPG Payment'!P13 -> 0 | O12: =IFERROR(N12-M12/M12,0) -> -1 | P12: ='MPG Payment'!AB13 -> -0.00092754711 | Q12: ='MPG Payment'!R13 -> 0 | R12: 0.41330465 | S12: 0.3946809 | T12: =R12-S12 -> 0.018623749
A13: ='MPG Payment'!A14 -> BMC Code :2001 | B13: ='MPG Payment'!B14 -> 20010027 | C13: ='MPG Payment'!C14 -> MURTO | D13: ='MPG Payment'!D14 -> MPG | E13: ='MPG Payment'!E14 -> Direct | G13: ='MPG Payment'!F14/3 -> 101.16667 | H13: =COUNTIF('Farmer Payment Calc'!D:D,'MPG Performance'!B13) -> 10 | I13: =IFERROR(G13/J13/H13*2,0) -> 1.4452381 | J13: 14 | K13: 0 | L13: ='MPG Payment'!#REF! -> #REF! | M13: =SUMIF('Farmer Payment Calc'!D:D,'MPG Performance'!B13,'Farmer Payment Calc'!Y:Y) -> 186.32317 | N13: ='MPG Payment'!P14 -> 0 | O13: =IFERROR(N13-M13/M13,0) -> -1 | P13: ='MPG Payment'!AB14 -> -0.002747345 | Q13: ='MPG Payment'!R14 -> 0 | R13: 0.43230464 | S13: 0.022246663 | T13: =R13-S13 -> 0.41005798
A14: ='MPG Payment'!A15 -> BMC Code :2001 | B14: ='MPG Payment'!B15 -> 20010033 | C14: ='MPG Payment'!C15 -> KHATRIKHATANGA | D14: ='MPG Payment'!D15 -> MPG | E14: ='MPG Payment'!E15 -> Direct | G14: ='MPG Payment'!F15/3 -> 123.14667 | H14: =COUNTIF('Farmer Payment Calc'!D:D,'MPG Performance'!B14) -> 2 | I14: =IFERROR(G14/J14/H14*2,0) -> 8.7961905 | J14: 14 | K14: 0 | L14: ='MPG Payment'!#REF! -> #REF! | M14: =SUMIF('Farmer Payment Calc'!D:D,'MPG Performance'!B14,'Farmer Payment Calc'!Y:Y) -> 66.261054 | N14: ='MPG Payment'!P15 -> 0 | O14: =IFERROR(N14-M14/M14,0) -> -1 | P14: ='MPG Payment'!AB15 -> 0.021549177 | Q14: ='MPG Payment'!R15 -> 0 | R14: 0.64557696 | S14: 0.65580318 | T14: =R14-S14 -> -0.010226216
... A113: ='MPG Payment'!A114 -> BMC Code :2008 | B113: ='MPG Payment'!B114 -> 20080043 | C113: ='MPG Payment'!C114 -> JATARGARI | D113: ='MPG Payment'!D114 -> MPG | E113: ='MPG Payment'!E114 -> Direct | G113: ='MPG Payment'!F114/3 -> 173.79333 | H113: =COUNTIF('Farmer Payment Calc'!D:D,'MPG Performance'!B113) -> 6 | I113: =IFERROR(G113/J113/H113*2,0) -> 4.1379365 | J113: 14 | K113: 0 | L113: ='MPG Payment'!#REF! -> #REF! | M113: =SUMIF('Farmer Payment Calc'!D:D,'MPG Performance'!B113,'Farmer Payment Calc'!Y:Y) -> 90.181117 | N113: ='MPG Payment'!P114 -> 0 | O113: =IFERROR(N113-M113/M113,0) -> -1 | P113: ='MPG Payment'!AB114 -> -0.013117846 | Q113: ='MPG Payment'!R114 -> 0 | R113: 0.96104746 | S113: 0.96104746 | T113: =R113-S113 -> 0
A114: ='MPG Payment'!A120 -> BMC Code :2009 | B114: ='MPG Payment'!B120 -> 20090010 | C114: ='MPG Payment'!C120 -> CHATWAL | D114: ='MPG Payment'!D120 -> VLC | E114: ='MPG Payment'!E120 -> Indirect | G114: ='MPG Payment'!F120/3 -> 140.9 | H114: =COUNTIF('Farmer Payment Calc'!D:D,'MPG Performance'!B114) -> 0 | I114: =IFERROR(G114/J114/H114*2,0) -> 0 | J114: 14 | K114: 0 | L114: ='MPG Payment'!#REF! -> #REF! | M114: =SUMIF('Farmer Payment Calc'!D:D,'MPG Performance'!B114,'Farmer Payment Calc'!Y:Y) -> 0 | N114: ='MPG Payment'!P120 -> 0 | O114: =IFERROR(N114-M114/M114,0) -> 0 | P114: ='MPG Payment'!AB120 -> -1 | Q114: ='MPG Payment'!R120 -> 0 | R114: 0.91697902 | S114: 1 | T114: =R114-S114 -> -0.083020981
A115: ='MPG Payment'!#REF! -> #REF! | B115: ='MPG Payment'!#REF! -> #REF! | C115: ='MPG Payment'!#REF! -> #REF! | D115: ='MPG Payment'!#REF! -> #REF! | E115: ='MPG Payment'!#REF! -> #REF! | G115: ='MPG Payment'!#REF!/3 -> #REF! | H115: =COUNTIF('Farmer Payment Calc'!D:D,'MPG Performance'!B115) -> 0 | I115: =IFERROR(G115/J115/H115*2,0) -> 0 | J115: 14 | K115: 0 | L115: ='MPG Payment'!#REF! -> #REF! | M115: =SUMIF('Farmer Payment Calc'!D:D,'MPG Performance'!B115,'Farmer Payment Calc'!Y:Y) -> 0 | N115: ='MPG Payment'!#REF! -> #REF! | O115: =IFERROR(N115-M115/M115,0) -> 0 | P115: ='MPG Payment'!#REF! -> #REF! | Q115: ='MPG Payment'!#REF! -> #REF! | R115: 0.57014451 | S115: 0.92219629 | T115: =R115-S115 -> -0.35205178
A116: ='MPG Payment'!#REF! -> #REF! | B116: ='MPG Payment'!#REF! -> #REF! | C116: ='MPG Payment'!#REF! -> #REF! | D116: ='MPG Payment'!#REF! -> #REF! | E116: ='MPG Payment'!#REF! -> #REF! | G116: ='MPG Payment'!#REF!/3 -> #REF! | H116: =COUNTIF('Farmer Payment Calc'!D:D,'MPG Performance'!B116) -> 0 | I116: =IFERROR(G116/J116/H116*2,0) -> 0 | J116: 14 | K116: 0 | L116: ='MPG Payment'!#REF! -> #REF! | M116: =SUMIF('Farmer Payment Calc'!D:D,'MPG Performance'!B116,'Farmer Payment Calc'!Y:Y) -> 0 | N116: ='MPG Payment'!#REF! -> #REF! | O116: =IFERROR(N116-M116/M116,0) -> 0 | P116: ='MPG Payment'!#REF! -> #REF! | Q116: ='MPG Payment'!#REF! -> #REF! | R116: 0.48514731 | S116: 1 | T116: =R116-S116 -> -0.51485269
A117: ='MPG Payment'!#REF! -> #REF! | B117: ='MPG Payment'!#REF! -> #REF! | C117: ='MPG Payment'!#REF! -> #REF! | D117: ='MPG Payment'!#REF! -> #REF! | E117: ='MPG Payment'!#REF! -> #REF! | G117: ='MPG Payment'!#REF!/3 -> #REF! | H117: =COUNTIF('Farmer Payment Calc'!D:D,'MPG Performance'!B117) -> 0 | I117: =IFERROR(G117/J117/H117*2,0) -> 0 | J117: 14 | K117: 0 | L117: ='MPG Payment'!#REF! -> #REF! | M117: =SUMIF('Farmer Payment Calc'!D:D,'MPG Performance'!B117,'Farmer Payment Calc'!Y:Y) -> 0 | N117: ='MPG Payment'!#REF! -> #REF! | O117: =IFERROR(N117-M117/M117,0) -> 0 | P117: ='MPG Payment'!#REF! -> #REF! | Q117: ='MPG Payment'!#REF! -> #REF! | R117: 0.58519403 | S117: 1 | T117: =R117-S117 -> -0.41480597
A118: ='MPG Payment'!#REF! -> #REF! | B118: ='MPG Payment'!#REF! -> #REF! | C118: ='MPG Payment'!#REF! -> #REF! | D118: ='MPG Payment'!#REF! -> #REF! | E118: ='MPG Payment'!#REF! -> #REF! | G118: ='MPG Payment'!#REF!/3 -> #REF! | H118: =COUNTIF('Farmer Payment Calc'!D:D,'MPG Performance'!B118) -> 0 | I118: =IFERROR(G118/J118/H118*2,0) -> 0 | J118: 14 | K118: 0 | L118: ='MPG Payment'!#REF! -> #REF! | M118: =SUMIF('Farmer Payment Calc'!D:D,'MPG Performance'!B118,'Farmer Payment Calc'!Y:Y) -> 0 | N118: ='MPG Payment'!#REF! -> #REF! | O118: =IFERROR(N118-M118/M118,0) -> 0 | P118: ='MPG Payment'!#REF! -> #REF! | Q118: ='MPG Payment'!#REF! -> #REF! | R118: 0.81362344 | S118: 0.90685313 | T118: =R118-S118 -> -0.093229695
A119: ='MPG Payment'!#REF! -> #REF! | B119: ='MPG Payment'!#REF! -> #REF! | C119: ='MPG Payment'!#REF! -> #REF! | D119: ='MPG Payment'!#REF! -> #REF! | E119: ='MPG Payment'!#REF! -> #REF! | G119: ='MPG Payment'!#REF!/3 -> #REF! | H119: =COUNTIF('Farmer Payment Calc'!D:D,'MPG Performance'!B119) -> 0 | I119: =IFERROR(G119/J119/H119*2,0) -> 0 | J119: 14 | K119: 0 | L119: ='MPG Payment'!#REF! -> #REF! | M119: =SUMIF('Farmer Payment Calc'!D:D,'MPG Performance'!B119,'Farmer Payment Calc'!Y:Y) -> 0 | N119: ='MPG Payment'!#REF! -> #REF! | O119: =IFERROR(N119-M119/M119,0) -> 0 | P119: ='MPG Payment'!#REF! -> #REF! | Q119: ='MPG Payment'!#REF! -> #REF! | R119: 0.62761286 | S119: 0.74330461 | T119: =R119-S119 -> -0.11569175
A120: ='MPG Payment'!#REF! -> #REF! | B120: ='MPG Payment'!#REF! -> #REF! | C120: ='MPG Payment'!#REF! -> #REF! | D120: ='MPG Payment'!#REF! -> #REF! | E120: ='MPG Payment'!#REF! -> #REF! | G120: ='MPG Payment'!#REF!/3 -> #REF! | H120: =COUNTIF('Farmer Payment Calc'!D:D,'MPG Performance'!B120) -> 0 | I120: =IFERROR(G120/J120/H120*2,0) -> 0 | J120: 14 | K120: 0 | L120: ='MPG Payment'!#REF! -> #REF! | M120: =SUMIF('Farmer Payment Calc'!D:D,'MPG Performance'!B120,'Farmer Payment Calc'!Y:Y) -> 0 | N120: ='MPG Payment'!#REF! -> #REF! | O120: =IFERROR(N120-M120/M120,0) -> 0 | P120: ='MPG Payment'!#REF! -> #REF! | Q120: ='MPG Payment'!#REF! -> #REF! | R120: 0.9699317 | S120: 1 | T120: =R120-S120 -> -0.030068299
A121: ='MPG Payment'!#REF! -> #REF! | B121: ='MPG Payment'!#REF! -> #REF! | C121: ='MPG Payment'!#REF! -> #REF! | D121: ='MPG Payment'!#REF! -> #REF! | E121: ='MPG Payment'!#REF! -> #REF! | G121: ='MPG Payment'!#REF!/3 -> #REF! | H121: =COUNTIF('Farmer Payment Calc'!D:D,'MPG Performance'!B121) -> 0 | I121: =IFERROR(G121/J121/H121*2,0) -> 0 | J121: 14 | K121: 0 | L121: ='MPG Payment'!#REF! -> #REF! | M121: =SUMIF('Farmer Payment Calc'!D:D,'MPG Performance'!B121,'Farmer Payment Calc'!Y:Y) -> 0 | N121: ='MPG Payment'!#REF! -> #REF! | O121: =IFERROR(N121-M121/M121,0) -> 0 | P121: ='MPG Payment'!#REF! -> #REF! | Q121: ='MPG Payment'!#REF! -> #REF! | R121: 0.69273009 | S121: 1 | T121: =R121-S121 -> -0.30726991
A122: ='MPG Payment'!#REF! -> #REF! | B122: ='MPG Payment'!#REF! -> #REF! | C122: ='MPG Payment'!#REF! -> #REF! | D122: ='MPG Payment'!#REF! -> #REF! | E122: ='MPG Payment'!#REF! -> #REF! | G122: ='MPG Payment'!#REF!/3 -> #REF! | H122: =COUNTIF('Farmer Payment Calc'!D:D,'MPG Performance'!B122) -> 0 | I122: =IFERROR(G122/J122/H122*2,0) -> 0 | J122: 14 | K122: 0 | L122: ='MPG Payment'!#REF! -> #REF! | M122: =SUMIF('Farmer Payment Calc'!D:D,'MPG Performance'!B122,'Farmer Payment Calc'!Y:Y) -> 0 | N122: ='MPG Payment'!#REF! -> #REF! | O122: =IFERROR(N122-M122/M122,0) -> 0 | P122: ='MPG Payment'!#REF! -> #REF! | Q122: ='MPG Payment'!#REF! -> #REF! | R122: 0.6652476 | S122: 0.89087743 | T122: =R122-S122 -> -0.22562983
A123: ='MPG Payment'!#REF! -> #REF! | B123: ='MPG Payment'!#REF! -> #REF! | C123: ='MPG Payment'!#REF! -> #REF! | D123: ='MPG Payment'!#REF! -> #REF! | E123: ='MPG Payment'!#REF! -> #REF! | G123: ='MPG Payment'!#REF!/3 -> #REF! | H123: =COUNTIF('Farmer Payment Calc'!D:D,'MPG Performance'!B123) -> 0 | I123: =IFERROR(G123/J123/H123*2,0) -> 0 | J123: 14 | K123: 0 | L123: ='MPG Payment'!#REF! -> #REF! | M123: =SUMIF('Farmer Payment Calc'!D:D,'MPG Performance'!B123,'Farmer Payment Calc'!Y:Y) -> 0 | N123: ='MPG Payment'!#REF! -> #REF! | O123: =IFERROR(N123-M123/M123,0) -> 0 | P123: ='MPG Payment'!#REF! -> #REF! | Q123: ='MPG Payment'!#REF! -> #REF! | R123: 0.99672113 | S123: 1 | T123: =R123-S123 -> -0.0032788714
A124: ='MPG Payment'!#REF! -> #REF! | B124: ='MPG Payment'!#REF! -> #REF! | C124: ='MPG Payment'!#REF! -> #REF! | D124: ='MPG Payment'!#REF! -> #REF! | E124: ='MPG Payment'!#REF! -> #REF! | G124: ='MPG Payment'!#REF!/3 -> #REF! | H124: =COUNTIF('Farmer Payment Calc'!D:D,'MPG Performance'!B124) -> 0 | I124: =IFERROR(G124/J124/H124*2,0) -> 0 | J124: 14 | K124: 0 | L124: ='MPG Payment'!#REF! -> #REF! | M124: =SUMIF('Farmer Payment Calc'!D:D,'MPG Performance'!B124,'Farmer Payment Calc'!Y:Y) -> 0 | N124: ='MPG Payment'!#REF! -> #REF! | O124: =IFERROR(N124-M124/M124,0) -> 0 | P124: ='MPG Payment'!#REF! -> #REF! | Q124: ='MPG Payment'!#REF! -> #REF! | R124: 0 | S124: 1 | T124: =R124-S124 -> -1
A125: ='MPG Payment'!#REF! -> #REF! | B125: ='MPG Payment'!#REF! -> #REF! | C125: ='MPG Payment'!#REF! -> #REF! | D125: ='MPG Payment'!#REF! -> #REF! | E125: ='MPG Payment'!#REF! -> #REF! | G125: ='MPG Payment'!#REF!/3 -> #REF! | H125: =COUNTIF('Farmer Payment Calc'!D:D,'MPG Performance'!B125) -> 0 | I125: =IFERROR(G125/J125/H125*2,0) -> 0 | J125: 14 | K125: 0 | L125: ='MPG Payment'!#REF! -> #REF! | M125: =SUMIF('Farmer Payment Calc'!D:D,'MPG Performance'!B125,'Farmer Payment Calc'!Y:Y) -> 0 | N125: ='MPG Payment'!#REF! -> #REF! | O125: =IFERROR(N125-M125/M125,0) -> 0 | P125: ='MPG Payment'!#REF! -> #REF! | Q125: ='MPG Payment'!#REF! -> #REF! | R125: 1 | S125: 1 | T125: =R125-S125 -> 0
A126: ='MPG Payment'!#REF! -> #REF! | B126: ='MPG Payment'!#REF! -> #REF! | C126: ='MPG Payment'!#REF! -> #REF! | D126: ='MPG Payment'!#REF! -> #REF! | E126: ='MPG Payment'!#REF! -> #REF! | G126: ='MPG Payment'!#REF!/3 -> #REF! | H126: =COUNTIF('Farmer Payment Calc'!D:D,'MPG Performance'!B126) -> 0 | I126: =IFERROR(G126/J126/H126*2,0) -> 0 | J126: 14 | K126: 0 | L126: ='MPG Payment'!#REF! -> #REF! | M126: =SUMIF('Farmer Payment Calc'!D:D,'MPG Performance'!B126,'Farmer Payment Calc'!Y:Y) -> 0 | N126: ='MPG Payment'!#REF! -> #REF! | O126: =IFERROR(N126-M126/M126,0) -> 0 | P126: ='MPG Payment'!#REF! -> #REF! | Q126: ='MPG Payment'!#REF! -> #REF! | R126: 0.89358765 | S126: 0.95163859 | T126: =R126-S126 -> -0.058050936
... A128: ='MPG Payment'!#REF! -> #REF! | B128: ='MPG Payment'!#REF! -> #REF! | C128: ='MPG Payment'!#REF! -> #REF! | D128: ='MPG Payment'!#REF! -> #REF! | E128: ='MPG Payment'!#REF! -> #REF! | G128: ='MPG Payment'!#REF!/3 -> #REF! | H128: =COUNTIF('Farmer Payment Calc'!D:D,'MPG Performance'!B128) -> 0 | I128: =IFERROR(G128/J128/H128*2,0) -> 0 | J128: 14 | K128: 0 | L128: ='MPG Payment'!#REF! -> #REF! | M128: =SUMIF('Farmer Payment Calc'!D:D,'MPG Performance'!B128,'Farmer Payment Calc'!Y:Y) -> 0 | N128: ='MPG Payment'!#REF! -> #REF! | O128: =IFERROR(N128-M128/M128,0) -> 0 | P128: ='MPG Payment'!#REF! -> #REF! | Q128: ='MPG Payment'!#REF! -> #REF! | R128: 0.7136421 | S128: 1 | T128: =R128-S128 -> -0.2863579

Sheet FAR PIVOT
A1: BMC Area | B1: (All)
A2: For the period of 02-08'Feb-24
F3: Values
A4: Code | B4: Farmers Code | C4: Farmers Account Name | D4: Accont no | E4: IFSC code | F4: Vol_L | G4: Amount | H4: Net Amount | I4: Sum of Milk Short
A5: 20010001 | B5: 0002 | C5: AMIT KUMAR TIWARI | D5: 7125658980 | E5: IDIB000I021 | F5: 9769 | G5: 417636.15 | H5: 402672 | I5: 0
A6: 20010001 | B6: 0004 | C6: BIRSA ORAON | D6: 358702010006943 | E6: UBIN0535877 | F6: 21.58 | G6: 1026.4586 | H6: 1026 | I6: 0
A7: 20010001 | B7: 0010 | C7: SHANTI DEVI | D7: 6496430309 | E7: IDIB000I021 | F7: 58.76 | G7: 2666.0376 | H7: 2666 | I7: 0
A8: 20010001 | B8: 0016 | C8: Suko Tirki | D8: 7100914953 | E8: IDIB000I021 | F8: 27.04 | G8: 1148.0662 | H8: 1148 | I8: 0
A9: 20010001 | B9: 0017 | C9: Bikram Gope | D9: 358702010006937 | E9: UBIN0535877 | F9: 17.98 | G9: 769.6052 | H9: 770 | I9: 0
A10: 20010001 | B10: 0019 | C10: Hiramani Kachhap | D10: 494310110016645 | E10: BKID0004943 | F10: 37.3 | G10: 1471.0452 | H10: 1471 | I10: 0
A11: 20010001 | B11: 0046 | C11: DHANI MAHALI | D11: 358702010628606 | E11: UBIN0535877 | F11: 53.26 | G11: 2076.4026 | H11: 2076 | I11: 0
A12: 20010001 | B12: 0047 | C12: Kusum Tirki | D12: 6511075905 | E12: IDIB000I021 | F12: 27.6 | G12: 1065.9122 | H12: 1066 | I12: 0
A13: 20010001 | B13: 0048 | C13: Anil Tirki | D13: 358702010004453 | E13: UBIN0535877 | F13: 37.54 | G13: 1563.155 | H13: 1563 | I13: 0
A14: 20010001 | B14: 0050 | C14: SABITA TIWARI | D14: 762901500038 | E14: ICIC0007629 | F14: 140 | G14: 5681.6 | H14: 5682 | I14: 0
A15: 20010001 | B15: 0064 | C15: SOHEL ANSARI | D15: 358702120002626 | E15: UBIN0535877 | F15: 54.8 | G15: 2449.294 | H15: 2449 | I15: 0
A16: 20010001 | B16: 0066 | C16: SUJIT KUMAR ACHARYA | D16: 07591530000649 | E16: HDFC0000759 | F16: 63 | G16: 2556.72 | H16: 2557 | I16: 0
... A25: 20010001 | B25: 0082 | C25: CHANDRA CHUDAMANI PATHAK | D25: 59103904965996 | E25: HDFC0008691 | F25: 804.94 | G25: 32214.236 | H25: 32214 | I25: 0
A26: 20010001 Total | F26: 11528.02 | G26: 489944.47 | H26: 474980 | I26: 0
A27: 20010003 | B27: 0003 | C27: PINKI DEVI | D27: 4895101003786 | E27: CNRB0004895 | F27: 1183.71 | G27: 47883.822 | H27: 40244 | I27: 20
A28: 20010003 | B28: 0013 | C28: JOSEF LAKRA | D28: 495910510003202 | E28: BKID0004959 | F28: 38.9 | G28: 1877.992 | H28: 1378 | I28: 500
A29: 20010003 | B29: 0026 | C29: Pankaj Tigga | D29: 41383270689 | E29: SBIN0012618 | F29: 31.96 | G29: 1303.1576 | H29: 0 | I29: 33
A30: 20010003 | B30: 0044 | C30: Manju Devi | D30: 08030100922544 | E30: UCBA0000803 | F30: 23.45 | G30: 1011.0627 | H30: 811 | I30: 200
A31: 20010003 | B31: 0077 | C31: PUNAM SINHA | D31: 495910100000166 | E31: BKID0004959 | F31: 5.35 | G31: 242.203 | H31: 242 | I31: 0
A32: 20010003 | B32: 0080 | C32: GEETA TANA BHAGTAIN | D32: 08033211029311 | E32: UCBA0000803 | F32: 8.22 | G32: 447.5265 | H32: 448 | I32: 0
A33: 20010003 | B33: 0105 | C33: SUKA TANA BHAGAT | D33: 08030100921195 | E33: UCBA0000803 | F33: 11.73 | G33: 569.2787 | H33: 143 | I33: 426
A34: 20010003 | B34: 0112 | C34: BANDE ORAON | D34: 495910510003218 | E34: BKID0004959 | F34: 40.63 | G34: 2002.2369 | H34: 1702 | I34: 300
A35: 20010003 | B35: 0116 | C35: ANITA DEVI | D35: 495918210005225 | E35: BKID0004959 | F35: 37.32 | G35: 1602.0912 | H35: 332 | I35: 0
A36: 20010003 | B36: 0115 | C36: SUNITA KUMARI | D36: 110048432290 | E36: CNRB0004895 | F36: 15.77 | G36: 717.9342 | H36: 718 | I36: 0
A37: 20010003 Total | F37: 1397.04 | G37: 57657.305 | H37: 46018 | I37: 1479
A38: 20010005 | B38: 0002 | C38: SAJJAD ANSARI | D38: 20421406720 | E38: SBIN0014340 | F38: 89.5 | G38: 3691.875 | H38: 3692 | I38: 0
A39: 20010005 | B39: 0005 | C39: MUNEJA KHATUN | D39: 494318210006630 | E39: BKID0004943 | F39: 47.37 | G39: 1864.3849 | H39: 1864 | I39: 0
A40: 20010005 | B40: 0008 | C40: ANISA KHATUN | D40: 50370873265 | E40: IDIB000N518 | F40: 35.21 | G40: 1504.7457 | H40: 1505 | I40: 0
A41: 20010005 | B41: 0009 | C41: RABUL ANSARI | D41: 494318210000448 | E41: BKID0004943 | F41: 51.19 | G41: 2129.8845 | H41: 2130 | I41: 0
A42: 20010005 | B42: 0011 | C42: EYASIN ANSARI | D42: 50363172838 | E42: IDIB000N518 | F42: 42.23 | G42: 2046.4712 | H42: 2046 | I42: 0
A43: 20010005 | B43: 0012 | C43: TAIRUN NISHA | D43: 371101000005005 | E43: IOBA0003711 | F43: 10.77 | G43: 513.242 | H43: 513 | I43: 0
A44: 20010005 | B44: 0014 | C44: SALIM ANSARI | D44: 494310110018804 | E44: BKID0004943 | F44: 52.81 | G44: 2472.5713 | H44: 2473 | I44: 0
A45: 20010005 | B45: 0016 | C45: ASIYA KHATOON | D45: 494318210006966 | E45: BKID0004943 | F45: 1.63 | G45: 64.5397 | H45: 65 | I45: 0
A46: 20010005 | B46: 0022 | C46: SHEIKH SAFIQUE | D46: 494310100000875 | E46: BKID0004943 | F46: 7.64 | G46: 278.2609 | H46: 278 | I46: 0
A47: 20010005 | B47: 0023 | C47: JOHRA KHATOON | D47: 50369500332 | E47: IDIB000N518 | F47: 24.88 | G47: 1007.5236 | H47: 1008 | I47: 0
A48: 20010005 | B48: 0029 | C48: IMAM ANSARI | D48: 494318210005769 | E48: BKID0004943 | F48: 19.35 | G48: 795.6549 | H48: 796 | I48: 0
A49: 20010005 | B49: 0033 | C49: Hamida Khatoon | D49: 39470934026 | E49: SBIN0014340 | F49: 22.14 | G49: 820.1015 | H49: 820 | I49: 0
... A60: 20010005 | B60: 0055 | C60: BABLU ORAON | D60: 371101000005236 | E60: IOBA0003711 | F60: 126.81 | G60: 5058.7558 | H60: 5059 | I60: 0
A61: 20010005 Total | F61: 1352.05 | G61: 54956.825 | H61: 54958 | I61: 0
A62: 20010008 | B62: 0005 | C62: SANJAY SAHU | D62: 494310100013455 | E62: BKID0004943 | F62: 29.63 | G62: 1247.2893 | H62: 1247 | I62: 0
A63: 20010008 | B63: 0010 | C63: MAMITA KUMARI | D63: 371101000006331 | E63: IOBA0003711 | F63: 12.84 | G63: 445.0187 | H63: 445 | I63: 0
A64: 20010008 | B64: 0017 | C64: RAM JI SAHU | D64: 22016771417 | E64: SBIN0RRVCGB | F64: 74.11 | G64: 2762.9766 | H64: 2763 | I64: 0
A65: 20010008 | B65: 0024 | C65: Mila Devi | D65: 494318210000940 | E65: BKID0004943 | F65: 44.14 | G65: 2007.8533 | H65: 2008 | I65: 0
A66: 20010008 | B66: 0035 | C66: LALITA DEVI | D66: 22016772818 | E66: SBIN0RRVCGB | F66: 472.35 | G66: 19721.392 | H66: 19721 | I66: 0
A67: 20010008 | B67: 0040 | C67: Rekha Kumari | D67: 371101000006095 | E67: IOBA0003711 | F67: 9.31 | G67: 474.606 | H67: 475 | I67: 0
A68: 20010008 | B68: 0041 | C68: Giridhari Sahu | D68: 31955655087 | E68: SBIN0014340 | F68: 31.3 | G68: 1369.0595 | H68: 1369 | I68: 0
A69: 20010008 | B69: 0045 | C69: BASANT SAW | D69: 43418630101 | E69: SBIN0014340 | F69: 9.04 | G69: 380.4024 | H69: 380 | I69: 0
A70: 20010008 | B70: 0050 | C70: SURAJMANI TOPPO | D70: 494310110002155 | E70: BKID0004943 | F70: 26.51 | G70: 1230.6473 | H70: 1231 | I70: 0
A71: 20010008 | B71: 0053 | C71: RAMA TOPPO | D71: 494310100006318 | E71: BKID0004943 | F71: 13.3 | G71: 696.5886 | H71: 697 | I71: 0
A72: 20010008 | B72: 0059 | C72: REKHA DEVI | D72: 84065679489 | E72: SBIN0RRVCGB | F72: 230.6 | G72: 9022.2713 | H72: 9022 | I72: 0
A73: 20010008 | B73: 0060 | C73: SUMITRA DEVI | D73: 22016801614 | E73: SBIN0RRVCGB | F73: 93.73 | G73: 3988.3792 | H73: 3988 | I73: 0
... A75: 20010008 | B75: 0061 | C75: SHANTI DEVI | D75: 33055486434 | E75: SBIN0014340 | F75: 95.35 | G75: 3574.2593 | H75: 3574 | I75: 0
A76: 20010008 Total | F76: 1185.43 | G76: 48571.347 | H76: 48571 | I76: 0
A77: 20010009 | B77: 0002 | C77: BAL KISHORE TIWARI | D77: 358702010009142 | E77: UBIN0535877 | F77: 56.88 | G77: 2277.0154 | H77: 2277 | I77: 0
A78: 20010009 | B78: 0016 | C78: BIRENDAR KUMAR GOPE | D78: 358702010626226 | E78: UBIN0535877 | F78: 182.28 | G78: 7741.1212 | H78: 7741 | I78: 0
A79: 20010009 | B79: 0017 | C79: PUSPA DEVI | D79: 50100184717426 | E79: HDFC0001470 | F79: 96.04 | G79: 3950.1017 | H79: 3950 | I79: 0
A80: 20010009 | B80: 0030 | C80: SUBHASH GOPE | D80: 7768139451 | E80: IDIB000I021 | F80: 188.99 | G80: 7923.5784 | H80: 7924 | I80: 0
A81: 20010009 | B81: 0031 | C81: MAMTA DEVI | D81: 589510110004327 | E81: BKID0005895 | F81: 56.54 | G81: 2361.2821 | H81: 2361 | I81: 0
A82: 20010009 | B82: 0032 | C82: REENA KUMARI | D82: 490218210000253 | E82: BKID0004902 | F82: 45.63 | G82: 1905.6502 | H82: 1906 | I82: 0
A83: 20010009 | B83: 0034 | C83: SOMESH GOPE | D83: 358702010629551 | E83: UBIN0535877 | F83: 25.12 | G83: 1019.5985 | H83: 1020 | I83: 0
A84: 20010009 Total | F84: 651.48 | G84: 27178.347 | H84: 27179 | I84: 0
A85: 20010015 | B85: 0003 | C85: Manga Bhagat | D85: 358702010612721 | E85: UBIN0535877 | F85: 4 | G85: 165.56 | H85: 166 | I85: 0
A86: 20010015 | B86: 0006 | C86: Shkila Khatoon | D86: 358702010614868 | E86: UBIN0535877 | F86: 20.48 | G86: 825.4914 | H86: 825 | I86: 0
A87: 20010015 | B87: 0013 | C87: Shashi Kala Urain | D87: 6443192285 | E87: IDIB000I021 | F87: 64.81 | G87: 2723.6595 | H87: 2724 | I87: 0
A88: 20010015 | B88: 0014 | C88: Putun Devi | D88: 358702120002678 | E88: UBIN0535877 | F88: 70.14 | G88: 3043.5703 | H88: 3044 | I88: 0
A89: 20010015 | B89: 0016 | C89: Evaren Khes | D89: 358702010605620 | E89: UBIN0535877 | F89: 42.68 | G89: 1927.1325 | H89: 1927 | I89: 0
A90: 20010015 | B90: 0017 | C90: Halima Khatoon | D90: 35769326327 | E90: SBIN0015346 | F90: 53.02 | G90: 2175.221 | H90: 2175 | I90: 0
A91: 20010015 | B91: 0021 | C91: Etwari Urain | D91: 6940856322 | E91: IDIB000I021 | F91: 50.38 | G91: 2046.3229 | H91: 2046 | I91: 0
A92: 20010015 | B92: 0022 | C92: Nejam Ansari | D92: 358702010612736 | E92: UBIN0535877 | F92: 13.89 | G92: 562.9346 | H92: 563 | I92: 0
A93: 20010015 | B93: 0024 | C93: Haidar Ansari | D93: 358702010603995 | E93: UBIN0535877 | F93: 5.76 | G93: 234.129 | H93: 234 | I93: 0
A94: 20010015 | B94: 0026 | C94: Jamahir Ansari | D94: 32449556244 | E94: SBIN0015346 | F94: 36.15 | G94: 1509.5489 | H94: 1510 | I94: 0
A95: 20010015 | B95: 0027 | C95: Shahid Ansari | D95: 7202563588 | E95: IDIB000I021 | F95: 73.3 | G95: 3022.2857 | H95: 3022 | I95: 0
A96: 20010015 | B96: 0028 | C96: Manita Khes | D96: 358702010005279 | E96: UBIN0535877 | F96: 46.62 | G96: 1898.4255 | H96: 1898 | I96: 0
... A137: 20010015 | B137: 0120 | C137: DULARI TOPPO | D137: 7416578560 | E137: IDIB000I021 | F137: 6.1 | G137: 251.783 | H137: 252 | I137: 0
A138: 20010015 Total | F138: 2579.38 | G138: 107851.96 | H138: 107853 | I138: 0
A139: 20010017 | B139: 0002 | C139: Suhail Hussain | D139: 9760000100022416 | E139: PUNB0976000 | F139: 169.04 | G139: 7490.8292 | H139: 7096 | I139: 395.28
A140: 20010017 | B140: 0010 | C140: Mahadev Minj | D140: 9760001700014250 | E140: PUNB0976000 | F140: 16.33 | G140: 841.5242 | H140: 842 | I140: 0
A141: 20010017 | B141: 0018 | C141: ANITA DEVI | D141: 495910510007136 | E141: BKID0004959 | F141: 18.81 | G141: 857.6571 | H141: 858 | I141: 0
A142: 20010017 | B142: 0020 | C142: Pyari Devi | D142: 495918210006595 | E142: BKID0004959 | F142: 6.82 | G142: 310.8392 | H142: 311 | I142: 0
A143: 20010017 | B143: 0025 | C143: ANITA DEVI | D143: 495910110006141 | E143: BKID0004959 | F143: 37.54 | G143: 1403.0564 | H143: 1403 | I143: 0
A144: 20010017 | B144: 0026 | C144: JAGAT PAL SAHU | D144: 08030100009205 | E144: UCBA0000803 | F144: 26.27 | G144: 1308.8734 | H144: 1309 | I144: 0
A145: 20010017 | B145: 0027 | C145: PANKAJ KHESS | D145: 495910510005882 | E145: BKID0004959 | F145: 10.77 | G145: 662.238 | H145: 662 | I145: 0
A146: 20010017 | B146: 0029 | C146: ISRAT PRAWEEN | D146: 9760001700028475 | E146: PUNB0976000 | F146: 11.6 | G146: 565.2456 | H146: 565 | I146: 0
A147: 20010017 | B147: 0030 | C147: AFJAL HUSSAIN | D147: 495918210007034 | E147: BKID0004959 | F147: 17.36 | G147: 675.0978 | H147: 675 | I147: 0
A148: 20010017 Total | F148: 314.54 | G148: 14115.361 | H148: 13721 | I148: 395.28
A149: 20010023 | B149: 0004 | C149: Somra Munda | D149: 371101000004289 | E149: IOBA0003711 | F149: 54.2 | G149: 2706.3362 | H149: 2706 | I149: 0
A150: 20010023 | B150: 0008 | C150: Lalo Munda | D150: 84032231436 | E150: SBIN0RRVCGB | F150: 31.82 | G150: 1667.718 | H150: 1668 | I150: 0
A151: 20010023 | B151: 0010 | C151: Sudama Gope | D151: 371101000002155 | E151: IOBA0003711 | F151: 8.22 | G151: 329.4634 | H151: 329 | I151: 0
A152: 20010023 | B152: 0011 | C152: Geeta Devi | D152: 22016749426 | E152: SBIN0RRVCGB | F152: 47.6 | G152: 1959.6806 | H152: 1960 | I152: 0
A153: 20010023 | B153: 0015 | C153: Charo Munda | D153: 494310100006547 | E153: BKID0004943 | F153: 39.07 | G153: 1781.7679 | H153: 1782 | I153: 0
A154: 20010023 | B154: 0016 | C154: Rani Devi | D154: 494310110014797 | E154: BKID0004943 | F154: 54.51 | G154: 2282.3886 | H154: 2282 | I154: 0
A155: 20010023 | B155: 0021 | C155: Dhaneshwar Gop | D155: 494310110002166 | E155: BKID0004943 | F155: 75.65 | G155: 3098.7116 | H155: 3099 | I155: 0
A156: 20010023 | B156: 0023 | C156: Shani Munda | D156: 7203940137 | E156: IDIB000N518 | F156: 61.76 | G156: 2653.8508 | H156: 2654 | I156: 0
A157: 20010023 | B157: 0024 | C157: Rupan Devi | D157: 494310110016123 | E157: BKID0004943 | F157: 33.93 | G157: 1371.7776 | H157: 1372 | I157: 0
A158: 20010023 | B158: 0026 | C158: Rajesh Gop | D158: 494318210002779 | E158: BKID0004943 | F158: 68.47 | G158: 3983.4398 | H158: 3983 | I158: 0
A159: 20010023 | B159: 0027 | C159: Chhoti Devi | D159: 371101000005125 | E159: IOBA0003711 | F159: 14.7 | G159: 604.2096 | H159: 604 | I159: 0
...

Sheet FARMER
A1: BMC Area | B1: (All)
A2: For the period of 08-14 Nov'24
F3: Values
A4: Code | B4: Farmers Code | C4: Farmers Account Name | D4: Accont no | E4: IFSC code | F4: Sum of Vol_L | G4: Sum of Amount | H4: Sum of Milk Short | I4: Sum of Net Amount
A5: 20010001 | B5: 0002 | C5: AMIT KUMAR TIWARI | D5: 7125658980 | E5: IDIB000I021 | F5: 9769 | G5: 417636.15 | H5: 0 | I5: 402672
A6: 20010001 | B6: 0004 | C6: BIRSA ORAON | D6: 358702010006943 | E6: UBIN0535877 | F6: 21.58 | G6: 1026.4586 | H6: 0 | I6: 1026
A7: 20010001 | B7: 0010 | C7: SHANTI DEVI | D7: 6496430309 | E7: IDIB000I021 | F7: 58.76 | G7: 2666.0376 | H7: 0 | I7: 2666
A8: 20010001 | B8: 0016 | C8: Suko Tirki | D8: 7100914953 | E8: IDIB000I021 | F8: 27.04 | G8: 1148.0662 | H8: 0 | I8: 1148
A9: 20010001 | B9: 0017 | C9: Bikram Gope | D9: 358702010006937 | E9: UBIN0535877 | F9: 17.98 | G9: 769.6052 | H9: 0 | I9: 770
A10: 20010001 | B10: 0019 | C10: Hiramani Kachhap | D10: 494310110016645 | E10: BKID0004943 | F10: 37.3 | G10: 1471.0452 | H10: 0 | I10: 1471
A11: 20010001 | B11: 0046 | C11: DHANI MAHALI | D11: 358702010628606 | E11: UBIN0535877 | F11: 53.26 | G11: 2076.4026 | H11: 0 | I11: 2076
A12: 20010001 | B12: 0047 | C12: Kusum Tirki | D12: 6511075905 | E12: IDIB000I021 | F12: 27.6 | G12: 1065.9122 | H12: 0 | I12: 1066
A13: 20010001 | B13: 0048 | C13: Anil Tirki | D13: 358702010004453 | E13: UBIN0535877 | F13: 37.54 | G13: 1563.155 | H13: 0 | I13: 1563
A14: 20010001 | B14: 0050 | C14: SABITA TIWARI | D14: 762901500038 | E14: ICIC0007629 | F14: 140 | G14: 5681.6 | H14: 0 | I14: 5682
A15: 20010001 | B15: 0051 | C15: SAHIL RAJ | D15: 40723769931 | E15: SBIN0000081 | F15: 72 | G15: 2923.55 | H15: 0 | I15: 2924
A16: 20010001 | B16: 0064 | C16: SOHEL ANSARI | D16: 358702120002626 | E16: UBIN0535877 | F16: 54.8 | G16: 2449.294 | H16: 0 | I16: 2449
... A25: 20010001 | B25: 0082 | C25: CHANDRA CHUDAMANI PATHAK | D25: 59103904965996 | E25: HDFC0008691 | F25: 804.94 | G25: 32214.236 | H25: 0 | I25: 32214
A26: 20010001 Total | F26: 11528.02 | G26: 489944.47 | H26: 0 | I26: 474980
A27: 20010003 | B27: 0003 | C27: PINKI DEVI | D27: 4895101003786 | E27: CNRB0004895 | F27: 1183.71 | G27: 47883.822 | H27: 20 | I27: 40244
A28: 20010003 | B28: 0013 | C28: JOSEF LAKRA | D28: 495910510003202 | E28: BKID0004959 | F28: 38.9 | G28: 1877.992 | H28: 500 | I28: 1378
A29: 20010003 | B29: 0026 | C29: Pankaj Tigga | D29: 41383270689 | E29: SBIN0012618 | F29: 31.96 | G29: 1303.1576 | H29: 33 | I29: 0
A30: 20010003 | B30: 0044 | C30: Manju Devi | D30: 08030100922544 | E30: UCBA0000803 | F30: 23.45 | G30: 1011.0627 | H30: 200 | I30: 811
A31: 20010003 | B31: 0077 | C31: PUNAM SINHA | D31: 495910100000166 | E31: BKID0004959 | F31: 5.35 | G31: 242.203 | H31: 0 | I31: 242
A32: 20010003 | B32: 0080 | C32: GEETA TANA BHAGTAIN | D32: 08033211029311 | E32: UCBA0000803 | F32: 8.22 | G32: 447.5265 | H32: 0 | I32: 448
A33: 20010003 | B33: 0105 | C33: SUKA TANA BHAGAT | D33: 08030100921195 | E33: UCBA0000803 | F33: 11.73 | G33: 569.2787 | H33: 426 | I33: 143
A34: 20010003 | B34: 0112 | C34: BANDE ORAON | D34: 495910510003218 | E34: BKID0004959 | F34: 40.63 | G34: 2002.2369 | H34: 300 | I34: 1702
A35: 20010003 | B35: 0116 | C35: ANITA DEVI | D35: 495918210005225 | E35: BKID0004959 | F35: 37.32 | G35: 1602.0912 | H35: 0 | I35: 332
A36: 20010003 | B36: 0115 | C36: SUNITA KUMARI | D36: 110048432290 | E36: CNRB0004895 | F36: 15.77 | G36: 717.9342 | H36: 0 | I36: 718
A37: 20010003 Total | F37: 1397.04 | G37: 57657.305 | H37: 1479 | I37: 46018
A38: 20010005 | B38: 0002 | C38: SAJJAD ANSARI | D38: 20421406720 | E38: SBIN0014340 | F38: 89.5 | G38: 3691.875 | H38: 0 | I38: 3692
A39: 20010005 | B39: 0005 | C39: MUNEJA KHATUN | D39: 494318210006630 | E39: BKID0004943 | F39: 47.37 | G39: 1864.3849 | H39: 0 | I39: 1864
A40: 20010005 | B40: 0008 | C40: ANISA KHATUN | D40: 50370873265 | E40: IDIB000N518 | F40: 35.21 | G40: 1504.7457 | H40: 0 | I40: 1505
A41: 20010005 | B41: 0009 | C41: RABUL ANSARI | D41: 494318210000448 | E41: BKID0004943 | F41: 51.19 | G41: 2129.8845 | H41: 0 | I41: 2130
A42: 20010005 | B42: 0011 | C42: EYASIN ANSARI | D42: 50363172838 | E42: IDIB000N518 | F42: 42.23 | G42: 2046.4712 | H42: 0 | I42: 2046
A43: 20010005 | B43: 0012 | C43: TAIRUN NISHA | D43: 371101000005005 | E43: IOBA0003711 | F43: 10.77 | G43: 513.242 | H43: 0 | I43: 513
A44: 20010005 | B44: 0014 | C44: SALIM ANSARI | D44: 494310110018804 | E44: BKID0004943 | F44: 52.81 | G44: 2472.5713 | H44: 0 | I44: 2473
A45: 20010005 | B45: 0016 | C45: ASIYA KHATOON | D45: 494318210006966 | E45: BKID0004943 | F45: 1.63 | G45: 64.5397 | H45: 0 | I45: 65
A46: 20010005 | B46: 0022 | C46: SHEIKH SAFIQUE | D46: 494310100000875 | E46: BKID0004943 | F46: 7.64 | G46: 278.2609 | H46: 0 | I46: 278
A47: 20010005 | B47: 0023 | C47: JOHRA KHATOON | D47: 50369500332 | E47: IDIB000N518 | F47: 24.88 | G47: 1007.5236 | H47: 0 | I47: 1008
A48: 20010005 | B48: 0029 | C48: IMAM ANSARI | D48: 494318210005769 | E48: BKID0004943 | F48: 19.35 | G48: 795.6549 | H48: 0 | I48: 796
A49: 20010005 | B49: 0033 | C49: Hamida Khatoon | D49: 39470934026 | E49: SBIN0014340 | F49: 22.14 | G49: 820.1015 | H49: 0 | I49: 820
... A60: 20010005 | B60: 0055 | C60: BABLU ORAON | D60: 371101000005236 | E60: IOBA0003711 | F60: 126.81 | G60: 5058.7558 | H60: 0 | I60: 5059
A61: 20010005 Total | F61: 1352.05 | G61: 54956.825 | H61: 0 | I61: 54958
A62: 20010008 | B62: 0005 | C62: SANJAY SAHU | D62: 494310100013455 | E62: BKID0004943 | F62: 29.63 | G62: 1247.2893 | H62: 0 | I62: 1247
A63: 20010008 | B63: 0010 | C63: MAMITA KUMARI | D63: 371101000006331 | E63: IOBA0003711 | F63: 12.84 | G63: 445.0187 | H63: 0 | I63: 445
A64: 20010008 | B64: 0017 | C64: RAM JI SAHU | D64: 22016771417 | E64: SBIN0RRVCGB | F64: 74.11 | G64: 2762.9766 | H64: 0 | I64: 2763
A65: 20010008 | B65: 0024 | C65: Mila Devi | D65: 494318210000940 | E65: BKID0004943 | F65: 44.14 | G65: 2007.8533 | H65: 0 | I65: 2008
A66: 20010008 | B66: 0035 | C66: LALITA DEVI | D66: 22016772818 | E66: SBIN0RRVCGB | F66: 472.35 | G66: 19721.392 | H66: 0 | I66: 19721
A67: 20010008 | B67: 0040 | C67: Rekha Kumari | D67: 371101000006095 | E67: IOBA0003711 | F67: 9.31 | G67: 474.606 | H67: 0 | I67: 475
A68: 20010008 | B68: 0041 | C68: Giridhari Sahu | D68: 31955655087 | E68: SBIN0014340 | F68: 31.3 | G68: 1369.0595 | H68: 0 | I68: 1369
A69: 20010008 | B69: 0045 | C69: BASANT SAW | D69: 43418630101 | E69: SBIN0014340 | F69: 9.04 | G69: 380.4024 | H69: 0 | I69: 380
A70: 20010008 | B70: 0050 | C70: SURAJMANI TOPPO | D70: 494310110002155 | E70: BKID0004943 | F70: 26.51 | G70: 1230.6473 | H70: 0 | I70: 1231
A71: 20010008 | B71: 0053 | C71: RAMA TOPPO | D71: 494310100006318 | E71: BKID0004943 | F71: 13.3 | G71: 696.5886 | H71: 0 | I71: 697
A72: 20010008 | B72: 0059 | C72: REKHA DEVI | D72: 84065679489 | E72: SBIN0RRVCGB | F72: 230.6 | G72: 9022.2713 | H72: 0 | I72: 9022
A73: 20010008 | B73: 0060 | C73: SUMITRA DEVI | D73: 22016801614 | E73: SBIN0RRVCGB | F73: 93.73 | G73: 3988.3792 | H73: 0 | I73: 3988
... A75: 20010008 | B75: 0061 | C75: SHANTI DEVI | D75: 33055486434 | E75: SBIN0014340 | F75: 95.35 | G75: 3574.2593 | H75: 0 | I75: 3574
A76: 20010008 Total | F76: 1185.43 | G76: 48571.347 | H76: 0 | I76: 48571
A77: 20010009 | B77: 0002 | C77: BAL KISHORE TIWARI | D77: 358702010009142 | E77: UBIN0535877 | F77: 56.88 | G77: 2277.0154 | H77: 0 | I77: 2277
A78: 20010009 | B78: 0016 | C78: BIRENDAR KUMAR GOPE | D78: 358702010626226 | E78: UBIN0535877 | F78: 182.28 | G78: 7741.1212 | H78: 0 | I78: 7741
A79: 20010009 | B79: 0017 | C79: PUSPA DEVI | D79: 50100184717426 | E79: HDFC0001470 | F79: 96.04 | G79: 3950.1017 | H79: 0 | I79: 3950
A80: 20010009 | B80: 0030 | C80: SUBHASH GOPE | D80: 7768139451 | E80: IDIB000I021 | F80: 188.99 | G80: 7923.5784 | H80: 0 | I80: 7924
A81: 20010009 | B81: 0031 | C81: MAMTA DEVI | D81: 589510110004327 | E81: BKID0005895 | F81: 56.54 | G81: 2361.2821 | H81: 0 | I81: 2361
A82: 20010009 | B82: 0032 | C82: REENA KUMARI | D82: 490218210000253 | E82: BKID0004902 | F82: 45.63 | G82: 1905.6502 | H82: 0 | I82: 1906
A83: 20010009 | B83: 0034 | C83: SOMESH GOPE | D83: 358702010629551 | E83: UBIN0535877 | F83: 25.12 | G83: 1019.5985 | H83: 0 | I83: 1020
A84: 20010009 Total | F84: 651.48 | G84: 27178.347 | H84: 0 | I84: 27179
A85: 20010015 | B85: 0003 | C85: Manga Bhagat | D85: 358702010612721 | E85: UBIN0535877 | F85: 4 | G85: 165.56 | H85: 0 | I85: 166
A86: 20010015 | B86: 0006 | C86: Shkila Khatoon | D86: 358702010614868 | E86: UBIN0535877 | F86: 20.48 | G86: 825.4914 | H86: 0 | I86: 825
A87: 20010015 | B87: 0013 | C87: Shashi Kala Urain | D87: 6443192285 | E87: IDIB000I021 | F87: 64.81 | G87: 2723.6595 | H87: 0 | I87: 2724
A88: 20010015 | B88: 0014 | C88: Putun Devi | D88: 358702120002678 | E88: UBIN0535877 | F88: 70.14 | G88: 3043.5703 | H88: 0 | I88: 3044
A89: 20010015 | B89: 0016 | C89: Evaren Khes | D89: 358702010605620 | E89: UBIN0535877 | F89: 42.68 | G89: 1927.1325 | H89: 0 | I89: 1927
A90: 20010015 | B90: 0017 | C90: Halima Khatoon | D90: 35769326327 | E90: SBIN0015346 | F90: 53.02 | G90: 2175.221 | H90: 0 | I90: 2175
A91: 20010015 | B91: 0021 | C91: Etwari Urain | D91: 6940856322 | E91: IDIB000I021 | F91: 50.38 | G91: 2046.3229 | H91: 0 | I91: 2046
A92: 20010015 | B92: 0022 | C92: Nejam Ansari | D92: 358702010612736 | E92: UBIN0535877 | F92: 13.89 | G92: 562.9346 | H92: 0 | I92: 563
A93: 20010015 | B93: 0024 | C93: Haidar Ansari | D93: 358702010603995 | E93: UBIN0535877 | F93: 5.76 | G93: 234.129 | H93: 0 | I93: 234
A94: 20010015 | B94: 0026 | C94: Jamahir Ansari | D94: 32449556244 | E94: SBIN0015346 | F94: 36.15 | G94: 1509.5489 | H94: 0 | I94: 1510
A95: 20010015 | B95: 0027 | C95: Shahid Ansari | D95: 7202563588 | E95: IDIB000I021 | F95: 73.3 | G95: 3022.2857 | H95: 0 | I95: 3022
A96: 20010015 | B96: 0028 | C96: Manita Khes | D96: 358702010005279 | E96: UBIN0535877 | F96: 46.62 | G96: 1898.4255 | H96: 0 | I96: 1898
... A137: 20010015 | B137: 0120 | C137: DULARI TOPPO | D137: 7416578560 | E137: IDIB000I021 | F137: 6.1 | G137: 251.783 | H137: 0 | I137: 252
A138: 20010015 Total | F138: 2579.38 | G138: 107851.96 | H138: 0 | I138: 107853
A139: 20010017 | B139: 0002 | C139: Suhail Hussain | D139: 9760000100022416 | E139: PUNB0976000 | F139: 169.04 | G139: 7490.8292 | H139: 395.28 | I139: 7096
A140: 20010017 | B140: 0010 | C140: Mahadev Minj | D140: 9760001700014250 | E140: PUNB0976000 | F140: 16.33 | G140: 841.5242 | H140: 0 | I140: 842
A141: 20010017 | B141: 0018 | C141: ANITA DEVI | D141: 495910510007136 | E141: BKID0004959 | F141: 18.81 | G141: 857.6571 | H141: 0 | I141: 858
A142: 20010017 | B142: 0020 | C142: Pyari Devi | D142: 495918210006595 | E142: BKID0004959 | F142: 6.82 | G142: 310.8392 | H142: 0 | I142: 311
A143: 20010017 | B143: 0025 | C143: ANITA DEVI | D143: 495910110006141 | E143: BKID0004959 | F143: 37.54 | G143: 1403.0564 | H143: 0 | I143: 1403
A144: 20010017 | B144: 0026 | C144: JAGAT PAL SAHU | D144: 08030100009205 | E144: UCBA0000803 | F144: 26.27 | G144: 1308.8734 | H144: 0 | I144: 1309
A145: 20010017 | B145: 0027 | C145: PANKAJ KHESS | D145: 495910510005882 | E145: BKID0004959 | F145: 10.77 | G145: 662.238 | H145: 0 | I145: 662
A146: 20010017 | B146: 0029 | C146: ISRAT PRAWEEN | D146: 9760001700028475 | E146: PUNB0976000 | F146: 11.6 | G146: 565.2456 | H146: 0 | I146: 565
A147: 20010017 | B147: 0030 | C147: AFJAL HUSSAIN | D147: 495918210007034 | E147: BKID0004959 | F147: 17.36 | G147: 675.0978 | H147: 0 | I147: 675
A148: 20010017 Total | F148: 314.54 | G148: 14115.361 | H148: 395.28 | I148: 13721
A149: 20010023 | B149: 0004 | C149: Somra Munda | D149: 371101000004289 | E149: IOBA0003711 | F149: 54.2 | G149: 2706.3362 | H149: 0 | I149: 2706
A150: 20010023 | B150: 0008 | C150: Lalo Munda | D150: 84032231436 | E150: SBIN0RRVCGB | F150: 31.82 | G150: 1667.718 | H150: 0 | I150: 1668
A151: 20010023 | B151: 0010 | C151: Sudama Gope | D151: 371101000002155 | E151: IOBA0003711 | F151: 8.22 | G151: 329.4634 | H151: 0 | I151: 329
A152: 20010023 | B152: 0011 | C152: Geeta Devi | D152: 22016749426 | E152: SBIN0RRVCGB | F152: 47.6 | G152: 1959.6806 | H152: 0 | I152: 1960
A153: 20010023 | B153: 0015 | C153: Charo Munda | D153: 494310100006547 | E153: BKID0004943 | F153: 39.07 | G153: 1781.7679 | H153: 0 | I153: 1782
A154: 20010023 | B154: 0016 | C154: Rani Devi | D154: 494310110014797 | E154: BKID0004943 | F154: 54.51 | G154: 2282.3886 | H154: 0 | I154: 2282
A155: 20010023 | B155: 0021 | C155: Dhaneshwar Gop | D155: 494310110002166 | E155: BKID0004943 | F155: 75.65 | G155: 3098.7116 | H155: 0 | I155: 3099
A156: 20010023 | B156: 0023 | C156: Shani Munda | D156: 7203940137 | E156: IDIB000N518 | F156: 61.76 | G156: 2653.8508 | H156: 0 | I156: 2654
A157: 20010023 | B157: 0024 | C157: Rupan Devi | D157: 494310110016123 | E157: BKID0004943 | F157: 33.93 | G157: 1371.7776 | H157: 0 | I157: 1372
A158: 20010023 | B158: 0026 | C158: Rajesh Gop | D158: 494318210002779 | E158: BKID0004943 | F158: 68.47 | G158: 3983.4398 | H158: 0 | I158: 3983
A159: 20010023 | B159: 0027 | C159: Chhoti Devi | D159: 371101000005125 | E159: IOBA0003711 | F159: 14.7 | G159: 604.2096 | H159: 0 | I159: 604
...

Sheet MPG Payment
F2: New Format | H2: Reg. Farmers | J2: Unreg. Farmers | L2: Total farmer
A3: BMC Code | B3: Code | C3: MPG NAME | D3: Type | E3: Farmer Payment | F3: BMC Volume | G3: BMC Amount | H3: Reg Vol | I3: reg Amt | J3: Unreg Vol | K3: Unreg Amt | L3: Total Vol | M3: Total Amt | N3: Payable | O3: TS Loss | P3: Deduction for excess payment | Q3: Loss Apportion | R3: CF Deduction | S3: Vet Deduction | T3: Advance | U3: Others | V3: Payment to Farmer A/c | W3: Unreg. Farmer payment | X3: Payment to MPGs A/c | Y3: Closing Reserve | Z3: Stop Payment | AA3: Diff | AB3: loss/gain | AC3: No of Farmers | AD3: Cycle | AE3: Remarks | AF3: CF OS | AG3: Deduction | AH3: Balance | AI3: CF OS Aging in Days
A4: BMC Code :2001 | B4: 20010001 | C4: Itki | D4: RMC | E4: =IFERROR(VLOOKUP(B4,Table2[[Code]:[Category]],13,0),"Indirect") -> Direct | F4: 11527.96 | G4: 489972.14 | H4: =SUMIFS(Table2[Vol_L],Table2[Code],'MPG Payment'!$B4,Table2[Account Details],"Available") -> 11528.02 | I4: =SUMIFS(Table2[Amount],Table2[Code],'MPG Payment'!$B4,Table2[Account Details],"Available") -> 489944.47 | J4: =IF(E4="direct",SUMIFS(Table2[Vol_L],Table2[Code],'MPG Payment'!$B4,Table2[Account Details],"Not Available"),0) -> 0 | K4: =IF(E4="direct",SUMIFS(Table2[Amount],Table2[Code],'MPG Payment'!$B4,Table2[Account Details],"Not Available"),0) -> 0 | L4: =H4+J4 -> 11528.02 | M4: =I4+K4 -> 489944.47 | N4: =IF(E4="indirect",G4,MIN(G4,M4)) -> 489944.47 | O4: =SUMIFS(Table2[TS Loss],Table2[Code],'MPG Payment'!$B4) -> 14964 | P4: =SUMIFS(Table2[Deduction for excess payment],Table2[Code],'MPG Payment'!$B4) -> 0 | Q4: =IF(M4>G4,(M4-G4),0) -> 0 | R4: =SUMIF(Table2[Code],'MPG Payment'!$B4,Table2[CF Deduction]) -> 0 | S4: =SUMIF('Farmer Payment Calc'!D:D,'MPG Payment'!B4,'Farmer Payment Calc'!M:M) -> 0 | T4: 0 | U4: 0 | V4: =IF(E4="direct",SUMIFS(Table2[Net Amount],Table2[Code],'MPG Payment'!$B4,Table2[Account Details],"Available"),0) -> 474980 | W4: =IF(E4="direct",SUMIFS(Table2[Net Amount],Table2[Code],'MPG Payment'!$B4,Table2[Account Details],"Not Available"),0) -> 0 | X4: =IF(Z4="Yes",0,IF(E4="indirect",(G4-O4-P4-R4-T4-U4-S4),0)) -> 0 | Y4: =IF(E4="direct",(G4-O4-P4-V4-X4-R4-S4-T4-U4),0)-W4 -> 28.14 | Z4: 0 | AA4: =ROUND(+N4-O4-P4-R4-T4-V4-W4-X4-S4,0)-U4 -> 0 | AB4: =(M4-G4)/G4 -> -5.6474231e-05 | AC4: =COUNTIF(Table2[Code],'MPG Payment'!B4) -> 21 | AD4: {=SUBSTITUTE(SUBSTITUTE(MID(CELL("filename"),FIND("[",CELL("filename"))+1,FIND("]",CELL("filename"))-FIND("[",CELL("filename"))-1),"JH Farmer Payment-",""),".xlsx","")} -> Indent | AF4: 0 | AG4: 0 | AH4: =AF4-AG4 -> 0 | AI4: 0
A5: BMC Code :2001 | B5: 20010002 | C5: Jamtoli | D5: MPG | E5: =IFERROR(VLOOKUP(B5,Table2[[Code]:[Category]],13,0),"Indirect") -> Direct | F5: 13.18 | G5: 498.36 | H5: =SUMIFS(Table2[Vol_L],Table2[Code],'MPG Payment'!$B5,Table2[Account Details],"Available") -> 12 | I5: =SUMIFS(Table2[Amount],Table2[Code],'MPG Payment'!$B5,Table2[Account Details],"Available") -> 495 | J5: =IF(E5="direct",SUMIFS(Table2[Vol_L],Table2[Code],'MPG Payment'!$B5,Table2[Account Details],"Not Available"),0) -> 0 | K5: =IF(E5="direct",SUMIFS(Table2[Amount],Table2[Code],'MPG Payment'!$B5,Table2[Account Details],"Not Available"),0) -> 0 | L5: =H5+J5 -> 12 | M5: =I5+K5 -> 495 | N5: =IF(E5="indirect",G5,MIN(G5,M5)) -> 495 | O5: =SUMIFS(Table2[TS Loss],Table2[Code],'MPG Payment'!$B5) -> 0 | P5: =SUMIFS(Table2[Deduction for excess payment],Table2[Code],'MPG Payment'!$B5) -> 0 | Q5: =IF(M5>G5,(M5-G5),0) -> 0 | R5: =SUMIF(Table2[Code],'MPG Payment'!$B5,Table2[CF Deduction]) -> 0 | S5: =SUMIF('Farmer Payment Calc'!D:D,'MPG Payment'!B5,'Farmer Payment Calc'!M:M) -> 0 | T5: 0 | U5: 0 | V5: =IF(E5="direct",SUMIFS(Table2[Net Amount],Table2[Code],'MPG Payment'!$B5,Table2[Account Details],"Available"),0) -> 495 | W5: =IF(E5="direct",SUMIFS(Table2[Net Amount],Table2[Code],'MPG Payment'!$B5,Table2[Account Details],"Not Available"),0) -> 0 | X5: =IF(Z5="Yes",0,IF(E5="indirect",(G5-O5-P5-R5-T5-U5-S5),0)) -> 0 | Y5: =IF(E5="direct",(G5-O5-P5-V5-X5-R5-S5-T5-U5),0)-W5 -> 3.36 | Z5: 0 | AA5: =ROUND(+N5-O5-P5-R5-T5-V5-W5-X5-S5,0)-U5 -> 0 | AB5: =(M5-G5)/G5 -> -0.0067421141 | AC5: =COUNTIF(Table2[Code],'MPG Payment'!B5) -> 1 | AD5: {=SUBSTITUTE(SUBSTITUTE(MID(CELL("filename"),FIND("[",CELL("filename"))+1,FIND("]",CELL("filename"))-FIND("[",CELL("filename"))-1),"JH Farmer Payment-",""),".xlsx","")} -> Indent | AF5: 0 | AG5: 0 | AH5: =AF5-AG5 -> 0 | AI5: 0
A6: BMC Code :2001 | B6: 20010003 | C6: Bero | D6: MPG | E6: =IFERROR(VLOOKUP(B6,Table2[[Code]:[Category]],13,0),"Indirect") -> Direct | F6: 1387.17 | G6: 56177.98 | H6: =SUMIFS(Table2[Vol_L],Table2[Code],'MPG Payment'!$B6,Table2[Account Details],"Available") -> 1397.04 | I6: =SUMIFS(Table2[Amount],Table2[Code],'MPG Payment'!$B6,Table2[Account Details],"Available") -> 57657.305 | J6: =IF(E6="direct",SUMIFS(Table2[Vol_L],Table2[Code],'MPG Payment'!$B6,Table2[Account Details],"Not Available"),0) -> 0 | K6: =IF(E6="direct",SUMIFS(Table2[Amount],Table2[Code],'MPG Payment'!$B6,Table2[Account Details],"Not Available"),0) -> 0 | L6: =H6+J6 -> 1397.04 | M6: =I6+K6 -> 57657.305 | N6: =IF(E6="indirect",G6,MIN(G6,M6)) -> 56177.98 | O6: =SUMIFS(Table2[TS Loss],Table2[Code],'MPG Payment'!$B6) -> 0 | P6: =SUMIFS(Table2[Deduction for excess payment],Table2[Code],'MPG Payment'!$B6) -> 0 | Q6: =IF(M6>G6,(M6-G6),0) -> 1479.3247 | R6: =SUMIF(Table2[Code],'MPG Payment'!$B6,Table2[CF Deduction]) -> 10160 | S6: =SUMIF('Farmer Payment Calc'!D:D,'MPG Payment'!B6,'Farmer Payment Calc'!M:M) -> 0 | T6: 0 | U6: 0 | V6: =IF(E6="direct",SUMIFS(Table2[Net Amount],Table2[Code],'MPG Payment'!$B6,Table2[Account Details],"Available"),0) -> 46018 | W6: =IF(E6="direct",SUMIFS(Table2[Net Amount],Table2[Code],'MPG Payment'!$B6,Table2[Account Details],"Not Available"),0) -> 0 | X6: =IF(Z6="Yes",0,IF(E6="indirect",(G6-O6-P6-R6-T6-U6-S6),0)) -> 0 | Y6: =IF(E6="direct",(G6-O6-P6-V6-X6-R6-S6-T6-U6),0)-W6 -> -0.02 | Z6: Release1 | AA6: =ROUND(+N6-O6-P6-R6-T6-V6-W6-X6-S6,0)-U6 -> 0 | AB6: =(M6-G6)/G6 -> 0.026332821 | AC6: =COUNTIF(Table2[Code],'MPG Payment'!B6) -> 10 | AD6: {=SUBSTITUTE(SUBSTITUTE(MID(CELL("filename"),FIND("[",CELL("filename"))+1,FIND("]",CELL("filename"))-FIND("[",CELL("filename"))-1),"JH Farmer Payment-",""),".xlsx","")} -> Indent | AE6: Letter not received | AF6: 0 | AG6: 0 | AH6: =AF6-AG6 -> 0 | AI6: 0
A7: BMC Code :2001 | B7: 20010005 | C7: Basila | D7: MPG | E7: =IFERROR(VLOOKUP(B7,Table2[[Code]:[Category]],13,0),"Indirect") -> Direct | F7: 1374.42 | G7: 54973.01 | H7: =SUMIFS(Table2[Vol_L],Table2[Code],'MPG Payment'!$B7,Table2[Account Details],"Available") -> 1352.05 | I7: =SUMIFS(Table2[Amount],Table2[Code],'MPG Payment'!$B7,Table2[Account Details],"Available") -> 54956.825 | J7: =IF(E7="direct",SUMIFS(Table2[Vol_L],Table2[Code],'MPG Payment'!$B7,Table2[Account Details],"Not Available"),0) -> 0 | K7: =IF(E7="direct",SUMIFS(Table2[Amount],Table2[Code],'MPG Payment'!$B7,Table2[Account Details],"Not Available"),0) -> 0 | L7: =H7+J7 -> 1352.05 | M7: =I7+K7 -> 54956.825 | N7: =IF(E7="indirect",G7,MIN(G7,M7)) -> 54956.825 | O7: =SUMIFS(Table2[TS Loss],Table2[Code],'MPG Payment'!$B7) -> 0 | P7: =SUMIFS(Table2[Deduction for excess payment],Table2[Code],'MPG Payment'!$B7) -> 0 | Q7: =IF(M7>G7,(M7-G7),0) -> 0 | R7: =SUMIF(Table2[Code],'MPG Payment'!$B7,Table2[CF Deduction]) -> 0 | S7: =SUMIF('Farmer Payment Calc'!D:D,'MPG Payment'!B7,'Farmer Payment Calc'!M:M) -> 0 | T7: 0 | U7: 0 | V7: =IF(E7="direct",SUMIFS(Table2[Net Amount],Table2[Code],'MPG Payment'!$B7,Table2[Account Details],"Available"),0) -> 54958 | W7: =IF(E7="direct",SUMIFS(Table2[Net Amount],Table2[Code],'MPG Payment'!$B7,Table2[Account Details],"Not Available"),0) -> 0 | X7: =IF(Z7="Yes",0,IF(E7="indirect",(G7-O7-P7-R7-T7-U7-S7),0)) -> 0 | Y7: =IF(E7="direct",(G7-O7-P7-V7-X7-R7-S7-T7-U7),0)-W7 -> 15.01 | Z7: 0 | AA7: =ROUND(+N7-O7-P7-R7-T7-V7-W7-X7-S7,0)-U7 -> -1 | AB7: =(M7-G7)/G7 -> -0.00029442448 | AC7: =COUNTIF(Table2[Code],'MPG Payment'!B7) -> 23 | AD7: {=SUBSTITUTE(SUBSTITUTE(MID(CELL("filename"),FIND("[",CELL("filename"))+1,FIND("]",CELL("filename"))-FIND("[",CELL("filename"))-1),"JH Farmer Payment-",""),".xlsx","")} -> Indent | AF7: 0 | AG7: 0 | AH7: =AF7-AG7 -> 0 | AI7: 0
A8: BMC Code :2001 | B8: 20010008 | C8: Erchoro | D8: MPG | E8: =IFERROR(VLOOKUP(B8,Table2[[Code]:[Category]],13,0),"Indirect") -> Direct | F8: 1215.92 | G8: 48622.24 | H8: =SUMIFS(Table2[Vol_L],Table2[Code],'MPG Payment'!$B8,Table2[Account Details],"Available") -> 1185.43 | I8: =SUMIFS(Table2[Amount],Table2[Code],'MPG Payment'!$B8,Table2[Account Details],"Available") -> 48571.347 | J8: =IF(E8="direct",SUMIFS(Table2[Vol_L],Table2[Code],'MPG Payment'!$B8,Table2[Account Details],"Not Available"),0) -> 0 | K8: =IF(E8="direct",SUMIFS(Table2[Amount],Table2[Code],'MPG Payment'!$B8,Table2[Account Details],"Not Available"),0) -> 0 | L8: =H8+J8 -> 1185.43 | M8: =I8+K8 -> 48571.347 | N8: =IF(E8="indirect",G8,MIN(G8,M8)) -> 48571.347 | O8: =SUMIFS(Table2[TS Loss],Table2[Code],'MPG Payment'!$B8) -> 0 | P8: =SUMIFS(Table2[Deduction for excess payment],Table2[Code],'MPG Payment'!$B8) -> 0 | Q8: =IF(M8>G8,(M8-G8),0) -> 0 | R8: =SUMIF(Table2[Code],'MPG Payment'!$B8,Table2[CF Deduction]) -> 0 | S8: =SUMIF('Farmer Payment Calc'!D:D,'MPG Payment'!B8,'Farmer Payment Calc'!M:M) -> 0 | T8: 0 | U8: 0 | V8: =IF(E8="direct",SUMIFS(Table2[Net Amount],Table2[Code],'MPG Payment'!$B8,Table2[Account Details],"Available"),0) -> 48571 | W8: =IF(E8="direct",SUMIFS(Table2[Net Amount],Table2[Code],'MPG Payment'!$B8,Table2[Account Details],"Not Available"),0) -> 0 | X8: =IF(Z8="Yes",0,IF(E8="indirect",(G8-O8-P8-R8-T8-U8-S8),0)) -> 0 | Y8: =IF(E8="direct",(G8-O8-P8-V8-X8-R8-S8-T8-U8),0)-W8 -> 51.24 | Z8: 0 | AA8: =ROUND(+N8-O8-P8-R8-T8-V8-W8-X8-S8,0)-U8 -> 0 | AB8: =(M8-G8)/G8 -> -0.0010467041 | AC8: =COUNTIF(Table2[Code],'MPG Payment'!B8) -> 14 | AD8: {=SUBSTITUTE(SUBSTITUTE(MID(CELL("filename"),FIND("[",CELL("filename"))+1,FIND("]",CELL("filename"))-FIND("[",CELL("filename"))-1),"JH Farmer Payment-",""),".xlsx","")} -> Indent | AF8: 0 | AG8: 0 | AH8: =AF8-AG8 -> 0 | AI8: 0
A9: BMC Code :2001 | B9: 20010009 | C9: Makunda | D9: MPG | E9: =IFERROR(VLOOKUP(B9,Table2[[Code]:[Category]],13,0),"Indirect") -> Direct | F9: 644.44 | G9: 27222.79 | H9: =SUMIFS(Table2[Vol_L],Table2[Code],'MPG Payment'!$B9,Table2[Account Details],"Available") -> 651.48 | I9: =SUMIFS(Table2[Amount],Table2[Code],'MPG Payment'!$B9,Table2[Account Details],"Available") -> 27178.347 | J9: =IF(E9="direct",SUMIFS(Table2[Vol_L],Table2[Code],'MPG Payment'!$B9,Table2[Account Details],"Not Available"),0) -> 0 | K9: =IF(E9="direct",SUMIFS(Table2[Amount],Table2[Code],'MPG Payment'!$B9,Table2[Account Details],"Not Available"),0) -> 0 | L9: =H9+J9 -> 651.48 | M9: =I9+K9 -> 27178.347 | N9: =IF(E9="indirect",G9,MIN(G9,M9)) -> 27178.347 | O9: =SUMIFS(Table2[TS Loss],Table2[Code],'MPG Payment'!$B9) -> 0 | P9: =SUMIFS(Table2[Deduction for excess payment],Table2[Code],'MPG Payment'!$B9) -> 0 | Q9: =IF(M9>G9,(M9-G9),0) -> 0 | R9: =SUMIF(Table2[Code],'MPG Payment'!$B9,Table2[CF Deduction]) -> 0 | S9: =SUMIF('Farmer Payment Calc'!D:D,'MPG Payment'!B9,'Farmer Payment Calc'!M:M) -> 0 | T9: 0 | U9: 0 | V9: =IF(E9="direct",SUMIFS(Table2[Net Amount],Table2[Code],'MPG Payment'!$B9,Table2[Account Details],"Available"),0) -> 27179 | W9: =IF(E9="direct",SUMIFS(Table2[Net Amount],Table2[Code],'MPG Payment'!$B9,Table2[Account Details],"Not Available"),0) -> 0 | X9: =IF(Z9="Yes",0,IF(E9="indirect",(G9-O9-P9-R9-T9-U9-S9),0)) -> 0 | Y9: =IF(E9="direct",(G9-O9-P9-V9-X9-R9-S9-T9-U9),0)-W9 -> 43.79 | Z9: 0 | AA9: =ROUND(+N9-O9-P9-R9-T9-V9-W9-X9-S9,0)-U9 -> -1 | AB9: =(M9-G9)/G9 -> -0.0016325476 | AC9: =COUNTIF(Table2[Code],'MPG Payment'!B9) -> 7 | AD9: {=SUBSTITUTE(SUBSTITUTE(MID(CELL("filename"),FIND("[",CELL("filename"))+1,FIND("]",CELL("filename"))-FIND("[",CELL("filename"))-1),"JH Farmer Payment-",""),".xlsx","")} -> Indent | AF9: 0 | AG9: 0 | AH9: =AF9-AG9 -> 0 | AI9: 0
A10: BMC Code :2001 | B10: 20010012 | C10: NAGRI | D10: VLC | E10: =IFERROR(VLOOKUP(B10,Table2[[Code]:[Category]],13,0),"Indirect") -> Indirect | F10: 276.5 | G10: 8623.76 | H10: =SUMIFS(Table2[Vol_L],Table2[Code],'MPG Payment'!$B10,Table2[Account Details],"Available") -> 0 | I10: =SUMIFS(Table2[Amount],Table2[Code],'MPG Payment'!$B10,Table2[Account Details],"Available") -> 0 | J10: =IF(E10="direct",SUMIFS(Table2[Vol_L],Table2[Code],'MPG Payment'!$B10,Table2[Account Details],"Not Available"),0) -> 0 | K10: =IF(E10="direct",SUMIFS(Table2[Amount],Table2[Code],'MPG Payment'!$B10,Table2[Account Details],"Not Available"),0) -> 0 | L10: =H10+J10 -> 0 | M10: =I10+K10 -> 0 | N10: =IF(E10="indirect",G10,MIN(G10,M10)) -> 8623.76 | O10: =SUMIFS(Table2[TS Loss],Table2[Code],'MPG Payment'!$B10) -> 0 | P10: =SUMIFS(Table2[Deduction for excess payment],Table2[Code],'MPG Payment'!$B10) -> 0 | Q10: =IF(M10>G10,(M10-G10),0) -> 0 | R10: =SUMIF(Table2[Code],'MPG Payment'!$B10,Table2[CF Deduction]) -> 0 | S10: =SUMIF('Farmer Payment Calc'!D:D,'MPG Payment'!B10,'Farmer Payment Calc'!M:M) -> 0 | T10: 0 | U10: 0 | V10: =IF(E10="direct",SUMIFS(Table2[Net Amount],Table2[Code],'MPG Payment'!$B10,Table2[Account Details],"Available"),0) -> 0 | W10: =IF(E10="direct",SUMIFS(Table2[Net Amount],Table2[Code],'MPG Payment'!$B10,Table2[Account Details],"Not Available"),0) -> 0 | X10: =IF(Z10="Yes",0,IF(E10="indirect",(G10-O10-P10-R10-T10-U10-S10),0)) -> 8623.76 | Y10: =IF(E10="direct",(G10-O10-P10-V10-X10-R10-S10-T10-U10),0)-W10 -> 0 | Z10: 0 | AA10: =ROUND(+N10-O10-P10-R10-T10-V10-W10-X10-S10,0)-U10 -> 0 | AB10: =(M10-G10)/G10 -> -1 | AC10: =COUNTIF(Table2[Code],'MPG Payment'!B10) -> 0 | AD10: {=SUBSTITUTE(SUBSTITUTE(MID(CELL("filename"),FIND("[",CELL("filename"))+1,FIND("]",CELL("filename"))-FIND("[",CELL("filename"))-1),"JH Farmer Payment-",""),".xlsx","")} -> Indent | AF10: 0 | AG10: 0 | AH10: =AF10-AG10 -> 0 | AI10: 0
A11: BMC Code :2001 | B11: 20010015 | C11: BOREYA | D11: MPG | E11: =IFERROR(VLOOKUP(B11,Table2[[Code]:[Category]],13,0),"Indirect") -> Direct | F11: 2661.3 | G11: 108173.94 | H11: =SUMIFS(Table2[Vol_L],Table2[Code],'MPG Payment'!$B11,Table2[Account Details],"Available") -> 2579.38 | I11: =SUMIFS(Table2[Amount],Table2[Code],'MPG Payment'!$B11,Table2[Account Details],"Available") -> 107851.96 | J11: =IF(E11="direct",SUMIFS(Table2[Vol_L],Table2[Code],'MPG Payment'!$B11,Table2[Account Details],"Not Available"),0) -> 0 | K11: =IF(E11="direct",SUMIFS(Table2[Amount],Table2[Code],'MPG Payment'!$B11,Table2[Account Details],"Not Available"),0) -> 0 | L11: =H11+J11 -> 2579.38 | M11: =I11+K11 -> 107851.96 | N11: =IF(E11="indirect",G11,MIN(G11,M11)) -> 107851.96 | O11: =SUMIFS(Table2[TS Loss],Table2[Code],'MPG Payment'!$B11) -> 0 | P11: =SUMIFS(Table2[Deduction for excess payment],Table2[Code],'MPG Payment'!$B11) -> 0 | Q11: =IF(M11>G11,(M11-G11),0) -> 0 | R11: =SUMIF(Table2[Code],'MPG Payment'!$B11,Table2[CF Deduction]) -> 0 | S11: =SUMIF('Farmer Payment Calc'!D:D,'MPG Payment'!B11,'Farmer Payment Calc'!M:M) -> 0 | T11: 0 | U11: 0 | V11: =IF(E11="direct",SUMIFS(Table2[Net Amount],Table2[Code],'MPG Payment'!$B11,Table2[Account Details],"Available"),0) -> 107853 | W11: =IF(E11="direct",SUMIFS(Table2[Net Amount],Table2[Code],'MPG Payment'!$B11,Table2[Account Details],"Not Available"),0) -> 0 | X11: =IF(Z11="Yes",0,IF(E11="indirect",(G11-O11-P11-R11-T11-U11-S11),0)) -> 0 | Y11: =IF(E11="direct",(G11-O11-P11-V11-X11-R11-S11-T11-U11),0)-W11 -> 320.94 | Z11: 0 | AA11: =ROUND(+N11-O11-P11-R11-T11-V11-W11-X11-S11,0)-U11 -> -1 | AB11: =(M11-G11)/G11 -> -0.0029764747 | AC11: =COUNTIF(Table2[Code],'MPG Payment'!B11) -> 53 | AD11: {=SUBSTITUTE(SUBSTITUTE(MID(CELL("filename"),FIND("[",CELL("filename"))+1,FIND("]",CELL("filename"))-FIND("[",CELL("filename"))-1),"JH Farmer Payment-",""),".xlsx","")} -> Indent | AF11: 0 | AG11: 0 | AH11: =AF11-AG11 -> 0 | AI11: 0
A12: BMC Code :2001 | B12: 20010017 | C12: DIGHIYA | D12: MPG | E12: =IFERROR(VLOOKUP(B12,Table2[[Code]:[Category]],13,0),"Indirect") -> Direct | F12: 323.26 | G12: 13720.72 | H12: =SUMIFS(Table2[Vol_L],Table2[Code],'MPG Payment'!$B12,Table2[Account Details],"Available") -> 314.54 | I12: =SUMIFS(Table2[Amount],Table2[Code],'MPG Payment'!$B12,Table2[Account Details],"Available") -> 14115.361 | J12: =IF(E12="direct",SUMIFS(Table2[Vol_L],Table2[Code],'MPG Payment'!$B12,Table2[Account Details],"Not Available"),0) -> 0 | K12: =IF(E12="direct",SUMIFS(Table2[Amount],Table2[Code],'MPG Payment'!$B12,Table2[Account Details],"Not Available"),0) -> 0 | L12: =H12+J12 -> 314.54 | M12: =I12+K12 -> 14115.361 | N12: =IF(E12="indirect",G12,MIN(G12,M12)) -> 13720.72 | O12: =SUMIFS(Table2[TS Loss],Table2[Code],'MPG Payment'!$B12) -> 0 | P12: =SUMIFS(Table2[Deduction for excess payment],Table2[Code],'MPG Payment'!$B12) -> 0 | Q12: =IF(M12>G12,(M12-G12),0) -> 394.6409 | R12: =SUMIF(Table2[Code],'MPG Payment'!$B12,Table2[CF Deduction]) -> 0 | S12: =SUMIF('Farmer Payment Calc'!D:D,'MPG Payment'!B12,'Farmer Payment Calc'!M:M) -> 0 | T12: 0 | U12: 0 | V12: =IF(E12="direct",SUMIFS(Table2[Net Amount],Table2[Code],'MPG Payment'!$B12,Table2[Account Details],"Available"),0) -> 13721 | W12: =IF(E12="direct",SUMIFS(Table2[Net Amount],Table2[Code],'MPG Payment'!$B12,Table2[Account Details],"Not Available"),0) -> 0 | X12: =IF(Z12="Yes",0,IF(E12="indirect",(G12-O12-P12-R12-T12-U12-S12),0)) -> 0 | Y12: =IF(E12="direct",(G12-O12-P12-V12-X12-R12-S12-T12-U12),0)-W12 -> -0.28 | Z12: 0 | AA12: =ROUND(+N12-O12-P12-R12-T12-V12-W12-X12-S12,0)-U12 -> 0 | AB12: =(M12-G12)/G12 -> 0.028762405 | AC12: =COUNTIF(Table2[Code],'MPG Payment'!B12) -> 9 | AD12: {=SUBSTITUTE(SUBSTITUTE(MID(CELL("filename"),FIND("[",CELL("filename"))+1,FIND("]",CELL("filename"))-FIND("[",CELL("filename"))-1),"JH Farmer Payment-",""),".xlsx","")} -> Indent | AF12: 0 | AG12: 0 | AH12: =AF12-AG12 -> 0 | AI12: 0
A13: BMC Code :2001 | B13: 20010023 | C13: KATARPA | D13: MPG | E13: =IFERROR(VLOOKUP(B13,Table2[[Code]:[Category]],13,0),"Indirect") -> Direct | F13: 818.18 | G13: 36830.69 | H13: =SUMIFS(Table2[Vol_L],Table2[Code],'MPG Payment'!$B13,Table2[Account Details],"Available") -> 833.65 | I13: =SUMIFS(Table2[Amount],Table2[Code],'MPG Payment'!$B13,Table2[Account Details],"Available") -> 36796.528 | J13: =IF(E13="direct",SUMIFS(Table2[Vol_L],Table2[Code],'MPG Payment'!$B13,Table2[Account Details],"Not Available"),0) -> 0 | K13: =IF(E13="direct",SUMIFS(Table2[Amount],Table2[Code],'MPG Payment'!$B13,Table2[Account Details],"Not Available"),0) -> 0 | L13: =H13+J13 -> 833.65 | M13: =I13+K13 -> 36796.528 | N13: =IF(E13="indirect",G13,MIN(G13,M13)) -> 36796.528 | O13: =SUMIFS(Table2[TS Loss],Table2[Code],'MPG Payment'!$B13) -> 0 | P13: =SUMIFS(Table2[Deduction for excess payment],Table2[Code],'MPG Payment'!$B13) -> 0 | Q13: =IF(M13>G13,(M13-G13),0) -> 0 | R13: =SUMIF(Table2[Code],'MPG Payment'!$B13,Table2[CF Deduction]) -> 0 | S13: =SUMIF('Farmer Payment Calc'!D:D,'MPG Payment'!B13,'Farmer Payment Calc'!M:M) -> 0 | T13: 0 | U13: 0 | V13: =IF(E13="direct",SUMIFS(Table2[Net Amount],Table2[Code],'MPG Payment'!$B13,Table2[Account Details],"Available"),0) -> 36797 | W13: =IF(E13="direct",SUMIFS(Table2[Net Amount],Table2[Code],'MPG Payment'!$B13,Table2[Account Details],"Not Available"),0) -> 0 | X13: =IF(Z13="Yes",0,IF(E13="indirect",(G13-O13-P13-R13-T13-U13-S13),0)) -> 0 | Y13: =IF(E13="direct",(G13-O13-P13-V13-X13-R13-S13-T13-U13),0)-W13 -> 33.69 | Z13: 0 | AA13: =ROUND(+N13-O13-P13-R13-T13-V13-W13-X13-S13,0)-U13 -> 0 | AB13: =(M13-G13)/G13 -> -0.00092754711 | AC13: =COUNTIF(Table2[Code],'MPG Payment'!B13) -> 22 | AD13: {=SUBSTITUTE(SUBSTITUTE(MID(CELL("filename"),FIND("[",CELL("filename"))+1,FIND("]",CELL("filename"))-FIND("[",CELL("filename"))-1),"JH Farmer Payment-",""),".xlsx","")} -> Indent | AF13: 0 | AG13: 0 | AH13: =AF13-AG13 -> 0 | AI13: 0
A14: BMC Code :2001 | B14: 20010027 | C14: MURTO | D14: MPG | E14: =IFERROR(VLOOKUP(B14,Table2[[Code]:[Category]],13,0),"Indirect") -> Direct | F14: 303.5 | G14: 12944.57 | H14: =SUMIFS(Table2[Vol_L],Table2[Code],'MPG Payment'!$B14,Table2[Account Details],"Available") -> 309.38 | I14: =SUMIFS(Table2[Amount],Table2[Code],'MPG Payment'!$B14,Table2[Account Details],"Available") -> 12909.007 | J14: =IF(E14="direct",SUMIFS(Table2[Vol_L],Table2[Code],'MPG Payment'!$B14,Table2[Account Details],"Not Available"),0) -> 0 | K14: =IF(E14="direct",SUMIFS(Table2[Amount],Table2[Code],'MPG Payment'!$B14,Table2[Account Details],"Not Available"),0) -> 0 | L14: =H14+J14 -> 309.38 | M14: =I14+K14 -> 12909.007 | N14: =IF(E14="indirect",G14,MIN(G14,M14)) -> 12909.007 | O14: =SUMIFS(Table2[TS Loss],Table2[Code],'MPG Payment'!$B14) -> 0 | P14: =SUMIFS(Table2[Deduction for excess payment],Table2[Code],'MPG Payment'!$B14) -> 0 | Q14: =IF(M14>G14,(M14-G14),0) -> 0 | R14: =SUMIF(Table2[Code],'MPG Payment'!$B14,Table2[CF Deduction]) -> 0 | S14: =SUMIF('Farmer Payment Calc'!D:D,'MPG Payment'!B14,'Farmer Payment Calc'!M:M) -> 0 | T14: 0 | U14: 0 | V14: =IF(E14="direct",SUMIFS(Table2[Net Amount],Table2[Code],'MPG Payment'!$B14,Table2[Account Details],"Available"),0) -> 12910 | W14: =IF(E14="direct",SUMIFS(Table2[Net Amount],Table2[Code],'MPG Payment'!$B14,Table2[Account Details],"Not Available"),0) -> 0 | X14: =IF(Z14="Yes",0,IF(E14="indirect",(G14-O14-P14-R14-T14-U14-S14),0)) -> 0 | Y14: =IF(E14="direct",(G14-O14-P14-V14-X14-R14-S14-T14-U14),0)-W14 -> 34.57 | Z14: 0 | AA14: =ROUND(+N14-O14-P14-R14-T14-V14-W14-X14-S14,0)-U14 -> -1 | AB14: =(M14-G14)/G14 -> -0.002747345 | AC14: =COUNTIF(Table2[Code],'MPG Payment'!B14) -> 10 | AD14: {=SUBSTITUTE(SUBSTITUTE(MID(CELL("filename"),FIND("[",CELL("filename"))+1,FIND("]",CELL("filename"))-FIND("[",CELL("filename"))-1),"JH Farmer Payment-",""),".xlsx","")} -> Indent | AF14: 0 | AG14: 0 | AH14: =AF14-AG14 -> 0 | AI14: 0
A15: BMC Code :2001 | B15: 20010033 | C15: KHATRIKHATANGA | D15: MPG | E15: =IFERROR(VLOOKUP(B15,Table2[[Code]:[Category]],13,0),"Indirect") -> Direct | F15: 369.44 | G15: 16065.11 | H15: =SUMIFS(Table2[Vol_L],Table2[Code],'MPG Payment'!$B15,Table2[Account Details],"Available") -> 371.89 | I15: =SUMIFS(Table2[Amount],Table2[Code],'MPG Payment'!$B15,Table2[Account Details],"Available") -> 16411.3 | J15: =IF(E15="direct",SUMIFS(Table2[Vol_L],Table2[Code],'MPG Payment'!$B15,Table2[Account Details],"Not Available"),0) -> 0 | K15: =IF(E15="direct",SUMIFS(Table2[Amount],Table2[Code],'MPG Payment'!$B15,Table2[Account Details],"Not Available"),0) -> 0 | L15: =H15+J15 -> 371.89 | M15: =I15+K15 -> 16411.3 | N15: =IF(E15="indirect",G15,MIN(G15,M15)) -> 16065.11 | O15: =SUMIFS(Table2[TS Loss],Table2[Code],'MPG Payment'!$B15) -> 0 | P15: =SUMIFS(Table2[Deduction for excess payment],Table2[Code],'MPG Payment'!$B15) -> 0 | Q15: =IF(M15>G15,(M15-G15),0) -> 346.1899 | R15: =SUMIF(Table2[Code],'MPG Payment'!$B15,Table2[CF Deduction]) -> 0 | S15: =SUMIF('Farmer Payment Calc'!D:D,'MPG Payment'!B15,'Farmer Payment Calc'!M:M) -> 0 | T15: 0 | U15: 0 | V15: =IF(E15="direct",SUMIFS(Table2[Net Amount],Table2[Code],'MPG Payment'!$B15,Table2[Account Details],"Available"),0) -> 16065 | W15: =IF(E15="direct",SUMIFS(Table2[Net Amount],Table2[Code],'MPG Payment'!$B15,Table2[Account Details],"Not Available"),0) -> 0 | X15: =IF(Z15="Yes",0,IF(E15="indirect",(G15-O15-P15-R15-T15-U15-S15),0)) -> 0 | Y15: =IF(E15="direct",(G15-O15-P15-V15-X15-R15-S15-T15-U15),0)-W15 -> 0.11 | Z15: 0 | AA15: =ROUND(+N15-O15-P15-R15-T15-V15-W15-X15-S15,0)-U15 -> 0 | AB15: =(M15-G15)/G15 -> 0.021549177 | AC15: =COUNTIF(Table2[Code],'MPG Payment'!B15) -> 2 | AD15: {=SUBSTITUTE(SUBSTITUTE(MID(CELL("filename"),FIND("[",CELL("filename"))+1,FIND("]",CELL("filename"))-FIND("[",CELL("filename"))-1),"JH Farmer Payment-",""),".xlsx","")} -> Indent | AF15: 0 | AG15: 0 | AH15: =AF15-AG15 -> 0 | AI15: 0
A16: BMC Code :2001 | B16: 20010034 | C16: GARGAON | D16: MPG | E16: =IFERROR(VLOOKUP(B16,Table2[[Code]:[Category]],13,0),"Indirect") -> Indirect | F16: 537.98 | G16: 20202.83 | H16: =SUMIFS(Table2[Vol_L],Table2[Code],'MPG Payment'!$B16,Table2[Account Details],"Available") -> 0 | I16: =SUMIFS(Table2[Amount],Table2[Code],'MPG Payment'!$B16,Table2[Account Details],"Available") -> 0 | J16: =IF(E16="direct",SUMIFS(Table2[Vol_L],Table2[Code],'MPG Payment'!$B16,Table2[Account Details],"Not Available"),0) -> 0 | K16: =IF(E16="direct",SUMIFS(Table2[Amount],Table2[Code],'MPG Payment'!$B16,Table2[Account Details],"Not Available"),0) -> 0 | L16: =H16+J16 -> 0 | M16: =I16+K16 -> 0 | N16: =IF(E16="indirect",G16,MIN(G16,M16)) -> 20202.83 | O16: =SUMIFS(Table2[TS Loss],Table2[Code],'MPG Payment'!$B16) -> 0 | P16: =SUMIFS(Table2[Deduction for excess payment],Table2[Code],'MPG Payment'!$B16) -> 0 | Q16: =IF(M16>G16,(M16-G16),0) -> 0 | R16: =SUMIF(Table2[Code],'MPG Payment'!$B16,Table2[CF Deduction]) -> 0 | S16: =SUMIF('Farmer Payment Calc'!D:D,'MPG Payment'!B16,'Farmer Payment Calc'!M:M) -> 0 | T16: 0 | U16: 0 | V16: =IF(E16="direct",SUMIFS(Table2[Net Amount],Table2[Code],'MPG Payment'!$B16,Table2[Account Details],"Available"),0) -> 0 | W16: =IF(E16="direct",SUMIFS(Table2[Net Amount],Table2[Code],'MPG Payment'!$B16,Table2[Account Details],"Not Available"),0) -> 0 | X16: =IF(Z16="Yes",0,IF(E16="indirect",(G16-O16-P16-R16-T16-U16-S16),0)) -> 20202.83 | Y16: =IF(E16="direct",(G16-O16-P16-V16-X16-R16-S16-T16-U16),0)-W16 -> 0 | Z16: 0 | AA16: =ROUND(+N16-O16-P16-R16-T16-V16-W16-X16-S16,0)-U16 -> 0 | AB16: =(M16-G16)/G16 -> -1 | AC16: =COUNTIF(Table2[Code],'MPG Payment'!B16) -> 0 | AD16: {=SUBSTITUTE(SUBSTITUTE(MID(CELL("filename"),FIND("[",CELL("filename"))+1,FIND("]",CELL("filename"))-FIND("[",CELL("filename"))-1),"JH Farmer Payment-",""),".xlsx","")} -> Indent | AF16: 0 | AG16: 0 | AH16: =AF16-AG16 -> 0 | AI16: 0
A17: BMC Code :2001 | B17: 20010036 | C17: GHAGHRA | D17: MPG | E17: =IFERROR(VLOOKUP(B17,Table2[[Code]:[Category]],13,0),"Indirect") -> Direct | F17: 164.99 | G17: 5973.4 | H17: =SUMIFS(Table2[Vol_L],Table2[Code],'MPG Payment'!$B17,Table2[Account Details],"Available") -> 138.11 | I17: =SUMIFS(Table2[Amount],Table2[Code],'MPG Payment'!$B17,Table2[Account Details],"Available") -> 5950.8843 | J17: =IF(E17="direct",SUMIFS(Table2[Vol_L],Table2[Code],'MPG Payment'!$B17,Table2[Account Details],"Not Available"),0) -> 0 | K17: =IF(E17="direct",SUMIFS(Table2[Amount],Table2[Code],'MPG Payment'!$B17,Table2[Account Details],"Not Available"),0) -> 0 | L17: =H17+J17 -> 138.11 | M17: =I17+K17 -> 5950.8843 | N17: =IF(E17="indirect",G17,MIN(G17,M17)) -> 5950.8843 | O17: =SUMIFS(Table2[TS Loss],Table2[Code],'MPG Payment'!$B17) -> 0 | P17: =SUMIFS(Table2[Deduction for excess payment],Table2[Code],'MPG Payment'!$B17) -> 0 | Q17: =IF(M17>G17,(M17-G17),0) -> 0 | R17: =SUMIF(Table2[Code],'MPG Payment'!$B17,Table2[CF Deduction]) -> 0 | S17: =SUMIF('Farmer Payment Calc'!D:D,'MPG Payment'!B17,'Farmer Payment Calc'!M:M) -> 0 | T17: 0 | U17: 0 | V17: =IF(E17="direct",SUMIFS(Table2[Net Amount],Table2[Code],'MPG Payment'!$B17,Table2[Account Details],"Available"),0) -> 5951 | W17: =IF(E17="direct",SUMIFS(Table2[Net Amount],Table2[Code],'MPG Payment'!$B17,Table2[Account Details],"Not Available"),0) -> 0 | X17: =IF(Z17="Yes",0,IF(E17="indirect",(G17-O17-P17-R17-T17-U17-S17),0)) -> 0 | Y17: =IF(E17="direct",(G17-O17-P17-V17-X17-R17-S17-T17-U17),0)-W17 -> 22.4 | Z17: 0 | AA17: =ROUND(+N17-O17-P17-R17-T17-V17-W17-X17-S17,0)-U17 -> 0 | AB17: =(M17-G17)/G17 -> -0.0037693274 | AC17: =COUNTIF(Table2[Code],'MPG Payment'!B17) -> 3 | AD17: {=SUBSTITUTE(SUBSTITUTE(MID(CELL("filename"),FIND("[",CELL("filename"))+1,FIND("]",CELL("filename"))-FIND("[",CELL("filename"))-1),"JH Farmer Payment-",""),".xlsx","")} -> Indent | AF17: 0 | AG17: 0 | AH17: =AF17-AG17 -> 0 | AI17: 0
A18: BMC Code :2001 | B18: 20010037 | C18: CHACHGURA | D18: MPG | E18: =IFERROR(VLOOKUP(B18,Table2[[Code]:[Category]],13,0),"Indirect") -> Indirect | F18: 333.12 | G18: 13031.1 | H18: =SUMIFS(Table2[Vol_L],Table2[Code],'MPG Payment'!$B18,Table2[Account Details],"Available") -> 0 | I18: =SUMIFS(Table2[Amount],Table2[Code],'MPG Payment'!$B18,Table2[Account Details],"Available") -> 0 | J18: =IF(E18="direct",SUMIFS(Table2[Vol_L],Table2[Code],'MPG Payment'!$B18,Table2[Account Details],"Not Available"),0) -> 0 | K18: =IF(E18="direct",SUMIFS(Table2[Amount],Table2[Code],'MPG Payment'!$B18,Table2[Account Details],"Not Available"),0) -> 0 | L18: =H18+J18 -> 0 | M18: =I18+K18 -> 0 | N18: =IF(E18="indirect",G18,MIN(G18,M18)) -> 13031.1 | O18: =SUMIFS(Table2[TS Loss],Table2[Code],'MPG Payment'!$B18) -> 0 | P18: =SUMIFS(Table2[Deduction for excess payment],Table2[Code],'MPG Payment'!$B18) -> 0 | Q18: =IF(M18>G18,(M18-G18),0) -> 0 | R18: =SUMIF(Table2[Code],'MPG Payment'!$B18,Table2[CF Deduction]) -> 0 | S18: =SUMIF('Farmer Payment Calc'!D:D,'MPG Payment'!B18,'Farmer Payment Calc'!M:M) -> 0 | T18: 0 | U18: 0 | V18: =IF(E18="direct",SUMIFS(Table2[Net Amount],Table2[Code],'MPG Payment'!$B18,Table2[Account Details],"Available"),0) -> 0 | W18: =IF(E18="direct",SUMIFS(Table2[Net Amount],Table2[Code],'MPG Payment'!$B18,Table2[Account Details],"Not Available"),0) -> 0 | X18: =IF(Z18="Yes",0,IF(E18="indirect",(G18-O18-P18-R18-T18-U18-S18),0)) -> 13031.1 | Y18: =IF(E18="direct",(G18-O18-P18-V18-X18-R18-S18-T18-U18),0)-W18 -> 0 | Z18: 0 | AA18: =ROUND(+N18-O18-P18-R18-T18-V18-W18-X18-S18,0)-U18 -> 0 | AB18: =(M18-G18)/G18 -> -1 | AC18: =COUNTIF(Table2[Code],'MPG Payment'!B18) -> 0 | AD18: {=SUBSTITUTE(SUBSTITUTE(MID(CELL("filename"),FIND("[",CELL("filename"))+1,FIND("]",CELL("filename"))-FIND("[",CELL("filename"))-1),"JH Farmer Payment-",""),".xlsx","")} -> Indent | AF18: 0 | AG18: 0 | AH18: =AF18-AG18 -> 0 | AI18: 0
... A22: BMC Code :2001 | B22: 20010042 | C22: RONHE | D22: MPG | E22: =IFERROR(VLOOKUP(B22,Table2[[Code]:[Category]],13,0),"Indirect") -> Direct | F22: 887.94 | G22: 38571.58 | H22: =SUMIFS(Table2[Vol_L],Table2[Code],'MPG Payment'!$B22,Table2[Account Details],"Available") -> 867.94 | I22: =SUMIFS(Table2[Amount],Table2[Code],'MPG Payment'!$B22,Table2[Account Details],"Available") -> 38556.261 | J22: =IF(E22="direct",SUMIFS(Table2[Vol_L],Table2[Code],'MPG Payment'!$B22,Table2[Account Details],"Not Available"),0) -> 0 | K22: =IF(E22="direct",SUMIFS(Table2[Amount],Table2[Code],'MPG Payment'!$B22,Table2[Account Details],"Not Available"),0) -> 0 | L22: =H22+J22 -> 867.94 | M22: =I22+K22 -> 38556.261 | N22: =IF(E22="indirect",G22,MIN(G22,M22)) -> 38556.261 | O22: =SUMIFS(Table2[TS Loss],Table2[Code],'MPG Payment'!$B22) -> 0 | P22: =SUMIFS(Table2[Deduction for excess payment],Table2[Code],'MPG Payment'!$B22) -> 0 | Q22: =IF(M22>G22,(M22-G22),0) -> 0 | R22: =SUMIF(Table2[Code],'MPG Payment'!$B22,Table2[CF Deduction]) -> 0 | S22: =SUMIF('Farmer Payment Calc'!D:D,'MPG Payment'!B22,'Farmer Payment Calc'!M:M) -> 0 | T22: 0 | U22: 0 | V22: =IF(E22="direct",SUMIFS(Table2[Net Amount],Table2[Code],'MPG Payment'!$B22,Table2[Account Details],"Available"),0) -> 38557 | W22: =IF(E22="direct",SUMIFS(Table2[Net Amount],Table2[Code],'MPG Payment'!$B22,Table2[Account Details],"Not Available"),0) -> 0 | X22: =IF(Z22="Yes",0,IF(E22="indirect",(G22-O22-P22-R22-T22-U22-S22),0)) -> 0 | Y22: =IF(E22="direct",(G22-O22-P22-V22-X22-R22-S22-T22-U22),0)-W22 -> 14.58 | Z22: 0 | AA22: =ROUND(+N22-O22-P22-R22-T22-V22-W22-X22-S22,0)-U22 -> -1 | AB22: =(M22-G22)/G22 -> -0.00039716029 | AC22: =COUNTIF(Table2[Code],'MPG Payment'!B22) -> 26 | AD22: {=SUBSTITUTE(SUBSTITUTE(MID(CELL("filename"),FIND("[",CELL("filename"))+1,FIND("]",CELL("filename"))-FIND("[",CELL("filename"))-1),"JH Farmer Payment-",""),".xlsx","")} -> Indent | AF22: 0 | AG22: 0 | AH22: =AF22-AG22 -> 0 | AI22: 0
A23: BMC Code :2001 | B23: 20010043 | C23: DARKHANDREY | D23: MPG | E23: =IFERROR(VLOOKUP(B23,Table2[[Code]:[Category]],13,0),"Indirect") -> Direct | F23: 827.96 | G23: 35245.39 | H23: =SUMIFS(Table2[Vol_L],Table2[Code],'MPG Payment'!$B23,Table2[Account Details],"Available") -> 826.54 | I23: =SUMIFS(Table2[Amount],Table2[Code],'MPG Payment'!$B23,Table2[Account Details],"Available") -> 36474.347 | J23: =IF(E23="direct",SUMIFS(Table2[Vol_L],Table2[Code],'MPG Payment'!$B23,Table2[Account Details],"Not Available"),0) -> 0 | K23: =IF(E23="direct",SUMIFS(Table2[Amount],Table2[Code],'MPG Payment'!$B23,Table2[Account Details],"Not Available"),0) -> 0 | L23: =H23+J23 -> 826.54 | M23: =I23+K23 -> 36474.347 | N23: =IF(E23="indirect",G23,MIN(G23,M23)) -> 35245.39 | O23: =SUMIFS(Table2[TS Loss],Table2[Code],'MPG Payment'!$B23) -> 0 | P23: =SUMIFS(Table2[Deduction for excess payment],Table2[Code],'MPG Payment'!$B23) -> 0 | Q23: =IF(M23>G23,(M23-G23),0) -> 1228.9566 | R23: =SUMIF(Table2[Code],'MPG Payment'!$B23,Table2[CF Deduction]) -> 0 | S23: =SUMIF('Farmer Payment Calc'!D:D,'MPG Payment'!B23,'Farmer Payment Calc'!M:M) -> 0 | T23: 0 | U23: 0 | V23: =IF(E23="direct",SUMIFS(Table2[Net Amount],Table2[Code],'MPG Payment'!$B23,Table2[Account Details],"Available"),0) -> 35245 | W23: =IF(E23="direct",SUMIFS(Table2[Net Amount],Table2[Code],'MPG Payment'!$B23,Table2[Account Details],"Not Available"),0) -> 0 | X23: =IF(Z23="Yes",0,IF(E23="indirect",(G23-O23-P23-R23-T23-U23-S23),0)) -> 0 | Y23: =IF(E23="direct",(G23-O23-P23-V23-X23-R23-S23-T23-U23),0)-W23 -> 0.39 | Z23: Release1 | AA23: =ROUND(+N23-O23-P23-R23-T23-V23-W23-X23-S23,0)-U23 -> 0 | AB23: =(M23-G23)/G23 -> 0.034868577 | AC23: =COUNTIF(Table2[Code],'MPG Payment'!B23) -> 23 | AD23: {=SUBSTITUTE(SUBSTITUTE(MID(CELL("filename"),FIND("[",CELL("filename"))+1,FIND("]",CELL("filename"))-FIND("[",CELL("filename"))-1),"JH Farmer Payment-",""),".xlsx","")} -> Indent | AE23: Letter not received | AF23: 0 | AG23: 0 | AH23: =AF23-AG23 -> 0 | AI23: 0
A24: BMC Code :2001 | B24: 20010050 | C24: SARNA TOLI | D24: VLC | E24: =IFERROR(VLOOKUP(B24,Table2[[Code]:[Category]],13,0),"Indirect") -> Direct | F24: 54.18 | G24: 2201.05 | H24: =SUMIFS(Table2[Vol_L],Table2[Code],'MPG Payment'!$B24,Table2[Account Details],"Available") -> 53 | I24: =SUMIFS(Table2[Amount],Table2[Code],'MPG Payment'!$B24,Table2[Account Details],"Available") -> 2186.25 | J24: =IF(E24="direct",SUMIFS(Table2[Vol_L],Table2[Code],'MPG Payment'!$B24,Table2[Account Details],"Not Available"),0) -> 0 | K24: =IF(E24="direct",SUMIFS(Table2[Amount],Table2[Code],'MPG Payment'!$B24,Table2[Account Details],"Not Available"),0) -> 0 | L24: =H24+J24 -> 53 | M24: =I24+K24 -> 2186.25 | N24: =IF(E24="indirect",G24,MIN(G24,M24)) -> 2186.25 | O24: =SUMIFS(Table2[TS Loss],Table2[Code],'MPG Payment'!$B24) -> 0 | P24: =SUMIFS(Table2[Deduction for excess payment],Table2[Code],'MPG Payment'!$B24) -> 0 | Q24: =IF(M24>G24,(M24-G24),0) -> 0 | R24: =SUMIF(Table2[Code],'MPG Payment'!$B24,Table2[CF Deduction]) -> 0 | S24: =SUMIF('Farmer Payment Calc'!D:D,'MPG Payment'!B24,'Farmer Payment Calc'!M:M) -> 0 | T24: 0 | U24: 0 | V24: =IF(E24="direct",SUMIFS(Table2[Net Amount],Table2[Code],'MPG Payment'!$B24,Table2[Account Details],"Available"),0) -> 2186 | W24: =IF(E24="direct",SUMIFS(Table2[Net Amount],Table2[Code],'MPG Payment'!$B24,Table2[Account Details],"Not Available"),0) -> 0 | X24: =IF(Z24="Yes",0,IF(E24="indirect",(G24-O24-P24-R24-T24-U24-S24),0)) -> 0 | Y24: =IF(E24="direct",(G24-O24-P24-V24-X24-R24-S24-T24-U24),0)-W24 -> 15.05 | Z24: 0 | AA24: =ROUND(+N24-O24-P24-R24-T24-V24-W24-X24-S24,0)-U24 -> 0 | AB24: =(M24-G24)/G24 -> -0.0067240635 | AC24: =COUNTIF(Table2[Code],'MPG Payment'!B24) -> 1 | AD24: {=SUBSTITUTE(SUBSTITUTE(MID(CELL("filename"),FIND("[",CELL("filename"))+1,FIND("]",CELL("filename"))-FIND("[",CELL("filename"))-1),"JH Farmer Payment-",""),".xlsx","")} -> Indent | AF24: 0 | AG24: 0 | AH24: =AF24-AG24 -> 0 | AI24: 0
A25: BMC Code :2001 | B25: 20010052 | C25: Kumbatoli | D25: MPG | E25: =IFERROR(VLOOKUP(B25,Table2[[Code]:[Category]],13,0),"Indirect") -> Direct | F25: 1209.42 | G25: 48843.03 | H25: =SUMIFS(Table2[Vol_L],Table2[Code],'MPG Payment'!$B25,Table2[Account Details],"Available") -> 1217.62 | I25: =SUMIFS(Table2[Amount],Table2[Code],'MPG Payment'!$B25,Table2[Account Details],"Available") -> 49012.153 | J25: =IF(E25="direct",SUMIFS(Table2[Vol_L],Table2[Code],'MPG Payment'!$B25,Table2[Account Details],"Not Available"),0) -> 0 | K25: =IF(E25="direct",SUMIFS(Table2[Amount],Table2[Code],'MPG Payment'!$B25,Table2[Account Details],"Not Available"),0) -> 0 | L25: =H25+J25 -> 1217.62 | M25: =I25+K25 -> 49012.153 | N25: =IF(E25="indirect",G25,MIN(G25,M25)) -> 48843.03 | O25: =SUMIFS(Table2[TS Loss],Table2[Code],'MPG Payment'!$B25) -> 0 | P25: =SUMIFS(Table2[Deduction for excess payment],Table2[Code],'MPG Payment'!$B25) -> 0 | Q25: =IF(M25>G25,(M25-G25),0) -> 169.1226 | R25: =SUMIF(Table2[Code],'MPG Payment'!$B25,Table2[CF Deduction]) -> 6350 | S25: =SUMIF('Farmer Payment Calc'!D:D,'MPG Payment'!B25,'Farmer Payment Calc'!M:M) -> 0 | T25: 0 | U25: 0 | V25: =IF(E25="direct",SUMIFS(Table2[Net Amount],Table2[Code],'MPG Payment'!$B25,Table2[Account Details],"Available"),0) -> 42493 | W25: =IF(E25="direct",SUMIFS(Table2[Net Amount],Table2[Code],'MPG Payment'!$B25,Table2[Account Details],"Not Available"),0) -> 0 | X25: =IF(Z25="Yes",0,IF(E25="indirect",(G25-O25-P25-R25-T25-U25-S25),0)) -> 0 | Y25: =IF(E25="direct",(G25-O25-P25-V25-X25-R25-S25-T25-U25),0)-W25 -> 0.03 | Z25: 0 | AA25: =ROUND(+N25-O25-P25-R25-T25-V25-W25-X25-S25,0)-U25 -> 0 | AB25: =(M25-G25)/G25 -> 0.0034625739 | AC25: =COUNTIF(Table2[Code],'MPG Payment'!B25) -> 20 | AD25: {=SUBSTITUTE(SUBSTITUTE(MID(CELL("filename"),FIND("[",CELL("filename"))+1,FIND("]",CELL("filename"))-FIND("[",CELL("filename"))-1),"JH Farmer Payment-",""),".xlsx","")} -> Indent | AF25: 0 | AG25: 0 | AH25: =AF25-AG25 -> 0 | AI25: 0
A26: BMC Code :2009 | B26: 20010054 | C26: NARKOPI | D26: MPG | E26: =IFERROR(VLOOKUP(B26,Table2[[Code]:[Category]],13,0),"Indirect") -> Direct | F26: 788.18 | G26: 32184.85 | H26: =SUMIFS(Table2[Vol_L],Table2[Code],'MPG Payment'!$B26,Table2[Account Details],"Available") -> 754.1 | I26: =SUMIFS(Table2[Amount],Table2[Code],'MPG Payment'!$B26,Table2[Account Details],"Available") -> 31820.98 | J26: =IF(E26="direct",SUMIFS(Table2[Vol_L],Table2[Code],'MPG Payment'!$B26,Table2[Account Details],"Not Available"),0) -> 0 | K26: =IF(E26="direct",SUMIFS(Table2[Amount],Table2[Code],'MPG Payment'!$B26,Table2[Account Details],"Not Available"),0) -> 0 | L26: =H26+J26 -> 754.1 | M26: =I26+K26 -> 31820.98 | N26: =IF(E26="indirect",G26,MIN(G26,M26)) -> 31820.98 | O26: =SUMIFS(Table2[TS Loss],Table2[Code],'MPG Payment'!$B26) -> 0 | P26: =SUMIFS(Table2[Deduction for excess payment],Table2[Code],'MPG Payment'!$B26) -> 0 | Q26: =IF(M26>G26,(M26-G26),0) -> 0 | R26: =SUMIF(Table2[Code],'MPG Payment'!$B26,Table2[CF Deduction]) -> 0 | S26: =SUMIF('Farmer Payment Calc'!D:D,'MPG Payment'!B26,'Farmer Payment Calc'!M:M) -> 0 | T26: 0 | U26: 0 | V26: =IF(E26="direct",SUMIFS(Table2[Net Amount],Table2[Code],'MPG Payment'!$B26,Table2[Account Details],"Available"),0) -> 31821 | W26: =IF(E26="direct",SUMIFS(Table2[Net Amount],Table2[Code],'MPG Payment'!$B26,Table2[Account Details],"Not Available"),0) -> 0 | X26: =IF(Z26="Yes",0,IF(E26="indirect",(G26-O26-P26-R26-T26-U26-S26),0)) -> 0 | Y26: =IF(E26="direct",(G26-O26-P26-V26-X26-R26-S26-T26-U26),0)-W26 -> 363.85 | Z26: 0 | AA26: =ROUND(+N26-O26-P26-R26-T26-V26-W26-X26-S26,0)-U26 -> 0 | AB26: =(M26-G26)/G26 -> -0.01130563 | AC26: =COUNTIF(Table2[Code],'MPG Payment'!B26) -> 16 | AD26: {=SUBSTITUTE(SUBSTITUTE(MID(CELL("filename"),FIND("[",CELL("filename"))+1,FIND("]",CELL("filename"))-FIND("[",CELL("filename"))-1),"JH Farmer Payment-",""),".xlsx","")} -> Indent | AF26: 0 | AG26: 0 | AH26: =AF26-AG26 -> 0 | AI26: 0
A27: BMC Code :2001 | B27: 20010055 | C27: MASU | D27: MPG | E27: =IFERROR(VLOOKUP(B27,Table2[[Code]:[Category]],13,0),"Indirect") -> Direct | F27: 613.9 | G27: 26031.54 | H27: =SUMIFS(Table2[Vol_L],Table2[Code],'MPG Payment'!$B27,Table2[Account Details],"Available") -> 590.8 | I27: =SUMIFS(Table2[Amount],Table2[Code],'MPG Payment'!$B27,Table2[Account Details],"Available") -> 24985.893 | J27: =IF(E27="direct",SUMIFS(Table2[Vol_L],Table2[Code],'MPG Payment'!$B27,Table2[Account Details],"Not Available"),0) -> 42.45 | K27: =IF(E27="direct",SUMIFS(Table2[Amount],Table2[Code],'MPG Payment'!$B27,Table2[Account Details],"Not Available"),0) -> 1740.552 | L27: =H27+J27 -> 633.25 | M27: =I27+K27 -> 26726.445 | N27: =IF(E27="indirect",G27,MIN(G27,M27)) -> 26031.54 | O27: =SUMIFS(Table2[TS Loss],Table2[Code],'MPG Payment'!$B27) -> 0 | P27: =SUMIFS(Table2[Deduction for excess payment],Table2[Code],'MPG Payment'!$B27) -> 0 | Q27: =IF(M27>G27,(M27-G27),0) -> 694.9054 | R27: =SUMIF(Table2[Code],'MPG Payment'!$B27,Table2[CF Deduction]) -> 1270 | S27: =SUMIF('Farmer Payment Calc'!D:D,'MPG Payment'!B27,'Farmer Payment Calc'!M:M) -> 0 | T27: 0 | U27: 0 | V27: =IF(E27="direct",SUMIFS(Table2[Net Amount],Table2[Code],'MPG Payment'!$B27,Table2[Account Details],"Available"),0) -> 24290 | W27: =IF(E27="direct",SUMIFS(Table2[Net Amount],Table2[Code],'MPG Payment'!$B27,Table2[Account Details],"Not Available"),0) -> 471 | X27: =IF(Z27="Yes",0,IF(E27="indirect",(G27-O27-P27-R27-T27-U27-S27),0)) -> 0 | Y27: =IF(E27="direct",(G27-O27-P27-V27-X27-R27-S27-T27-U27),0)-W27 -> 0.54 | Z27: 0 | AA27: =ROUND(+N27-O27-P27-R27-T27-V27-W27-X27-S27,0)-U27 -> 1 | AB27: =(M27-G27)/G27 -> 0.026694748 | AC27: =COUNTIF(Table2[Code],'MPG Payment'!B27) -> 19 | AD27: {=SUBSTITUTE(SUBSTITUTE(MID(CELL("filename"),FIND("[",CELL("filename"))+1,FIND("]",CELL("filename"))-FIND("[",CELL("filename"))-1),"JH Farmer Payment-",""),".xlsx","")} -> Indent | AF27: 0 | AG27: 0 | AH27: =AF27-AG27 -> 0 | AI27: 0
A28: BMC Code :2001 | B28: 20010057 | C28: PANDEPARA | D28: VLC | E28: =IFERROR(VLOOKUP(B28,Table2[[Code]:[Category]],13,0),"Indirect") -> Direct | F28: 265.4 | G28: 11065.02 | H28: =SUMIFS(Table2[Vol_L],Table2[Code],'MPG Payment'!$B28,Table2[Account Details],"Available") -> 277 | I28: =SUMIFS(Table2[Amount],Table2[Code],'MPG Payment'!$B28,Table2[Account Details],"Available") -> 10706.696 | J28: =IF(E28="direct",SUMIFS(Table2[Vol_L],Table2[Code],'MPG Payment'!$B28,Table2[Account Details],"Not Available"),0) -> 5.06 | K28: =IF(E28="direct",SUMIFS(Table2[Amount],Table2[Code],'MPG Payment'!$B28,Table2[Account Details],"Not Available"),0) -> 313.522 | L28: =H28+J28 -> 282.06 | M28: =I28+K28 -> 11020.218 | N28: =IF(E28="indirect",G28,MIN(G28,M28)) -> 11020.218 | O28: =SUMIFS(Table2[TS Loss],Table2[Code],'MPG Payment'!$B28) -> 0 | P28: =SUMIFS(Table2[Deduction for excess payment],Table2[Code],'MPG Payment'!$B28) -> 0 | Q28: =IF(M28>G28,(M28-G28),0) -> 0 | R28: =SUMIF(Table2[Code],'MPG Payment'!$B28,Table2[CF Deduction]) -> 0 | S28: =SUMIF('Farmer Payment Calc'!D:D,'MPG Payment'!B28,'Farmer Payment Calc'!M:M) -> 0 | T28: 0 | U28: 0 | V28: =IF(E28="direct",SUMIFS(Table2[Net Amount],Table2[Code],'MPG Payment'!$B28,Table2[Account Details],"Available"),0) -> 10706 | W28: =IF(E28="direct",SUMIFS(Table2[Net Amount],Table2[Code],'MPG Payment'!$B28,Table2[Account Details],"Not Available"),0) -> 314 | X28: =IF(Z28="Yes",0,IF(E28="indirect",(G28-O28-P28-R28-T28-U28-S28),0)) -> 0 | Y28: =IF(E28="direct",(G28-O28-P28-V28-X28-R28-S28-T28-U28),0)-W28 -> 45.02 | Z28: 0 | AA28: =ROUND(+N28-O28-P28-R28-T28-V28-W28-X28-S28,0)-U28 -> 0 | AB28: =(M28-G28)/G28 -> -0.0040489398 | AC28: =COUNTIF(Table2[Code],'MPG Payment'!B28) -> 5 | AD28: {=SUBSTITUTE(SUBSTITUTE(MID(CELL("filename"),FIND("[",CELL("filename"))+1,FIND("]",CELL("filename"))-FIND("[",CELL("filename"))-1),"JH Farmer Payment-",""),".xlsx","")} -> Indent | AF28: 0 | AG28: 0 | AH28: =AF28-AG28 -> 0 | AI28: 0
A29: BMC Code :2001 | B29: 20010059 | C29: KARANJI 2 | D29: MPG | E29: =IFERROR(VLOOKUP(B29,Table2[[Code]:[Category]],13,0),"Indirect") -> Direct | F29: 129.18 | G29: 5059.1 | H29: =SUMIFS(Table2[Vol_L],Table2[Code],'MPG Payment'!$B29,Table2[Account Details],"Available") -> 130.61 | I29: =SUMIFS(Table2[Amount],Table2[Code],'MPG Payment'!$B29,Table2[Account Details],"Available") -> 5396.5655 | J29: =IF(E29="direct",SUMIFS(Table2[Vol_L],Table2[Code],'MPG Payment'!$B29,Table2[Account Details],"Not Available"),0) -> 0 | K29: =IF(E29="direct",SUMIFS(Table2[Amount],Table2[Code],'MPG Payment'!$B29,Table2[Account Details],"Not Available"),0) -> 0 | L29: =H29+J29 -> 130.61 | M29: =I29+K29 -> 5396.5655 | N29: =IF(E29="indirect",G29,MIN(G29,M29)) -> 5059.1 | O29: =SUMIFS(Table2[TS Loss],Table2[Code],'MPG Payment'!$B29) -> 0 | P29: =SUMIFS(Table2[Deduction for excess payment],Table2[Code],'MPG Payment'!$B29) -> 0 | Q29: =IF(M29>G29,(M29-G29),0) -> 337.4655 | R29: =SUMIF(Table2[Code],'MPG Payment'!$B29,Table2[CF Deduction]) -> 0 | S29: =SUMIF('Farmer Payment Calc'!D:D,'MPG Payment'!B29,'Farmer Payment Calc'!M:M) -> 0 | T29: 0 | U29: 0 | V29: =IF(E29="direct",SUMIFS(Table2[Net Amount],Table2[Code],'MPG Payment'!$B29,Table2[Account Details],"Available"),0) -> 5059 | W29: =IF(E29="direct",SUMIFS(Table2[Net Amount],Table2[Code],'MPG Payment'!$B29,Table2[Account Details],"Not Available"),0) -> 0 | X29: =IF(Z29="Yes",0,IF(E29="indirect",(G29-O29-P29-R29-T29-U29-S29),0)) -> 0 | Y29: =IF(E29="direct",(G29-O29-P29-V29-X29-R29-S29-T29-U29),0)-W29 -> 0.1 | Z29: 0 | AA29: =ROUND(+N29-O29-P29-R29-T29-V29-W29-X29-S29,0)-U29 -> 0 | AB29: =(M29-G29)/G29 -> 0.066704651 | AC29: =COUNTIF(Table2[Code],'MPG Payment'!B29) -> 2 | AD29: {=SUBSTITUTE(SUBSTITUTE(MID(CELL("filename"),FIND("[",CELL("filename"))+1,FIND("]",CELL("filename"))-FIND("[",CELL("filename"))-1),"JH Farmer Payment-",""),".xlsx","")} -> Indent | AF29: 0 | AG29: 0 | AH29: =AF29-AG29 -> 0 | AI29: 0
A30: BMC Code :2001 | B30: 20010060 | C30: ITKI 2 | D30: VLC | E30: =IFERROR(VLOOKUP(B30,Table2[[Code]:[Category]],13,0),"Indirect") -> Indirect | F30: 68.76 | G30: 2613.79 | H30: =SUMIFS(Table2[Vol_L],Table2[Code],'MPG Payment'!$B30,Table2[Account Details],"Available") -> 0 | I30: =SUMIFS(Table2[Amount],Table2[Code],'MPG Payment'!$B30,Table2[Account Details],"Available") -> 0 | J30: =IF(E30="direct",SUMIFS(Table2[Vol_L],Table2[Code],'MPG Payment'!$B30,Table2[Account Details],"Not Available"),0) -> 0 | K30: =IF(E30="direct",SUMIFS(Table2[Amount],Table2[Code],'MPG Payment'!$B30,Table2[Account Details],"Not Available"),0) -> 0 | L30: =H30+J30 -> 0 | M30: =I30+K30 -> 0 | N30: =IF(E30="indirect",G30,MIN(G30,M30)) -> 2613.79 | O30: =SUMIFS(Table2[TS Loss],Table2[Code],'MPG Payment'!$B30) -> 0 | P30: =SUMIFS(Table2[Deduction for excess payment],Table2[Code],'MPG Payment'!$B30) -> 0 | Q30: =IF(M30>G30,(M30-G30),0) -> 0 | R30: =SUMIF(Table2[Code],'MPG Payment'!$B30,Table2[CF Deduction]) -> 0 | S30: =SUMIF('Farmer Payment Calc'!D:D,'MPG Payment'!B30,'Farmer Payment Calc'!M:M) -> 0 | T30: 0 | U30: 0 | V30: =IF(E30="direct",SUMIFS(Table2[Net Amount],Table2[Code],'MPG Payment'!$B30,Table2[Account Details],"Available"),0) -> 0 | W30: =IF(E30="direct",SUMIFS(Table2[Net Amount],Table2[Code],'MPG Payment'!$B30,Table2[Account Details],"Not Available"),0) -> 0 | X30: =IF(Z30="Yes",0,IF(E30="indirect",(G30-O30-P30-R30-T30-U30-S30),0)) -> 2613.79 | Y30: =IF(E30="direct",(G30-O30-P30-V30-X30-R30-S30-T30-U30),0)-W30 -> 0 | Z30: 0 | AA30: =ROUND(+N30-O30-P30-R30-T30-V30-W30-X30-S30,0)-U30 -> 0 | AB30: =(M30-G30)/G30 -> -1 | AC30: =COUNTIF(Table2[Code],'MPG Payment'!B30) -> 0 | AD30: {=SUBSTITUTE(SUBSTITUTE(MID(CELL("filename"),FIND("[",CELL("filename"))+1,FIND("]",CELL("filename"))-FIND("[",CELL("filename"))-1),"JH Farmer Payment-",""),".xlsx","")} -> Indent | AF30: 0 | AG30: 0 | AH30: =AF30-AG30 -> 0 | AI30: 0
A31: BMC Code :2001 | B31: 20010061 | C31: SEMRA | D31: MPG | E31: =IFERROR(VLOOKUP(B31,Table2[[Code]:[Category]],13,0),"Indirect") -> Direct | F31: 524.12 | G31: 21078.52 | H31: =SUMIFS(Table2[Vol_L],Table2[Code],'MPG Payment'!$B31,Table2[Account Details],"Available") -> 522.21 | I31: =SUMIFS(Table2[Amount],Table2[Code],'MPG Payment'!$B31,Table2[Account Details],"Available") -> 21217.406 | J31: =IF(E31="direct",SUMIFS(Table2[Vol_L],Table2[Code],'MPG Payment'!$B31,Table2[Account Details],"Not Available"),0) -> 0 | K31: =IF(E31="direct",SUMIFS(Table2[Amount],Table2[Code],'MPG Payment'!$B31,Table2[Account Details],"Not Available"),0) -> 0 | L31: =H31+J31 -> 522.21 | M31: =I31+K31 -> 21217.406 | N31: =IF(E31="indirect",G31,MIN(G31,M31)) -> 21078.52 | O31: =SUMIFS(Table2[TS Loss],Table2[Code],'MPG Payment'!$B31) -> 0 | P31: =SUMIFS(Table2[Deduction for excess payment],Table2[Code],'MPG Payment'!$B31) -> 0 | Q31: =IF(M31>G31,(M31-G31),0) -> 138.8861 | R31: =SUMIF(Table2[Code],'MPG Payment'!$B31,Table2[CF Deduction]) -> 0 | S31: =SUMIF('Farmer Payment Calc'!D:D,'MPG Payment'!B31,'Farmer Payment Calc'!M:M) -> 0 | T31: 0 | U31: 0 | V31: =IF(E31="direct",SUMIFS(Table2[Net Amount],Table2[Code],'MPG Payment'!$B31,Table2[Account Details],"Available"),0) -> 21079 | W31: =IF(E31="direct",SUMIFS(Table2[Net Amount],Table2[Code],'MPG Payment'!$B31,Table2[Account Details],"Not Available"),0) -> 0 | X31: =IF(Z31="Yes",0,IF(E31="indirect",(G31-O31-P31-R31-T31-U31-S31),0)) -> 0 | Y31: =IF(E31="direct",(G31-O31-P31-V31-X31-R31-S31-T31-U31),0)-W31 -> -0.48 | Z31: 0 | AA31: =ROUND(+N31-O31-P31-R31-T31-V31-W31-X31-S31,0)-U31 -> 0 | AB31: =(M31-G31)/G31 -> 0.0065889873 | AC31: =COUNTIF(Table2[Code],'MPG Payment'!B31) -> 5 | AD31: {=SUBSTITUTE(SUBSTITUTE(MID(CELL("filename"),FIND("[",CELL("filename"))+1,FIND("]",CELL("filename"))-FIND("[",CELL("filename"))-1),"JH Farmer Payment-",""),".xlsx","")} -> Indent | AF31: 0 | AG31: 0 | AH31: =AF31-AG31 -> 0 | AI31: 0
A32: BMC Code :2001 | B32: 20010062 | C32: PISKA | D32: MPG | E32: =IFERROR(VLOOKUP(B32,Table2[[Code]:[Category]],13,0),"Indirect") -> Direct | F32: 174.06 | G32: 6904.76 | H32: =SUMIFS(Table2[Vol_L],Table2[Code],'MPG Payment'!$B32,Table2[Account Details],"Available") -> 174.24 | I32: =SUMIFS(Table2[Amount],Table2[Code],'MPG Payment'!$B32,Table2[Account Details],"Available") -> 6726.8369 | J32: =IF(E32="direct",SUMIFS(Table2[Vol_L],Table2[Code],'MPG Payment'!$B32,Table2[Account Details],"Not Available"),0) -> 0 | K32: =IF(E32="direct",SUMIFS(Table2[Amount],Table2[Code],'MPG Payment'!$B32,Table2[Account Details],"Not Available"),0) -> 0 | L32: =H32+J32 -> 174.24 | M32: =I32+K32 -> 6726.8369 | N32: =IF(E32="indirect",G32,MIN(G32,M32)) -> 6726.8369 | O32: =SUMIFS(Table2[TS Loss],Table2[Code],'MPG Payment'!$B32) -> 0 | P32: =SUMIFS(Table2[Deduction for excess payment],Table2[Code],'MPG Payment'!$B32) -> 0 | Q32: =IF(M32>G32,(M32-G32),0) -> 0 | R32: =SUMIF(Table2[Code],'MPG Payment'!$B32,Table2[CF Deduction]) -> 0 | S32: =SUMIF('Farmer Payment Calc'!D:D,'MPG Payment'!B32,'Farmer Payment Calc'!M:M) -> 0 | T32: 0 | U32: 0 | V32: =IF(E32="direct",SUMIFS(Table2[Net Amount],Table2[Code],'MPG Payment'!$B32,Table2[Account Details],"Available"),0) -> 6727 | W32: =IF(E32="direct",SUMIFS(Table2[Net Amount],Table2[Code],'MPG Payment'!$B32,Table2[Account Details],"Not Available"),0) -> 0 | X32: =IF(Z32="Yes",0,IF(E32="indirect",(G32-O32-P32-R32-T32-U32-S32),0)) -> 0 | Y32: =IF(E32="direct",(G32-O32-P32-V32-X32-R32-S32-T32-U32),0)-W32 -> 177.76 | Z32: 0 | AA32: =ROUND(+N32-O32-P32-R32-T32-V32-W32-X32-S32,0)-U32 -> 0 | AB32: =(M32-G32)/G32 -> -0.02576818 | AC32: =COUNTIF(Table2[Code],'MPG Payment'!B32) -> 6 | AD32: {=SUBSTITUTE(SUBSTITUTE(MID(CELL("filename"),FIND("[",CELL("filename"))+1,FIND("]",CELL("filename"))-FIND("[",CELL("filename"))-1),"JH Farmer Payment-",""),".xlsx","")} -> Indent | AF32: 0 | AG32: 0 | AH32: =AF32-AG32 -> 0 | AI32: 0
A33: BMC Code :2001 | B33: 20010063 | C33: BANDHIYA | D33: VLC | E33: =IFERROR(VLOOKUP(B33,Table2[[Code]:[Category]],13,0),"Indirect") -> Indirect | F33: 406.02 | G33: 16734.9 | H33: =SUMIFS(Table2[Vol_L],Table2[Code],'MPG Payment'!$B33,Table2[Account Details],"Available") -> 0 | I33: =SUMIFS(Table2[Amount],Table2[Code],'MPG Payment'!$B33,Table2[Account Details],"Available") -> 0 | J33: =IF(E33="direct",SUMIFS(Table2[Vol_L],Table2[Code],'MPG Payment'!$B33,Table2[Account Details],"Not Available"),0) -> 0 | K33: =IF(E33="direct",SUMIFS(Table2[Amount],Table2[Code],'MPG Payment'!$B33,Table2[Account Details],"Not Available"),0) -> 0 | L33: =H33+J33 -> 0 | M33: =I33+K33 -> 0 | N33: =IF(E33="indirect",G33,MIN(G33,M33)) -> 16734.9 | O33: =SUMIFS(Table2[TS Loss],Table2[Code],'MPG Payment'!$B33) -> 0 | P33: =SUMIFS(Table2[Deduction for excess payment],Table2[Code],'MPG Payment'!$B33) -> 0 | Q33: =IF(M33>G33,(M33-G33),0) -> 0 | R33: =SUMIF(Table2[Code],'MPG Payment'!$B33,Table2[CF Deduction]) -> 0 | S33: =SUMIF('Farmer Payment Calc'!D:D,'MPG Payment'!B33,'Farmer Payment Calc'!M:M) -> 0 | T33: 0 | U33: 0 | V33: =IF(E33="direct",SUMIFS(Table2[Net Amount],Table2[Code],'MPG Payment'!$B33,Table2[Account Details],"Available"),0) -> 0 | W33: =IF(E33="direct",SUMIFS(Table2[Net Amount],Table2[Code],'MPG Payment'!$B33,Table2[Account Details],"Not Available"),0) -> 0 | X33: =IF(Z33="Yes",0,IF(E33="indirect",(G33-O33-P33-R33-T33-U33-S33),0)) -> 16734.9 | Y33: =IF(E33="direct",(G33-O33-P33-V33-X33-R33-S33-T33-U33),0)-W33 -> 0 | Z33: 0 | AA33: =ROUND(+N33-O33-P33-R33-T33-V33-W33-X33-S33,0)-U33 -> 0 | AB33: =(M33-G33)/G33 -> -1 | AC33: =COUNTIF(Table2[Code],'MPG Payment'!B33) -> 0 | AD33: {=SUBSTITUTE(SUBSTITUTE(MID(CELL("filename"),FIND("[",CELL("filename"))+1,FIND("]",CELL("filename"))-FIND("[",CELL("filename"))-1),"JH Farmer Payment-",""),".xlsx","")} -> Indent | AF33: 0 | AG33: 0 | AH33: =AF33-AG33 -> 0 | AI33: 0
A34: BMC Code :2002 | B34: 20020001 | C34: Paali | D34: RMC | E34: =IFERROR(VLOOKUP(B34,Table2[[Code]:[Category]],13,0),"Indirect") -> Direct | F34: 4902.1 | G34: 198731.52 | H34: =SUMIFS(Table2[Vol_L],Table2[Code],'MPG Payment'!$B34,Table2[Account Details],"Available") -> 4902.1 | I34: =SUMIFS(Table2[Amount],Table2[Code],'MPG Payment'!$B34,Table2[Account Details],"Available") -> 198731.25 | J34: =IF(E34="direct",SUMIFS(Table2[Vol_L],Table2[Code],'MPG Payment'!$B34,Table2[Account Details],"Not Available"),0) -> 0 | K34: =IF(E34="direct",SUMIFS(Table2[Amount],Table2[Code],'MPG Payment'!$B34,Table2[Account Details],"Not Available"),0) -> 0 | L34: =H34+J34 -> 4902.1 | M34: =I34+K34 -> 198731.25 | N34: =IF(E34="indirect",G34,MIN(G34,M34)) -> 198731.25 | O34: =SUMIFS(Table2[TS Loss],Table2[Code],'MPG Payment'!$B34) -> 1292 | P34: =SUMIFS(Table2[Deduction for excess payment],Table2[Code],'MPG Payment'!$B34) -> 0 | Q34: =IF(M34>G34,(M34-G34),0) -> 0 | R34: =SUMIF(Table2[Code],'MPG Payment'!$B34,Table2[CF Deduction]) -> 12051 | S34: =SUMIF('Farmer Payment Calc'!D:D,'MPG Payment'!B34,'Farmer Payment Calc'!M:M) -> 0 | T34: 0 | U34: 0 | V34: =IF(E34="direct",SUMIFS(Table2[Net Amount],Table2[Code],'MPG Payment'!$B34,Table2[Account Details],"Available"),0) -> 185386 | W34: =IF(E34="direct",SUMIFS(Table2[Net Amount],Table2[Code],'MPG Payment'!$B34,Table2[Account Details],"Not Available"),0) -> 0 | X34: =IF(Z34="Yes",0,IF(E34="indirect",(G34-O34-P34-R34-T34-U34-S34),0)) -> 0 | Y34: =IF(E34="direct",(G34-O34-P34-V34-X34-R34-S34-T34-U34),0)-W34 -> 2.52 | Z34: Release1 | AA34: =ROUND(+N34-O34-P34-R34-T34-V34-W34-X34-S34,0)-U34 -> 2 | AB34: =(M34-G34)/G34 -> -1.353585e-06 | AC34: =COUNTIF(Table2[Code],'MPG Payment'!B34) -> 84 | AD34: {=SUBSTITUTE(SUBSTITUTE(MID(CELL("filename"),FIND("[",CELL("filename"))+1,FIND("]",CELL("filename"))-FIND("[",CELL("filename"))-1),"JH Farmer Payment-",""),".xlsx","")} -> Indent | AE34: TS Loss | AF34: 0 | AG34: 0 | AH34: =AF34-AG34 -> 0 | AI34: 0
A35: BMC Code :2002 | B35: 20020002 | C35: Jari | D35: MPG | E35: =IFERROR(VLOOKUP(B35,Table2[[Code]:[Category]],13,0),"Indirect") -> Direct | F35: 2123.77 | G35: 85525.57 | H35: =SUMIFS(Table2[Vol_L],Table2[Code],'MPG Payment'!$B35,Table2[Account Details],"Available") -> 2016.03 | I35: =SUMIFS(Table2[Amount],Table2[Code],'MPG Payment'!$B35,Table2[Account Details],"Available") -> 85435.301 | J35: =IF(E35="direct",SUMIFS(Table2[Vol_L],Table2[Code],'MPG Payment'!$B35,Table2[Account Details],"Not Available"),0) -> 0 | K35: =IF(E35="direct",SUMIFS(Table2[Amount],Table2[Code],'MPG Payment'!$B35,Table2[Account Details],"Not Available"),0) -> 0 | L35: =H35+J35 -> 2016.03 | M35: =I35+K35 -> 85435.301 | N35: =IF(E35="indirect",G35,MIN(G35,M35)) -> 85435.301 | O35: =SUMIFS(Table2[TS Loss],Table2[Code],'MPG Payment'!$B35) -> 0 | P35: =SUMIFS(Table2[Deduction for excess payment],Table2[Code],'MPG Payment'!$B35) -> 0 | Q35: =IF(M35>G35,(M35-G35),0) -> 0 | R35: =SUMIF(Table2[Code],'MPG Payment'!$B35,Table2[CF Deduction]) -> 0 | S35: =SUMIF('Farmer Payment Calc'!D:D,'MPG Payment'!B35,'Farmer Payment Calc'!M:M) -> 0 | T35: 0 | U35: 0 | V35: =IF(E35="direct",SUMIFS(Table2[Net Amount],Table2[Code],'MPG Payment'!$B35,Table2[Account Details],"Available"),0) -> 85438 | W35: =IF(E35="direct",SUMIFS(Table2[Net Amount],Table2[Code],'MPG Payment'!$B35,Table2[Account Details],"Not Available"),0) -> 0 | X35: =IF(Z35="Yes",0,IF(E35="indirect",(G35-O35-P35-R35-T35-U35-S35),0)) -> 0 | Y35: =IF(E35="direct",(G35-O35-P35-V35-X35-R35-S35-T35-U35),0)-W35 -> 87.57 | Z35: 0 | AA35: =ROUND(+N35-O35-P35-R35-T35-V35-W35-X35-S35,0)-U35 -> -3 | AB35: =(M35-G35)/G35 -> -0.0010554621 | AC35: =COUNTIF(Table2[Code],'MPG Payment'!B35) -> 30 | AD35: {=SUBSTITUTE(SUBSTITUTE(MID(CELL("filename"),FIND("[",CELL("filename"))+1,FIND("]",CELL("filename"))-FIND("[",CELL("filename"))-1),"JH Farmer Payment-",""),".xlsx","")} -> Indent | AF35: 0 | AG35: 0 | AH35: =AF35-AG35 -> 0 | AI35: 0
A36: BMC Code :2002 | B36: 20020003 | C36: Bijuliya | D36: MPG | E36: =IFERROR(VLOOKUP(B36,Table2[[Code]:[Category]],13,0),"Indirect") -> Direct | F36: 830.9 | G36: 34337.67 | H36: =SUMIFS(Table2[Vol_L],Table2[Code],'MPG Payment'!$B36,Table2[Account Details],"Available") -> 828.31 | I36: =SUMIFS(Table2[Amount],Table2[Code],'MPG Payment'!$B36,Table2[Account Details],"Available") -> 34843.778 | J36: =IF(E36="direct",SUMIFS(Table2[Vol_L],Table2[Code],'MPG Payment'!$B36,Table2[Account Details],"Not Available"),0) -> 0 | K36: =IF(E36="direct",SUMIFS(Table2[Amount],Table2[Code],'MPG Payment'!$B36,Table2[Account Details],"Not Available"),0) -> 0 | L36: =H36+J36 -> 828.31 | M36: =I36+K36 -> 34843.778 | N36: =IF(E36="indirect",G36,MIN(G36,M36)) -> 34337.67 | O36: =SUMIFS(Table2[TS Loss],Table2[Code],'MPG Payment'!$B36) -> 0 | P36: =SUMIFS(Table2[Deduction for excess payment],Table2[Code],'MPG Payment'!$B36) -> 0 | Q36: =IF(M36>G36,(M36-G36),0) -> 506.1078 | R36: =SUMIF(Table2[Code],'MPG Payment'!$B36,Table2[CF Deduction]) -> 12700 | S36: =SUMIF('Farmer Payment Calc'!D:D,'MPG Payment'!B36,'Farmer Payment Calc'!M:M) -> 0 | T36: 0 | U36: 0 | V36: =IF(E36="direct",SUMIFS(Table2[Net Amount],Table2[Code],'MPG Payment'!$B36,Table2[Account Details],"Available"),0) -> 21637 | W36: =IF(E36="direct",SUMIFS(Table2[Net Amount],Table2[Code],'MPG Payment'!$B36,Table2[Account Details],"Not Available"),0) -> 0 | X36: =IF(Z36="Yes",0,IF(E36="indirect",(G36-O36-P36-R36-T36-U36-S36),0)) -> 0 | Y36: =IF(E36="direct",(G36-O36-P36-V36-X36-R36-S36-T36-U36),0)-W36 -> 0.67 | Z36: 0 | AA36: =ROUND(+N36-O36-P36-R36-T36-V36-W36-X36-S36,0)-U36 -> 1 | AB36: =(M36-G36)/G36 -> 0.014739142 | AC36: =COUNTIF(Table2[Code],'MPG Payment'!B36) -> 9 | AD36: {=SUBSTITUTE(SUBSTITUTE(MID(CELL("filename"),FIND("[",CELL("filename"))+1,FIND("]",CELL("filename"))-FIND("[",CELL("filename"))-1),"JH Farmer Payment-",""),".xlsx","")} -> Indent | AF36: 0 | AG36: 0 | AH36: =AF36-AG36 -> 0 | AI36: 0
A37: BMC Code :2002 | B37: 20020004 | C37: Pandra | D37: MPG | E37: =IFERROR(VLOOKUP(B37,Table2[[Code]:[Category]],13,0),"Indirect") -> Direct | F37: 357.31 | G37: 14537.03 | H37: =SUMIFS(Table2[Vol_L],Table2[Code],'MPG Payment'!$B37,Table2[Account Details],"Available") -> 350.64 | I37: =SUMIFS(Table2[Amount],Table2[Code],'MPG Payment'!$B37,Table2[Account Details],"Available") -> 14535.209 | J37: =IF(E37="direct",SUMIFS(Table2[Vol_L],Table2[Code],'MPG Payment'!$B37,Table2[Account Details],"Not Available"),0) -> 0 | K37: =IF(E37="direct",SUMIFS(Table2[Amount],Table2[Code],'MPG Payment'!$B37,Table2[Account Details],"Not Available"),0) -> 0 | L37: =H37+J37 -> 350.64 | M37: =I37+K37 -> 14535.209 | N37: =IF(E37="indirect",G37,MIN(G37,M37)) -> 14535.209 | O37: =SUMIFS(Table2[TS Loss],Table2[Code],'MPG Payment'!$B37) -> 0 | P37: =SUMIFS(Table2[Deduction for excess payment],Table2[Code],'MPG Payment'!$B37) -> 0 | Q37: =IF(M37>G37,(M37-G37),0) -> 0 | R37: =SUMIF(Table2[Code],'MPG Payment'!$B37,Table2[CF Deduction]) -> 0 | S37: =SUMIF('Farmer Payment Calc'!D:D,'MPG Payment'!B37,'Farmer Payment Calc'!M:M) -> 0 | T37: 0 | U37: 0 | V37: =IF(E37="direct",SUMIFS(Table2[Net Amount],Table2[Code],'MPG Payment'!$B37,Table2[Account Details],"Available"),0) -> 14537 | W37: =IF(E37="direct",SUMIFS(Table2[Net Amount],Table2[Code],'MPG Payment'!$B37,Table2[Account Details],"Not Available"),0) -> 0 | X37: =IF(Z37="Yes",0,IF(E37="indirect",(G37-O37-P37-R37-T37-U37-S37),0)) -> 0 | Y37: =IF(E37="direct",(G37-O37-P37-V37-X37-R37-S37-T37-U37),0)-W37 -> 0.03 | Z37: 0 | AA37: =ROUND(+N37-O37-P37-R37-T37-V37-W37-X37-S37,0)-U37 -> -2 | AB37: =(M37-G37)/G37 -> -0.00012524567 | AC37: =COUNTIF(Table2[Code],'MPG Payment'!B37) -> 12 | AD37: {=SUBSTITUTE(SUBSTITUTE(MID(CELL("filename"),FIND("[",CELL("filename"))+1,FIND("]",CELL("filename"))-FIND("[",CELL("filename"))-1),"JH Farmer Payment-",""),".xlsx","")} -> Indent | AF37: 0 | AG37: 0 | AH37: =AF37-AG37 -> 0 | AI37: 0
A38: BMC Code :2002 | B38: 20020005 | C38: BASKI | D38: MPG | E38: =IFERROR(VLOOKUP(B38,Table2[[Code]:[Category]],13,0),"Indirect") -> Direct | F38: 391 | G38: 16584.01 | H38: =SUMIFS(Table2[Vol_L],Table2[Code],'MPG Payment'!$B38,Table2[Account Details],"Available") -> 402.6 | I38: =SUMIFS(Table2[Amount],Table2[Code],'MPG Payment'!$B38,Table2[Account Details],"Available") -> 16554.226 | J38: =IF(E38="direct",SUMIFS(Table2[Vol_L],Table2[Code],'MPG Payment'!$B38,Table2[Account Details],"Not Available"),0) -> 0 | K38: =IF(E38="direct",SUMIFS(Table2[Amount],Table2[Code],'MPG Payment'!$B38,Table2[Account Details],"Not Available"),0) -> 0 | L38: =H38+J38 -> 402.6 | M38: =I38+K38 -> 16554.226 | N38: =IF(E38="indirect",G38,MIN(G38,M38)) -> 16554.226 | O38: =SUMIFS(Table2[TS Loss],Table2[Code],'MPG Payment'!$B38) -> 0 | P38: =SUMIFS(Table2[Deduction for excess payment],Table2[Code],'MPG Payment'!$B38) -> 0 | Q38: =IF(M38>G38,(M38-G38),0) -> 0 | R38: =SUMIF(Table2[Code],'MPG Payment'!$B38,Table2[CF Deduction]) -> 0 | S38: =SUMIF('Farmer Payment Calc'!D:D,'MPG Payment'!B38,'Farmer Payment Calc'!M:M) -> 0 | T38: 0 | U38: 0 | V38: =IF(E38="direct",SUMIFS(Table2[Net Amount],Table2[Code],'MPG Payment'!$B38,Table2[Account Details],"Available"),0) -> 16553 | W38: =IF(E38="direct",SUMIFS(Table2[Net Amount],Table2[Code],'MPG Payment'!$B38,Table2[Account Details],"Not Available"),0) -> 0 | X38: =IF(Z38="Yes",0,IF(E38="indirect",(G38-O38-P38-R38-T38-U38-S38),0)) -> 0 | Y38: =IF(E38="direct",(G38-O38-P38-V38-X38-R38-S38-T38-U38),0)-W38 -> 31.01 | Z38: 0 | AA38: =ROUND(+N38-O38-P38-R38-T38-V38-W38-X38-S38,0)-U38 -> 1 | AB38: =(M38-G38)/G38 -> -0.0017959468 | AC38: =COUNTIF(Table2[Code],'MPG Payment'!B38) -> 16 | AD38: {=SUBSTITUTE(SUBSTITUTE(MID(CELL("filename"),FIND("[",CELL("filename"))+1,FIND("]",CELL("filename"))-FIND("[",CELL("filename"))-1),"JH Farmer Payment-",""),".xlsx","")} -> Indent | AF38: 0 | AG38: 0 | AH38: =AF38-AG38 -> 0 | AI38: 0
A39: BMC Code :2002 | B39: 20020006 | C39: RANIKHATANGA | D39: MPG | E39: =IFERROR(VLOOKUP(B39,Table2[[Code]:[Category]],13,0),"Indirect") -> Direct | F39: 2471.7 | G39: 95501.73 | H39: =SUMIFS(Table2[Vol_L],Table2[Code],'MPG Payment'!$B39,Table2[Account Details],"Available") -> 2550.34 | I39: =SUMIFS(Table2[Amount],Table2[Code],'MPG Payment'!$B39,Table2[Account Details],"Available") -> 97786.113 | J39: =IF(E39="direct",SUMIFS(Table2[Vol_L],Table2[Code],'MPG Payment'!$B39,Table2[Account Details],"Not Available"),0) -> 0 | K39: =IF(E39="direct",SUMIFS(Table2[Amount],Table2[Code],'MPG Payment'!$B39,Table2[Account Details],"Not Available"),0) -> 0 | L39: =H39+J39 -> 2550.34 | M39: =I39+K39 -> 97786.113 | N39: =IF(E39="indirect",G39,MIN(G39,M39)) -> 95501.73 | O39: =SUMIFS(Table2[TS Loss],Table2[Code],'MPG Payment'!$B39) -> 0 | P39: =SUMIFS(Table2[Deduction for excess payment],Table2[Code],'MPG Payment'!$B39) -> 0 | Q39: =IF(M39>G39,(M39-G39),0) -> 2284.3827 | R39: =SUMIF(Table2[Code],'MPG Payment'!$B39,Table2[CF Deduction]) -> 6048 | S39: =SUMIF('Farmer Payment Calc'!D:D,'MPG Payment'!B39,'Farmer Payment Calc'!M:M) -> 0 | T39: 0 | U39: 0 | V39: =IF(E39="direct",SUMIFS(Table2[Net Amount],Table2[Code],'MPG Payment'!$B39,Table2[Account Details],"Available"),0) -> 89454 | W39: =IF(E39="direct",SUMIFS(Table2[Net Amount],Table2[Code],'MPG Payment'!$B39,Table2[Account Details],"Not Available"),0) -> 0 | X39: =IF(Z39="Yes",0,IF(E39="indirect",(G39-O39-P39-R39-T39-U39-S39),0)) -> 0 | Y39: =IF(E39="direct",(G39-O39-P39-V39-X39-R39-S39-T39-U39),0)-W39 -> -0.27 | Z39: Release1 | AA39: =ROUND(+N39-O39-P39-R39-T39-V39-W39-X39-S39,0)-U39 -> 0 | AB39: =(M39-G39)/G39 -> 0.023919804 | AC39: =COUNTIF(Table2[Code],'MPG Payment'!B39) -> 2 | AD39: {=SUBSTITUTE(SUBSTITUTE(MID(CELL("filename"),FIND("[",CELL("filename"))+1,FIND("]",CELL("filename"))-FIND("[",CELL("filename"))-1),"JH Farmer Payment-",""),".xlsx","")} -> Indent | AE39: CF OS> 15 Day's | AF39: 6350 | AG39: 6048 | AH39: =AF39-AG39 -> 302 | AI39: 0
A40: BMC Code :2002 | B40: 20020007 | C40: SURSA | D40: MPG | E40: =IFERROR(VLOOKUP(B40,Table2[[Code]:[Category]],13,0),"Indirect") -> Direct | F40: 1549.16 | G40: 64524.53 | H40: =SUMIFS(Table2[Vol_L],Table2[Code],'MPG Payment'!$B40,Table2[Account Details],"Available") -> 1557.97 | I40: =SUMIFS(Table2[Amount],Table2[Code],'MPG Payment'!$B40,Table2[Account Details],"Available") -> 64503.424 | J40: =IF(E40="direct",SUMIFS(Table2[Vol_L],Table2[Code],'MPG Payment'!$B40,Table2[Account Details],"Not Available"),0) -> 0 | K40: =IF(E40="direct",SUMIFS(Table2[Amount],Table2[Code],'MPG Payment'!$B40,Table2[Account Details],"Not Available"),0) -> 0 | L40: =H40+J40 -> 1557.97 | M40: =I40+K40 -> 64503.424 | N40: =IF(E40="indirect",G40,MIN(G40,M40)) -> 64503.424 | O40: =SUMIFS(Table2[TS Loss],Table2[Code],'MPG Payment'!$B40) -> 0 | P40: =SUMIFS(Table2[Deduction for excess payment],Table2[Code],'MPG Payment'!$B40) -> 0 | Q40: =IF(M40>G40,(M40-G40),0) -> 0 | R40: =SUMIF(Table2[Code],'MPG Payment'!$B40,Table2[CF Deduction]) -> 0 | S40: =SUMIF('Farmer Payment Calc'!D:D,'MPG Payment'!B40,'Farmer Payment Calc'!M:M) -> 0 | T40: 0 | U40: 0 | V40: =IF(E40="direct",SUMIFS(Table2[Net Amount],Table2[Code],'MPG Payment'!$B40,Table2[Account Details],"Available"),0) -> 64505 | W40: =IF(E40="direct",SUMIFS(Table2[Net Amount],Table2[Code],'MPG Payment'!$B40,Table2[Account Details],"Not Available"),0) -> 0 | X40: =IF(Z40="Yes",0,IF(E40="indirect",(G40-O40-P40-R40-T40-U40-S40),0)) -> 0 | Y40: =IF(E40="direct",(G40-O40-P40-V40-X40-R40-S40-T40-U40),0)-W40 -> 19.53 | Z40: 0 | AA40: =ROUND(+N40-O40-P40-R40-T40-V40-W40-X40-S40,0)-U40 -> -2 | AB40: =(M40-G40)/G40 -> -0.00032710196 | AC40: =COUNTIF(Table2[Code],'MPG Payment'!B40) -> 48 | AD40: {=SUBSTITUTE(SUBSTITUTE(MID(CELL("filename"),FIND("[",CELL("filename"))+1,FIND("]",CELL("filename"))-FIND("[",CELL("filename"))-1),"JH Farmer Payment-",""),".xlsx","")} -> Indent | AF40: 0 | AG40: 0 | AH40: =AF40-AG40 -> 0 | AI40: 0
A41: BMC Code :2002 | B41: 20020011 | C41: DHONTHA TOLI | D41: MPG | E41: =IFERROR(VLOOKUP(B41,Table2[[Code]:[Category]],13,0),"Indirect") -> Direct | F41: 885 | G41: 36636.91 | H41: =SUMIFS(Table2[Vol_L],Table2[Code],'MPG Payment'!$B41,Table2[Account Details],"Available") -> 844.48 | I41: =SUMIFS(Table2[Amount],Table2[Code],'MPG Payment'!$B41,Table2[Account Details],"Available") -> 36933.028 | J41: =IF(E41="direct",SUMIFS(Table2[Vol_L],Table2[Code],'MPG Payment'!$B41,Table2[Account Details],"Not Available"),0) -> 0 | K41: =IF(E41="direct",SUMIFS(Table2[Amount],Table2[Code],'MPG Payment'!$B41,Table2[Account Details],"Not Available"),0) -> 0 | L41: =H41+J41 -> 844.48 | M41: =I41+K41 -> 36933.028 | N41: =IF(E41="indirect",G41,MIN(G41,M41)) -> 36636.91 | O41: =SUMIFS(Table2[TS Loss],Table2[Code],'MPG Payment'!$B41) -> 0 | P41: =SUMIFS(Table2[Deduction for excess payment],Table2[Code],'MPG Payment'!$B41) -> 0 | Q41: =IF(M41>G41,(M41-G41),0) -> 296.1178 | R41: =SUMIF(Table2[Code],'MPG Payment'!$B41,Table2[CF Deduction]) -> 0 | S41: =SUMIF('Farmer Payment Calc'!D:D,'MPG Payment'!B41,'Farmer Payment Calc'!M:M) -> 0 | T41: 0 | U41: 0 | V41: =IF(E41="direct",SUMIFS(Table2[Net Amount],Table2[Code],'MPG Payment'!$B41,Table2[Account Details],"Available"),0) -> 36637 | W41: =IF(E41="direct",SUMIFS(Table2[Net Amount],Table2[Code],'MPG Payment'!$B41,Table2[Account Details],"Not Available"),0) -> 0 | X41: =IF(Z41="Yes",0,IF(E41="indirect",(G41-O41-P41-R41-T41-U41-S41),0)) -> 0 | Y41: =IF(E41="direct",(G41-O41-P41-V41-X41-R41-S41-T41-U41),0)-W41 -> -0.09 | Z41: Release1 | AA41: =ROUND(+N41-O41-P41-R41-T41-V41-W41-X41-S41,0)-U41 -> 0 | AB41: =(M41-G41)/G41 -> 0.0080824993 | AC41: =COUNTIF(Table2[Code],'MPG Payment'!B41) -> 23 | AD41: {=SUBSTITUTE(SUBSTITUTE(MID(CELL("filename"),FIND("[",CELL("filename"))+1,FIND("]",CELL("filename"))-FIND("[",CELL("filename"))-1),"JH Farmer Payment-",""),".xlsx","")} -> Indent | AE41: Letter not received | AF41: 0 | AG41: 0 | AH41: =AF41-AG41 -> 0 | AI41: 0
A42: BMC Code :2002 | B42: 20020013 | C42: BAJPUR | D42: VLC | E42: =IFERROR(VLOOKUP(B42,Table2[[Code]:[Category]],13,0),"Indirect") -> Indirect | F42: 152.8 | G42: 6032.26 | H42: =SUMIFS(Table2[Vol_L],Table2[Code],'MPG Payment'!$B42,Table2[Account Details],"Available") -> 0 | I42: =SUMIFS(Table2[Amount],Table2[Code],'MPG Payment'!$B42,Table2[Account Details],"Available") -> 0 | J42: =IF(E42="direct",SUMIFS(Table2[Vol_L],Table2[Code],'MPG Payment'!$B42,Table2[Account Details],"Not Available"),0) -> 0 | K42: =IF(E42="direct",SUMIFS(Table2[Amount],Table2[Code],'MPG Payment'!$B42,Table2[Account Details],"Not Available"),0) -> 0 | L42: =H42+J42 -> 0 | M42: =I42+K42 -> 0 | N42: =IF(E42="indirect",G42,MIN(G42,M42)) -> 6032.26 | O42: =SUMIFS(Table2[TS Loss],Table2[Code],'MPG Payment'!$B42) -> 0 | P42: =SUMIFS(Table2[Deduction for excess payment],Table2[Code],'MPG Payment'!$B42) -> 0 | Q42: =IF(M42>G42,(M42-G42),0) -> 0 | R42: =SUMIF(Table2[Code],'MPG Payment'!$B42,Table2[CF Deduction]) -> 0 | S42: =SUMIF('Farmer Payment Calc'!D:D,'MPG Payment'!B42,'Farmer Payment Calc'!M:M) -> 0 | T42: 0 | U42: 0 | V42: =IF(E42="direct",SUMIFS(Table2[Net Amount],Table2[Code],'MPG Payment'!$B42,Table2[Account Details],"Available"),0) -> 0 | W42: =IF(E42="direct",SUMIFS(Table2[Net Amount],Table2[Code],'MPG Payment'!$B42,Table2[Account Details],"Not Available"),0) -> 0 | X42: =IF(Z42="Yes",0,IF(E42="indirect",(G42-O42-P42-R42-T42-U42-S42),0)) -> 6032.26 | Y42: =IF(E42="direct",(G42-O42-P42-V42-X42-R42-S42-T42-U42),0)-W42 -> 0 | Z42: 0 | AA42: =ROUND(+N42-O42-P42-R42-T42-V42-W42-X42-S42,0)-U42 -> 0 | AB42: =(M42-G42)/G42 -> -1 | AC42: =COUNTIF(Table2[Code],'MPG Payment'!B42) -> 0 | AD42: {=SUBSTITUTE(SUBSTITUTE(MID(CELL("filename"),FIND("[",CELL("filename"))+1,FIND("]",CELL("filename"))-FIND("[",CELL("filename"))-1),"JH Farmer Payment-",""),".xlsx","")} -> Indent | AF42: 0 | AG42: 0 | AH42: =AF42-AG42 -> 0 | AI42: 0
A43: BMC Code :2002 | B43: 20020014 | C43: BARGARI | D43: MPG | E43: =IFERROR(VLOOKUP(B43,Table2[[Code]:[Category]],13,0),"Indirect") -> Direct | F43: 1231.2 | G43: 49544.95 | H43: =SUMIFS(Table2[Vol_L],Table2[Code],'MPG Payment'!$B43,Table2[Account Details],"Available") -> 1223.91 | I43: =SUMIFS(Table2[Amount],Table2[Code],'MPG Payment'!$B43,Table2[Account Details],"Available") -> 49479.495 | J43: =IF(E43="direct",SUMIFS(Table2[Vol_L],Table2[Code],'MPG Payment'!$B43,Table2[Account Details],"Not Available"),0) -> 0 | K43: =IF(E43="direct",SUMIFS(Table2[Amount],Table2[Code],'MPG Payment'!$B43,Table2[Account Details],"Not Available"),0) -> 0 | L43: =H43+J43 -> 1223.91 | M43: =I43+K43 -> 49479.495 | N43: =IF(E43="indirect",G43,MIN(G43,M43)) -> 49479.495 | O43: =SUMIFS(Table2[TS Loss],Table2[Code],'MPG Payment'!$B43) -> 0 | P43: =SUMIFS(Table2[Deduction for excess payment],Table2[Code],'MPG Payment'!$B43) -> 0 | Q43: =IF(M43>G43,(M43-G43),0) -> 0 | R43: =SUMIF(Table2[Code],'MPG Payment'!$B43,Table2[CF Deduction]) -> 0 | S43: =SUMIF('Farmer Payment Calc'!D:D,'MPG Payment'!B43,'Farmer Payment Calc'!M:M) -> 0 | T43: 0 | U43: 0 | V43: =IF(E43="direct",SUMIFS(Table2[Net Amount],Table2[Code],'MPG Payment'!$B43,Table2[Account Details],"Available"),0) -> 49478 | W43: =IF(E43="direct",SUMIFS(Table2[Net Amount],Table2[Code],'MPG Payment'!$B43,Table2[Account Details],"Not Available"),0) -> 0 | X43: =IF(Z43="Yes",0,IF(E43="indirect",(G43-O43-P43-R43-T43-U43-S43),0)) -> 0 | Y43: =IF(E43="direct",(G43-O43-P43-V43-X43-R43-S43-T43-U43),0)-W43 -> 66.95 | Z43: 0 | AA43: =ROUND(+N43-O43-P43-R43-T43-V43-W43-X43-S43,0)-U43 -> 1 | AB43: =(M43-G43)/G43 -> -0.0013211276 | AC43: =COUNTIF(Table2[Code],'MPG Payment'!B43) -> 17 | AD43: {=SUBSTITUTE(SUBSTITUTE(MID(CELL("filename"),FIND("[",CELL("filename"))+1,FIND("]",CELL("filename"))-FIND("[",CELL("filename"))-1),"JH Farmer Payment-",""),".xlsx","")} -> Indent | AF43: 0 | AG43: 0 | AH43: =AF43-AG43 -> 0 | AI43: 0
A44: BMC Code :2002 | B44: 20020015 | C44: PATRATOLI | D44: MPG | E44: =IFERROR(VLOOKUP(B44,Table2[[Code]:[Category]],13,0),"Indirect") -> Direct | F44: 1902.6 | G44: 75884.61 | H44: =SUMIFS(Table2[Vol_L],Table2[Code],'MPG Payment'!$B44,Table2[Account Details],"Available") -> 1956.33 | I44: =SUMIFS(Table2[Amount],Table2[Code],'MPG Payment'!$B44,Table2[Account Details],"Available") -> 75830.974 | J44: =IF(E44="direct",SUMIFS(Table2[Vol_L],Table2[Code],'MPG Payment'!$B44,Table2[Account Details],"Not Available"),0) -> 0 | K44: =IF(E44="direct",SUMIFS(Table2[Amount],Table2[Code],'MPG Payment'!$B44,Table2[Account Details],"Not Available"),0) -> 0 | L44: =H44+J44 -> 1956.33 | M44: =I44+K44 -> 75830.974 | N44: =IF(E44="indirect",G44,MIN(G44,M44)) -> 75830.974 | O44: =SUMIFS(Table2[TS Loss],Table2[Code],'MPG Payment'!$B44) -> 0 | P44: =SUMIFS(Table2[Deduction for excess payment],Table2[Code],'MPG Payment'!$B44) -> 0 | Q44: =IF(M44>G44,(M44-G44),0) -> 0 | R44: =SUMIF(Table2[Code],'MPG Payment'!$B44,Table2[CF Deduction]) -> 0 | S44: =SUMIF('Farmer Payment Calc'!D:D,'MPG Payment'!B44,'Farmer Payment Calc'!M:M) -> 0 | T44: 0 | U44: 0 | V44: =IF(E44="direct",SUMIFS(Table2[Net Amount],Table2[Code],'MPG Payment'!$B44,Table2[Account Details],"Available"),0) -> 75831 | W44: =IF(E44="direct",SUMIFS(Table2[Net Amount],Table2[Code],'MPG Payment'!$B44,Table2[Account Details],"Not Available"),0) -> 0 | X44: =IF(Z44="Yes",0,IF(E44="indirect",(G44-O44-P44-R44-T44-U44-S44),0)) -> 0 | Y44: =IF(E44="direct",(G44-O44-P44-V44-X44-R44-S44-T44-U44),0)-W44 -> 53.61 | Z44: 0 | AA44: =ROUND(+N44-O44-P44-R44-T44-V44-W44-X44-S44,0)-U44 -> 0 | AB44: =(M44-G44)/G44 -> -0.00070680471 | AC44: =COUNTIF(Table2[Code],'MPG Payment'!B44) -> 34 | AD44: {=SUBSTITUTE(SUBSTITUTE(MID(CELL("filename"),FIND("[",CELL("filename"))+1,FIND("]",CELL("filename"))-FIND("[",CELL("filename"))-1),"JH Farmer Payment-",""),".xlsx","")} -> Indent | AF44: 0 | AG44: 0 | AH44: =AF44-AG44 -> 0 | AI44: 0
A45: BMC Code :2002 | B45: 20020016 | C45: BANAPIRI | D45: MPG | E45: =IFERROR(VLOOKUP(B45,Table2[[Code]:[Category]],13,0),"Indirect") -> Indirect | F45: 294.9 | G45: 12294.22 | H45: =SUMIFS(Table2[Vol_L],Table2[Code],'MPG Payment'!$B45,Table2[Account Details],"Available") -> 0 | I45: =SUMIFS(Table2[Amount],Table2[Code],'MPG Payment'!$B45,Table2[Account Details],"Available") -> 0 | J45: =IF(E45="direct",SUMIFS(Table2[Vol_L],Table2[Code],'MPG Payment'!$B45,Table2[Account Details],"Not Available"),0) -> 0 | K45: =IF(E45="direct",SUMIFS(Table2[Amount],Table2[Code],'MPG Payment'!$B45,Table2[Account Details],"Not Available"),0) -> 0 | L45: =H45+J45 -> 0 | M45: =I45+K45 -> 0 | N45: =IF(E45="indirect",G45,MIN(G45,M45)) -> 12294.22 | O45: =SUMIFS(Table2[TS Loss],Table2[Code],'MPG Payment'!$B45) -> 0 | P45: =SUMIFS(Table2[Deduction for excess payment],Table2[Code],'MPG Payment'!$B45) -> 0 | Q45: =IF(M45>G45,(M45-G45),0) -> 0 | R45: =SUMIF(Table2[Code],'MPG Payment'!$B45,Table2[CF Deduction]) -> 0 | S45: =SUMIF('Farmer Payment Calc'!D:D,'MPG Payment'!B45,'Farmer Payment Calc'!M:M) -> 0 | T45: 0 | U45: 0 | V45: =IF(E45="direct",SUMIFS(Table2[Net Amount],Table2[Code],'MPG Payment'!$B45,Table2[Account Details],"Available"),0) -> 0 | W45: =IF(E45="direct",SUMIFS(Table2[Net Amount],Table2[Code],'MPG Payment'!$B45,Table2[Account Details],"Not Available"),0) -> 0 | X45: =IF(Z45="Yes",0,IF(E45="indirect",(G45-O45-P45-R45-T45-U45-S45),0)) -> 12294.22 | Y45: =IF(E45="direct",(G45-O45-P45-V45-X45-R45-S45-T45-U45),0)-W45 -> 0 | Z45: 0 | AA45: =ROUND(+N45-O45-P45-R45-T45-V45-W45-X45-S45,0)-U45 -> 0 | AB45: =(M45-G45)/G45 -> -1 | AC45: =COUNTIF(Table2[Code],'MPG Payment'!B45) -> 0 | AD45: {=SUBSTITUTE(SUBSTITUTE(MID(CELL("filename"),FIND("[",CELL("filename"))+1,FIND("]",CELL("filename"))-FIND("[",CELL("filename"))-1),"JH Farmer Payment-",""),".xlsx","")} -> Indent | AF45: 0 | AG45: 0 | AH45: =AF45-AG45 -> 0 | AI45: 0
A46: BMC Code :2002 | B46: 20020020 | C46: TIKO TOLI | D46: MPG | E46: =IFERROR(VLOOKUP(B46,Table2[[Code]:[Category]],13,0),"Indirect") -> Direct | F46: 1397.39 | G46: 56696.93 | H46: =SUMIFS(Table2[Vol_L],Table2[Code],'MPG Payment'!$B46,Table2[Account Details],"Available") -> 1387.32 | I46: =SUMIFS(Table2[Amount],Table2[Code],'MPG Payment'!$B46,Table2[Account Details],"Available") -> 56648.601 | J46: =IF(E46="direct",SUMIFS(Table2[Vol_L],Table2[Code],'MPG Payment'!$B46,Table2[Account Details],"Not Available"),0) -> 0 | K46: =IF(E46="direct",SUMIFS(Table2[Amount],Table2[Code],'MPG Payment'!$B46,Table2[Account Details],"Not Available"),0) -> 0 | L46: =H46+J46 -> 1387.32 | M46: =I46+K46 -> 56648.601 | N46: =IF(E46="indirect",G46,MIN(G46,M46)) -> 56648.601 | O46: =SUMIFS(Table2[TS Loss],Table2[Code],'MPG Payment'!$B46) -> 0 | P46: =SUMIFS(Table2[Deduction for excess payment],Table2[Code],'MPG Payment'!$B46) -> 0 | Q46: =IF(M46>G46,(M46-G46),0) -> 0 | R46: =SUMIF(Table2[Code],'MPG Payment'!$B46,Table2[CF Deduction]) -> 0 | S46: =SUMIF('Farmer Payment Calc'!D:D,'MPG Payment'!B46,'Farmer Payment Calc'!M:M) -> 0 | T46: 0 | U46: 0 | V46: =IF(E46="direct",SUMIFS(Table2[Net Amount],Table2[Code],'MPG Payment'!$B46,Table2[Account Details],"Available"),0) -> 56650 | W46: =IF(E46="direct",SUMIFS(Table2[Net Amount],Table2[Code],'MPG Payment'!$B46,Table2[Account Details],"Not Available"),0) -> 0 | X46: =IF(Z46="Yes",0,IF(E46="indirect",(G46-O46-P46-R46-T46-U46-S46),0)) -> 0 | Y46: =IF(E46="direct",(G46-O46-P46-V46-X46-R46-S46-T46-U46),0)-W46 -> 46.93 | Z46: 0 | AA46: =ROUND(+N46-O46-P46-R46-T46-V46-W46-X46-S46,0)-U46 -> -1 | AB46: =(M46-G46)/G46 -> -0.000852413 | AC46: =COUNTIF(Table2[Code],'MPG Payment'!B46) -> 34 | AD46: {=SUBSTITUTE(SUBSTITUTE(MID(CELL("filename"),FIND("[",CELL("filename"))+1,FIND("]",CELL("filename"))-FIND("[",CELL("filename"))-1),"JH Farmer Payment-",""),".xlsx","")} -> Indent | AF46: 0 | AG46: 0 | AH46: =AF46-AG46 -> 0 | AI46: 0
A47: BMC Code :2002 | B47: 20020021 | C47: PUNGI | D47: MPG | E47: =IFERROR(VLOOKUP(B47,Table2[[Code]:[Category]],13,0),"Indirect") -> Direct | F47: 457.9 | G47: 19641.39 | H47: =SUMIFS(Table2[Vol_L],Table2[Code],'MPG Payment'!$B47,Table2[Account Details],"Available") -> 461.14 | I47: =SUMIFS(Table2[Amount],Table2[Code],'MPG Payment'!$B47,Table2[Account Details],"Available") -> 19605.734 | J47: =IF(E47="direct",SUMIFS(Table2[Vol_L],Table2[Code],'MPG Payment'!$B47,Table2[Account Details],"Not Available"),0) -> 0 | K47: =IF(E47="direct",SUMIFS(Table2[Amount],Table2[Code],'MPG Payment'!$B47,Table2[Account Details],"Not Available"),0) -> 0 | L47: =H47+J47 -> 461.14 | M47: =I47+K47 -> 19605.734 | N47: =IF(E47="indirect",G47,MIN(G47,M47)) -> 19605.734 | O47: =SUMIFS(Table2[TS Loss],Table2[Code],'MPG Payment'!$B47) -> 0 | P47: =SUMIFS(Table2[Deduction for excess payment],Table2[Code],'MPG Payment'!$B47) -> 0 | Q47: =IF(M47>G47,(M47-G47),0) -> 0 | R47: =SUMIF(Table2[Code],'MPG Payment'!$B47,Table2[CF Deduction]) -> 0 | S47: =SUMIF('Farmer Payment Calc'!D:D,'MPG Payment'!B47,'Farmer Payment Calc'!M:M) -> 0 | T47: 0 | U47: 0 | V47: =IF(E47="direct",SUMIFS(Table2[Net Amount],Table2[Code],'MPG Payment'!$B47,Table2[Account Details],"Available"),0) -> 19607 | W47: =IF(E47="direct",SUMIFS(Table2[Net Amount],Table2[Code],'MPG Payment'!$B47,Table2[Account Details],"Not Available"),0) -> 0 | X47: =IF(Z47="Yes",0,IF(E47="indirect",(G47-O47-P47-R47-T47-U47-S47),0)) -> 0 | Y47: =IF(E47="direct",(G47-O47-P47-V47-X47-R47-S47-T47-U47),0)-W47 -> 34.39 | Z47: 0 | AA47: =ROUND(+N47-O47-P47-R47-T47-V47-W47-X47-S47,0)-U47 -> -1 | AB47: =(M47-G47)/G47 -> -0.0018153298 | AC47: =COUNTIF(Table2[Code],'MPG Payment'!B47) -> 20 | AD47: {=SUBSTITUTE(SUBSTITUTE(MID(CELL("filename"),FIND("[",CELL("filename"))+1,FIND("]",CELL("filename"))-FIND("[",CELL("filename"))-1),"JH Farmer Payment-",""),".xlsx","")} -> Indent | AF47: 0 | AG47: 0 | AH47: =AF47-AG47 -> 0 | AI47: 0
A48: BMC Code :2002 | B48: 20020023 | C48: BARTOLI | D48: MPG | E48: =IFERROR(VLOOKUP(B48,Table2[[Code]:[Category]],13,0),"Indirect") -> Direct | F48: 794.7 | G48: 30502.73 | H48: =SUMIFS(Table2[Vol_L],Table2[Code],'MPG Payment'!$B48,Table2[Account Details],"Available") -> 747.95 | I48: =SUMIFS(Table2[Amount],Table2[Code],'MPG Payment'!$B48,Table2[Account Details],"Available") -> 30437.188 | J48: =IF(E48="direct",SUMIFS(Table2[Vol_L],Table2[Code],'MPG Payment'!$B48,Table2[Account Details],"Not Available"),0) -> 0 | K48: =IF(E48="direct",SUMIFS(Table2[Amount],Table2[Code],'MPG Payment'!$B48,Table2[Account Details],"Not Available"),0) -> 0 | L48: =H48+J48 -> 747.95 | M48: =I48+K48 -> 30437.188 | N48: =IF(E48="indirect",G48,MIN(G48,M48)) -> 30437.188 | O48: =SUMIFS(Table2[TS Loss],Table2[Code],'MPG Payment'!$B48) -> 0 | P48: =SUMIFS(Table2[Deduction for excess payment],Table2[Code],'MPG Payment'!$B48) -> 0 | Q48: =IF(M48>G48,(M48-G48),0) -> 0 | R48: =SUMIF(Table2[Code],'MPG Payment'!$B48,Table2[CF Deduction]) -> 0 | S48: =SUMIF('Farmer Payment Calc'!D:D,'MPG Payment'!B48,'Farmer Payment Calc'!M:M) -> 0 | T48: 0 | U48: 0 | V48: =IF(E48="direct",SUMIFS(Table2[Net Amount],Table2[Code],'MPG Payment'!$B48,Table2[Account Details],"Available"),0) -> 30437 | W48: =IF(E48="direct",SUMIFS(Table2[Net Amount],Table2[Code],'MPG Payment'!$B48,Table2[Account Details],"Not Available"),0) -> 0 | X48: =IF(Z48="Yes",0,IF(E48="indirect",(G48-O48-P48-R48-T48-U48-S48),0)) -> 0 | Y48: =IF(E48="direct",(G48-O48-P48-V48-X48-R48-S48-T48-U48),0)-W48 -> 65.73 | Z48: 0 | AA48: =ROUND(+N48-O48-P48-R48-T48-V48-W48-X48-S48,0)-U48 -> 0 | AB48: =(M48-G48)/G48 -> -0.0021487126 | AC48: =COUNTIF(Table2[Code],'MPG Payment'!B48) -> 18 | AD48: {=SUBSTITUTE(SUBSTITUTE(MID(CELL("filename"),FIND("[",CELL("filename"))+1,FIND("]",CELL("filename"))-FIND("[",CELL("filename"))-1),"JH Farmer Payment-",""),".xlsx","")} -> Indent | AF48: 0 | AG48: 0 | AH48: =AF48-AG48 -> 0 | AI48: 0
A49: BMC Code :2002 | B49: 20020025 | C49: AGRU | D49: VLC | E49: =IFERROR(VLOOKUP(B49,Table2[[Code]:[Category]],13,0),"Indirect") -> Direct | F49: 417.3 | G49: 17218.63 | H49: =SUMIFS(Table2[Vol_L],Table2[Code],'MPG Payment'!$B49,Table2[Account Details],"Available") -> 419.51 | I49: =SUMIFS(Table2[Amount],Table2[Code],'MPG Payment'!$B49,Table2[Account Details],"Available") -> 17146.427 | J49: =IF(E49="direct",SUMIFS(Table2[Vol_L],Table2[Code],'MPG Payment'!$B49,Table2[Account Details],"Not Available"),0) -> 0 | K49: =IF(E49="direct",SUMIFS(Table2[Amount],Table2[Code],'MPG Payment'!$B49,Table2[Account Details],"Not Available"),0) -> 0 | L49: =H49+J49 -> 419.51 | M49: =I49+K49 -> 17146.427 | N49: =IF(E49="indirect",G49,MIN(G49,M49)) -> 17146.427 | O49: =SUMIFS(Table2[TS Loss],Table2[Code],'MPG Payment'!$B49) -> 0 | P49: =SUMIFS(Table2[Deduction for excess payment],Table2[Code],'MPG Payment'!$B49) -> 0 | Q49: =IF(M49>G49,(M49-G49),0) -> 0 | R49: =SUMIF(Table2[Code],'MPG Payment'!$B49,Table2[CF Deduction]) -> 0 | S49: =SUMIF('Farmer Payment Calc'!D:D,'MPG Payment'!B49,'Farmer Payment Calc'!M:M) -> 0 | T49: 0 | U49: 0 | V49: =IF(E49="direct",SUMIFS(Table2[Net Amount],Table2[Code],'MPG Payment'!$B49,Table2[Account Details],"Available"),0) -> 17147 | W49: =IF(E49="direct",SUMIFS(Table2[Net Amount],Table2[Code],'MPG Payment'!$B49,Table2[Account Details],"Not Available"),0) -> 0 | X49: =IF(Z49="Yes",0,IF(E49="indirect",(G49-O49-P49-R49-T49-U49-S49),0)) -> 0 | Y49: =IF(E49="direct",(G49-O49-P49-V49-X49-R49-S49-T49-U49),0)-W49 -> 71.63 | Z49: 0 | AA49: =ROUND(+N49-O49-P49-R49-T49-V49-W49-X49-S49,0)-U49 -> -1 | AB49: =(M49-G49)/G49 -> -0.0041933243 | AC49: =COUNTIF(Table2[Code],'MPG Payment'!B49) -> 9 | AD49: {=SUBSTITUTE(SUBSTITUTE(MID(CELL("filename"),FIND("[",CELL("filename"))+1,FIND("]",CELL("filename"))-FIND("[",CELL("filename"))-1),"JH Farmer Payment-",""),".xlsx","")} -> Indent | AF49: 0 | AG49: 0 | AH49: =AF49-AG49 -> 0 | AI49: 0
A50: BMC Code :2002 | B50: 20020026 | C50: TIGRA | D50: MPG | E50: =IFERROR(VLOOKUP(B50,Table2[[Code]:[Category]],13,0),"Indirect") -> Direct | F50: 3840.1 | G50: 155719.03 | H50: =SUMIFS(Table2[Vol_L],Table2[Code],'MPG Payment'!$B50,Table2[Account Details],"Available") -> 3752.99 | I50: =SUMIFS(Table2[Amount],Table2[Code],'MPG Payment'!$B50,Table2[Account Details],"Available") -> 155620.52 | J50: =IF(E50="direct",SUMIFS(Table2[Vol_L],Table2[Code],'MPG Payment'!$B50,Table2[Account Details],"Not Available"),0) -> 0 | K50: =IF(E50="direct",SUMIFS(Table2[Amount],Table2[Code],'MPG Payment'!$B50,Table2[Account Details],"Not Available"),0) -> 0 | L50: =H50+J50 -> 3752.99 | M50: =I50+K50 -> 155620.52 | N50: =IF(E50="indirect",G50,MIN(G50,M50)) -> 155620.52 | O50: =SUMIFS(Table2[TS Loss],Table2[Code],'MPG Payment'!$B50) -> 0 | P50: =SUMIFS(Table2[Deduction for excess payment],Table2[Code],'MPG Payment'!$B50) -> 0 | Q50: =IF(M50>G50,(M50-G50),0) -> 0 | R50: =SUMIF(Table2[Code],'MPG Payment'!$B50,Table2[CF Deduction]) -> 0 | S50: =SUMIF('Farmer Payment Calc'!D:D,'MPG Payment'!B50,'Farmer Payment Calc'!M:M) -> 0 | T50: 0 | U50: 0 | V50: =IF(E50="direct",SUMIFS(Table2[Net Amount],Table2[Code],'MPG Payment'!$B50,Table2[Account Details],"Available"),0) -> 155617 | W50: =IF(E50="direct",SUMIFS(Table2[Net Amount],Table2[Code],'MPG Payment'!$B50,Table2[Account Details],"Not Available"),0) -> 0 | X50: =IF(Z50="Yes",0,IF(E50="indirect",(G50-O50-P50-R50-T50-U50-S50),0)) -> 0 | Y50: =IF(E50="direct",(G50-O50-P50-V50-X50-R50-S50-T50-U50),0)-W50 -> 102.03 | Z50: 0 | AA50: =ROUND(+N50-O50-P50-R50-T50-V50-W50-X50-S50,0)-U50 -> 4 | AB50: =(M50-G50)/G50 -> -0.00063264008 | AC50: =COUNTIF(Table2[Code],'MPG Payment'!B50) -> 42 | AD50: {=SUBSTITUTE(SUBSTITUTE(MID(CELL("filename"),FIND("[",CELL("filename"))+1,FIND("]",CELL("filename"))-FIND("[",CELL("filename"))-1),"JH Farmer Payment-",""),".xlsx","")} -> Indent | AF50: 0 | AG50: 0 | AH50: =AF50-AG50 -> 0 | AI50: 0
A51: BMC Code :2002 | B51: 20020027 | C51: GARRI | D51: VLC | E51: =IFERROR(VLOOKUP(B51,Table2[[Code]:[Category]],13,0),"Indirect") -> Direct | F51: 483.9 | G51: 20220.84 | H51: =SUMIFS(Table2[Vol_L],Table2[Code],'MPG Payment'!$B51,Table2[Account Details],"Available") -> 461.02 | I51: =SUMIFS(Table2[Amount],Table2[Code],'MPG Payment'!$B51,Table2[Account Details],"Available") -> 20183.355 | J51: =IF(E51="direct",SUMIFS(Table2[Vol_L],Table2[Code],'MPG Payment'!$B51,Table2[Account Details],"Not Available"),0) -> 0 | K51: =IF(E51="direct",SUMIFS(Table2[Amount],Table2[Code],'MPG Payment'!$B51,Table2[Account Details],"Not Available"),0) -> 0 | L51: =H51+J51 -> 461.02 | M51: =I51+K51 -> 20183.355 | N51: =IF(E51="indirect",G51,MIN(G51,M51)) -> 20183.355 | O51: =SUMIFS(Table2[TS Loss],Table2[Code],'MPG Payment'!$B51) -> 0 | P51: =SUMIFS(Table2[Deduction for excess payment],Table2[Code],'MPG Payment'!$B51) -> 0 | Q51: =IF(M51>G51,(M51-G51),0) -> 0 | R51: =SUMIF(Table2[Code],'MPG Payment'!$B51,Table2[CF Deduction]) -> 5515 | S51: =SUMIF('Farmer Payment Calc'!D:D,'MPG Payment'!B51,'Farmer Payment Calc'!M:M) -> 0 | T51: 0 | U51: 0 | V51: =IF(E51="direct",SUMIFS(Table2[Net Amount],Table2[Code],'MPG Payment'!$B51,Table2[Account Details],"Available"),0) -> 14670 | W51: =IF(E51="direct",SUMIFS(Table2[Net Amount],Table2[Code],'MPG Payment'!$B51,Table2[Account Details],"Not Available"),0) -> 0 | X51: =IF(Z51="Yes",0,IF(E51="indirect",(G51-O51-P51-R51-T51-U51-S51),0)) -> 0 | Y51: =IF(E51="direct",(G51-O51-P51-V51-X51-R51-S51-T51-U51),0)-W51 -> 35.84 | Z51: 0 | AA51: =ROUND(+N51-O51-P51-R51-T51-V51-W51-X51-S51,0)-U51 -> -2 | AB51: =(M51-G51)/G51 -> -0.0018537855 | AC51: =COUNTIF(Table2[Code],'MPG Payment'!B51) -> 6 | AD51: {=SUBSTITUTE(SUBSTITUTE(MID(CELL("filename"),FIND("[",CELL("filename"))+1,FIND("]",CELL("filename"))-FIND("[",CELL("filename"))-1),"JH Farmer Payment-",""),".xlsx","")} -> Indent | AF51: 0 | AG51: 0 | AH51: =AF51-AG51 -> 0 | AI51: 0
A52: BMC Code :2002 | B52: 20020028 | C52: HISRI | D52: VLC | E52: =IFERROR(VLOOKUP(B52,Table2[[Code]:[Category]],13,0),"Indirect") -> Direct | F52: 1334.38 | G52: 56181.34 | H52: =SUMIFS(Table2[Vol_L],Table2[Code],'MPG Payment'!$B52,Table2[Account Details],"Available") -> 1351.34 | I52: =SUMIFS(Table2[Amount],Table2[Code],'MPG Payment'!$B52,Table2[Account Details],"Available") -> 56173.931 | J52: =IF(E52="direct",SUMIFS(Table2[Vol_L],Table2[Code],'MPG Payment'!$B52,Table2[Account Details],"Not Available"),0) -> 0 | K52: =IF(E52="direct",SUMIFS(Table2[Amount],Table2[Code],'MPG Payment'!$B52,Table2[Account Details],"Not Available"),0) -> 0 | L52: =H52+J52 -> 1351.34 | M52: =I52+K52 -> 56173.931 | N52: =IF(E52="indirect",G52,MIN(G52,M52)) -> 56173.931 | O52: =SUMIFS(Table2[TS Loss],Table2[Code],'MPG Payment'!$B52) -> 0 | P52: =SUMIFS(Table2[Deduction for excess payment],Table2[Code],'MPG Payment'!$B52) -> 0 | Q52: =IF(M52>G52,(M52-G52),0) -> 0 | R52: =SUMIF(Table2[Code],'MPG Payment'!$B52,Table2[CF Deduction]) -> 0 | S52: =SUMIF('Farmer Payment Calc'!D:D,'MPG Payment'!B52,'Farmer Payment Calc'!M:M) -> 0 | T52: 0 | U52: 0 | V52: =IF(E52="direct",SUMIFS(Table2[Net Amount],Table2[Code],'MPG Payment'!$B52,Table2[Account Details],"Available"),0) -> 56173 | W52: =IF(E52="direct",SUMIFS(Table2[Net Amount],Table2[Code],'MPG Payment'!$B52,Table2[Account Details],"Not Available"),0) -> 0 | X52: =IF(Z52="Yes",0,IF(E52="indirect",(G52-O52-P52-R52-T52-U52-S52),0)) -> 0 | Y52: =IF(E52="direct",(G52-O52-P52-V52-X52-R52-S52-T52-U52),0)-W52 -> 8.34 | Z52: 0 | AA52: =ROUND(+N52-O52-P52-R52-T52-V52-W52-X52-S52,0)-U52 -> 1 | AB52: =(M52-G52)/G52 -> -0.00013187119 | AC52: =COUNTIF(Table2[Code],'MPG Payment'!B52) -> 32 | AD52: {=SUBSTITUTE(SUBSTITUTE(MID(CELL("filename"),FIND("[",CELL("filename"))+1,FIND("]",CELL("filename"))-FIND("[",CELL("filename"))-1),"JH Farmer Payment-",""),".xlsx","")} -> Indent | AF52: 0 | AG52: 0 | AH52: =AF52-AG52 -> 0 | AI52: 0
A53: BMC Code :2002 | B53: 20020029 | C53: MURMA | D53: VLC | E53: =IFERROR(VLOOKUP(B53,Table2[[Code]:[Category]],13,0),"Indirect") -> Direct | F53: 794.5 | G53: 32003.1 | H53: =SUMIFS(Table2[Vol_L],Table2[Code],'MPG Payment'!$B53,Table2[Account Details],"Available") -> 793.19 | I53: =SUMIFS(Table2[Amount],Table2[Code],'MPG Payment'!$B53,Table2[Account Details],"Available") -> 31909.739 | J53: =IF(E53="direct",SUMIFS(Table2[Vol_L],Table2[Code],'MPG Payment'!$B53,Table2[Account Details],"Not Available"),0) -> 0 | K53: =IF(E53="direct",SUMIFS(Table2[Amount],Table2[Code],'MPG Payment'!$B53,Table2[Account Details],"Not Available"),0) -> 0 | L53: =H53+J53 -> 793.19 | M53: =I53+K53 -> 31909.739 | N53: =IF(E53="indirect",G53,MIN(G53,M53)) -> 31909.739 | O53: =SUMIFS(Table2[TS Loss],Table2[Code],'MPG Payment'!$B53) -> 0 | P53: =SUMIFS(Table2[Deduction for excess payment],Table2[Code],'MPG Payment'!$B53) -> 0 | Q53: =IF(M53>G53,(M53-G53),0) -> 0 | R53: =SUMIF(Table2[Code],'MPG Payment'!$B53,Table2[CF Deduction]) -> 6350 | S53: =SUMIF('Farmer Payment Calc'!D:D,'MPG Payment'!B53,'Farmer Payment Calc'!M:M) -> 0 | T53: 0 | U53: 0 | V53: =IF(E53="direct",SUMIFS(Table2[Net Amount],Table2[Code],'MPG Payment'!$B53,Table2[Account Details],"Available"),0) -> 25561 | W53: =IF(E53="direct",SUMIFS(Table2[Net Amount],Table2[Code],'MPG Payment'!$B53,Table2[Account Details],"Not Available"),0) -> 0 | X53: =IF(Z53="Yes",0,IF(E53="indirect",(G53-O53-P53-R53-T53-U53-S53),0)) -> 0 | Y53: =IF(E53="direct",(G53-O53-P53-V53-X53-R53-S53-T53-U53),0)-W53 -> 92.1 | Z53: 0 | AA53: =ROUND(+N53-O53-P53-R53-T53-V53-W53-X53-S53,0)-U53 -> -1 | AB53: =(M53-G53)/G53 -> -0.0029172486 | AC53: =COUNTIF(Table2[Code],'MPG Payment'!B53) -> 18 | AD53: {=SUBSTITUTE(SUBSTITUTE(MID(CELL("filename"),FIND("[",CELL("filename"))+1,FIND("]",CELL("filename"))-FIND("[",CELL("filename"))-1),"JH Farmer Payment-",""),".xlsx","")} -> Indent | AF53: 0 | AG53: 0 | AH53: =AF53-AG53 -> 0 | AI53: 0
A54: BMC Code :2002 | B54: 20020030 | C54: NAYASARIYA | D54: VLC | E54: =IFERROR(VLOOKUP(B54,Table2[[Code]:[Category]],13,0),"Indirect") -> Indirect | F54: 557.3 | G54: 22238.06 | H54: =SUMIFS(Table2[Vol_L],Table2[Code],'MPG Payment'!$B54,Table2[Account Details],"Available") -> 0 | I54: =SUMIFS(Table2[Amount],Table2[Code],'MPG Payment'!$B54,Table2[Account Details],"Available") -> 0 | J54: =IF(E54="direct",SUMIFS(Table2[Vol_L],Table2[Code],'MPG Payment'!$B54,Table2[Account Details],"Not Available"),0) -> 0 | K54: =IF(E54="direct",SUMIFS(Table2[Amount],Table2[Code],'MPG Payment'!$B54,Table2[Account Details],"Not Available"),0) -> 0 | L54: =H54+J54 -> 0 | M54: =I54+K54 -> 0 | N54: =IF(E54="indirect",G54,MIN(G54,M54)) -> 22238.06 | O54: =SUMIFS(Table2[TS Loss],Table2[Code],'MPG Payment'!$B54) -> 0 | P54: =SUMIFS(Table2[Deduction for excess payment],Table2[Code],'MPG Payment'!$B54) -> 0 | Q54: =IF(M54>G54,(M54-G54),0) -> 0 | R54: 7620 | S54: =SUMIF('Farmer Payment Calc'!D:D,'MPG Payment'!B54,'Farmer Payment Calc'!M:M) -> 0 | T54: 0 | U54: 0 | V54: =IF(E54="direct",SUMIFS(Table2[Net Amount],Table2[Code],'MPG Payment'!$B54,Table2[Account Details],"Available"),0) -> 0 | W54: =IF(E54="direct",SUMIFS(Table2[Net Amount],Table2[Code],'MPG Payment'!$B54,Table2[Account Details],"Not Available"),0) -> 0 | X54: =IF(Z54="Yes",0,IF(E54="indirect",(G54-O54-P54-R54-T54-U54-S54),0)) -> 14618.06 | Y54: =IF(E54="direct",(G54-O54-P54-V54-X54-R54-S54-T54-U54),0)-W54 -> 0 | Z54: 0 | AA54: =ROUND(+N54-O54-P54-R54-T54-V54-W54-X54-S54,0)-U54 -> 0 | AB54: =(M54-G54)/G54 -> -1 | AC54: =COUNTIF(Table2[Code],'MPG Payment'!B54) -> 0 | AD54: {=SUBSTITUTE(SUBSTITUTE(MID(CELL("filename"),FIND("[",CELL("filename"))+1,FIND("]",CELL("filename"))-FIND("[",CELL("filename"))-1),"JH Farmer Payment-",""),".xlsx","")} -> Indent | AF54: 0 | AG54: 0 | AH54: =AF54-AG54 -> 0 | AI54: 0
A55: BMC Code :2003 | B55: 20030001 | C55: Hisri Thakurgaon | D55: RMC | E55: =IFERROR(VLOOKUP(B55,Table2[[Code]:[Category]],13,0),"Indirect") -> Direct | F55: 3919.56 | G55: 147183.69 | H55: =SUMIFS(Table2[Vol_L],Table2[Code],'MPG Payment'!$B55,Table2[Account Details],"Available") -> 3919.56 | I55: =SUMIFS(Table2[Amount],Table2[Code],'MPG Payment'!$B55,Table2[Account Details],"Available") -> 147109.14 | J55: =IF(E55="direct",SUMIFS(Table2[Vol_L],Table2[Code],'MPG Payment'!$B55,Table2[Account Details],"Not Available"),0) -> 0 | K55: =IF(E55="direct",SUMIFS(Table2[Amount],Table2[Code],'MPG Payment'!$B55,Table2[Account Details],"Not Available"),0) -> 0 | L55: =H55+J55 -> 3919.56 | M55: =I55+K55 -> 147109.14 | N55: =IF(E55="indirect",G55,MIN(G55,M55)) -> 147109.14 | O55: =SUMIFS(Table2[TS Loss],Table2[Code],'MPG Payment'!$B55) -> 1169 | P55: =SUMIFS(Table2[Deduction for excess payment],Table2[Code],'MPG Payment'!$B55) -> 0 | Q55: =IF(M55>G55,(M55-G55),0) -> 0 | R55: =SUMIF(Table2[Code],'MPG Payment'!$B55,Table2[CF Deduction]) -> 0 | S55: =SUMIF('Farmer Payment Calc'!D:D,'MPG Payment'!B55,'Farmer Payment Calc'!M:M) -> 0 | T55: 0 | U55: 0 | V55: =IF(E55="direct",SUMIFS(Table2[Net Amount],Table2[Code],'MPG Payment'!$B55,Table2[Account Details],"Available"),0) -> 145939 | W55: =IF(E55="direct",SUMIFS(Table2[Net Amount],Table2[Code],'MPG Payment'!$B55,Table2[Account Details],"Not Available"),0) -> 0 | X55: =IF(Z55="Yes",0,IF(E55="indirect",(G55-O55-P55-R55-T55-U55-S55),0)) -> 0 | Y55: =IF(E55="direct",(G55-O55-P55-V55-X55-R55-S55-T55-U55),0)-W55 -> 75.69 | Z55: 0 | AA55: =ROUND(+N55-O55-P55-R55-T55-V55-W55-X55-S55,0)-U55 -> 1 | AB55: =(M55-G55)/G55 -> -0.00050653439 | AC55: =COUNTIF(Table2[Code],'MPG Payment'!B55) -> 20 | AD55: {=SUBSTITUTE(SUBSTITUTE(MID(CELL("filename"),FIND("[",CELL("filename"))+1,FIND("]",CELL("filename"))-FIND("[",CELL("filename"))-1),"JH Farmer Payment-",""),".xlsx","")} -> Indent | AF55: 0 | AG55: 0 | AH55: =AF55-AG55 -> 0 | AI55: 0
A56: BMC Code :2003 | B56: 20030002 | C56: UMEDANDA | D56: MPG | E56: =IFERROR(VLOOKUP(B56,Table2[[Code]:[Category]],13,0),"Indirect") -> Direct | F56: 728.35 | G56: 29799.21 | H56: =SUMIFS(Table2[Vol_L],Table2[Code],'MPG Payment'!$B56,Table2[Account Details],"Available") -> 729.44 | I56: =SUMIFS(Table2[Amount],Table2[Code],'MPG Payment'!$B56,Table2[Account Details],"Available") -> 29683.688 | J56: =IF(E56="direct",SUMIFS(Table2[Vol_L],Table2[Code],'MPG Payment'!$B56,Table2[Account Details],"Not Available"),0) -> 0 | K56: =IF(E56="direct",SUMIFS(Table2[Amount],Table2[Code],'MPG Payment'!$B56,Table2[Account Details],"Not Available"),0) -> 0 | L56: =H56+J56 -> 729.44 | M56: =I56+K56 -> 29683.688 | N56: =IF(E56="indirect",G56,MIN(G56,M56)) -> 29683.688 | O56: =SUMIFS(Table2[TS Loss],Table2[Code],'MPG Payment'!$B56) -> 0 | P56: =SUMIFS(Table2[Deduction for excess payment],Table2[Code],'MPG Payment'!$B56) -> 0 | Q56: =IF(M56>G56,(M56-G56),0) -> 0 | R56: =SUMIF(Table2[Code],'MPG Payment'!$B56,Table2[CF Deduction]) -> 0 | S56: =SUMIF('Farmer Payment Calc'!D:D,'MPG Payment'!B56,'Farmer Payment Calc'!M:M) -> 0 | T56: 0 | U56: 0 | V56: =IF(E56="direct",SUMIFS(Table2[Net Amount],Table2[Code],'MPG Payment'!$B56,Table2[Account Details],"Available"),0) -> 29684 | W56: =IF(E56="direct",SUMIFS(Table2[Net Amount],Table2[Code],'MPG Payment'!$B56,Table2[Account Details],"Not Available"),0) -> 0 | X56: =IF(Z56="Yes",0,IF(E56="indirect",(G56-O56-P56-R56-T56-U56-S56),0)) -> 0 | Y56: =IF(E56="direct",(G56-O56-P56-V56-X56-R56-S56-T56-U56),0)-W56 -> 115.21 | Z56: 0 | AA56: =ROUND(+N56-O56-P56-R56-T56-V56-W56-X56-S56,0)-U56 -> 0 | AB56: =(M56-G56)/G56 -> -0.0038766934 | AC56: =COUNTIF(Table2[Code],'MPG Payment'!B56) -> 9 | AD56: {=SUBSTITUTE(SUBSTITUTE(MID(CELL("filename"),FIND("[",CELL("filename"))+1,FIND("]",CELL("filename"))-FIND("[",CELL("filename"))-1),"JH Farmer Payment-",""),".xlsx","")} -> Indent | AF56: 0 | AG56: 0 | AH56: =AF56-AG56 -> 0 | AI56: 0
A57: BMC Code :2003 | B57: 20030005 | C57: THAKURGAON | D57: VLC | E57: =IFERROR(VLOOKUP(B57,Table2[[Code]:[Category]],13,0),"Indirect") -> Indirect | F57: 202.66 | G57: 8054.15 | H57: =SUMIFS(Table2[Vol_L],Table2[Code],'MPG Payment'!$B57,Table2[Account Details],"Available") -> 0 | I57: =SUMIFS(Table2[Amount],Table2[Code],'MPG Payment'!$B57,Table2[Account Details],"Available") -> 0 | J57: =IF(E57="direct",SUMIFS(Table2[Vol_L],Table2[Code],'MPG Payment'!$B57,Table2[Account Details],"Not Available"),0) -> 0 | K57: =IF(E57="direct",SUMIFS(Table2[Amount],Table2[Code],'MPG Payment'!$B57,Table2[Account Details],"Not Available"),0) -> 0 | L57: =H57+J57 -> 0 | M57: =I57+K57 -> 0 | N57: =IF(E57="indirect",G57,MIN(G57,M57)) -> 8054.15 | O57: =SUMIFS(Table2[TS Loss],Table2[Code],'MPG Payment'!$B57) -> 0 | P57: =SUMIFS(Table2[Deduction for excess payment],Table2[Code],'MPG Payment'!$B57) -> 0 | Q57: =IF(M57>G57,(M57-G57),0) -> 0 | R57: =SUMIF(Table2[Code],'MPG Payment'!$B57,Table2[CF Deduction]) -> 0 | S57: =SUMIF('Farmer Payment Calc'!D:D,'MPG Payment'!B57,'Farmer Payment Calc'!M:M) -> 0 | T57: 0 | U57: 0 | V57: =IF(E57="direct",SUMIFS(Table2[Net Amount],Table2[Code],'MPG Payment'!$B57,Table2[Account Details],"Available"),0) -> 0 | W57: =IF(E57="direct",SUMIFS(Table2[Net Amount],Table2[Code],'MPG Payment'!$B57,Table2[Account Details],"Not Available"),0) -> 0 | X57: =IF(Z57="Yes",0,IF(E57="indirect",(G57-O57-P57-R57-T57-U57-S57),0)) -> 8054.15 | Y57: =IF(E57="direct",(G57-O57-P57-V57-X57-R57-S57-T57-U57),0)-W57 -> 0 | Z57: 0 | AA57: =ROUND(+N57-O57-P57-R57-T57-V57-W57-X57-S57,0)-U57 -> 0 | AB57: =(M57-G57)/G57 -> -1 | AC57: =COUNTIF(Table2[Code],'MPG Payment'!B57) -> 0 | AD57: {=SUBSTITUTE(SUBSTITUTE(MID(CELL("filename"),FIND("[",CELL("filename"))+1,FIND("]",CELL("filename"))-FIND("[",CELL("filename"))-1),"JH Farmer Payment-",""),".xlsx","")} -> Indent | AF57: 0 | AG57: 0 | AH57: =AF57-AG57 -> 0 | AI57: 0
A58: BMC Code :2003 | B58: 20030009 | C58: SURID | D58: MPG | E58: =IFERROR(VLOOKUP(B58,Table2[[Code]:[Category]],13,0),"Indirect") -> Direct | F58: 689.72 | G58: 30875.93 | H58: =SUMIFS(Table2[Vol_L],Table2[Code],'MPG Payment'!$B58,Table2[Account Details],"Available") -> 696.79 | I58: =SUMIFS(Table2[Amount],Table2[Code],'MPG Payment'!$B58,Table2[Account Details],"Available") -> 31031.447 | J58: =IF(E58="direct",SUMIFS(Table2[Vol_L],Table2[Code],'MPG Payment'!$B58,Table2[Account Details],"Not Available"),0) -> 0 | K58: =IF(E58="direct",SUMIFS(Table2[Amount],Table2[Code],'MPG Payment'!$B58,Table2[Account Details],"Not Available"),0) -> 0 | L58: =H58+J58 -> 696.79 | M58: =I58+K58 -> 31031.447 | N58: =IF(E58="indirect",G58,MIN(G58,M58)) -> 30875.93 | O58: =SUMIFS(Table2[TS Loss],Table2[Code],'MPG Payment'!$B58) -> 0 | P58: =SUMIFS(Table2[Deduction for excess payment],Table2[Code],'MPG Payment'!$B58) -> 0 | Q58: =IF(M58>G58,(M58-G58),0) -> 155.5166 | R58: =SUMIF(Table2[Code],'MPG Payment'!$B58,Table2[CF Deduction]) -> 0 | S58: =SUMIF('Farmer Payment Calc'!D:D,'MPG Payment'!B58,'Farmer Payment Calc'!M:M) -> 0 | T58: 0 | U58: 0 | V58: =IF(E58="direct",SUMIFS(Table2[Net Amount],Table2[Code],'MPG Payment'!$B58,Table2[Account Details],"Available"),0) -> 30876 | W58: =IF(E58="direct",SUMIFS(Table2[Net Amount],Table2[Code],'MPG Payment'!$B58,Table2[Account Details],"Not Available"),0) -> 0 | X58: =IF(Z58="Yes",0,IF(E58="indirect",(G58-O58-P58-R58-T58-U58-S58),0)) -> 0 | Y58: =IF(E58="direct",(G58-O58-P58-V58-X58-R58-S58-T58-U58),0)-W58 -> -0.07 | Z58: 0 | AA58: =ROUND(+N58-O58-P58-R58-T58-V58-W58-X58-S58,0)-U58 -> 0 | AB58: =(M58-G58)/G58 -> 0.0050368232 | AC58: =COUNTIF(Table2[Code],'MPG Payment'!B58) -> 29 | AD58: {=SUBSTITUTE(SUBSTITUTE(MID(CELL("filename"),FIND("[",CELL("filename"))+1,FIND("]",CELL("filename"))-FIND("[",CELL("filename"))-1),"JH Farmer Payment-",""),".xlsx","")} -> Indent | AF58: 0 | AG58: 0 | AH58: =AF58-AG58 -> 0 | AI58: 0
A59: BMC Code :2003 | B59: 20030012 | C59: URUGUTU | D59: VLC | E59: =IFERROR(VLOOKUP(B59,Table2[[Code]:[Category]],13,0),"Indirect") -> Indirect | F59: 509.36 | G59: 21256.73 | H59: =SUMIFS(Table2[Vol_L],Table2[Code],'MPG Payment'!$B59,Table2[Account Details],"Available") -> 0 | I59: =SUMIFS(Table2[Amount],Table2[Code],'MPG Payment'!$B59,Table2[Account Details],"Available") -> 0 | J59: =IF(E59="direct",SUMIFS(Table2[Vol_L],Table2[Code],'MPG Payment'!$B59,Table2[Account Details],"Not Available"),0) -> 0 | K59: =IF(E59="direct",SUMIFS(Table2[Amount],Table2[Code],'MPG Payment'!$B59,Table2[Account Details],"Not Available"),0) -> 0 | L59: =H59+J59 -> 0 | M59: =I59+K59 -> 0 | N59: =IF(E59="indirect",G59,MIN(G59,M59)) -> 21256.73 | O59: =SUMIFS(Table2[TS Loss],Table2[Code],'MPG Payment'!$B59) -> 0 | P59: =SUMIFS(Table2[Deduction for excess payment],Table2[Code],'MPG Payment'!$B59) -> 0 | Q59: =IF(M59>G59,(M59-G59),0) -> 0 | R59: =SUMIF(Table2[Code],'MPG Payment'!$B59,Table2[CF Deduction]) -> 0 | S59: =SUMIF('Farmer Payment Calc'!D:D,'MPG Payment'!B59,'Farmer Payment Calc'!M:M) -> 0 | T59: 0 | U59: 0 | V59: =IF(E59="direct",SUMIFS(Table2[Net Amount],Table2[Code],'MPG Payment'!$B59,Table2[Account Details],"Available"),0) -> 0 | W59: =IF(E59="direct",SUMIFS(Table2[Net Amount],Table2[Code],'MPG Payment'!$B59,Table2[Account Details],"Not Available"),0) -> 0 | X59: =IF(Z59="Yes",0,IF(E59="indirect",(G59-O59-P59-R59-T59-U59-S59),0)) -> 21256.73 | Y59: =IF(E59="direct",(G59-O59-P59-V59-X59-R59-S59-T59-U59),0)-W59 -> 0 | Z59: 0 | AA59: =ROUND(+N59-O59-P59-R59-T59-V59-W59-X59-S59,0)-U59 -> 0 | AB59: =(M59-G59)/G59 -> -1 | AC59: =COUNTIF(Table2[Code],'MPG Payment'!B59) -> 0 | AD59: {=SUBSTITUTE(SUBSTITUTE(MID(CELL("filename"),FIND("[",CELL("filename"))+1,FIND("]",CELL("filename"))-FIND("[",CELL("filename"))-1),"JH Farmer Payment-",""),".xlsx","")} -> Indent | AF59: 0 | AG59: 0 | AH59: =AF59-AG59 -> 0 | AI59: 0
A60: BMC Code :2004 | B60: 20040001 | C60: CHOREYA | D60: RMC | E60: =IFERROR(VLOOKUP(B60,Table2[[Code]:[Category]],13,0),"Indirect") -> Direct | F60: 2627.79 | G60: 95965.61 | H60: =SUMIFS(Table2[Vol_L],Table2[Code],'MPG Payment'!$B60,Table2[Account Details],"Available") -> 2627.79 | I60: =SUMIFS(Table2[Amount],Table2[Code],'MPG Payment'!$B60,Table2[Account Details],"Available") -> 95965.511 | J60: =IF(E60="direct",SUMIFS(Table2[Vol_L],Table2[Code],'MPG Payment'!$B60,Table2[Account Details],"Not Available"),0) -> 0 | K60: =IF(E60="direct",SUMIFS(Table2[Amount],Table2[Code],'MPG Payment'!$B60,Table2[Account Details],"Not Available"),0) -> 0 | L60: =H60+J60 -> 2627.79 | M60: =I60+K60 -> 95965.511 | N60: =IF(E60="indirect",G60,MIN(G60,M60)) -> 95965.511 | O60: =SUMIFS(Table2[TS Loss],Table2[Code],'MPG Payment'!$B60) -> 11789 | P60: =SUMIFS(Table2[Deduction for excess payment],Table2[Code],'MPG Payment'!$B60) -> 0 | Q60: =IF(M60>G60,(M60-G60),0) -> 0 | R60: =SUMIF(Table2[Code],'MPG Payment'!$B60,Table2[CF Deduction]) -> 3260 | S60: =SUMIF('Farmer Payment Calc'!D:D,'MPG Payment'!B60,'Farmer Payment Calc'!M:M) -> 0 | T60: 0 | U60: 0 | V60: =IF(E60="direct",SUMIFS(Table2[Net Amount],Table2[Code],'MPG Payment'!$B60,Table2[Account Details],"Available"),0) -> 80917 | W60: =IF(E60="direct",SUMIFS(Table2[Net Amount],Table2[Code],'MPG Payment'!$B60,Table2[Account Details],"Not Available"),0) -> 0 | X60: =IF(Z60="Yes",0,IF(E60="indirect",(G60-O60-P60-R60-T60-U60-S60),0)) -> 0 | Y60: =IF(E60="direct",(G60-O60-P60-V60-X60-R60-S60-T60-U60),0)-W60 -> -0.39 | Z60: Release1 | AA60: =ROUND(+N60-O60-P60-R60-T60-V60-W60-X60-S60,0)-U60 -> 0 | AB60: =(M60-G60)/G60 -> -1.0284934e-06 | AC60: =COUNTIF(Table2[Code],'MPG Payment'!B60) -> 26 | AD60: {=SUBSTITUTE(SUBSTITUTE(MID(CELL("filename"),FIND("[",CELL("filename"))+1,FIND("]",CELL("filename"))-FIND("[",CELL("filename"))-1),"JH Farmer Payment-",""),".xlsx","")} -> Indent | AE60: TS Loss | AF60: 0 | AG60: 0 | AH60: =AF60-AG60 -> 0 | AI60: 0
A61: BMC Code :2004 | B61: 20040006 | C61: KADAM TOLI | D61: MPG | E61: =IFERROR(VLOOKUP(B61,Table2[[Code]:[Category]],13,0),"Indirect") -> Direct | F61: 610.2 | G61: 24263.6 | H61: =SUMIFS(Table2[Vol_L],Table2[Code],'MPG Payment'!$B61,Table2[Account Details],"Available") -> 566.82 | I61: =SUMIFS(Table2[Amount],Table2[Code],'MPG Payment'!$B61,Table2[Account Details],"Available") -> 24137.807 | J61: =IF(E61="direct",SUMIFS(Table2[Vol_L],Table2[Code],'MPG Payment'!$B61,Table2[Account Details],"Not Available"),0) -> 0 | K61: =IF(E61="direct",SUMIFS(Table2[Amount],Table2[Code],'MPG Payment'!$B61,Table2[Account Details],"Not Available"),0) -> 0 | L61: =H61+J61 -> 566.82 | M61: =I61+K61 -> 24137.807 | N61: =IF(E61="indirect",G61,MIN(G61,M61)) -> 24137.807 | O61: =SUMIFS(Table2[TS Loss],Table2[Code],'MPG Payment'!$B61) -> 0 | P61: =SUMIFS(Table2[Deduction for excess payment],Table2[Code],'MPG Payment'!$B61) -> 0 | Q61: =IF(M61>G61,(M61-G61),0) -> 0 | R61: =SUMIF(Table2[Code],'MPG Payment'!$B61,Table2[CF Deduction]) -> 3166 | S61: =SUMIF('Farmer Payment Calc'!D:D,'MPG Payment'!B61,'Farmer Payment Calc'!M:M) -> 0 | T61: 0 | U61: 0 | V61: =IF(E61="direct",SUMIFS(Table2[Net Amount],Table2[Code],'MPG Payment'!$B61,Table2[Account Details],"Available"),0) -> 20972 | W61: =IF(E61="direct",SUMIFS(Table2[Net Amount],Table2[Code],'MPG Payment'!$B61,Table2[Account Details],"Not Available"),0) -> 0 | X61: =IF(Z61="Yes",0,IF(E61="indirect",(G61-O61-P61-R61-T61-U61-S61),0)) -> 0 | Y61: =IF(E61="direct",(G61-O61-P61-V61-X61-R61-S61-T61-U61),0)-W61 -> 125.6 | Z61: 0 | AA61: =ROUND(+N61-O61-P61-R61-T61-V61-W61-X61-S61,0)-U61 -> 0 | AB61: =(M61-G61)/G61 -> -0.0051844409 | AC61: =COUNTIF(Table2[Code],'MPG Payment'!B61) -> 17 | AD61: {=SUBSTITUTE(SUBSTITUTE(MID(CELL("filename"),FIND("[",CELL("filename"))+1,FIND("]",CELL("filename"))-FIND("[",CELL("filename"))-1),"JH Farmer Payment-",""),".xlsx","")} -> Indent | AF61: 0 | AG61: 0 | AH61: =AF61-AG61 -> 0 | AI61: 0
A62: BMC Code :2004 | B62: 20040007 | C62: MADHUKAM | D62: MPG | E62: =IFERROR(VLOOKUP(B62,Table2[[Code]:[Category]],13,0),"Indirect") -> Direct | F62: 819.12 | G62: 33770.29 | H62: =SUMIFS(Table2[Vol_L],Table2[Code],'MPG Payment'!$B62,Table2[Account Details],"Available") -> 787.12 | I62: =SUMIFS(Table2[Amount],Table2[Code],'MPG Payment'!$B62,Table2[Account Details],"Available") -> 33579.958 | J62: =IF(E62="direct",SUMIFS(Table2[Vol_L],Table2[Code],'MPG Payment'!$B62,Table2[Account Details],"Not Available"),0) -> 0 | K62: =IF(E62="direct",SUMIFS(Table2[Amount],Table2[Code],'MPG Payment'!$B62,Table2[Account Details],"Not Available"),0) -> 0 | L62: =H62+J62 -> 787.12 | M62: =I62+K62 -> 33579.958 | N62: =IF(E62="indirect",G62,MIN(G62,M62)) -> 33579.958 | O62: =SUMIFS(Table2[TS Loss],Table2[Code],'MPG Payment'!$B62) -> 0 | P62: =SUMIFS(Table2[Deduction for excess payment],Table2[Code],'MPG Payment'!$B62) -> 0 | Q62: =IF(M62>G62,(M62-G62),0) -> 0 | R62: =SUMIF(Table2[Code],'MPG Payment'!$B62,Table2[CF Deduction]) -> 0 | S62: =SUMIF('Farmer Payment Calc'!D:D,'MPG Payment'!B62,'Farmer Payment Calc'!M:M) -> 0 | T62: 0 | U62: 0 | V62: =IF(E62="direct",SUMIFS(Table2[Net Amount],Table2[Code],'MPG Payment'!$B62,Table2[Account Details],"Available"),0) -> 33581 | W62: =IF(E62="direct",SUMIFS(Table2[Net Amount],Table2[Code],'MPG Payment'!$B62,Table2[Account Details],"Not Available"),0) -> 0 | X62: =IF(Z62="Yes",0,IF(E62="indirect",(G62-O62-P62-R62-T62-U62-S62),0)) -> 0 | Y62: =IF(E62="direct",(G62-O62-P62-V62-X62-R62-S62-T62-U62),0)-W62 -> 189.29 | Z62: 0 | AA62: =ROUND(+N62-O62-P62-R62-T62-V62-W62-X62-S62,0)-U62 -> -1 | AB62: =(M62-G62)/G62 -> -0.0056360754 | AC62: =COUNTIF(Table2[Code],'MPG Payment'!B62) -> 19 | AD62: {=SUBSTITUTE(SUBSTITUTE(MID(CELL("filename"),FIND("[",CELL("filename"))+1,FIND("]",CELL("filename"))-FIND("[",CELL("filename"))-1),"JH Farmer Payment-",""),".xlsx","")} -> Indent | AF62: 0 | AG62: 0 | AH62: =AF62-AG62 -> 0 | AI62: 0
A63: BMC Code :2002 | B63: 20050001 | C63: Baski 2 | D63: RMC | E63: =IFERROR(VLOOKUP(B63,Table2[[Code]:[Category]],13,0),"Indirect") -> Direct | F63: 946.6 | G63: 38688.22 | H63: =SUMIFS(Table2[Vol_L],Table2[Code],'MPG Payment'!$B63,Table2[Account Details],"Available") -> 943.01 | I63: =SUMIFS(Table2[Amount],Table2[Code],'MPG Payment'!$B63,Table2[Account Details],"Available") -> 38626.398 | J63: =IF(E63="direct",SUMIFS(Table2[Vol_L],Table2[Code],'MPG Payment'!$B63,Table2[Account Details],"Not Available"),0) -> 0 | K63: =IF(E63="direct",SUMIFS(Table2[Amount],Table2[Code],'MPG Payment'!$B63,Table2[Account Details],"Not Available"),0) -> 0 | L63: =H63+J63 -> 943.01 | M63: =I63+K63 -> 38626.398 | N63: =IF(E63="indirect",G63,MIN(G63,M63)) -> 38626.398 | O63: =SUMIFS(Table2[TS Loss],Table2[Code],'MPG Payment'!$B63) -> 0 | P63: =SUMIFS(Table2[Deduction for excess payment],Table2[Code],'MPG Payment'!$B63) -> 0 | Q63: =IF(M63>G63,(M63-G63),0) -> 0 | R63: =SUMIF(Table2[Code],'MPG Payment'!$B63,Table2[CF Deduction]) -> 1092 | S63: =SUMIF('Farmer Payment Calc'!D:D,'MPG Payment'!B63,'Farmer Payment Calc'!M:M) -> 0 | T63: 0 | U63: 0 | V63: =IF(E63="direct",SUMIFS(Table2[Net Amount],Table2[Code],'MPG Payment'!$B63,Table2[Account Details],"Available"),0) -> 37535 | W63: =IF(E63="direct",SUMIFS(Table2[Net Amount],Table2[Code],'MPG Payment'!$B63,Table2[Account Details],"Not Available"),0) -> 0 | X63: =IF(Z63="Yes",0,IF(E63="indirect",(G63-O63-P63-R63-T63-U63-S63),0)) -> 0 | Y63: =IF(E63="direct",(G63-O63-P63-V63-X63-R63-S63-T63-U63),0)-W63 -> 61.22 | Z63: Release1 | AA63: =ROUND(+N63-O63-P63-R63-T63-V63-W63-X63-S63,0)-U63 -> -1 | AB63: =(M63-G63)/G63 -> -0.0015979593 | AC63: =COUNTIF(Table2[Code],'MPG Payment'!B63) -> 30 | AD63: {=SUBSTITUTE(SUBSTITUTE(MID(CELL("filename"),FIND("[",CELL("filename"))+1,FIND("]",CELL("filename"))-FIND("[",CELL("filename"))-1),"JH Farmer Payment-",""),".xlsx","")} -> Indent | AE63: CF OS> 15 Day's | AF63: 1092.06 | AG63: 1092 | AH63: =AF63-AG63 -> 0.06 | AI63: 0
A64: BMC Code :2002 | B64: 20050003 | C64: UCHARI | D64: MPG | E64: =IFERROR(VLOOKUP(B64,Table2[[Code]:[Category]],13,0),"Indirect") -> Direct | F64: 1835.1 | G64: 74032.52 | H64: =SUMIFS(Table2[Vol_L],Table2[Code],'MPG Payment'!$B64,Table2[Account Details],"Available") -> 1832.4 | I64: =SUMIFS(Table2[Amount],Table2[Code],'MPG Payment'!$B64,Table2[Account Details],"Available") -> 73958.713 | J64: =IF(E64="direct",SUMIFS(Table2[Vol_L],Table2[Code],'MPG Payment'!$B64,Table2[Account Details],"Not Available"),0) -> 0 | K64: =IF(E64="direct",SUMIFS(Table2[Amount],Table2[Code],'MPG Payment'!$B64,Table2[Account Details],"Not Available"),0) -> 0 | L64: =H64+J64 -> 1832.4 | M64: =I64+K64 -> 73958.713 | N64: =IF(E64="indirect",G64,MIN(G64,M64)) -> 73958.713 | O64: =SUMIFS(Table2[TS Loss],Table2[Code],'MPG Payment'!$B64) -> 0 | P64: =SUMIFS(Table2[Deduction for excess payment],Table2[Code],'MPG Payment'!$B64) -> 0 | Q64: =IF(M64>G64,(M64-G64),0) -> 0 | R64: =SUMIF(Table2[Code],'MPG Payment'!$B64,Table2[CF Deduction]) -> 0 | S64: =SUMIF('Farmer Payment Calc'!D:D,'MPG Payment'!B64,'Farmer Payment Calc'!M:M) -> 0 | T64: 0 | U64: 0 | V64: =IF(E64="direct",SUMIFS(Table2[Net Amount],Table2[Code],'MPG Payment'!$B64,Table2[Account Details],"Available"),0) -> 73958 | W64: =IF(E64="direct",SUMIFS(Table2[Net Amount],Table2[Code],'MPG Payment'!$B64,Table2[Account Details],"Not Available"),0) -> 0 | X64: =IF(Z64="Yes",0,IF(E64="indirect",(G64-O64-P64-R64-T64-U64-S64),0)) -> 0 | Y64: =IF(E64="direct",(G64-O64-P64-V64-X64-R64-S64-T64-U64),0)-W64 -> 74.52 | Z64: 0 | AA64: =ROUND(+N64-O64-P64-R64-T64-V64-W64-X64-S64,0)-U64 -> 1 | AB64: =(M64-G64)/G64 -> -0.00099695377 | AC64: =COUNTIF(Table2[Code],'MPG Payment'!B64) -> 37 | AD64: {=SUBSTITUTE(SUBSTITUTE(MID(CELL("filename"),FIND("[",CELL("filename"))+1,FIND("]",CELL("filename"))-FIND("[",CELL("filename"))-1),"JH Farmer Payment-",""),".xlsx","")} -> Indent | AF64: 0 | AG64: 0 | AH64: =AF64-AG64 -> 0 | AI64: 0
A65: BMC Code :2006 | B65: 20060001 | C65: ORMANJHI | D65: RMC | E65: =IFERROR(VLOOKUP(B65,Table2[[Code]:[Category]],13,0),"Indirect") -> Direct | F65: 1529.69 | G65: 61598.57 | H65: =SUMIFS(Table2[Vol_L],Table2[Code],'MPG Payment'!$B65,Table2[Account Details],"Available") -> 1529.7 | I65: =SUMIFS(Table2[Amount],Table2[Code],'MPG Payment'!$B65,Table2[Account Details],"Available") -> 61707.881 | J65: =IF(E65="direct",SUMIFS(Table2[Vol_L],Table2[Code],'MPG Payment'!$B65,Table2[Account Details],"Not Available"),0) -> 0 | K65: =IF(E65="direct",SUMIFS(Table2[Amount],Table2[Code],'MPG Payment'!$B65,Table2[Account Details],"Not Available"),0) -> 0 | L65: =H65+J65 -> 1529.7 | M65: =I65+K65 -> 61707.881 | N65: =IF(E65="indirect",G65,MIN(G65,M65)) -> 61598.57 | O65: =SUMIFS(Table2[TS Loss],Table2[Code],'MPG Payment'!$B65) -> 0 | P65: =SUMIFS(Table2[Deduction for excess payment],Table2[Code],'MPG Payment'!$B65) -> 0 | Q65: =IF(M65>G65,(M65-G65),0) -> 109.311 | R65: =SUMIF(Table2[Code],'MPG Payment'!$B65,Table2[CF Deduction]) -> 0 | S65: =SUMIF('Farmer Payment Calc'!D:D,'MPG Payment'!B65,'Farmer Payment Calc'!M:M) -> 0 | T65: 0 | U65: 0 | V65: =IF(E65="direct",SUMIFS(Table2[Net Amount],Table2[Code],'MPG Payment'!$B65,Table2[Account Details],"Available"),0) -> 61599 | W65: =IF(E65="direct",SUMIFS(Table2[Net Amount],Table2[Code],'MPG Payment'!$B65,Table2[Account Details],"Not Available"),0) -> 0 | X65: =IF(Z65="Yes",0,IF(E65="indirect",(G65-O65-P65-R65-T65-U65-S65),0)) -> 0 | Y65: =IF(E65="direct",(G65-O65-P65-V65-X65-R65-S65-T65-U65),0)-W65 -> -0.43 | Z65: 0 | AA65: =ROUND(+N65-O65-P65-R65-T65-V65-W65-X65-S65,0)-U65 -> 0 | AB65: =(M65-G65)/G65 -> 0.0017745704 | AC65: =COUNTIF(Table2[Code],'MPG Payment'!B65) -> 10 | AD65: {=SUBSTITUTE(SUBSTITUTE(MID(CELL("filename"),FIND("[",CELL("filename"))+1,FIND("]",CELL("filename"))-FIND("[",CELL("filename"))-1),"JH Farmer Payment-",""),".xlsx","")} -> Indent | AF65: 0 | AG65: 0 | AH65: =AF65-AG65 -> 0 | AI65: 0
A66: BMC Code :2006 | B66: 20060002 | C66: MANDRO | D66: MPG | E66: =IFERROR(VLOOKUP(B66,Table2[[Code]:[Category]],13,0),"Indirect") -> Direct | F66: 336.1 | G66: 14741.57 | H66: =SUMIFS(Table2[Vol_L],Table2[Code],'MPG Payment'!$B66,Table2[Account Details],"Available") -> 337.82 | I66: =SUMIFS(Table2[Amount],Table2[Code],'MPG Payment'!$B66,Table2[Account Details],"Available") -> 14723.378 | J66: =IF(E66="direct",SUMIFS(Table2[Vol_L],Table2[Code],'MPG Payment'!$B66,Table2[Account Details],"Not Available"),0) -> 0 | K66: =IF(E66="direct",SUMIFS(Table2[Amount],Table2[Code],'MPG Payment'!$B66,Table2[Account Details],"Not Available"),0) -> 0 | L66: =H66+J66 -> 337.82 | M66: =I66+K66 -> 14723.378 | N66: =IF(E66="indirect",G66,MIN(G66,M66)) -> 14723.378 | O66: =SUMIFS(Table2[TS Loss],Table2[Code],'MPG Payment'!$B66) -> 0 | P66: =SUMIFS(Table2[Deduction for excess payment],Table2[Code],'MPG Payment'!$B66) -> 0 | Q66: =IF(M66>G66,(M66-G66),0) -> 0 | R66: =SUMIF(Table2[Code],'MPG Payment'!$B66,Table2[CF Deduction]) -> 0 | S66: =SUMIF('Farmer Payment Calc'!D:D,'MPG Payment'!B66,'Farmer Payment Calc'!M:M) -> 0 | T66: 0 | U66: 0 | V66: =IF(E66="direct",SUMIFS(Table2[Net Amount],Table2[Code],'MPG Payment'!$B66,Table2[Account Details],"Available"),0) -> 14724 | W66: =IF(E66="direct",SUMIFS(Table2[Net Amount],Table2[Code],'MPG Payment'!$B66,Table2[Account Details],"Not Available"),0) -> 0 | X66: =IF(Z66="Yes",0,IF(E66="indirect",(G66-O66-P66-R66-T66-U66-S66),0)) -> 0 | Y66: =IF(E66="direct",(G66-O66-P66-V66-X66-R66-S66-T66-U66),0)-W66 -> 17.57 | Z66: 0 | AA66: =ROUND(+N66-O66-P66-R66-T66-V66-W66-X66-S66,0)-U66 -> -1 | AB66: =(M66-G66)/G66 -> -0.0012340612 | AC66: =COUNTIF(Table2[Code],'MPG Payment'!B66) -> 10 | AD66: {=SUBSTITUTE(SUBSTITUTE(MID(CELL("filename"),FIND("[",CELL("filename"))+1,FIND("]",CELL("filename"))-FIND("[",CELL("filename"))-1),"JH Farmer Payment-",""),".xlsx","")} -> Indent | AF66: 0 | AG66: 0 | AH66: =AF66-AG66 -> 0 | AI66: 0
A67: BMC Code :2006 | B67: 20060003 | C67: DUMARDAGA | D67: MPG | E67: =IFERROR(VLOOKUP(B67,Table2[[Code]:[Category]],13,0),"Indirect") -> Direct | F67: 1532.1 | G67: 53604.81 | H67: =SUMIFS(Table2[Vol_L],Table2[Code],'MPG Payment'!$B67,Table2[Account Details],"Available") -> 1548.18 | I67: =SUMIFS(Table2[Amount],Table2[Code],'MPG Payment'!$B67,Table2[Account Details],"Available") -> 56015.187 | J67: =IF(E67="direct",SUMIFS(Table2[Vol_L],Table2[Code],'MPG Payment'!$B67,Table2[Account Details],"Not Available"),0) -> 0 | K67: =IF(E67="direct",SUMIFS(Table2[Amount],Table2[Code],'MPG Payment'!$B67,Table2[Account Details],"Not Available"),0) -> 0 | L67: =H67+J67 -> 1548.18 | M67: =I67+K67 -> 56015.187 | N67: =IF(E67="indirect",G67,MIN(G67,M67)) -> 53604.81 | O67: =SUMIFS(Table2[TS Loss],Table2[Code],'MPG Payment'!$B67) -> 0 | P67: =SUMIFS(Table2[Deduction for excess payment],Table2[Code],'MPG Payment'!$B67) -> 0 | Q67: =IF(M67>G67,(M67-G67),0) -> 2410.3765 | R67: =SUMIF(Table2[Code],'MPG Payment'!$B67,Table2[CF Deduction]) -> 25400 | S67: =SUMIF('Farmer Payment Calc'!D:D,'MPG Payment'!B67,'Farmer Payment Calc'!M:M) -> 0 | T67: 0 | U67: 0 | V67: =IF(E67="direct",SUMIFS(Table2[Net Amount],Table2[Code],'MPG Payment'!$B67,Table2[Account Details],"Available"),0) -> 28205 | W67: =IF(E67="direct",SUMIFS(Table2[Net Amount],Table2[Code],'MPG Payment'!$B67,Table2[Account Details],"Not Available"),0) -> 0 | X67: =IF(Z67="Yes",0,IF(E67="indirect",(G67-O67-P67-R67-T67-U67-S67),0)) -> 0 | Y67: =IF(E67="direct",(G67-O67-P67-V67-X67-R67-S67-T67-U67),0)-W67 -> -0.19 | Z67: Release1 | AA67: =ROUND(+N67-O67-P67-R67-T67-V67-W67-X67-S67,0)-U67 -> 0 | AB67: =(M67-G67)/G67 -> 0.044965676 | AC67: =COUNTIF(Table2[Code],'MPG Payment'!B67) -> 2 | AD67: {=SUBSTITUTE(SUBSTITUTE(MID(CELL("filename"),FIND("[",CELL("filename"))+1,FIND("]",CELL("filename"))-FIND("[",CELL("filename"))-1),"JH Farmer Payment-",""),".xlsx","")} -> Indent | AE67: CF OS> 15 Day's | AF67: 25400 | AG67: 25400 | AH67: =AF67-AG67 -> 0 | AI67: 0
A68: BMC Code :2006 | B68: 20060004 | C68: CHUTTU | D68: MPG | E68: =IFERROR(VLOOKUP(B68,Table2[[Code]:[Category]],13,0),"Indirect") -> Direct | F68: 1237.5 | G68: 52188.38 | H68: =SUMIFS(Table2[Vol_L],Table2[Code],'MPG Payment'!$B68,Table2[Account Details],"Available") -> 1250.3 | I68: =SUMIFS(Table2[Amount],Table2[Code],'MPG Payment'!$B68,Table2[Account Details],"Available") -> 52149.659 | J68: =IF(E68="direct",SUMIFS(Table2[Vol_L],Table2[Code],'MPG Payment'!$B68,Table2[Account Details],"Not Available"),0) -> 0 | K68: =IF(E68="direct",SUMIFS(Table2[Amount],Table2[Code],'MPG Payment'!$B68,Table2[Account Details],"Not Available"),0) -> 0 | L68: =H68+J68 -> 1250.3 | M68: =I68+K68 -> 52149.659 | N68: =IF(E68="indirect",G68,MIN(G68,M68)) -> 52149.659 | O68: =SUMIFS(Table2[TS Loss],Table2[Code],'MPG Payment'!$B68) -> 0 | P68: =SUMIFS(Table2[Deduction for excess payment],Table2[Code],'MPG Payment'!$B68) -> 0 | Q68: =IF(M68>G68,(M68-G68),0) -> 0 | R68: =SUMIF(Table2[Code],'MPG Payment'!$B68,Table2[CF Deduction]) -> 6350 | S68: =SUMIF('Farmer Payment Calc'!D:D,'MPG Payment'!B68,'Farmer Payment Calc'!M:M) -> 0 | T68: 0 | U68: 0 | V68: =IF(E68="direct",SUMIFS(Table2[Net Amount],Table2[Code],'MPG Payment'!$B68,Table2[Account Details],"Available"),0) -> 45802 | W68: =IF(E68="direct",SUMIFS(Table2[Net Amount],Table2[Code],'MPG Payment'!$B68,Table2[Account Details],"Not Available"),0) -> 0 | X68: =IF(Z68="Yes",0,IF(E68="indirect",(G68-O68-P68-R68-T68-U68-S68),0)) -> 0 | Y68: =IF(E68="direct",(G68-O68-P68-V68-X68-R68-S68-T68-U68),0)-W68 -> 36.38 | Z68: 0 | AA68: =ROUND(+N68-O68-P68-R68-T68-V68-W68-X68-S68,0)-U68 -> -2 | AB68: =(M68-G68)/G68 -> -0.00074194294 | AC68: =COUNTIF(Table2[Code],'MPG Payment'!B68) -> 29 | AD68: {=SUBSTITUTE(SUBSTITUTE(MID(CELL("filename"),FIND("[",CELL("filename"))+1,FIND("]",CELL("filename"))-FIND("[",CELL("filename"))-1),"JH Farmer Payment-",""),".xlsx","")} -> Indent | AF68: 0 | AG68: 0 | AH68: =AF68-AG68 -> 0 | AI68: 0
A69: BMC Code :2006 | B69: 20060005 | C69: JIRABAR | D69: MPG | E69: =IFERROR(VLOOKUP(B69,Table2[[Code]:[Category]],13,0),"Indirect") -> Direct | F69: 866.9 | G69: 40526.79 | H69: =SUMIFS(Table2[Vol_L],Table2[Code],'MPG Payment'!$B69,Table2[Account Details],"Available") -> 844.88 | I69: =SUMIFS(Table2[Amount],Table2[Code],'MPG Payment'!$B69,Table2[Account Details],"Available") -> 40505.831 | J69: =IF(E69="direct",SUMIFS(Table2[Vol_L],Table2[Code],'MPG Payment'!$B69,Table2[Account Details],"Not Available"),0) -> 0 | K69: =IF(E69="direct",SUMIFS(Table2[Amount],Table2[Code],'MPG Payment'!$B69,Table2[Account Details],"Not Available"),0) -> 0 | L69: =H69+J69 -> 844.88 | M69: =I69+K69 -> 40505.831 | N69: =IF(E69="indirect",G69,MIN(G69,M69)) -> 40505.831 | O69: =SUMIFS(Table2[TS Loss],Table2[Code],'MPG Payment'!$B69) -> 0 | P69: =SUMIFS(Table2[Deduction for excess payment],Table2[Code],'MPG Payment'!$B69) -> 0 | Q69: =IF(M69>G69,(M69-G69),0) -> 0 | R69: =SUMIF(Table2[Code],'MPG Payment'!$B69,Table2[CF Deduction]) -> 0 | S69: =SUMIF('Farmer Payment Calc'!D:D,'MPG Payment'!B69,'Farmer Payment Calc'!M:M) -> 0 | T69: 0 | U69: 0 | V69: =IF(E69="direct",SUMIFS(Table2[Net Amount],Table2[Code],'MPG Payment'!$B69,Table2[Account Details],"Available"),0) -> 40507 | W69: =IF(E69="direct",SUMIFS(Table2[Net Amount],Table2[Code],'MPG Payment'!$B69,Table2[Account Details],"Not Available"),0) -> 0 | X69: =IF(Z69="Yes",0,IF(E69="indirect",(G69-O69-P69-R69-T69-U69-S69),0)) -> 0 | Y69: =IF(E69="direct",(G69-O69-P69-V69-X69-R69-S69-T69-U69),0)-W69 -> 19.79 | Z69: 0 | AA69: =ROUND(+N69-O69-P69-R69-T69-V69-W69-X69-S69,0)-U69 -> -1 | AB69: =(M69-G69)/G69 -> -0.00051716901 | AC69: =COUNTIF(Table2[Code],'MPG Payment'!B69) -> 14 | AD69: {=SUBSTITUTE(SUBSTITUTE(MID(CELL("filename"),FIND("[",CELL("filename"))+1,FIND("]",CELL("filename"))-FIND("[",CELL("filename"))-1),"JH Farmer Payment-",""),".xlsx","")} -> Indent | AF69: 0 | AG69: 0 | AH69: =AF69-AG69 -> 0 | AI69: 0
A70: BMC Code :2006 | B70: 20060007 | C70: HOCHAR | D70: MPG | E70: =IFERROR(VLOOKUP(B70,Table2[[Code]:[Category]],13,0),"Indirect") -> Direct | F70: 688.2 | G70: 28601.91 | H70: =SUMIFS(Table2[Vol_L],Table2[Code],'MPG Payment'!$B70,Table2[Account Details],"Available") -> 684.29 | I70: =SUMIFS(Table2[Amount],Table2[Code],'MPG Payment'!$B70,Table2[Account Details],"Available") -> 28568.271 | J70: =IF(E70="direct",SUMIFS(Table2[Vol_L],Table2[Code],'MPG Payment'!$B70,Table2[Account Details],"Not Available"),0) -> 0 | K70: =IF(E70="direct",SUMIFS(Table2[Amount],Table2[Code],'MPG Payment'!$B70,Table2[Account Details],"Not Available"),0) -> 0 | L70: =H70+J70 -> 684.29 | M70: =I70+K70 -> 28568.271 | N70: =IF(E70="indirect",G70,MIN(G70,M70)) -> 28568.271 | O70: =SUMIFS(Table2[TS Loss],Table2[Code],'MPG Payment'!$B70) -> 0 | P70: =SUMIFS(Table2[Deduction for excess payment],Table2[Code],'MPG Payment'!$B70) -> 0 | Q70: =IF(M70>G70,(M70-G70),0) -> 0 | R70: =SUMIF(Table2[Code],'MPG Payment'!$B70,Table2[CF Deduction]) -> 0 | S70: =SUMIF('Farmer Payment Calc'!D:D,'MPG Payment'!B70,'Farmer Payment Calc'!M:M) -> 0 | T70: 0 | U70: 0 | V70: =IF(E70="direct",SUMIFS(Table2[Net Amount],Table2[Code],'MPG Payment'!$B70,Table2[Account Details],"Available"),0) -> 28568 | W70: =IF(E70="direct",SUMIFS(Table2[Net Amount],Table2[Code],'MPG Payment'!$B70,Table2[Account Details],"Not Available"),0) -> 0 | X70: =IF(Z70="Yes",0,IF(E70="indirect",(G70-O70-P70-R70-T70-U70-S70),0)) -> 0 | Y70: =IF(E70="direct",(G70-O70-P70-V70-X70-R70-S70-T70-U70),0)-W70 -> 33.91 | Z70: 0 | AA70: =ROUND(+N70-O70-P70-R70-T70-V70-W70-X70-S70,0)-U70 -> 0 | AB70: =(M70-G70)/G70 -> -0.0011760963 | AC70: =COUNTIF(Table2[Code],'MPG Payment'!B70) -> 6 | AD70: {=SUBSTITUTE(SUBSTITUTE(MID(CELL("filename"),FIND("[",CELL("filename"))+1,FIND("]",CELL("filename"))-FIND("[",CELL("filename"))-1),"JH Farmer Payment-",""),".xlsx","")} -> Indent | AF70: 0 | AG70: 0 | AH70: =AF70-AG70 -> 0 | AI70: 0
A71: BMC Code :2006 | B71: 20060008 | C71: ADELHATU | D71: MPG | E71: =IFERROR(VLOOKUP(B71,Table2[[Code]:[Category]],13,0),"Indirect") -> Direct | F71: 1139.4 | G71: 46369.7 | H71: =SUMIFS(Table2[Vol_L],Table2[Code],'MPG Payment'!$B71,Table2[Account Details],"Available") -> 1041.66 | I71: =SUMIFS(Table2[Amount],Table2[Code],'MPG Payment'!$B71,Table2[Account Details],"Available") -> 41790.618 | J71: =IF(E71="direct",SUMIFS(Table2[Vol_L],Table2[Code],'MPG Payment'!$B71,Table2[Account Details],"Not Available"),0) -> 0 | K71: =IF(E71="direct",SUMIFS(Table2[Amount],Table2[Code],'MPG Payment'!$B71,Table2[Account Details],"Not Available"),0) -> 0 | L71: =H71+J71 -> 1041.66 | M71: =I71+K71 -> 41790.618 | N71: =IF(E71="indirect",G71,MIN(G71,M71)) -> 41790.618 | O71: =SUMIFS(Table2[TS Loss],Table2[Code],'MPG Payment'!$B71) -> 0 | P71: =SUMIFS(Table2[Deduction for excess payment],Table2[Code],'MPG Payment'!$B71) -> 0 | Q71: =IF(M71>G71,(M71-G71),0) -> 0 | R71: =SUMIF(Table2[Code],'MPG Payment'!$B71,Table2[CF Deduction]) -> 0 | S71: =SUMIF('Farmer Payment Calc'!D:D,'MPG Payment'!B71,'Farmer Payment Calc'!M:M) -> 0 | T71: 0 | U71: 0 | V71: =IF(E71="direct",SUMIFS(Table2[Net Amount],Table2[Code],'MPG Payment'!$B71,Table2[Account Details],"Available"),0) -> 41791 | W71: =IF(E71="direct",SUMIFS(Table2[Net Amount],Table2[Code],'MPG Payment'!$B71,Table2[Account Details],"Not Available"),0) -> 0 | X71: =IF(Z71="Yes",0,IF(E71="indirect",(G71-O71-P71-R71-T71-U71-S71),0)) -> 0 | Y71: =IF(E71="direct",(G71-O71-P71-V71-X71-R71-S71-T71-U71),0)-W71 -> 4578.7 | Z71: 0 | AA71: =ROUND(+N71-O71-P71-R71-T71-V71-W71-X71-S71,0)-U71 -> 0 | AB71: =(M71-G71)/G71 -> -0.098751605 | AC71: =COUNTIF(Table2[Code],'MPG Payment'!B71) -> 1 | AD71: {=SUBSTITUTE(SUBSTITUTE(MID(CELL("filename"),FIND("[",CELL("filename"))+1,FIND("]",CELL("filename"))-FIND("[",CELL("filename"))-1),"JH Farmer Payment-",""),".xlsx","")} -> Indent | AF71: 0 | AG71: 0 | AH71: =AF71-AG71 -> 0 | AI71: 0
A72: BMC Code :2006 | B72: 20060009 | C72: KUCHU | D72: MPG | E72: =IFERROR(VLOOKUP(B72,Table2[[Code]:[Category]],13,0),"Indirect") -> Direct | F72: 524 | G72: 20951.74 | H72: =SUMIFS(Table2[Vol_L],Table2[Code],'MPG Payment'!$B72,Table2[Account Details],"Available") -> 511.66 | I72: =SUMIFS(Table2[Amount],Table2[Code],'MPG Payment'!$B72,Table2[Account Details],"Available") -> 20412.671 | J72: =IF(E72="direct",SUMIFS(Table2[Vol_L],Table2[Code],'MPG Payment'!$B72,Table2[Account Details],"Not Available"),0) -> 12.82 | K72: =IF(E72="direct",SUMIFS(Table2[Amount],Table2[Code],'MPG Payment'!$B72,Table2[Account Details],"Not Available"),0) -> 529.5792 | L72: =H72+J72 -> 524.48 | M72: =I72+K72 -> 20942.25 | N72: =IF(E72="indirect",G72,MIN(G72,M72)) -> 20942.25 | O72: =SUMIFS(Table2[TS Loss],Table2[Code],'MPG Payment'!$B72) -> 0 | P72: =SUMIFS(Table2[Deduction for excess payment],Table2[Code],'MPG Payment'!$B72) -> 0 | Q72: =IF(M72>G72,(M72-G72),0) -> 0 | R72: =SUMIF(Table2[Code],'MPG Payment'!$B72,Table2[CF Deduction]) -> 0 | S72: =SUMIF('Farmer Payment Calc'!D:D,'MPG Payment'!B72,'Farmer Payment Calc'!M:M) -> 0 | T72: 0 | U72: 0 | V72: =IF(E72="direct",SUMIFS(Table2[Net Amount],Table2[Code],'MPG Payment'!$B72,Table2[Account Details],"Available"),0) -> 20413 | W72: =IF(E72="direct",SUMIFS(Table2[Net Amount],Table2[Code],'MPG Payment'!$B72,Table2[Account Details],"Not Available"),0) -> 530 | X72: =IF(Z72="Yes",0,IF(E72="indirect",(G72-O72-P72-R72-T72-U72-S72),0)) -> 0 | Y72: =IF(E72="direct",(G72-O72-P72-V72-X72-R72-S72-T72-U72),0)-W72 -> 8.74 | Z72: 0 | AA72: =ROUND(+N72-O72-P72-R72-T72-V72-W72-X72-S72,0)-U72 -> -1 | AB72: =(M72-G72)/G72 -> -0.00045294567 | AC72: =COUNTIF(Table2[Code],'MPG Payment'!B72) -> 18 | AD72: {=SUBSTITUTE(SUBSTITUTE(MID(CELL("filename"),FIND("[",CELL("filename"))+1,FIND("]",CELL("filename"))-FIND("[",CELL("filename"))-1),"JH Farmer Payment-",""),".xlsx","")} -> Indent | AF72: 0 | AG72: 0 | AH72: =AF72-AG72 -> 0 | AI72: 0
A73: BMC Code :2006 | B73: 20060013 | C73: CHATAKPUR | D73: VLC | E73: =IFERROR(VLOOKUP(B73,Table2[[Code]:[Category]],13,0),"Indirect") -> Indirect | F73: 414.5 | G73: 16110.23 | H73: =SUMIFS(Table2[Vol_L],Table2[Code],'MPG Payment'!$B73,Table2[Account Details],"Available") -> 0 | I73: =SUMIFS(Table2[Amount],Table2[Code],'MPG Payment'!$B73,Table2[Account Details],"Available") -> 0 | J73: =IF(E73="direct",SUMIFS(Table2[Vol_L],Table2[Code],'MPG Payment'!$B73,Table2[Account Details],"Not Available"),0) -> 0 | K73: =IF(E73="direct",SUMIFS(Table2[Amount],Table2[Code],'MPG Payment'!$B73,Table2[Account Details],"Not Available"),0) -> 0 | L73: =H73+J73 -> 0 | M73: =I73+K73 -> 0 | N73: =IF(E73="indirect",G73,MIN(G73,M73)) -> 16110.23 | O73: =SUMIFS(Table2[TS Loss],Table2[Code],'MPG Payment'!$B73) -> 0 | P73: =SUMIFS(Table2[Deduction for excess payment],Table2[Code],'MPG Payment'!$B73) -> 0 | Q73: =IF(M73>G73,(M73-G73),0) -> 0 | R73: =SUMIF(Table2[Code],'MPG Payment'!$B73,Table2[CF Deduction]) -> 0 | S73: =SUMIF('Farmer Payment Calc'!D:D,'MPG Payment'!B73,'Farmer Payment Calc'!M:M) -> 0 | T73: 0 | U73: 0 | V73: =IF(E73="direct",SUMIFS(Table2[Net Amount],Table2[Code],'MPG Payment'!$B73,Table2[Account Details],"Available"),0) -> 0 | W73: =IF(E73="direct",SUMIFS(Table2[Net Amount],Table2[Code],'MPG Payment'!$B73,Table2[Account Details],"Not Available"),0) -> 0 | X73: =IF(Z73="Yes",0,IF(E73="indirect",(G73-O73-P73-R73-T73-U73-S73),0)) -> 16110.23 | Y73: =IF(E73="direct",(G73-O73-P73-V73-X73-R73-S73-T73-U73),0)-W73 -> 0 | Z73: 0 | AA73: =ROUND(+N73-O73-P73-R73-T73-V73-W73-X73-S73,0)-U73 -> 0 | AB73: =(M73-G73)/G73 -> -1 | AC73: =COUNTIF(Table2[Code],'MPG Payment'!B73) -> 0 | AD73: {=SUBSTITUTE(SUBSTITUTE(MID(CELL("filename"),FIND("[",CELL("filename"))+1,FIND("]",CELL("filename"))-FIND("[",CELL("filename"))-1),"JH Farmer Payment-",""),".xlsx","")} -> Indent | AF73: 0 | AG73: 0 | AH73: =AF73-AG73 -> 0 | AI73: 0
