Workbook

Sheet PDF
A1: MCC | B1: Mahua BMC | C1: Sahayak Comission Month Of May'26
C3: Values
A4: Code | B4: MPG NAME | C4: BMC Volume | D4: BMC Amount | E4: Sahayak Comission @ 0.75/- | F4: Std gain @ 0.95/- | G4: Farmer Sample Milk | H4: AMC from MPG @ 0.10/- | I4: Actual Volume Penalty | J4: Net Sahayak Income | K4: New Assets EMI | L4: Can Deduction | M4: PCB Ded | N4: Other | O4: Consumables | P4: Payble to Sahyak | Q4: Hold | R4: Net Payble
A5: 10130101 | B5: Gomukh Karhatiya Bujurg | C5: 340.4 | D5: 13995.795 | E5: 255.3 | F5: 323.38 | G5: 0 | H5: 34.04 | I5: 544.60774 | J5: 0 | K5: 0 | L5: 0 | M5: 0 | N5: 0 | O5: 0 | P5: 0 | Q5: 0 | R5: 0
A6: 10130101 Total | C6: 340.4 | D6: 13995.795 | E6: 255.3 | F6: 323.38 | G6: 0 | H6: 34.04 | I6: 544.60774 | J6: 0 | K6: 0 | L6: 0 | M6: 0 | N6: 0 | O6: 0 | P6: 0 | Q6: 0 | R6: 0
A8: 10610002 | B8: GOMUKH CHEHRAKALA | C8: 1358.2 | D8: 63779.783 | E8: 1018.65 | F8: 1290.29 | G8: 0 | H8: 135.82 | I8: 1352.1841 | J8: 821 | K8: 821 | L8: 0 | M8: 0 | N8: 0 | O8: 0 | P8: 0 | Q8: 0 | R8: 0
A9: 10610002 Total | C9: 1358.2 | D9: 63779.783 | E9: 1018.65 | F9: 1290.29 | G9: 0 | H9: 135.82 | I9: 1352.1841 | J9: 821 | K9: 821 | L9: 0 | M9: 0 | N9: 0 | O9: 0 | P9: 0 | Q9: 0 | R9: 0
A11: 10610006 | B11: GOMUKH PREMRAJ | C11: 1421.9 | D11: 67545.511 | E11: 1066.425 | F11: 1350.805 | G11: 507.52766 | H11: 142.19 | I11: 1310.7516 | J11: 1472 | K11: 1472 | L11: 0 | M11: 0 | N11: 0 | O11: 0 | P11: 0 | Q11: 0 | R11: 0
A12: 10610006 Total | C12: 1421.9 | D12: 67545.511 | E12: 1066.425 | F12: 1350.805 | G12: 507.52766 | H12: 142.19 | I12: 1310.7516 | J12: 1472 | K12: 1472 | L12: 0 | M12: 0 | N12: 0 | O12: 0 | P12: 0 | Q12: 0 | R12: 0
A14: 10610007 | B14: GOMUKH MAGURAHI | C14: 1142.1 | D14: 58621.038 | E14: 856.575 | F14: 1084.995 | G14: 1309.3328 | H14: 114.21 | I14: 1702.7384 | J14: 0 | K14: 0 | L14: 0 | M14: 0 | N14: 0 | O14: 0 | P14: 0 | Q14: 0 | R14: 0
A15: 10610007 Total | C15: 1142.1 | D15: 58621.038 | E15: 856.575 | F15: 1084.995 | G15: 1309.3328 | H15: 114.21 | I15: 1702.7384 | J15: 0 | K15: 0 | L15: 0 | M15: 0 | N15: 0 | O15: 0 | P15: 0 | Q15: 0 | R15: 0
A17: 10610008 | B17: GOMUKH GANGATI | C17: 2003.5 | D17: 87514.05 | E17: 1502.625 | F17: 1903.325 | G17: 0 | H17: 200.35 | I17: 693.56796 | J17: 2512 | K17: 1861 | L17: 0 | M17: 0 | N17: 0 | O17: 0 | P17: 651 | Q17: 0 | R17: 651
A18: 10610008 Total | C18: 2003.5 | D18: 87514.05 | E18: 1502.625 | F18: 1903.325 | G18: 0 | H18: 200.35 | I18: 693.56796 | J18: 2512 | K18: 1861 | L18: 0 | M18: 0 | N18: 0 | O18: 0 | P18: 651 | Q18: 0 | R18: 651
A20: 10610010 | B20: GOMUKH Bhagwatpur | C20: 1837.6 | D20: 77916.535 | E20: 1378.2 | F20: 1745.72 | G20: 0 | H20: 183.76 | I20: 831.62846 | J20: 2109 | K20: 1861 | L20: 0 | M20: 0 | N20: 0 | O20: 0 | P20: 248 | Q20: 0 | R20: 248
A21: 10610010 Total | C21: 1837.6 | D21: 77916.535 | E21: 1378.2 | F21: 1745.72 | G21: 0 | H21: 183.76 | I21: 831.62846 | J21: 2109 | K21: 1861 | L21: 0 | M21: 0 | N21: 0 | O21: 0 | P21: 248 | Q21: 0 | R21: 248
A23: 10610009 | B23: GOMUKH Khanpatti | C23: 3795.06 | D23: 170116.62 | E23: 2846.295 | F23: 3605.307 | G23: 979.39073 | H23: 379.506 | I23: 0 | J23: 7051 | K23: 3402.3324 | L23: 0 | M23: 0 | N23: 0 | O23: 0 | P23: 3649 | Q23: 0 | R23: 3649
A24: 10610009 Total | C24: 3795.06 | D24: 170116.62 | E24: 2846.295 | F24: 3605.307 | G24: 979.39073 | H24: 379.506 | I24: 0 | J24: 7051 | K24: 3402.3324 | L24: 0 | M24: 0 | N24: 0 | O24: 0 | P24: 3649 | Q24: 0 | R24: 3649
A26: 10610001 | B26: GOMUKH BHATOLIYA | C26: 3502.2 | D26: 152429.46 | E26: 2626.65 | F26: 3327.09 | G26: 1130.4825 | H26: 350.22 | I26: 0 | J26: 6734 | K26: 0 | L26: 0 | M26: 0 | N26: 0 | O26: 0 | P26: 6734 | Q26: 0 | R26: 6734
A27: 10610001 Total | C27: 3502.2 | D27: 152429.46 | E27: 2626.65 | F27: 3327.09 | G27: 1130.4825 | H27: 350.22 | I27: 0 | J27: 6734 | K27: 0 | L27: 0 | M27: 0 | N27: 0 | O27: 0 | P27: 6734 | Q27: 0 | R27: 6734
A29: 10610003 | B29: GOMUKH KHAJECHAND | C29: 1637.5 | D29: 64818.105 | E29: 1228.125 | F29: 1555.625 | G29: 0 | H29: 163.75 | I29: 0 | J29: 2620 | K29: 0 | L29: 0 | M29: 0 | N29: 0 | O29: 0 | P29: 2620 | Q29: 0 | R29: 2620
A30: 10610003 Total | C30: 1637.5 | D30: 64818.105 | E30: 1228.125 | F30: 1555.625 | G30: 0 | H30: 163.75 | I30: 0 | J30: 2620 | K30: 0 | L30: 0 | M30: 0 | N30: 0 | O30: 0 | P30: 2620 | Q30: 0 | R30: 2620
A32: 10610004 | B32: GOMUKH SALEMPUR | C32: 651.9 | D32: 27768.049 | E32: 488.925 | F32: 619.305 | G32: 609.17569 | H32: 65.19 | I32: 0 | J32: 1652 | K32: 0 | L32: 0 | M32: 0 | N32: 0 | O32: 0 | P32: 1652 | Q32: 0 | R32: 1652
A33: 10610004 Total | C33: 651.9 | D33: 27768.049 | E33: 488.925 | F33: 619.305 | G33: 609.17569 | H33: 65.19 | I33: 0 | J33: 1652 | K33: 0 | L33: 0 | M33: 0 | N33: 0 | O33: 0 | P33: 1652 | Q33: 0 | R33: 1652
A35: 10610005 | B35: Gomukh Paharpur | C35: 1786 | D35: 75963.545 | E35: 1339.5 | F35: 1696.7 | G35: 0 | H35: 178.6 | I35: 0 | J35: 2858 | K35: 0 | L35: 0 | M35: 0 | N35: 0 | O35: 0 | P35: 2858 | Q35: 0 | R35: 2858
A36: 10610005 Total | C36: 1786 | D36: 75963.545 | E36: 1339.5 | F36: 1696.7 | G36: 0 | H36: 178.6 | I36: 0 | J36: 2858 | K36: 0 | L36: 0 | M36: 0 | N36: 0 | O36: 0 | P36: 2858 | Q36: 0 | R36: 2858
A38: 10610011 | B38: GOMUKH JIRWARA | C38: 1217.6 | D38: 48086.769 | E38: 913.2 | F38: 1156.72 | G38: 0 | H38: 121.76 | I38: 0 | J38: 1948 | K38: 0 | L38: 0 | M38: 0 | N38: 0 | O38: 0 | P38: 1948 | Q38: 0 | R38: 1948
A39: 10610011 Total | C39: 1217.6 | D39: 48086.769 | E39: 913.2 | F39: 1156.72 | G39: 0 | H39: 121.76 | I39: 0 | J39: 1948 | K39: 0 | L39: 0 | M39: 0 | N39: 0 | O39: 0 | P39: 1948 | Q39: 0 | R39: 1948
A41: 10610013 | B41: GOMUKH Karhatiya | C41: 1083.8 | D41: 39638.404 | E41: 812.85 | F41: 1029.61 | G41: 0 | H41: 108.38 | I41: 0 | J41: 1734 | K41: 0 | L41: 0 | M41: 0 | N41: 0 | O41: 0 | P41: 1734 | Q41: 0 | R41: 1734
A42: 10610013 Total | C42: 1083.8 | D42: 39638.404 | E42: 812.85 | F42: 1029.61 | G42: 0 | H42: 108.38 | I42: 0 | J42: 1734 | K42: 0 | L42: 0 | M42: 0 | N42: 0 | O42: 0 | P42: 1734 | Q42: 0 | R42: 1734
A44: 10610015 | B44: Gomukh Karhatiya Bujurg | C44: 1024.6 | D44: 36365.174 | E44: 768.45 | F44: 973.37 | G44: 0 | H44: 102.46 | I44: 0 | J44: 1639 | K44: 0 | L44: 0 | M44: 0 | N44: 0 | O44: 0 | P44: 1639 | Q44: 0 | R44: 1639
A45: 10610015 Total | C45: 1024.6 | D45: 36365.174 | E45: 768.45 | F45: 973.37 | G45: 0 | H45: 102.46 | I45: 0 | J45: 1639 | K45: 0 | L45: 0 | M45: 0 | N45: 0 | O45: 0 | P45: 1639 | Q45: 0 | R45: 1639
A47: 10610017 | B47: GOMUKH Bheraukhara | C47: 810.2 | D47: 32818.885 | E47: 607.65 | F47: 769.69 | G47: 0 | H47: 81.02 | I47: 0 | J47: 1296 | K47: 0 | L47: 0 | M47: 0 | N47: 0 | O47: 0 | P47: 1296 | Q47: 0 | R47: 1296
A48: 10610017 Total | C48: 810.2 | D48: 32818.885 | E48: 607.65 | F48: 769.69 | G48: 0 | H48: 81.02 | I48: 0 | J48: 1296 | K48: 0 | L48: 0 | M48: 0 | N48: 0 | O48: 0 | P48: 1296 | Q48: 0 | R48: 1296
A50: 10610018 | B50: GOMUKH SUPOLTARIYA | C50: 1931.5 | D50: 85431.684 | E50: 1448.625 | F50: 1834.925 | G50: 0 | H50: 193.15 | I50: 0 | J50: 3090 | K50: 0 | L50: 0 | M50: 0 | N50: 0 | O50: 0 | P50: 3090 | Q50: 0 | R50: 3090
A51: 10610018 Total | C51: 1931.5 | D51: 85431.684 | E51: 1448.625 | F51: 1834.925 | G51: 0 | H51: 193.15 | I51: 0 | J51: 3090 | K51: 0 | L51: 0 | M51: 0 | N51: 0 | O51: 0 | P51: 3090 | Q51: 0 | R51: 3090
A53: 10610020 | B53: GOMUKH Jilwara | C53: 1607.5 | D53: 65022.825 | E53: 1205.625 | F53: 1527.125 | G53: 0 | H53: 160.75 | I53: 0 | J53: 2572 | K53: 0 | L53: 0 | M53: 0 | N53: 0 | O53: 0 | P53: 2572 | Q53: 0 | R53: 2572
A54: 10610020 Total | C54: 1607.5 | D54: 65022.825 | E54: 1205.625 | F54: 1527.125 | G54: 0 | H54: 160.75 | I54: 0 | J54: 2572 | K54: 0 | L54: 0 | M54: 0 | N54: 0 | O54: 0 | P54: 2572 | Q54: 0 | R54: 2572
A56: 10610022 | B56: GOMUKH ABBUCHAK | C56: 924.9 | D56: 39161.727 | E56: 693.675 | F56: 878.655 | G56: 0 | H56: 92.49 | I56: 0 | J56: 1480 | K56: 0 | L56: 0 | M56: 0 | N56: 0 | O56: 0 | P56: 1480 | Q56: 0 | R56: 1480
A57: 10610022 Total | C57: 924.9 | D57: 39161.727 | E57: 693.675 | F57: 878.655 | G57: 0 | H57: 92.49 | I57: 0 | J57: 1480 | K57: 0 | L57: 0 | M57: 0 | N57: 0 | O57: 0 | P57: 1480 | Q57: 0 | R57: 1480
A59: 10610025 | B59: Gomukh Dumari | C59: 153.2 | D59: 5588.22 | E59: 114.9 | F59: 145.54 | G59: 0 | H59: 15.32 | I59: 0 | J59: 245 | K59: 0 | L59: 0 | M59: 0 | N59: 0 | O59: 0 | P59: 245 | Q59: 0 | R59: 245
A60: 10610025 Total | C60: 153.2 | D60: 5588.22 | E60: 114.9 | F60: 145.54 | G60: 0 | H60: 15.32 | I60: 0 | J60: 245 | K60: 0 | L60: 0 | M60: 0 | N60: 0 | O60: 0 | P60: 245 | Q60: 0 | R60: 245
A62: 10610019 | B62: GOMUKH Shravanapatti | C62: 583.3 | D62: 27719.24 | E62: 437.475 | F62: 554.135 | G62: 0 | H62: 58.33 | I62: 0 | J62: 933 | K62: 0 | L62: 0 | M62: 0 | N62: 0 | O62: 0 | P62: 933 | Q62: 0 | R62: 933
A63: 10610019 Total | C63: 583.3 | D63: 27719.24 | E63: 437.475 | F63: 554.135 | G63: 0 | H63: 58.33 | I63: 0 | J63: 933 | K63: 0 | L63: 0 | M63: 0 | N63: 0 | O63: 0 | P63: 933 | Q63: 0 | R63: 933
A65: 10610021 | B65: GOMUKH KHANPATTI EAST | C65: 67.2 | D65: 3063.4257 | E65: 50.4 | F65: 63.84 | G65: 0 | H65: 6.72 | I65: 0 | J65: 108 | K65: 0 | L65: 0 | M65: 0 | N65: 0 | O65: 0 | P65: 108 | Q65: 0 | R65: 108
A66: 10610021 Total | C66: 67.2 | D66: 3063.4257 | E66: 50.4 | F66: 63.84 | G66: 0 | H66: 6.72 | I66: 0 | J66: 108 | K66: 0 | L66: 0 | M66: 0 | N66: 0 | O66: 0 | P66: 108 | Q66: 0 | R66: 108
A68: 10610024 | B68: GOMUKH KAILA JALALPUR | C68: 1017.1 | D68: 38892.769 | E68: 762.825 | F68: 966.245 | G68: 517.77917 | H68: 101.71 | I68: 0 | J68: 2145 | K68: 0 | L68: 0 | M68: 0 | N68: 0 | O68: 0 | P68: 2145 | Q68: 0 | R68: 2145
A69: 10610024 Total | C69: 1017.1 | D69: 38892.769 | E69: 762.825 | F69: 966.245 | G69: 517.77917 | H69: 101.71 | I69: 0 | J69: 2145 | K69: 0 | L69: 0 | M69: 0 | N69: 0 | O69: 0 | P69: 2145 | Q69: 0 | R69: 2145
A71: 10610026 | B71: Gomukh Jhitkahi East | C71: 297.5 | D71: 18858.178 | E71: 223.125 | F71: 282.625 | G71: 0 | H71: 29.75 | I71: 0 | J71: 476 | K71: 0 | L71: 0 | M71: 0 | N71: 0 | O71: 0 | P71: 476 | Q71: 0 | R71: 476
A72: 10610026 Total | C72: 297.5 | D72: 18858.178 | E72: 223.125 | F72: 282.625 | G72: 0 | H72: 29.75 | I72: 0 | J72: 476 | K72: 0 | L72: 0 | M72: 0 | N72: 0 | O72: 0 | P72: 476 | Q72: 0 | R72: 476
A74: 10610027 | B74: GOMUKH UPHRAUL | C74: 5524.5 | D74: 186236.98 | E74: 4143.375 | F74: 5248.275 | G74: 0 | H74: 552.45 | I74: 0 | J74: 8839 | K74: 0 | L74: 0 | M74: 0 | N74: 0 | O74: 0 | P74: 8839 | Q74: 0 | R74: 8839
A75: 10610027 Total | C75: 5524.5 | D75: 186236.98 | E75: 4143.375 | F75: 5248.275 | G75: 0 | H75: 552.45 | I75: 0 | J75: 8839 | K75: 0 | L75: 0 | M75: 0 | N75: 0 | O75: 0 | P75: 8839 | Q75: 0 | R75: 8839
A77: 10610028 | B77: GOMUKH SHERPUR | C77: 372.4 | D77: 13280.408 | E77: 279.3 | F77: 353.78 | G77: 0 | H77: 37.24 | I77: 0 | J77: 596 | K77: 0 | L77: 0 | M77: 0 | N77: 0 | O77: 0 | P77: 596 | Q77: 0 | R77: 596
A78: 10610028 Total | C78: 372.4 | D78: 13280.408 | E78: 279.3 | F78: 353.78 | G78: 0 | H78: 37.24 | I78: 0 | J78: 596 | K78: 0 | L78: 0 | M78: 0 | N78: 0 | O78: 0 | P78: 596 | Q78: 0 | R78: 596
A80: 10610031 | B80: GOMUKH PANSALA | C80: 397.2 | D80: 13367.886 | E80: 297.9 | F80: 377.34 | G80: 0 | H80: 39.72 | I80: 0 | J80: 636 | K80: 0 | L80: 0 | M80: 0 | N80: 0 | O80: 0 | P80: 636 | Q80: 0 | R80: 636
A81: 10610031 Total | C81: 397.2 | D81: 13367.886 | E81: 297.9 | F81: 377.34 | G81: 0 | H81: 39.72 | I81: 0 | J81: 636 | K81: 0 | L81: 0 | M81: 0 | N81: 0 | O81: 0 | P81: 636 | Q81: 0 | R81: 636
A83: 10610034 | B83: GOMUKH PACHAI | C83: 1584.6 | D83: 58568.042 | E83: 1188.45 | F83: 1505.37 | G83: 0 | H83: 158.46 | I83: 0 | J83: 2535 | K83: 0 | L83: 0 | M83: 0 | N83: 0 | O83: 0 | P83: 2535 | Q83: 0 | R83: 2535
A84: 10610034 Total | C84: 1584.6 | D84: 58568.042 | E84: 1188.45 | F84: 1505.37 | G84: 0 | H84: 158.46 | I84: 0 | J84: 2535 | K84: 0 | L84: 0 | M84: 0 | N84: 0 | O84: 0 | P84: 2535 | Q84: 0 | R84: 2535
A86: 10610035 | B86: GOMUKH GARAHI | C86: 1787.4 | D86: 54657.386 | E86: 1340.55 | F86: 1698.03 | G86: 0 | H86: 178.74 | I86: 0 | J86: 2860 | K86: 0 | L86: 0 | M86: 0 | N86: 0 | O86: 0 | P86: 2860 | Q86: 0 | R86: 2860
A87: 10610035 Total | C87: 1787.4 | D87: 54657.386 | E87: 1340.55 | F87: 1698.03 | G87: 0 | H87: 178.74 | I87: 0 | J87: 2860 | K87: 0 | L87: 0 | M87: 0 | N87: 0 | O87: 0 | P87: 2860 | Q87: 0 | R87: 2860
A89: 10610036 | B89: GOMUKH BAIKUNTHPUR | C89: 529.1 | D89: 18823.053 | E89: 396.825 | F89: 502.645 | G89: 0 | H89: 52.91 | I89: 0 | J89: 847 | K89: 0 | L89: 0 | M89: 0 | N89: 0 | O89: 0 | P89: 847 | Q89: 0 | R89: 847
A90: 10610036 Total | C90: 529.1 | D90: 18823.053 | E90: 396.825 | F90: 502.645 | G90: 0 | H90: 52.91 | I90: 0 | J90: 847 | K90: 0 | L90: 0 | M90: 0 | N90: 0 | O90: 0 | P90: 847 | Q90: 0 | R90: 847
A92: 10610038 | B92: GOMUKH BAHASHI | C92: 3480.8 | D92: 124560.21 | E92: 2610.6 | F92: 3306.76 | G92: 0 | H92: 348.08 | I92: 0 | J92: 5569 | K92: 0 | L92: 0 | M92: 0 | N92: 0 | O92: 0 | P92: 5569 | Q92: 0 | R92: 5569
A93: 10610038 Total | C93: 3480.8 | D93: 124560.21 | E93: 2610.6 | F93: 3306.76 | G93: 0 | H93: 348.08 | I93: 0 | J93: 5569 | K93: 0 | L93: 0 | M93: 0 | N93: 0 | O93: 0 | P93: 5569 | Q93: 0 | R93: 5569
A95: 10610039 | B95: GOMUKH BAKHRI | C95: 768.4 | D95: 28187.77 | E95: 576.3 | F95: 729.98 | G95: 0 | H95: 76.84 | I95: 0 | J95: 1229 | K95: 0 | L95: 0 | M95: 0 | N95: 0 | O95: 0 | P95: 1229 | Q95: 0 | R95: 1229
A96: 10610039 Total | C96: 768.4 | D96: 28187.77 | E96: 576.3 | F96: 729.98 | G96: 0 | H96: 76.84 | I96: 0 | J96: 1229 | K96: 0 | L96: 0 | M96: 0 | N96: 0 | O96: 0 | P96: 1229 | Q96: 0 | R96: 1229
A98: 10610044 | B98: GOMUKH BABA CHAUK | C98: 49.3 | D98: 1741.74 | E98: 36.975 | F98: 46.835 | G98: 0 | H98: 4.93 | I98: 0 | J98: 79 | K98: 0 | L98: 0 | M98: 0 | N98: 0 | O98: 0 | P98: 79 | Q98: 0 | R98: 79
A99: 10610044 Total | C99: 49.3 | D99: 1741.74 | E99: 36.975 | F99: 46.835 | G99: 0 | H99: 4.93 | I99: 0 | J99: 79 | K99: 0 | L99: 0 | M99: 0 | N99: 0 | O99: 0 | P99: 79 | Q99: 0 | R99: 79
A101: 10610045 | B101: GOMUKH KHARIKA | C101: 1451.3 | D101: 53654.781 | E101: 1088.475 | F101: 1378.735 | G101: 0 | H101: 145.13 | I101: 0 | J101: 2322 | K101: 0 | L101: 0 | M101: 0 | N101: 0 | O101: 0 | P101: 2322 | Q101: 0 | R101: 2322
A102: 10610045 Total | C102: 1451.3 | D102: 53654.781 | E102: 1088.475 | F102: 1378.735 | G102: 0 | H102: 145.13 | I102: 0 | J102: 2322 | K102: 0 | L102: 0 | M102: 0 | N102: 0 | O102: 0 | P102: 2322 | Q102: 0 | R102: 2322
A104: 10610046 | B104: GOMUKH KALYANPUR | C104: 315.8 | D104: 11073.13 | E104: 236.85 | F104: 300.01 | G104: 0 | H104: 31.58 | I104: 0 | J104: 505 | K104: 0 | L104: 0 | M104: 0 | N104: 0 | O104: 0 | P104: 505 | Q104: 0 | R104: 505
A105: 10610046 Total | C105: 315.8 | D105: 11073.13 | E105: 236.85 | F105: 300.01 | G105: 0 | H105: 31.58 | I105: 0 | J105: 505 | K105: 0 | L105: 0 | M105: 0 | N105: 0 | O105: 0 | P105: 505 | Q105: 0 | R105: 505
A107: 10610050 | B107: GOMUKH HARPUR RAJESH | C107: 683.4 | D107: 28512.566 | E107: 512.55 | F107: 649.23 | G107: 0 | H107: 68.34 | I107: 0 | J107: 1093 | K107: 0 | L107: 0 | M107: 0 | N107: 0 | O107: 0 | P107: 1093 | Q107: 0 | R107: 1093
A108: 10610050 Total | C108: 683.4 | D108: 28512.566 | E108: 512.55 | F108: 649.23 | G108: 0 | H108: 68.34 | I108: 0 | J108: 1093 | K108: 0 | L108: 0 | M108: 0 | N108: 0 | O108: 0 | P108: 1093 | Q108: 0 | R108: 1093
A110: 10610051 | B110: GOMUKH SANICHAR HATT | C110: 793.9 | D110: 30173.637 | E110: 595.425 | F110: 754.205 | G110: 0 | H110: 79.39 | I110: 0 | J110: 1270 | K110: 0 | L110: 0 | M110: 0 | N110: 0 | O110: 0 | P110: 1270 | Q110: 0 | R110: 1270
A111: 10610051 Total | C111: 793.9 | D111: 30173.637 | E111: 595.425 | F111: 754.205 | G111: 0 | H111: 79.39 | I111: 0 | J111: 1270 | K111: 0 | L111: 0 | M111: 0 | N111: 0 | O111: 0 | P111: 1270 | Q111: 0 | R111: 1270
A113: 10610052 | B113: GOMUKH SAHARIYA | C113: 2454.6 | D113: 99733.777 | E113: 1840.95 | F113: 2331.87 | G113: 0 | H113: 245.46 | I113: 0 | J113: 3927 | K113: 0 | L113: 0 | M113: 0 | N113: 0 | O113: 0 | P113: 3927 | Q113: 0 | R113: 3927
A114: 10610052 Total | C114: 2454.6 | D114: 99733.777 | E114: 1840.95 | F114: 2331.87 | G114: 0 | H114: 245.46 | I114: 0 | J114: 3927 | K114: 0 | L114: 0 | M114: 0 | N114: 0 | O114: 0 | P114: 3927 | Q114: 0 | R114: 3927
A116: 10610041 | B116: GOMUKH RUSULPUR GANGATI | C116: 72.5 | D116: 2647.8783 | E116: 54.375 | F116: 68.875 | G116: 0 | H116: 7.25 | I116: 0 | J116: 116 | K116: 0 | L116: 0 | M116: 0 | N116: 0 | O116: 0 | P116: 116 | Q116: 0 | R116: 116
A117: 10610041 Total | C117: 72.5 | D117: 2647.8783 | E117: 54.375 | F117: 68.875 | G117: 0 | H117: 7.25 | I117: 0 | J117: 116 | K117: 0 | L117: 0 | M117: 0 | N117: 0 | O117: 0 | P117: 116 | Q117: 0 | R117: 116
A119: 10610055 | B119: GOMUKH PAITRAPUR | C119: 250.7 | D119: 11215.822 | E119: 188.025 | F119: 238.165 | G119: 0 | H119: 25.07 | I119: 0 | J119: 401 | K119: 0 | L119: 0 | M119: 0 | N119: 0 | O119: 0 | P119: 401 | Q119: 0 | R119: 401
A120: 10610055 Total | C120: 250.7 | D120: 11215.822 | E120: 188.025 | F120: 238.165 | G120: 0 | H120: 25.07 | I120: 0 | J120: 401 | K120: 0 | L120: 0 | M120: 0 | N120: 0 | O120: 0 | P120: 401 | Q120: 0 | R120: 401
A122: 10610056 | B122: GOMUKH JAI MATA DI MILK CENTER | C122: 431.7 | D122: 20301.181 | E122: 323.775 | F122: 410.115 | G122: 0 | H122: 43.17 | I122: 0 | J122: 691 | K122: 0 | L122: 0 | M122: 0 | N122: 0 | O122: 0 | P122: 691 | Q122: 0 | R122: 691
A123: 10610056 Total | C123: 431.7 | D123: 20301.181 | E123: 323.775 | F123: 410.115 | G123: 0 | H123: 43.17 | I123: 0 | J123: 691 | K123: 0 | L123: 0 | M123: 0 | N123: 0 | O123: 0 | P123: 691 | Q123: 0 | R123: 691
A125: Grand Total | C125: 51142.36 | D125: 2057852 | E125: 38356.77 | F125: 48585.242 | G125: 5053.6885 | H125: 5114.236 | I125: 6435.4783 | J125: 79010 | K125: 9417.3324 | L125: 0 | M125: 0 | N125: 0 | O125: 0 | P125: 69593 | Q125: 0 | R125: 69593

Sheet Shayak Income 
M1: MPG Payment | Q1: MPG Sheet | R1: Internal | T1: MPG Deduction | W1: Other Security Deduction | AG1: -1
A2: Opening Balance ____ | M2: =SUBTOTAL(9,M4:M1036) -> 3651113.1 | N2: =SUBTOTAL(9,N4:N1036) -> 1.4131596e+08 | O2: Income | W2: =SUBTOTAL(9,W4:W1036) -> 667970.21 | X2: =SUBTOTAL(9,X4:X1036) -> 74053.738 | Y2: =SUBTOTAL(9,Y4:Y1036) -> 34928 | Z2: =SUBTOTAL(9,Z4:Z1036) -> 17372 | AA2: =SUBTOTAL(9,AA4:AA1036) -> 27705.3 | AB2: =SUBTOTAL(9,AB4:AB1036) -> 5051093 | AC2: =SUBTOTAL(9,AC4:AC1036) -> 406958 | AD2: =SUBTOTAL(9,AD4:AD1036) -> 4644135 | AG2: -1 | AN2: =SUBTOTAL(9,AN4:AN1036) -> 1146908.2 | AO2: =SUBTOTAL(9,AO4:AO1036) -> 37196 | AP2: =SUBTOTAL(9,AP4:AP1036) -> 667970.21 | AQ2: =SUBTOTAL(9,AQ4:AQ1036) -> 705166.21
A3: AMCU | B3: Milk Cans | C3: Assets Value | D3: Code | E3: MPG NAME | F3: Amcu type | G3: VLC Type | H3: Farmer Payment | I3: BMC Code | J3: MCC | K3: status | L3: Start Date | M3: BMC Volume | N3: BMC Amount | O3: Sahayak Comission @ 0.75/- | P3: Std gain @ 0.95/- | Q3: Farmer Sample Milk | R3: Std Gain @ 3% | S3: Reserve from Std Gain | T3: AMC from MPG @ 0.10/- | U3: Actual Volume Penalty | V3: Net Sahayak Income | W3: New Assets EMI | X3: Can Deduction | Y3: PCB Ded | Z3: Other | AA3: Consumables | AB3: Payble to Sahyak | AC3: Hold | AD3: Net Payble | AE3: Payment relase | AG3: Stop Payment | AH3: Remarks | AI3: Pending Down Payment | AJ3: Recommendation | AK3: 29-04 Jun | AL3: Irregular Pourer | AM3: No of pouring shift | AN3: EMI | AO3: Recovery from Milk | AP3: Recovery from Com | AQ3: Net Recovered | AT3: HDFC | AU3: OTHER | AV3: Remarks
A4: =IFERROR(VLOOKUP(D4,'Monthly Deduction'!$I$3:$J$957,2,0),0) -> 24146.671 | B4: =IFERROR(VLOOKUP(D4,'Monthly Deduction'!$E$3:$F$957,2,0),0) -> 12800 | C4: =A4+B4 -> 36946.671 | D4: 10010013 | E4: =VLOOKUP(D4,'MPG Payment '!$E$3:$G$498218,2,0) -> Gomukh Kumbhi | F4: =IFERROR(_xlfn.XLOOKUP(D4,'Monthly Deduction'!$I$3:$I$957,'Monthly Deduction'!$H$3:$H$957),0) -> 0 | G4: =VLOOKUP(D4,'MPG Payment '!$E$3:$G$334579,3,0) -> MPG | H4: =VLOOKUP(D4,'MPG Payment '!$E$3:$H$334579,4,0) -> Direct | I4: =INDEX('MPG Payment '!$C:$C,MATCH('Shayak Income '!D4,'MPG Payment '!E:E,0)) -> 1001 | J4: =INDEX('MPG Payment '!$D:$D,MATCH('Shayak Income '!D4,'MPG Payment '!E:E,0)) -> Majhaul | K4: Old | L4: 45013 | M4: =SUMIF('MPG Payment '!$E$3:$E$34579,'Shayak Income '!D4,'MPG Payment '!$I$3:$I$34579) -> 2891 | N4: =SUMIF('MPG Payment '!$E$3:$E$34579,'Shayak Income '!D4,'MPG Payment '!$J$3:$J$34579) -> 109798.24 | O4: =+M4*0.75 -> 2168.25 | P4: =+M4*0.95 -> 2746.45 | Q4: =SUMIF('MPG Payment '!$E$3:$E$34579,'Shayak Income '!D4,'MPG Payment '!$S$3:$S$34579) -> 795.52465 | R4: =+N4*3% -> 3293.9472 | S4: =R4-P4 -> 547.4972 | T4: =M4*0.1 -> 289.1 | U4: =(((IF(K4="New",0,SUMIF('MPG Payment '!$E$3:$E$34579,'Shayak Income '!D4,'MPG Payment '!$AC$3:$AC$34579))))+0)+0 -> 15.305181 | V4: =ROUND((SUM(O4:Q4)-SUM(T4:U4)),0) -> 5406 | W4: =(((AN4-AO4)))+0 -> 2195.9648 | X4: 0 | Y4: =IFERROR(VLOOKUP(D4,'Monthly Deduction'!$M$2:$N$64,2,0),0) -> 0 | Z4: 0 | AA4: =IFERROR(VLOOKUP(D4,'Monthly Deduction'!A:B,2,0),0) -> 0 | AB4: =ROUND(IFERROR(V4-SUM(W4:AA4),0),0) -> 3210 | AC4: 0 | AD4: =ROUND(AB4-AC4,0) -> 3210 | AE4: =IF(AC4<>0,"Yes","Release") -> Release | AG4: 0 | AI4: 0 | AK4: 720.9 | AL4: =COUNTIF(AK4:AK4,"=NA") -> 0 | AN4: =((MIN(IF(A4>0,MAX(N4*2%,1861),0),A4)))+0 -> 2195.9648 | AO4: =SUMIF('MPG Payment '!E:E,'Shayak Income '!D4,'MPG Payment '!AJ:AJ) -> 0 | AP4: =W4 -> 2195.9648 | AQ4: =AO4+AP4 -> 2195.9648 | AS4: =B4-X4 -> 12800
A5: =IFERROR(VLOOKUP(D5,'Monthly Deduction'!$I$3:$J$957,2,0),0) -> 64838 | B5: =IFERROR(VLOOKUP(D5,'Monthly Deduction'!$E$3:$F$957,2,0),0) -> 6400 | C5: =A5+B5 -> 71238 | D5: 10010017 | E5: =VLOOKUP(D5,'MPG Payment '!$E$3:$G$498218,2,0) -> Gomukh Amba | F5: =IFERROR(_xlfn.XLOOKUP(D5,'Monthly Deduction'!$I$3:$I$957,'Monthly Deduction'!$H$3:$H$957),0) -> 0 | G5: =VLOOKUP(D5,'MPG Payment '!$E$3:$G$334579,3,0) -> MPG | H5: =VLOOKUP(D5,'MPG Payment '!$E$3:$H$334579,4,0) -> Direct | I5: =INDEX('MPG Payment '!$C:$C,MATCH('Shayak Income '!D5,'MPG Payment '!E:E,0)) -> 1008 | J5: =INDEX('MPG Payment '!$D:$D,MATCH('Shayak Income '!D5,'MPG Payment '!E:E,0)) -> Teghra | K5: Old | L5: 45016 | M5: =SUMIF('MPG Payment '!$E$3:$E$34579,'Shayak Income '!D5,'MPG Payment '!$I$3:$I$34579) -> 158.25 | N5: =SUMIF('MPG Payment '!$E$3:$E$34579,'Shayak Income '!D5,'MPG Payment '!$J$3:$J$34579) -> 5257.6122 | O5: =+M5*0.75 -> 118.6875 | P5: =+M5*0.95 -> 150.3375 | Q5: =SUMIF('MPG Payment '!$E$3:$E$34579,'Shayak Income '!D5,'MPG Payment '!$S$3:$S$34579) -> 0 | R5: =+N5*3% -> 157.72836 | S5: =R5-P5 -> 7.3908645 | T5: =M5*0.1 -> 15.825 | U5: =(((IF(K5="New",0,SUMIF('MPG Payment '!$E$3:$E$34579,'Shayak Income '!D5,'MPG Payment '!$AC$3:$AC$34579))))+0)+-1481 -> 252.76736 | V5: =ROUND((SUM(O5:Q5)-SUM(T5:U5)),0) -> 0 | W5: 0 | X5: 0 | Y5: =IFERROR(VLOOKUP(D5,'Monthly Deduction'!$M$2:$N$64,2,0),0) -> 0 | Z5: 0 | AA5: =IFERROR(VLOOKUP(D5,'Monthly Deduction'!A:B,2,0),0) -> 0 | AB5: =ROUND(IFERROR(V5-SUM(W5:AA5),0),0) -> 0 | AC5: 0 | AD5: =ROUND(AB5-AC5,0) -> 0 | AE5: =IF(AC5<>0,"Yes","Release") -> Release | AG5: 0 | AI5: 0 | AK5: 28.5 | AL5: =COUNTIF(AK5:AK5,"=NA") -> 0 | AN5: =((MIN(IF(A5>0,MAX(N5*2%,1861),0),A5)))+0 -> 1861 | AO5: =SUMIF('MPG Payment '!E:E,'Shayak Income '!D5,'MPG Payment '!AJ:AJ) -> 500 | AP5: =W5 -> 0 | AQ5: =AO5+AP5 -> 500 | AS5: =B5-X5 -> 6400
A6: =IFERROR(VLOOKUP(D6,'Monthly Deduction'!$I$3:$J$957,2,0),0) -> 30537.325 | B6: =IFERROR(VLOOKUP(D6,'Monthly Deduction'!$E$3:$F$957,2,0),0) -> 6400 | C6: =A6+B6 -> 36937.325 | D6: 10010019 | E6: =VLOOKUP(D6,'MPG Payment '!$E$3:$G$498218,2,0) -> Gomukh Jagdar | F6: =IFERROR(_xlfn.XLOOKUP(D6,'Monthly Deduction'!$I$3:$I$957,'Monthly Deduction'!$H$3:$H$957),0) -> 0 | G6: =VLOOKUP(D6,'MPG Payment '!$E$3:$G$334579,3,0) -> MPG | H6: =VLOOKUP(D6,'MPG Payment '!$E$3:$H$334579,4,0) -> Direct | I6: =INDEX('MPG Payment '!$C:$C,MATCH('Shayak Income '!D6,'MPG Payment '!E:E,0)) -> 1001 | J6: =INDEX('MPG Payment '!$D:$D,MATCH('Shayak Income '!D6,'MPG Payment '!E:E,0)) -> Majhaul | K6: Old | L6: 45040 | M6: =SUMIF('MPG Payment '!$E$3:$E$34579,'Shayak Income '!D6,'MPG Payment '!$I$3:$I$34579) -> 3099.7 | N6: =SUMIF('MPG Payment '!$E$3:$E$34579,'Shayak Income '!D6,'MPG Payment '!$J$3:$J$34579) -> 122858.96 | O6: =+M6*0.75 -> 2324.775 | P6: =+M6*0.95 -> 2944.715 | Q6: =SUMIF('MPG Payment '!$E$3:$E$34579,'Shayak Income '!D6,'MPG Payment '!$S$3:$S$34579) -> 1681.2057 | R6: =+N6*3% -> 3685.7689 | S6: =R6-P6 -> 741.05391 | T6: =M6*0.1 -> 309.97 | U6: =(((IF(K6="New",0,SUMIF('MPG Payment '!$E$3:$E$34579,'Shayak Income '!D6,'MPG Payment '!$AC$3:$AC$34579))))+0)+0 -> 0 | V6: =ROUND((SUM(O6:Q6)-SUM(T6:U6)),0) -> 6641 | W6: =(((AN6-AO6)))+0 -> 2457.1793 | X6: 0 | Y6: =IFERROR(VLOOKUP(D6,'Monthly Deduction'!$M$2:$N$64,2,0),0) -> 0 | Z6: 0 | AA6: =IFERROR(VLOOKUP(D6,'Monthly Deduction'!A:B,2,0),0) -> 0 | AB6: =ROUND(IFERROR(V6-SUM(W6:AA6),0),0) -> 4184 | AC6: 0 | AD6: =ROUND(AB6-AC6,0) -> 4184 | AE6: =IF(AC6<>0,"Yes","Release") -> Release | AG6: 0 | AI6: 0 | AK6: 1007.2 | AL6: =COUNTIF(AK6:AK6,"=NA") -> 0 | AN6: =((MIN(IF(A6>0,MAX(N6*2%,1861),0),A6)))+0 -> 2457.1793 | AO6: =SUMIF('MPG Payment '!E:E,'Shayak Income '!D6,'MPG Payment '!AJ:AJ) -> 0 | AP6: =W6 -> 2457.1793 | AQ6: =AO6+AP6 -> 2457.1793 | AS6: =B6-X6 -> 6400
A7: =IFERROR(VLOOKUP(D7,'Monthly Deduction'!$I$3:$J$957,2,0),0) -> 38140.006 | B7: =IFERROR(VLOOKUP(D7,'Monthly Deduction'!$E$3:$F$957,2,0),0) -> 5744.916 | C7: =A7+B7 -> 43884.922 | D7: 10010038 | E7: =VLOOKUP(D7,'MPG Payment '!$E$3:$G$498218,2,0) -> Gomukh Goriyari | F7: =IFERROR(_xlfn.XLOOKUP(D7,'Monthly Deduction'!$I$3:$I$957,'Monthly Deduction'!$H$3:$H$957),0) -> 0 | G7: =VLOOKUP(D7,'MPG Payment '!$E$3:$G$334579,3,0) -> MPG | H7: =VLOOKUP(D7,'MPG Payment '!$E$3:$H$334579,4,0) -> Direct | I7: =INDEX('MPG Payment '!$C:$C,MATCH('Shayak Income '!D7,'MPG Payment '!E:E,0)) -> 1058 | J7: =INDEX('MPG Payment '!$D:$D,MATCH('Shayak Income '!D7,'MPG Payment '!E:E,0)) -> Hasanpur | K7: Old | L7: 45128 | M7: =SUMIF('MPG Payment '!$E$3:$E$34579,'Shayak Income '!D7,'MPG Payment '!$I$3:$I$34579) -> 4882.3 | N7: =SUMIF('MPG Payment '!$E$3:$E$34579,'Shayak Income '!D7,'MPG Payment '!$J$3:$J$34579) -> 189127.27 | O7: =+M7*0.75 -> 3661.725 | P7: =+M7*0.95 -> 4638.185 | Q7: =SUMIF('MPG Payment '!$E$3:$E$34579,'Shayak Income '!D7,'MPG Payment '!$S$3:$S$34579) -> 830.22511 | R7: =+N7*3% -> 5673.818 | S7: =R7-P7 -> 1035.633 | T7: =M7*0.1 -> 488.23 | U7: =(((IF(K7="New",0,SUMIF('MPG Payment '!$E$3:$E$34579,'Shayak Income '!D7,'MPG Payment '!$AC$3:$AC$34579))))+0)+0 -> 0 | V7: =ROUND((SUM(O7:Q7)-SUM(T7:U7)),0) -> 8642 | W7: =(((AN7-AO7)))+0 -> 3782.5453 | X7: 0 | Y7: =IFERROR(VLOOKUP(D7,'Monthly Deduction'!$M$2:$N$64,2,0),0) -> 0 | Z7: 0 | AA7: =IFERROR(VLOOKUP(D7,'Monthly Deduction'!A:B,2,0),0) -> 0 | AB7: =ROUND(IFERROR(V7-SUM(W7:AA7),0),0) -> 4859 | AC7: 0 | AD7: =ROUND(AB7-AC7,0) -> 4859 | AE7: =IF(AC7<>0,"Yes","Release") -> Release | AG7: 0 | AI7: 0 | AK7: 1382.3 | AL7: =COUNTIF(AK7:AK7,"=NA") -> 0 | AN7: =((MIN(IF(A7>0,MAX(N7*2%,1861),0),A7)))+0 -> 3782.5453 | AO7: =SUMIF('MPG Payment '!E:E,'Shayak Income '!D7,'MPG Payment '!AJ:AJ) -> 0 | AP7: =W7 -> 3782.5453 | AQ7: =AO7+AP7 -> 3782.5453 | AS7: =B7-X7 -> 5744.916
A8: =IFERROR(VLOOKUP(D8,'Monthly Deduction'!$I$3:$J$957,2,0),0) -> 0 | B8: =IFERROR(VLOOKUP(D8,'Monthly Deduction'!$E$3:$F$957,2,0),0) -> 0 | C8: =A8+B8 -> 0 | D8: 10010047 | E8: =VLOOKUP(D8,'MPG Payment '!$E$3:$G$498218,2,0) -> Mohanpur - Chandan | F8: =IFERROR(_xlfn.XLOOKUP(D8,'Monthly Deduction'!$I$3:$I$957,'Monthly Deduction'!$H$3:$H$957),0) -> 0 | G8: =VLOOKUP(D8,'MPG Payment '!$E$3:$G$334579,3,0) -> vlc | H8: =VLOOKUP(D8,'MPG Payment '!$E$3:$H$334579,4,0) -> Indirect | I8: =INDEX('MPG Payment '!$C:$C,MATCH('Shayak Income '!D8,'MPG Payment '!E:E,0)) -> 1001 | J8: =INDEX('MPG Payment '!$D:$D,MATCH('Shayak Income '!D8,'MPG Payment '!E:E,0)) -> Majhaul | K8: Old | L8: 45121 | M8: =SUMIF('MPG Payment '!$E$3:$E$34579,'Shayak Income '!D8,'MPG Payment '!$I$3:$I$34579) -> 325 | N8: =SUMIF('MPG Payment '!$E$3:$E$34579,'Shayak Income '!D8,'MPG Payment '!$J$3:$J$34579) -> 13308.744 | O8: =+M8*0.75 -> 243.75 | P8: =+M8*0.95 -> 308.75 | Q8: =SUMIF('MPG Payment '!$E$3:$E$34579,'Shayak Income '!D8,'MPG Payment '!$S$3:$S$34579) -> 0 | R8: =+N8*3% -> 399.26232 | S8: =R8-P8 -> 90.512321 | T8: =M8*0.1 -> 32.5 | U8: =(((IF(K8="New",0,SUMIF('MPG Payment '!$E$3:$E$34579,'Shayak Income '!D8,'MPG Payment '!$AC$3:$AC$34579))))+0)+-1591 -> 520.48048 | V8: =ROUND((SUM(O8:Q8)-SUM(T8:U8)),0) -> 0 | W8: 0 | X8: 0 | Y8: =IFERROR(VLOOKUP(D8,'Monthly Deduction'!$M$2:$N$64,2,0),0) -> 0 | Z8: 0 | AA8: =IFERROR(VLOOKUP(D8,'Monthly Deduction'!A:B,2,0),0) -> 0 | AB8: =ROUND(IFERROR(V8-SUM(W8:AA8),0),0) -> 0 | AC8: 0 | AD8: =ROUND(AB8-AC8,0) -> 0 | AE8: =IF(AC8<>0,"Yes","Release") -> Release | AG8: 0 | AI8: 0 | AK8: 115.9 | AL8: =COUNTIF(AK8:AK8,"=NA") -> 0 | AN8: =((MIN(IF(A8>0,MAX(N8*2%,1861),0),A8)))+0 -> 0 | AO8: =SUMIF('MPG Payment '!E:E,'Shayak Income '!D8,'MPG Payment '!AJ:AJ) -> 0 | AP8: =W8 -> 0 | AQ8: =AO8+AP8 -> 0 | AS8: =B8-X8 -> 0
A9: =IFERROR(VLOOKUP(D9,'Monthly Deduction'!$I$3:$J$957,2,0),0) -> 36739.688 | B9: =IFERROR(VLOOKUP(D9,'Monthly Deduction'!$E$3:$F$957,2,0),0) -> 0 | C9: =A9+B9 -> 36739.688 | D9: 10010050 | E9: =VLOOKUP(D9,'MPG Payment '!$E$3:$G$498218,2,0) -> Ekamba - Ashutosh | F9: =IFERROR(_xlfn.XLOOKUP(D9,'Monthly Deduction'!$I$3:$I$957,'Monthly Deduction'!$H$3:$H$957),0) -> 0 | G9: =VLOOKUP(D9,'MPG Payment '!$E$3:$G$334579,3,0) -> vlc | H9: =VLOOKUP(D9,'MPG Payment '!$E$3:$H$334579,4,0) -> Indirect | I9: =INDEX('MPG Payment '!$C:$C,MATCH('Shayak Income '!D9,'MPG Payment '!E:E,0)) -> 1058 | J9: =INDEX('MPG Payment '!$D:$D,MATCH('Shayak Income '!D9,'MPG Payment '!E:E,0)) -> Hasanpur | K9: Old | L9: 45098 | M9: =SUMIF('MPG Payment '!$E$3:$E$34579,'Shayak Income '!D9,'MPG Payment '!$I$3:$I$34579) -> 3298.4 | N9: =SUMIF('MPG Payment '!$E$3:$E$34579,'Shayak Income '!D9,'MPG Payment '!$J$3:$J$34579) -> 123601.22 | O9: =+M9*0.75 -> 2473.8 | P9: =+M9*0.95 -> 3133.48 | Q9: =SUMIF('MPG Payment '!$E$3:$E$34579,'Shayak Income '!D9,'MPG Payment '!$S$3:$S$34579) -> 0 | R9: =+N9*3% -> 3708.0365 | S9: =R9-P9 -> 574.5565 | T9: =M9*0.1 -> 329.84 | U9: =(((IF(K9="New",0,SUMIF('MPG Payment '!$E$3:$E$34579,'Shayak Income '!D9,'MPG Payment '!$AC$3:$AC$34579))))+0)+0 -> 40.707069 | V9: =ROUND((SUM(O9:Q9)-SUM(T9:U9)),0) -> 5237 | W9: =(((AN9-AO9)))+0 -> 2472.0243 | X9: 0 | Y9: =IFERROR(VLOOKUP(D9,'Monthly Deduction'!$M$2:$N$64,2,0),0) -> 0 | Z9: 0 | AA9: =IFERROR(VLOOKUP(D9,'Monthly Deduction'!A:B,2,0),0) -> 0 | AB9: =ROUND(IFERROR(V9-SUM(W9:AA9),0),0) -> 2765 | AC9: 0 | AD9: =ROUND(AB9-AC9,0) -> 2765 | AE9: =IF(AC9<>0,"Yes","Release") -> Release | AG9: 0 | AI9: 0 | AK9: 1008.9 | AL9: =COUNTIF(AK9:AK9,"=NA") -> 0 | AN9: =((MIN(IF(A9>0,MAX(N9*2%,1861),0),A9)))+0 -> 2472.0243 | AO9: =SUMIF('MPG Payment '!E:E,'Shayak Income '!D9,'MPG Payment '!AJ:AJ) -> 0 | AP9: =W9 -> 2472.0243 | AQ9: =AO9+AP9 -> 2472.0243 | AS9: =B9-X9 -> 0
A10: =IFERROR(VLOOKUP(D10,'Monthly Deduction'!$I$3:$J$957,2,0),0) -> 27138.825 | B10: =IFERROR(VLOOKUP(D10,'Monthly Deduction'!$E$3:$F$957,2,0),0) -> 570.1518 | C10: =A10+B10 -> 27708.977 | D10: 10010051 | E10: =VLOOKUP(D10,'MPG Payment '!$E$3:$G$498218,2,0) -> Gomukh Dunahi | F10: =IFERROR(_xlfn.XLOOKUP(D10,'Monthly Deduction'!$I$3:$I$957,'Monthly Deduction'!$H$3:$H$957),0) -> 0 | G10: =VLOOKUP(D10,'MPG Payment '!$E$3:$G$334579,3,0) -> MPG | H10: =VLOOKUP(D10,'MPG Payment '!$E$3:$H$334579,4,0) -> Direct | I10: =INDEX('MPG Payment '!$C:$C,MATCH('Shayak Income '!D10,'MPG Payment '!E:E,0)) -> 1058 | J10: =INDEX('MPG Payment '!$D:$D,MATCH('Shayak Income '!D10,'MPG Payment '!E:E,0)) -> Hasanpur | K10: Old | L10: 45219 | M10: =SUMIF('MPG Payment '!$E$3:$E$34579,'Shayak Income '!D10,'MPG Payment '!$I$3:$I$34579) -> 2234.8 | N10: =SUMIF('MPG Payment '!$E$3:$E$34579,'Shayak Income '!D10,'MPG Payment '!$J$3:$J$34579) -> 83104.667 | O10: =+M10*0.75 -> 1676.1 | P10: =+M10*0.95 -> 2123.06 | Q10: =SUMIF('MPG Payment '!$E$3:$E$34579,'Shayak Income '!D10,'MPG Payment '!$S$3:$S$34579) -> 618.92895 | R10: =+N10*3% -> 2493.14 | S10: =R10-P10 -> 370.08001 | T10: =M10*0.1 -> 223.48 | U10: =(((IF(K10="New",0,SUMIF('MPG Payment '!$E$3:$E$34579,'Shayak Income '!D10,'MPG Payment '!$AC$3:$AC$34579))))+0)+0 -> 213.3474 | V10: =ROUND((SUM(O10:Q10)-SUM(T10:U10)),0) -> 3981 | W10: =(((AN10-AO10)))+0 -> 1861 | X10: 0 | Y10: =IFERROR(VLOOKUP(D10,'Monthly Deduction'!$M$2:$N$64,2,0),0) -> 0 | Z10: 0 | AA10: =IFERROR(VLOOKUP(D10,'Monthly Deduction'!A:B,2,0),0) -> 0 | AB10: =ROUND(IFERROR(V10-SUM(W10:AA10),0),0) -> 2120 | AC10: 0 | AD10: =ROUND(AB10-AC10,0) -> 2120 | AE10: =IF(AC10<>0,"Yes","Release") -> Release | AG10: 0 | AI10: 0 | AK10: 1132.6 | AL10: =COUNTIF(AK10:AK10,"=NA") -> 0 | AN10: =((MIN(IF(A10>0,MAX(N10*2%,1861),0),A10)))+0 -> 1861 | AO10: =SUMIF('MPG Payment '!E:E,'Shayak Income '!D10,'MPG Payment '!AJ:AJ) -> 0 | AP10: =W10 -> 1861 | AQ10: =AO10+AP10 -> 1861 | AS10: =B10-X10 -> 570.1518
A11: =IFERROR(VLOOKUP(D11,'Monthly Deduction'!$I$3:$J$957,2,0),0) -> 82375.427 | B11: =IFERROR(VLOOKUP(D11,'Monthly Deduction'!$E$3:$F$957,2,0),0) -> 6400 | C11: =A11+B11 -> 88775.427 | D11: 10010055 | E11: =VLOOKUP(D11,'MPG Payment '!$E$3:$G$498218,2,0) -> GOMUKH BIRPUR PASCHIM | F11: =IFERROR(_xlfn.XLOOKUP(D11,'Monthly Deduction'!$I$3:$I$957,'Monthly Deduction'!$H$3:$H$957),0) -> 0 | G11: =VLOOKUP(D11,'MPG Payment '!$E$3:$G$334579,3,0) -> MPG | H11: =VLOOKUP(D11,'MPG Payment '!$E$3:$H$334579,4,0) -> Direct | I11: =INDEX('MPG Payment '!$C:$C,MATCH('Shayak Income '!D11,'MPG Payment '!E:E,0)) -> 1001 | J11: =INDEX('MPG Payment '!$D:$D,MATCH('Shayak Income '!D11,'MPG Payment '!E:E,0)) -> Majhaul | K11: Old | L11: 45231 | M11: =SUMIF('MPG Payment '!$E$3:$E$34579,'Shayak Income '!D11,'MPG Payment '!$I$3:$I$34579) -> 526.7 | N11: =SUMIF('MPG Payment '!$E$3:$E$34579,'Shayak Income '!D11,'MPG Payment '!$J$3:$J$34579) -> 21545.007 | O11: =+M11*0.75 -> 395.025 | P11: =+M11*0.95 -> 500.365 | Q11: =SUMIF('MPG Payment '!$E$3:$E$34579,'Shayak Income '!D11,'MPG Payment '!$S$3:$S$34579) -> 0 | R11: =+N11*3% -> 646.3502 | S11: =R11-P11 -> 145.9852 | T11: =M11*0.1 -> 52.67 | U11: =(((IF(K11="New",0,SUMIF('MPG Payment '!$E$3:$E$34579,'Shayak Income '!D11,'MPG Payment '!$AC$3:$AC$34579))))+0)+-1018 -> 842.25604 | V11: =ROUND((SUM(O11:Q11)-SUM(T11:U11)),0) -> 0 | W11: 0 | X11: 0 | Y11: =IFERROR(VLOOKUP(D11,'Monthly Deduction'!$M$2:$N$64,2,0),0) -> 0 | Z11: 0 | AA11: =IFERROR(VLOOKUP(D11,'Monthly Deduction'!A:B,2,0),0) -> 0 | AB11: =ROUND(IFERROR(V11-SUM(W11:AA11),0),0) -> 0 | AC11: 0 | AD11: =ROUND(AB11-AC11,0) -> 0 | AE11: =IF(AC11<>0,"Yes","Release") -> Release | AG11: 0 | AI11: 0 | AK11: 115.8 | AL11: =COUNTIF(AK11:AK11,"=NA") -> 0 | AN11: =((MIN(IF(A11>0,MAX(N11*2%,1861),0),A11)))+0 -> 1861 | AO11: =SUMIF('MPG Payment '!E:E,'Shayak Income '!D11,'MPG Payment '!AJ:AJ) -> 500 | AP11: =W11 -> 0 | AQ11: =AO11+AP11 -> 500 | AS11: =B11-X11 -> 6400
A12: =IFERROR(VLOOKUP(D12,'Monthly Deduction'!$I$3:$J$957,2,0),0) -> 39104.976 | B12: =IFERROR(VLOOKUP(D12,'Monthly Deduction'!$E$3:$F$957,2,0),0) -> 0 | C12: =A12+B12 -> 39104.976 | D12: 10010056 | E12: =VLOOKUP(D12,'MPG Payment '!$E$3:$G$498218,2,0) -> Gomukh Harigiridham | F12: =IFERROR(_xlfn.XLOOKUP(D12,'Monthly Deduction'!$I$3:$I$957,'Monthly Deduction'!$H$3:$H$957),0) -> 0 | G12: =VLOOKUP(D12,'MPG Payment '!$E$3:$G$334579,3,0) -> MPG | H12: =VLOOKUP(D12,'MPG Payment '!$E$3:$H$334579,4,0) -> Direct | I12: =INDEX('MPG Payment '!$C:$C,MATCH('Shayak Income '!D12,'MPG Payment '!E:E,0)) -> 1058 | J12: =INDEX('MPG Payment '!$D:$D,MATCH('Shayak Income '!D12,'MPG Payment '!E:E,0)) -> Hasanpur | K12: Old | L12: 45297 | M12: =SUMIF('MPG Payment '!$E$3:$E$34579,'Shayak Income '!D12,'MPG Payment '!$I$3:$I$34579) -> 310.5 | N12: =SUMIF('MPG Payment '!$E$3:$E$34579,'Shayak Income '!D12,'MPG Payment '!$J$3:$J$34579) -> 10255.82 | O12: =+M12*0.75 -> 232.875 | P12: =+M12*0.95 -> 294.975 | Q12: =SUMIF('MPG Payment '!$E$3:$E$34579,'Shayak Income '!D12,'MPG Payment '!$S$3:$S$34579) -> 181.65058 | R12: =+N12*3% -> 307.6746 | S12: =R12-P12 -> 12.6996 | T12: =M12*0.1 -> 31.05 | U12: =(((IF(K12="New",0,SUMIF('MPG Payment '!$E$3:$E$34579,'Shayak Income '!D12,'MPG Payment '!$AC$3:$AC$34579))))+0)+0 -> 257.30383 | V12: =ROUND((SUM(O12:Q12)-SUM(T12:U12)),0) -> 421 | W12: 421 | X12: 0 | Y12: =IFERROR(VLOOKUP(D12,'Monthly Deduction'!$M$2:$N$64,2,0),0) -> 0 | Z12: 0 | AA12: =IFERROR(VLOOKUP(D12,'Monthly Deduction'!A:B,2,0),0) -> 0 | AB12: =ROUND(IFERROR(V12-SUM(W12:AA12),0),0) -> 0 | AC12: =AB12 -> 0 | AD12: =ROUND(AB12-AC12,0) -> 0 | AE12: =IF(AC12<>0,"Yes","Release") -> Release | AG12: 0 | AH12: Non pouring | AI12: 0 | AK12: 0 | AL12: =COUNTIF(AK12:AK12,"=NA") -> 0 | AN12: =((MIN(IF(A12>0,MAX(N12*2%,1861),0),A12)))+0 -> 1861 | AO12: =SUMIF('MPG Payment '!E:E,'Shayak Income '!D12,'MPG Payment '!AJ:AJ) -> 0 | AP12: =W12 -> 421 | AQ12: =AO12+AP12 -> 421 | AS12: =B12-X12 -> 0
A13: =IFERROR(VLOOKUP(D13,'Monthly Deduction'!$I$3:$J$957,2,0),0) -> 0 | B13: =IFERROR(VLOOKUP(D13,'Monthly Deduction'!$E$3:$F$957,2,0),0) -> 0 | C13: =A13+B13 -> 0 | D13: 10010057 | E13: =VLOOKUP(D13,'MPG Payment '!$E$3:$G$498218,2,0) -> Manish Dairy | F13: =IFERROR(_xlfn.XLOOKUP(D13,'Monthly Deduction'!$I$3:$I$957,'Monthly Deduction'!$H$3:$H$957),0) -> 0 | G13: =VLOOKUP(D13,'MPG Payment '!$E$3:$G$334579,3,0) -> vlc | H13: =VLOOKUP(D13,'MPG Payment '!$E$3:$H$334579,4,0) -> Indirect | I13: =INDEX('MPG Payment '!$C:$C,MATCH('Shayak Income '!D13,'MPG Payment '!E:E,0)) -> 1001 | J13: =INDEX('MPG Payment '!$D:$D,MATCH('Shayak Income '!D13,'MPG Payment '!E:E,0)) -> Majhaul | K13: Old | L13: 45000 | M13: =SUMIF('MPG Payment '!$E$3:$E$34579,'Shayak Income '!D13,'MPG Payment '!$I$3:$I$34579) -> 43651.7 | N13: =SUMIF('MPG Payment '!$E$3:$E$34579,'Shayak Income '!D13,'MPG Payment '!$J$3:$J$34579) -> 1561069.5 | O13: =+M13*0.75 -> 32738.775 | P13: =+M13*0.95 -> 41469.115 | Q13: =SUMIF('MPG Payment '!$E$3:$E$34579,'Shayak Income '!D13,'MPG Payment '!$S$3:$S$34579) -> 0 | R13: =+N13*3% -> 46832.086 | S13: =R13-P13 -> 5362.9713 | T13: =M13*0.1 -> 4365.17 | U13: =(((IF(K13="New",0,SUMIF('MPG Payment '!$E$3:$E$34579,'Shayak Income '!D13,'MPG Payment '!$AC$3:$AC$34579))))+0)+0 -> 0 | V13: =ROUND((SUM(O13:Q13)-SUM(T13:U13)),0) -> 69843 | W13: =(((AN13-AO13)))+0 -> 0 | X13: =((MIN(IF(B13>0,MAX(N13*2%),0),B13)))+0 -> 0 | Y13: =IFERROR(VLOOKUP(D13,'Monthly Deduction'!$M$2:$N$64,2,0),0) -> 0 | Z13: 0 | AA13: =IFERROR(VLOOKUP(D13,'Monthly Deduction'!A:B,2,0),0) -> 0 | AB13: =ROUND(IFERROR(V13-SUM(W13:AA13),0),0) -> 69843 | AC13: 0 | AD13: =ROUND(AB13-AC13,0) -> 69843 | AE13: =IF(AC13<>0,"Yes","Release") -> Release | AG13: 0 | AI13: 0 | AK13: 15240.5 | AL13: =COUNTIF(AK13:AK13,"=NA") -> 0 | AN13: =((MIN(IF(A13>0,MAX(N13*2%,1861),0),A13)))+0 -> 0 | AO13: =SUMIF('MPG Payment '!E:E,'Shayak Income '!D13,'MPG Payment '!AJ:AJ) -> 0 | AP13: =W13 -> 0 | AQ13: =AO13+AP13 -> 0 | AS13: =B13-X13 -> 0
A14: =IFERROR(VLOOKUP(D14,'Monthly Deduction'!$I$3:$J$957,2,0),0) -> 46072.587 | B14: =IFERROR(VLOOKUP(D14,'Monthly Deduction'!$E$3:$F$957,2,0),0) -> 16599 | C14: =A14+B14 -> 62671.587 | D14: 10010076 | E14: =VLOOKUP(D14,'MPG Payment '!$E$3:$G$498218,2,0) -> Gomukh Bhith-02 | F14: =IFERROR(_xlfn.XLOOKUP(D14,'Monthly Deduction'!$I$3:$I$957,'Monthly Deduction'!$H$3:$H$957),0) -> 0 | G14: =VLOOKUP(D14,'MPG Payment '!$E$3:$G$334579,3,0) -> MPG | H14: =VLOOKUP(D14,'MPG Payment '!$E$3:$H$334579,4,0) -> Direct | I14: =INDEX('MPG Payment '!$C:$C,MATCH('Shayak Income '!D14,'MPG Payment '!E:E,0)) -> 1001 | J14: =INDEX('MPG Payment '!$D:$D,MATCH('Shayak Income '!D14,'MPG Payment '!E:E,0)) -> Majhaul | K14: Old | L14: 45471 | M14: =SUMIF('MPG Payment '!$E$3:$E$34579,'Shayak Income '!D14,'MPG Payment '!$I$3:$I$34579) -> 1377.5 | N14: =SUMIF('MPG Payment '!$E$3:$E$34579,'Shayak Income '!D14,'MPG Payment '!$J$3:$J$34579) -> 56156.066 | O14: =+M14*0.75 -> 1033.125 | P14: =+M14*0.95 -> 1308.625 | Q14: =SUMIF('MPG Payment '!$E$3:$E$34579,'Shayak Income '!D14,'MPG Payment '!$S$3:$S$34579) -> 0 | R14: =+N14*3% -> 1684.682 | S14: =R14-P14 -> 376.05698 | T14: =M14*0.1 -> 137.75 | U14: =(((IF(K14="New",0,SUMIF('MPG Payment '!$E$3:$E$34579,'Shayak Income '!D14,'MPG Payment '!$AC$3:$AC$34579))))+0)+0 -> 1086.5227 | V14: =ROUND((SUM(O14:Q14)-SUM(T14:U14)),0) -> 1117 | W14: 1117 | X14: 0 | Y14: 0 | Z14: 0 | AA14: =IFERROR(VLOOKUP(D14,'Monthly Deduction'!A:B,2,0),0) -> 0 | AB14: =ROUND(IFERROR(V14-SUM(W14:AA14),0),0) -> 0 | AC14: 0 | AD14: =ROUND(AB14-AC14,0) -> 0 | AE14: =IF(AC14<>0,"Yes","Release") -> Release | AG14: 0 | AI14: 0 | AK14: 721.2 | AL14: =COUNTIF(AK14:AK14,"=NA") -> 0 | AN14: =((MIN(IF(A14>0,MAX(N14*2%,1861),0),A14)))+0 -> 1861 | AO14: =SUMIF('MPG Payment '!E:E,'Shayak Income '!D14,'MPG Payment '!AJ:AJ) -> 0 | AP14: =W14 -> 1117 | AQ14: =AO14+AP14 -> 1117 | AS14: =B14-X14 -> 16599
A15: =IFERROR(VLOOKUP(D15,'Monthly Deduction'!$I$3:$J$957,2,0),0) -> 24636.831 | B15: =IFERROR(VLOOKUP(D15,'Monthly Deduction'!$E$3:$F$957,2,0),0) -> 25600 | C15: =A15+B15 -> 50236.831 | D15: 10010082 | E15: =VLOOKUP(D15,'MPG Payment '!$E$3:$G$498218,2,0) -> Gomukh Sharmatola Sahuri | F15: =IFERROR(_xlfn.XLOOKUP(D15,'Monthly Deduction'!$I$3:$I$957,'Monthly Deduction'!$H$3:$H$957),0) -> 0 | G15: =VLOOKUP(D15,'MPG Payment '!$E$3:$G$334579,3,0) -> MPG | H15: =VLOOKUP(D15,'MPG Payment '!$E$3:$H$334579,4,0) -> Direct | I15: =INDEX('MPG Payment '!$C:$C,MATCH('Shayak Income '!D15,'MPG Payment '!E:E,0)) -> 1001 | J15: =INDEX('MPG Payment '!$D:$D,MATCH('Shayak Income '!D15,'MPG Payment '!E:E,0)) -> Majhaul | K15: Old | L15: 45568 | M15: =SUMIF('MPG Payment '!$E$3:$E$34579,'Shayak Income '!D15,'MPG Payment '!$I$3:$I$34579) -> 4217.7 | N15: =SUMIF('MPG Payment '!$E$3:$E$34579,'Shayak Income '!D15,'MPG Payment '!$J$3:$J$34579) -> 161653.62 | O15: =+M15*0.75 -> 3163.275 | P15: =+M15*0.95 -> 4006.815 | Q15: =SUMIF('MPG Payment '!$E$3:$E$34579,'Shayak Income '!D15,'MPG Payment '!$S$3:$S$34579) -> 0 | R15: =+N15*3% -> 4849.6085 | S15: =R15-P15 -> 842.79346 | T15: =M15*0.1 -> 421.77 | U15: =(((IF(K15="New",0,SUMIF('MPG Payment '!$E$3:$E$34579,'Shayak Income '!D15,'MPG Payment '!$AC$3:$AC$34579))))+0)+0 -> 0 | V15: =ROUND((SUM(O15:Q15)-SUM(T15:U15)),0) -> 6748 | W15: =(((AN15-AO15)))+0 -> 3233.0723 | X15: 0 | Y15: =IFERROR(VLOOKUP(D15,'Monthly Deduction'!$M$2:$N$64,2,0),0) -> 0 | Z15: 0 | AA15: =IFERROR(VLOOKUP(D15,'Monthly Deduction'!A:B,2,0),0) -> 0 | AB15: =ROUND(IFERROR(V15-SUM(W15:AA15),0),0) -> 3515 | AC15: 0 | AD15: =ROUND(AB15-AC15,0) -> 3515 | AE15: =IF(AC15<>0,"Yes","Release") -> Release | AG15: 0 | AI15: 0 | AK15: 1098.4 | AL15: =COUNTIF(AK15:AK15,"=NA") -> 0 | AN15: =((MIN(IF(A15>0,MAX(N15*2%,1861),0),A15)))+0 -> 3233.0723 | AO15: =SUMIF('MPG Payment '!E:E,'Shayak Income '!D15,'MPG Payment '!AJ:AJ) -> 0 | AP15: =W15 -> 3233.0723 | AQ15: =AO15+AP15 -> 3233.0723 | AS15: =B15-X15 -> 25600
A16: =IFERROR(VLOOKUP(D16,'Monthly Deduction'!$I$3:$J$957,2,0),0) -> 0 | B16: =IFERROR(VLOOKUP(D16,'Monthly Deduction'!$E$3:$F$957,2,0),0) -> 0 | C16: =A16+B16 -> 0 | D16: 10010084 | E16: =VLOOKUP(D16,'MPG Payment '!$E$3:$G$498218,2,0) -> Sangat- Sanjeev Kumar | F16: =IFERROR(_xlfn.XLOOKUP(D16,'Monthly Deduction'!$I$3:$I$957,'Monthly Deduction'!$H$3:$H$957),0) -> 0 | G16: =VLOOKUP(D16,'MPG Payment '!$E$3:$G$334579,3,0) -> vlc | H16: =VLOOKUP(D16,'MPG Payment '!$E$3:$H$334579,4,0) -> Indirect | I16: =INDEX('MPG Payment '!$C:$C,MATCH('Shayak Income '!D16,'MPG Payment '!E:E,0)) -> 1001 | J16: =INDEX('MPG Payment '!$D:$D,MATCH('Shayak Income '!D16,'MPG Payment '!E:E,0)) -> Majhaul | K16: Old | L16: 45567 | M16: =SUMIF('MPG Payment '!$E$3:$E$34579,'Shayak Income '!D16,'MPG Payment '!$I$3:$I$34579) -> 695.8 | N16: =SUMIF('MPG Payment '!$E$3:$E$34579,'Shayak Income '!D16,'MPG Payment '!$J$3:$J$34579) -> 24056.155 | O16: =+M16*0.75 -> 521.85 | P16: =+M16*0.95 -> 661.01 | Q16: =SUMIF('MPG Payment '!$E$3:$E$34579,'Shayak Income '!D16,'MPG Payment '!$S$3:$S$34579) -> 0 | R16: =+N16*3% -> 721.68464 | S16: =R16-P16 -> 60.674641 | T16: =M16*0.1 -> 69.58 | U16: =(((IF(K16="New",0,SUMIF('MPG Payment '!$E$3:$E$34579,'Shayak Income '!D16,'MPG Payment '!$AC$3:$AC$34579))))+0)+-348 -> 1113.7438 | V16: =ROUND((SUM(O16:Q16)-SUM(T16:U16)),0) -> 0 | W16: 0 | X16: 0 | Y16: =IFERROR(VLOOKUP(D16,'Monthly Deduction'!$M$2:$N$64,2,0),0) -> 0 | Z16: 0 | AA16: =IFERROR(VLOOKUP(D16,'Monthly Deduction'!A:B,2,0),0) -> 0 | AB16: =ROUND(IFERROR(V16-SUM(W16:AA16),0),0) -> 0 | AC16: 0 | AD16: =ROUND(AB16-AC16,0) -> 0 | AE16: =IF(AC16<>0,"Yes","Release") -> Release | AG16: 0 | AI16: 0 | AK16: 212.4 | AL16: =COUNTIF(AK16:AK16,"=NA") -> 0 | AN16: =((MIN(IF(A16>0,MAX(N16*2%,1861),0),A16)))+0 -> 0 | AO16: =SUMIF('MPG Payment '!E:E,'Shayak Income '!D16,'MPG Payment '!AJ:AJ) -> 0 | AP16: =W16 -> 0 | AQ16: =AO16+AP16 -> 0 | AS16: =B16-X16 -> 0
A17: =IFERROR(VLOOKUP(D17,'Monthly Deduction'!$I$3:$J$957,2,0),0) -> 69596 | B17: =IFERROR(VLOOKUP(D17,'Monthly Deduction'!$E$3:$F$957,2,0),0) -> 6400 | C17: =A17+B17 -> 75996 | D17: 10010086 | E17: =VLOOKUP(D17,'MPG Payment '!$E$3:$G$498218,2,0) -> Gomukh Garhi Bisanpur | F17: =IFERROR(_xlfn.XLOOKUP(D17,'Monthly Deduction'!$I$3:$I$957,'Monthly Deduction'!$H$3:$H$957),0) -> 0 | G17: =VLOOKUP(D17,'MPG Payment '!$E$3:$G$334579,3,0) -> MPG | H17: =VLOOKUP(D17,'MPG Payment '!$E$3:$H$334579,4,0) -> Direct | I17: =INDEX('MPG Payment '!$C:$C,MATCH('Shayak Income '!D17,'MPG Payment '!E:E,0)) -> 1058 | J17: =INDEX('MPG Payment '!$D:$D,MATCH('Shayak Income '!D17,'MPG Payment '!E:E,0)) -> Hasanpur | K17: Old | L17: 45631 | M17: =SUMIF('MPG Payment '!$E$3:$E$34579,'Shayak Income '!D17,'MPG Payment '!$I$3:$I$34579) -> 667.8 | N17: =SUMIF('MPG Payment '!$E$3:$E$34579,'Shayak Income '!D17,'MPG Payment '!$J$3:$J$34579) -> 27120.529 | O17: =+M17*0.75 -> 500.85 | P17: =+M17*0.95 -> 634.41 | Q17: =SUMIF('MPG Payment '!$E$3:$E$34579,'Shayak Income '!D17,'MPG Payment '!$S$3:$S$34579) -> 687.72875 | R17: =+N17*3% -> 813.61586 | S17: =R17-P17 -> 179.20586 | T17: =M17*0.1 -> 66.78 | U17: =(((IF(K17="New",0,SUMIF('MPG Payment '!$E$3:$E$34579,'Shayak Income '!D17,'MPG Payment '!$AC$3:$AC$34579))))+0)+0 -> 1730.2541 | V17: =ROUND((SUM(O17:Q17)-SUM(T17:U17)),0) -> 26 | W17: 26 | X17: 0 | Y17: =IFERROR(VLOOKUP(D17,'Monthly Deduction'!$M$2:$N$64,2,0),0) -> 0 | Z17: 0 | AA17: =IFERROR(VLOOKUP(D17,'Monthly Deduction'!A:B,2,0),0) -> 0 | AB17: =ROUND(IFERROR(V17-SUM(W17:AA17),0),0) -> 0 | AC17: 0 | AD17: =ROUND(AB17-AC17,0) -> 0 | AE17: =IF(AC17<>0,"Yes","Release") -> Release | AG17: 0 | AI17: 0 | AK17: 171.9 | AL17: =COUNTIF(AK17:AK17,"=NA") -> 0 | AN17: =((MIN(IF(A17>0,MAX(N17*2%,1861),0),A17)))+0 -> 1861 | AO17: =SUMIF('MPG Payment '!E:E,'Shayak Income '!D17,'MPG Payment '!AJ:AJ) -> 500 | AP17: =W17 -> 26 | AQ17: =AO17+AP17 -> 526 | AS17: =B17-X17 -> 6400
A18: =IFERROR(VLOOKUP(D18,'Monthly Deduction'!$I$3:$J$957,2,0),0) -> 0 | B18: =IFERROR(VLOOKUP(D18,'Monthly Deduction'!$E$3:$F$957,2,0),0) -> 0 | C18: =A18+B18 -> 0 | D18: 10010087 | E18: =VLOOKUP(D18,'MPG Payment '!$E$3:$G$498218,2,0) -> Bagaraha-Gopal Yadav | F18: =IFERROR(_xlfn.XLOOKUP(D18,'Monthly Deduction'!$I$3:$I$957,'Monthly Deduction'!$H$3:$H$957),0) -> 0 | G18: =VLOOKUP(D18,'MPG Payment '!$E$3:$G$334579,3,0) -> vlc | H18: =VLOOKUP(D18,'MPG Payment '!$E$3:$H$334579,4,0) -> Indirect | I18: =INDEX('MPG Payment '!$C:$C,MATCH('Shayak Income '!D18,'MPG Payment '!E:E,0)) -> 1058 | J18: =INDEX('MPG Payment '!$D:$D,MATCH('Shayak Income '!D18,'MPG Payment '!E:E,0)) -> Hasanpur | K18: Old | L18: 45597 | M18: =SUMIF('MPG Payment '!$E$3:$E$34579,'Shayak Income '!D18,'MPG Payment '!$I$3:$I$34579) -> 369.2 | N18: =SUMIF('MPG Payment '!$E$3:$E$34579,'Shayak Income '!D18,'MPG Payment '!$J$3:$J$34579) -> 11256.47 | O18: =+M18*0.75 -> 276.9 | P18: =+M18*0.95 -> 350.74 | Q18: =SUMIF('MPG Payment '!$E$3:$E$34579,'Shayak Income '!D18,'MPG Payment '!$S$3:$S$34579) -> 0 | R18: =+N18*3% -> 337.6941 | S18: =R18-P18 -> -13.0459 | T18: =M18*0.1 -> 36.92 | U18: =(((IF(K18="New",0,SUMIF('MPG Payment '!$E$3:$E$34579,'Shayak Income '!D18,'MPG Payment '!$AC$3:$AC$34579))))+0)+-459 -> 590.61245 | V18: =ROUND((SUM(O18:Q18)-SUM(T18:U18)),0) -> 0 | W18: 0 | X18: 0 | Y18: =IFERROR(VLOOKUP(D18,'Monthly Deduction'!$M$2:$N$64,2,0),0) -> 0 | Z18: 0 | AA18: =IFERROR(VLOOKUP(D18,'Monthly Deduction'!A:B,2,0),0) -> 0 | AB18: =ROUND(IFERROR(V18-SUM(W18:AA18),0),0) -> 0 | AC18: =AB18 -> 0 | AD18: =ROUND(AB18-AC18,0) -> 0 | AE18: =IF(AC18<>0,"Yes","Release") -> Release | AG18: 0 | AH18: Non pouring | AI18: 0 | AK18: 0 | AL18: =COUNTIF(AK18:AK18,"=NA") -> 0 | AN18: =((MIN(IF(A18>0,MAX(N18*2%,1861),0),A18)))+0 -> 0 | AO18: =SUMIF('MPG Payment '!E:E,'Shayak Income '!D18,'MPG Payment '!AJ:AJ) -> 0 | AP18: =W18 -> 0 | AQ18: =AO18+AP18 -> 0 | AS18: =B18-X18 -> 0
A19: =IFERROR(VLOOKUP(D19,'Monthly Deduction'!$I$3:$J$957,2,0),0) -> 76509.047 | B19: =IFERROR(VLOOKUP(D19,'Monthly Deduction'!$E$3:$F$957,2,0),0) -> 12099 | C19: =A19+B19 -> 88608.047 | D19: 10010089 | E19: =VLOOKUP(D19,'MPG Payment '!$E$3:$G$498218,2,0) -> Gomukh Barkurwa | F19: =IFERROR(_xlfn.XLOOKUP(D19,'Monthly Deduction'!$I$3:$I$957,'Monthly Deduction'!$H$3:$H$957),0) -> 0 | G19: =VLOOKUP(D19,'MPG Payment '!$E$3:$G$334579,3,0) -> MPG | H19: =VLOOKUP(D19,'MPG Payment '!$E$3:$H$334579,4,0) -> Direct | I19: =INDEX('MPG Payment '!$C:$C,MATCH('Shayak Income '!D19,'MPG Payment '!E:E,0)) -> 1058 | J19: =INDEX('MPG Payment '!$D:$D,MATCH('Shayak Income '!D19,'MPG Payment '!E:E,0)) -> Hasanpur | K19: Old | L19: 45627 | M19: =SUMIF('MPG Payment '!$E$3:$E$34579,'Shayak Income '!D19,'MPG Payment '!$I$3:$I$34579) -> 1480.6 | N19: =SUMIF('MPG Payment '!$E$3:$E$34579,'Shayak Income '!D19,'MPG Payment '!$J$3:$J$34579) -> 54697.528 | O19: =+M19*0.75 -> 1110.45 | P19: =+M19*0.95 -> 1406.57 | Q19: =SUMIF('MPG Payment '!$E$3:$E$34579,'Shayak Income '!D19,'MPG Payment '!$S$3:$S$34579) -> 1025.9872 | R19: =+N19*3% -> 1640.9258 | S19: =R19-P19 -> 234.35584 | T19: =M19*0.1 -> 148.06 | U19: =(((IF(K19="New",0,SUMIF('MPG Payment '!$E$3:$E$34579,'Shayak Income '!D19,'MPG Payment '!$AC$3:$AC$34579))))+0)+0 -> 970.92356 | V19: =ROUND((SUM(O19:Q19)-SUM(T19:U19)),0) -> 2424 | W19: =(((AN19-AO19)))+0 -> 1861 | X19: 0 | Y19: =IFERROR(VLOOKUP(D19,'Monthly Deduction'!$M$2:$N$64,2,0),0) -> 0 | Z19: 0 | AA19: =IFERROR(VLOOKUP(D19,'Monthly Deduction'!A:B,2,0),0) -> 0 | AB19: =ROUND(IFERROR(V19-SUM(W19:AA19),0),0) -> 563 | AC19: 0 | AD19: =ROUND(AB19-AC19,0) -> 563 | AE19: =IF(AC19<>0,"Yes","Release") -> Release | AG19: 0 | AI19: 0 | AK19: 385 | AL19: =COUNTIF(AK19:AK19,"=NA") -> 0 | AN19: =((MIN(IF(A19>0,MAX(N19*2%,1861),0),A19)))+0 -> 1861 | AO19: =SUMIF('MPG Payment '!E:E,'Shayak Income '!D19,'MPG Payment '!AJ:AJ) -> 0 | AP19: =W19 -> 1861 | AQ19: =AO19+AP19 -> 1861 | AS19: =B19-X19 -> 12099
A20: =IFERROR(VLOOKUP(D20,'Monthly Deduction'!$I$3:$J$957,2,0),0) -> 0 | B20: =IFERROR(VLOOKUP(D20,'Monthly Deduction'!$E$3:$F$957,2,0),0) -> 0 | C20: =A20+B20 -> 0 | D20: 10010092 | E20: =VLOOKUP(D20,'MPG Payment '!$E$3:$G$498218,2,0) -> Kamla- Amarjeet | F20: =IFERROR(_xlfn.XLOOKUP(D20,'Monthly Deduction'!$I$3:$I$957,'Monthly Deduction'!$H$3:$H$957),0) -> 0 | G20: =VLOOKUP(D20,'MPG Payment '!$E$3:$G$334579,3,0) -> vlc | H20: =VLOOKUP(D20,'MPG Payment '!$E$3:$H$334579,4,0) -> Indirect | I20: =INDEX('MPG Payment '!$C:$C,MATCH('Shayak Income '!D20,'MPG Payment '!E:E,0)) -> 1001 | J20: =INDEX('MPG Payment '!$D:$D,MATCH('Shayak Income '!D20,'MPG Payment '!E:E,0)) -> Majhaul | K20: Old | L20: 45689 | M20: =SUMIF('MPG Payment '!$E$3:$E$34579,'Shayak Income '!D20,'MPG Payment '!$I$3:$I$34579) -> 2502.7 | N20: =SUMIF('MPG Payment '!$E$3:$E$34579,'Shayak Income '!D20,'MPG Payment '!$J$3:$J$34579) -> 80861.315 | O20: =+M20*0.75 -> 1877.025 | P20: =+M20*0.95 -> 2377.565 | Q20: =SUMIF('MPG Payment '!$E$3:$E$34579,'Shayak Income '!D20,'MPG Payment '!$S$3:$S$34579) -> 0 | R20: =+N20*3% -> 2425.8395 | S20: =R20-P20 -> 48.274456 | T20: =M20*0.1 -> 250.27 | U20: =(((IF(K20="New",0,SUMIF('MPG Payment '!$E$3:$E$34579,'Shayak Income '!D20,'MPG Payment '!$AC$3:$AC$34579))))+0)+0 -> 398.6475 | V20: =ROUND((SUM(O20:Q20)-SUM(T20:U20)),0) -> 3606 | W20: =(((AN20-AO20)))+0 -> 0 | X20: =((MIN(IF(B20>0,MAX(N20*2%),0),B20)))+0 -> 0 | Y20: =IFERROR(VLOOKUP(D20,'Monthly Deduction'!$M$2:$N$64,2,0),0) -> 0 | Z20: 0 | AA20: =IFERROR(VLOOKUP(D20,'Monthly Deduction'!A:B,2,0),0) -> 0 | AB20: =ROUND(IFERROR(V20-SUM(W20:AA20),0),0) -> 3606 | AC20: 0 | AD20: =ROUND(AB20-AC20,0) -> 3606 | AE20: =IF(AC20<>0,"Yes","Release") -> Release | AG20: 0 | AI20: 0 | AK20: 924.6 | AL20: =COUNTIF(AK20:AK20,"=NA") -> 0 | AN20: =((MIN(IF(A20>0,MAX(N20*2%,1861),0),A20)))+0 -> 0 | AO20: =SUMIF('MPG Payment '!E:E,'Shayak Income '!D20,'MPG Payment '!AJ:AJ) -> 0 | AP20: =W20 -> 0 | AQ20: =AO20+AP20 -> 0 | AS20: =B20-X20 -> 0
A21: =IFERROR(VLOOKUP(D21,'Monthly Deduction'!$I$3:$J$957,2,0),0) -> 74949 | B21: =IFERROR(VLOOKUP(D21,'Monthly Deduction'!$E$3:$F$957,2,0),0) -> 3016.2028 | C21: =A21+B21 -> 77965.203 | D21: 10010095 | E21: =VLOOKUP(D21,'MPG Payment '!$E$3:$G$498218,2,0) -> Gomukh Goha-02 | F21: =IFERROR(_xlfn.XLOOKUP(D21,'Monthly Deduction'!$I$3:$I$957,'Monthly Deduction'!$H$3:$H$957),0) -> 0 | G21: =VLOOKUP(D21,'MPG Payment '!$E$3:$G$334579,3,0) -> MPG | H21: =VLOOKUP(D21,'MPG Payment '!$E$3:$H$334579,4,0) -> Direct | I21: =INDEX('MPG Payment '!$C:$C,MATCH('Shayak Income '!D21,'MPG Payment '!E:E,0)) -> 1058 | J21: =INDEX('MPG Payment '!$D:$D,MATCH('Shayak Income '!D21,'MPG Payment '!E:E,0)) -> Hasanpur | K21: Old | L21: 45700 | M21: =SUMIF('MPG Payment '!$E$3:$E$34579,'Shayak Income '!D21,'MPG Payment '!$I$3:$I$34579) -> 1413.8 | N21: =SUMIF('MPG Payment '!$E$3:$E$34579,'Shayak Income '!D21,'MPG Payment '!$J$3:$J$34579) -> 56374.5 | O21: =+M21*0.75 -> 1060.35 | P21: =+M21*0.95 -> 1343.11 | Q21: =SUMIF('MPG Payment '!$E$3:$E$34579,'Shayak Income '!D21,'MPG Payment '!$S$3:$S$34579) -> 613.81683 | R21: =+N21*3% -> 1691.235 | S21: =R21-P21 -> 348.12501 | T21: =M21*0.1 -> 141.38 | U21: =(((IF(K21="New",0,SUMIF('MPG Payment '!$E$3:$E$34579,'Shayak Income '!D21,'MPG Payment '!$AC$3:$AC$34579))))+0)+0 -> 1108.3637 | V21: =ROUND((SUM(O21:Q21)-SUM(T21:U21)),0) -> 1768 | W21: 1768 | X21: 0 | Y21: =IFERROR(VLOOKUP(D21,'Monthly Deduction'!$M$2:$N$64,2,0),0) -> 0 | Z21: 0 | AA21: =IFERROR(VLOOKUP(D21,'Monthly Deduction'!A:B,2,0),0) -> 0 | AB21: =ROUND(IFERROR(V21-SUM(W21:AA21),0),0) -> 0 | AC21: 0 | AD21: =ROUND(AB21-AC21,0) -> 0 | AE21: =IF(AC21<>0,"Yes","Release") -> Release | AG21: 0 | AI21: 0 | AK21: 364.8 | AL21: =COUNTIF(AK21:AK21,"=NA") -> 0 | AN21: =((MIN(IF(A21>0,MAX(N21*2%,1861),0),A21)))+0 -> 1861 | AO21: =SUMIF('MPG Payment '!E:E,'Shayak Income '!D21,'MPG Payment '!AJ:AJ) -> 0 | AP21: =W21 -> 1768 | AQ21: =AO21+AP21 -> 1768 | AS21: =B21-X21 -> 3016.2028
A22: =IFERROR(VLOOKUP(D22,'Monthly Deduction'!$I$3:$J$957,2,0),0) -> 53294.033 | B22: =IFERROR(VLOOKUP(D22,'Monthly Deduction'!$E$3:$F$957,2,0),0) -> 1290.9666 | C22: =A22+B22 -> 54584.999 | D22: 10010097 | E22: =VLOOKUP(D22,'MPG Payment '!$E$3:$G$498218,2,0) -> Gomukh Cheria Bariarpur | F22: =IFERROR(_xlfn.XLOOKUP(D22,'Monthly Deduction'!$I$3:$I$957,'Monthly Deduction'!$H$3:$H$957),0) -> 0 | G22: =VLOOKUP(D22,'MPG Payment '!$E$3:$G$334579,3,0) -> MPG | H22: =VLOOKUP(D22,'MPG Payment '!$E$3:$H$334579,4,0) -> Direct | I22: =INDEX('MPG Payment '!$C:$C,MATCH('Shayak Income '!D22,'MPG Payment '!E:E,0)) -> 1001 | J22: =INDEX('MPG Payment '!$D:$D,MATCH('Shayak Income '!D22,'MPG Payment '!E:E,0)) -> Majhaul | K22: Old | L22: 45708 | M22: =SUMIF('MPG Payment '!$E$3:$E$34579,'Shayak Income '!D22,'MPG Payment '!$I$3:$I$34579) -> 5359.2 | N22: =SUMIF('MPG Payment '!$E$3:$E$34579,'Shayak Income '!D22,'MPG Payment '!$J$3:$J$34579) -> 202797.15 | O22: =+M22*0.75 -> 4019.4 | P22: =+M22*0.95 -> 5091.24 | Q22: =SUMIF('MPG Payment '!$E$3:$E$34579,'Shayak Income '!D22,'MPG Payment '!$S$3:$S$34579) -> 268.4937 | R22: =+N22*3% -> 6083.9145 | S22: =R22-P22 -> 992.67455 | T22: =M22*0.1 -> 535.92 | U22: =(((IF(K22="New",0,SUMIF('MPG Payment '!$E$3:$E$34579,'Shayak Income '!D22,'MPG Payment '!$AC$3:$AC$34579))))+0)+0 -> 0 | V22: =ROUND((SUM(O22:Q22)-SUM(T22:U22)),0) -> 8843 | W22: =(((AN22-AO22)))+0 -> 4055.943 | X22: 0 | Y22: =IFERROR(VLOOKUP(D22,'Monthly Deduction'!$M$2:$N$64,2,0),0) -> 0 | Z22: 0 | AA22: =IFERROR(VLOOKUP(D22,'Monthly Deduction'!A:B,2,0),0) -> 0 | AB22: =ROUND(IFERROR(V22-SUM(W22:AA22),0),0) -> 4787 | AC22: 0 | AD22: =ROUND(AB22-AC22,0) -> 4787 | AE22: =IF(AC22<>0,"Yes","Release") -> Release | AG22: 0 | AI22: 0 | AK22: 1354.1 | AL22: =COUNTIF(AK22:AK22,"=NA") -> 0 | AN22: =((MIN(IF(A22>0,MAX(N22*2%,1861),0),A22)))+0 -> 4055.943 | AO22: =SUMIF('MPG Payment '!E:E,'Shayak Income '!D22,'MPG Payment '!AJ:AJ) -> 0 | AP22: =W22 -> 4055.943 | AQ22: =AO22+AP22 -> 4055.943 | AS22: =B22-X22 -> 1290.9666
A23: =IFERROR(VLOOKUP(D23,'Monthly Deduction'!$I$3:$J$957,2,0),0) -> 65590.14 | B23: =IFERROR(VLOOKUP(D23,'Monthly Deduction'!$E$3:$F$957,2,0),0) -> 4832.8168 | C23: =A23+B23 -> 70422.957 | D23: 10010098 | E23: =VLOOKUP(D23,'MPG Payment '!$E$3:$G$498218,2,0) -> Gomukh Rahul Nagar | F23: =IFERROR(_xlfn.XLOOKUP(D23,'Monthly Deduction'!$I$3:$I$957,'Monthly Deduction'!$H$3:$H$957),0) -> 0 | G23: =VLOOKUP(D23,'MPG Payment '!$E$3:$G$334579,3,0) -> MPG | H23: =VLOOKUP(D23,'MPG Payment '!$E$3:$H$334579,4,0) -> Direct | I23: =INDEX('MPG Payment '!$C:$C,MATCH('Shayak Income '!D23,'MPG Payment '!E:E,0)) -> 1058 | J23: =INDEX('MPG Payment '!$D:$D,MATCH('Shayak Income '!D23,'MPG Payment '!E:E,0)) -> Hasanpur | K23: Old | L23: 45700 | M23: =SUMIF('MPG Payment '!$E$3:$E$34579,'Shayak Income '!D23,'MPG Payment '!$I$3:$I$34579) -> 1460.8 | N23: =SUMIF('MPG Payment '!$E$3:$E$34579,'Shayak Income '!D23,'MPG Payment '!$J$3:$J$34579) -> 54507.871 | O23: =+M23*0.75 -> 1095.6 | P23: =+M23*0.95 -> 1387.76 | Q23: =SUMIF('MPG Payment '!$E$3:$E$34579,'Shayak Income '!D23,'MPG Payment '!$S$3:$S$34579) -> 918.93757 | R23: =+N23*3% -> 1635.2361 | S23: =R23-P23 -> 247.47614 | T23: =M23*0.1 -> 146.08 | U23: =(((IF(K23="New",0,SUMIF('MPG Payment '!$E$3:$E$34579,'Shayak Income '!D23,'MPG Payment '!$AC$3:$AC$34579))))+0)+0 -> 999.94029 | V23: =ROUND((SUM(O23:Q23)-SUM(T23:U23)),0) -> 2256 | W23: =(((AN23-AO23)))+0 -> 1861 | X23: 0 | Y23: =IFERROR(VLOOKUP(D23,'Monthly Deduction'!$M$2:$N$64,2,0),0) -> 0 | Z23: 0 | AA23: =IFERROR(VLOOKUP(D23,'Monthly Deduction'!A:B,2,0),0) -> 0 | AB23: =ROUND(IFERROR(V23-SUM(W23:AA23),0),0) -> 395 | AC23: =AB23 -> 395 | AD23: =ROUND(AB23-AC23,0) -> 0 | AE23: =IF(AC23<>0,"Yes","Release") -> Yes | AG23: 0 | AH23: Non pouring | AI23: 0 | AK23: 0 | AL23: =COUNTIF(AK23:AK23,"=NA") -> 0 | AN23: =((MIN(IF(A23>0,MAX(N23*2%,1861),0),A23)))+0 -> 1861 | AO23: =SUMIF('MPG Payment '!E:E,'Shayak Income '!D23,'MPG Payment '!AJ:AJ) -> 0 | AP23: =W23 -> 1861 | AQ23: =AO23+AP23 -> 1861 | AS23: =B23-X23 -> 4832.8168
A24: =IFERROR(VLOOKUP(D24,'Monthly Deduction'!$I$3:$J$957,2,0),0) -> 71985 | B24: =IFERROR(VLOOKUP(D24,'Monthly Deduction'!$E$3:$F$957,2,0),0) -> 0 | C24: =A24+B24 -> 71985 | D24: 10010099 | E24: =VLOOKUP(D24,'MPG Payment '!$E$3:$G$498218,2,0) -> Gomukh Bagraha-01 | F24: =IFERROR(_xlfn.XLOOKUP(D24,'Monthly Deduction'!$I$3:$I$957,'Monthly Deduction'!$H$3:$H$957),0) -> 0 | G24: =VLOOKUP(D24,'MPG Payment '!$E$3:$G$334579,3,0) -> MPG | H24: =VLOOKUP(D24,'MPG Payment '!$E$3:$H$334579,4,0) -> Direct | I24: =INDEX('MPG Payment '!$C:$C,MATCH('Shayak Income '!D24,'MPG Payment '!E:E,0)) -> 1058 | J24: =INDEX('MPG Payment '!$D:$D,MATCH('Shayak Income '!D24,'MPG Payment '!E:E,0)) -> Hasanpur | K24: Old | L24: 45736 | M24: =SUMIF('MPG Payment '!$E$3:$E$34579,'Shayak Income '!D24,'MPG Payment '!$I$3:$I$34579) -> 465.4 | N24: =SUMIF('MPG Payment '!$E$3:$E$34579,'Shayak Income '!D24,'MPG Payment '!$J$3:$J$34579) -> 20751.825 | O24: =+M24*0.75 -> 349.05 | P24: =+M24*0.95 -> 442.13 | Q24: =SUMIF('MPG Payment '!$E$3:$E$34579,'Shayak Income '!D24,'MPG Payment '!$S$3:$S$34579) -> 205.92554 | R24: =+N24*3% -> 622.55476 | S24: =R24-P24 -> 180.42476 | T24: =M24*0.1 -> 46.54 | U24: =(((IF(K24="New",0,SUMIF('MPG Payment '!$E$3:$E$34579,'Shayak Income '!D24,'MPG Payment '!$AC$3:$AC$34579))))+0)+-1146 -> 951.06353 | V24: =ROUND((SUM(O24:Q24)-SUM(T24:U24)),0) -> 0 | W24: 0 | X24: 0 | Y24: =IFERROR(VLOOKUP(D24,'Monthly Deduction'!$M$2:$N$64,2,0),0) -> 0 | Z24: 0 | AA24: =IFERROR(VLOOKUP(D24,'Monthly Deduction'!A:B,2,0),0) -> 0 | AB24: =ROUND(IFERROR(V24-SUM(W24:AA24),0),0) -> 0 | AC24: 0 | AD24: =ROUND(AB24-AC24,0) -> 0 | AE24: =IF(AC24<>0,"Yes","Release") -> Release | AG24: 0 | AI24: 0 | AK24: 201.8 | AL24: =COUNTIF(AK24:AK24,"=NA") -> 0 | AN24: =((MIN(IF(A24>0,MAX(N24*2%,1861),0),A24)))+0 -> 1861 | AO24: =SUMIF('MPG Payment '!E:E,'Shayak Income '!D24,'MPG Payment '!AJ:AJ) -> 500 | AP24: =W24 -> 0 | AQ24: =AO24+AP24 -> 500 | AS24: =B24-X24 -> 0
A25: =IFERROR(VLOOKUP(D25,'Monthly Deduction'!$I$3:$J$957,2,0),0) -> 67263.302 | B25: =IFERROR(VLOOKUP(D25,'Monthly Deduction'!$E$3:$F$957,2,0),0) -> 6400 | C25: =A25+B25 -> 73663.302 | D25: 10010103 | E25: =VLOOKUP(D25,'MPG Payment '!$E$3:$G$498218,2,0) -> Gomukh Shobhaipura | F25: =IFERROR(_xlfn.XLOOKUP(D25,'Monthly Deduction'!$I$3:$I$957,'Monthly Deduction'!$H$3:$H$957),0) -> 0 | G25: =VLOOKUP(D25,'MPG Payment '!$E$3:$G$334579,3,0) -> MPG | H25: =VLOOKUP(D25,'MPG Payment '!$E$3:$H$334579,4,0) -> Direct | I25: =INDEX('MPG Payment '!$C:$C,MATCH('Shayak Income '!D25,'MPG Payment '!E:E,0)) -> 1058 | J25: =INDEX('MPG Payment '!$D:$D,MATCH('Shayak Income '!D25,'MPG Payment '!E:E,0)) -> Hasanpur | K25: Old | L25: 45737 | M25: =SUMIF('MPG Payment '!$E$3:$E$34579,'Shayak Income '!D25,'MPG Payment '!$I$3:$I$34579) -> 20.3 | N25: =SUMIF('MPG Payment '!$E$3:$E$34579,'Shayak Income '!D25,'MPG Payment '!$J$3:$J$34579) -> 753.82 | O25: =+M25*0.75 -> 15.225 | P25: =+M25*0.95 -> 19.285 | Q25: =SUMIF('MPG Payment '!$E$3:$E$34579,'Shayak Income '!D25,'MPG Payment '!$S$3:$S$34579) -> 0 | R25: =+N25*3% -> 22.6146 | S25: =R25-P25 -> 3.3296 | T25: =M25*0.1 -> 2.03 | U25: =(((IF(K25="New",0,SUMIF('MPG Payment '!$E$3:$E$34579,'Shayak Income '!D25,'MPG Payment '!$AC$3:$AC$34579))))+0)+-472 -> 32.799462 | V25: =ROUND((SUM(O25:Q25)-SUM(T25:U25)),0) -> 0 | W25: 0 | X25: 0 | Y25: =IFERROR(VLOOKUP(D25,'Monthly Deduction'!$M$2:$N$64,2,0),0) -> 0 | Z25: 0 | AA25: =IFERROR(VLOOKUP(D25,'Monthly Deduction'!A:B,2,0),0) -> 0 | AB25: =ROUND(IFERROR(V25-SUM(W25:AA25),0),0) -> 0 | AC25: =AB25 -> 0 | AD25: =ROUND(AB25-AC25,0) -> 0 | AE25: =IF(AC25<>0,"Yes","Release") -> Release | AG25: 0 | AH25: Non pouring | AI25: 0 | AK25: 0 | AL25: =COUNTIF(AK25:AK25,"=NA") -> 0 | AN25: =((MIN(IF(A25>0,MAX(N25*2%,1861),0),A25)))+0 -> 1861 | AO25: =SUMIF('MPG Payment '!E:E,'Shayak Income '!D25,'MPG Payment '!AJ:AJ) -> 0 | AP25: =W25 -> 0 | AQ25: =AO25+AP25 -> 0 | AS25: =B25-X25 -> 6400
A26: =IFERROR(VLOOKUP(D26,'Monthly Deduction'!$I$3:$J$957,2,0),0) -> 91249 | B26: =IFERROR(VLOOKUP(D26,'Monthly Deduction'!$E$3:$F$957,2,0),0) -> 0 | C26: =A26+B26 -> 91249 | D26: 10010108 | E26: =VLOOKUP(D26,'MPG Payment '!$E$3:$G$498218,2,0) -> Gomukh Pirauna | F26: =IFERROR(_xlfn.XLOOKUP(D26,'Monthly Deduction'!$I$3:$I$957,'Monthly Deduction'!$H$3:$H$957),0) -> 0 | G26: =VLOOKUP(D26,'MPG Payment '!$E$3:$G$334579,3,0) -> MPG | H26: =VLOOKUP(D26,'MPG Payment '!$E$3:$H$334579,4,0) -> Direct | I26: =INDEX('MPG Payment '!$C:$C,MATCH('Shayak Income '!D26,'MPG Payment '!E:E,0)) -> 1001 | J26: =INDEX('MPG Payment '!$D:$D,MATCH('Shayak Income '!D26,'MPG Payment '!E:E,0)) -> Majhaul | K26: Old | L26: 45777 | M26: =SUMIF('MPG Payment '!$E$3:$E$34579,'Shayak Income '!D26,'MPG Payment '!$I$3:$I$34579) -> 619.2 | N26: =SUMIF('MPG Payment '!$E$3:$E$34579,'Shayak Income '!D26,'MPG Payment '!$J$3:$J$34579) -> 22612.027 | O26: =+M26*0.75 -> 464.4 | P26: =+M26*0.95 -> 588.24 | Q26: =SUMIF('MPG Payment '!$E$3:$E$34579,'Shayak Income '!D26,'MPG Payment '!$S$3:$S$34579) -> 249.45331 | R26: =+N26*3% -> 678.36081 | S26: =R26-P26 -> 90.120806 | T26: =M26*0.1 -> 61.92 | U26: =(((IF(K26="New",0,SUMIF('MPG Payment '!$E$3:$E$34579,'Shayak Income '!D26,'MPG Payment '!$AC$3:$AC$34579))))+0)+-332 -> 1240.5158 | V26: =ROUND((SUM(O26:Q26)-SUM(T26:U26)),0) -> 0 | W26: 0 | X26: 0 | Y26: =IFERROR(VLOOKUP(D26,'Monthly Deduction'!$M$2:$N$64,2,0),0) -> 0 | Z26: 0 | AA26: 0 | AB26: =ROUND(IFERROR(V26-SUM(W26:AA26),0),0) -> 0 | AC26: =AB26 -> 0 | AD26: =ROUND(AB26-AC26,0) -> 0 | AE26: =IF(AC26<>0,"Yes","Release") -> Release | AG26: 0 | AH26: Down Payment / Agreement issue | AI26: 9803 | AK26: 280.3 | AL26: =COUNTIF(AK26:AK26,"=NA") -> 0 | AN26: =((MIN(IF(A26>0,MAX(N26*2%,1861),0),A26)))+0 -> 1861 | AO26: =SUMIF('MPG Payment '!E:E,'Shayak Income '!D26,'MPG Payment '!AJ:AJ) -> 500 | AP26: =W26 -> 0 | AQ26: =AO26+AP26 -> 500 | AS26: =B26-X26 -> 0
A27: =IFERROR(VLOOKUP(D27,'Monthly Deduction'!$I$3:$J$957,2,0),0) -> 0 | B27: =IFERROR(VLOOKUP(D27,'Monthly Deduction'!$E$3:$F$957,2,0),0) -> 0 | C27: =A27+B27 -> 0 | D27: 10010109 | E27: =VLOOKUP(D27,'MPG Payment '!$E$3:$G$498218,2,0) -> Parra- Nagendra Kumar | F27: =IFERROR(_xlfn.XLOOKUP(D27,'Monthly Deduction'!$I$3:$I$957,'Monthly Deduction'!$H$3:$H$957),0) -> 0 | G27: =VLOOKUP(D27,'MPG Payment '!$E$3:$G$334579,3,0) -> vlc | H27: =VLOOKUP(D27,'MPG Payment '!$E$3:$H$334579,4,0) -> Indirect | I27: =INDEX('MPG Payment '!$C:$C,MATCH('Shayak Income '!D27,'MPG Payment '!E:E,0)) -> 1001 | J27: =INDEX('MPG Payment '!$D:$D,MATCH('Shayak Income '!D27,'MPG Payment '!E:E,0)) -> Majhaul | K27: Old | L27: 45777 | M27: =SUMIF('MPG Payment '!$E$3:$E$34579,'Shayak Income '!D27,'MPG Payment '!$I$3:$I$34579) -> 1161 | N27: =SUMIF('MPG Payment '!$E$3:$E$34579,'Shayak Income '!D27,'MPG Payment '!$J$3:$J$34579) -> 39071.586 | O27: =+M27*0.75 -> 870.75 | P27: =+M27*0.95 -> 1102.95 | Q27: =SUMIF('MPG Payment '!$E$3:$E$34579,'Shayak Income '!D27,'MPG Payment '!$S$3:$S$34579) -> 0 | R27: =+N27*3% -> 1172.1476 | S27: =R27-P27 -> 69.197579 | T27: =M27*0.1 -> 116.1 | U27: =(((IF(K27="New",0,SUMIF('MPG Payment '!$E$3:$E$34579,'Shayak Income '!D27,'MPG Payment '!$AC$3:$AC$34579))))+0)+0 -> 1102.2143 | V27: =ROUND((SUM(O27:Q27)-SUM(T27:U27)),0) -> 755 | W27: =(((AN27-AO27)))+0 -> 0 | X27: =((MIN(IF(B27>0,MAX(N27*2%),0),B27)))+0 -> 0 | Y27: =IFERROR(VLOOKUP(D27,'Monthly Deduction'!$M$2:$N$64,2,0),0) -> 0 | Z27: 0 | AA27: =IFERROR(VLOOKUP(D27,'Monthly Deduction'!A:B,2,0),0) -> 0 | AB27: =ROUND(IFERROR(V27-SUM(W27:AA27),0),0) -> 755 | AC27: 0 | AD27: =ROUND(AB27-AC27,0) -> 755 | AE27: =IF(AC27<>0,"Yes","Release") -> Release | AG27: 0 | AI27: 0 | AK27: 285.5 | AL27: =COUNTIF(AK27:AK27,"=NA") -> 0 | AN27: =((MIN(IF(A27>0,MAX(N27*2%,1861),0),A27)))+0 -> 0 | AO27: =SUMIF('MPG Payment '!E:E,'Shayak Income '!D27,'MPG Payment '!AJ:AJ) -> 0 | AP27: =W27 -> 0 | AQ27: =AO27+AP27 -> 0 | AS27: =B27-X27 -> 0
A28: =IFERROR(VLOOKUP(D28,'Monthly Deduction'!$I$3:$J$957,2,0),0) -> 83878.195 | B28: =IFERROR(VLOOKUP(D28,'Monthly Deduction'!$E$3:$F$957,2,0),0) -> 0 | C28: =A28+B28 -> 83878.195 | D28: 10010113 | E28: =VLOOKUP(D28,'MPG Payment '!$E$3:$G$498218,2,0) -> Gomukh Basahi | F28: =IFERROR(_xlfn.XLOOKUP(D28,'Monthly Deduction'!$I$3:$I$957,'Monthly Deduction'!$H$3:$H$957),0) -> 0 | G28: =VLOOKUP(D28,'MPG Payment '!$E$3:$G$334579,3,0) -> MPG | H28: =VLOOKUP(D28,'MPG Payment '!$E$3:$H$334579,4,0) -> Direct | I28: =INDEX('MPG Payment '!$C:$C,MATCH('Shayak Income '!D28,'MPG Payment '!E:E,0)) -> 1001 | J28: =INDEX('MPG Payment '!$D:$D,MATCH('Shayak Income '!D28,'MPG Payment '!E:E,0)) -> Majhaul | K28: Old | L28: 45810 | M28: =SUMIF('MPG Payment '!$E$3:$E$34579,'Shayak Income '!D28,'MPG Payment '!$I$3:$I$34579) -> 3226.1 | N28: =SUMIF('MPG Payment '!$E$3:$E$34579,'Shayak Income '!D28,'MPG Payment '!$J$3:$J$34579) -> 127677.23 | O28: =+M28*0.75 -> 2419.575 | P28: =+M28*0.95 -> 3064.795 | Q28: =SUMIF('MPG Payment '!$E$3:$E$34579,'Shayak Income '!D28,'MPG Payment '!$S$3:$S$34579) -> 997.33556 | R28: =+N28*3% -> 3830.3169 | S28: =R28-P28 -> 765.52186 | T28: =M28*0.1 -> 322.61 | U28: =(((IF(K28="New",0,SUMIF('MPG Payment '!$E$3:$E$34579,'Shayak Income '!D28,'MPG Payment '!$AC$3:$AC$34579))))+0)+0 -> 0 | V28: =ROUND((SUM(O28:Q28)-SUM(T28:U28)),0) -> 6159 | W28: =(((AN28-AO28)))+0 -> 2553.5446 | X28: 0 | Y28: =IFERROR(VLOOKUP(D28,'Monthly Deduction'!$M$2:$N$64,2,0),0) -> 0 | Z28: 0 | AA28: =IFERROR(VLOOKUP(D28,'Monthly Deduction'!A:B,2,0),0) -> 0 | AB28: =ROUND(IFERROR(V28-SUM(W28:AA28),0),0) -> 3605 | AC28: 0 | AD28: =ROUND(AB28-AC28,0) -> 3605 | AE28: =IF(AC28<>0,"Yes","Release") -> Release | AG28: 0 | AI28: 0 | AK28: 858.7 | AL28: =COUNTIF(AK28:AK28,"=NA") -> 0 | AN28: =((MIN(IF(A28>0,MAX(N28*2%,1861),0),A28)))+0 -> 2553.5446 | AO28: =SUMIF('MPG Payment '!E:E,'Shayak Income '!D28,'MPG Payment '!AJ:AJ) -> 0 | AP28: =W28 -> 2553.5446 | AQ28: =AO28+AP28 -> 2553.5446 | AS28: =B28-X28 -> 0
A29: =IFERROR(VLOOKUP(D29,'Monthly Deduction'!$I$3:$J$957,2,0),0) -> 0 | B29: =IFERROR(VLOOKUP(D29,'Monthly Deduction'!$E$3:$F$957,2,0),0) -> 0 | C29: =A29+B29 -> 0 | D29: 10010116 | E29: =VLOOKUP(D29,'MPG Payment '!$E$3:$G$498218,2,0) -> Mohanpur- Mukesh Kumar | F29: =IFERROR(_xlfn.XLOOKUP(D29,'Monthly Deduction'!$I$3:$I$957,'Monthly Deduction'!$H$3:$H$957),0) -> 0 | G29: =VLOOKUP(D29,'MPG Payment '!$E$3:$G$334579,3,0) -> vlc | H29: =VLOOKUP(D29,'MPG Payment '!$E$3:$H$334579,4,0) -> Indirect | I29: =INDEX('MPG Payment '!$C:$C,MATCH('Shayak Income '!D29,'MPG Payment '!E:E,0)) -> 1001 | J29: =INDEX('MPG Payment '!$D:$D,MATCH('Shayak Income '!D29,'MPG Payment '!E:E,0)) -> Majhaul | K29: Old | L29: 45840 | M29: =SUMIF('MPG Payment '!$E$3:$E$34579,'Shayak Income '!D29,'MPG Payment '!$I$3:$I$34579) -> 2983.6 | N29: =SUMIF('MPG Payment '!$E$3:$E$34579,'Shayak Income '!D29,'MPG Payment '!$J$3:$J$34579) -> 110876.94 | O29: =+M29*0.75 -> 2237.7 | P29: =+M29*0.95 -> 2834.42 | Q29: =SUMIF('MPG Payment '!$E$3:$E$34579,'Shayak Income '!D29,'MPG Payment '!$S$3:$S$34579) -> 0 | R29: =+N29*3% -> 3326.3081 | S29: =R29-P29 -> 491.88811 | T29: =M29*0.1 -> 298.36 | U29: =(((IF(K29="New",0,SUMIF('MPG Payment '!$E$3:$E$34579,'Shayak Income '!D29,'MPG Payment '!$AC$3:$AC$34579))))+0)+0 -> 123.5131 | V29: =ROUND((SUM(O29:Q29)-SUM(T29:U29)),0) -> 4650 | W29: =(((AN29-AO29)))+0 -> 0 | X29: =((MIN(IF(B29>0,MAX(N29*2%),0),B29)))+0 -> 0 | Y29: =IFERROR(VLOOKUP(D29,'Monthly Deduction'!$M$2:$N$64,2,0),0) -> 0 | Z29: 0 | AA29: =IFERROR(VLOOKUP(D29,'Monthly Deduction'!A:B,2,0),0) -> 0 | AB29: =ROUND(IFERROR(V29-SUM(W29:AA29),0),0) -> 4650 | AC29: 0 | AD29: =ROUND(AB29-AC29,0) -> 4650 | AE29: =IF(AC29<>0,"Yes","Release") -> Release | AG29: 0 | AI29: 0 | AK29: 326.8 | AL29: =COUNTIF(AK29:AK29,"=NA") -> 0 | AN29: =((MIN(IF(A29>0,MAX(N29*2%,1861),0),A29)))+0 -> 0 | AO29: =SUMIF('MPG Payment '!E:E,'Shayak Income '!D29,'MPG Payment '!AJ:AJ) -> 0 | AP29: =W29 -> 0 | AQ29: =AO29+AP29 -> 0 | AS29: =B29-X29 -> 0
A30: =IFERROR(VLOOKUP(D30,'Monthly Deduction'!$I$3:$J$957,2,0),0) -> 51333.458 | B30: =IFERROR(VLOOKUP(D30,'Monthly Deduction'!$E$3:$F$957,2,0),0) -> 0 | C30: =A30+B30 -> 51333.458 | D30: 10010121 | E30: =VLOOKUP(D30,'MPG Payment '!$E$3:$G$498218,2,0) -> Gomukh Sawantpur | F30: =IFERROR(_xlfn.XLOOKUP(D30,'Monthly Deduction'!$I$3:$I$957,'Monthly Deduction'!$H$3:$H$957),0) -> 0 | G30: =VLOOKUP(D30,'MPG Payment '!$E$3:$G$334579,3,0) -> MPG | H30: =VLOOKUP(D30,'MPG Payment '!$E$3:$H$334579,4,0) -> Direct | I30: =INDEX('MPG Payment '!$C:$C,MATCH('Shayak Income '!D30,'MPG Payment '!E:E,0)) -> 1001 | J30: =INDEX('MPG Payment '!$D:$D,MATCH('Shayak Income '!D30,'MPG Payment '!E:E,0)) -> Majhaul | K30: Old | L30: 45842 | M30: =SUMIF('MPG Payment '!$E$3:$E$34579,'Shayak Income '!D30,'MPG Payment '!$I$3:$I$34579) -> 4589.5 | N30: =SUMIF('MPG Payment '!$E$3:$E$34579,'Shayak Income '!D30,'MPG Payment '!$J$3:$J$34579) -> 170904.69 | O30: =+M30*0.75 -> 3442.125 | P30: =+M30*0.95 -> 4360.025 | Q30: =SUMIF('MPG Payment '!$E$3:$E$34579,'Shayak Income '!D30,'MPG Payment '!$S$3:$S$34579) -> 794.37707 | R30: =+N30*3% -> 5127.1408 | S30: =R30-P30 -> 767.11575 | T30: =M30*0.1 -> 458.95 | U30: =(((IF(K30="New",0,SUMIF('MPG Payment '!$E$3:$E$34579,'Shayak Income '!D30,'MPG Payment '!$AC$3:$AC$34579))))+0)+0 -> 0 | V30: =ROUND((SUM(O30:Q30)-SUM(T30:U30)),0) -> 8138 | W30: =(((AN30-AO30)))+0 -> 3418.0938 | X30: 0 | Y30: =IFERROR(VLOOKUP(D30,'Monthly Deduction'!$M$2:$N$64,2,0),0) -> 0 | Z30: 0 | AA30: =IFERROR(VLOOKUP(D30,'Monthly Deduction'!A:B,2,0),0) -> 0 | AB30: =ROUND(IFERROR(V30-SUM(W30:AA30),0),0) -> 4720 | AC30: 0 | AD30: =ROUND(AB30-AC30,0) -> 4720 | AE30: =IF(AC30<>0,"Yes","Release") -> Release | AG30: 0 | AI30: 0 | AK30: 1551.6 | AL30: =COUNTIF(AK30:AK30,"=NA") -> 0 | AN30: =((MIN(IF(A30>0,MAX(N30*2%,1861),0),A30)))+0 -> 3418.0938 | AO30: =SUMIF('MPG Payment '!E:E,'Shayak Income '!D30,'MPG Payment '!AJ:AJ) -> 0 | AP30: =W30 -> 3418.0938 | AQ30: =AO30+AP30 -> 3418.0938 | AS30: =B30-X30 -> 0
A31: =IFERROR(VLOOKUP(D31,'Monthly Deduction'!$I$3:$J$957,2,0),0) -> 0 | B31: =IFERROR(VLOOKUP(D31,'Monthly Deduction'!$E$3:$F$957,2,0),0) -> 0 | C31: =A31+B31 -> 0 | D31: 10010125 | E31: =VLOOKUP(D31,'MPG Payment '!$E$3:$G$498218,2,0) -> Maida- Ram Kumar | F31: =IFERROR(_xlfn.XLOOKUP(D31,'Monthly Deduction'!$I$3:$I$957,'Monthly Deduction'!$H$3:$H$957),0) -> 0 | G31: =VLOOKUP(D31,'MPG Payment '!$E$3:$G$334579,3,0) -> vlc | H31: =VLOOKUP(D31,'MPG Payment '!$E$3:$H$334579,4,0) -> Indirect | I31: =INDEX('MPG Payment '!$C:$C,MATCH('Shayak Income '!D31,'MPG Payment '!E:E,0)) -> 1001 | J31: =INDEX('MPG Payment '!$D:$D,MATCH('Shayak Income '!D31,'MPG Payment '!E:E,0)) -> Majhaul | K31: Old | L31: 45869 | M31: =SUMIF('MPG Payment '!$E$3:$E$34579,'Shayak Income '!D31,'MPG Payment '!$I$3:$I$34579) -> 1231 | N31: =SUMIF('MPG Payment '!$E$3:$E$34579,'Shayak Income '!D31,'MPG Payment '!$J$3:$J$34579) -> 48227.967 | O31: =+M31*0.75 -> 923.25 | P31: =+M31*0.95 -> 1169.45 | Q31: =SUMIF('MPG Payment '!$E$3:$E$34579,'Shayak Income '!D31,'MPG Payment '!$S$3:$S$34579) -> 0 | R31: =+N31*3% -> 1446.839 | S31: =R31-P31 -> 277.389 | T31: =M31*0.1 -> 123.1 | U31: =(((IF(K31="New",0,SUMIF('MPG Payment '!$E$3:$E$34579,'Shayak Income '!D31,'MPG Payment '!$AC$3:$AC$34579))))+0)+0 -> 1167.939 | V31: =ROUND((SUM(O31:Q31)-SUM(T31:U31)),0) -> 802 | W31: =(((AN31-AO31)))+0 -> 0 | X31: =((MIN(IF(B31>0,MAX(N31*2%),0),B31)))+0 -> 0 | Y31: =IFERROR(VLOOKUP(D31,'Monthly Deduction'!$M$2:$N$64,2,0),0) -> 0 | Z31: 0 | AA31: =IFERROR(VLOOKUP(D31,'Monthly Deduction'!A:B,2,0),0) -> 0 | AB31: =ROUND(IFERROR(V31-SUM(W31:AA31),0),0) -> 802 | AC31: 0 | AD31: =ROUND(AB31-AC31,0) -> 802 | AE31: =IF(AC31<>0,"Yes","Release") -> Release | AG31: 0 | AI31: 0 | AK31: 717.1 | AL31: =COUNTIF(AK31:AK31,"=NA") -> 0 | AN31: =((MIN(IF(A31>0,MAX(N31*2%,1861),0),A31)))+0 -> 0 | AO31: =SUMIF('MPG Payment '!E:E,'Shayak Income '!D31,'MPG Payment '!AJ:AJ) -> 0 | AP31: =W31 -> 0 | AQ31: =AO31+AP31 -> 0 | AS31: =B31-X31 -> 0
A32: =IFERROR(VLOOKUP(D32,'Monthly Deduction'!$I$3:$J$957,2,0),0) -> 50054.763 | B32: =IFERROR(VLOOKUP(D32,'Monthly Deduction'!$E$3:$F$957,2,0),0) -> 0 | C32: =A32+B32 -> 50054.763 | D32: 10010128 | E32: =VLOOKUP(D32,'MPG Payment '!$E$3:$G$498218,2,0) -> Gomukh Aure Bikrampur | F32: =IFERROR(_xlfn.XLOOKUP(D32,'Monthly Deduction'!$I$3:$I$957,'Monthly Deduction'!$H$3:$H$957),0) -> 0 | G32: =VLOOKUP(D32,'MPG Payment '!$E$3:$G$334579,3,0) -> MPG | H32: =VLOOKUP(D32,'MPG Payment '!$E$3:$H$334579,4,0) -> Direct | I32: =INDEX('MPG Payment '!$C:$C,MATCH('Shayak Income '!D32,'MPG Payment '!E:E,0)) -> 1001 | J32: =INDEX('MPG Payment '!$D:$D,MATCH('Shayak Income '!D32,'MPG Payment '!E:E,0)) -> Majhaul | K32: Old | L32: 45869 | M32: =SUMIF('MPG Payment '!$E$3:$E$34579,'Shayak Income '!D32,'MPG Payment '!$I$3:$I$34579) -> 4687.5 | N32: =SUMIF('MPG Payment '!$E$3:$E$34579,'Shayak Income '!D32,'MPG Payment '!$J$3:$J$34579) -> 191106.92 | O32: =+M32*0.75 -> 3515.625 | P32: =+M32*0.95 -> 4453.125 | Q32: =SUMIF('MPG Payment '!$E$3:$E$34579,'Shayak Income '!D32,'MPG Payment '!$S$3:$S$34579) -> 44.648937 | R32: =+N32*3% -> 5733.2077 | S32: =R32-P32 -> 1280.0827 | T32: =M32*0.1 -> 468.75 | U32: =(((IF(K32="New",0,SUMIF('MPG Payment '!$E$3:$E$34579,'Shayak Income '!D32,'MPG Payment '!$AC$3:$AC$34579))))+0)+0 -> 0 | V32: =ROUND((SUM(O32:Q32)-SUM(T32:U32)),0) -> 7545 | W32: =(((AN32-AO32)))+0 -> 3822.1385 | X32: 0 | Y32: =IFERROR(VLOOKUP(D32,'Monthly Deduction'!$M$2:$N$64,2,0),0) -> 0 | Z32: 0 | AA32: =IFERROR(VLOOKUP(D32,'Monthly Deduction'!A:B,2,0),0) -> 0 | AB32: =ROUND(IFERROR(V32-SUM(W32:AA32),0),0) -> 3723 | AC32: 0 | AD32: =ROUND(AB32-AC32,0) -> 3723 | AE32: =IF(AC32<>0,"Yes","Release") -> Release | AG32: 0 | AI32: 0 | AK32: 1079 | AL32: =COUNTIF(AK32:AK32,"=NA") -> 0 | AN32: =((MIN(IF(A32>0,MAX(N32*2%,1861),0),A32)))+0 -> 3822.1385 | AO32: =SUMIF('MPG Payment '!E:E,'Shayak Income '!D32,'MPG Payment '!AJ:AJ) -> 0 | AP32: =W32 -> 3822.1385 | AQ32: =AO32+AP32 -> 3822.1385 | AS32: =B32-X32 -> 0
A33: =IFERROR(VLOOKUP(D33,'Monthly Deduction'!$I$3:$J$957,2,0),0) -> 0 | B33: =IFERROR(VLOOKUP(D33,'Monthly Deduction'!$E$3:$F$957,2,0),0) -> 0 | C33: =A33+B33 -> 0 | D33: 10010129 | E33: =VLOOKUP(D33,'MPG Payment '!$E$3:$G$498218,2,0) -> Manjhaul- Gulshan Kumar | F33: =IFERROR(_xlfn.XLOOKUP(D33,'Monthly Deduction'!$I$3:$I$957,'Monthly Deduction'!$H$3:$H$957),0) -> 0 | G33: =VLOOKUP(D33,'MPG Payment '!$E$3:$G$334579,3,0) -> vlc | H33: =VLOOKUP(D33,'MPG Payment '!$E$3:$H$334579,4,0) -> Indirect | I33: =INDEX('MPG Payment '!$C:$C,MATCH('Shayak Income '!D33,'MPG Payment '!E:E,0)) -> 1001 | J33: =INDEX('MPG Payment '!$D:$D,MATCH('Shayak Income '!D33,'MPG Payment '!E:E,0)) -> Majhaul | K33: Old | L33: 45869 | M33: =SUMIF('MPG Payment '!$E$3:$E$34579,'Shayak Income '!D33,'MPG Payment '!$I$3:$I$34579) -> 3536.2 | N33: =SUMIF('MPG Payment '!$E$3:$E$34579,'Shayak Income '!D33,'MPG Payment '!$J$3:$J$34579) -> 133843.86 | O33: =+M33*0.75 -> 2652.15 | P33: =+M33*0.95 -> 3359.39 | Q33: =SUMIF('MPG Payment '!$E$3:$E$34579,'Shayak Income '!D33,'MPG Payment '!$S$3:$S$34579) -> 0 | R33: =+N33*3% -> 4015.3158 | S33: =R33-P33 -> 655.92578 | T33: =M33*0.1 -> 353.62 | U33: =(((IF(K33="New",0,SUMIF('MPG Payment '!$E$3:$E$34579,'Shayak Income '!D33,'MPG Payment '!$AC$3:$AC$34579))))+0)+0 -> 156.00272 | V33: =ROUND((SUM(O33:Q33)-SUM(T33:U33)),0) -> 5502 | W33: =(((AN33-AO33)))+0 -> 0 | X33: =((MIN(IF(B33>0,MAX(N33*2%),0),B33)))+0 -> 0 | Y33: =IFERROR(VLOOKUP(D33,'Monthly Deduction'!$M$2:$N$64,2,0),0) -> 0 | Z33: 0 | AA33: =IFERROR(VLOOKUP(D33,'Monthly Deduction'!A:B,2,0),0) -> 0 | AB33: =ROUND(IFERROR(V33-SUM(W33:AA33),0),0) -> 5502 | AC33: 0 | AD33: =ROUND(AB33-AC33,0) -> 5502 | AE33: =IF(AC33<>0,"Yes","Release") -> Release | AG33: 0 | AI33: 0 | AK33: 932 | AL33: =COUNTIF(AK33:AK33,"=NA") -> 0 | AN33: =((MIN(IF(A33>0,MAX(N33*2%,1861),0),A33)))+0 -> 0 | AO33: =SUMIF('MPG Payment '!E:E,'Shayak Income '!D33,'MPG Payment '!AJ:AJ) -> 0 | AP33: =W33 -> 0 | AQ33: =AO33+AP33 -> 0 | AS33: =B33-X33 -> 0
A34: =IFERROR(VLOOKUP(D34,'Monthly Deduction'!$I$3:$J$957,2,0),0) -> 0 | B34: =IFERROR(VLOOKUP(D34,'Monthly Deduction'!$E$3:$F$957,2,0),0) -> 0 | C34: =A34+B34 -> 0 | D34: 10010130 | E34: =VLOOKUP(D34,'MPG Payment '!$E$3:$G$498218,2,0) -> Khaira Manjhaul | F34: =IFERROR(_xlfn.XLOOKUP(D34,'Monthly Deduction'!$I$3:$I$957,'Monthly Deduction'!$H$3:$H$957),0) -> 0 | G34: =VLOOKUP(D34,'MPG Payment '!$E$3:$G$334579,3,0) -> vlc | H34: =VLOOKUP(D34,'MPG Payment '!$E$3:$H$334579,4,0) -> Indirect | I34: =INDEX('MPG Payment '!$C:$C,MATCH('Shayak Income '!D34,'MPG Payment '!E:E,0)) -> 1001 | J34: =INDEX('MPG Payment '!$D:$D,MATCH('Shayak Income '!D34,'MPG Payment '!E:E,0)) -> Majhaul | K34: Old | L34: 45870 | M34: =SUMIF('MPG Payment '!$E$3:$E$34579,'Shayak Income '!D34,'MPG Payment '!$I$3:$I$34579) -> 1914.6 | N34: =SUMIF('MPG Payment '!$E$3:$E$34579,'Shayak Income '!D34,'MPG Payment '!$J$3:$J$34579) -> 68984.526 | O34: =+M34*0.75 -> 1435.95 | P34: =+M34*0.95 -> 1818.87 | Q34: =SUMIF('MPG Payment '!$E$3:$E$34579,'Shayak Income '!D34,'MPG Payment '!$S$3:$S$34579) -> 0 | R34: =+N34*3% -> 2069.5358 | S34: =R34-P34 -> 250.66578 | T34: =M34*0.1 -> 191.46 | U34: =(((IF(K34="New",0,SUMIF('MPG Payment '!$E$3:$E$34579,'Shayak Income '!D34,'MPG Payment '!$AC$3:$AC$34579))))+0)+0 -> 634.33163 | V34: =ROUND((SUM(O34:Q34)-SUM(T34:U34)),0) -> 2429 | W34: =(((AN34-AO34)))+0 -> 0 | X34: =((MIN(IF(B34>0,MAX(N34*2%),0),B34)))+0 -> 0 | Y34: =IFERROR(VLOOKUP(D34,'Monthly Deduction'!$M$2:$N$64,2,0),0) -> 0 | Z34: 0 | AA34: =IFERROR(VLOOKUP(D34,'Monthly Deduction'!A:B,2,0),0) -> 0 | AB34: =ROUND(IFERROR(V34-SUM(W34:AA34),0),0) -> 2429 | AC34: 0 | AD34: =ROUND(AB34-AC34,0) -> 2429 | AE34: =IF(AC34<>0,"Yes","Release") -> Release | AG34: 0 | AI34: 0 | AK34: 347.1 | AL34: =COUNTIF(AK34:AK34,"=NA") -> 0 | AN34: =((MIN(IF(A34>0,MAX(N34*2%,1861),0),A34)))+0 -> 0 | AO34: =SUMIF('MPG Payment '!E:E,'Shayak Income '!D34,'MPG Payment '!AJ:AJ) -> 0 | AP34: =W34 -> 0 | AQ34: =AO34+AP34 -> 0 | AS34: =B34-X34 -> 0
A35: =IFERROR(VLOOKUP(D35,'Monthly Deduction'!$I$3:$J$957,2,0),0) -> 0 | B35: =IFERROR(VLOOKUP(D35,'Monthly Deduction'!$E$3:$F$957,2,0),0) -> 0 | C35: =A35+B35 -> 0 | D35: 10010131 | E35: =VLOOKUP(D35,'MPG Payment '!$E$3:$G$498218,2,0) -> Mehda Shahpur | F35: =IFERROR(_xlfn.XLOOKUP(D35,'Monthly Deduction'!$I$3:$I$957,'Monthly Deduction'!$H$3:$H$957),0) -> 0 | G35: =VLOOKUP(D35,'MPG Payment '!$E$3:$G$334579,3,0) -> vlc | H35: =VLOOKUP(D35,'MPG Payment '!$E$3:$H$334579,4,0) -> Indirect | I35: =INDEX('MPG Payment '!$C:$C,MATCH('Shayak Income '!D35,'MPG Payment '!E:E,0)) -> 1001 | J35: =INDEX('MPG Payment '!$D:$D,MATCH('Shayak Income '!D35,'MPG Payment '!E:E,0)) -> Majhaul | K35: Old | L35: 45870 | M35: =SUMIF('MPG Payment '!$E$3:$E$34579,'Shayak Income '!D35,'MPG Payment '!$I$3:$I$34579) -> 2295.7 | N35: =SUMIF('MPG Payment '!$E$3:$E$34579,'Shayak Income '!D35,'MPG Payment '!$J$3:$J$34579) -> 83412.733 | O35: =+M35*0.75 -> 1721.775 | P35: =+M35*0.95 -> 2180.915 | Q35: =SUMIF('MPG Payment '!$E$3:$E$34579,'Shayak Income '!D35,'MPG Payment '!$S$3:$S$34579) -> 0 | R35: =+N35*3% -> 2502.382 | S35: =R35-P35 -> 321.46699 | T35: =M35*0.1 -> 229.57 | U35: =(((IF(K35="New",0,SUMIF('MPG Payment '!$E$3:$E$34579,'Shayak Income '!D35,'MPG Payment '!$AC$3:$AC$34579))))+0)+0 -> 392.31252 | V35: =ROUND((SUM(O35:Q35)-SUM(T35:U35)),0) -> 3281 | W35: =(((AN35-AO35)))+0 -> 0 | X35: =((MIN(IF(B35>0,MAX(N35*2%),0),B35)))+0 -> 0 | Y35: =IFERROR(VLOOKUP(D35,'Monthly Deduction'!$M$2:$N$64,2,0),0) -> 0 | Z35: 0 | AA35: =IFERROR(VLOOKUP(D35,'Monthly Deduction'!A:B,2,0),0) -> 0 | AB35: =ROUND(IFERROR(V35-SUM(W35:AA35),0),0) -> 3281 | AC35: 0 | AD35: =ROUND(AB35-AC35,0) -> 3281 | AE35: =IF(AC35<>0,"Yes","Release") -> Release | AG35: 0 | AI35: 0 | AK35: 677 | AL35: =COUNTIF(AK35:AK35,"=NA") -> 0 | AN35: =((MIN(IF(A35>0,MAX(N35*2%,1861),0),A35)))+0 -> 0 | AO35: =SUMIF('MPG Payment '!E:E,'Shayak Income '!D35,'MPG Payment '!AJ:AJ) -> 0 | AP35: =W35 -> 0 | AQ35: =AO35+AP35 -> 0 | AS35: =B35-X35 -> 0
A36: =IFERROR(VLOOKUP(D36,'Monthly Deduction'!$I$3:$J$957,2,0),0) -> 0 | B36: =IFERROR(VLOOKUP(D36,'Monthly Deduction'!$E$3:$F$957,2,0),0) -> 0 | C36: =A36+B36 -> 0 | D36: 10020002 | E36: =VLOOKUP(D36,'MPG Payment '!$E$3:$G$498218,2,0) -> PIPARIYA DIH -2 | F36: =IFERROR(_xlfn.XLOOKUP(D36,'Monthly Deduction'!$I$3:$I$957,'Monthly Deduction'!$H$3:$H$957),0) -> 0 | G36: =VLOOKUP(D36,'MPG Payment '!$E$3:$G$334579,3,0) -> MPG | H36: =VLOOKUP(D36,'MPG Payment '!$E$3:$H$334579,4,0) -> Direct | I36: =INDEX('MPG Payment '!$C:$C,MATCH('Shayak Income '!D36,'MPG Payment '!E:E,0)) -> 1002 | J36: =INDEX('MPG Payment '!$D:$D,MATCH('Shayak Income '!D36,'MPG Payment '!E:E,0)) -> Laldiyara | K36: Old | L36: 42979 | M36: =SUMIF('MPG Payment '!$E$3:$E$34579,'Shayak Income '!D36,'MPG Payment '!$I$3:$I$34579) -> 10419.2 | N36: =SUMIF('MPG Payment '!$E$3:$E$34579,'Shayak Income '!D36,'MPG Payment '!$J$3:$J$34579) -> 455126.77 | O36: =+M36*0.75 -> 7814.4 | P36: =+M36*0.95 -> 9898.24 | Q36: =SUMIF('MPG Payment '!$E$3:$E$34579,'Shayak Income '!D36,'MPG Payment '!$S$3:$S$34579) -> 4828.8558 | R36: =+N36*3% -> 13653.803 | S36: =R36-P36 -> 3755.563 | T36: =M36*0.1 -> 1041.92 | U36: =(((IF(K36="New",0,SUMIF('MPG Payment '!$E$3:$E$34579,'Shayak Income '!D36,'MPG Payment '!$AC$3:$AC$34579))))+0)+0 -> 0 | V36: =ROUND((SUM(O36:Q36)-SUM(T36:U36)),0) -> 21500 | W36: =(((AN36-AO36)))+0 -> 0 | X36: =((MIN(IF(B36>0,MAX(N36*2%),0),B36)))+0 -> 0 | Y36: =IFERROR(VLOOKUP(D36,'Monthly Deduction'!$M$2:$N$64,2,0),0) -> 0 | Z36: 0 | AA36: =IFERROR(VLOOKUP(D36,'Monthly Deduction'!A:B,2,0),0) -> 0 | AB36: =ROUND(IFERROR(V36-SUM(W36:AA36),0),0) -> 21500 | AC36: 0 | AD36: =ROUND(AB36-AC36,0) -> 21500 | AE36: =IF(AC36<>0,"Yes","Release") -> Release | AG36: 0 | AI36: 0 | AK36: 2676.9 | AL36: =COUNTIF(AK36:AK36,"=NA") -> 0 | AN36: =((MIN(IF(A36>0,MAX(N36*2%,1861),0),A36)))+0 -> 0 | AO36: =SUMIF('MPG Payment '!E:E,'Shayak Income '!D36,'MPG Payment '!AJ:AJ) -> 0 | AP36: =W36 -> 0 | AQ36: =AO36+AP36 -> 0 | AS36: =B36-X36 -> 0
A37: =IFERROR(VLOOKUP(D37,'Monthly Deduction'!$I$3:$J$957,2,0),0) -> 0 | B37: =IFERROR(VLOOKUP(D37,'Monthly Deduction'!$E$3:$F$957,2,0),0) -> 0 | C37: =A37+B37 -> 0 | D37: 10020004 | E37: =VLOOKUP(D37,'MPG Payment '!$E$3:$G$498218,2,0) -> LAL DIYARA -1 | F37: =IFERROR(_xlfn.XLOOKUP(D37,'Monthly Deduction'!$I$3:$I$957,'Monthly Deduction'!$H$3:$H$957),0) -> 0 | G37: =VLOOKUP(D37,'MPG Payment '!$E$3:$G$334579,3,0) -> MPG | H37: =VLOOKUP(D37,'MPG Payment '!$E$3:$H$334579,4,0) -> Direct | I37: =INDEX('MPG Payment '!$C:$C,MATCH('Shayak Income '!D37,'MPG Payment '!E:E,0)) -> 1002 | J37: =INDEX('MPG Payment '!$D:$D,MATCH('Shayak Income '!D37,'MPG Payment '!E:E,0)) -> Laldiyara | K37: Old | L37: 42979 | M37: =SUMIF('MPG Payment '!$E$3:$E$34579,'Shayak Income '!D37,'MPG Payment '!$I$3:$I$34579) -> 2219.6 | N37: =SUMIF('MPG Payment '!$E$3:$E$34579,'Shayak Income '!D37,'MPG Payment '!$J$3:$J$34579) -> 83944.32 | O37: =+M37*0.75 -> 1664.7 | P37: =+M37*0.95 -> 2108.62 | Q37: =SUMIF('MPG Payment '!$E$3:$E$34579,'Shayak Income '!D37,'MPG Payment '!$S$3:$S$34579) -> 0 | R37: =+N37*3% -> 2518.3296 | S37: =R37-P37 -> 409.70959 | T37: =M37*0.1 -> 221.96 | U37: =(((IF(K37="New",0,SUMIF('MPG Payment '!$E$3:$E$34579,'Shayak Income '!D37,'MPG Payment '!$AC$3:$AC$34579))))+0)+0 -> 442.40062 | V37: =ROUND((SUM(O37:Q37)-SUM(T37:U37)),0) -> 3109 | W37: =(((AN37-AO37)))+0 -> 0 | X37: =((MIN(IF(B37>0,MAX(N37*2%),0),B37)))+0 -> 0 | Y37: =IFERROR(VLOOKUP(D37,'Monthly Deduction'!$M$2:$N$64,2,0),0) -> 0 | Z37: 0 | AA37: =IFERROR(VLOOKUP(D37,'Monthly Deduction'!A:B,2,0),0) -> 0 | AB37: =ROUND(IFERROR(V37-SUM(W37:AA37),0),0) -> 3109 | AC37: 0 | AD37: =ROUND(AB37-AC37,0) -> 3109 | AE37: =IF(AC37<>0,"Yes","Release") -> Release | AG37: 0 | AI37: 0 | AK37: 376.9 | AL37: =COUNTIF(AK37:AK37,"=NA") -> 0 | AN37: =((MIN(IF(A37>0,MAX(N37*2%,1861),0),A37)))+0 -> 0 | AO37: =SUMIF('MPG Payment '!E:E,'Shayak Income '!D37,'MPG Payment '!AJ:AJ) -> 0 | AP37: =W37 -> 0 | AQ37: =AO37+AP37 -> 0 | AS37: =B37-X37 -> 0
A38: =IFERROR(VLOOKUP(D38,'Monthly Deduction'!$I$3:$J$957,2,0),0) -> 0 | B38: =IFERROR(VLOOKUP(D38,'Monthly Deduction'!$E$3:$F$957,2,0),0) -> 0 | C38: =A38+B38 -> 0 | D38: 10020006 | E38: =VLOOKUP(D38,'MPG Payment '!$E$3:$G$498218,2,0) -> GANGA KINARE KHUTHA | F38: =IFERROR(_xlfn.XLOOKUP(D38,'Monthly Deduction'!$I$3:$I$957,'Monthly Deduction'!$H$3:$H$957),0) -> 0 | G38: =VLOOKUP(D38,'MPG Payment '!$E$3:$G$334579,3,0) -> vlc | H38: =VLOOKUP(D38,'MPG Payment '!$E$3:$H$334579,4,0) -> Indirect | I38: =INDEX('MPG Payment '!$C:$C,MATCH('Shayak Income '!D38,'MPG Payment '!E:E,0)) -> 1002 | J38: =INDEX('MPG Payment '!$D:$D,MATCH('Shayak Income '!D38,'MPG Payment '!E:E,0)) -> Laldiyara | K38: Old | L38: 42979 | M38: =SUMIF('MPG Payment '!$E$3:$E$34579,'Shayak Income '!D38,'MPG Payment '!$I$3:$I$34579) -> 723.7 | N38: =SUMIF('MPG Payment '!$E$3:$E$34579,'Shayak Income '!D38,'MPG Payment '!$J$3:$J$34579) -> 27108.598 | O38: =+M38*0.75 -> 542.775 | P38: =+M38*0.95 -> 687.515 | Q38: =SUMIF('MPG Payment '!$E$3:$E$34579,'Shayak Income '!D38,'MPG Payment '!$S$3:$S$34579) -> 0 | R38: =+N38*3% -> 813.25793 | S38: =R38-P38 -> 125.74293 | T38: =M38*0.1 -> 72.37 | U38: =(((IF(K38="New",0,SUMIF('MPG Payment '!$E$3:$E$34579,'Shayak Income '!D38,'MPG Payment '!$AC$3:$AC$34579))))+0)+-399 -> 1157.5274 | V38: =ROUND((SUM(O38:Q38)-SUM(T38:U38)),0) -> 0 | W38: 0 | X38: 0 | Y38: =IFERROR(VLOOKUP(D38,'Monthly Deduction'!$M$2:$N$64,2,0),0) -> 0 | Z38: 0 | AA38: =IFERROR(VLOOKUP(D38,'Monthly Deduction'!A:B,2,0),0) -> 0 | AB38: =ROUND(IFERROR(V38-SUM(W38:AA38),0),0) -> 0 | AC38: 0 | AD38: =ROUND(AB38-AC38,0) -> 0 | AE38: =IF(AC38<>0,"Yes","Release") -> Release | AG38: 0 | AI38: 0 | AK38: 189.8 | AL38: =COUNTIF(AK38:AK38,"=NA") -> 0 | AN38: =((MIN(IF(A38>0,MAX(N38*2%,1861),0),A38)))+0 -> 0 | AO38: =SUMIF('MPG Payment '!E:E,'Shayak Income '!D38,'MPG Payment '!AJ:AJ) -> 0 | AP38: =W38 -> 0 | AQ38: =AO38+AP38 -> 0 | AS38: =B38-X38 -> 0
A39: =IFERROR(VLOOKUP(D39,'Monthly Deduction'!$I$3:$J$957,2,0),0) -> 0 | B39: =IFERROR(VLOOKUP(D39,'Monthly Deduction'!$E$3:$F$957,2,0),0) -> 0 | C39: =A39+B39 -> 0 | D39: 10020007 | E39: =VLOOKUP(D39,'MPG Payment '!$E$3:$G$498218,2,0) -> Gomukh ID Khutaha Ganga | F39: =IFERROR(_xlfn.XLOOKUP(D39,'Monthly Deduction'!$I$3:$I$957,'Monthly Deduction'!$H$3:$H$957),0) -> 0 | G39: =VLOOKUP(D39,'MPG Payment '!$E$3:$G$334579,3,0) -> vlc | H39: =VLOOKUP(D39,'MPG Payment '!$E$3:$H$334579,4,0) -> Indirect | I39: =INDEX('MPG Payment '!$C:$C,MATCH('Shayak Income '!D39,'MPG Payment '!E:E,0)) -> 1002 | J39: =INDEX('MPG Payment '!$D:$D,MATCH('Shayak Income '!D39,'MPG Payment '!E:E,0)) -> Laldiyara | K39: Old | L39: 42979 | M39: =SUMIF('MPG Payment '!$E$3:$E$34579,'Shayak Income '!D39,'MPG Payment '!$I$3:$I$34579) -> 434.8 | N39: =SUMIF('MPG Payment '!$E$3:$E$34579,'Shayak Income '!D39,'MPG Payment '!$J$3:$J$34579) -> 15655.311 | O39: =+M39*0.75 -> 326.1 | P39: =+M39*0.95 -> 413.06 | Q39: =SUMIF('MPG Payment '!$E$3:$E$34579,'Shayak Income '!D39,'MPG Payment '!$S$3:$S$34579) -> 0 | R39: =+N39*3% -> 469.65934 | S39: =R39-P39 -> 56.599337 | T39: =M39*0.1 -> 43.48 | U39: =(((IF(K39="New",0,SUMIF('MPG Payment '!$E$3:$E$34579,'Shayak Income '!D39,'MPG Payment '!$AC$3:$AC$34579))))+0)+0 -> 680.95225 | V39: =ROUND((SUM(O39:Q39)-SUM(T39:U39)),0) -> 15 | W39: =(((AN39-AO39)))+0 -> 0 | X39: =((MIN(IF(B39>0,MAX(N39*2%),0),B39)))+0 -> 0 | Y39: =IFERROR(VLOOKUP(D39,'Monthly Deduction'!$M$2:$N$64,2,0),0) -> 0 | Z39: 0 | AA39: =IFERROR(VLOOKUP(D39,'Monthly Deduction'!A:B,2,0),0) -> 0 | AB39: =ROUND(IFERROR(V39-SUM(W39:AA39),0),0) -> 15 | AC39: 0 | AD39: =ROUND(AB39-AC39,0) -> 15 | AE39: =IF(AC39<>0,"Yes","Release") -> Release | AG39: 0 | AI39: 0 | AK39: 105.5 | AL39: =COUNTIF(AK39:AK39,"=NA") -> 0 | AN39: =((MIN(IF(A39>0,MAX(N39*2%,1861),0),A39)))+0 -> 0 | AO39: =SUMIF('MPG Payment '!E:E,'Shayak Income '!D39,'MPG Payment '!AJ:AJ) -> 0 | AP39: =W39 -> 0 | AQ39: =AO39+AP39 -> 0 | AS39: =B39-X39 -> 0
A40: =IFERROR(VLOOKUP(D40,'Monthly Deduction'!$I$3:$J$957,2,0),0) -> 0 | B40: =IFERROR(VLOOKUP(D40,'Monthly Deduction'!$E$3:$F$957,2,0),0) -> 0 | C40: =A40+B40 -> 0 | D40: 10020008 | E40: =VLOOKUP(D40,'MPG Payment '!$E$3:$G$498218,2,0) -> Gomukh ID Khutaha Dhih | F40: =IFERROR(_xlfn.XLOOKUP(D40,'Monthly Deduction'!$I$3:$I$957,'Monthly Deduction'!$H$3:$H$957),0) -> 0 | G40: =VLOOKUP(D40,'MPG Payment '!$E$3:$G$334579,3,0) -> vlc | H40: =VLOOKUP(D40,'MPG Payment '!$E$3:$H$334579,4,0) -> Indirect | I40: =INDEX('MPG Payment '!$C:$C,MATCH('Shayak Income '!D40,'MPG Payment '!E:E,0)) -> 1002 | J40: =INDEX('MPG Payment '!$D:$D,MATCH('Shayak Income '!D40,'MPG Payment '!E:E,0)) -> Laldiyara | K40: Old | L40: 44161 | M40: =SUMIF('MPG Payment '!$E$3:$E$34579,'Shayak Income '!D40,'MPG Payment '!$I$3:$I$34579) -> 4735.9 | N40: =SUMIF('MPG Payment '!$E$3:$E$34579,'Shayak Income '!D40,'MPG Payment '!$J$3:$J$34579) -> 188026.56 | O40: =+M40*0.75 -> 3551.925 | P40: =+M40*0.95 -> 4499.105 | Q40: =SUMIF('MPG Payment '!$E$3:$E$34579,'Shayak Income '!D40,'MPG Payment '!$S$3:$S$34579) -> 0 | R40: =+N40*3% -> 5640.7969 | S40: =R40-P40 -> 1141.6919 | T40: =M40*0.1 -> 473.59 | U40: =(((IF(K40="New",0,SUMIF('MPG Payment '!$E$3:$E$34579,'Shayak Income '!D40,'MPG Payment '!$AC$3:$AC$34579))))+0)+0 -> 146.06776 | V40: =ROUND((SUM(O40:Q40)-SUM(T40:U40)),0) -> 7431 | W40: =(((AN40-AO40)))+0 -> 0 | X40: =((MIN(IF(B40>0,MAX(N40*2%),0),B40)))+0 -> 0 | Y40: =IFERROR(VLOOKUP(D40,'Monthly Deduction'!$M$2:$N$64,2,0),0) -> 0 | Z40: 0 | AA40: =IFERROR(VLOOKUP(D40,'Monthly Deduction'!A:B,2,0),0) -> 0 | AB40: =ROUND(IFERROR(V40-SUM(W40:AA40),0),0) -> 7431 | AC40: 0 | AD40: =ROUND(AB40-AC40,0) -> 7431 | AE40: =IF(AC40<>0,"Yes","Release") -> Release | AG40: 0 | AI40: 0 | AK40: 1668.7 | AL40: =COUNTIF(AK40:AK40,"=NA") -> 0 | AN40: =((MIN(IF(A40>0,MAX(N40*2%,1861),0),A40)))+0 -> 0 | AO40: =SUMIF('MPG Payment '!E:E,'Shayak Income '!D40,'MPG Payment '!AJ:AJ) -> 0 | AP40: =W40 -> 0 | AQ40: =AO40+AP40 -> 0 | AS40: =B40-X40 -> 0
A41: =IFERROR(VLOOKUP(D41,'Monthly Deduction'!$I$3:$J$957,2,0),0) -> 0 | B41: =IFERROR(VLOOKUP(D41,'Monthly Deduction'!$E$3:$F$957,2,0),0) -> 0 | C41: =A41+B41 -> 0 | D41: 10020012 | E41: =VLOOKUP(D41,'MPG Payment '!$E$3:$G$498218,2,0) -> KANHAIYA YADAV | F41: =IFERROR(_xlfn.XLOOKUP(D41,'Monthly Deduction'!$I$3:$I$957,'Monthly Deduction'!$H$3:$H$957),0) -> 0 | G41: =VLOOKUP(D41,'MPG Payment '!$E$3:$G$334579,3,0) -> vlc | H41: =VLOOKUP(D41,'MPG Payment '!$E$3:$H$334579,4,0) -> Indirect | I41: =INDEX('MPG Payment '!$C:$C,MATCH('Shayak Income '!D41,'MPG Payment '!E:E,0)) -> 1002 | J41: =INDEX('MPG Payment '!$D:$D,MATCH('Shayak Income '!D41,'MPG Payment '!E:E,0)) -> Laldiyara | K41: Old | L41: 44435 | M41: =SUMIF('MPG Payment '!$E$3:$E$34579,'Shayak Income '!D41,'MPG Payment '!$I$3:$I$34579) -> 950 | N41: =SUMIF('MPG Payment '!$E$3:$E$34579,'Shayak Income '!D41,'MPG Payment '!$J$3:$J$34579) -> 37678.904 | O41: =+M41*0.75 -> 712.5 | P41: =+M41*0.95 -> 902.5 | Q41: =SUMIF('MPG Payment '!$E$3:$E$34579,'Shayak Income '!D41,'MPG Payment '!$S$3:$S$34579) -> 0 | R41: =+N41*3% -> 1130.3671 | S41: =R41-P41 -> 227.86713 | T41: =M41*0.1 -> 95 | U41: =(((IF(K41="New",0,SUMIF('MPG Payment '!$E$3:$E$34579,'Shayak Income '!D41,'MPG Payment '!$AC$3:$AC$34579))))+0)+0 -> 1464.0946 | V41: =ROUND((SUM(O41:Q41)-SUM(T41:U41)),0) -> 56 | W41: =(((AN41-AO41)))+0 -> 0 | X41: =((MIN(IF(B41>0,MAX(N41*2%),0),B41)))+0 -> 0 | Y41: =IFERROR(VLOOKUP(D41,'Monthly Deduction'!$M$2:$N$64,2,0),0) -> 0 | Z41: 0 | AA41: =IFERROR(VLOOKUP(D41,'Monthly Deduction'!A:B,2,0),0) -> 0 | AB41: =ROUND(IFERROR(V41-SUM(W41:AA41),0),0) -> 56 | AC41: 0 | AD41: =ROUND(AB41-AC41,0) -> 56 | AE41: =IF(AC41<>0,"Yes","Release") -> Release | AG41: 0 | AI41: 0 | AK41: 234.3 | AL41: =COUNTIF(AK41:AK41,"=NA") -> 0 | AN41: =((MIN(IF(A41>0,MAX(N41*2%,1861),0),A41)))+0 -> 0 | AO41: =SUMIF('MPG Payment '!E:E,'Shayak Income '!D41,'MPG Payment '!AJ:AJ) -> 0 | AP41: =W41 -> 0 | AQ41: =AO41+AP41 -> 0 | AS41: =B41-X41 -> 0
A42: =IFERROR(VLOOKUP(D42,'Monthly Deduction'!$I$3:$J$957,2,0),0) -> 0 | B42: =IFERROR(VLOOKUP(D42,'Monthly Deduction'!$E$3:$F$957,2,0),0) -> 0 | C42: =A42+B42 -> 0 | D42: 10020015 | E42: =VLOOKUP(D42,'MPG Payment '!$E$3:$G$498218,2,0) -> GOMUKH LALDIYARA TIRASHI | F42: =IFERROR(_xlfn.XLOOKUP(D42,'Monthly Deduction'!$I$3:$I$957,'Monthly Deduction'!$H$3:$H$957),0) -> 0 | G42: =VLOOKUP(D42,'MPG Payment '!$E$3:$G$334579,3,0) -> vlc | H42: =VLOOKUP(D42,'MPG Payment '!$E$3:$H$334579,4,0) -> Indirect | I42: =INDEX('MPG Payment '!$C:$C,MATCH('Shayak Income '!D42,'MPG Payment '!E:E,0)) -> 1002 | J42: =INDEX('MPG Payment '!$D:$D,MATCH('Shayak Income '!D42,'MPG Payment '!E:E,0)) -> Laldiyara | K42: Old | L42: 44652 | M42: =SUMIF('MPG Payment '!$E$3:$E$34579,'Shayak Income '!D42,'MPG Payment '!$I$3:$I$34579) -> 102855.9 | N42: =SUMIF('MPG Payment '!$E$3:$E$34579,'Shayak Income '!D42,'MPG Payment '!$J$3:$J$34579) -> 4044117.9 | O42: =+M42*0.75 -> 77141.925 | P42: =+M42*0.95 -> 97713.105 | Q42: =SUMIF('MPG Payment '!$E$3:$E$34579,'Shayak Income '!D42,'MPG Payment '!$S$3:$S$34579) -> 0 | R42: =+N42*3% -> 121323.54 | S42: =R42-P42 -> 23610.433 | T42: =M42*0.1 -> 10285.59 | U42: =(((IF(K42="New",0,SUMIF('MPG Payment '!$E$3:$E$34579,'Shayak Income '!D42,'MPG Payment '!$AC$3:$AC$34579))))+0)+0 -> 0 | V42: =ROUND((SUM(O42:Q42)-SUM(T42:U42)),0) -> 164569 | W42: =(((AN42-AO42)))+0 -> 0 | X42: =((MIN(IF(B42>0,MAX(N42*2%),0),B42)))+0 -> 0 | Y42: =IFERROR(VLOOKUP(D42,'Monthly Deduction'!$M$2:$N$64,2,0),0) -> 0 | Z42: 0 | AA42: =IFERROR(VLOOKUP(D42,'Monthly Deduction'!A:B,2,0),0) -> 0 | AB42: =ROUND(IFERROR(V42-SUM(W42:AA42),0),0) -> 164569 | AC42: 0 | AD42: =ROUND(AB42-AC42,0) -> 164569 | AE42: =IF(AC42<>0,"Yes","Release") -> Release | AG42: 0 | AI42: 0 | AK42: 28618.2 | AL42: =COUNTIF(AK42:AK42,"=NA") -> 0 | AN42: =((MIN(IF(A42>0,MAX(N42*2%,1861),0),A42)))+0 -> 0 | AO42: =SUMIF('MPG Payment '!E:E,'Shayak Income '!D42,'MPG Payment '!AJ:AJ) -> 0 | AP42: =W42 -> 0 | AQ42: =AO42+AP42 -> 0 | AS42: =B42-X42 -> 0
A43: =IFERROR(VLOOKUP(D43,'Monthly Deduction'!$I$3:$J$957,2,0),0) -> 0 | B43: =IFERROR(VLOOKUP(D43,'Monthly Deduction'!$E$3:$F$957,2,0),0) -> 0 | C43: =A43+B43 -> 0 | D43: 10020016 | E43: =VLOOKUP(D43,'MPG Payment '!$E$3:$G$498218,2,0) -> GOMUKH LALDIYARA PURBI | F43: =IFERROR(_xlfn.XLOOKUP(D43,'Monthly Deduction'!$I$3:$I$957,'Monthly Deduction'!$H$3:$H$957),0) -> 0 | G43: =VLOOKUP(D43,'MPG Payment '!$E$3:$G$334579,3,0) -> vlc | H43: =VLOOKUP(D43,'MPG Payment '!$E$3:$H$334579,4,0) -> Indirect | I43: =INDEX('MPG Payment '!$C:$C,MATCH('Shayak Income '!D43,'MPG Payment '!E:E,0)) -> 1002 | J43: =INDEX('MPG Payment '!$D:$D,MATCH('Shayak Income '!D43,'MPG Payment '!E:E,0)) -> Laldiyara | K43: Old | L43: 44652 | M43: =SUMIF('MPG Payment '!$E$3:$E$34579,'Shayak Income '!D43,'MPG Payment '!$I$3:$I$34579) -> 102504.9 | N43: =SUMIF('MPG Payment '!$E$3:$E$34579,'Shayak Income '!D43,'MPG Payment '!$J$3:$J$34579) -> 4085618.2 | O43: =+M43*0.75 -> 76878.675 | P43: =+M43*0.95 -> 97379.655 | Q43: =SUMIF('MPG Payment '!$E$3:$E$34579,'Shayak Income '!D43,'MPG Payment '!$S$3:$S$34579) -> 0 | R43: =+N43*3% -> 122568.55 | S43: =R43-P43 -> 25188.891 | T43: =M43*0.1 -> 10250.49 | U43: =(((IF(K43="New",0,SUMIF('MPG Payment '!$E$3:$E$34579,'Shayak Income '!D43,'MPG Payment '!$AC$3:$AC$34579))))+0)+0 -> 0 | V43: =ROUND((SUM(O43:Q43)-SUM(T43:U43)),0) -> 164008 | W43: =(((AN43-AO43)))+0 -> 0 | X43: =((MIN(IF(B43>0,MAX(N43*2%),0),B43)))+0 -> 0 | Y43: =IFERROR(VLOOKUP(D43,'Monthly Deduction'!$M$2:$N$64,2,0),0) -> 0 | Z43: 0 | AA43: =IFERROR(VLOOKUP(D43,'Monthly Deduction'!A:B,2,0),0) -> 0 | AB43: =ROUND(IFERROR(V43-SUM(W43:AA43),0),0) -> 164008 | AC43: 0 | AD43: =ROUND(AB43-AC43,0) -> 164008 | AE43: =IF(AC43<>0,"Yes","Release") -> Release | AG43: 0 | AI43: 0 | AK43: 26534.3 | AL43: =COUNTIF(AK43:AK43,"=NA") -> 0 | AN43: =((MIN(IF(A43>0,MAX(N43*2%,1861),0),A43)))+0 -> 0 | AO43: =SUMIF('MPG Payment '!E:E,'Shayak Income '!D43,'MPG Payment '!AJ:AJ) -> 0 | AP43: =W43 -> 0 | AQ43: =AO43+AP43 -> 0 | AS43: =B43-X43 -> 0
A44: =IFERROR(VLOOKUP(D44,'Monthly Deduction'!$I$3:$J$957,2,0),0) -> 0 | B44: =IFERROR(VLOOKUP(D44,'Monthly Deduction'!$E$3:$F$957,2,0),0) -> 0 | C44: =A44+B44 -> 0 | D44: 10020017 | E44: =VLOOKUP(D44,'MPG Payment '!$E$3:$G$498218,2,0) -> GOMUKH RAMCHANDARPUR II | F44: =IFERROR(_xlfn.XLOOKUP(D44,'Monthly Deduction'!$I$3:$I$957,'Monthly Deduction'!$H$3:$H$957),0) -> 0 | G44: =VLOOKUP(D44,'MPG Payment '!$E$3:$G$334579,3,0) -> MPG | H44: =VLOOKUP(D44,'MPG Payment '!$E$3:$H$334579,4,0) -> Direct | I44: =INDEX('MPG Payment '!$C:$C,MATCH('Shayak Income '!D44,'MPG Payment '!E:E,0)) -> 1002 | J44: =INDEX('MPG Payment '!$D:$D,MATCH('Shayak Income '!D44,'MPG Payment '!E:E,0)) -> Laldiyara | K44: Old | L44: 44652 | M44: =SUMIF('MPG Payment '!$E$3:$E$34579,'Shayak Income '!D44,'MPG Payment '!$I$3:$I$34579) -> 15404.8 | N44: =SUMIF('MPG Payment '!$E$3:$E$34579,'Shayak Income '!D44,'MPG Payment '!$J$3:$J$34579) -> 645130.96 | O44: =+M44*0.75 -> 11553.6 | P44: =+M44*0.95 -> 14634.56 | Q44: =SUMIF('MPG Payment '!$E$3:$E$34579,'Shayak Income '!D44,'MPG Payment '!$S$3:$S$34579) -> 4745.9818 | R44: =+N44*3% -> 19353.929 | S44: =R44-P44 -> 4719.3687 | T44: =M44*0.1 -> 1540.48 | U44: =(((IF(K44="New",0,SUMIF('MPG Payment '!$E$3:$E$34579,'Shayak Income '!D44,'MPG Payment '!$AC$3:$AC$34579))))+0)+0 -> 0 | V44: =ROUND((SUM(O44:Q44)-SUM(T44:U44)),0) -> 29394 | W44: =(((AN44-AO44)))+0 -> 0 | X44: =((MIN(IF(B44>0,MAX(N44*2%),0),B44)))+0 -> 0 | Y44: =IFERROR(VLOOKUP(D44,'Monthly Deduction'!$M$2:$N$64,2,0),0) -> 0 | Z44: 0 | AA44: =IFERROR(VLOOKUP(D44,'Monthly Deduction'!A:B,2,0),0) -> 0 | AB44: =ROUND(IFERROR(V44-SUM(W44:AA44),0),0) -> 29394 | AC44: 0 | AD44: =ROUND(AB44-AC44,0) -> 29394 | AE44: =IF(AC44<>0,"Yes","Release") -> Release | AG44: 0 | AI44: 0 | AK44: 4246.6 | AL44: =COUNTIF(AK44:AK44,"=NA") -> 0 | AN44: =((MIN(IF(A44>0,MAX(N44*2%,1861),0),A44)))+0 -> 0 | AO44: =SUMIF('MPG Payment '!E:E,'Shayak Income '!D44,'MPG Payment '!AJ:AJ) -> 0 | AP44: =W44 -> 0 | AQ44: =AO44+AP44 -> 0 | AS44: =B44-X44 -> 0
A45: =IFERROR(VLOOKUP(D45,'Monthly Deduction'!$I$3:$J$957,2,0),0) -> 0 | B45: =IFERROR(VLOOKUP(D45,'Monthly Deduction'!$E$3:$F$957,2,0),0) -> 0 | C45: =A45+B45 -> 0 | D45: 10020021 | E45: =VLOOKUP(D45,'MPG Payment '!$E$3:$G$498218,2,0) -> MOHANPUR | F45: =IFERROR(_xlfn.XLOOKUP(D45,'Monthly Deduction'!$I$3:$I$957,'Monthly Deduction'!$H$3:$H$957),0) -> 0 | G45: =VLOOKUP(D45,'MPG Payment '!$E$3:$G$334579,3,0) -> MPG | H45: =VLOOKUP(D45,'MPG Payment '!$E$3:$H$334579,4,0) -> Direct | I45: =INDEX('MPG Payment '!$C:$C,MATCH('Shayak Income '!D45,'MPG Payment '!E:E,0)) -> 1002 | J45: =INDEX('MPG Payment '!$D:$D,MATCH('Shayak Income '!D45,'MPG Payment '!E:E,0)) -> Laldiyara | K45: Old | L45: 44694 | M45: =SUMIF('MPG Payment '!$E$3:$E$34579,'Shayak Income '!D45,'MPG Payment '!$I$3:$I$34579) -> 16199.4 | N45: =SUMIF('MPG Payment '!$E$3:$E$34579,'Shayak Income '!D45,'MPG Payment '!$J$3:$J$34579) -> 715575.84 | O45: =+M45*0.75 -> 12149.55 | P45: =+M45*0.95 -> 15389.43 | Q45: =SUMIF('MPG Payment '!$E$3:$E$34579,'Shayak Income '!D45,'MPG Payment '!$S$3:$S$34579) -> 5954.2798 | R45: =+N45*3% -> 21467.275 | S45: =R45-P45 -> 6077.8452 | T45: =M45*0.1 -> 1619.94 | U45: =(((IF(K45="New",0,SUMIF('MPG Payment '!$E$3:$E$34579,'Shayak Income '!D45,'MPG Payment '!$AC$3:$AC$34579))))+0)+0 -> 0 | V45: =ROUND((SUM(O45:Q45)-SUM(T45:U45)),0) -> 31873 | W45: =(((AN45-AO45)))+0 -> 0 | X45: =((MIN(IF(B45>0,MAX(N45*2%),0),B45)))+0 -> 0 | Y45: =IFERROR(VLOOKUP(D45,'Monthly Deduction'!$M$2:$N$64,2,0),0) -> 0 | Z45: 0 | AA45: =IFERROR(VLOOKUP(D45,'Monthly Deduction'!A:B,2,0),0) -> 0 | AB45: =ROUND(IFERROR(V45-SUM(W45:AA45),0),0) -> 31873 | AC45: 0 | AD45: =ROUND(AB45-AC45,0) -> 31873 | AE45: =IF(AC45<>0,"Yes","Release") -> Release | AG45: 0 | AI45: 0 | AK45: 5236.2 | AL45: =COUNTIF(AK45:AK45,"=NA") -> 0 | AN45: =((MIN(IF(A45>0,MAX(N45*2%,1861),0),A45)))+0 -> 0 | AO45: =SUMIF('MPG Payment '!E:E,'Shayak Income '!D45,'MPG Payment '!AJ:AJ) -> 0 | AP45: =W45 -> 0 | AQ45: =AO45+AP45 -> 0 | AS45: =B45-X45 -> 0
A46: =IFERROR(VLOOKUP(D46,'Monthly Deduction'!$I$3:$J$957,2,0),0) -> 0 | B46: =IFERROR(VLOOKUP(D46,'Monthly Deduction'!$E$3:$F$957,2,0),0) -> 0 | C46: =A46+B46 -> 0 | D46: 10020023 | E46: =VLOOKUP(D46,'MPG Payment '!$E$3:$G$498218,2,0) -> Juwas | F46: =IFERROR(_xlfn.XLOOKUP(D46,'Monthly Deduction'!$I$3:$I$957,'Monthly Deduction'!$H$3:$H$957),0) -> 0 | G46: =VLOOKUP(D46,'MPG Payment '!$E$3:$G$334579,3,0) -> MPG | H46: =VLOOKUP(D46,'MPG Payment '!$E$3:$H$334579,4,0) -> Direct | I46: =INDEX('MPG Payment '!$C:$C,MATCH('Shayak Income '!D46,'MPG Payment '!E:E,0)) -> 1002 | J46: =INDEX('MPG Payment '!$D:$D,MATCH('Shayak Income '!D46,'MPG Payment '!E:E,0)) -> Laldiyara | K46: Old | L46: 44779 | M46: =SUMIF('MPG Payment '!$E$3:$E$34579,'Shayak Income '!D46,'MPG Payment '!$I$3:$I$34579) -> 3662.6 | N46: =SUMIF('MPG Payment '!$E$3:$E$34579,'Shayak Income '!D46,'MPG Payment '!$J$3:$J$34579) -> 138695.3 | O46: =+M46*0.75 -> 2746.95 | P46: =+M46*0.95 -> 3479.47 | Q46: =SUMIF('MPG Payment '!$E$3:$E$34579,'Shayak Income '!D46,'MPG Payment '!$S$3:$S$34579) -> 1315.1581 | R46: =+N46*3% -> 4160.8589 | S46: =R46-P46 -> 681.38888 | T46: =M46*0.1 -> 366.26 | U46: =(((IF(K46="New",0,SUMIF('MPG Payment '!$E$3:$E$34579,'Shayak Income '!D46,'MPG Payment '!$AC$3:$AC$34579))))+0)+0 -> 0 | V46: =ROUND((SUM(O46:Q46)-SUM(T46:U46)),0) -> 7175 | W46: =(((AN46-AO46)))+0 -> 0 | X46: =((MIN(IF(B46>0,MAX(N46*2%),0),B46)))+0 -> 0 | Y46: =IFERROR(VLOOKUP(D46,'Monthly Deduction'!$M$2:$N$64,2,0),0) -> 0 | Z46: 0 | AA46: =IFERROR(VLOOKUP(D46,'Monthly Deduction'!A:B,2,0),0) -> 0 | AB46: =ROUND(IFERROR(V46-SUM(W46:AA46),0),0) -> 7175 | AC46: 0 | AD46: =ROUND(AB46-AC46,0) -> 7175 | AE46: =IF(AC46<>0,"Yes","Release") -> Release | AG46: 0 | AI46: 0 | AK46: 991.8 | AL46: =COUNTIF(AK46:AK46,"=NA") -> 0 | AN46: =((MIN(IF(A46>0,MAX(N46*2%,1861),0),A46)))+0 -> 0 | AO46: =SUMIF('MPG Payment '!E:E,'Shayak Income '!D46,'MPG Payment '!AJ:AJ) -> 0 | AP46: =W46 -> 0 | AQ46: =AO46+AP46 -> 0 | AS46: =B46-X46 -> 0
A47: =IFERROR(VLOOKUP(D47,'Monthly Deduction'!$I$3:$J$957,2,0),0) -> 0 | B47: =IFERROR(VLOOKUP(D47,'Monthly Deduction'!$E$3:$F$957,2,0),0) -> 0 | C47: =A47+B47 -> 0 | D47: 10020024 | E47: =VLOOKUP(D47,'MPG Payment '!$E$3:$G$498218,2,0) -> Morwariya | F47: =IFERROR(_xlfn.XLOOKUP(D47,'Monthly Deduction'!$I$3:$I$957,'Monthly Deduction'!$H$3:$H$957),0) -> 0 | G47: =VLOOKUP(D47,'MPG Payment '!$E$3:$G$334579,3,0) -> MPG | H47: =VLOOKUP(D47,'MPG Payment '!$E$3:$H$334579,4,0) -> Direct | I47: =INDEX('MPG Payment '!$C:$C,MATCH('Shayak Income '!D47,'MPG Payment '!E:E,0)) -> 1002 | J47: =INDEX('MPG Payment '!$D:$D,MATCH('Shayak Income '!D47,'MPG Payment '!E:E,0)) -> Laldiyara | K47: Old | L47: 44801 | M47: =SUMIF('MPG Payment '!$E$3:$E$34579,'Shayak Income '!D47,'MPG Payment '!$I$3:$I$34579) -> 13043.7 | N47: =SUMIF('MPG Payment '!$E$3:$E$34579,'Shayak Income '!D47,'MPG Payment '!$J$3:$J$34579) -> 519562.73 | O47: =+M47*0.75 -> 9782.775 | P47: =+M47*0.95 -> 12391.515 | Q47: =SUMIF('MPG Payment '!$E$3:$E$34579,'Shayak Income '!D47,'MPG Payment '!$S$3:$S$34579) -> 0 | R47: =+N47*3% -> 15586.882 | S47: =R47-P47 -> 3195.367 | T47: =M47*0.1 -> 1304.37 | U47: =(((IF(K47="New",0,SUMIF('MPG Payment '!$E$3:$E$34579,'Shayak Income '!D47,'MPG Payment '!$AC$3:$AC$34579))))+0)+0 -> 0 | V47: =ROUND((SUM(O47:Q47)-SUM(T47:U47)),0) -> 20870 | W47: =(((AN47-AO47)))+0 -> 0 | X47: =((MIN(IF(B47>0,MAX(N47*2%),0),B47)))+0 -> 0 | Y47: =IFERROR(VLOOKUP(D47,'Monthly Deduction'!$M$2:$N$64,2,0),0) -> 0 | Z47: 0 | AA47: =IFERROR(VLOOKUP(D47,'Monthly Deduction'!A:B,2,0),0) -> 0 | AB47: =ROUND(IFERROR(V47-SUM(W47:AA47),0),0) -> 20870 | AC47: 0 | AD47: =ROUND(AB47-AC47,0) -> 20870 | AE47: =IF(AC47<>0,"Yes","Release") -> Release | AG47: 0 | AI47: 0 | AK47: 3029.5 | AL47: =COUNTIF(AK47:AK47,"=NA") -> 0 | AN47: =((MIN(IF(A47>0,MAX(N47*2%,1861),0),A47)))+0 -> 0 | AO47: =SUMIF('MPG Payment '!E:E,'Shayak Income '!D47,'MPG Payment '!AJ:AJ) -> 0 | AP47: =W47 -> 0 | AQ47: =AO47+AP47 -> 0 | AS47: =B47-X47 -> 0
A48: =IFERROR(VLOOKUP(D48,'Monthly Deduction'!$I$3:$J$957,2,0),0) -> 0 | B48: =IFERROR(VLOOKUP(D48,'Monthly Deduction'!$E$3:$F$957,2,0),0) -> 0 | C48: =A48+B48 -> 0 | D48: 10020025 | E48: =VLOOKUP(D48,'MPG Payment '!$E$3:$G$498218,2,0) -> Dumri 2 | F48: =IFERROR(_xlfn.XLOOKUP(D48,'Monthly Deduction'!$I$3:$I$957,'Monthly Deduction'!$H$3:$H$957),0) -> 0 | G48: =VLOOKUP(D48,'MPG Payment '!$E$3:$G$334579,3,0) -> MPG | H48: =VLOOKUP(D48,'MPG Payment '!$E$3:$H$334579,4,0) -> Direct | I48: =INDEX('MPG Payment '!$C:$C,MATCH('Shayak Income '!D48,'MPG Payment '!E:E,0)) -> 1002 | J48: =INDEX('MPG Payment '!$D:$D,MATCH('Shayak Income '!D48,'MPG Payment '!E:E,0)) -> Laldiyara | K48: Old | L48: 44866 | M48: =SUMIF('MPG Payment '!$E$3:$E$34579,'Shayak Income '!D48,'MPG Payment '!$I$3:$I$34579) -> 3683 | N48: =SUMIF('MPG Payment '!$E$3:$E$34579,'Shayak Income '!D48,'MPG Payment '!$J$3:$J$34579) -> 140205.46 | O48: =+M48*0.75 -> 2762.25 | P48: =+M48*0.95 -> 3498.85 | Q48: =SUMIF('MPG Payment '!$E$3:$E$34579,'Shayak Income '!D48,'MPG Payment '!$S$3:$S$34579) -> 1339.4605 | R48: =+N48*3% -> 4206.1638 | S48: =R48-P48 -> 707.31385 | T48: =M48*0.1 -> 368.3 | U48: =(((IF(K48="New",0,SUMIF('MPG Payment '!$E$3:$E$34579,'Shayak Income '!D48,'MPG Payment '!$AC$3:$AC$34579))))+0)+0 -> 0 | V48: =ROUND((SUM(O48:Q48)-SUM(T48:U48)),0) -> 7232 | W48: =(((AN48-AO48)))+0 -> 0 | X48: =((MIN(IF(B48>0,MAX(N48*2%),0),B48)))+0 -> 0 | Y48: =IFERROR(VLOOKUP(D48,'Monthly Deduction'!$M$2:$N$64,2,0),0) -> 0 | Z48: 0 | AA48: =IFERROR(VLOOKUP(D48,'Monthly Deduction'!A:B,2,0),0) -> 0 | AB48: =ROUND(IFERROR(V48-SUM(W48:AA48),0),0) -> 7232 | AC48: 0 | AD48: =ROUND(AB48-AC48,0) -> 7232 | AE48: =IF(AC48<>0,"Yes","Release") -> Release | AG48: 0 | AI48: 0 | AK48: 914.5 | AL48: =COUNTIF(AK48:AK48,"=NA") -> 0 | AN48: =((MIN(IF(A48>0,MAX(N48*2%,1861),0),A48)))+0 -> 0 | AO48: =SUMIF('MPG Payment '!E:E,'Shayak Income '!D48,'MPG Payment '!AJ:AJ) -> 0 | AP48: =W48 -> 0 | AQ48: =AO48+AP48 -> 0 | AS48: =B48-X48 -> 0
A49: =IFERROR(VLOOKUP(D49,'Monthly Deduction'!$I$3:$J$957,2,0),0) -> 0 | B49: =IFERROR(VLOOKUP(D49,'Monthly Deduction'!$E$3:$F$957,2,0),0) -> 0 | C49: =A49+B49 -> 0 | D49: 10020026 | E49: =VLOOKUP(D49,'MPG Payment '!$E$3:$G$498218,2,0) -> Gomukh Jhakhaur | F49: =IFERROR(_xlfn.XLOOKUP(D49,'Monthly Deduction'!$I$3:$I$957,'Monthly Deduction'!$H$3:$H$957),0) -> 0 | G49: =VLOOKUP(D49,'MPG Payment '!$E$3:$G$334579,3,0) -> MPG | H49: =VLOOKUP(D49,'MPG Payment '!$E$3:$H$334579,4,0) -> Direct | I49: =INDEX('MPG Payment '!$C:$C,MATCH('Shayak Income '!D49,'MPG Payment '!E:E,0)) -> 1002 | J49: =INDEX('MPG Payment '!$D:$D,MATCH('Shayak Income '!D49,'MPG Payment '!E:E,0)) -> Laldiyara | K49: Old | L49: 44866 | M49: =SUMIF('MPG Payment '!$E$3:$E$34579,'Shayak Income '!D49,'MPG Payment '!$I$3:$I$34579) -> 2735.9 | N49: =SUMIF('MPG Payment '!$E$3:$E$34579,'Shayak Income '!D49,'MPG Payment '!$J$3:$J$34579) -> 111813.44 | O49: =+M49*0.75 -> 2051.925 | P49: =+M49*0.95 -> 2599.105 | Q49: =SUMIF('MPG Payment '!$E$3:$E$34579,'Shayak Income '!D49,'MPG Payment '!$S$3:$S$34579) -> 247.01509 | R49: =+N49*3% -> 3354.4033 | S49: =R49-P49 -> 755.29826 | T49: =M49*0.1 -> 273.59 | U49: =(((IF(K49="New",0,SUMIF('MPG Payment '!$E$3:$E$34579,'Shayak Income '!D49,'MPG Payment '!$AC$3:$AC$34579))))+0)+0 -> 116.12808 | V49: =ROUND((SUM(O49:Q49)-SUM(T49:U49)),0) -> 4508 | W49: =(((AN49-AO49)))+0 -> 0 | X49: =((MIN(IF(B49>0,MAX(N49*2%),0),B49)))+0 -> 0 | Y49: =IFERROR(VLOOKUP(D49,'Monthly Deduction'!$M$2:$N$64,2,0),0) -> 0 | Z49: 0 | AA49: =IFERROR(VLOOKUP(D49,'Monthly Deduction'!A:B,2,0),0) -> 0 | AB49: =ROUND(IFERROR(V49-SUM(W49:AA49),0),0) -> 4508 | AC49: 0 | AD49: =ROUND(AB49-AC49,0) -> 4508 | AE49: =IF(AC49<>0,"Yes","Release") -> Release | AG49: 0 | AI49: 0 | AK49: 576.5 | AL49: =COUNTIF(AK49:AK49,"=NA") -> 0 | AN49: =((MIN(IF(A49>0,MAX(N49*2%,1861),0),A49)))+0 -> 0 | AO49: =SUMIF('MPG Payment '!E:E,'Shayak Income '!D49,'MPG Payment '!AJ:AJ) -> 0 | AP49: =W49 -> 0 | AQ49: =AO49+AP49 -> 0 | AS49: =B49-X49 -> 0
A50: =IFERROR(VLOOKUP(D50,'Monthly Deduction'!$I$3:$J$957,2,0),0) -> 0 | B50: =IFERROR(VLOOKUP(D50,'Monthly Deduction'!$E$3:$F$957,2,0),0) -> 0 | C50: =A50+B50 -> 0 | D50: 10020029 | E50: =VLOOKUP(D50,'MPG Payment '!$E$3:$G$498218,2,0) -> Gomukh Virupur | F50: =IFERROR(_xlfn.XLOOKUP(D50,'Monthly Deduction'!$I$3:$I$957,'Monthly Deduction'!$H$3:$H$957),0) -> 0 | G50: =VLOOKUP(D50,'MPG Payment '!$E$3:$G$334579,3,0) -> MPG | H50: =VLOOKUP(D50,'MPG Payment '!$E$3:$H$334579,4,0) -> Direct | I50: =INDEX('MPG Payment '!$C:$C,MATCH('Shayak Income '!D50,'MPG Payment '!E:E,0)) -> 1002 | J50: =INDEX('MPG Payment '!$D:$D,MATCH('Shayak Income '!D50,'MPG Payment '!E:E,0)) -> Laldiyara | K50: Old | L50: 44899 | M50: =SUMIF('MPG Payment '!$E$3:$E$34579,'Shayak Income '!D50,'MPG Payment '!$I$3:$I$34579) -> 1406.2 | N50: =SUMIF('MPG Payment '!$E$3:$E$34579,'Shayak Income '!D50,'MPG Payment '!$J$3:$J$34579) -> 55439.124 | O50: =+M50*0.75 -> 1054.65 | P50: =+M50*0.95 -> 1335.89 | Q50: =SUMIF('MPG Payment '!$E$3:$E$34579,'Shayak Income '!D50,'MPG Payment '!$S$3:$S$34579) -> 374.02998 | R50: =+N50*3% -> 1663.1737 | S50: =R50-P50 -> 327.28372 | T50: =M50*0.1 -> 140.62 | U50: =(((IF(K50="New",0,SUMIF('MPG Payment '!$E$3:$E$34579,'Shayak Income '!D50,'MPG Payment '!$AC$3:$AC$34579))))+0)+0 -> 1099.4032 | V50: =ROUND((SUM(O50:Q50)-SUM(T50:U50)),0) -> 1525 | W50: =(((AN50-AO50)))+0 -> 0 | X50: =((MIN(IF(B50>0,MAX(N50*2%),0),B50)))+0 -> 0 | Y50: =IFERROR(VLOOKUP(D50,'Monthly Deduction'!$M$2:$N$64,2,0),0) -> 0 | Z50: 0 | AA50: =IFERROR(VLOOKUP(D50,'Monthly Deduction'!A:B,2,0),0) -> 0 | AB50: =ROUND(IFERROR(V50-SUM(W50:AA50),0),0) -> 1525 | AC50: 0 | AD50: =ROUND(AB50-AC50,0) -> 1525 | AE50: =IF(AC50<>0,"Yes","Release") -> Release | AG50: 0 | AI50: 0 | AK50: 311.1 | AL50: =COUNTIF(AK50:AK50,"=NA") -> 0 | AN50: =((MIN(IF(A50>0,MAX(N50*2%,1861),0),A50)))+0 -> 0 | AO50: =SUMIF('MPG Payment '!E:E,'Shayak Income '!D50,'MPG Payment '!AJ:AJ) -> 0 | AP50: =W50 -> 0 | AQ50: =AO50+AP50 -> 0 | AS50: =B50-X50 -> 0
... A53: =IFERROR(VLOOKUP(D53,'Monthly Deduction'!$I$3:$J$957,2,0),0) -> 0 | B53: =IFERROR(VLOOKUP(D53,'Monthly Deduction'!$E$3:$F$957,2,0),0) -> 0 | C53: =A53+B53 -> 0 | D53: 10020035 | E53: =VLOOKUP(D53,'MPG Payment '!$E$3:$G$498218,2,0) -> PATHUA | F53: =IFERROR(_xlfn.XLOOKUP(D53,'Monthly Deduction'!$I$3:$I$957,'Monthly Deduction'!$H$3:$H$957),0) -> 0 | G53: =VLOOKUP(D53,'MPG Payment '!$E$3:$G$334579,3,0) -> MPG | H53: =VLOOKUP(D53,'MPG Payment '!$E$3:$H$334579,4,0) -> Direct | I53: =INDEX('MPG Payment '!$C:$C,MATCH('Shayak Income '!D53,'MPG Payment '!E:E,0)) -> 1002 | J53: =INDEX('MPG Payment '!$D:$D,MATCH('Shayak Income '!D53,'MPG Payment '!E:E,0)) -> Laldiyara | K53: Old | L53: 44950 | M53: =SUMIF('MPG Payment '!$E$3:$E$34579,'Shayak Income '!D53,'MPG Payment '!$I$3:$I$34579) -> 4389.5 | N53: =SUMIF('MPG Payment '!$E$3:$E$34579,'Shayak Income '!D53,'MPG Payment '!$J$3:$J$34579) -> 186666.87 | O53: =+M53*0.75 -> 3292.125 | P53: =+M53*0.95 -> 4170.025 | Q53: =SUMIF('MPG Payment '!$E$3:$E$34579,'Shayak Income '!D53,'MPG Payment '!$S$3:$S$34579) -> 5058.9107 | R53: =+N53*3% -> 5600.0062 | S53: =R53-P53 -> 1429.9812 | T53: =M53*0.1 -> 438.95 | U53: =(((IF(K53="New",0,SUMIF('MPG Payment '!$E$3:$E$34579,'Shayak Income '!D53,'MPG Payment '!$AC$3:$AC$34579))))+0)+0 -> 0 | V53: =ROUND((SUM(O53:Q53)-SUM(T53:U53)),0) -> 12082 | W53: =(((AN53-AO53)))+0 -> 0 | X53: =((MIN(IF(B53>0,MAX(N53*2%),0),B53)))+0 -> 0 | Y53: =IFERROR(VLOOKUP(D53,'Monthly Deduction'!$M$2:$N$64,2,0),0) -> 0 | Z53: 0 | AA53: =IFERROR(VLOOKUP(D53,'Monthly Deduction'!A:B,2,0),0) -> 0 | AB53: =ROUND(IFERROR(V53-SUM(W53:AA53),0),0) -> 12082 | AC53: 0 | AD53: =ROUND(AB53-AC53,0) -> 12082 | AE53: =IF(AC53<>0,"Yes","Release") -> Release | AG53: 0 | AI53: 0 | AK53: 1328.2 | AL53: =COUNTIF(AK53:AK53,"=NA") -> 0 | AN53: =((MIN(IF(A53>0,MAX(N53*2%,1861),0),A53)))+0 -> 0 | AO53: =SUMIF('MPG Payment '!E:E,'Shayak Income '!D53,'MPG Payment '!AJ:AJ) -> 0 | AP53: =W53 -> 0 | AQ53: =AO53+AP53 -> 0 | AS53: =B53-X53 -> 0
A54: =IFERROR(VLOOKUP(D54,'Monthly Deduction'!$I$3:$J$957,2,0),0) -> 10665.353 | B54: =IFERROR(VLOOKUP(D54,'Monthly Deduction'!$E$3:$F$957,2,0),0) -> 0 | C54: =A54+B54 -> 10665.353 | D54: 10020038 | E54: =VLOOKUP(D54,'MPG Payment '!$E$3:$G$498218,2,0) -> LODIYA | F54: =IFERROR(_xlfn.XLOOKUP(D54,'Monthly Deduction'!$I$3:$I$957,'Monthly Deduction'!$H$3:$H$957),0) -> 0 | G54: =VLOOKUP(D54,'MPG Payment '!$E$3:$G$334579,3,0) -> MPG | H54: =VLOOKUP(D54,'MPG Payment '!$E$3:$H$334579,4,0) -> Direct | I54: =INDEX('MPG Payment '!$C:$C,MATCH('Shayak Income '!D54,'MPG Payment '!E:E,0)) -> 1002 | J54: =INDEX('MPG Payment '!$D:$D,MATCH('Shayak Income '!D54,'MPG Payment '!E:E,0)) -> Laldiyara | K54: Old | L54: 44967 | M54: =SUMIF('MPG Payment '!$E$3:$E$34579,'Shayak Income '!D54,'MPG Payment '!$I$3:$I$34579) -> 2405 | N54: =SUMIF('MPG Payment '!$E$3:$E$34579,'Shayak Income '!D54,'MPG Payment '!$J$3:$J$34579) -> 95619.189 | O54: =+M54*0.75 -> 1803.75 | P54: =+M54*0.95 -> 2284.75 | Q54: =SUMIF('MPG Payment '!$E$3:$E$34579,'Shayak Income '!D54,'MPG Payment '!$S$3:$S$34579) -> 863.60406 | R54: =+N54*3% -> 2868.5757 | S54: =R54-P54 -> 583.82567 | T54: =M54*0.1 -> 240.5 | U54: =(((IF(K54="New",0,SUMIF('MPG Payment '!$E$3:$E$34579,'Shayak Income '!D54,'MPG Payment '!$AC$3:$AC$34579))))+0)+0 -> 313.06697 | V54: =ROUND((SUM(O54:Q54)-SUM(T54:U54)),0) -> 4399 | W54: =(((AN54-AO54)))+0 -> 1912.3838 | X54: 0 | Y54: =IFERROR(VLOOKUP(D54,'Monthly Deduction'!$M$2:$N$64,2,0),0) -> 0 | Z54: 0 | AA54: =IFERROR(VLOOKUP(D54,'Monthly Deduction'!A:B,2,0),0) -> 0 | AB54: =ROUND(IFERROR(V54-SUM(W54:AA54),0),0) -> 2487 | AC54: 0 | AD54: =ROUND(AB54-AC54,0) -> 2487 | AE54: =IF(AC54<>0,"Yes","Release") -> Release | AG54: 0 | AI54: 0 | AK54: 654.7 | AL54: =COUNTIF(AK54:AK54,"=NA") -> 0 | AN54: =((MIN(IF(A54>0,MAX(N54*2%,1861),0),A54)))+0 -> 1912.3838 | AO54: =SUMIF('MPG Payment '!E:E,'Shayak Income '!D54,'MPG Payment '!AJ:AJ) -> 0 | AP54: =W54 -> 1912.3838 | AQ54: =AO54+AP54 -> 1912.3838 | AS54: =B54-X54 -> 0
A55: =IFERROR(VLOOKUP(D55,'Monthly Deduction'!$I$3:$J$957,2,0),0) -> 696.24802 | B55: =IFERROR(VLOOKUP(D55,'Monthly Deduction'!$E$3:$F$957,2,0),0) -> 3752.6762 | C55: =A55+B55 -> 4448.9242 | D55: 10020041 | E55: =VLOOKUP(D55,'MPG Payment '!$E$3:$G$498218,2,0) -> ADARSH LAXMIPUR-3 | F55: =IFERROR(_xlfn.XLOOKUP(D55,'Monthly Deduction'!$I$3:$I$957,'Monthly Deduction'!$H$3:$H$957),0) -> 0 | G55: =VLOOKUP(D55,'MPG Payment '!$E$3:$G$334579,3,0) -> MPG | H55: =VLOOKUP(D55,'MPG Payment '!$E$3:$H$334579,4,0) -> Direct | I55: =INDEX('MPG Payment '!$C:$C,MATCH('Shayak Income '!D55,'MPG Payment '!E:E,0)) -> 1002 | J55: =INDEX('MPG Payment '!$D:$D,MATCH('Shayak Income '!D55,'MPG Payment '!E:E,0)) -> Laldiyara | K55: Old | L55: 44986 | M55: =SUMIF('MPG Payment '!$E$3:$E$34579,'Shayak Income '!D55,'MPG Payment '!$I$3:$I$34579) -> 1054.6 | N55: =SUMIF('MPG Payment '!$E$3:$E$34579,'Shayak Income '!D55,'MPG Payment '!$J$3:$J$34579) -> 44242.085 | O55: =+M55*0.75 -> 790.95 | P55: =+M55*0.95 -> 1001.87 | Q55: =SUMIF('MPG Payment '!$E$3:$E$34579,'Shayak Income '!D55,'MPG Payment '!$S$3:$S$34579) -> 189.18909 | R55: =+N55*3% -> 1327.2626 | S55: =R55-P55 -> 325.39255 | T55: =M55*0.1 -> 105.46 | U55: =(((IF(K55="New",0,SUMIF('MPG Payment '!$E$3:$E$34579,'Shayak Income '!D55,'MPG Payment '!$AC$3:$AC$34579))))+0)+0 -> 1463.7011 | V55: =ROUND((SUM(O55:Q55)-SUM(T55:U55)),0) -> 413 | W55: =(((AN55-AO55)))+0 -> 196.24802 | X55: 0 | Y55: 217 | Z55: 0 | AA55: 0 | AB55: =ROUND(IFERROR(V55-SUM(W55:AA55),0),0) -> 0 | AC55: 0 | AD55: =ROUND(AB55-AC55,0) -> 0 | AE55: =IF(AC55<>0,"Yes","Release") -> Release | AG55: 0 | AI55: 0 | AK55: 257.6 | AL55: =COUNTIF(AK55:AK55,"=NA") -> 0 | AN55: =((MIN(IF(A55>0,MAX(N55*2%,1861),0),A55)))+0 -> 696.24802 | AO55: =SUMIF('MPG Payment '!E:E,'Shayak Income '!D55,'MPG Payment '!AJ:AJ) -> 500 | AP55: =W55 -> 196.24802 | AQ55: =AO55+AP55 -> 696.24802 | AS55: =B55-X55 -> 3752.6762
A56: =IFERROR(VLOOKUP(D56,'Monthly Deduction'!$I$3:$J$957,2,0),0) -> 7224.8759 | B56: =IFERROR(VLOOKUP(D56,'Monthly Deduction'!$E$3:$F$957,2,0),0) -> 8907 | C56: =A56+B56 -> 16131.876 | D56: 10020042 | E56: =VLOOKUP(D56,'MPG Payment '!$E$3:$G$498218,2,0) -> BHANPUR | F56: =IFERROR(_xlfn.XLOOKUP(D56,'Monthly Deduction'!$I$3:$I$957,'Monthly Deduction'!$H$3:$H$957),0) -> 0 | G56: =VLOOKUP(D56,'MPG Payment '!$E$3:$G$334579,3,0) -> MPG | H56: =VLOOKUP(D56,'MPG Payment '!$E$3:$H$334579,4,0) -> Direct | I56: =INDEX('MPG Payment '!$C:$C,MATCH('Shayak Income '!D56,'MPG Payment '!E:E,0)) -> 1002 | J56: =INDEX('MPG Payment '!$D:$D,MATCH('Shayak Income '!D56,'MPG Payment '!E:E,0)) -> Laldiyara | K56: Old | L56: 45009 | M56: =SUMIF('MPG Payment '!$E$3:$E$34579,'Shayak Income '!D56,'MPG Payment '!$I$3:$I$34579) -> 1856 | N56: =SUMIF('MPG Payment '!$E$3:$E$34579,'Shayak Income '!D56,'MPG Payment '!$J$3:$J$34579) -> 69698.654 | O56: =+M56*0.75 -> 1392 | P56: =+M56*0.95 -> 1763.2 | Q56: =SUMIF('MPG Payment '!$E$3:$E$34579,'Shayak Income '!D56,'MPG Payment '!$S$3:$S$34579) -> 0 | R56: =+N56*3% -> 2090.9596 | S56: =R56-P56 -> 327.75961 | T56: =M56*0.1 -> 185.6 | U56: =(((IF(K56="New",0,SUMIF('MPG Payment '!$E$3:$E$34579,'Shayak Income '!D56,'MPG Payment '!$AC$3:$AC$34579))))+0)+0 -> 709.28626 | V56: =ROUND((SUM(O56:Q56)-SUM(T56:U56)),0) -> 2260 | W56: =(((AN56-AO56)))+0 -> 1861 | X56: 0 | Y56: =IFERROR(VLOOKUP(D56,'Monthly Deduction'!$M$2:$N$64,2,0),0) -> 0 | Z56: 0 | AA56: =IFERROR(VLOOKUP(D56,'Monthly Deduction'!A:B,2,0),0) -> 0 | AB56: =ROUND(IFERROR(V56-SUM(W56:AA56),0),0) -> 399 | AC56: 0 | AD56: =ROUND(AB56-AC56,0) -> 399 | AE56: =IF(AC56<>0,"Yes","Release") -> Release | AG56: 0 | AI56: 0 | AK56: 494.7 | AL56: =COUNTIF(AK56:AK56,"=NA") -> 0 | AN56: =((MIN(IF(A56>0,MAX(N56*2%,1861),0),A56)))+0 -> 1861 | AO56: =SUMIF('MPG Payment '!E:E,'Shayak Income '!D56,'MPG Payment '!AJ:AJ) -> 0 | AP56: =W56 -> 1861 | AQ56: =AO56+AP56 -> 1861 | AS56: =B56-X56 -> 8907
A57: =IFERROR(VLOOKUP(D57,'Monthly Deduction'!$I$3:$J$957,2,0),0) -> 0 | B57: =IFERROR(VLOOKUP(D57,'Monthly Deduction'!$E$3:$F$957,2,0),0) -> 0 | C57: =A57+B57 -> 0 | D57: 10020043 | E57: =VLOOKUP(D57,'MPG Payment '!$E$3:$G$498218,2,0) -> Karari Pipariya 2 | F57: =IFERROR(_xlfn.XLOOKUP(D57,'Monthly Deduction'!$I$3:$I$957,'Monthly Deduction'!$H$3:$H$957),0) -> 0 | G57: =VLOOKUP(D57,'MPG Payment '!$E$3:$G$334579,3,0) -> MPG | H57: =VLOOKUP(D57,'MPG Payment '!$E$3:$H$334579,4,0) -> Direct | I57: =INDEX('MPG Payment '!$C:$C,MATCH('Shayak Income '!D57,'MPG Payment '!E:E,0)) -> 1002 | J57: =INDEX('MPG Payment '!$D:$D,MATCH('Shayak Income '!D57,'MPG Payment '!E:E,0)) -> Laldiyara | K57: Old | L57: 45012 | M57: =SUMIF('MPG Payment '!$E$3:$E$34579,'Shayak Income '!D57,'MPG Payment '!$I$3:$I$34579) -> 4150.5 | N57: =SUMIF('MPG Payment '!$E$3:$E$34579,'Shayak Income '!D57,'MPG Payment '!$J$3:$J$34579) -> 173231.82 | O57: =+M57*0.75 -> 3112.875 | P57: =+M57*0.95 -> 3942.975 | Q57: =SUMIF('MPG Payment '!$E$3:$E$34579,'Shayak Income '!D57,'MPG Payment '!$S$3:$S$34579) -> 1547.3361 | R57: =+N57*3% -> 5196.9546 | S57: =R57-P57 -> 1253.9796 | T57: =M57*0.1 -> 415.05 | U57: =(((IF(K57="New",0,SUMIF('MPG Payment '!$E$3:$E$34579,'Shayak Income '!D57,'MPG Payment '!$AC$3:$AC$34579))))+0)+0 -> 0 | V57: =ROUND((SUM(O57:Q57)-SUM(T57:U57)),0) -> 8188 | W57: =(((AN57-AO57)))+0 -> 0 | X57: =((MIN(IF(B57>0,MAX(N57*2%),0),B57)))+0 -> 0 | Y57: =IFERROR(VLOOKUP(D57,'Monthly Deduction'!$M$2:$N$64,2,0),0) -> 0 | Z57: 5600 | AA57: =IFERROR(VLOOKUP(D57,'Monthly Deduction'!A:B,2,0),0) -> 0 | AB57: =ROUND(IFERROR(V57-SUM(W57:AA57),0),0) -> 2588 | AC57: 0 | AD57: =ROUND(AB57-AC57,0) -> 2588 | AE57: =IF(AC57<>0,"Yes","Release") -> Release | AG57: 0 | AH57: BIO-GAS | AI57: 0 | AK57: 1159.1 | AL57: =COUNTIF(AK57:AK57,"=NA") -> 0 | AN57: =((MIN(IF(A57>0,MAX(N57*2%,1861),0),A57)))+0 -> 0 | AO57: =SUMIF('MPG Payment '!E:E,'Shayak Income '!D57,'MPG Payment '!AJ:AJ) -> 0 | AP57: =W57 -> 0 | AQ57: =AO57+AP57 -> 0 | AS57: =B57-X57 -> 0
A58: =IFERROR(VLOOKUP(D58,'Monthly Deduction'!$I$3:$J$957,2,0),0) -> 0 | B58: =IFERROR(VLOOKUP(D58,'Monthly Deduction'!$E$3:$F$957,2,0),0) -> 0 | C58: =A58+B58 -> 0 | D58: 10020044 | E58: =VLOOKUP(D58,'MPG Payment '!$E$3:$G$498218,2,0) -> DIYARA PIPARIYA-THANA | F58: =IFERROR(_xlfn.XLOOKUP(D58,'Monthly Deduction'!$I$3:$I$957,'Monthly Deduction'!$H$3:$H$957),0) -> 0 | G58: =VLOOKUP(D58,'MPG Payment '!$E$3:$G$334579,3,0) -> MPG | H58: =VLOOKUP(D58,'MPG Payment '!$E$3:$H$334579,4,0) -> Direct | I58: =INDEX('MPG Payment '!$C:$C,MATCH('Shayak Income '!D58,'MPG Payment '!E:E,0)) -> 1002 | J58: =INDEX('MPG Payment '!$D:$D,MATCH('Shayak Income '!D58,'MPG Payment '!E:E,0)) -> Laldiyara | K58: Old | L58: 45064 | M58: =SUMIF('MPG Payment '!$E$3:$E$34579,'Shayak Income '!D58,'MPG Payment '!$I$3:$I$34579) -> 4586.6 | N58: =SUMIF('MPG Payment '!$E$3:$E$34579,'Shayak Income '!D58,'MPG Payment '!$J$3:$J$34579) -> 201372.12 | O58: =+M58*0.75 -> 3439.95 | P58: =+M58*0.95 -> 4357.27 | Q58: =SUMIF('MPG Payment '!$E$3:$E$34579,'Shayak Income '!D58,'MPG Payment '!$S$3:$S$34579) -> 1376.2222 | R58: =+N58*3% -> 6041.1637 | S58: =R58-P58 -> 1683.8937 | T58: =M58*0.1 -> 458.66 | U58: =(((IF(K58="New",0,SUMIF('MPG Payment '!$E$3:$E$34579,'Shayak Income '!D58,'MPG Payment '!$AC$3:$AC$34579))))+0)+0 -> 0 | V58: =ROUND((SUM(O58:Q58)-SUM(T58:U58)),0) -> 8715 | W58: =(((AN58-AO58)))+0 -> 0 | X58: =((MIN(IF(B58>0,MAX(N58*2%),0),B58)))+0 -> 0 | Y58: =IFERROR(VLOOKUP(D58,'Monthly Deduction'!$M$2:$N$64,2,0),0) -> 0 | Z58: 0 | AA58: =IFERROR(VLOOKUP(D58,'Monthly Deduction'!A:B,2,0),0) -> 0 | AB58: =ROUND(IFERROR(V58-SUM(W58:AA58),0),0) -> 8715 | AC58: 0 | AD58: =ROUND(AB58-AC58,0) -> 8715 | AE58: =IF(AC58<>0,"Yes","Release") -> Release | AG58: 0 | AI58: 0 | AK58: 1165.8 | AL58: =COUNTIF(AK58:AK58,"=NA") -> 0 | AN58: =((MIN(IF(A58>0,MAX(N58*2%,1861),0),A58)))+0 -> 0 | AO58: =SUMIF('MPG Payment '!E:E,'Shayak Income '!D58,'MPG Payment '!AJ:AJ) -> 0 | AP58: =W58 -> 0 | AQ58: =AO58+AP58 -> 0 | AS58: =B58-X58 -> 0
A59: =IFERROR(VLOOKUP(D59,'Monthly Deduction'!$I$3:$J$957,2,0),0) -> 0 | B59: =IFERROR(VLOOKUP(D59,'Monthly Deduction'!$E$3:$F$957,2,0),0) -> 0 | C59: =A59+B59 -> 0 | D59: 10020047 | E59: =VLOOKUP(D59,'MPG Payment '!$E$3:$G$498218,2,0) -> SRI RAM SINGH(VLC) | F59: =IFERROR(_xlfn.XLOOKUP(D59,'Monthly Deduction'!$I$3:$I$957,'Monthly Deduction'!$H$3:$H$957),0) -> 0 | G59: =VLOOKUP(D59,'MPG Payment '!$E$3:$G$334579,3,0) -> vlc | H59: =VLOOKUP(D59,'MPG Payment '!$E$3:$H$334579,4,0) -> Indirect | I59: =INDEX('MPG Payment '!$C:$C,MATCH('Shayak Income '!D59,'MPG Payment '!E:E,0)) -> 1002 | J59: =INDEX('MPG Payment '!$D:$D,MATCH('Shayak Income '!D59,'MPG Payment '!E:E,0)) -> Laldiyara | K59: Old | L59: 45156 | M59: =SUMIF('MPG Payment '!$E$3:$E$34579,'Shayak Income '!D59,'MPG Payment '!$I$3:$I$34579) -> 14198.7 | N59: =SUMIF('MPG Payment '!$E$3:$E$34579,'Shayak Income '!D59,'MPG Payment '!$J$3:$J$34579) -> 573865.64 | O59: =+M59*0.75 -> 10649.025 | P59: =+M59*0.95 -> 13488.765 | Q59: =SUMIF('MPG Payment '!$E$3:$E$34579,'Shayak Income '!D59,'MPG Payment '!$S$3:$S$34579) -> 0 | R59: =+N59*3% -> 17215.969 | S59: =R59-P59 -> 3727.2042 | T59: =M59*0.1 -> 1419.87 | U59: =(((IF(K59="New",0,SUMIF('MPG Payment '!$E$3:$E$34579,'Shayak Income '!D59,'MPG Payment '!$AC$3:$AC$34579))))+0)+0 -> 0 | V59: =ROUND((SUM(O59:Q59)-SUM(T59:U59)),0) -> 22718 | W59: =(((AN59-AO59)))+0 -> 0 | X59: =((MIN(IF(B59>0,MAX(N59*2%),0),B59)))+0 -> 0 | Y59: =IFERROR(VLOOKUP(D59,'Monthly Deduction'!$M$2:$N$64,2,0),0) -> 0 | Z59: 0 | AA59: =IFERROR(VLOOKUP(D59,'Monthly Deduction'!A:B,2,0),0) -> 0 | AB59: =ROUND(IFERROR(V59-SUM(W59:AA59),0),0) -> 22718 | AC59: 0 | AD59: =ROUND(AB59-AC59,0) -> 22718 | AE59: =IF(AC59<>0,"Yes","Release") -> Release | AG59: 0 | AI59: 0 | AK59: 2819.3 | AL59: =COUNTIF(AK59:AK59,"=NA") -> 0 | AN59: =((MIN(IF(A59>0,MAX(N59*2%,1861),0),A59)))+0 -> 0 | AO59: =SUMIF('MPG Payment '!E:E,'Shayak Income '!D59,'MPG Payment '!AJ:AJ) -> 0 | AP59: =W59 -> 0 | AQ59: =AO59+AP59 -> 0 | AS59: =B59-X59 -> 0
A60: =IFERROR(VLOOKUP(D60,'Monthly Deduction'!$I$3:$J$957,2,0),0) -> 0 | B60: =IFERROR(VLOOKUP(D60,'Monthly Deduction'!$E$3:$F$957,2,0),0) -> 0 | C60: =A60+B60 -> 0 | D60: 10020050 | E60: =VLOOKUP(D60,'MPG Payment '!$E$3:$G$498218,2,0) -> GADHTOLA | F60: =IFERROR(_xlfn.XLOOKUP(D60,'Monthly Deduction'!$I$3:$I$957,'Monthly Deduction'!$H$3:$H$957),0) -> 0 | G60: =VLOOKUP(D60,'MPG Payment '!$E$3:$G$334579,3,0) -> MPG | H60: =VLOOKUP(D60,'MPG Payment '!$E$3:$H$334579,4,0) -> Direct | I60: =INDEX('MPG Payment '!$C:$C,MATCH('Shayak Income '!D60,'MPG Payment '!E:E,0)) -> 1002 | J60: =INDEX('MPG Payment '!$D:$D,MATCH('Shayak Income '!D60,'MPG Payment '!E:E,0)) -> Laldiyara | K60: Old | L60: 45168 | M60: =SUMIF('MPG Payment '!$E$3:$E$34579,'Shayak Income '!D60,'MPG Payment '!$I$3:$I$34579) -> 4232.5 | N60: =SUMIF('MPG Payment '!$E$3:$E$34579,'Shayak Income '!D60,'MPG Payment '!$J$3:$J$34579) -> 171365.7 | O60: =+M60*0.75 -> 3174.375 | P60: =+M60*0.95 -> 4020.875 | Q60: =SUMIF('MPG Payment '!$E$3:$E$34579,'Shayak Income '!D60,'MPG Payment '!$S$3:$S$34579) -> 749.27021 | R60: =+N60*3% -> 5140.9709 | S60: =R60-P60 -> 1120.0959 | T60: =M60*0.1 -> 423.25 | U60: =(((IF(K60="New",0,SUMIF('MPG Payment '!$E$3:$E$34579,'Shayak Income '!D60,'MPG Payment '!$AC$3:$AC$34579))))+0)+0 -> 0 | V60: =ROUND((SUM(O60:Q60)-SUM(T60:U60)),0) -> 7521 | W60: =(((AN60-AO60)))+0 -> 0 | X60: =((MIN(IF(B60>0,MAX(N60*2%),0),B60)))+0 -> 0 | Y60: =IFERROR(VLOOKUP(D60,'Monthly Deduction'!$M$2:$N$64,2,0),0) -> 0 | Z60: 0 | AA60: =IFERROR(VLOOKUP(D60,'Monthly Deduction'!A:B,2,0),0) -> 0 | AB60: =ROUND(IFERROR(V60-SUM(W60:AA60),0),0) -> 7521 | AC60: 0 | AD60: =ROUND(AB60-AC60,0) -> 7521 | AE60: =IF(AC60<>0,"Yes","Release") -> Release | AG60: 0 | AI60: 0 | AK60: 1614.4 | AL60: =COUNTIF(AK60:AK60,"=NA") -> 0 | AN60: =((MIN(IF(A60>0,MAX(N60*2%,1861),0),A60)))+0 -> 0 | AO60: =SUMIF('MPG Payment '!E:E,'Shayak Income '!D60,'MPG Payment '!AJ:AJ) -> 0 | AP60: =W60 -> 0 | AQ60: =AO60+AP60 -> 0 | AS60: =B60-X60 -> 0
A61: =IFERROR(VLOOKUP(D61,'Monthly Deduction'!$I$3:$J$957,2,0),0) -> 0 | B61: =IFERROR(VLOOKUP(D61,'Monthly Deduction'!$E$3:$F$957,2,0),0) -> 0 | C61: =A61+B61 -> 0 | D61: 10020054 | E61: =VLOOKUP(D61,'MPG Payment '!$E$3:$G$498218,2,0) -> Diyara-Pipariya-Utri - Chandan | F61: =IFERROR(_xlfn.XLOOKUP(D61,'Monthly Deduction'!$I$3:$I$957,'Monthly Deduction'!$H$3:$H$957),0) -> 0 | G61: =VLOOKUP(D61,'MPG Payment '!$E$3:$G$334579,3,0) -> vlc | H61: =VLOOKUP(D61,'MPG Payment '!$E$3:$H$334579,4,0) -> Indirect | I61: =INDEX('MPG Payment '!$C:$C,MATCH('Shayak Income '!D61,'MPG Payment '!E:E,0)) -> 1002 | J61: =INDEX('MPG Payment '!$D:$D,MATCH('Shayak Income '!D61,'MPG Payment '!E:E,0)) -> Laldiyara | K61: Old | L61: 44710 | M61: =SUMIF('MPG Payment '!$E$3:$E$34579,'Shayak Income '!D61,'MPG Payment '!$I$3:$I$34579) -> 4321.8 | N61: =SUMIF('MPG Payment '!$E$3:$E$34579,'Shayak Income '!D61,'MPG Payment '!$J$3:$J$34579) -> 175498.89 | O61: =+M61*0.75 -> 3241.35 | P61: =+M61*0.95 -> 4105.71 | Q61: =SUMIF('MPG Payment '!$E$3:$E$34579,'Shayak Income '!D61,'MPG Payment '!$S$3:$S$34579) -> 0 | R61: =+N61*3% -> 5264.9668 | S61: =R61-P61 -> 1159.2568 | T61: =M61*0.1 -> 432.18 | U61: =(((IF(K61="New",0,SUMIF('MPG Payment '!$E$3:$E$34579,'Shayak Income '!D61,'MPG Payment '!$AC$3:$AC$34579))))+0)+0 -> 220.3049 | V61: =ROUND((SUM(O61:Q61)-SUM(T61:U61)),0) -> 6695 | W61: =(((AN61-AO61)))+0 -> 0 | X61: =((MIN(IF(B61>0,MAX(N61*2%),0),B61)))+0 -> 0 | Y61: =IFERROR(VLOOKUP(D61,'Monthly Deduction'!$M$2:$N$64,2,0),0) -> 0 | Z61: 0 | AA61: =IFERROR(VLOOKUP(D61,'Monthly Deduction'!A:B,2,0),0) -> 0 | AB61: =ROUND(IFERROR(V61-SUM(W61:AA61),0),0) -> 6695 | AC61: 0 | AD61: =ROUND(AB61-AC61,0) -> 6695 | AE61: =IF(AC61<>0,"Yes","Release") -> Release | AG61: 0 | AI61: 0 | AK61: 1619.2 | AL61: =COUNTIF(AK61:AK61,"=NA") -> 0 | AN61: =((MIN(IF(A61>0,MAX(N61*2%,1861),0),A61)))+0 -> 0 | AO61: =SUMIF('MPG Payment '!E:E,'Shayak Income '!D61,'MPG Payment '!AJ:AJ) -> 0 | AP61: =W61 -> 0 | AQ61: =AO61+AP61 -> 0 | AS61: =B61-X61 -> 0
A62: =IFERROR(VLOOKUP(D62,'Monthly Deduction'!$I$3:$J$957,2,0),0) -> 0 | B62: =IFERROR(VLOOKUP(D62,'Monthly Deduction'!$E$3:$F$957,2,0),0) -> 0 | C62: =A62+B62 -> 0 | D62: 10020057 | E62: =VLOOKUP(D62,'MPG Payment '!$E$3:$G$498218,2,0) -> KANHARPUR-2 | F62: =IFERROR(_xlfn.XLOOKUP(D62,'Monthly Deduction'!$I$3:$I$957,'Monthly Deduction'!$H$3:$H$957),0) -> 0 | G62: =VLOOKUP(D62,'MPG Payment '!$E$3:$G$334579,3,0) -> MPG | H62: =VLOOKUP(D62,'MPG Payment '!$E$3:$H$334579,4,0) -> Direct | I62: =INDEX('MPG Payment '!$C:$C,MATCH('Shayak Income '!D62,'MPG Payment '!E:E,0)) -> 1002 | J62: =INDEX('MPG Payment '!$D:$D,MATCH('Shayak Income '!D62,'MPG Payment '!E:E,0)) -> Laldiyara | K62: Old | L62: 45248 | M62: =SUMIF('MPG Payment '!$E$3:$E$34579,'Shayak Income '!D62,'MPG Payment '!$I$3:$I$34579) -> 11300.5 | N62: =SUMIF('MPG Payment '!$E$3:$E$34579,'Shayak Income '!D62,'MPG Payment '!$J$3:$J$34579) -> 492448.5 | O62: =+M62*0.75 -> 8475.375 | P62: =+M62*0.95 -> 10735.475 | Q62: =SUMIF('MPG Payment '!$E$3:$E$34579,'Shayak Income '!D62,'MPG Payment '!$S$3:$S$34579) -> 6391.6614 | R62: =+N62*3% -> 14773.455 | S62: =R62-P62 -> 4037.9801 | T62: =M62*0.1 -> 1130.05 | U62: =(((IF(K62="New",0,SUMIF('MPG Payment '!$E$3:$E$34579,'Shayak Income '!D62,'MPG Payment '!$AC$3:$AC$34579))))+0)+0 -> 0 | V62: =ROUND((SUM(O62:Q62)-SUM(T62:U62)),0) -> 24472 | W62: =(((AN62-AO62)))+0 -> 0 | X62: =((MIN(IF(B62>0,MAX(N62*2%),0),B62)))+0 -> 0 | Y62: =IFERROR(VLOOKUP(D62,'Monthly Deduction'!$M$2:$N$64,2,0),0) -> 0 | Z62: 0 | AA62: =IFERROR(VLOOKUP(D62,'Monthly Deduction'!A:B,2,0),0) -> 0 | AB62: =ROUND(IFERROR(V62-SUM(W62:AA62),0),0) -> 24472 | AC62: 0 | AD62: =ROUND(AB62-AC62,0) -> 24472 | AE62: =IF(AC62<>0,"Yes","Release") -> Release | AG62: 0 | AI62: 0 | AK62: 2837.7 | AL62: =COUNTIF(AK62:AK62,"=NA") -> 0 | AN62: =((MIN(IF(A62>0,MAX(N62*2%,1861),0),A62)))+0 -> 0 | AO62: =SUMIF('MPG Payment '!E:E,'Shayak Income '!D62,'MPG Payment '!AJ:AJ) -> 0 | AP62: =W62 -> 0 | AQ62: =AO62+AP62 -> 0 | AS62: =B62-X62 -> 0
A63: =IFERROR(VLOOKUP(D63,'Monthly Deduction'!$I$3:$J$957,2,0),0) -> 0 | B63: =IFERROR(VLOOKUP(D63,'Monthly Deduction'!$E$3:$F$957,2,0),0) -> 5844.2936 | C63: =A63+B63 -> 5844.2936 | D63: 10020058 | E63: =VLOOKUP(D63,'MPG Payment '!$E$3:$G$498218,2,0) -> BASAUNA | F63: =IFERROR(_xlfn.XLOOKUP(D63,'Monthly Deduction'!$I$3:$I$957,'Monthly Deduction'!$H$3:$H$957),0) -> 0 | G63: =VLOOKUP(D63,'MPG Payment '!$E$3:$G$334579,3,0) -> MPG | H63: =VLOOKUP(D63,'MPG Payment '!$E$3:$H$334579,4,0) -> Direct | I63: =INDEX('MPG Payment '!$C:$C,MATCH('Shayak Income '!D63,'MPG Payment '!E:E,0)) -> 1002 | J63: =INDEX('MPG Payment '!$D:$D,MATCH('Shayak Income '!D63,'MPG Payment '!E:E,0)) -> Laldiyara | K63: Old | L63: 45283 | M63: =SUMIF('MPG Payment '!$E$3:$E$34579,'Shayak Income '!D63,'MPG Payment '!$I$3:$I$34579) -> 3914 | N63: =SUMIF('MPG Payment '!$E$3:$E$34579,'Shayak Income '!D63,'MPG Payment '!$J$3:$J$34579) -> 156649.62 | O63: =+M63*0.75 -> 2935.5 | P63: =+M63*0.95 -> 3718.3 | Q63: =SUMIF('MPG Payment '!$E$3:$E$34579,'Shayak Income '!D63,'MPG Payment '!$S$3:$S$34579) -> 921.86857 | R63: =+N63*3% -> 4699.4885 | S63: =R63-P63 -> 981.18847 | T63: =M63*0.1 -> 391.4 | U63: =(((IF(K63="New",0,SUMIF('MPG Payment '!$E$3:$E$34579,'Shayak Income '!D63,'MPG Payment '!$AC$3:$AC$34579))))+0)+0 -> 0 | V63: =ROUND((SUM(O63:Q63)-SUM(T63:U63)),0) -> 7184 | W63: =(((AN63-AO63)))+0 -> 0 | X63: =((MIN(IF(B63>0,MAX(N63*2%),0),B63)))+0 -> 3132.9923 | Y63: =IFERROR(VLOOKUP(D63,'Monthly Deduction'!$M$2:$N$64,2,0),0) -> 0 | Z63: 0 | AA63: =IFERROR(VLOOKUP(D63,'Monthly Deduction'!A:B,2,0),0) -> 0 | AB63: =ROUND(IFERROR(V63-SUM(W63:AA63),0),0) -> 4051 | AC63: 0 | AD63: =ROUND(AB63-AC63,0) -> 4051 | AE63: =IF(AC63<>0,"Yes","Release") -> Release | AG63: 0 | AI63: 0 | AK63: 1040.1 | AL63: =COUNTIF(AK63:AK63,"=NA") -> 0 | AN63: =((MIN(IF(A63>0,MAX(N63*2%,1861),0),A63)))+0 -> 0 | AO63: =SUMIF('MPG Payment '!E:E,'Shayak Income '!D63,'MPG Payment '!AJ:AJ) -> 0 | AP63: =W63 -> 0 | AQ63: =AO63+AP63 -> 0 | AS63: =B63-X63 -> 2711.3013
A64: =IFERROR(VLOOKUP(D64,'Monthly Deduction'!$I$3:$J$957,2,0),0) -> 5297.5668 | B64: =IFERROR(VLOOKUP(D64,'Monthly Deduction'!$E$3:$F$957,2,0),0) -> 12800 | C64: =A64+B64 -> 18097.567 | D64: 10020059 | E64: =VLOOKUP(D64,'MPG Payment '!$E$3:$G$498218,2,0) -> GANGA-SARAI | F64: =IFERROR(_xlfn.XLOOKUP(D64,'Monthly Deduction'!$I$3:$I$957,'Monthly Deduction'!$H$3:$H$957),0) -> 0 | G64: =VLOOKUP(D64,'MPG Payment '!$E$3:$G$334579,3,0) -> MPG | H64: =VLOOKUP(D64,'MPG Payment '!$E$3:$H$334579,4,0) -> Direct | I64: =INDEX('MPG Payment '!$C:$C,MATCH('Shayak Income '!D64,'MPG Payment '!E:E,0)) -> 1002 | J64: =INDEX('MPG Payment '!$D:$D,MATCH('Shayak Income '!D64,'MPG Payment '!E:E,0)) -> Laldiyara | K64: Old | L64: 45268 | M64: =SUMIF('MPG Payment '!$E$3:$E$34579,'Shayak Income '!D64,'MPG Payment '!$I$3:$I$34579) -> 5251.4 | N64: =SUMIF('MPG Payment '!$E$3:$E$34579,'Shayak Income '!D64,'MPG Payment '!$J$3:$J$34579) -> 209452.65 | O64: =+M64*0.75 -> 3938.55 | P64: =+M64*0.95 -> 4988.83 | Q64: =SUMIF('MPG Payment '!$E$3:$E$34579,'Shayak Income '!D64,'MPG Payment '!$S$3:$S$34579) -> 1995.9258 | R64: =+N64*3% -> 6283.5796 | S64: =R64-P64 -> 1294.7496 | T64: =M64*0.1 -> 525.14 | U64: =(((IF(K64="New",0,SUMIF('MPG Payment '!$E$3:$E$34579,'Shayak Income '!D64,'MPG Payment '!$AC$3:$AC$34579))))+0)+0 -> 0 | V64: =ROUND((SUM(O64:Q64)-SUM(T64:U64)),0) -> 10398 | W64: =(((AN64-AO64)))+0 -> 4189.0531 | X64: 0 | Y64: =IFERROR(VLOOKUP(D64,'Monthly Deduction'!$M$2:$N$64,2,0),0) -> 0 | Z64: 0 | AA64: =IFERROR(VLOOKUP(D64,'Monthly Deduction'!A:B,2,0),0) -> 0 | AB64: =ROUND(IFERROR(V64-SUM(W64:AA64),0),0) -> 6209 | AC64: 0 | AD64: =ROUND(AB64-AC64,0) -> 6209 | AE64: =IF(AC64<>0,"Yes","Release") -> Release | AG64: 0 | AI64: 0 | AK64: 1541.6 | AL64: =COUNTIF(AK64:AK64,"=NA") -> 0 | AN64: =((MIN(IF(A64>0,MAX(N64*2%,1861),0),A64)))+0 -> 4189.0531 | AO64: =SUMIF('MPG Payment '!E:E,'Shayak Income '!D64,'MPG Payment '!AJ:AJ) -> 0 | AP64: =W64 -> 4189.0531 | AQ64: =AO64+AP64 -> 4189.0531 | AS64: =B64-X64 -> 12800
A65: =IFERROR(VLOOKUP(D65,'Monthly Deduction'!$I$3:$J$957,2,0),0) -> 26623.522 | B65: =IFERROR(VLOOKUP(D65,'Monthly Deduction'!$E$3:$F$957,2,0),0) -> 11212.327 | C65: =A65+B65 -> 37835.849 | D65: 10020062 | E65: =VLOOKUP(D65,'MPG Payment '!$E$3:$G$498218,2,0) -> GOVIND-BIGHA | F65: =IFERROR(_xlfn.XLOOKUP(D65,'Monthly Deduction'!$I$3:$I$957,'Monthly Deduction'!$H$3:$H$957),0) -> 0 | G65: =VLOOKUP(D65,'MPG Payment '!$E$3:$G$334579,3,0) -> MPG | H65: =VLOOKUP(D65,'MPG Payment '!$E$3:$H$334579,4,0) -> Direct | I65: =INDEX('MPG Payment '!$C:$C,MATCH('Shayak Income '!D65,'MPG Payment '!E:E,0)) -> 1002 | J65: =INDEX('MPG Payment '!$D:$D,MATCH('Shayak Income '!D65,'MPG Payment '!E:E,0)) -> Laldiyara | K65: Old | L65: 45205 | M65: =SUMIF('MPG Payment '!$E$3:$E$34579,'Shayak Income '!D65,'MPG Payment '!$I$3:$I$34579) -> 1356.7 | N65: =SUMIF('MPG Payment '!$E$3:$E$34579,'Shayak Income '!D65,'MPG Payment '!$J$3:$J$34579) -> 54309.509 | O65: =+M65*0.75 -> 1017.525 | P65: =+M65*0.95 -> 1288.865 | Q65: =SUMIF('MPG Payment '!$E$3:$E$34579,'Shayak Income '!D65,'MPG Payment '!$S$3:$S$34579) -> 737.22626 | R65: =+N65*3% -> 1629.2853 | S65: =R65-P65 -> 340.42026 | T65: =M65*0.1 -> 135.67 | U65: =(((IF(K65="New",0,SUMIF('MPG Payment '!$E$3:$E$34579,'Shayak Income '!D65,'MPG Payment '!$AC$3:$AC$34579))))+0)+0 -> 1157.4707 | V65: =ROUND((SUM(O65:Q65)-SUM(T65:U65)),0) -> 1750 | W65: 1750 | X65: 0 | Y65: =IFERROR(VLOOKUP(D65,'Monthly Deduction'!$M$2:$N$64,2,0),0) -> 0 | Z65: 0 | AA65: =IFERROR(VLOOKUP(D65,'Monthly Deduction'!A:B,2,0),0) -> 0 | AB65: =ROUND(IFERROR(V65-SUM(W65:AA65),0),0) -> 0 | AC65: 0 | AD65: =ROUND(AB65-AC65,0) -> 0 | AE65: =IF(AC65<>0,"Yes","Release") -> Release | AG65: 0 | AI65: 0 | AK65: 352.5 | AL65: =COUNTIF(AK65:AK65,"=NA") -> 0 | AN65: =((MIN(IF(A65>0,MAX(N65*2%,1861),0),A65)))+0 -> 1861 | AO65: =SUMIF('MPG Payment '!E:E,'Shayak Income '!D65,'MPG Payment '!AJ:AJ) -> 0 | AP65: =W65 -> 1750 | AQ65: =AO65+AP65 -> 1750 | AS65: =B65-X65 -> 11212.327
A66: =IFERROR(VLOOKUP(D66,'Monthly Deduction'!$I$3:$J$957,2,0),0) -> 0 | B66: =IFERROR(VLOOKUP(D66,'Monthly Deduction'!$E$3:$F$957,2,0),0) -> 0 | C66: =A66+B66 -> 0 | D66: 10020063 | E66: =VLOOKUP(D66,'MPG Payment '!$E$3:$G$498218,2,0) -> MALPUR | F66: =IFERROR(_xlfn.XLOOKUP(D66,'Monthly Deduction'!$I$3:$I$957,'Monthly Deduction'!$H$3:$H$957),0) -> 0 | G66: =VLOOKUP(D66,'MPG Payment '!$E$3:$G$334579,3,0) -> MPG | H66: =VLOOKUP(D66,'MPG Payment '!$E$3:$H$334579,4,0) -> Direct | I66: =INDEX('MPG Payment '!$C:$C,MATCH('Shayak Income '!D66,'MPG Payment '!E:E,0)) -> 1002 | J66: =INDEX('MPG Payment '!$D:$D,MATCH('Shayak Income '!D66,'MPG Payment '!E:E,0)) -> Laldiyara | K66: Old | L66: 45198 | M66: =SUMIF('MPG Payment '!$E$3:$E$34579,'Shayak Income '!D66,'MPG Payment '!$I$3:$I$34579) -> 4637.6 | N66: =SUMIF('MPG Payment '!$E$3:$E$34579,'Shayak Income '!D66,'MPG Payment '!$J$3:$J$34579) -> 193388.88 | O66: =+M66*0.75 -> 3478.2 | P66: =+M66*0.95 -> 4405.72 | Q66: =SUMIF('MPG Payment '!$E$3:$E$34579,'Shayak Income '!D66,'MPG Payment '!$S$3:$S$34579) -> 1231.526 | R66: =+N66*3% -> 5801.6663 | S66: =R66-P66 -> 1395.9463 | T66: =M66*0.1 -> 463.76 | U66: =(((IF(K66="New",0,SUMIF('MPG Payment '!$E$3:$E$34579,'Shayak Income '!D66,'MPG Payment '!$AC$3:$AC$34579))))+0)+0 -> 0 | V66: =ROUND((SUM(O66:Q66)-SUM(T66:U66)),0) -> 8652 | W66: =(((AN66-AO66)))+0 -> 0 | X66: =((MIN(IF(B66>0,MAX(N66*2%),0),B66)))+0 -> 0 | Y66: =IFERROR(VLOOKUP(D66,'Monthly Deduction'!$M$2:$N$64,2,0),0) -> 0 | Z66: 0 | AA66: =IFERROR(VLOOKUP(D66,'Monthly Deduction'!A:B,2,0),0) -> 0 | AB66: =ROUND(IFERROR(V66-SUM(W66:AA66),0),0) -> 8652 | AC66: 0 | AD66: =ROUND(AB66-AC66,0) -> 8652 | AE66: =IF(AC66<>0,"Yes","Release") -> Release | AG66: 0 | AI66: 0 | AK66: 1122.6 | AL66: =COUNTIF(AK66:AK66,"=NA") -> 0 | AN66: =((MIN(IF(A66>0,MAX(N66*2%,1861),0),A66)))+0 -> 0 | AO66: =SUMIF('MPG Payment '!E:E,'Shayak Income '!D66,'MPG Payment '!AJ:AJ) -> 0 | AP66: =W66 -> 0 | AQ66: =AO66+AP66 -> 0 | AS66: =B66-X66 -> 0
A67: =IFERROR(VLOOKUP(D67,'Monthly Deduction'!$I$3:$J$957,2,0),0) -> 0 | B67: =IFERROR(VLOOKUP(D67,'Monthly Deduction'!$E$3:$F$957,2,0),0) -> 0 | C67: =A67+B67 -> 0 | D67: 10020064 | E67: =VLOOKUP(D67,'MPG Payment '!$E$3:$G$498218,2,0) -> Gomukh Hasanpur | F67: =IFERROR(_xlfn.XLOOKUP(D67,'Monthly Deduction'!$I$3:$I$957,'Monthly Deduction'!$H$3:$H$957),0) -> 0 | G67: =VLOOKUP(D67,'MPG Payment '!$E$3:$G$334579,3,0) -> vlc | H67: =VLOOKUP(D67,'MPG Payment '!$E$3:$H$334579,4,0) -> Indirect | I67: =INDEX('MPG Payment '!$C:$C,MATCH('Shayak Income '!D67,'MPG Payment '!E:E,0)) -> 1002 | J67: =INDEX('MPG Payment '!$D:$D,MATCH('Shayak Income '!D67,'MPG Payment '!E:E,0)) -> Laldiyara | K67: Old | L67: 44958 | M67: =SUMIF('MPG Payment '!$E$3:$E$34579,'Shayak Income '!D67,'MPG Payment '!$I$3:$I$34579) -> 3248.9 | N67: =SUMIF('MPG Payment '!$E$3:$E$34579,'Shayak Income '!D67,'MPG Payment '!$J$3:$J$34579) -> 129413.76 | O67: =+M67*0.75 -> 2436.675 | P67: =+M67*0.95 -> 3086.455 | Q67: =SUMIF('MPG Payment '!$E$3:$E$34579,'Shayak Income '!D67,'MPG Payment '!$S$3:$S$34579) -> 0 | R67: =+N67*3% -> 3882.4127 | S67: =R67-P67 -> 795.95767 | T67: =M67*0.1 -> 324.89 | U67: =(((IF(K67="New",0,SUMIF('MPG Payment '!$E$3:$E$34579,'Shayak Income '!D67,'MPG Payment '!$AC$3:$AC$34579))))+0)+0 -> 379.02661 | V67: =ROUND((SUM(O67:Q67)-SUM(T67:U67)),0) -> 4819 | W67: =(((AN67-AO67)))+0 -> 0 | X67: =((MIN(IF(B67>0,MAX(N67*2%),0),B67)))+0 -> 0 | Y67: =IFERROR(VLOOKUP(D67,'Monthly Deduction'!$M$2:$N$64,2,0),0) -> 0 | Z67: 0 | AA67: =IFERROR(VLOOKUP(D67,'Monthly Deduction'!A:B,2,0),0) -> 0 | AB67: =ROUND(IFERROR(V67-SUM(W67:AA67),0),0) -> 4819 | AC67: 0 | AD67: =ROUND(AB67-AC67,0) -> 4819 | AE67: =IF(AC67<>0,"Yes","Release") -> Release | AG67: 0 | AI67: 0 | AK67: 1256.62 | AL67: =COUNTIF(AK67:AK67,"=NA") -> 0 | AN67: =((MIN(IF(A67>0,MAX(N67*2%,1861),0),A67)))+0 -> 0 | AO67: =SUMIF('MPG Payment '!E:E,'Shayak Income '!D67,'MPG Payment '!AJ:AJ) -> 0 | AP67: =W67 -> 0 | AQ67: =AO67+AP67 -> 0 | AS67: =B67-X67 -> 0
A68: =IFERROR(VLOOKUP(D68,'Monthly Deduction'!$I$3:$J$957,2,0),0) -> 0 | B68: =IFERROR(VLOOKUP(D68,'Monthly Deduction'!$E$3:$F$957,2,0),0) -> 0 | C68: =A68+B68 -> 0 | D68: 10020067 | E68: =VLOOKUP(D68,'MPG Payment '!$E$3:$G$498218,2,0) -> ADARSH LAXMIPUR-2 | F68: =IFERROR(_xlfn.XLOOKUP(D68,'Monthly Deduction'!$I$3:$I$957,'Monthly Deduction'!$H$3:$H$957),0) -> 0 | G68: =VLOOKUP(D68,'MPG Payment '!$E$3:$G$334579,3,0) -> vlc | H68: =VLOOKUP(D68,'MPG Payment '!$E$3:$H$334579,4,0) -> Indirect | I68: =INDEX('MPG Payment '!$C:$C,MATCH('Shayak Income '!D68,'MPG Payment '!E:E,0)) -> 1002 | J68: =INDEX('MPG Payment '!$D:$D,MATCH('Shayak Income '!D68,'MPG Payment '!E:E,0)) -> Laldiyara | K68: Old | L68: 45423 | M68: =SUMIF('MPG Payment '!$E$3:$E$34579,'Shayak Income '!D68,'MPG Payment '!$I$3:$I$34579) -> 4946.2 | N68: =SUMIF('MPG Payment '!$E$3:$E$34579,'Shayak Income '!D68,'MPG Payment '!$J$3:$J$34579) -> 194721.86 | O68: =+M68*0.75 -> 3709.65 | P68: =+M68*0.95 -> 4698.89 | Q68: =SUMIF('MPG Payment '!$E$3:$E$34579,'Shayak Income '!D68,'MPG Payment '!$S$3:$S$34579) -> 0 | R68: =+N68*3% -> 5841.6558 | S68: =R68-P68 -> 1142.7658 | T68: =M68*0.1 -> 494.62 | U68: =(((IF(K68="New",0,SUMIF('MPG Payment '!$E$3:$E$34579,'Shayak Income '!D68,'MPG Payment '!$AC$3:$AC$34579))))+0)+0 -> 0 | V68: =ROUND((SUM(O68:Q68)-SUM(T68:U68)),0) -> 7914 | W68: =(((AN68-AO68)))+0 -> 0 | X68: =((MIN(IF(B68>0,MAX(N68*2%),0),B68)))+0 -> 0 | Y68: =IFERROR(VLOOKUP(D68,'Monthly Deduction'!$M$2:$N$64,2,0),0) -> 0 | Z68: 0 | AA68: =IFERROR(VLOOKUP(D68,'Monthly Deduction'!A:B,2,0),0) -> 0 | AB68: =ROUND(IFERROR(V68-SUM(W68:AA68),0),0) -> 7914 | AC68: 0 | AD68: =ROUND(AB68-AC68,0) -> 7914 | AE68: =IF(AC68<>0,"Yes","Release") -> Release | AG68: 0 | AI68: 0 | AK68: 1385.54 | AL68: =COUNTIF(AK68:AK68,"=NA") -> 0 | AN68: =((MIN(IF(A68>0,MAX(N68*2%,1861),0),A68)))+0 -> 0 | AO68: =SUMIF('MPG Payment '!E:E,'Shayak Income '!D68,'MPG Payment '!AJ:AJ) -> 0 | AP68: =W68 -> 0 | AQ68: =AO68+AP68 -> 0 | AS68: =B68-X68 -> 0
A69: =IFERROR(VLOOKUP(D69,'Monthly Deduction'!$I$3:$J$957,2,0),0) -> 24194.817 | B69: =IFERROR(VLOOKUP(D69,'Monthly Deduction'!$E$3:$F$957,2,0),0) -> 9080.5224 | C69: =A69+B69 -> 33275.339 | D69: 10020068 | E69: =VLOOKUP(D69,'MPG Payment '!$E$3:$G$498218,2,0) -> SABIKPUR | F69: =IFERROR(_xlfn.XLOOKUP(D69,'Monthly Deduction'!$I$3:$I$957,'Monthly Deduction'!$H$3:$H$957),0) -> 0 | G69: =VLOOKUP(D69,'MPG Payment '!$E$3:$G$334579,3,0) -> MPG | H69: =VLOOKUP(D69,'MPG Payment '!$E$3:$H$334579,4,0) -> Direct | I69: =INDEX('MPG Payment '!$C:$C,MATCH('Shayak Income '!D69,'MPG Payment '!E:E,0)) -> 1002 | J69: =INDEX('MPG Payment '!$D:$D,MATCH('Shayak Income '!D69,'MPG Payment '!E:E,0)) -> Laldiyara | K69: Old | L69: 45491 | M69: =SUMIF('MPG Payment '!$E$3:$E$34579,'Shayak Income '!D69,'MPG Payment '!$I$3:$I$34579) -> 2911.8 | N69: =SUMIF('MPG Payment '!$E$3:$E$34579,'Shayak Income '!D69,'MPG Payment '!$J$3:$J$34579) -> 118342.2 | O69: =+M69*0.75 -> 2183.85 | P69: =+M69*0.95 -> 2766.21 | Q69: =SUMIF('MPG Payment '!$E$3:$E$34579,'Shayak Income '!D69,'MPG Payment '!$S$3:$S$34579) -> 0 | R69: =+N69*3% -> 3550.266 | S69: =R69-P69 -> 784.05601 | T69: =M69*0.1 -> 291.18 | U69: =(((IF(K69="New",0,SUMIF('MPG Payment '!$E$3:$E$34579,'Shayak Income '!D69,'MPG Payment '!$AC$3:$AC$34579))))+0)+0 -> 127.38819 | V69: =ROUND((SUM(O69:Q69)-SUM(T69:U69)),0) -> 4531 | W69: =(((AN69-AO69)))+0 -> 2366.844 | X69: 0 | Y69: =IFERROR(VLOOKUP(D69,'Monthly Deduction'!$M$2:$N$64,2,0),0) -> 0 | Z69: 0 | AA69: =IFERROR(VLOOKUP(D69,'Monthly Deduction'!A:B,2,0),0) -> 0 | AB69: =ROUND(IFERROR(V69-SUM(W69:AA69),0),0) -> 2164 | AC69: =AB69 -> 2164 | AD69: =ROUND(AB69-AC69,0) -> 0 | AE69: =IF(AC69<>0,"Yes","Release") -> Yes | AG69: 0 | AH69: Agreement issue | AI69: 0 | AK69: 937.9 | AL69: =COUNTIF(AK69:AK69,"=NA") -> 0 | AN69: =((MIN(IF(A69>0,MAX(N69*2%,1861),0),A69)))+0 -> 2366.844 | AO69: =SUMIF('MPG Payment '!E:E,'Shayak Income '!D69,'MPG Payment '!AJ:AJ) -> 0 | AP69: =W69 -> 2366.844 | AQ69: =AO69+AP69 -> 2366.844 | AS69: =B69-X69 -> 9080.5224
A70: =IFERROR(VLOOKUP(D70,'Monthly Deduction'!$I$3:$J$957,2,0),0) -> 94478.603 | B70: =IFERROR(VLOOKUP(D70,'Monthly Deduction'!$E$3:$F$957,2,0),0) -> 12800 | C70: =A70+B70 -> 107278.6 | D70: 10020069 | E70: =VLOOKUP(D70,'MPG Payment '!$E$3:$G$498218,2,0) -> CHETAN-TOLA-KHUTHA | F70: =IFERROR(_xlfn.XLOOKUP(D70,'Monthly Deduction'!$I$3:$I$957,'Monthly Deduction'!$H$3:$H$957),0) -> 0 | G70: =VLOOKUP(D70,'MPG Payment '!$E$3:$G$334579,3,0) -> MPG | H70: =VLOOKUP(D70,'MPG Payment '!$E$3:$H$334579,4,0) -> Direct | I70: =INDEX('MPG Payment '!$C:$C,MATCH('Shayak Income '!D70,'MPG Payment '!E:E,0)) -> 1002 | J70: =INDEX('MPG Payment '!$D:$D,MATCH('Shayak Income '!D70,'MPG Payment '!E:E,0)) -> Laldiyara | K70: Old | L70: 45567 | M70: =SUMIF('MPG Payment '!$E$3:$E$34579,'Shayak Income '!D70,'MPG Payment '!$I$3:$I$34579) -> 869 | N70: =SUMIF('MPG Payment '!$E$3:$E$34579,'Shayak Income '!D70,'MPG Payment '!$J$3:$J$34579) -> 34181.952 | O70: =+M70*0.75 -> 651.75 | P70: =+M70*0.95 -> 825.55 | Q70: =SUMIF('MPG Payment '!$E$3:$E$34579,'Shayak Income '!D70,'MPG Payment '!$S$3:$S$34579) -> 1005.0917 | R70: =+N70*3% -> 1025.4585 | S70: =R70-P70 -> 199.90855 | T70: =M70*0.1 -> 86.9 | U70: =(((IF(K70="New",0,SUMIF('MPG Payment '!$E$3:$E$34579,'Shayak Income '!D70,'MPG Payment '!$AC$3:$AC$34579))))+0)+0 -> 1518.0331 | V70: =ROUND((SUM(O70:Q70)-SUM(T70:U70)),0) -> 877 | W70: 877 | X70: 0 | Y70: =IFERROR(VLOOKUP(D70,'Monthly Deduction'!$M$2:$N$64,2,0),0) -> 0 | Z70: 0 | AA70: 0 | AB70: =ROUND(IFERROR(V70-SUM(W70:AA70),0),0) -> 0 | AC70: =AB70 -> 0 | AD70: =ROUND(AB70-AC70,0) -> 0 | AE70: =IF(AC70<>0,"Yes","Release") -> Release | AG70: 0 | AH70: Down Payment / Agreement issue | AI70: 20000 | AK70: 212.9 | AL70: =COUNTIF(AK70:AK70,"=NA") -> 0 | AN70: =((MIN(IF(A70>0,MAX(N70*2%,1861),0),A70)))+0 -> 1861 | AO70: =SUMIF('MPG Payment '!E:E,'Shayak Income '!D70,'MPG Payment '!AJ:AJ) -> 500 | AP70: =W70 -> 877 | AQ70: =AO70+AP70 -> 1377 | AS70: =B70-X70 -> 12800
A71: =IFERROR(VLOOKUP(D71,'Monthly Deduction'!$I$3:$J$957,2,0),0) -> 36991.755 | B71: =IFERROR(VLOOKUP(D71,'Monthly Deduction'!$E$3:$F$957,2,0),0) -> 6400 | C71: =A71+B71 -> 43391.755 | D71: 10020070 | E71: =VLOOKUP(D71,'MPG Payment '!$E$3:$G$498218,2,0) -> LAXMIPUR | F71: =IFERROR(_xlfn.XLOOKUP(D71,'Monthly Deduction'!$I$3:$I$957,'Monthly Deduction'!$H$3:$H$957),0) -> 0 | G71: =VLOOKUP(D71,'MPG Payment '!$E$3:$G$334579,3,0) -> MPG | H71: =VLOOKUP(D71,'MPG Payment '!$E$3:$H$334579,4,0) -> Direct | I71: =INDEX('MPG Payment '!$C:$C,MATCH('Shayak Income '!D71,'MPG Payment '!E:E,0)) -> 1002 | J71: =INDEX('MPG Payment '!$D:$D,MATCH('Shayak Income '!D71,'MPG Payment '!E:E,0)) -> Laldiyara | K71: Old | L71: 45618 | M71: =SUMIF('MPG Payment '!$E$3:$E$34579,'Shayak Income '!D71,'MPG Payment '!$I$3:$I$34579) -> 3504.7 | N71: =SUMIF('MPG Payment '!$E$3:$E$34579,'Shayak Income '!D71,'MPG Payment '!$J$3:$J$34579) -> 140680.34 | O71: =+M71*0.75 -> 2628.525 | P71: =+M71*0.95 -> 3329.465 | Q71: =SUMIF('MPG Payment '!$E$3:$E$34579,'Shayak Income '!D71,'MPG Payment '!$S$3:$S$34579) -> 0 | R71: =+N71*3% -> 4220.4103 | S71: =R71-P71 -> 890.94526 | T71: =M71*0.1 -> 350.47 | U71: =(((IF(K71="New",0,SUMIF('MPG Payment '!$E$3:$E$34579,'Shayak Income '!D71,'MPG Payment '!$AC$3:$AC$34579))))+0)+0 -> 55.205734 | V71: =ROUND((SUM(O71:Q71)-SUM(T71:U71)),0) -> 5552 | W71: =(((AN71-AO71)))+0 -> 2813.6068 | X71: 0 | Y71: 2738 | Z71: 0 | AA71: =IFERROR(VLOOKUP(D71,'Monthly Deduction'!A:B,2,0),0) -> 0 | AB71: =ROUND(IFERROR(V71-SUM(W71:AA71),0),0) -> 0 | AC71: 0 | AD71: =ROUND(AB71-AC71,0) -> 0 | AE71: =IF(AC71<>0,"Yes","Release") -> Release | AG71: 0 | AI71: 0 | AK71: 623 | AL71: =COUNTIF(AK71:AK71,"=NA") -> 0 | AN71: =((MIN(IF(A71>0,MAX(N71*2%,1861),0),A71)))+0 -> 2813.6068 | AO71: =SUMIF('MPG Payment '!E:E,'Shayak Income '!D71,'MPG Payment '!AJ:AJ) -> 0 | AP71: =W71 -> 2813.6068 | AQ71: =AO71+AP71 -> 2813.6068 | AS71: =B71-X71 -> 6400
A72: =IFERROR(VLOOKUP(D72,'Monthly Deduction'!$I$3:$J$957,2,0),0) -> 0 | B72: =IFERROR(VLOOKUP(D72,'Monthly Deduction'!$E$3:$F$957,2,0),0) -> 0 | C72: =A72+B72 -> 0 | D72: 10020073 | E72: =VLOOKUP(D72,'MPG Payment '!$E$3:$G$498218,2,0) -> REHUA RK | F72: =IFERROR(_xlfn.XLOOKUP(D72,'Monthly Deduction'!$I$3:$I$957,'Monthly Deduction'!$H$3:$H$957),0) -> 0 | G72: =VLOOKUP(D72,'MPG Payment '!$E$3:$G$334579,3,0) -> vlc | H72: =VLOOKUP(D72,'MPG Payment '!$E$3:$H$334579,4,0) -> Indirect | I72: =INDEX('MPG Payment '!$C:$C,MATCH('Shayak Income '!D72,'MPG Payment '!E:E,0)) -> 1002 | J72: =INDEX('MPG Payment '!$D:$D,MATCH('Shayak Income '!D72,'MPG Payment '!E:E,0)) -> Laldiyara | K72: Old | L72: 45638 | M72: =SUMIF('MPG Payment '!$E$3:$E$34579,'Shayak Income '!D72,'MPG Payment '!$I$3:$I$34579) -> 4549.9 | N72: =SUMIF('MPG Payment '!$E$3:$E$34579,'Shayak Income '!D72,'MPG Payment '!$J$3:$J$34579) -> 189915.7 | O72: =+M72*0.75 -> 3412.425 | P72: =+M72*0.95 -> 4322.405 | Q72: =SUMIF('MPG Payment '!$E$3:$E$34579,'Shayak Income '!D72,'MPG Payment '!$S$3:$S$34579) -> 0 | R72: =+N72*3% -> 5697.4711 | S72: =R72-P72 -> 1375.0661 | T72: =M72*0.1 -> 454.99 | U72: =(((IF(K72="New",0,SUMIF('MPG Payment '!$E$3:$E$34579,'Shayak Income '!D72,'MPG Payment '!$AC$3:$AC$34579))))+0)+0 -> 0 | V72: =ROUND((SUM(O72:Q72)-SUM(T72:U72)),0) -> 7280 | W72: =(((AN72-AO72)))+0 -> 0 | X72: =((MIN(IF(B72>0,MAX(N72*2%),0),B72)))+0 -> 0 | Y72: =IFERROR(VLOOKUP(D72,'Monthly Deduction'!$M$2:$N$64,2,0),0) -> 0 | Z72: 0 | AA72: =IFERROR(VLOOKUP(D72,'Monthly Deduction'!A:B,2,0),0) -> 0 | AB72: =ROUND(IFERROR(V72-SUM(W72:AA72),0),0) -> 7280 | AC72: 0 | AD72: =ROUND(AB72-AC72,0) -> 7280 | AE72: =IF(AC72<>0,"Yes","Release") -> Release | AG72: 0 | AI72: 0 | AK72: 1190.5 | AL72: =COUNTIF(AK72:AK72,"=NA") -> 0 | AN72: =((MIN(IF(A72>0,MAX(N72*2%,1861),0),A72)))+0 -> 0 | AO72: =SUMIF('MPG Payment '!E:E,'Shayak Income '!D72,'MPG Payment '!AJ:AJ) -> 0 | AP72: =W72 -> 0 | AQ72: =AO72+AP72 -> 0 | AS72: =B72-X72 -> 0
A73: =IFERROR(VLOOKUP(D73,'Monthly Deduction'!$I$3:$J$957,2,0),0) -> 79587.256 | B73: =IFERROR(VLOOKUP(D73,'Monthly Deduction'!$E$3:$F$957,2,0),0) -> 0 | C73: =A73+B73 -> 79587.256 | D73: 10020075 | E73: =VLOOKUP(D73,'MPG Payment '!$E$3:$G$498218,2,0) -> RAMNAGAR | F73: =IFERROR(_xlfn.XLOOKUP(D73,'Monthly Deduction'!$I$3:$I$957,'Monthly Deduction'!$H$3:$H$957),0) -> 0 | G73: =VLOOKUP(D73,'MPG Payment '!$E$3:$G$334579,3,0) -> MPG | H73: =VLOOKUP(D73,'MPG Payment '!$E$3:$H$334579,4,0) -> Direct | I73: =INDEX('MPG Payment '!$C:$C,MATCH('Shayak Income '!D73,'MPG Payment '!E:E,0)) -> 1002 | J73: =INDEX('MPG Payment '!$D:$D,MATCH('Shayak Income '!D73,'MPG Payment '!E:E,0)) -> Laldiyara | K73: Old | L73: 45869 | M73: =SUMIF('MPG Payment '!$E$3:$E$34579,'Shayak Income '!D73,'MPG Payment '!$I$3:$I$34579) -> 1083.7 | N73: =SUMIF('MPG Payment '!$E$3:$E$34579,'Shayak Income '!D73,'MPG Payment '!$J$3:$J$34579) -> 45105.724 | O73: =+M73*0.75 -> 812.775 | P73: =+M73*0.95 -> 1029.515 | Q73: =SUMIF('MPG Payment '!$E$3:$E$34579,'Shayak Income '!D73,'MPG Payment '!$S$3:$S$34579) -> 0 | R73: =+N73*3% -> 1353.1717 | S73: =R73-P73 -> 323.65673 | T73: =M73*0.1 -> 108.37 | U73: =(((IF(K73="New",0,SUMIF('MPG Payment '!$E$3:$E$34579,'Shayak Income '!D73,'MPG Payment '!$AC$3:$AC$34579))))+0)+0 -> 1436.7718 | V73: =ROUND((SUM(O73:Q73)-SUM(T73:U73)),0) -> 297 | W73: 297 | X73: 0 | Y73: =IFERROR(VLOOKUP(D73,'Monthly Deduction'!$M$2:$N$64,2,0),0) -> 0 | Z73: 0 | AA73: 0 | AB73: =ROUND(IFERROR(V73-SUM(W73:AA73),0),0) -> 0 | AC73: 0 | AD73: =ROUND(AB73-AC73,0) -> 0 | AE73: =IF(AC73<>0,"Yes","Release") -> Release | AG73: 0 | AI73: 0 | AK73: 253.4 | AL73: =COUNTIF(AK73:AK73,"=NA") -> 0 | AN73: =((MIN(IF(A73>0,MAX(N73*2%,1861),0),A73)))+0 -> 1861 | AO73: =SUMIF('MPG Payment '!E:E,'Shayak Income '!D73,'MPG Payment '!AJ:AJ) -> 0 | AP73: =W73 -> 297 | AQ73: =AO73+AP73 -> 297 | AS73: =B73-X73 -> 0
A74: =IFERROR(VLOOKUP(D74,'Monthly Deduction'!$I$3:$J$957,2,0),0) -> 77879.294 | B74: =IFERROR(VLOOKUP(D74,'Monthly Deduction'!$E$3:$F$957,2,0),0) -> 0 | C74: =A74+B74 -> 77879.294 | D74: 10020077 | E74: =VLOOKUP(D74,'MPG Payment '!$E$3:$G$498218,2,0) -> BANSIPUR | F74: =IFERROR(_xlfn.XLOOKUP(D74,'Monthly Deduction'!$I$3:$I$957,'Monthly Deduction'!$H$3:$H$957),0) -> 0 | G74: =VLOOKUP(D74,'MPG Payment '!$E$3:$G$334579,3,0) -> MPG | H74: =VLOOKUP(D74,'MPG Payment '!$E$3:$H$334579,4,0) -> Direct | I74: =INDEX('MPG Payment '!$C:$C,MATCH('Shayak Income '!D74,'MPG Payment '!E:E,0)) -> 1002 | J74: =INDEX('MPG Payment '!$D:$D,MATCH('Shayak Income '!D74,'MPG Payment '!E:E,0)) -> Laldiyara | K74: Old | L74: 45869 | M74: =SUMIF('MPG Payment '!$E$3:$E$34579,'Shayak Income '!D74,'MPG Payment '!$I$3:$I$34579) -> 572.7 | N74: =SUMIF('MPG Payment '!$E$3:$E$34579,'Shayak Income '!D74,'MPG Payment '!$J$3:$J$34579) -> 26486.904 | O74: =+M74*0.75 -> 429.525 | P74: =+M74*0.95 -> 544.065 | Q74: =SUMIF('MPG Payment '!$E$3:$E$34579,'Shayak Income '!D74,'MPG Payment '!$S$3:$S$34579) -> 0 | R74: =+N74*3% -> 794.60712 | S74: =R74-P74 -> 250.54212 | T74: =M74*0.1 -> 57.27 | U74: =(((IF(K74="New",0,SUMIF('MPG Payment '!$E$3:$E$34579,'Shayak Income '!D74,'MPG Payment '!$AC$3:$AC$34579))))+0)+-1092 -> 916.35734 | V74: =ROUND((SUM(O74:Q74)-SUM(T74:U74)),0) -> 0 | W74: 0 | X74: 0 | Y74: =IFERROR(VLOOKUP(D74,'Monthly Deduction'!$M$2:$N$64,2,0),0) -> 0 | Z74: 0 | AA74: =IFERROR(VLOOKUP(D74,'Monthly Deduction'!A:B,2,0),0) -> 0 | AB74: =ROUND(IFERROR(V74-SUM(W74:AA74),0),0) -> 0 | AC74: 0 | AD74: =ROUND(AB74-AC74,0) -> 0 | AE74: =IF(AC74<>0,"Yes","Release") -> Release | AG74: 0 | AI74: 0 | AK74: 193.01 | AL74: =COUNTIF(AK74:AK74,"=NA") -> 0 | AN74: =((MIN(IF(A74>0,MAX(N74*2%,1861),0),A74)))+0 -> 1861 | AO74: =SUMIF('MPG Payment '!E:E,'Shayak Income '!D74,'MPG Payment '!AJ:AJ) -> 500 | AP74: =W74 -> 0 | AQ74: =AO74+AP74 -> 500 | AS74: =B74-X74 -> 0
A75: =IFERROR(VLOOKUP(D75,'Monthly Deduction'!$I$3:$J$957,2,0),0) -> 91198 | B75: =IFERROR(VLOOKUP(D75,'Monthly Deduction'!$E$3:$F$957,2,0),0) -> 0 | C75: =A75+B75 -> 91198 | D75: 10020078 | E75: =VLOOKUP(D75,'MPG Payment '!$E$3:$G$498218,2,0) -> GODIH | F75: =IFERROR(_xlfn.XLOOKUP(D75,'Monthly Deduction'!$I$3:$I$957,'Monthly Deduction'!$H$3:$H$957),0) -> 0 | G75: =VLOOKUP(D75,'MPG Payment '!$E$3:$G$334579,3,0) -> MPG | H75: =VLOOKUP(D75,'MPG Payment '!$E$3:$H$334579,4,0) -> Direct | I75: =INDEX('MPG Payment '!$C:$C,MATCH('Shayak Income '!D75,'MPG Payment '!E:E,0)) -> 1002 | J75: =INDEX('MPG Payment '!$D:$D,MATCH('Shayak Income '!D75,'MPG Payment '!E:E,0)) -> Laldiyara | K75: Old | L75: 45869 | M75: =SUMIF('MPG Payment '!$E$3:$E$34579,'Shayak Income '!D75,'MPG Payment '!$I$3:$I$34579) -> 1485.7 | N75: =SUMIF('MPG Payment '!$E$3:$E$34579,'Shayak Income '!D75,'MPG Payment '!$J$3:$J$34579) -> 60951.617 | O75: =+M75*0.75 -> 1114.275 | P75: =+M75*0.95 -> 1411.415 | Q75: =SUMIF('MPG Payment '!$E$3:$E$34579,'Shayak Income '!D75,'MPG Payment '!$S$3:$S$34579) -> 0 | R75: =+N75*3% -> 1828.5485 | S75: =R75-P75 -> 417.13351 | T75: =M75*0.1 -> 148.57 | U75: =(((IF(K75="New",0,SUMIF('MPG Payment '!$E$3:$E$34579,'Shayak Income '!D75,'MPG Payment '!$AC$3:$AC$34579))))+0)+0 -> 1082.6274 | V75: =ROUND((SUM(O75:Q75)-SUM(T75:U75)),0) -> 1294 | W75: 1294 | X75: 0 | Y75: =IFERROR(VLOOKUP(D75,'Monthly Deduction'!$M$2:$N$64,2,0),0) -> 0 | Z75: 0 | AA75: =IFERROR(VLOOKUP(D75,'Monthly Deduction'!A:B,2,0),0) -> 0 | AB75: =ROUND(IFERROR(V75-SUM(W75:AA75),0),0) -> 0 | AC75: =AB75 -> 0 | AD75: =ROUND(AB75-AC75,0) -> 0 | AE75: =IF(AC75<>0,"Yes","Release") -> Release | AG75: 0 | AH75: Down Payment | AI75: 9637 | AK75: 335 | AL75: =COUNTIF(AK75:AK75,"=NA") -> 0 | AN75: =((MIN(IF(A75>0,MAX(N75*2%,1861),0),A75)))+0 -> 1861 | AO75: =SUMIF('MPG Payment '!E:E,'Shayak Income '!D75,'MPG Payment '!AJ:AJ) -> 0 | AP75: =W75 -> 1294 | AQ75: =AO75+AP75 -> 1294 | AS75: =B75-X75 -> 0
A76: =IFERROR(VLOOKUP(D76,'Monthly Deduction'!$I$3:$J$957,2,0),0) -> 94961 | B76: =IFERROR(VLOOKUP(D76,'Monthly Deduction'!$E$3:$F$957,2,0),0) -> 0 | C76: =A76+B76 -> 94961 | D76: 10020079 | E76: =VLOOKUP(D76,'MPG Payment '!$E$3:$G$498218,2,0) -> SINGARPUR | F76: =IFERROR(_xlfn.XLOOKUP(D76,'Monthly Deduction'!$I$3:$I$957,'Monthly Deduction'!$H$3:$H$957),0) -> 0 | G76: =VLOOKUP(D76,'MPG Payment '!$E$3:$G$334579,3,0) -> MPG | H76: =VLOOKUP(D76,'MPG Payment '!$E$3:$H$334579,4,0) -> Direct | I76: =INDEX('MPG Payment '!$C:$C,MATCH('Shayak Income '!D76,'MPG Payment '!E:E,0)) -> 1002 | J76: =INDEX('MPG Payment '!$D:$D,MATCH('Shayak Income '!D76,'MPG Payment '!E:E,0)) -> Laldiyara | K76: Old | L76: 45869 | M76: =SUMIF('MPG Payment '!$E$3:$E$34579,'Shayak Income '!D76,'MPG Payment '!$I$3:$I$34579) -> 1075.9 | N76: =SUMIF('MPG Payment '!$E$3:$E$34579,'Shayak Income '!D76,'MPG Payment '!$J$3:$J$34579) -> 55828.613 | O76: =+M76*0.75 -> 806.925 | P76: =+M76*0.95 -> 1022.105 | Q76: =SUMIF('MPG Payment '!$E$3:$E$34579,'Shayak Income '!D76,'MPG Payment '!$S$3:$S$34579) -> 0 | R76: =+N76*3% -> 1674.8584 | S76: =R76-P76 -> 652.75339 | T76: =M76*0.1 -> 107.59 | U76: =(((IF(K76="New",0,SUMIF('MPG Payment '!$E$3:$E$34579,'Shayak Income '!D76,'MPG Payment '!$AC$3:$AC$34579))))+0)+-78 -> 1721.7928 | V76: =ROUND((SUM(O76:Q76)-SUM(T76:U76)),0) -> 0 | W76: 0 | X76: 0 | Y76: =IFERROR(VLOOKUP(D76,'Monthly Deduction'!$M$2:$N$64,2,0),0) -> 0 | Z76: 0 | AA76: 0 | AB76: =ROUND(IFERROR(V76-SUM(W76:AA76),0),0) -> 0 | AC76: =AB76 -> 0 | AD76: =ROUND(AB76-AC76,0) -> 0 | AE76: =IF(AC76<>0,"Yes","Release") -> Release | AG76: 0 | AH76: Down Payment | AI76: 9580 | AK76: 192.3 | AL76: =COUNTIF(AK76:AK76,"=NA") -> 0 | AN76: =((MIN(IF(A76>0,MAX(N76*2%,1861),0),A76)))+0 -> 1861 | AO76: =SUMIF('MPG Payment '!E:E,'Shayak Income '!D76,'MPG Payment '!AJ:AJ) -> 500 | AP76: =W76 -> 0 | AQ76: =AO76+AP76 -> 500 | AS76: =B76-X76 -> 0
A77: =IFERROR(VLOOKUP(D77,'Monthly Deduction'!$I$3:$J$957,2,0),0) -> 0 | B77: =IFERROR(VLOOKUP(D77,'Monthly Deduction'!$E$3:$F$957,2,0),0) -> 0 | C77: =A77+B77 -> 0 | D77: 10030002 | E77: =VLOOKUP(D77,'MPG Payment '!$E$3:$G$498218,2,0) -> MOHANPUR | F77: =IFERROR(_xlfn.XLOOKUP(D77,'Monthly Deduction'!$I$3:$I$957,'Monthly Deduction'!$H$3:$H$957),0) -> 0 | G77: =VLOOKUP(D77,'MPG Payment '!$E$3:$G$334579,3,0) -> vlc | H77: =VLOOKUP(D77,'MPG Payment '!$E$3:$H$334579,4,0) -> Indirect | I77: =INDEX('MPG Payment '!$C:$C,MATCH('Shayak Income '!D77,'MPG Payment '!E:E,0)) -> 1003 | J77: =INDEX('MPG Payment '!$D:$D,MATCH('Shayak Income '!D77,'MPG Payment '!E:E,0)) -> Asarganj | K77: Old | L77: 42979 | M77: =SUMIF('MPG Payment '!$E$3:$E$34579,'Shayak Income '!D77,'MPG Payment '!$I$3:$I$34579) -> 2079.6 | N77: =SUMIF('MPG Payment '!$E$3:$E$34579,'Shayak Income '!D77,'MPG Payment '!$J$3:$J$34579) -> 81551.521 | O77: =+M77*0.75 -> 1559.7 | P77: =+M77*0.95 -> 1975.62 | Q77: =SUMIF('MPG Payment '!$E$3:$E$34579,'Shayak Income '!D77,'MPG Payment '!$S$3:$S$34579) -> 0 | R77: =+N77*3% -> 2446.5456 | S77: =R77-P77 -> 470.92563 | T77: =M77*0.1 -> 207.96 | U77: =(((IF(K77="New",0,SUMIF('MPG Payment '!$E$3:$E$34579,'Shayak Income '!D77,'MPG Payment '!$AC$3:$AC$34579))))+0)+0 -> 565.36026 | V77: =ROUND((SUM(O77:Q77)-SUM(T77:U77)),0) -> 2762 | W77: =(((AN77-AO77)))+0 -> 0 | X77: =((MIN(IF(B77>0,MAX(N77*2%),0),B77)))+0 -> 0 | Y77: =IFERROR(VLOOKUP(D77,'Monthly Deduction'!$M$2:$N$64,2,0),0) -> 0 | Z77: 0 | AA77: =IFERROR(VLOOKUP(D77,'Monthly Deduction'!A:B,2,0),0) -> 0 | AB77: =ROUND(IFERROR(V77-SUM(W77:AA77),0),0) -> 2762 | AC77: 0 | AD77: =ROUND(AB77-AC77,0) -> 2762 | AE77: =IF(AC77<>0,"Yes","Release") -> Release | AG77: 0 | AI77: 0 | AK77: 507.45 | AL77: =COUNTIF(AK77:AK77,"=NA") -> 0 | AN77: =((MIN(IF(A77>0,MAX(N77*2%,1861),0),A77)))+0 -> 0 | AO77: =SUMIF('MPG Payment '!E:E,'Shayak Income '!D77,'MPG Payment '!AJ:AJ) -> 0 | AP77: =W77 -> 0 | AQ77: =AO77+AP77 -> 0 | AS77: =B77-X77 -> 0
A78: =IFERROR(VLOOKUP(D78,'Monthly Deduction'!$I$3:$J$957,2,0),0) -> 0 | B78: =IFERROR(VLOOKUP(D78,'Monthly Deduction'!$E$3:$F$957,2,0),0) -> 0 | C78: =A78+B78 -> 0 | D78: 10030003 | E78: =VLOOKUP(D78,'MPG Payment '!$E$3:$G$498218,2,0) -> CHATMADIH | F78: =IFERROR(_xlfn.XLOOKUP(D78,'Monthly Deduction'!$I$3:$I$957,'Monthly Deduction'!$H$3:$H$957),0) -> 0 | G78: =VLOOKUP(D78,'MPG Payment '!$E$3:$G$334579,3,0) -> MPG | H78: =VLOOKUP(D78,'MPG Payment '!$E$3:$H$334579,4,0) -> Direct | I78: =INDEX('MPG Payment '!$C:$C,MATCH('Shayak Income '!D78,'MPG Payment '!E:E,0)) -> 1003 | J78: =INDEX('MPG Payment '!$D:$D,MATCH('Shayak Income '!D78,'MPG Payment '!E:E,0)) -> Asarganj | K78: Old | L78: 42979 | M78: =SUMIF('MPG Payment '!$E$3:$E$34579,'Shayak Income '!D78,'MPG Payment '!$I$3:$I$34579) -> 7050.3 | N78: =SUMIF('MPG Payment '!$E$3:$E$34579,'Shayak Income '!D78,'MPG Payment '!$J$3:$J$34579) -> 306084.86 | O78: =+M78*0.75 -> 5287.725 | P78: =+M78*0.95 -> 6697.785 | Q78: =SUMIF('MPG Payment '!$E$3:$E$34579,'Shayak Income '!D78,'MPG Payment '!$S$3:$S$34579) -> 5506.6015 | R78: =+N78*3% -> 9182.5459 | S78: =R78-P78 -> 2484.7609 | T78: =M78*0.1 -> 705.03 | U78: =(((IF(K78="New",0,SUMIF('MPG Payment '!$E$3:$E$34579,'Shayak Income '!D78,'MPG Payment '!$AC$3:$AC$34579))))+0)+0 -> 0 | V78: =ROUND((SUM(O78:Q78)-SUM(T78:U78)),0) -> 16787 | W78: =(((AN78-AO78)))+0 -> 0 | X78: =((MIN(IF(B78>0,MAX(N78*2%),0),B78)))+0 -> 0 | Y78: =IFERROR(VLOOKUP(D78,'Monthly Deduction'!$M$2:$N$64,2,0),0) -> 0 | Z78: 0 | AA78: =IFERROR(VLOOKUP(D78,'Monthly Deduction'!A:B,2,0),0) -> 0 | AB78: =ROUND(IFERROR(V78-SUM(W78:AA78),0),0) -> 16787 | AC78: 0 | AD78: =ROUND(AB78-AC78,0) -> 16787 | AE78: =IF(AC78<>0,"Yes","Release") -> Release | AG78: 0 | AI78: 0 | AK78: 1998.4 | AL78: =COUNTIF(AK78:AK78,"=NA") -> 0 | AN78: =((MIN(IF(A78>0,MAX(N78*2%,1861),0),A78)))+0 -> 0 | AO78: =SUMIF('MPG Payment '!E:E,'Shayak Income '!D78,'MPG Payment '!AJ:AJ) -> 0 | AP78: =W78 -> 0 | AQ78: =AO78+AP78 -> 0 | AS78: =B78-X78 -> 0
A79: =IFERROR(VLOOKUP(D79,'Monthly Deduction'!$I$3:$J$957,2,0),0) -> 0 | B79: =IFERROR(VLOOKUP(D79,'Monthly Deduction'!$E$3:$F$957,2,0),0) -> 0 | C79: =A79+B79 -> 0 | D79: 10030007 | E79: =VLOOKUP(D79,'MPG Payment '!$E$3:$G$498218,2,0) -> SIYADIH | F79: =IFERROR(_xlfn.XLOOKUP(D79,'Monthly Deduction'!$I$3:$I$957,'Monthly Deduction'!$H$3:$H$957),0) -> 0 | G79: =VLOOKUP(D79,'MPG Payment '!$E$3:$G$334579,3,0) -> vlc | H79: =VLOOKUP(D79,'MPG Payment '!$E$3:$H$334579,4,0) -> Indirect | I79: =INDEX('MPG Payment '!$C:$C,MATCH('Shayak Income '!D79,'MPG Payment '!E:E,0)) -> 1003 | J79: =INDEX('MPG Payment '!$D:$D,MATCH('Shayak Income '!D79,'MPG Payment '!E:E,0)) -> Asarganj | K79: Old | L79: 42979 | M79: =SUMIF('MPG Payment '!$E$3:$E$34579,'Shayak Income '!D79,'MPG Payment '!$I$3:$I$34579) -> 2855 | N79: =SUMIF('MPG Payment '!$E$3:$E$34579,'Shayak Income '!D79,'MPG Payment '!$J$3:$J$34579) -> 85334.725 | O79: =+M79*0.75 -> 2141.25 | P79: =+M79*0.95 -> 2712.25 | Q79: =SUMIF('MPG Payment '!$E$3:$E$34579,'Shayak Income '!D79,'MPG Payment '!$S$3:$S$34579) -> 0 | R79: =+N79*3% -> 2560.0417 | S79: =R79-P79 -> -152.20826 | T79: =M79*0.1 -> 285.5 | U79: =(((IF(K79="New",0,SUMIF('MPG Payment '!$E$3:$E$34579,'Shayak Income '!D79,'MPG Payment '!$AC$3:$AC$34579))))+0)+0 -> 109.32812 | V79: =ROUND((SUM(O79:Q79)-SUM(T79:U79)),0) -> 4459 | W79: =(((AN79-AO79)))+0 -> 0 | X79: =((MIN(IF(B79>0,MAX(N79*2%),0),B79)))+0 -> 0 | Y79: =IFERROR(VLOOKUP(D79,'Monthly Deduction'!$M$2:$N$64,2,0),0) -> 0 | Z79: 0 | AA79: =IFERROR(VLOOKUP(D79,'Monthly Deduction'!A:B,2,0),0) -> 0 | AB79: =ROUND(IFERROR(V79-SUM(W79:AA79),0),0) -> 4459 | AC79: 0 | AD79: =ROUND(AB79-AC79,0) -> 4459 | AE79: =IF(AC79<>0,"Yes","Release") -> Release | AG79: 0 | AI79: 0 | AK79: 790.45 | AL79: =COUNTIF(AK79:AK79,"=NA") -> 0 | AN79: =((MIN(IF(A79>0,MAX(N79*2%,1861),0),A79)))+0 -> 0 | AO79: =SUMIF('MPG Payment '!E:E,'Shayak Income '!D79,'MPG Payment '!AJ:AJ) -> 0 | AP79: =W79 -> 0 | AQ79: =AO79+AP79 -> 0 | AS79: =B79-X79 -> 0
A80: =IFERROR(VLOOKUP(D80,'Monthly Deduction'!$I$3:$J$957,2,0),0) -> 0 | B80: =IFERROR(VLOOKUP(D80,'Monthly Deduction'!$E$3:$F$957,2,0),0) -> 0 | C80: =A80+B80 -> 0 | D80: 10030008 | E80: =VLOOKUP(D80,'MPG Payment '!$E$3:$G$498218,2,0) -> HARPUR M | F80: =IFERROR(_xlfn.XLOOKUP(D80,'Monthly Deduction'!$I$3:$I$957,'Monthly Deduction'!$H$3:$H$957),0) -> 0 | G80: =VLOOKUP(D80,'MPG Payment '!$E$3:$G$334579,3,0) -> RMC | H80: =VLOOKUP(D80,'MPG Payment '!$E$3:$H$334579,4,0) -> Direct | I80: =INDEX('MPG Payment '!$C:$C,MATCH('Shayak Income '!D80,'MPG Payment '!E:E,0)) -> 1003 | J80: =INDEX('MPG Payment '!$D:$D,MATCH('Shayak Income '!D80,'MPG Payment '!E:E,0)) -> Asarganj | K80: Old | L80: 42979 | M80: =SUMIF('MPG Payment '!$E$3:$E$34579,'Shayak Income '!D80,'MPG Payment '!$I$3:$I$34579) -> 947.55 | N80: =SUMIF('MPG Payment '!$E$3:$E$34579,'Shayak Income '!D80,'MPG Payment '!$J$3:$J$34579) -> 30650.216 | O80: =+M80*0.75 -> 710.6625 | P80: =+M80*0.95 -> 900.1725 | Q80: =SUMIF('MPG Payment '!$E$3:$E$34579,'Shayak Income '!D80,'MPG Payment '!$S$3:$S$34579) -> 14.234045 | R80: =+N80*3% -> 919.50648 | S80: =R80-P80 -> 19.333981 | T80: =M80*0.1 -> 94.755 | U80: =(((IF(K80="New",0,SUMIF('MPG Payment '!$E$3:$E$34579,'Shayak Income '!D80,'MPG Payment '!$AC$3:$AC$34579))))+0)+0 -> 0 | V80: =ROUND((SUM(O80:Q80)-SUM(T80:U80)),0) -> 1530 | W80: =(((AN80-AO80)))+0 -> 0 | X80: =((MIN(IF(B80>0,MAX(N80*2%),0),B80)))+0 -> 0 | Y80: =IFERROR(VLOOKUP(D80,'Monthly Deduction'!$M$2:$N$64,2,0),0) -> 0 | Z80: 0 | AA80: =IFERROR(VLOOKUP(D80,'Monthly Deduction'!A:B,2,0),0) -> 0 | AB80: =ROUND(IFERROR(V80-SUM(W80:AA80),0),0) -> 1530 | AC80: 0 | AD80: =ROUND(AB80-AC80,0) -> 1530 | AE80: =IF(AC80<>0,"Yes","Release") -> Release | AG80: 0 | AI80: 0 | AK80: 816 | AL80: =COUNTIF(AK80:AK80,"=NA") -> 0 | AN80: =((MIN(IF(A80>0,MAX(N80*2%,1861),0),A80)))+0 -> 0 | AO80: =SUMIF('MPG Payment '!E:E,'Shayak Income '!D80,'MPG Payment '!AJ:AJ) -> 0 | AP80: =W80 -> 0 | AQ80: =AO80+AP80 -> 0 | AS80: =B80-X80 -> 0
A81: =IFERROR(VLOOKUP(D81,'Monthly Deduction'!$I$3:$J$957,2,0),0) -> 0 | B81: =IFERROR(VLOOKUP(D81,'Monthly Deduction'!$E$3:$F$957,2,0),0) -> 0 | C81: =A81+B81 -> 0 | D81: 10030009 | E81: =VLOOKUP(D81,'MPG Payment '!$E$3:$G$498218,2,0) -> Gomukh ID Laldiyara | F81: =IFERROR(_xlfn.XLOOKUP(D81,'Monthly Deduction'!$I$3:$I$957,'Monthly Deduction'!$H$3:$H$957),0) -> 0 | G81: =VLOOKUP(D81,'MPG Payment '!$E$3:$G$334579,3,0) -> vlc | H81: =VLOOKUP(D81,'MPG Payment '!$E$3:$H$334579,4,0) -> Indirect | I81: =INDEX('MPG Payment '!$C:$C,MATCH('Shayak Income '!D81,'MPG Payment '!E:E,0)) -> 1003 | J81: =INDEX('MPG Payment '!$D:$D,MATCH('Shayak Income '!D81,'MPG Payment '!E:E,0)) -> Asarganj | K81: Old | L81: 43315 | M81: =SUMIF('MPG Payment '!$E$3:$E$34579,'Shayak Income '!D81,'MPG Payment '!$I$3:$I$34579) -> 37762.95 | N81: =SUMIF('MPG Payment '!$E$3:$E$34579,'Shayak Income '!D81,'MPG Payment '!$J$3:$J$34579) -> 1434032.4 | O81: =+M81*0.75 -> 28322.212 | P81: =+M81*0.95 -> 35874.802 | Q81: =SUMIF('MPG Payment '!$E$3:$E$34579,'Shayak Income '!D81,'MPG Payment '!$S$3:$S$34579) -> 0 | R81: =+N81*3% -> 43020.971 | S81: =R81-P81 -> 7146.1685 | T81: =M81*0.1 -> 3776.295 | U81: =(((IF(K81="New",0,SUMIF('MPG Payment '!$E$3:$E$34579,'Shayak Income '!D81,'MPG Payment '!$AC$3:$AC$34579))))+0)+0 -> 0 | V81: =ROUND((SUM(O81:Q81)-SUM(T81:U81)),0) -> 60421 | W81: =(((AN81-AO81)))+0 -> 0 | X81: =((MIN(IF(B81>0,MAX(N81*2%),0),B81)))+0 -> 0 | Y81: =IFERROR(VLOOKUP(D81,'Monthly Deduction'!$M$2:$N$64,2,0),0) -> 0 | Z81: 0 | AA81: =IFERROR(VLOOKUP(D81,'Monthly Deduction'!A:B,2,0),0) -> 0 | AB81: =ROUND(IFERROR(V81-SUM(W81:AA81),0),0) -> 60421 | AC81: 0 | AD81: =ROUND(AB81-AC81,0) -> 60421 | AE81: =IF(AC81<>0,"Yes","Release") -> Release | AG81: 0 | AI81: 0 | AK81: 10917 | AL81: =COUNTIF(AK81:AK81,"=NA") -> 0 | AN81: =((MIN(IF(A81>0,MAX(N81*2%,1861),0),A81)))+0 -> 0 | AO81: =SUMIF('MPG Payment '!E:E,'Shayak Income '!D81,'MPG Payment '!AJ:AJ) -> 0 | AP81: =W81 -> 0 | AQ81: =AO81+AP81 -> 0 | AS81: =B81-X81 -> 0
A82: =IFERROR(VLOOKUP(D82,'Monthly Deduction'!$I$3:$J$957,2,0),0) -> 39837.523 | B82: =IFERROR(VLOOKUP(D82,'Monthly Deduction'!$E$3:$F$957,2,0),0) -> 4335 | C82: =A82+B82 -> 44172.523 | D82: 10030010 | E82: =VLOOKUP(D82,'MPG Payment '!$E$3:$G$498218,2,0) -> KATHNI | F82: =IFERROR(_xlfn.XLOOKUP(D82,'Monthly Deduction'!$I$3:$I$957,'Monthly Deduction'!$H$3:$H$957),0) -> 0 | G82: =VLOOKUP(D82,'MPG Payment '!$E$3:$G$334579,3,0) -> MPG | H82: =VLOOKUP(D82,'MPG Payment '!$E$3:$H$334579,4,0) -> Direct | I82: =INDEX('MPG Payment '!$C:$C,MATCH('Shayak Income '!D82,'MPG Payment '!E:E,0)) -> 1003 | J82: =INDEX('MPG Payment '!$D:$D,MATCH('Shayak Income '!D82,'MPG Payment '!E:E,0)) -> Asarganj | K82: Old | L82: 43315 | M82: =SUMIF('MPG Payment '!$E$3:$E$34579,'Shayak Income '!D82,'MPG Payment '!$I$3:$I$34579) -> 1364.6 | N82: =SUMIF('MPG Payment '!$E$3:$E$34579,'Shayak Income '!D82,'MPG Payment '!$J$3:$J$34579) -> 46010.3 | O82: =+M82*0.75 -> 1023.45 | P82: =+M82*0.95 -> 1296.37 | Q82: =SUMIF('MPG Payment '!$E$3:$E$34579,'Shayak Income '!D82,'MPG Payment '!$S$3:$S$34579) -> 0 | R82: =+N82*3% -> 1380.309 | S82: =R82-P82 -> 83.939012 | T82: =M82*0.1 -> 136.46 | U82: =(((IF(K82="New",0,SUMIF('MPG Payment '!$E$3:$E$34579,'Shayak Income '!D82,'MPG Payment '!$AC$3:$AC$34579))))+0)+0 -> 966.05531 | V82: =ROUND((SUM(O82:Q82)-SUM(T82:U82)),0) -> 1217 | W82: 1217 | X82: 0 | Y82: =IFERROR(VLOOKUP(D82,'Monthly Deduction'!$M$2:$N$64,2,0),0) -> 0 | Z82: 0 | AA82: =IFERROR(VLOOKUP(D82,'Monthly Deduction'!A:B,2,0),0) -> 0 | AB82: =ROUND(IFERROR(V82-SUM(W82:AA82),0),0) -> 0 | AC82: 0 | AD82: =ROUND(AB82-AC82,0) -> 0 | AE82: =IF(AC82<>0,"Yes","Release") -> Release | AG82: 0 | AI82: 0 | AK82: 293.65 | AL82: =COUNTIF(AK82:AK82,"=NA") -> 0 | AN82: =((MIN(IF(A82>0,MAX(N82*2%,1861),0),A82)))+0 -> 1861 | AO82: =SUMIF('MPG Payment '!E:E,'Shayak Income '!D82,'MPG Payment '!AJ:AJ) -> 0 | AP82: =W82 -> 1217 | AQ82: =AO82+AP82 -> 1217 | AS82: =B82-X82 -> 4335
A83: =IFERROR(VLOOKUP(D83,'Monthly Deduction'!$I$3:$J$957,2,0),0) -> 0 | B83: =IFERROR(VLOOKUP(D83,'Monthly Deduction'!$E$3:$F$957,2,0),0) -> 0 | C83: =A83+B83 -> 0 | D83: 10030011 | E83: =VLOOKUP(D83,'MPG Payment '!$E$3:$G$498218,2,0) -> DEVDHA GOMUKH MPG | F83: =IFERROR(_xlfn.XLOOKUP(D83,'Monthly Deduction'!$I$3:$I$957,'Monthly Deduction'!$H$3:$H$957),0) -> 0 | G83: =VLOOKUP(D83,'MPG Payment '!$E$3:$G$334579,3,0) -> MPG | H83: =VLOOKUP(D83,'MPG Payment '!$E$3:$H$334579,4,0) -> Direct | I83: =INDEX('MPG Payment '!$C:$C,MATCH('Shayak Income '!D83,'MPG Payment '!E:E,0)) -> 1003 | J83: =INDEX('MPG Payment '!$D:$D,MATCH('Shayak Income '!D83,'MPG Payment '!E:E,0)) -> Asarganj | K83: Old | L83: 43343 | M83: =SUMIF('MPG Payment '!$E$3:$E$34579,'Shayak Income '!D83,'MPG Payment '!$I$3:$I$34579) -> 4931.3 | N83: =SUMIF('MPG Payment '!$E$3:$E$34579,'Shayak Income '!D83,'MPG Payment '!$J$3:$J$34579) -> 192745.95 | O83: =+M83*0.75 -> 3698.475 | P83: =+M83*0.95 -> 4684.735 | Q83: =SUMIF('MPG Payment '!$E$3:$E$34579,'Shayak Income '!D83,'MPG Payment '!$S$3:$S$34579) -> 1106.4274 | R83: =+N83*3% -> 5782.3786 | S83: =R83-P83 -> 1097.6436 | T83: =M83*0.1 -> 493.13 | U83: =(((IF(K83="New",0,SUMIF('MPG Payment '!$E$3:$E$34579,'Shayak Income '!D83,'MPG Payment '!$AC$3:$AC$34579))))+0)+0 -> 0 | V83: =ROUND((SUM(O83:Q83)-SUM(T83:U83)),0) -> 8997 | W83: =(((AN83-AO83)))+0 -> 0 | X83: =((MIN(IF(B83>0,MAX(N83*2%),0),B83)))+0 -> 0 | Y83: =IFERROR(VLOOKUP(D83,'Monthly Deduction'!$M$2:$N$64,2,0),0) -> 0 | Z83: 0 | AA83: =IFERROR(VLOOKUP(D83,'Monthly Deduction'!A:B,2,0),0) -> 0 | AB83: =ROUND(IFERROR(V83-SUM(W83:AA83),0),0) -> 8997 | AC83: 0 | AD83: =ROUND(AB83-AC83,0) -> 8997 | AE83: =IF(AC83<>0,"Yes","Release") -> Release | AG83: 0 | AI83: 0 | AK83: 1716.1 | AL83: =COUNTIF(AK83:AK83,"=NA") -> 0 | AN83: =((MIN(IF(A83>0,MAX(N83*2%,1861),0),A83)))+0 -> 0 | AO83: =SUMIF('MPG Payment '!E:E,'Shayak Income '!D83,'MPG Payment '!AJ:AJ) -> 0 | AP83: =W83 -> 0 | AQ83: =AO83+AP83 -> 0 | AS83: =B83-X83 -> 0
A84: =IFERROR(VLOOKUP(D84,'Monthly Deduction'!$I$3:$J$957,2,0),0) -> 0 | B84: =IFERROR(VLOOKUP(D84,'Monthly Deduction'!$E$3:$F$957,2,0),0) -> 0 | C84: =A84+B84 -> 0 | D84: 10030012 | E84: =VLOOKUP(D84,'MPG Payment '!$E$3:$G$498218,2,0) -> KASBA(MANGOAN) | F84: =IFERROR(_xlfn.XLOOKUP(D84,'Monthly Deduction'!$I$3:$I$957,'Monthly Deduction'!$H$3:$H$957),0) -> 0 | G84: =VLOOKUP(D84,'MPG Payment '!$E$3:$G$334579,3,0) -> vlc | H84: =VLOOKUP(D84,'MPG Payment '!$E$3:$H$334579,4,0) -> Indirect | I84: =INDEX('MPG Payment '!$C:$C,MATCH('Shayak Income '!D84,'MPG Payment '!E:E,0)) -> 1003 | J84: =INDEX('MPG Payment '!$D:$D,MATCH('Shayak Income '!D84,'MPG Payment '!E:E,0)) -> Asarganj | K84: Old | L84: 44652 | M84: =SUMIF('MPG Payment '!$E$3:$E$34579,'Shayak Income '!D84,'MPG Payment '!$I$3:$I$34579) -> 4605.2 | N84: =SUMIF('MPG Payment '!$E$3:$E$34579,'Shayak Income '!D84,'MPG Payment '!$J$3:$J$34579) -> 153783.46 | O84: =+M84*0.75 -> 3453.9 | P84: =+M84*0.95 -> 4374.94 | Q84: =SUMIF('MPG Payment '!$E$3:$E$34579,'Shayak Income '!D84,'MPG Payment '!$S$3:$S$34579) -> 0 | R84: =+N84*3% -> 4613.5038 | S84: =R84-P84 -> 238.56383 | T84: =M84*0.1 -> 460.52 | U84: =(((IF(K84="New",0,SUMIF('MPG Payment '!$E$3:$E$34579,'Shayak Income '!D84,'MPG Payment '!$AC$3:$AC$34579))))+0)+0 -> 409.53401 | V84: =ROUND((SUM(O84:Q84)-SUM(T84:U84)),0) -> 6959 | W84: =(((AN84-AO84)))+0 -> 0 | X84: =((MIN(IF(B84>0,MAX(N84*2%),0),B84)))+0 -> 0 | Y84: =IFERROR(VLOOKUP(D84,'Monthly Deduction'!$M$2:$N$64,2,0),0) -> 0 | Z84: 0 | AA84: =IFERROR(VLOOKUP(D84,'Monthly Deduction'!A:B,2,0),0) -> 0 | AB84: =ROUND(IFERROR(V84-SUM(W84:AA84),0),0) -> 6959 | AC84: 0 | AD84: =ROUND(AB84-AC84,0) -> 6959 | AE84: =IF(AC84<>0,"Yes","Release") -> Release | AG84: 0 | AI84: 0 | AK84: 1454.5 | AL84: =COUNTIF(AK84:AK84,"=NA") -> 0 | AN84: =((MIN(IF(A84>0,MAX(N84*2%,1861),0),A84)))+0 -> 0 | AO84: =SUMIF('MPG Payment '!E:E,'Shayak Income '!D84,'MPG Payment '!AJ:AJ) -> 0 | AP84: =W84 -> 0 | AQ84: =AO84+AP84 -> 0 | AS84: =B84-X84 -> 0
A85: =IFERROR(VLOOKUP(D85,'Monthly Deduction'!$I$3:$J$957,2,0),0) -> 0 | B85: =IFERROR(VLOOKUP(D85,'Monthly Deduction'!$E$3:$F$957,2,0),0) -> 9877.5724 | C85: =A85+B85 -> 9877.5724 | D85: 10030013 | E85: =VLOOKUP(D85,'MPG Payment '!$E$3:$G$498218,2,0) -> LOHRA | F85: =IFERROR(_xlfn.XLOOKUP(D85,'Monthly Deduction'!$I$3:$I$957,'Monthly Deduction'!$H$3:$H$957),0) -> 0 | G85: =VLOOKUP(D85,'MPG Payment '!$E$3:$G$334579,3,0) -> MPG | H85: =VLOOKUP(D85,'MPG Payment '!$E$3:$H$334579,4,0) -> Direct | I85: =INDEX('MPG Payment '!$C:$C,MATCH('Shayak Income '!D85,'MPG Payment '!E:E,0)) -> 1003 | J85: =INDEX('MPG Payment '!$D:$D,MATCH('Shayak Income '!D85,'MPG Payment '!E:E,0)) -> Asarganj | K85: Old | L85: 44927 | M85: =SUMIF('MPG Payment '!$E$3:$E$34579,'Shayak Income '!D85,'MPG Payment '!$I$3:$I$34579) -> 2041 | N85: =SUMIF('MPG Payment '!$E$3:$E$34579,'Shayak Income '!D85,'MPG Payment '!$J$3:$J$34579) -> 102984.93 | O85: =+M85*0.75 -> 1530.75 | P85: =+M85*0.95 -> 1938.95 | Q85: =SUMIF('MPG Payment '!$E$3:$E$34579,'Shayak Income '!D85,'MPG Payment '!$S$3:$S$34579) -> 2877.5878 | R85: =+N85*3% -> 3089.548 | S85: =R85-P85 -> 1150.598 | T85: =M85*0.1 -> 204.1 | U85: =(((IF(K85="New",0,SUMIF('MPG Payment '!$E$3:$E$34579,'Shayak Income '!D85,'MPG Payment '!$AC$3:$AC$34579))))+0)+0 -> 750.65722 | V85: =ROUND((SUM(O85:Q85)-SUM(T85:U85)),0) -> 5393 | W85: =(((AN85-AO85)))+0 -> 0 | X85: =((MIN(IF(B85>0,MAX(N85*2%),0),B85)))+0 -> 2059.6986 | Y85: =IFERROR(VLOOKUP(D85,'Monthly Deduction'!$M$2:$N$64,2,0),0) -> 0 | Z85: 0 | AA85: =IFERROR(VLOOKUP(D85,'Monthly Deduction'!A:B,2,0),0) -> 0 | AB85: =ROUND(IFERROR(V85-SUM(W85:AA85),0),0) -> 3333 | AC85: 0 | AD85: =ROUND(AB85-AC85,0) -> 3333 | AE85: =IF(AC85<>0,"Yes","Release") -> Release | AG85: 0 | AI85: 0 | AK85: 700.75 | AL85: =COUNTIF(AK85:AK85,"=NA") -> 0 | AN85: =((MIN(IF(A85>0,MAX(N85*2%,1861),0),A85)))+0 -> 0 | AO85: =SUMIF('MPG Payment '!E:E,'Shayak Income '!D85,'MPG Payment '!AJ:AJ) -> 0 | AP85: =W85 -> 0 | AQ85: =AO85+AP85 -> 0 | AS85: =B85-X85 -> 7817.8738
A86: =IFERROR(VLOOKUP(D86,'Monthly Deduction'!$I$3:$J$957,2,0),0) -> 44253.951 | B86: =IFERROR(VLOOKUP(D86,'Monthly Deduction'!$E$3:$F$957,2,0),0) -> 6400 | C86: =A86+B86 -> 50653.951 | D86: 10030015 | E86: =VLOOKUP(D86,'MPG Payment '!$E$3:$G$498218,2,0) -> KAMATPUR | F86: =IFERROR(_xlfn.XLOOKUP(D86,'Monthly Deduction'!$I$3:$I$957,'Monthly Deduction'!$H$3:$H$957),0) -> 0 | G86: =VLOOKUP(D86,'MPG Payment '!$E$3:$G$334579,3,0) -> MPG | H86: =VLOOKUP(D86,'MPG Payment '!$E$3:$H$334579,4,0) -> Direct | I86: =INDEX('MPG Payment '!$C:$C,MATCH('Shayak Income '!D86,'MPG Payment '!E:E,0)) -> 1003 | J86: =INDEX('MPG Payment '!$D:$D,MATCH('Shayak Income '!D86,'MPG Payment '!E:E,0)) -> Asarganj | K86: Old | L86: 44981 | M86: =SUMIF('MPG Payment '!$E$3:$E$34579,'Shayak Income '!D86,'MPG Payment '!$I$3:$I$34579) -> 2268.1 | N86: =SUMIF('MPG Payment '!$E$3:$E$34579,'Shayak Income '!D86,'MPG Payment '!$J$3:$J$34579) -> 81887.521 | O86: =+M86*0.75 -> 1701.075 | P86: =+M86*0.95 -> 2154.695 | Q86: =SUMIF('MPG Payment '!$E$3:$E$34579,'Shayak Income '!D86,'MPG Payment '!$S$3:$S$34579) -> 1335.278 | R86: =+N86*3% -> 2456.6256 | S86: =R86-P86 -> 301.93063 | T86: =M86*0.1 -> 226.81 | U86: =(((IF(K86="New",0,SUMIF('MPG Payment '!$E$3:$E$34579,'Shayak Income '!D86,'MPG Payment '!$AC$3:$AC$34579))))+0)+0 -> 634.54341 | V86: =ROUND((SUM(O86:Q86)-SUM(T86:U86)),0) -> 4330 | W86: =(((AN86-AO86)))+0 -> 1861 | X86: 0 | Y86: =IFERROR(VLOOKUP(D86,'Monthly Deduction'!$M$2:$N$64,2,0),0) -> 0 | Z86: 0 | AA86: =IFERROR(VLOOKUP(D86,'Monthly Deduction'!A:B,2,0),0) -> 0 | AB86: =ROUND(IFERROR(V86-SUM(W86:AA86),0),0) -> 2469 | AC86: 0 | AD86: =ROUND(AB86-AC86,0) -> 2469 | AE86: =IF(AC86<>0,"Yes","Release") -> Release | AG86: 0 | AI86: 0 | AK86: 893.2 | AL86: =COUNTIF(AK86:AK86,"=NA") -> 0 | AN86: =((MIN(IF(A86>0,MAX(N86*2%,1861),0),A86)))+0 -> 1861 | AO86: =SUMIF('MPG Payment '!E:E,'Shayak Income '!D86,'MPG Payment '!AJ:AJ) -> 0 | AP86: =W86 -> 1861 | AQ86: =AO86+AP86 -> 1861 | AS86: =B86-X86 -> 6400
A87: =IFERROR(VLOOKUP(D87,'Monthly Deduction'!$I$3:$J$957,2,0),0) -> 19851.727 | B87: =IFERROR(VLOOKUP(D87,'Monthly Deduction'!$E$3:$F$957,2,0),0) -> 19200 | C87: =A87+B87 -> 39051.727 | D87: 10030016 | E87: =VLOOKUP(D87,'MPG Payment '!$E$3:$G$498218,2,0) -> GIRDHARA | F87: =IFERROR(_xlfn.XLOOKUP(D87,'Monthly Deduction'!$I$3:$I$957,'Monthly Deduction'!$H$3:$H$957),0) -> 0 | G87: =VLOOKUP(D87,'MPG Payment '!$E$3:$G$334579,3,0) -> MPG | H87: =VLOOKUP(D87,'MPG Payment '!$E$3:$H$334579,4,0) -> Direct | I87: =INDEX('MPG Payment '!$C:$C,MATCH('Shayak Income '!D87,'MPG Payment '!E:E,0)) -> 1003 | J87: =INDEX('MPG Payment '!$D:$D,MATCH('Shayak Income '!D87,'MPG Payment '!E:E,0)) -> Asarganj | K87: Old | L87: 44982 | M87: =SUMIF('MPG Payment '!$E$3:$E$34579,'Shayak Income '!D87,'MPG Payment '!$I$3:$I$34579) -> 4581.6 | N87: =SUMIF('MPG Payment '!$E$3:$E$34579,'Shayak Income '!D87,'MPG Payment '!$J$3:$J$34579) -> 180675.86 | O87: =+M87*0.75 -> 3436.2 | P87: =+M87*0.95 -> 4352.52 | Q87: =SUMIF('MPG Payment '!$E$3:$E$34579,'Shayak Income '!D87,'MPG Payment '!$S$3:$S$34579) -> 1246.1546 | R87: =+N87*3% -> 5420.2759 | S87: =R87-P87 -> 1067.7559 | T87: =M87*0.1 -> 458.16 | U87: =(((IF(K87="New",0,SUMIF('MPG Payment '!$E$3:$E$34579,'Shayak Income '!D87,'MPG Payment '!$AC$3:$AC$34579))))+0)+0 -> 0 | V87: =ROUND((SUM(O87:Q87)-SUM(T87:U87)),0) -> 8577 | W87: =(((AN87-AO87)))+0 -> 3613.5173 | X87: 0 | Y87: =IFERROR(VLOOKUP(D87,'Monthly Deduction'!$M$2:$N$64,2,0),0) -> 0 | Z87: 0 | AA87: =IFERROR(VLOOKUP(D87,'Monthly Deduction'!A:B,2,0),0) -> 0 | AB87: =ROUND(IFERROR(V87-SUM(W87:AA87),0),0) -> 4963 | AC87: 0 | AD87: =ROUND(AB87-AC87,0) -> 4963 | AE87: =IF(AC87<>0,"Yes","Release") -> Release | AG87: 0 | AI87: 0 | AK87: 1263.35 | AL87: =COUNTIF(AK87:AK87,"=NA") -> 0 | AN87: =((MIN(IF(A87>0,MAX(N87*2%,1861),0),A87)))+0 -> 3613.5173 | AO87: =SUMIF('MPG Payment '!E:E,'Shayak Income '!D87,'MPG Payment '!AJ:AJ) -> 0 | AP87: =W87 -> 3613.5173 | AQ87: =AO87+AP87 -> 3613.5173 | AS87: =B87-X87 -> 19200
A88: =IFERROR(VLOOKUP(D88,'Monthly Deduction'!$I$3:$J$957,2,0),0) -> 0 | B88: =IFERROR(VLOOKUP(D88,'Monthly Deduction'!$E$3:$F$957,2,0),0) -> 0 | C88: =A88+B88 -> 0 | D88: 10030017 | E88: =VLOOKUP(D88,'MPG Payment '!$E$3:$G$498218,2,0) -> RATNI | F88: =IFERROR(_xlfn.XLOOKUP(D88,'Monthly Deduction'!$I$3:$I$957,'Monthly Deduction'!$H$3:$H$957),0) -> 0 | G88: =VLOOKUP(D88,'MPG Payment '!$E$3:$G$334579,3,0) -> MPG | H88: =VLOOKUP(D88,'MPG Payment '!$E$3:$H$334579,4,0) -> Direct | I88: =INDEX('MPG Payment '!$C:$C,MATCH('Shayak Income '!D88,'MPG Payment '!E:E,0)) -> 1003 | J88: =INDEX('MPG Payment '!$D:$D,MATCH('Shayak Income '!D88,'MPG Payment '!E:E,0)) -> Asarganj | K88: Old | L88: 44995 | M88: =SUMIF('MPG Payment '!$E$3:$E$34579,'Shayak Income '!D88,'MPG Payment '!$I$3:$I$34579) -> 4149.85 | N88: =SUMIF('MPG Payment '!$E$3:$E$34579,'Shayak Income '!D88,'MPG Payment '!$J$3:$J$34579) -> 210186.73 | O88: =+M88*0.75 -> 3112.3875 | P88: =+M88*0.95 -> 3942.3575 | Q88: =SUMIF('MPG Payment '!$E$3:$E$34579,'Shayak Income '!D88,'MPG Payment '!$S$3:$S$34579) -> 4153.6648 | R88: =+N88*3% -> 6305.6018 | S88: =R88-P88 -> 2363.2443 | T88: =M88*0.1 -> 414.985 | U88: =(((IF(K88="New",0,SUMIF('MPG Payment '!$E$3:$E$34579,'Shayak Income '!D88,'MPG Payment '!$AC$3:$AC$34579))))+0)+0 -> 0 | V88: =ROUND((SUM(O88:Q88)-SUM(T88:U88)),0) -> 10793 | W88: =(((AN88-AO88)))+0 -> 0 | X88: =((MIN(IF(B88>0,MAX(N88*2%),0),B88)))+0 -> 0 | Y88: =IFERROR(VLOOKUP(D88,'Monthly Deduction'!$M$2:$N$64,2,0),0) -> 0 | Z88: 0 | AA88: =IFERROR(VLOOKUP(D88,'Monthly Deduction'!A:B,2,0),0) -> 0 | AB88: =ROUND(IFERROR(V88-SUM(W88:AA88),0),0) -> 10793 | AC88: 0 | AD88: =ROUND(AB88-AC88,0) -> 10793 | AE88: =IF(AC88<>0,"Yes","Release") -> Release | AG88: 0 | AI88: 0 | AK88: 1403.2 | AL88: =COUNTIF(AK88:AK88,"=NA") -> 0 | AN88: =((MIN(IF(A88>0,MAX(N88*2%,1861),0),A88)))+0 -> 0 | AO88: =SUMIF('MPG Payment '!E:E,'Shayak Income '!D88,'MPG Payment '!AJ:AJ) -> 0 | AP88: =W88 -> 0 | AQ88: =AO88+AP88 -> 0 | AS88: =B88-X88 -> 0
A89: =IFERROR(VLOOKUP(D89,'Monthly Deduction'!$I$3:$J$957,2,0),0) -> 0 | B89: =IFERROR(VLOOKUP(D89,'Monthly Deduction'!$E$3:$F$957,2,0),0) -> 0 | C89: =A89+B89 -> 0 | D89: 10030018 | E89: =VLOOKUP(D89,'MPG Payment '!$E$3:$G$498218,2,0) -> DHAPARI | F89: =IFERROR(_xlfn.XLOOKUP(D89,'Monthly Deduction'!$I$3:$I$957,'Monthly Deduction'!$H$3:$H$957),0) -> 0 | G89: =VLOOKUP(D89,'MPG Payment '!$E$3:$G$334579,3,0) -> MPG | H89: =VLOOKUP(D89,'MPG Payment '!$E$3:$H$334579,4,0) -> Direct | I89: =INDEX('MPG Payment '!$C:$C,MATCH('Shayak Income '!D89,'MPG Payment '!E:E,0)) -> 1003 | J89: =INDEX('MPG Payment '!$D:$D,MATCH('Shayak Income '!D89,'MPG Payment '!E:E,0)) -> Asarganj | K89: Old | L89: 44995 | M89: =SUMIF('MPG Payment '!$E$3:$E$34579,'Shayak Income '!D89,'MPG Payment '!$I$3:$I$34579) -> 3407.05 | N89: =SUMIF('MPG Payment '!$E$3:$E$34579,'Shayak Income '!D89,'MPG Payment '!$J$3:$J$34579) -> 133636.75 | O89: =+M89*0.75 -> 2555.2875 | P89: =+M89*0.95 -> 3236.6975 | Q89: =SUMIF('MPG Payment '!$E$3:$E$34579,'Shayak Income '!D89,'MPG Payment '!$S$3:$S$34579) -> 4224.0742 | R89: =+N89*3% -> 4009.1025 | S89: =R89-P89 -> 772.40505 | T89: =M89*0.1 -> 340.705 | U89: =(((IF(K89="New",0,SUMIF('MPG Payment '!$E$3:$E$34579,'Shayak Income '!D89,'MPG Payment '!$AC$3:$AC$34579))))+0)+0 -> 0 | V89: =ROUND((SUM(O89:Q89)-SUM(T89:U89)),0) -> 9675 | W89: =(((AN89-AO89)))+0 -> 0 | X89: =((MIN(IF(B89>0,MAX(N89*2%),0),B89)))+0 -> 0 | Y89: =IFERROR(VLOOKUP(D89,'Monthly Deduction'!$M$2:$N$64,2,0),0) -> 0 | Z89: 0 | AA89: =IFERROR(VLOOKUP(D89,'Monthly Deduction'!A:B,2,0),0) -> 0 | AB89: =ROUND(IFERROR(V89-SUM(W89:AA89),0),0) -> 9675 | AC89: 0 | AD89: =ROUND(AB89-AC89,0) -> 9675 | AE89: =IF(AC89<>0,"Yes","Release") -> Release | AG89: 0 | AI89: 0 | AK89: 999.65 | AL89: =COUNTIF(AK89:AK89,"=NA") -> 0 | AN89: =((MIN(IF(A89>0,MAX(N89*2%,1861),0),A89)))+0 -> 0 | AO89: =SUMIF('MPG Payment '!E:E,'Shayak Income '!D89,'MPG Payment '!AJ:AJ) -> 0 | AP89: =W89 -> 0 | AQ89: =AO89+AP89 -> 0 | AS89: =B89-X89 -> 0
A90: =IFERROR(VLOOKUP(D90,'Monthly Deduction'!$I$3:$J$957,2,0),0) -> 0 | B90: =IFERROR(VLOOKUP(D90,'Monthly Deduction'!$E$3:$F$957,2,0),0) -> 0 | C90: =A90+B90 -> 0 | D90: 10030019 | E90: =VLOOKUP(D90,'MPG Payment '!$E$3:$G$498218,2,0) -> KHARUI | F90: =IFERROR(_xlfn.XLOOKUP(D90,'Monthly Deduction'!$I$3:$I$957,'Monthly Deduction'!$H$3:$H$957),0) -> 0 | G90: =VLOOKUP(D90,'MPG Payment '!$E$3:$G$334579,3,0) -> MPG | H90: =VLOOKUP(D90,'MPG Payment '!$E$3:$H$334579,4,0) -> Direct | I90: =INDEX('MPG Payment '!$C:$C,MATCH('Shayak Income '!D90,'MPG Payment '!E:E,0)) -> 1003 | J90: =INDEX('MPG Payment '!$D:$D,MATCH('Shayak Income '!D90,'MPG Payment '!E:E,0)) -> Asarganj | K90: Old | L90: 44995 | M90: =SUMIF('MPG Payment '!$E$3:$E$34579,'Shayak Income '!D90,'MPG Payment '!$I$3:$I$34579) -> 2422.3 | N90: =SUMIF('MPG Payment '!$E$3:$E$34579,'Shayak Income '!D90,'MPG Payment '!$J$3:$J$34579) -> 107970.96 | O90: =+M90*0.75 -> 1816.725 | P90: =+M90*0.95 -> 2301.185 | Q90: =SUMIF('MPG Payment '!$E$3:$E$34579,'Shayak Income '!D90,'MPG Payment '!$S$3:$S$34579) -> 5863.9311 | R90: =+N90*3% -> 3239.1288 | S90: =R90-P90 -> 937.94385 | T90: =M90*0.1 -> 242.23 | U90: =(((IF(K90="New",0,SUMIF('MPG Payment '!$E$3:$E$34579,'Shayak Income '!D90,'MPG Payment '!$AC$3:$AC$34579))))+0)+0 -> 338.1844 | V90: =ROUND((SUM(O90:Q90)-SUM(T90:U90)),0) -> 9401 | W90: =(((AN90-AO90)))+0 -> 0 | X90: =((MIN(IF(B90>0,MAX(N90*2%),0),B90)))+0 -> 0 | Y90: =IFERROR(VLOOKUP(D90,'Monthly Deduction'!$M$2:$N$64,2,0),0) -> 0 | Z90: 0 | AA90: =IFERROR(VLOOKUP(D90,'Monthly Deduction'!A:B,2,0),0) -> 0 | AB90: =ROUND(IFERROR(V90-SUM(W90:AA90),0),0) -> 9401 | AC90: 0 | AD90: =ROUND(AB90-AC90,0) -> 9401 | AE90: =IF(AC90<>0,"Yes","Release") -> Release | AG90: 0 | AI90: 0 | AK90: 524.2 | AL90: =COUNTIF(AK90:AK90,"=NA") -> 0 | AN90: =((MIN(IF(A90>0,MAX(N90*2%,1861),0),A90)))+0 -> 0 | AO90: =SUMIF('MPG Payment '!E:E,'Shayak Income '!D90,'MPG Payment '!AJ:AJ) -> 0 | AP90: =W90 -> 0 | AQ90: =AO90+AP90 -> 0 | AS90: =B90-X90 -> 0
A91: =IFERROR(VLOOKUP(D91,'Monthly Deduction'!$I$3:$J$957,2,0),0) -> 0 | B91: =IFERROR(VLOOKUP(D91,'Monthly Deduction'!$E$3:$F$957,2,0),0) -> 0 | C91: =A91+B91 -> 0 | D91: 10030021 | E91: =VLOOKUP(D91,'MPG Payment '!$E$3:$G$498218,2,0) -> KHAIRA | F91: =IFERROR(_xlfn.XLOOKUP(D91,'Monthly Deduction'!$I$3:$I$957,'Monthly Deduction'!$H$3:$H$957),0) -> 0 | G91: =VLOOKUP(D91,'MPG Payment '!$E$3:$G$334579,3,0) -> MPG | H91: =VLOOKUP(D91,'MPG Payment '!$E$3:$H$334579,4,0) -> Direct | I91: =INDEX('MPG Payment '!$C:$C,MATCH('Shayak Income '!D91,'MPG Payment '!E:E,0)) -> 1003 | J91: =INDEX('MPG Payment '!$D:$D,MATCH('Shayak Income '!D91,'MPG Payment '!E:E,0)) -> Asarganj | K91: Old | L91: 44995 | M91: =SUMIF('MPG Payment '!$E$3:$E$34579,'Shayak Income '!D91,'MPG Payment '!$I$3:$I$34579) -> 3130.5 | N91: =SUMIF('MPG Payment '!$E$3:$E$34579,'Shayak Income '!D91,'MPG Payment '!$J$3:$J$34579) -> 124744.47 | O91: =+M91*0.75 -> 2347.875 | P91: =+M91*0.95 -> 2973.975 | Q91: =SUMIF('MPG Payment '!$E$3:$E$34579,'Shayak Income '!D91,'MPG Payment '!$S$3:$S$34579) -> 4507.6999 | R91: =+N91*3% -> 3742.3342 | S91: =R91-P91 -> 768.35922 | T91: =M91*0.1 -> 313.05 | U91: =(((IF(K91="New",0,SUMIF('MPG Payment '!$E$3:$E$34579,'Shayak Income '!D91,'MPG Payment '!$AC$3:$AC$34579))))+0)+0 -> 0 | V91: =ROUND((SUM(O91:Q91)-SUM(T91:U91)),0) -> 9516 | W91: =(((AN91-AO91)))+0 -> 0 | X91: =((MIN(IF(B91>0,MAX(N91*2%),0),B91)))+0 -> 0 | Y91: =IFERROR(VLOOKUP(D91,'Monthly Deduction'!$M$2:$N$64,2,0),0) -> 0 | Z91: 0 | AA91: =IFERROR(VLOOKUP(D91,'Monthly Deduction'!A:B,2,0),0) -> 0 | AB91: =ROUND(IFERROR(V91-SUM(W91:AA91),0),0) -> 9516 | AC91: 0 | AD91: =ROUND(AB91-AC91,0) -> 9516 | AE91: =IF(AC91<>0,"Yes","Release") -> Release | AG91: 0 | AI91: 0 | AK91: 773 | AL91: =COUNTIF(AK91:AK91,"=NA") -> 0 | AN91: =((MIN(IF(A91>0,MAX(N91*2%,1861),0),A91)))+0 -> 0 | AO91: =SUMIF('MPG Payment '!E:E,'Shayak Income '!D91,'MPG Payment '!AJ:AJ) -> 0 | AP91: =W91 -> 0 | AQ91: =AO91+AP91 -> 0 | AS91: =B91-X91 -> 0
A92: =IFERROR(VLOOKUP(D92,'Monthly Deduction'!$I$3:$J$957,2,0),0) -> 0 | B92: =IFERROR(VLOOKUP(D92,'Monthly Deduction'!$E$3:$F$957,2,0),0) -> 0 | C92: =A92+B92 -> 0 | D92: 10030022 | E92: =VLOOKUP(D92,'MPG Payment '!$E$3:$G$498218,2,0) -> SISUA | F92: =IFERROR(_xlfn.XLOOKUP(D92,'Monthly Deduction'!$I$3:$I$957,'Monthly Deduction'!$H$3:$H$957),0) -> 0 | G92: =VLOOKUP(D92,'MPG Payment '!$E$3:$G$334579,3,0) -> MPG | H92: =VLOOKUP(D92,'MPG Payment '!$E$3:$H$334579,4,0) -> Direct | I92: =INDEX('MPG Payment '!$C:$C,MATCH('Shayak Income '!D92,'MPG Payment '!E:E,0)) -> 1003 | J92: =INDEX('MPG Payment '!$D:$D,MATCH('Shayak Income '!D92,'MPG Payment '!E:E,0)) -> Asarganj | K92: Old | L92: 44995 | M92: =SUMIF('MPG Payment '!$E$3:$E$34579,'Shayak Income '!D92,'MPG Payment '!$I$3:$I$34579) -> 6464.05 | N92: =SUMIF('MPG Payment '!$E$3:$E$34579,'Shayak Income '!D92,'MPG Payment '!$J$3:$J$34579) -> 253575.06 | O92: =+M92*0.75 -> 4848.0375 | P92: =+M92*0.95 -> 6140.8475 | Q92: =SUMIF('MPG Payment '!$E$3:$E$34579,'Shayak Income '!D92,'MPG Payment '!$S$3:$S$34579) -> 3220.6154 | R92: =+N92*3% -> 7607.2519 | S92: =R92-P92 -> 1466.4044 | T92: =M92*0.1 -> 646.405 | U92: =(((IF(K92="New",0,SUMIF('MPG Payment '!$E$3:$E$34579,'Shayak Income '!D92,'MPG Payment '!$AC$3:$AC$34579))))+0)+0 -> 0 | V92: =ROUND((SUM(O92:Q92)-SUM(T92:U92)),0) -> 13563 | W92: =(((AN92-AO92)))+0 -> 0 | X92: =((MIN(IF(B92>0,MAX(N92*2%),0),B92)))+0 -> 0 | Y92: =IFERROR(VLOOKUP(D92,'Monthly Deduction'!$M$2:$N$64,2,0),0) -> 0 | Z92: 0 | AA92: =IFERROR(VLOOKUP(D92,'Monthly Deduction'!A:B,2,0),0) -> 0 | AB92: =ROUND(IFERROR(V92-SUM(W92:AA92),0),0) -> 13563 | AC92: 0 | AD92: =ROUND(AB92-AC92,0) -> 13563 | AE92: =IF(AC92<>0,"Yes","Release") -> Release | AG92: 0 | AI92: 0 | AK92: 1827.4 | AL92: =COUNTIF(AK92:AK92,"=NA") -> 0 | AN92: =((MIN(IF(A92>0,MAX(N92*2%,1861),0),A92)))+0 -> 0 | AO92: =SUMIF('MPG Payment '!E:E,'Shayak Income '!D92,'MPG Payment '!AJ:AJ) -> 0 | AP92: =W92 -> 0 | AQ92: =AO92+AP92 -> 0 | AS92: =B92-X92 -> 0
A93: =IFERROR(VLOOKUP(D93,'Monthly Deduction'!$I$3:$J$957,2,0),0) -> 33325.281 | B93: =IFERROR(VLOOKUP(D93,'Monthly Deduction'!$E$3:$F$957,2,0),0) -> 3656.774 | C93: =A93+B93 -> 36982.055 | D93: 10030023 | E93: =VLOOKUP(D93,'MPG Payment '!$E$3:$G$498218,2,0) -> BISAI | F93: =IFERROR(_xlfn.XLOOKUP(D93,'Monthly Deduction'!$I$3:$I$957,'Monthly Deduction'!$H$3:$H$957),0) -> 0 | G93: =VLOOKUP(D93,'MPG Payment '!$E$3:$G$334579,3,0) -> MPG | H93: =VLOOKUP(D93,'MPG Payment '!$E$3:$H$334579,4,0) -> Direct | I93: =INDEX('MPG Payment '!$C:$C,MATCH('Shayak Income '!D93,'MPG Payment '!E:E,0)) -> 1003 | J93: =INDEX('MPG Payment '!$D:$D,MATCH('Shayak Income '!D93,'MPG Payment '!E:E,0)) -> Asarganj | K93: Old | L93: 44995 | M93: =SUMIF('MPG Payment '!$E$3:$E$34579,'Shayak Income '!D93,'MPG Payment '!$I$3:$I$34579) -> 977.15 | N93: =SUMIF('MPG Payment '!$E$3:$E$34579,'Shayak Income '!D93,'MPG Payment '!$J$3:$J$34579) -> 40696.686 | O93: =+M93*0.75 -> 732.8625 | P93: =+M93*0.95 -> 928.2925 | Q93: =SUMIF('MPG Payment '!$E$3:$E$34579,'Shayak Income '!D93,'MPG Payment '!$S$3:$S$34579) -> 2044.9577 | R93: =+N93*3% -> 1220.9006 | S93: =R93-P93 -> 292.60809 | T93: =M93*0.1 -> 97.715 | U93: =(((IF(K93="New",0,SUMIF('MPG Payment '!$E$3:$E$34579,'Shayak Income '!D93,'MPG Payment '!$AC$3:$AC$34579))))+0)+0 -> 1520.9042 | V93: =ROUND((SUM(O93:Q93)-SUM(T93:U93)),0) -> 2087 | W93: =(((AN93-AO93)))+0 -> 1861 | X93: 0 | Y93: =IFERROR(VLOOKUP(D93,'Monthly Deduction'!$M$2:$N$64,2,0),0) -> 0 | Z93: 0 | AA93: =IFERROR(VLOOKUP(D93,'Monthly Deduction'!A:B,2,0),0) -> 0 | AB93: =ROUND(IFERROR(V93-SUM(W93:AA93),0),0) -> 226 | AC93: 0 | AD93: =ROUND(AB93-AC93,0) -> 226 | AE93: =IF(AC93<>0,"Yes","Release") -> Release | AG93: 0 | AI93: 0 | AK93: 316.65 | AL93: =COUNTIF(AK93:AK93,"=NA") -> 0 | AN93: =((MIN(IF(A93>0,MAX(N93*2%,1861),0),A93)))+0 -> 1861 | AO93: =SUMIF('MPG Payment '!E:E,'Shayak Income '!D93,'MPG Payment '!AJ:AJ) -> 0 | AP93: =W93 -> 1861 | AQ93: =AO93+AP93 -> 1861 | AS93: =B93-X93 -> 3656.774
A94: =IFERROR(VLOOKUP(D94,'Monthly Deduction'!$I$3:$J$957,2,0),0) -> 0 | B94: =IFERROR(VLOOKUP(D94,'Monthly Deduction'!$E$3:$F$957,2,0),0) -> 0 | C94: =A94+B94 -> 0 | D94: 10030025 | E94: =VLOOKUP(D94,'MPG Payment '!$E$3:$G$498218,2,0) -> SAJUA-1 | F94: =IFERROR(_xlfn.XLOOKUP(D94,'Monthly Deduction'!$I$3:$I$957,'Monthly Deduction'!$H$3:$H$957),0) -> 0 | G94: =VLOOKUP(D94,'MPG Payment '!$E$3:$G$334579,3,0) -> MPG | H94: =VLOOKUP(D94,'MPG Payment '!$E$3:$H$334579,4,0) -> Direct | I94: =INDEX('MPG Payment '!$C:$C,MATCH('Shayak Income '!D94,'MPG Payment '!E:E,0)) -> 1003 | J94: =INDEX('MPG Payment '!$D:$D,MATCH('Shayak Income '!D94,'MPG Payment '!E:E,0)) -> Asarganj | K94: Old | L94: 45015 | M94: =SUMIF('MPG Payment '!$E$3:$E$34579,'Shayak Income '!D94,'MPG Payment '!$I$3:$I$34579) -> 2904.8 | N94: =SUMIF('MPG Payment '!$E$3:$E$34579,'Shayak Income '!D94,'MPG Payment '!$J$3:$J$34579) -> 108895.93 | O94: =+M94*0.75 -> 2178.6 | P94: =+M94*0.95 -> 2759.56 | Q94: =SUMIF('MPG Payment '!$E$3:$E$34579,'Shayak Income '!D94,'MPG Payment '!$S$3:$S$34579) -> 1306.1893 | R94: =+N94*3% -> 3266.878 | S94: =R94-P94 -> 507.31797 | T94: =M94*0.1 -> 290.48 | U94: =(((IF(K94="New",0,SUMIF('MPG Payment '!$E$3:$E$34579,'Shayak Income '!D94,'MPG Payment '!$AC$3:$AC$34579))))+0)+0 -> 91.155133 | V94: =ROUND((SUM(O94:Q94)-SUM(T94:U94)),0) -> 5863 | W94: =(((AN94-AO94)))+0 -> 0 | X94: =((MIN(IF(B94>0,MAX(N94*2%),0),B94)))+0 -> 0 | Y94: =IFERROR(VLOOKUP(D94,'Monthly Deduction'!$M$2:$N$64,2,0),0) -> 0 | Z94: 0 | AA94: =IFERROR(VLOOKUP(D94,'Monthly Deduction'!A:B,2,0),0) -> 0 | AB94: =ROUND(IFERROR(V94-SUM(W94:AA94),0),0) -> 5863 | AC94: 0 | AD94: =ROUND(AB94-AC94,0) -> 5863 | AE94: =IF(AC94<>0,"Yes","Release") -> Release | AG94: 0 | AI94: 0 | AK94: 812.75 | AL94: =COUNTIF(AK94:AK94,"=NA") -> 0 | AN94: =((MIN(IF(A94>0,MAX(N94*2%,1861),0),A94)))+0 -> 0 | AO94: =SUMIF('MPG Payment '!E:E,'Shayak Income '!D94,'MPG Payment '!AJ:AJ) -> 0 | AP94: =W94 -> 0 | AQ94: =AO94+AP94 -> 0 | AS94: =B94-X94 -> 0
A95: =IFERROR(VLOOKUP(D95,'Monthly Deduction'!$I$3:$J$957,2,0),0) -> 0 | B95: =IFERROR(VLOOKUP(D95,'Monthly Deduction'!$E$3:$F$957,2,0),0) -> 0 | C95: =A95+B95 -> 0 | D95: 10030026 | E95: =VLOOKUP(D95,'MPG Payment '!$E$3:$G$498218,2,0) -> SAJUA-2 | F95: =IFERROR(_xlfn.XLOOKUP(D95,'Monthly Deduction'!$I$3:$I$957,'Monthly Deduction'!$H$3:$H$957),0) -> 0 | G95: =VLOOKUP(D95,'MPG Payment '!$E$3:$G$334579,3,0) -> MPG | H95: =VLOOKUP(D95,'MPG Payment '!$E$3:$H$334579,4,0) -> Direct | I95: =INDEX('MPG Payment '!$C:$C,MATCH('Shayak Income '!D95,'MPG Payment '!E:E,0)) -> 1003 | J95: =INDEX('MPG Payment '!$D:$D,MATCH('Shayak Income '!D95,'MPG Payment '!E:E,0)) -> Asarganj | K95: Old | L95: 45015 | M95: =SUMIF('MPG Payment '!$E$3:$E$34579,'Shayak Income '!D95,'MPG Payment '!$I$3:$I$34579) -> 4982.95 | N95: =SUMIF('MPG Payment '!$E$3:$E$34579,'Shayak Income '!D95,'MPG Payment '!$J$3:$J$34579) -> 187126.53 | O95: =+M95*0.75 -> 3737.2125 | P95: =+M95*0.95 -> 4733.8025 | Q95: =SUMIF('MPG Payment '!$E$3:$E$34579,'Shayak Income '!D95,'MPG Payment '!$S$3:$S$34579) -> 0 | R95: =+N95*3% -> 5613.7959 | S95: =R95-P95 -> 879.99335 | T95: =M95*0.1 -> 498.295 | U95: =(((IF(K95="New",0,SUMIF('MPG Payment '!$E$3:$E$34579,'Shayak Income '!D95,'MPG Payment '!$AC$3:$AC$34579))))+0)+0 -> 0 | V95: =ROUND((SUM(O95:Q95)-SUM(T95:U95)),0) -> 7973 | W95: =(((AN95-AO95)))+0 -> 0 | X95: =((MIN(IF(B95>0,MAX(N95*2%),0),B95)))+0 -> 0 | Y95: =IFERROR(VLOOKUP(D95,'Monthly Deduction'!$M$2:$N$64,2,0),0) -> 0 | Z95: 3000 | AA95: =IFERROR(VLOOKUP(D95,'Monthly Deduction'!A:B,2,0),0) -> 0 | AB95: =ROUND(IFERROR(V95-SUM(W95:AA95),0),0) -> 4973 | AC95: 0 | AD95: =ROUND(AB95-AC95,0) -> 4973 | AE95: =IF(AC95<>0,"Yes","Release") -> Release | AG95: 0 | AH95: BIO-GAS | AI95: 0 | AK95: 1546.5 | AL95: =COUNTIF(AK95:AK95,"=NA") -> 0 | AN95: =((MIN(IF(A95>0,MAX(N95*2%,1861),0),A95)))+0 -> 0 | AO95: =SUMIF('MPG Payment '!E:E,'Shayak Income '!D95,'MPG Payment '!AJ:AJ) -> 0 | AP95: =W95 -> 0 | AQ95: =AO95+AP95 -> 0 | AS95: =B95-X95 -> 0
A96: =IFERROR(VLOOKUP(D96,'Monthly Deduction'!$I$3:$J$957,2,0),0) -> 0 | B96: =IFERROR(VLOOKUP(D96,'Monthly Deduction'!$E$3:$F$957,2,0),0) -> 0 | C96: =A96+B96 -> 0 | D96: 10030027 | E96: =VLOOKUP(D96,'MPG Payment '!$E$3:$G$498218,2,0) -> CHORGAUN | F96: =IFERROR(_xlfn.XLOOKUP(D96,'Monthly Deduction'!$I$3:$I$957,'Monthly Deduction'!$H$3:$H$957),0) -> 0 | G96: =VLOOKUP(D96,'MPG Payment '!$E$3:$G$334579,3,0) -> MPG | H96: =VLOOKUP(D96,'MPG Payment '!$E$3:$H$334579,4,0) -> Direct | I96: =INDEX('MPG Payment '!$C:$C,MATCH('Shayak Income '!D96,'MPG Payment '!E:E,0)) -> 1003 | J96: =INDEX('MPG Payment '!$D:$D,MATCH('Shayak Income '!D96,'MPG Payment '!E:E,0)) -> Asarganj | K96: Old | L96: 45015 | M96: =SUMIF('MPG Payment '!$E$3:$E$34579,'Shayak Income '!D96,'MPG Payment '!$I$3:$I$34579) -> 2897 | N96: =SUMIF('MPG Payment '!$E$3:$E$34579,'Shayak Income '!D96,'MPG Payment '!$J$3:$J$34579) -> 108729.54 | O96: =+M96*0.75 -> 2172.75 | P96: =+M96*0.95 -> 2752.15 | Q96: =SUMIF('MPG Payment '!$E$3:$E$34579,'Shayak Income '!D96,'MPG Payment '!$S$3:$S$34579) -> 3572.2726 | R96: =+N96*3% -> 3261.8863 | S96: =R96-P96 -> 509.73625 | T96: =M96*0.1 -> 289.7 | U96: =(((IF(K96="New",0,SUMIF('MPG Payment '!$E$3:$E$34579,'Shayak Income '!D96,'MPG Payment '!$AC$3:$AC$34579))))+0)+0 -> 62.298054 | V96: =ROUND((SUM(O96:Q96)-SUM(T96:U96)),0) -> 8145 | W96: =(((AN96-AO96)))+0 -> 0 | X96: =((MIN(IF(B96>0,MAX(N96*2%),0),B96)))+0 -> 0 | Y96: =IFERROR(VLOOKUP(D96,'Monthly Deduction'!$M$2:$N$64,2,0),0) -> 0 | Z96: 0 | AA96: =IFERROR(VLOOKUP(D96,'Monthly Deduction'!A:B,2,0),0) -> 0 | AB96: =ROUND(IFERROR(V96-SUM(W96:AA96),0),0) -> 8145 | AC96: 0 | AD96: =ROUND(AB96-AC96,0) -> 8145 | AE96: =IF(AC96<>0,"Yes","Release") -> Release | AG96: 0 | AI96: 0 | AK96: 827.7 | AL96: =COUNTIF(AK96:AK96,"=NA") -> 0 | AN96: =((MIN(IF(A96>0,MAX(N96*2%,1861),0),A96)))+0 -> 0 | AO96: =SUMIF('MPG Payment '!E:E,'Shayak Income '!D96,'MPG Payment '!AJ:AJ) -> 0 | AP96: =W96 -> 0 | AQ96: =AO96+AP96 -> 0 | AS96: =B96-X96 -> 0
